Workbook

Sheet Links
A1: Links e IMPORTRANGE
A2: Pegar en B el link de cada Google Sheet. La primera vez, tocar la primera celda de cada bloque y «Permitir acceso». Todos los IMPORTRANGE del libro están en esta hoja.
A3: Archivo | B3: Link | G3: Qué se importa | L3: Estado
A4: Proyecciones | B4: https://docs.google.com/spreadsheets/d/1xc4xDAwSYT3l-RulPYtcePxiCninrbQGzaBUsgO0YEs/edit?gid=1764491891#gid=1764491891 | G4: Indexado Dim Técnico B3:K10 y B15:K22 → Demanda | L4: =IF(ISERROR(C11),"Falta el link o «Permitir acceso»","OK") -> OK
A5: Aprovechamiento Recargas Planta Comercial | B5: PEGAR ACÁ EL LINK DEL GOOGLE SHEET | G5: sobrestock_sustitutos B73:K76 y B86:K89 → Demanda | L5: =IF(ISERROR(C44),"Falta el link o «Permitir acceso»","OK") -> OK
A6: Aprovechamiento Recargas Planta Industrial | B6: PEGAR ACÁ EL LINK DEL GOOGLE SHEET | G6: sobrestock_sustitutos B73:K76 y B86:K89 → Demanda | L6: =IF(ISERROR(C33),"Falta el link o «Permitir acceso»","OK") -> OK
A7: Sin link, esa fuente suma 0 en Demanda (la columna Estado lo avisa).
A9: Proyecciones · Indexado Dim Técnico B3:K10: matafuegos terminados
A10: Formato | B10: Qué es | C10: 2026 | D10: 2027 | E10: 2028 | F10: 2029 | G10: 2030 | H10: 2031 | I10: 2032 | J10: 2033 | K10: 2034 | L10: 2035
A11: 1 kg | B11: Terminados | C11: =IFERROR(__xludf.DUMMYFUNCTION("IMPORTRANGE(Links!$B$4,""Indexado Dim Técnico!B3:K10"")"),4178.736543) -> 4178.7365
A12: 2,5 kg | B12: Terminados
A13: 5 kg | B13: Terminados
A14: 10 kg | B14: Terminados
A15: 25 kg | B15: Terminados
A16: 50 kg | B16: Terminados
A17: 70 kg | B17: Terminados
A18: 100 kg | B18: Terminados
A20: Proyecciones · Indexado Dim Técnico B15:K22: cilindros vendidos vacíos
A21: Formato | B21: Qué es | C21: 2026 | D21: 2027 | E21: 2028 | F21: 2029 | G21: 2030 | H21: 2031 | I21: 2032 | J21: 2033 | K21: 2034 | L21: 2035
A22: 1 kg | B22: Cilindros | C22: =IFERROR(__xludf.DUMMYFUNCTION("IMPORTRANGE(Links!$B$4,""Indexado Dim Técnico!B15:K22"")"),0) -> 0
A23: 2,5 kg | B23: Cilindros
A24: 5 kg | B24: Cilindros
A25: 10 kg | B25: Cilindros
A26: 25 kg | B26: Cilindros
A27: 50 kg | B27: Cilindros
A28: 70 kg | B28: Cilindros
A29: 100 kg | B29: Cilindros
A31: Recargas Planta Industrial · sobrestock_sustitutos B73:K76 y B86:K89: sustitutos ABC terminados
A32: Formato | B32: Qué es | C32: 2026 | D32: 2027 | E32: 2028 | F32: 2029 | G32: 2030 | H32: 2031 | I32: 2032 | J32: 2033 | K32: 2034 | L32: 2035
A33: 1 kg | B33: Sustitutos | C33: =IFERROR(__xludf.DUMMYFUNCTION("IMPORTRANGE(Links!$B$6,""sobrestock_sustitutos!B73:K76"")"),0) -> 0
A34: 2,5 kg | B34: Sustitutos
A35: 5 kg | B35: Sustitutos
A36: 10 kg | B36: Sustitutos
A37: 25 kg | B37: Sustitutos | C37: =IFERROR(__xludf.DUMMYFUNCTION("IMPORTRANGE(Links!$B$6,""sobrestock_sustitutos!B86:K89"")"),1) -> 1
A38: 50 kg | B38: Sustitutos
A39: 70 kg | B39: Sustitutos
A40: 100 kg | B40: Sustitutos
A42: Recargas Planta Comercial · sobrestock_sustitutos B73:K76 y B86:K89: sustitutos ABC cilindros vacíos
A43: Formato | B43: Qué es | C43: 2026 | D43: 2027 | E43: 2028 | F43: 2029 | G43: 2030 | H43: 2031 | I43: 2032 | J43: 2033 | K43: 2034 | L43: 2035
A44: 1 kg | B44: Sustitutos | C44: =IFERROR(__xludf.DUMMYFUNCTION("IMPORTRANGE(Links!$B$5,""sobrestock_sustitutos!B73:K76"")"),0) -> 0
A45: 2,5 kg | B45: Sustitutos
A46: 5 kg | B46: Sustitutos
A47: 10 kg | B47: Sustitutos
A48: 25 kg | B48: Sustitutos | C48: =IFERROR(__xludf.DUMMYFUNCTION("IMPORTRANGE(Links!$B$5,""sobrestock_sustitutos!B86:K89"")"),1) -> 1
A49: 50 kg | B49: Sustitutos
A50: 70 kg | B50: Sustitutos
A51: 100 kg | B51: Sustitutos

Sheet Resumen
A1: Corte de chapa: comparación de alternativas 2026-2035
A2: Cuerpos de 1 a 100 kg, cúpulas y fondos de 1 a 10 kg. Valor actual = inversión + costos de 10 años descontados. Menor es mejor.
A4: Indicador | B4: A: bobina por formato + fleje | C4: B: hojas para todo | D4: C: bobina madre propia | E4: D: hojas + fleje | F4: Referencia: cuerpos a medida
A5: Cuerpos: se compra | B5: Bobina de ancho estándar por formato, línea de corte transversal | C5: Hojas estándar, dos guillotinas en serie | D5: Bobina madre por espesor, cortada en flejes propios | E5: Hojas estándar, dos guillotinas en serie | F5: Cuerpos comprados cortados a medida
A6: Cúpulas y fondos: se compra | B6: Fleje a medida por disco | C6: Tiras de hoja cargadas a mano | D6: Flejes propios de la bobina madre | E6: Fleje a medida por disco | F6: Fleje a medida por disco
A7: Inversión en equipos (USD) | B7: =Datos!$C$117 -> 160806.26 | C7: =Datos!$D$117 -> 72506.259 | D7: =Datos!$E$117 -> 191000 | E7: =Datos!$F$117 -> 86006.259 | F7: =Datos!$G$117 -> 15000
A8: Acero comprado 2026-2035 (t) | B8: =SUM(Cálculo!$C$32:$L$32) -> 1817.5432 | C8: =SUM(Cálculo!$C$61:$L$61) -> 1924.7473 | D8: =SUM(Cálculo!$C$85:$L$85) -> 1833.9308 | E8: =SUM(Cálculo!$C$99:$L$99) -> 1877.59 | F8: =SUM(Cálculo!$C$113:$L$113) -> 1760.2126
A9: Aprovechamiento de chapa 2026-2035 | B9: =SUM(Cálculo!$C$25:$L$25)/B8 -> 0.90524497 | C9: =SUM(Cálculo!$C$25:$L$25)/C8 -> 0.85482487 | D9: =SUM(Cálculo!$C$25:$L$25)/D8 -> 0.89715591 | E9: =SUM(Cálculo!$C$25:$L$25)/E8 -> 0.87629452 | F9: =SUM(Cálculo!$C$25:$L$25)/F8 -> 0.93472906
A10: Horas-hombre de corte en el año de referencia | B10: =INDEX(Cálculo!$C$41:$L$41,Datos!$B$6-2025) -> 318.27451 | C10: =INDEX(Cálculo!$C$67:$L$67,Datos!$B$6-2025) -> 399.38628 | D10: =INDEX(Cálculo!$C$93:$L$93,Datos!$B$6-2025) -> 406.03852 | E10: =INDEX(Cálculo!$C$105:$L$105,Datos!$B$6-2025) -> 113.60639 | F10: =INDEX(Cálculo!$C$119:$L$119,Datos!$B$6-2025) -> 20.146699
A11: Costo anual en el año de referencia (USD) | B11: =INDEX(Cálculo!$C$44:$L$44,Datos!$B$6-2025) -> 510842.2 | C11: =INDEX(Cálculo!$C$70:$L$70,Datos!$B$6-2025) -> 565521.55 | D11: =INDEX(Cálculo!$C$96:$L$96,Datos!$B$6-2025) -> 523443.22 | E11: =INDEX(Cálculo!$C$108:$L$108,Datos!$B$6-2025) -> 539731.1 | F11: =INDEX(Cálculo!$C$122:$L$122,Datos!$B$6-2025) -> 539193.47
A12: Valor actual a 10 años (USD) | B12: =B7+SUMPRODUCT(Cálculo!$C$44:$L$44,Cálculo!$C$6:$L$6) -> 1139875.8 | C12: =C7+SUMPRODUCT(Cálculo!$C$70:$L$70,Cálculo!$C$6:$L$6) -> 1140454.4 | D12: =D7+SUMPRODUCT(Cálculo!$C$96:$L$96,Cálculo!$C$6:$L$6) -> 1202188.3 | E12: =E7+SUMPRODUCT(Cálculo!$C$108:$L$108,Cálculo!$C$6:$L$6) -> 1107926.9 | F12: =F7+SUMPRODUCT(Cálculo!$C$122:$L$122,Cálculo!$C$6:$L$6) -> 1028430.1
A13: Ranking (1 = conviene; la referencia no corta en planta) | B13: =RANK(B12,$B$12:$E$12,1) -> 2 | C13: =RANK(C12,$B$12:$E$12,1) -> 3 | D13: =RANK(D12,$B$12:$E$12,1) -> 4 | E13: =RANK(E12,$B$12:$E$12,1) -> 1 | F13: —
A14: Diferencia contra la que conviene (USD) | B14: =B12-MIN($B$12:$E$12) -> 31948.883 | C14: =C12-MIN($B$12:$E$12) -> 32527.491 | D14: =D12-MIN($B$12:$E$12) -> 94261.32 | E14: =E12-MIN($B$12:$E$12) -> 0 | F14: =F12-MIN($B$12:$E$12) -> -79496.897
A16: Conviene (de las que cortan en planta) | B16: =INDEX({"A: bobina por formato + fleje","B: hojas para todo","C: bobina madre propia","D: hojas + fleje"},MATCH(MIN($B$12:$E$12),$B$12:$E$12,0)) -> D: hojas + fleje
A17: Margen de D: suba del precio de la hoja que la iguala con A | B17: =($B$12-$E$12)/SUMPRODUCT(Cálculo!$C$55:$L$55,Cálculo!$C$6:$L$6) -> 0.040192118
A18: Margen de D: suba del precio del fleje que la iguala con B | B18: =($C$12-$E$12)/SUMPRODUCT(Cálculo!$C$31:$L$31,Cálculo!$C$6:$L$6) -> 0.14427753
A20: Datos editables en la hoja Datos (gris claro). Demanda por IMPORTRANGE (hoja Links). Medidas de cuerpos y discos del plano (hoja Piezas).

Sheet Datos
A1: Datos
A2: Gris claro: dato editable. Todo lo demás del libro sale de acá, de Demanda y de Piezas.
A4: 1. Generales
A5: Concepto | B5: Valor | C5: Unidad | D5: Fuente o criterio
A6: Año de referencia | B6: 2035 | C6: año | D6: Año de diseño del proyecto (Proyecciones).
A7: Tasa de descuento anual en USD | B7: 0.12 | C7: % | D7: Evaluación económica del Excel V2 (12 % real).
A8: Mantenimiento anual de equipos | B8: 0.03 | C8: % de la inversión | D8: Criterio del grupo.
A9: Precio de venta del scrap | B9: 250 | C9: USD/t | D9: Reaquila (mar-2026): acero reciclado $300-1.200/kg con dólar ~$1.480.
A10: Densidad del acero SAE 1010 | B10: 7.87 | C10: g/cm³ | D10: Planilla «Dimensiones de chapa».
A11: Costo mensual de un operario con cargas | B11: 1337922 | C11: ARS/mes | D11: Planilla «Costo oportunidad operario-máquina», CCT 260/75, ago-2026.
A12: Horas por mes | B12: 150 | C12: h/mes | D12: Excel V2.
A13: Horas productivas por operario y año | B13: 1800 | C13: h/año | D13: Excel V2 (150 h × 12).
A14: Tipo de cambio | B14: 1420 | C14: ARS/USD | D14: Valor fijo del proyecto (criterio del grupo).
A15: Costo hora de operario | B15: =Datos!$B$11/Datos!$B$12/Datos!$B$14 -> 6.2813239 | C15: USD/h | D15: Cálculo.
A17: 2. Corte y puentes
A18: Concepto | B18: Valor | C18: Unidad | D18: Fuente o criterio
A19: Margen mínimo de borde a lo ancho de una bobina | B19: 10 | C19: mm | D19: Criterio del grupo: bordes de laminación y tolerancia de ancho.
A20: Despunte de cabeza y cola de bobina | B20: 0.005 | C20: % | D20: Criterio del grupo.
A21: Puente de avance entre discos | B21: 1.5 | C21: × espesor | D21: MISUMI, Press Dies Tutorial: 1,5 veces el espesor, mínimo 0,7 mm.
A22: Puente mínimo entre discos | B22: 0.7 | C22: mm | D22: MISUMI.
A23: Puente al borde del fleje | B23: 1.5 | C23: × puente de avance | D23: MISUMI: 1,5 veces el de avance (la guía del fleje deja juego).
A24: ¿Mezclar 70 y 100 kg en la misma hoja? | B24: SI | C24: SI/NO | D24: Proceso de carros: la hoja mixta lleva 1 cuerpo de 100 kg y 3 de 70 kg.
A25: Cuerpos de 100 kg por hoja mixta | B25: 1 | C25: u | D25: Proceso de carros.
A26: Cuerpos de 70 kg por hoja mixta | B26: 3 | C26: u | D26: Proceso de carros.
A27: ¿Combinar 25 y 50 kg en la hoja de 3,2 mm (corte en tres etapas)? | B27: SI | C27: SI/NO | D27: Hoja Nesting: el aprovechamiento de la chapa de 3,2 mm sube del 85 % al 90 %.
A28: ¿Discos en fleje de dos filas al tresbolillo? | B28: NO | C28: SI/NO | D28: Corte, sección C: necesita matriz de dos discos o alimentador en zigzag (sin cotización).
A30: 3. Máquinas
A31: Concepto | B31: Valor | C31: Unidad | D31: Fuente o criterio
A32: Guillotina 1 (franjas) Ermaksan CNC HGS 2600-6: golpes por minuto | B32: 20 | C32: golpes/min | D32: Aprovechamiento Manuales del grupo. La ficha de la máquina (resale.info, 2018) da 24.
A33: Guillotina 1: largo de corte | B33: 2600 | C33: mm | D33: Ficha Ermaksan CNC HGS 2600-6: 2.600 × 6 mm.
A34: Guillotina 1: recorrido del tope trasero | B34: 1000 | C34: mm | D34: Ficha Ermaksan CNC HGS 2600-6: tope trasero motorizado de 1.000 mm.
A35: Guillotina 2 (piezas) QC12Y 6 × 2500: golpes por minuto | B35: 20 | C35: golpes/min | D35: Confirmado por el grupo (igual que la HG 6 × 2500 de la ficha Molinari Panther).
A36: Guillotina 2: largo de corte para franjas en paralelo | B36: 2500 | C36: mm | D36: Publicación Alibaba 1600900259147: 6 × 2500, cuchilla de 2.550 mm.
A37: Guillotina 2: recorrido del tope trasero | B37: 800 | C37: mm | D37: Publicación Alibaba 1600900259147: 20 a 800 mm.
A38: Hojas por ciclo como máximo (franjas de hojas enteras en paralelo en G2) | B38: 4 | C38: hojas | D38: Criterio del grupo (comentarios del corte de 5 y 10 kg): sin franjas sueltas en el pulmón.
A39: Guillotina 1 Ermaksan CNC HGS 2600-6 usada (2018) | B39: 26000 | C39: EUR | D39: Anuncio resale.info N.° 165879844 (nov-2024), sin flete ni nacionalización.
A40: Tipo de cambio euro / dólar | B40: =1/0.8723 -> 1.1463946 | C40: USD/EUR | D40: Pound Sterling Live: USD/EUR 0,8723 al cierre del 21/09/2026.
A41: Línea de corte transversal (A y C): golpes por hora | B41: 1200 | C41: golpes/h | D41: Criterio del grupo: 20 golpes por minuto.
A42: Cortadora longitudinal (C): velocidad efectiva | B42: 40 | C42: m/min | D42: Criterio del grupo (máquinas de 60 a 120 m/min nominales).
A43: Cortadora: armado de cuchillas por bobina madre | B43: 45 | C43: min | D43: Criterio del grupo.
A44: Operarios en la cortadora | B44: 2 | C44: personas | D44: Criterio del grupo.
A45: Carga manual de una tira en el balancín (B) | B45: 15 | C45: s/tira | D45: Criterio del grupo.
A46: Cambio de fleje en el desbobinador de la prensa | B46: 15 | C46: min/fleje | D46: Criterio del grupo.
A48: 4. Compras y stock
A49: Concepto | B49: Valor | C49: Unidad | D49: Fuente o criterio
A50: Stock de seguridad | B50: 2 | C50: semanas | D50: Criterio del grupo.
A51: Lote de compra de hojas y de chapa a medida | B51: 1 | C51: meses | D51: Criterio del grupo: compra mensual.
A52: Cobertura objetivo de un rollo o bobina | B52: 1 | C52: meses | D52: Criterio del grupo.
A53: Cobertura máxima de stock por rollo | B53: 3 | C53: meses | D53: Criterio del grupo.
A54: Peso mínimo de rollo | B54: 0.5 | C54: t | D54: Criterio del grupo.
A55: Diámetro exterior máximo de bobina | B55: 1500 | C55: mm | D55: Criterio del grupo.
A56: Diámetro interior de bobina | B56: 508 | C56: mm | D56: Estándar de mercado.
A57: Peso máximo de bobina por mm de ancho | B57: =PI()/4*(Datos!$B$55^2-Datos!$B$56^2)*Datos!$B$10/1000000000 -> 0.012312323 | C57: t/mm | D57: Cálculo con el diámetro exterior máximo.
A58: Desbobinador de la línea de corte transversal | B58: 10 | C58: t | D58: A especificar al comprar.
A59: Desbobinador de fleje de la prensa | B59: 3 | C59: t | D59: A especificar al comprar.
A60: Desbobinador de la cortadora longitudinal | B60: 14 | C60: t | D60: Pradecon: la bobina madre pesa 13-14 t.
A61: Precio de la bobina madre sobre la flejada | B61: 0 | C61: % | D61: Pradecon (mail 28/09/2026): no cobra el flejado.
A62: ¿El puente grúa ya está en el layout por otro motivo? | B62: NO | C62: SI/NO | D62: Si es SI, no se carga a A ni a C.
A64: 5. Cotizaciones de acero recibidas (sin IVA)
A65: Cotización | B65: Id | C65: Espesor (mm) | D65: Moneda | E65: Precio por kg | F65: TC | G65: USD/kg | H65: Formato | I65: Producto y nota
A66: Pradecon 173170 | B66: Q1 | C66: 0.9 | D66: USD | E66: 1.26285 | F66: 1545 | G66: =IF(D66="USD",E66,E66/F66) -> 1.26285 | H66: Ancho 1.220 | I66: Bobina LAF flejada. Flejado sin cargo.
A67: Pradecon 173170 | B67: Q2 | C67: 1.25 | D67: USD | E67: 1.25056 | F67: 1545 | G67: =IF(D67="USD",E67,E67/F67) -> 1.25056 | H67: Ancho 1.220 | I67: Bobina LAF flejada.
A68: Pradecon 173170 | B68: Q3 | C68: 1.6 | D68: USD | E68: 1.25056 | F68: 1545 | G68: =IF(D68="USD",E68,E68/F68) -> 1.25056 | H68: Ancho 1.220 o 1.000 | I68: Bobina LAF flejada.
A69: Pradecon 173170 | B69: Q4 | C69: 2 | D69: USD | E69: 1.26285 | F69: 1545 | G69: =IF(D69="USD",E69,E69/F69) -> 1.26285 | H69: Ancho 1.220 o 1.000 | I69: Bobina LAF flejada.
A70: Pradecon 173170 | B70: Q5 | C70: 3.2 | D70: USD | E70: 1.11373 | F70: 1545 | G70: =IF(D70="USD",E70,E70/F70) -> 1.11373 | H70: Ancho 1.245 o 1.500 | I70: Bobina LAC flejada.
A71: Pradecon 173170 | B71: Q6 | C71: 4.75 | D71: USD | E71: 1.05792 | F71: 1545 | G71: =IF(D71="USD",E71,E71/F71) -> 1.05792 | H71: 1500 × 3000 | I71: Hoja LAC. Mismo producto que Q11.
A72: Pradecon 173195 | B72: Q7 | C72: 1.6 | D72: ARS | E72: 2051.02 | F72: 1545 | G72: =IF(D72="USD",E72,E72/F72) -> 1.327521 | H72: 1000 × 2000 | I72: Hoja LAF C16.
A73: Pradecon 173195 | B73: Q8 | C73: 1.25 | D73: ARS | E73: 1993.51 | F73: 1545 | G73: =IF(D73="USD",E73,E73/F73) -> 1.2902977 | H73: 1220 × 2440 | I73: Hoja LAF C18.
A74: Pradecon 173195 | B74: Q9 | C74: 2 | D74: ARS | E74: 1978.22 | F74: 1545 | G74: =IF(D74="USD",E74,E74/F74) -> 1.2804013 | H74: 1500 × 3000 | I74: Hoja LAF C14.
A75: Pradecon 173195 | B75: Q10 | C75: 3.2 | D75: ARS | E75: 1702.49 | F75: 1545 | G75: =IF(D75="USD",E75,E75/F75) -> 1.1019353 | H75: 1500 × 3000 | I75: Hoja LAC 1/8.
A76: Pradecon 173195 | B76: Q11 | C76: 4.75 | D76: ARS | E76: 1685.56 | F76: 1545 | G76: =IF(D76="USD",E76,E76/F76) -> 1.0909773 | H76: 1500 × 3000 | I76: Hoja LAC 3/16.
A77: Hierros Parrotta 413329 | B77: Q12 | C77: 0.9 | D77: USD | E77: 1.3561 | F77: 1 | G77: =IF(D77="USD",E77,E77/F77) -> 1.3561 | H77: 1220 × 2440 | I77: Hoja doble decapada N.° 20. Neto con 6,84 % de descuento, contado.
... A91: Pacheco Chapas PR 42024 | B91: Q26 | C91: 4.75 | D91: USD | E91: 1.236 | F91: 1530 | G91: =IF(D91="USD",E91,E91/F91) -> 1.236 | H91: 1245 × 1360 / 1800 | I91: Plancha a medida LAC.
A93: 6. Precio del acero por espesor y forma de compra (USD/kg)
A94: Espesor (mm) | B94: Bobina (A) | C94: Hoja (B y D) | D94: Fleje a medida | E94: Bobina madre (C) | F94: A medida (Ref.) | I94: Cotización usada
A95: 0.9 | B95: =Datos!$G$66 -> 1.26285 | C95: =Datos!$G$77 -> 1.3561 | D95: =Datos!$G$66 -> 1.26285 | E95: =B95*(1+Datos!$B$61) -> 1.26285 | F95: =Datos!$G$77 -> 1.3561 | I95: Bobina Q1 · hoja Q12 · fleje Q1 · a medida Q12. A medida: sin cotización, se toma la hoja Q12.
A96: 1.25 | B96: =Datos!$G$67 -> 1.25056 | C96: =Datos!$G$73 -> 1.2902977 | D96: =Datos!$G$84 -> 1.186 | E96: =B96*(1+Datos!$B$61) -> 1.25056 | F96: =Datos!$G$87 -> 1.426 | I96: Bobina Q2 · hoja Q8 · fleje Q19 · a medida Q22.
A97: 1.6 | B97: =Datos!$G$68 -> 1.25056 | C97: =Datos!$G$72 -> 1.327521 | D97: =Datos!$G$85 -> 1.186 | E97: =B97*(1+Datos!$B$61) -> 1.25056 | F97: =Datos!$G$88 -> 1.453 | I97: Bobina Q3 · hoja Q7 · fleje Q20 · a medida Q23.
A98: 2 | B98: =Datos!$G$69 -> 1.26285 | C98: =Datos!$G$74 -> 1.2804013 | D98: =Datos!$G$86 -> 1.198 | E98: =B98*(1+Datos!$B$61) -> 1.26285 | F98: =Datos!$G$89 -> 1.429 | I98: Bobina Q4 · hoja Q9 · fleje Q21 · a medida Q24.
A99: 3.2 | B99: =Datos!$G$70 -> 1.11373 | C99: =Datos!$G$75 -> 1.1019353 | D99: =Datos!$G$70 -> 1.11373 | E99: =B99*(1+Datos!$B$61) -> 1.11373 | F99: =Datos!$G$90 -> 1.256 | I99: Bobina Q5 · hoja Q10 · fleje Q5 · a medida Q25. Fleje: la bobina flejada Q5.
A100: 4.75 | B100: =Datos!$G$70 -> 1.11373 | C100: =Datos!$G$76 -> 1.0909773 | D100: =Datos!$G$70 -> 1.11373 | E100: =B100*(1+Datos!$B$61) -> 1.11373 | F100: =Datos!$G$91 -> 1.236 | I100: Bobina Q5 · hoja Q11 · fleje Q5 · a medida Q26. Bobina: sin cotización, se toma la de 3,2 (Q5).
A102: 7. Equipos de corte y manejo (USD sin IVA)
A103: Equipo | B103: Precio (USD) | C103: A | D103: B | E103: C | F103: D | G103: Ref. | I103: Fuente
A104: Línea de corte transversal 1-6 mm × 1.600 (desbobinador, aplanadora, alimentador, cizalla) | B104: 80000 | C104: 1 | D104: 0 | E104: 1 | F104: 0 | G104: 0 | I104: ESTIMADO del grupo: Hener da USD 45.000 para 0,2-3 mm × 1.250; para 4,75 mm, más pesada.
A105: Guillotina 1 (franjas) Ermaksan CNC HGS 2600-6, tope 1.000 mm | B105: =Datos!$B$39*Datos!$B$40 -> 29806.259 | C105: 1 | D105: 1 | E105: 0 | F105: 1 | G105: 0 | I105: Anuncio resale.info (usada, 2018), en EUR pasado a USD (sección 3).
A106: Guillotina 2 (piezas) QC12Y 6 × 2500, tope 800 mm | B106: 10700 | C106: 0 | D106: 1 | E106: 0 | F106: 1 | G106: 0 | I106: Publicación Alibaba 1600900259147: FOB China, 1 a 2 unidades.
A107: Cortadora longitudinal 0,3-3,2 × 1.600 | B107: 60000 | C107: 0 | D107: 0 | E107: 1 | F107: 0 | G107: 0 | I107: ESTIMADO del grupo: Cangzhou Zunsheng USD 28.600-59.620 FOB.
A108: Puente grúa monoviga 10 t con carrilera | B108: 30000 | C108: =IF(Datos!$B$62="SI",0,1) -> 1 | D108: 0 | E108: =IF(Datos!$B$62="SI",0,1) -> 1 | F108: 0 | G108: 0 | I108: Dongqi Crane: USD 10.000-50.000 (10 t básico).
A109: Pinza en C portabobinas y cunas | B109: 6000 | C109: 1 | D109: 0 | E109: 1 | F109: 0 | G109: 0 | I109: ESTIMADO del grupo.
A110: Desbobinador, enderezador y alimentador servo de la prensa de discos | B110: 12000 | C110: 1 | D110: 0 | E110: 1 | F110: 1 | G110: 1 | I110: ESTIMADO del grupo (en cotización).
A111: Estantería porta-flejes | B111: 3000 | C111: 1 | D111: 0 | E111: 1 | F111: 1 | G111: 1 | I111: ESTIMADO del grupo.
A112: Autoelevador eléctrico 2,5 t | B112: 20000 | C112: 0 | D112: 1 | E112: 0 | F112: 1 | G112: 0 | I112: Mercado Libre GBA, nuevos 2026: USD 13.700-26.700.
A113: Mesa elevadora de tijera 3 t | B113: 7000 | C113: 0 | D113: 1 | E113: 0 | F113: 1 | G113: 0 | I113: ESTIMADO del grupo.
A114: Mesa de bolas entre la mesa elevadora y la guillotina | B114: 1500 | C114: 0 | D114: 1 | E114: 0 | F114: 1 | G114: 0 | I114: ESTIMADO del grupo.
A115: Racks por espesor y carros porta-desarrollos (pulmón entre guillotinas) | B115: 2000 | C115: 0 | D115: 1 | E115: 0 | F115: 1 | G115: 0 | I115: ESTIMADO del grupo.
A116: Mesa de alimentación de tiras al balancín | B116: 1500 | C116: 0 | D116: 1 | E116: 0 | F116: 0 | G116: 0 | I116: ESTIMADO del grupo.
A117: Inversión por alternativa | C117: =SUMPRODUCT($B$104:$B$116,C104:C116) -> 160806.26 | D117: =SUMPRODUCT($B$104:$B$116,D104:D116) -> 72506.259 | E117: =SUMPRODUCT($B$104:$B$116,E104:E116) -> 191000 | F117: =SUMPRODUCT($B$104:$B$116,F104:F116) -> 86006.259 | G117: =SUMPRODUCT($B$104:$B$116,G104:G116) -> 15000
A118: Prensa de discos y cilindradoras están en todas las alternativas y no entran. La guillotina 2 está a precio FOB.

Sheet Demanda
A1: Demanda: cuerpos a fabricar por formato
A2: Terminados + cilindros vacíos + sustitutos de las dos plantas de recargas, todo desde la hoja Links. Cada unidad lleva un cuerpo; las de 1 a 10 kg, además, cúpula y fondo.
A4: Unidades a fabricar = terminados + cilindros + sustitutos
A5: Formato | B5: Línea | C5: 2026 | D5: 2027 | E5: 2028 | F5: 2029 | G5: 2030 | H5: 2031 | I5: 2032 | J5: 2033 | K5: 2034 | L5: 2035
A6: 1 kg | B6: Manual | C6: =IFERROR(Links!C11,0)+IFERROR(Links!C22,0)+IFERROR(Links!C33,0)+IFERROR(Links!C44,0) -> 4178.7365 | D6: =IFERROR(Links!D11,0)+IFERROR(Links!D22,0)+IFERROR(Links!D33,0)+IFERROR(Links!D44,0) -> 5997.304 | E6: =IFERROR(Links!E11,0)+IFERROR(Links!E22,0)+IFERROR(Links!E33,0)+IFERROR(Links!E44,0) -> 14514.148 | F6: =IFERROR(Links!F11,0)+IFERROR(Links!F22,0)+IFERROR(Links!F33,0)+IFERROR(Links!F44,0) -> 35161.936 | G6: =IFERROR(Links!G11,0)+IFERROR(Links!G22,0)+IFERROR(Links!G33,0)+IFERROR(Links!G44,0) -> 62115.433 | H6: =IFERROR(Links!H11,0)+IFERROR(Links!H22,0)+IFERROR(Links!H33,0)+IFERROR(Links!H44,0) -> 87300.453 | I6: =IFERROR(Links!I11,0)+IFERROR(Links!I22,0)+IFERROR(Links!I33,0)+IFERROR(Links!I44,0) -> 121673.15 | J6: =IFERROR(Links!J11,0)+IFERROR(Links!J22,0)+IFERROR(Links!J33,0)+IFERROR(Links!J44,0) -> 156133.08 | ... L6: =IFERROR(Links!L11,0)+IFERROR(Links!L22,0)+IFERROR(Links!L33,0)+IFERROR(Links!L44,0) -> 202620.64
A7: 2,5 kg | B7: Manual | C7: =IFERROR(Links!C12,0)+IFERROR(Links!C23,0)+IFERROR(Links!C34,0)+IFERROR(Links!C45,0) -> 300.03036 | D7: =IFERROR(Links!D12,0)+IFERROR(Links!D23,0)+IFERROR(Links!D34,0)+IFERROR(Links!D45,0) -> 724.12745 | E7: =IFERROR(Links!E12,0)+IFERROR(Links!E23,0)+IFERROR(Links!E34,0)+IFERROR(Links!E45,0) -> 1309.9881 | F7: =IFERROR(Links!F12,0)+IFERROR(Links!F23,0)+IFERROR(Links!F34,0)+IFERROR(Links!F45,0) -> 2581.7182 | G7: =IFERROR(Links!G12,0)+IFERROR(Links!G23,0)+IFERROR(Links!G34,0)+IFERROR(Links!G45,0) -> 4284.6277 | H7: =IFERROR(Links!H12,0)+IFERROR(Links!H23,0)+IFERROR(Links!H34,0)+IFERROR(Links!H45,0) -> 6099.5099 | I7: =IFERROR(Links!I12,0)+IFERROR(Links!I23,0)+IFERROR(Links!I34,0)+IFERROR(Links!I45,0) -> 8105.7555 | J7: =IFERROR(Links!J12,0)+IFERROR(Links!J23,0)+IFERROR(Links!J34,0)+IFERROR(Links!J45,0) -> 10259.067 | ... L7: =IFERROR(Links!L12,0)+IFERROR(Links!L23,0)+IFERROR(Links!L34,0)+IFERROR(Links!L45,0) -> 14126.338
A8: 5 kg | B8: Manual | C8: =IFERROR(Links!C13,0)+IFERROR(Links!C24,0)+IFERROR(Links!C35,0)+IFERROR(Links!C46,0) -> 2281.773 | D8: =IFERROR(Links!D13,0)+IFERROR(Links!D24,0)+IFERROR(Links!D35,0)+IFERROR(Links!D46,0) -> 3928.0589 | E8: =IFERROR(Links!E13,0)+IFERROR(Links!E24,0)+IFERROR(Links!E35,0)+IFERROR(Links!E46,0) -> 6711.7376 | F8: =IFERROR(Links!F13,0)+IFERROR(Links!F24,0)+IFERROR(Links!F35,0)+IFERROR(Links!F46,0) -> 12203.995 | G8: =IFERROR(Links!G13,0)+IFERROR(Links!G24,0)+IFERROR(Links!G35,0)+IFERROR(Links!G46,0) -> 20592.787 | H8: =IFERROR(Links!H13,0)+IFERROR(Links!H24,0)+IFERROR(Links!H35,0)+IFERROR(Links!H46,0) -> 28701.604 | I8: =IFERROR(Links!I13,0)+IFERROR(Links!I24,0)+IFERROR(Links!I35,0)+IFERROR(Links!I46,0) -> 38664.6 | J8: =IFERROR(Links!J13,0)+IFERROR(Links!J24,0)+IFERROR(Links!J35,0)+IFERROR(Links!J46,0) -> 48842.226 | ... L8: =IFERROR(Links!L13,0)+IFERROR(Links!L24,0)+IFERROR(Links!L35,0)+IFERROR(Links!L46,0) -> 63852.659
A9: 10 kg | B9: Manual | C9: =IFERROR(Links!C14,0)+IFERROR(Links!C25,0)+IFERROR(Links!C36,0)+IFERROR(Links!C47,0) -> 94.833182 | D9: =IFERROR(Links!D14,0)+IFERROR(Links!D25,0)+IFERROR(Links!D36,0)+IFERROR(Links!D47,0) -> 182.4873 | E9: =IFERROR(Links!E14,0)+IFERROR(Links!E25,0)+IFERROR(Links!E36,0)+IFERROR(Links!E47,0) -> 352.01878 | F9: =IFERROR(Links!F14,0)+IFERROR(Links!F25,0)+IFERROR(Links!F36,0)+IFERROR(Links!F47,0) -> 687.30049 | G9: =IFERROR(Links!G14,0)+IFERROR(Links!G25,0)+IFERROR(Links!G36,0)+IFERROR(Links!G47,0) -> 1200.4382 | H9: =IFERROR(Links!H14,0)+IFERROR(Links!H25,0)+IFERROR(Links!H36,0)+IFERROR(Links!H47,0) -> 1735.685 | I9: =IFERROR(Links!I14,0)+IFERROR(Links!I25,0)+IFERROR(Links!I36,0)+IFERROR(Links!I47,0) -> 2335.9605 | J9: =IFERROR(Links!J14,0)+IFERROR(Links!J25,0)+IFERROR(Links!J36,0)+IFERROR(Links!J47,0) -> 2951.5648 | ... L9: =IFERROR(Links!L14,0)+IFERROR(Links!L25,0)+IFERROR(Links!L36,0)+IFERROR(Links!L47,0) -> 3862.9281
A10: 25 kg | B10: Rodante | C10: =IFERROR(Links!C15,0)+IFERROR(Links!C26,0)+IFERROR(Links!C37,0)+IFERROR(Links!C48,0) -> 36.051791 | D10: =IFERROR(Links!D15,0)+IFERROR(Links!D26,0)+IFERROR(Links!D37,0)+IFERROR(Links!D48,0) -> 58.622147 | E10: =IFERROR(Links!E15,0)+IFERROR(Links!E26,0)+IFERROR(Links!E37,0)+IFERROR(Links!E48,0) -> 90.76854 | F10: =IFERROR(Links!F15,0)+IFERROR(Links!F26,0)+IFERROR(Links!F37,0)+IFERROR(Links!F48,0) -> 152.96985 | G10: =IFERROR(Links!G15,0)+IFERROR(Links!G26,0)+IFERROR(Links!G37,0)+IFERROR(Links!G48,0) -> 252.276 | H10: =IFERROR(Links!H15,0)+IFERROR(Links!H26,0)+IFERROR(Links!H37,0)+IFERROR(Links!H48,0) -> 349.57448 | I10: =IFERROR(Links!I15,0)+IFERROR(Links!I26,0)+IFERROR(Links!I37,0)+IFERROR(Links!I48,0) -> 465.46823 | J10: =IFERROR(Links!J15,0)+IFERROR(Links!J26,0)+IFERROR(Links!J37,0)+IFERROR(Links!J48,0) -> 586.72867 | ... L10: =IFERROR(Links!L15,0)+IFERROR(Links!L26,0)+IFERROR(Links!L37,0)+IFERROR(Links!L48,0) -> 777.31053
A11: 50 kg | B11: Rodante | C11: =IFERROR(Links!C16,0)+IFERROR(Links!C27,0)+IFERROR(Links!C38,0)+IFERROR(Links!C49,0) -> 76.913941 | D11: =IFERROR(Links!D16,0)+IFERROR(Links!D27,0)+IFERROR(Links!D38,0)+IFERROR(Links!D49,0) -> 129.77672 | E11: =IFERROR(Links!E16,0)+IFERROR(Links!E27,0)+IFERROR(Links!E38,0)+IFERROR(Links!E49,0) -> 200.49879 | F11: =IFERROR(Links!F16,0)+IFERROR(Links!F27,0)+IFERROR(Links!F38,0)+IFERROR(Links!F49,0) -> 337.44568 | G11: =IFERROR(Links!G16,0)+IFERROR(Links!G27,0)+IFERROR(Links!G38,0)+IFERROR(Links!G49,0) -> 554.00721 | H11: =IFERROR(Links!H16,0)+IFERROR(Links!H27,0)+IFERROR(Links!H38,0)+IFERROR(Links!H49,0) -> 769.13586 | I11: =IFERROR(Links!I16,0)+IFERROR(Links!I27,0)+IFERROR(Links!I38,0)+IFERROR(Links!I49,0) -> 1025.2701 | J11: =IFERROR(Links!J16,0)+IFERROR(Links!J27,0)+IFERROR(Links!J38,0)+IFERROR(Links!J49,0) -> 1292.1071 | ... L11: =IFERROR(Links!L16,0)+IFERROR(Links!L27,0)+IFERROR(Links!L38,0)+IFERROR(Links!L49,0) -> 1708.4352
A12: 70 kg | B12: Rodante | C12: =IFERROR(Links!C17,0)+IFERROR(Links!C28,0)+IFERROR(Links!C39,0)+IFERROR(Links!C50,0) -> 18.34486 | D12: =IFERROR(Links!D17,0)+IFERROR(Links!D28,0)+IFERROR(Links!D39,0)+IFERROR(Links!D50,0) -> 28.221831 | E12: =IFERROR(Links!E17,0)+IFERROR(Links!E28,0)+IFERROR(Links!E39,0)+IFERROR(Links!E50,0) -> 43.260099 | F12: =IFERROR(Links!F17,0)+IFERROR(Links!F28,0)+IFERROR(Links!F39,0)+IFERROR(Links!F50,0) -> 73.814329 | G12: =IFERROR(Links!G17,0)+IFERROR(Links!G28,0)+IFERROR(Links!G39,0)+IFERROR(Links!G50,0) -> 122.26048 | H12: =IFERROR(Links!H17,0)+IFERROR(Links!H28,0)+IFERROR(Links!H39,0)+IFERROR(Links!H50,0) -> 167.52855 | I12: =IFERROR(Links!I17,0)+IFERROR(Links!I28,0)+IFERROR(Links!I39,0)+IFERROR(Links!I50,0) -> 224.48075 | J12: =IFERROR(Links!J17,0)+IFERROR(Links!J28,0)+IFERROR(Links!J39,0)+IFERROR(Links!J50,0) -> 281.64736 | ... L12: =IFERROR(Links!L17,0)+IFERROR(Links!L28,0)+IFERROR(Links!L39,0)+IFERROR(Links!L50,0) -> 374.12986
A13: 100 kg | B13: Rodante | C13: =IFERROR(Links!C18,0)+IFERROR(Links!C29,0)+IFERROR(Links!C40,0)+IFERROR(Links!C51,0) -> 12.896573 | D13: =IFERROR(Links!D18,0)+IFERROR(Links!D29,0)+IFERROR(Links!D40,0)+IFERROR(Links!D51,0) -> 18.867887 | E13: =IFERROR(Links!E18,0)+IFERROR(Links!E29,0)+IFERROR(Links!E40,0)+IFERROR(Links!E51,0) -> 28.826733 | F13: =IFERROR(Links!F18,0)+IFERROR(Links!F29,0)+IFERROR(Links!F40,0)+IFERROR(Links!F51,0) -> 48.329553 | G13: =IFERROR(Links!G18,0)+IFERROR(Links!G29,0)+IFERROR(Links!G40,0)+IFERROR(Links!G51,0) -> 80.640321 | H13: =IFERROR(Links!H18,0)+IFERROR(Links!H29,0)+IFERROR(Links!H40,0)+IFERROR(Links!H51,0) -> 110.85903 | I13: =IFERROR(Links!I18,0)+IFERROR(Links!I29,0)+IFERROR(Links!I40,0)+IFERROR(Links!I51,0) -> 149.89383 | J13: =IFERROR(Links!J18,0)+IFERROR(Links!J29,0)+IFERROR(Links!J40,0)+IFERROR(Links!J51,0) -> 186.51157 | ... L13: =IFERROR(Links!L18,0)+IFERROR(Links!L29,0)+IFERROR(Links!L40,0)+IFERROR(Links!L51,0) -> 247.44657
A14: Total | C14: =SUM(C6:C13) -> 6999.5803 | D14: =SUM(D6:D13) -> 11067.466 | E14: =SUM(E6:E13) -> 23251.246 | F14: =SUM(F6:F13) -> 51247.509 | G14: =SUM(G6:G13) -> 89202.47 | H14: =SUM(H6:H13) -> 125234.35 | I14: =SUM(I6:I13) -> 172644.58 | J14: =SUM(J6:J13) -> 220532.93 | ... L14: =SUM(L6:L13) -> 287569.89
A16: Discos de rodantes (25 a 100 kg): se compran embutidos, no entran en este análisis.

Sheet Piezas
A1: Piezas del plano: cuerpos y discos de cúpula y fondo
A2: Medidas de los planos de recipiente (modelo 3D). El disco sale de la pieza embutida por igualdad de superficie, con su relación de embutido.
A4: A) Cuerpos (desarrollo = π·(Ø − e), fibra media)
A5: Formato | B5: Línea | C5: Plano | D5: Ø ext. (mm) | E5: Espesor (mm) | F5: Alto (mm) | G5: Desarrollo (mm) | H5: Masa (kg) | I5: Acero
A6: 1 kg | B6: Manual | C6: Plano recipiente 1 kg 3" R1 | D6: 76.2 | E6: 0.9 | F6: 263.5 | G6: =ROUND(PI()*(D6-E6)*2,0)/2 -> 236.5 | H6: =F6*G6*E6*Datos!$B$10/1000000 -> 0.44139662 | I6: LAF
A7: 2,5 kg | B7: Manual | C7: Plano recipiente 2,5 kg R2 | D7: 124 | E7: 1.25 | F7: 267.5 | G7: =ROUND(PI()*(D7-E7)*2,0)/2 -> 385.5 | H7: =F7*G7*E7*Datos!$B$10/1000000 -> 1.0144553 | I7: LAF
A8: 5 kg | B8: Manual | C8: Plano recipiente 5 kg R2 | D8: 153 | E8: 1.6 | F8: 327.5 | G8: =ROUND(PI()*(D8-E8)*2,0)/2 -> 475.5 | H8: =F8*G8*E8*Datos!$B$10/1000000 -> 1.9609049 | I8: LAF
A9: 10 kg | B9: Manual | C9: Plano recipiente 10 kg R2 | D9: 181.5 | E9: 2 | F9: 493 | G9: =ROUND(PI()*(D9-E9)*2,0)/2 -> 564 | H9: =F9*G9*E9*Datos!$B$10/1000000 -> 4.3765385 | I9: LAF
A10: 25 kg | B10: Rodante | C10: Plano recipiente 25 kg R3 | D10: 276.5 | E10: 3.2 | F10: 493 | G10: =ROUND(PI()*(D10-E10)*2,0)/2 -> 858.5 | H10: =F10*G10*E10*Datos!$B$10/1000000 -> 10.658889 | I10: LAC
A11: 50 kg | B11: Rodante | C11: Plano recipiente 50 kg R2 | D11: 320 | E11: 3.2 | F11: 640 | G11: =ROUND(PI()*(D11-E11)*2,0)/2 -> 995.5 | H11: =F11*G11*E11*Datos!$B$10/1000000 -> 16.04523 | I11: LAC
A12: 70 kg | B12: Rodante | C12: Plano extintor rodante 70 kg (Ø390) | D12: 390 | E12: 4.75 | F12: 680 | G12: =ROUND(PI()*(D12-E12)*2,0)/2 -> 1210.5 | H12: =F12*G12*E12*Datos!$B$10/1000000 -> 30.771031 | I12: LAC
A13: 100 kg | B13: Rodante | C13: Plano extintor rodante 100 kg R1 (Ø390) | D13: 390 | E13: 4.75 | F13: 900 | G13: =ROUND(PI()*(D13-E13)*2,0)/2 -> 1210.5 | H13: =F13*G13*E13*Datos!$B$10/1000000 -> 40.726365 | I13: LAC
A14: Alto: cuerpo del modelo 3D del plano (incluye el labio del encastre). 1 kg en chapa de 0,9 mm por decisión del grupo.
A16: B) Discos: igual superficie que la pieza embutida (sin sobremedida de recorte)
A17: Formato | B17: Pieza | C17: Perfil del plano | D17: Espesor e (mm) | E17: Ø ext. (mm) | F17: Altura h (mm) | G17: Pollera o pestaña p (mm) | H17: a = Ø/2 − e/2 (mm) | I17: b o profundidad (mm) | J17: Área media (mm²) | K17: D0 = √(4A/π) (mm) | L17: D0 adoptado (mm) | M17: d = 2a (mm) | N17: m = d/D0 | O17: e/D0 × 100 | P17: m1 mínimo | Q17: ¿Un solo embutido? | R17: h/d | S17: Masa del disco (kg) | T17: Plano | V17: e/D0 × 100 desde | W17: hasta | X17: m1 (1.er embutido)
A18: 1 kg | B18: Cúpula | C18: Semielipsoide + pollera | D18: 0.9 | E18: 76.2 | F18: 12.5 | G18: 6 | H18: =E18/2-D18/2 -> 37.65 | I18: =F18-G18-D18/2 -> 6.05 | J18: =PI()*H18^2+PI()*I18^2/(2*SQRT(1-(I18/H18)^2))*LN((1+SQRT(1-(I18/H18)^2))/(1-SQRT(1-(I18/H18)^2)))+2*PI()*H18*G18 -> 6165.6464 | K18: =SQRT(4*J18/PI()) -> 88.602172 | L18: =CEILING(K18,0.5) -> 89 | M18: =2*H18 -> 75.3 | N18: =M18/L18 -> 0.84606742 | O18: =D18/L18*100 -> 1.011236 | P18: =INDEX($X$18:$X$23,MATCH(O18,$V$18:$V$23,1)) -> 0.53 | Q18: =IF(N18>=P18,"Sí","No: dos embutidos") -> Sí | R18: =F18/E18 -> 0.16404199 | S18: =PI()*L18^2/4*D18*Datos!$B$10/1000000 -> 0.044064326 | T18: Plano recipiente 1 kg 3" R1 | V18: 0.08 | W18: 0.15 | X18: 0.63
A19: 1 kg | B19: Fondo | C19: Semielipsoide + pollera | D19: 1.25 | E19: 76.2 | F19: 22 | G19: 6 | H19: =E19/2-D19/2 -> 37.475 | I19: =F19-G19-D19/2 -> 15.375 | J19: =PI()*H19^2+PI()*I19^2/(2*SQRT(1-(I19/H19)^2))*LN((1+SQRT(1-(I19/H19)^2))/(1-SQRT(1-(I19/H19)^2)))+2*PI()*H19*G19 -> 7078.062 | K19: =SQRT(4*J19/PI()) -> 94.931915 | L19: =CEILING(K19,0.5) -> 95 | M19: =2*H19 -> 74.95 | N19: =M19/L19 -> 0.78894737 | O19: =D19/L19*100 -> 1.3157895 | P19: =INDEX($X$18:$X$23,MATCH(O19,$V$18:$V$23,1)) -> 0.53 | Q19: =IF(N19>=P19,"Sí","No: dos embutidos") -> Sí | R19: =F19/E19 -> 0.28871391 | S19: =PI()*L19^2/4*D19*Datos!$B$10/1000000 -> 0.069730349 | T19: Plano recipiente 1 kg 3" R1 | V19: 0.15 | W19: 0.3 | X19: 0.6
A20: 2,5 kg | B20: Cúpula | C20: Semielipsoide + pollera | D20: 1.25 | E20: 124 | F20: 39.5 | G20: 6 | H20: =E20/2-D20/2 -> 61.375 | I20: =F20-G20-D20/2 -> 32.875 | J20: =PI()*H20^2+PI()*I20^2/(2*SQRT(1-(I20/H20)^2))*LN((1+SQRT(1-(I20/H20)^2))/(1-SQRT(1-(I20/H20)^2)))+2*PI()*H20*G20 -> 19119.382 | K20: =SQRT(4*J20/PI()) -> 156.02421 | L20: =CEILING(K20,0.5) -> 156.5 | M20: =2*H20 -> 122.75 | N20: =M20/L20 -> 0.78434505 | O20: =D20/L20*100 -> 0.79872204 | P20: =INDEX($X$18:$X$23,MATCH(O20,$V$18:$V$23,1)) -> 0.55 | Q20: =IF(N20>=P20,"Sí","No: dos embutidos") -> Sí | R20: =F20/E20 -> 0.31854839 | S20: =PI()*L20^2/4*D20*Datos!$B$10/1000000 -> 0.1892358 | T20: Plano recipiente 2,5 kg R2 | V20: 0.3 | W20: 0.6 | X20: 0.58
A21: 2,5 kg | B21: Fondo | C21: Paraboloide + pestaña | D21: 1.25 | E21: 121.5 | F21: 10.5 | G21: 10 | H21: =E21/2-D21/2 -> 60.125 | I21: =F21 -> 10.5 | J21: =PI()*H21^4/(6*I21^2)*((1+4*I21^2/H21^2)^1.5-1)+2*PI()*H21*G21 -> 15474.294 | K21: =SQRT(4*J21/PI()) -> 140.36553 | L21: =CEILING(K21,0.5) -> 140.5 | M21: =2*H21 -> 120.25 | N21: =M21/L21 -> 0.85587189 | O21: =D21/L21*100 -> 0.88967972 | P21: =INDEX($X$18:$X$23,MATCH(O21,$V$18:$V$23,1)) -> 0.55 | Q21: =IF(N21>=P21,"Sí","No: dos embutidos") -> Sí | R21: =(F21+G21)/E21 -> 0.16872428 | S21: =PI()*L21^2/4*D21*Datos!$B$10/1000000 -> 0.15252017 | T21: Plano recipiente 2,5 kg R2; Ø del fondo = Ø del cuerpo − 2 e | V21: 0.6 | W21: 1 | X21: 0.55
A22: 5 kg | B22: Cúpula | C22: Semielipsoide + pollera | D22: 1.6 | E22: 153 | F22: 54.5 | G22: 6 | H22: =E22/2-D22/2 -> 75.7 | I22: =F22-G22-D22/2 -> 47.7 | J22: =PI()*H22^2+PI()*I22^2/(2*SQRT(1-(I22/H22)^2))*LN((1+SQRT(1-(I22/H22)^2))/(1-SQRT(1-(I22/H22)^2)))+2*PI()*H22*G22 -> 30398.075 | K22: =SQRT(4*J22/PI()) -> 196.7334 | L22: =CEILING(K22,0.5) -> 197 | M22: =2*H22 -> 151.4 | N22: =M22/L22 -> 0.76852792 | O22: =D22/L22*100 -> 0.81218274 | P22: =INDEX($X$18:$X$23,MATCH(O22,$V$18:$V$23,1)) -> 0.55 | Q22: =IF(N22>=P22,"Sí","No: dos embutidos") -> Sí | R22: =F22/E22 -> 0.35620915 | S22: =PI()*L22^2/4*D22*Datos!$B$10/1000000 -> 0.38381067 | T22: Plano recipiente 5 kg R2 | V22: 1 | W22: 1.5 | X22: 0.53
A23: 5 kg | B23: Fondo | C23: Paraboloide + pestaña | D23: 1.6 | E23: 149.8 | F23: 16 | G23: 10 | H23: =E23/2-D23/2 -> 74.1 | I23: =F23 -> 16 | J23: =PI()*H23^4/(6*I23^2)*((1+4*I23^2/H23^2)^1.5-1)+2*PI()*H23*G23 -> 22686.58 | K23: =SQRT(4*J23/PI()) -> 169.9572 | L23: =CEILING(K23,0.5) -> 170 | M23: =2*H23 -> 148.2 | N23: =M23/L23 -> 0.87176471 | O23: =D23/L23*100 -> 0.94117647 | P23: =INDEX($X$18:$X$23,MATCH(O23,$V$18:$V$23,1)) -> 0.55 | Q23: =IF(N23>=P23,"Sí","No: dos embutidos") -> Sí | R23: =(F23+G23)/E23 -> 0.17356475 | S23: =PI()*L23^2/4*D23*Datos!$B$10/1000000 -> 0.2858133 | T23: Plano recipiente 5 kg R2; Ø del fondo = Ø del cuerpo − 2 e | V23: 1.5 | W23: 2 | X23: 0.5
A24: 10 kg | B24: Cúpula | C24: Semielipsoide + pollera | D24: 1.6 | E24: 181.5 | F24: 62.5 | G24: 6 | H24: =E24/2-D24/2 -> 89.95 | I24: =F24-G24-D24/2 -> 55.7 | J24: =PI()*H24^2+PI()*I24^2/(2*SQRT(1-(I24/H24)^2))*LN((1+SQRT(1-(I24/H24)^2))/(1-SQRT(1-(I24/H24)^2)))+2*PI()*H24*G24 -> 41952.632 | K24: =SQRT(4*J24/PI()) -> 231.11848 | L24: =CEILING(K24,0.5) -> 231.5 | M24: =2*H24 -> 179.9 | N24: =M24/L24 -> 0.77710583 | O24: =D24/L24*100 -> 0.69114471 | P24: =INDEX($X$18:$X$23,MATCH(O24,$V$18:$V$23,1)) -> 0.55 | Q24: =IF(N24>=P24,"Sí","No: dos embutidos") -> Sí | R24: =F24/E24 -> 0.34435262 | S24: =PI()*L24^2/4*D24*Datos!$B$10/1000000 -> 0.53001308 | T24: Plano recipiente 10 kg R2 | V24: Valor alto de cada rango (lado seguro).
A25: 10 kg | B25: Fondo | C25: Paraboloide + pestaña | D25: 2 | E25: 177.5 | F25: 11.7 | G25: 10 | H25: =E25/2-D25/2 -> 87.75 | I25: =F25 -> 11.7 | J25: =PI()*H25^4/(6*I25^2)*((1+4*I25^2/H25^2)^1.5-1)+2*PI()*H25*G25 -> 30129.042 | K25: =SQRT(4*J25/PI()) -> 195.86089 | L25: =CEILING(K25,0.5) -> 196 | M25: =2*H25 -> 175.5 | N25: =M25/L25 -> 0.89540816 | O25: =D25/L25*100 -> 1.0204082 | P25: =INDEX($X$18:$X$23,MATCH(O25,$V$18:$V$23,1)) -> 0.53 | Q25: =IF(N25>=P25,"Sí","No: dos embutidos") -> Sí | R25: =(F25+G25)/E25 -> 0.12225352 | S25: =PI()*L25^2/4*D25*Datos!$B$10/1000000 -> 0.47490501 | T25: Plano recipiente 10 kg R2; Ø del fondo = Ø del cuerpo − 2 e
A27: Fuentes
A28: Disco y pieza tienen la misma superficie (el espesor no cambia): Harsle, «How to Calculate Deep Drawing Parts» (harslepress.com).
A29: Superficie del semielipsoide achatado y del paraboloide de revolución: fórmulas de geometría (MathWorld, «Oblate Spheroid» y «Paraboloid»).
A30: m1: relación de embutido del primer paso, copa sin brida, con prensachapas (EasyChair, preprint Vxvp, tabla 2). Límite general D0/d ≤ 2 (Univ. Mustansiriyah, apunte de embutido).
A31: Sin sobremedida de recorte: la prensa corta y embute en el mismo golpe, sin recorte después (W-MAN, puesto 4), y la tabla de recorte de Harsle arranca en h/d = 0,5 (estas piezas tienen h/d de 0,12 a 0,36).
A32: Geometría (Ø, alturas, pollera de 6 mm, pestaña de 10 mm, espesores): planos de recipiente (modelo 3D).

Sheet Corte
A1: Corte: cómo sale cada pieza de la hoja, la bobina, el fleje y la bobina madre
A2: Medidas de la hoja Piezas. G1 corta franjas por el lado corto de la hoja; pasan por un pulmón y G2 apoya las franjas de hojas enteras una al lado de la otra y corta una pieza de cada una por golpe.
A4: A) Cuerpos en hoja estándar con dos guillotinas en serie (B y D)
A5: Formato | B5: Hoja: lado corto (mm) | C5: Hoja: lado largo (mm) | D5: Orientación (1 alto, 2 desarrollo a lo largo) | E5: Franja = 1.er corte y tope de G1 (mm) | F5: Franjas por hoja | G5: Pieza = 2.º corte (mm) | H5: Piezas por franja | I5: Piezas por hoja | J5: Aprovech. | K5: Masa de la franja (kg) | L5: Tope de G2 (pieza u orilla, mm) | M5: Franjas que entran en G2 | N5: Hojas por ciclo | O5: Tandas de G2 por ciclo | P5: Golpes G1 por hoja | Q5: Golpes G2 por tanda | R5: Golpes G2 por hoja | S5: Min G1 por hoja | T5: Min G2 por hoja | U5: Manda | V5: Cuerpos por hora | W5: Masa de la hoja (kg) | X5: USD por hoja | Y5: Control | AA5: Tandas por hoja con ciclo de 1 hoja | AB5: 2 hojas | AC5: 3 hojas | AD5: 4 hojas | AE5: Piezas por hoja, orientación 1 | AF5: orientación 2
A6: 1 kg | B6: 1220 | C6: 2440 | D6: =IF(AE6>AF6,1,IF(AF6>AE6,2,IF(INT(C6/Piezas!$F$6)<=INT(C6/Piezas!$G$6),1,2))) -> 1 | E6: =IF(D6=1,Piezas!$F$6,Piezas!$G$6) -> 263.5 | F6: =INT(C6/E6) -> 9 | G6: =IF(D6=1,Piezas!$G$6,Piezas!$F$6) -> 236.5 | H6: =INT(B6/G6) -> 5 | I6: =F6*H6 -> 45 | J6: =I6*Piezas!$F$6*Piezas!$G$6/(B6*C6) -> 0.94205145 | K6: =E6*B6*Piezas!$E$6*Datos!$B$10/1000000 -> 2.276972 | L6: =IF(G6<=Datos!$B$37,G6,B6-H6*G6) -> 236.5 | M6: =INT(Datos!$B$36/E6) -> 9 | N6: =MATCH(MIN(AA6:AD6),AA6:AD6,0) -> 1 | O6: =ROUND(INDEX(AA6:AD6,N6)*N6,0) -> 1 | P6: =IF(C6-F6*E6>0.001,F6,F6-1) -> 9 | Q6: =IF(G6<=Datos!$B$37,IF(B6-H6*G6>0.001,H6,H6-1),1) -> 5 | R6: =Q6*O6/N6 -> 5 | S6: =P6/Datos!$B$32 -> 0.45 | T6: =R6/Datos!$B$35 -> 0.25 | U6: =IF(S6>=T6,"G1","G2") -> G1 | V6: =I6*60/MAX(S6,T6) -> 6000 | W6: =B6*C6*Piezas!$E$6*Datos!$B$10/1000000 -> 21.084674 | X6: =W6*INDEX(Datos!$C$95:$C$100,MATCH(Piezas!$E$6,Datos!$A$95:$A$100,0)) -> 28.592927 | Y6: =IF(I6=0,"No entra ninguna pieza",IF(B6>Datos!$B$33,"Hoja más ancha que la cuchilla de G1",IF(E6>Datos!$B$34,"Franja mayor que el tope de G1",IF(L6>Datos!$B$37,"2.º corte mayor que el tope de G2",IF(M6<1,"La franja no entra en G2","OK"))))) -> OK | AA6: =IFERROR(IF(1>Datos!$B$38,1000000000,CEILING(1*F6/M6,1)/1),1000000000) -> 1 | AB6: =IFERROR(IF(2>Datos!$B$38,1000000000,CEILING(2*F6/M6,1)/2),1000000000) -> 1 | AC6: =IFERROR(IF(3>Datos!$B$38,1000000000,CEILING(3*F6/M6,1)/3),1000000000) -> 1 | AD6: =IFERROR(IF(4>Datos!$B$38,1000000000,CEILING(4*F6/M6,1)/4),1000000000) -> 1 | AE6: =IF(AND(Piezas!$F$6<=Datos!$B$34,Piezas!$F$6<=Datos!$B$36,B6<=Datos!$B$33,OR(Piezas!$G$6<=Datos!$B$37,AND(INT(B6/Piezas!$G$6)=1,B6-Piezas!$G$6<=Datos!$B$37))),INT(C6/Piezas!$F$6)*INT(B6/Piezas!$G$6),0) -> 45 | AF6: =IF(AND(Piezas!$G$6<=Datos!$B$34,Piezas!$G$6<=Datos!$B$36,B6<=Datos!$B$33,OR(Piezas!$F$6<=Datos!$B$37,AND(INT(B6/Piezas!$F$6)=1,B6-Piezas!$F$6<=Datos!$B$37))),INT(C6/Piezas!$G$6)*INT(B6/Piezas!$F$6),0) -> 40
A7: 2,5 kg | B7: 1220 | C7: 2440 | D7: =IF(AE7>AF7,1,IF(AF7>AE7,2,IF(INT(C7/Piezas!$F$7)<=INT(C7/Piezas!$G$7),1,2))) -> 1 | E7: =IF(D7=1,Piezas!$F$7,Piezas!$G$7) -> 267.5 | F7: =INT(C7/E7) -> 9 | G7: =IF(D7=1,Piezas!$G$7,Piezas!$F$7) -> 385.5 | H7: =INT(B7/G7) -> 3 | I7: =F7*H7 -> 27 | J7: =I7*Piezas!$F$7*Piezas!$G$7/(B7*C7) -> 0.93532443 | K7: =E7*B7*Piezas!$E$7*Datos!$B$10/1000000 -> 3.2104681 | L7: =IF(G7<=Datos!$B$37,G7,B7-H7*G7) -> 385.5 | M7: =INT(Datos!$B$36/E7) -> 9 | N7: =MATCH(MIN(AA7:AD7),AA7:AD7,0) -> 1 | O7: =ROUND(INDEX(AA7:AD7,N7)*N7,0) -> 1 | P7: =IF(C7-F7*E7>0.001,F7,F7-1) -> 9 | Q7: =IF(G7<=Datos!$B$37,IF(B7-H7*G7>0.001,H7,H7-1),1) -> 3 | R7: =Q7*O7/N7 -> 3 | S7: =P7/Datos!$B$32 -> 0.45 | T7: =R7/Datos!$B$35 -> 0.15 | U7: =IF(S7>=T7,"G1","G2") -> G1 | V7: =I7*60/MAX(S7,T7) -> 3600 | W7: =B7*C7*Piezas!$E$7*Datos!$B$10/1000000 -> 29.28427 | X7: =W7*INDEX(Datos!$C$95:$C$100,MATCH(Piezas!$E$7,Datos!$A$95:$A$100,0)) -> 37.785427 | Y7: =IF(I7=0,"No entra ninguna pieza",IF(B7>Datos!$B$33,"Hoja más ancha que la cuchilla de G1",IF(E7>Datos!$B$34,"Franja mayor que el tope de G1",IF(L7>Datos!$B$37,"2.º corte mayor que el tope de G2",IF(M7<1,"La franja no entra en G2","OK"))))) -> OK | AA7: =IFERROR(IF(1>Datos!$B$38,1000000000,CEILING(1*F7/M7,1)/1),1000000000) -> 1 | AB7: =IFERROR(IF(2>Datos!$B$38,1000000000,CEILING(2*F7/M7,1)/2),1000000000) -> 1 | AC7: =IFERROR(IF(3>Datos!$B$38,1000000000,CEILING(3*F7/M7,1)/3),1000000000) -> 1 | AD7: =IFERROR(IF(4>Datos!$B$38,1000000000,CEILING(4*F7/M7,1)/4),1000000000) -> 1 | AE7: =IF(AND(Piezas!$F$7<=Datos!$B$34,Piezas!$F$7<=Datos!$B$36,B7<=Datos!$B$33,OR(Piezas!$G$7<=Datos!$B$37,AND(INT(B7/Piezas!$G$7)=1,B7-Piezas!$G$7<=Datos!$B$37))),INT(C7/Piezas!$F$7)*INT(B7/Piezas!$G$7),0) -> 27 | AF7: =IF(AND(Piezas!$G$7<=Datos!$B$34,Piezas!$G$7<=Datos!$B$36,B7<=Datos!$B$33,OR(Piezas!$F$7<=Datos!$B$37,AND(INT(B7/Piezas!$F$7)=1,B7-Piezas!$F$7<=Datos!$B$37))),INT(C7/Piezas!$G$7)*INT(B7/Piezas!$F$7),0) -> 24
A8: 5 kg | B8: 1000 | C8: 2000 | D8: =IF(AE8>AF8,1,IF(AF8>AE8,2,IF(INT(C8/Piezas!$F$8)<=INT(C8/Piezas!$G$8),1,2))) -> 2 | E8: =IF(D8=1,Piezas!$F$8,Piezas!$G$8) -> 475.5 | F8: =INT(C8/E8) -> 4 | G8: =IF(D8=1,Piezas!$G$8,Piezas!$F$8) -> 327.5 | H8: =INT(B8/G8) -> 3 | I8: =F8*H8 -> 12 | J8: =I8*Piezas!$F$8*Piezas!$G$8/(B8*C8) -> 0.9343575 | K8: =E8*B8*Piezas!$E$8*Datos!$B$10/1000000 -> 5.987496 | L8: =IF(G8<=Datos!$B$37,G8,B8-H8*G8) -> 327.5 | M8: =INT(Datos!$B$36/E8) -> 5 | N8: =MATCH(MIN(AA8:AD8),AA8:AD8,0) -> 1 | O8: =ROUND(INDEX(AA8:AD8,N8)*N8,0) -> 1 | P8: =IF(C8-F8*E8>0.001,F8,F8-1) -> 4 | Q8: =IF(G8<=Datos!$B$37,IF(B8-H8*G8>0.001,H8,H8-1),1) -> 3 | R8: =Q8*O8/N8 -> 3 | S8: =P8/Datos!$B$32 -> 0.2 | T8: =R8/Datos!$B$35 -> 0.15 | U8: =IF(S8>=T8,"G1","G2") -> G1 | V8: =I8*60/MAX(S8,T8) -> 3600 | W8: =B8*C8*Piezas!$E$8*Datos!$B$10/1000000 -> 25.184 | X8: =W8*INDEX(Datos!$C$95:$C$100,MATCH(Piezas!$E$8,Datos!$A$95:$A$100,0)) -> 33.43229 | Y8: =IF(I8=0,"No entra ninguna pieza",IF(B8>Datos!$B$33,"Hoja más ancha que la cuchilla de G1",IF(E8>Datos!$B$34,"Franja mayor que el tope de G1",IF(L8>Datos!$B$37,"2.º corte mayor que el tope de G2",IF(M8<1,"La franja no entra en G2","OK"))))) -> OK | AA8: =IFERROR(IF(1>Datos!$B$38,1000000000,CEILING(1*F8/M8,1)/1),1000000000) -> 1 | AB8: =IFERROR(IF(2>Datos!$B$38,1000000000,CEILING(2*F8/M8,1)/2),1000000000) -> 1 | AC8: =IFERROR(IF(3>Datos!$B$38,1000000000,CEILING(3*F8/M8,1)/3),1000000000) -> 1 | AD8: =IFERROR(IF(4>Datos!$B$38,1000000000,CEILING(4*F8/M8,1)/4),1000000000) -> 1 | AE8: =IF(AND(Piezas!$F$8<=Datos!$B$34,Piezas!$F$8<=Datos!$B$36,B8<=Datos!$B$33,OR(Piezas!$G$8<=Datos!$B$37,AND(INT(B8/Piezas!$G$8)=1,B8-Piezas!$G$8<=Datos!$B$37))),INT(C8/Piezas!$F$8)*INT(B8/Piezas!$G$8),0) -> 12 | AF8: =IF(AND(Piezas!$G$8<=Datos!$B$34,Piezas!$G$8<=Datos!$B$36,B8<=Datos!$B$33,OR(Piezas!$F$8<=Datos!$B$37,AND(INT(B8/Piezas!$F$8)=1,B8-Piezas!$F$8<=Datos!$B$37))),INT(C8/Piezas!$G$8)*INT(B8/Piezas!$F$8),0) -> 12
A9: 10 kg | B9: 1500 | C9: 3000 | D9: =IF(AE9>AF9,1,IF(AF9>AE9,2,IF(INT(C9/Piezas!$F$9)<=INT(C9/Piezas!$G$9),1,2))) -> 2 | E9: =IF(D9=1,Piezas!$F$9,Piezas!$G$9) -> 564 | F9: =INT(C9/E9) -> 5 | G9: =IF(D9=1,Piezas!$G$9,Piezas!$F$9) -> 493 | H9: =INT(B9/G9) -> 3 | I9: =F9*H9 -> 15 | J9: =I9*Piezas!$F$9*Piezas!$G$9/(B9*C9) -> 0.92684 | K9: =E9*B9*Piezas!$E$9*Datos!$B$10/1000000 -> 13.31604 | L9: =IF(G9<=Datos!$B$37,G9,B9-H9*G9) -> 493 | M9: =INT(Datos!$B$36/E9) -> 4 | N9: =MATCH(MIN(AA9:AD9),AA9:AD9,0) -> 4 | O9: =ROUND(INDEX(AA9:AD9,N9)*N9,0) -> 5 | P9: =IF(C9-F9*E9>0.001,F9,F9-1) -> 5 | Q9: =IF(G9<=Datos!$B$37,IF(B9-H9*G9>0.001,H9,H9-1),1) -> 3 | R9: =Q9*O9/N9 -> 3.75 | S9: =P9/Datos!$B$32 -> 0.25 | T9: =R9/Datos!$B$35 -> 0.1875 | U9: =IF(S9>=T9,"G1","G2") -> G1 | V9: =I9*60/MAX(S9,T9) -> 3600 | W9: =B9*C9*Piezas!$E$9*Datos!$B$10/1000000 -> 70.83 | X9: =W9*INDEX(Datos!$C$95:$C$100,MATCH(Piezas!$E$9,Datos!$A$95:$A$100,0)) -> 90.690824 | Y9: =IF(I9=0,"No entra ninguna pieza",IF(B9>Datos!$B$33,"Hoja más ancha que la cuchilla de G1",IF(E9>Datos!$B$34,"Franja mayor que el tope de G1",IF(L9>Datos!$B$37,"2.º corte mayor que el tope de G2",IF(M9<1,"La franja no entra en G2","OK"))))) -> OK | AA9: =IFERROR(IF(1>Datos!$B$38,1000000000,CEILING(1*F9/M9,1)/1),1000000000) -> 2 | AB9: =IFERROR(IF(2>Datos!$B$38,1000000000,CEILING(2*F9/M9,1)/2),1000000000) -> 1.5 | AC9: =IFERROR(IF(3>Datos!$B$38,1000000000,CEILING(3*F9/M9,1)/3),1000000000) -> 1.3333333 | AD9: =IFERROR(IF(4>Datos!$B$38,1000000000,CEILING(4*F9/M9,1)/4),1000000000) -> 1.25 | AE9: =IF(AND(Piezas!$F$9<=Datos!$B$34,Piezas!$F$9<=Datos!$B$36,B9<=Datos!$B$33,OR(Piezas!$G$9<=Datos!$B$37,AND(INT(B9/Piezas!$G$9)=1,B9-Piezas!$G$9<=Datos!$B$37))),INT(C9/Piezas!$F$9)*INT(B9/Piezas!$G$9),0) -> 12 | AF9: =IF(AND(Piezas!$G$9<=Datos!$B$34,Piezas!$G$9<=Datos!$B$36,B9<=Datos!$B$33,OR(Piezas!$F$9<=Datos!$B$37,AND(INT(B9/Piezas!$F$9)=1,B9-Piezas!$F$9<=Datos!$B$37))),INT(C9/Piezas!$G$9)*INT(B9/Piezas!$F$9),0) -> 15
A10: 25 kg | B10: 1500 | C10: 3000 | D10: =IF(AE10>AF10,1,IF(AF10>AE10,2,IF(INT(C10/Piezas!$F$10)<=INT(C10/Piezas!$G$10),1,2))) -> 2 | E10: =IF(D10=1,Piezas!$F$10,Piezas!$G$10) -> 858.5 | F10: =INT(C10/E10) -> 3 | G10: =IF(D10=1,Piezas!$G$10,Piezas!$F$10) -> 493 | H10: =INT(B10/G10) -> 3 | I10: =F10*H10 -> 9 | J10: =I10*Piezas!$F$10*Piezas!$G$10/(B10*C10) -> 0.846481 | K10: =E10*B10*Piezas!$E$10*Datos!$B$10/1000000 -> 32.430696 | L10: =IF(G10<=Datos!$B$37,G10,B10-H10*G10) -> 493 | M10: =INT(Datos!$B$36/E10) -> 2 | N10: =MATCH(MIN(AA10:AD10),AA10:AD10,0) -> 2 | O10: =ROUND(INDEX(AA10:AD10,N10)*N10,0) -> 3 | P10: =IF(C10-F10*E10>0.001,F10,F10-1) -> 3 | Q10: =IF(G10<=Datos!$B$37,IF(B10-H10*G10>0.001,H10,H10-1),1) -> 3 | R10: =Q10*O10/N10 -> 4.5 | S10: =P10/Datos!$B$32 -> 0.15 | T10: =R10/Datos!$B$35 -> 0.225 | U10: =IF(S10>=T10,"G1","G2") -> G2 | V10: =I10*60/MAX(S10,T10) -> 2400 | W10: =B10*C10*Piezas!$E$10*Datos!$B$10/1000000 -> 113.328 | X10: =W10*INDEX(Datos!$C$95:$C$100,MATCH(Piezas!$E$10,Datos!$A$95:$A$100,0)) -> 124.88012 | Y10: =IF(I10=0,"No entra ninguna pieza",IF(B10>Datos!$B$33,"Hoja más ancha que la cuchilla de G1",IF(E10>Datos!$B$34,"Franja mayor que el tope de G1",IF(L10>Datos!$B$37,"2.º corte mayor que el tope de G2",IF(M10<1,"La franja no entra en G2","OK"))))) -> OK | AA10: =IFERROR(IF(1>Datos!$B$38,1000000000,CEILING(1*F10/M10,1)/1),1000000000) -> 2 | AB10: =IFERROR(IF(2>Datos!$B$38,1000000000,CEILING(2*F10/M10,1)/2),1000000000) -> 1.5 | AC10: =IFERROR(IF(3>Datos!$B$38,1000000000,CEILING(3*F10/M10,1)/3),1000000000) -> 1.6666667 | AD10: =IFERROR(IF(4>Datos!$B$38,1000000000,CEILING(4*F10/M10,1)/4),1000000000) -> 1.5 | AE10: =IF(AND(Piezas!$F$10<=Datos!$B$34,Piezas!$F$10<=Datos!$B$36,B10<=Datos!$B$33,OR(Piezas!$G$10<=Datos!$B$37,AND(INT(B10/Piezas!$G$10)=1,B10-Piezas!$G$10<=Datos!$B$37))),INT(C10/Piezas!$F$10)*INT(B10/Piezas!$G$10),0) -> 6 | AF10: =IF(AND(Piezas!$G$10<=Datos!$B$34,Piezas!$G$10<=Datos!$B$36,B10<=Datos!$B$33,OR(Piezas!$F$10<=Datos!$B$37,AND(INT(B10/Piezas!$F$10)=1,B10-Piezas!$F$10<=Datos!$B$37))),INT(C10/Piezas!$G$10)*INT(B10/Piezas!$F$10),0) -> 9
A11: 50 kg | B11: 1500 | C11: 3000 | D11: =IF(AE11>AF11,1,IF(AF11>AE11,2,IF(INT(C11/Piezas!$F$11)<=INT(C11/Piezas!$G$11),1,2))) -> 2 | E11: =IF(D11=1,Piezas!$F$11,Piezas!$G$11) -> 995.5 | F11: =INT(C11/E11) -> 3 | G11: =IF(D11=1,Piezas!$G$11,Piezas!$F$11) -> 640 | H11: =INT(B11/G11) -> 2 | I11: =F11*H11 -> 6 | J11: =I11*Piezas!$F$11*Piezas!$G$11/(B11*C11) -> 0.84949333 | K11: =E11*B11*Piezas!$E$11*Datos!$B$10/1000000 -> 37.606008 | L11: =IF(G11<=Datos!$B$37,G11,B11-H11*G11) -> 640 | M11: =INT(Datos!$B$36/E11) -> 2 | N11: =MATCH(MIN(AA11:AD11),AA11:AD11,0) -> 2 | O11: =ROUND(INDEX(AA11:AD11,N11)*N11,0) -> 3 | P11: =IF(C11-F11*E11>0.001,F11,F11-1) -> 3 | Q11: =IF(G11<=Datos!$B$37,IF(B11-H11*G11>0.001,H11,H11-1),1) -> 2 | R11: =Q11*O11/N11 -> 3 | S11: =P11/Datos!$B$32 -> 0.15 | T11: =R11/Datos!$B$35 -> 0.15 | U11: =IF(S11>=T11,"G1","G2") -> G1 | V11: =I11*60/MAX(S11,T11) -> 2400 | W11: =B11*C11*Piezas!$E$11*Datos!$B$10/1000000 -> 113.328 | X11: =W11*INDEX(Datos!$C$95:$C$100,MATCH(Piezas!$E$11,Datos!$A$95:$A$100,0)) -> 124.88012 | Y11: =IF(I11=0,"No entra ninguna pieza",IF(B11>Datos!$B$33,"Hoja más ancha que la cuchilla de G1",IF(E11>Datos!$B$34,"Franja mayor que el tope de G1",IF(L11>Datos!$B$37,"2.º corte mayor que el tope de G2",IF(M11<1,"La franja no entra en G2","OK"))))) -> OK | AA11: =IFERROR(IF(1>Datos!$B$38,1000000000,CEILING(1*F11/M11,1)/1),1000000000) -> 2 | AB11: =IFERROR(IF(2>Datos!$B$38,1000000000,CEILING(2*F11/M11,1)/2),1000000000) -> 1.5 | AC11: =IFERROR(IF(3>Datos!$B$38,1000000000,CEILING(3*F11/M11,1)/3),1000000000) -> 1.6666667 | AD11: =IFERROR(IF(4>Datos!$B$38,1000000000,CEILING(4*F11/M11,1)/4),1000000000) -> 1.5 | AE11: =IF(AND(Piezas!$F$11<=Datos!$B$34,Piezas!$F$11<=Datos!$B$36,B11<=Datos!$B$33,OR(Piezas!$G$11<=Datos!$B$37,AND(INT(B11/Piezas!$G$11)=1,B11-Piezas!$G$11<=Datos!$B$37))),INT(C11/Piezas!$F$11)*INT(B11/Piezas!$G$11),0) -> 4 | AF11: =IF(AND(Piezas!$G$11<=Datos!$B$34,Piezas!$G$11<=Datos!$B$36,B11<=Datos!$B$33,OR(Piezas!$F$11<=Datos!$B$37,AND(INT(B11/Piezas!$F$11)=1,B11-Piezas!$F$11<=Datos!$B$37))),INT(C11/Piezas!$G$11)*INT(B11/Piezas!$F$11),0) -> 6
A12: 70 kg | B12: 1500 | C12: 3000 | D12: =IF(AE12>AF12,1,IF(AF12>AE12,2,IF(INT(C12/Piezas!$F$12)<=INT(C12/Piezas!$G$12),1,2))) -> 1 | E12: =IF(D12=1,Piezas!$F$12,Piezas!$G$12) -> 680 | F12: =INT(C12/E12) -> 4 | G12: =IF(D12=1,Piezas!$G$12,Piezas!$F$12) -> 1210.5 | H12: =INT(B12/G12) -> 1 | I12: =F12*H12 -> 4 | J12: =I12*Piezas!$F$12*Piezas!$G$12/(B12*C12) -> 0.73168 | K12: =E12*B12*Piezas!$E$12*Datos!$B$10/1000000 -> 38.13015 | L12: =IF(G12<=Datos!$B$37,G12,B12-H12*G12) -> 289.5 | M12: =INT(Datos!$B$36/E12) -> 3 | N12: =MATCH(MIN(AA12:AD12),AA12:AD12,0) -> 3 | O12: =ROUND(INDEX(AA12:AD12,N12)*N12,0) -> 4 | P12: =IF(C12-F12*E12>0.001,F12,F12-1) -> 4 | Q12: =IF(G12<=Datos!$B$37,IF(B12-H12*G12>0.001,H12,H12-1),1) -> 1 | R12: =Q12*O12/N12 -> 1.3333333 | S12: =P12/Datos!$B$32 -> 0.2 | T12: =R12/Datos!$B$35 -> 0.066666667 | U12: =IF(S12>=T12,"G1","G2") -> G1 | V12: =I12*60/MAX(S12,T12) -> 1200 | W12: =B12*C12*Piezas!$E$12*Datos!$B$10/1000000 -> 168.22125 | X12: =W12*INDEX(Datos!$C$95:$C$100,MATCH(Piezas!$E$12,Datos!$A$95:$A$100,0)) -> 183.52557 | Y12: =IF(IF(I12=0,"No entra ninguna pieza",IF(B12>Datos!$B$33,"Hoja más ancha que la cuchilla de G1",IF(E12>Datos!$B$34,"Franja mayor que el tope de G1",IF(L12>Datos!$B$37,"2.º corte mayor que el tope de G2",IF(M12<1,"La franja no entra en G2","OK")))))="OK",IF(Datos!$B$24="SI","OK; con mezcla va en la hoja mixta","OK"),IF(I12=0,"No entra ninguna pieza",IF(B12>Datos!$B$33,"Hoja más ancha que la cuchilla de G1",IF(E12>Datos!$B$34,"Franja mayor que el tope de G1",IF(L12>Datos!$B$37,"2.º corte mayor que el tope de G2",IF(M12<1,"La franja no entra en G2","OK")))))) -> OK; con mezcla va en la hoja mixta | AA12: =IFERROR(IF(1>Datos!$B$38,1000000000,CEILING(1*F12/M12,1)/1),1000000000) -> 2 | AB12: =IFERROR(IF(2>Datos!$B$38,1000000000,CEILING(2*F12/M12,1)/2),1000000000) -> 1.5 | AC12: =IFERROR(IF(3>Datos!$B$38,1000000000,CEILING(3*F12/M12,1)/3),1000000000) -> 1.3333333 | AD12: =IFERROR(IF(4>Datos!$B$38,1000000000,CEILING(4*F12/M12,1)/4),1000000000) -> 1.5 | AE12: =IF(AND(Piezas!$F$12<=Datos!$B$34,Piezas!$F$12<=Datos!$B$36,B12<=Datos!$B$33,OR(Piezas!$G$12<=Datos!$B$37,AND(INT(B12/Piezas!$G$12)=1,B12-Piezas!$G$12<=Datos!$B$37))),INT(C12/Piezas!$F$12)*INT(B12/Piezas!$G$12),0) -> 4 | AF12: =IF(AND(Piezas!$G$12<=Datos!$B$34,Piezas!$G$12<=Datos!$B$36,B12<=Datos!$B$33,OR(Piezas!$F$12<=Datos!$B$37,AND(INT(B12/Piezas!$F$12)=1,B12-Piezas!$F$12<=Datos!$B$37))),INT(C12/Piezas!$G$12)*INT(B12/Piezas!$F$12),0) -> 0
A13: 100 kg | B13: 1500 | C13: 3000 | D13: =IF(AE13>AF13,1,IF(AF13>AE13,2,IF(INT(C13/Piezas!$F$13)<=INT(C13/Piezas!$G$13),1,2))) -> 1 | E13: =IF(D13=1,Piezas!$F$13,Piezas!$G$13) -> 900 | F13: =INT(C13/E13) -> 3 | G13: =IF(D13=1,Piezas!$G$13,Piezas!$F$13) -> 1210.5 | H13: =INT(B13/G13) -> 1 | I13: =F13*H13 -> 3 | J13: =I13*Piezas!$F$13*Piezas!$G$13/(B13*C13) -> 0.7263 | K13: =E13*B13*Piezas!$E$13*Datos!$B$10/1000000 -> 50.466375 | L13: =IF(G13<=Datos!$B$37,G13,B13-H13*G13) -> 289.5 | M13: =INT(Datos!$B$36/E13) -> 2 | N13: =MATCH(MIN(AA13:AD13),AA13:AD13,0) -> 2 | O13: =ROUND(INDEX(AA13:AD13,N13)*N13,0) -> 3 | P13: =IF(C13-F13*E13>0.001,F13,F13-1) -> 3 | Q13: =IF(G13<=Datos!$B$37,IF(B13-H13*G13>0.001,H13,H13-1),1) -> 1 | R13: =Q13*O13/N13 -> 1.5 | S13: =P13/Datos!$B$32 -> 0.15 | T13: =R13/Datos!$B$35 -> 0.075 | U13: =IF(S13>=T13,"G1","G2") -> G1 | V13: =I13*60/MAX(S13,T13) -> 1200 | W13: =B13*C13*Piezas!$E$13*Datos!$B$10/1000000 -> 168.22125 | X13: =W13*INDEX(Datos!$C$95:$C$100,MATCH(Piezas!$E$13,Datos!$A$95:$A$100,0)) -> 183.52557 | Y13: =IF(I13=0,"No entra ninguna pieza",IF(B13>Datos!$B$33,"Hoja más ancha que la cuchilla de G1",IF(E13>Datos!$B$34,"Franja mayor que el tope de G1",IF(L13>Datos!$B$37,"2.º corte mayor que el tope de G2",IF(M13<1,"La franja no entra en G2","OK"))))) -> OK | AA13: =IFERROR(IF(1>Datos!$B$38,1000000000,CEILING(1*F13/M13,1)/1),1000000000) -> 2 | AB13: =IFERROR(IF(2>Datos!$B$38,1000000000,CEILING(2*F13/M13,1)/2),1000000000) -> 1.5 | AC13: =IFERROR(IF(3>Datos!$B$38,1000000000,CEILING(3*F13/M13,1)/3),1000000000) -> 1.6666667 | AD13: =IFERROR(IF(4>Datos!$B$38,1000000000,CEILING(4*F13/M13,1)/4),1000000000) -> 1.5 | AE13: =IF(AND(Piezas!$F$13<=Datos!$B$34,Piezas!$F$13<=Datos!$B$36,B13<=Datos!$B$33,OR(Piezas!$G$13<=Datos!$B$37,AND(INT(B13/Piezas!$G$13)=1,B13-Piezas!$G$13<=Datos!$B$37))),INT(C13/Piezas!$F$13)*INT(B13/Piezas!$G$13),0) -> 3 | AF13: =IF(AND(Piezas!$G$13<=Datos!$B$34,Piezas!$G$13<=Datos!$B$36,B13<=Datos!$B$33,OR(Piezas!$F$13<=Datos!$B$37,AND(INT(B13/Piezas!$F$13)=1,B13-Piezas!$F$13<=Datos!$B$37))),INT(C13/Piezas!$G$13)*INT(B13/Piezas!$F$13),0) -> 0
A14: Hoja mixta 70 + 100 kg | B14: =B13 -> 1500 | C14: =C13 -> 3000 | D14: 1 | E14: =MAX(Piezas!$F$13,Piezas!$F$12) -> 900 | F14: =Datos!$B$25+Datos!$B$26 -> 4 | G14: =MAX(Piezas!$G$13,Piezas!$G$12) -> 1210.5 | H14: =INT(B14/G14) -> 1 | I14: =F14*H14 -> 4 | J14: =(Datos!$B$25*Piezas!$F$13*Piezas!$G$13+Datos!$B$26*Piezas!$F$12*Piezas!$G$12)/(B14*C14) -> 0.79086 | K14: =E14*B14*Piezas!$E$13*Datos!$B$10/1000000 -> 50.466375 | L14: =IF(G14<=Datos!$B$37,G14,B14-H14*G14) -> 289.5 | M14: =INT(Datos!$B$36/MIN(Piezas!$F$13,Piezas!$F$12)) -> 3 | N14: =MATCH(MIN(AA14:AD14),AA14:AD14,0) -> 3 | O14: =ROUND(INDEX(AA14:AD14,N14)*N14,0) -> 4 | P14: =IF(C14-(Datos!$B$25*Piezas!$F$13+Datos!$B$26*Piezas!$F$12)>0.001,F14,F14-1) -> 4 | Q14: =IF(G14<=Datos!$B$37,IF(B14-H14*G14>0.001,H14,H14-1),1) -> 1 | R14: =Q14*O14/N14 -> 1.3333333 | S14: =P14/Datos!$B$32 -> 0.2 | T14: =R14/Datos!$B$35 -> 0.066666667 | U14: =IF(S14>=T14,"G1","G2") -> G1 | V14: =I14*60/MAX(S14,T14) -> 1200 | W14: =B14*C14*Piezas!$E$13*Datos!$B$10/1000000 -> 168.22125 | X14: =W14*INDEX(Datos!$C$95:$C$100,MATCH(Piezas!$E$13,Datos!$A$95:$A$100,0)) -> 183.52557 | Y14: =IF(AND(Piezas!$G$12<=B14,Piezas!$G$13<=B14,(Datos!$B$25*Piezas!$F$13+Datos!$B$26*Piezas!$F$12)<=C14,E14<=Datos!$B$34,L14<=Datos!$B$37),"OK: "&Datos!$B$25&" de 100 kg y "&Datos!$B$26&" de 70 kg","No entra") -> OK: 1 de 100 kg y 3 de 70 kg | AA14: =IFERROR(IF(1>Datos!$B$38,1000000000,MAX(CEILING(1*F14/M14,1),CEILING(1*(Datos!$B$25*Piezas!$F$13+Datos!$B$26*Piezas!$F$12)/Datos!$B$36,1))/1),1000000000) -> 2 | AB14: =IFERROR(IF(2>Datos!$B$38,1000000000,MAX(CEILING(2*F14/M14,1),CEILING(2*(Datos!$B$25*Piezas!$F$13+Datos!$B$26*Piezas!$F$12)/Datos!$B$36,1))/2),1000000000) -> 1.5 | AC14: =IFERROR(IF(3>Datos!$B$38,1000000000,MAX(CEILING(3*F14/M14,1),CEILING(3*(Datos!$B$25*Piezas!$F$13+Datos!$B$26*Piezas!$F$12)/Datos!$B$36,1))/3),1000000000) -> 1.3333333 | AD14: =IFERROR(IF(4>Datos!$B$38,1000000000,MAX(CEILING(4*F14/M14,1),CEILING(4*(Datos!$B$25*Piezas!$F$13+Datos!$B$26*Piezas!$F$12)/Datos!$B$36,1))/4),1000000000) -> 1.5
A15: 1.er corte por el lado corto (franjas de hasta 1.500 mm de largo). G1 hace solo el 1.er corte y G2 solo el 2.º: la pieza, o la orilla si la pieza supera el tope. Franjas en paralelo: hojas enteras, con el ciclo que da menos tandas por hoja (Datos, «Hojas por ciclo»).
A17: Para los Aprovechamientos de Manuales (1 a 10 kg) y Carros (25 a 100 kg): IMPORTRANGE
A18: Formato | B18: Piezas por hoja | C18: Golpes G1 por hoja | D18: Golpes G2 por hoja | E18: Tandas de G2 por hoja | F18: Golpes por minuto G1 | G18: Golpes por minuto G2
A19: =A6 -> 1 kg | B19: =I6 -> 45 | C19: =P6 -> 9 | D19: =R6 -> 5 | E19: =O6/N6 -> 1 | F19: =Datos!$B$32 -> 20 | G19: =Datos!$B$35 -> 20
A20: =A7 -> 2,5 kg | B20: =I7 -> 27 | C20: =P7 -> 9 | D20: =R7 -> 3 | E20: =O7/N7 -> 1 | F20: =Datos!$B$32 -> 20 | G20: =Datos!$B$35 -> 20
A21: =A8 -> 5 kg | B21: =I8 -> 12 | C21: =P8 -> 4 | D21: =R8 -> 3 | E21: =O8/N8 -> 1 | F21: =Datos!$B$32 -> 20 | G21: =Datos!$B$35 -> 20
A22: =A9 -> 10 kg | B22: =I9 -> 15 | C22: =P9 -> 5 | D22: =R9 -> 3.75 | E22: =O9/N9 -> 1.25 | F22: =Datos!$B$32 -> 20 | G22: =Datos!$B$35 -> 20
A23: =A10 -> 25 kg | B23: =IF(Datos!$B$27="SI",Nesting!$B$52,I10) -> 7.1119843 | C23: =IF(Datos!$B$27="SI",Nesting!$B$53,P10) -> 3 | D23: =IF(Datos!$B$27="SI",Nesting!$B$54,R10) -> 4.1119843 | E23: =IF(Datos!$B$27="SI",Nesting!$B$55,O10/N10) -> 2.0559921 | F23: =Datos!$B$32 -> 20 | G23: =Datos!$B$35 -> 20
A24: =A11 -> 50 kg | B24: =IF(Datos!$B$27="SI",Nesting!$B$52,I11) -> 7.1119843 | C24: =IF(Datos!$B$27="SI",Nesting!$B$53,P11) -> 3 | D24: =IF(Datos!$B$27="SI",Nesting!$B$54,R11) -> 4.1119843 | E24: =IF(Datos!$B$27="SI",Nesting!$B$55,O11/N11) -> 2.0559921 | F24: =Datos!$B$32 -> 20 | G24: =Datos!$B$35 -> 20
A25: =A12 -> 70 kg | B25: =I12 -> 4 | C25: =P12 -> 4 | D25: =R12 -> 1.3333333 | E25: =O12/N12 -> 1.3333333 | F25: =Datos!$B$32 -> 20 | G25: =Datos!$B$35 -> 20
A26: =A13 -> 100 kg | B26: =I13 -> 3 | C26: =P13 -> 3 | D26: =R13 -> 1.5 | E26: =O13/N13 -> 1.5 | F26: =Datos!$B$32 -> 20 | G26: =Datos!$B$35 -> 20
A27: =A14 -> Hoja mixta 70 + 100 kg | B27: =I14 -> 4 | C27: =P14 -> 4 | D27: =R14 -> 1.3333333 | E27: =O14/N14 -> 1.3333333 | F27: =Datos!$B$32 -> 20 | G27: =Datos!$B$35 -> 20
A30: B) Cuerpos en bobina de ancho estándar con línea de corte transversal (A) y a medida (Ref.)
A31: Formato | B31: Ancho de bobina (mm) | C31: Piezas por golpe | D31: Avance por golpe (mm) | E31: Aprovech. | F31: kg comprados por cuerpo | G31: USD por cuerpo | H31: Peso de bobina (t) | I31: USD por cuerpo a medida (Ref.)
A32: 1 kg | B32: 1220 | C32: =IF(INT((B32-Datos!$B$19)/Piezas!$F$6)*Piezas!$F$6/B32>=INT((B32-Datos!$B$19)/Piezas!$G$6)*Piezas!$G$6/B32,INT((B32-Datos!$B$19)/Piezas!$F$6),INT((B32-Datos!$B$19)/Piezas!$G$6)) -> 5 | D32: =IF(INT((B32-Datos!$B$19)/Piezas!$F$6)*Piezas!$F$6/B32>=INT((B32-Datos!$B$19)/Piezas!$G$6)*Piezas!$G$6/B32,Piezas!$G$6,Piezas!$F$6) -> 263.5 | E32: =MAX(INT((B32-Datos!$B$19)/Piezas!$F$6)*Piezas!$F$6/B32,INT((B32-Datos!$B$19)/Piezas!$G$6)*Piezas!$G$6/B32)*(1-Datos!$B$20) -> 0.96441598 | F32: =Piezas!$H$6/E32 -> 0.45768282 | G32: =F32*INDEX(Datos!$B$95:$B$100,MATCH(Piezas!$E$6,Datos!$A$95:$A$100,0)) -> 0.57798474 | H32: =MIN(ROUNDDOWN(MIN(B32*Datos!$B$57,Datos!$B$58)*2,0)/2,MAX(Datos!$B$54,ROUNDUP(INDEX(Demanda!$C$6:$L$6,Datos!$B$6-2025)*F32/1000/12*Datos!$B$52*2,0)/2)) -> 8 | I32: =Piezas!$H$6*INDEX(Datos!$F$95:$F$100,MATCH(Piezas!$E$6,Datos!$A$95:$A$100,0)) -> 0.59857796
A33: 2,5 kg | B33: 1220 | C33: =IF(INT((B33-Datos!$B$19)/Piezas!$F$7)*Piezas!$F$7/B33>=INT((B33-Datos!$B$19)/Piezas!$G$7)*Piezas!$G$7/B33,INT((B33-Datos!$B$19)/Piezas!$F$7),INT((B33-Datos!$B$19)/Piezas!$G$7)) -> 3 | D33: =IF(INT((B33-Datos!$B$19)/Piezas!$F$7)*Piezas!$F$7/B33>=INT((B33-Datos!$B$19)/Piezas!$G$7)*Piezas!$G$7/B33,Piezas!$G$7,Piezas!$F$7) -> 267.5 | E33: =MAX(INT((B33-Datos!$B$19)/Piezas!$F$7)*Piezas!$F$7/B33,INT((B33-Datos!$B$19)/Piezas!$G$7)*Piezas!$G$7/B33)*(1-Datos!$B$20) -> 0.94321107 | F33: =Piezas!$H$7/E33 -> 1.0755337 | G33: =F33*INDEX(Datos!$B$95:$B$100,MATCH(Piezas!$E$7,Datos!$A$95:$A$100,0)) -> 1.3450194 | H33: =MIN(ROUNDDOWN(MIN(B33*Datos!$B$57,Datos!$B$58)*2,0)/2,MAX(Datos!$B$54,ROUNDUP(INDEX(Demanda!$C$7:$L$7,Datos!$B$6-2025)*F33/1000/12*Datos!$B$52*2,0)/2)) -> 1.5 | I33: =Piezas!$H$7*INDEX(Datos!$F$95:$F$100,MATCH(Piezas!$E$7,Datos!$A$95:$A$100,0)) -> 1.4466133
A34: 5 kg | B34: 1000 | C34: =IF(INT((B34-Datos!$B$19)/Piezas!$F$8)*Piezas!$F$8/B34>=INT((B34-Datos!$B$19)/Piezas!$G$8)*Piezas!$G$8/B34,INT((B34-Datos!$B$19)/Piezas!$F$8),INT((B34-Datos!$B$19)/Piezas!$G$8)) -> 3 | D34: =IF(INT((B34-Datos!$B$19)/Piezas!$F$8)*Piezas!$F$8/B34>=INT((B34-Datos!$B$19)/Piezas!$G$8)*Piezas!$G$8/B34,Piezas!$G$8,Piezas!$F$8) -> 475.5 | E34: =MAX(INT((B34-Datos!$B$19)/Piezas!$F$8)*Piezas!$F$8/B34,INT((B34-Datos!$B$19)/Piezas!$G$8)*Piezas!$G$8/B34)*(1-Datos!$B$20) -> 0.9775875 | F34: =Piezas!$H$8/E34 -> 2.0058613 | G34: =F34*INDEX(Datos!$B$95:$B$100,MATCH(Piezas!$E$8,Datos!$A$95:$A$100,0)) -> 2.5084499 | H34: =MIN(ROUNDDOWN(MIN(B34*Datos!$B$57,Datos!$B$58)*2,0)/2,MAX(Datos!$B$54,ROUNDUP(INDEX(Demanda!$C$8:$L$8,Datos!$B$6-2025)*F34/1000/12*Datos!$B$52*2,0)/2)) -> 10 | I34: =Piezas!$H$8*INDEX(Datos!$F$95:$F$100,MATCH(Piezas!$E$8,Datos!$A$95:$A$100,0)) -> 2.8491949
A35: 10 kg | B35: 1000 | C35: =IF(INT((B35-Datos!$B$19)/Piezas!$F$9)*Piezas!$F$9/B35>=INT((B35-Datos!$B$19)/Piezas!$G$9)*Piezas!$G$9/B35,INT((B35-Datos!$B$19)/Piezas!$F$9),INT((B35-Datos!$B$19)/Piezas!$G$9)) -> 2 | D35: =IF(INT((B35-Datos!$B$19)/Piezas!$F$9)*Piezas!$F$9/B35>=INT((B35-Datos!$B$19)/Piezas!$G$9)*Piezas!$G$9/B35,Piezas!$G$9,Piezas!$F$9) -> 564 | E35: =MAX(INT((B35-Datos!$B$19)/Piezas!$F$9)*Piezas!$F$9/B35,INT((B35-Datos!$B$19)/Piezas!$G$9)*Piezas!$G$9/B35)*(1-Datos!$B$20) -> 0.98107 | F35: =Piezas!$H$9/E35 -> 4.4609849 | G35: =F35*INDEX(Datos!$B$95:$B$100,MATCH(Piezas!$E$9,Datos!$A$95:$A$100,0)) -> 5.6335548 | H35: =MIN(ROUNDDOWN(MIN(B35*Datos!$B$57,Datos!$B$58)*2,0)/2,MAX(Datos!$B$54,ROUNDUP(INDEX(Demanda!$C$9:$L$9,Datos!$B$6-2025)*F35/1000/12*Datos!$B$52*2,0)/2)) -> 1.5 | I35: =Piezas!$H$9*INDEX(Datos!$F$95:$F$100,MATCH(Piezas!$E$9,Datos!$A$95:$A$100,0)) -> 6.2540735
A36: 25 kg | B36: 1500 | C36: =IF(INT((B36-Datos!$B$19)/Piezas!$F$10)*Piezas!$F$10/B36>=INT((B36-Datos!$B$19)/Piezas!$G$10)*Piezas!$G$10/B36,INT((B36-Datos!$B$19)/Piezas!$F$10),INT((B36-Datos!$B$19)/Piezas!$G$10)) -> 3 | D36: =IF(INT((B36-Datos!$B$19)/Piezas!$F$10)*Piezas!$F$10/B36>=INT((B36-Datos!$B$19)/Piezas!$G$10)*Piezas!$G$10/B36,Piezas!$G$10,Piezas!$F$10) -> 858.5 | E36: =MAX(INT((B36-Datos!$B$19)/Piezas!$F$10)*Piezas!$F$10/B36,INT((B36-Datos!$B$19)/Piezas!$G$10)*Piezas!$G$10/B36)*(1-Datos!$B$20) -> 0.98107 | F36: =Piezas!$H$10/E36 -> 10.864555 | G36: =F36*INDEX(Datos!$B$95:$B$100,MATCH(Piezas!$E$10,Datos!$A$95:$A$100,0)) -> 12.100181 | H36: =MIN(ROUNDDOWN(MIN(B36*Datos!$B$57,Datos!$B$58)*2,0)/2,MAX(Datos!$B$54,ROUNDUP(INDEX(Demanda!$C$10:$L$10,Datos!$B$6-2025)*F36/1000/12*Datos!$B$52*2,0)/2)) -> 1 | I36: =Piezas!$H$10*INDEX(Datos!$F$95:$F$100,MATCH(Piezas!$E$10,Datos!$A$95:$A$100,0)) -> 13.387564
A37: 50 kg | B37: 1500 | C37: =IF(INT((B37-Datos!$B$19)/Piezas!$F$11)*Piezas!$F$11/B37>=INT((B37-Datos!$B$19)/Piezas!$G$11)*Piezas!$G$11/B37,INT((B37-Datos!$B$19)/Piezas!$F$11),INT((B37-Datos!$B$19)/Piezas!$G$11)) -> 2 | D37: =IF(INT((B37-Datos!$B$19)/Piezas!$F$11)*Piezas!$F$11/B37>=INT((B37-Datos!$B$19)/Piezas!$G$11)*Piezas!$G$11/B37,Piezas!$G$11,Piezas!$F$11) -> 995.5 | E37: =MAX(INT((B37-Datos!$B$19)/Piezas!$F$11)*Piezas!$F$11/B37,INT((B37-Datos!$B$19)/Piezas!$G$11)*Piezas!$G$11/B37)*(1-Datos!$B$20) -> 0.84906667 | F37: =Piezas!$H$11/E37 -> 18.897491 | G37: =F37*INDEX(Datos!$B$95:$B$100,MATCH(Piezas!$E$11,Datos!$A$95:$A$100,0)) -> 21.046703 | H37: =MIN(ROUNDDOWN(MIN(B37*Datos!$B$57,Datos!$B$58)*2,0)/2,MAX(Datos!$B$54,ROUNDUP(INDEX(Demanda!$C$11:$L$11,Datos!$B$6-2025)*F37/1000/12*Datos!$B$52*2,0)/2)) -> 3 | I37: =Piezas!$H$11*INDEX(Datos!$F$95:$F$100,MATCH(Piezas!$E$11,Datos!$A$95:$A$100,0)) -> 20.152809
A38: 70 kg | B38: 1245 | C38: =IF(INT((B38-Datos!$B$19)/Piezas!$F$12)*Piezas!$F$12/B38>=INT((B38-Datos!$B$19)/Piezas!$G$12)*Piezas!$G$12/B38,INT((B38-Datos!$B$19)/Piezas!$F$12),INT((B38-Datos!$B$19)/Piezas!$G$12)) -> 1 | D38: =IF(INT((B38-Datos!$B$19)/Piezas!$F$12)*Piezas!$F$12/B38>=INT((B38-Datos!$B$19)/Piezas!$G$12)*Piezas!$G$12/B38,Piezas!$G$12,Piezas!$F$12) -> 680 | E38: =MAX(INT((B38-Datos!$B$19)/Piezas!$F$12)*Piezas!$F$12/B38,INT((B38-Datos!$B$19)/Piezas!$G$12)*Piezas!$G$12/B38)*(1-Datos!$B$20) -> 0.96742771 | F38: =Piezas!$H$12/E38 -> 31.80706 | G38: =F38*INDEX(Datos!$B$95:$B$100,MATCH(Piezas!$E$12,Datos!$A$95:$A$100,0)) -> 35.424477 | H38: =MIN(ROUNDDOWN(MIN(B38*Datos!$B$57,Datos!$B$58)*2,0)/2,MAX(Datos!$B$54,ROUNDUP(INDEX(Demanda!$C$12:$L$12,Datos!$B$6-2025)*F38/1000/12*Datos!$B$52*2,0)/2)) -> 1 | I38: =Piezas!$H$12*INDEX(Datos!$F$95:$F$100,MATCH(Piezas!$E$12,Datos!$A$95:$A$100,0)) -> 38.032994
A39: 100 kg | B39: 1245 | C39: =IF(INT((B39-Datos!$B$19)/Piezas!$F$13)*Piezas!$F$13/B39>=INT((B39-Datos!$B$19)/Piezas!$G$13)*Piezas!$G$13/B39,INT((B39-Datos!$B$19)/Piezas!$F$13),INT((B39-Datos!$B$19)/Piezas!$G$13)) -> 1 | D39: =IF(INT((B39-Datos!$B$19)/Piezas!$F$13)*Piezas!$F$13/B39>=INT((B39-Datos!$B$19)/Piezas!$G$13)*Piezas!$G$13/B39,Piezas!$G$13,Piezas!$F$13) -> 900 | E39: =MAX(INT((B39-Datos!$B$19)/Piezas!$F$13)*Piezas!$F$13/B39,INT((B39-Datos!$B$19)/Piezas!$G$13)*Piezas!$G$13/B39)*(1-Datos!$B$20) -> 0.96742771 | F39: =Piezas!$H$13/E39 -> 42.097579 | G39: =F39*INDEX(Datos!$B$95:$B$100,MATCH(Piezas!$E$13,Datos!$A$95:$A$100,0)) -> 46.885337 | H39: =MIN(ROUNDDOWN(MIN(B39*Datos!$B$57,Datos!$B$58)*2,0)/2,MAX(Datos!$B$54,ROUNDUP(INDEX(Demanda!$C$13:$L$13,Datos!$B$6-2025)*F39/1000/12*Datos!$B$52*2,0)/2)) -> 1 | I39: =Piezas!$H$13*INDEX(Datos!$F$95:$F$100,MATCH(Piezas!$E$13,Datos!$A$95:$A$100,0)) -> 50.337787
A42: C) Cúpulas y fondos: fleje a medida (A, D, Ref.) o tiras de hoja (B)
A43: Pieza | B43: Ø disco (mm) | C43: Espesor (mm) | D43: Puente de avance (mm) | E43: Puente al borde (mm) | F43: Ancho de fleje (mm) | G43: Paso (mm) | H43: Aprovech. del fleje | I43: kg de fleje por disco | J43: USD de fleje por disco | K43: Peso de rollo (t) | L43: Hoja: lado corto = largo de la tira | M43: lado largo | N43: Tiras por hoja | O43: Discos por tira | P43: Discos por hoja | Q43: Aprovech. de la hoja | R43: kg de hoja por disco | S43: USD de hoja por disco | T43: Fleje 1 fila: ancho (mm) | U43: Aprovech. 1 fila | V43: Fleje 2 filas al tresbolillo: ancho (mm) | W43: Aprovech. 2 filas | X43: kg por disco, 1 fila | Y43: kg por disco, 2 filas
A44: Cúpula 1 kg | B44: =Piezas!$L$18 -> 89 | C44: =Piezas!$D$18 -> 0.9 | D44: =MAX(Datos!$B$21*C44,Datos!$B$22) -> 1.35 | E44: =Datos!$B$23*D44 -> 2.025 | F44: =IF(Datos!$B$28="SI",V44,T44) -> 93.05 | G44: =B44+D44 -> 90.35 | H44: =IF(Datos!$B$28="SI",W44,U44) -> 0.73628922 | I44: =Piezas!$S$18/H44 -> 0.059846492 | J44: =I44*INDEX(Datos!$D$95:$D$100,MATCH(C44,Datos!$A$95:$A$100,0)) -> 0.075577142 | K44: =MIN(ROUNDDOWN(MIN(F44*Datos!$B$57,Datos!$B$59)*2,0)/2,MAX(Datos!$B$54,ROUNDUP(INDEX(Demanda!$C$6:$L$6,Datos!$B$6-2025)*I44/1000/12*Datos!$B$52*2,0)/2)) -> 1 | L44: 1220 | M44: 2440 | N44: =INT(M44/T44) -> 26 | O44: =INT((L44-D44)/G44) -> 13 | P44: =N44*O44 -> 338 | Q44: =P44*PI()*B44^2/4/(L44*M44) -> 0.70637763 | R44: =L44*M44*C44*Datos!$B$10/1000000/P44 -> 0.062380693 | S44: =R44*INDEX(Datos!$C$95:$C$100,MATCH(C44,Datos!$A$95:$A$100,0)) -> 0.084594458 | T44: =B44+2*E44 -> 93.05 | U44: =PI()*B44^2/4/(T44*G44)*(1-Datos!$B$20) -> 0.73628922 | V44: =B44+G44*SQRT(3)/2+2*E44 -> 171.2954 | W44: =2*PI()*B44^2/4/(V44*G44)*(1-Datos!$B$20) -> 0.79992473 | X44: =Piezas!$S$18/U44 -> 0.059846492 | Y44: =Piezas!$S$18/W44 -> 0.055085591
A45: Fondo 1 kg | B45: =Piezas!$L$19 -> 95 | C45: =Piezas!$D$19 -> 1.25 | D45: =MAX(Datos!$B$21*C45,Datos!$B$22) -> 1.875 | E45: =Datos!$B$23*D45 -> 2.8125 | F45: =IF(Datos!$B$28="SI",V45,T45) -> 100.625 | G45: =B45+D45 -> 96.875 | H45: =IF(Datos!$B$28="SI",W45,U45) -> 0.72350671 | I45: =Piezas!$S$19/H45 -> 0.096378303 | J45: =I45*INDEX(Datos!$D$95:$D$100,MATCH(C45,Datos!$A$95:$A$100,0)) -> 0.11430467 | K45: =MIN(ROUNDDOWN(MIN(F45*Datos!$B$57,Datos!$B$59)*2,0)/2,MAX(Datos!$B$54,ROUNDUP(INDEX(Demanda!$C$6:$L$6,Datos!$B$6-2025)*I45/1000/12*Datos!$B$52*2,0)/2)) -> 1 | L45: 1220 | M45: 2440 | N45: =INT(M45/T45) -> 24 | O45: =INT((L45-D45)/G45) -> 12 | P45: =N45*O45 -> 288 | Q45: =P45*PI()*B45^2/4/(L45*M45) -> 0.68577227 | R45: =L45*M45*C45*Datos!$B$10/1000000/P45 -> 0.10168149 | S45: =R45*INDEX(Datos!$C$95:$C$100,MATCH(C45,Datos!$A$95:$A$100,0)) -> 0.1311994 | T45: =B45+2*E45 -> 100.625 | U45: =PI()*B45^2/4/(T45*G45)*(1-Datos!$B$20) -> 0.72350671 | V45: =B45+G45*SQRT(3)/2+2*E45 -> 184.52121 | W45: =2*PI()*B45^2/4/(V45*G45)*(1-Datos!$B$20) -> 0.78910021 | X45: =Piezas!$S$19/U45 -> 0.096378303 | Y45: =Piezas!$S$19/W45 -> 0.088366912
A46: Cúpula 2,5 kg | B46: =Piezas!$L$20 -> 156.5 | C46: =Piezas!$D$20 -> 1.25 | D46: =MAX(Datos!$B$21*C46,Datos!$B$22) -> 1.875 | E46: =Datos!$B$23*D46 -> 2.8125 | F46: =IF(Datos!$B$28="SI",V46,T46) -> 162.125 | G46: =B46+D46 -> 158.375 | H46: =IF(Datos!$B$28="SI",W46,U46) -> 0.74542684 | I46: =Piezas!$S$20/H46 -> 0.25386234 | J46: =I46*INDEX(Datos!$D$95:$D$100,MATCH(C46,Datos!$A$95:$A$100,0)) -> 0.30108074 | K46: =MIN(ROUNDDOWN(MIN(F46*Datos!$B$57,Datos!$B$59)*2,0)/2,MAX(Datos!$B$54,ROUNDUP(INDEX(Demanda!$C$7:$L$7,Datos!$B$6-2025)*I46/1000/12*Datos!$B$52*2,0)/2)) -> 0.5 | L46: 1220 | M46: 2440 | N46: =INT(M46/T46) -> 15 | O46: =INT((L46-D46)/G46) -> 7 | P46: =N46*O46 -> 105 | Q46: =P46*PI()*B46^2/4/(L46*M46) -> 0.67851305 | R46: =L46*M46*C46*Datos!$B$10/1000000/P46 -> 0.27889781 | S46: =R46*INDEX(Datos!$C$95:$C$100,MATCH(C46,Datos!$A$95:$A$100,0)) -> 0.35986121 | T46: =B46+2*E46 -> 162.125 | U46: =PI()*B46^2/4/(T46*G46)*(1-Datos!$B$20) -> 0.74542684 | V46: =B46+G46*SQRT(3)/2+2*E46 -> 299.28177 | W46: =2*PI()*B46^2/4/(V46*G46)*(1-Datos!$B$20) -> 0.80761569 | X46: =Piezas!$S$20/U46 -> 0.25386234 | Y46: =Piezas!$S$20/W46 -> 0.23431418
A47: Fondo 2,5 kg | B47: =Piezas!$L$21 -> 140.5 | C47: =Piezas!$D$21 -> 1.25 | D47: =MAX(Datos!$B$21*C47,Datos!$B$22) -> 1.875 | E47: =Datos!$B$23*D47 -> 2.8125 | F47: =IF(Datos!$B$28="SI",V47,T47) -> 146.125 | G47: =B47+D47 -> 142.375 | H47: =IF(Datos!$B$28="SI",W47,U47) -> 0.7414935 | I47: =Piezas!$S$21/H47 -> 0.2056932 | J47: =I47*INDEX(Datos!$D$95:$D$100,MATCH(C47,Datos!$A$95:$A$100,0)) -> 0.24395213 | K47: =MIN(ROUNDDOWN(MIN(F47*Datos!$B$57,Datos!$B$59)*2,0)/2,MAX(Datos!$B$54,ROUNDUP(INDEX(Demanda!$C$7:$L$7,Datos!$B$6-2025)*I47/1000/12*Datos!$B$52*2,0)/2)) -> 0.5 | L47: 1220 | M47: 2440 | N47: =INT(M47/T47) -> 16 | O47: =INT((L47-D47)/G47) -> 8 | P47: =N47*O47 -> 128 | Q47: =P47*PI()*B47^2/4/(L47*M47) -> 0.66665761 | R47: =L47*M47*C47*Datos!$B$10/1000000/P47 -> 0.22878336 | S47: =R47*INDEX(Datos!$C$95:$C$100,MATCH(C47,Datos!$A$95:$A$100,0)) -> 0.29519865 | T47: =B47+2*E47 -> 146.125 | U47: =PI()*B47^2/4/(T47*G47)*(1-Datos!$B$20) -> 0.7414935 | V47: =B47+G47*SQRT(3)/2+2*E47 -> 269.42537 | W47: =2*PI()*B47^2/4/(V47*G47)*(1-Datos!$B$20) -> 0.80430985 | X47: =Piezas!$S$21/U47 -> 0.2056932 | Y47: =Piezas!$S$21/W47 -> 0.18962862
A48: Cúpula 5 kg | B48: =Piezas!$L$22 -> 197 | C48: =Piezas!$D$22 -> 1.6 | D48: =MAX(Datos!$B$21*C48,Datos!$B$22) -> 2.4 | E48: =Datos!$B$23*D48 -> 3.6 | F48: =IF(Datos!$B$28="SI",V48,T48) -> 204.2 | G48: =B48+D48 -> 199.4 | H48: =IF(Datos!$B$28="SI",W48,U48) -> 0.74484263 | I48: =Piezas!$S$22/H48 -> 0.51529096 | J48: =I48*INDEX(Datos!$D$95:$D$100,MATCH(C48,Datos!$A$95:$A$100,0)) -> 0.61113508 | K48: =MIN(ROUNDDOWN(MIN(F48*Datos!$B$57,Datos!$B$59)*2,0)/2,MAX(Datos!$B$54,ROUNDUP(INDEX(Demanda!$C$8:$L$8,Datos!$B$6-2025)*I48/1000/12*Datos!$B$52*2,0)/2)) -> 2.5 | L48: 1220 | M48: 2440 | N48: =INT(M48/T48) -> 11 | O48: =INT((L48-D48)/G48) -> 6 | P48: =N48*O48 -> 66 | Q48: =P48*PI()*B48^2/4/(L48*M48) -> 0.67579755 | R48: =L48*M48*C48*Datos!$B$10/1000000/P48 -> 0.56793736 | S48: =R48*INDEX(Datos!$C$95:$C$100,MATCH(C48,Datos!$A$95:$A$100,0)) -> 0.75394879 | T48: =B48+2*E48 -> 204.2 | U48: =PI()*B48^2/4/(T48*G48)*(1-Datos!$B$20) -> 0.74484263 | V48: =B48+G48*SQRT(3)/2+2*E48 -> 376.88547 | W48: =2*PI()*B48^2/4/(V48*G48)*(1-Datos!$B$20) -> 0.80712513 | X48: =Piezas!$S$22/U48 -> 0.51529096 | Y48: =Piezas!$S$22/W48 -> 0.4755281
A49: Fondo 5 kg | B49: =Piezas!$L$23 -> 170 | C49: =Piezas!$D$23 -> 1.6 | D49: =MAX(Datos!$B$21*C49,Datos!$B$22) -> 2.4 | E49: =Datos!$B$23*D49 -> 3.6 | F49: =IF(Datos!$B$28="SI",V49,T49) -> 177.2 | G49: =B49+D49 -> 172.4 | H49: =IF(Datos!$B$28="SI",W49,U49) -> 0.73928148 | I49: =Piezas!$S$23/H49 -> 0.38660958 | J49: =I49*INDEX(Datos!$D$95:$D$100,MATCH(C49,Datos!$A$95:$A$100,0)) -> 0.45851896 | K49: =MIN(ROUNDDOWN(MIN(F49*Datos!$B$57,Datos!$B$59)*2,0)/2,MAX(Datos!$B$54,ROUNDUP(INDEX(Demanda!$C$8:$L$8,Datos!$B$6-2025)*I49/1000/12*Datos!$B$52*2,0)/2)) -> 2 | L49: 1000 | M49: 2000 | N49: =INT(M49/T49) -> 11 | O49: =INT((L49-D49)/G49) -> 5 | P49: =N49*O49 -> 55 | Q49: =P49*PI()*B49^2/4/(L49*M49) -> 0.62419519 | R49: =L49*M49*C49*Datos!$B$10/1000000/P49 -> 0.45789091 | S49: =R49*INDEX(Datos!$C$95:$C$100,MATCH(C49,Datos!$A$95:$A$100,0)) -> 0.60785981 | T49: =B49+2*E49 -> 177.2 | U49: =PI()*B49^2/4/(T49*G49)*(1-Datos!$B$20) -> 0.73928148 | V49: =B49+G49*SQRT(3)/2+2*E49 -> 326.50278 | W49: =2*PI()*B49^2/4/(V49*G49)*(1-Datos!$B$20) -> 0.80244755 | X49: =Piezas!$S$23/U49 -> 0.38660958 | Y49: =Piezas!$S$23/W49 -> 0.35617693
A50: Cúpula 10 kg | B50: =Piezas!$L$24 -> 231.5 | C50: =Piezas!$D$24 -> 1.6 | D50: =MAX(Datos!$B$21*C50,Datos!$B$22) -> 2.4 | E50: =Datos!$B$23*D50 -> 3.6 | F50: =IF(Datos!$B$28="SI",V50,T50) -> 238.7 | G50: =B50+D50 -> 233.9 | H50: =IF(Datos!$B$28="SI",W50,U50) -> 0.75012271 | I50: =Piezas!$S$24/H50 -> 0.70656851 | J50: =I50*INDEX(Datos!$D$95:$D$100,MATCH(C50,Datos!$A$95:$A$100,0)) -> 0.83799025 | K50: =MIN(ROUNDDOWN(MIN(F50*Datos!$B$57,Datos!$B$59)*2,0)/2,MAX(Datos!$B$54,ROUNDUP(INDEX(Demanda!$C$9:$L$9,Datos!$B$6-2025)*I50/1000/12*Datos!$B$52*2,0)/2)) -> 0.5 | L50: 1000 | M50: 2000 | N50: =INT(M50/T50) -> 8 | O50: =INT((L50-D50)/G50) -> 4 | P50: =N50*O50 -> 32 | Q50: =P50*PI()*B50^2/4/(L50*M50) -> 0.67346008 | R50: =L50*M50*C50*Datos!$B$10/1000000/P50 -> 0.787 | S50: =R50*INDEX(Datos!$C$95:$C$100,MATCH(C50,Datos!$A$95:$A$100,0)) -> 1.0447591 | T50: =B50+2*E50 -> 238.7 | U50: =PI()*B50^2/4/(T50*G50)*(1-Datos!$B$20) -> 0.75012271 | V50: =B50+G50*SQRT(3)/2+2*E50 -> 441.26334 | W50: =2*PI()*B50^2/4/(V50*G50)*(1-Datos!$B$20) -> 0.81155298 | X50: =Piezas!$S$24/U50 -> 0.70656851 | Y50: =Piezas!$S$24/W50 -> 0.653085
A51: Fondo 10 kg | B51: =Piezas!$L$25 -> 196 | C51: =Piezas!$D$25 -> 2 | D51: =MAX(Datos!$B$21*C51,Datos!$B$22) -> 3 | E51: =Datos!$B$23*D51 -> 4.5 | F51: =IF(Datos!$B$28="SI",V51,T51) -> 205 | G51: =B51+D51 -> 199 | H51: =IF(Datos!$B$28="SI",W51,U51) -> 0.73589892 | I51: =Piezas!$S$25/H51 -> 0.64534 | J51: =I51*INDEX(Datos!$D$95:$D$100,MATCH(C51,Datos!$A$95:$A$100,0)) -> 0.77311732 | K51: =MIN(ROUNDDOWN(MIN(F51*Datos!$B$57,Datos!$B$59)*2,0)/2,MAX(Datos!$B$54,ROUNDUP(INDEX(Demanda!$C$9:$L$9,Datos!$B$6-2025)*I51/1000/12*Datos!$B$52*2,0)/2)) -> 0.5 | L51: 1500 | M51: 3000 | N51: =INT(M51/T51) -> 14 | O51: =INT((L51-D51)/G51) -> 7 | P51: =N51*O51 -> 98 | Q51: =P51*PI()*B51^2/4/(L51*M51) -> 0.65707597 | R51: =L51*M51*C51*Datos!$B$10/1000000/P51 -> 0.7227551 | S51: =R51*INDEX(Datos!$C$95:$C$100,MATCH(C51,Datos!$A$95:$A$100,0)) -> 0.92541657 | T51: =B51+2*E51 -> 205 | U51: =PI()*B51^2/4/(T51*G51)*(1-Datos!$B$20) -> 0.73589892 | V51: =B51+G51*SQRT(3)/2+2*E51 -> 377.33906 | W51: =2*PI()*B51^2/4/(V51*G51)*(1-Datos!$B$20) -> 0.79959536 | X51: =Piezas!$S$25/U51 -> 0.64534 | Y51: =Piezas!$S$25/W51 -> 0.59393167
A53: Por unidad de matafuego (cúpula + fondo)
A54: Formato | B54: Masa neta (kg) | C54: kg de fleje | D54: USD de fleje | E54: kg de hoja | F54: USD de hoja | G54: Tiras de hoja
A55: 1 kg | B55: =Piezas!$S$18+Piezas!$S$19 -> 0.11379468 | C55: =I44+I45 -> 0.15622479 | D55: =J44+J45 -> 0.18988181 | E55: =R44+R45 -> 0.16406219 | F55: =S44+S45 -> 0.21579386 | G55: =1/O44+1/O45 -> 0.16025641
A56: 2,5 kg | B56: =Piezas!$S$20+Piezas!$S$21 -> 0.34175597 | C56: =I46+I47 -> 0.45955554 | D56: =J46+J47 -> 0.54503287 | E56: =R46+R47 -> 0.50768117 | F56: =S46+S47 -> 0.65505986 | G56: =1/O46+1/O47 -> 0.26785714
A57: 5 kg | B57: =Piezas!$S$22+Piezas!$S$23 -> 0.66962398 | C57: =I48+I49 -> 0.90190054 | D57: =J48+J49 -> 1.069654 | E57: =R48+R49 -> 1.0258283 | F57: =S48+S49 -> 1.3618086 | G57: =1/O48+1/O49 -> 0.36666667
A58: 10 kg | B58: =Piezas!$S$24+Piezas!$S$25 -> 1.0049181 | C58: =I50+I51 -> 1.3519085 | D58: =J50+J51 -> 1.6111076 | E58: =R50+R51 -> 1.5097551 | F58: =S50+S51 -> 1.9701756 | G58: =1/O50+1/O51 -> 0.39285714
A61: D) Bobina madre por espesor con corte longitudinal propio (C): patrones de tiras
A62: Grupo | B62: Ancho de madre (mm) | C62: Cuerpo a lo ancho (1 alto, 2 desarrollo) | D62: kg por metro | E62: USD/kg | F62: Tiras de disco por ancho | G62: Peso de madre (t) | H62: Control
A63: 0,9 mm | B63: 1220 | C63: 2 | D63: =B63*0.9*Datos!$B$10/1000 -> 8.64126 | E63: =INDEX(Datos!$E$95:$E$100,MATCH(0.9,Datos!$A$95:$A$100,0)) -> 1.26285 | F63: =H73 -> 1.5145 | G63: =MIN(ROUNDDOWN(MIN(B63*Datos!$B$57,Datos!$B$60)*2,0)/2,MAX(Datos!$B$54,ROUNDUP(INDEX(Cálculo!$C$79:$L$79,Datos!$B$6-2025)/12*Datos!$B$52*2,0)/2)) -> 9 | H63: =IF(AND(H75="Suma 100 %",COUNTIF(E77:G77,"No entra")=0),"OK","Revisar") -> OK
A64: 1,25 mm | B64: 1000 | C64: 2 | D64: =B64*1.25*Datos!$B$10/1000 -> 9.8375 | E64: =INDEX(Datos!$E$95:$E$100,MATCH(1.25,Datos!$A$95:$A$100,0)) -> 1.25056 | F64: =H82+H83+H84 -> 5.7712 | G64: =MIN(ROUNDDOWN(MIN(B64*Datos!$B$57,Datos!$B$60)*2,0)/2,MAX(Datos!$B$54,ROUNDUP(INDEX(Cálculo!$C$80:$L$80,Datos!$B$6-2025)/12*Datos!$B$52*2,0)/2)) -> 3.5 | H64: =IF(AND(H85="Suma 100 %",COUNTIF(E87:G87,"No entra")=0),"OK","Revisar") -> OK
A65: 1,6 mm | B65: 1000 | C65: 1 | D65: =B65*1.6*Datos!$B$10/1000 -> 12.592 | E65: =INDEX(Datos!$E$95:$E$100,MATCH(1.6,Datos!$A$95:$A$100,0)) -> 1.25056 | F65: =H92+H93+H94 -> 1.6455 | G65: =MIN(ROUNDDOWN(MIN(B65*Datos!$B$57,Datos!$B$60)*2,0)/2,MAX(Datos!$B$54,ROUNDUP(INDEX(Cálculo!$C$81:$L$81,Datos!$B$6-2025)/12*Datos!$B$52*2,0)/2)) -> 12 | H65: =IF(AND(H95="Suma 100 %",COUNTIF(E97:G97,"No entra")=0),"OK","Revisar") -> OK
A66: 2,0 mm | B66: 1000 | C66: 1 | D66: =B66*2*Datos!$B$10/1000 -> 15.74 | E66: =INDEX(Datos!$E$95:$E$100,MATCH(2,Datos!$A$95:$A$100,0)) -> 1.26285 | F66: =H102 -> 0.5998 | G66: =MIN(ROUNDDOWN(MIN(B66*Datos!$B$57,Datos!$B$60)*2,0)/2,MAX(Datos!$B$54,ROUNDUP(INDEX(Cálculo!$C$82:$L$82,Datos!$B$6-2025)/12*Datos!$B$52*2,0)/2)) -> 2 | H66: =IF(AND(H103="Suma 100 %",COUNTIF(E105:G105,"No entra")=0),"OK","Revisar") -> OK
A67: 3,2 mm | B67: 1500 | C67: 1 | D67: =B67*3.2*Datos!$B$10/1000 -> 37.776 | E67: =INDEX(Datos!$E$95:$E$100,MATCH(3.2,Datos!$A$95:$A$100,0)) -> 1.11373 | F67: 0 | G67: =MIN(ROUNDDOWN(MIN(B67*Datos!$B$57,Datos!$B$60)*2,0)/2,MAX(Datos!$B$54,ROUNDUP(INDEX(Cálculo!$C$83:$L$83,Datos!$B$6-2025)/12*Datos!$B$52*2,0)/2)) -> 3.5 | H67: =IF(AND(H111="Suma 100 %",COUNTIF(E113:G113,"No entra")=0),"OK","Revisar") -> OK
A68: 4,75 mm | B68: 1245 | C68: 2 (fijo) | D68: =B68*4.75*Datos!$B$10/1000 -> 46.541213 | E68: =INDEX(Datos!$E$95:$E$100,MATCH(4.75,Datos!$A$95:$A$100,0)) -> 1.11373 | F68: 0 | G68: =MIN(ROUNDDOWN(MIN(B68*Datos!$B$57,Datos!$B$60)*2,0)/2,MAX(Datos!$B$54,ROUNDUP(INDEX(Cálculo!$C$84:$L$84,Datos!$B$6-2025)/12*Datos!$B$52*2,0)/2)) -> 2 | H68: =IF(AND(H118="Suma 100 %",COUNTIF(E120:G120,"No entra")=0),"OK","Revisar") -> OK
A71: Grupo 0,9 mm
A72: Tira | B72: Formato | C72: Ancho (mm) | D72: Avance por pieza (mm) | E72: Patrón 1 | F72: Patrón 2 | G72: Patrón 3 | H72: Tiras por metro de madre
A73: Cúpula 1 kg | B73: 1 kg | C73: =F44 -> 93.05 | D73: =G44 -> 90.35 | E73: 0 | F73: 13 | G73: 0 | H73: =E73*$E$75+F73*$F$75+G73*$G$75 -> 1.5145
A74: Cuerpo 1 kg | B74: 1 kg | C74: =IF($C$63=1,Piezas!$F$6,Piezas!$G$6) -> 236.5 | D74: =IF($C$63=1,Piezas!$G$6,Piezas!$F$6) -> 263.5 | E74: 5 | F74: 0 | G74: 0 | H74: =E74*$E$75+F74*$F$75+G74*$G$75 -> 4.4175
A75: Participación (% de los metros de madre) | E75: 0.8835 | F75: 0.1165 | G75: 0 | H75: =IF(ABS(SUM(E75:G75)-1)<0.001,"Suma 100 %","Revisar: no suma 100 %") -> Suma 100 %
A76: Ancho usado (mm) | E76: =SUMPRODUCT($C$73:$C$74,E73:E74) -> 1182.5 | F76: =SUMPRODUCT($C$73:$C$74,F73:F74) -> 1209.65 | G76: =SUMPRODUCT($C$73:$C$74,G73:G74) -> 0
A77: ¿Entra en la madre? (orilla ≥ margen) | E77: =IF(E76=0,"sin uso",IF($B$63-E76>=Datos!$B$19,"OK","No entra")) -> OK | F77: =IF(F76=0,"sin uso",IF($B$63-F76>=Datos!$B$19,"OK","No entra")) -> OK | G77: =IF(G76=0,"sin uso",IF($B$63-G76>=Datos!$B$19,"OK","No entra")) -> sin uso
A79: Grupo 1,25 mm
A80: Tira | B80: Formato | C80: Ancho (mm) | D80: Avance por pieza (mm) | E80: Patrón 1 | F80: Patrón 2 | G80: Patrón 3 | H80: Tiras por metro de madre
A81: Cuerpo 2,5 kg | B81: 2,5 kg | C81: =IF($C$64=1,Piezas!$F$7,Piezas!$G$7) -> 385.5 | D81: =IF($C$64=1,Piezas!$G$7,Piezas!$F$7) -> 267.5 | E81: 1 | F81: 1 | G81: 0 | H81: =E81*$E$85+F81*$F$85+G81*$G$85 -> 0.9062
A82: Cúpula 2,5 kg | B82: 2,5 kg | C82: =F46 -> 162.125 | D82: =G46 -> 158.375 | E82: 0 | F82: 1 | G82: 4 | H82: =E82*$E$85+F82*$F$85+G82*$G$85 -> 0.5365
A83: Fondo 2,5 kg | B83: 2,5 kg | C83: =F47 -> 146.125 | D83: =G47 -> 142.375 | E83: 0 | F83: 3 | G83: 0 | H83: =E83*$E$85+F83*$F$85+G83*$G$85 -> 0.4839
A84: Fondo 1 kg | B84: 1 kg | C84: =F45 -> 100.625 | D84: =G45 -> 96.875 | E84: 6 | F84: 0 | G84: 3 | H84: =E84*$E$85+F84*$F$85+G84*$G$85 -> 4.7508
A85: Participación (% de los metros de madre) | E85: 0.7449 | F85: 0.1613 | G85: 0.0938 | H85: =IF(ABS(SUM(E85:G85)-1)<0.001,"Suma 100 %","Revisar: no suma 100 %") -> Suma 100 %
A86: Ancho usado (mm) | E86: =SUMPRODUCT($C$81:$C$84,E81:E84) -> 989.25 | F86: =SUMPRODUCT($C$81:$C$84,F81:F84) -> 986 | G86: =SUMPRODUCT($C$81:$C$84,G81:G84) -> 950.375
A87: ¿Entra en la madre? (orilla ≥ margen) | E87: =IF(E86=0,"sin uso",IF($B$64-E86>=Datos!$B$19,"OK","No entra")) -> OK | F87: =IF(F86=0,"sin uso",IF($B$64-F86>=Datos!$B$19,"OK","No entra")) -> OK | G87: =IF(G86=0,"sin uso",IF($B$64-G86>=Datos!$B$19,"OK","No entra")) -> OK
A89: Grupo 1,6 mm
A90: Tira | B90: Formato | C90: Ancho (mm) | D90: Avance por pieza (mm) | E90: Patrón 1 | F90: Patrón 2 | G90: Patrón 3 | H90: Tiras por metro de madre
A91: Cuerpo 5 kg | B91: 5 kg | C91: =IF($C$65=1,Piezas!$F$8,Piezas!$G$8) -> 327.5 | D91: =IF($C$65=1,Piezas!$G$8,Piezas!$F$8) -> 475.5 | E91: 3 | F91: 0 | G91: 0 | H91: =E91*$E$95+F91*$F$95+G91*$G$95 -> 2.0127
A92: Cúpula 5 kg | B92: 5 kg | C92: =F48 -> 204.2 | D92: =G48 -> 199.4 | E92: 0 | F92: 3 | G92: 1 | H92: =E92*$E$95+F92*$F$95+G92*$G$95 -> 0.8441
A93: Fondo 5 kg | B93: 5 kg | C93: =F49 -> 177.2 | D93: =G49 -> 172.4 | E93: 0 | F93: 2 | G93: 3 | H93: =E93*$E$95+F93*$F$95+G93*$G$95 -> 0.7298
A94: Cúpula 10 kg | B94: 10 kg | C94: =F50 -> 238.7 | D94: =G50 -> 233.9 | E94: 0 | F94: 0 | G94: 1 | H94: =E94*$E$95+F94*$F$95+G94*$G$95 -> 0.0716
A95: Participación (% de los metros de madre) | E95: 0.6709 | F95: 0.2575 | G95: 0.0716 | H95: =IF(ABS(SUM(E95:G95)-1)<0.001,"Suma 100 %","Revisar: no suma 100 %") -> Suma 100 %
A96: Ancho usado (mm) | E96: =SUMPRODUCT($C$91:$C$94,E91:E94) -> 982.5 | F96: =SUMPRODUCT($C$91:$C$94,F91:F94) -> 967 | G96: =SUMPRODUCT($C$91:$C$94,G91:G94) -> 974.5
A97: ¿Entra en la madre? (orilla ≥ margen) | E97: =IF(E96=0,"sin uso",IF($B$65-E96>=Datos!$B$19,"OK","No entra")) -> OK | F97: =IF(F96=0,"sin uso",IF($B$65-F96>=Datos!$B$19,"OK","No entra")) -> OK | G97: =IF(G96=0,"sin uso",IF($B$65-G96>=Datos!$B$19,"OK","No entra")) -> OK
A99: Grupo 2,0 mm
A100: Tira | B100: Formato | C100: Ancho (mm) | D100: Avance por pieza (mm) | E100: Patrón 1 | F100: Patrón 2 | G100: Patrón 3 | H100: Tiras por metro de madre
A101: Cuerpo 10 kg | B101: 10 kg | C101: =IF($C$66=1,Piezas!$F$9,Piezas!$G$9) -> 493 | D101: =IF($C$66=1,Piezas!$G$9,Piezas!$F$9) -> 564 | E101: 2 | F101: 1 | G101: 0 | H101: =E101*$E$103+F101*$F$103+G101*$G$103 -> 1.7001
A102: Fondo 10 kg | B102: 10 kg | C102: =F51 -> 205 | D102: =G51 -> 199 | E102: 0 | F102: 2 | G102: 0 | H102: =E102*$E$103+F102*$F$103+G102*$G$103 -> 0.5998
A103: Participación (% de los metros de madre) | E103: 0.7001 | F103: 0.2999 | G103: 0 | H103: =IF(ABS(SUM(E103:G103)-1)<0.001,"Suma 100 %","Revisar: no suma 100 %") -> Suma 100 %
A104: Ancho usado (mm) | E104: =SUMPRODUCT($C$101:$C$102,E101:E102) -> 986 | F104: =SUMPRODUCT($C$101:$C$102,F101:F102) -> 903 | G104: =SUMPRODUCT($C$101:$C$102,G101:G102) -> 0
A105: ¿Entra en la madre? (orilla ≥ margen) | E105: =IF(E104=0,"sin uso",IF($B$66-E104>=Datos!$B$19,"OK","No entra")) -> OK | F105: =IF(F104=0,"sin uso",IF($B$66-F104>=Datos!$B$19,"OK","No entra")) -> OK | G105: =IF(G104=0,"sin uso",IF($B$66-G104>=Datos!$B$19,"OK","No entra")) -> sin uso
A107: Grupo 3,2 mm
A108: Tira | B108: Formato | C108: Ancho (mm) | D108: Avance por pieza (mm) | E108: Patrón 1 | F108: Patrón 2 | G108: Patrón 3 | H108: Tiras por metro de madre
A109: Cuerpo 25 kg | B109: 25 kg | C109: =IF($C$67=1,Piezas!$F$10,Piezas!$G$10) -> 493 | D109: =IF($C$67=1,Piezas!$G$10,Piezas!$F$10) -> 858.5 | E109: 0 | F109: 3 | G109: 0 | H109: =E109*$E$111+F109*$F$111+G109*$G$111 -> 0.6216
A110: Cuerpo 50 kg | B110: 50 kg | C110: =IF($C$67=1,Piezas!$F$11,Piezas!$G$11) -> 640 | D110: =IF($C$67=1,Piezas!$G$11,Piezas!$F$11) -> 995.5 | E110: 2 | F110: 0 | G110: 0 | H110: =E110*$E$111+F110*$F$111+G110*$G$111 -> 1.5856
A111: Participación (% de los metros de madre) | E111: 0.7928 | F111: 0.2072 | G111: 0 | H111: =IF(ABS(SUM(E111:G111)-1)<0.001,"Suma 100 %","Revisar: no suma 100 %") -> Suma 100 %
A112: Ancho usado (mm) | E112: =SUMPRODUCT($C$109:$C$110,E109:E110) -> 1280 | F112: =SUMPRODUCT($C$109:$C$110,F109:F110) -> 1479 | G112: =SUMPRODUCT($C$109:$C$110,G109:G110) -> 0
A113: ¿Entra en la madre? (orilla ≥ margen) | E113: =IF(E112=0,"sin uso",IF($B$67-E112>=Datos!$B$19,"OK","No entra")) -> OK | F113: =IF(F112=0,"sin uso",IF($B$67-F112>=Datos!$B$19,"OK","No entra")) -> OK | G113: =IF(G112=0,"sin uso",IF($B$67-G112>=Datos!$B$19,"OK","No entra")) -> sin uso
A115: Grupo 4,75 mm
A116: Tira | B116: Formato | C116: Ancho (mm) | D116: Avance por pieza (mm) | E116: Patrón 1 | F116: Patrón 2 | G116: Patrón 3 | H116: Tiras por metro de madre
...

Sheet Nesting
A1: Nesting: ¿es el mejor corte?
A2: Todas las hojas cotizadas y todos los patrones de guillotina con el 1.er corte por el lado corto (hasta tres etapas). Los patrones salen de enumerarlos todos; la mezcla, de programación lineal.
A4: A) La hoja que conviene para cada formato (corte en dos etapas)
A5: Formato | B5: Hoja: lado corto (mm) | C5: lado largo (mm) | D5: Espesor (mm) | E5: Cotización | F5: USD/kg | G5: Franjas × piezas | H5: Piezas por hoja | I5: Aprovech. | J5: Masa de la hoja (kg) | K5: kg por cuerpo | L5: USD por cuerpo | M5: La más barata | N5: En Corte
A6: 1 kg | B6: 1220 | C6: 2440 | D6: =Piezas!$E$6 -> 0.9 | E6: Q12 | F6: =Datos!$G$77 -> 1.3561 | G6: =IF(IF(AND(Piezas!$F$6<=Datos!$B$34,Piezas!$F$6<=Datos!$B$36,B6<=Datos!$B$33,OR(Piezas!$G$6<=Datos!$B$37,AND(INT(B6/Piezas!$G$6)=1,B6-Piezas!$G$6<=Datos!$B$37))),INT(C6/Piezas!$F$6)*INT(B6/Piezas!$G$6),0)>=IF(AND(Piezas!$G$6<=Datos!$B$34,Piezas!$G$6<=Datos!$B$36,B6<=Datos!$B$33,OR(Piezas!$F$6<=Datos!$B$37,AND(INT(B6/Piezas!$F$6)=1,B6-Piezas!$F$6<=Datos!$B$37))),INT(C6/Piezas!$G$6)*INT(B6/Piezas!$F$6),0),INT(C6/Piezas!$F$6)&" × "&INT(B6/Piezas!$G$6),INT(C6/Piezas!$G$6)&" × "&INT(B6/Piezas!$F$6)) -> 9 × 5 | H6: =MAX(IF(AND(Piezas!$F$6<=Datos!$B$34,Piezas!$F$6<=Datos!$B$36,B6<=Datos!$B$33,OR(Piezas!$G$6<=Datos!$B$37,AND(INT(B6/Piezas!$G$6)=1,B6-Piezas!$G$6<=Datos!$B$37))),INT(C6/Piezas!$F$6)*INT(B6/Piezas!$G$6),0),IF(AND(Piezas!$G$6<=Datos!$B$34,Piezas!$G$6<=Datos!$B$36,B6<=Datos!$B$33,OR(Piezas!$F$6<=Datos!$B$37,AND(INT(B6/Piezas!$F$6)=1,B6-Piezas!$F$6<=Datos!$B$37))),INT(C6/Piezas!$G$6)*INT(B6/Piezas!$F$6),0)) -> 45 | I6: =IF(H6=0,0,H6*Piezas!$F$6*Piezas!$G$6/(B6*C6)) -> 0.94205145 | J6: =B6*C6*D6*Datos!$B$10/1000000 -> 21.084674 | K6: =IF(H6=0,0,J6/H6) -> 0.46854832 | L6: =IF(H6=0,0,K6*F6) -> 0.63539838 | M6: =IF(L6=MIN($L$6:$L$7),"Sí","") -> Sí | N6: =IF(AND(B6=Corte!$B$6,C6=Corte!$C$6,F6=INDEX(Datos!$C$95:$C$100,MATCH(Piezas!$E$6,Datos!$A$95:$A$100,0))),"Sí","") -> Sí
A7: 1 kg | B7: 1000 | C7: 2000 | D7: =Piezas!$E$6 -> 0.9 | E7: Q13 | F7: =Datos!$G$78 -> 1.3993 | G7: =IF(IF(AND(Piezas!$F$6<=Datos!$B$34,Piezas!$F$6<=Datos!$B$36,B7<=Datos!$B$33,OR(Piezas!$G$6<=Datos!$B$37,AND(INT(B7/Piezas!$G$6)=1,B7-Piezas!$G$6<=Datos!$B$37))),INT(C7/Piezas!$F$6)*INT(B7/Piezas!$G$6),0)>=IF(AND(Piezas!$G$6<=Datos!$B$34,Piezas!$G$6<=Datos!$B$36,B7<=Datos!$B$33,OR(Piezas!$F$6<=Datos!$B$37,AND(INT(B7/Piezas!$F$6)=1,B7-Piezas!$F$6<=Datos!$B$37))),INT(C7/Piezas!$G$6)*INT(B7/Piezas!$F$6),0),INT(C7/Piezas!$F$6)&" × "&INT(B7/Piezas!$G$6),INT(C7/Piezas!$G$6)&" × "&INT(B7/Piezas!$F$6)) -> 7 × 4 | H7: =MAX(IF(AND(Piezas!$F$6<=Datos!$B$34,Piezas!$F$6<=Datos!$B$36,B7<=Datos!$B$33,OR(Piezas!$G$6<=Datos!$B$37,AND(INT(B7/Piezas!$G$6)=1,B7-Piezas!$G$6<=Datos!$B$37))),INT(C7/Piezas!$F$6)*INT(B7/Piezas!$G$6),0),IF(AND(Piezas!$G$6<=Datos!$B$34,Piezas!$G$6<=Datos!$B$36,B7<=Datos!$B$33,OR(Piezas!$F$6<=Datos!$B$37,AND(INT(B7/Piezas!$F$6)=1,B7-Piezas!$F$6<=Datos!$B$37))),INT(C7/Piezas!$G$6)*INT(B7/Piezas!$F$6),0)) -> 28 | I7: =IF(H7=0,0,H7*Piezas!$F$6*Piezas!$G$6/(B7*C7)) -> 0.8724485 | J7: =B7*C7*D7*Datos!$B$10/1000000 -> 14.166 | K7: =IF(H7=0,0,J7/H7) -> 0.50592857 | L7: =IF(H7=0,0,K7*F7) -> 0.70794585 | M7: =IF(L7=MIN($L$6:$L$7),"Sí","") | N7: =IF(AND(B7=Corte!$B$6,C7=Corte!$C$6,F7=INDEX(Datos!$C$95:$C$100,MATCH(Piezas!$E$6,Datos!$A$95:$A$100,0))),"Sí","")
A8: 2,5 kg | B8: 1220 | C8: 2440 | D8: =Piezas!$E$7 -> 1.25 | E8: Q8 | F8: =Datos!$G$73 -> 1.2902977 | G8: =IF(IF(AND(Piezas!$F$7<=Datos!$B$34,Piezas!$F$7<=Datos!$B$36,B8<=Datos!$B$33,OR(Piezas!$G$7<=Datos!$B$37,AND(INT(B8/Piezas!$G$7)=1,B8-Piezas!$G$7<=Datos!$B$37))),INT(C8/Piezas!$F$7)*INT(B8/Piezas!$G$7),0)>=IF(AND(Piezas!$G$7<=Datos!$B$34,Piezas!$G$7<=Datos!$B$36,B8<=Datos!$B$33,OR(Piezas!$F$7<=Datos!$B$37,AND(INT(B8/Piezas!$F$7)=1,B8-Piezas!$F$7<=Datos!$B$37))),INT(C8/Piezas!$G$7)*INT(B8/Piezas!$F$7),0),INT(C8/Piezas!$F$7)&" × "&INT(B8/Piezas!$G$7),INT(C8/Piezas!$G$7)&" × "&INT(B8/Piezas!$F$7)) -> 9 × 3 | H8: =MAX(IF(AND(Piezas!$F$7<=Datos!$B$34,Piezas!$F$7<=Datos!$B$36,B8<=Datos!$B$33,OR(Piezas!$G$7<=Datos!$B$37,AND(INT(B8/Piezas!$G$7)=1,B8-Piezas!$G$7<=Datos!$B$37))),INT(C8/Piezas!$F$7)*INT(B8/Piezas!$G$7),0),IF(AND(Piezas!$G$7<=Datos!$B$34,Piezas!$G$7<=Datos!$B$36,B8<=Datos!$B$33,OR(Piezas!$F$7<=Datos!$B$37,AND(INT(B8/Piezas!$F$7)=1,B8-Piezas!$F$7<=Datos!$B$37))),INT(C8/Piezas!$G$7)*INT(B8/Piezas!$F$7),0)) -> 27 | I8: =IF(H8=0,0,H8*Piezas!$F$7*Piezas!$G$7/(B8*C8)) -> 0.93532443 | J8: =B8*C8*D8*Datos!$B$10/1000000 -> 29.28427 | K8: =IF(H8=0,0,J8/H8) -> 1.0846026 | L8: =IF(H8=0,0,K8*F8) -> 1.3994603 | M8: =IF(L8=MIN($L$8:$L$8),"Sí","") -> Sí | N8: =IF(AND(B8=Corte!$B$7,C8=Corte!$C$7,F8=INDEX(Datos!$C$95:$C$100,MATCH(Piezas!$E$7,Datos!$A$95:$A$100,0))),"Sí","") -> Sí
A9: 5 kg | B9: 1000 | C9: 2000 | D9: =Piezas!$E$8 -> 1.6 | E9: Q7 | F9: =Datos!$G$72 -> 1.327521 | G9: =IF(IF(AND(Piezas!$F$8<=Datos!$B$34,Piezas!$F$8<=Datos!$B$36,B9<=Datos!$B$33,OR(Piezas!$G$8<=Datos!$B$37,AND(INT(B9/Piezas!$G$8)=1,B9-Piezas!$G$8<=Datos!$B$37))),INT(C9/Piezas!$F$8)*INT(B9/Piezas!$G$8),0)>=IF(AND(Piezas!$G$8<=Datos!$B$34,Piezas!$G$8<=Datos!$B$36,B9<=Datos!$B$33,OR(Piezas!$F$8<=Datos!$B$37,AND(INT(B9/Piezas!$F$8)=1,B9-Piezas!$F$8<=Datos!$B$37))),INT(C9/Piezas!$G$8)*INT(B9/Piezas!$F$8),0),INT(C9/Piezas!$F$8)&" × "&INT(B9/Piezas!$G$8),INT(C9/Piezas!$G$8)&" × "&INT(B9/Piezas!$F$8)) -> 6 × 2 | H9: =MAX(IF(AND(Piezas!$F$8<=Datos!$B$34,Piezas!$F$8<=Datos!$B$36,B9<=Datos!$B$33,OR(Piezas!$G$8<=Datos!$B$37,AND(INT(B9/Piezas!$G$8)=1,B9-Piezas!$G$8<=Datos!$B$37))),INT(C9/Piezas!$F$8)*INT(B9/Piezas!$G$8),0),IF(AND(Piezas!$G$8<=Datos!$B$34,Piezas!$G$8<=Datos!$B$36,B9<=Datos!$B$33,OR(Piezas!$F$8<=Datos!$B$37,AND(INT(B9/Piezas!$F$8)=1,B9-Piezas!$F$8<=Datos!$B$37))),INT(C9/Piezas!$G$8)*INT(B9/Piezas!$F$8),0)) -> 12 | I9: =IF(H9=0,0,H9*Piezas!$F$8*Piezas!$G$8/(B9*C9)) -> 0.9343575 | J9: =B9*C9*D9*Datos!$B$10/1000000 -> 25.184 | K9: =IF(H9=0,0,J9/H9) -> 2.0986667 | L9: =IF(H9=0,0,K9*F9) -> 2.7860241 | M9: =IF(L9=MIN($L$9:$L$10),"Sí","") -> Sí | N9: =IF(AND(B9=Corte!$B$8,C9=Corte!$C$8,F9=INDEX(Datos!$C$95:$C$100,MATCH(Piezas!$E$8,Datos!$A$95:$A$100,0))),"Sí","") -> Sí
A10: 5 kg | B10: 1220 | C10: 2440 | D10: =Piezas!$E$8 -> 1.6 | E10: Q15 | F10: =Datos!$G$80 -> 1.3443 | G10: =IF(IF(AND(Piezas!$F$8<=Datos!$B$34,Piezas!$F$8<=Datos!$B$36,B10<=Datos!$B$33,OR(Piezas!$G$8<=Datos!$B$37,AND(INT(B10/Piezas!$G$8)=1,B10-Piezas!$G$8<=Datos!$B$37))),INT(C10/Piezas!$F$8)*INT(B10/Piezas!$G$8),0)>=IF(AND(Piezas!$G$8<=Datos!$B$34,Piezas!$G$8<=Datos!$B$36,B10<=Datos!$B$33,OR(Piezas!$F$8<=Datos!$B$37,AND(INT(B10/Piezas!$F$8)=1,B10-Piezas!$F$8<=Datos!$B$37))),INT(C10/Piezas!$G$8)*INT(B10/Piezas!$F$8),0),INT(C10/Piezas!$F$8)&" × "&INT(B10/Piezas!$G$8),INT(C10/Piezas!$G$8)&" × "&INT(B10/Piezas!$F$8)) -> 5 × 3 | H10: =MAX(IF(AND(Piezas!$F$8<=Datos!$B$34,Piezas!$F$8<=Datos!$B$36,B10<=Datos!$B$33,OR(Piezas!$G$8<=Datos!$B$37,AND(INT(B10/Piezas!$G$8)=1,B10-Piezas!$G$8<=Datos!$B$37))),INT(C10/Piezas!$F$8)*INT(B10/Piezas!$G$8),0),IF(AND(Piezas!$G$8<=Datos!$B$34,Piezas!$G$8<=Datos!$B$36,B10<=Datos!$B$33,OR(Piezas!$F$8<=Datos!$B$37,AND(INT(B10/Piezas!$F$8)=1,B10-Piezas!$F$8<=Datos!$B$37))),INT(C10/Piezas!$G$8)*INT(B10/Piezas!$F$8),0)) -> 15 | I10: =IF(H10=0,0,H10*Piezas!$F$8*Piezas!$G$8/(B10*C10)) -> 0.78469959 | J10: =B10*C10*D10*Datos!$B$10/1000000 -> 37.483866 | K10: =IF(H10=0,0,J10/H10) -> 2.4989244 | L10: =IF(H10=0,0,K10*F10) -> 3.359304 | M10: =IF(L10=MIN($L$9:$L$10),"Sí","") | N10: =IF(AND(B10=Corte!$B$8,C10=Corte!$C$8,F10=INDEX(Datos!$C$95:$C$100,MATCH(Piezas!$E$8,Datos!$A$95:$A$100,0))),"Sí","")
A11: 10 kg | B11: 1500 | C11: 3000 | D11: =Piezas!$E$9 -> 2 | E11: Q9 | F11: =Datos!$G$74 -> 1.2804013 | G11: =IF(IF(AND(Piezas!$F$9<=Datos!$B$34,Piezas!$F$9<=Datos!$B$36,B11<=Datos!$B$33,OR(Piezas!$G$9<=Datos!$B$37,AND(INT(B11/Piezas!$G$9)=1,B11-Piezas!$G$9<=Datos!$B$37))),INT(C11/Piezas!$F$9)*INT(B11/Piezas!$G$9),0)>=IF(AND(Piezas!$G$9<=Datos!$B$34,Piezas!$G$9<=Datos!$B$36,B11<=Datos!$B$33,OR(Piezas!$F$9<=Datos!$B$37,AND(INT(B11/Piezas!$F$9)=1,B11-Piezas!$F$9<=Datos!$B$37))),INT(C11/Piezas!$G$9)*INT(B11/Piezas!$F$9),0),INT(C11/Piezas!$F$9)&" × "&INT(B11/Piezas!$G$9),INT(C11/Piezas!$G$9)&" × "&INT(B11/Piezas!$F$9)) -> 5 × 3 | H11: =MAX(IF(AND(Piezas!$F$9<=Datos!$B$34,Piezas!$F$9<=Datos!$B$36,B11<=Datos!$B$33,OR(Piezas!$G$9<=Datos!$B$37,AND(INT(B11/Piezas!$G$9)=1,B11-Piezas!$G$9<=Datos!$B$37))),INT(C11/Piezas!$F$9)*INT(B11/Piezas!$G$9),0),IF(AND(Piezas!$G$9<=Datos!$B$34,Piezas!$G$9<=Datos!$B$36,B11<=Datos!$B$33,OR(Piezas!$F$9<=Datos!$B$37,AND(INT(B11/Piezas!$F$9)=1,B11-Piezas!$F$9<=Datos!$B$37))),INT(C11/Piezas!$G$9)*INT(B11/Piezas!$F$9),0)) -> 15 | I11: =IF(H11=0,0,H11*Piezas!$F$9*Piezas!$G$9/(B11*C11)) -> 0.92684 | J11: =B11*C11*D11*Datos!$B$10/1000000 -> 70.83 | K11: =IF(H11=0,0,J11/H11) -> 4.722 | L11: =IF(H11=0,0,K11*F11) -> 6.0460549 | M11: =IF(L11=MIN($L$11:$L$12),"Sí","") -> Sí | N11: =IF(AND(B11=Corte!$B$9,C11=Corte!$C$9,F11=INDEX(Datos!$C$95:$C$100,MATCH(Piezas!$E$9,Datos!$A$95:$A$100,0))),"Sí","") -> Sí
A12: 10 kg | B12: 1220 | C12: 2440 | D12: =Piezas!$E$9 -> 2 | E12: Q16 | F12: =Datos!$G$81 -> 1.3605 | G12: =IF(IF(AND(Piezas!$F$9<=Datos!$B$34,Piezas!$F$9<=Datos!$B$36,B12<=Datos!$B$33,OR(Piezas!$G$9<=Datos!$B$37,AND(INT(B12/Piezas!$G$9)=1,B12-Piezas!$G$9<=Datos!$B$37))),INT(C12/Piezas!$F$9)*INT(B12/Piezas!$G$9),0)>=IF(AND(Piezas!$G$9<=Datos!$B$34,Piezas!$G$9<=Datos!$B$36,B12<=Datos!$B$33,OR(Piezas!$F$9<=Datos!$B$37,AND(INT(B12/Piezas!$F$9)=1,B12-Piezas!$F$9<=Datos!$B$37))),INT(C12/Piezas!$G$9)*INT(B12/Piezas!$F$9),0),INT(C12/Piezas!$F$9)&" × "&INT(B12/Piezas!$G$9),INT(C12/Piezas!$G$9)&" × "&INT(B12/Piezas!$F$9)) -> 4 × 2 | H12: =MAX(IF(AND(Piezas!$F$9<=Datos!$B$34,Piezas!$F$9<=Datos!$B$36,B12<=Datos!$B$33,OR(Piezas!$G$9<=Datos!$B$37,AND(INT(B12/Piezas!$G$9)=1,B12-Piezas!$G$9<=Datos!$B$37))),INT(C12/Piezas!$F$9)*INT(B12/Piezas!$G$9),0),IF(AND(Piezas!$G$9<=Datos!$B$34,Piezas!$G$9<=Datos!$B$36,B12<=Datos!$B$33,OR(Piezas!$F$9<=Datos!$B$37,AND(INT(B12/Piezas!$F$9)=1,B12-Piezas!$F$9<=Datos!$B$37))),INT(C12/Piezas!$G$9)*INT(B12/Piezas!$F$9),0)) -> 8 | I12: =IF(H12=0,0,H12*Piezas!$F$9*Piezas!$G$9/(B12*C12)) -> 0.74725074 | J12: =B12*C12*D12*Datos!$B$10/1000000 -> 46.854832 | K12: =IF(H12=0,0,J12/H12) -> 5.856854 | L12: =IF(H12=0,0,K12*F12) -> 7.9682499 | M12: =IF(L12=MIN($L$11:$L$12),"Sí","") | N12: =IF(AND(B12=Corte!$B$9,C12=Corte!$C$9,F12=INDEX(Datos!$C$95:$C$100,MATCH(Piezas!$E$9,Datos!$A$95:$A$100,0))),"Sí","")
A13: 25 kg | B13: 1500 | C13: 3000 | D13: =Piezas!$E$10 -> 3.2 | E13: Q10 | F13: =Datos!$G$75 -> 1.1019353 | G13: =IF(IF(AND(Piezas!$F$10<=Datos!$B$34,Piezas!$F$10<=Datos!$B$36,B13<=Datos!$B$33,OR(Piezas!$G$10<=Datos!$B$37,AND(INT(B13/Piezas!$G$10)=1,B13-Piezas!$G$10<=Datos!$B$37))),INT(C13/Piezas!$F$10)*INT(B13/Piezas!$G$10),0)>=IF(AND(Piezas!$G$10<=Datos!$B$34,Piezas!$G$10<=Datos!$B$36,B13<=Datos!$B$33,OR(Piezas!$F$10<=Datos!$B$37,AND(INT(B13/Piezas!$F$10)=1,B13-Piezas!$F$10<=Datos!$B$37))),INT(C13/Piezas!$G$10)*INT(B13/Piezas!$F$10),0),INT(C13/Piezas!$F$10)&" × "&INT(B13/Piezas!$G$10),INT(C13/Piezas!$G$10)&" × "&INT(B13/Piezas!$F$10)) -> 3 × 3 | H13: =MAX(IF(AND(Piezas!$F$10<=Datos!$B$34,Piezas!$F$10<=Datos!$B$36,B13<=Datos!$B$33,OR(Piezas!$G$10<=Datos!$B$37,AND(INT(B13/Piezas!$G$10)=1,B13-Piezas!$G$10<=Datos!$B$37))),INT(C13/Piezas!$F$10)*INT(B13/Piezas!$G$10),0),IF(AND(Piezas!$G$10<=Datos!$B$34,Piezas!$G$10<=Datos!$B$36,B13<=Datos!$B$33,OR(Piezas!$F$10<=Datos!$B$37,AND(INT(B13/Piezas!$F$10)=1,B13-Piezas!$F$10<=Datos!$B$37))),INT(C13/Piezas!$G$10)*INT(B13/Piezas!$F$10),0)) -> 9 | I13: =IF(H13=0,0,H13*Piezas!$F$10*Piezas!$G$10/(B13*C13)) -> 0.846481 | J13: =B13*C13*D13*Datos!$B$10/1000000 -> 113.328 | K13: =IF(H13=0,0,J13/H13) -> 12.592 | L13: =IF(H13=0,0,K13*F13) -> 13.875569 | M13: =IF(L13=MIN($L$13:$L$14),"Sí","") -> Sí | N13: =IF(AND(B13=Corte!$B$10,C13=Corte!$C$10,F13=INDEX(Datos!$C$95:$C$100,MATCH(Piezas!$E$10,Datos!$A$95:$A$100,0))),"Sí","") -> Sí
A14: 25 kg | B14: 1500 | C14: 3000 | D14: =Piezas!$E$10 -> 3.2 | E14: Q17 | F14: =Datos!$G$82 -> 1.1607 | G14: =IF(IF(AND(Piezas!$F$10<=Datos!$B$34,Piezas!$F$10<=Datos!$B$36,B14<=Datos!$B$33,OR(Piezas!$G$10<=Datos!$B$37,AND(INT(B14/Piezas!$G$10)=1,B14-Piezas!$G$10<=Datos!$B$37))),INT(C14/Piezas!$F$10)*INT(B14/Piezas!$G$10),0)>=IF(AND(Piezas!$G$10<=Datos!$B$34,Piezas!$G$10<=Datos!$B$36,B14<=Datos!$B$33,OR(Piezas!$F$10<=Datos!$B$37,AND(INT(B14/Piezas!$F$10)=1,B14-Piezas!$F$10<=Datos!$B$37))),INT(C14/Piezas!$G$10)*INT(B14/Piezas!$F$10),0),INT(C14/Piezas!$F$10)&" × "&INT(B14/Piezas!$G$10),INT(C14/Piezas!$G$10)&" × "&INT(B14/Piezas!$F$10)) -> 3 × 3 | H14: =MAX(IF(AND(Piezas!$F$10<=Datos!$B$34,Piezas!$F$10<=Datos!$B$36,B14<=Datos!$B$33,OR(Piezas!$G$10<=Datos!$B$37,AND(INT(B14/Piezas!$G$10)=1,B14-Piezas!$G$10<=Datos!$B$37))),INT(C14/Piezas!$F$10)*INT(B14/Piezas!$G$10),0),IF(AND(Piezas!$G$10<=Datos!$B$34,Piezas!$G$10<=Datos!$B$36,B14<=Datos!$B$33,OR(Piezas!$F$10<=Datos!$B$37,AND(INT(B14/Piezas!$F$10)=1,B14-Piezas!$F$10<=Datos!$B$37))),INT(C14/Piezas!$G$10)*INT(B14/Piezas!$F$10),0)) -> 9 | I14: =IF(H14=0,0,H14*Piezas!$F$10*Piezas!$G$10/(B14*C14)) -> 0.846481 | J14: =B14*C14*D14*Datos!$B$10/1000000 -> 113.328 | K14: =IF(H14=0,0,J14/H14) -> 12.592 | L14: =IF(H14=0,0,K14*F14) -> 14.615534 | M14: =IF(L14=MIN($L$13:$L$14),"Sí","") | N14: =IF(AND(B14=Corte!$B$10,C14=Corte!$C$10,F14=INDEX(Datos!$C$95:$C$100,MATCH(Piezas!$E$10,Datos!$A$95:$A$100,0))),"Sí","")
A15: 50 kg | B15: 1500 | C15: 3000 | D15: =Piezas!$E$11 -> 3.2 | E15: Q10 | F15: =Datos!$G$75 -> 1.1019353 | G15: =IF(IF(AND(Piezas!$F$11<=Datos!$B$34,Piezas!$F$11<=Datos!$B$36,B15<=Datos!$B$33,OR(Piezas!$G$11<=Datos!$B$37,AND(INT(B15/Piezas!$G$11)=1,B15-Piezas!$G$11<=Datos!$B$37))),INT(C15/Piezas!$F$11)*INT(B15/Piezas!$G$11),0)>=IF(AND(Piezas!$G$11<=Datos!$B$34,Piezas!$G$11<=Datos!$B$36,B15<=Datos!$B$33,OR(Piezas!$F$11<=Datos!$B$37,AND(INT(B15/Piezas!$F$11)=1,B15-Piezas!$F$11<=Datos!$B$37))),INT(C15/Piezas!$G$11)*INT(B15/Piezas!$F$11),0),INT(C15/Piezas!$F$11)&" × "&INT(B15/Piezas!$G$11),INT(C15/Piezas!$G$11)&" × "&INT(B15/Piezas!$F$11)) -> 3 × 2 | H15: =MAX(IF(AND(Piezas!$F$11<=Datos!$B$34,Piezas!$F$11<=Datos!$B$36,B15<=Datos!$B$33,OR(Piezas!$G$11<=Datos!$B$37,AND(INT(B15/Piezas!$G$11)=1,B15-Piezas!$G$11<=Datos!$B$37))),INT(C15/Piezas!$F$11)*INT(B15/Piezas!$G$11),0),IF(AND(Piezas!$G$11<=Datos!$B$34,Piezas!$G$11<=Datos!$B$36,B15<=Datos!$B$33,OR(Piezas!$F$11<=Datos!$B$37,AND(INT(B15/Piezas!$F$11)=1,B15-Piezas!$F$11<=Datos!$B$37))),INT(C15/Piezas!$G$11)*INT(B15/Piezas!$F$11),0)) -> 6 | I15: =IF(H15=0,0,H15*Piezas!$F$11*Piezas!$G$11/(B15*C15)) -> 0.84949333 | J15: =B15*C15*D15*Datos!$B$10/1000000 -> 113.328 | K15: =IF(H15=0,0,J15/H15) -> 18.888 | L15: =IF(H15=0,0,K15*F15) -> 20.813353 | M15: =IF(L15=MIN($L$15:$L$16),"Sí","") -> Sí | N15: =IF(AND(B15=Corte!$B$11,C15=Corte!$C$11,F15=INDEX(Datos!$C$95:$C$100,MATCH(Piezas!$E$11,Datos!$A$95:$A$100,0))),"Sí","") -> Sí
A16: 50 kg | B16: 1500 | C16: 3000 | D16: =Piezas!$E$11 -> 3.2 | E16: Q17 | F16: =Datos!$G$82 -> 1.1607 | G16: =IF(IF(AND(Piezas!$F$11<=Datos!$B$34,Piezas!$F$11<=Datos!$B$36,B16<=Datos!$B$33,OR(Piezas!$G$11<=Datos!$B$37,AND(INT(B16/Piezas!$G$11)=1,B16-Piezas!$G$11<=Datos!$B$37))),INT(C16/Piezas!$F$11)*INT(B16/Piezas!$G$11),0)>=IF(AND(Piezas!$G$11<=Datos!$B$34,Piezas!$G$11<=Datos!$B$36,B16<=Datos!$B$33,OR(Piezas!$F$11<=Datos!$B$37,AND(INT(B16/Piezas!$F$11)=1,B16-Piezas!$F$11<=Datos!$B$37))),INT(C16/Piezas!$G$11)*INT(B16/Piezas!$F$11),0),INT(C16/Piezas!$F$11)&" × "&INT(B16/Piezas!$G$11),INT(C16/Piezas!$G$11)&" × "&INT(B16/Piezas!$F$11)) -> 3 × 2 | H16: =MAX(IF(AND(Piezas!$F$11<=Datos!$B$34,Piezas!$F$11<=Datos!$B$36,B16<=Datos!$B$33,OR(Piezas!$G$11<=Datos!$B$37,AND(INT(B16/Piezas!$G$11)=1,B16-Piezas!$G$11<=Datos!$B$37))),INT(C16/Piezas!$F$11)*INT(B16/Piezas!$G$11),0),IF(AND(Piezas!$G$11<=Datos!$B$34,Piezas!$G$11<=Datos!$B$36,B16<=Datos!$B$33,OR(Piezas!$F$11<=Datos!$B$37,AND(INT(B16/Piezas!$F$11)=1,B16-Piezas!$F$11<=Datos!$B$37))),INT(C16/Piezas!$G$11)*INT(B16/Piezas!$F$11),0)) -> 6 | I16: =IF(H16=0,0,H16*Piezas!$F$11*Piezas!$G$11/(B16*C16)) -> 0.84949333 | J16: =B16*C16*D16*Datos!$B$10/1000000 -> 113.328 | K16: =IF(H16=0,0,J16/H16) -> 18.888 | L16: =IF(H16=0,0,K16*F16) -> 21.923302 | M16: =IF(L16=MIN($L$15:$L$16),"Sí","") | N16: =IF(AND(B16=Corte!$B$11,C16=Corte!$C$11,F16=INDEX(Datos!$C$95:$C$100,MATCH(Piezas!$E$11,Datos!$A$95:$A$100,0))),"Sí","")
A17: 70 kg | B17: 1500 | C17: 3000 | D17: =Piezas!$E$12 -> 4.75 | E17: Q11 | F17: =Datos!$G$76 -> 1.0909773 | G17: =IF(IF(AND(Piezas!$F$12<=Datos!$B$34,Piezas!$F$12<=Datos!$B$36,B17<=Datos!$B$33,OR(Piezas!$G$12<=Datos!$B$37,AND(INT(B17/Piezas!$G$12)=1,B17-Piezas!$G$12<=Datos!$B$37))),INT(C17/Piezas!$F$12)*INT(B17/Piezas!$G$12),0)>=IF(AND(Piezas!$G$12<=Datos!$B$34,Piezas!$G$12<=Datos!$B$36,B17<=Datos!$B$33,OR(Piezas!$F$12<=Datos!$B$37,AND(INT(B17/Piezas!$F$12)=1,B17-Piezas!$F$12<=Datos!$B$37))),INT(C17/Piezas!$G$12)*INT(B17/Piezas!$F$12),0),INT(C17/Piezas!$F$12)&" × "&INT(B17/Piezas!$G$12),INT(C17/Piezas!$G$12)&" × "&INT(B17/Piezas!$F$12)) -> 4 × 1 | H17: =MAX(IF(AND(Piezas!$F$12<=Datos!$B$34,Piezas!$F$12<=Datos!$B$36,B17<=Datos!$B$33,OR(Piezas!$G$12<=Datos!$B$37,AND(INT(B17/Piezas!$G$12)=1,B17-Piezas!$G$12<=Datos!$B$37))),INT(C17/Piezas!$F$12)*INT(B17/Piezas!$G$12),0),IF(AND(Piezas!$G$12<=Datos!$B$34,Piezas!$G$12<=Datos!$B$36,B17<=Datos!$B$33,OR(Piezas!$F$12<=Datos!$B$37,AND(INT(B17/Piezas!$F$12)=1,B17-Piezas!$F$12<=Datos!$B$37))),INT(C17/Piezas!$G$12)*INT(B17/Piezas!$F$12),0)) -> 4 | I17: =IF(H17=0,0,H17*Piezas!$F$12*Piezas!$G$12/(B17*C17)) -> 0.73168 | J17: =B17*C17*D17*Datos!$B$10/1000000 -> 168.22125 | K17: =IF(H17=0,0,J17/H17) -> 42.055312 | L17: =IF(H17=0,0,K17*F17) -> 45.881393 | M17: =IF(L17=MIN($L$17:$L$18),"Sí","") -> Sí | N17: =IF(AND(B17=Corte!$B$12,C17=Corte!$C$12,F17=INDEX(Datos!$C$95:$C$100,MATCH(Piezas!$E$12,Datos!$A$95:$A$100,0))),"Sí","") -> Sí
A18: 70 kg | B18: 1500 | C18: 3000 | D18: =Piezas!$E$12 -> 4.75 | E18: Q18 | F18: =Datos!$G$83 -> 1.1678 | G18: =IF(IF(AND(Piezas!$F$12<=Datos!$B$34,Piezas!$F$12<=Datos!$B$36,B18<=Datos!$B$33,OR(Piezas!$G$12<=Datos!$B$37,AND(INT(B18/Piezas!$G$12)=1,B18-Piezas!$G$12<=Datos!$B$37))),INT(C18/Piezas!$F$12)*INT(B18/Piezas!$G$12),0)>=IF(AND(Piezas!$G$12<=Datos!$B$34,Piezas!$G$12<=Datos!$B$36,B18<=Datos!$B$33,OR(Piezas!$F$12<=Datos!$B$37,AND(INT(B18/Piezas!$F$12)=1,B18-Piezas!$F$12<=Datos!$B$37))),INT(C18/Piezas!$G$12)*INT(B18/Piezas!$F$12),0),INT(C18/Piezas!$F$12)&" × "&INT(B18/Piezas!$G$12),INT(C18/Piezas!$G$12)&" × "&INT(B18/Piezas!$F$12)) -> 4 × 1 | H18: =MAX(IF(AND(Piezas!$F$12<=Datos!$B$34,Piezas!$F$12<=Datos!$B$36,B18<=Datos!$B$33,OR(Piezas!$G$12<=Datos!$B$37,AND(INT(B18/Piezas!$G$12)=1,B18-Piezas!$G$12<=Datos!$B$37))),INT(C18/Piezas!$F$12)*INT(B18/Piezas!$G$12),0),IF(AND(Piezas!$G$12<=Datos!$B$34,Piezas!$G$12<=Datos!$B$36,B18<=Datos!$B$33,OR(Piezas!$F$12<=Datos!$B$37,AND(INT(B18/Piezas!$F$12)=1,B18-Piezas!$F$12<=Datos!$B$37))),INT(C18/Piezas!$G$12)*INT(B18/Piezas!$F$12),0)) -> 4 | I18: =IF(H18=0,0,H18*Piezas!$F$12*Piezas!$G$12/(B18*C18)) -> 0.73168 | J18: =B18*C18*D18*Datos!$B$10/1000000 -> 168.22125 | K18: =IF(H18=0,0,J18/H18) -> 42.055312 | L18: =IF(H18=0,0,K18*F18) -> 49.112194 | M18: =IF(L18=MIN($L$17:$L$18),"Sí","") | N18: =IF(AND(B18=Corte!$B$12,C18=Corte!$C$12,F18=INDEX(Datos!$C$95:$C$100,MATCH(Piezas!$E$12,Datos!$A$95:$A$100,0))),"Sí","")
A19: 100 kg | B19: 1500 | C19: 3000 | D19: =Piezas!$E$13 -> 4.75 | E19: Q11 | F19: =Datos!$G$76 -> 1.0909773 | G19: =IF(IF(AND(Piezas!$F$13<=Datos!$B$34,Piezas!$F$13<=Datos!$B$36,B19<=Datos!$B$33,OR(Piezas!$G$13<=Datos!$B$37,AND(INT(B19/Piezas!$G$13)=1,B19-Piezas!$G$13<=Datos!$B$37))),INT(C19/Piezas!$F$13)*INT(B19/Piezas!$G$13),0)>=IF(AND(Piezas!$G$13<=Datos!$B$34,Piezas!$G$13<=Datos!$B$36,B19<=Datos!$B$33,OR(Piezas!$F$13<=Datos!$B$37,AND(INT(B19/Piezas!$F$13)=1,B19-Piezas!$F$13<=Datos!$B$37))),INT(C19/Piezas!$G$13)*INT(B19/Piezas!$F$13),0),INT(C19/Piezas!$F$13)&" × "&INT(B19/Piezas!$G$13),INT(C19/Piezas!$G$13)&" × "&INT(B19/Piezas!$F$13)) -> 3 × 1 | H19: =MAX(IF(AND(Piezas!$F$13<=Datos!$B$34,Piezas!$F$13<=Datos!$B$36,B19<=Datos!$B$33,OR(Piezas!$G$13<=Datos!$B$37,AND(INT(B19/Piezas!$G$13)=1,B19-Piezas!$G$13<=Datos!$B$37))),INT(C19/Piezas!$F$13)*INT(B19/Piezas!$G$13),0),IF(AND(Piezas!$G$13<=Datos!$B$34,Piezas!$G$13<=Datos!$B$36,B19<=Datos!$B$33,OR(Piezas!$F$13<=Datos!$B$37,AND(INT(B19/Piezas!$F$13)=1,B19-Piezas!$F$13<=Datos!$B$37))),INT(C19/Piezas!$G$13)*INT(B19/Piezas!$F$13),0)) -> 3 | I19: =IF(H19=0,0,H19*Piezas!$F$13*Piezas!$G$13/(B19*C19)) -> 0.7263 | J19: =B19*C19*D19*Datos!$B$10/1000000 -> 168.22125 | K19: =IF(H19=0,0,J19/H19) -> 56.07375 | L19: =IF(H19=0,0,K19*F19) -> 61.175191 | M19: =IF(L19=MIN($L$19:$L$20),"Sí","") -> Sí | N19: =IF(AND(B19=Corte!$B$13,C19=Corte!$C$13,F19=INDEX(Datos!$C$95:$C$100,MATCH(Piezas!$E$13,Datos!$A$95:$A$100,0))),"Sí","") -> Sí
A20: 100 kg | B20: 1500 | C20: 3000 | D20: =Piezas!$E$13 -> 4.75 | E20: Q18 | F20: =Datos!$G$83 -> 1.1678 | G20: =IF(IF(AND(Piezas!$F$13<=Datos!$B$34,Piezas!$F$13<=Datos!$B$36,B20<=Datos!$B$33,OR(Piezas!$G$13<=Datos!$B$37,AND(INT(B20/Piezas!$G$13)=1,B20-Piezas!$G$13<=Datos!$B$37))),INT(C20/Piezas!$F$13)*INT(B20/Piezas!$G$13),0)>=IF(AND(Piezas!$G$13<=Datos!$B$34,Piezas!$G$13<=Datos!$B$36,B20<=Datos!$B$33,OR(Piezas!$F$13<=Datos!$B$37,AND(INT(B20/Piezas!$F$13)=1,B20-Piezas!$F$13<=Datos!$B$37))),INT(C20/Piezas!$G$13)*INT(B20/Piezas!$F$13),0),INT(C20/Piezas!$F$13)&" × "&INT(B20/Piezas!$G$13),INT(C20/Piezas!$G$13)&" × "&INT(B20/Piezas!$F$13)) -> 3 × 1 | H20: =MAX(IF(AND(Piezas!$F$13<=Datos!$B$34,Piezas!$F$13<=Datos!$B$36,B20<=Datos!$B$33,OR(Piezas!$G$13<=Datos!$B$37,AND(INT(B20/Piezas!$G$13)=1,B20-Piezas!$G$13<=Datos!$B$37))),INT(C20/Piezas!$F$13)*INT(B20/Piezas!$G$13),0),IF(AND(Piezas!$G$13<=Datos!$B$34,Piezas!$G$13<=Datos!$B$36,B20<=Datos!$B$33,OR(Piezas!$F$13<=Datos!$B$37,AND(INT(B20/Piezas!$F$13)=1,B20-Piezas!$F$13<=Datos!$B$37))),INT(C20/Piezas!$G$13)*INT(B20/Piezas!$F$13),0)) -> 3 | I20: =IF(H20=0,0,H20*Piezas!$F$13*Piezas!$G$13/(B20*C20)) -> 0.7263 | J20: =B20*C20*D20*Datos!$B$10/1000000 -> 168.22125 | K20: =IF(H20=0,0,J20/H20) -> 56.07375 | L20: =IF(H20=0,0,K20*F20) -> 65.482925 | M20: =IF(L20=MIN($L$19:$L$20),"Sí","") | N20: =IF(AND(B20=Corte!$B$13,C20=Corte!$C$13,F20=INDEX(Datos!$C$95:$C$100,MATCH(Piezas!$E$13,Datos!$A$95:$A$100,0))),"Sí","")
A21: Cotizaciones de la hoja Datos (sección 5). 25 y 50 kg y 70 y 100 kg se pueden combinar en la misma hoja: secciones B y C.
A23: B) 3,2 mm: 25 y 50 kg en la misma hoja de 1.500 × 3.000 (corte en tres etapas)
A24: En una franja de 995,5 mm (desarrollo del 50 kg) entran, a lo largo, una pieza de 50 kg (640) y un tramo de 858,5 que se corta a lo largo en dos piezas de 25 kg (493 + 493).
A25: Patrón | B25: Franjas | E25: 25 kg por hoja | F25: 50 kg por hoja | G25: Golpes G1 por hoja | H25: Golpes G2 por hoja | I25: Tandas de G2 por hoja | J25: Etapas | K25: Aprovech.
A26: P1 | B26: 3 franjas de 995,5: 1 de 50 kg (640) + 2 de 25 kg (tramo de 858,5 cortado en 493 + 493) | E26: 6 | F26: 3 | G26: 3 | H26: 6 | I26: 3 | J26: 3 | K26: =(E26*Piezas!$F$10*Piezas!$G$10+F26*Piezas!$F$11*Piezas!$G$11)/(Corte!$B$10*Corte!$C$10) -> 0.98906733
A27: P2 | B27: 2 franjas de 995,5 con 2 de 50 kg + 1 franja como P1 (= ⅓ P1 + ⅔ P3) | E27: 2 | F27: 5 | G27: 3 | H27: 4 | I27: 2 | J27: 3 | K27: =(E27*Piezas!$F$10*Piezas!$G$10+F27*Piezas!$F$11*Piezas!$G$11)/(Corte!$B$10*Corte!$C$10) -> 0.896018
A28: P3 | B28: 3 franjas de 995,5 con 2 de 50 kg | E28: 0 | F28: 6 | G28: 3 | H28: 3 | I28: 1.5 | J28: 2 | K28: =(E28*Piezas!$F$10*Piezas!$G$10+F28*Piezas!$F$11*Piezas!$G$11)/(Corte!$B$10*Corte!$C$10) -> 0.84949333
A29: P4 | B29: 3 franjas de 858,5 con 3 de 25 kg | E29: 9 | F29: 0 | G29: 3 | H29: 4.5 | I29: 1.5 | J29: 2 | K29: =(E29*Piezas!$F$10*Piezas!$G$10+F29*Piezas!$F$11*Piezas!$G$11)/(Corte!$B$10*Corte!$C$10) -> 0.846481
A30: Golpes de G2 en P1: cada tanda de 2 franjas lleva 2 golpes (pieza de 50 kg y tramo) y cada tanda de 2 tramos girados, 2 más (493 y el recorte). El plan usa P1, P3 y P4: P2 da las mismas hojas.
A32: Controles de P1 (con las medidas del plano)
A33: Control | B33: Medida (mm) | C33: Límite (mm) | E33: Resultado
A34: Dos piezas de 25 kg a lo ancho de la franja de 50 kg | B34: =2*Piezas!$F$10 -> 986 | C34: =Piezas!$G$11 -> 995.5 | E34: =IF(B34<=C34,"OK (sobran "&TEXT(C34-B34,"0.0")&" mm)","No entra") -> OK (sobran 9.5 mm)
A35: Pieza de 50 kg + tramo de 25 kg a lo largo de la franja | B35: =Piezas!$F$11+Piezas!$G$10 -> 1498.5 | C35: =Corte!$B$10 -> 1500 | E35: =IF(B35<=C35,"OK (sobran "&TEXT(C35-B35,"0.0")&" mm)","No entra") -> OK (sobran 1.5 mm)
A36: Tres franjas a lo largo de la hoja | B36: =3*Piezas!$G$11 -> 2986.5 | C36: =Corte!$C$10 -> 3000 | E36: =IF(B36<=C36,"OK (sobran "&TEXT(C36-B36,"0.0")&" mm)","No entra") -> OK (sobran 13.5 mm)
A37: Franja dentro del tope de G1 | B37: =Piezas!$G$11 -> 995.5 | C37: =Datos!$B$34 -> 1000 | E37: =IF(B37<=C37,"OK (sobran "&TEXT(C37-B37,"0.0")&" mm)","No entra") -> OK (sobran 4.5 mm)
A38: Corte a lo largo (493) dentro del tope de G2 | B38: =Piezas!$F$10 -> 493 | C38: =Datos!$B$37 -> 800 | E38: =IF(B38<=C38,"OK (sobran "&TEXT(C38-B38,"0.0")&" mm)","No entra") -> OK (sobran 307.0 mm)
A39: Sobran 1,5 mm a lo largo de la franja: la chapa laminada en caliente viene con tolerancia de ancho +0 (nunca más angosta), así que el recorte final siempre existe.
A41: Plan del año de referencia: cada formato en su hoja o combinados (mezcla de patrones)
A42: Concepto | B42: Separados (2 etapas) | C42: Combinados | D42: Diferencia
A43: Cuerpos de 25 kg | B43: =INDEX(Cálculo!$C$12:$L$12,Datos!$B$6-2025) -> 777.31053 | C43: =INDEX(Cálculo!$C$12:$L$12,Datos!$B$6-2025) -> 777.31053 | D43: =C43-B43 -> 0
A44: Cuerpos de 50 kg | B44: =INDEX(Cálculo!$C$13:$L$13,Datos!$B$6-2025) -> 1708.4352 | C44: =INDEX(Cálculo!$C$13:$L$13,Datos!$B$6-2025) -> 1708.4352 | D44: =C44-B44 -> 0
A45: Hojas de 3,2 mm | B45: =INDEX(Cálculo!$C$12:$L$12,Datos!$B$6-2025)/Corte!$I$10+INDEX(Cálculo!$C$13:$L$13,Datos!$B$6-2025)/Corte!$I$11 -> 371.10703 | C45: =INDEX(Cálculo!$C$50:$L$50,Datos!$B$6-2025)+INDEX(Cálculo!$C$51:$L$51,Datos!$B$6-2025)+INDEX(Cálculo!$C$52:$L$52,Datos!$B$6-2025) -> 349.51507 | D45: =C45-B45 -> -21.591959
A46: Acero (t) | B46: =B45*Corte!$W$10/1000 -> 42.056818 | C46: =C45*Corte!$W$10/1000 -> 39.609844 | D46: =C46-B46 -> -2.4469736
A47: Aprovechamiento | B47: =(INDEX(Cálculo!$C$12:$L$12,Datos!$B$6-2025)*Piezas!$F$10*Piezas!$G$10+INDEX(Cálculo!$C$13:$L$13,Datos!$B$6-2025)*Piezas!$F$11*Piezas!$G$11)/(B45*Corte!$B$10*Corte!$C$10) -> 0.84879227 | C47: =(INDEX(Cálculo!$C$12:$L$12,Datos!$B$6-2025)*Piezas!$F$10*Piezas!$G$10+INDEX(Cálculo!$C$13:$L$13,Datos!$B$6-2025)*Piezas!$F$11*Piezas!$G$11)/(C45*Corte!$B$10*Corte!$C$10) -> 0.90122803 | D47: =C47-B47 -> 0.052435759
A48: Costo del acero (USD) | B48: =B46*1000*INDEX(Datos!$C$95:$C$100,MATCH(Piezas!$E$10,Datos!$A$95:$A$100,0)) -> 46343.891 | C48: =C46*1000*INDEX(Datos!$C$95:$C$100,MATCH(Piezas!$E$10,Datos!$A$95:$A$100,0)) -> 43647.485 | D48: =C48-B48 -> -2696.4065
A49: Combinar conviene | B49: =IF(C46<B46,"Sí: ahorra "&TEXT(B45-C45,"0")&" hojas y USD "&TEXT(B48-C48,"#,##0")&" en el año","No") -> Sí: ahorra 22 hojas y USD 2,696 en el año
A50: Plan: P1 hasta cubrir el 25 kg (o el 50 kg, si es menos de la mitad) y el resto en P3 o P4. Es el mínimo de hojas (Word «Esquema de corte en guillotina», 5.2).
A51: Promedio por hoja de 3,2 mm con el plan elegido (va a Corte, tabla para los Aprovechamientos)
A52: Piezas por hoja | B52: =IF((INDEX(Cálculo!$C$50:$L$50,Datos!$B$6-2025)+INDEX(Cálculo!$C$51:$L$51,Datos!$B$6-2025)+INDEX(Cálculo!$C$52:$L$52,Datos!$B$6-2025))=0,0,(INDEX(Cálculo!$C$12:$L$12,Datos!$B$6-2025)+INDEX(Cálculo!$C$13:$L$13,Datos!$B$6-2025))/(INDEX(Cálculo!$C$50:$L$50,Datos!$B$6-2025)+INDEX(Cálculo!$C$51:$L$51,Datos!$B$6-2025)+INDEX(Cálculo!$C$52:$L$52,Datos!$B$6-2025))) -> 7.1119843
A53: Golpes G1 por hoja | B53: =IF((INDEX(Cálculo!$C$50:$L$50,Datos!$B$6-2025)+INDEX(Cálculo!$C$51:$L$51,Datos!$B$6-2025)+INDEX(Cálculo!$C$52:$L$52,Datos!$B$6-2025))=0,0,(INDEX(Cálculo!$C$50:$L$50,Datos!$B$6-2025)*G26+INDEX(Cálculo!$C$51:$L$51,Datos!$B$6-2025)*G28+INDEX(Cálculo!$C$52:$L$52,Datos!$B$6-2025)*G29)/(INDEX(Cálculo!$C$50:$L$50,Datos!$B$6-2025)+INDEX(Cálculo!$C$51:$L$51,Datos!$B$6-2025)+INDEX(Cálculo!$C$52:$L$52,Datos!$B$6-2025))) -> 3
A54: Golpes G2 por hoja | B54: =IF((INDEX(Cálculo!$C$50:$L$50,Datos!$B$6-2025)+INDEX(Cálculo!$C$51:$L$51,Datos!$B$6-2025)+INDEX(Cálculo!$C$52:$L$52,Datos!$B$6-2025))=0,0,(INDEX(Cálculo!$C$50:$L$50,Datos!$B$6-2025)*H26+INDEX(Cálculo!$C$51:$L$51,Datos!$B$6-2025)*H28+INDEX(Cálculo!$C$52:$L$52,Datos!$B$6-2025)*H29)/(INDEX(Cálculo!$C$50:$L$50,Datos!$B$6-2025)+INDEX(Cálculo!$C$51:$L$51,Datos!$B$6-2025)+INDEX(Cálculo!$C$52:$L$52,Datos!$B$6-2025))) -> 4.1119843
A55: Tandas de G2 por hoja | B55: =IF((INDEX(Cálculo!$C$50:$L$50,Datos!$B$6-2025)+INDEX(Cálculo!$C$51:$L$51,Datos!$B$6-2025)+INDEX(Cálculo!$C$52:$L$52,Datos!$B$6-2025))=0,0,(INDEX(Cálculo!$C$50:$L$50,Datos!$B$6-2025)*I26+INDEX(Cálculo!$C$51:$L$51,Datos!$B$6-2025)*I28+INDEX(Cálculo!$C$52:$L$52,Datos!$B$6-2025)*I29)/(INDEX(Cálculo!$C$50:$L$50,Datos!$B$6-2025)+INDEX(Cálculo!$C$51:$L$51,Datos!$B$6-2025)+INDEX(Cálculo!$C$52:$L$52,Datos!$B$6-2025))) -> 2.0559921
A57: C) 4,75 mm: 70 y 100 kg en la hoja de 1.500 × 3.000
A58: Patrón | B58: 70 kg por hoja | C58: 100 kg por hoja | E58: Aprovech.
A59: 3 de 70 kg + 1 de 100 kg (hoja mixta) | B59: 3 | C59: 1 | E59: =(B59*Piezas!$F$12*Piezas!$G$12+C59*Piezas!$F$13*Piezas!$G$13)/(Corte!$B$13*Corte!$C$13) -> 0.79086
A60: 4 de 70 kg | B60: 4 | C60: 0 | E60: =(B60*Piezas!$F$12*Piezas!$G$12+C60*Piezas!$F$13*Piezas!$G$13)/(Corte!$B$13*Corte!$C$13) -> 0.73168
A61: 3 de 100 kg | B61: 0 | C61: 3 | E61: =(B61*Piezas!$F$12*Piezas!$G$12+C61*Piezas!$F$13*Piezas!$G$13)/(Corte!$B$13*Corte!$C$13) -> 0.7263
A62: 1 de 70 kg + 2 de 100 kg | B62: 1 | C62: 2 | E62: =(B62*Piezas!$F$12*Piezas!$G$12+C62*Piezas!$F$13*Piezas!$G$13)/(Corte!$B$13*Corte!$C$13) -> 0.66712
A63: La mezcla óptima es la del plan actual: hojas mixtas hasta agotar los 70 kg y el resto de 100 kg solos (77,5 % en 2035).
A65: D) Discos: fleje de una fila o de dos filas al tresbolillo (detalle en Corte, sección C)
A66: Pieza | B66: Ancho 1 fila (mm) | C66: Aprovech. 1 fila | D66: Ancho 2 filas (mm) | E66: Aprovech. 2 filas | F66: kg de fleje por año, 1 fila | G66: kg, 2 filas | H66: Ahorro (kg)
A67: =Corte!A44 -> Cúpula 1 kg | B67: =Corte!$T$44 -> 93.05 | C67: =Corte!$U$44 -> 0.73628922 | D67: =Corte!$V$44 -> 171.2954 | E67: =Corte!$W$44 -> 0.79992473 | F67: =INDEX(Cálculo!$C$16:$L$16,Datos!$B$6-2025)*Corte!$X$44 -> 12126.134 | G67: =INDEX(Cálculo!$C$16:$L$16,Datos!$B$6-2025)*Corte!$Y$44 -> 11161.478 | H67: =F67-G67 -> 964.65678
A68: =Corte!A45 -> Fondo 1 kg | B68: =Corte!$T$45 -> 100.625 | C68: =Corte!$U$45 -> 0.72350671 | D68: =Corte!$V$45 -> 184.52121 | E68: =Corte!$W$45 -> 0.78910021 | F68: =INDEX(Cálculo!$C$17:$L$17,Datos!$B$6-2025)*Corte!$X$45 -> 19528.233 | G68: =INDEX(Cálculo!$C$17:$L$17,Datos!$B$6-2025)*Corte!$Y$45 -> 17904.96 | H68: =F68-G68 -> 1623.273
A69: =Corte!A46 -> Cúpula 2,5 kg | B69: =Corte!$T$46 -> 162.125 | C69: =Corte!$U$46 -> 0.74542684 | D69: =Corte!$V$46 -> 299.28177 | E69: =Corte!$W$46 -> 0.80761569 | F69: =INDEX(Cálculo!$C$18:$L$18,Datos!$B$6-2025)*Corte!$X$46 -> 3586.1454 | G69: =INDEX(Cálculo!$C$18:$L$18,Datos!$B$6-2025)*Corte!$Y$46 -> 3310.0014 | H69: =F69-G69 -> 276.14399
A70: =Corte!A47 -> Fondo 2,5 kg | B70: =Corte!$T$47 -> 146.125 | C70: =Corte!$U$47 -> 0.7414935 | D70: =Corte!$V$47 -> 269.42537 | E70: =Corte!$W$47 -> 0.80430985 | F70: =INDEX(Cálculo!$C$19:$L$19,Datos!$B$6-2025)*Corte!$X$47 -> 2905.6917 | G70: =INDEX(Cálculo!$C$19:$L$19,Datos!$B$6-2025)*Corte!$Y$47 -> 2678.7581 | H70: =F70-G70 -> 226.93361
A71: =Corte!A48 -> Cúpula 5 kg | B71: =Corte!$T$48 -> 204.2 | C71: =Corte!$U$48 -> 0.74484263 | D71: =Corte!$V$48 -> 376.88547 | E71: =Corte!$W$48 -> 0.80712513 | F71: =INDEX(Cálculo!$C$20:$L$20,Datos!$B$6-2025)*Corte!$X$48 -> 32902.698 | G71: =INDEX(Cálculo!$C$20:$L$20,Datos!$B$6-2025)*Corte!$Y$48 -> 30363.733 | H71: =F71-G71 -> 2538.9648
A72: =Corte!A49 -> Fondo 5 kg | B72: =Corte!$T$49 -> 177.2 | C72: =Corte!$U$49 -> 0.73928148 | D72: =Corte!$V$49 -> 326.50278 | E72: =Corte!$W$49 -> 0.80244755 | F72: =INDEX(Cálculo!$C$21:$L$21,Datos!$B$6-2025)*Corte!$X$49 -> 24686.05 | G72: =INDEX(Cálculo!$C$21:$L$21,Datos!$B$6-2025)*Corte!$Y$49 -> 22742.844 | H72: =F72-G72 -> 1943.2059
A73: =Corte!A50 -> Cúpula 10 kg | B73: =Corte!$T$50 -> 238.7 | C73: =Corte!$U$50 -> 0.75012271 | D73: =Corte!$V$50 -> 441.26334 | E73: =Corte!$W$50 -> 0.81155298 | F73: =INDEX(Cálculo!$C$22:$L$22,Datos!$B$6-2025)*Corte!$X$50 -> 2729.4233 | G73: =INDEX(Cálculo!$C$22:$L$22,Datos!$B$6-2025)*Corte!$Y$50 -> 2522.8204 | H73: =F73-G73 -> 206.60293
A74: =Corte!A51 -> Fondo 10 kg | B74: =Corte!$T$51 -> 205 | C74: =Corte!$U$51 -> 0.73589892 | D74: =Corte!$V$51 -> 377.33906 | E74: =Corte!$W$51 -> 0.79959536 | F74: =INDEX(Cálculo!$C$23:$L$23,Datos!$B$6-2025)*Corte!$X$51 -> 2492.902 | G74: =INDEX(Cálculo!$C$23:$L$23,Datos!$B$6-2025)*Corte!$Y$51 -> 2294.3153 | H74: =F74-G74 -> 198.58667
A75: Total | F75: =SUM(F67:F74) -> 100957.28 | G75: =SUM(G67:G74) -> 92978.91 | H75: =SUM(H67:H74) -> 7978.3677
A76: Dos filas al tresbolillo: centros de una fila corridos medio paso y separados paso × √3/2, así entre discos de filas vecinas queda el mismo puente de avance.

Sheet Cálculo
A1: Cálculo año por año de cada alternativa
A2: No se edita: sale de Datos, Demanda, Piezas y Corte. Los costos van en USD sin IVA.
A4: Concepto | B4: Unidad | C4: 2026 | D4: 2027 | E4: 2028 | F4: 2029 | G4: 2030 | H4: 2031 | I4: 2032 | J4: 2033 | K4: 2034 | L4: 2035
A5: Período k (para descontar) | C5: 1 | D5: 2 | E5: 3 | F5: 4 | G5: 5 | H5: 6 | I5: 7 | J5: 8 | K5: 9 | L5: 10
A6: Factor de descuento 1/(1+i)^k | C6: =1/(1+Datos!$B$7)^C5 -> 0.89285714 | D6: =1/(1+Datos!$B$7)^D5 -> 0.79719388 | E6: =1/(1+Datos!$B$7)^E5 -> 0.71178025 | F6: =1/(1+Datos!$B$7)^F5 -> 0.63551808 | G6: =1/(1+Datos!$B$7)^G5 -> 0.56742686 | H6: =1/(1+Datos!$B$7)^H5 -> 0.50663112 | I6: =1/(1+Datos!$B$7)^I5 -> 0.45234922 | J6: =1/(1+Datos!$B$7)^J5 -> 0.40388323 | ... L6: =1/(1+Datos!$B$7)^L5 -> 0.32197324
A7: Unidades a fabricar (cuerpos)
A8: 1 kg | B8: u | C8: =Demanda!C6 -> 4178.7365 | D8: =Demanda!D6 -> 5997.304 | E8: =Demanda!E6 -> 14514.148 | F8: =Demanda!F6 -> 35161.936 | G8: =Demanda!G6 -> 62115.433 | H8: =Demanda!H6 -> 87300.453 | I8: =Demanda!I6 -> 121673.15 | J8: =Demanda!J6 -> 156133.08 | ... L8: =Demanda!L6 -> 202620.64
A9: 2,5 kg | B9: u | C9: =Demanda!C7 -> 300.03036 | D9: =Demanda!D7 -> 724.12745 | E9: =Demanda!E7 -> 1309.9881 | F9: =Demanda!F7 -> 2581.7182 | G9: =Demanda!G7 -> 4284.6277 | H9: =Demanda!H7 -> 6099.5099 | I9: =Demanda!I7 -> 8105.7555 | J9: =Demanda!J7 -> 10259.067 | ... L9: =Demanda!L7 -> 14126.338
A10: 5 kg | B10: u | C10: =Demanda!C8 -> 2281.773 | D10: =Demanda!D8 -> 3928.0589 | E10: =Demanda!E8 -> 6711.7376 | F10: =Demanda!F8 -> 12203.995 | G10: =Demanda!G8 -> 20592.787 | H10: =Demanda!H8 -> 28701.604 | I10: =Demanda!I8 -> 38664.6 | J10: =Demanda!J8 -> 48842.226 | ... L10: =Demanda!L8 -> 63852.659
A11: 10 kg | B11: u | C11: =Demanda!C9 -> 94.833182 | D11: =Demanda!D9 -> 182.4873 | E11: =Demanda!E9 -> 352.01878 | F11: =Demanda!F9 -> 687.30049 | G11: =Demanda!G9 -> 1200.4382 | H11: =Demanda!H9 -> 1735.685 | I11: =Demanda!I9 -> 2335.9605 | J11: =Demanda!J9 -> 2951.5648 | ... L11: =Demanda!L9 -> 3862.9281
A12: 25 kg | B12: u | C12: =Demanda!C10 -> 36.051791 | D12: =Demanda!D10 -> 58.622147 | E12: =Demanda!E10 -> 90.76854 | F12: =Demanda!F10 -> 152.96985 | G12: =Demanda!G10 -> 252.276 | H12: =Demanda!H10 -> 349.57448 | I12: =Demanda!I10 -> 465.46823 | J12: =Demanda!J10 -> 586.72867 | ... L12: =Demanda!L10 -> 777.31053
A13: 50 kg | B13: u | C13: =Demanda!C11 -> 76.913941 | D13: =Demanda!D11 -> 129.77672 | E13: =Demanda!E11 -> 200.49879 | F13: =Demanda!F11 -> 337.44568 | G13: =Demanda!G11 -> 554.00721 | H13: =Demanda!H11 -> 769.13586 | I13: =Demanda!I11 -> 1025.2701 | J13: =Demanda!J11 -> 1292.1071 | ... L13: =Demanda!L11 -> 1708.4352
A14: 70 kg | B14: u | C14: =Demanda!C12 -> 18.34486 | D14: =Demanda!D12 -> 28.221831 | E14: =Demanda!E12 -> 43.260099 | F14: =Demanda!F12 -> 73.814329 | G14: =Demanda!G12 -> 122.26048 | H14: =Demanda!H12 -> 167.52855 | I14: =Demanda!I12 -> 224.48075 | J14: =Demanda!J12 -> 281.64736 | ... L14: =Demanda!L12 -> 374.12986
A15: 100 kg | B15: u | C15: =Demanda!C13 -> 12.896573 | D15: =Demanda!D13 -> 18.867887 | E15: =Demanda!E13 -> 28.826733 | F15: =Demanda!F13 -> 48.329553 | G15: =Demanda!G13 -> 80.640321 | H15: =Demanda!H13 -> 110.85903 | I15: =Demanda!I13 -> 149.89383 | J15: =Demanda!J13 -> 186.51157 | ... L15: =Demanda!L13 -> 247.44657
A16: Cúpula 1 kg | B16: u | C16: =C8 -> 4178.7365 | D16: =D8 -> 5997.304 | E16: =E8 -> 14514.148 | F16: =F8 -> 35161.936 | G16: =G8 -> 62115.433 | H16: =H8 -> 87300.453 | I16: =I8 -> 121673.15 | J16: =J8 -> 156133.08 | ... L16: =L8 -> 202620.64
A17: Fondo 1 kg | B17: u | C17: =C8 -> 4178.7365 | D17: =D8 -> 5997.304 | E17: =E8 -> 14514.148 | F17: =F8 -> 35161.936 | G17: =G8 -> 62115.433 | H17: =H8 -> 87300.453 | I17: =I8 -> 121673.15 | J17: =J8 -> 156133.08 | ... L17: =L8 -> 202620.64
A18: Cúpula 2,5 kg | B18: u | C18: =C9 -> 300.03036 | D18: =D9 -> 724.12745 | E18: =E9 -> 1309.9881 | F18: =F9 -> 2581.7182 | G18: =G9 -> 4284.6277 | H18: =H9 -> 6099.5099 | I18: =I9 -> 8105.7555 | J18: =J9 -> 10259.067 | ... L18: =L9 -> 14126.338
A19: Fondo 2,5 kg | B19: u | C19: =C9 -> 300.03036 | D19: =D9 -> 724.12745 | E19: =E9 -> 1309.9881 | F19: =F9 -> 2581.7182 | G19: =G9 -> 4284.6277 | H19: =H9 -> 6099.5099 | I19: =I9 -> 8105.7555 | J19: =J9 -> 10259.067 | ... L19: =L9 -> 14126.338
A20: Cúpula 5 kg | B20: u | C20: =C10 -> 2281.773 | D20: =D10 -> 3928.0589 | E20: =E10 -> 6711.7376 | F20: =F10 -> 12203.995 | G20: =G10 -> 20592.787 | H20: =H10 -> 28701.604 | I20: =I10 -> 38664.6 | J20: =J10 -> 48842.226 | ... L20: =L10 -> 63852.659
A21: Fondo 5 kg | B21: u | C21: =C10 -> 2281.773 | D21: =D10 -> 3928.0589 | E21: =E10 -> 6711.7376 | F21: =F10 -> 12203.995 | G21: =G10 -> 20592.787 | H21: =H10 -> 28701.604 | I21: =I10 -> 38664.6 | J21: =J10 -> 48842.226 | ... L21: =L10 -> 63852.659
A22: Cúpula 10 kg | B22: u | C22: =C11 -> 94.833182 | D22: =D11 -> 182.4873 | E22: =E11 -> 352.01878 | F22: =F11 -> 687.30049 | G22: =G11 -> 1200.4382 | H22: =H11 -> 1735.685 | I22: =I11 -> 2335.9605 | J22: =J11 -> 2951.5648 | ... L22: =L11 -> 3862.9281
A23: Fondo 10 kg | B23: u | C23: =C11 -> 94.833182 | D23: =D11 -> 182.4873 | E23: =E11 -> 352.01878 | F23: =F11 -> 687.30049 | G23: =G11 -> 1200.4382 | H23: =H11 -> 1735.685 | I23: =I11 -> 2335.9605 | J23: =J11 -> 2951.5648 | ... L23: =L11 -> 3862.9281
A25: Acero neto en piezas (cuerpos + cúpulas + fondos) | B25: t | C25: =(SUMPRODUCT(C$8:C$15,Piezas!$H$6:$H$13)+SUMPRODUCT(C$16:C$23,Piezas!$S$18:$S$25))/1000 -> 11.947608 | D25: =(SUMPRODUCT(D$8:D$15,Piezas!$H$6:$H$13)+SUMPRODUCT(D$16:D$23,Piezas!$S$18:$S$25))/1000 -> 19.97062 | E25: =(SUMPRODUCT(E$8:E$15,Piezas!$H$6:$H$13)+SUMPRODUCT(E$16:E$23,Piezas!$S$18:$S$25))/1000 -> 36.07425 | F25: =(SUMPRODUCT(F$8:F$15,Piezas!$H$6:$H$13)+SUMPRODUCT(F$16:F$23,Piezas!$S$18:$S$25))/1000 -> 70.109108 | G25: =(SUMPRODUCT(G$8:G$15,Piezas!$H$6:$H$13)+SUMPRODUCT(G$16:G$23,Piezas!$S$18:$S$25))/1000 -> 119.55126 | H25: =(SUMPRODUCT(H$8:H$15,Piezas!$H$6:$H$13)+SUMPRODUCT(H$16:H$23,Piezas!$S$18:$S$25))/1000 -> 167.31854 | I25: =(SUMPRODUCT(I$8:I$15,Piezas!$H$6:$H$13)+SUMPRODUCT(I$16:I$23,Piezas!$S$18:$S$25))/1000 -> 227.24842 | J25: =(SUMPRODUCT(J$8:J$15,Piezas!$H$6:$H$13)+SUMPRODUCT(J$16:J$23,Piezas!$S$18:$S$25))/1000 -> 288.21034 | ... L25: =(SUMPRODUCT(L$8:L$15,Piezas!$H$6:$H$13)+SUMPRODUCT(L$16:L$23,Piezas!$S$18:$S$25))/1000 -> 377.69342
A27: A — Bobina por formato para cuerpos + fleje a medida para discos
A28: Acero de bobina para cuerpos | B28: t | C28: =SUMPRODUCT(C$8:C$15,Corte!$F$32:$F$39)/1000 -> 10.206776 | D28: =SUMPRODUCT(D$8:D$15,Corte!$F$32:$F$39)/1000 -> 16.998205 | E28: =SUMPRODUCT(E$8:E$15,Corte!$F$32:$F$39)/1000 -> 30.449574 | F28: =SUMPRODUCT(F$8:F$15,Corte!$F$32:$F$39)/1000 -> 58.836498 | G28: =SUMPRODUCT(G$8:G$15,Corte!$F$32:$F$39)/1000 -> 100.19256 | H28: =SUMPRODUCT(H$8:H$15,Corte!$F$32:$F$39)/1000 -> 140.15864 | I28: =SUMPRODUCT(I$8:I$15,Corte!$F$32:$F$39)/1000 -> 190.26461 | J28: =SUMPRODUCT(J$8:J$15,Corte!$F$32:$F$39)/1000 -> 241.23321 | ... L28: =SUMPRODUCT(L$8:L$15,Corte!$F$32:$F$39)/1000 -> 316.28852
A29: Costo de la bobina para cuerpos | B29: USD | C29: =SUMPRODUCT(C$8:C$15,Corte!$G$32:$G$39) -> 12386.289 | D29: =SUMPRODUCT(D$8:D$15,Corte!$G$32:$G$39) -> 20646.788 | E29: =SUMPRODUCT(E$8:E$15,Corte!$G$32:$G$39) -> 37172.262 | F29: =SUMPRODUCT(F$8:F$15,Corte!$G$32:$G$39) -> 72114.443 | G29: =SUMPRODUCT(G$8:G$15,Corte!$G$32:$G$39) -> 122907.86 | H29: =SUMPRODUCT(H$8:H$15,Corte!$G$32:$G$39) -> 171986.87 | I29: =SUMPRODUCT(I$8:I$15,Corte!$G$32:$G$39) -> 233566.34 | J29: =SUMPRODUCT(J$8:J$15,Corte!$G$32:$G$39) -> 296203.25 | ... L29: =SUMPRODUCT(L$8:L$15,Corte!$G$32:$G$39) -> 388262.55
A30: Acero de fleje para discos | B30: t | C30: =SUMPRODUCT(C$16:C$23,Corte!$I$44:$I$51)/1000 -> 2.976841 | D30: =SUMPRODUCT(D$16:D$23,Corte!$I$44:$I$51)/1000 -> 5.0591289 | E30: =SUMPRODUCT(E$16:E$23,Corte!$I$44:$I$51)/1000 -> 9.398699 | F30: =SUMPRODUCT(F$16:F$23,Corte!$I$44:$I$51)/1000 -> 18.615566 | G30: =SUMPRODUCT(G$16:G$23,Corte!$I$44:$I$51)/1000 -> 31.868523 | H30: =SUMPRODUCT(H$16:H$23,Corte!$I$44:$I$51)/1000 -> 44.674039 | I30: =SUMPRODUCT(I$16:I$23,Corte!$I$44:$I$51)/1000 -> 60.763037 | J30: =SUMPRODUCT(J$16:J$23,Corte!$I$44:$I$51)/1000 -> 77.147545 | ... L30: =SUMPRODUCT(L$16:L$23,Corte!$I$44:$I$51)/1000 -> 100.95728
A31: Costo del fleje para discos | B31: USD | C31: =SUMPRODUCT(C$16:C$23,Corte!$J$44:$J$51) -> 3550.4867 | D31: =SUMPRODUCT(D$16:D$23,Corte!$J$44:$J$51) -> 6029.1229 | E31: =SUMPRODUCT(E$16:E$23,Corte!$J$44:$J$51) -> 11216.337 | F31: =SUMPRODUCT(F$16:F$23,Corte!$J$44:$J$51) -> 22245.101 | G31: =SUMPRODUCT(G$16:G$23,Corte!$J$44:$J$51) -> 38091.047 | H31: =SUMPRODUCT(H$16:H$23,Corte!$J$44:$J$51) -> 53398.364 | I31: =SUMPRODUCT(I$16:I$23,Corte!$J$44:$J$51) -> 72642.651 | J31: =SUMPRODUCT(J$16:J$23,Corte!$J$44:$J$51) -> 92237.933 | ... L31: =SUMPRODUCT(L$16:L$23,Corte!$J$44:$J$51) -> 120697.14
A32: Acero comprado | B32: t | C32: =C28+C30 -> 13.183617 | D32: =D28+D30 -> 22.057334 | E32: =E28+E30 -> 39.848273 | F32: =F28+F30 -> 77.452064 | G32: =G28+G30 -> 132.06108 | H32: =H28+H30 -> 184.83268 | I32: =I28+I30 -> 251.02765 | J32: =J28+J30 -> 318.38075 | ... L32: =L28+L30 -> 417.2458
A33: Costo del acero | B33: USD | C33: =C29+C31 -> 15936.776 | D33: =D29+D31 -> 26675.911 | E33: =E29+E31 -> 48388.598 | F33: =F29+F31 -> 94359.544 | G33: =G29+G31 -> 160998.91 | H33: =H29+H31 -> 225385.23 | I33: =I29+I31 -> 306208.99 | J33: =J29+J31 -> 388441.18 | ... L33: =L29+L31 -> 508959.69
A34: Scrap | B34: t | C34: =C32-C25 -> 1.236009 | D34: =D32-D25 -> 2.0867133 | E34: =E32-E25 -> 3.7740231 | F34: =F32-F25 -> 7.3429558 | G34: =G32-G25 -> 12.509825 | H34: =H32-H25 -> 17.514145 | I34: =I32-I25 -> 23.779234 | J34: =J32-J25 -> 30.170407 | ... L34: =L32-L25 -> 39.552379
A35: Venta de scrap (resta) | B35: USD | C35: =-C34*Datos!$B$9 -> -309.00226 | D35: =-D34*Datos!$B$9 -> -521.67833 | E35: =-E34*Datos!$B$9 -> -943.50578 | F35: =-F34*Datos!$B$9 -> -1835.739 | G35: =-G34*Datos!$B$9 -> -3127.4563 | H35: =-H34*Datos!$B$9 -> -4378.5363 | I35: =-I34*Datos!$B$9 -> -5944.8086 | J35: =-J34*Datos!$B$9 -> -7542.6016 | ... L35: =-L34*Datos!$B$9 -> -9888.0946
A36: Stock de bobinas de cuerpo | B36: t | C36: =SUMPRODUCT((Corte!$H$32:$H$39+C$8:C$15*Corte!$F$32:$F$39/1000*Datos!$B$53/12-ABS(Corte!$H$32:$H$39-C$8:C$15*Corte!$F$32:$F$39/1000*Datos!$B$53/12))/4+C$8:C$15*Corte!$F$32:$F$39/1000*Datos!$B$50/52) -> 1.6684153 | D36: =SUMPRODUCT((Corte!$H$32:$H$39+D$8:D$15*Corte!$F$32:$F$39/1000*Datos!$B$53/12-ABS(Corte!$H$32:$H$39-D$8:D$15*Corte!$F$32:$F$39/1000*Datos!$B$53/12))/4+D$8:D$15*Corte!$F$32:$F$39/1000*Datos!$B$50/52) -> 2.7785527 | E36: =SUMPRODUCT((Corte!$H$32:$H$39+E$8:E$15*Corte!$F$32:$F$39/1000*Datos!$B$53/12-ABS(Corte!$H$32:$H$39-E$8:E$15*Corte!$F$32:$F$39/1000*Datos!$B$53/12))/4+E$8:E$15*Corte!$F$32:$F$39/1000*Datos!$B$50/52) -> 4.9773342 | F36: =SUMPRODUCT((Corte!$H$32:$H$39+F$8:F$15*Corte!$F$32:$F$39/1000*Datos!$B$53/12-ABS(Corte!$H$32:$H$39-F$8:F$15*Corte!$F$32:$F$39/1000*Datos!$B$53/12))/4+F$8:F$15*Corte!$F$32:$F$39/1000*Datos!$B$50/52) -> 9.6175045 | G36: =SUMPRODUCT((Corte!$H$32:$H$39+G$8:G$15*Corte!$F$32:$F$39/1000*Datos!$B$53/12-ABS(Corte!$H$32:$H$39-G$8:G$15*Corte!$F$32:$F$39/1000*Datos!$B$53/12))/4+G$8:G$15*Corte!$F$32:$F$39/1000*Datos!$B$50/52) -> 16.214346 | H36: =SUMPRODUCT((Corte!$H$32:$H$39+H$8:H$15*Corte!$F$32:$F$39/1000*Datos!$B$53/12-ABS(Corte!$H$32:$H$39-H$8:H$15*Corte!$F$32:$F$39/1000*Datos!$B$53/12))/4+H$8:H$15*Corte!$F$32:$F$39/1000*Datos!$B$50/52) -> 18.865463 | I36: =SUMPRODUCT((Corte!$H$32:$H$39+I$8:I$15*Corte!$F$32:$F$39/1000*Datos!$B$53/12-ABS(Corte!$H$32:$H$39-I$8:I$15*Corte!$F$32:$F$39/1000*Datos!$B$53/12))/4+I$8:I$15*Corte!$F$32:$F$39/1000*Datos!$B$50/52) -> 20.81787 | J36: =SUMPRODUCT((Corte!$H$32:$H$39+J$8:J$15*Corte!$F$32:$F$39/1000*Datos!$B$53/12-ABS(Corte!$H$32:$H$39-J$8:J$15*Corte!$F$32:$F$39/1000*Datos!$B$53/12))/4+J$8:J$15*Corte!$F$32:$F$39/1000*Datos!$B$50/52) -> 22.7782 | ... L36: =SUMPRODUCT((Corte!$H$32:$H$39+L$8:L$15*Corte!$F$32:$F$39/1000*Datos!$B$53/12-ABS(Corte!$H$32:$H$39-L$8:L$15*Corte!$F$32:$F$39/1000*Datos!$B$53/12))/4+L$8:L$15*Corte!$F$32:$F$39/1000*Datos!$B$50/52) -> 25.664943
A37: Stock de rollos de fleje | B37: t | C37: =SUMPRODUCT((Corte!$K$44:$K$51+C$16:C$23*Corte!$I$44:$I$51/1000*Datos!$B$53/12-ABS(Corte!$K$44:$K$51-C$16:C$23*Corte!$I$44:$I$51/1000*Datos!$B$53/12))/4+C$16:C$23*Corte!$I$44:$I$51/1000*Datos!$B$50/52) -> 0.48659901 | D37: =SUMPRODUCT((Corte!$K$44:$K$51+D$16:D$23*Corte!$I$44:$I$51/1000*Datos!$B$53/12-ABS(Corte!$K$44:$K$51-D$16:D$23*Corte!$I$44:$I$51/1000*Datos!$B$53/12))/4+D$16:D$23*Corte!$I$44:$I$51/1000*Datos!$B$50/52) -> 0.826973 | E37: =SUMPRODUCT((Corte!$K$44:$K$51+E$16:E$23*Corte!$I$44:$I$51/1000*Datos!$B$53/12-ABS(Corte!$K$44:$K$51-E$16:E$23*Corte!$I$44:$I$51/1000*Datos!$B$53/12))/4+E$16:E$23*Corte!$I$44:$I$51/1000*Datos!$B$50/52) -> 1.5363258 | F37: =SUMPRODUCT((Corte!$K$44:$K$51+F$16:F$23*Corte!$I$44:$I$51/1000*Datos!$B$53/12-ABS(Corte!$K$44:$K$51-F$16:F$23*Corte!$I$44:$I$51/1000*Datos!$B$53/12))/4+F$16:F$23*Corte!$I$44:$I$51/1000*Datos!$B$50/52) -> 3.0429291 | G37: =SUMPRODUCT((Corte!$K$44:$K$51+G$16:G$23*Corte!$I$44:$I$51/1000*Datos!$B$53/12-ABS(Corte!$K$44:$K$51-G$16:G$23*Corte!$I$44:$I$51/1000*Datos!$B$53/12))/4+G$16:G$23*Corte!$I$44:$I$51/1000*Datos!$B$50/52) -> 4.8845457 | H37: =SUMPRODUCT((Corte!$K$44:$K$51+H$16:H$23*Corte!$I$44:$I$51/1000*Datos!$B$53/12-ABS(Corte!$K$44:$K$51-H$16:H$23*Corte!$I$44:$I$51/1000*Datos!$B$53/12))/4+H$16:H$23*Corte!$I$44:$I$51/1000*Datos!$B$50/52) -> 5.6119261 | I37: =SUMPRODUCT((Corte!$K$44:$K$51+I$16:I$23*Corte!$I$44:$I$51/1000*Datos!$B$53/12-ABS(Corte!$K$44:$K$51-I$16:I$23*Corte!$I$44:$I$51/1000*Datos!$B$53/12))/4+I$16:I$23*Corte!$I$44:$I$51/1000*Datos!$B$50/52) -> 6.4402028 | J37: =SUMPRODUCT((Corte!$K$44:$K$51+J$16:J$23*Corte!$I$44:$I$51/1000*Datos!$B$53/12-ABS(Corte!$K$44:$K$51-J$16:J$23*Corte!$I$44:$I$51/1000*Datos!$B$53/12))/4+J$16:J$23*Corte!$I$44:$I$51/1000*Datos!$B$50/52) -> 7.2053086 | ... L37: =SUMPRODUCT((Corte!$K$44:$K$51+L$16:L$23*Corte!$I$44:$I$51/1000*Datos!$B$53/12-ABS(Corte!$K$44:$K$51-L$16:L$23*Corte!$I$44:$I$51/1000*Datos!$B$53/12))/4+L$16:L$23*Corte!$I$44:$I$51/1000*Datos!$B$50/52) -> 8.1329722
A38: Stock promedio | B38: t | C38: =C36+C37 -> 2.1550143 | D38: =D36+D37 -> 3.6055257 | E38: =E36+E37 -> 6.51366 | F38: =F36+F37 -> 12.660434 | G38: =G36+G37 -> 21.098891 | H38: =H36+H37 -> 24.47739 | I38: =I36+I37 -> 27.258073 | J38: =J36+J37 -> 29.983509 | ... L38: =L36+L37 -> 33.797915
A39: Costo financiero del stock | B39: USD | C39: =IF(C32=0,0,C38*C33/C32*Datos!$B$7) -> 312.60599 | D39: =IF(D32=0,0,D38*D33/D32*Datos!$B$7) -> 523.25826 | E39: =IF(E32=0,0,E38*E33/E32*Datos!$B$7) -> 949.16097 | F39: =IF(F32=0,0,F38*F33/F32*Datos!$B$7) -> 1850.8987 | G39: =IF(G32=0,0,G38*G33/G32*Datos!$B$7) -> 3086.6612 | H39: =IF(H32=0,0,H38*H33/H32*Datos!$B$7) -> 3581.7315 | I39: =IF(I32=0,0,I38*I33/I32*Datos!$B$7) -> 3989.9988 | J39: =IF(J32=0,0,J38*J33/J32*Datos!$B$7) -> 4389.774 | ... L39: =IF(L32=0,0,L38*L33/L32*Datos!$B$7) -> 4947.2353
A40: Rollos de fleje por año | B40: rollos | C40: =SUMPRODUCT(C$16:C$23*Corte!$I$44:$I$51/1000/Corte!$K$44:$K$51) -> 2.0963835 | D40: =SUMPRODUCT(D$16:D$23*Corte!$I$44:$I$51/1000/Corte!$K$44:$K$51) -> 3.6648433 | E40: =SUMPRODUCT(E$16:E$23*Corte!$I$44:$I$51/1000/Corte!$K$44:$K$51) -> 7.1040988 | F40: =SUMPRODUCT(F$16:F$23*Corte!$I$44:$I$51/1000/Corte!$K$44:$K$51) -> 14.598921 | G40: =SUMPRODUCT(G$16:G$23*Corte!$I$44:$I$51/1000/Corte!$K$44:$K$51) -> 25.11298 | H40: =SUMPRODUCT(H$16:H$23*Corte!$I$44:$I$51/1000/Corte!$K$44:$K$51) -> 35.401626 | I40: =SUMPRODUCT(I$16:I$23*Corte!$I$44:$I$51/1000/Corte!$K$44:$K$51) -> 48.217923 | J40: =SUMPRODUCT(J$16:J$23*Corte!$I$44:$I$51/1000/Corte!$K$44:$K$51) -> 61.31019 | ... L40: =SUMPRODUCT(L$16:L$23*Corte!$I$44:$I$51/1000/Corte!$K$44:$K$51) -> 80.586796
A41: Horas-hombre de corte: línea + guillotina 1 + cambios de fleje | B41: h | C41: =SUMPRODUCT(C$8:C$15/Corte!$C$32:$C$39)/Datos!$B$41+SUM(C$8:C$15)/(Datos!$B$32*60)+C40*Datos!$B$46/60 -> 7.8783134 | D41: =SUMPRODUCT(D$8:D$15/Corte!$C$32:$C$39)/Datos!$B$41+SUM(D$8:D$15)/(Datos!$B$32*60)+D40*Datos!$B$46/60 -> 12.616559 | E41: =SUMPRODUCT(E$8:E$15/Corte!$C$32:$C$39)/Datos!$B$41+SUM(E$8:E$15)/(Datos!$B$32*60)+E40*Datos!$B$46/60 -> 26.114847 | F41: =SUMPRODUCT(F$8:F$15/Corte!$C$32:$C$39)/Datos!$B$41+SUM(F$8:F$15)/(Datos!$B$32*60)+F40*Datos!$B$46/60 -> 56.894709 | G41: =SUMPRODUCT(G$8:G$15/Corte!$C$32:$C$39)/Datos!$B$41+SUM(G$8:G$15)/(Datos!$B$32*60)+G40*Datos!$B$46/60 -> 98.846781 | H41: =SUMPRODUCT(H$8:H$15/Corte!$C$32:$C$39)/Datos!$B$41+SUM(H$8:H$15)/(Datos!$B$32*60)+H40*Datos!$B$46/60 -> 138.80219 | I41: =SUMPRODUCT(I$8:I$15/Corte!$C$32:$C$39)/Datos!$B$41+SUM(I$8:I$15)/(Datos!$B$32*60)+I40*Datos!$B$46/60 -> 191.03738 | J41: =SUMPRODUCT(J$8:J$15/Corte!$C$32:$C$39)/Datos!$B$41+SUM(J$8:J$15)/(Datos!$B$32*60)+J40*Datos!$B$46/60 -> 243.8655 | ... L41: =SUMPRODUCT(L$8:L$15/Corte!$C$32:$C$39)/Datos!$B$41+SUM(L$8:L$15)/(Datos!$B$32*60)+L40*Datos!$B$46/60 -> 318.27451
A42: Mano de obra de corte | B42: USD | C42: =C41*Datos!$B$15 -> 49.486238 | D42: =D41*Datos!$B$15 -> 79.248696 | E42: =E41*Datos!$B$15 -> 164.03581 | F42: =F41*Datos!$B$15 -> 357.3741 | G42: =G41*Datos!$B$15 -> 620.88865 | H42: =H41*Datos!$B$15 -> 871.86149 | I42: =I41*Datos!$B$15 -> 1199.9677 | J42: =J41*Datos!$B$15 -> 1531.7982 | ... L42: =L41*Datos!$B$15 -> 1999.1853
A43: Mantenimiento de equipos | B43: USD | C43: =Datos!$C$117*Datos!$B$8 -> 4824.1878 | D43: =Datos!$C$117*Datos!$B$8 -> 4824.1878 | E43: =Datos!$C$117*Datos!$B$8 -> 4824.1878 | F43: =Datos!$C$117*Datos!$B$8 -> 4824.1878 | G43: =Datos!$C$117*Datos!$B$8 -> 4824.1878 | H43: =Datos!$C$117*Datos!$B$8 -> 4824.1878 | I43: =Datos!$C$117*Datos!$B$8 -> 4824.1878 | J43: =Datos!$C$117*Datos!$B$8 -> 4824.1878 | ... L43: =Datos!$C$117*Datos!$B$8 -> 4824.1878
A44: COSTO ANUAL A | B44: USD | C44: =C33+C35+C39+C42+C43 -> 20814.054 | D44: =D33+D35+D39+D42+D43 -> 31580.928 | E44: =E33+E35+E39+E42+E43 -> 53382.477 | F44: =F33+F35+F39+F42+F43 -> 99556.265 | G44: =G33+G35+G39+G42+G43 -> 166403.19 | H44: =H33+H35+H39+H42+H43 -> 230284.47 | I44: =I33+I35+I39+I42+I43 -> 310278.34 | J44: =J33+J35+J39+J42+J43 -> 391644.34 | ... L44: =L33+L35+L39+L42+L43 -> 510842.2
A46: B — Hojas para todo: cuerpos con dos guillotinas y discos de tiras de hoja
A47: Hojas mixtas 70 + 100 kg | B47: hojas | C47: =IF(Datos!$B$24="SI",MIN(C15/Datos!$B$25,C14/Datos!$B$26),0) -> 6.1149533 | D47: =IF(Datos!$B$24="SI",MIN(D15/Datos!$B$25,D14/Datos!$B$26),0) -> 9.4072769 | E47: =IF(Datos!$B$24="SI",MIN(E15/Datos!$B$25,E14/Datos!$B$26),0) -> 14.420033 | F47: =IF(Datos!$B$24="SI",MIN(F15/Datos!$B$25,F14/Datos!$B$26),0) -> 24.604776 | G47: =IF(Datos!$B$24="SI",MIN(G15/Datos!$B$25,G14/Datos!$B$26),0) -> 40.753494 | H47: =IF(Datos!$B$24="SI",MIN(H15/Datos!$B$25,H14/Datos!$B$26),0) -> 55.842851 | I47: =IF(Datos!$B$24="SI",MIN(I15/Datos!$B$25,I14/Datos!$B$26),0) -> 74.826917 | J47: =IF(Datos!$B$24="SI",MIN(J15/Datos!$B$25,J14/Datos!$B$26),0) -> 93.882454 | ... L47: =IF(Datos!$B$24="SI",MIN(L15/Datos!$B$25,L14/Datos!$B$26),0) -> 124.70995
A48: Hojas de 70 kg solas | B48: hojas | C48: =(C14-Datos!$B$26*C47)/Corte!$I$12 -> 0 | D48: =(D14-Datos!$B$26*D47)/Corte!$I$12 -> 0 | E48: =(E14-Datos!$B$26*E47)/Corte!$I$12 -> 0 | F48: =(F14-Datos!$B$26*F47)/Corte!$I$12 -> 0 | G48: =(G14-Datos!$B$26*G47)/Corte!$I$12 -> 0 | H48: =(H14-Datos!$B$26*H47)/Corte!$I$12 -> 0 | I48: =(I14-Datos!$B$26*I47)/Corte!$I$12 -> 0 | J48: =(J14-Datos!$B$26*J47)/Corte!$I$12 -> 0 | ... L48: =(L14-Datos!$B$26*L47)/Corte!$I$12 -> 0
A49: Hojas de 100 kg solas | B49: hojas | C49: =(C15-Datos!$B$25*C47)/Corte!$I$13 -> 2.26054 | D49: =(D15-Datos!$B$25*D47)/Corte!$I$13 -> 3.1535368 | E49: =(E15-Datos!$B$25*E47)/Corte!$I$13 -> 4.8022332 | F49: =(F15-Datos!$B$25*F47)/Corte!$I$13 -> 7.9082588 | G49: =(G15-Datos!$B$25*G47)/Corte!$I$13 -> 13.295609 | H49: =(H15-Datos!$B$25*H47)/Corte!$I$13 -> 18.338728 | I49: =(I15-Datos!$B$25*I47)/Corte!$I$13 -> 25.022306 | J49: =(J15-Datos!$B$25*J47)/Corte!$I$13 -> 30.876374 | ... L49: =(L15-Datos!$B$25*L47)/Corte!$I$13 -> 40.912206
A50: Hojas de 3,2 mm, patrón P1 (6 de 25 kg + 3 de 50 kg) | B50: hojas | C50: =IF(Datos!$B$27="SI",MIN(C12/Nesting!$E$26,C13/Nesting!$F$26),0) -> 6.0086319 | D50: =IF(Datos!$B$27="SI",MIN(D12/Nesting!$E$26,D13/Nesting!$F$26),0) -> 9.7703579 | E50: =IF(Datos!$B$27="SI",MIN(E12/Nesting!$E$26,E13/Nesting!$F$26),0) -> 15.12809 | F50: =IF(Datos!$B$27="SI",MIN(F12/Nesting!$E$26,F13/Nesting!$F$26),0) -> 25.494975 | G50: =IF(Datos!$B$27="SI",MIN(G12/Nesting!$E$26,G13/Nesting!$F$26),0) -> 42.046001 | H50: =IF(Datos!$B$27="SI",MIN(H12/Nesting!$E$26,H13/Nesting!$F$26),0) -> 58.262414 | I50: =IF(Datos!$B$27="SI",MIN(I12/Nesting!$E$26,I13/Nesting!$F$26),0) -> 77.578039 | J50: =IF(Datos!$B$27="SI",MIN(J12/Nesting!$E$26,J13/Nesting!$F$26),0) -> 97.788112 | ... L50: =IF(Datos!$B$27="SI",MIN(L12/Nesting!$E$26,L13/Nesting!$F$26),0) -> 129.55176
A51: Hojas de 3,2 mm, patrón P3 (6 de 50 kg) | B51: hojas | C51: =IF(Datos!$B$27="SI",(C13-C50*Nesting!$F$26)/Nesting!$F$28,C13/Corte!$I$11) -> 9.8146742 | D51: =IF(Datos!$B$27="SI",(D13-D50*Nesting!$F$26)/Nesting!$F$28,D13/Corte!$I$11) -> 16.744275 | E51: =IF(Datos!$B$27="SI",(E13-E50*Nesting!$F$26)/Nesting!$F$28,E13/Corte!$I$11) -> 25.85242 | F51: =IF(Datos!$B$27="SI",(F13-F50*Nesting!$F$26)/Nesting!$F$28,F13/Corte!$I$11) -> 43.493458 | G51: =IF(Datos!$B$27="SI",(G13-G50*Nesting!$F$26)/Nesting!$F$28,G13/Corte!$I$11) -> 71.311534 | H51: =IF(Datos!$B$27="SI",(H13-H50*Nesting!$F$26)/Nesting!$F$28,H13/Corte!$I$11) -> 99.058103 | I51: =IF(Datos!$B$27="SI",(I13-I50*Nesting!$F$26)/Nesting!$F$28,I13/Corte!$I$11) -> 132.08933 | J51: =IF(Datos!$B$27="SI",(J13-J50*Nesting!$F$26)/Nesting!$F$28,J13/Corte!$I$11) -> 166.45712 | ... L51: =IF(Datos!$B$27="SI",(L13-L50*Nesting!$F$26)/Nesting!$F$28,L13/Corte!$I$11) -> 219.96332
A52: Hojas de 3,2 mm, patrón P4 (9 de 25 kg) | B52: hojas | C52: =IF(Datos!$B$27="SI",(C12-C50*Nesting!$E$26)/Nesting!$E$29,C12/Corte!$I$10) -> 0 | D52: =IF(Datos!$B$27="SI",(D12-D50*Nesting!$E$26)/Nesting!$E$29,D12/Corte!$I$10) -> 0 | E52: =IF(Datos!$B$27="SI",(E12-E50*Nesting!$E$26)/Nesting!$E$29,E12/Corte!$I$10) -> 0 | F52: =IF(Datos!$B$27="SI",(F12-F50*Nesting!$E$26)/Nesting!$E$29,F12/Corte!$I$10) -> 0 | G52: =IF(Datos!$B$27="SI",(G12-G50*Nesting!$E$26)/Nesting!$E$29,G12/Corte!$I$10) -> 0 | H52: =IF(Datos!$B$27="SI",(H12-H50*Nesting!$E$26)/Nesting!$E$29,H12/Corte!$I$10) -> 0 | I52: =IF(Datos!$B$27="SI",(I12-I50*Nesting!$E$26)/Nesting!$E$29,I12/Corte!$I$10) -> 0 | J52: =IF(Datos!$B$27="SI",(J12-J50*Nesting!$E$26)/Nesting!$E$29,J12/Corte!$I$10) -> 0 | ... L52: =IF(Datos!$B$27="SI",(L12-L50*Nesting!$E$26)/Nesting!$E$29,L12/Corte!$I$10) -> 0
A53: Hojas para cuerpos | B53: hojas | C53: =SUMPRODUCT(C$8:C$11/Corte!$I$6:$I$9)+C50+C51+C52+C48+C49+C47 -> 324.64181 | D53: =SUMPRODUCT(D$8:D$11/Corte!$I$6:$I$9)+D50+D51+D52+D48+D49+D47 -> 538.67246 | E53: =SUMPRODUCT(E$8:E$11/Corte!$I$6:$I$9)+E50+E51+E52+E48+E49+E47 -> 1014.0369 | F53: =SUMPRODUCT(F$8:F$11/Corte!$I$6:$I$9)+F50+F51+F52+F48+F49+F47 -> 2041.3166 | G53: =SUMPRODUCT(G$8:G$11/Corte!$I$6:$I$9)+G50+G51+G52+G48+G49+G47 -> 3502.5343 | H53: =SUMPRODUCT(H$8:H$11/Corte!$I$6:$I$9)+H50+H51+H52+H48+H49+H47 -> 4904.9326 | I53: =SUMPRODUCT(I$8:I$11/Corte!$I$6:$I$9)+I50+I51+I52+I48+I49+I47 -> 6691.3583 | J53: =SUMPRODUCT(J$8:J$11/Corte!$I$6:$I$9)+J50+J51+J52+J48+J49+J47 -> 8505.55 | ... L53: =SUMPRODUCT(L$8:L$11/Corte!$I$6:$I$9)+L50+L51+L52+L48+L49+L47 -> 11119.599
A54: Acero de hojas para cuerpos | B54: t | C54: =(SUMPRODUCT(C$8:C$11/Corte!$I$6:$I$9*Corte!$W$6:$W$9)+(C50+C51+C52)*Corte!$W$10+C48*Corte!$W$12+C49*Corte!$W$13+C47*Corte!$W$14)/1000 -> 10.721997 | D54: =(SUMPRODUCT(D$8:D$11/Corte!$I$6:$I$9*Corte!$W$6:$W$9)+(D50+D51+D52)*Corte!$W$10+D48*Corte!$W$12+D49*Corte!$W$13+D47*Corte!$W$14)/1000 -> 17.818655 | E54: =(SUMPRODUCT(E$8:E$11/Corte!$I$6:$I$9*Corte!$W$6:$W$9)+(E50+E51+E52)*Corte!$W$10+E48*Corte!$W$12+E49*Corte!$W$13+E47*Corte!$W$14)/1000 -> 31.847161 | F54: =(SUMPRODUCT(F$8:F$11/Corte!$I$6:$I$9*Corte!$W$6:$W$9)+(F50+F51+F52)*Corte!$W$10+F48*Corte!$W$12+F49*Corte!$W$13+F47*Corte!$W$14)/1000 -> 61.42046 | G54: =(SUMPRODUCT(G$8:G$11/Corte!$I$6:$I$9*Corte!$W$6:$W$9)+(G50+G51+G52)*Corte!$W$10+G48*Corte!$W$12+G49*Corte!$W$13+G47*Corte!$W$14)/1000 -> 104.57585 | H54: =(SUMPRODUCT(H$8:H$11/Corte!$I$6:$I$9*Corte!$W$6:$W$9)+(H50+H51+H52)*Corte!$W$10+H48*Corte!$W$12+H49*Corte!$W$13+H47*Corte!$W$14)/1000 -> 146.25877 | I54: =(SUMPRODUCT(I$8:I$11/Corte!$I$6:$I$9*Corte!$W$6:$W$9)+(I50+I51+I52)*Corte!$W$10+I48*Corte!$W$12+I49*Corte!$W$13+I47*Corte!$W$14)/1000 -> 198.53373 | J54: =(SUMPRODUCT(J$8:J$11/Corte!$I$6:$I$9*Corte!$W$6:$W$9)+(J50+J51+J52)*Corte!$W$10+J48*Corte!$W$12+J49*Corte!$W$13+J47*Corte!$W$14)/1000 -> 251.65721 | ... L54: =(SUMPRODUCT(L$8:L$11/Corte!$I$6:$I$9*Corte!$W$6:$W$9)+(L50+L51+L52)*Corte!$W$10+L48*Corte!$W$12+L49*Corte!$W$13+L47*Corte!$W$14)/1000 -> 329.97623
A55: Costo de las hojas para cuerpos | B55: USD | C55: =SUMPRODUCT(C$8:C$11/Corte!$I$6:$I$9*Corte!$X$6:$X$9)+(C50+C51+C52)*Corte!$X$10+C48*Corte!$X$12+C49*Corte!$X$13+C47*Corte!$X$14 -> 13518.618 | D55: =SUMPRODUCT(D$8:D$11/Corte!$I$6:$I$9*Corte!$X$6:$X$9)+(D50+D51+D52)*Corte!$X$10+D48*Corte!$X$12+D49*Corte!$X$13+D47*Corte!$X$14 -> 22487.441 | E55: =SUMPRODUCT(E$8:E$11/Corte!$I$6:$I$9*Corte!$X$6:$X$9)+(E50+E51+E52)*Corte!$X$10+E48*Corte!$X$12+E49*Corte!$X$13+E47*Corte!$X$14 -> 40528.358 | F55: =SUMPRODUCT(F$8:F$11/Corte!$I$6:$I$9*Corte!$X$6:$X$9)+(F50+F51+F52)*Corte!$X$10+F48*Corte!$X$12+F49*Corte!$X$13+F47*Corte!$X$14 -> 78693.188 | G55: =SUMPRODUCT(G$8:G$11/Corte!$I$6:$I$9*Corte!$X$6:$X$9)+(G50+G51+G52)*Corte!$X$10+G48*Corte!$X$12+G49*Corte!$X$13+G47*Corte!$X$14 -> 134169.62 | H55: =SUMPRODUCT(H$8:H$11/Corte!$I$6:$I$9*Corte!$X$6:$X$9)+(H50+H51+H52)*Corte!$X$10+H48*Corte!$X$12+H49*Corte!$X$13+H47*Corte!$X$14 -> 187724.42 | I55: =SUMPRODUCT(I$8:I$11/Corte!$I$6:$I$9*Corte!$X$6:$X$9)+(I50+I51+I52)*Corte!$X$10+I48*Corte!$X$12+I49*Corte!$X$13+I47*Corte!$X$14 -> 255006.63 | J55: =SUMPRODUCT(J$8:J$11/Corte!$I$6:$I$9*Corte!$X$6:$X$9)+(J50+J51+J52)*Corte!$X$10+J48*Corte!$X$12+J49*Corte!$X$13+J47*Corte!$X$14 -> 323380.22 | ... L55: =SUMPRODUCT(L$8:L$11/Corte!$I$6:$I$9*Corte!$X$6:$X$9)+(L50+L51+L52)*Corte!$X$10+L48*Corte!$X$12+L49*Corte!$X$13+L47*Corte!$X$14 -> 423807.98
A56: Horas de la guillotina 1 (1.er corte: franjas) | B56: h | C56: =(SUMPRODUCT(C$8:C$11/Corte!$I$6:$I$9*Corte!$P$6:$P$9)+C50*Nesting!$G$26+C51*Nesting!$G$28+C52*Nesting!$G$29+C48*Corte!$P$12+C49*Corte!$P$13+C47*Corte!$P$14)/Datos!$B$32/60 -> 1.505559 | D56: =(SUMPRODUCT(D$8:D$11/Corte!$I$6:$I$9*Corte!$P$6:$P$9)+D50*Nesting!$G$26+D51*Nesting!$G$28+D52*Nesting!$G$29+D48*Corte!$P$12+D49*Corte!$P$13+D47*Corte!$P$14)/Datos!$B$32/60 -> 2.4480436 | E56: =(SUMPRODUCT(E$8:E$11/Corte!$I$6:$I$9*Corte!$P$6:$P$9)+E50*Nesting!$G$26+E51*Nesting!$G$28+E52*Nesting!$G$29+E48*Corte!$P$12+E49*Corte!$P$13+E47*Corte!$P$14)/Datos!$B$32/60 -> 4.9075884 | F56: =(SUMPRODUCT(F$8:F$11/Corte!$I$6:$I$9*Corte!$P$6:$P$9)+F50*Nesting!$G$26+F51*Nesting!$G$28+F52*Nesting!$G$29+F48*Corte!$P$12+F49*Corte!$P$13+F47*Corte!$P$14)/Datos!$B$32/60 -> 10.43264 | G56: =(SUMPRODUCT(G$8:G$11/Corte!$I$6:$I$9*Corte!$P$6:$P$9)+G50*Nesting!$G$26+G51*Nesting!$G$28+G52*Nesting!$G$29+G48*Corte!$P$12+G49*Corte!$P$13+G47*Corte!$P$14)/Datos!$B$32/60 -> 18.048898 | H56: =(SUMPRODUCT(H$8:H$11/Corte!$I$6:$I$9*Corte!$P$6:$P$9)+H50*Nesting!$G$26+H51*Nesting!$G$28+H52*Nesting!$G$29+H48*Corte!$P$12+H49*Corte!$P$13+H47*Corte!$P$14)/Datos!$B$32/60 -> 25.324477 | I56: =(SUMPRODUCT(I$8:I$11/Corte!$I$6:$I$9*Corte!$P$6:$P$9)+I50*Nesting!$G$26+I51*Nesting!$G$28+I52*Nesting!$G$29+I48*Corte!$P$12+I49*Corte!$P$13+I47*Corte!$P$14)/Datos!$B$32/60 -> 34.755649 | J56: =(SUMPRODUCT(J$8:J$11/Corte!$I$6:$I$9*Corte!$P$6:$P$9)+J50*Nesting!$G$26+J51*Nesting!$G$28+J52*Nesting!$G$29+J48*Corte!$P$12+J49*Corte!$P$13+J47*Corte!$P$14)/Datos!$B$32/60 -> 44.30983 | ... L56: =(SUMPRODUCT(L$8:L$11/Corte!$I$6:$I$9*Corte!$P$6:$P$9)+L50*Nesting!$G$26+L51*Nesting!$G$28+L52*Nesting!$G$29+L48*Corte!$P$12+L49*Corte!$P$13+L47*Corte!$P$14)/Datos!$B$32/60 -> 57.895743
A57: Horas de la guillotina 2 (2.º corte, franjas en paralelo) | B57: h | C57: =(SUMPRODUCT(C$8:C$11/Corte!$I$6:$I$9*Corte!$R$6:$R$9)+C50*Nesting!$H$26+C51*Nesting!$H$28+C52*Nesting!$H$29+C48*Corte!$R$12+C49*Corte!$R$13+C47*Corte!$R$14)/Datos!$B$35/60 -> 0.97402684 | D57: =(SUMPRODUCT(D$8:D$11/Corte!$I$6:$I$9*Corte!$R$6:$R$9)+D50*Nesting!$H$26+D51*Nesting!$H$28+D52*Nesting!$H$29+D48*Corte!$R$12+D49*Corte!$R$13+D47*Corte!$R$14)/Datos!$B$35/60 -> 1.5838255 | E57: =(SUMPRODUCT(E$8:E$11/Corte!$I$6:$I$9*Corte!$R$6:$R$9)+E50*Nesting!$H$26+E51*Nesting!$H$28+E52*Nesting!$H$29+E48*Corte!$R$12+E49*Corte!$R$13+E47*Corte!$R$14)/Datos!$B$35/60 -> 3.0991102 | F57: =(SUMPRODUCT(F$8:F$11/Corte!$I$6:$I$9*Corte!$R$6:$R$9)+F50*Nesting!$H$26+F51*Nesting!$H$28+F52*Nesting!$H$29+F48*Corte!$R$12+F49*Corte!$R$13+F47*Corte!$R$14)/Datos!$B$35/60 -> 6.4539019 | G57: =(SUMPRODUCT(G$8:G$11/Corte!$I$6:$I$9*Corte!$R$6:$R$9)+G50*Nesting!$H$26+G51*Nesting!$H$28+G52*Nesting!$H$29+G48*Corte!$R$12+G49*Corte!$R$13+G47*Corte!$R$14)/Datos!$B$35/60 -> 11.138819 | H57: =(SUMPRODUCT(H$8:H$11/Corte!$I$6:$I$9*Corte!$R$6:$R$9)+H50*Nesting!$H$26+H51*Nesting!$H$28+H52*Nesting!$H$29+H48*Corte!$R$12+H49*Corte!$R$13+H47*Corte!$R$14)/Datos!$B$35/60 -> 15.613175 | I57: =(SUMPRODUCT(I$8:I$11/Corte!$I$6:$I$9*Corte!$R$6:$R$9)+I50*Nesting!$H$26+I51*Nesting!$H$28+I52*Nesting!$H$29+I48*Corte!$R$12+I49*Corte!$R$13+I47*Corte!$R$14)/Datos!$B$35/60 -> 21.390881 | J57: =(SUMPRODUCT(J$8:J$11/Corte!$I$6:$I$9*Corte!$R$6:$R$9)+J50*Nesting!$H$26+J51*Nesting!$H$28+J52*Nesting!$H$29+J48*Corte!$R$12+J49*Corte!$R$13+J47*Corte!$R$14)/Datos!$B$35/60 -> 27.245046 | ... L57: =(SUMPRODUCT(L$8:L$11/Corte!$I$6:$I$9*Corte!$R$6:$R$9)+L50*Nesting!$H$26+L51*Nesting!$H$28+L52*Nesting!$H$29+L48*Corte!$R$12+L49*Corte!$R$13+L47*Corte!$R$14)/Datos!$B$35/60 -> 35.563952
A58: Acero de hojas para discos | B58: t | C58: =SUMPRODUCT(C$8:C$11,Corte!$E$55:$E$58)/1000 -> 3.3217746 | D58: =SUMPRODUCT(D$8:D$11,Corte!$E$55:$E$58)/1000 -> 5.6565816 | E58: =SUMPRODUCT(E$8:E$11,Corte!$E$55:$E$58)/1000 -> 10.462831 | F58: =SUMPRODUCT(F$8:F$11,Corte!$E$55:$E$58)/1000 -> 20.636293 | G58: =SUMPRODUCT(G$8:G$11,Corte!$E$55:$E$58)/1000 -> 35.303049 | H58: =SUMPRODUCT(H$8:H$11,Corte!$E$55:$E$58)/1000 -> 49.482686 | I58: =SUMPRODUCT(I$8:I$11,Corte!$E$55:$E$58)/1000 -> 67.267071 | J58: =SUMPRODUCT(J$8:J$11,Corte!$E$55:$E$58)/1000 -> 85.383746 | ... L58: =SUMPRODUCT(L$8:L$11,Corte!$E$55:$E$58)/1000 -> 111.748
A59: Costo de las hojas para discos | B59: USD | C59: =SUMPRODUCT(C$8:C$11,Corte!$F$55:$F$58) -> 4392.4597 | D59: =SUMPRODUCT(D$8:D$11,Corte!$F$55:$F$58) -> 7477.3246 | E59: =SUMPRODUCT(E$8:E$11,Corte!$F$55:$F$58) -> 13823.825 | F59: =SUMPRODUCT(F$8:F$11,Corte!$F$55:$F$58) -> 27252.518 | G59: =SUMPRODUCT(G$8:G$11,Corte!$F$55:$F$58) -> 46619.325 | H59: =SUMPRODUCT(H$8:H$11,Corte!$F$55:$F$58) -> 65340.141 | I59: =SUMPRODUCT(I$8:I$11,Corte!$F$55:$F$58) -> 88822.112 | J59: =SUMPRODUCT(J$8:J$11,Corte!$F$55:$F$58) -> 112741.73 | ... L59: =SUMPRODUCT(L$8:L$11,Corte!$F$55:$F$58) -> 147543.63
A60: Tiras de hoja para discos | B60: tiras | C60: =SUMPRODUCT(C$8:C$11,Corte!$G$55:$G$58) -> 1623.9406 | D60: =SUMPRODUCT(D$8:D$11,Corte!$G$55:$G$58) -> 2667.0488 | E60: =SUMPRODUCT(E$8:E$11,Corte!$G$55:$G$58) -> 5276.1384 | F60: =SUMPRODUCT(F$8:F$11,Corte!$G$55:$G$58) -> 11071.266 | G60: =SUMPRODUCT(G$8:G$11,Corte!$G$55:$G$58) -> 19124.354 | H60: =SUMPRODUCT(H$8:H$11,Corte!$G$55:$G$58) -> 26830.052 | I60: =SUMPRODUCT(I$8:I$11,Corte!$G$55:$G$58) -> 36764.806 | J60: =SUMPRODUCT(J$8:J$11,Corte!$G$55:$G$58) -> 46837.651 | ... L60: =SUMPRODUCT(L$8:L$11,Corte!$G$55:$G$58) -> 61185.317
A61: Acero comprado | B61: t | C61: =C54+C58 -> 14.043771 | D61: =D54+D58 -> 23.475236 | E61: =E54+E58 -> 42.309993 | F61: =F54+F58 -> 82.056752 | G61: =G54+G58 -> 139.8789 | H61: =H54+H58 -> 195.74145 | I61: =I54+I58 -> 265.8008 | J61: =J54+J58 -> 337.04096 | ... L61: =L54+L58 -> 441.72423
A62: Costo del acero | B62: USD | C62: =C55+C59 -> 17911.078 | D62: =D55+D59 -> 29964.766 | E62: =E55+E59 -> 54352.184 | F62: =F55+F59 -> 105945.71 | G62: =G55+G59 -> 180788.95 | H62: =H55+H59 -> 253064.56 | I62: =I55+I59 -> 343828.75 | J62: =J55+J59 -> 436121.95 | ... L62: =L55+L59 -> 571351.62
A63: Scrap | B63: t | C63: =C61-C25 -> 2.0961631 | D63: =D61-D25 -> 3.5046158 | E63: =E61-E25 -> 6.2357433 | F63: =F61-F25 -> 11.947644 | G63: =G61-G25 -> 20.327645 | H63: =H61-H25 -> 28.422914 | I63: =I61-I25 -> 38.552388 | J63: =J61-J25 -> 48.830615 | ... L63: =L61-L25 -> 64.030803
A64: Venta de scrap (resta) | B64: USD | C64: =-C63*Datos!$B$9 -> -524.04078 | D64: =-D63*Datos!$B$9 -> -876.15396 | E64: =-E63*Datos!$B$9 -> -1558.9358 | F64: =-F63*Datos!$B$9 -> -2986.911 | G64: =-G63*Datos!$B$9 -> -5081.9113 | H64: =-H63*Datos!$B$9 -> -7105.7286 | I64: =-I63*Datos!$B$9 -> -9638.097 | J64: =-J63*Datos!$B$9 -> -12207.654 | ... L64: =-L63*Datos!$B$9 -> -16007.701
A65: Stock promedio (hojas) | B65: t | C65: =C61*(Datos!$B$51/2/12+Datos!$B$50/52) -> 1.1253022 | D65: =D61*(Datos!$B$51/2/12+Datos!$B$50/52) -> 1.8810285 | E65: =E61*(Datos!$B$51/2/12+Datos!$B$50/52) -> 3.3902238 | F65: =F61*(Datos!$B$51/2/12+Datos!$B$50/52) -> 6.5750603 | G65: =G61*(Datos!$B$51/2/12+Datos!$B$50/52) -> 11.208246 | H65: =H61*(Datos!$B$51/2/12+Datos!$B$50/52) -> 15.684411 | I65: =I61*(Datos!$B$51/2/12+Datos!$B$50/52) -> 21.298141 | J65: =J61*(Datos!$B$51/2/12+Datos!$B$50/52) -> 27.006487 | ... L65: =L61*(Datos!$B$51/2/12+Datos!$B$50/52) -> 35.394569
A66: Costo financiero del stock | B66: USD | C66: =IF(C61=0,0,C65*C62/C61*Datos!$B$7) -> 172.2219 | D66: =IF(D61=0,0,D65*D62/D61*Datos!$B$7) -> 288.12275 | E66: =IF(E61=0,0,E65*E62/E61*Datos!$B$7) -> 522.61715 | F66: =IF(F61=0,0,F65*F62/F61*Datos!$B$7) -> 1018.7087 | G66: =IF(G61=0,0,G65*G62/G61*Datos!$B$7) -> 1738.3553 | H66: =IF(H61=0,0,H65*H62/H61*Datos!$B$7) -> 2433.3131 | I66: =IF(I61=0,0,I65*I62/I61*Datos!$B$7) -> 3306.0456 | J66: =IF(J61=0,0,J65*J62/J61*Datos!$B$7) -> 4193.4802 | ... L66: =IF(L61=0,0,L65*L62/L61*Datos!$B$7) -> 5493.7656
A67: Horas-hombre de corte: guillotinas + tiras + carga manual | B67: h | C67: =C56+C57+C60/Datos!$B$32/60+C60*Datos!$B$45/3600 -> 10.599289 | D67: =D56+D57+D60/Datos!$B$32/60+D60*Datos!$B$45/3600 -> 17.367113 | E67: =E56+E57+E60/Datos!$B$32/60+E60*Datos!$B$45/3600 -> 34.387391 | F67: =F56+F57+F60/Datos!$B$32/60+F60*Datos!$B$45/3600 -> 72.242874 | G67: =G56+G57+G60/Datos!$B$32/60+G60*Datos!$B$45/3600 -> 124.80949 | H67: =H56+H57+H60/Datos!$B$32/60+H60*Datos!$B$45/3600 -> 175.08791 | I67: =I56+I57+I60/Datos!$B$32/60+I60*Datos!$B$45/3600 -> 239.97056 | J67: =J56+J57+J60/Datos!$B$32/60+J60*Datos!$B$45/3600 -> 305.74313 | ... L67: =L56+L57+L60/Datos!$B$32/60+L60*Datos!$B$45/3600 -> 399.38628
A68: Mano de obra de corte | B68: USD | C68: =C67*Datos!$B$15 -> 66.577567 | D68: =D67*Datos!$B$15 -> 109.08846 | E68: =E67*Datos!$B$15 -> 215.99834 | F68: =F67*Datos!$B$15 -> 453.78089 | G68: =G67*Datos!$B$15 -> 783.96881 | H68: =H67*Datos!$B$15 -> 1099.7839 | I68: =I67*Datos!$B$15 -> 1507.3328 | J68: =J67*Datos!$B$15 -> 1920.4716 | ... L68: =L67*Datos!$B$15 -> 2508.6746
A69: Mantenimiento de equipos | B69: USD | C69: =Datos!$D$117*Datos!$B$8 -> 2175.1878 | D69: =Datos!$D$117*Datos!$B$8 -> 2175.1878 | E69: =Datos!$D$117*Datos!$B$8 -> 2175.1878 | F69: =Datos!$D$117*Datos!$B$8 -> 2175.1878 | G69: =Datos!$D$117*Datos!$B$8 -> 2175.1878 | H69: =Datos!$D$117*Datos!$B$8 -> 2175.1878 | I69: =Datos!$D$117*Datos!$B$8 -> 2175.1878 | J69: =Datos!$D$117*Datos!$B$8 -> 2175.1878 | ... L69: =Datos!$D$117*Datos!$B$8 -> 2175.1878
A70: COSTO ANUAL B | B70: USD | C70: =C62+C64+C66+C68+C69 -> 19801.024 | D70: =D62+D64+D66+D68+D69 -> 31661.011 | E70: =E62+E64+E66+E68+E69 -> 55707.051 | F70: =F62+F64+F66+F68+F69 -> 106606.47 | G70: =G62+G64+G66+G68+G69 -> 180404.55 | H70: =H62+H64+H66+H68+H69 -> 251667.12 | I70: =I62+I64+I66+I68+I69 -> 341179.21 | J70: =J62+J64+J66+J68+J69 -> 432203.43 | ... L70: =L62+L64+L66+L68+L69 -> 565521.55
A72: C — Bobina madre por espesor con corte longitudinal propio
A73: Metros de madre de 0,9 mm | B73: m | C73: =MAX(IF(Corte!$H$73=0,IF(C8>0,1000000000000,0),C8*Corte!$D$73/1000/Corte!$H$73),IF(Corte!$H$74=0,IF(C8>0,1000000000000,0),C8*Corte!$D$74/1000/Corte!$H$74)) -> 249.28943 | D73: =MAX(IF(Corte!$H$73=0,IF(D8>0,1000000000000,0),D8*Corte!$D$73/1000/Corte!$H$73),IF(Corte!$H$74=0,IF(D8>0,1000000000000,0),D8*Corte!$D$74/1000/Corte!$H$74)) -> 357.77908 | E73: =MAX(IF(Corte!$H$73=0,IF(E8>0,1000000000000,0),E8*Corte!$D$73/1000/Corte!$H$73),IF(Corte!$H$74=0,IF(E8>0,1000000000000,0),E8*Corte!$D$74/1000/Corte!$H$74)) -> 865.86547 | F73: =MAX(IF(Corte!$H$73=0,IF(F8>0,1000000000000,0),F8*Corte!$D$73/1000/Corte!$H$73),IF(Corte!$H$74=0,IF(F8>0,1000000000000,0),F8*Corte!$D$74/1000/Corte!$H$74)) -> 2097.6434 | G73: =MAX(IF(Corte!$H$73=0,IF(G8>0,1000000000000,0),G8*Corte!$D$73/1000/Corte!$H$73),IF(Corte!$H$74=0,IF(G8>0,1000000000000,0),G8*Corte!$D$74/1000/Corte!$H$74)) -> 3705.5988 | H73: =MAX(IF(Corte!$H$73=0,IF(H8>0,1000000000000,0),H8*Corte!$D$73/1000/Corte!$H$73),IF(Corte!$H$74=0,IF(H8>0,1000000000000,0),H8*Corte!$D$74/1000/Corte!$H$74)) -> 5208.0528 | I73: =MAX(IF(Corte!$H$73=0,IF(I8>0,1000000000000,0),I8*Corte!$D$73/1000/Corte!$H$73),IF(Corte!$H$74=0,IF(I8>0,1000000000000,0),I8*Corte!$D$74/1000/Corte!$H$74)) -> 7258.613 | J73: =MAX(IF(Corte!$H$73=0,IF(J8>0,1000000000000,0),J8*Corte!$D$73/1000/Corte!$H$73),IF(Corte!$H$74=0,IF(J8>0,1000000000000,0),J8*Corte!$D$74/1000/Corte!$H$74)) -> 9314.3768 | ... L73: =MAX(IF(Corte!$H$73=0,IF(L8>0,1000000000000,0),L8*Corte!$D$73/1000/Corte!$H$73),IF(Corte!$H$74=0,IF(L8>0,1000000000000,0),L8*Corte!$D$74/1000/Corte!$H$74)) -> 12087.669
A74: Metros de madre de 1,25 mm | B74: m | C74: =MAX(IF(Corte!$H$81=0,IF(C9>0,1000000000000,0),C9*Corte!$D$81/1000/Corte!$H$81),IF(Corte!$H$82=0,IF(C9>0,1000000000000,0),C9*Corte!$D$82/1000/Corte!$H$82),IF(Corte!$H$83=0,IF(C9>0,1000000000000,0),C9*Corte!$D$83/1000/Corte!$H$83),IF(Corte!$H$84=0,IF(C8>0,1000000000000,0),C8*Corte!$D$84/1000/Corte!$H$84)) -> 88.569073 | D74: =MAX(IF(Corte!$H$81=0,IF(D9>0,1000000000000,0),D9*Corte!$D$81/1000/Corte!$H$81),IF(Corte!$H$82=0,IF(D9>0,1000000000000,0),D9*Corte!$D$82/1000/Corte!$H$82),IF(Corte!$H$83=0,IF(D9>0,1000000000000,0),D9*Corte!$D$83/1000/Corte!$H$83),IF(Corte!$H$84=0,IF(D8>0,1000000000000,0),D8*Corte!$D$84/1000/Corte!$H$84)) -> 213.76269 | E74: =MAX(IF(Corte!$H$81=0,IF(E9>0,1000000000000,0),E9*Corte!$D$81/1000/Corte!$H$81),IF(Corte!$H$82=0,IF(E9>0,1000000000000,0),E9*Corte!$D$82/1000/Corte!$H$82),IF(Corte!$H$83=0,IF(E9>0,1000000000000,0),E9*Corte!$D$83/1000/Corte!$H$83),IF(Corte!$H$84=0,IF(E8>0,1000000000000,0),E8*Corte!$D$84/1000/Corte!$H$84)) -> 386.70896 | F74: =MAX(IF(Corte!$H$81=0,IF(F9>0,1000000000000,0),F9*Corte!$D$81/1000/Corte!$H$81),IF(Corte!$H$82=0,IF(F9>0,1000000000000,0),F9*Corte!$D$82/1000/Corte!$H$82),IF(Corte!$H$83=0,IF(F9>0,1000000000000,0),F9*Corte!$D$83/1000/Corte!$H$83),IF(Corte!$H$84=0,IF(F8>0,1000000000000,0),F8*Corte!$D$84/1000/Corte!$H$84)) -> 762.12417 | G74: =MAX(IF(Corte!$H$81=0,IF(G9>0,1000000000000,0),G9*Corte!$D$81/1000/Corte!$H$81),IF(Corte!$H$82=0,IF(G9>0,1000000000000,0),G9*Corte!$D$82/1000/Corte!$H$82),IF(Corte!$H$83=0,IF(G9>0,1000000000000,0),G9*Corte!$D$83/1000/Corte!$H$83),IF(Corte!$H$84=0,IF(G8>0,1000000000000,0),G8*Corte!$D$84/1000/Corte!$H$84)) -> 1266.6146 | H74: =MAX(IF(Corte!$H$81=0,IF(H9>0,1000000000000,0),H9*Corte!$D$81/1000/Corte!$H$81),IF(Corte!$H$82=0,IF(H9>0,1000000000000,0),H9*Corte!$D$82/1000/Corte!$H$82),IF(Corte!$H$83=0,IF(H9>0,1000000000000,0),H9*Corte!$D$83/1000/Corte!$H$83),IF(Corte!$H$84=0,IF(H8>0,1000000000000,0),H8*Corte!$D$84/1000/Corte!$H$84)) -> 1800.5776 | I74: =MAX(IF(Corte!$H$81=0,IF(I9>0,1000000000000,0),I9*Corte!$D$81/1000/Corte!$H$81),IF(Corte!$H$82=0,IF(I9>0,1000000000000,0),I9*Corte!$D$82/1000/Corte!$H$82),IF(Corte!$H$83=0,IF(I9>0,1000000000000,0),I9*Corte!$D$83/1000/Corte!$H$83),IF(Corte!$H$84=0,IF(I8>0,1000000000000,0),I8*Corte!$D$84/1000/Corte!$H$84)) -> 2481.0741 | J74: =MAX(IF(Corte!$H$81=0,IF(J9>0,1000000000000,0),J9*Corte!$D$81/1000/Corte!$H$81),IF(Corte!$H$82=0,IF(J9>0,1000000000000,0),J9*Corte!$D$82/1000/Corte!$H$82),IF(Corte!$H$83=0,IF(J9>0,1000000000000,0),J9*Corte!$D$83/1000/Corte!$H$83),IF(Corte!$H$84=0,IF(J8>0,1000000000000,0),J8*Corte!$D$84/1000/Corte!$H$84)) -> 3183.7568 | ... L74: =MAX(IF(Corte!$H$81=0,IF(L9>0,1000000000000,0),L9*Corte!$D$81/1000/Corte!$H$81),IF(Corte!$H$82=0,IF(L9>0,1000000000000,0),L9*Corte!$D$82/1000/Corte!$H$82),IF(Corte!$H$83=0,IF(L9>0,1000000000000,0),L9*Corte!$D$83/1000/Corte!$H$83),IF(Corte!$H$84=0,IF(L8>0,1000000000000,0),L8*Corte!$D$84/1000/Corte!$H$84)) -> 4170.1004
A75: Metros de madre de 1,6 mm | B75: m | C75: =MAX(IF(Corte!$H$91=0,IF(C10>0,1000000000000,0),C10*Corte!$D$91/1000/Corte!$H$91),IF(Corte!$H$92=0,IF(C10>0,1000000000000,0),C10*Corte!$D$92/1000/Corte!$H$92),IF(Corte!$H$93=0,IF(C10>0,1000000000000,0),C10*Corte!$D$93/1000/Corte!$H$93),IF(Corte!$H$94=0,IF(C11>0,1000000000000,0),C11*Corte!$D$94/1000/Corte!$H$94)) -> 539.06845 | D75: =MAX(IF(Corte!$H$91=0,IF(D10>0,1000000000000,0),D10*Corte!$D$91/1000/Corte!$H$91),IF(Corte!$H$92=0,IF(D10>0,1000000000000,0),D10*Corte!$D$92/1000/Corte!$H$92),IF(Corte!$H$93=0,IF(D10>0,1000000000000,0),D10*Corte!$D$93/1000/Corte!$H$93),IF(Corte!$H$94=0,IF(D11>0,1000000000000,0),D11*Corte!$D$94/1000/Corte!$H$94)) -> 928.00318 | E75: =MAX(IF(Corte!$H$91=0,IF(E10>0,1000000000000,0),E10*Corte!$D$91/1000/Corte!$H$91),IF(Corte!$H$92=0,IF(E10>0,1000000000000,0),E10*Corte!$D$92/1000/Corte!$H$92),IF(Corte!$H$93=0,IF(E10>0,1000000000000,0),E10*Corte!$D$93/1000/Corte!$H$93),IF(Corte!$H$94=0,IF(E11>0,1000000000000,0),E11*Corte!$D$94/1000/Corte!$H$94)) -> 1585.6468 | F75: =MAX(IF(Corte!$H$91=0,IF(F10>0,1000000000000,0),F10*Corte!$D$91/1000/Corte!$H$91),IF(Corte!$H$92=0,IF(F10>0,1000000000000,0),F10*Corte!$D$92/1000/Corte!$H$92),IF(Corte!$H$93=0,IF(F10>0,1000000000000,0),F10*Corte!$D$93/1000/Corte!$H$93),IF(Corte!$H$94=0,IF(F11>0,1000000000000,0),F11*Corte!$D$94/1000/Corte!$H$94)) -> 2883.1916 | G75: =MAX(IF(Corte!$H$91=0,IF(G10>0,1000000000000,0),G10*Corte!$D$91/1000/Corte!$H$91),IF(Corte!$H$92=0,IF(G10>0,1000000000000,0),G10*Corte!$D$92/1000/Corte!$H$92),IF(Corte!$H$93=0,IF(G10>0,1000000000000,0),G10*Corte!$D$93/1000/Corte!$H$93),IF(Corte!$H$94=0,IF(G11>0,1000000000000,0),G11*Corte!$D$94/1000/Corte!$H$94)) -> 4865.0421 | H75: =MAX(IF(Corte!$H$91=0,IF(H10>0,1000000000000,0),H10*Corte!$D$91/1000/Corte!$H$91),IF(Corte!$H$92=0,IF(H10>0,1000000000000,0),H10*Corte!$D$92/1000/Corte!$H$92),IF(Corte!$H$93=0,IF(H10>0,1000000000000,0),H10*Corte!$D$93/1000/Corte!$H$93),IF(Corte!$H$94=0,IF(H11>0,1000000000000,0),H11*Corte!$D$94/1000/Corte!$H$94)) -> 6780.7486 | I75: =MAX(IF(Corte!$H$91=0,IF(I10>0,1000000000000,0),I10*Corte!$D$91/1000/Corte!$H$91),IF(Corte!$H$92=0,IF(I10>0,1000000000000,0),I10*Corte!$D$92/1000/Corte!$H$92),IF(Corte!$H$93=0,IF(I10>0,1000000000000,0),I10*Corte!$D$93/1000/Corte!$H$93),IF(Corte!$H$94=0,IF(I11>0,1000000000000,0),I11*Corte!$D$94/1000/Corte!$H$94)) -> 9134.5045 | J75: =MAX(IF(Corte!$H$91=0,IF(J10>0,1000000000000,0),J10*Corte!$D$91/1000/Corte!$H$91),IF(Corte!$H$92=0,IF(J10>0,1000000000000,0),J10*Corte!$D$92/1000/Corte!$H$92),IF(Corte!$H$93=0,IF(J10>0,1000000000000,0),J10*Corte!$D$93/1000/Corte!$H$93),IF(Corte!$H$94=0,IF(J11>0,1000000000000,0),J11*Corte!$D$94/1000/Corte!$H$94)) -> 11538.967 | ... L75: =MAX(IF(Corte!$H$91=0,IF(L10>0,1000000000000,0),L10*Corte!$D$91/1000/Corte!$H$91),IF(Corte!$H$92=0,IF(L10>0,1000000000000,0),L10*Corte!$D$92/1000/Corte!$H$92),IF(Corte!$H$93=0,IF(L10>0,1000000000000,0),L10*Corte!$D$93/1000/Corte!$H$93),IF(Corte!$H$94=0,IF(L11>0,1000000000000,0),L11*Corte!$D$94/1000/Corte!$H$94)) -> 15085.179
A76: Metros de madre de 2,0 mm | B76: m | C76: =MAX(IF(Corte!$H$101=0,IF(C11>0,1000000000000,0),C11*Corte!$D$101/1000/Corte!$H$101),IF(Corte!$H$102=0,IF(C11>0,1000000000000,0),C11*Corte!$D$102/1000/Corte!$H$102)) -> 31.463493 | D76: =MAX(IF(Corte!$H$101=0,IF(D11>0,1000000000000,0),D11*Corte!$D$101/1000/Corte!$H$101),IF(Corte!$H$102=0,IF(D11>0,1000000000000,0),D11*Corte!$D$102/1000/Corte!$H$102)) -> 60.545135 | E76: =MAX(IF(Corte!$H$101=0,IF(E11>0,1000000000000,0),E11*Corte!$D$101/1000/Corte!$H$101),IF(Corte!$H$102=0,IF(E11>0,1000000000000,0),E11*Corte!$D$102/1000/Corte!$H$102)) -> 116.79183 | F76: =MAX(IF(Corte!$H$101=0,IF(F11>0,1000000000000,0),F11*Corte!$D$101/1000/Corte!$H$101),IF(Corte!$H$102=0,IF(F11>0,1000000000000,0),F11*Corte!$D$102/1000/Corte!$H$102)) -> 228.03067 | G76: =MAX(IF(Corte!$H$101=0,IF(G11>0,1000000000000,0),G11*Corte!$D$101/1000/Corte!$H$101),IF(Corte!$H$102=0,IF(G11>0,1000000000000,0),G11*Corte!$D$102/1000/Corte!$H$102)) -> 398.27808 | H76: =MAX(IF(Corte!$H$101=0,IF(H11>0,1000000000000,0),H11*Corte!$D$101/1000/Corte!$H$101),IF(Corte!$H$102=0,IF(H11>0,1000000000000,0),H11*Corte!$D$102/1000/Corte!$H$102)) -> 575.86082 | I76: =MAX(IF(Corte!$H$101=0,IF(I11>0,1000000000000,0),I11*Corte!$D$101/1000/Corte!$H$101),IF(Corte!$H$102=0,IF(I11>0,1000000000000,0),I11*Corte!$D$102/1000/Corte!$H$102)) -> 775.01859 | J76: =MAX(IF(Corte!$H$101=0,IF(J11>0,1000000000000,0),J11*Corte!$D$101/1000/Corte!$H$101),IF(Corte!$H$102=0,IF(J11>0,1000000000000,0),J11*Corte!$D$102/1000/Corte!$H$102)) -> 979.26208 | ... L76: =MAX(IF(Corte!$H$101=0,IF(L11>0,1000000000000,0),L11*Corte!$D$101/1000/Corte!$H$101),IF(Corte!$H$102=0,IF(L11>0,1000000000000,0),L11*Corte!$D$102/1000/Corte!$H$102)) -> 1281.6317
A77: Metros de madre de 3,2 mm | B77: m | C77: =MAX(IF(Corte!$H$109=0,IF(C12>0,1000000000000,0),C12*Corte!$D$109/1000/Corte!$H$109),IF(Corte!$H$110=0,IF(C13>0,1000000000000,0),C13*Corte!$D$110/1000/Corte!$H$110)) -> 49.791607 | D77: =MAX(IF(Corte!$H$109=0,IF(D12>0,1000000000000,0),D12*Corte!$D$109/1000/Corte!$H$109),IF(Corte!$H$110=0,IF(D13>0,1000000000000,0),D13*Corte!$D$110/1000/Corte!$H$110)) -> 81.478765 | E77: =MAX(IF(Corte!$H$109=0,IF(E12>0,1000000000000,0),E12*Corte!$D$109/1000/Corte!$H$109),IF(Corte!$H$110=0,IF(E13>0,1000000000000,0),E13*Corte!$D$110/1000/Corte!$H$110)) -> 125.88077 | F77: =MAX(IF(Corte!$H$109=0,IF(F12>0,1000000000000,0),F12*Corte!$D$109/1000/Corte!$H$109),IF(Corte!$H$110=0,IF(F13>0,1000000000000,0),F13*Corte!$D$110/1000/Corte!$H$110)) -> 211.86123 | G77: =MAX(IF(Corte!$H$109=0,IF(G12>0,1000000000000,0),G12*Corte!$D$109/1000/Corte!$H$109),IF(Corte!$H$110=0,IF(G13>0,1000000000000,0),G13*Corte!$D$110/1000/Corte!$H$110)) -> 348.42173 | H77: =MAX(IF(Corte!$H$109=0,IF(H12>0,1000000000000,0),H12*Corte!$D$109/1000/Corte!$H$109),IF(Corte!$H$110=0,IF(H13>0,1000000000000,0),H13*Corte!$D$110/1000/Corte!$H$110)) -> 482.89275 | I77: =MAX(IF(Corte!$H$109=0,IF(I12>0,1000000000000,0),I12*Corte!$D$109/1000/Corte!$H$109),IF(Corte!$H$110=0,IF(I13>0,1000000000000,0),I13*Corte!$D$110/1000/Corte!$H$110)) -> 643.70358 | J77: =MAX(IF(Corte!$H$109=0,IF(J12>0,1000000000000,0),J12*Corte!$D$109/1000/Corte!$H$109),IF(Corte!$H$110=0,IF(J13>0,1000000000000,0),J13*Corte!$D$110/1000/Corte!$H$110)) -> 811.23398 | ... L77: =MAX(IF(Corte!$H$109=0,IF(L12>0,1000000000000,0),L12*Corte!$D$109/1000/Corte!$H$109),IF(Corte!$H$110=0,IF(L13>0,1000000000000,0),L13*Corte!$D$110/1000/Corte!$H$110)) -> 1073.5539
A78: Metros de madre de 4,75 mm | B78: m | C78: =(C14*Piezas!$F$12+C15*Piezas!$F$13)/1000/Corte!$H$117 -> 24.081421 | D78: =(D14*Piezas!$F$12+D15*Piezas!$F$13)/1000/Corte!$H$117 -> 36.171943 | E78: =(E14*Piezas!$F$12+E15*Piezas!$F$13)/1000/Corte!$H$117 -> 55.360927 | F78: =(F14*Piezas!$F$12+F15*Piezas!$F$13)/1000/Corte!$H$117 -> 93.690342 | G78: =(G14*Piezas!$F$12+G15*Piezas!$F$13)/1000/Corte!$H$117 -> 155.71342 | H78: =(H14*Piezas!$F$12+H15*Piezas!$F$13)/1000/Corte!$H$117 -> 213.69255 | I78: =(I14*Piezas!$F$12+I15*Piezas!$F$13)/1000/Corte!$H$117 -> 287.55136 | J78: =(J14*Piezas!$F$12+J15*Piezas!$F$13)/1000/Corte!$H$117 -> 359.38062 | ... L78: =(L14*Piezas!$F$12+L15*Piezas!$F$13)/1000/Corte!$H$117 -> 477.11022
A79: Acero de madre de 0,9 mm | B79: t | C79: =C73*Corte!$D$63/1000/(1-Datos!$B$20) -> 2.1649998 | D79: =D73*Corte!$D$63/1000/(1-Datos!$B$20) -> 3.107198 | E79: =E73*Corte!$D$63/1000/(1-Datos!$B$20) -> 7.5197675 | F79: =F73*Corte!$D$63/1000/(1-Datos!$B$20) -> 18.217369 | G79: =G73*Corte!$D$63/1000/(1-Datos!$B$20) -> 32.181952 | H79: =H73*Corte!$D$63/1000/(1-Datos!$B$20) -> 45.23029 | I79: =I73*Corte!$D$63/1000/(1-Datos!$B$20) -> 63.038756 | J79: =J73*Corte!$D$63/1000/(1-Datos!$B$20) -> 80.892414 | ... L79: =L73*Corte!$D$63/1000/(1-Datos!$B$20) -> 104.97758
A80: Acero de madre de 1,25 mm | B80: t | C80: =C74*Corte!$D$64/1000/(1-Datos!$B$20) -> 0.87567664 | D80: =D74*Corte!$D$64/1000/(1-Datos!$B$20) -> 2.1134578 | E80: =E74*Corte!$D$64/1000/(1-Datos!$B$20) -> 3.8233663 | F80: =F74*Corte!$D$64/1000/(1-Datos!$B$20) -> 7.5350719 | G80: =G74*Corte!$D$64/1000/(1-Datos!$B$20) -> 12.522936 | H80: =H74*Corte!$D$64/1000/(1-Datos!$B$20) -> 17.802193 | I80: =I74*Corte!$D$64/1000/(1-Datos!$B$20) -> 24.530217 | J80: =J74*Corte!$D$64/1000/(1-Datos!$B$20) -> 31.477596 | ... L80: =L74*Corte!$D$64/1000/(1-Datos!$B$20) -> 41.22951
A81: Acero de madre de 1,6 mm | B81: t | C81: =C75*Corte!$D$65/1000/(1-Datos!$B$20) -> 6.8220602 | D81: =D75*Corte!$D$65/1000/(1-Datos!$B$20) -> 11.744137 | E81: =E75*Corte!$D$65/1000/(1-Datos!$B$20) -> 20.066798 | F81: =F75*Corte!$D$65/1000/(1-Datos!$B$20) -> 36.487587 | G81: =G75*Corte!$D$65/1000/(1-Datos!$B$20) -> 61.568452 | H81: =H75*Corte!$D$65/1000/(1-Datos!$B$20) -> 85.812248 | I81: =I75*Corte!$D$65/1000/(1-Datos!$B$20) -> 115.59968 | J81: =J75*Corte!$D$65/1000/(1-Datos!$B$20) -> 146.02882 | ... L81: =L75*Corte!$D$65/1000/(1-Datos!$B$20) -> 190.90711
A82: Acero de madre de 2,0 mm | B82: t | C82: =C76*Corte!$D$66/1000/(1-Datos!$B$20) -> 0.497724 | D82: =D76*Corte!$D$66/1000/(1-Datos!$B$20) -> 0.95776927 | E82: =E76*Corte!$D$66/1000/(1-Datos!$B$20) -> 1.847541 | F82: =F76*Corte!$D$66/1000/(1-Datos!$B$20) -> 3.607239 | G82: =G76*Corte!$D$66/1000/(1-Datos!$B$20) -> 6.300399 | H82: =H76*Corte!$D$66/1000/(1-Datos!$B$20) -> 9.1095973 | I82: =I76*Corte!$D$66/1000/(1-Datos!$B$20) -> 12.260093 | J82: =J76*Corte!$D$66/1000/(1-Datos!$B$20) -> 15.49104 | ... L82: =L76*Corte!$D$66/1000/(1-Datos!$B$20) -> 20.274254
A83: Acero de madre de 3,2 mm | B83: t | C83: =C77*Corte!$D$67/1000/(1-Datos!$B$20) -> 1.8903796 | D83: =D77*Corte!$D$67/1000/(1-Datos!$B$20) -> 3.0934089 | E83: =E77*Corte!$D$67/1000/(1-Datos!$B$20) -> 4.7791677 | F83: =F77*Corte!$D$67/1000/(1-Datos!$B$20) -> 8.0434874 | G83: =G77*Corte!$D$67/1000/(1-Datos!$B$20) -> 13.22812 | H83: =H77*Corte!$D$67/1000/(1-Datos!$B$20) -> 18.333424 | I83: =I77*Corte!$D$67/1000/(1-Datos!$B$20) -> 24.43874 | J83: =J77*Corte!$D$67/1000/(1-Datos!$B$20) -> 30.799171 | ... L83: =L77*Corte!$D$67/1000/(1-Datos!$B$20) -> 40.758363
A84: Acero de madre de 4,75 mm | B84: t | C84: =C78*Corte!$D$68/1000/(1-Datos!$B$20) -> 1.1264106 | D84: =D78*Corte!$D$68/1000/(1-Datos!$B$20) -> 1.6919458 | E84: =E78*Corte!$D$68/1000/(1-Datos!$B$20) -> 2.5895122 | F84: =F78*Corte!$D$68/1000/(1-Datos!$B$20) -> 4.382374 | G84: =G78*Corte!$D$68/1000/(1-Datos!$B$20) -> 7.2835088 | H84: =H78*Corte!$D$68/1000/(1-Datos!$B$20) -> 9.9954876 | I84: =I78*Corte!$D$68/1000/(1-Datos!$B$20) -> 13.45024 | J84: =J78*Corte!$D$68/1000/(1-Datos!$B$20) -> 16.81006 | ... L84: =L78*Corte!$D$68/1000/(1-Datos!$B$20) -> 22.316872
A85: Acero comprado | B85: t | C85: =SUM(C79:C84) -> 13.377251 | D85: =SUM(D79:D84) -> 22.707916 | E85: =SUM(E79:E84) -> 40.626153 | F85: =SUM(F79:F84) -> 78.273128 | G85: =SUM(G79:G84) -> 133.08537 | H85: =SUM(H79:H84) -> 186.28324 | I85: =SUM(I79:I84) -> 253.31773 | J85: =SUM(J79:J84) -> 321.4991 | ... L85: =SUM(L79:L84) -> 420.46368
A86: Costo del acero | B86: USD | C86: =SUMPRODUCT(C79:C84,Corte!$E$63:$E$68)*1000 -> 16348.992 | D86: =SUMPRODUCT(D79:D84,Corte!$E$63:$E$68)*1000 -> 27792.79 | E86: =SUMPRODUCT(E79:E84,Corte!$E$63:$E$68)*1000 -> 49912.309 | F86: =SUMPRODUCT(F79:F84,Corte!$E$63:$E$68)*1000 -> 96453.236 | G86: =SUMPRODUCT(G79:G84,Corte!$E$63:$E$68)*1000 -> 164097.58 | H86: =SUMPRODUCT(H79:H84,Corte!$E$63:$E$68)*1000 -> 229749.96 | I86: =SUMPRODUCT(I79:I84,Corte!$E$63:$E$68)*1000 -> 312530.09 | J86: =SUMPRODUCT(J79:J84,Corte!$E$63:$E$68)*1000 -> 396724.09 | ... L86: =SUMPRODUCT(L79:L84,Corte!$E$63:$E$68)*1000 -> 518723.83
A87: Scrap | B87: t | C87: =C85-C25 -> 1.4296429 | D87: =D85-D25 -> 2.7372961 | E87: =E85-E25 -> 4.5519031 | F87: =F85-F25 -> 8.1640191 | G87: =G85-G25 -> 13.534109 | H87: =H85-H25 -> 18.964701 | I87: =I85-I25 -> 26.069311 | J87: =J85-J25 -> 33.288752 | ... L87: =L85-L25 -> 42.770262
A88: Venta de scrap (resta) | B88: USD | C88: =-C87*Datos!$B$9 -> -357.41073 | D88: =-D87*Datos!$B$9 -> -684.32403 | E88: =-E87*Datos!$B$9 -> -1137.9758 | F88: =-F87*Datos!$B$9 -> -2041.0048 | G88: =-G87*Datos!$B$9 -> -3383.5273 | H88: =-H87*Datos!$B$9 -> -4741.1753 | I88: =-I87*Datos!$B$9 -> -6517.3277 | J88: =-J87*Datos!$B$9 -> -8322.1879 | ... L88: =-L87*Datos!$B$9 -> -10692.565
A89: Stock promedio (madres y flejes en proceso) | B89: t | C89: =SUMPRODUCT((Corte!$G$63:$G$68+C79:C84*Datos!$B$53/12-ABS(Corte!$G$63:$G$68-C79:C84*Datos!$B$53/12))/2+C79:C84*Datos!$B$50/52) -> 3.8588224 | D89: =SUMPRODUCT((Corte!$G$63:$G$68+D79:D84*Datos!$B$53/12-ABS(Corte!$G$63:$G$68-D79:D84*Datos!$B$53/12))/2+D79:D84*Datos!$B$50/52) -> 6.5503605 | E89: =SUMPRODUCT((Corte!$G$63:$G$68+E79:E84*Datos!$B$53/12-ABS(Corte!$G$63:$G$68-E79:E84*Datos!$B$53/12))/2+E79:E84*Datos!$B$50/52) -> 11.719082 | F89: =SUMPRODUCT((Corte!$G$63:$G$68+F79:F84*Datos!$B$53/12-ABS(Corte!$G$63:$G$68-F79:F84*Datos!$B$53/12))/2+F79:F84*Datos!$B$50/52) -> 22.578787 | G89: =SUMPRODUCT((Corte!$G$63:$G$68+G79:G84*Datos!$B$53/12-ABS(Corte!$G$63:$G$68-G79:G84*Datos!$B$53/12))/2+G79:G84*Datos!$B$50/52) -> 34.997897 | H89: =SUMPRODUCT((Corte!$G$63:$G$68+H79:H84*Datos!$B$53/12-ABS(Corte!$G$63:$G$68-H79:H84*Datos!$B$53/12))/2+H79:H84*Datos!$B$50/52) -> 39.16474 | I89: =SUMPRODUCT((Corte!$G$63:$G$68+I79:I84*Datos!$B$53/12-ABS(Corte!$G$63:$G$68-I79:I84*Datos!$B$53/12))/2+I79:I84*Datos!$B$50/52) -> 41.742989 | J89: =SUMPRODUCT((Corte!$G$63:$G$68+J79:J84*Datos!$B$53/12-ABS(Corte!$G$63:$G$68-J79:J84*Datos!$B$53/12))/2+J79:J84*Datos!$B$50/52) -> 44.36535 | ... L89: =SUMPRODUCT((Corte!$G$63:$G$68+L79:L84*Datos!$B$53/12-ABS(Corte!$G$63:$G$68-L79:L84*Datos!$B$53/12))/2+L79:L84*Datos!$B$50/52) -> 48.17168
A90: Costo financiero del stock | B90: USD | C90: =IF(C85=0,0,C89*C86/C85*Datos!$B$7) -> 565.92666 | D90: =IF(D85=0,0,D89*D86/D85*Datos!$B$7) -> 962.05813 | E90: =IF(E85=0,0,E89*E86/E85*Datos!$B$7) -> 1727.7338 | F90: =IF(F85=0,0,F89*F86/F85*Datos!$B$7) -> 3338.7659 | G90: =IF(G85=0,0,G89*G86/G85*Datos!$B$7) -> 5178.3936 | H90: =IF(H85=0,0,H89*H86/H85*Datos!$B$7) -> 5796.3974 | I90: =IF(I85=0,0,I89*I86/I85*Datos!$B$7) -> 6180.0366 | J90: =IF(J85=0,0,J89*J86/J85*Datos!$B$7) -> 6569.5251 | ... L90: =IF(L85=0,0,L89*L86/L85*Datos!$B$7) -> 7131.4977
A91: Horas de la cortadora longitudinal (máquina) | B91: h | C91: =SUM(C73:C78)/(Datos!$B$42*60)+SUMPRODUCT(C79:C84/Corte!$G$63:$G$68)*Datos!$B$43/60 -> 2.2178487 | D91: =SUM(D73:D78)/(Datos!$B$42*60)+SUMPRODUCT(D79:D84/Corte!$G$63:$G$68)*Datos!$B$43/60 -> 3.8014007 | E91: =SUM(E73:E78)/(Datos!$B$42*60)+SUMPRODUCT(E79:E84/Corte!$G$63:$G$68)*Datos!$B$43/60 -> 6.6948901 | F91: =SUM(F73:F78)/(Datos!$B$42*60)+SUMPRODUCT(F79:F84/Corte!$G$63:$G$68)*Datos!$B$43/60 -> 12.748181 | G91: =SUM(G73:G78)/(Datos!$B$42*60)+SUMPRODUCT(G79:G84/Corte!$G$63:$G$68)*Datos!$B$43/60 -> 21.616768 | H91: =SUM(H73:H78)/(Datos!$B$42*60)+SUMPRODUCT(H79:H84/Corte!$G$63:$G$68)*Datos!$B$43/60 -> 30.31597 | I91: =SUM(I73:I78)/(Datos!$B$42*60)+SUMPRODUCT(I79:I84/Corte!$G$63:$G$68)*Datos!$B$43/60 -> 41.188126 | J91: =SUM(J73:J78)/(Datos!$B$42*60)+SUMPRODUCT(J79:J84/Corte!$G$63:$G$68)*Datos!$B$43/60 -> 52.23701 | ... L91: =SUM(L73:L78)/(Datos!$B$42*60)+SUMPRODUCT(L79:L84/Corte!$G$63:$G$68)*Datos!$B$43/60 -> 68.460013
A92: Flejes de disco generados | B92: flejes | C92: =SUMPRODUCT(C79:C84/Corte!$G$63:$G$68*Corte!$F$63:$F$68) -> 2.8929795 | D92: =SUMPRODUCT(D79:D84/Corte!$G$63:$G$68*Corte!$F$63:$F$68) -> 5.9054329 | E92: =SUMPRODUCT(E79:E84/Corte!$G$63:$G$68*Corte!$F$63:$F$68) -> 10.87555 | F92: =SUMPRODUCT(F79:F84/Corte!$G$63:$G$68*Corte!$F$63:$F$68) -> 21.575437 | G92: =SUMPRODUCT(G79:G84/Corte!$G$63:$G$68*Corte!$F$63:$F$68) -> 36.396818 | H92: =SUMPRODUCT(H79:H84/Corte!$G$63:$G$68*Corte!$F$63:$F$68) -> 51.464516 | I92: =SUMPRODUCT(I79:I84/Corte!$G$63:$G$68*Corte!$F$63:$F$68) -> 70.584655 | J92: =SUMPRODUCT(J79:J84/Corte!$G$63:$G$68*Corte!$F$63:$F$68) -> 90.186217 | ... L92: =SUMPRODUCT(L79:L84/Corte!$G$63:$G$68*Corte!$F$63:$F$68) -> 117.90771
A93: Horas-hombre de corte: cortadora + línea + cambios de fleje | B93: h | C93: =C91*Datos!$B$44+SUM(C$8:C$15)/Datos!$B$41+C92*Datos!$B$46/60 -> 10.991926 | D93: =D91*Datos!$B$44+SUM(D$8:D$15)/Datos!$B$41+D92*Datos!$B$46/60 -> 18.302048 | E93: =E91*Datos!$B$44+SUM(E$8:E$15)/Datos!$B$41+E92*Datos!$B$46/60 -> 35.484706 | F93: =F91*Datos!$B$44+SUM(F$8:F$15)/Datos!$B$41+F92*Datos!$B$46/60 -> 73.596479 | G93: =G91*Datos!$B$44+SUM(G$8:G$15)/Datos!$B$41+G92*Datos!$B$46/60 -> 126.66813 | H93: =H91*Datos!$B$44+SUM(H$8:H$15)/Datos!$B$41+H92*Datos!$B$46/60 -> 177.86003 | I93: =I91*Datos!$B$44+SUM(I$8:I$15)/Datos!$B$41+I92*Datos!$B$46/60 -> 243.8929 | J93: =J91*Datos!$B$44+SUM(J$8:J$15)/Datos!$B$41+J92*Datos!$B$46/60 -> 310.79802 | ... L93: =L91*Datos!$B$44+SUM(L$8:L$15)/Datos!$B$41+L92*Datos!$B$46/60 -> 406.03852
A94: Mano de obra de corte | B94: USD | C94: =C93*Datos!$B$15 -> 69.043847 | D94: =D93*Datos!$B$15 -> 114.96109 | E94: =E93*Datos!$B$15 -> 222.89094 | F94: =F93*Datos!$B$15 -> 462.28333 | G94: =G93*Datos!$B$15 -> 795.64357 | H94: =H93*Datos!$B$15 -> 1117.1964 | I94: =I93*Datos!$B$15 -> 1531.9703 | J94: =J93*Datos!$B$15 -> 1952.223 | ... L94: =L93*Datos!$B$15 -> 2550.4595
A95: Mantenimiento de equipos | B95: USD | C95: =Datos!$E$117*Datos!$B$8 -> 5730 | D95: =Datos!$E$117*Datos!$B$8 -> 5730 | E95: =Datos!$E$117*Datos!$B$8 -> 5730 | F95: =Datos!$E$117*Datos!$B$8 -> 5730 | G95: =Datos!$E$117*Datos!$B$8 -> 5730 | H95: =Datos!$E$117*Datos!$B$8 -> 5730 | I95: =Datos!$E$117*Datos!$B$8 -> 5730 | J95: =Datos!$E$117*Datos!$B$8 -> 5730 | ... L95: =Datos!$E$117*Datos!$B$8 -> 5730
A96: COSTO ANUAL C | B96: USD | C96: =C86+C88+C90+C94+C95 -> 22356.552 | D96: =D86+D88+D90+D94+D95 -> 33915.486 | E96: =E86+E88+E90+E94+E95 -> 56454.958 | F96: =F86+F88+F90+F94+F95 -> 103943.28 | G96: =G86+G88+G90+G94+G95 -> 172418.09 | H96: =H86+H88+H90+H94+H95 -> 237652.38 | I96: =I86+I88+I90+I94+I95 -> 319454.77 | J96: =J86+J88+J90+J94+J95 -> 402653.65 | ... L96: =L86+L88+L90+L94+L95 -> 523443.22
A98: D — Hojas para cuerpos (dos guillotinas en serie) + fleje a medida para discos
A99: Acero comprado: hojas de cuerpo + fleje | B99: t | C99: =C54+C30 -> 13.698838 | D99: =D54+D30 -> 22.877784 | E99: =E54+E30 -> 41.24586 | F99: =F54+F30 -> 80.036026 | G99: =G54+G30 -> 136.44438 | H99: =H54+H30 -> 190.93281 | I99: =I54+I30 -> 259.29677 | J99: =J54+J30 -> 328.80476 | ... L99: =L54+L30 -> 430.9335
A100: Costo del acero | B100: USD | C100: =C55+C31 -> 17069.105 | D100: =D55+D31 -> 28516.564 | E100: =E55+E31 -> 51744.695 | F100: =F55+F31 -> 100938.29 | G100: =G55+G31 -> 172260.67 | H100: =H55+H31 -> 241122.78 | I100: =I55+I31 -> 327649.28 | J100: =J55+J31 -> 415618.15 | ... L100: =L55+L31 -> 544505.12
A101: Scrap | B101: t | C101: =C99-C25 -> 1.7512295 | D101: =D99-D25 -> 2.9071631 | E101: =E99-E25 -> 5.1716109 | F101: =F99-F25 -> 9.9269178 | G101: =G99-G25 -> 16.89312 | H101: =H99-H25 -> 23.614267 | I101: =I99-I25 -> 32.048354 | J101: =J99-J25 -> 40.594414 | ... L101: =L99-L25 -> 53.240082
A102: Venta de scrap (resta) | B102: USD | C102: =-C101*Datos!$B$9 -> -437.80738 | D102: =-D101*Datos!$B$9 -> -726.79079 | E102: =-E101*Datos!$B$9 -> -1292.9027 | F102: =-F101*Datos!$B$9 -> -2481.7294 | G102: =-G101*Datos!$B$9 -> -4223.2799 | H102: =-H101*Datos!$B$9 -> -5903.5668 | I102: =-I101*Datos!$B$9 -> -8012.0885 | J102: =-J101*Datos!$B$9 -> -10148.604 | ... L102: =-L101*Datos!$B$9 -> -13310.02
A103: Stock promedio: hojas + rollos de fleje | B103: t | C103: =C54*(Datos!$B$51/2/12+Datos!$B$50/52)+C37 -> 1.3457333 | D103: =D54*(Datos!$B$51/2/12+Datos!$B$50/52)+D37 -> 2.2547498 | E103: =E54*(Datos!$B$51/2/12+Datos!$B$50/52)+E37 -> 4.0881817 | F103: =F54*(Datos!$B$51/2/12+Datos!$B$50/52)+F37 -> 7.9644403 | G103: =G54*(Datos!$B$51/2/12+Datos!$B$50/52)+G37 -> 13.264021 | H103: =H54*(Datos!$B$51/2/12+Datos!$B$50/52)+H37 -> 17.331379 | I103: =I54*(Datos!$B$51/2/12+Datos!$B$50/52)+I37 -> 22.348354 | J103: =J54*(Datos!$B$51/2/12+Datos!$B$50/52)+J37 -> 27.370149 | ... L103: =L54*(Datos!$B$51/2/12+Datos!$B$50/52)+L37 -> 34.573375
A104: Costo financiero del stock | B104: USD | C104: =IF(C99=0,0,C103*C100/C99*Datos!$B$7) -> 201.21821 | D104: =IF(D99=0,0,D103*D100/D99*Datos!$B$7) -> 337.25846 | E104: =IF(E99=0,0,E103*E100/E99*Datos!$B$7) -> 615.45584 | F104: =IF(F99=0,0,F103*F100/F99*Datos!$B$7) -> 1205.3327 | G104: =IF(G99=0,0,G103*G100/G99*Datos!$B$7) -> 2009.4951 | H104: =IF(H99=0,0,H103*H100/H99*Datos!$B$7) -> 2626.4676 | I104: =IF(I99=0,0,I103*I100/I99*Datos!$B$7) -> 3388.7452 | J104: =IF(J99=0,0,J103*J100/J99*Datos!$B$7) -> 4151.5935 | ... L104: =IF(L99=0,0,L103*L100/L99*Datos!$B$7) -> 5242.2138
A105: Horas-hombre de corte: guillotinas 1 y 2 + cambios de fleje | B105: h | C105: =C56+C57+C40*Datos!$B$46/60 -> 3.0036818 | D105: =D56+D57+D40*Datos!$B$46/60 -> 4.9480799 | E105: =E56+E57+E40*Datos!$B$46/60 -> 9.7827233 | F105: =F56+F57+F40*Datos!$B$46/60 -> 20.536272 | G105: =G56+G57+G40*Datos!$B$46/60 -> 35.465962 | H105: =H56+H57+H40*Datos!$B$46/60 -> 49.788059 | I105: =I56+I57+I40*Datos!$B$46/60 -> 68.201012 | J105: =J56+J57+J40*Datos!$B$46/60 -> 86.882424 | ... L105: =L56+L57+L40*Datos!$B$46/60 -> 113.60639
A106: Mano de obra de corte | B106: USD | C106: =C105*Datos!$B$15 -> 18.867098 | D106: =D105*Datos!$B$15 -> 31.080493 | E106: =E105*Datos!$B$15 -> 61.448454 | F106: =F105*Datos!$B$15 -> 128.99498 | G106: =G105*Datos!$B$15 -> 222.7732 | H106: =H105*Datos!$B$15 -> 312.73493 | I106: =I105*Datos!$B$15 -> 428.39265 | J106: =J105*Datos!$B$15 -> 545.73665 | ... L106: =L105*Datos!$B$15 -> 713.59856
...
