Workbook

Sheet Links
A1: Links e IMPORTRANGE
A2: Pegar en B el link de cada Google Sheet. La primera vez, tocar la primera celda de cada bloque y «Permitir acceso». Todos los IMPORTRANGE del libro están en esta hoja; las demás la leen.
A3: Archivo | B3: Link | G3: Qué se importa | M3: Estado
A4: MRP (FLAMA_MRP) | B4: PEGAR ACÁ EL LINK DEL GOOGLE SHEET | G4: DEMANDA, MANUALES, RODANTES, RECARGAS, REVENDIDOS y POLITICA_STOCK | M4: =IF(ISERROR(B12),"Falta el link o «Permitir acceso»","OK") -> OK
A5: Aprovechamiento Manuales | B5: PEGAR ACÁ EL LINK DEL GOOGLE SHEET | G5: datos_base, parametros, Plan mensual, Demanda puesto y Resumen cap. con sobrestock | M5: =IF(ISERROR(B472),"Falta el link o «Permitir acceso»","OK") -> OK
A6: Aprovechamiento Carros | B6: PEGAR ACÁ EL LINK DEL GOOGLE SHEET | G6: datos_base, parametros, Plan mensual, Demanda por puesto y Resumen Capacidad | M6: =IF(ISERROR(B1011),"Falta el link o «Permitir acceso»","OK") -> OK
A7: Aprovechamiento Recargas Planta Industrial | B7: PEGAR ACÁ EL LINK DEL GOOGLE SHEET | G7: datos_base, parametros, Plan mensual, Demanda por puesto y Resumen Capacidad | M7: =IF(ISERROR(B1421),"Falta el link o «Permitir acceso»","OK") -> OK
A8: Análisis alternativas corte chapa | B8: PEGAR ACÁ EL LINK DEL GOOGLE SHEET | G8: Corte (hojas y piezas por hoja) y Piezas (masas y discos) | M8: =IF(ISERROR(B2191),"Falta el link o «Permitir acceso»","OK") -> OK
A11: MRP (FLAMA_MRP) · DEMANDA!C4:M50: demanda por producto (D01 a D47)
B12: =IFERROR(__xludf.DUMMYFUNCTION("IMPORTRANGE(Links!$B$4,""DEMANDA!C4:M50"")"),"Parte de la planta industrial") -> Parte de la planta industrial
A60: MRP (FLAMA_MRP) · MANUALES!B16:W75: consumo por unidad y compra por año
B61: =IFERROR(__xludf.DUMMYFUNCTION("IMPORTRANGE(Links!$B$4,""MANUALES!B16:W75"")"),"MP-01") -> MP-01
A122: MRP (FLAMA_MRP) · RODANTES!B16:W72: consumo por unidad y compra por año
B123: =IFERROR(__xludf.DUMMYFUNCTION("IMPORTRANGE(Links!$B$4,""RODANTES!B16:W72"")"),"MP-11") -> MP-11
A181: MRP (FLAMA_MRP) · RECARGAS!B16:AG37: consumo por unidad y compra por año
B182: =IFERROR(__xludf.DUMMYFUNCTION("IMPORTRANGE(Links!$B$4,""RECARGAS!B16:AG37"")"),"MP-33") -> MP-33
A205: MRP (FLAMA_MRP) · REVENDIDOS!B16:X25: consumo por unidad y compra por año
B206: =IFERROR(__xludf.DUMMYFUNCTION("IMPORTRANGE(Links!$B$4,""REVENDIDOS!B16:X25"")"),"RV-AGUA_10l") -> RV-AGUA_10l
A217: MRP (FLAMA_MRP) · POLITICA_STOCK!B5:B129: código
B218: =IFERROR(__xludf.DUMMYFUNCTION("IMPORTRANGE(Links!$B$4,""POLITICA_STOCK!B5:B129"")"),"MP-01") -> MP-01
A344: MRP (FLAMA_MRP) · POLITICA_STOCK!O5:P129: unidad de compra y contenido
B345: =IFERROR(__xludf.DUMMYFUNCTION("IMPORTRANGE(Links!$B$4,""POLITICA_STOCK!O5:P129"")"),"Paquete de 50 hojas") -> Paquete de 50 hojas
A471: Aprovechamiento Manuales · datos_base!B2:K29: producción y proyecciones
B472: =IFERROR(__xludf.DUMMYFUNCTION("IMPORTRANGE(Links!$B$5,""datos_base!B2:K29"")"),4178.736543) -> 4178.7365
A501: Aprovechamiento Manuales · Plan mensual!D1:P109: plan mensual por año (11 filas por año)
B502: =IFERROR(__xludf.DUMMYFUNCTION("IMPORTRANGE(Links!$B$5,""Plan mensual!D1:P109"")"),"Ene") -> Ene
A612: Aprovechamiento Manuales · parametros_manuales!K19:K44: tiempo tipo (s/u)
B613: =IFERROR(__xludf.DUMMYFUNCTION("IMPORTRANGE(Links!$B$5,""parametros_manuales!K19:K44"")"),60) -> 60
A640: Aprovechamiento Manuales · parametros_manuales!B7:B7: horas productivas por mes (1 turno)
B641: =IFERROR(__xludf.DUMMYFUNCTION("IMPORTRANGE(Links!$B$5,""parametros_manuales!B7:B7"")"),150) -> 150
A643: Aprovechamiento Manuales · Demanda puesto con sobrestock!N1:N279: unidades por puesto y año (28 filas por año)
B644: =IFERROR(__xludf.DUMMYFUNCTION("IMPORTRANGE(Links!$B$5,""Demanda puesto con sobrestock!N1:N279"")"),"Total anual") -> Total anual
A924: Aprovechamiento Manuales · Resumen cap. con sobrestock!B2:K85: aprovechamiento, máquinas y turnos
B925: =IFERROR(__xludf.DUMMYFUNCTION("IMPORTRANGE(Links!$B$5,""Resumen cap. con sobrestock!B2:K85"")"),0.0685537310673) -> 0.068553731
A1010: Aprovechamiento Carros · datos_base!B2:K12: proyección de carros y cilindros
B1011: =IFERROR(__xludf.DUMMYFUNCTION("IMPORTRANGE(Links!$B$6,""datos_base!B2:K12"")"),34.05179136) -> 34.051791
A1023: Aprovechamiento Carros · Plan mensual!D1:P109: plan mensual por año (11 filas por año)
B1024: =IFERROR(__xludf.DUMMYFUNCTION("IMPORTRANGE(Links!$B$6,""Plan mensual!D1:P109"")"),"Ene") -> Ene
A1134: Aprovechamiento Carros · parametros_carros!I19:I36: tiempo ponderado (min/u)
B1135: =IFERROR(__xludf.DUMMYFUNCTION("IMPORTRANGE(Links!$B$6,""parametros_carros!I19:I36"")"),1.7825) -> 1.7825
A1154: Aprovechamiento Carros · parametros_carros!B7:B7: horas productivas por mes (1 turno)
B1155: =IFERROR(__xludf.DUMMYFUNCTION("IMPORTRANGE(Links!$B$6,""parametros_carros!B7:B7"")"),150) -> 150
A1157: Aprovechamiento Carros · Demanda por puesto!N1:N199: horas por puesto y año (20 filas)
B1158: =IFERROR(__xludf.DUMMYFUNCTION("IMPORTRANGE(Links!$B$6,""Demanda por puesto!N1:N199"")"),"Total anual (h)") -> Total anual (h)
A1358: Aprovechamiento Carros · Resumen Capacidad!B2:K61: aprovechamiento, máquinas y turnos
B1359: =IFERROR(__xludf.DUMMYFUNCTION("IMPORTRANGE(Links!$B$6,""Resumen Capacidad!B2:K61"")"),0.0506816038352574) -> 0.050681604
A1420: Aprovechamiento Recargas Planta Industrial · datos_base!B2:K18: recargas por tipo
B1421: =IFERROR(__xludf.DUMMYFUNCTION("IMPORTRANGE(Links!$B$7,""datos_base!B2:K18"")"),1002.33729536048) -> 1002.3373
A1439: Aprovechamiento Recargas Planta Industrial · Plan mensual!D1:P318: plan mensual por año (32 filas por año)
B1440: =IFERROR(__xludf.DUMMYFUNCTION("IMPORTRANGE(Links!$B$7,""Plan mensual!D1:P318"")"),"Ene") -> Ene
A1759: Aprovechamiento Recargas Planta Industrial · parametros_recargas!N76:N98: tiempo tipo (s/u)
B1760: =IFERROR(__xludf.DUMMYFUNCTION("IMPORTRANGE(Links!$B$7,""parametros_recargas!N76:N98"")"),75) -> 75
A1784: Aprovechamiento Recargas Planta Industrial · parametros_recargas!B6:B6: horas productivas por mes (1 turno)
B1785: =IFERROR(__xludf.DUMMYFUNCTION("IMPORTRANGE(Links!$B$7,""parametros_recargas!B6:B6"")"),150) -> 150
A1787: Aprovechamiento Recargas Planta Industrial · Demanda por puesto!N1:N312: unidades por puesto y año (32 filas)
B1788: =IFERROR(__xludf.DUMMYFUNCTION("IMPORTRANGE(Links!$B$7,""Demanda por puesto!N1:N312"")"),"Total anual") -> Total anual
A2101: Aprovechamiento Recargas Planta Industrial · Resumen Capacidad!B2:K88: aprovechamiento, máquinas y turnos
B2102: =IFERROR(__xludf.DUMMYFUNCTION("IMPORTRANGE(Links!$B$7,""Resumen Capacidad!B2:K88"")"),0.0294969285801908) -> 0.029496929
A2190: Análisis alternativas corte chapa · Corte!B6:J14: hojas, franjas, piezas por hoja, aprovech.
B2191: =IFERROR(__xludf.DUMMYFUNCTION("IMPORTRANGE(Links!$B$8,""Corte!B6:J14"")"),1220) -> 1220
A2201: Análisis alternativas corte chapa · Piezas!D6:H13: cuerpos: Ø, espesor, alto, desarrollo, masa
B2202: =IFERROR(__xludf.DUMMYFUNCTION("IMPORTRANGE(Links!$B$8,""Piezas!D6:H13"")"),76.2) -> 76.2
A2211: Análisis alternativas corte chapa · Piezas!D18:L25: discos: espesor ... D0 adoptado
B2212: =IFERROR(__xludf.DUMMYFUNCTION("IMPORTRANGE(Links!$B$8,""Piezas!D18:L25"")"),0.9) -> 0.9

Sheet Resumen
A1: BALANCEO DE MATERIALES Y DE LÍNEA — planta industrial FLAMA
A2: Elegí el año en C3. Todo sale de las hojas que llegan por IMPORTRANGE (hoja Links).
A3: Año | C3: 2035
A5: 1) Producción contra demanda y contra lo que compra el MRP (año elegido)
A6: Línea | B6: Producto | C6: Demanda (Proyecciones) | D6: Producción (Aprovechamiento) | E6: Sobrestock (u) | F6: Sobrestock (%) | G6: ¿Producción ≥ demanda? | H6: El MRP compra para (u) | I6: ¿El MRP cubre la producción? | J6: MRP − producción (u)
A7: MANUALES | B7: Matafuego ABC 1 kg | C7: =INDEX(Links!$B$489:$K$489,1,(Resumen!$C$3-2025)) -> 32072.639 | D7: =INDEX(Links!$N$502:$N$610,(Resumen!$C$3-2026)*11+2) -> 32072.639 | E7: =D7-C7 -> 0 | F7: =IF(C7=0,0,D7/C7-1) -> 0 | G7: =IF(ROUND(D7-C7,1)>=0,"✔ Sí","✖ No") -> ✔ Sí | H7: =INDEX(Links!$C$16:$L$16,1,(Resumen!$C$3-2025)) -> 32072.639 | I7: =IF(ROUND(H7-D7,1)>=0,"✔ Sí","✖ No") -> ✔ Sí | J7: =H7-D7 -> 0
A8: MANUALES | B8: Matafuego ABC 2,5 kg | C8: =INDEX(Links!$B$490:$K$490,1,(Resumen!$C$3-2025)) -> 7424.8584 | D8: =INDEX(Links!$N$502:$N$610,(Resumen!$C$3-2026)*11+3) -> 7436.4584 | E8: =D8-C8 -> 11.6 | F8: =IF(C8=0,0,D8/C8-1) -> 0.0015623193 | G8: =IF(ROUND(D8-C8,1)>=0,"✔ Sí","✖ No") -> ✔ Sí | H8: =INDEX(Links!$C$17:$L$17,1,(Resumen!$C$3-2025)) -> 7424.8584 | I8: =IF(ROUND(H8-D8,1)>=0,"✔ Sí","✖ No") -> ✖ No | J8: =H8-D8 -> -11.6
A9: MANUALES | B9: Matafuego ABC 5 kg | C9: =INDEX(Links!$B$491:$K$491,1,(Resumen!$C$3-2025)) -> 30750.779 | D9: =INDEX(Links!$N$502:$N$610,(Resumen!$C$3-2026)*11+4) -> 30814.979 | E9: =D9-C9 -> 64.2 | F9: =IF(C9=0,0,D9/C9-1) -> 0.002087752 | G9: =IF(ROUND(D9-C9,1)>=0,"✔ Sí","✖ No") -> ✔ Sí | H9: =INDEX(Links!$C$18:$L$18,1,(Resumen!$C$3-2025)) -> 30860.771 | I9: =IF(ROUND(H9-D9,1)>=0,"✔ Sí","✖ No") -> ✔ Sí | J9: =H9-D9 -> 45.791966
A10: MANUALES | B10: Matafuego ABC 10 kg | C10: =INDEX(Links!$B$492:$K$492,1,(Resumen!$C$3-2025)) -> 1840.8481 | D10: =INDEX(Links!$N$502:$N$610,(Resumen!$C$3-2026)*11+5) -> 1844.9281 | E10: =D10-C10 -> 4.08 | F10: =IF(C10=0,0,D10/C10-1) -> 0.0022163698 | G10: =IF(ROUND(D10-C10,1)>=0,"✔ Sí","✖ No") -> ✔ Sí | H10: =INDEX(Links!$C$19:$L$19,1,(Resumen!$C$3-2025)) -> 1842.877 | I10: =IF(ROUND(H10-D10,1)>=0,"✔ Sí","✖ No") -> ✖ No | J10: =H10-D10 -> -2.0511058
A11: MANUALES | B11: Cilindro ABC 1 kg vacío | C11: =INDEX(Links!$B$496:$K$496,1,(Resumen!$C$3-2025)) -> 170548 | D11: =INDEX(Links!$N$502:$N$610,(Resumen!$C$3-2026)*11+6) -> 170548 | E11: =D11-C11 -> 0 | F11: =IF(C11=0,0,D11/C11-1) -> 0 | G11: =IF(ROUND(D11-C11,1)>=0,"✔ Sí","✖ No") -> ✔ Sí | H11: =INDEX(Links!$C$20:$L$20,1,(Resumen!$C$3-2025)) -> 170548 | I11: =IF(ROUND(H11-D11,1)>=0,"✔ Sí","✖ No") -> ✔ Sí | J11: =H11-D11 -> 0
A12: MANUALES | B12: Cilindro ABC 2,5 kg vacío | C12: =INDEX(Links!$B$497:$K$497,1,(Resumen!$C$3-2025)) -> 6669 | D12: =INDEX(Links!$N$502:$N$610,(Resumen!$C$3-2026)*11+7) -> 6689.88 | E12: =D12-C12 -> 20.88 | F12: =IF(C12=0,0,D12/C12-1) -> 0.0031309042 | G12: =IF(ROUND(D12-C12,1)>=0,"✔ Sí","✖ No") -> ✔ Sí | H12: =INDEX(Links!$C$21:$L$21,1,(Resumen!$C$3-2025)) -> 6669 | I12: =IF(ROUND(H12-D12,1)>=0,"✔ Sí","✖ No") -> ✖ No | J12: =H12-D12 -> -20.88
A13: MANUALES | B13: Cilindro ABC 5 kg vacío | C13: =INDEX(Links!$B$498:$K$498,1,(Resumen!$C$3-2025)) -> 32915 | D13: =INDEX(Links!$N$502:$N$610,(Resumen!$C$3-2026)*11+8) -> 33037.68 | E13: =D13-C13 -> 122.68 | F13: =IF(C13=0,0,D13/C13-1) -> 0.0037271761 | G13: =IF(ROUND(D13-C13,1)>=0,"✔ Sí","✖ No") -> ✔ Sí | H13: =INDEX(Links!$C$22:$L$22,1,(Resumen!$C$3-2025)) -> 32915 | I13: =IF(ROUND(H13-D13,1)>=0,"✔ Sí","✖ No") -> ✖ No | J13: =H13-D13 -> -122.68
A14: MANUALES | B14: Cilindro ABC 10 kg vacío | C14: =INDEX(Links!$B$499:$K$499,1,(Resumen!$C$3-2025)) -> 2011 | D14: =INDEX(Links!$N$502:$N$610,(Resumen!$C$3-2026)*11+9) -> 2018 | E14: =D14-C14 -> 7 | F14: =IF(C14=0,0,D14/C14-1) -> 0.0034808553 | G14: =IF(ROUND(D14-C14,1)>=0,"✔ Sí","✖ No") -> ✔ Sí | H14: =INDEX(Links!$C$23:$L$23,1,(Resumen!$C$3-2025)) -> 2011 | I14: =IF(ROUND(H14-D14,1)>=0,"✔ Sí","✖ No") -> ✖ No | J14: =H14-D14 -> -7
A15: RODANTES | B15: Carro ABC 25 kg | C15: =INDEX(Links!$B$1011:$K$1011,1,(Resumen!$C$3-2025)) -> 453.27053 | D15: =INDEX(Links!$N$1024:$N$1132,(Resumen!$C$3-2026)*11+2) -> 453.67053 | E15: =D15-C15 -> 0.4 | F15: =IF(C15=0,0,D15/C15-1) -> 0.00088247519 | G15: =IF(ROUND(D15-C15,1)>=0,"✔ Sí","✖ No") -> ✔ Sí | H15: =INDEX(Links!$C$24:$L$24,1,(Resumen!$C$3-2025)) -> 453.27053 | I15: =IF(ROUND(H15-D15,1)>=0,"✔ Sí","✖ No") -> ✖ No | J15: =H15-D15 -> -0.4
A16: RODANTES | B16: Carro ABC 50 kg | C16: =INDEX(Links!$B$1012:$K$1012,1,(Resumen!$C$3-2025)) -> 997.19517 | D16: =INDEX(Links!$N$1024:$N$1132,(Resumen!$C$3-2026)*11+3) -> 997.99517 | E16: =D16-C16 -> 0.8 | F16: =IF(C16=0,0,D16/C16-1) -> 0.00080225017 | G16: =IF(ROUND(D16-C16,1)>=0,"✔ Sí","✖ No") -> ✔ Sí | H16: =INDEX(Links!$C$25:$L$25,1,(Resumen!$C$3-2025)) -> 998.25998 | I16: =IF(ROUND(H16-D16,1)>=0,"✔ Sí","✖ No") -> ✔ Sí | J16: =H16-D16 -> 0.26480972
A17: RODANTES | B17: Carro ABC 70 kg | C17: =INDEX(Links!$B$1013:$K$1013,1,(Resumen!$C$3-2025)) -> 217.56986 | D17: =INDEX(Links!$N$1024:$N$1132,(Resumen!$C$3-2026)*11+4) -> 217.80986 | E17: =D17-C17 -> 0.24 | F17: =IF(C17=0,0,D17/C17-1) -> 0.001103094 | G17: =IF(ROUND(D17-C17,1)>=0,"✔ Sí","✖ No") -> ✔ Sí | H17: =INDEX(Links!$C$26:$L$26,1,(Resumen!$C$3-2025)) -> 217.56986 | I17: =IF(ROUND(H17-D17,1)>=0,"✔ Sí","✖ No") -> ✖ No | J17: =H17-D17 -> -0.24
A18: RODANTES | B18: Carro ABC 100 kg | C18: =INDEX(Links!$B$1014:$K$1014,1,(Resumen!$C$3-2025)) -> 145.04657 | D18: =INDEX(Links!$N$1024:$N$1132,(Resumen!$C$3-2026)*11+5) -> 145.20657 | E18: =D18-C18 -> 0.16 | F18: =IF(C18=0,0,D18/C18-1) -> 0.001103094 | G18: =IF(ROUND(D18-C18,1)>=0,"✔ Sí","✖ No") -> ✔ Sí | H18: =INDEX(Links!$C$27:$L$27,1,(Resumen!$C$3-2025)) -> 145.17607 | I18: =IF(ROUND(H18-D18,1)>=0,"✔ Sí","✖ No") -> ✔ Sí | J18: =H18-D18 -> -0.030496115
A19: RODANTES | B19: Cilindro ABC 25 kg vacío | C19: =INDEX(Links!$B$1018:$K$1018,1,(Resumen!$C$3-2025)) -> 322 | D19: =INDEX(Links!$N$1024:$N$1132,(Resumen!$C$3-2026)*11+6) -> 323.64 | E19: =D19-C19 -> 1.64 | F19: =IF(C19=0,0,D19/C19-1) -> 0.0050931677 | G19: =IF(ROUND(D19-C19,1)>=0,"✔ Sí","✖ No") -> ✔ Sí | H19: =INDEX(Links!$C$28:$L$28,1,(Resumen!$C$3-2025)) -> 322 | I19: =IF(ROUND(H19-D19,1)>=0,"✔ Sí","✖ No") -> ✖ No | J19: =H19-D19 -> -1.64
A20: RODANTES | B20: Cilindro ABC 50 kg vacío | C20: =INDEX(Links!$B$1019:$K$1019,1,(Resumen!$C$3-2025)) -> 708 | D20: =INDEX(Links!$N$1024:$N$1132,(Resumen!$C$3-2026)*11+7) -> 710.44 | E20: =D20-C20 -> 2.44 | F20: =IF(C20=0,0,D20/C20-1) -> 0.0034463277 | G20: =IF(ROUND(D20-C20,1)>=0,"✔ Sí","✖ No") -> ✔ Sí | H20: =INDEX(Links!$C$29:$L$29,1,(Resumen!$C$3-2025)) -> 708 | I20: =IF(ROUND(H20-D20,1)>=0,"✔ Sí","✖ No") -> ✖ No | J20: =H20-D20 -> -2.44
A21: RODANTES | B21: Cilindro ABC 70 kg vacío | C21: =INDEX(Links!$B$1020:$K$1020,1,(Resumen!$C$3-2025)) -> 155 | D21: =INDEX(Links!$N$1024:$N$1132,(Resumen!$C$3-2026)*11+8) -> 156.32 | E21: =D21-C21 -> 1.32 | F21: =IF(C21=0,0,D21/C21-1) -> 0.008516129 | G21: =IF(ROUND(D21-C21,1)>=0,"✔ Sí","✖ No") -> ✔ Sí | H21: =INDEX(Links!$C$30:$L$30,1,(Resumen!$C$3-2025)) -> 155 | I21: =IF(ROUND(H21-D21,1)>=0,"✔ Sí","✖ No") -> ✖ No | J21: =H21-D21 -> -1.32
A22: RODANTES | B22: Cilindro ABC 100 kg vacío | C22: =INDEX(Links!$B$1021:$K$1021,1,(Resumen!$C$3-2025)) -> 102 | D22: =INDEX(Links!$N$1024:$N$1132,(Resumen!$C$3-2026)*11+9) -> 102.24 | E22: =D22-C22 -> 0.24 | F22: =IF(C22=0,0,D22/C22-1) -> 0.0023529412 | G22: =IF(ROUND(D22-C22,1)>=0,"✔ Sí","✖ No") -> ✔ Sí | H22: =INDEX(Links!$C$31:$L$31,1,(Resumen!$C$3-2025)) -> 102 | I22: =IF(ROUND(H22-D22,1)>=0,"✔ Sí","✖ No") -> ✖ No | J22: =H22-D22 -> -0.24
A23: RECARGAS | B23: Recarga ABC 1 kg | C23: =INDEX(Links!$B$1421:$K$1421,1,(Resumen!$C$3-2025)) -> 56575.837 | D23: =INDEX(Links!$N$1440:$N$1757,(Resumen!$C$3-2026)*32+2) -> 56575.837 | E23: =D23-C23 -> 0 | F23: =IF(C23=0,0,D23/C23-1) -> 0 | G23: =IF(ROUND(D23-C23,1)>=0,"✔ Sí","✖ No") -> ✔ Sí | H23: =INDEX(Links!$C$32:$L$32,1,(Resumen!$C$3-2025)) -> 56487.491 | I23: =IF(ROUND(H23-D23,1)>=0,"✔ Sí","✖ No") -> ✖ No | J23: =H23-D23 -> -88.345775
A24: RECARGAS | B24: Recarga ABC 2,5 kg | C24: =INDEX(Links!$B$1422:$K$1422,1,(Resumen!$C$3-2025)) -> 4790.7101 | D24: =INDEX(Links!$N$1440:$N$1757,(Resumen!$C$3-2026)*32+3) -> 4860.7101 | E24: =D24-C24 -> 70 | F24: =IF(C24=0,0,D24/C24-1) -> 0.014611613 | G24: =IF(ROUND(D24-C24,1)>=0,"✔ Sí","✖ No") -> ✔ Sí | H24: =INDEX(Links!$C$33:$L$33,1,(Resumen!$C$3-2025)) -> 4783.2292 | I24: =IF(ROUND(H24-D24,1)>=0,"✔ Sí","✖ No") -> ✖ No | J24: =H24-D24 -> -77.480915
A25: RECARGAS | B25: Recarga ABC 5 kg | C25: =INDEX(Links!$B$1423:$K$1423,1,(Resumen!$C$3-2025)) -> 29139.32 | D25: =INDEX(Links!$N$1440:$N$1757,(Resumen!$C$3-2026)*32+4) -> 29554.32 | E25: =D25-C25 -> 415 | F25: =IF(C25=0,0,D25/C25-1) -> 0.014241925 | G25: =IF(ROUND(D25-C25,1)>=0,"✔ Sí","✖ No") -> ✔ Sí | H25: =INDEX(Links!$C$34:$L$34,1,(Resumen!$C$3-2025)) -> 30068.838 | I25: =IF(ROUND(H25-D25,1)>=0,"✔ Sí","✖ No") -> ✔ Sí | J25: =H25-D25 -> 514.51797
A26: RECARGAS | B26: Recarga ABC 10 kg | C26: =INDEX(Links!$B$1424:$K$1424,1,(Resumen!$C$3-2025)) -> 1725.3696 | D26: =INDEX(Links!$N$1440:$N$1757,(Resumen!$C$3-2026)*32+5) -> 1751.3696 | E26: =D26-C26 -> 26 | F26: =IF(C26=0,0,D26/C26-1) -> 0.015069235 | G26: =IF(ROUND(D26-C26,1)>=0,"✔ Sí","✖ No") -> ✔ Sí | H26: =INDEX(Links!$C$35:$L$35,1,(Resumen!$C$3-2025)) -> 1741.3814 | I26: =IF(ROUND(H26-D26,1)>=0,"✔ Sí","✖ No") -> ✖ No | J26: =H26-D26 -> -9.9881273
A27: RECARGAS | B27: Recarga Agua 10 l | C27: =INDEX(Links!$B$1425:$K$1425,1,(Resumen!$C$3-2025)) -> 2435.8331 | D27: =INDEX(Links!$N$1440:$N$1757,(Resumen!$C$3-2026)*32+6) -> 2471.8331 | E27: =D27-C27 -> 36 | F27: =IF(C27=0,0,D27/C27-1) -> 0.014779338 | G27: =IF(ROUND(D27-C27,1)>=0,"✔ Sí","✖ No") -> ✔ Sí | H27: =INDEX(Links!$C$36:$L$36,1,(Resumen!$C$3-2025)) -> 2458.5058 | I27: =IF(ROUND(H27-D27,1)>=0,"✔ Sí","✖ No") -> ✖ No | J27: =H27-D27 -> -13.327316
A28: RECARGAS | B28: Recarga AFFF 10 l | C28: =INDEX(Links!$B$1426:$K$1426,1,(Resumen!$C$3-2025)) -> 462.45859 | D28: =INDEX(Links!$N$1440:$N$1757,(Resumen!$C$3-2026)*32+7) -> 468.45859 | E28: =D28-C28 -> 6 | F28: =IF(C28=0,0,D28/C28-1) -> 0.012974135 | G28: =IF(ROUND(D28-C28,1)>=0,"✔ Sí","✖ No") -> ✔ Sí | H28: =INDEX(Links!$C$37:$L$37,1,(Resumen!$C$3-2025)) -> 466.91659 | I28: =IF(ROUND(H28-D28,1)>=0,"✔ Sí","✖ No") -> ✖ No | J28: =H28-D28 -> -1.541995
A29: RECARGAS | B29: Recarga AFFF 50 l s/ruedas | C29: =INDEX(Links!$B$1427:$K$1427,1,(Resumen!$C$3-2025)) -> 241.06683 | D29: =INDEX(Links!$N$1440:$N$1757,(Resumen!$C$3-2026)*32+8) -> 244.06683 | E29: =D29-C29 -> 3 | F29: =IF(C29=0,0,D29/C29-1) -> 0.012444682 | G29: =IF(ROUND(D29-C29,1)>=0,"✔ Sí","✖ No") -> ✔ Sí | H29: =INDEX(Links!$C$38:$L$38,1,(Resumen!$C$3-2025)) -> 243.56826 | I29: =IF(ROUND(H29-D29,1)>=0,"✔ Sí","✖ No") -> ✖ No | J29: =H29-D29 -> -0.49857283
A30: RECARGAS | B30: Recarga BC 5 kg | C30: =INDEX(Links!$B$1428:$K$1428,1,(Resumen!$C$3-2025)) -> 139.35636 | D30: =INDEX(Links!$N$1440:$N$1757,(Resumen!$C$3-2026)*32+9) -> 141.35636 | E30: =D30-C30 -> 2 | F30: =IF(C30=0,0,D30/C30-1) -> 0.014351696 | G30: =IF(ROUND(D30-C30,1)>=0,"✔ Sí","✖ No") -> ✔ Sí | H30: =INDEX(Links!$C$39:$L$39,1,(Resumen!$C$3-2025)) -> 140.86546 | I30: =IF(ROUND(H30-D30,1)>=0,"✔ Sí","✖ No") -> ✖ No | J30: =H30-D30 -> -0.49089279
A31: RECARGAS | B31: Recarga Sales K 6 l | C31: =INDEX(Links!$B$1429:$K$1429,1,(Resumen!$C$3-2025)) -> 1201.2428 | D31: =INDEX(Links!$N$1440:$N$1757,(Resumen!$C$3-2026)*32+10) -> 1218.2428 | E31: =D31-C31 -> 17 | F31: =IF(C31=0,0,D31/C31-1) -> 0.01415201 | G31: =IF(ROUND(D31-C31,1)>=0,"✔ Sí","✖ No") -> ✔ Sí | H31: =INDEX(Links!$C$40:$L$40,1,(Resumen!$C$3-2025)) -> 1212.3174 | I31: =IF(ROUND(H31-D31,1)>=0,"✔ Sí","✖ No") -> ✖ No | J31: =H31-D31 -> -5.9254075
A32: RECARGAS | B32: Recarga CO₂ 2 kg | C32: =INDEX(Links!$B$1430:$K$1430,1,(Resumen!$C$3-2025)) -> 6552.9133 | D32: =INDEX(Links!$N$1440:$N$1757,(Resumen!$C$3-2026)*32+11) -> 6648.9133 | E32: =D32-C32 -> 96 | F32: =IF(C32=0,0,D32/C32-1) -> 0.014649972 | G32: =IF(ROUND(D32-C32,1)>=0,"✔ Sí","✖ No") -> ✔ Sí | H32: =INDEX(Links!$C$41:$L$41,1,(Resumen!$C$3-2025)) -> 6542.6807 | I32: =IF(ROUND(H32-D32,1)>=0,"✔ Sí","✖ No") -> ✖ No | J32: =H32-D32 -> -106.23268
A33: RECARGAS | B33: Recarga CO₂ 5 kg | C33: =INDEX(Links!$B$1431:$K$1431,1,(Resumen!$C$3-2025)) -> 2239.4758 | D33: =INDEX(Links!$N$1440:$N$1757,(Resumen!$C$3-2026)*32+12) -> 2270.4758 | E33: =D33-C33 -> 31 | F33: =IF(C33=0,0,D33/C33-1) -> 0.013842525 | G33: =IF(ROUND(D33-C33,1)>=0,"✔ Sí","✖ No") -> ✔ Sí | H33: =INDEX(Links!$C$42:$L$42,1,(Resumen!$C$3-2025)) -> 2330.9482 | I33: =IF(ROUND(H33-D33,1)>=0,"✔ Sí","✖ No") -> ✔ Sí | J33: =H33-D33 -> 60.472471
A34: RECARGAS | B34: Recarga HCFC/HFC 5 kg | C34: =INDEX(Links!$B$1432:$K$1432,1,(Resumen!$C$3-2025)) -> 366.61986 | D34: =INDEX(Links!$N$1440:$N$1757,(Resumen!$C$3-2026)*32+13) -> 372.61986 | E34: =D34-C34 -> 6 | F34: =IF(C34=0,0,D34/C34-1) -> 0.016365726 | G34: =IF(ROUND(D34-C34,1)>=0,"✔ Sí","✖ No") -> ✔ Sí | H34: =INDEX(Links!$C$43:$L$43,1,(Resumen!$C$3-2025)) -> 370.07637 | I34: =IF(ROUND(H34-D34,1)>=0,"✔ Sí","✖ No") -> ✖ No | J34: =H34-D34 -> -2.543484
A35: RECARGAS | B35: Recarga Clase D 9 l | C35: =INDEX(Links!$B$1433:$K$1433,1,(Resumen!$C$3-2025)) -> 125.86907 | D35: =INDEX(Links!$N$1440:$N$1757,(Resumen!$C$3-2026)*32+14) -> 127.86907 | E35: =D35-C35 -> 2 | F35: =IF(C35=0,0,D35/C35-1) -> 0.015889527 | G35: =IF(ROUND(D35-C35,1)>=0,"✔ Sí","✖ No") -> ✔ Sí | H35: =INDEX(Links!$C$44:$L$44,1,(Resumen!$C$3-2025)) -> 127.11145 | I35: =IF(ROUND(H35-D35,1)>=0,"✔ Sí","✖ No") -> ✖ No | J35: =H35-D35 -> -0.75761821
A36: RECARGAS | B36: Recarga ABC 25 kg s/ruedas | C36: =INDEX(Links!$B$1434:$K$1434,1,(Resumen!$C$3-2025)) -> 300.32506 | D36: =INDEX(Links!$N$1440:$N$1757,(Resumen!$C$3-2026)*32+15) -> 305.32506 | E36: =D36-C36 -> 5 | F36: =IF(C36=0,0,D36/C36-1) -> 0.016648627 | G36: =IF(ROUND(D36-C36,1)>=0,"✔ Sí","✖ No") -> ✔ Sí | H36: =INDEX(Links!$C$45:$L$45,1,(Resumen!$C$3-2025)) -> 299.85609 | I36: =IF(ROUND(H36-D36,1)>=0,"✔ Sí","✖ No") -> ✖ No | J36: =H36-D36 -> -5.4689714
A37: RECARGAS | B37: Recarga ABC 50 kg s/ruedas | C37: =INDEX(Links!$B$1435:$K$1435,1,(Resumen!$C$3-2025)) -> 660.71513 | D37: =INDEX(Links!$N$1440:$N$1757,(Resumen!$C$3-2026)*32+16) -> 670.71513 | E37: =D37-C37 -> 10 | F37: =IF(C37=0,0,D37/C37-1) -> 0.015135116 | G37: =IF(ROUND(D37-C37,1)>=0,"✔ Sí","✖ No") -> ✔ Sí | H37: =INDEX(Links!$C$46:$L$46,1,(Resumen!$C$3-2025)) -> 670.0437 | I37: =IF(ROUND(H37-D37,1)>=0,"✔ Sí","✖ No") -> ✖ No | J37: =H37-D37 -> -0.67142631
A38: RECARGAS | B38: Recarga ABC 70 kg s/ruedas | C38: =INDEX(Links!$B$1436:$K$1436,1,(Resumen!$C$3-2025)) -> 144.15603 | D38: =INDEX(Links!$N$1440:$N$1757,(Resumen!$C$3-2026)*32+17) -> 147.15603 | E38: =D38-C38 -> 3 | F38: =IF(C38=0,0,D38/C38-1) -> 0.020810784 | G38: =IF(ROUND(D38-C38,1)>=0,"✔ Sí","✖ No") -> ✔ Sí | H38: =INDEX(Links!$C$47:$L$47,1,(Resumen!$C$3-2025)) -> 143.93092 | I38: =IF(ROUND(H38-D38,1)>=0,"✔ Sí","✖ No") -> ✖ No | J38: =H38-D38 -> -3.2251064
A39: RECARGAS | B39: Recarga ABC 100 kg s/ruedas | C39: =INDEX(Links!$B$1437:$K$1437,1,(Resumen!$C$3-2025)) -> 96.104019 | D39: =INDEX(Links!$N$1440:$N$1757,(Resumen!$C$3-2026)*32+18) -> 98.104019 | E39: =D39-C39 -> 2 | F39: =IF(C39=0,0,D39/C39-1) -> 0.020810784 | G39: =IF(ROUND(D39-C39,1)>=0,"✔ Sí","✖ No") -> ✔ Sí | H39: =INDEX(Links!$C$48:$L$48,1,(Resumen!$C$3-2025)) -> 98.544026 | I39: =IF(ROUND(H39-D39,1)>=0,"✔ Sí","✖ No") -> ✔ Sí | J39: =H39-D39 -> 0.44000699
A41: Totales por línea (año elegido)
A42: Línea | C42: Demanda | D42: Producción | E42: Sobrestock (u) | F42: Sobrestock (%) | G42: Productos con producción < demanda | H42: MRP compra para | I42: Productos que el MRP no cubre | J42: MRP − producción
A43: MANUALES | C43: =SUMIF($A$7:$A$39,$A43,C$7:C$39) -> 284232.12 | D43: =SUMIF($A$7:$A$39,$A43,D$7:D$39) -> 284462.56 | E43: =SUMIF($A$7:$A$39,$A43,E$7:E$39) -> 230.44 | F43: =IF(C43=0,0,D43/C43-1) -> 0.0008107458 | G43: =COUNTIFS($A$7:$A$39,$A43,$G$7:$G$39,"✖ No") -> 0 | H43: =SUMIF($A$7:$A$39,$A43,H$7:H$39) -> 284344.15 | I43: =COUNTIFS($A$7:$A$39,$A43,$I$7:$I$39,"✖ No") -> 5 | J43: =SUMIF($A$7:$A$39,$A43,J$7:J$39) -> -118.41914
A44: RODANTES | C44: =SUMIF($A$7:$A$39,$A44,C$7:C$39) -> 3100.0821 | D44: =SUMIF($A$7:$A$39,$A44,D$7:D$39) -> 3107.3221 | E44: =SUMIF($A$7:$A$39,$A44,E$7:E$39) -> 7.24 | F44: =IF(C44=0,0,D44/C44-1) -> 0.002335422 | G44: =COUNTIFS($A$7:$A$39,$A44,$G$7:$G$39,"✖ No") -> 0 | H44: =SUMIF($A$7:$A$39,$A44,H$7:H$39) -> 3101.2764 | I44: =COUNTIFS($A$7:$A$39,$A44,$I$7:$I$39,"✖ No") -> 6 | J44: =SUMIF($A$7:$A$39,$A44,J$7:J$39) -> -6.0456864
A45: RECARGAS | C45: =SUMIF($A$7:$A$39,$A45,C$7:C$39) -> 107197.37 | D45: =SUMIF($A$7:$A$39,$A45,D$7:D$39) -> 107927.37 | E45: =SUMIF($A$7:$A$39,$A45,E$7:E$39) -> 730 | F45: =IF(C45=0,0,D45/C45-1) -> 0.0068098684 | G45: =COUNTIFS($A$7:$A$39,$A45,$G$7:$G$39,"✖ No") -> 0 | H45: =SUMIF($A$7:$A$39,$A45,H$7:H$39) -> 108186.3 | I45: =COUNTIFS($A$7:$A$39,$A45,$I$7:$I$39,"✖ No") -> 14 | J45: =SUMIF($A$7:$A$39,$A45,J$7:J$39) -> 258.93216
A47: 2) Todos los años: sobrestock y checks por línea
A48: Línea | B48: Indicador | C48: 2026 | D48: 2027 | E48: 2028 | F48: 2029 | G48: 2030 | H48: 2031 | I48: 2032 | J48: 2033 | K48: 2034 | L48: 2035
A49: MANUALES | B49: Producción (u) | C49: =SUM(Links!$N$503:$N$510) -> 6855.3731 | D49: =SUM(Links!$N$514:$N$521) -> 10831.978 | E49: =SUM(Links!$N$525:$N$532) -> 22887.892 | F49: =SUM(Links!$N$536:$N$543) -> 50634.95 | G49: =SUM(Links!$N$547:$N$554) -> 88193.286 | H49: =SUM(Links!$N$558:$N$565) -> 123837.25 | I49: =SUM(Links!$N$569:$N$576) -> 170779.47 | J49: =SUM(Links!$N$580:$N$587) -> 218185.94 | K49: =SUM(Links!$N$591:$N$598) -> 246197.64 | L49: =SUM(Links!$N$602:$N$609) -> 284462.56
A50: MANUALES | B50: Demanda (u) | C50: =SUM(Links!$B$489:$B$492)+SUM(Links!$B$496:$B$499) -> 6821.3731 | D50: =SUM(Links!$C$489:$C$492)+SUM(Links!$C$496:$C$499) -> 10731.258 | E50: =SUM(Links!$D$489:$D$492)+SUM(Links!$D$496:$D$499) -> 22716.332 | F50: =SUM(Links!$E$489:$E$492)+SUM(Links!$E$496:$E$499) -> 50354.51 | G50: =SUM(Links!$F$489:$F$492)+SUM(Links!$F$496:$F$499) -> 87907.286 | H50: =SUM(Links!$G$489:$G$492)+SUM(Links!$G$496:$G$499) -> 123514.89 | I50: =SUM(Links!$H$489:$H$492)+SUM(Links!$H$496:$H$499) -> 170497.39 | J50: =SUM(Links!$I$489:$I$492)+SUM(Links!$I$496:$I$499) -> 217952.02 | K50: =SUM(Links!$J$489:$J$492)+SUM(Links!$J$496:$J$499) -> 245977 | L50: =SUM(Links!$K$489:$K$492)+SUM(Links!$K$496:$K$499) -> 284232.12
A51: MANUALES | B51: Sobrestock (%) | C51: =IF(C50=0,0,C49/C50-1) -> 0.0049843337 | D51: =IF(D50=0,0,D49/D50-1) -> 0.009385666 | E51: =IF(E50=0,0,E49/E50-1) -> 0.0075522755 | F51: =IF(F50=0,0,F49/F50-1) -> 0.0055693125 | G51: =IF(G50=0,0,G49/G50-1) -> 0.0032534277 | H51: =IF(H50=0,0,H49/H50-1) -> 0.0026098877 | I51: =IF(I50=0,0,I49/I50-1) -> 0.0016544535 | J51: =IF(J50=0,0,J49/J50-1) -> 0.0010732638 | ... L51: =IF(L50=0,0,L49/L50-1) -> 0.0008107458
A52: MANUALES | B52: Productos con producción < demanda | C52: =SUMPRODUCT(--(ROUND(Links!$N$503:$N$506-Links!$B$489:$B$492,1)<0))+SUMPRODUCT(--(ROUND(Links!$N$507:$N$510-Links!$B$496:$B$499,1)<0)) -> 0 | D52: =SUMPRODUCT(--(ROUND(Links!$N$514:$N$517-Links!$C$489:$C$492,1)<0))+SUMPRODUCT(--(ROUND(Links!$N$518:$N$521-Links!$C$496:$C$499,1)<0)) -> 0 | E52: =SUMPRODUCT(--(ROUND(Links!$N$525:$N$528-Links!$D$489:$D$492,1)<0))+SUMPRODUCT(--(ROUND(Links!$N$529:$N$532-Links!$D$496:$D$499,1)<0)) -> 0 | F52: =SUMPRODUCT(--(ROUND(Links!$N$536:$N$539-Links!$E$489:$E$492,1)<0))+SUMPRODUCT(--(ROUND(Links!$N$540:$N$543-Links!$E$496:$E$499,1)<0)) -> 0 | G52: =SUMPRODUCT(--(ROUND(Links!$N$547:$N$550-Links!$F$489:$F$492,1)<0))+SUMPRODUCT(--(ROUND(Links!$N$551:$N$554-Links!$F$496:$F$499,1)<0)) -> 0 | H52: =SUMPRODUCT(--(ROUND(Links!$N$558:$N$561-Links!$G$489:$G$492,1)<0))+SUMPRODUCT(--(ROUND(Links!$N$562:$N$565-Links!$G$496:$G$499,1)<0)) -> 0 | I52: =SUMPRODUCT(--(ROUND(Links!$N$569:$N$572-Links!$H$489:$H$492,1)<0))+SUMPRODUCT(--(ROUND(Links!$N$573:$N$576-Links!$H$496:$H$499,1)<0)) -> 0 | J52: =SUMPRODUCT(--(ROUND(Links!$N$580:$N$583-Links!$I$489:$I$492,1)<0))+SUMPRODUCT(--(ROUND(Links!$N$584:$N$587-Links!$I$496:$I$499,1)<0)) -> 0 | K52: =SUMPRODUCT(--(ROUND(Links!$N$591:$N$594-Links!$J$489:$J$492,1)<0))+SUMPRODUCT(--(ROUND(Links!$N$595:$N$598-Links!$J$496:$J$499,1)<0)) -> 0 | L52: =SUMPRODUCT(--(ROUND(Links!$N$602:$N$605-Links!$K$489:$K$492,1)<0))+SUMPRODUCT(--(ROUND(Links!$N$606:$N$609-Links!$K$496:$K$499,1)<0)) -> 0
A53: MANUALES | B53: Productos que el MRP no cubre | C53: =SUMPRODUCT(--(ROUND(Links!$C$16:$C$23-Links!$N$503:$N$510,1)<0)) -> 5 | D53: =SUMPRODUCT(--(ROUND(Links!$D$16:$D$23-Links!$N$514:$N$521,1)<0)) -> 5 | E53: =SUMPRODUCT(--(ROUND(Links!$E$16:$E$23-Links!$N$525:$N$532,1)<0)) -> 5 | F53: =SUMPRODUCT(--(ROUND(Links!$F$16:$F$23-Links!$N$536:$N$543,1)<0)) -> 5 | G53: =SUMPRODUCT(--(ROUND(Links!$G$16:$G$23-Links!$N$547:$N$554,1)<0)) -> 5 | H53: =SUMPRODUCT(--(ROUND(Links!$H$16:$H$23-Links!$N$558:$N$565,1)<0)) -> 5 | I53: =SUMPRODUCT(--(ROUND(Links!$I$16:$I$23-Links!$N$569:$N$576,1)<0)) -> 5 | J53: =SUMPRODUCT(--(ROUND(Links!$J$16:$J$23-Links!$N$580:$N$587,1)<0)) -> 5 | K53: =SUMPRODUCT(--(ROUND(Links!$K$16:$K$23-Links!$N$591:$N$598,1)<0)) -> 5 | L53: =SUMPRODUCT(--(ROUND(Links!$L$16:$L$23-Links!$N$602:$N$609,1)<0)) -> 5
A54: RODANTES | B54: Producción (u) | C54: =SUM(Links!$N$1025:$N$1032) -> 144.20717 | D54: =SUM(Links!$N$1036:$N$1043) -> 235.48859 | E54: =SUM(Links!$N$1047:$N$1054) -> 363.35416 | F54: =SUM(Links!$N$1058:$N$1065) -> 612.55941 | G54: =SUM(Links!$N$1069:$N$1076) -> 1009.184 | H54: =SUM(Links!$N$1080:$N$1087) -> 1397.0979 | I54: =SUM(Links!$N$1091:$N$1098) -> 1865.1129 | J54: =SUM(Links!$N$1102:$N$1109) -> 2346.9947 | K54: =SUM(Links!$N$1113:$N$1120) -> 2690.0297 | L54: =SUM(Links!$N$1124:$N$1131) -> 3107.3221
A55: RODANTES | B55: Demanda (u) | C55: =SUM(Links!$B$1011:$B$1014)+SUM(Links!$B$1018:$B$1021) -> 136.20717 | D55: =SUM(Links!$C$1011:$C$1014)+SUM(Links!$C$1018:$C$1021) -> 233.84859 | E55: =SUM(Links!$D$1011:$D$1014)+SUM(Links!$D$1018:$D$1021) -> 358.63416 | F55: =SUM(Links!$E$1011:$E$1014)+SUM(Links!$E$1018:$E$1021) -> 603.51941 | G55: =SUM(Links!$F$1011:$F$1014)+SUM(Links!$F$1018:$F$1021) -> 996.50401 | H55: =SUM(Links!$G$1011:$G$1014)+SUM(Links!$G$1018:$G$1021) -> 1388.5379 | I55: =SUM(Links!$H$1011:$H$1014)+SUM(Links!$H$1018:$H$1021) -> 1855.0729 | J55: =SUM(Links!$I$1011:$I$1014)+SUM(Links!$I$1018:$I$1021) -> 2339.3947 | K55: =SUM(Links!$J$1011:$J$1014)+SUM(Links!$J$1018:$J$1021) -> 2682.1097 | L55: =SUM(Links!$K$1011:$K$1014)+SUM(Links!$K$1018:$K$1021) -> 3100.0821
A56: RODANTES | B56: Sobrestock (%) | C56: =IF(C55=0,0,C54/C55-1) -> 0.058734061 | D56: =IF(D55=0,0,D54/D55-1) -> 0.0070130848 | E56: =IF(E55=0,0,E54/E55-1) -> 0.013161044 | F56: =IF(F55=0,0,F54/F55-1) -> 0.014978806 | G56: =IF(G55=0,0,G54/G55-1) -> 0.012724485 | H56: =IF(H55=0,0,H54/H55-1) -> 0.0061647578 | I56: =IF(I55=0,0,I54/I55-1) -> 0.0054121861 | J56: =IF(J55=0,0,J54/J55-1) -> 0.0032487036 | ... L56: =IF(L55=0,0,L54/L55-1) -> 0.002335422
A57: RODANTES | B57: Productos con producción < demanda | C57: =SUMPRODUCT(--(ROUND(Links!$N$1025:$N$1028-Links!$B$1011:$B$1014,1)<0))+SUMPRODUCT(--(ROUND(Links!$N$1029:$N$1032-Links!$B$1018:$B$1021,1)<0)) -> 0 | D57: =SUMPRODUCT(--(ROUND(Links!$N$1036:$N$1039-Links!$C$1011:$C$1014,1)<0))+SUMPRODUCT(--(ROUND(Links!$N$1040:$N$1043-Links!$C$1018:$C$1021,1)<0)) -> 0 | E57: =SUMPRODUCT(--(ROUND(Links!$N$1047:$N$1050-Links!$D$1011:$D$1014,1)<0))+SUMPRODUCT(--(ROUND(Links!$N$1051:$N$1054-Links!$D$1018:$D$1021,1)<0)) -> 0 | F57: =SUMPRODUCT(--(ROUND(Links!$N$1058:$N$1061-Links!$E$1011:$E$1014,1)<0))+SUMPRODUCT(--(ROUND(Links!$N$1062:$N$1065-Links!$E$1018:$E$1021,1)<0)) -> 0 | G57: =SUMPRODUCT(--(ROUND(Links!$N$1069:$N$1072-Links!$F$1011:$F$1014,1)<0))+SUMPRODUCT(--(ROUND(Links!$N$1073:$N$1076-Links!$F$1018:$F$1021,1)<0)) -> 0 | H57: =SUMPRODUCT(--(ROUND(Links!$N$1080:$N$1083-Links!$G$1011:$G$1014,1)<0))+SUMPRODUCT(--(ROUND(Links!$N$1084:$N$1087-Links!$G$1018:$G$1021,1)<0)) -> 0 | I57: =SUMPRODUCT(--(ROUND(Links!$N$1091:$N$1094-Links!$H$1011:$H$1014,1)<0))+SUMPRODUCT(--(ROUND(Links!$N$1095:$N$1098-Links!$H$1018:$H$1021,1)<0)) -> 0 | J57: =SUMPRODUCT(--(ROUND(Links!$N$1102:$N$1105-Links!$I$1011:$I$1014,1)<0))+SUMPRODUCT(--(ROUND(Links!$N$1106:$N$1109-Links!$I$1018:$I$1021,1)<0)) -> 0 | K57: =SUMPRODUCT(--(ROUND(Links!$N$1113:$N$1116-Links!$J$1011:$J$1014,1)<0))+SUMPRODUCT(--(ROUND(Links!$N$1117:$N$1120-Links!$J$1018:$J$1021,1)<0)) -> 0 | L57: =SUMPRODUCT(--(ROUND(Links!$N$1124:$N$1127-Links!$K$1011:$K$1014,1)<0))+SUMPRODUCT(--(ROUND(Links!$N$1128:$N$1131-Links!$K$1018:$K$1021,1)<0)) -> 0
A58: RODANTES | B58: Productos que el MRP no cubre | C58: =SUMPRODUCT(--(ROUND(Links!$C$24:$C$31-Links!$N$1025:$N$1032,1)<0)) -> 8 | D58: =SUMPRODUCT(--(ROUND(Links!$D$24:$D$31-Links!$N$1036:$N$1043,1)<0)) -> 7 | E58: =SUMPRODUCT(--(ROUND(Links!$E$24:$E$31-Links!$N$1047:$N$1054,1)<0)) -> 6 | F58: =SUMPRODUCT(--(ROUND(Links!$F$24:$F$31-Links!$N$1058:$N$1065,1)<0)) -> 7 | G58: =SUMPRODUCT(--(ROUND(Links!$G$24:$G$31-Links!$N$1069:$N$1076,1)<0)) -> 7 | H58: =SUMPRODUCT(--(ROUND(Links!$H$24:$H$31-Links!$N$1080:$N$1087,1)<0)) -> 6 | I58: =SUMPRODUCT(--(ROUND(Links!$I$24:$I$31-Links!$N$1091:$N$1098,1)<0)) -> 7 | J58: =SUMPRODUCT(--(ROUND(Links!$J$24:$J$31-Links!$N$1102:$N$1109,1)<0)) -> 7 | K58: =SUMPRODUCT(--(ROUND(Links!$K$24:$K$31-Links!$N$1113:$N$1120,1)<0)) -> 7 | L58: =SUMPRODUCT(--(ROUND(Links!$L$24:$L$31-Links!$N$1124:$N$1131,1)<0)) -> 6
A59: RECARGAS | B59: Producción (u) | C59: =SUM(Links!$N$1441:$N$1457) -> 1968.5957 | D59: =SUM(Links!$N$1473:$N$1489) -> 8865.104 | E59: =SUM(Links!$N$1505:$N$1521) -> 17794.662 | F59: =SUM(Links!$N$1537:$N$1553) -> 33024.603 | G59: =SUM(Links!$N$1569:$N$1585) -> 48661.376 | H59: =SUM(Links!$N$1601:$N$1617) -> 66252.19 | I59: =SUM(Links!$N$1633:$N$1649) -> 82312.116 | J59: =SUM(Links!$N$1665:$N$1681) -> 93600.624 | K59: =SUM(Links!$N$1697:$N$1713) -> 100694.14 | L59: =SUM(Links!$N$1729:$N$1745) -> 107927.37
A60: RECARGAS | B60: Demanda (u) | C60: =SUM(Links!$B$1421:$B$1437) -> 1968.5957 | D60: =SUM(Links!$C$1421:$C$1437) -> 8838.104 | E60: =SUM(Links!$D$1421:$D$1437) -> 17721.662 | F60: =SUM(Links!$E$1421:$E$1437) -> 32873.603 | G60: =SUM(Links!$F$1421:$F$1437) -> 48386.376 | H60: =SUM(Links!$G$1421:$G$1437) -> 65859.19 | I60: =SUM(Links!$H$1421:$H$1437) -> 81795.116 | J60: =SUM(Links!$I$1421:$I$1437) -> 92988.624 | K60: =SUM(Links!$J$1421:$J$1437) -> 100019.14 | L60: =SUM(Links!$K$1421:$K$1437) -> 107197.37
A61: RECARGAS | B61: Sobrestock (%) | C61: =IF(C60=0,0,C59/C60-1) -> 0 | D61: =IF(D60=0,0,D59/D60-1) -> 0.0030549539 | E61: =IF(E60=0,0,E59/E60-1) -> 0.0041192525 | F61: =IF(F60=0,0,F59/F60-1) -> 0.0045933511 | G61: =IF(G60=0,0,G59/G60-1) -> 0.005683418 | H61: =IF(H60=0,0,H59/H60-1) -> 0.0059672765 | I61: =IF(I60=0,0,I59/I60-1) -> 0.0063206708 | J61: =IF(J60=0,0,J59/J60-1) -> 0.0065814502 | ... L61: =IF(L60=0,0,L59/L60-1) -> 0.0068098684
A62: RECARGAS | B62: Productos con producción < demanda | C62: =SUMPRODUCT(--(ROUND(Links!$N$1441:$N$1457-Links!$B$1421:$B$1437,1)<0)) -> 0 | D62: =SUMPRODUCT(--(ROUND(Links!$N$1473:$N$1489-Links!$C$1421:$C$1437,1)<0)) -> 0 | E62: =SUMPRODUCT(--(ROUND(Links!$N$1505:$N$1521-Links!$D$1421:$D$1437,1)<0)) -> 0 | F62: =SUMPRODUCT(--(ROUND(Links!$N$1537:$N$1553-Links!$E$1421:$E$1437,1)<0)) -> 0 | G62: =SUMPRODUCT(--(ROUND(Links!$N$1569:$N$1585-Links!$F$1421:$F$1437,1)<0)) -> 0 | H62: =SUMPRODUCT(--(ROUND(Links!$N$1601:$N$1617-Links!$G$1421:$G$1437,1)<0)) -> 0 | I62: =SUMPRODUCT(--(ROUND(Links!$N$1633:$N$1649-Links!$H$1421:$H$1437,1)<0)) -> 0 | J62: =SUMPRODUCT(--(ROUND(Links!$N$1665:$N$1681-Links!$I$1421:$I$1437,1)<0)) -> 0 | K62: =SUMPRODUCT(--(ROUND(Links!$N$1697:$N$1713-Links!$J$1421:$J$1437,1)<0)) -> 0 | L62: =SUMPRODUCT(--(ROUND(Links!$N$1729:$N$1745-Links!$K$1421:$K$1437,1)<0)) -> 0
A63: RECARGAS | B63: Productos que el MRP no cubre | C63: =SUMPRODUCT(--(ROUND(Links!$C$32:$C$48-Links!$N$1441:$N$1457,1)<0)) -> 3 | D63: =SUMPRODUCT(--(ROUND(Links!$D$32:$D$48-Links!$N$1473:$N$1489,1)<0)) -> 12 | E63: =SUMPRODUCT(--(ROUND(Links!$E$32:$E$48-Links!$N$1505:$N$1521,1)<0)) -> 11 | F63: =SUMPRODUCT(--(ROUND(Links!$F$32:$F$48-Links!$N$1537:$N$1553,1)<0)) -> 13 | G63: =SUMPRODUCT(--(ROUND(Links!$G$32:$G$48-Links!$N$1569:$N$1585,1)<0)) -> 12 | H63: =SUMPRODUCT(--(ROUND(Links!$H$32:$H$48-Links!$N$1601:$N$1617,1)<0)) -> 12 | I63: =SUMPRODUCT(--(ROUND(Links!$I$32:$I$48-Links!$N$1633:$N$1649,1)<0)) -> 12 | J63: =SUMPRODUCT(--(ROUND(Links!$J$32:$J$48-Links!$N$1665:$N$1681,1)<0)) -> 13 | K63: =SUMPRODUCT(--(ROUND(Links!$K$32:$K$48-Links!$N$1697:$N$1713,1)<0)) -> 14 | L63: =SUMPRODUCT(--(ROUND(Links!$L$32:$L$48-Links!$N$1729:$N$1745,1)<0)) -> 14
A65: Demanda = Proyecciones (manuales y carros: datos_base de cada Aprovechamiento; recargas: Proyecciones × parte de la planta industrial). Producción = Plan mensual de cada Aprovechamiento (incluye sustitutos). MRP = DEMANDA del MRP, con la que compra la materia prima.
A66: Revendidos no se fabrican: la compra del MRP es el producto terminado (hoja Materiales).

Sheet Esquema materiales
A1: ESQUEMA DEL BALANCE DE MATERIALES (año elegido en Resumen) — los números salen de la hoja Materiales
A2: Azul: materia prima · amarillo: semielaborados · verde: producto terminado · rojo: scrap, desechos y mermas · gris: checks. Editable: los textos son fórmulas.
B4: LÍNEA DE MANUALES
B5: ="MATERIA PRIMA"&CHAR(10)&"Chapa: "&TEXT(Materiales!$C$7,"#,##0")&" hojas"&CHAR(10)&"Fleje: "&TEXT(Materiales!$C$8,"#,##0")&" kg"&CHAR(10)&"Polvo ABC: "&TEXT(Materiales!$C$15,"#,##0")&" kg"&CHAR(10)&"Componentes: "&TEXT(Materiales!$C$17,"#,##0")&" u" -> MATERIA PRIMA Chapa: 10,604 hojas Fleje: 100,701 kg Polvo ABC: 230,062 kg Componentes: 693,428 u | G5: ➜ | H5: ="CORTE"&CHAR(10)&TEXT(Materiales!$G$22,"#,##0")&" planchuelas"&CHAR(10)&TEXT(Materiales!$G$23,"#,##0")&" discos" -> CORTE 284,463 planchuelas 568,925 discos | M5: ➜ | N5: ="EMBUTIDO Y SOLDADURA"&CHAR(10)&TEXT(Materiales!$G$24,"#,##0")&" casquetes"&CHAR(10)&TEXT(Materiales!$G$26,"#,##0")&" recipientes" -> EMBUTIDO Y SOLDADURA 568,925 casquetes 284,463 recipientes | S5: ➜ | T5: ="TERMINACIÓN"&CHAR(10)&"PH, secado, granallado, pintura"&CHAR(10)&TEXT(Materiales!$G$27,"#,##0")&" recipientes pintados" -> TERMINACIÓN PH, secado, granallado, pintura 284,463 recipientes pintados | Y5: ➜ | Z5: ="CARGA Y ARMADO"&CHAR(10)&"polvo, válvula, N₂, ensayo de pérdidas" -> CARGA Y ARMADO polvo, válvula, N₂, ensayo de pérdidas | AE5: ➜ | AF5: ="PRODUCTO TERMINADO"&CHAR(10)&TEXT(Materiales!$C$51,"#,##0")&" u"&CHAR(10)&"matafuegos 1 a 10 kg y cilindros vacíos" -> PRODUCTO TERMINADO 284,463 u matafuegos 1 a 10 kg y cilindros vacíos | AL5: ="CHECKS "&Resumen!$C$3&""&CHAR(10)&"Producción ≥ demanda: "&IF(Resumen!$G$43=0,"✔","✖ "&Resumen!$G$43&" productos")&CHAR(10)&"Sobrestock: "&TEXT(Resumen!$F$43,"0.0%")&CHAR(10)&"MRP cubre la producción: "&IF(Resumen!$I$43=0,"✔","✖ "&Resumen!$I$43&" productos") -> CHECKS 2035 Producción ≥ demanda: ✔ Sobrestock: 0.1% MRP cubre la producción: ✖ 5 productos
J12: ▼ | P12: ▼ | V12: ▼ | AB12: ▼
H13: ="SCRAP Y MERMAS"&CHAR(10)&"Chatarra: "&TEXT(Materiales!$C$32+Materiales!$C$33,"#,##0")&" kg (recortes y esqueleto de fleje)"&CHAR(10)&"Desechos: "&TEXT(Materiales!$C$34+Materiales!$C$37+Materiales!$C$38,"#,##0")&" kg (salpicadura, granalla, pintura)"&CHAR(10)&"Gases: "&TEXT(Materiales!$C$35,"#,##0")&" m³" -> SCRAP Y MERMAS Chatarra: 42,322 kg (recortes y esqueleto de fleje) Desechos: 23,236 kg (salpicadura, granalla, pintura) Gases: 8,199 m³
B19: LÍNEA DE CARROS
B20: ="MATERIA PRIMA"&CHAR(10)&"Chapa: "&TEXT(Materiales!$C$61,"#,##0")&" hojas"&CHAR(10)&"Casquetes y cuplas: "&TEXT(Materiales!$C$62,"#,##0")&" u"&CHAR(10)&"Polvo ABC 90: "&TEXT(Materiales!$C$68,"#,##0")&" kg"&CHAR(10)&"Caños y barras: "&TEXT(Materiales!$C$63,"#,##0.0")&" barras" -> MATERIA PRIMA Chapa: 515 hojas Casquetes y cuplas: 9,322 u Polvo ABC 90: 91,919 kg Caños y barras: 783.5 barras | G20: ➜ | H20: ="CORTE Y ROLADO"&CHAR(10)&TEXT(Materiales!$G$75,"#,##0")&" planchuelas"&CHAR(10)&TEXT(Materiales!$G$76,"#,##0")&" virolas" -> CORTE Y ROLADO 3,107 planchuelas 3,107 virolas | M20: ➜ | N20: ="ARMADO Y SOLDADURA"&CHAR(10)&TEXT(Materiales!$G$77,"#,##0")&" recipientes"&CHAR(10)&"accesorios del carro" -> ARMADO Y SOLDADURA 3,107 recipientes accesorios del carro | S20: ➜ | T20: ="PH, SECADO Y PINTURA"&CHAR(10)&TEXT(Materiales!$G$79,"#,##0")&" recipientes"&CHAR(10)&"(pintura tercerizada)" -> PH, SECADO Y PINTURA 3,107 recipientes (pintura tercerizada) | Y20: ➜ | Z20: ="CARGA Y ARMADO"&CHAR(10)&TEXT(Materiales!$G$80,"#,##0")&" carros" -> CARGA Y ARMADO 1,815 carros | AE20: ➜ | AF20: ="PRODUCTO TERMINADO"&CHAR(10)&TEXT(Materiales!$C$101,"#,##0")&" u"&CHAR(10)&"carros 25 a 100 kg y cilindros vacíos" -> PRODUCTO TERMINADO 3,107 u carros 25 a 100 kg y cilindros vacíos | AL20: ="CHECKS "&Resumen!$C$3&""&CHAR(10)&"Producción ≥ demanda: "&IF(Resumen!$G$44=0,"✔","✖ "&Resumen!$G$44&" productos")&CHAR(10)&"Sobrestock: "&TEXT(Resumen!$F$44,"0.0%")&CHAR(10)&"MRP cubre la producción: "&IF(Resumen!$I$44=0,"✔","✖ "&Resumen!$I$44&" productos") -> CHECKS 2035 Producción ≥ demanda: ✔ Sobrestock: 0.2% MRP cubre la producción: ✖ 6 productos
J27: ▼ | P27: ▼ | V27: ▼ | AB27: ▼
H28: ="SCRAP Y MERMAS"&CHAR(10)&"Chatarra de chapa: "&TEXT(Materiales!$C$84,"#,##0")&" kg"&CHAR(10)&"Recorte de caño y barra: "&TEXT(Materiales!$C$85,"#,##0.0")&" m"&CHAR(10)&"Desechos: "&TEXT(Materiales!$C$86,"#,##0.0")&" kg y "&TEXT(Materiales!$C$88,"#,##0")&" abrasivos" -> SCRAP Y MERMAS Chatarra de chapa: 10,012 kg Recorte de caño y barra: 223.5 m Desechos: 69.5 kg y 176 abrasivos
B34: LÍNEA DE RECARGAS
B35: ="MATERIA PRIMA"&CHAR(10)&"Polvos: "&TEXT(Materiales!$C$111,"#,##0")&" kg"&CHAR(10)&"CO₂ y limpio: "&TEXT(Materiales!$C$112,"#,##0")&" kg"&CHAR(10)&"Líquidos: "&TEXT(Materiales!$C$113,"#,##0")&" L"&CHAR(10)&"Repuestos e identificación: "&TEXT(Materiales!$C$116+Materiales!$C$117,"#,##0")&" u" -> MATERIA PRIMA Polvos: 54,828 kg CO₂ y limpio: 2,651 kg Líquidos: 7,926 L Repuestos e identificación: 622,638 u | G35: ➜ | H35: ="RECEPCIÓN Y DESCARGA"&CHAR(10)&TEXT(Materiales!$C$121,"#,##0")&" recibidos"&CHAR(10)&TEXT(Materiales!$C$122,"#,##0")&" descargados" -> RECEPCIÓN Y DESCARGA 115,783 recibidos 106,704 descargados | M35: ➜ | N35: ="DESARME Y PH"&CHAR(10)&TEXT(Materiales!$C$123,"#,##0")&" desarmados"&CHAR(10)&TEXT(Materiales!$C$124,"#,##0")&" con PH" -> DESARME Y PH 109,297 desarmados 30,659 con PH | S35: ➜ | T35: ="SECADO Y PINTURA"&CHAR(10)&TEXT(Materiales!$C$125,"#,##0")&" secados"&CHAR(10)&TEXT(Materiales!$C$126,"#,##0")&" pintados" -> SECADO Y PINTURA 28,526 secados 17,367 pintados | Y35: ➜ | Z35: ="CARGA Y ENSAYO"&CHAR(10)&TEXT(Materiales!$C$127,"#,##0")&" cargados"&CHAR(10)&TEXT(Materiales!$C$128,"#,##0")&" ensayados" -> CARGA Y ENSAYO 100,780 cargados 115,783 ensayados | AE35: ➜ | AF35: ="PRODUCTO TERMINADO"&CHAR(10)&TEXT(Materiales!$C$146,"#,##0")&" recargas"&CHAR(10)&"precintadas y etiquetadas" -> PRODUCTO TERMINADO 107,927 recargas precintadas y etiquetadas | AL35: ="CHECKS "&Resumen!$C$3&""&CHAR(10)&"Producción ≥ demanda: "&IF(Resumen!$G$45=0,"✔","✖ "&Resumen!$G$45&" productos")&CHAR(10)&"Sobrestock: "&TEXT(Resumen!$F$45,"0.0%")&CHAR(10)&"MRP cubre la producción: "&IF(Resumen!$I$45=0,"✔","✖ "&Resumen!$I$45&" productos") -> CHECKS 2035 Producción ≥ demanda: ✔ Sobrestock: 0.7% MRP cubre la producción: ✖ 14 productos
J42: ▼ | P42: ▼ | V42: ▼ | AB42: ▼
H43: ="SCRAP Y MERMAS"&CHAR(10)&"Polvo a descarte: "&TEXT(Materiales!$C$133,"#,##0")&" kg"&CHAR(10)&"Líquidos: "&TEXT(Materiales!$C$134,"#,##0")&" L"&CHAR(10)&"Equipos inutilizados: "&TEXT(Materiales!$C$135,"#,##0")&" (chatarra)" -> SCRAP Y MERMAS Polvo a descarte: 54,828 kg Líquidos: 48,916 L Equipos inutilizados: 9,114 (chatarra)
B49: REVENDIDOS
B50: ="COMPRA"&CHAR(10)&TEXT(Materiales!$C$159,"#,##0")&" equipos" -> COMPRA 18,027 equipos | G50: ➜ | H50: ="VENTA"&CHAR(10)&TEXT(Materiales!$C$159,"#,##0")&" equipos" -> VENTA 18,027 equipos

Sheet Esquema linea
A1: ESQUEMA DEL BALANCEO DE LÍNEA (año elegido en Resumen) — cada caja es un puesto, en orden de proceso
A2: Color por aprovechamiento: verde < 75 % · amarillo 75 a 90 % · rojo ≥ 90 % (umbral). El borde grueso marca el cuello de botella. Los números salen de la hoja Linea.
B4: LÍNEA DE MANUALES | N4: ="Takt "&TEXT(Linea!$C$8,"#,##0.0")&" s/u · contenido "&TEXT(Linea!$C$9,"#,##0.0")&" s/u · eficiencia de balanceo "&TEXT(Linea!$C$15,"0%")&" · cuello: "&Linea!$C$13&" ("&TEXT(Linea!$C$14,"0%")&")" -> Takt 16.2 s/u · contenido 754.1 s/u · eficiencia de balanceo 78% · cuello: Soldadura longitudinal — 2,5 a 10 kg (79%)
B5: =Linea!$A$19&". "&Linea!$B$19&CHAR(10)&Linea!$I$19&" recurso(s)" -> 1. Recepción de materia prima 4 recurso(s) | I5: =Linea!$A$20&". "&Linea!$B$20&CHAR(10)&Linea!$I$20&" recurso(s)" -> 2. Corte de chapa — 1.er corte en franjas (guillotina 1, manuales + carros) 1 recurso(s) | P5: =Linea!$A$21&". "&Linea!$B$21&CHAR(10)&Linea!$I$21&" recurso(s)" -> 3. Corte de chapa — 2.º corte en piezas (guillotina 2, manuales + carros) 1 recurso(s) | W5: =Linea!$A$22&". "&Linea!$B$22&CHAR(10)&Linea!$I$22&" recurso(s)" -> 4. Corte de disco y embutido (cúpula y fondo) 2 recurso(s) | AD5: =Linea!$A$23&". "&Linea!$B$23&CHAR(10)&Linea!$I$23&" recurso(s)" -> 5. Preparación de cuello 4 recurso(s) | AK5: =Linea!$A$24&". "&Linea!$B$24&CHAR(10)&Linea!$I$24&" recurso(s)" -> 6. Numerado de cúpula 2 recurso(s)
H6: ➜ | O6: ➜ | V6: ➜ | AC6: ➜ | AJ6: ➜
B8: =Linea!$J$19 -> 0.71115641 | I8: =Linea!$J$20 -> 0.34440579 | P8: =Linea!$J$21 -> 0.25565166 | W8: =Linea!$J$22 -> 0.55776973 | AD8: =Linea!$J$23 -> 0.71115641 | AK8: =Linea!$J$24 -> 0.47410427
AM9: ⬇
B10: =Linea!$A$30&". "&Linea!$B$30&CHAR(10)&Linea!$I$30&" recurso(s)" -> 12. Bordoneado 2 recurso(s) | I10: =Linea!$A$29&". "&Linea!$B$29&CHAR(10)&Linea!$I$29&" recurso(s)" -> 11. Encastre de fondo 2 recurso(s) | P10: =Linea!$A$28&". "&Linea!$B$28&CHAR(10)&Linea!$I$28&" recurso(s)" -> 10. Soldadura longitudinal TIG — 1 kg 2 recurso(s) | W10: =Linea!$A$27&". "&Linea!$B$27&CHAR(10)&Linea!$I$27&" recurso(s)" -> 9. Soldadura longitudinal — 2,5 a 10 kg 2 recurso(s) | AD10: =Linea!$A$26&". "&Linea!$B$26&CHAR(10)&Linea!$I$26&" recurso(s)" -> 8. Cilindrado 1 recurso(s) | AK10: =Linea!$A$25&". "&Linea!$B$25&CHAR(10)&Linea!$I$25&" recurso(s)" -> 7. Soldadura del cuello a la cúpula 2 recurso(s)
H11: ⬅ | O11: ⬅ | V11: ⬅ | AC11: ⬅ | AJ11: ⬅
B13: =Linea!$J$30 -> 0.48268535 | I13: =Linea!$J$29 -> 0.72402802 | P13: =Linea!$J$28 -> 0.5065516 | W13: =Linea!$J$27 -> 0.79491735 | AD13: =Linea!$J$26 -> 0.72076663 | AK13: =Linea!$J$25 -> 0.60886679
D14: ⬇
B15: =Linea!$A$31&". "&Linea!$B$31&CHAR(10)&Linea!$I$31&" recurso(s)" -> 13. Soldadura circunferencial de cúpula y fondo 4 recurso(s) | I15: =Linea!$A$32&". "&Linea!$B$32&CHAR(10)&Linea!$I$32&" recurso(s)" -> 14. Control de calidad — Espesor 1 recurso(s) | P15: =Linea!$A$33&". "&Linea!$B$33&CHAR(10)&Linea!$I$33&" recurso(s)" -> 15. Prueba hidráulica 4 recurso(s) | W15: =Linea!$A$34&". "&Linea!$B$34&CHAR(10)&Linea!$I$34&" recurso(s)" -> 16. Secado 8 recurso(s) | AD15: =Linea!$A$35&". "&Linea!$B$35&CHAR(10)&Linea!$I$35&" recurso(s)" -> 17. Granallado 2 recurso(s) | AK15: =Linea!$A$36&". "&Linea!$B$36&CHAR(10)&Linea!$I$36&" recurso(s)" -> 18. Detección de defectos 2 recurso(s)
H16: ➜ | O16: ➜ | V16: ➜ | AC16: ➜ | AJ16: ➜
B18: =Linea!$J$31 -> 0.72402802 | I18: =Linea!$J$32 -> 0.11378503 | P18: =Linea!$J$33 -> 0.72402802 | W18: =Linea!$J$34 -> 0.71115641 | AD18: =Linea!$J$35 -> 0.71115641 | AK18: =Linea!$J$36 -> 0.47410427
AM19: ⬇
B20: =Linea!$A$42&". "&Linea!$B$42&CHAR(10)&Linea!$I$42&" recurso(s)" -> 24. Control de calidad — Ensayo de pérdidas 1 recurso(s) | I20: =Linea!$A$41&". "&Linea!$B$41&CHAR(10)&Linea!$I$41&" recurso(s)" -> 23. Presurización 1 recurso(s) | P20: =Linea!$A$40&". "&Linea!$B$40&CHAR(10)&Linea!$I$40&" recurso(s)" -> 22. Ensamblaje 2 recurso(s) | W20: =Linea!$A$39&". "&Linea!$B$39&CHAR(10)&Linea!$I$39&" recurso(s)" -> 21. Carga de polvo 1 recurso(s) | AD20: =Linea!$A$38&". "&Linea!$B$38&CHAR(10)&Linea!$I$38&" recurso(s)" -> 20. Pintura en polvo + horno 2 recurso(s) | AK20: =Linea!$A$37&". "&Linea!$B$37&CHAR(10)&Linea!$I$37&" recurso(s)" -> 19. Corrección de defectos 1 recurso(s)
H21: ⬅ | O21: ⬅ | V21: ⬅ | AC21: ⬅ | AJ21: ⬅
B23: =Linea!$J$42 -> 0.4811267 | I23: =Linea!$J$41 -> 0.36084502 | P23: =Linea!$J$40 -> 0.61229359 | W23: =Linea!$J$39 -> 0.54126753 | AD23: =Linea!$J$38 -> 0.62601797 | AK23: =Linea!$J$37 -> 0.42669385
D24: ⬇
B25: =Linea!$A$43&". "&Linea!$B$43&CHAR(10)&Linea!$I$43&" recurso(s)" -> 25. Etiquetado 1 recurso(s) | I25: =Linea!$A$44&". "&Linea!$B$44&CHAR(10)&Linea!$I$44&" recurso(s)" -> 26. Embalaje y paletizado 4 recurso(s)
H26: ➜
B28: =Linea!$J$43 -> 0.72169004 | I28: =Linea!$J$44 -> 0.53815087
B32: LÍNEA DE CARROS | N32: ="Takt "&TEXT(Linea!$C$52,"#,##0.0")&" s/u · contenido "&TEXT(Linea!$C$53,"#,##0.0")&" s/u · eficiencia de balanceo "&TEXT(Linea!$C$59,"0%")&" · cuello: "&Linea!$C$57&" ("&TEXT(Linea!$C$58,"0%")&")" -> Takt 1,930.9 s/u · contenido 6,202.1 s/u · eficiencia de balanceo 43% · cuello: Soldadura de accesorios (52%)
B33: =Linea!$A$63&". "&Linea!$B$63&CHAR(10)&Linea!$I$63&" recurso(s)" -> 1. Recepción de materia prima 1 recurso(s) | I33: =Linea!$A$64&". "&Linea!$B$64&CHAR(10)&Linea!$I$64&" recurso(s)" -> 2. Corte de chapa (guillotina) 1 recurso(s) | P33: =Linea!$A$65&". "&Linea!$B$65&CHAR(10)&Linea!$I$65&" recurso(s)" -> 3. Marcado del cuerpo 1 recurso(s) | W33: =Linea!$A$66&". "&Linea!$B$66&CHAR(10)&Linea!$I$66&" recurso(s)" -> 4. Cilindrado 1 recurso(s) | AD33: =Linea!$A$67&". "&Linea!$B$67&CHAR(10)&Linea!$I$67&" recurso(s)" -> 5. Punteo del cuerpo 1 recurso(s) | AK33: =Linea!$A$68&". "&Linea!$B$68&CHAR(10)&Linea!$I$68&" recurso(s)" -> 6. Soldadura longitudinal 1 recurso(s)
H34: ➜ | O34: ➜ | V34: ➜ | AC34: ➜ | AJ34: ➜
B36: =Linea!$J$63 -> 0.10349913 | I36: =Linea!$J$64 -> 0.17603599 | P36: =Linea!$J$65 -> 0.060696783 | W36: =Linea!$J$66 -> 0.14374045 | AD36: =Linea!$J$67 -> 0.16491995 | AK36: =Linea!$J$68 -> 0.12344906
AM37: ⬇
B38: =Linea!$A$74&". "&Linea!$B$74&CHAR(10)&Linea!$I$74&" recurso(s)" -> 12. Secado 1 recurso(s) | I38: =Linea!$A$73&". "&Linea!$B$73&CHAR(10)&Linea!$I$73&" recurso(s)" -> 11. Prueba hidráulica 1 recurso(s) | P38: =Linea!$A$72&". "&Linea!$B$72&CHAR(10)&Linea!$I$72&" recurso(s)" -> 10. Fabricación de accesorios 1 recurso(s) | W38: =Linea!$A$71&". "&Linea!$B$71&CHAR(10)&Linea!$I$71&" recurso(s)" -> 9. Soldadura de accesorios 1 recurso(s) | AD38: =Linea!$A$70&". "&Linea!$B$70&CHAR(10)&Linea!$I$70&" recurso(s)" -> 8. Armado y soldadura circunferencial 1 recurso(s) | AK38: =Linea!$A$69&". "&Linea!$B$69&CHAR(10)&Linea!$I$69&" recurso(s)" -> 7. Soldadura de cupla en la cúpula 1 recurso(s)
H39: ⬅ | O39: ⬅ | V39: ⬅ | AC39: ⬅ | AJ39: ⬅
B41: =Linea!$J$74 -> 0.31256646 | I41: =Linea!$J$73 -> 0.30125591 | P41: =Linea!$J$72 -> 0.37513877 | W41: =Linea!$J$71 -> 0.5230764 | AD41: =Linea!$J$70 -> 0.51375531 | AK41: =Linea!$J$69 -> 0.12440692
D42: ⬇
B43: =Linea!$A$75&". "&Linea!$B$75&CHAR(10)&Linea!$I$75&" recurso(s)" -> 13. Pulmón de despacho y carga a pintura 1 recurso(s) | I43: =Linea!$A$76&". "&Linea!$B$76&CHAR(10)&Linea!$I$76&" recurso(s)" -> 14. Recepción de pintados y cambio de juego 1 recurso(s) | P43: =Linea!$A$77&". "&Linea!$B$77&CHAR(10)&Linea!$I$77&" recurso(s)" -> 15. Carga de polvo y presurización 1 recurso(s) | W43: =Linea!$A$78&". "&Linea!$B$78&CHAR(10)&Linea!$I$78&" recurso(s)" -> 16. Montaje, manga, precinto y etiquetado 1 recurso(s) | AD43: =Linea!$A$79&". "&Linea!$B$79&CHAR(10)&Linea!$I$79&" recurso(s)" -> 17. Calidad: pérdidas, inspección final, liberación y ensayos de lote 1 recurso(s) | AK43: =Linea!$A$80&". "&Linea!$B$80&CHAR(10)&Linea!$I$80&" recurso(s)" -> 18. Depósito de producto terminado y despacho 1 recurso(s)
H44: ➜ | O44: ➜ | V44: ➜ | AC44: ➜ | AJ44: ➜
B46: =Linea!$J$75 -> 0.058606883 | I46: =Linea!$J$76 -> 0.10614908 | P46: =Linea!$J$77 -> 0.31227327 | W46: =Linea!$J$78 -> 0.16135546 | AD46: =Linea!$J$79 -> 0.4571455 | AK46: =Linea!$J$80 -> 0.064482699
B50: LÍNEA DE RECARGAS | N50: ="Takt "&TEXT(Linea!$C$88,"#,##0.0")&" s/u · contenido "&TEXT(Linea!$C$89,"#,##0.0")&" s/u · eficiencia de balanceo "&TEXT(Linea!$C$95,"0%")&" · cuello: "&Linea!$C$93&" ("&TEXT(Linea!$C$94,"0%")&")" -> Takt 48.6 s/u · contenido 1,184.2 s/u · eficiencia de balanceo 59% · cuello: Ensayo de pérdidas (87%)
B51: =Linea!$A$99&". "&Linea!$B$99&CHAR(10)&Linea!$I$99&" recurso(s)" -> 1. Recepción y registro 2 recurso(s) | I51: =Linea!$A$100&". "&Linea!$B$100&CHAR(10)&Linea!$I$100&" recurso(s)" -> 2. Inspección visual 4 recurso(s) | P51: =Linea!$A$101&". "&Linea!$B$101&CHAR(10)&Linea!$I$101&" recurso(s)" -> 3. Descarga ABC — ruta recuperable 2 recurso(s) | W51: =Linea!$A$102&". "&Linea!$B$102&CHAR(10)&Linea!$I$102&" recurso(s)" -> 4. Descarga a descarte (ABC, BC y Clase D) 1 recurso(s) | AD51: =Linea!$A$103&". "&Linea!$B$103&CHAR(10)&Linea!$I$103&" recurso(s)" -> 5. Descarga y carga de agua / AFFF / sales K 1 recurso(s) | AK51: =Linea!$A$104&". "&Linea!$B$104&CHAR(10)&Linea!$I$104&" recurso(s)" -> 6. Recuperación y carga de CO₂ 1 recurso(s)
H52: ➜ | O52: ➜ | V52: ➜ | AC52: ➜ | AJ52: ➜
B54: =Linea!$J$99 -> 0.81813919 | I54: =Linea!$J$100 -> 0.49088352 | P54: =Linea!$J$101 -> 0.7069479 | W54: =Linea!$J$102 -> 0.16045446 | AD54: =Linea!$J$103 -> 0.19268982 | AK54: =Linea!$J$104 -> 0.24142776
AM55: ⬇
B56: =Linea!$A$110&". "&Linea!$B$110&CHAR(10)&Linea!$I$110&" recurso(s)" -> 12. Secado 2 recurso(s) | I56: =Linea!$A$109&". "&Linea!$B$109&CHAR(10)&Linea!$I$109&" recurso(s)" -> 11. Prueba hidráulica 2 recurso(s) | P56: =Linea!$A$108&". "&Linea!$B$108&CHAR(10)&Linea!$I$108&" recurso(s)" -> 10. Laboratorio — Puffer y mufla 1 recurso(s) | W56: =Linea!$A$107&". "&Linea!$B$107&CHAR(10)&Linea!$I$107&" recurso(s)" -> 9. Desarme e inspección interior — zona general 1 recurso(s) | AD56: =Linea!$A$106&". "&Linea!$B$106&CHAR(10)&Linea!$I$106&" recurso(s)" -> 8. Desarme y limpieza — recinto 4 recurso(s) | AK56: =Linea!$A$105&". "&Linea!$B$105&CHAR(10)&Linea!$I$105&" recurso(s)" -> 7. Recuperación y carga de halogenado 1 recurso(s)
H57: ⬅ | O57: ⬅ | V57: ⬅ | AC57: ⬅ | AJ57: ⬅
B59: =Linea!$J$110 -> 0.48853119 | I59: =Linea!$J$109 -> 0.86365731 | P59: =Linea!$J$108 -> 0.64383763 | W59: =Linea!$J$107 -> 0.26529125 | AD59: =Linea!$J$106 -> 0.51178569 | AK59: =Linea!$J$105 -> 0.019639009
D60: ⬇
B61: =Linea!$A$111&". "&Linea!$B$111&CHAR(10)&Linea!$I$111&" recurso(s)" -> 13. Inspección interior con videoscopio 1 recurso(s) | I61: =Linea!$A$112&". "&Linea!$B$112&CHAR(10)&Linea!$I$112&" recurso(s)" -> 14. Pintura 4 recurso(s) | P61: =Linea!$A$113&". "&Linea!$B$113&CHAR(10)&Linea!$I$113&" recurso(s)" -> 15. Carga de polvo ABC, BC y Clase D 4 recurso(s) | W61: =Linea!$A$114&". "&Linea!$B$114&CHAR(10)&Linea!$I$114&" recurso(s)" -> 16. Ensamblaje y marbete — recinto 4 recurso(s) | AD61: =Linea!$A$115&". "&Linea!$B$115&CHAR(10)&Linea!$I$115&" recurso(s)" -> 17. Presurización — recinto 2 recurso(s) | AK61: =Linea!$A$116&". "&Linea!$B$116&CHAR(10)&Linea!$I$116&" recurso(s)" -> 18. Ensamblaje y presurización — zona general 1 recurso(s)
H62: ➜ | O62: ➜ | V62: ➜ | AC62: ➜ | AJ62: ➜
B64: =Linea!$J$111 -> 0.46139056 | I64: =Linea!$J$112 -> 0.5031556 | P64: =Linea!$J$113 -> 0.48815107 | W64: =Linea!$J$114 -> 0.58489793 | AD64: =Linea!$J$115 -> 0.71162581 | AK64: =Linea!$J$116 -> 0.25624723
AM65: ⬇
I66: =Linea!$A$121&". "&Linea!$B$121&CHAR(10)&Linea!$I$121&" recurso(s)" -> 23. PH de mangueras (CO₂ y rodantes) 1 recurso(s) | P66: =Linea!$A$120&". "&Linea!$B$120&CHAR(10)&Linea!$I$120&" recurso(s)" -> 22. Inutilización y disposición final 1 recurso(s) | W66: =Linea!$A$119&". "&Linea!$B$119&CHAR(10)&Linea!$I$119&" recurso(s)" -> 21. Precinto, etiqueta y despacho 4 recurso(s) | AD66: =Linea!$A$118&". "&Linea!$B$118&CHAR(10)&Linea!$I$118&" recurso(s)" -> 20. Ensayo de pérdidas 2 recurso(s) | AK66: =Linea!$A$117&". "&Linea!$B$117&CHAR(10)&Linea!$I$117&" recurso(s)" -> 19. Control de peso (CO₂ y halogenados sin recarga) 1 recurso(s)
O67: ⬅ | V67: ⬅ | AC67: ⬅ | AJ67: ⬅
I69: =Linea!$J$121 -> 0.19423684 | P69: =Linea!$J$120 -> 0.67176509 | W69: =Linea!$J$119 -> 0.46906647 | AD69: =Linea!$J$118 -> 0.87268181 | AK69: =Linea!$J$117 -> 0.04463681

Sheet Materiales
A1: BALANCE DE MATERIALES (año elegido en Resumen)
A2: 1) materia prima que entra · 2) semielaborados en proceso · 3) scrap, desechos y mermas · 4) producto terminado. Cantidades = lo que pide la producción del año (MP_detalle).
A4: LÍNEA DE MANUALES (1 a 10 kg)
A5: 1) Materia prima que entra
A6: Familia | B6: Formato de compra | C6: Cantidad | D6: UM | E6: Unidades de compra | F6: kg
A7: Chapa en hojas | B7: =IFERROR(INDEX(MP_detalle!$F$7:$F$66,MATCH("Chapa en hojas",MP_detalle!$B$7:$B$66,0)),"") -> Paquete de 50 hojas | C7: =SUMIFS(MP_detalle!$H$7:$H$66,MP_detalle!$B$7:$B$66,"Chapa en hojas") -> 10604.462 | D7: hojas | E7: =SUMIFS(MP_detalle!$L$7:$L$66,MP_detalle!$B$7:$B$66,"Chapa en hojas") -> 179.90718 | F7: =SUMIFS(MP_detalle!$N$7:$N$66,MP_detalle!$B$7:$B$66,"Chapa en hojas") -> 261838.11
A8: Fleje en rollos | B8: =IFERROR(INDEX(MP_detalle!$F$7:$F$66,MATCH("Fleje en rollos",MP_detalle!$B$7:$B$66,0)),"") -> Rollo de 1.900 kg | C8: =SUMIFS(MP_detalle!$H$7:$H$66,MP_detalle!$B$7:$B$66,"Fleje en rollos") -> 100700.72 | D8: kg | E8: =SUMIFS(MP_detalle!$L$7:$L$66,MP_detalle!$B$7:$B$66,"Fleje en rollos") -> 142.79836 | F8: =SUMIFS(MP_detalle!$N$7:$N$66,MP_detalle!$B$7:$B$66,"Fleje en rollos") -> 100700.72
A9: Asientos de válvula | B9: =IFERROR(INDEX(MP_detalle!$F$7:$F$66,MATCH("Asientos de válvula",MP_detalle!$B$7:$B$66,0)),"") -> Caja de 1.000 u | C9: =SUMIFS(MP_detalle!$H$7:$H$66,MP_detalle!$B$7:$B$66,"Asientos de válvula") -> 284462.56 | D9: u | E9: =SUMIFS(MP_detalle!$L$7:$L$66,MP_detalle!$B$7:$B$66,"Asientos de válvula") -> 284.46256 | F9: =SUMIFS(MP_detalle!$N$7:$N$66,MP_detalle!$B$7:$B$66,"Asientos de válvula") -> 0
A10: Soldadura: alambre | B10: =IFERROR(INDEX(MP_detalle!$F$7:$F$66,MATCH("Soldadura: alambre",MP_detalle!$B$7:$B$66,0)),"") -> Pallet de 900 kg | C10: =SUMIFS(MP_detalle!$H$7:$H$66,MP_detalle!$B$7:$B$66,"Soldadura: alambre") -> 5990.0382 | D10: kg | E10: =SUMIFS(MP_detalle!$L$7:$L$66,MP_detalle!$B$7:$B$66,"Soldadura: alambre") -> 6.655598 | F10: =SUMIFS(MP_detalle!$N$7:$N$66,MP_detalle!$B$7:$B$66,"Soldadura: alambre") -> 5990.0382
A11: Soldadura: gases | B11: =IFERROR(INDEX(MP_detalle!$F$7:$F$66,MATCH("Soldadura: gases",MP_detalle!$B$7:$B$66,0)),"") -> Batería de 11 cilindros | C11: =SUMIFS(MP_detalle!$H$7:$H$66,MP_detalle!$B$7:$B$66,"Soldadura: gases") -> 8198.9088 | D11: m³ | E11: =SUMIFS(MP_detalle!$L$7:$L$66,MP_detalle!$B$7:$B$66,"Soldadura: gases") -> 140.29827 | F11: =SUMIFS(MP_detalle!$N$7:$N$66,MP_detalle!$B$7:$B$66,"Soldadura: gases") -> 0
A12: Soldadura: electrodo TIG | B12: =IFERROR(INDEX(MP_detalle!$F$7:$F$66,MATCH("Soldadura: electrodo TIG",MP_detalle!$B$7:$B$66,0)),"") -> Caja de 10 u | C12: =SUMIFS(MP_detalle!$H$7:$H$66,MP_detalle!$B$7:$B$66,"Soldadura: electrodo TIG") -> 166.62882 | D12: u | E12: =SUMIFS(MP_detalle!$L$7:$L$66,MP_detalle!$B$7:$B$66,"Soldadura: electrodo TIG") -> 16.662882 | F12: =SUMIFS(MP_detalle!$N$7:$N$66,MP_detalle!$B$7:$B$66,"Soldadura: electrodo TIG") -> 0
A13: Granalla | B13: =IFERROR(INDEX(MP_detalle!$F$7:$F$66,MATCH("Granalla",MP_detalle!$B$7:$B$66,0)),"") -> Pallet de 1.000 kg | C13: =SUMIFS(MP_detalle!$H$7:$H$66,MP_detalle!$B$7:$B$66,"Granalla") -> 22757.005 | D13: kg | E13: =SUMIFS(MP_detalle!$L$7:$L$66,MP_detalle!$B$7:$B$66,"Granalla") -> 22.757005 | F13: =SUMIFS(MP_detalle!$N$7:$N$66,MP_detalle!$B$7:$B$66,"Granalla") -> 22757.005
A14: Pintura | B14: =IFERROR(INDEX(MP_detalle!$F$7:$F$66,MATCH("Pintura",MP_detalle!$B$7:$B$66,0)),"") -> Pallet de 600 kg | C14: =SUMIFS(MP_detalle!$H$7:$H$66,MP_detalle!$B$7:$B$66,"Pintura") -> 3581.9354 | D14: kg | E14: =SUMIFS(MP_detalle!$L$7:$L$66,MP_detalle!$B$7:$B$66,"Pintura") -> 5.9698923 | F14: =SUMIFS(MP_detalle!$N$7:$N$66,MP_detalle!$B$7:$B$66,"Pintura") -> 3581.9354
A15: Agente: polvo | B15: =IFERROR(INDEX(MP_detalle!$F$7:$F$66,MATCH("Agente: polvo",MP_detalle!$B$7:$B$66,0)),"") -> Big bag de 1.000 kg | C15: =SUMIFS(MP_detalle!$H$7:$H$66,MP_detalle!$B$7:$B$66,"Agente: polvo") -> 230062.4 | D15: kg | E15: =SUMIFS(MP_detalle!$L$7:$L$66,MP_detalle!$B$7:$B$66,"Agente: polvo") -> 230.0624 | F15: =SUMIFS(MP_detalle!$N$7:$N$66,MP_detalle!$B$7:$B$66,"Agente: polvo") -> 230062.4
A16: Nitrógeno | B16: =IFERROR(INDEX(MP_detalle!$F$7:$F$66,MATCH("Nitrógeno",MP_detalle!$B$7:$B$66,0)),"") -> Pack de 12 cilindros | C16: =SUMIFS(MP_detalle!$H$7:$H$66,MP_detalle!$B$7:$B$66,"Nitrógeno") -> 1268.5157 | D16: m³ | E16: =SUMIFS(MP_detalle!$L$7:$L$66,MP_detalle!$B$7:$B$66,"Nitrógeno") -> 11.531961 | F16: =SUMIFS(MP_detalle!$N$7:$N$66,MP_detalle!$B$7:$B$66,"Nitrógeno") -> 0
A17: Componentes comprados | B17: =IFERROR(INDEX(MP_detalle!$F$7:$F$66,MATCH("Componentes comprados",MP_detalle!$B$7:$B$66,0)),"") & " (varios)" -> Pallet de 3.000 u (varios) | C17: =SUMIFS(MP_detalle!$H$7:$H$66,MP_detalle!$B$7:$B$66,"Componentes comprados") -> 693427.68 | D17: u | E17: =SUMIFS(MP_detalle!$L$7:$L$66,MP_detalle!$B$7:$B$66,"Componentes comprados") -> 3319.4842 | F17: =SUMIFS(MP_detalle!$N$7:$N$66,MP_detalle!$B$7:$B$66,"Componentes comprados") -> 0
A18: Identificación y embalaje | B18: =IFERROR(INDEX(MP_detalle!$F$7:$F$66,MATCH("Identificación y embalaje",MP_detalle!$B$7:$B$66,0)),"") & " (varios)" -> Rollo de 1.000 u (varios) | C18: =SUMIFS(MP_detalle!$H$7:$H$66,MP_detalle!$B$7:$B$66,"Identificación y embalaje") -> 1421744.6 | D18: u | E18: =SUMIFS(MP_detalle!$L$7:$L$66,MP_detalle!$B$7:$B$66,"Identificación y embalaje") -> 2052.1905 | F18: =SUMIFS(MP_detalle!$N$7:$N$66,MP_detalle!$B$7:$B$66,"Identificación y embalaje") -> 0
A20: 2) Semielaborados en proceso
A21: Etapa | B21: Formato | C21: ABC 1 kg | D21: ABC 2,5 kg | E21: ABC 5 kg | F21: ABC 10 kg | G21: Total (u) | H21: kg de acero
A22: Planchuela de cuerpo cortada | B22: Rectángulo de chapa: desarrollo × alto (Piezas) | C22: =1*(Resumen!$D$7+Resumen!$D$11) -> 202620.64 | D22: =1*(Resumen!$D$8+Resumen!$D$12) -> 14126.338 | E22: =1*(Resumen!$D$9+Resumen!$D$13) -> 63852.659 | F22: =1*(Resumen!$D$10+Resumen!$D$14) -> 3862.9281 | G22: =SUM(C22:F22) -> 284462.56 | H22: =(Resumen!$D$7+Resumen!$D$11)*Links!$F$2202+(Resumen!$D$8+Resumen!$D$12)*Links!$F$2203+(Resumen!$D$9+Resumen!$D$13)*Links!$F$2204+(Resumen!$D$10+Resumen!$D$14)*Links!$F$2205 -> 245881.85
A23: Discos de cúpula y fondo | B23: Disco plano Ø D0 desde fleje (2 por recipiente) | C23: =2*(Resumen!$D$7+Resumen!$D$11) -> 405241.28 | D23: =2*(Resumen!$D$8+Resumen!$D$12) -> 28252.677 | E23: =2*(Resumen!$D$9+Resumen!$D$13) -> 127705.32 | F23: =2*(Resumen!$D$10+Resumen!$D$14) -> 7725.8562 | G23: =SUM(C23:F23) -> 568925.13 | H23: =(Resumen!$D$7+Resumen!$D$11)*((PI()*Links!$J$2212^2/4*Links!$B$2212*7.85/1000000)+(PI()*Links!$J$2213^2/4*Links!$B$2213*7.85/1000000))+(Resumen!$D$8+Resumen!$D$12)*((PI()*Links!$J$2214^2/4*Links!$B$2214*7.85/1000000)+(PI()*Links!$J$2215^2/4*Links!$B$2215*7.85/1000000))+(Resumen!$D$9+Resumen!$D$13)*((PI()*Links!$J$2216^2/4*Links!$B$2216*7.85/1000000)+(PI()*Links!$J$2217^2/4*Links!$B$2217*7.85/1000000))+(Resumen!$D$10+Resumen!$D$14)*((PI()*Links!$J$2218^2/4*Links!$B$2218*7.85/1000000)+(PI()*Links!$J$2219^2/4*Links!$B$2219*7.85/1000000)) -> 74334.72
A24: Casquetes embutidos (cúpula numerada con cuello, fondo) | B24: Casquete embutido | C24: =2*(Resumen!$D$7+Resumen!$D$11) -> 405241.28 | D24: =2*(Resumen!$D$8+Resumen!$D$12) -> 28252.677 | E24: =2*(Resumen!$D$9+Resumen!$D$13) -> 127705.32 | F24: =2*(Resumen!$D$10+Resumen!$D$14) -> 7725.8562 | G24: =SUM(C24:F24) -> 568925.13 | H24: =(Resumen!$D$7+Resumen!$D$11)*((PI()*Links!$J$2212^2/4*Links!$B$2212*7.85/1000000)+(PI()*Links!$J$2213^2/4*Links!$B$2213*7.85/1000000))+(Resumen!$D$8+Resumen!$D$12)*((PI()*Links!$J$2214^2/4*Links!$B$2214*7.85/1000000)+(PI()*Links!$J$2215^2/4*Links!$B$2215*7.85/1000000))+(Resumen!$D$9+Resumen!$D$13)*((PI()*Links!$J$2216^2/4*Links!$B$2216*7.85/1000000)+(PI()*Links!$J$2217^2/4*Links!$B$2217*7.85/1000000))+(Resumen!$D$10+Resumen!$D$14)*((PI()*Links!$J$2218^2/4*Links!$B$2218*7.85/1000000)+(PI()*Links!$J$2219^2/4*Links!$B$2219*7.85/1000000)) -> 74334.72
A25: Virola cilindrada y soldada | B25: Tubo con costura longitudinal | C25: =1*(Resumen!$D$7+Resumen!$D$11) -> 202620.64 | D25: =1*(Resumen!$D$8+Resumen!$D$12) -> 14126.338 | E25: =1*(Resumen!$D$9+Resumen!$D$13) -> 63852.659 | F25: =1*(Resumen!$D$10+Resumen!$D$14) -> 3862.9281 | G25: =SUM(C25:F25) -> 284462.56 | H25: =(Resumen!$D$7+Resumen!$D$11)*Links!$F$2202+(Resumen!$D$8+Resumen!$D$12)*Links!$F$2203+(Resumen!$D$9+Resumen!$D$13)*Links!$F$2204+(Resumen!$D$10+Resumen!$D$14)*Links!$F$2205 -> 245881.85
A26: Recipiente soldado (PH, secado, granallado) | B26: Recipiente cerrado sin pintar | C26: =1*(Resumen!$D$7+Resumen!$D$11) -> 202620.64 | D26: =1*(Resumen!$D$8+Resumen!$D$12) -> 14126.338 | E26: =1*(Resumen!$D$9+Resumen!$D$13) -> 63852.659 | F26: =1*(Resumen!$D$10+Resumen!$D$14) -> 3862.9281 | G26: =SUM(C26:F26) -> 284462.56 | H26: =(Resumen!$D$7+Resumen!$D$11)*(Links!$F$2202+((PI()*Links!$J$2212^2/4*Links!$B$2212*7.85/1000000)+(PI()*Links!$J$2213^2/4*Links!$B$2213*7.85/1000000)))+(Resumen!$D$8+Resumen!$D$12)*(Links!$F$2203+((PI()*Links!$J$2214^2/4*Links!$B$2214*7.85/1000000)+(PI()*Links!$J$2215^2/4*Links!$B$2215*7.85/1000000)))+(Resumen!$D$9+Resumen!$D$13)*(Links!$F$2204+((PI()*Links!$J$2216^2/4*Links!$B$2216*7.85/1000000)+(PI()*Links!$J$2217^2/4*Links!$B$2217*7.85/1000000)))+(Resumen!$D$10+Resumen!$D$14)*(Links!$F$2205+((PI()*Links!$J$2218^2/4*Links!$B$2218*7.85/1000000)+(PI()*Links!$J$2219^2/4*Links!$B$2219*7.85/1000000))) -> 320216.57
A27: Recipiente pintado | B27: Cilindro pintado rojo | C27: =1*(Resumen!$D$7+Resumen!$D$11) -> 202620.64 | D27: =1*(Resumen!$D$8+Resumen!$D$12) -> 14126.338 | E27: =1*(Resumen!$D$9+Resumen!$D$13) -> 63852.659 | F27: =1*(Resumen!$D$10+Resumen!$D$14) -> 3862.9281 | G27: =SUM(C27:F27) -> 284462.56 | H27: =(Resumen!$D$7+Resumen!$D$11)*(Links!$F$2202+((PI()*Links!$J$2212^2/4*Links!$B$2212*7.85/1000000)+(PI()*Links!$J$2213^2/4*Links!$B$2213*7.85/1000000)))+(Resumen!$D$8+Resumen!$D$12)*(Links!$F$2203+((PI()*Links!$J$2214^2/4*Links!$B$2214*7.85/1000000)+(PI()*Links!$J$2215^2/4*Links!$B$2215*7.85/1000000)))+(Resumen!$D$9+Resumen!$D$13)*(Links!$F$2204+((PI()*Links!$J$2216^2/4*Links!$B$2216*7.85/1000000)+(PI()*Links!$J$2217^2/4*Links!$B$2217*7.85/1000000)))+(Resumen!$D$10+Resumen!$D$14)*(Links!$F$2205+((PI()*Links!$J$2218^2/4*Links!$B$2218*7.85/1000000)+(PI()*Links!$J$2219^2/4*Links!$B$2219*7.85/1000000))) -> 320216.57
A28: Matafuego cargado y presurizado (antes de etiquetar) | B28: Recipiente + válvula + polvo + N₂ | C28: =Resumen!$D$7 -> 32072.639 | D28: =Resumen!$D$8 -> 7436.4584 | E28: =Resumen!$D$9 -> 30814.979 | F28: =Resumen!$D$10 -> 1844.9281 | G28: =SUM(C28:F28) -> 72169.004
A30: 3) Scrap, desechos no recuperables y mermas
A31: Qué | B31: De dónde sale | C31: Cantidad | D31: UM | E31: ¿Se recupera? | F31: Destino / formato
A32: Recortes de hoja | B32: Corte en guillotinas | C32: =SUMIFS(MP_detalle!$N$7:$N$66,MP_detalle!$B$7:$B$66,"Chapa en hojas")-H22 -> 15956.261 | D32: kg | E32: Sí: chatarra | F32: Contenedor de chatarra (playa de scrap)
A33: Esqueleto de fleje y despunte | B33: Corte de disco y embutido | C33: =SUMIFS(MP_detalle!$N$7:$N$66,MP_detalle!$B$7:$B$66,"Fleje en rollos")-H23 -> 26365.995 | D33: kg | E33: Sí: chatarra | F33: Contenedor de chatarra
A34: Salpicadura de soldadura | B34: Soldaduras MAG | C34: =SUMIFS(MP_detalle!$H$7:$H$66,MP_detalle!$B$7:$B$66,"Soldadura: alambre")*0.05 -> 299.50191 | D34: kg | E34: No | F34: Residuo (5% del alambre: BOM, rendimiento ESAB)
A35: Gas de protección y argón | B35: Soldaduras MAG y TIG | C35: =SUMIFS(MP_detalle!$H$7:$H$66,MP_detalle!$B$7:$B$66,"Soldadura: gases") -> 8198.9088 | D35: m³ | E35: No (se consume) | F35: Merma: queda en el ambiente de soldadura
A36: Electrodo de tungsteno gastado | B36: Soldadura TIG del 1 kg | C36: =SUMIFS(MP_detalle!$H$7:$H$66,MP_detalle!$B$7:$B$66,"Soldadura: electrodo TIG") -> 166.62882 | D36: u | E36: No | F36: Residuo (criterio a medir: MRP)
A37: Granalla gastada y óxido | B37: Granallado | C37: =SUMIFS(MP_detalle!$H$7:$H$66,MP_detalle!$B$7:$B$66,"Granalla") -> 22757.005 | D37: kg | E37: No | F37: Residuo del colector de la granalladora
A38: Polvo de pintura no recuperado | B38: Cabina de pintura | C38: =SUMIFS(MP_detalle!$H$7:$H$66,MP_detalle!$B$7:$B$66,"Pintura")*0.05 -> 179.09677 | D38: kg | E38: No | F38: Residuo (5%: el resto se recupera en la cabina)
A39: Polvo ABC de carga | B39: Carga de polvo | C39: =0 -> 0 | D39: kg | E39: — | F39: El proceso de manuales no agrega merma (MRP)
A41: 4) Producto terminado
A42: Producto | B42: Formato | C42: Unidades
A43: Matafuego ABC 1 kg | B43: Embalado en caja, en pallet | C43: =Resumen!$D$7 -> 32072.639
A44: Matafuego ABC 2,5 kg | B44: Embalado en caja, en pallet | C44: =Resumen!$D$8 -> 7436.4584
A45: Matafuego ABC 5 kg | B45: Embalado en caja, en pallet | C45: =Resumen!$D$9 -> 30814.979
A46: Matafuego ABC 10 kg | B46: Embalado en caja, en pallet | C46: =Resumen!$D$10 -> 1844.9281
A47: Cilindro ABC 1 kg vacío | B47: Cilindro pintado, en pallet | C47: =Resumen!$D$11 -> 170548
A48: Cilindro ABC 2,5 kg vacío | B48: Cilindro pintado, en pallet | C48: =Resumen!$D$12 -> 6689.88
A49: Cilindro ABC 5 kg vacío | B49: Cilindro pintado, en pallet | C49: =Resumen!$D$13 -> 33037.68
A50: Cilindro ABC 10 kg vacío | B50: Cilindro pintado, en pallet | C50: =Resumen!$D$14 -> 2018
A51: Total producto terminado | C51: =SUM(C43:C50) -> 284462.56
A53: Balance de acero (kg)
A54: Entra (MP) | B54: Queda en el producto | C54: Chatarra | D54: Cierre (entra − producto − chatarra) | E54: Aprovechamiento real | F54: ¿Cierra?
A55: =SUMIFS(MP_detalle!$N$7:$N$66,MP_detalle!$B$7:$B$66,"Chapa en hojas")+SUMIFS(MP_detalle!$N$7:$N$66,MP_detalle!$B$7:$B$66,"Fleje en rollos") -> 362538.83 | B55: =H27 -> 320216.57 | C55: =C32+C33 -> 42322.256 | D55: =A55-B55-C55 -> 0 | E55: =IF(A55=0,0,B55/A55) -> 0.88326145 | F55: =IF(ABS(D55)<1,"✔ Sí","✖ No") -> ✔ Sí
A56: Chapa de cuerpos y fleje de cúpulas y fondos. Producto = planchuelas y discos de la producción del año (Piezas del Excel de corte).
A58: LÍNEA DE CARROS (25 a 100 kg)
A59: 1) Materia prima que entra
A60: Familia | B60: Formato de compra | C60: Cantidad | D60: UM | E60: Unidades de compra | F60: kg
A61: Chapa en hojas | B61: =IFERROR(INDEX(MP_detalle!$F$71:$F$127,MATCH("Chapa en hojas",MP_detalle!$B$71:$B$127,0)),"") -> Paquete de 20 hojas | C61: =SUMIFS(MP_detalle!$H$71:$H$127,MP_detalle!$B$71:$B$127,"Chapa en hojas") -> 515.13723 | D61: hojas | E61: =SUMIFS(MP_detalle!$L$71:$L$127,MP_detalle!$B$71:$B$127,"Chapa en hojas") -> 28.517231 | F61: =SUMIFS(MP_detalle!$N$71:$N$127,MP_detalle!$B$71:$B$127,"Chapa en hojas") -> 67299.547
A62: Casquetes y cuplas | B62: =IFERROR(INDEX(MP_detalle!$F$71:$F$127,MATCH("Casquetes y cuplas",MP_detalle!$B$71:$B$127,0)),"") -> Pallet de 400 u | C62: =SUMIFS(MP_detalle!$H$71:$H$127,MP_detalle!$B$71:$B$127,"Casquetes y cuplas") -> 9321.9664 | D62: u | E62: =SUMIFS(MP_detalle!$L$71:$L$127,MP_detalle!$B$71:$B$127,"Casquetes y cuplas") -> 63.960674 | F62: =SUMIFS(MP_detalle!$N$71:$N$127,MP_detalle!$B$71:$B$127,"Casquetes y cuplas") -> 0
A63: Caños y barras | B63: =IFERROR(INDEX(MP_detalle!$F$71:$F$127,MATCH("Caños y barras",MP_detalle!$B$71:$B$127,0)),"") -> Barra de 6 m | C63: =SUMIFS(MP_detalle!$H$71:$H$127,MP_detalle!$B$71:$B$127,"Caños y barras") -> 783.5396 | D63: barras | E63: =SUMIFS(MP_detalle!$L$71:$L$127,MP_detalle!$B$71:$B$127,"Caños y barras") -> 783.5396 | F63: =SUMIFS(MP_detalle!$N$71:$N$127,MP_detalle!$B$71:$B$127,"Caños y barras") -> 0
A64: Soldadura: alambre | B64: =IFERROR(INDEX(MP_detalle!$F$71:$F$127,MATCH("Soldadura: alambre",MP_detalle!$B$71:$B$127,0)),"") -> Pallet de 900 kg | C64: =SUMIFS(MP_detalle!$H$71:$H$127,MP_detalle!$B$71:$B$127,"Soldadura: alambre") -> 1390.5974 | D64: kg | E64: =SUMIFS(MP_detalle!$L$71:$L$127,MP_detalle!$B$71:$B$127,"Soldadura: alambre") -> 1.5451082 | F64: =SUMIFS(MP_detalle!$N$71:$N$127,MP_detalle!$B$71:$B$127,"Soldadura: alambre") -> 1390.5974
A65: Soldadura: gases | B65: =IFERROR(INDEX(MP_detalle!$F$71:$F$127,MATCH("Soldadura: gases",MP_detalle!$B$71:$B$127,0)),"") -> Batería de 11 cilindros | C65: =SUMIFS(MP_detalle!$H$71:$H$127,MP_detalle!$B$71:$B$127,"Soldadura: gases") -> 561.28411 | D65: m³ | E65: =SUMIFS(MP_detalle!$L$71:$L$127,MP_detalle!$B$71:$B$127,"Soldadura: gases") -> 4.8596026 | F65: =SUMIFS(MP_detalle!$N$71:$N$127,MP_detalle!$B$71:$B$127,"Soldadura: gases") -> 0
A66: Abrasivos y corte | B66: =IFERROR(INDEX(MP_detalle!$F$71:$F$127,MATCH("Abrasivos y corte",MP_detalle!$B$71:$B$127,0)),"") -> Caja de 25 u | C66: =SUMIFS(MP_detalle!$H$71:$H$127,MP_detalle!$B$71:$B$127,"Abrasivos y corte") -> 175.56074 | D66: u | E66: =SUMIFS(MP_detalle!$L$71:$L$127,MP_detalle!$B$71:$B$127,"Abrasivos y corte") -> 7.0224298 | F66: =SUMIFS(MP_detalle!$N$71:$N$127,MP_detalle!$B$71:$B$127,"Abrasivos y corte") -> 0
A67: Pintura (servicio) | B67: =IFERROR(INDEX(MP_detalle!$F$71:$F$127,MATCH("Pintura (servicio)",MP_detalle!$B$71:$B$127,0)),"") | C67: =SUMIFS(MP_detalle!$H$71:$H$127,MP_detalle!$B$71:$B$127,"Pintura (servicio)") -> 3107.3221 | D67: servicio | E67: =SUMIFS(MP_detalle!$L$71:$L$127,MP_detalle!$B$71:$B$127,"Pintura (servicio)") -> 3107.3221 | F67: =SUMIFS(MP_detalle!$N$71:$N$127,MP_detalle!$B$71:$B$127,"Pintura (servicio)") -> 0
A68: Agente: polvo | B68: =IFERROR(INDEX(MP_detalle!$F$71:$F$127,MATCH("Agente: polvo",MP_detalle!$B$71:$B$127,0)),"") -> Big bag de 1.000 kg | C68: =SUMIFS(MP_detalle!$H$71:$H$127,MP_detalle!$B$71:$B$127,"Agente: polvo") -> 91918.958 | D68: kg | E68: =SUMIFS(MP_detalle!$L$71:$L$127,MP_detalle!$B$71:$B$127,"Agente: polvo") -> 91.918958 | F68: =SUMIFS(MP_detalle!$N$71:$N$127,MP_detalle!$B$71:$B$127,"Agente: polvo") -> 91918.958
A69: Nitrógeno | B69: =IFERROR(INDEX(MP_detalle!$F$71:$F$127,MATCH("Nitrógeno",MP_detalle!$B$71:$B$127,0)),"") -> Pack de 12 cilindros | C69: =SUMIFS(MP_detalle!$H$71:$H$127,MP_detalle!$B$71:$B$127,"Nitrógeno") -> 540.22318 | D69: m³ | E69: =SUMIFS(MP_detalle!$L$71:$L$127,MP_detalle!$B$71:$B$127,"Nitrógeno") -> 4.9111198 | F69: =SUMIFS(MP_detalle!$N$71:$N$127,MP_detalle!$B$71:$B$127,"Nitrógeno") -> 0
A70: Componentes comprados | B70: =IFERROR(INDEX(MP_detalle!$F$71:$F$127,MATCH("Componentes comprados",MP_detalle!$B$71:$B$127,0)),"") & " (varios)" -> Bolsa de 1.000 u (varios) | C70: =SUMIFS(MP_detalle!$H$71:$H$127,MP_detalle!$B$71:$B$127,"Componentes comprados") -> 24883.508 | D70: u | E70: =SUMIFS(MP_detalle!$L$71:$L$127,MP_detalle!$B$71:$B$127,"Componentes comprados") -> 535.18649 | F70: =SUMIFS(MP_detalle!$N$71:$N$127,MP_detalle!$B$71:$B$127,"Componentes comprados") -> 0
A71: Identificación y embalaje | B71: =IFERROR(INDEX(MP_detalle!$F$71:$F$127,MATCH("Identificación y embalaje",MP_detalle!$B$71:$B$127,0)),"") & " (varios)" -> Rollo de 1.000 u (varios) | C71: =SUMIFS(MP_detalle!$H$71:$H$127,MP_detalle!$B$71:$B$127,"Identificación y embalaje") -> 12451.765 | D71: u | E71: =SUMIFS(MP_detalle!$L$71:$L$127,MP_detalle!$B$71:$B$127,"Identificación y embalaje") -> 24.980021 | F71: =SUMIFS(MP_detalle!$N$71:$N$127,MP_detalle!$B$71:$B$127,"Identificación y embalaje") -> 0
A73: 2) Semielaborados en proceso
A74: Etapa | B74: Formato | C74: ABC 25 kg | D74: ABC 50 kg | E74: ABC 70 kg | F74: ABC 100 kg | G74: Total (u) | H74: kg de acero
A75: Planchuela de cuerpo cortada | B75: Rectángulo de chapa LAC: desarrollo × alto (Piezas) | C75: =(Resumen!$D$15+Resumen!$D$19) -> 777.31053 | D75: =(Resumen!$D$16+Resumen!$D$20) -> 1708.4352 | E75: =(Resumen!$D$17+Resumen!$D$21) -> 374.12986 | F75: =(Resumen!$D$18+Resumen!$D$22) -> 247.44657 | G75: =SUM(C75:F75) -> 3107.3221 | H75: =(Resumen!$D$15+Resumen!$D$19)*Links!$F$2206+(Resumen!$D$16+Resumen!$D$20)*Links!$F$2207+(Resumen!$D$17+Resumen!$D$21)*Links!$F$2208+(Resumen!$D$18+Resumen!$D$22)*Links!$F$2209 -> 57287.463
A76: Virola rolada, punteada y soldada | B76: Tubo con costura longitudinal | C76: =(Resumen!$D$15+Resumen!$D$19) -> 777.31053 | D76: =(Resumen!$D$16+Resumen!$D$20) -> 1708.4352 | E76: =(Resumen!$D$17+Resumen!$D$21) -> 374.12986 | F76: =(Resumen!$D$18+Resumen!$D$22) -> 247.44657 | G76: =SUM(C76:F76) -> 3107.3221 | H76: =(Resumen!$D$15+Resumen!$D$19)*Links!$F$2206+(Resumen!$D$16+Resumen!$D$20)*Links!$F$2207+(Resumen!$D$17+Resumen!$D$21)*Links!$F$2208+(Resumen!$D$18+Resumen!$D$22)*Links!$F$2209 -> 57287.463
A77: Recipiente armado (cuerpo + 2 casquetes + cupla) | B77: Recipiente cerrado sin pintar | C77: =(Resumen!$D$15+Resumen!$D$19) -> 777.31053 | D77: =(Resumen!$D$16+Resumen!$D$20) -> 1708.4352 | E77: =(Resumen!$D$17+Resumen!$D$21) -> 374.12986 | F77: =(Resumen!$D$18+Resumen!$D$22) -> 247.44657 | G77: =SUM(C77:F77) -> 3107.3221 | H77: =(Resumen!$D$15+Resumen!$D$19)*Links!$F$2206+(Resumen!$D$16+Resumen!$D$20)*Links!$F$2207+(Resumen!$D$17+Resumen!$D$21)*Links!$F$2208+(Resumen!$D$18+Resumen!$D$22)*Links!$F$2209 -> 57287.463
A78: Recipiente probado y secado | B78: Recipiente probado (PH) | C78: =(Resumen!$D$15+Resumen!$D$19) -> 777.31053 | D78: =(Resumen!$D$16+Resumen!$D$20) -> 1708.4352 | E78: =(Resumen!$D$17+Resumen!$D$21) -> 374.12986 | F78: =(Resumen!$D$18+Resumen!$D$22) -> 247.44657 | G78: =SUM(C78:F78) -> 3107.3221 | H78: =(Resumen!$D$15+Resumen!$D$19)*Links!$F$2206+(Resumen!$D$16+Resumen!$D$20)*Links!$F$2207+(Resumen!$D$17+Resumen!$D$21)*Links!$F$2208+(Resumen!$D$18+Resumen!$D$22)*Links!$F$2209 -> 57287.463
A79: Recipiente pintado (tercerizado: sale y vuelve) | B79: Cilindro pintado rojo | C79: =(Resumen!$D$15+Resumen!$D$19) -> 777.31053 | D79: =(Resumen!$D$16+Resumen!$D$20) -> 1708.4352 | E79: =(Resumen!$D$17+Resumen!$D$21) -> 374.12986 | F79: =(Resumen!$D$18+Resumen!$D$22) -> 247.44657 | G79: =SUM(C79:F79) -> 3107.3221 | H79: =(Resumen!$D$15+Resumen!$D$19)*Links!$F$2206+(Resumen!$D$16+Resumen!$D$20)*Links!$F$2207+(Resumen!$D$17+Resumen!$D$21)*Links!$F$2208+(Resumen!$D$18+Resumen!$D$22)*Links!$F$2209 -> 57287.463
A80: Carro armado y cargado | B80: Recipiente + carro + manga + polvo + N₂ | C80: =Resumen!$D$15 -> 453.67053 | D80: =Resumen!$D$16 -> 997.99517 | E80: =Resumen!$D$17 -> 217.80986 | F80: =Resumen!$D$18 -> 145.20657 | G80: =SUM(C80:F80) -> 1814.6821
A82: 3) Scrap, desechos no recuperables y mermas
A83: Qué | B83: De dónde sale | C83: Cantidad | D83: UM | E83: ¿Se recupera? | F83: Destino / formato
A84: Recortes de hoja | B84: Corte en guillotinas | C84: =SUMIFS(MP_detalle!$N$71:$N$127,MP_detalle!$B$71:$B$127,"Chapa en hojas")-H75 -> 10012.084 | D84: kg | E84: Sí: chatarra | F84: Contenedor de chatarra (playa de scrap)
A85: Recortes de caño y barra | B85: Fabricación de accesorios (sensitiva) | C85: =(MP_detalle!$H$78+MP_detalle!$H$79+MP_detalle!$H$81)*6+(MP_detalle!$H$80)*4-(Resumen!$D$15*(1440+354+490)/1000+Resumen!$D$16*(1520+354+510)/1000+Resumen!$D$17*(1590+434+590)/1000+Resumen!$D$18*(1590+434+590)/1000) -> 223.49103 | D85: m | E85: Sí: chatarra | F85: Contenedor de chatarra
A86: Salpicadura de soldadura | B86: Soldaduras MAG | C86: =SUMIFS(MP_detalle!$H$71:$H$127,MP_detalle!$B$71:$B$127,"Soldadura: alambre")*0.05 -> 69.529869 | D86: kg | E86: No | F86: Residuo (5% del alambre: BOM)
A87: Gas de protección | B87: Soldaduras MAG | C87: =SUMIFS(MP_detalle!$H$71:$H$127,MP_detalle!$B$71:$B$127,"Soldadura: gases") -> 561.28411 | D87: m³ | E87: No (se consume) | F87: Merma
A88: Discos de corte y flap, mechas, aerosoles gastados | B88: Corte y terminación de accesorios | C88: =SUMIFS(MP_detalle!$H$71:$H$127,MP_detalle!$B$71:$B$127,"Abrasivos y corte") -> 175.56074 | D88: u | E88: No | F88: Residuo
A89: Pintura | B89: Tercerizada | C89: =0 -> 0 | D89: kg | E89: — | F89: La merma queda en el pintor de carros
A91: 4) Producto terminado
A92: Producto | B92: Formato | C92: Unidades
A93: Carro ABC 25 kg | B93: Carro armado, film, en pallet | C93: =Resumen!$D$15 -> 453.67053
A94: Carro ABC 50 kg | B94: Carro armado, film, en pallet | C94: =Resumen!$D$16 -> 997.99517
A95: Carro ABC 70 kg | B95: Carro armado, film, en pallet | C95: =Resumen!$D$17 -> 217.80986
A96: Carro ABC 100 kg | B96: Carro armado, film, en pallet | C96: =Resumen!$D$18 -> 145.20657
A97: Cilindro ABC 25 kg vacío | B97: Cilindro pintado, en pallet | C97: =Resumen!$D$19 -> 323.64
A98: Cilindro ABC 50 kg vacío | B98: Cilindro pintado, en pallet | C98: =Resumen!$D$20 -> 710.44
A99: Cilindro ABC 70 kg vacío | B99: Cilindro pintado, en pallet | C99: =Resumen!$D$21 -> 156.32
A100: Cilindro ABC 100 kg vacío | B100: Cilindro pintado, en pallet | C100: =Resumen!$D$22 -> 102.24
A101: Total producto terminado | C101: =SUM(C93:C100) -> 3107.3221
A103: Balance de acero (kg)
A104: Entra (MP) | B104: Queda en el producto | C104: Chatarra | D104: Cierre (entra − producto − chatarra) | E104: Aprovechamiento real | F104: ¿Cierra?
A105: =SUMIFS(MP_detalle!$N$71:$N$127,MP_detalle!$B$71:$B$127,"Chapa en hojas") -> 67299.547 | B105: =H75 -> 57287.463 | C105: =C84 -> 10012.084 | D105: =A105-B105-C105 -> 0 | E105: =IF(A105=0,0,B105/A105) -> 0.85123103 | F105: =IF(ABS(D105)<1,"✔ Sí","✖ No") -> ✔ Sí
A106: Solo la chapa del cuerpo: los casquetes y la cupla se compran terminados. Producto = planchuelas y discos de la producción del año (Piezas del Excel de corte).
A108: LÍNEA DE RECARGAS (planta industrial)
A109: 1) Materia prima que entra
A110: Familia | B110: Formato de compra | C110: Cantidad | D110: UM | E110: Unidades de compra | F110: kg
A111: Agente: polvo | B111: =IFERROR(INDEX(MP_detalle!$F$132:$F$153,MATCH("Agente: polvo",MP_detalle!$B$132:$B$153,0)),"") -> Big bag de 1.000 kg | C111: =SUMIFS(MP_detalle!$H$132:$H$153,MP_detalle!$B$132:$B$153,"Agente: polvo") -> 54827.75 | D111: kg | E111: =SUMIFS(MP_detalle!$L$132:$L$153,MP_detalle!$B$132:$B$153,"Agente: polvo") -> 128.84925 | F111: =SUMIFS(MP_detalle!$N$132:$N$153,MP_detalle!$B$132:$B$153,"Agente: polvo") -> 54827.75
...

Sheet MP_detalle
A1: CASCADA DEL MRP: compra de cada material contra lo que pide la producción (año elegido)
A2: Necesario = consumo por unidad del MRP × producción de cada producto (Resumen). Si el MRP compra menos de lo necesario, el balance no cierra para esa producción.
A4: MANUALES
A5: Producción | B5: (mismo orden que el MRP) → | O5: =Resumen!$D$7 -> 32072.639 | P5: =Resumen!$D$8 -> 7436.4584 | Q5: =Resumen!$D$9 -> 30814.979 | R5: =Resumen!$D$10 -> 1844.9281 | S5: =Resumen!$D$11 -> 170548 | T5: =Resumen!$D$12 -> 6689.88 | U5: =Resumen!$D$13 -> 33037.68 | V5: =Resumen!$D$14 -> 2018
A6: Línea | B6: Familia | C6: Código | D6: Material | E6: UM | F6: Formato de compra | G6: Compra MRP | H6: Necesario para la producción | I6: Compra − necesario | J6: ¿Cubre? | K6: Contenido de la unidad de compra | L6: Unidades de compra necesarias | M6: kg por UM | N6: kg necesarios
A7: MANUALES | B7: Chapa en hojas | C7: =Links!$B$61 -> MP-01 | D7: =Links!$C$61 -> Hoja LAF 0,9 × 1220 × 2440 mm (cuerpo 1 kg) | E7: =Links!$D$61 -> hoja | F7: =IFERROR(INDEX(Links!$B$345:$B$469,MATCH(C7,Links!$B$218:$B$342,0)),"") -> Paquete de 50 hojas | G7: =INDEX(Links!$N$61:$W$61,1,(Resumen!$C$3-2025)) -> 4502.6809 | H7: =SUMPRODUCT(Links!$F$61:$M$61,$O$5:$V$5)*IF(Links!$E$61="CABA",INDEX(Links!$C$13:$L$13,1,(Resumen!$C$3-2025)),IF(Links!$E$61="PBA",1-INDEX(Links!$C$13:$L$13,1,(Resumen!$C$3-2025)),1)) -> 4502.6809 | I7: =G7-H7 -> 0 | J7: =IF(ROUND(G7-H7,1)>=0,"✔ Sí","✖ No") -> ✔ Sí | K7: =IFERROR(INDEX(Links!$C$345:$C$469,MATCH(C7,Links!$B$218:$B$342,0)),1) -> 50 | L7: =IF(K7>0,H7/K7,0) -> 90.053617 | M7: =Links!$B$2191*Links!$C$2191*Links!$C$2202*7.85/1000000 -> 21.031092 | N7: =H7*M7 -> 94696.296
A8: MANUALES | B8: Chapa en hojas | C8: =Links!$B$62 -> MP-02 | D8: =Links!$C$62 -> Hoja LAF 1,25 × 1220 × 2440 mm | E8: =Links!$D$62 -> hoja | F8: =IFERROR(INDEX(Links!$B$345:$B$469,MATCH(C8,Links!$B$218:$B$342,0)),"") -> Paquete de 50 hojas | G8: =INDEX(Links!$N$62:$W$62,1,(Resumen!$C$3-2025)) -> 521.99476 | H8: =SUMPRODUCT(Links!$F$62:$M$62,$O$5:$V$5)*IF(Links!$E$62="CABA",INDEX(Links!$C$13:$L$13,1,(Resumen!$C$3-2025)),IF(Links!$E$62="PBA",1-INDEX(Links!$C$13:$L$13,1,(Resumen!$C$3-2025)),1)) -> 523.19772 | I8: =G8-H8 -> -1.202963 | J8: =IF(ROUND(G8-H8,1)>=0,"✔ Sí","✖ No") -> ✖ No | K8: =IFERROR(INDEX(Links!$C$345:$C$469,MATCH(C8,Links!$B$218:$B$342,0)),1) -> 50 | L8: =IF(K8>0,H8/K8,0) -> 10.463954 | M8: =Links!$B$2192*Links!$C$2192*Links!$C$2203*7.85/1000000 -> 29.20985 | N8: =H8*M8 -> 15282.527
A9: MANUALES | B9: Chapa en hojas | C9: =Links!$B$63 -> MP-03 | D9: =Links!$C$63 -> Hoja LAF 1,6 × 1000 × 2000 mm | E9: =Links!$D$63 -> hoja | F9: =IFERROR(INDEX(Links!$B$345:$B$469,MATCH(C9,Links!$B$218:$B$342,0)),"") -> Paquete de 80 hojas | G9: =INDEX(Links!$N$63:$W$63,1,(Resumen!$C$3-2025)) -> 5314.6476 | H9: =SUMPRODUCT(Links!$F$63:$M$63,$O$5:$V$5)*IF(Links!$E$63="CABA",INDEX(Links!$C$13:$L$13,1,(Resumen!$C$3-2025)),IF(Links!$E$63="PBA",1-INDEX(Links!$C$13:$L$13,1,(Resumen!$C$3-2025)),1)) -> 5321.0549 | I9: =G9-H9 -> -6.4073361 | J9: =IF(ROUND(G9-H9,1)>=0,"✔ Sí","✖ No") -> ✖ No | K9: =IFERROR(INDEX(Links!$C$345:$C$469,MATCH(C9,Links!$B$218:$B$342,0)),1) -> 80 | L9: =IF(K9>0,H9/K9,0) -> 66.513186 | M9: =Links!$B$2193*Links!$C$2193*Links!$C$2204*7.85/1000000 -> 25.12 | N9: =H9*M9 -> 133664.9
A10: MANUALES | B10: Chapa en hojas | C10: =Links!$B$64 -> MP-04 | D10: =Links!$C$64 -> Hoja LAF 2,0 × 1500 × 3000 mm | E10: =Links!$D$64 -> hoja | F10: =IFERROR(INDEX(Links!$B$345:$B$469,MATCH(C10,Links!$B$218:$B$342,0)),"") -> Paquete de 20 hojas | G10: =INDEX(Links!$N$64:$W$64,1,(Resumen!$C$3-2025)) -> 256.92513 | H10: =SUMPRODUCT(Links!$F$64:$M$64,$O$5:$V$5)*IF(Links!$E$64="CABA",INDEX(Links!$C$13:$L$13,1,(Resumen!$C$3-2025)),IF(Links!$E$64="PBA",1-INDEX(Links!$C$13:$L$13,1,(Resumen!$C$3-2025)),1)) -> 257.52854 | I10: =G10-H10 -> -0.60340705 | J10: =IF(ROUND(G10-H10,1)>=0,"✔ Sí","✖ No") -> ✖ No | K10: =IFERROR(INDEX(Links!$C$345:$C$469,MATCH(C10,Links!$B$218:$B$342,0)),1) -> 20 | L10: =IF(K10>0,H10/K10,0) -> 12.876427 | M10: =Links!$B$2194*Links!$C$2194*Links!$C$2205*7.85/1000000 -> 70.65 | N10: =H10*M10 -> 18194.391
A11: MANUALES | B11: Fleje en rollos | C11: =Links!$B$65 -> MP-05 | D11: =Links!$C$65 -> Fleje LAF 0,9 × 93,05 mm (cúpula 1 kg) | E11: =Links!$D$65 -> kg | F11: =IFERROR(INDEX(Links!$B$345:$B$469,MATCH(C11,Links!$B$218:$B$342,0)),"") -> Rollo de 1.900 kg | G11: =INDEX(Links!$N$65:$W$65,1,(Resumen!$C$3-2025)) -> 12095.318 | H11: =SUMPRODUCT(Links!$F$65:$M$65,$O$5:$V$5)*IF(Links!$E$65="CABA",INDEX(Links!$C$13:$L$13,1,(Resumen!$C$3-2025)),IF(Links!$E$65="PBA",1-INDEX(Links!$C$13:$L$13,1,(Resumen!$C$3-2025)),1)) -> 12095.318 | I11: =G11-H11 -> 0 | J11: =IF(ROUND(G11-H11,1)>=0,"✔ Sí","✖ No") -> ✔ Sí | K11: =IFERROR(INDEX(Links!$C$345:$C$469,MATCH(C11,Links!$B$218:$B$342,0)),1) -> 1900 | L11: =IF(K11>0,H11/K11,0) -> 6.365957 | M11: =IF(E11="kg",1,0) -> 1 | N11: =H11*M11 -> 12095.318
A12: MANUALES | B12: Fleje en rollos | C12: =Links!$B$66 -> MP-13 | D12: =Links!$C$66 -> Fleje LAF 1,25 × 100,6 mm (fondo 1 kg) | E12: =Links!$D$66 -> kg | F12: =IFERROR(INDEX(Links!$B$345:$B$469,MATCH(C12,Links!$B$218:$B$342,0)),"") -> Rollo de 1.900 kg | G12: =INDEX(Links!$N$66:$W$66,1,(Resumen!$C$3-2025)) -> 19478.606 | H12: =SUMPRODUCT(Links!$F$66:$M$66,$O$5:$V$5)*IF(Links!$E$66="CABA",INDEX(Links!$C$13:$L$13,1,(Resumen!$C$3-2025)),IF(Links!$E$66="PBA",1-INDEX(Links!$C$13:$L$13,1,(Resumen!$C$3-2025)),1)) -> 19478.606 | I12: =G12-H12 -> 0 | J12: =IF(ROUND(G12-H12,1)>=0,"✔ Sí","✖ No") -> ✔ Sí | K12: =IFERROR(INDEX(Links!$C$345:$C$469,MATCH(C12,Links!$B$218:$B$342,0)),1) -> 1900 | L12: =IF(K12>0,H12/K12,0) -> 10.251898 | M12: =IF(E12="kg",1,0) -> 1 | N12: =H12*M12 -> 19478.606
A13: MANUALES | B13: Fleje en rollos | C13: =Links!$B$67 -> MP-06 | D13: =Links!$C$67 -> Fleje LAF 1,25 × 162,1 mm (cúpula 2,5 kg) | E13: =Links!$D$67 -> kg | F13: =IFERROR(INDEX(Links!$B$345:$B$469,MATCH(C13,Links!$B$218:$B$342,0)),"") -> Rollo de 492 kg | G13: =INDEX(Links!$N$67:$W$67,1,(Resumen!$C$3-2025)) -> 3568.8074 | H13: =SUMPRODUCT(Links!$F$67:$M$67,$O$5:$V$5)*IF(Links!$E$67="CABA",INDEX(Links!$C$13:$L$13,1,(Resumen!$C$3-2025)),IF(Links!$E$67="PBA",1-INDEX(Links!$C$13:$L$13,1,(Resumen!$C$3-2025)),1)) -> 3577.0319 | I13: =G13-H13 -> -8.2244947 | J13: =IF(ROUND(G13-H13,1)>=0,"✔ Sí","✖ No") -> ✖ No | K13: =IFERROR(INDEX(Links!$C$345:$C$469,MATCH(C13,Links!$B$218:$B$342,0)),1) -> 492 | L13: =IF(K13>0,H13/K13,0) -> 7.27039 | M13: =IF(E13="kg",1,0) -> 1 | N13: =H13*M13 -> 3577.0319
A14: MANUALES | B14: Fleje en rollos | C14: =Links!$B$68 -> MP-14 | D14: =Links!$C$68 -> Fleje LAF 1,25 × 146,1 mm (fondo 2,5 kg) | E14: =Links!$D$68 -> kg | F14: =IFERROR(INDEX(Links!$B$345:$B$469,MATCH(C14,Links!$B$218:$B$342,0)),"") -> Rollo de 492 kg | G14: =INDEX(Links!$N$68:$W$68,1,(Resumen!$C$3-2025)) -> 2891.6435 | H14: =SUMPRODUCT(Links!$F$68:$M$68,$O$5:$V$5)*IF(Links!$E$68="CABA",INDEX(Links!$C$13:$L$13,1,(Resumen!$C$3-2025)),IF(Links!$E$68="PBA",1-INDEX(Links!$C$13:$L$13,1,(Resumen!$C$3-2025)),1)) -> 2898.3075 | I14: =G14-H14 -> -6.6639368 | J14: =IF(ROUND(G14-H14,1)>=0,"✔ Sí","✖ No") -> ✖ No | K14: =IFERROR(INDEX(Links!$C$345:$C$469,MATCH(C14,Links!$B$218:$B$342,0)),1) -> 492 | L14: =IF(K14>0,H14/K14,0) -> 5.8908689 | M14: =IF(E14="kg",1,0) -> 1 | N14: =H14*M14 -> 2898.3075
A15: MANUALES | B15: Fleje en rollos | C15: =Links!$B$69 -> MP-07 | D15: =Links!$C$69 -> Fleje LAF 1,6 × 204,2 mm (cúpula 5 kg) | E15: =Links!$D$69 -> kg | F15: =IFERROR(INDEX(Links!$B$345:$B$469,MATCH(C15,Links!$B$218:$B$342,0)),"") -> Rollo de 615 kg | G15: =INDEX(Links!$N$69:$W$69,1,(Resumen!$C$3-2025)) -> 32779.563 | H15: =SUMPRODUCT(Links!$F$69:$M$69,$O$5:$V$5)*IF(Links!$E$69="CABA",INDEX(Links!$C$13:$L$13,1,(Resumen!$C$3-2025)),IF(Links!$E$69="PBA",1-INDEX(Links!$C$13:$L$13,1,(Resumen!$C$3-2025)),1)) -> 32819.083 | I15: =G15-H15 -> -39.519024 | J15: =IF(ROUND(G15-H15,1)>=0,"✔ Sí","✖ No") -> ✖ No | K15: =IFERROR(INDEX(Links!$C$345:$C$469,MATCH(C15,Links!$B$218:$B$342,0)),1) -> 615 | L15: =IF(K15>0,H15/K15,0) -> 53.364362 | M15: =IF(E15="kg",1,0) -> 1 | N15: =H15*M15 -> 32819.083
A16: MANUALES | B16: Fleje en rollos | C16: =Links!$B$70 -> MP-08 | D16: =Links!$C$70 -> Fleje LAF 1,6 × 177,2 mm (fondo 5 kg) | E16: =Links!$D$70 -> kg | F16: =IFERROR(INDEX(Links!$B$345:$B$469,MATCH(C16,Links!$B$218:$B$342,0)),"") -> Rollo de 492 kg | G16: =INDEX(Links!$N$70:$W$70,1,(Resumen!$C$3-2025)) -> 24593.665 | H16: =SUMPRODUCT(Links!$F$70:$M$70,$O$5:$V$5)*IF(Links!$E$70="CABA",INDEX(Links!$C$13:$L$13,1,(Resumen!$C$3-2025)),IF(Links!$E$70="PBA",1-INDEX(Links!$C$13:$L$13,1,(Resumen!$C$3-2025)),1)) -> 24623.315 | I16: =G16-H16 -> -29.650109 | J16: =IF(ROUND(G16-H16,1)>=0,"✔ Sí","✖ No") -> ✖ No | K16: =IFERROR(INDEX(Links!$C$345:$C$469,MATCH(C16,Links!$B$218:$B$342,0)),1) -> 492 | L16: =IF(K16>0,H16/K16,0) -> 50.047388 | M16: =IF(E16="kg",1,0) -> 1 | N16: =H16*M16 -> 24623.315
A17: MANUALES | B17: Fleje en rollos | C17: =Links!$B$71 -> MP-09 | D17: =Links!$C$71 -> Fleje LAF 1,6 × 238,7 mm (cúpula 10 kg) | E17: =Links!$D$71 -> kg | F17: =IFERROR(INDEX(Links!$B$345:$B$469,MATCH(C17,Links!$B$218:$B$342,0)),"") -> Rollo de 590 kg | G17: =INDEX(Links!$N$71:$W$71,1,(Resumen!$C$3-2025)) -> 2716.1081 | H17: =SUMPRODUCT(Links!$F$71:$M$71,$O$5:$V$5)*IF(Links!$E$71="CABA",INDEX(Links!$C$13:$L$13,1,(Resumen!$C$3-2025)),IF(Links!$E$71="PBA",1-INDEX(Links!$C$13:$L$13,1,(Resumen!$C$3-2025)),1)) -> 2722.487 | I17: =G17-H17 -> -6.3789741 | J17: =IF(ROUND(G17-H17,1)>=0,"✔ Sí","✖ No") -> ✖ No | K17: =IFERROR(INDEX(Links!$C$345:$C$469,MATCH(C17,Links!$B$218:$B$342,0)),1) -> 590 | L17: =IF(K17>0,H17/K17,0) -> 4.6143848 | M17: =IF(E17="kg",1,0) -> 1 | N17: =H17*M17 -> 2722.487
A18: MANUALES | B18: Fleje en rollos | C18: =Links!$B$72 -> MP-10 | D18: =Links!$C$72 -> Fleje LAF 2,0 × 205 mm (fondo 10 kg) | E18: =Links!$D$72 -> kg | F18: =IFERROR(INDEX(Links!$B$345:$B$469,MATCH(C18,Links!$B$218:$B$342,0)),"") -> Rollo de 498 kg | G18: =INDEX(Links!$N$72:$W$72,1,(Resumen!$C$3-2025)) -> 2480.7406 | H18: =SUMPRODUCT(Links!$F$72:$M$72,$O$5:$V$5)*IF(Links!$E$72="CABA",INDEX(Links!$C$13:$L$13,1,(Resumen!$C$3-2025)),IF(Links!$E$72="PBA",1-INDEX(Links!$C$13:$L$13,1,(Resumen!$C$3-2025)),1)) -> 2486.5668 | I18: =G18-H18 -> -5.8261968 | J18: =IF(ROUND(G18-H18,1)>=0,"✔ Sí","✖ No") -> ✖ No | K18: =IFERROR(INDEX(Links!$C$345:$C$469,MATCH(C18,Links!$B$218:$B$342,0)),1) -> 498 | L18: =IF(K18>0,H18/K18,0) -> 4.993106 | M18: =IF(E18="kg",1,0) -> 1 | N18: =H18*M18 -> 2486.5668
A19: MANUALES | B19: Asientos de válvula | C19: =Links!$B$73 -> MP-18 | D19: =Links!$C$73 -> Asiento de válvula M22 × 1,5 (1 kg) | E19: =Links!$D$73 -> u | F19: =IFERROR(INDEX(Links!$B$345:$B$469,MATCH(C19,Links!$B$218:$B$342,0)),"") -> Caja de 1.000 u | G19: =INDEX(Links!$N$73:$W$73,1,(Resumen!$C$3-2025)) -> 202620.64 | H19: =SUMPRODUCT(Links!$F$73:$M$73,$O$5:$V$5)*IF(Links!$E$73="CABA",INDEX(Links!$C$13:$L$13,1,(Resumen!$C$3-2025)),IF(Links!$E$73="PBA",1-INDEX(Links!$C$13:$L$13,1,(Resumen!$C$3-2025)),1)) -> 202620.64 | I19: =G19-H19 -> 0 | J19: =IF(ROUND(G19-H19,1)>=0,"✔ Sí","✖ No") -> ✔ Sí | K19: =IFERROR(INDEX(Links!$C$345:$C$469,MATCH(C19,Links!$B$218:$B$342,0)),1) -> 1000 | L19: =IF(K19>0,H19/K19,0) -> 202.62064 | M19: =IF(E19="kg",1,0) -> 0 | N19: =H19*M19 -> 0
A20: MANUALES | B20: Asientos de válvula | C20: =Links!$B$74 -> MP-19 | D20: =Links!$C$74 -> Asiento de válvula M30 × 1,5 (2,5 a 10 kg) | E20: =Links!$D$74 -> u | F20: =IFERROR(INDEX(Links!$B$345:$B$469,MATCH(C20,Links!$B$218:$B$342,0)),"") -> Caja de 1.000 u | G20: =INDEX(Links!$N$74:$W$74,1,(Resumen!$C$3-2025)) -> 81723.506 | H20: =SUMPRODUCT(Links!$F$74:$M$74,$O$5:$V$5)*IF(Links!$E$74="CABA",INDEX(Links!$C$13:$L$13,1,(Resumen!$C$3-2025)),IF(Links!$E$74="PBA",1-INDEX(Links!$C$13:$L$13,1,(Resumen!$C$3-2025)),1)) -> 81841.925 | I20: =G20-H20 -> -118.41914 | J20: =IF(ROUND(G20-H20,1)>=0,"✔ Sí","✖ No") -> ✖ No | K20: =IFERROR(INDEX(Links!$C$345:$C$469,MATCH(C20,Links!$B$218:$B$342,0)),1) -> 1000 | L20: =IF(K20>0,H20/K20,0) -> 81.841925 | M20: =IF(E20="kg",1,0) -> 0 | N20: =H20*M20 -> 0
A21: MANUALES | B21: Soldadura: alambre | C21: =Links!$B$75 -> MP-23 | D21: =Links!$C$75 -> Alambre MAG ER70S-6 Ø0,9 mm (manuales) | E21: =Links!$D$75 -> kg | F21: =IFERROR(INDEX(Links!$B$345:$B$469,MATCH(C21,Links!$B$218:$B$342,0)),"") -> Pallet de 900 kg | G21: =INDEX(Links!$N$75:$W$75,1,(Resumen!$C$3-2025)) -> 5985.8111 | H21: =SUMPRODUCT(Links!$F$75:$M$75,$O$5:$V$5)*IF(Links!$E$75="CABA",INDEX(Links!$C$13:$L$13,1,(Resumen!$C$3-2025)),IF(Links!$E$75="PBA",1-INDEX(Links!$C$13:$L$13,1,(Resumen!$C$3-2025)),1)) -> 5990.0382 | I21: =G21-H21 -> -4.2271153 | J21: =IF(ROUND(G21-H21,1)>=0,"✔ Sí","✖ No") -> ✖ No | K21: =IFERROR(INDEX(Links!$C$345:$C$469,MATCH(C21,Links!$B$218:$B$342,0)),1) -> 900 | L21: =IF(K21>0,H21/K21,0) -> 6.655598 | M21: =IF(E21="kg",1,0) -> 1 | N21: =H21*M21 -> 5990.0382
A22: MANUALES | B22: Soldadura: gases | C22: =Links!$B$76 -> MP-25 | D22: =Links!$C$76 -> Gas MAG Ar + 8 % CO₂ (Arcal 21) | E22: =Links!$D$76 -> m³ | F22: =IFERROR(INDEX(Links!$B$345:$B$469,MATCH(C22,Links!$B$218:$B$342,0)),"") -> Batería de 11 cilindros | G22: =INDEX(Links!$N$76:$W$76,1,(Resumen!$C$3-2025)) -> 7393.1341 | H22: =SUMPRODUCT(Links!$F$76:$M$76,$O$5:$V$5)*IF(Links!$E$76="CABA",INDEX(Links!$C$13:$L$13,1,(Resumen!$C$3-2025)),IF(Links!$E$76="PBA",1-INDEX(Links!$C$13:$L$13,1,(Resumen!$C$3-2025)),1)) -> 7398.3547 | I22: =G22-H22 -> -5.2205103 | J22: =IF(ROUND(G22-H22,1)>=0,"✔ Sí","✖ No") -> ✖ No | K22: =IFERROR(INDEX(Links!$C$345:$C$469,MATCH(C22,Links!$B$218:$B$342,0)),1) -> 115.5 | L22: =IF(K22>0,H22/K22,0) -> 64.055019 | M22: =IF(E22="kg",1,0) -> 0 | N22: =H22*M22 -> 0
A23: MANUALES | B23: Soldadura: gases | C23: =Links!$B$77 -> MP-26 | D23: =Links!$C$77 -> Argón puro EN ISO 14175 I1 (costura longitudinal TIG del 1 kg) | E23: =Links!$D$77 -> m³ | F23: =IFERROR(INDEX(Links!$B$345:$B$469,MATCH(C23,Links!$B$218:$B$342,0)),"") -> Cilindro de 10,5 m³ | G23: =INDEX(Links!$N$77:$W$77,1,(Resumen!$C$3-2025)) -> 800.55415 | H23: =SUMPRODUCT(Links!$F$77:$M$77,$O$5:$V$5)*IF(Links!$E$77="CABA",INDEX(Links!$C$13:$L$13,1,(Resumen!$C$3-2025)),IF(Links!$E$77="PBA",1-INDEX(Links!$C$13:$L$13,1,(Resumen!$C$3-2025)),1)) -> 800.55415 | I23: =G23-H23 -> 0 | J23: =IF(ROUND(G23-H23,1)>=0,"✔ Sí","✖ No") -> ✔ Sí | K23: =IFERROR(INDEX(Links!$C$345:$C$469,MATCH(C23,Links!$B$218:$B$342,0)),1) -> 10.5 | L23: =IF(K23>0,H23/K23,0) -> 76.243252 | M23: =IF(E23="kg",1,0) -> 0 | N23: =H23*M23 -> 0
A24: MANUALES | B24: Soldadura: electrodo TIG | C24: =Links!$B$78 -> MP-29 | D24: =Links!$C$78 -> Electrodo de tungsteno lantanado 2 % (WL20) Ø2,4 × 175 mm | E24: =Links!$D$78 -> u | F24: =IFERROR(INDEX(Links!$B$345:$B$469,MATCH(C24,Links!$B$218:$B$342,0)),"") -> Caja de 10 u | G24: =INDEX(Links!$N$78:$W$78,1,(Resumen!$C$3-2025)) -> 166.62882 | H24: =SUMPRODUCT(Links!$F$78:$M$78,$O$5:$V$5)*IF(Links!$E$78="CABA",INDEX(Links!$C$13:$L$13,1,(Resumen!$C$3-2025)),IF(Links!$E$78="PBA",1-INDEX(Links!$C$13:$L$13,1,(Resumen!$C$3-2025)),1)) -> 166.62882 | I24: =G24-H24 -> 0 | J24: =IF(ROUND(G24-H24,1)>=0,"✔ Sí","✖ No") -> ✔ Sí | K24: =IFERROR(INDEX(Links!$C$345:$C$469,MATCH(C24,Links!$B$218:$B$342,0)),1) -> 10 | L24: =IF(K24>0,H24/K24,0) -> 16.662882 | M24: =IF(E24="kg",1,0) -> 0 | N24: =H24*M24 -> 0
A25: MANUALES | B25: Granalla | C25: =Links!$B$79 -> MP-28 | D25: =Links!$C$79 -> Granalla de acero S330 / S390 | E25: =Links!$D$79 -> kg | F25: =IFERROR(INDEX(Links!$B$345:$B$469,MATCH(C25,Links!$B$218:$B$342,0)),"") -> Pallet de 1.000 kg | G25: =INDEX(Links!$N$79:$W$79,1,(Resumen!$C$3-2025)) -> 22747.532 | H25: =SUMPRODUCT(Links!$F$79:$M$79,$O$5:$V$5)*IF(Links!$E$79="CABA",INDEX(Links!$C$13:$L$13,1,(Resumen!$C$3-2025)),IF(Links!$E$79="PBA",1-INDEX(Links!$C$13:$L$13,1,(Resumen!$C$3-2025)),1)) -> 22757.005 | I25: =G25-H25 -> -9.4735312 | J25: =IF(ROUND(G25-H25,1)>=0,"✔ Sí","✖ No") -> ✖ No | K25: =IFERROR(INDEX(Links!$C$345:$C$469,MATCH(C25,Links!$B$218:$B$342,0)),1) -> 1000 | L25: =IF(K25>0,H25/K25,0) -> 22.757005 | M25: =IF(E25="kg",1,0) -> 1 | N25: =H25*M25 -> 22757.005
A26: MANUALES | B26: Pintura | C26: =Links!$B$80 -> MP-31 | D26: =Links!$C$80 -> Pintura en polvo poliéster rojo 03-1-050 | E26: =Links!$D$80 -> kg | F26: =IFERROR(INDEX(Links!$B$345:$B$469,MATCH(C26,Links!$B$218:$B$342,0)),"") -> Pallet de 600 kg | G26: =INDEX(Links!$N$80:$W$80,1,(Resumen!$C$3-2025)) -> 3579.296 | H26: =SUMPRODUCT(Links!$F$80:$M$80,$O$5:$V$5)*IF(Links!$E$80="CABA",INDEX(Links!$C$13:$L$13,1,(Resumen!$C$3-2025)),IF(Links!$E$80="PBA",1-INDEX(Links!$C$13:$L$13,1,(Resumen!$C$3-2025)),1)) -> 3581.9354 | I26: =G26-H26 -> -2.6393931 | J26: =IF(ROUND(G26-H26,1)>=0,"✔ Sí","✖ No") -> ✖ No | K26: =IFERROR(INDEX(Links!$C$345:$C$469,MATCH(C26,Links!$B$218:$B$342,0)),1) -> 600 | L26: =IF(K26>0,H26/K26,0) -> 5.9698923 | M26: =IF(E26="kg",1,0) -> 1 | N26: =H26*M26 -> 3581.9354
A27: MANUALES | B27: Agente: polvo | C27: =Links!$B$81 -> MP-33 | D27: =Links!$C$81 -> Polvo ABC 60 (manuales y sus recargas) | E27: =Links!$D$81 -> kg | F27: =IFERROR(INDEX(Links!$B$345:$B$469,MATCH(C27,Links!$B$218:$B$342,0)),"") -> Big bag de 1.000 kg | G27: =INDEX(Links!$N$81:$W$81,1,(Resumen!$C$3-2025)) -> 230247.83 | H27: =SUMPRODUCT(Links!$F$81:$M$81,$O$5:$V$5)*IF(Links!$E$81="CABA",INDEX(Links!$C$13:$L$13,1,(Resumen!$C$3-2025)),IF(Links!$E$81="PBA",1-INDEX(Links!$C$13:$L$13,1,(Resumen!$C$3-2025)),1)) -> 230062.4 | I27: =G27-H27 -> 185.4299 | J27: =IF(ROUND(G27-H27,1)>=0,"✔ Sí","✖ No") -> ✔ Sí | K27: =IFERROR(INDEX(Links!$C$345:$C$469,MATCH(C27,Links!$B$218:$B$342,0)),1) -> 1000 | L27: =IF(K27>0,H27/K27,0) -> 230.0624 | M27: =IF(E27="kg",1,0) -> 1 | N27: =H27*M27 -> 230062.4
A28: MANUALES | B28: Nitrógeno | C28: =Links!$B$82 -> MP-34 | D28: =Links!$C$82 -> Nitrógeno seco | E28: =Links!$D$82 -> m³ | F28: =IFERROR(INDEX(Links!$B$345:$B$469,MATCH(C28,Links!$B$218:$B$342,0)),"") -> Pack de 12 cilindros | G28: =INDEX(Links!$N$82:$W$82,1,(Resumen!$C$3-2025)) -> 1269.4888 | H28: =SUMPRODUCT(Links!$F$82:$M$82,$O$5:$V$5)*IF(Links!$E$82="CABA",INDEX(Links!$C$13:$L$13,1,(Resumen!$C$3-2025)),IF(Links!$E$82="PBA",1-INDEX(Links!$C$13:$L$13,1,(Resumen!$C$3-2025)),1)) -> 1268.5157 | I28: =G28-H28 -> 0.97306055 | J28: =IF(ROUND(G28-H28,1)>=0,"✔ Sí","✖ No") -> ✔ Sí | K28: =IFERROR(INDEX(Links!$C$345:$C$469,MATCH(C28,Links!$B$218:$B$342,0)),1) -> 110 | L28: =IF(K28>0,H28/K28,0) -> 11.531961 | M28: =IF(E28="kg",1,0) -> 0 | N28: =H28*M28 -> 0
A29: MANUALES | B29: Componentes comprados | C29: =Links!$B$83 -> MP-42 | D29: =Links!$C$83 -> Válvula HZ M-22 con tubo de pesca (1 kg) | E29: =Links!$D$83 -> u | F29: =IFERROR(INDEX(Links!$B$345:$B$469,MATCH(C29,Links!$B$218:$B$342,0)),"") -> Pallet de 3.000 u | G29: =INDEX(Links!$N$83:$W$83,1,(Resumen!$C$3-2025)) -> 32072.639 | H29: =SUMPRODUCT(Links!$F$83:$M$83,$O$5:$V$5)*IF(Links!$E$83="CABA",INDEX(Links!$C$13:$L$13,1,(Resumen!$C$3-2025)),IF(Links!$E$83="PBA",1-INDEX(Links!$C$13:$L$13,1,(Resumen!$C$3-2025)),1)) -> 32072.639 | I29: =G29-H29 -> 0 | J29: =IF(ROUND(G29-H29,1)>=0,"✔ Sí","✖ No") -> ✔ Sí | K29: =IFERROR(INDEX(Links!$C$345:$C$469,MATCH(C29,Links!$B$218:$B$342,0)),1) -> 3000 | L29: =IF(K29>0,H29/K29,0) -> 10.69088 | M29: =IF(E29="kg",1,0) -> 0 | N29: =H29*M29 -> 0
A30: MANUALES | B30: Componentes comprados | C30: =Links!$B$84 -> MP-43 | D30: =Links!$C$84 -> Válvula HZ M-30 con resorte, sin tubo pescante (2,5 a 10 kg) | E30: =Links!$D$84 -> u | F30: =IFERROR(INDEX(Links!$B$345:$B$469,MATCH(C30,Links!$B$218:$B$342,0)),"") -> Pallet de 1.500 u | G30: =INDEX(Links!$N$84:$W$84,1,(Resumen!$C$3-2025)) -> 40128.506 | H30: =SUMPRODUCT(Links!$F$84:$M$84,$O$5:$V$5)*IF(Links!$E$84="CABA",INDEX(Links!$C$13:$L$13,1,(Resumen!$C$3-2025)),IF(Links!$E$84="PBA",1-INDEX(Links!$C$13:$L$13,1,(Resumen!$C$3-2025)),1)) -> 40096.365 | I30: =G30-H30 -> 32.14086 | J30: =IF(ROUND(G30-H30,1)>=0,"✔ Sí","✖ No") -> ✔ Sí | K30: =IFERROR(INDEX(Links!$C$345:$C$469,MATCH(C30,Links!$B$218:$B$342,0)),1) -> 1500 | L30: =IF(K30>0,H30/K30,0) -> 26.73091 | M30: =IF(E30="kg",1,0) -> 0 | N30: =H30*M30 -> 0
A31: MANUALES | B31: Componentes comprados | C31: =Links!$B$85 -> MP-45 | D31: =Links!$C$85 -> Manómetro 1,4 MPa | E31: =Links!$D$85 -> u | F31: =IFERROR(INDEX(Links!$B$345:$B$469,MATCH(C31,Links!$B$218:$B$342,0)),"") -> Caja de 100 u | G31: =INDEX(Links!$N$85:$W$85,1,(Resumen!$C$3-2025)) -> 72201.145 | H31: =SUMPRODUCT(Links!$F$85:$M$85,$O$5:$V$5)*IF(Links!$E$85="CABA",INDEX(Links!$C$13:$L$13,1,(Resumen!$C$3-2025)),IF(Links!$E$85="PBA",1-INDEX(Links!$C$13:$L$13,1,(Resumen!$C$3-2025)),1)) -> 72169.004 | I31: =G31-H31 -> 32.14086 | J31: =IF(ROUND(G31-H31,1)>=0,"✔ Sí","✖ No") -> ✔ Sí | K31: =IFERROR(INDEX(Links!$C$345:$C$469,MATCH(C31,Links!$B$218:$B$342,0)),1) -> 100 | L31: =IF(K31>0,H31/K31,0) -> 721.69004 | M31: =IF(E31="kg",1,0) -> 0 | N31: =H31*M31 -> 0
A32: MANUALES | B32: Componentes comprados | C32: =Links!$B$86 -> MP-46/ABC2.5 | D32: =Links!$C$86 -> Tubo pescante de PVC rígido, ABC 2,5 kg | E32: =Links!$D$86 -> u | F32: =IFERROR(INDEX(Links!$B$345:$B$469,MATCH(C32,Links!$B$218:$B$342,0)),"") -> Caja de 200 u | G32: =INDEX(Links!$N$86:$W$86,1,(Resumen!$C$3-2025)) -> 7424.8584 | H32: =SUMPRODUCT(Links!$F$86:$M$86,$O$5:$V$5)*IF(Links!$E$86="CABA",INDEX(Links!$C$13:$L$13,1,(Resumen!$C$3-2025)),IF(Links!$E$86="PBA",1-INDEX(Links!$C$13:$L$13,1,(Resumen!$C$3-2025)),1)) -> 7436.4584 | I32: =G32-H32 -> -11.6 | J32: =IF(ROUND(G32-H32,1)>=0,"✔ Sí","✖ No") -> ✖ No | K32: =IFERROR(INDEX(Links!$C$345:$C$469,MATCH(C32,Links!$B$218:$B$342,0)),1) -> 200 | L32: =IF(K32>0,H32/K32,0) -> 37.182292 | M32: =IF(E32="kg",1,0) -> 0 | N32: =H32*M32 -> 0
A33: MANUALES | B33: Componentes comprados | C33: =Links!$B$87 -> MP-46/ABC5 | D33: =Links!$C$87 -> Tubo pescante de PVC rígido, ABC 5 kg | E33: =Links!$D$87 -> u | F33: =IFERROR(INDEX(Links!$B$345:$B$469,MATCH(C33,Links!$B$218:$B$342,0)),"") -> Caja de 200 u | G33: =INDEX(Links!$N$87:$W$87,1,(Resumen!$C$3-2025)) -> 30860.771 | H33: =SUMPRODUCT(Links!$F$87:$M$87,$O$5:$V$5)*IF(Links!$E$87="CABA",INDEX(Links!$C$13:$L$13,1,(Resumen!$C$3-2025)),IF(Links!$E$87="PBA",1-INDEX(Links!$C$13:$L$13,1,(Resumen!$C$3-2025)),1)) -> 30814.979 | I33: =G33-H33 -> 45.791966 | J33: =IF(ROUND(G33-H33,1)>=0,"✔ Sí","✖ No") -> ✔ Sí | K33: =IFERROR(INDEX(Links!$C$345:$C$469,MATCH(C33,Links!$B$218:$B$342,0)),1) -> 200 | L33: =IF(K33>0,H33/K33,0) -> 154.07489 | M33: =IF(E33="kg",1,0) -> 0 | N33: =H33*M33 -> 0
A34: MANUALES | B34: Componentes comprados | C34: =Links!$B$88 -> MP-46/ABC10 | D34: =Links!$C$88 -> Tubo pescante de PVC rígido, ABC 10 kg | E34: =Links!$D$88 -> u | F34: =IFERROR(INDEX(Links!$B$345:$B$469,MATCH(C34,Links!$B$218:$B$342,0)),"") -> Caja de 200 u | G34: =INDEX(Links!$N$88:$W$88,1,(Resumen!$C$3-2025)) -> 1842.877 | H34: =SUMPRODUCT(Links!$F$88:$M$88,$O$5:$V$5)*IF(Links!$E$88="CABA",INDEX(Links!$C$13:$L$13,1,(Resumen!$C$3-2025)),IF(Links!$E$88="PBA",1-INDEX(Links!$C$13:$L$13,1,(Resumen!$C$3-2025)),1)) -> 1844.9281 | I34: =G34-H34 -> -2.0511058 | J34: =IF(ROUND(G34-H34,1)>=0,"✔ Sí","✖ No") -> ✖ No | K34: =IFERROR(INDEX(Links!$C$345:$C$469,MATCH(C34,Links!$B$218:$B$342,0)),1) -> 200 | L34: =IF(K34>0,H34/K34,0) -> 9.2246404 | M34: =IF(E34="kg",1,0) -> 0 | N34: =H34*M34 -> 0
A35: MANUALES | B35: Componentes comprados | C35: =Links!$B$89 -> MP-48/ABC1 | D35: =Links!$C$89 -> Tobera ABC 1 kg | E35: =Links!$D$89 -> u | F35: =IFERROR(INDEX(Links!$B$345:$B$469,MATCH(C35,Links!$B$218:$B$342,0)),"") -> Caja de 50 u | G35: =INDEX(Links!$N$89:$W$89,1,(Resumen!$C$3-2025)) -> 32072.639 | H35: =SUMPRODUCT(Links!$F$89:$M$89,$O$5:$V$5)*IF(Links!$E$89="CABA",INDEX(Links!$C$13:$L$13,1,(Resumen!$C$3-2025)),IF(Links!$E$89="PBA",1-INDEX(Links!$C$13:$L$13,1,(Resumen!$C$3-2025)),1)) -> 32072.639 | I35: =G35-H35 -> 0 | J35: =IF(ROUND(G35-H35,1)>=0,"✔ Sí","✖ No") -> ✔ Sí | K35: =IFERROR(INDEX(Links!$C$345:$C$469,MATCH(C35,Links!$B$218:$B$342,0)),1) -> 50 | L35: =IF(K35>0,H35/K35,0) -> 641.45278 | M35: =IF(E35="kg",1,0) -> 0 | N35: =H35*M35 -> 0
A36: MANUALES | B36: Componentes comprados | C36: =Links!$B$90 -> MP-48/ABC2.5 | D36: =Links!$C$90 -> Manguera con tobera ABC 2,5 kg | E36: =Links!$D$90 -> u | F36: =IFERROR(INDEX(Links!$B$345:$B$469,MATCH(C36,Links!$B$218:$B$342,0)),"") -> Caja de 50 u | G36: =INDEX(Links!$N$90:$W$90,1,(Resumen!$C$3-2025)) -> 7424.8584 | H36: =SUMPRODUCT(Links!$F$90:$M$90,$O$5:$V$5)*IF(Links!$E$90="CABA",INDEX(Links!$C$13:$L$13,1,(Resumen!$C$3-2025)),IF(Links!$E$90="PBA",1-INDEX(Links!$C$13:$L$13,1,(Resumen!$C$3-2025)),1)) -> 7436.4584 | I36: =G36-H36 -> -11.6 | J36: =IF(ROUND(G36-H36,1)>=0,"✔ Sí","✖ No") -> ✖ No | K36: =IFERROR(INDEX(Links!$C$345:$C$469,MATCH(C36,Links!$B$218:$B$342,0)),1) -> 50 | L36: =IF(K36>0,H36/K36,0) -> 148.72917 | M36: =IF(E36="kg",1,0) -> 0 | N36: =H36*M36 -> 0
A37: MANUALES | B37: Componentes comprados | C37: =Links!$B$91 -> MP-48/ABC5 | D37: =Links!$C$91 -> Manguera con tobera ABC 5 kg | E37: =Links!$D$91 -> u | F37: =IFERROR(INDEX(Links!$B$345:$B$469,MATCH(C37,Links!$B$218:$B$342,0)),"") -> Caja de 50 u | G37: =INDEX(Links!$N$91:$W$91,1,(Resumen!$C$3-2025)) -> 30860.771 | H37: =SUMPRODUCT(Links!$F$91:$M$91,$O$5:$V$5)*IF(Links!$E$91="CABA",INDEX(Links!$C$13:$L$13,1,(Resumen!$C$3-2025)),IF(Links!$E$91="PBA",1-INDEX(Links!$C$13:$L$13,1,(Resumen!$C$3-2025)),1)) -> 30814.979 | I37: =G37-H37 -> 45.791966 | J37: =IF(ROUND(G37-H37,1)>=0,"✔ Sí","✖ No") -> ✔ Sí | K37: =IFERROR(INDEX(Links!$C$345:$C$469,MATCH(C37,Links!$B$218:$B$342,0)),1) -> 50 | L37: =IF(K37>0,H37/K37,0) -> 616.29957 | M37: =IF(E37="kg",1,0) -> 0 | N37: =H37*M37 -> 0
A38: MANUALES | B38: Componentes comprados | C38: =Links!$B$92 -> MP-48/ABC10 | D38: =Links!$C$92 -> Manguera con tobera ABC 10 kg | E38: =Links!$D$92 -> u | F38: =IFERROR(INDEX(Links!$B$345:$B$469,MATCH(C38,Links!$B$218:$B$342,0)),"") -> Caja de 50 u | G38: =INDEX(Links!$N$92:$W$92,1,(Resumen!$C$3-2025)) -> 1842.877 | H38: =SUMPRODUCT(Links!$F$92:$M$92,$O$5:$V$5)*IF(Links!$E$92="CABA",INDEX(Links!$C$13:$L$13,1,(Resumen!$C$3-2025)),IF(Links!$E$92="PBA",1-INDEX(Links!$C$13:$L$13,1,(Resumen!$C$3-2025)),1)) -> 1844.9281 | I38: =G38-H38 -> -2.0511058 | J38: =IF(ROUND(G38-H38,1)>=0,"✔ Sí","✖ No") -> ✖ No | K38: =IFERROR(INDEX(Links!$C$345:$C$469,MATCH(C38,Links!$B$218:$B$342,0)),1) -> 50 | L38: =IF(K38>0,H38/K38,0) -> 36.898562 | M38: =IF(E38="kg",1,0) -> 0 | N38: =H38*M38 -> 0
A39: MANUALES | B39: Componentes comprados | C39: =Links!$B$93 -> MP-50/M22 | D39: =Links!$C$93 -> Junta tórica del cuello M22 | E39: =Links!$D$93 -> u | F39: =IFERROR(INDEX(Links!$B$345:$B$469,MATCH(C39,Links!$B$218:$B$342,0)),"") -> Bolsa de 1.000 u | G39: =INDEX(Links!$N$93:$W$93,1,(Resumen!$C$3-2025)) -> 32072.639 | H39: =SUMPRODUCT(Links!$F$93:$M$93,$O$5:$V$5)*IF(Links!$E$93="CABA",INDEX(Links!$C$13:$L$13,1,(Resumen!$C$3-2025)),IF(Links!$E$93="PBA",1-INDEX(Links!$C$13:$L$13,1,(Resumen!$C$3-2025)),1)) -> 32072.639 | I39: =G39-H39 -> 0 | J39: =IF(ROUND(G39-H39,1)>=0,"✔ Sí","✖ No") -> ✔ Sí | K39: =IFERROR(INDEX(Links!$C$345:$C$469,MATCH(C39,Links!$B$218:$B$342,0)),1) -> 1000 | L39: =IF(K39>0,H39/K39,0) -> 32.072639 | M39: =IF(E39="kg",1,0) -> 0 | N39: =H39*M39 -> 0
A40: MANUALES | B40: Componentes comprados | C40: =Links!$B$94 -> MP-50/M30 | D40: =Links!$C$94 -> Junta tórica del cuello M30 | E40: =Links!$D$94 -> u | F40: =IFERROR(INDEX(Links!$B$345:$B$469,MATCH(C40,Links!$B$218:$B$342,0)),"") -> Bolsa de 1.000 u | G40: =INDEX(Links!$N$94:$W$94,1,(Resumen!$C$3-2025)) -> 40128.506 | H40: =SUMPRODUCT(Links!$F$94:$M$94,$O$5:$V$5)*IF(Links!$E$94="CABA",INDEX(Links!$C$13:$L$13,1,(Resumen!$C$3-2025)),IF(Links!$E$94="PBA",1-INDEX(Links!$C$13:$L$13,1,(Resumen!$C$3-2025)),1)) -> 40096.365 | I40: =G40-H40 -> 32.14086 | J40: =IF(ROUND(G40-H40,1)>=0,"✔ Sí","✖ No") -> ✔ Sí | K40: =IFERROR(INDEX(Links!$C$345:$C$469,MATCH(C40,Links!$B$218:$B$342,0)),1) -> 1000 | L40: =IF(K40>0,H40/K40,0) -> 40.096365 | M40: =IF(E40="kg",1,0) -> 0 | N40: =H40*M40 -> 0
A41: MANUALES | B41: Componentes comprados | C41: =Links!$B$95 -> MP-52/ABC2.5 | D41: =Links!$C$95 -> Soporte de pared ABC 2,5 kg | E41: =Links!$D$95 -> u | F41: =IFERROR(INDEX(Links!$B$345:$B$469,MATCH(C41,Links!$B$218:$B$342,0)),"") -> Caja de 100 u | G41: =INDEX(Links!$N$95:$W$95,1,(Resumen!$C$3-2025)) -> 7424.8584 | H41: =SUMPRODUCT(Links!$F$95:$M$95,$O$5:$V$5)*IF(Links!$E$95="CABA",INDEX(Links!$C$13:$L$13,1,(Resumen!$C$3-2025)),IF(Links!$E$95="PBA",1-INDEX(Links!$C$13:$L$13,1,(Resumen!$C$3-2025)),1)) -> 7436.4584 | I41: =G41-H41 -> -11.6 | J41: =IF(ROUND(G41-H41,1)>=0,"✔ Sí","✖ No") -> ✖ No | K41: =IFERROR(INDEX(Links!$C$345:$C$469,MATCH(C41,Links!$B$218:$B$342,0)),1) -> 100 | L41: =IF(K41>0,H41/K41,0) -> 74.364584 | M41: =IF(E41="kg",1,0) -> 0 | N41: =H41*M41 -> 0
A42: MANUALES | B42: Componentes comprados | C42: =Links!$B$96 -> MP-52/ABC5 | D42: =Links!$C$96 -> Soporte de pared ABC 5 kg | E42: =Links!$D$96 -> u | F42: =IFERROR(INDEX(Links!$B$345:$B$469,MATCH(C42,Links!$B$218:$B$342,0)),"") -> Caja de 100 u | G42: =INDEX(Links!$N$96:$W$96,1,(Resumen!$C$3-2025)) -> 30860.771 | H42: =SUMPRODUCT(Links!$F$96:$M$96,$O$5:$V$5)*IF(Links!$E$96="CABA",INDEX(Links!$C$13:$L$13,1,(Resumen!$C$3-2025)),IF(Links!$E$96="PBA",1-INDEX(Links!$C$13:$L$13,1,(Resumen!$C$3-2025)),1)) -> 30814.979 | I42: =G42-H42 -> 45.791966 | J42: =IF(ROUND(G42-H42,1)>=0,"✔ Sí","✖ No") -> ✔ Sí | K42: =IFERROR(INDEX(Links!$C$345:$C$469,MATCH(C42,Links!$B$218:$B$342,0)),1) -> 100 | L42: =IF(K42>0,H42/K42,0) -> 308.14979 | M42: =IF(E42="kg",1,0) -> 0 | N42: =H42*M42 -> 0
A43: MANUALES | B43: Componentes comprados | C43: =Links!$B$97 -> MP-52/ABC10 | D43: =Links!$C$97 -> Soporte de pared ABC 10 kg | E43: =Links!$D$97 -> u | F43: =IFERROR(INDEX(Links!$B$345:$B$469,MATCH(C43,Links!$B$218:$B$342,0)),"") -> Caja de 100 u | G43: =INDEX(Links!$N$97:$W$97,1,(Resumen!$C$3-2025)) -> 1842.877 | H43: =SUMPRODUCT(Links!$F$97:$M$97,$O$5:$V$5)*IF(Links!$E$97="CABA",INDEX(Links!$C$13:$L$13,1,(Resumen!$C$3-2025)),IF(Links!$E$97="PBA",1-INDEX(Links!$C$13:$L$13,1,(Resumen!$C$3-2025)),1)) -> 1844.9281 | I43: =G43-H43 -> -2.0511058 | J43: =IF(ROUND(G43-H43,1)>=0,"✔ Sí","✖ No") -> ✖ No | K43: =IFERROR(INDEX(Links!$C$345:$C$469,MATCH(C43,Links!$B$218:$B$342,0)),1) -> 100 | L43: =IF(K43>0,H43/K43,0) -> 18.449281 | M43: =IF(E43="kg",1,0) -> 0 | N43: =H43*M43 -> 0
A44: MANUALES | B44: Componentes comprados | C44: =Links!$B$98 -> MP-87 | D44: =Links!$C$98 -> Soporte vehicular (1 kg) | E44: =Links!$D$98 -> u | F44: =IFERROR(INDEX(Links!$B$345:$B$469,MATCH(C44,Links!$B$218:$B$342,0)),"") -> Caja de 100 u | G44: =INDEX(Links!$N$98:$W$98,1,(Resumen!$C$3-2025)) -> 32072.639 | H44: =SUMPRODUCT(Links!$F$98:$M$98,$O$5:$V$5)*IF(Links!$E$98="CABA",INDEX(Links!$C$13:$L$13,1,(Resumen!$C$3-2025)),IF(Links!$E$98="PBA",1-INDEX(Links!$C$13:$L$13,1,(Resumen!$C$3-2025)),1)) -> 32072.639 | I44: =G44-H44 -> 0 | J44: =IF(ROUND(G44-H44,1)>=0,"✔ Sí","✖ No") -> ✔ Sí | K44: =IFERROR(INDEX(Links!$C$345:$C$469,MATCH(C44,Links!$B$218:$B$342,0)),1) -> 100 | L44: =IF(K44>0,H44/K44,0) -> 320.72639 | M44: =IF(E44="kg",1,0) -> 0 | N44: =H44*M44 -> 0
A45: MANUALES | B45: Componentes comprados | C45: =Links!$B$99 -> MP-86 | D45: =Links!$C$99 -> Tornillo y tarugo de fijación | E45: =Links!$D$99 -> u | F45: =IFERROR(INDEX(Links!$B$345:$B$469,MATCH(C45,Links!$B$218:$B$342,0)),"") -> Bolsa de 1.000 u | G45: =INDEX(Links!$N$99:$W$99,1,(Resumen!$C$3-2025)) -> 80257.012 | H45: =SUMPRODUCT(Links!$F$99:$M$99,$O$5:$V$5)*IF(Links!$E$99="CABA",INDEX(Links!$C$13:$L$13,1,(Resumen!$C$3-2025)),IF(Links!$E$99="PBA",1-INDEX(Links!$C$13:$L$13,1,(Resumen!$C$3-2025)),1)) -> 80192.73 | I45: =G45-H45 -> 64.281721 | J45: =IF(ROUND(G45-H45,1)>=0,"✔ Sí","✖ No") -> ✔ Sí | K45: =IFERROR(INDEX(Links!$C$345:$C$469,MATCH(C45,Links!$B$218:$B$342,0)),1) -> 1000 | L45: =IF(K45>0,H45/K45,0) -> 80.19273 | M45: =IF(E45="kg",1,0) -> 0 | N45: =H45*M45 -> 0
A46: MANUALES | B46: Identificación y embalaje | C46: =Links!$B$100 -> MP-56/ABC1 | D46: =Links!$C$100 -> Etiqueta de características ABC 1 kg | E46: =Links!$D$100 -> u | F46: =IFERROR(INDEX(Links!$B$345:$B$469,MATCH(C46,Links!$B$218:$B$342,0)),"") -> Rollo de 1.000 u | G46: =INDEX(Links!$N$100:$W$100,1,(Resumen!$C$3-2025)) -> 32072.639 | H46: =SUMPRODUCT(Links!$F$100:$M$100,$O$5:$V$5)*IF(Links!$E$100="CABA",INDEX(Links!$C$13:$L$13,1,(Resumen!$C$3-2025)),IF(Links!$E$100="PBA",1-INDEX(Links!$C$13:$L$13,1,(Resumen!$C$3-2025)),1)) -> 32072.639 | I46: =G46-H46 -> 0 | J46: =IF(ROUND(G46-H46,1)>=0,"✔ Sí","✖ No") -> ✔ Sí | K46: =IFERROR(INDEX(Links!$C$345:$C$469,MATCH(C46,Links!$B$218:$B$342,0)),1) -> 1000 | L46: =IF(K46>0,H46/K46,0) -> 32.072639 | M46: =IF(E46="kg",1,0) -> 0 | N46: =H46*M46 -> 0
A47: MANUALES | B47: Identificación y embalaje | C47: =Links!$B$101 -> MP-56/ABC2.5 | D47: =Links!$C$101 -> Etiqueta de características ABC 2,5 kg | E47: =Links!$D$101 -> u | F47: =IFERROR(INDEX(Links!$B$345:$B$469,MATCH(C47,Links!$B$218:$B$342,0)),"") -> Rollo de 1.000 u | G47: =INDEX(Links!$N$101:$W$101,1,(Resumen!$C$3-2025)) -> 7424.8584 | H47: =SUMPRODUCT(Links!$F$101:$M$101,$O$5:$V$5)*IF(Links!$E$101="CABA",INDEX(Links!$C$13:$L$13,1,(Resumen!$C$3-2025)),IF(Links!$E$101="PBA",1-INDEX(Links!$C$13:$L$13,1,(Resumen!$C$3-2025)),1)) -> 7436.4584 | I47: =G47-H47 -> -11.6 | J47: =IF(ROUND(G47-H47,1)>=0,"✔ Sí","✖ No") -> ✖ No | K47: =IFERROR(INDEX(Links!$C$345:$C$469,MATCH(C47,Links!$B$218:$B$342,0)),1) -> 1000 | L47: =IF(K47>0,H47/K47,0) -> 7.4364584 | M47: =IF(E47="kg",1,0) -> 0 | N47: =H47*M47 -> 0
A48: MANUALES | B48: Identificación y embalaje | C48: =Links!$B$102 -> MP-56/ABC5 | D48: =Links!$C$102 -> Etiqueta de características ABC 5 kg | E48: =Links!$D$102 -> u | F48: =IFERROR(INDEX(Links!$B$345:$B$469,MATCH(C48,Links!$B$218:$B$342,0)),"") -> Rollo de 1.000 u | G48: =INDEX(Links!$N$102:$W$102,1,(Resumen!$C$3-2025)) -> 30860.771 | H48: =SUMPRODUCT(Links!$F$102:$M$102,$O$5:$V$5)*IF(Links!$E$102="CABA",INDEX(Links!$C$13:$L$13,1,(Resumen!$C$3-2025)),IF(Links!$E$102="PBA",1-INDEX(Links!$C$13:$L$13,1,(Resumen!$C$3-2025)),1)) -> 30814.979 | I48: =G48-H48 -> 45.791966 | J48: =IF(ROUND(G48-H48,1)>=0,"✔ Sí","✖ No") -> ✔ Sí | K48: =IFERROR(INDEX(Links!$C$345:$C$469,MATCH(C48,Links!$B$218:$B$342,0)),1) -> 1000 | L48: =IF(K48>0,H48/K48,0) -> 30.814979 | M48: =IF(E48="kg",1,0) -> 0 | N48: =H48*M48 -> 0
A49: MANUALES | B49: Identificación y embalaje | C49: =Links!$B$103 -> MP-56/ABC10 | D49: =Links!$C$103 -> Etiqueta de características ABC 10 kg | E49: =Links!$D$103 -> u | F49: =IFERROR(INDEX(Links!$B$345:$B$469,MATCH(C49,Links!$B$218:$B$342,0)),"") -> Rollo de 1.000 u | G49: =INDEX(Links!$N$103:$W$103,1,(Resumen!$C$3-2025)) -> 1842.877 | H49: =SUMPRODUCT(Links!$F$103:$M$103,$O$5:$V$5)*IF(Links!$E$103="CABA",INDEX(Links!$C$13:$L$13,1,(Resumen!$C$3-2025)),IF(Links!$E$103="PBA",1-INDEX(Links!$C$13:$L$13,1,(Resumen!$C$3-2025)),1)) -> 1844.9281 | I49: =G49-H49 -> -2.0511058 | J49: =IF(ROUND(G49-H49,1)>=0,"✔ Sí","✖ No") -> ✖ No | K49: =IFERROR(INDEX(Links!$C$345:$C$469,MATCH(C49,Links!$B$218:$B$342,0)),1) -> 1000 | L49: =IF(K49>0,H49/K49,0) -> 1.8449281 | M49: =IF(E49="kg",1,0) -> 0 | N49: =H49*M49 -> 0
A50: MANUALES | B50: Identificación y embalaje | C50: =Links!$B$104 -> MP-78 | D50: =Links!$C$104 -> Oblea de fabricación (PBA) | E50: =Links!$D$104 -> u | F50: =IFERROR(INDEX(Links!$B$345:$B$469,MATCH(C50,Links!$B$218:$B$342,0)),"") -> Paquete de 500 u | G50: =INDEX(Links!$N$104:$W$104,1,(Resumen!$C$3-2025)) -> 55146.14 | H50: =SUMPRODUCT(Links!$F$104:$M$104,$O$5:$V$5)*IF(Links!$E$104="CABA",INDEX(Links!$C$13:$L$13,1,(Resumen!$C$3-2025)),IF(Links!$E$104="PBA",1-INDEX(Links!$C$13:$L$13,1,(Resumen!$C$3-2025)),1)) -> 55121.591 | I50: =G50-H50 -> 24.548702 | J50: =IF(ROUND(G50-H50,1)>=0,"✔ Sí","✖ No") -> ✔ Sí | K50: =IFERROR(INDEX(Links!$C$345:$C$469,MATCH(C50,Links!$B$218:$B$342,0)),1) -> 500 | L50: =IF(K50>0,H50/K50,0) -> 110.24318 | M50: =IF(E50="kg",1,0) -> 0 | N50: =H50*M50 -> 0
A51: MANUALES | B51: Identificación y embalaje | C51: =Links!$B$105 -> MP-79 | D51: =Links!$C$105 -> Estampilla IRAM de conformidad | E51: =Links!$D$105 -> u | F51: =IFERROR(INDEX(Links!$B$345:$B$469,MATCH(C51,Links!$B$218:$B$342,0)),"") -> Paquete de 500 u | G51: =INDEX(Links!$N$105:$W$105,1,(Resumen!$C$3-2025)) -> 72201.145 | H51: =SUMPRODUCT(Links!$F$105:$M$105,$O$5:$V$5)*IF(Links!$E$105="CABA",INDEX(Links!$C$13:$L$13,1,(Resumen!$C$3-2025)),IF(Links!$E$105="PBA",1-INDEX(Links!$C$13:$L$13,1,(Resumen!$C$3-2025)),1)) -> 72169.004 | I51: =G51-H51 -> 32.14086 | J51: =IF(ROUND(G51-H51,1)>=0,"✔ Sí","✖ No") -> ✔ Sí | K51: =IFERROR(INDEX(Links!$C$345:$C$469,MATCH(C51,Links!$B$218:$B$342,0)),1) -> 500 | L51: =IF(K51>0,H51/K51,0) -> 144.33801 | M51: =IF(E51="kg",1,0) -> 0 | N51: =H51*M51 -> 0
A52: MANUALES | B52: Identificación y embalaje | C52: =Links!$B$106 -> MP-77 | D52: =Links!$C$106 -> Tarjeta de identificación AGC (CABA) | E52: =Links!$D$106 -> u | F52: =IFERROR(INDEX(Links!$B$345:$B$469,MATCH(C52,Links!$B$218:$B$342,0)),"") -> Paquete de 500 u | G52: =INDEX(Links!$N$106:$W$106,1,(Resumen!$C$3-2025)) -> 9478.9618 | H52: =SUMPRODUCT(Links!$F$106:$M$106,$O$5:$V$5)*IF(Links!$E$106="CABA",INDEX(Links!$C$13:$L$13,1,(Resumen!$C$3-2025)),IF(Links!$E$106="PBA",1-INDEX(Links!$C$13:$L$13,1,(Resumen!$C$3-2025)),1)) -> 9471.3696 | I52: =G52-H52 -> 7.5921587 | J52: =IF(ROUND(G52-H52,1)>=0,"✔ Sí","✖ No") -> ✔ Sí | K52: =IFERROR(INDEX(Links!$C$345:$C$469,MATCH(C52,Links!$B$218:$B$342,0)),1) -> 500 | L52: =IF(K52>0,H52/K52,0) -> 18.942739 | M52: =IF(E52="kg",1,0) -> 0 | N52: =H52*M52 -> 0
A53: MANUALES | B53: Identificación y embalaje | C53: =Links!$B$107 -> MP-80 | D53: =Links!$C$107 -> Etiqueta de n° de serie GS1 | E53: =Links!$D$107 -> u | F53: =IFERROR(INDEX(Links!$B$345:$B$469,MATCH(C53,Links!$B$218:$B$342,0)),"") -> Rollo de 1.000 u | G53: =INDEX(Links!$N$107:$W$107,1,(Resumen!$C$3-2025)) -> 72201.145 | H53: =SUMPRODUCT(Links!$F$107:$M$107,$O$5:$V$5)*IF(Links!$E$107="CABA",INDEX(Links!$C$13:$L$13,1,(Resumen!$C$3-2025)),IF(Links!$E$107="PBA",1-INDEX(Links!$C$13:$L$13,1,(Resumen!$C$3-2025)),1)) -> 72169.004 | I53: =G53-H53 -> 32.14086 | J53: =IF(ROUND(G53-H53,1)>=0,"✔ Sí","✖ No") -> ✔ Sí | K53: =IFERROR(INDEX(Links!$C$345:$C$469,MATCH(C53,Links!$B$218:$B$342,0)),1) -> 1000 | L53: =IF(K53>0,H53/K53,0) -> 72.169004 | M53: =IF(E53="kg",1,0) -> 0 | N53: =H53*M53 -> 0
A54: MANUALES | B54: Identificación y embalaje | C54: =Links!$B$108 -> MP-81 | D54: =Links!$C$108 -> Faja de garantía válvula-cuello | E54: =Links!$D$108 -> u | F54: =IFERROR(INDEX(Links!$B$345:$B$469,MATCH(C54,Links!$B$218:$B$342,0)),"") -> Rollo de 1.000 u | G54: =INDEX(Links!$N$108:$W$108,1,(Resumen!$C$3-2025)) -> 72201.145 | H54: =SUMPRODUCT(Links!$F$108:$M$108,$O$5:$V$5)*IF(Links!$E$108="CABA",INDEX(Links!$C$13:$L$13,1,(Resumen!$C$3-2025)),IF(Links!$E$108="PBA",1-INDEX(Links!$C$13:$L$13,1,(Resumen!$C$3-2025)),1)) -> 72169.004 | I54: =G54-H54 -> 32.14086 | J54: =IF(ROUND(G54-H54,1)>=0,"✔ Sí","✖ No") -> ✔ Sí | K54: =IFERROR(INDEX(Links!$C$345:$C$469,MATCH(C54,Links!$B$218:$B$342,0)),1) -> 1000 | L54: =IF(K54>0,H54/K54,0) -> 72.169004 | M54: =IF(E54="kg",1,0) -> 0 | N54: =H54*M54 -> 0
A55: MANUALES | B55: Identificación y embalaje | C55: =Links!$B$109 -> MP-51 | D55: =Links!$C$109 -> Precinto de fábrica | E55: =Links!$D$109 -> u | F55: =IFERROR(INDEX(Links!$B$345:$B$469,MATCH(C55,Links!$B$218:$B$342,0)),"") -> Bolsa de 1.000 u | G55: =INDEX(Links!$N$109:$W$109,1,(Resumen!$C$3-2025)) -> 72201.145 | H55: =SUMPRODUCT(Links!$F$109:$M$109,$O$5:$V$5)*IF(Links!$E$109="CABA",INDEX(Links!$C$13:$L$13,1,(Resumen!$C$3-2025)),IF(Links!$E$109="PBA",1-INDEX(Links!$C$13:$L$13,1,(Resumen!$C$3-2025)),1)) -> 72169.004 | I55: =G55-H55 -> 32.14086 | J55: =IF(ROUND(G55-H55,1)>=0,"✔ Sí","✖ No") -> ✔ Sí | K55: =IFERROR(INDEX(Links!$C$345:$C$469,MATCH(C55,Links!$B$218:$B$342,0)),1) -> 1000 | L55: =IF(K55>0,H55/K55,0) -> 72.169004 | M55: =IF(E55="kg",1,0) -> 0 | N55: =H55*M55 -> 0
A56: MANUALES | B56: Identificación y embalaje | C56: =Links!$B$110 -> MP-88 | D56: =Links!$C$110 -> Etiqueta del cilindro suelto | E56: =Links!$D$110 -> u | F56: =IFERROR(INDEX(Links!$B$345:$B$469,MATCH(C56,Links!$B$218:$B$342,0)),"") -> Rollo de 1.000 u | G56: =INDEX(Links!$N$110:$W$110,1,(Resumen!$C$3-2025)) -> 212143 | H56: =SUMPRODUCT(Links!$F$110:$M$110,$O$5:$V$5)*IF(Links!$E$110="CABA",INDEX(Links!$C$13:$L$13,1,(Resumen!$C$3-2025)),IF(Links!$E$110="PBA",1-INDEX(Links!$C$13:$L$13,1,(Resumen!$C$3-2025)),1)) -> 212293.56 | I56: =G56-H56 -> -150.56 | J56: =IF(ROUND(G56-H56,1)>=0,"✔ Sí","✖ No") -> ✖ No | K56: =IFERROR(INDEX(Links!$C$345:$C$469,MATCH(C56,Links!$B$218:$B$342,0)),1) -> 1000 | L56: =IF(K56>0,H56/K56,0) -> 212.29356 | M56: =IF(E56="kg",1,0) -> 0 | N56: =H56*M56 -> 0
A57: MANUALES | B57: Componentes comprados | C57: =Links!$B$111 -> MP-62/M22 | D57: =Links!$C$111 -> Tapón protector de rosca M22 | E57: =Links!$D$111 -> u | F57: =IFERROR(INDEX(Links!$B$345:$B$469,MATCH(C57,Links!$B$218:$B$342,0)),"") -> Caja de 5.000 u | G57: =INDEX(Links!$N$111:$W$111,1,(Resumen!$C$3-2025)) -> 170548 | H57: =SUMPRODUCT(Links!$F$111:$M$111,$O$5:$V$5)*IF(Links!$E$111="CABA",INDEX(Links!$C$13:$L$13,1,(Resumen!$C$3-2025)),IF(Links!$E$111="PBA",1-INDEX(Links!$C$13:$L$13,1,(Resumen!$C$3-2025)),1)) -> 170548 | I57: =G57-H57 -> 0 | J57: =IF(ROUND(G57-H57,1)>=0,"✔ Sí","✖ No") -> ✔ Sí | K57: =IFERROR(INDEX(Links!$C$345:$C$469,MATCH(C57,Links!$B$218:$B$342,0)),1) -> 5000 | L57: =IF(K57>0,H57/K57,0) -> 34.1096 | M57: =IF(E57="kg",1,0) -> 0 | N57: =H57*M57 -> 0
A58: MANUALES | B58: Componentes comprados | C58: =Links!$B$112 -> MP-62/M30 | D58: =Links!$C$112 -> Tapón protector de rosca M30 | E58: =Links!$D$112 -> u | F58: =IFERROR(INDEX(Links!$B$345:$B$469,MATCH(C58,Links!$B$218:$B$342,0)),"") -> Caja de 5.000 u | G58: =INDEX(Links!$N$112:$W$112,1,(Resumen!$C$3-2025)) -> 41595 | H58: =SUMPRODUCT(Links!$F$112:$M$112,$O$5:$V$5)*IF(Links!$E$112="CABA",INDEX(Links!$C$13:$L$13,1,(Resumen!$C$3-2025)),IF(Links!$E$112="PBA",1-INDEX(Links!$C$13:$L$13,1,(Resumen!$C$3-2025)),1)) -> 41745.56 | I58: =G58-H58 -> -150.56 | J58: =IF(ROUND(G58-H58,1)>=0,"✔ Sí","✖ No") -> ✖ No | K58: =IFERROR(INDEX(Links!$C$345:$C$469,MATCH(C58,Links!$B$218:$B$342,0)),1) -> 5000 | L58: =IF(K58>0,H58/K58,0) -> 8.349112 | M58: =IF(E58="kg",1,0) -> 0 | N58: =H58*M58 -> 0
A59: MANUALES | B59: Identificación y embalaje | C59: =Links!$B$113 -> MP-85 | D59: =Links!$C$113 -> Impresos (protocolo de ensayo, remito de préstamo) | E59: =Links!$D$113 -> u | F59: =IFERROR(INDEX(Links!$B$345:$B$469,MATCH(C59,Links!$B$218:$B$342,0)),"") -> Paquete de 500 u | G59: =INDEX(Links!$N$113:$W$113,1,(Resumen!$C$3-2025)) -> 212143 | H59: =SUMPRODUCT(Links!$F$113:$M$113,$O$5:$V$5)*IF(Links!$E$113="CABA",INDEX(Links!$C$13:$L$13,1,(Resumen!$C$3-2025)),IF(Links!$E$113="PBA",1-INDEX(Links!$C$13:$L$13,1,(Resumen!$C$3-2025)),1)) -> 212293.56 | I59: =G59-H59 -> -150.56 | J59: =IF(ROUND(G59-H59,1)>=0,"✔ Sí","✖ No") -> ✖ No | K59: =IFERROR(INDEX(Links!$C$345:$C$469,MATCH(C59,Links!$B$218:$B$342,0)),1) -> 500 | L59: =IF(K59>0,H59/K59,0) -> 424.58712 | M59: =IF(E59="kg",1,0) -> 0 | N59: =H59*M59 -> 0
A60: MANUALES | B60: Identificación y embalaje | C60: =Links!$B$114 -> MP-59/ABC1 | D60: =Links!$C$114 -> Caja de cartón simple ABC 1 kg | E60: =Links!$D$114 -> u | F60: =IFERROR(INDEX(Links!$B$345:$B$469,MATCH(C60,Links!$B$218:$B$342,0)),"") -> Pallet de 600 cajas | G60: =INDEX(Links!$N$114:$W$114,1,(Resumen!$C$3-2025)) -> 202620.64 | H60: =SUMPRODUCT(Links!$F$114:$M$114,$O$5:$V$5)*IF(Links!$E$114="CABA",INDEX(Links!$C$13:$L$13,1,(Resumen!$C$3-2025)),IF(Links!$E$114="PBA",1-INDEX(Links!$C$13:$L$13,1,(Resumen!$C$3-2025)),1)) -> 202620.64 | I60: =G60-H60 -> 0 | J60: =IF(ROUND(G60-H60,1)>=0,"✔ Sí","✖ No") -> ✔ Sí | K60: =IFERROR(INDEX(Links!$C$345:$C$469,MATCH(C60,Links!$B$218:$B$342,0)),1) -> 600 | L60: =IF(K60>0,H60/K60,0) -> 337.70107 | M60: =IF(E60="kg",1,0) -> 0 | N60: =H60*M60 -> 0
A61: MANUALES | B61: Identificación y embalaje | C61: =Links!$B$115 -> MP-59/ABC2.5 | D61: =Links!$C$115 -> Caja de cartón simple ABC 2,5 kg | E61: =Links!$D$115 -> u | F61: =IFERROR(INDEX(Links!$B$345:$B$469,MATCH(C61,Links!$B$218:$B$342,0)),"") -> Pallet de 600 cajas | G61: =INDEX(Links!$N$115:$W$115,1,(Resumen!$C$3-2025)) -> 14093.858 | H61: =SUMPRODUCT(Links!$F$115:$M$115,$O$5:$V$5)*IF(Links!$E$115="CABA",INDEX(Links!$C$13:$L$13,1,(Resumen!$C$3-2025)),IF(Links!$E$115="PBA",1-INDEX(Links!$C$13:$L$13,1,(Resumen!$C$3-2025)),1)) -> 14126.338 | I61: =G61-H61 -> -32.48 | J61: =IF(ROUND(G61-H61,1)>=0,"✔ Sí","✖ No") -> ✖ No | K61: =IFERROR(INDEX(Links!$C$345:$C$469,MATCH(C61,Links!$B$218:$B$342,0)),1) -> 600 | L61: =IF(K61>0,H61/K61,0) -> 23.543897 | M61: =IF(E61="kg",1,0) -> 0 | N61: =H61*M61 -> 0
A62: MANUALES | B62: Identificación y embalaje | C62: =Links!$B$116 -> MP-59/ABC5 | D62: =Links!$C$116 -> Caja de cartón simple ABC 5 kg | E62: =Links!$D$116 -> u | F62: =IFERROR(INDEX(Links!$B$345:$B$469,MATCH(C62,Links!$B$218:$B$342,0)),"") -> Pallet de 600 cajas | G62: =INDEX(Links!$N$116:$W$116,1,(Resumen!$C$3-2025)) -> 63775.771 | H62: =SUMPRODUCT(Links!$F$116:$M$116,$O$5:$V$5)*IF(Links!$E$116="CABA",INDEX(Links!$C$13:$L$13,1,(Resumen!$C$3-2025)),IF(Links!$E$116="PBA",1-INDEX(Links!$C$13:$L$13,1,(Resumen!$C$3-2025)),1)) -> 63852.659 | I62: =G62-H62 -> -76.888034 | J62: =IF(ROUND(G62-H62,1)>=0,"✔ Sí","✖ No") -> ✖ No | K62: =IFERROR(INDEX(Links!$C$345:$C$469,MATCH(C62,Links!$B$218:$B$342,0)),1) -> 600 | L62: =IF(K62>0,H62/K62,0) -> 106.4211 | M62: =IF(E62="kg",1,0) -> 0 | N62: =H62*M62 -> 0
A63: MANUALES | B63: Identificación y embalaje | C63: =Links!$B$117 -> MP-59/ABC10 | D63: =Links!$C$117 -> Caja de cartón doble ABC 10 kg | E63: =Links!$D$117 -> u | F63: =IFERROR(INDEX(Links!$B$345:$B$469,MATCH(C63,Links!$B$218:$B$342,0)),"") -> Pallet de 600 cajas | G63: =INDEX(Links!$N$117:$W$117,1,(Resumen!$C$3-2025)) -> 3853.877 | H63: =SUMPRODUCT(Links!$F$117:$M$117,$O$5:$V$5)*IF(Links!$E$117="CABA",INDEX(Links!$C$13:$L$13,1,(Resumen!$C$3-2025)),IF(Links!$E$117="PBA",1-INDEX(Links!$C$13:$L$13,1,(Resumen!$C$3-2025)),1)) -> 3862.9281 | I63: =G63-H63 -> -9.0511058 | J63: =IF(ROUND(G63-H63,1)>=0,"✔ Sí","✖ No") -> ✖ No | K63: =IFERROR(INDEX(Links!$C$345:$C$469,MATCH(C63,Links!$B$218:$B$342,0)),1) -> 600 | L63: =IF(K63>0,H63/K63,0) -> 6.4382135 | M63: =IF(E63="kg",1,0) -> 0 | N63: =H63*M63 -> 0
A64: MANUALES | B64: Identificación y embalaje | C64: =Links!$B$118 -> MP-89 | D64: =Links!$C$118 -> Etiqueta de caja | E64: =Links!$D$118 -> u | F64: =IFERROR(INDEX(Links!$B$345:$B$469,MATCH(C64,Links!$B$218:$B$342,0)),"") -> Rollo de 1.000 u | G64: =INDEX(Links!$N$118:$W$118,1,(Resumen!$C$3-2025)) -> 284344.15 | H64: =SUMPRODUCT(Links!$F$118:$M$118,$O$5:$V$5)*IF(Links!$E$118="CABA",INDEX(Links!$C$13:$L$13,1,(Resumen!$C$3-2025)),IF(Links!$E$118="PBA",1-INDEX(Links!$C$13:$L$13,1,(Resumen!$C$3-2025)),1)) -> 284462.56 | I64: =G64-H64 -> -118.41914 | J64: =IF(ROUND(G64-H64,1)>=0,"✔ Sí","✖ No") -> ✖ No | K64: =IFERROR(INDEX(Links!$C$345:$C$469,MATCH(C64,Links!$B$218:$B$342,0)),1) -> 1000 | L64: =IF(K64>0,H64/K64,0) -> 284.46256 | M64: =IF(E64="kg",1,0) -> 0 | N64: =H64*M64 -> 0
A65: MANUALES | B65: Identificación y embalaje | C65: =Links!$B$119 -> MP-60 | D65: =Links!$C$119 -> Pallet de madera 1200 × 1000 | E65: =Links!$D$119 -> u | F65: =IFERROR(INDEX(Links!$B$345:$B$469,MATCH(C65,Links!$B$218:$B$342,0)),"") -> Pila de 15 u | G65: =INDEX(Links!$N$119:$W$119,1,(Resumen!$C$3-2025)) -> 1395.9126 | H65: =SUMPRODUCT(Links!$F$119:$M$119,$O$5:$V$5)*IF(Links!$E$119="CABA",INDEX(Links!$C$13:$L$13,1,(Resumen!$C$3-2025)),IF(Links!$E$119="PBA",1-INDEX(Links!$C$13:$L$13,1,(Resumen!$C$3-2025)),1)) -> 1397.1876 | I65: =G65-H65 -> -1.2750801 | J65: =IF(ROUND(G65-H65,1)>=0,"✔ Sí","✖ No") -> ✖ No | K65: =IFERROR(INDEX(Links!$C$345:$C$469,MATCH(C65,Links!$B$218:$B$342,0)),1) -> 15 | L65: =IF(K65>0,H65/K65,0) -> 93.145843 | M65: =IF(E65="kg",1,0) -> 0 | N65: =H65*M65 -> 0
A66: MANUALES | B66: Identificación y embalaje | C66: =Links!$B$120 -> MP-90 | D66: =Links!$C$120 -> Etiqueta de pallet | E66: =Links!$D$120 -> u | F66: =IFERROR(INDEX(Links!$B$345:$B$469,MATCH(C66,Links!$B$218:$B$342,0)),"") -> Rollo de 1.000 u | G66: =INDEX(Links!$N$120:$W$120,1,(Resumen!$C$3-2025)) -> 1395.9126 | H66: =SUMPRODUCT(Links!$F$120:$M$120,$O$5:$V$5)*IF(Links!$E$120="CABA",INDEX(Links!$C$13:$L$13,1,(Resumen!$C$3-2025)),IF(Links!$E$120="PBA",1-INDEX(Links!$C$13:$L$13,1,(Resumen!$C$3-2025)),1)) -> 1397.1876 | I66: =G66-H66 -> -1.2750801 | J66: =IF(ROUND(G66-H66,1)>=0,"✔ Sí","✖ No") -> ✖ No | K66: =IFERROR(INDEX(Links!$C$345:$C$469,MATCH(C66,Links!$B$218:$B$342,0)),1) -> 1000 | L66: =IF(K66>0,H66/K66,0) -> 1.3971876 | M66: =IF(E66="kg",1,0) -> 0 | N66: =H66*M66 -> 0
A68: RODANTES
A69: Producción | B69: (mismo orden que el MRP) → | O69: =Resumen!$D$15 -> 453.67053 | P69: =Resumen!$D$16 -> 997.99517 | Q69: =Resumen!$D$17 -> 217.80986 | R69: =Resumen!$D$18 -> 145.20657 | S69: =Resumen!$D$19 -> 323.64 | T69: =Resumen!$D$20 -> 710.44 | U69: =Resumen!$D$21 -> 156.32 | V69: =Resumen!$D$22 -> 102.24
A70: Línea | B70: Familia | C70: Código | D70: Material | E70: UM | F70: Formato de compra | G70: Compra MRP | H70: Necesario para la producción | I70: Compra − necesario | J70: ¿Cubre? | K70: Contenido de la unidad de compra | L70: Unidades de compra necesarias | M70: kg por UM | N70: kg necesarios
A71: RODANTES | B71: Chapa en hojas | C71: =Links!$B$123 -> MP-11 | D71: =Links!$C$123 -> Hoja LAC 3,2 × 1500 × 3000 mm | E71: =Links!$D$123 -> hoja | F71: =IFERROR(INDEX(Links!$B$345:$B$469,MATCH(C71,Links!$B$218:$B$342,0)),"") -> Paquete de 20 hojas | G71: =INDEX(Links!$N$123:$W$123,1,(Resumen!$C$3-2025)) -> 348.98254 | H71: =SUMPRODUCT(Links!$F$123:$M$123,$O$69:$V$69)*IF(Links!$E$123="CABA",INDEX(Links!$C$13:$L$13,1,(Resumen!$C$3-2025)),IF(Links!$E$123="PBA",1-INDEX(Links!$C$13:$L$13,1,(Resumen!$C$3-2025)),1)) -> 349.51507 | I71: =G71-H71 -> -0.53253171 | J71: =IF(ROUND(G71-H71,1)>=0,"✔ Sí","✖ No") -> ✖ No | K71: =IFERROR(INDEX(Links!$C$345:$C$469,MATCH(C71,Links!$B$218:$B$342,0)),1) -> 20 | L71: =IF(K71>0,H71/K71,0) -> 17.475754 | M71: =Links!$B$2195*Links!$C$2195*Links!$C$2206*7.85/1000000 -> 113.04 | N71: =H71*M71 -> 39509.184
A72: RODANTES | B72: Chapa en hojas | C72: =Links!$B$124 -> MP-12 | D72: =Links!$C$124 -> Hoja LAC 4,75 × 1500 × 3000 mm | E72: =Links!$D$124 -> hoja | F72: =IFERROR(INDEX(Links!$B$345:$B$469,MATCH(C72,Links!$B$218:$B$342,0)),"") -> Paquete de 15 hojas | G72: =INDEX(Links!$N$124:$W$124,1,(Resumen!$C$3-2025)) -> 165.18533 | H72: =SUMPRODUCT(Links!$F$124:$M$124,$O$69:$V$69)*IF(Links!$E$124="CABA",INDEX(Links!$C$13:$L$13,1,(Resumen!$C$3-2025)),IF(Links!$E$124="PBA",1-INDEX(Links!$C$13:$L$13,1,(Resumen!$C$3-2025)),1)) -> 165.62216 | I72: =G72-H72 -> -0.43683204 | J72: =IF(ROUND(G72-H72,1)>=0,"✔ Sí","✖ No") -> ✖ No | K72: =IFERROR(INDEX(Links!$C$345:$C$469,MATCH(C72,Links!$B$218:$B$342,0)),1) -> 15 | L72: =IF(K72>0,H72/K72,0) -> 11.041477 | M72: =Links!$B$2197*Links!$C$2197*Links!$C$2208*7.85/1000000 -> 167.79375 | N72: =H72*M72 -> 27790.363
A73: RODANTES | B73: Casquetes y cuplas | C73: =Links!$B$125 -> MP-15 | D73: =Links!$C$125 -> Casquete 10" × 3,2 mm (carro 25 kg) | E73: =Links!$D$125 -> u | F73: =IFERROR(INDEX(Links!$B$345:$B$469,MATCH(C73,Links!$B$218:$B$342,0)),"") -> Pallet de 400 u | G73: =INDEX(Links!$N$125:$W$125,1,(Resumen!$C$3-2025)) -> 1550.5411 | H73: =SUMPRODUCT(Links!$F$125:$M$125,$O$69:$V$69)*IF(Links!$E$125="CABA",INDEX(Links!$C$13:$L$13,1,(Resumen!$C$3-2025)),IF(Links!$E$125="PBA",1-INDEX(Links!$C$13:$L$13,1,(Resumen!$C$3-2025)),1)) -> 1554.6211 | I73: =G73-H73 -> -4.08 | J73: =IF(ROUND(G73-H73,1)>=0,"✔ Sí","✖ No") -> ✖ No | K73: =IFERROR(INDEX(Links!$C$345:$C$469,MATCH(C73,Links!$B$218:$B$342,0)),1) -> 400 | L73: =IF(K73>0,H73/K73,0) -> 3.8865527 | M73: =IF(E73="kg",1,0) -> 0 | N73: =H73*M73 -> 0
A74: RODANTES | B74: Casquetes y cuplas | C74: =Links!$B$126 -> MP-16 | D74: =Links!$C$126 -> Casquete 12" × 3,2 mm (carro 50 kg) | E74: =Links!$D$126 -> u | F74: =IFERROR(INDEX(Links!$B$345:$B$469,MATCH(C74,Links!$B$218:$B$342,0)),"") -> Pallet de 300 u | G74: =INDEX(Links!$N$126:$W$126,1,(Resumen!$C$3-2025)) -> 3412.52 | H74: =SUMPRODUCT(Links!$F$126:$M$126,$O$69:$V$69)*IF(Links!$E$126="CABA",INDEX(Links!$C$13:$L$13,1,(Resumen!$C$3-2025)),IF(Links!$E$126="PBA",1-INDEX(Links!$C$13:$L$13,1,(Resumen!$C$3-2025)),1)) -> 3416.8703 | I74: =G74-H74 -> -4.3503806 | J74: =IF(ROUND(G74-H74,1)>=0,"✔ Sí","✖ No") -> ✖ No | K74: =IFERROR(INDEX(Links!$C$345:$C$469,MATCH(C74,Links!$B$218:$B$342,0)),1) -> 300 | L74: =IF(K74>0,H74/K74,0) -> 11.389568 | M74: =IF(E74="kg",1,0) -> 0 | N74: =H74*M74 -> 0
A75: RODANTES | B75: Casquetes y cuplas | C75: =Links!$B$127 -> MP-17 | D75: =Links!$C$127 -> Casquete 15" × 4,75 mm (carros 70 y 100 kg) | E75: =Links!$D$127 -> u | F75: =IFERROR(INDEX(Links!$B$345:$B$469,MATCH(C75,Links!$B$218:$B$342,0)),"") -> Pallet de 150 u | G75: =INDEX(Links!$N$127:$W$127,1,(Resumen!$C$3-2025)) -> 1239.4919 | H75: =SUMPRODUCT(Links!$F$127:$M$127,$O$69:$V$69)*IF(Links!$E$127="CABA",INDEX(Links!$C$13:$L$13,1,(Resumen!$C$3-2025)),IF(Links!$E$127="PBA",1-INDEX(Links!$C$13:$L$13,1,(Resumen!$C$3-2025)),1)) -> 1243.1529 | I75: =G75-H75 -> -3.6609922 | J75: =IF(ROUND(G75-H75,1)>=0,"✔ Sí","✖ No") -> ✖ No | K75: =IFERROR(INDEX(Links!$C$345:$C$469,MATCH(C75,Links!$B$218:$B$342,0)),1) -> 150 | L75: =IF(K75>0,H75/K75,0) -> 8.2876857 | M75: =IF(E75="kg",1,0) -> 0 | N75: =H75*M75 -> 0
A76: RODANTES | B76: Casquetes y cuplas | C76: =Links!$B$128 -> MP-20 | D76: =Links!$C$128 -> Cupla M30 × 1,5 (carros 25 y 50 kg) | E76: =Links!$D$128 -> u | F76: =IFERROR(INDEX(Links!$B$345:$B$469,MATCH(C76,Links!$B$218:$B$342,0)),"") -> Caja de 100 u | G76: =INDEX(Links!$N$128:$W$128,1,(Resumen!$C$3-2025)) -> 2481.5305 | H76: =SUMPRODUCT(Links!$F$128:$M$128,$O$69:$V$69)*IF(Links!$E$128="CABA",INDEX(Links!$C$13:$L$13,1,(Resumen!$C$3-2025)),IF(Links!$E$128="PBA",1-INDEX(Links!$C$13:$L$13,1,(Resumen!$C$3-2025)),1)) -> 2485.7457 | I76: =G76-H76 -> -4.2151903 | J76: =IF(ROUND(G76-H76,1)>=0,"✔ Sí","✖ No") -> ✖ No | K76: =IFERROR(INDEX(Links!$C$345:$C$469,MATCH(C76,Links!$B$218:$B$342,0)),1) -> 100 | L76: =IF(K76>0,H76/K76,0) -> 24.857457 | M76: =IF(E76="kg",1,0) -> 0 | N76: =H76*M76 -> 0
A77: RODANTES | B77: Casquetes y cuplas | C77: =Links!$B$129 -> MP-21 | D77: =Links!$C$129 -> Cupla 2½" BSP (carros 70 y 100 kg) | E77: =Links!$D$129 -> u | F77: =IFERROR(INDEX(Links!$B$345:$B$469,MATCH(C77,Links!$B$218:$B$342,0)),"") -> Caja de 40 u | G77: =INDEX(Links!$N$129:$W$129,1,(Resumen!$C$3-2025)) -> 619.74593 | H77: =SUMPRODUCT(Links!$F$129:$M$129,$O$69:$V$69)*IF(Links!$E$129="CABA",INDEX(Links!$C$13:$L$13,1,(Resumen!$C$3-2025)),IF(Links!$E$129="PBA",1-INDEX(Links!$C$13:$L$13,1,(Resumen!$C$3-2025)),1)) -> 621.57643 | I77: =G77-H77 -> -1.8304961 | J77: =IF(ROUND(G77-H77,1)>=0,"✔ Sí","✖ No") -> ✖ No | K77: =IFERROR(INDEX(Links!$C$345:$C$469,MATCH(C77,Links!$B$218:$B$342,0)),1) -> 40 | L77: =IF(K77>0,H77/K77,0) -> 15.539411 | M77: =IF(E77="kg",1,0) -> 0 | N77: =H77*M77 -> 0
A78: RODANTES | B78: Caños y barras | C78: =Links!$B$130 -> MP-66 | D78: =Links!$C$130 -> Caño SAE 1010 1" × 2,0 × 6 m (manija; caño del eje 25 kg) | E78: =Links!$D$130 -> barra | F78: =IFERROR(INDEX(Links!$B$345:$B$469,MATCH(C78,Links!$B$218:$B$342,0)),"") -> Barra de 6 m | G78: =INDEX(Links!$N$130:$W$130,1,(Resumen!$C$3-2025)) -> 510.05062 | H78: =SUMPRODUCT(Links!$F$130:$M$130,$O$69:$V$69)*IF(Links!$E$130="CABA",INDEX(Links!$C$13:$L$13,1,(Resumen!$C$3-2025)),IF(Links!$E$130="PBA",1-INDEX(Links!$C$13:$L$13,1,(Resumen!$C$3-2025)),1)) -> 510.18135 | I78: =G78-H78 -> -0.13073299 | J78: =IF(ROUND(G78-H78,1)>=0,"✔ Sí","✖ No") -> ✖ No | K78: =IFERROR(INDEX(Links!$C$345:$C$469,MATCH(C78,Links!$B$218:$B$342,0)),1) -> 1 | L78: =IF(K78>0,H78/K78,0) -> 510.18135 | M78: =IF(E78="kg",1,0) -> 0 | N78: =H78*M78 -> 0
A79: RODANTES | B79: Caños y barras | C79: =Links!$B$131 -> MP-67 | D79: =Links!$C$131 -> Caño SAE 1010 1¼" × 2,0 × 6 m (caño del eje 50 a 100 kg) | E79: =Links!$D$131 -> barra | F79: =IFERROR(INDEX(Links!$B$345:$B$469,MATCH(C79,Links!$B$218:$B$342,0)),"") -> Barra de 6 m | G79: =INDEX(Links!$N$131:$W$131,1,(Resumen!$C$3-2025)) -> 89.616801 | H79: =SUMPRODUCT(Links!$F$131:$M$131,$O$69:$V$69)*IF(Links!$E$131="CABA",INDEX(Links!$C$13:$L$13,1,(Resumen!$C$3-2025)),IF(Links!$E$131="PBA",1-INDEX(Links!$C$13:$L$13,1,(Resumen!$C$3-2025)),1)) -> 89.620951 | I79: =G79-H79 -> -0.0041495917 | J79: =IF(ROUND(G79-H79,1)>=0,"✔ Sí","✖ No") -> ✔ Sí | K79: =IFERROR(INDEX(Links!$C$345:$C$469,MATCH(C79,Links!$B$218:$B$342,0)),1) -> 1 | L79: =IF(K79>0,H79/K79,0) -> 89.620951 | M79: =IF(E79="kg",1,0) -> 0 | N79: =H79*M79 -> 0
A80: RODANTES | B80: Caños y barras | C80: =Links!$B$132 -> MP-68 | D80: =Links!$C$132 -> Barra trefilada SAE 1045 3/4" × 4 m (eje 25 kg) | E80: =Links!$D$132 -> barra | F80: =IFERROR(INDEX(Links!$B$345:$B$469,MATCH(C80,Links!$B$218:$B$342,0)),"") -> Barra de 4 m | G80: =INDEX(Links!$N$132:$W$132,1,(Resumen!$C$3-2025)) -> 56.658817 | H80: =SUMPRODUCT(Links!$F$132:$M$132,$O$69:$V$69)*IF(Links!$E$132="CABA",INDEX(Links!$C$13:$L$13,1,(Resumen!$C$3-2025)),IF(Links!$E$132="PBA",1-INDEX(Links!$C$13:$L$13,1,(Resumen!$C$3-2025)),1)) -> 56.708817 | I80: =G80-H80 -> -0.05 | J80: =IF(ROUND(G80-H80,1)>=0,"✔ Sí","✖ No") -> ✖ No | K80: =IFERROR(INDEX(Links!$C$345:$C$469,MATCH(C80,Links!$B$218:$B$342,0)),1) -> 1 | L80: =IF(K80>0,H80/K80,0) -> 56.708817 | M80: =IF(E80="kg",1,0) -> 0 | N80: =H80*M80 -> 0
A81: RODANTES | B81: Caños y barras | C81: =Links!$B$133 -> MP-69 | D81: =Links!$C$133 -> Barra trefilada SAE 1045 1" × 6 m (eje 50 a 100 kg) | E81: =Links!$D$133 -> barra | F81: =IFERROR(INDEX(Links!$B$345:$B$469,MATCH(C81,Links!$B$218:$B$342,0)),"") -> Barra de 6 m | G81: =INDEX(Links!$N$133:$W$133,1,(Resumen!$C$3-2025)) -> 127.0255 | H81: =SUMPRODUCT(Links!$F$133:$M$133,$O$69:$V$69)*IF(Links!$E$133="CABA",INDEX(Links!$C$13:$L$13,1,(Resumen!$C$3-2025)),IF(Links!$E$133="PBA",1-INDEX(Links!$C$13:$L$13,1,(Resumen!$C$3-2025)),1)) -> 127.02848 | I81: =G81-H81 -> -0.0029760006 | J81: =IF(ROUND(G81-H81,1)>=0,"✔ Sí","✖ No") -> ✔ Sí | K81: =IFERROR(INDEX(Links!$C$345:$C$469,MATCH(C81,Links!$B$218:$B$342,0)),1) -> 1 | L81: =IF(K81>0,H81/K81,0) -> 127.02848 | M81: =IF(E81="kg",1,0) -> 0 | N81: =H81*M81 -> 0
A82: RODANTES | B82: Soldadura: alambre | C82: =Links!$B$134 -> MP-24 | D82: =Links!$C$134 -> Alambre MAG ER70S-6 Ø1,0 mm (carros) | E82: =Links!$D$134 -> kg | F82: =IFERROR(INDEX(Links!$B$345:$B$469,MATCH(C82,Links!$B$218:$B$342,0)),"") -> Pallet de 900 kg | G82: =INDEX(Links!$N$134:$W$134,1,(Resumen!$C$3-2025)) -> 1388.1953 | H82: =SUMPRODUCT(Links!$F$134:$M$134,$O$69:$V$69)*IF(Links!$E$134="CABA",INDEX(Links!$C$13:$L$13,1,(Resumen!$C$3-2025)),IF(Links!$E$134="PBA",1-INDEX(Links!$C$13:$L$13,1,(Resumen!$C$3-2025)),1)) -> 1390.5974 | I82: =G82-H82 -> -2.4020952 | J82: =IF(ROUND(G82-H82,1)>=0,"✔ Sí","✖ No") -> ✖ No | K82: =IFERROR(INDEX(Links!$C$345:$C$469,MATCH(C82,Links!$B$218:$B$342,0)),1) -> 900 | L82: =IF(K82>0,H82/K82,0) -> 1.5451082 | M82: =IF(E82="kg",1,0) -> 1 | N82: =H82*M82 -> 1390.5974
A83: RODANTES | B83: Soldadura: gases | C83: =Links!$B$135 -> MP-25 | D83: =Links!$C$135 -> Gas MAG Ar + 8 % CO₂ (Arcal 21) | E83: =Links!$D$135 -> m³ | F83: =IFERROR(INDEX(Links!$B$345:$B$469,MATCH(C83,Links!$B$218:$B$342,0)),"") -> Batería de 11 cilindros | G83: =INDEX(Links!$N$135:$W$135,1,(Resumen!$C$3-2025)) -> 560.46851 | H83: =SUMPRODUCT(Links!$F$135:$M$135,$O$69:$V$69)*IF(Links!$E$135="CABA",INDEX(Links!$C$13:$L$13,1,(Resumen!$C$3-2025)),IF(Links!$E$135="PBA",1-INDEX(Links!$C$13:$L$13,1,(Resumen!$C$3-2025)),1)) -> 561.28411 | I83: =G83-H83 -> -0.81559122 | J83: =IF(ROUND(G83-H83,1)>=0,"✔ Sí","✖ No") -> ✖ No | K83: =IFERROR(INDEX(Links!$C$345:$C$469,MATCH(C83,Links!$B$218:$B$342,0)),1) -> 115.5 | L83: =IF(K83>0,H83/K83,0) -> 4.8596026 | M83: =IF(E83="kg",1,0) -> 0 | N83: =H83*M83 -> 0
A84: RODANTES | B84: Abrasivos y corte | C84: =Links!$B$136 -> MP-92 | D84: =Links!$C$136 -> Disco de sensitiva 355 mm | E84: =Links!$D$136 -> u | F84: =IFERROR(INDEX(Links!$B$345:$B$469,MATCH(C84,Links!$B$218:$B$342,0)),"") -> Caja de 25 u | G84: =INDEX(Links!$N$136:$W$136,1,(Resumen!$C$3-2025)) -> 27.214147 | H84: =SUMPRODUCT(Links!$F$136:$M$136,$O$69:$V$69)*IF(Links!$E$136="CABA",INDEX(Links!$C$13:$L$13,1,(Resumen!$C$3-2025)),IF(Links!$E$136="PBA",1-INDEX(Links!$C$13:$L$13,1,(Resumen!$C$3-2025)),1)) -> 27.220232 | I84: =G84-H84 -> -0.0060852959 | J84: =IF(ROUND(G84-H84,1)>=0,"✔ Sí","✖ No") -> ✔ Sí | K84: =IFERROR(INDEX(Links!$C$345:$C$469,MATCH(C84,Links!$B$218:$B$342,0)),1) -> 25 | L84: =IF(K84>0,H84/K84,0) -> 1.0888093 | M84: =IF(E84="kg",1,0) -> 0 | N84: =H84*M84 -> 0
A85: RODANTES | B85: Abrasivos y corte | C85: =Links!$B$137 -> MP-27 | D85: =Links!$C$137 -> Disco de corte 115 × 1,0 mm | E85: =Links!$D$137 -> u | F85: =IFERROR(INDEX(Links!$B$345:$B$469,MATCH(C85,Links!$B$218:$B$342,0)),"") -> Caja de 25 u | G85: =INDEX(Links!$N$137:$W$137,1,(Resumen!$C$3-2025)) -> 99.58468 | H85: =SUMPRODUCT(Links!$F$137:$M$137,$O$69:$V$69)*IF(Links!$E$137="CABA",INDEX(Links!$C$13:$L$13,1,(Resumen!$C$3-2025)),IF(Links!$E$137="PBA",1-INDEX(Links!$C$13:$L$13,1,(Resumen!$C$3-2025)),1)) -> 99.754991 | I85: =G85-H85 -> -0.17031057 | J85: =IF(ROUND(G85-H85,1)>=0,"✔ Sí","✖ No") -> ✖ No | K85: =IFERROR(INDEX(Links!$C$345:$C$469,MATCH(C85,Links!$B$218:$B$342,0)),1) -> 25 | L85: =IF(K85>0,H85/K85,0) -> 3.9901996 | M85: =IF(E85="kg",1,0) -> 0 | N85: =H85*M85 -> 0
A86: RODANTES | B86: Abrasivos y corte | C86: =Links!$B$138 -> MP-93 | D86: =Links!$C$138 -> Disco flap 115 mm grano 60 | E86: =Links!$D$138 -> u | F86: =IFERROR(INDEX(Links!$B$345:$B$469,MATCH(C86,Links!$B$218:$B$342,0)),"") -> Caja de 25 u | G86: =INDEX(Links!$N$138:$W$138,1,(Resumen!$C$3-2025)) -> 22.628324 | H86: =SUMPRODUCT(Links!$F$138:$M$138,$O$69:$V$69)*IF(Links!$E$138="CABA",INDEX(Links!$C$13:$L$13,1,(Resumen!$C$3-2025)),IF(Links!$E$138="PBA",1-INDEX(Links!$C$13:$L$13,1,(Resumen!$C$3-2025)),1)) -> 22.670395 | I86: =G86-H86 -> -0.042070534 | J86: =IF(ROUND(G86-H86,1)>=0,"✔ Sí","✖ No") -> ✔ Sí | K86: =IFERROR(INDEX(Links!$C$345:$C$469,MATCH(C86,Links!$B$218:$B$342,0)),1) -> 25 | L86: =IF(K86>0,H86/K86,0) -> 0.9068158 | M86: =IF(E86="kg",1,0) -> 0 | N86: =H86*M86 -> 0
A87: RODANTES | B87: Abrasivos y corte | C87: =Links!$B$139 -> MP-94 | D87: =Links!$C$139 -> Mecha de acero rápido 4,5 mm | E87: =Links!$D$139 -> u | F87: =IFERROR(INDEX(Links!$B$345:$B$469,MATCH(C87,Links!$B$218:$B$342,0)),"") -> Caja de 25 u | G87: =INDEX(Links!$N$139:$W$139,1,(Resumen!$C$3-2025)) -> 18.142764 | H87: =SUMPRODUCT(Links!$F$139:$M$139,$O$69:$V$69)*IF(Links!$E$139="CABA",INDEX(Links!$C$13:$L$13,1,(Resumen!$C$3-2025)),IF(Links!$E$139="PBA",1-INDEX(Links!$C$13:$L$13,1,(Resumen!$C$3-2025)),1)) -> 18.146821 | I87: =G87-H87 -> -0.0040568639 | J87: =IF(ROUND(G87-H87,1)>=0,"✔ Sí","✖ No") -> ✔ Sí | K87: =IFERROR(INDEX(Links!$C$345:$C$469,MATCH(C87,Links!$B$218:$B$342,0)),1) -> 25 | L87: =IF(K87>0,H87/K87,0) -> 0.72587285 | M87: =IF(E87="kg",1,0) -> 0 | N87: =H87*M87 -> 0
A88: RODANTES | B88: Abrasivos y corte | C88: =Links!$B$140 -> MP-95 | D88: =Links!$C$140 -> Spray antiproyecciones 400 ml | E88: =Links!$D$140 -> u | F88: =IFERROR(INDEX(Links!$B$345:$B$469,MATCH(C88,Links!$B$218:$B$342,0)),"") -> Caja de 25 u | G88: =INDEX(Links!$N$140:$W$140,1,(Resumen!$C$3-2025)) -> 7.7531911 | H88: =SUMPRODUCT(Links!$F$140:$M$140,$O$69:$V$69)*IF(Links!$E$140="CABA",INDEX(Links!$C$13:$L$13,1,(Resumen!$C$3-2025)),IF(Links!$E$140="PBA",1-INDEX(Links!$C$13:$L$13,1,(Resumen!$C$3-2025)),1)) -> 7.7683053 | I88: =G88-H88 -> -0.015114216 | J88: =IF(ROUND(G88-H88,1)>=0,"✔ Sí","✖ No") -> ✔ Sí | K88: =IFERROR(INDEX(Links!$C$345:$C$469,MATCH(C88,Links!$B$218:$B$342,0)),1) -> 25 | L88: =IF(K88>0,H88/K88,0) -> 0.31073221 | M88: =IF(E88="kg",1,0) -> 0 | N88: =H88*M88 -> 0
A89: RODANTES | B89: Pintura (servicio) | C89: =Links!$B$141 -> MP-96/ABC25 | D89: =Links!$C$141 -> Servicio de pintura, carro 25 kg (tercerizado) | E89: =Links!$D$141 -> u | F89: =IFERROR(INDEX(Links!$B$345:$B$469,MATCH(C89,Links!$B$218:$B$342,0)),"") | G89: =INDEX(Links!$N$141:$W$141,1,(Resumen!$C$3-2025)) -> 775.27053 | H89: =SUMPRODUCT(Links!$F$141:$M$141,$O$69:$V$69)*IF(Links!$E$141="CABA",INDEX(Links!$C$13:$L$13,1,(Resumen!$C$3-2025)),IF(Links!$E$141="PBA",1-INDEX(Links!$C$13:$L$13,1,(Resumen!$C$3-2025)),1)) -> 777.31053 | I89: =G89-H89 -> -2.04 | J89: =IF(ROUND(G89-H89,1)>=0,"✔ Sí","✖ No") -> ✖ No | K89: =IFERROR(INDEX(Links!$C$345:$C$469,MATCH(C89,Links!$B$218:$B$342,0)),1) -> 1 | L89: =IF(K89>0,H89/K89,0) -> 777.31053 | M89: =IF(E89="kg",1,0) -> 0 | N89: =H89*M89 -> 0
A90: RODANTES | B90: Pintura (servicio) | C90: =Links!$B$142 -> MP-96/ABC50 | D90: =Links!$C$142 -> Servicio de pintura, carro 50 kg (tercerizado) | E90: =Links!$D$142 -> u | F90: =IFERROR(INDEX(Links!$B$345:$B$469,MATCH(C90,Links!$B$218:$B$342,0)),"") | G90: =INDEX(Links!$N$142:$W$142,1,(Resumen!$C$3-2025)) -> 1706.26 | H90: =SUMPRODUCT(Links!$F$142:$M$142,$O$69:$V$69)*IF(Links!$E$142="CABA",INDEX(Links!$C$13:$L$13,1,(Resumen!$C$3-2025)),IF(Links!$E$142="PBA",1-INDEX(Links!$C$13:$L$13,1,(Resumen!$C$3-2025)),1)) -> 1708.4352 | I90: =G90-H90 -> -2.1751903 | J90: =IF(ROUND(G90-H90,1)>=0,"✔ Sí","✖ No") -> ✖ No | K90: =IFERROR(INDEX(Links!$C$345:$C$469,MATCH(C90,Links!$B$218:$B$342,0)),1) -> 1 | L90: =IF(K90>0,H90/K90,0) -> 1708.4352 | M90: =IF(E90="kg",1,0) -> 0 | N90: =H90*M90 -> 0
A91: RODANTES | B91: Pintura (servicio) | C91: =Links!$B$143 -> MP-96/ABC70 | D91: =Links!$C$143 -> Servicio de pintura, carro 70 kg (tercerizado) | E91: =Links!$D$143 -> u | F91: =IFERROR(INDEX(Links!$B$345:$B$469,MATCH(C91,Links!$B$218:$B$342,0)),"") | G91: =INDEX(Links!$N$143:$W$143,1,(Resumen!$C$3-2025)) -> 372.56986 | H91: =SUMPRODUCT(Links!$F$143:$M$143,$O$69:$V$69)*IF(Links!$E$143="CABA",INDEX(Links!$C$13:$L$13,1,(Resumen!$C$3-2025)),IF(Links!$E$143="PBA",1-INDEX(Links!$C$13:$L$13,1,(Resumen!$C$3-2025)),1)) -> 374.12986 | I91: =G91-H91 -> -1.56 | J91: =IF(ROUND(G91-H91,1)>=0,"✔ Sí","✖ No") -> ✖ No | K91: =IFERROR(INDEX(Links!$C$345:$C$469,MATCH(C91,Links!$B$218:$B$342,0)),1) -> 1 | L91: =IF(K91>0,H91/K91,0) -> 374.12986 | M91: =IF(E91="kg",1,0) -> 0 | N91: =H91*M91 -> 0
A92: RODANTES | B92: Pintura (servicio) | C92: =Links!$B$144 -> MP-96/ABC100 | D92: =Links!$C$144 -> Servicio de pintura, carro 100 kg (tercerizado) | E92: =Links!$D$144 -> u | F92: =IFERROR(INDEX(Links!$B$345:$B$469,MATCH(C92,Links!$B$218:$B$342,0)),"") | G92: =INDEX(Links!$N$144:$W$144,1,(Resumen!$C$3-2025)) -> 247.17607 | H92: =SUMPRODUCT(Links!$F$144:$M$144,$O$69:$V$69)*IF(Links!$E$144="CABA",INDEX(Links!$C$13:$L$13,1,(Resumen!$C$3-2025)),IF(Links!$E$144="PBA",1-INDEX(Links!$C$13:$L$13,1,(Resumen!$C$3-2025)),1)) -> 247.44657 | I92: =G92-H92 -> -0.27049612 | J92: =IF(ROUND(G92-H92,1)>=0,"✔ Sí","✖ No") -> ✖ No | K92: =IFERROR(INDEX(Links!$C$345:$C$469,MATCH(C92,Links!$B$218:$B$342,0)),1) -> 1 | L92: =IF(K92>0,H92/K92,0) -> 247.44657 | M92: =IF(E92="kg",1,0) -> 0 | N92: =H92*M92 -> 0
A93: RODANTES | B93: Agente: polvo | C93: =Links!$B$145 -> MP-33B | D93: =Links!$C$145 -> Polvo ABC 90 (carros y sus recargas) | E93: =Links!$D$145 -> kg | F93: =IFERROR(INDEX(Links!$B$345:$B$469,MATCH(C93,Links!$B$218:$B$342,0)),"") -> Big bag de 1.000 kg | G93: =INDEX(Links!$N$145:$W$145,1,(Resumen!$C$3-2025)) -> 91902.182 | H93: =SUMPRODUCT(Links!$F$145:$M$145,$O$69:$V$69)*IF(Links!$E$145="CABA",INDEX(Links!$C$13:$L$13,1,(Resumen!$C$3-2025)),IF(Links!$E$145="PBA",1-INDEX(Links!$C$13:$L$13,1,(Resumen!$C$3-2025)),1)) -> 91918.958 | I93: =G93-H93 -> -16.775217 | J93: =IF(ROUND(G93-H93,1)>=0,"✔ Sí","✖ No") -> ✖ No | K93: =IFERROR(INDEX(Links!$C$345:$C$469,MATCH(C93,Links!$B$218:$B$342,0)),1) -> 1000 | L93: =IF(K93>0,H93/K93,0) -> 91.918958 | M93: =IF(E93="kg",1,0) -> 1 | N93: =H93*M93 -> 91918.958
A94: RODANTES | B94: Nitrógeno | C94: =Links!$B$146 -> MP-34 | D94: =Links!$C$146 -> Nitrógeno seco | E94: =Links!$D$146 -> m³ | F94: =IFERROR(INDEX(Links!$B$345:$B$469,MATCH(C94,Links!$B$218:$B$342,0)),"") -> Pack de 12 cilindros | G94: =INDEX(Links!$N$146:$W$146,1,(Resumen!$C$3-2025)) -> 540.11059 | H94: =SUMPRODUCT(Links!$F$146:$M$146,$O$69:$V$69)*IF(Links!$E$146="CABA",INDEX(Links!$C$13:$L$13,1,(Resumen!$C$3-2025)),IF(Links!$E$146="PBA",1-INDEX(Links!$C$13:$L$13,1,(Resumen!$C$3-2025)),1)) -> 540.22318 | I94: =G94-H94 -> -0.11258235 | J94: =IF(ROUND(G94-H94,1)>=0,"✔ Sí","✖ No") -> ✖ No | K94: =IFERROR(INDEX(Links!$C$345:$C$469,MATCH(C94,Links!$B$218:$B$342,0)),1) -> 110 | L94: =IF(K94>0,H94/K94,0) -> 4.9111198 | M94: =IF(E94="kg",1,0) -> 0 | N94: =H94*M94 -> 0
A95: RODANTES | B95: Componentes comprados | C95: =Links!$B$147 -> MP-70 | D95: =Links!$C$147 -> Arandela de tope del eje | E95: =Links!$D$147 -> u | F95: =IFERROR(INDEX(Links!$B$345:$B$469,MATCH(C95,Links!$B$218:$B$342,0)),"") -> Bolsa de 1.000 u | G95: =INDEX(Links!$N$147:$W$147,1,(Resumen!$C$3-2025)) -> 7257.1058 | H95: =SUMPRODUCT(Links!$F$147:$M$147,$O$69:$V$69)*IF(Links!$E$147="CABA",INDEX(Links!$C$13:$L$13,1,(Resumen!$C$3-2025)),IF(Links!$E$147="PBA",1-INDEX(Links!$C$13:$L$13,1,(Resumen!$C$3-2025)),1)) -> 7258.7285 | I95: =G95-H95 -> -1.6227456 | J95: =IF(ROUND(G95-H95,1)>=0,"✔ Sí","✖ No") -> ✖ No | K95: =IFERROR(INDEX(Links!$C$345:$C$469,MATCH(C95,Links!$B$218:$B$342,0)),1) -> 1000 | L95: =IF(K95>0,H95/K95,0) -> 7.2587285 | M95: =IF(E95="kg",1,0) -> 0 | N95: =H95*M95 -> 0
A96: RODANTES | B96: Componentes comprados | C96: =Links!$B$148 -> MP-71 | D96: =Links!$C$148 -> Pasador partido del eje | E96: =Links!$D$148 -> u | F96: =IFERROR(INDEX(Links!$B$345:$B$469,MATCH(C96,Links!$B$218:$B$342,0)),"") -> Bolsa de 1.000 u | G96: =INDEX(Links!$N$148:$W$148,1,(Resumen!$C$3-2025)) -> 3628.5529 | H96: =SUMPRODUCT(Links!$F$148:$M$148,$O$69:$V$69)*IF(Links!$E$148="CABA",INDEX(Links!$C$13:$L$13,1,(Resumen!$C$3-2025)),IF(Links!$E$148="PBA",1-INDEX(Links!$C$13:$L$13,1,(Resumen!$C$3-2025)),1)) -> 3629.3643 | I96: =G96-H96 -> -0.81137279 | J96: =IF(ROUND(G96-H96,1)>=0,"✔ Sí","✖ No") -> ✖ No | K96: =IFERROR(INDEX(Links!$C$345:$C$469,MATCH(C96,Links!$B$218:$B$342,0)),1) -> 1000 | L96: =IF(K96>0,H96/K96,0) -> 3.6293643 | M96: =IF(E96="kg",1,0) -> 0 | N96: =H96*M96 -> 0
A97: RODANTES | B97: Componentes comprados | C97: =Links!$B$149 -> MP-54/300 | D97: =Links!$C$149 -> Rueda Ø300 × 50, buje 3/4" (carro 25 kg) | E97: =Links!$D$149 -> u | F97: =IFERROR(INDEX(Links!$B$345:$B$469,MATCH(C97,Links!$B$218:$B$342,0)),"") -> Pallet de 72 u | G97: =INDEX(Links!$N$149:$W$149,1,(Resumen!$C$3-2025)) -> 906.54107 | H97: =SUMPRODUCT(Links!$F$149:$M$149,$O$69:$V$69)*IF(Links!$E$149="CABA",INDEX(Links!$C$13:$L$13,1,(Resumen!$C$3-2025)),IF(Links!$E$149="PBA",1-INDEX(Links!$C$13:$L$13,1,(Resumen!$C$3-2025)),1)) -> 907.34107 | I97: =G97-H97 -> -0.8 | J97: =IF(ROUND(G97-H97,1)>=0,"✔ Sí","✖ No") -> ✖ No | K97: =IFERROR(INDEX(Links!$C$345:$C$469,MATCH(C97,Links!$B$218:$B$342,0)),1) -> 72 | L97: =IF(K97>0,H97/K97,0) -> 12.601959 | M97: =IF(E97="kg",1,0) -> 0 | N97: =H97*M97 -> 0
A98: RODANTES | B98: Componentes comprados | C98: =Links!$B$150 -> MP-54/350 | D98: =Links!$C$150 -> Rueda Ø350 × 60, buje 1" (carro 50 kg) | E98: =Links!$D$150 -> u | F98: =IFERROR(INDEX(Links!$B$345:$B$469,MATCH(C98,Links!$B$218:$B$342,0)),"") -> Pallet de 72 u | G98: =INDEX(Links!$N$150:$W$150,1,(Resumen!$C$3-2025)) -> 1996.52 | H98: =SUMPRODUCT(Links!$F$150:$M$150,$O$69:$V$69)*IF(Links!$E$150="CABA",INDEX(Links!$C$13:$L$13,1,(Resumen!$C$3-2025)),IF(Links!$E$150="PBA",1-INDEX(Links!$C$13:$L$13,1,(Resumen!$C$3-2025)),1)) -> 1995.9903 | I98: =G98-H98 -> 0.52961944 | J98: =IF(ROUND(G98-H98,1)>=0,"✔ Sí","✖ No") -> ✔ Sí | K98: =IFERROR(INDEX(Links!$C$345:$C$469,MATCH(C98,Links!$B$218:$B$342,0)),1) -> 72 | L98: =IF(K98>0,H98/K98,0) -> 27.722088 | M98: =IF(E98="kg",1,0) -> 0 | N98: =H98*M98 -> 0
A99: RODANTES | B99: Componentes comprados | C99: =Links!$B$151 -> MP-54/400 | D99: =Links!$C$151 -> Rueda Ø400 × 60, buje 1" (carros 70 y 100 kg) | E99: =Links!$D$151 -> u | F99: =IFERROR(INDEX(Links!$B$345:$B$469,MATCH(C99,Links!$B$218:$B$342,0)),"") -> Pallet de 72 u | G99: =INDEX(Links!$N$151:$W$151,1,(Resumen!$C$3-2025)) -> 725.49186 | H99: =SUMPRODUCT(Links!$F$151:$M$151,$O$69:$V$69)*IF(Links!$E$151="CABA",INDEX(Links!$C$13:$L$13,1,(Resumen!$C$3-2025)),IF(Links!$E$151="PBA",1-INDEX(Links!$C$13:$L$13,1,(Resumen!$C$3-2025)),1)) -> 726.03285 | I99: =G99-H99 -> -0.54099223 | J99: =IF(ROUND(G99-H99,1)>=0,"✔ Sí","✖ No") -> ✖ No | K99: =IFERROR(INDEX(Links!$C$345:$C$469,MATCH(C99,Links!$B$218:$B$342,0)),1) -> 72 | L99: =IF(K99>0,H99/K99,0) -> 10.08379 | M99: =IF(E99="kg",1,0) -> 0 | N99: =H99*M99 -> 0
A100: RODANTES | B100: Componentes comprados | C100: =Links!$B$152 -> MP-44/25 | D100: =Links!$C$152 -> Válvula HZ de carro 25 kg, sin tubo pescante | E100: =Links!$D$152 -> u | F100: =IFERROR(INDEX(Links!$B$345:$B$469,MATCH(C100,Links!$B$218:$B$342,0)),"") -> Caja de 10 u | G100: =INDEX(Links!$N$152:$W$152,1,(Resumen!$C$3-2025)) -> 453.27053 | H100: =SUMPRODUCT(Links!$F$152:$M$152,$O$69:$V$69)*IF(Links!$E$152="CABA",INDEX(Links!$C$13:$L$13,1,(Resumen!$C$3-2025)),IF(Links!$E$152="PBA",1-INDEX(Links!$C$13:$L$13,1,(Resumen!$C$3-2025)),1)) -> 453.67053 | I100: =G100-H100 -> -0.4 | J100: =IF(ROUND(G100-H100,1)>=0,"✔ Sí","✖ No") -> ✖ No | K100: =IFERROR(INDEX(Links!$C$345:$C$469,MATCH(C100,Links!$B$218:$B$342,0)),1) -> 10 | L100: =IF(K100>0,H100/K100,0) -> 45.367053 | M100: =IF(E100="kg",1,0) -> 0 | N100: =H100*M100 -> 0
A101: RODANTES | B101: Componentes comprados | C101: =Links!$B$153 -> MP-44/50 | D101: =Links!$C$153 -> Válvula HZ de carro 50-70-100 kg, sin tubo pescante | E101: =Links!$D$153 -> u | F101: =IFERROR(INDEX(Links!$B$345:$B$469,MATCH(C101,Links!$B$218:$B$342,0)),"") -> Caja de 10 u | G101: =INDEX(Links!$N$153:$W$153,1,(Resumen!$C$3-2025)) -> 1361.0059 | H101: =SUMPRODUCT(Links!$F$153:$M$153,$O$69:$V$69)*IF(Links!$E$153="CABA",INDEX(Links!$C$13:$L$13,1,(Resumen!$C$3-2025)),IF(Links!$E$153="PBA",1-INDEX(Links!$C$13:$L$13,1,(Resumen!$C$3-2025)),1)) -> 1361.0116 | I101: =G101-H101 -> -0.0056863947 | J101: =IF(ROUND(G101-H101,1)>=0,"✔ Sí","✖ No") -> ✔ Sí | K101: =IFERROR(INDEX(Links!$C$345:$C$469,MATCH(C101,Links!$B$218:$B$342,0)),1) -> 10 | L101: =IF(K101>0,H101/K101,0) -> 136.10116 | M101: =IF(E101="kg",1,0) -> 0 | N101: =H101*M101 -> 0
A102: RODANTES | B102: Componentes comprados | C102: =Links!$B$154 -> MP-45 | D102: =Links!$C$154 -> Manómetro 1,4 MPa | E102: =Links!$D$154 -> u | F102: =IFERROR(INDEX(Links!$B$345:$B$469,MATCH(C102,Links!$B$218:$B$342,0)),"") -> Caja de 100 u | G102: =INDEX(Links!$N$154:$W$154,1,(Resumen!$C$3-2025)) -> 1814.2764 | H102: =SUMPRODUCT(Links!$F$154:$M$154,$O$69:$V$69)*IF(Links!$E$154="CABA",INDEX(Links!$C$13:$L$13,1,(Resumen!$C$3-2025)),IF(Links!$E$154="PBA",1-INDEX(Links!$C$13:$L$13,1,(Resumen!$C$3-2025)),1)) -> 1814.6821 | I102: =G102-H102 -> -0.40568639 | J102: =IF(ROUND(G102-H102,1)>=0,"✔ Sí","✖ No") -> ✖ No | K102: =IFERROR(INDEX(Links!$C$345:$C$469,MATCH(C102,Links!$B$218:$B$342,0)),1) -> 100 | L102: =IF(K102>0,H102/K102,0) -> 18.146821 | M102: =IF(E102="kg",1,0) -> 0 | N102: =H102*M102 -> 0
...

Sheet Linea
A1: BALANCEO DE LÍNEA (año elegido en Resumen)
A2: Tiempos, unidades y recursos de cada Aprovechamiento. Eficiencia de balanceo = aprovechamiento medio / aprovechamiento del cuello de botella (100 % = línea perfectamente balanceada).
A4: LÍNEA DE MANUALES
B5: Unidades del año (recipientes / recargas) | C5: =SUM(Resumen!$D$7:$D$14) -> 284462.56
B6: Unidades del mes pico | C6: =MAX(INDEX(Links!$B$502:$M$610,(Resumen!$C$3-2026)*11+10,0)) -> 33317.088
B7: Horas productivas por mes (1 turno) | C7: =Links!$B$641 -> 150
B8: Takt del mes pico, 1 turno (s/u) | C8: =IF(C6=0,0,C7*3600/C6) -> 16.207899
B9: Contenido de trabajo por unidad (s/u) | C9: =IF(C5=0,0,F45*3600/C5) -> 754.11409
B10: Recursos-turno mínimos teóricos (contenido / takt) | C10: =IF(C8=0,0,C9/C8) -> 46.527566
B11: Recursos-turno instalados (máquinas × turnos) | C11: =I45 -> 59
B12: Aprovechamiento medio (ponderado por recursos) | C12: =IF(I45=0,0,SUMPRODUCT(J19:J44,I19:I44)/I45) -> 0.6175348
B13: Cuello de botella | C13: =INDEX(B19:B44,MATCH(MAX(J19:J44),J19:J44,0)) -> Soldadura longitudinal — 2,5 a 10 kg
B14: Aprovechamiento del cuello de botella | C14: =MAX(J19:J44) -> 0.79491735
B15: Eficiencia de balanceo (medio / cuello) | C15: =IF(C14=0,0,C12/C14) -> 0.7768541
B16: Tiempo ocioso del balanceo | C16: =1-C15 -> 0.2231459
A18: N° | B18: Puesto | C18: Recurso | D18: Tiempo (s/u) | E18: Unidades del año | F18: Horas de trabajo | G18: Máq. | H18: Turnos | I18: Recursos | J18: Aprovechamiento | K18: Cuello
A19: 1 | B19: Recepción de materia prima | C19: Manual | D19: =Links!$B$613 -> 60 | E19: =INDEX(Links!$B$644:$B$922,(Resumen!$C$3-2026)*28+2) -> 284462.56 | F19: =E19*D19/3600 -> 4741.0427 | G19: =INDEX(Links!$B$954:$K$954,1,(Resumen!$C$3-2025)) -> 2 | H19: =INDEX(Links!$B$983:$K$983,1,(Resumen!$C$3-2025)) -> 2 | I19: =G19*H19 -> 4 | J19: =INDEX(Links!$B$925:$K$925,1,(Resumen!$C$3-2025)) -> 0.71115641 | K19: =IF(J19=MAX($J$19:$J$44),"◀ cuello","")
A20: 2 | B20: Corte de chapa — 1.er corte en franjas (guillotina 1, manuales + carros) | C20: Máquina | D20: =Links!$B$614 -> 6.5815524 | E20: =INDEX(Links!$B$644:$B$922,(Resumen!$C$3-2026)*28+3) -> 307140.07 | F20: =E20*D20/3600 -> 561.51625 | G20: =INDEX(Links!$B$955:$K$955,1,(Resumen!$C$3-2025)) -> 1 | H20: =INDEX(Links!$B$984:$K$984,1,(Resumen!$C$3-2025)) -> 1 | I20: =G20*H20 -> 1 | J20: =INDEX(Links!$B$926:$K$926,1,(Resumen!$C$3-2025)) -> 0.34440579 | K20: =IF(J20=MAX($J$19:$J$44),"◀ cuello","")
A21: 3 | B21: Corte de chapa — 2.º corte en piezas (guillotina 2, manuales + carros) | C21: Máquina | D21: =Links!$B$615 -> 4.8793839 | E21: =INDEX(Links!$B$644:$B$922,(Resumen!$C$3-2026)*28+4) -> 313905.44 | F21: =E21*D21/3600 -> 425.46254 | G21: =INDEX(Links!$B$956:$K$956,1,(Resumen!$C$3-2025)) -> 1 | H21: =INDEX(Links!$B$985:$K$985,1,(Resumen!$C$3-2025)) -> 1 | I21: =G21*H21 -> 1 | J21: =INDEX(Links!$B$927:$K$927,1,(Resumen!$C$3-2025)) -> 0.25565166 | K21: =IF(J21=MAX($J$19:$J$44),"◀ cuello","")
A22: 4 | B22: Corte de disco y embutido (cúpula y fondo) | C22: Máquina | D22: =Links!$B$616 -> 8 | E22: =INDEX(Links!$B$644:$B$922,(Resumen!$C$3-2026)*28+5) -> 568925.13 | F22: =E22*D22/3600 -> 1264.2781 | G22: =INDEX(Links!$B$957:$K$957,1,(Resumen!$C$3-2025)) -> 1 | H22: =INDEX(Links!$B$986:$K$986,1,(Resumen!$C$3-2025)) -> 2 | I22: =G22*H22 -> 2 | J22: =INDEX(Links!$B$928:$K$928,1,(Resumen!$C$3-2025)) -> 0.55776973 | K22: =IF(J22=MAX($J$19:$J$44),"◀ cuello","")
A23: 5 | B23: Preparación de cuello | C23: Máquina | D23: =Links!$B$617 -> 60 | E23: =INDEX(Links!$B$644:$B$922,(Resumen!$C$3-2026)*28+6) -> 284462.56 | F23: =E23*D23/3600 -> 4741.0427 | G23: =INDEX(Links!$B$958:$K$958,1,(Resumen!$C$3-2025)) -> 2 | H23: =INDEX(Links!$B$987:$K$987,1,(Resumen!$C$3-2025)) -> 2 | I23: =G23*H23 -> 4 | J23: =INDEX(Links!$B$929:$K$929,1,(Resumen!$C$3-2025)) -> 0.71115641 | K23: =IF(J23=MAX($J$19:$J$44),"◀ cuello","")
A24: 6 | B24: Numerado de cúpula | C24: Máquina | D24: =Links!$B$618 -> 20 | E24: =INDEX(Links!$B$644:$B$922,(Resumen!$C$3-2026)*28+7) -> 284462.56 | F24: =E24*D24/3600 -> 1580.3476 | G24: =INDEX(Links!$B$959:$K$959,1,(Resumen!$C$3-2025)) -> 1 | H24: =INDEX(Links!$B$988:$K$988,1,(Resumen!$C$3-2025)) -> 2 | I24: =G24*H24 -> 2 | J24: =INDEX(Links!$B$930:$K$930,1,(Resumen!$C$3-2025)) -> 0.47410427 | K24: =IF(J24=MAX($J$19:$J$44),"◀ cuello","")
A25: 7 | B25: Soldadura del cuello a la cúpula | C25: Máquina | D25: =Links!$B$619 -> 25 | E25: =INDEX(Links!$B$644:$B$922,(Resumen!$C$3-2026)*28+8) -> 284462.56 | F25: =E25*D25/3600 -> 1975.4345 | G25: =INDEX(Links!$B$960:$K$960,1,(Resumen!$C$3-2025)) -> 1 | H25: =INDEX(Links!$B$989:$K$989,1,(Resumen!$C$3-2025)) -> 2 | I25: =G25*H25 -> 2 | J25: =INDEX(Links!$B$931:$K$931,1,(Resumen!$C$3-2025)) -> 0.60886679 | K25: =IF(J25=MAX($J$19:$J$44),"◀ cuello","")
A26: 8 | B26: Cilindrado | C26: Máquina | D26: =Links!$B$620 -> 15 | E26: =INDEX(Links!$B$644:$B$922,(Resumen!$C$3-2026)*28+9) -> 284462.56 | F26: =E26*D26/3600 -> 1185.2607 | G26: =INDEX(Links!$B$961:$K$961,1,(Resumen!$C$3-2025)) -> 1 | H26: =INDEX(Links!$B$990:$K$990,1,(Resumen!$C$3-2025)) -> 1 | I26: =G26*H26 -> 1 | J26: =INDEX(Links!$B$932:$K$932,1,(Resumen!$C$3-2025)) -> 0.72076663 | K26: =IF(J26=MAX($J$19:$J$44),"◀ cuello","")
A27: 9 | B27: Soldadura longitudinal — 2,5 a 10 kg | C27: Máquina | D27: =Links!$B$621 -> 115 | E27: =INDEX(Links!$B$644:$B$922,(Resumen!$C$3-2026)*28+10) -> 81841.925 | F27: =E27*D27/3600 -> 2614.3948 | G27: =INDEX(Links!$B$962:$K$962,1,(Resumen!$C$3-2025)) -> 1 | H27: =INDEX(Links!$B$991:$K$991,1,(Resumen!$C$3-2025)) -> 2 | I27: =G27*H27 -> 2 | J27: =INDEX(Links!$B$933:$K$933,1,(Resumen!$C$3-2025)) -> 0.79491735 | K27: =IF(J27=MAX($J$19:$J$44),"◀ cuello","") -> ◀ cuello
A28: 10 | B28: Soldadura longitudinal TIG — 1 kg | C28: Máquina | D28: =Links!$B$622 -> 30 | E28: =INDEX(Links!$B$644:$B$922,(Resumen!$C$3-2026)*28+11) -> 202620.64 | F28: =E28*D28/3600 -> 1688.5053 | G28: =INDEX(Links!$B$963:$K$963,1,(Resumen!$C$3-2025)) -> 1 | H28: =INDEX(Links!$B$992:$K$992,1,(Resumen!$C$3-2025)) -> 2 | I28: =G28*H28 -> 2 | J28: =INDEX(Links!$B$934:$K$934,1,(Resumen!$C$3-2025)) -> 0.5065516 | K28: =IF(J28=MAX($J$19:$J$44),"◀ cuello","")
A29: 11 | B29: Encastre de fondo | C29: Máquina | D29: =Links!$B$623 -> 30 | E29: =INDEX(Links!$B$644:$B$922,(Resumen!$C$3-2026)*28+12) -> 284462.56 | F29: =E29*D29/3600 -> 2370.5214 | G29: =INDEX(Links!$B$964:$K$964,1,(Resumen!$C$3-2025)) -> 1 | H29: =INDEX(Links!$B$993:$K$993,1,(Resumen!$C$3-2025)) -> 2 | I29: =G29*H29 -> 2 | J29: =INDEX(Links!$B$935:$K$935,1,(Resumen!$C$3-2025)) -> 0.72402802 | K29: =IF(J29=MAX($J$19:$J$44),"◀ cuello","")
A30: 12 | B30: Bordoneado | C30: Máquina | D30: =Links!$B$624 -> 20 | E30: =INDEX(Links!$B$644:$B$922,(Resumen!$C$3-2026)*28+13) -> 284462.56 | F30: =E30*D30/3600 -> 1580.3476 | G30: =INDEX(Links!$B$965:$K$965,1,(Resumen!$C$3-2025)) -> 1 | H30: =INDEX(Links!$B$994:$K$994,1,(Resumen!$C$3-2025)) -> 2 | I30: =G30*H30 -> 2 | J30: =INDEX(Links!$B$936:$K$936,1,(Resumen!$C$3-2025)) -> 0.48268535 | K30: =IF(J30=MAX($J$19:$J$44),"◀ cuello","")
A31: 13 | B31: Soldadura circunferencial de cúpula y fondo | C31: Máquina | D31: =Links!$B$625 -> 60 | E31: =INDEX(Links!$B$644:$B$922,(Resumen!$C$3-2026)*28+14) -> 284462.56 | F31: =E31*D31/3600 -> 4741.0427 | G31: =INDEX(Links!$B$966:$K$966,1,(Resumen!$C$3-2025)) -> 2 | H31: =INDEX(Links!$B$995:$K$995,1,(Resumen!$C$3-2025)) -> 2 | I31: =G31*H31 -> 4 | J31: =INDEX(Links!$B$937:$K$937,1,(Resumen!$C$3-2025)) -> 0.72402802 | K31: =IF(J31=MAX($J$19:$J$44),"◀ cuello","")
A32: 14 | B32: Control de calidad — Espesor | C32: Manual | D32: =Links!$B$626 -> 120 | E32: =INDEX(Links!$B$644:$B$922,(Resumen!$C$3-2026)*28+15) -> 5689.2513 | F32: =E32*D32/3600 -> 189.64171 | G32: =INDEX(Links!$B$967:$K$967,1,(Resumen!$C$3-2025)) -> 1 | H32: =INDEX(Links!$B$996:$K$996,1,(Resumen!$C$3-2025)) -> 1 | I32: =G32*H32 -> 1 | J32: =INDEX(Links!$B$938:$K$938,1,(Resumen!$C$3-2025)) -> 0.11378503 | K32: =IF(J32=MAX($J$19:$J$44),"◀ cuello","")
A33: 15 | B33: Prueba hidráulica | C33: Máquina | D33: =Links!$B$627 -> 60 | E33: =INDEX(Links!$B$644:$B$922,(Resumen!$C$3-2026)*28+16) -> 284462.56 | F33: =E33*D33/3600 -> 4741.0427 | G33: =INDEX(Links!$B$968:$K$968,1,(Resumen!$C$3-2025)) -> 2 | H33: =INDEX(Links!$B$997:$K$997,1,(Resumen!$C$3-2025)) -> 2 | I33: =G33*H33 -> 4 | J33: =INDEX(Links!$B$939:$K$939,1,(Resumen!$C$3-2025)) -> 0.72402802 | K33: =IF(J33=MAX($J$19:$J$44),"◀ cuello","")
A34: 16 | B34: Secado | C34: Máquina | D34: =Links!$B$628 -> 120 | E34: =INDEX(Links!$B$644:$B$922,(Resumen!$C$3-2026)*28+17) -> 284462.56 | F34: =E34*D34/3600 -> 9482.0855 | G34: =INDEX(Links!$B$969:$K$969,1,(Resumen!$C$3-2025)) -> 4 | H34: =INDEX(Links!$B$998:$K$998,1,(Resumen!$C$3-2025)) -> 2 | I34: =G34*H34 -> 8 | J34: =INDEX(Links!$B$940:$K$940,1,(Resumen!$C$3-2025)) -> 0.71115641 | K34: =IF(J34=MAX($J$19:$J$44),"◀ cuello","")
A35: 17 | B35: Granallado | C35: Máquina | D35: =Links!$B$629 -> 30 | E35: =INDEX(Links!$B$644:$B$922,(Resumen!$C$3-2026)*28+18) -> 284462.56 | F35: =E35*D35/3600 -> 2370.5214 | G35: =INDEX(Links!$B$970:$K$970,1,(Resumen!$C$3-2025)) -> 1 | H35: =INDEX(Links!$B$999:$K$999,1,(Resumen!$C$3-2025)) -> 2 | I35: =G35*H35 -> 2 | J35: =INDEX(Links!$B$941:$K$941,1,(Resumen!$C$3-2025)) -> 0.71115641 | K35: =IF(J35=MAX($J$19:$J$44),"◀ cuello","")
A36: 18 | B36: Detección de defectos | C36: Manual | D36: =Links!$B$630 -> 20 | E36: =INDEX(Links!$B$644:$B$922,(Resumen!$C$3-2026)*28+19) -> 284462.56 | F36: =E36*D36/3600 -> 1580.3476 | G36: =INDEX(Links!$B$971:$K$971,1,(Resumen!$C$3-2025)) -> 1 | H36: =INDEX(Links!$B$1000:$K$1000,1,(Resumen!$C$3-2025)) -> 2 | I36: =G36*H36 -> 2 | J36: =INDEX(Links!$B$942:$K$942,1,(Resumen!$C$3-2025)) -> 0.47410427 | K36: =IF(J36=MAX($J$19:$J$44),"◀ cuello","")
A37: 19 | B37: Corrección de defectos | C37: Manual | D37: =Links!$B$631 -> 180 | E37: =INDEX(Links!$B$644:$B$922,(Resumen!$C$3-2026)*28+20) -> 14223.128 | F37: =E37*D37/3600 -> 711.15641 | G37: =INDEX(Links!$B$972:$K$972,1,(Resumen!$C$3-2025)) -> 1 | H37: =INDEX(Links!$B$1001:$K$1001,1,(Resumen!$C$3-2025)) -> 1 | I37: =G37*H37 -> 1 | J37: =INDEX(Links!$B$943:$K$943,1,(Resumen!$C$3-2025)) -> 0.42669385 | K37: =IF(J37=MAX($J$19:$J$44),"◀ cuello","")
A38: 20 | B38: Pintura en polvo + horno | C38: Máquina | D38: =Links!$B$632 -> 25 | E38: =INDEX(Links!$B$644:$B$922,(Resumen!$C$3-2026)*28+21) -> 284462.56 | F38: =E38*D38/3600 -> 1975.4345 | G38: =INDEX(Links!$B$973:$K$973,1,(Resumen!$C$3-2025)) -> 1 | H38: =INDEX(Links!$B$1002:$K$1002,1,(Resumen!$C$3-2025)) -> 2 | I38: =G38*H38 -> 2 | J38: =INDEX(Links!$B$944:$K$944,1,(Resumen!$C$3-2025)) -> 0.62601797 | K38: =IF(J38=MAX($J$19:$J$44),"◀ cuello","")
A39: 21 | B39: Carga de polvo | C39: Máquina | D39: =Links!$B$633 -> 45 | E39: =INDEX(Links!$B$644:$B$922,(Resumen!$C$3-2026)*28+22) -> 72169.004 | F39: =E39*D39/3600 -> 902.11255 | G39: =INDEX(Links!$B$974:$K$974,1,(Resumen!$C$3-2025)) -> 1 | H39: =INDEX(Links!$B$1003:$K$1003,1,(Resumen!$C$3-2025)) -> 1 | I39: =G39*H39 -> 1 | J39: =INDEX(Links!$B$945:$K$945,1,(Resumen!$C$3-2025)) -> 0.54126753 | K39: =IF(J39=MAX($J$19:$J$44),"◀ cuello","")
A40: 22 | B40: Ensamblaje | C40: Manual | D40: =Links!$B$634 -> 100 | E40: =INDEX(Links!$B$644:$B$922,(Resumen!$C$3-2026)*28+23) -> 72169.004 | F40: =E40*D40/3600 -> 2004.6946 | G40: =INDEX(Links!$B$975:$K$975,1,(Resumen!$C$3-2025)) -> 1 | H40: =INDEX(Links!$B$1004:$K$1004,1,(Resumen!$C$3-2025)) -> 2 | I40: =G40*H40 -> 2 | J40: =INDEX(Links!$B$946:$K$946,1,(Resumen!$C$3-2025)) -> 0.61229359 | K40: =IF(J40=MAX($J$19:$J$44),"◀ cuello","")
A41: 23 | B41: Presurización | C41: Máquina | D41: =Links!$B$635 -> 30 | E41: =INDEX(Links!$B$644:$B$922,(Resumen!$C$3-2026)*28+24) -> 72169.004 | F41: =E41*D41/3600 -> 601.40837 | G41: =INDEX(Links!$B$976:$K$976,1,(Resumen!$C$3-2025)) -> 1 | H41: =INDEX(Links!$B$1005:$K$1005,1,(Resumen!$C$3-2025)) -> 1 | I41: =G41*H41 -> 1 | J41: =INDEX(Links!$B$947:$K$947,1,(Resumen!$C$3-2025)) -> 0.36084502 | K41: =IF(J41=MAX($J$19:$J$44),"◀ cuello","")
A42: 24 | B42: Control de calidad — Ensayo de pérdidas | C42: Máquina | D42: =Links!$B$636 -> 40 | E42: =INDEX(Links!$B$644:$B$922,(Resumen!$C$3-2026)*28+25) -> 72169.004 | F42: =E42*D42/3600 -> 801.87783 | G42: =INDEX(Links!$B$977:$K$977,1,(Resumen!$C$3-2025)) -> 1 | H42: =INDEX(Links!$B$1006:$K$1006,1,(Resumen!$C$3-2025)) -> 1 | I42: =G42*H42 -> 1 | J42: =INDEX(Links!$B$948:$K$948,1,(Resumen!$C$3-2025)) -> 0.4811267 | K42: =IF(J42=MAX($J$19:$J$44),"◀ cuello","")
A43: 25 | B43: Etiquetado | C43: Máquina | D43: =Links!$B$637 -> 60 | E43: =INDEX(Links!$B$644:$B$922,(Resumen!$C$3-2026)*28+26) -> 72169.004 | F43: =E43*D43/3600 -> 1202.8167 | G43: =INDEX(Links!$B$978:$K$978,1,(Resumen!$C$3-2025)) -> 1 | H43: =INDEX(Links!$B$1007:$K$1007,1,(Resumen!$C$3-2025)) -> 1 | I43: =G43*H43 -> 1 | J43: =INDEX(Links!$B$949:$K$949,1,(Resumen!$C$3-2025)) -> 0.72169004 | K43: =IF(J43=MAX($J$19:$J$44),"◀ cuello","")
A44: 26 | B44: Embalaje y paletizado | C44: Manual | D44: =Links!$B$638 -> 45 | E44: =INDEX(Links!$B$644:$B$922,(Resumen!$C$3-2026)*28+27) -> 284462.56 | F44: =E44*D44/3600 -> 3555.7821 | G44: =INDEX(Links!$B$979:$K$979,1,(Resumen!$C$3-2025)) -> 2 | H44: =INDEX(Links!$B$1008:$K$1008,1,(Resumen!$C$3-2025)) -> 2 | I44: =G44*H44 -> 4 | J44: =INDEX(Links!$B$950:$K$950,1,(Resumen!$C$3-2025)) -> 0.53815087 | K44: =IF(J44=MAX($J$19:$J$44),"◀ cuello","")
B45: Total | F45: =SUM(F19:F44) -> 59588.119 | I45: =SUM(I19:I44) -> 59
A48: LÍNEA DE CARROS
B49: Unidades del año (recipientes / recargas) | C49: =SUM(Resumen!$D$15:$D$22) -> 3107.3221
B50: Unidades del mes pico | C50: =MAX(INDEX(Links!$B$1024:$M$1132,(Resumen!$C$3-2026)*11+10,0)) -> 279.65899
B51: Horas productivas por mes (1 turno) | C51: =Links!$B$1155 -> 150
B52: Takt del mes pico, 1 turno (s/u) | C52: =IF(C50=0,0,C51*3600/C50) -> 1930.9231
B53: Contenido de trabajo por unidad (s/u) | C53: =IF(C49=0,0,F81*3600/C49) -> 6202.1219
B54: Recursos-turno mínimos teóricos (contenido / takt) | C54: =IF(C52=0,0,C53/C52) -> 3.2119985
B55: Recursos-turno instalados (máquinas × turnos) | C55: =I81 -> 18
B56: Aprovechamiento medio (ponderado por recursos) | C56: =IF(I81=0,0,SUMPRODUCT(J63:J80,I63:I80)/I81) -> 0.22680856
B57: Cuello de botella | C57: =INDEX(B63:B80,MATCH(MAX(J63:J80),J63:J80,0)) -> Soldadura de accesorios
B58: Aprovechamiento del cuello de botella | C58: =MAX(J63:J80) -> 0.5230764
B59: Eficiencia de balanceo (medio / cuello) | C59: =IF(C58=0,0,C56/C58) -> 0.43360503
B60: Tiempo ocioso del balanceo | C60: =1-C59 -> 0.56639497
A62: N° | B62: Puesto | C62: Recurso | D62: Tiempo (min/u) | E62: Unidades del año | F62: Horas de trabajo | G62: Máq. | H62: Turnos | I62: Recursos | J62: Aprovechamiento | K62: Cuello
A63: 1 | B63: Recepción de materia prima | C63: Manual | D63: =Links!$B$1135 -> 1.7825 | E63: =IF(D63=0,0,F63*60/D63) -> 3107.3221 | F63: =INDEX(Links!$B$1158:$B$1356,(Resumen!$C$3-2026)*20+2) -> 92.313362 | G63: =INDEX(Links!$B$1380:$K$1380,1,(Resumen!$C$3-2025)) -> 1 | H63: =INDEX(Links!$B$1401:$K$1401,1,(Resumen!$C$3-2025)) -> 1 | I63: =G63*H63 -> 1 | J63: =INDEX(Links!$B$1359:$K$1359,1,(Resumen!$C$3-2025)) -> 0.10349913 | K63: =IF(J63=MAX($J$63:$J$80),"◀ cuello","")
A64: 2 | B64: Corte de chapa (guillotina) | C64: Máquina | D64: =Links!$B$1136 -> 3.6621941 | E64: =IF(D64=0,0,F64*60/D64) -> 3107.8026 | F64: =INDEX(Links!$B$1158:$B$1356,(Resumen!$C$3-2026)*20+3) -> 189.68961 | G64: =INDEX(Links!$B$1381:$K$1381,1,(Resumen!$C$3-2025)) -> 1 | H64: =INDEX(Links!$B$1402:$K$1402,1,(Resumen!$C$3-2025)) -> 1 | I64: =G64*H64 -> 1 | J64: =INDEX(Links!$B$1360:$K$1360,1,(Resumen!$C$3-2025)) -> 0.17603599 | K64: =IF(J64=MAX($J$63:$J$80),"◀ cuello","")
A65: 3 | B65: Marcado del cuerpo | C65: Máquina | D65: =Links!$B$1137 -> 1.5599613 | E65: =IF(D65=0,0,F65*60/D65) -> 3107.4208 | F65: =INDEX(Links!$B$1158:$B$1356,(Resumen!$C$3-2026)*20+4) -> 80.790935 | G65: =INDEX(Links!$B$1382:$K$1382,1,(Resumen!$C$3-2025)) -> 1 | H65: =INDEX(Links!$B$1403:$K$1403,1,(Resumen!$C$3-2025)) -> 1 | I65: =G65*H65 -> 1 | J65: =INDEX(Links!$B$1361:$K$1361,1,(Resumen!$C$3-2025)) -> 0.060696783 | K65: =IF(J65=MAX($J$63:$J$80),"◀ cuello","")
A66: 4 | B66: Cilindrado | C66: Máquina | D66: =Links!$B$1138 -> 3.3381707 | E66: =IF(D66=0,0,F66*60/D66) -> 3107.7034 | F66: =INDEX(Links!$B$1158:$B$1356,(Resumen!$C$3-2026)*20+5) -> 172.90074 | G66: =INDEX(Links!$B$1383:$K$1383,1,(Resumen!$C$3-2025)) -> 1 | H66: =INDEX(Links!$B$1404:$K$1404,1,(Resumen!$C$3-2025)) -> 1 | I66: =G66*H66 -> 1 | J66: =INDEX(Links!$B$1362:$K$1362,1,(Resumen!$C$3-2025)) -> 0.14374045 | K66: =IF(J66=MAX($J$63:$J$80),"◀ cuello","")
A67: 5 | B67: Punteo del cuerpo | C67: Manual | D67: =Links!$B$1139 -> 4.9485072 | E67: =IF(D67=0,0,F67*60/D67) -> 3108.1866 | F67: =INDEX(Links!$B$1158:$B$1356,(Resumen!$C$3-2026)*20+6) -> 256.34806 | G67: =INDEX(Links!$B$1384:$K$1384,1,(Resumen!$C$3-2025)) -> 1 | H67: =INDEX(Links!$B$1405:$K$1405,1,(Resumen!$C$3-2025)) -> 1 | I67: =G67*H67 -> 1 | J67: =INDEX(Links!$B$1363:$K$1363,1,(Resumen!$C$3-2025)) -> 0.16491995 | K67: =IF(J67=MAX($J$63:$J$80),"◀ cuello","")
A68: 6 | B68: Soldadura longitudinal | C68: Máquina | D68: =Links!$B$1140 -> 3.4006816 | E68: =IF(D68=0,0,F68*60/D68) -> 3107.356 | F68: =INDEX(Links!$B$1158:$B$1356,(Resumen!$C$3-2026)*20+7) -> 176.11881 | G68: =INDEX(Links!$B$1385:$K$1385,1,(Resumen!$C$3-2025)) -> 1 | H68: =INDEX(Links!$B$1406:$K$1406,1,(Resumen!$C$3-2025)) -> 1 | I68: =G68*H68 -> 1 | J68: =INDEX(Links!$B$1364:$K$1364,1,(Resumen!$C$3-2025)) -> 0.12344906 | K68: =IF(J68=MAX($J$63:$J$80),"◀ cuello","")
A69: 7 | B69: Soldadura de cupla en la cúpula | C69: Máquina | D69: =Links!$B$1141 -> 3.3598968 | E69: =IF(D69=0,0,F69*60/D69) -> 3107.4443 | F69: =INDEX(Links!$B$1158:$B$1356,(Resumen!$C$3-2026)*20+8) -> 174.01153 | G69: =INDEX(Links!$B$1386:$K$1386,1,(Resumen!$C$3-2025)) -> 1 | H69: =INDEX(Links!$B$1407:$K$1407,1,(Resumen!$C$3-2025)) -> 1 | I69: =G69*H69 -> 1 | J69: =INDEX(Links!$B$1365:$K$1365,1,(Resumen!$C$3-2025)) -> 0.12440692 | K69: =IF(J69=MAX($J$63:$J$80),"◀ cuello","")
A70: 8 | B70: Armado y soldadura circunferencial | C70: Máquina | D70: =Links!$B$1142 -> 15.88941 | E70: =IF(D70=0,0,F70*60/D70) -> 3107.4491 | F70: =INDEX(Links!$B$1158:$B$1356,(Resumen!$C$3-2026)*20+9) -> 822.92552 | G70: =INDEX(Links!$B$1387:$K$1387,1,(Resumen!$C$3-2025)) -> 1 | H70: =INDEX(Links!$B$1408:$K$1408,1,(Resumen!$C$3-2025)) -> 1 | I70: =G70*H70 -> 1 | J70: =INDEX(Links!$B$1366:$K$1366,1,(Resumen!$C$3-2025)) -> 0.51375531 | K70: =IF(J70=MAX($J$63:$J$80),"◀ cuello","")
A71: 9 | B71: Soldadura de accesorios | C71: Manual | D71: =Links!$B$1143 -> 16.189765 | E71: =IF(D71=0,0,F71*60/D71) -> 3107.3732 | F71: =INDEX(Links!$B$1158:$B$1356,(Resumen!$C$3-2026)*20+10) -> 838.46066 | G71: =INDEX(Links!$B$1388:$K$1388,1,(Resumen!$C$3-2025)) -> 1 | H71: =INDEX(Links!$B$1409:$K$1409,1,(Resumen!$C$3-2025)) -> 1 | I71: =G71*H71 -> 1 | J71: =INDEX(Links!$B$1367:$K$1367,1,(Resumen!$C$3-2025)) -> 0.5230764 | K71: =IF(J71=MAX($J$63:$J$80),"◀ cuello","") -> ◀ cuello
A72: 10 | B72: Fabricación de accesorios | C72: Manual | D72: =Links!$B$1144 -> 11 | E72: =IF(D72=0,0,F72*60/D72) -> 3107.3221 | F72: =INDEX(Links!$B$1158:$B$1356,(Resumen!$C$3-2026)*20+11) -> 569.67572 | G72: =INDEX(Links!$B$1389:$K$1389,1,(Resumen!$C$3-2025)) -> 1 | H72: =INDEX(Links!$B$1410:$K$1410,1,(Resumen!$C$3-2025)) -> 1 | I72: =G72*H72 -> 1 | J72: =INDEX(Links!$B$1368:$K$1368,1,(Resumen!$C$3-2025)) -> 0.37513877 | K72: =IF(J72=MAX($J$63:$J$80),"◀ cuello","")
A73: 11 | B73: Prueba hidráulica | C73: Máquina | D73: =Links!$B$1145 -> 8.9799355 | E73: =IF(D73=0,0,F73*60/D73) -> 3107.3017 | F73: =INDEX(Links!$B$1158:$B$1356,(Resumen!$C$3-2026)*20+12) -> 465.05615 | G73: =INDEX(Links!$B$1390:$K$1390,1,(Resumen!$C$3-2025)) -> 1 | H73: =INDEX(Links!$B$1411:$K$1411,1,(Resumen!$C$3-2025)) -> 1 | I73: =G73*H73 -> 1 | J73: =INDEX(Links!$B$1369:$K$1369,1,(Resumen!$C$3-2025)) -> 0.30125591 | K73: =IF(J73=MAX($J$63:$J$80),"◀ cuello","")
A74: 12 | B74: Secado | C74: Máquina | D74: =Links!$B$1146 -> 10.058961 | E74: =IF(D74=0,0,F74*60/D74) -> 3107.3433 | F74: =INDEX(Links!$B$1158:$B$1356,(Resumen!$C$3-2026)*20+13) -> 520.9441 | G74: =INDEX(Links!$B$1391:$K$1391,1,(Resumen!$C$3-2025)) -> 1 | H74: =INDEX(Links!$B$1412:$K$1412,1,(Resumen!$C$3-2025)) -> 1 | I74: =G74*H74 -> 1 | J74: =INDEX(Links!$B$1370:$K$1370,1,(Resumen!$C$3-2025)) -> 0.31256646 | K74: =IF(J74=MAX($J$63:$J$80),"◀ cuello","")
A75: 13 | B75: Pulmón de despacho y carga a pintura | C75: Manual | D75: =Links!$B$1147 -> 1.5999032 | E75: =IF(D75=0,0,F75*60/D75) -> 3107.5626 | F75: =INDEX(Links!$B$1158:$B$1356,(Resumen!$C$3-2026)*20+14) -> 82.863324 | G75: =INDEX(Links!$B$1392:$K$1392,1,(Resumen!$C$3-2025)) -> 1 | H75: =INDEX(Links!$B$1413:$K$1413,1,(Resumen!$C$3-2025)) -> 1 | I75: =G75*H75 -> 1 | J75: =INDEX(Links!$B$1371:$K$1371,1,(Resumen!$C$3-2025)) -> 0.058606883 | K75: =IF(J75=MAX($J$63:$J$80),"◀ cuello","")
A76: 14 | B76: Recepción de pintados y cambio de juego | C76: Manual | D76: =Links!$B$1148 -> 3.1298839 | E76: =IF(D76=0,0,F76*60/D76) -> 3107.4696 | F76: =INDEX(Links!$B$1158:$B$1356,(Resumen!$C$3-2026)*20+15) -> 162.10032 | G76: =INDEX(Links!$B$1393:$K$1393,1,(Resumen!$C$3-2025)) -> 1 | H76: =INDEX(Links!$B$1414:$K$1414,1,(Resumen!$C$3-2025)) -> 1 | I76: =G76*H76 -> 1 | J76: =INDEX(Links!$B$1372:$K$1372,1,(Resumen!$C$3-2025)) -> 0.10614908 | K76: =IF(J76=MAX($J$63:$J$80),"◀ cuello","")
A77: 15 | B77: Carga de polvo y presurización | C77: Máquina | D77: =Links!$B$1149 -> 11.33 | E77: =IF(D77=0,0,F77*60/D77) -> 1814.7097 | F77: =INDEX(Links!$B$1158:$B$1356,(Resumen!$C$3-2026)*20+16) -> 342.67768 | G77: =INDEX(Links!$B$1394:$K$1394,1,(Resumen!$C$3-2025)) -> 1 | H77: =INDEX(Links!$B$1415:$K$1415,1,(Resumen!$C$3-2025)) -> 1 | I77: =G77*H77 -> 1 | J77: =INDEX(Links!$B$1373:$K$1373,1,(Resumen!$C$3-2025)) -> 0.31227327 | K77: =IF(J77=MAX($J$63:$J$80),"◀ cuello","")
A78: 16 | B78: Montaje, manga, precinto y etiquetado | C78: Manual | D78: =Links!$B$1150 -> 6.32 | E78: =IF(D78=0,0,F78*60/D78) -> 1814.6961 | F78: =INDEX(Links!$B$1158:$B$1356,(Resumen!$C$3-2026)*20+17) -> 191.14798 | G78: =INDEX(Links!$B$1395:$K$1395,1,(Resumen!$C$3-2025)) -> 1 | H78: =INDEX(Links!$B$1416:$K$1416,1,(Resumen!$C$3-2025)) -> 1 | I78: =G78*H78 -> 1 | J78: =INDEX(Links!$B$1374:$K$1374,1,(Resumen!$C$3-2025)) -> 0.16135546 | K78: =IF(J78=MAX($J$63:$J$80),"◀ cuello","")
A79: 17 | B79: Calidad: pérdidas, inspección final, liberación y ensayos de lote | C79: Manual | D79: =Links!$B$1151 -> 4.79 | E79: =IF(D79=0,0,F79*60/D79) -> 1814.6821 | F79: =INDEX(Links!$B$1158:$B$1356,(Resumen!$C$3-2026)*20+18) -> 144.87212 | G79: =INDEX(Links!$B$1396:$K$1396,1,(Resumen!$C$3-2025)) -> 1 | H79: =INDEX(Links!$B$1417:$K$1417,1,(Resumen!$C$3-2025)) -> 1 | I79: =G79*H79 -> 1 | J79: =INDEX(Links!$B$1375:$K$1375,1,(Resumen!$C$3-2025)) -> 0.4571455 | K79: =IF(J79=MAX($J$63:$J$80),"◀ cuello","")
A80: 18 | B80: Depósito de producto terminado y despacho | C80: Manual | D80: =Links!$B$1152 -> 1.3598968 | E80: =IF(D80=0,0,F80*60/D80) -> 3107.6239 | F80: =INDEX(Links!$B$1158:$B$1356,(Resumen!$C$3-2026)*20+19) -> 70.434128 | G80: =INDEX(Links!$B$1397:$K$1397,1,(Resumen!$C$3-2025)) -> 1 | H80: =INDEX(Links!$B$1418:$K$1418,1,(Resumen!$C$3-2025)) -> 1 | I80: =G80*H80 -> 1 | J80: =INDEX(Links!$B$1376:$K$1376,1,(Resumen!$C$3-2025)) -> 0.064482699 | K80: =IF(J80=MAX($J$63:$J$80),"◀ cuello","")
B81: Total | F81: =SUM(F63:F80) -> 5353.3308 | I81: =SUM(I63:I80) -> 18
A84: LÍNEA DE RECARGAS
B85: Unidades del año (recipientes / recargas) | C85: =SUM(Resumen!$D$23:$D$39) -> 107927.37
B86: Unidades del mes pico | C86: =MAX(INDEX(Links!$B$1440:$M$1757,(Resumen!$C$3-2026)*32+19,0)) -> 11106.787
B87: Horas productivas por mes (1 turno) | C87: =Links!$B$1785 -> 150
B88: Takt del mes pico, 1 turno (s/u) | C88: =IF(C86=0,0,C87*3600/C86) -> 48.618919
B89: Contenido de trabajo por unidad (s/u) | C89: =IF(C85=0,0,F122*3600/C85) -> 1184.2015
B90: Recursos-turno mínimos teóricos (contenido / takt) | C90: =IF(C88=0,0,C89/C88) -> 24.356804
B91: Recursos-turno instalados (máquinas × turnos) | C91: =I122 -> 47
B92: Aprovechamiento medio (ponderado por recursos) | C92: =IF(I122=0,0,SUMPRODUCT(J99:J121,I99:I121)/I122) -> 0.51630945
B93: Cuello de botella | C93: =INDEX(B99:B121,MATCH(MAX(J99:J121),J99:J121,0)) -> Ensayo de pérdidas
B94: Aprovechamiento del cuello de botella | C94: =MAX(J99:J121) -> 0.87268181
B95: Eficiencia de balanceo (medio / cuello) | C95: =IF(C94=0,0,C92/C94) -> 0.5916354
B96: Tiempo ocioso del balanceo | C96: =1-C95 -> 0.4083646
A98: N° | B98: Puesto | C98: Recurso | D98: Tiempo (s/u) | E98: Unidades del año | F98: Horas de trabajo | G98: Máq. | H98: Turnos | I98: Recursos | J98: Aprovechamiento | K98: Cuello
A99: 1 | B99: Recepción y registro | C99: Manual | D99: =Links!$B$1760 -> 75 | E99: =INDEX(Links!$B$1788:$B$2099,(Resumen!$C$3-2026)*32+2) -> 115782.99 | F99: =E99*D99/3600 -> 2412.1457 | G99: =INDEX(Links!$B$2134:$K$2134,1,(Resumen!$C$3-2025)) -> 2 | H99: =INDEX(Links!$B$2166:$K$2166,1,(Resumen!$C$3-2025)) -> 1 | I99: =G99*H99 -> 2 | J99: =INDEX(Links!$B$2102:$K$2102,1,(Resumen!$C$3-2025)) -> 0.81813919 | K99: =IF(J99=MAX($J$99:$J$121),"◀ cuello","")
A100: 2 | B100: Inspección visual | C100: Manual | D100: =Links!$B$1761 -> 90 | E100: =INDEX(Links!$B$1788:$B$2099,(Resumen!$C$3-2026)*32+3) -> 115782.99 | F100: =E100*D100/3600 -> 2894.5748 | G100: =INDEX(Links!$B$2135:$K$2135,1,(Resumen!$C$3-2025)) -> 2 | H100: =INDEX(Links!$B$2167:$K$2167,1,(Resumen!$C$3-2025)) -> 2 | I100: =G100*H100 -> 4 | J100: =INDEX(Links!$B$2103:$K$2103,1,(Resumen!$C$3-2025)) -> 0.49088352 | K100: =IF(J100=MAX($J$99:$J$121),"◀ cuello","")
A101: 3 | B101: Descarga ABC — ruta recuperable | C101: Máquina | D101: =Links!$B$1762 -> 85 | E101: =INDEX(Links!$B$1788:$B$2099,(Resumen!$C$3-2026)*32+4) -> 85936.691 | F101: =E101*D101/3600 -> 2029.0607 | G101: =INDEX(Links!$B$2136:$K$2136,1,(Resumen!$C$3-2025)) -> 1 | H101: =INDEX(Links!$B$2168:$K$2168,1,(Resumen!$C$3-2025)) -> 2 | I101: =G101*H101 -> 2 | J101: =INDEX(Links!$B$2104:$K$2104,1,(Resumen!$C$3-2025)) -> 0.7069479 | K101: =IF(J101=MAX($J$99:$J$121),"◀ cuello","")
A102: 4 | B102: Descarga a descarte (ABC, BC y Clase D) | C102: Máquina | D102: =Links!$B$1763 -> 85 | E102: =INDEX(Links!$B$1788:$B$2099,(Resumen!$C$3-2026)*32+5) -> 9804.2853 | F102: =E102*D102/3600 -> 231.49007 | G102: =INDEX(Links!$B$2137:$K$2137,1,(Resumen!$C$3-2025)) -> 1 | H102: =INDEX(Links!$B$2169:$K$2169,1,(Resumen!$C$3-2025)) -> 1 | I102: =G102*H102 -> 1 | J102: =INDEX(Links!$B$2105:$K$2105,1,(Resumen!$C$3-2025)) -> 0.16045446 | K102: =IF(J102=MAX($J$99:$J$121),"◀ cuello","")
A103: 5 | B103: Descarga y carga de agua / AFFF / sales K | C103: Máquina | D103: =Links!$B$1764 -> 205 | E103: =INDEX(Links!$B$1788:$B$2099,(Resumen!$C$3-2026)*32+6) -> 5425.4576 | F103: =E103*D103/3600 -> 308.94967 | G103: =INDEX(Links!$B$2138:$K$2138,1,(Resumen!$C$3-2025)) -> 1 | H103: =INDEX(Links!$B$2170:$K$2170,1,(Resumen!$C$3-2025)) -> 1 | I103: =G103*H103 -> 1 | J103: =INDEX(Links!$B$2106:$K$2106,1,(Resumen!$C$3-2025)) -> 0.19268982 | K103: =IF(J103=MAX($J$99:$J$121),"◀ cuello","")
A104: 6 | B104: Recuperación y carga de CO₂ | C104: Máquina | D104: =Links!$B$1765 -> 240 | E104: =INDEX(Links!$B$1788:$B$2099,(Resumen!$C$3-2026)*32+7) -> 5407.3796 | F104: =E104*D104/3600 -> 360.49198 | G104: =INDEX(Links!$B$2139:$K$2139,1,(Resumen!$C$3-2025)) -> 1 | H104: =INDEX(Links!$B$2171:$K$2171,1,(Resumen!$C$3-2025)) -> 1 | I104: =G104*H104 -> 1 | J104: =INDEX(Links!$B$2107:$K$2107,1,(Resumen!$C$3-2025)) -> 0.24142776 | K104: =IF(J104=MAX($J$99:$J$121),"◀ cuello","")
A105: 7 | B105: Recuperación y carga de halogenado | C105: Máquina | D105: =Links!$B$1766 -> 895 | E105: =INDEX(Links!$B$1788:$B$2099,(Resumen!$C$3-2026)*32+8) -> 130.41695 | F105: =E105*D105/3600 -> 32.423103 | G105: =INDEX(Links!$B$2140:$K$2140,1,(Resumen!$C$3-2025)) -> 1 | H105: =INDEX(Links!$B$2172:$K$2172,1,(Resumen!$C$3-2025)) -> 1 | I105: =G105*H105 -> 1 | J105: =INDEX(Links!$B$2108:$K$2108,1,(Resumen!$C$3-2025)) -> 0.019639009 | K105: =IF(J105=MAX($J$99:$J$121),"◀ cuello","")
A106: 8 | B106: Desarme y limpieza — recinto | C106: Manual | D106: =Links!$B$1767 -> 105 | E106: =INDEX(Links!$B$1788:$B$2099,(Resumen!$C$3-2026)*32+9) -> 100779.97 | F106: =E106*D106/3600 -> 2939.4159 | G106: =INDEX(Links!$B$2141:$K$2141,1,(Resumen!$C$3-2025)) -> 2 | H106: =INDEX(Links!$B$2173:$K$2173,1,(Resumen!$C$3-2025)) -> 2 | I106: =G106*H106 -> 4 | J106: =INDEX(Links!$B$2109:$K$2109,1,(Resumen!$C$3-2025)) -> 0.51178569 | K106: =IF(J106=MAX($J$99:$J$121),"◀ cuello","")
A107: 9 | B107: Desarme e inspección interior — zona general | C107: Manual | D107: =Links!$B$1768 -> 176 | E107: =INDEX(Links!$B$1788:$B$2099,(Resumen!$C$3-2026)*32+10) -> 8517.2417 | F107: =E107*D107/3600 -> 416.39848 | G107: =INDEX(Links!$B$2142:$K$2142,1,(Resumen!$C$3-2025)) -> 1 | H107: =INDEX(Links!$B$2174:$K$2174,1,(Resumen!$C$3-2025)) -> 1 | I107: =G107*H107 -> 1 | J107: =INDEX(Links!$B$2110:$K$2110,1,(Resumen!$C$3-2025)) -> 0.26529125 | K107: =IF(J107=MAX($J$99:$J$121),"◀ cuello","")
A108: 10 | B108: Laboratorio — Puffer y mufla | C108: Máquina | D108: =Links!$B$1769 -> 3180 | E108: =INDEX(Links!$B$1788:$B$2099,(Resumen!$C$3-2026)*32+11) -> 1045.9945 | F108: =E108*D108/3600 -> 923.96177 | G108: =INDEX(Links!$B$2143:$K$2143,1,(Resumen!$C$3-2025)) -> 1 | H108: =INDEX(Links!$B$2175:$K$2175,1,(Resumen!$C$3-2025)) -> 1 | I108: =G108*H108 -> 1 | J108: =INDEX(Links!$B$2111:$K$2111,1,(Resumen!$C$3-2025)) -> 0.64383763 | K108: =IF(J108=MAX($J$99:$J$121),"◀ cuello","")
...
