Workbook

Sheet Resumen
A1: Corte de chapa: comparación de alternativas 2026-2035
A2: Cuerpos de 1 a 100 kg, cúpulas y fondos de 1 a 10 kg. Valor actual = inversión + costos de 10 años descontados. Menor es mejor.
A4: Indicador | B4: A: bobina por formato + fleje | C4: B: hojas para todo | D4: C: bobina madre propia | E4: D: hojas + fleje | F4: Referencia: cuerpos a medida
A5: Cuerpos: se compra | B5: Bobina de ancho estándar por formato, línea de corte transversal | C5: Hojas estándar, dos guillotinas en serie | D5: Bobina madre por espesor, cortada en flejes propios | E5: Hojas estándar, dos guillotinas en serie | F5: Cuerpos comprados cortados a medida
A6: Cúpulas y fondos: se compra | B6: Fleje a medida por disco | C6: Tiras de hoja cargadas a mano | D6: Flejes propios de la bobina madre | E6: Fleje a medida por disco | F6: Fleje a medida por disco
A7: Inversión en equipos (USD) | B7: =Datos!$C$112 -> 167800 | C7: =Datos!$D$112 -> 79500 | D7: =Datos!$E$112 -> 191000 | E7: =Datos!$F$112 -> 93000 | F7: =Datos!$G$112 -> 15000
A8: Acero comprado 2026-2035 (t) | B8: =SUM(Cálculo!$C$32:$L$32) -> 1818.7749 | C8: =SUM(Cálculo!$C$58:$L$58) -> 1931.7673 | D8: =SUM(Cálculo!$C$82:$L$82) -> 1835.2968 | E8: =SUM(Cálculo!$C$96:$L$96) -> 1889.6979 | F8: =SUM(Cálculo!$C$110:$L$110) -> 1761.4191
A9: Aprovechamiento de chapa 2026-2035 | B9: =SUM(Cálculo!$C$25:$L$25)/B8 -> 0.90524548 | C9: =SUM(Cálculo!$C$25:$L$25)/C8 -> 0.85229613 | D9: =SUM(Cálculo!$C$25:$L$25)/D8 -> 0.89709617 | E9: =SUM(Cálculo!$C$25:$L$25)/E8 -> 0.87127038 | F9: =SUM(Cálculo!$C$25:$L$25)/F8 -> 0.93472235
A10: Horas-hombre de corte en el año de referencia | B10: =INDEX(Cálculo!$C$41:$L$41,Datos!$B$6-2025) -> 558.01462 | C10: =INDEX(Cálculo!$C$64:$L$64,Datos!$B$6-2025) -> 301.50285 | D10: =INDEX(Cálculo!$C$90:$L$90,Datos!$B$6-2025) -> 406.12929 | E10: =INDEX(Cálculo!$C$102:$L$102,Datos!$B$6-2025) -> 118.26219 | F10: =INDEX(Cálculo!$C$116:$L$116,Datos!$B$6-2025) -> 20.15545
A11: Costo anual en el año de referencia (USD) | B11: =INDEX(Cálculo!$C$44:$L$44,Datos!$B$6-2025) -> 512740.56 | C11: =INDEX(Cálculo!$C$67:$L$67,Datos!$B$6-2025) -> 566169.1 | D11: =INDEX(Cálculo!$C$93:$L$93,Datos!$B$6-2025) -> 523613.79 | E11: =INDEX(Cálculo!$C$105:$L$105,Datos!$B$6-2025) -> 542274.01 | F11: =INDEX(Cálculo!$C$119:$L$119,Datos!$B$6-2025) -> 539391.98
A12: Valor actual a 10 años (USD) | B12: =B7+SUMPRODUCT(Cálculo!$C$44:$L$44,Cálculo!$C$6:$L$6) -> 1151597 | C12: =C7+SUMPRODUCT(Cálculo!$C$67:$L$67,Cálculo!$C$6:$L$6) -> 1150161.1 | D12: =D7+SUMPRODUCT(Cálculo!$C$93:$L$93,Cálculo!$C$6:$L$6) -> 1203055.3 | E12: =E7+SUMPRODUCT(Cálculo!$C$105:$L$105,Cálculo!$C$6:$L$6) -> 1121061.7 | F12: =F7+SUMPRODUCT(Cálculo!$C$119:$L$119,Cálculo!$C$6:$L$6) -> 1029277.7
A13: Ranking (1 = conviene; la referencia no corta en planta) | B13: =RANK(B12,$B$12:$E$12,1) -> 3 | C13: =RANK(C12,$B$12:$E$12,1) -> 2 | D13: =RANK(D12,$B$12:$E$12,1) -> 4 | E13: =RANK(E12,$B$12:$E$12,1) -> 1 | F13: —
A14: Diferencia contra la que conviene (USD) | B14: =B12-MIN($B$12:$E$12) -> 30535.286 | C14: =C12-MIN($B$12:$E$12) -> 29099.411 | D14: =D12-MIN($B$12:$E$12) -> 81993.62 | E14: =E12-MIN($B$12:$E$12) -> 0 | F14: =F12-MIN($B$12:$E$12) -> -91783.991
A16: Conviene (de las que cortan en planta) | B16: =INDEX({"A: bobina por formato + fleje","B: hojas para todo","C: bobina madre propia","D: hojas + fleje"},MATCH(MIN($B$12:$E$12),$B$12:$E$12,0)) -> D: hojas + fleje
A17: Margen de D: suba del precio de la hoja que la iguala con A | B17: =($B$12-$E$12)/SUMPRODUCT(Cálculo!$C$52:$L$52,Cálculo!$C$6:$L$6) -> 0.038134177
A18: Margen de D: suba del precio del fleje que la iguala con B | B18: =($C$12-$E$12)/SUMPRODUCT(Cálculo!$C$31:$L$31,Cálculo!$C$6:$L$6) -> 0.12894913
A20: Datos editables en la hoja Datos (gris claro). Demanda por IMPORTRANGE (hoja Links). Medidas de cuerpos y discos del plano (hoja Piezas).

Sheet Datos
A1: Datos
A2: Gris claro: dato editable. Todo lo demás del libro sale de acá, de Demanda y de Piezas.
A4: 1. Generales
A5: Concepto | B5: Valor | C5: Unidad | D5: Fuente o criterio
A6: Año de referencia | B6: 2035 | C6: año | D6: Año de diseño del proyecto (Proyecciones).
A7: Tasa de descuento anual en USD | B7: 0.12 | C7: % | D7: Evaluación económica del Excel V2 (12 % real).
A8: Mantenimiento anual de equipos | B8: 0.03 | C8: % de la inversión | D8: Criterio del grupo.
A9: Precio de venta del scrap | B9: 250 | C9: USD/t | D9: Reaquila (mar-2026): acero reciclado $300-1.200/kg con dólar ~$1.480.
A10: Densidad del acero SAE 1010 | B10: 7.87 | C10: g/cm³ | D10: Planilla «Dimensiones de chapa».
A11: Costo mensual de un operario con cargas | B11: 1337922 | C11: ARS/mes | D11: Planilla «Costo oportunidad operario-máquina», CCT 260/75, ago-2026.
A12: Horas por mes | B12: 150 | C12: h/mes | D12: Excel V2.
A13: Horas productivas por operario y año | B13: 1800 | C13: h/año | D13: Excel V2 (150 h × 12).
A14: Tipo de cambio | B14: 1420 | C14: ARS/USD | D14: Valor fijo del proyecto (criterio del grupo).
A15: Costo hora de operario | B15: =Datos!$B$11/Datos!$B$12/Datos!$B$14 -> 6.2813239 | C15: USD/h | D15: Cálculo.
A17: 2. Corte y puentes
A18: Concepto | B18: Valor | C18: Unidad | D18: Fuente o criterio
A19: Margen mínimo de borde a lo ancho de una bobina | B19: 10 | C19: mm | D19: Criterio del grupo: bordes de laminación y tolerancia de ancho.
A20: Despunte de cabeza y cola de bobina | B20: 0.005 | C20: % | D20: Criterio del grupo.
A21: Puente de avance entre discos | B21: 1.5 | C21: × espesor | D21: MISUMI, Press Dies Tutorial: 1,5 veces el espesor, mínimo 0,7 mm.
A22: Puente mínimo entre discos | B22: 0.7 | C22: mm | D22: MISUMI.
A23: Puente al borde del fleje | B23: 1.5 | C23: × puente de avance | D23: MISUMI: 1,5 veces el de avance (la guía del fleje deja juego).
A24: ¿Mezclar 70 y 100 kg en la misma hoja? | B24: SI | C24: SI/NO | D24: Proceso de carros: la hoja mixta lleva 1 cuerpo de 100 kg y 3 de 70 kg.
A25: Cuerpos de 100 kg por hoja mixta | B25: 1 | C25: u | D25: Proceso de carros.
A26: Cuerpos de 70 kg por hoja mixta | B26: 3 | C26: u | D26: Proceso de carros.
A28: 3. Máquinas
A29: Concepto | B29: Valor | C29: Unidad | D29: Fuente o criterio
A30: Guillotina 1 (franjas) CENA 8 × 3200: golpes por minuto | B30: 10 | C30: golpes/min | D30: Cotización CENA (Drive).
A31: Guillotina 1: largo de corte | B31: 3200 | C31: mm | D31: Cotización CENA.
A32: Guillotina 1: recorrido del tope trasero | B32: 1000 | C32: mm | D32: Cotización CENA: 20 a 1.000 mm.
A33: Guillotina 2 (piezas) QC12Y 6 × 2500: golpes por minuto | B33: 20 | C33: golpes/min | D33: Confirmado por el grupo (igual que la HG 6 × 2500 de la ficha Molinari Panther).
A34: Guillotina 2: largo de corte para franjas en paralelo | B34: 2500 | C34: mm | D34: Publicación Alibaba 1600900259147: 6 × 2500, cuchilla de 2.550 mm.
A35: Guillotina 2: recorrido del tope trasero | B35: 800 | C35: mm | D35: Publicación Alibaba 1600900259147: 20 a 800 mm.
A36: Línea de corte transversal (A y C): golpes por hora | B36: 1200 | C36: golpes/h | D36: Criterio del grupo: 20 golpes por minuto.
A37: Cortadora longitudinal (C): velocidad efectiva | B37: 40 | C37: m/min | D37: Criterio del grupo (máquinas de 60 a 120 m/min nominales).
A38: Cortadora: armado de cuchillas por bobina madre | B38: 45 | C38: min | D38: Criterio del grupo.
A39: Operarios en la cortadora | B39: 2 | C39: personas | D39: Criterio del grupo.
A40: Carga manual de una tira en el balancín (B) | B40: 15 | C40: s/tira | D40: Criterio del grupo.
A41: Cambio de fleje en el desbobinador de la prensa | B41: 15 | C41: min/fleje | D41: Criterio del grupo.
A43: 4. Compras y stock
A44: Concepto | B44: Valor | C44: Unidad | D44: Fuente o criterio
A45: Stock de seguridad | B45: 2 | C45: semanas | D45: Criterio del grupo.
A46: Lote de compra de hojas y de chapa a medida | B46: 1 | C46: meses | D46: Criterio del grupo: compra mensual.
A47: Cobertura objetivo de un rollo o bobina | B47: 1 | C47: meses | D47: Criterio del grupo.
A48: Cobertura máxima de stock por rollo | B48: 3 | C48: meses | D48: Criterio del grupo.
A49: Peso mínimo de rollo | B49: 0.5 | C49: t | D49: Criterio del grupo.
A50: Diámetro exterior máximo de bobina | B50: 1500 | C50: mm | D50: Criterio del grupo.
A51: Diámetro interior de bobina | B51: 508 | C51: mm | D51: Estándar de mercado.
A52: Peso máximo de bobina por mm de ancho | B52: =PI()/4*(Datos!$B$50^2-Datos!$B$51^2)*Datos!$B$10/1000000000 -> 0.012312323 | C52: t/mm | D52: Cálculo con el diámetro exterior máximo.
A53: Desbobinador de la línea de corte transversal | B53: 10 | C53: t | D53: A especificar al comprar.
A54: Desbobinador de fleje de la prensa | B54: 3 | C54: t | D54: A especificar al comprar.
A55: Desbobinador de la cortadora longitudinal | B55: 14 | C55: t | D55: Pradecon: la bobina madre pesa 13-14 t.
A56: Precio de la bobina madre sobre la flejada | B56: 0 | C56: % | D56: Pradecon (mail 28/09/2026): no cobra el flejado.
A57: ¿El puente grúa ya está en el layout por otro motivo? | B57: NO | C57: SI/NO | D57: Si es SI, no se carga a A ni a C.
A59: 5. Cotizaciones de acero recibidas (sin IVA)
A60: Cotización | B60: Id | C60: Espesor (mm) | D60: Moneda | E60: Precio por kg | F60: TC | G60: USD/kg | H60: Formato | I60: Producto y nota
A61: Pradecon 173170 | B61: Q1 | C61: 0.9 | D61: USD | E61: 1.26285 | F61: 1545 | G61: =IF(D61="USD",E61,E61/F61) -> 1.26285 | H61: Ancho 1.220 | I61: Bobina LAF flejada. Flejado sin cargo.
A62: Pradecon 173170 | B62: Q2 | C62: 1.25 | D62: USD | E62: 1.25056 | F62: 1545 | G62: =IF(D62="USD",E62,E62/F62) -> 1.25056 | H62: Ancho 1.220 | I62: Bobina LAF flejada.
A63: Pradecon 173170 | B63: Q3 | C63: 1.6 | D63: USD | E63: 1.25056 | F63: 1545 | G63: =IF(D63="USD",E63,E63/F63) -> 1.25056 | H63: Ancho 1.220 o 1.000 | I63: Bobina LAF flejada.
A64: Pradecon 173170 | B64: Q4 | C64: 2 | D64: USD | E64: 1.26285 | F64: 1545 | G64: =IF(D64="USD",E64,E64/F64) -> 1.26285 | H64: Ancho 1.220 o 1.000 | I64: Bobina LAF flejada.
A65: Pradecon 173170 | B65: Q5 | C65: 3.2 | D65: USD | E65: 1.11373 | F65: 1545 | G65: =IF(D65="USD",E65,E65/F65) -> 1.11373 | H65: Ancho 1.245 o 1.500 | I65: Bobina LAC flejada.
A66: Pradecon 173170 | B66: Q6 | C66: 4.75 | D66: USD | E66: 1.05792 | F66: 1545 | G66: =IF(D66="USD",E66,E66/F66) -> 1.05792 | H66: 1500 × 3000 | I66: Hoja LAC. Mismo producto que Q11.
A67: Pradecon 173195 | B67: Q7 | C67: 1.6 | D67: ARS | E67: 2051.02 | F67: 1545 | G67: =IF(D67="USD",E67,E67/F67) -> 1.327521 | H67: 1000 × 2000 | I67: Hoja LAF C16.
A68: Pradecon 173195 | B68: Q8 | C68: 1.25 | D68: ARS | E68: 1993.51 | F68: 1545 | G68: =IF(D68="USD",E68,E68/F68) -> 1.2902977 | H68: 1220 × 2440 | I68: Hoja LAF C18.
A69: Pradecon 173195 | B69: Q9 | C69: 2 | D69: ARS | E69: 1978.22 | F69: 1545 | G69: =IF(D69="USD",E69,E69/F69) -> 1.2804013 | H69: 1500 × 3000 | I69: Hoja LAF C14.
A70: Pradecon 173195 | B70: Q10 | C70: 3.2 | D70: ARS | E70: 1702.49 | F70: 1545 | G70: =IF(D70="USD",E70,E70/F70) -> 1.1019353 | H70: 1500 × 3000 | I70: Hoja LAC 1/8.
A71: Pradecon 173195 | B71: Q11 | C71: 4.75 | D71: ARS | E71: 1685.56 | F71: 1545 | G71: =IF(D71="USD",E71,E71/F71) -> 1.0909773 | H71: 1500 × 3000 | I71: Hoja LAC 3/16.
A72: Hierros Parrotta 413329 | B72: Q12 | C72: 0.9 | D72: USD | E72: 1.3561 | F72: 1 | G72: =IF(D72="USD",E72,E72/F72) -> 1.3561 | H72: 1220 × 2440 | I72: Hoja doble decapada N.° 20. Neto con 6,84 % de descuento, contado.
... A86: Pacheco Chapas PR 42024 | B86: Q26 | C86: 4.75 | D86: USD | E86: 1.236 | F86: 1530 | G86: =IF(D86="USD",E86,E86/F86) -> 1.236 | H86: 1245 × 1360 / 1800 | I86: Plancha a medida LAC.
A88: 6. Precio del acero por espesor y forma de compra (USD/kg)
A89: Espesor (mm) | B89: Bobina (A) | C89: Hoja (B y D) | D89: Fleje a medida | E89: Bobina madre (C) | F89: A medida (Ref.) | I89: Cotización usada
A90: 0.9 | B90: =Datos!$G$61 -> 1.26285 | C90: =Datos!$G$72 -> 1.3561 | D90: =Datos!$G$61 -> 1.26285 | E90: =B90*(1+Datos!$B$56) -> 1.26285 | F90: =Datos!$G$72 -> 1.3561 | I90: Bobina Q1 · hoja Q12 · fleje Q1 · a medida Q12. A medida: sin cotización, se toma la hoja Q12.
A91: 1.25 | B91: =Datos!$G$62 -> 1.25056 | C91: =Datos!$G$68 -> 1.2902977 | D91: =Datos!$G$79 -> 1.186 | E91: =B91*(1+Datos!$B$56) -> 1.25056 | F91: =Datos!$G$82 -> 1.426 | I91: Bobina Q2 · hoja Q8 · fleje Q19 · a medida Q22.
A92: 1.6 | B92: =Datos!$G$63 -> 1.25056 | C92: =Datos!$G$67 -> 1.327521 | D92: =Datos!$G$80 -> 1.186 | E92: =B92*(1+Datos!$B$56) -> 1.25056 | F92: =Datos!$G$83 -> 1.453 | I92: Bobina Q3 · hoja Q7 · fleje Q20 · a medida Q23.
A93: 2 | B93: =Datos!$G$64 -> 1.26285 | C93: =Datos!$G$69 -> 1.2804013 | D93: =Datos!$G$81 -> 1.198 | E93: =B93*(1+Datos!$B$56) -> 1.26285 | F93: =Datos!$G$84 -> 1.429 | I93: Bobina Q4 · hoja Q9 · fleje Q21 · a medida Q24.
A94: 3.2 | B94: =Datos!$G$65 -> 1.11373 | C94: =Datos!$G$70 -> 1.1019353 | D94: =Datos!$G$65 -> 1.11373 | E94: =B94*(1+Datos!$B$56) -> 1.11373 | F94: =Datos!$G$85 -> 1.256 | I94: Bobina Q5 · hoja Q10 · fleje Q5 · a medida Q25. Fleje: la bobina flejada Q5.
A95: 4.75 | B95: =Datos!$G$65 -> 1.11373 | C95: =Datos!$G$71 -> 1.0909773 | D95: =Datos!$G$65 -> 1.11373 | E95: =B95*(1+Datos!$B$56) -> 1.11373 | F95: =Datos!$G$86 -> 1.236 | I95: Bobina Q5 · hoja Q11 · fleje Q5 · a medida Q26. Bobina: sin cotización, se toma la de 3,2 (Q5).
A97: 7. Equipos de corte y manejo (USD sin IVA)
A98: Equipo | B98: Precio (USD) | C98: A | D98: B | E98: C | F98: D | G98: Ref. | I98: Fuente
A99: Línea de corte transversal 1-6 mm × 1.600 (desbobinador, aplanadora, alimentador, cizalla) | B99: 80000 | C99: 1 | D99: 0 | E99: 1 | F99: 0 | G99: 0 | I99: ESTIMADO del grupo: Hener da USD 45.000 para 0,2-3 mm × 1.250; para 4,75 mm, más pesada.
A100: Guillotina 1 (franjas) CENA 8 × 3200 E21, tope 1.000 mm | B100: 36800 | C100: 1 | D100: 1 | E100: 0 | F100: 1 | G100: 0 | I100: Cotización CENA (Drive), sin IVA.
A101: Guillotina 2 (piezas) QC12Y 6 × 2500, tope 800 mm | B101: 10700 | C101: 0 | D101: 1 | E101: 0 | F101: 1 | G101: 0 | I101: Publicación Alibaba 1600900259147: FOB China, 1 a 2 unidades.
A102: Cortadora longitudinal 0,3-3,2 × 1.600 | B102: 60000 | C102: 0 | D102: 0 | E102: 1 | F102: 0 | G102: 0 | I102: ESTIMADO del grupo: Cangzhou Zunsheng USD 28.600-59.620 FOB.
A103: Puente grúa monoviga 10 t con carrilera | B103: 30000 | C103: =IF(Datos!$B$57="SI",0,1) -> 1 | D103: 0 | E103: =IF(Datos!$B$57="SI",0,1) -> 1 | F103: 0 | G103: 0 | I103: Dongqi Crane: USD 10.000-50.000 (10 t básico).
A104: Pinza en C portabobinas y cunas | B104: 6000 | C104: 1 | D104: 0 | E104: 1 | F104: 0 | G104: 0 | I104: ESTIMADO del grupo.
A105: Desbobinador, enderezador y alimentador servo de la prensa de discos | B105: 12000 | C105: 1 | D105: 0 | E105: 1 | F105: 1 | G105: 1 | I105: ESTIMADO del grupo (en cotización).
A106: Estantería porta-flejes | B106: 3000 | C106: 1 | D106: 0 | E106: 1 | F106: 1 | G106: 1 | I106: ESTIMADO del grupo.
A107: Autoelevador eléctrico 2,5 t | B107: 20000 | C107: 0 | D107: 1 | E107: 0 | F107: 1 | G107: 0 | I107: Mercado Libre GBA, nuevos 2026: USD 13.700-26.700.
A108: Mesa elevadora de tijera 3 t | B108: 7000 | C108: 0 | D108: 1 | E108: 0 | F108: 1 | G108: 0 | I108: ESTIMADO del grupo.
A109: Mesa de bolas entre la mesa elevadora y la guillotina | B109: 1500 | C109: 0 | D109: 1 | E109: 0 | F109: 1 | G109: 0 | I109: ESTIMADO del grupo.
A110: Racks por espesor y carros porta-desarrollos (pulmón entre guillotinas) | B110: 2000 | C110: 0 | D110: 1 | E110: 0 | F110: 1 | G110: 0 | I110: ESTIMADO del grupo.
A111: Mesa de alimentación de tiras al balancín | B111: 1500 | C111: 0 | D111: 1 | E111: 0 | F111: 0 | G111: 0 | I111: ESTIMADO del grupo.
A112: Inversión por alternativa | C112: =SUMPRODUCT($B$99:$B$111,C99:C111) -> 167800 | D112: =SUMPRODUCT($B$99:$B$111,D99:D111) -> 79500 | E112: =SUMPRODUCT($B$99:$B$111,E99:E111) -> 191000 | F112: =SUMPRODUCT($B$99:$B$111,F99:F111) -> 93000 | G112: =SUMPRODUCT($B$99:$B$111,G99:G111) -> 15000
A113: Prensa de discos y cilindradoras están en todas las alternativas y no entran. La guillotina 2 está a precio FOB.

Sheet Links
A1: Links de los IMPORTRANGE
A2: Pegar en B el link de cada Google Sheet: todos los IMPORTRANGE lo leen de acá.
A3: Archivo | B3: Link | C3: Qué se importa
A4: Proyecciones | B4: https://docs.google.com/spreadsheets/d/1xc4xDAwSYT3l-RulPYtcePxiCninrbQGzaBUsgO0YEs/edit?gid=1764491891#gid=1764491891 | C4: Indexado Dim Técnico B3:K10 (terminados 1 a 100 kg) y B15:K22 (cilindros vacíos) → Demanda
A5: Dimensionamiento Recargas Planta Comercial | B5: PEGAR ACÁ EL LINK DEL GOOGLE SHEET | C5: sobrestock_sustitutos B73:K76 y B86:K89: sustitutos ABC como cilindro vacío → Demanda
A6: Dimensionamiento Recargas Planta Industrial | B6: PEGAR ACÁ EL LINK DEL GOOGLE SHEET | C6: sobrestock_sustitutos B73:K76 y B86:K89: sustitutos ABC terminados → Demanda

Sheet Demanda
A1: Demanda: cuerpos a fabricar por formato
A2: Por IMPORTRANGE (hoja Links). Cada unidad lleva un cuerpo; las de 1 a 10 kg, además, una cúpula y un fondo.
A4: Unidades a fabricar = terminados + cilindros + sustitutos
A5: Formato | B5: Línea | C5: 2026 | D5: 2027 | E5: 2028 | F5: 2029 | G5: 2030 | H5: 2031 | I5: 2032 | J5: 2033 | K5: 2034 | L5: 2035
A6: 1 kg | B6: Manual | C6: =C18+C30+C42+C54 -> 4178.7365 | D6: =D18+D30+D42+D54 -> 5997.304 | E6: =E18+E30+E42+E54 -> 14514.148 | F6: =F18+F30+F42+F54 -> 35161.936 | G6: =G18+G30+G42+G54 -> 62115.433 | H6: =H18+H30+H42+H54 -> 87300.453 | I6: =I18+I30+I42+I54 -> 121673.15 | J6: =J18+J30+J42+J54 -> 156133.08 | ... L6: =L18+L30+L42+L54 -> 202620.64
A7: 2,5 kg | B7: Manual | C7: =C19+C31+C43+C55 -> 302.03036 | D7: =D19+D31+D43+D55 -> 727.28745 | E7: =E19+E31+E43+E55 -> 1317.3881 | F7: =F19+F31+F43+F55 -> 2592.6782 | G7: =G19+G31+G43+G55 -> 4297.3877 | H7: =H19+H31+H43+H55 -> 6113.1499 | I7: =I19+I31+I43+I55 -> 8117.2755 | J7: =J19+J31+J43+J55 -> 10270.227 | ... L7: =L19+L31+L43+L55 -> 14135.378
A8: 5 kg | B8: Manual | C8: =C20+C32+C44+C56 -> 2286.773 | D8: =D20+D32+D44+D56 -> 3940.4589 | E8: =E20+E32+E44+E56 -> 6733.0976 | F8: =F20+F32+F44+F56 -> 12240.955 | G8: =G20+G32+G44+G56 -> 20628.467 | H8: =H20+H32+H44+H56 -> 28744.684 | I8: =I20+I32+I44+I56 -> 38699.48 | J8: =J20+J32+J44+J56 -> 48872.026 | ... L8: =L20+L32+L44+L56 -> 63882.939
A9: 10 kg | B9: Manual | C9: =C21+C33+C45+C57 -> 94.833182 | D9: =D21+D33+D45+D57 -> 184.4873 | E9: =E21+E33+E45+E57 -> 356.17878 | F9: =F21+F33+F45+F57 -> 693.78049 | G9: =G21+G33+G45+G57 -> 1206.3982 | H9: =H21+H33+H45+H57 -> 1743.045 | I9: =I21+I33+I45+I57 -> 2339.8005 | J9: =J21+J33+J45+J57 -> 2957.5648 | ... L9: =L21+L33+L45+L57 -> 3868.3281
A10: 25 kg | B10: Rodante | C10: =C22+C34+C46+C58 -> 36.051791 | D10: =D22+D34+D46+D58 -> 58.622147 | E10: =E22+E34+E46+E58 -> 90.76854 | F10: =F22+F34+F46+F58 -> 153.96985 | G10: =G22+G34+G46+G58 -> 251.356 | H10: =H22+H34+H46+H58 -> 349.57448 | I10: =I22+I34+I46+I58 -> 465.46823 | J10: =J22+J34+J46+J58 -> 587.72867 | ... L10: =L22+L34+L46+L58 -> 777.31053
A11: 50 kg | B11: Rodante | C11: =C23+C35+C47+C59 -> 76.913941 | D11: =D23+D35+D47+D59 -> 129.77672 | E11: =E23+E35+E47+E59 -> 201.49879 | F11: =F23+F35+F47+F59 -> 336.52568 | G11: =G23+G35+G47+G59 -> 554.00721 | H11: =H23+H35+H47+H59 -> 770.13586 | I11: =I23+I35+I47+I59 -> 1024.3501 | J11: =J23+J35+J47+J59 -> 1292.1071 | ... L11: =L23+L35+L47+L59 -> 1709.4352
A12: 70 kg | B12: Rodante | C12: =C24+C36+C48+C60 -> 18.34486 | D12: =D24+D36+D48+D60 -> 28.221831 | E12: =E24+E36+E48+E60 -> 43.260099 | F12: =F24+F36+F48+F60 -> 73.814329 | G12: =G24+G36+G48+G60 -> 122.26048 | H12: =H24+H36+H48+H60 -> 167.52855 | I12: =I24+I36+I48+I60 -> 224.48075 | J12: =J24+J36+J48+J60 -> 281.64736 | ... L12: =L24+L36+L48+L60 -> 374.12986
A13: 100 kg | B13: Rodante | C13: =C25+C37+C49+C61 -> 12.896573 | D13: =D25+D37+D49+D61 -> 18.867887 | E13: =E25+E37+E49+E61 -> 28.826733 | F13: =F25+F37+F49+F61 -> 48.329553 | G13: =G25+G37+G49+G61 -> 80.640321 | H13: =H25+H37+H49+H61 -> 111.85903 | I13: =I25+I37+I49+I61 -> 148.97383 | J13: =J25+J37+J49+J61 -> 186.51157 | ... L13: =L25+L37+L49+L61 -> 247.44657
A14: Total | C14: =SUM(C6:C13) -> 7006.5803 | D14: =SUM(D6:D13) -> 11085.026 | E14: =SUM(E6:E13) -> 23285.166 | F14: =SUM(F6:F13) -> 51301.989 | G14: =SUM(G6:G13) -> 89255.95 | H14: =SUM(H6:H13) -> 125300.43 | I14: =SUM(I6:I13) -> 172692.98 | J14: =SUM(J6:J13) -> 220580.89 | ... L14: =SUM(L6:L13) -> 287615.61
A16: Matafuegos terminados (Proyecciones)
A17: Formato | B17: Línea | C17: 2026 | D17: 2027 | E17: 2028 | F17: 2029 | G17: 2030 | H17: 2031 | I17: 2032 | J17: 2033 | K17: 2034 | L17: 2035
A18: 1 kg | B18: Manual | C18: =IFERROR(__xludf.DUMMYFUNCTION("IMPORTRANGE(Links!$B$4,""Indexado Dim Técnico!B3:K10"")"),4178.736543) -> 4178.7365 | D18: =IFERROR(__xludf.DUMMYFUNCTION("""COMPUTED_VALUE"""),5997.303977) -> 5997.304 | E18: =IFERROR(__xludf.DUMMYFUNCTION("""COMPUTED_VALUE"""),6851.747758) -> 6851.7478 | F18: =IFERROR(__xludf.DUMMYFUNCTION("""COMPUTED_VALUE"""),8467.135549) -> 8467.1355 | G18: =IFERROR(__xludf.DUMMYFUNCTION("""COMPUTED_VALUE"""),12680.63271) -> 12680.633 | H18: =IFERROR(__xludf.DUMMYFUNCTION("""COMPUTED_VALUE"""),15620.25307) -> 15620.253 | I18: =IFERROR(__xludf.DUMMYFUNCTION("""COMPUTED_VALUE"""),20332.55326) -> 20332.553 | J18: =IFERROR(__xludf.DUMMYFUNCTION("""COMPUTED_VALUE"""),25132.07848) -> 25132.078 | K18: =IFERROR(__xludf.DUMMYFUNCTION("""COMPUTED_VALUE"""),28573.33614) -> 28573.336 | L18: =IFERROR(__xludf.DUMMYFUNCTION("""COMPUTED_VALUE"""),32072.63913) -> 32072.639
A19: 2,5 kg | B19: Manual | C19: =IFERROR(__xludf.DUMMYFUNCTION("""COMPUTED_VALUE"""),295.0303572) -> 295.03036 | D19: =IFERROR(__xludf.DUMMYFUNCTION("""COMPUTED_VALUE"""),709.7274503) -> 709.72745 | E19: =IFERROR(__xludf.DUMMYFUNCTION("""COMPUTED_VALUE"""),986.8680576) -> 986.86806 | F19: =IFERROR(__xludf.DUMMYFUNCTION("""COMPUTED_VALUE"""),1500.638174) -> 1500.6382 | G19: =IFERROR(__xludf.DUMMYFUNCTION("""COMPUTED_VALUE"""),2312.627726) -> 2312.6277 | H19: =IFERROR(__xludf.DUMMYFUNCTION("""COMPUTED_VALUE"""),3252.869887) -> 3252.8699 | I19: =IFERROR(__xludf.DUMMYFUNCTION("""COMPUTED_VALUE"""),4102.315524) -> 4102.3155 | J19: =IFERROR(__xludf.DUMMYFUNCTION("""COMPUTED_VALUE"""),5104.306587) -> 5104.3066 | K19: =IFERROR(__xludf.DUMMYFUNCTION("""COMPUTED_VALUE"""),6195.186243) -> 6195.1862 | L19: =IFERROR(__xludf.DUMMYFUNCTION("""COMPUTED_VALUE"""),7424.858444) -> 7424.8584
A20: 5 kg | B20: Manual | C20: =IFERROR(__xludf.DUMMYFUNCTION("""COMPUTED_VALUE"""),2255.773025) -> 2255.773 | D20: =IFERROR(__xludf.DUMMYFUNCTION("""COMPUTED_VALUE"""),3846.978881) -> 3846.9789 | E20: =IFERROR(__xludf.DUMMYFUNCTION("""COMPUTED_VALUE"""),5093.537591) -> 5093.5376 | F20: =IFERROR(__xludf.DUMMYFUNCTION("""COMPUTED_VALUE"""),6823.115313) -> 6823.1153 | G20: =IFERROR(__xludf.DUMMYFUNCTION("""COMPUTED_VALUE"""),10819.30694) -> 10819.307 | H20: =IFERROR(__xludf.DUMMYFUNCTION("""COMPUTED_VALUE"""),14605.96411) -> 14605.964 | I20: =IFERROR(__xludf.DUMMYFUNCTION("""COMPUTED_VALUE"""),18877.75984) -> 18877.76 | J20: =IFERROR(__xludf.DUMMYFUNCTION("""COMPUTED_VALUE"""),23368.18637) -> 23368.186 | K20: =IFERROR(__xludf.DUMMYFUNCTION("""COMPUTED_VALUE"""),26967.72455) -> 26967.725 | L20: =IFERROR(__xludf.DUMMYFUNCTION("""COMPUTED_VALUE"""),30750.77872) -> 30750.779
A21: 10 kg | B21: Manual | C21: =IFERROR(__xludf.DUMMYFUNCTION("""COMPUTED_VALUE"""),91.83318153) -> 91.833182 | D21: =IFERROR(__xludf.DUMMYFUNCTION("""COMPUTED_VALUE"""),177.2472967) -> 177.2473 | E21: =IFERROR(__xludf.DUMMYFUNCTION("""COMPUTED_VALUE"""),252.9787798) -> 252.97878 | F21: =IFERROR(__xludf.DUMMYFUNCTION("""COMPUTED_VALUE"""),358.0204941) -> 358.02049 | G21: =IFERROR(__xludf.DUMMYFUNCTION("""COMPUTED_VALUE"""),602.7181519) -> 602.71815 | H21: =IFERROR(__xludf.DUMMYFUNCTION("""COMPUTED_VALUE"""),872.605032) -> 872.60503 | I21: =IFERROR(__xludf.DUMMYFUNCTION("""COMPUTED_VALUE"""),1127.160545) -> 1127.1605 | J21: =IFERROR(__xludf.DUMMYFUNCTION("""COMPUTED_VALUE"""),1395.444812) -> 1395.4448 | K21: =IFERROR(__xludf.DUMMYFUNCTION("""COMPUTED_VALUE"""),1612.350054) -> 1612.3501 | L21: =IFERROR(__xludf.DUMMYFUNCTION("""COMPUTED_VALUE"""),1840.848079) -> 1840.8481
A22: 25 kg | B22: Rodante | C22: =IFERROR(__xludf.DUMMYFUNCTION("""COMPUTED_VALUE"""),34.05179136) -> 34.051791 | D22: =IFERROR(__xludf.DUMMYFUNCTION("""COMPUTED_VALUE"""),58.46214745) -> 58.462147 | E22: =IFERROR(__xludf.DUMMYFUNCTION("""COMPUTED_VALUE"""),75.20853998) -> 75.20854 | F22: =IFERROR(__xludf.DUMMYFUNCTION("""COMPUTED_VALUE"""),100.5298529) -> 100.52985 | G22: =IFERROR(__xludf.DUMMYFUNCTION("""COMPUTED_VALUE"""),155.8760035) -> 155.876 | H22: =IFERROR(__xludf.DUMMYFUNCTION("""COMPUTED_VALUE"""),211.9344827) -> 211.93448 | I22: =IFERROR(__xludf.DUMMYFUNCTION("""COMPUTED_VALUE"""),272.6682332) -> 272.66823 | J22: =IFERROR(__xludf.DUMMYFUNCTION("""COMPUTED_VALUE"""),337.8486707) -> 337.84867 | K22: =IFERROR(__xludf.DUMMYFUNCTION("""COMPUTED_VALUE"""),393.6274156) -> 393.62742 | L22: =IFERROR(__xludf.DUMMYFUNCTION("""COMPUTED_VALUE"""),453.2705332) -> 453.27053
A23: 50 kg | B23: Rodante | C23: =IFERROR(__xludf.DUMMYFUNCTION("""COMPUTED_VALUE"""),74.913941) -> 74.913941 | D23: =IFERROR(__xludf.DUMMYFUNCTION("""COMPUTED_VALUE"""),128.6167244) -> 128.61672 | E23: =IFERROR(__xludf.DUMMYFUNCTION("""COMPUTED_VALUE"""),165.458788) -> 165.45879 | F23: =IFERROR(__xludf.DUMMYFUNCTION("""COMPUTED_VALUE"""),221.1656765) -> 221.16568 | G23: =IFERROR(__xludf.DUMMYFUNCTION("""COMPUTED_VALUE"""),342.9272077) -> 342.92721 | H23: =IFERROR(__xludf.DUMMYFUNCTION("""COMPUTED_VALUE"""),466.255862) -> 466.25586 | I23: =IFERROR(__xludf.DUMMYFUNCTION("""COMPUTED_VALUE"""),599.8701129) -> 599.87011 | J23: =IFERROR(__xludf.DUMMYFUNCTION("""COMPUTED_VALUE"""),743.2670756) -> 743.26708 | K23: =IFERROR(__xludf.DUMMYFUNCTION("""COMPUTED_VALUE"""),865.9803143) -> 865.98031 | L23: =IFERROR(__xludf.DUMMYFUNCTION("""COMPUTED_VALUE"""),997.1951731) -> 997.19517
A24: 70 kg | B24: Rodante | C24: =IFERROR(__xludf.DUMMYFUNCTION("""COMPUTED_VALUE"""),16.34485985) -> 16.34486 | D24: =IFERROR(__xludf.DUMMYFUNCTION("""COMPUTED_VALUE"""),28.06183078) -> 28.061831 | E24: =IFERROR(__xludf.DUMMYFUNCTION("""COMPUTED_VALUE"""),36.10009919) -> 36.100099 | F24: =IFERROR(__xludf.DUMMYFUNCTION("""COMPUTED_VALUE"""),48.25432941) -> 48.254329 | G24: =IFERROR(__xludf.DUMMYFUNCTION("""COMPUTED_VALUE"""),74.82048167) -> 74.820482 | H24: =IFERROR(__xludf.DUMMYFUNCTION("""COMPUTED_VALUE"""),101.7285517) -> 101.72855 | I24: =IFERROR(__xludf.DUMMYFUNCTION("""COMPUTED_VALUE"""),130.8807519) -> 130.88075 | J24: =IFERROR(__xludf.DUMMYFUNCTION("""COMPUTED_VALUE"""),162.1673619) -> 162.16736 | K24: =IFERROR(__xludf.DUMMYFUNCTION("""COMPUTED_VALUE"""),188.9411595) -> 188.94116 | L24: =IFERROR(__xludf.DUMMYFUNCTION("""COMPUTED_VALUE"""),217.569856) -> 217.56986
A25: 100 kg | B25: Rodante | C25: =IFERROR(__xludf.DUMMYFUNCTION("""COMPUTED_VALUE"""),10.89657324) -> 10.896573 | D25: =IFERROR(__xludf.DUMMYFUNCTION("""COMPUTED_VALUE"""),18.70788719) -> 18.707887 | E25: =IFERROR(__xludf.DUMMYFUNCTION("""COMPUTED_VALUE"""),24.06673279) -> 24.066733 | F25: =IFERROR(__xludf.DUMMYFUNCTION("""COMPUTED_VALUE"""),32.16955294) -> 32.169553 | G25: =IFERROR(__xludf.DUMMYFUNCTION("""COMPUTED_VALUE"""),49.88032112) -> 49.880321 | H25: =IFERROR(__xludf.DUMMYFUNCTION("""COMPUTED_VALUE"""),67.81903447) -> 67.819034 | I25: =IFERROR(__xludf.DUMMYFUNCTION("""COMPUTED_VALUE"""),87.25383461) -> 87.253835 | J25: =IFERROR(__xludf.DUMMYFUNCTION("""COMPUTED_VALUE"""),108.1115746) -> 108.11157 | K25: =IFERROR(__xludf.DUMMYFUNCTION("""COMPUTED_VALUE"""),125.960773) -> 125.96077 | L25: =IFERROR(__xludf.DUMMYFUNCTION("""COMPUTED_VALUE"""),145.0465706) -> 145.04657
A26: Total | C26: =SUM(C18:C25) -> 6957.5803 | D26: =SUM(D18:D25) -> 10965.106 | E26: =SUM(E18:E25) -> 13485.966 | F26: =SUM(F18:F25) -> 17551.029 | G26: =SUM(G18:G25) -> 27038.79 | H26: =SUM(H18:H25) -> 35199.43 | I26: =SUM(I18:I25) -> 45530.462 | J26: =SUM(J18:J25) -> 56351.411 | ... L26: =SUM(L18:L25) -> 73902.207
A28: Cilindros vendidos vacíos (Proyecciones)
A29: Formato | B29: Línea | C29: 2026 | D29: 2027 | E29: 2028 | F29: 2029 | G29: 2030 | H29: 2031 | I29: 2032 | J29: 2033 | K29: 2034 | L29: 2035
A30: 1 kg | B30: Manual | C30: =IFERROR(__xludf.DUMMYFUNCTION("IMPORTRANGE(Links!$B$4,""Indexado Dim Técnico!B15:K22"")"),0) -> 0 | D30: =IFERROR(__xludf.DUMMYFUNCTION("""COMPUTED_VALUE"""),0) -> 0 | E30: =IFERROR(__xludf.DUMMYFUNCTION("""COMPUTED_VALUE"""),7662.4) -> 7662.4 | F30: =IFERROR(__xludf.DUMMYFUNCTION("""COMPUTED_VALUE"""),26694.8) -> 26694.8 | G30: =IFERROR(__xludf.DUMMYFUNCTION("""COMPUTED_VALUE"""),49434.8) -> 49434.8 | H30: =IFERROR(__xludf.DUMMYFUNCTION("""COMPUTED_VALUE"""),71680.2) -> 71680.2 | I30: =IFERROR(__xludf.DUMMYFUNCTION("""COMPUTED_VALUE"""),101340.6) -> 101340.6 | J30: =IFERROR(__xludf.DUMMYFUNCTION("""COMPUTED_VALUE"""),131001) -> 131001 | K30: =IFERROR(__xludf.DUMMYFUNCTION("""COMPUTED_VALUE"""),146819.8) -> 146819.8 | L30: =IFERROR(__xludf.DUMMYFUNCTION("""COMPUTED_VALUE"""),170548) -> 170548
A31: 2,5 kg | B31: Manual | C31: =IFERROR(__xludf.DUMMYFUNCTION("""COMPUTED_VALUE"""),0) -> 0 | D31: =IFERROR(__xludf.DUMMYFUNCTION("""COMPUTED_VALUE"""),0) -> 0 | E31: =IFERROR(__xludf.DUMMYFUNCTION("""COMPUTED_VALUE"""),299.6) -> 299.6 | F31: =IFERROR(__xludf.DUMMYFUNCTION("""COMPUTED_VALUE"""),1043.8) -> 1043.8 | G31: =IFERROR(__xludf.DUMMYFUNCTION("""COMPUTED_VALUE"""),1933) -> 1933 | H31: =IFERROR(__xludf.DUMMYFUNCTION("""COMPUTED_VALUE"""),2803) -> 2803 | I31: =IFERROR(__xludf.DUMMYFUNCTION("""COMPUTED_VALUE"""),3963) -> 3963 | J31: =IFERROR(__xludf.DUMMYFUNCTION("""COMPUTED_VALUE"""),5123) -> 5123 | K31: =IFERROR(__xludf.DUMMYFUNCTION("""COMPUTED_VALUE"""),5741.4) -> 5741.4 | L31: =IFERROR(__xludf.DUMMYFUNCTION("""COMPUTED_VALUE"""),6669) -> 6669
A32: 5 kg | B32: Manual | C32: =IFERROR(__xludf.DUMMYFUNCTION("""COMPUTED_VALUE"""),0) -> 0 | D32: =IFERROR(__xludf.DUMMYFUNCTION("""COMPUTED_VALUE"""),0) -> 0 | E32: =IFERROR(__xludf.DUMMYFUNCTION("""COMPUTED_VALUE"""),1478.8) -> 1478.8 | F32: =IFERROR(__xludf.DUMMYFUNCTION("""COMPUTED_VALUE"""),5152) -> 5152 | G32: =IFERROR(__xludf.DUMMYFUNCTION("""COMPUTED_VALUE"""),9540.8) -> 9540.8 | H32: =IFERROR(__xludf.DUMMYFUNCTION("""COMPUTED_VALUE"""),13834.2) -> 13834.2 | I32: =IFERROR(__xludf.DUMMYFUNCTION("""COMPUTED_VALUE"""),19558.6) -> 19558.6 | J32: =IFERROR(__xludf.DUMMYFUNCTION("""COMPUTED_VALUE"""),25283) -> 25283 | K32: =IFERROR(__xludf.DUMMYFUNCTION("""COMPUTED_VALUE"""),28335.8) -> 28335.8 | L32: =IFERROR(__xludf.DUMMYFUNCTION("""COMPUTED_VALUE"""),32915) -> 32915
A33: 10 kg | B33: Manual | C33: =IFERROR(__xludf.DUMMYFUNCTION("""COMPUTED_VALUE"""),0) -> 0 | D33: =IFERROR(__xludf.DUMMYFUNCTION("""COMPUTED_VALUE"""),0) -> 0 | E33: =IFERROR(__xludf.DUMMYFUNCTION("""COMPUTED_VALUE"""),90.4) -> 90.4 | F33: =IFERROR(__xludf.DUMMYFUNCTION("""COMPUTED_VALUE"""),315) -> 315 | G33: =IFERROR(__xludf.DUMMYFUNCTION("""COMPUTED_VALUE"""),583.4) -> 583.4 | H33: =IFERROR(__xludf.DUMMYFUNCTION("""COMPUTED_VALUE"""),845.8) -> 845.8 | I33: =IFERROR(__xludf.DUMMYFUNCTION("""COMPUTED_VALUE"""),1195.4) -> 1195.4 | J33: =IFERROR(__xludf.DUMMYFUNCTION("""COMPUTED_VALUE"""),1545) -> 1545 | K33: =IFERROR(__xludf.DUMMYFUNCTION("""COMPUTED_VALUE"""),1731.4) -> 1731.4 | L33: =IFERROR(__xludf.DUMMYFUNCTION("""COMPUTED_VALUE"""),2011) -> 2011
A34: 25 kg | B34: Rodante | C34: =IFERROR(__xludf.DUMMYFUNCTION("""COMPUTED_VALUE"""),0) -> 0 | D34: =IFERROR(__xludf.DUMMYFUNCTION("""COMPUTED_VALUE"""),0) -> 0 | E34: =IFERROR(__xludf.DUMMYFUNCTION("""COMPUTED_VALUE"""),14.4) -> 14.4 | F34: =IFERROR(__xludf.DUMMYFUNCTION("""COMPUTED_VALUE"""),50.2) -> 50.2 | G34: =IFERROR(__xludf.DUMMYFUNCTION("""COMPUTED_VALUE"""),93) -> 93 | H34: =IFERROR(__xludf.DUMMYFUNCTION("""COMPUTED_VALUE"""),135) -> 135 | I34: =IFERROR(__xludf.DUMMYFUNCTION("""COMPUTED_VALUE"""),191) -> 191 | J34: =IFERROR(__xludf.DUMMYFUNCTION("""COMPUTED_VALUE"""),247) -> 247 | K34: =IFERROR(__xludf.DUMMYFUNCTION("""COMPUTED_VALUE"""),277) -> 277 | L34: =IFERROR(__xludf.DUMMYFUNCTION("""COMPUTED_VALUE"""),322) -> 322
A35: 50 kg | B35: Rodante | C35: =IFERROR(__xludf.DUMMYFUNCTION("""COMPUTED_VALUE"""),0) -> 0 | D35: =IFERROR(__xludf.DUMMYFUNCTION("""COMPUTED_VALUE"""),0) -> 0 | E35: =IFERROR(__xludf.DUMMYFUNCTION("""COMPUTED_VALUE"""),31.8) -> 31.8 | F35: =IFERROR(__xludf.DUMMYFUNCTION("""COMPUTED_VALUE"""),110.8) -> 110.8 | G35: =IFERROR(__xludf.DUMMYFUNCTION("""COMPUTED_VALUE"""),205.2) -> 205.2 | H35: =IFERROR(__xludf.DUMMYFUNCTION("""COMPUTED_VALUE"""),297.6) -> 297.6 | I35: =IFERROR(__xludf.DUMMYFUNCTION("""COMPUTED_VALUE"""),420.8) -> 420.8 | J35: =IFERROR(__xludf.DUMMYFUNCTION("""COMPUTED_VALUE"""),544) -> 544 | K35: =IFERROR(__xludf.DUMMYFUNCTION("""COMPUTED_VALUE"""),609.6) -> 609.6 | L35: =IFERROR(__xludf.DUMMYFUNCTION("""COMPUTED_VALUE"""),708) -> 708
A36: 70 kg | B36: Rodante | C36: =IFERROR(__xludf.DUMMYFUNCTION("""COMPUTED_VALUE"""),0) -> 0 | D36: =IFERROR(__xludf.DUMMYFUNCTION("""COMPUTED_VALUE"""),0) -> 0 | E36: =IFERROR(__xludf.DUMMYFUNCTION("""COMPUTED_VALUE"""),7) -> 7 | F36: =IFERROR(__xludf.DUMMYFUNCTION("""COMPUTED_VALUE"""),24.4) -> 24.4 | G36: =IFERROR(__xludf.DUMMYFUNCTION("""COMPUTED_VALUE"""),45.2) -> 45.2 | H36: =IFERROR(__xludf.DUMMYFUNCTION("""COMPUTED_VALUE"""),65.4) -> 65.4 | I36: =IFERROR(__xludf.DUMMYFUNCTION("""COMPUTED_VALUE"""),92.2) -> 92.2 | J36: =IFERROR(__xludf.DUMMYFUNCTION("""COMPUTED_VALUE"""),119) -> 119 | K36: =IFERROR(__xludf.DUMMYFUNCTION("""COMPUTED_VALUE"""),133.4) -> 133.4 | L36: =IFERROR(__xludf.DUMMYFUNCTION("""COMPUTED_VALUE"""),155) -> 155
A37: 100 kg | B37: Rodante | C37: =IFERROR(__xludf.DUMMYFUNCTION("""COMPUTED_VALUE"""),0) -> 0 | D37: =IFERROR(__xludf.DUMMYFUNCTION("""COMPUTED_VALUE"""),0) -> 0 | E37: =IFERROR(__xludf.DUMMYFUNCTION("""COMPUTED_VALUE"""),4.6) -> 4.6 | F37: =IFERROR(__xludf.DUMMYFUNCTION("""COMPUTED_VALUE"""),16) -> 16 | G37: =IFERROR(__xludf.DUMMYFUNCTION("""COMPUTED_VALUE"""),29.6) -> 29.6 | H37: =IFERROR(__xludf.DUMMYFUNCTION("""COMPUTED_VALUE"""),42.8) -> 42.8 | I37: =IFERROR(__xludf.DUMMYFUNCTION("""COMPUTED_VALUE"""),60.4) -> 60.4 | J37: =IFERROR(__xludf.DUMMYFUNCTION("""COMPUTED_VALUE"""),78) -> 78 | K37: =IFERROR(__xludf.DUMMYFUNCTION("""COMPUTED_VALUE"""),87.6) -> 87.6 | L37: =IFERROR(__xludf.DUMMYFUNCTION("""COMPUTED_VALUE"""),102) -> 102
A38: Total | C38: =SUM(C30:C37) -> 0 | D38: =SUM(D30:D37) -> 0 | E38: =SUM(E30:E37) -> 9589 | F38: =SUM(F30:F37) -> 33407 | G38: =SUM(G30:G37) -> 61865 | H38: =SUM(H30:H37) -> 89704 | I38: =SUM(I30:I37) -> 126822 | J38: =SUM(J30:J37) -> 163940 | ... L38: =SUM(L30:L37) -> 213430
A40: Sustitutos ABC terminados para la planta industrial de recargas
A41: Formato | B41: Línea | C41: 2026 | D41: 2027 | E41: 2028 | F41: 2029 | G41: 2030 | H41: 2031 | I41: 2032 | J41: 2033 | K41: 2034 | L41: 2035
A42: 1 kg | B42: Manual | C42: =IFERROR(__xludf.DUMMYFUNCTION("IMPORTRANGE(Links!$B$6,""sobrestock_sustitutos!B73:K76"")"),0) -> 0 | D42: =IFERROR(__xludf.DUMMYFUNCTION("""COMPUTED_VALUE"""),0) -> 0 | E42: =IFERROR(__xludf.DUMMYFUNCTION("""COMPUTED_VALUE"""),0) -> 0 | F42: =IFERROR(__xludf.DUMMYFUNCTION("""COMPUTED_VALUE"""),0) -> 0 | G42: =IFERROR(__xludf.DUMMYFUNCTION("""COMPUTED_VALUE"""),0) -> 0 | H42: =IFERROR(__xludf.DUMMYFUNCTION("""COMPUTED_VALUE"""),0) -> 0 | I42: =IFERROR(__xludf.DUMMYFUNCTION("""COMPUTED_VALUE"""),0) -> 0 | J42: =IFERROR(__xludf.DUMMYFUNCTION("""COMPUTED_VALUE"""),0) -> 0 | K42: =IFERROR(__xludf.DUMMYFUNCTION("""COMPUTED_VALUE"""),0) -> 0 | L42: =IFERROR(__xludf.DUMMYFUNCTION("""COMPUTED_VALUE"""),0) -> 0
A43: 2,5 kg | B43: Manual | C43: =IFERROR(__xludf.DUMMYFUNCTION("""COMPUTED_VALUE"""),3) -> 3 | D43: =IFERROR(__xludf.DUMMYFUNCTION("""COMPUTED_VALUE"""),6.24) -> 6.24 | E43: =IFERROR(__xludf.DUMMYFUNCTION("""COMPUTED_VALUE"""),10.72) -> 10.72 | F43: =IFERROR(__xludf.DUMMYFUNCTION("""COMPUTED_VALUE"""),17.52) -> 17.52 | G43: =IFERROR(__xludf.DUMMYFUNCTION("""COMPUTED_VALUE"""),18.8) -> 18.8 | H43: =IFERROR(__xludf.DUMMYFUNCTION("""COMPUTED_VALUE"""),21.08) -> 21.08 | I43: =IFERROR(__xludf.DUMMYFUNCTION("""COMPUTED_VALUE"""),18.44) -> 18.44 | J43: =IFERROR(__xludf.DUMMYFUNCTION("""COMPUTED_VALUE"""),15.48) -> 15.48 | K43: =IFERROR(__xludf.DUMMYFUNCTION("""COMPUTED_VALUE"""),14.2) -> 14.2 | L43: =IFERROR(__xludf.DUMMYFUNCTION("""COMPUTED_VALUE"""),14.76) -> 14.76
A44: 5 kg | B44: Manual | C44: =IFERROR(__xludf.DUMMYFUNCTION("""COMPUTED_VALUE"""),11) -> 11 | D44: =IFERROR(__xludf.DUMMYFUNCTION("""COMPUTED_VALUE"""),33.88) -> 33.88 | E44: =IFERROR(__xludf.DUMMYFUNCTION("""COMPUTED_VALUE"""),57.52) -> 57.52 | F44: =IFERROR(__xludf.DUMMYFUNCTION("""COMPUTED_VALUE"""),95.84) -> 95.84 | G44: =IFERROR(__xludf.DUMMYFUNCTION("""COMPUTED_VALUE"""),95.88) -> 95.88 | H44: =IFERROR(__xludf.DUMMYFUNCTION("""COMPUTED_VALUE"""),109.36) -> 109.36 | I44: =IFERROR(__xludf.DUMMYFUNCTION("""COMPUTED_VALUE"""),93.4) -> 93.4 | J44: =IFERROR(__xludf.DUMMYFUNCTION("""COMPUTED_VALUE"""),79.6) -> 79.6 | K44: =IFERROR(__xludf.DUMMYFUNCTION("""COMPUTED_VALUE"""),73.28) -> 73.28 | L44: =IFERROR(__xludf.DUMMYFUNCTION("""COMPUTED_VALUE"""),78.16) -> 78.16
A45: 10 kg | B45: Manual | C45: =IFERROR(__xludf.DUMMYFUNCTION("""COMPUTED_VALUE"""),1) -> 1 | D45: =IFERROR(__xludf.DUMMYFUNCTION("""COMPUTED_VALUE"""),3.08) -> 3.08 | E45: =IFERROR(__xludf.DUMMYFUNCTION("""COMPUTED_VALUE"""),4.32) -> 4.32 | F45: =IFERROR(__xludf.DUMMYFUNCTION("""COMPUTED_VALUE"""),7.64) -> 7.64 | G45: =IFERROR(__xludf.DUMMYFUNCTION("""COMPUTED_VALUE"""),7.2) -> 7.2 | H45: =IFERROR(__xludf.DUMMYFUNCTION("""COMPUTED_VALUE"""),8.68) -> 8.68 | I45: =IFERROR(__xludf.DUMMYFUNCTION("""COMPUTED_VALUE"""),6.24) -> 6.24 | J45: =IFERROR(__xludf.DUMMYFUNCTION("""COMPUTED_VALUE"""),6.56) -> 6.56 | K45: =IFERROR(__xludf.DUMMYFUNCTION("""COMPUTED_VALUE"""),4.88) -> 4.88 | L45: =IFERROR(__xludf.DUMMYFUNCTION("""COMPUTED_VALUE"""),6.04) -> 6.04
A46: 25 kg | B46: Rodante | C46: =IFERROR(__xludf.DUMMYFUNCTION("IMPORTRANGE(Links!$B$6,""sobrestock_sustitutos!B86:K89"")"),1) -> 1 | D46: =IFERROR(__xludf.DUMMYFUNCTION("""COMPUTED_VALUE"""),0.08) -> 0.08 | E46: =IFERROR(__xludf.DUMMYFUNCTION("""COMPUTED_VALUE"""),0.08) -> 0.08 | F46: =IFERROR(__xludf.DUMMYFUNCTION("""COMPUTED_VALUE"""),1.08) -> 1.08 | G46: =IFERROR(__xludf.DUMMYFUNCTION("""COMPUTED_VALUE"""),1.16) -> 1.16 | H46: =IFERROR(__xludf.DUMMYFUNCTION("""COMPUTED_VALUE"""),1.24) -> 1.24 | I46: =IFERROR(__xludf.DUMMYFUNCTION("""COMPUTED_VALUE"""),0.32) -> 0.32 | J46: =IFERROR(__xludf.DUMMYFUNCTION("""COMPUTED_VALUE"""),1.32) -> 1.32 | K46: =IFERROR(__xludf.DUMMYFUNCTION("""COMPUTED_VALUE"""),0.4) -> 0.4 | L46: =IFERROR(__xludf.DUMMYFUNCTION("""COMPUTED_VALUE"""),0.4) -> 0.4
A47: 50 kg | B47: Rodante | C47: =IFERROR(__xludf.DUMMYFUNCTION("""COMPUTED_VALUE"""),1) -> 1 | D47: =IFERROR(__xludf.DUMMYFUNCTION("""COMPUTED_VALUE"""),0.08) -> 0.08 | E47: =IFERROR(__xludf.DUMMYFUNCTION("""COMPUTED_VALUE"""),2.08) -> 2.08 | F47: =IFERROR(__xludf.DUMMYFUNCTION("""COMPUTED_VALUE"""),1.24) -> 1.24 | G47: =IFERROR(__xludf.DUMMYFUNCTION("""COMPUTED_VALUE"""),2.32) -> 2.32 | H47: =IFERROR(__xludf.DUMMYFUNCTION("""COMPUTED_VALUE"""),2.48) -> 2.48 | I47: =IFERROR(__xludf.DUMMYFUNCTION("""COMPUTED_VALUE"""),0.64) -> 0.64 | J47: =IFERROR(__xludf.DUMMYFUNCTION("""COMPUTED_VALUE"""),1.64) -> 1.64 | K47: =IFERROR(__xludf.DUMMYFUNCTION("""COMPUTED_VALUE"""),1.72) -> 1.72 | L47: =IFERROR(__xludf.DUMMYFUNCTION("""COMPUTED_VALUE"""),1.8) -> 1.8
A48: 70 kg | B48: Rodante | C48: =IFERROR(__xludf.DUMMYFUNCTION("""COMPUTED_VALUE"""),1) -> 1 | D48: =IFERROR(__xludf.DUMMYFUNCTION("""COMPUTED_VALUE"""),0.08) -> 0.08 | E48: =IFERROR(__xludf.DUMMYFUNCTION("""COMPUTED_VALUE"""),0.08) -> 0.08 | F48: =IFERROR(__xludf.DUMMYFUNCTION("""COMPUTED_VALUE"""),0.08) -> 0.08 | G48: =IFERROR(__xludf.DUMMYFUNCTION("""COMPUTED_VALUE"""),1.08) -> 1.08 | H48: =IFERROR(__xludf.DUMMYFUNCTION("""COMPUTED_VALUE"""),0.16) -> 0.16 | I48: =IFERROR(__xludf.DUMMYFUNCTION("""COMPUTED_VALUE"""),0.16) -> 0.16 | J48: =IFERROR(__xludf.DUMMYFUNCTION("""COMPUTED_VALUE"""),0.16) -> 0.16 | K48: =IFERROR(__xludf.DUMMYFUNCTION("""COMPUTED_VALUE"""),1.16) -> 1.16 | L48: =IFERROR(__xludf.DUMMYFUNCTION("""COMPUTED_VALUE"""),0.24) -> 0.24
A49: 100 kg | B49: Rodante | C49: =IFERROR(__xludf.DUMMYFUNCTION("""COMPUTED_VALUE"""),1) -> 1 | D49: =IFERROR(__xludf.DUMMYFUNCTION("""COMPUTED_VALUE"""),0.08) -> 0.08 | E49: =IFERROR(__xludf.DUMMYFUNCTION("""COMPUTED_VALUE"""),0.08) -> 0.08 | F49: =IFERROR(__xludf.DUMMYFUNCTION("""COMPUTED_VALUE"""),0.08) -> 0.08 | G49: =IFERROR(__xludf.DUMMYFUNCTION("""COMPUTED_VALUE"""),0.08) -> 0.08 | H49: =IFERROR(__xludf.DUMMYFUNCTION("""COMPUTED_VALUE"""),1.08) -> 1.08 | I49: =IFERROR(__xludf.DUMMYFUNCTION("""COMPUTED_VALUE"""),0.16) -> 0.16 | J49: =IFERROR(__xludf.DUMMYFUNCTION("""COMPUTED_VALUE"""),0.16) -> 0.16 | K49: =IFERROR(__xludf.DUMMYFUNCTION("""COMPUTED_VALUE"""),0.16) -> 0.16 | L49: =IFERROR(__xludf.DUMMYFUNCTION("""COMPUTED_VALUE"""),0.16) -> 0.16
A50: Total | C50: =SUM(C42:C49) -> 19 | D50: =SUM(D42:D49) -> 43.52 | E50: =SUM(E42:E49) -> 74.88 | F50: =SUM(F42:F49) -> 123.48 | G50: =SUM(G42:G49) -> 126.52 | H50: =SUM(H42:H49) -> 144.08 | I50: =SUM(I42:I49) -> 119.36 | J50: =SUM(J42:J49) -> 104.92 | ... L50: =SUM(L42:L49) -> 101.56
A52: Sustitutos ABC cilindros vacíos para la planta comercial de recargas
A53: Formato | B53: Línea | C53: 2026 | D53: 2027 | E53: 2028 | F53: 2029 | G53: 2030 | H53: 2031 | I53: 2032 | J53: 2033 | K53: 2034 | L53: 2035
A54: 1 kg | B54: Manual | C54: =IFERROR(__xludf.DUMMYFUNCTION("IMPORTRANGE(Links!$B$5,""sobrestock_sustitutos!B73:K76"")"),0) -> 0 | D54: =IFERROR(__xludf.DUMMYFUNCTION("""COMPUTED_VALUE"""),0) -> 0 | E54: =IFERROR(__xludf.DUMMYFUNCTION("""COMPUTED_VALUE"""),0) -> 0 | F54: =IFERROR(__xludf.DUMMYFUNCTION("""COMPUTED_VALUE"""),0) -> 0 | G54: =IFERROR(__xludf.DUMMYFUNCTION("""COMPUTED_VALUE"""),0) -> 0 | H54: =IFERROR(__xludf.DUMMYFUNCTION("""COMPUTED_VALUE"""),0) -> 0 | I54: =IFERROR(__xludf.DUMMYFUNCTION("""COMPUTED_VALUE"""),0) -> 0 | J54: =IFERROR(__xludf.DUMMYFUNCTION("""COMPUTED_VALUE"""),0) -> 0 | K54: =IFERROR(__xludf.DUMMYFUNCTION("""COMPUTED_VALUE"""),0) -> 0 | L54: =IFERROR(__xludf.DUMMYFUNCTION("""COMPUTED_VALUE"""),0) -> 0
A55: 2,5 kg | B55: Manual | C55: =IFERROR(__xludf.DUMMYFUNCTION("""COMPUTED_VALUE"""),4) -> 4 | D55: =IFERROR(__xludf.DUMMYFUNCTION("""COMPUTED_VALUE"""),11.32) -> 11.32 | E55: =IFERROR(__xludf.DUMMYFUNCTION("""COMPUTED_VALUE"""),20.2) -> 20.2 | F55: =IFERROR(__xludf.DUMMYFUNCTION("""COMPUTED_VALUE"""),30.72) -> 30.72 | G55: =IFERROR(__xludf.DUMMYFUNCTION("""COMPUTED_VALUE"""),32.96) -> 32.96 | H55: =IFERROR(__xludf.DUMMYFUNCTION("""COMPUTED_VALUE"""),36.2) -> 36.2 | I55: =IFERROR(__xludf.DUMMYFUNCTION("""COMPUTED_VALUE"""),33.52) -> 33.52 | J55: =IFERROR(__xludf.DUMMYFUNCTION("""COMPUTED_VALUE"""),27.44) -> 27.44 | K55: =IFERROR(__xludf.DUMMYFUNCTION("""COMPUTED_VALUE"""),25.72) -> 25.72 | L55: =IFERROR(__xludf.DUMMYFUNCTION("""COMPUTED_VALUE"""),26.76) -> 26.76
A56: 5 kg | B56: Manual | C56: =IFERROR(__xludf.DUMMYFUNCTION("""COMPUTED_VALUE"""),20) -> 20 | D56: =IFERROR(__xludf.DUMMYFUNCTION("""COMPUTED_VALUE"""),59.6) -> 59.6 | E56: =IFERROR(__xludf.DUMMYFUNCTION("""COMPUTED_VALUE"""),103.24) -> 103.24 | F56: =IFERROR(__xludf.DUMMYFUNCTION("""COMPUTED_VALUE"""),170) -> 170 | G56: =IFERROR(__xludf.DUMMYFUNCTION("""COMPUTED_VALUE"""),172.48) -> 172.48 | H56: =IFERROR(__xludf.DUMMYFUNCTION("""COMPUTED_VALUE"""),195.16) -> 195.16 | I56: =IFERROR(__xludf.DUMMYFUNCTION("""COMPUTED_VALUE"""),169.72) -> 169.72 | J56: =IFERROR(__xludf.DUMMYFUNCTION("""COMPUTED_VALUE"""),141.24) -> 141.24 | K56: =IFERROR(__xludf.DUMMYFUNCTION("""COMPUTED_VALUE"""),132.72) -> 132.72 | L56: =IFERROR(__xludf.DUMMYFUNCTION("""COMPUTED_VALUE"""),139) -> 139
A57: 10 kg | B57: Manual | C57: =IFERROR(__xludf.DUMMYFUNCTION("""COMPUTED_VALUE"""),2) -> 2 | D57: =IFERROR(__xludf.DUMMYFUNCTION("""COMPUTED_VALUE"""),4.16) -> 4.16 | E57: =IFERROR(__xludf.DUMMYFUNCTION("""COMPUTED_VALUE"""),8.48) -> 8.48 | F57: =IFERROR(__xludf.DUMMYFUNCTION("""COMPUTED_VALUE"""),13.12) -> 13.12 | G57: =IFERROR(__xludf.DUMMYFUNCTION("""COMPUTED_VALUE"""),13.08) -> 13.08 | H57: =IFERROR(__xludf.DUMMYFUNCTION("""COMPUTED_VALUE"""),15.96) -> 15.96 | I57: =IFERROR(__xludf.DUMMYFUNCTION("""COMPUTED_VALUE"""),11) -> 11 | J57: =IFERROR(__xludf.DUMMYFUNCTION("""COMPUTED_VALUE"""),10.56) -> 10.56 | K57: =IFERROR(__xludf.DUMMYFUNCTION("""COMPUTED_VALUE"""),10.04) -> 10.04 | L57: =IFERROR(__xludf.DUMMYFUNCTION("""COMPUTED_VALUE"""),10.44) -> 10.44
A58: 25 kg | B58: Rodante | C58: =IFERROR(__xludf.DUMMYFUNCTION("IMPORTRANGE(Links!$B$5,""sobrestock_sustitutos!B86:K89"")"),1) -> 1 | D58: =IFERROR(__xludf.DUMMYFUNCTION("""COMPUTED_VALUE"""),0.08) -> 0.08 | E58: =IFERROR(__xludf.DUMMYFUNCTION("""COMPUTED_VALUE"""),1.08) -> 1.08 | F58: =IFERROR(__xludf.DUMMYFUNCTION("""COMPUTED_VALUE"""),2.16) -> 2.16 | G58: =IFERROR(__xludf.DUMMYFUNCTION("""COMPUTED_VALUE"""),1.32) -> 1.32 | H58: =IFERROR(__xludf.DUMMYFUNCTION("""COMPUTED_VALUE"""),1.4) -> 1.4 | I58: =IFERROR(__xludf.DUMMYFUNCTION("""COMPUTED_VALUE"""),1.48) -> 1.48 | J58: =IFERROR(__xludf.DUMMYFUNCTION("""COMPUTED_VALUE"""),1.56) -> 1.56 | K58: =IFERROR(__xludf.DUMMYFUNCTION("""COMPUTED_VALUE"""),0.64) -> 0.64 | L58: =IFERROR(__xludf.DUMMYFUNCTION("""COMPUTED_VALUE"""),1.64) -> 1.64
A59: 50 kg | B59: Rodante | C59: =IFERROR(__xludf.DUMMYFUNCTION("""COMPUTED_VALUE"""),1) -> 1 | D59: =IFERROR(__xludf.DUMMYFUNCTION("""COMPUTED_VALUE"""),1.08) -> 1.08 | E59: =IFERROR(__xludf.DUMMYFUNCTION("""COMPUTED_VALUE"""),2.16) -> 2.16 | F59: =IFERROR(__xludf.DUMMYFUNCTION("""COMPUTED_VALUE"""),3.32) -> 3.32 | G59: =IFERROR(__xludf.DUMMYFUNCTION("""COMPUTED_VALUE"""),3.56) -> 3.56 | H59: =IFERROR(__xludf.DUMMYFUNCTION("""COMPUTED_VALUE"""),3.8) -> 3.8 | I59: =IFERROR(__xludf.DUMMYFUNCTION("""COMPUTED_VALUE"""),3.04) -> 3.04 | J59: =IFERROR(__xludf.DUMMYFUNCTION("""COMPUTED_VALUE"""),3.2) -> 3.2 | K59: =IFERROR(__xludf.DUMMYFUNCTION("""COMPUTED_VALUE"""),2.36) -> 2.36 | L59: =IFERROR(__xludf.DUMMYFUNCTION("""COMPUTED_VALUE"""),2.44) -> 2.44
A60: 70 kg | B60: Rodante | C60: =IFERROR(__xludf.DUMMYFUNCTION("""COMPUTED_VALUE"""),1) -> 1 | D60: =IFERROR(__xludf.DUMMYFUNCTION("""COMPUTED_VALUE"""),0.08) -> 0.08 | E60: =IFERROR(__xludf.DUMMYFUNCTION("""COMPUTED_VALUE"""),0.08) -> 0.08 | F60: =IFERROR(__xludf.DUMMYFUNCTION("""COMPUTED_VALUE"""),1.08) -> 1.08 | G60: =IFERROR(__xludf.DUMMYFUNCTION("""COMPUTED_VALUE"""),1.16) -> 1.16 | H60: =IFERROR(__xludf.DUMMYFUNCTION("""COMPUTED_VALUE"""),0.24) -> 0.24 | I60: =IFERROR(__xludf.DUMMYFUNCTION("""COMPUTED_VALUE"""),1.24) -> 1.24 | J60: =IFERROR(__xludf.DUMMYFUNCTION("""COMPUTED_VALUE"""),0.32) -> 0.32 | K60: =IFERROR(__xludf.DUMMYFUNCTION("""COMPUTED_VALUE"""),0.32) -> 0.32 | L60: =IFERROR(__xludf.DUMMYFUNCTION("""COMPUTED_VALUE"""),1.32) -> 1.32
A61: 100 kg | B61: Rodante | C61: =IFERROR(__xludf.DUMMYFUNCTION("""COMPUTED_VALUE"""),1) -> 1 | D61: =IFERROR(__xludf.DUMMYFUNCTION("""COMPUTED_VALUE"""),0.08) -> 0.08 | E61: =IFERROR(__xludf.DUMMYFUNCTION("""COMPUTED_VALUE"""),0.08) -> 0.08 | F61: =IFERROR(__xludf.DUMMYFUNCTION("""COMPUTED_VALUE"""),0.08) -> 0.08 | G61: =IFERROR(__xludf.DUMMYFUNCTION("""COMPUTED_VALUE"""),1.08) -> 1.08 | H61: =IFERROR(__xludf.DUMMYFUNCTION("""COMPUTED_VALUE"""),0.16) -> 0.16 | I61: =IFERROR(__xludf.DUMMYFUNCTION("""COMPUTED_VALUE"""),1.16) -> 1.16 | J61: =IFERROR(__xludf.DUMMYFUNCTION("""COMPUTED_VALUE"""),0.24) -> 0.24 | K61: =IFERROR(__xludf.DUMMYFUNCTION("""COMPUTED_VALUE"""),0.24) -> 0.24 | L61: =IFERROR(__xludf.DUMMYFUNCTION("""COMPUTED_VALUE"""),0.24) -> 0.24
A62: Total | C62: =SUM(C54:C61) -> 30 | D62: =SUM(D54:D61) -> 76.4 | E62: =SUM(E54:E61) -> 135.32 | F62: =SUM(F54:F61) -> 220.48 | G62: =SUM(G54:G61) -> 225.64 | H62: =SUM(H54:H61) -> 252.92 | I62: =SUM(I54:I61) -> 221.16 | J62: =SUM(J54:J61) -> 184.56 | ... L62: =SUM(L54:L61) -> 181.84
A64: Discos de rodantes (25 a 100 kg): se compran embutidos, no entran en este análisis.

Sheet Piezas
A1: Piezas del plano: cuerpos y discos de cúpula y fondo
A2: Medidas de los planos de recipiente (modelo 3D). El disco sale de la pieza embutida por igualdad de superficie, con su relación de embutido.
A4: A) Cuerpos (desarrollo = π·(Ø − e), fibra media)
A5: Formato | B5: Línea | C5: Plano | D5: Ø ext. (mm) | E5: Espesor (mm) | F5: Alto (mm) | G5: Desarrollo (mm) | H5: Masa (kg) | I5: Acero
A6: 1 kg | B6: Manual | C6: Plano recipiente 1 kg 3" R1 | D6: 76.2 | E6: 0.9 | F6: 263.5 | G6: =ROUND(PI()*(D6-E6)*2,0)/2 -> 236.5 | H6: =F6*G6*E6*Datos!$B$10/1000000 -> 0.44139662 | I6: LAF
A7: 2,5 kg | B7: Manual | C7: Plano recipiente 2,5 kg R2 | D7: 124 | E7: 1.25 | F7: 267.5 | G7: =ROUND(PI()*(D7-E7)*2,0)/2 -> 385.5 | H7: =F7*G7*E7*Datos!$B$10/1000000 -> 1.0144553 | I7: LAF
A8: 5 kg | B8: Manual | C8: Plano recipiente 5 kg R2 | D8: 153 | E8: 1.6 | F8: 327.5 | G8: =ROUND(PI()*(D8-E8)*2,0)/2 -> 475.5 | H8: =F8*G8*E8*Datos!$B$10/1000000 -> 1.9609049 | I8: LAF
A9: 10 kg | B9: Manual | C9: Plano recipiente 10 kg R2 | D9: 181.5 | E9: 2 | F9: 493 | G9: =ROUND(PI()*(D9-E9)*2,0)/2 -> 564 | H9: =F9*G9*E9*Datos!$B$10/1000000 -> 4.3765385 | I9: LAF
A10: 25 kg | B10: Rodante | C10: Plano recipiente 25 kg R3 | D10: 276.5 | E10: 3.2 | F10: 493 | G10: =ROUND(PI()*(D10-E10)*2,0)/2 -> 858.5 | H10: =F10*G10*E10*Datos!$B$10/1000000 -> 10.658889 | I10: LAC
A11: 50 kg | B11: Rodante | C11: Plano recipiente 50 kg R2 | D11: 320 | E11: 3.2 | F11: 640 | G11: =ROUND(PI()*(D11-E11)*2,0)/2 -> 995.5 | H11: =F11*G11*E11*Datos!$B$10/1000000 -> 16.04523 | I11: LAC
A12: 70 kg | B12: Rodante | C12: Plano extintor rodante 70 kg (Ø390) | D12: 390 | E12: 4.75 | F12: 680 | G12: =ROUND(PI()*(D12-E12)*2,0)/2 -> 1210.5 | H12: =F12*G12*E12*Datos!$B$10/1000000 -> 30.771031 | I12: LAC
A13: 100 kg | B13: Rodante | C13: Plano extintor rodante 100 kg R1 (Ø390) | D13: 390 | E13: 4.75 | F13: 900 | G13: =ROUND(PI()*(D13-E13)*2,0)/2 -> 1210.5 | H13: =F13*G13*E13*Datos!$B$10/1000000 -> 40.726365 | I13: LAC
A14: Alto: cuerpo del modelo 3D del plano (incluye el labio del encastre). 1 kg en chapa de 0,9 mm por decisión del grupo.
A16: B) Discos: igual superficie que la pieza embutida (sin sobremedida de recorte)
A17: Formato | B17: Pieza | C17: Perfil del plano | D17: Espesor e (mm) | E17: Ø ext. (mm) | F17: Altura h (mm) | G17: Pollera o pestaña p (mm) | H17: a = Ø/2 − e/2 (mm) | I17: b o profundidad (mm) | J17: Área media (mm²) | K17: D0 = √(4A/π) (mm) | L17: D0 adoptado (mm) | M17: d = 2a (mm) | N17: m = d/D0 | O17: e/D0 × 100 | P17: m1 mínimo | Q17: ¿Un solo embutido? | R17: h/d | S17: Masa del disco (kg) | T17: Plano | V17: e/D0 × 100 desde | W17: hasta | X17: m1 (1.er embutido)
A18: 1 kg | B18: Cúpula | C18: Semielipsoide + pollera | D18: 0.9 | E18: 76.2 | F18: 12.5 | G18: 6 | H18: =E18/2-D18/2 -> 37.65 | I18: =F18-G18-D18/2 -> 6.05 | J18: =PI()*H18^2+PI()*I18^2/(2*SQRT(1-(I18/H18)^2))*LN((1+SQRT(1-(I18/H18)^2))/(1-SQRT(1-(I18/H18)^2)))+2*PI()*H18*G18 -> 6165.6464 | K18: =SQRT(4*J18/PI()) -> 88.602172 | L18: =CEILING(K18,0.5) -> 89 | M18: =2*H18 -> 75.3 | N18: =M18/L18 -> 0.84606742 | O18: =D18/L18*100 -> 1.011236 | P18: =INDEX($X$18:$X$23,MATCH(O18,$V$18:$V$23,1)) -> 0.53 | Q18: =IF(N18>=P18,"Sí","No: dos embutidos") -> Sí | R18: =F18/E18 -> 0.16404199 | S18: =PI()*L18^2/4*D18*Datos!$B$10/1000000 -> 0.044064326 | T18: Plano recipiente 1 kg 3" R1 | V18: 0.08 | W18: 0.15 | X18: 0.63
A19: 1 kg | B19: Fondo | C19: Semielipsoide + pollera | D19: 1.25 | E19: 76.2 | F19: 22 | G19: 6 | H19: =E19/2-D19/2 -> 37.475 | I19: =F19-G19-D19/2 -> 15.375 | J19: =PI()*H19^2+PI()*I19^2/(2*SQRT(1-(I19/H19)^2))*LN((1+SQRT(1-(I19/H19)^2))/(1-SQRT(1-(I19/H19)^2)))+2*PI()*H19*G19 -> 7078.062 | K19: =SQRT(4*J19/PI()) -> 94.931915 | L19: =CEILING(K19,0.5) -> 95 | M19: =2*H19 -> 74.95 | N19: =M19/L19 -> 0.78894737 | O19: =D19/L19*100 -> 1.3157895 | P19: =INDEX($X$18:$X$23,MATCH(O19,$V$18:$V$23,1)) -> 0.53 | Q19: =IF(N19>=P19,"Sí","No: dos embutidos") -> Sí | R19: =F19/E19 -> 0.28871391 | S19: =PI()*L19^2/4*D19*Datos!$B$10/1000000 -> 0.069730349 | T19: Plano recipiente 1 kg 3" R1 | V19: 0.15 | W19: 0.3 | X19: 0.6
A20: 2,5 kg | B20: Cúpula | C20: Semielipsoide + pollera | D20: 1.25 | E20: 124 | F20: 39.5 | G20: 6 | H20: =E20/2-D20/2 -> 61.375 | I20: =F20-G20-D20/2 -> 32.875 | J20: =PI()*H20^2+PI()*I20^2/(2*SQRT(1-(I20/H20)^2))*LN((1+SQRT(1-(I20/H20)^2))/(1-SQRT(1-(I20/H20)^2)))+2*PI()*H20*G20 -> 19119.382 | K20: =SQRT(4*J20/PI()) -> 156.02421 | L20: =CEILING(K20,0.5) -> 156.5 | M20: =2*H20 -> 122.75 | N20: =M20/L20 -> 0.78434505 | O20: =D20/L20*100 -> 0.79872204 | P20: =INDEX($X$18:$X$23,MATCH(O20,$V$18:$V$23,1)) -> 0.55 | Q20: =IF(N20>=P20,"Sí","No: dos embutidos") -> Sí | R20: =F20/E20 -> 0.31854839 | S20: =PI()*L20^2/4*D20*Datos!$B$10/1000000 -> 0.1892358 | T20: Plano recipiente 2,5 kg R2 | V20: 0.3 | W20: 0.6 | X20: 0.58
A21: 2,5 kg | B21: Fondo | C21: Paraboloide + pestaña | D21: 1.25 | E21: 121.5 | F21: 10.5 | G21: 10 | H21: =E21/2-D21/2 -> 60.125 | I21: =F21 -> 10.5 | J21: =PI()*H21^4/(6*I21^2)*((1+4*I21^2/H21^2)^1.5-1)+2*PI()*H21*G21 -> 15474.294 | K21: =SQRT(4*J21/PI()) -> 140.36553 | L21: =CEILING(K21,0.5) -> 140.5 | M21: =2*H21 -> 120.25 | N21: =M21/L21 -> 0.85587189 | O21: =D21/L21*100 -> 0.88967972 | P21: =INDEX($X$18:$X$23,MATCH(O21,$V$18:$V$23,1)) -> 0.55 | Q21: =IF(N21>=P21,"Sí","No: dos embutidos") -> Sí | R21: =(F21+G21)/E21 -> 0.16872428 | S21: =PI()*L21^2/4*D21*Datos!$B$10/1000000 -> 0.15252017 | T21: Plano recipiente 2,5 kg R2; Ø del fondo = Ø del cuerpo − 2 e | V21: 0.6 | W21: 1 | X21: 0.55
A22: 5 kg | B22: Cúpula | C22: Semielipsoide + pollera | D22: 1.6 | E22: 153 | F22: 54.5 | G22: 6 | H22: =E22/2-D22/2 -> 75.7 | I22: =F22-G22-D22/2 -> 47.7 | J22: =PI()*H22^2+PI()*I22^2/(2*SQRT(1-(I22/H22)^2))*LN((1+SQRT(1-(I22/H22)^2))/(1-SQRT(1-(I22/H22)^2)))+2*PI()*H22*G22 -> 30398.075 | K22: =SQRT(4*J22/PI()) -> 196.7334 | L22: =CEILING(K22,0.5) -> 197 | M22: =2*H22 -> 151.4 | N22: =M22/L22 -> 0.76852792 | O22: =D22/L22*100 -> 0.81218274 | P22: =INDEX($X$18:$X$23,MATCH(O22,$V$18:$V$23,1)) -> 0.55 | Q22: =IF(N22>=P22,"Sí","No: dos embutidos") -> Sí | R22: =F22/E22 -> 0.35620915 | S22: =PI()*L22^2/4*D22*Datos!$B$10/1000000 -> 0.38381067 | T22: Plano recipiente 5 kg R2 | V22: 1 | W22: 1.5 | X22: 0.53
A23: 5 kg | B23: Fondo | C23: Paraboloide + pestaña | D23: 1.6 | E23: 149.8 | F23: 16 | G23: 10 | H23: =E23/2-D23/2 -> 74.1 | I23: =F23 -> 16 | J23: =PI()*H23^4/(6*I23^2)*((1+4*I23^2/H23^2)^1.5-1)+2*PI()*H23*G23 -> 22686.58 | K23: =SQRT(4*J23/PI()) -> 169.9572 | L23: =CEILING(K23,0.5) -> 170 | M23: =2*H23 -> 148.2 | N23: =M23/L23 -> 0.87176471 | O23: =D23/L23*100 -> 0.94117647 | P23: =INDEX($X$18:$X$23,MATCH(O23,$V$18:$V$23,1)) -> 0.55 | Q23: =IF(N23>=P23,"Sí","No: dos embutidos") -> Sí | R23: =(F23+G23)/E23 -> 0.17356475 | S23: =PI()*L23^2/4*D23*Datos!$B$10/1000000 -> 0.2858133 | T23: Plano recipiente 5 kg R2; Ø del fondo = Ø del cuerpo − 2 e | V23: 1.5 | W23: 2 | X23: 0.5
A24: 10 kg | B24: Cúpula | C24: Semielipsoide + pollera | D24: 1.6 | E24: 181.5 | F24: 62.5 | G24: 6 | H24: =E24/2-D24/2 -> 89.95 | I24: =F24-G24-D24/2 -> 55.7 | J24: =PI()*H24^2+PI()*I24^2/(2*SQRT(1-(I24/H24)^2))*LN((1+SQRT(1-(I24/H24)^2))/(1-SQRT(1-(I24/H24)^2)))+2*PI()*H24*G24 -> 41952.632 | K24: =SQRT(4*J24/PI()) -> 231.11848 | L24: =CEILING(K24,0.5) -> 231.5 | M24: =2*H24 -> 179.9 | N24: =M24/L24 -> 0.77710583 | O24: =D24/L24*100 -> 0.69114471 | P24: =INDEX($X$18:$X$23,MATCH(O24,$V$18:$V$23,1)) -> 0.55 | Q24: =IF(N24>=P24,"Sí","No: dos embutidos") -> Sí | R24: =F24/E24 -> 0.34435262 | S24: =PI()*L24^2/4*D24*Datos!$B$10/1000000 -> 0.53001308 | T24: Plano recipiente 10 kg R2 | V24: Valor alto de cada rango (lado seguro).
A25: 10 kg | B25: Fondo | C25: Paraboloide + pestaña | D25: 2 | E25: 177.5 | F25: 11.7 | G25: 10 | H25: =E25/2-D25/2 -> 87.75 | I25: =F25 -> 11.7 | J25: =PI()*H25^4/(6*I25^2)*((1+4*I25^2/H25^2)^1.5-1)+2*PI()*H25*G25 -> 30129.042 | K25: =SQRT(4*J25/PI()) -> 195.86089 | L25: =CEILING(K25,0.5) -> 196 | M25: =2*H25 -> 175.5 | N25: =M25/L25 -> 0.89540816 | O25: =D25/L25*100 -> 1.0204082 | P25: =INDEX($X$18:$X$23,MATCH(O25,$V$18:$V$23,1)) -> 0.53 | Q25: =IF(N25>=P25,"Sí","No: dos embutidos") -> Sí | R25: =(F25+G25)/E25 -> 0.12225352 | S25: =PI()*L25^2/4*D25*Datos!$B$10/1000000 -> 0.47490501 | T25: Plano recipiente 10 kg R2; Ø del fondo = Ø del cuerpo − 2 e
A27: Fuentes
A28: Disco y pieza tienen la misma superficie (el espesor no cambia): Harsle, «How to Calculate Deep Drawing Parts» (harslepress.com).
A29: Superficie del semielipsoide achatado y del paraboloide de revolución: fórmulas de geometría (MathWorld, «Oblate Spheroid» y «Paraboloid»).
A30: m1: relación de embutido del primer paso, copa sin brida, con prensachapas (EasyChair, preprint Vxvp, tabla 2). Límite general D0/d ≤ 2 (Univ. Mustansiriyah, apunte de embutido).
A31: Sin sobremedida de recorte: la prensa corta y embute en el mismo golpe, sin recorte después (W-MAN, puesto 4), y la tabla de recorte de Harsle arranca en h/d = 0,5 (estas piezas tienen h/d de 0,12 a 0,36).
A32: Geometría (Ø, alturas, pollera de 6 mm, pestaña de 10 mm, espesores): planos de recipiente (modelo 3D).

Sheet Corte
A1: Corte: cómo sale cada pieza de la hoja, la bobina, el fleje y la bobina madre
A2: Medidas de la hoja Piezas. Dos guillotinas en serie: G1 corta franjas, pasan por un pulmón y G2 apoya varias franjas una al lado de la otra y corta una pieza de cada una por golpe.
A4: A) Cuerpos en hoja estándar con dos guillotinas en serie (B y D)
A5: Formato | B5: Hoja ancho (mm) | C5: Hoja largo (mm) | D5: Piezas por hoja | E5: Aprovech. | F5: Franja = 1.er corte (mm) | G5: Franjas por hoja | H5: Piezas por franja | I5: Pieza = 2.º corte (mm) | J5: Tope de G1 en el 1.er corte (mm) | K5: 2.º corte en | L5: Franjas en paralelo | M5: Golpes G1 por hoja | N5: Golpes G2 por hoja | O5: Minutos de guillotina por hoja | P5: Masa de la hoja (kg) | Q5: USD por hoja | R5: Control
A6: 1 kg | B6: 1220 | C6: 2440 | D6: =MAX(INT(B6/Piezas!$F$6)*INT(C6/Piezas!$G$6),INT(B6/Piezas!$G$6)*INT(C6/Piezas!$F$6)) -> 45 | E6: =D6*Piezas!$F$6*Piezas!$G$6/(B6*C6) -> 0.94205145 | F6: =IF(INT(B6/Piezas!$F$6)*INT(C6/Piezas!$G$6)>=INT(B6/Piezas!$G$6)*INT(C6/Piezas!$F$6),Piezas!$F$6,Piezas!$G$6) -> 236.5 | G6: =INT(B6/F6) -> 5 | H6: =IF(INT(B6/Piezas!$F$6)*INT(C6/Piezas!$G$6)>=INT(B6/Piezas!$G$6)*INT(C6/Piezas!$F$6),INT(C6/Piezas!$G$6),INT(C6/Piezas!$F$6)) -> 9 | I6: =IF(INT(B6/Piezas!$F$6)*INT(C6/Piezas!$G$6)>=INT(B6/Piezas!$G$6)*INT(C6/Piezas!$F$6),Piezas!$G$6,Piezas!$F$6) -> 263.5 | J6: =IF(F6<=Datos!$B$32,F6,B6-F6*G6) -> 236.5 | K6: =IF(AND(I6<=Datos!$B$35,F6<=Datos!$B$34),"G2","G1") -> G2 | L6: =INT(IF(K6="G2",Datos!$B$34,Datos!$B$31)/F6) -> 10 | M6: =G6+IF(K6="G1",G6*H6/L6,0) -> 5 | N6: =IF(K6="G2",G6*H6/L6,0) -> 4.5 | O6: =M6/Datos!$B$30+N6/Datos!$B$33 -> 0.725 | P6: =B6*C6*Piezas!$E$6*Datos!$B$10/1000000 -> 21.084674 | Q6: =P6*INDEX(Datos!$C$90:$C$95,MATCH(Piezas!$E$6,Datos!$A$90:$A$95,0)) -> 28.592927 | R6: =IF(C6>Datos!$B$31,"Hoja más larga que la cuchilla de G1",IF(J6>Datos!$B$32,"Franja mayor que el tope de G1",IF(AND(K6="G1",I6>Datos!$B$32),"Pieza mayor que el tope de G1: va en la hoja mixta","OK"))) -> OK
A7: 2,5 kg | B7: 1220 | C7: 2440 | D7: =MAX(INT(B7/Piezas!$F$7)*INT(C7/Piezas!$G$7),INT(B7/Piezas!$G$7)*INT(C7/Piezas!$F$7)) -> 27 | E7: =D7*Piezas!$F$7*Piezas!$G$7/(B7*C7) -> 0.93532443 | F7: =IF(INT(B7/Piezas!$F$7)*INT(C7/Piezas!$G$7)>=INT(B7/Piezas!$G$7)*INT(C7/Piezas!$F$7),Piezas!$F$7,Piezas!$G$7) -> 385.5 | G7: =INT(B7/F7) -> 3 | H7: =IF(INT(B7/Piezas!$F$7)*INT(C7/Piezas!$G$7)>=INT(B7/Piezas!$G$7)*INT(C7/Piezas!$F$7),INT(C7/Piezas!$G$7),INT(C7/Piezas!$F$7)) -> 9 | I7: =IF(INT(B7/Piezas!$F$7)*INT(C7/Piezas!$G$7)>=INT(B7/Piezas!$G$7)*INT(C7/Piezas!$F$7),Piezas!$G$7,Piezas!$F$7) -> 267.5 | J7: =IF(F7<=Datos!$B$32,F7,B7-F7*G7) -> 385.5 | K7: =IF(AND(I7<=Datos!$B$35,F7<=Datos!$B$34),"G2","G1") -> G2 | L7: =INT(IF(K7="G2",Datos!$B$34,Datos!$B$31)/F7) -> 6 | M7: =G7+IF(K7="G1",G7*H7/L7,0) -> 3 | N7: =IF(K7="G2",G7*H7/L7,0) -> 4.5 | O7: =M7/Datos!$B$30+N7/Datos!$B$33 -> 0.525 | P7: =B7*C7*Piezas!$E$7*Datos!$B$10/1000000 -> 29.28427 | Q7: =P7*INDEX(Datos!$C$90:$C$95,MATCH(Piezas!$E$7,Datos!$A$90:$A$95,0)) -> 37.785427 | R7: =IF(C7>Datos!$B$31,"Hoja más larga que la cuchilla de G1",IF(J7>Datos!$B$32,"Franja mayor que el tope de G1",IF(AND(K7="G1",I7>Datos!$B$32),"Pieza mayor que el tope de G1: va en la hoja mixta","OK"))) -> OK
A8: 5 kg | B8: 1000 | C8: 2000 | D8: =MAX(INT(B8/Piezas!$F$8)*INT(C8/Piezas!$G$8),INT(B8/Piezas!$G$8)*INT(C8/Piezas!$F$8)) -> 12 | E8: =D8*Piezas!$F$8*Piezas!$G$8/(B8*C8) -> 0.9343575 | F8: =IF(INT(B8/Piezas!$F$8)*INT(C8/Piezas!$G$8)>=INT(B8/Piezas!$G$8)*INT(C8/Piezas!$F$8),Piezas!$F$8,Piezas!$G$8) -> 327.5 | G8: =INT(B8/F8) -> 3 | H8: =IF(INT(B8/Piezas!$F$8)*INT(C8/Piezas!$G$8)>=INT(B8/Piezas!$G$8)*INT(C8/Piezas!$F$8),INT(C8/Piezas!$G$8),INT(C8/Piezas!$F$8)) -> 4 | I8: =IF(INT(B8/Piezas!$F$8)*INT(C8/Piezas!$G$8)>=INT(B8/Piezas!$G$8)*INT(C8/Piezas!$F$8),Piezas!$G$8,Piezas!$F$8) -> 475.5 | J8: =IF(F8<=Datos!$B$32,F8,B8-F8*G8) -> 327.5 | K8: =IF(AND(I8<=Datos!$B$35,F8<=Datos!$B$34),"G2","G1") -> G2 | L8: =INT(IF(K8="G2",Datos!$B$34,Datos!$B$31)/F8) -> 7 | M8: =G8+IF(K8="G1",G8*H8/L8,0) -> 3 | N8: =IF(K8="G2",G8*H8/L8,0) -> 1.7142857 | O8: =M8/Datos!$B$30+N8/Datos!$B$33 -> 0.38571429 | P8: =B8*C8*Piezas!$E$8*Datos!$B$10/1000000 -> 25.184 | Q8: =P8*INDEX(Datos!$C$90:$C$95,MATCH(Piezas!$E$8,Datos!$A$90:$A$95,0)) -> 33.43229 | R8: =IF(C8>Datos!$B$31,"Hoja más larga que la cuchilla de G1",IF(J8>Datos!$B$32,"Franja mayor que el tope de G1",IF(AND(K8="G1",I8>Datos!$B$32),"Pieza mayor que el tope de G1: va en la hoja mixta","OK"))) -> OK
A9: 10 kg | B9: 1500 | C9: 3000 | D9: =MAX(INT(B9/Piezas!$F$9)*INT(C9/Piezas!$G$9),INT(B9/Piezas!$G$9)*INT(C9/Piezas!$F$9)) -> 15 | E9: =D9*Piezas!$F$9*Piezas!$G$9/(B9*C9) -> 0.92684 | F9: =IF(INT(B9/Piezas!$F$9)*INT(C9/Piezas!$G$9)>=INT(B9/Piezas!$G$9)*INT(C9/Piezas!$F$9),Piezas!$F$9,Piezas!$G$9) -> 493 | G9: =INT(B9/F9) -> 3 | H9: =IF(INT(B9/Piezas!$F$9)*INT(C9/Piezas!$G$9)>=INT(B9/Piezas!$G$9)*INT(C9/Piezas!$F$9),INT(C9/Piezas!$G$9),INT(C9/Piezas!$F$9)) -> 5 | I9: =IF(INT(B9/Piezas!$F$9)*INT(C9/Piezas!$G$9)>=INT(B9/Piezas!$G$9)*INT(C9/Piezas!$F$9),Piezas!$G$9,Piezas!$F$9) -> 564 | J9: =IF(F9<=Datos!$B$32,F9,B9-F9*G9) -> 493 | K9: =IF(AND(I9<=Datos!$B$35,F9<=Datos!$B$34),"G2","G1") -> G2 | L9: =INT(IF(K9="G2",Datos!$B$34,Datos!$B$31)/F9) -> 5 | M9: =G9+IF(K9="G1",G9*H9/L9,0) -> 3 | N9: =IF(K9="G2",G9*H9/L9,0) -> 3 | O9: =M9/Datos!$B$30+N9/Datos!$B$33 -> 0.45 | P9: =B9*C9*Piezas!$E$9*Datos!$B$10/1000000 -> 70.83 | Q9: =P9*INDEX(Datos!$C$90:$C$95,MATCH(Piezas!$E$9,Datos!$A$90:$A$95,0)) -> 90.690824 | R9: =IF(C9>Datos!$B$31,"Hoja más larga que la cuchilla de G1",IF(J9>Datos!$B$32,"Franja mayor que el tope de G1",IF(AND(K9="G1",I9>Datos!$B$32),"Pieza mayor que el tope de G1: va en la hoja mixta","OK"))) -> OK
A10: 25 kg | B10: 1500 | C10: 3000 | D10: =MAX(INT(B10/Piezas!$F$10)*INT(C10/Piezas!$G$10),INT(B10/Piezas!$G$10)*INT(C10/Piezas!$F$10)) -> 9 | E10: =D10*Piezas!$F$10*Piezas!$G$10/(B10*C10) -> 0.846481 | F10: =IF(INT(B10/Piezas!$F$10)*INT(C10/Piezas!$G$10)>=INT(B10/Piezas!$G$10)*INT(C10/Piezas!$F$10),Piezas!$F$10,Piezas!$G$10) -> 493 | G10: =INT(B10/F10) -> 3 | H10: =IF(INT(B10/Piezas!$F$10)*INT(C10/Piezas!$G$10)>=INT(B10/Piezas!$G$10)*INT(C10/Piezas!$F$10),INT(C10/Piezas!$G$10),INT(C10/Piezas!$F$10)) -> 3 | I10: =IF(INT(B10/Piezas!$F$10)*INT(C10/Piezas!$G$10)>=INT(B10/Piezas!$G$10)*INT(C10/Piezas!$F$10),Piezas!$G$10,Piezas!$F$10) -> 858.5 | J10: =IF(F10<=Datos!$B$32,F10,B10-F10*G10) -> 493 | K10: =IF(AND(I10<=Datos!$B$35,F10<=Datos!$B$34),"G2","G1") -> G1 | L10: =INT(IF(K10="G2",Datos!$B$34,Datos!$B$31)/F10) -> 6 | M10: =G10+IF(K10="G1",G10*H10/L10,0) -> 4.5 | N10: =IF(K10="G2",G10*H10/L10,0) -> 0 | O10: =M10/Datos!$B$30+N10/Datos!$B$33 -> 0.45 | P10: =B10*C10*Piezas!$E$10*Datos!$B$10/1000000 -> 113.328 | Q10: =P10*INDEX(Datos!$C$90:$C$95,MATCH(Piezas!$E$10,Datos!$A$90:$A$95,0)) -> 124.88012 | R10: =IF(C10>Datos!$B$31,"Hoja más larga que la cuchilla de G1",IF(J10>Datos!$B$32,"Franja mayor que el tope de G1",IF(AND(K10="G1",I10>Datos!$B$32),"Pieza mayor que el tope de G1: va en la hoja mixta","OK"))) -> OK
A11: 50 kg | B11: 1500 | C11: 3000 | D11: =MAX(INT(B11/Piezas!$F$11)*INT(C11/Piezas!$G$11),INT(B11/Piezas!$G$11)*INT(C11/Piezas!$F$11)) -> 6 | E11: =D11*Piezas!$F$11*Piezas!$G$11/(B11*C11) -> 0.84949333 | F11: =IF(INT(B11/Piezas!$F$11)*INT(C11/Piezas!$G$11)>=INT(B11/Piezas!$G$11)*INT(C11/Piezas!$F$11),Piezas!$F$11,Piezas!$G$11) -> 640 | G11: =INT(B11/F11) -> 2 | H11: =IF(INT(B11/Piezas!$F$11)*INT(C11/Piezas!$G$11)>=INT(B11/Piezas!$G$11)*INT(C11/Piezas!$F$11),INT(C11/Piezas!$G$11),INT(C11/Piezas!$F$11)) -> 3 | I11: =IF(INT(B11/Piezas!$F$11)*INT(C11/Piezas!$G$11)>=INT(B11/Piezas!$G$11)*INT(C11/Piezas!$F$11),Piezas!$G$11,Piezas!$F$11) -> 995.5 | J11: =IF(F11<=Datos!$B$32,F11,B11-F11*G11) -> 640 | K11: =IF(AND(I11<=Datos!$B$35,F11<=Datos!$B$34),"G2","G1") -> G1 | L11: =INT(IF(K11="G2",Datos!$B$34,Datos!$B$31)/F11) -> 5 | M11: =G11+IF(K11="G1",G11*H11/L11,0) -> 3.2 | N11: =IF(K11="G2",G11*H11/L11,0) -> 0 | O11: =M11/Datos!$B$30+N11/Datos!$B$33 -> 0.32 | P11: =B11*C11*Piezas!$E$11*Datos!$B$10/1000000 -> 113.328 | Q11: =P11*INDEX(Datos!$C$90:$C$95,MATCH(Piezas!$E$11,Datos!$A$90:$A$95,0)) -> 124.88012 | R11: =IF(C11>Datos!$B$31,"Hoja más larga que la cuchilla de G1",IF(J11>Datos!$B$32,"Franja mayor que el tope de G1",IF(AND(K11="G1",I11>Datos!$B$32),"Pieza mayor que el tope de G1: va en la hoja mixta","OK"))) -> OK
A12: 70 kg | B12: 1500 | C12: 3000 | D12: =MAX(INT(B12/Piezas!$F$12)*INT(C12/Piezas!$G$12),INT(B12/Piezas!$G$12)*INT(C12/Piezas!$F$12)) -> 4 | E12: =D12*Piezas!$F$12*Piezas!$G$12/(B12*C12) -> 0.73168 | F12: =IF(INT(B12/Piezas!$F$12)*INT(C12/Piezas!$G$12)>=INT(B12/Piezas!$G$12)*INT(C12/Piezas!$F$12),Piezas!$F$12,Piezas!$G$12) -> 680 | G12: =INT(B12/F12) -> 2 | H12: =IF(INT(B12/Piezas!$F$12)*INT(C12/Piezas!$G$12)>=INT(B12/Piezas!$G$12)*INT(C12/Piezas!$F$12),INT(C12/Piezas!$G$12),INT(C12/Piezas!$F$12)) -> 2 | I12: =IF(INT(B12/Piezas!$F$12)*INT(C12/Piezas!$G$12)>=INT(B12/Piezas!$G$12)*INT(C12/Piezas!$F$12),Piezas!$G$12,Piezas!$F$12) -> 1210.5 | J12: =IF(F12<=Datos!$B$32,F12,B12-F12*G12) -> 680 | K12: =IF(AND(I12<=Datos!$B$35,F12<=Datos!$B$34),"G2","G1") -> G1 | L12: =INT(IF(K12="G2",Datos!$B$34,Datos!$B$31)/F12) -> 4 | M12: =G12+IF(K12="G1",G12*H12/L12,0) -> 3 | N12: =IF(K12="G2",G12*H12/L12,0) -> 0 | O12: =M12/Datos!$B$30+N12/Datos!$B$33 -> 0.3 | P12: =B12*C12*Piezas!$E$12*Datos!$B$10/1000000 -> 168.22125 | Q12: =P12*INDEX(Datos!$C$90:$C$95,MATCH(Piezas!$E$12,Datos!$A$90:$A$95,0)) -> 183.52557 | R12: =IF(C12>Datos!$B$31,"Hoja más larga que la cuchilla de G1",IF(J12>Datos!$B$32,"Franja mayor que el tope de G1",IF(AND(K12="G1",I12>Datos!$B$32),"Pieza mayor que el tope de G1: va en la hoja mixta","OK"))) -> Pieza mayor que el tope de G1: va en la hoja mixta
A13: 100 kg | B13: 1500 | C13: 3000 | D13: =MAX(INT(B13/Piezas!$F$13)*INT(C13/Piezas!$G$13),INT(B13/Piezas!$G$13)*INT(C13/Piezas!$F$13)) -> 3 | E13: =D13*Piezas!$F$13*Piezas!$G$13/(B13*C13) -> 0.7263 | F13: =IF(INT(B13/Piezas!$F$13)*INT(C13/Piezas!$G$13)>=INT(B13/Piezas!$G$13)*INT(C13/Piezas!$F$13),Piezas!$F$13,Piezas!$G$13) -> 1210.5 | G13: =INT(B13/F13) -> 1 | H13: =IF(INT(B13/Piezas!$F$13)*INT(C13/Piezas!$G$13)>=INT(B13/Piezas!$G$13)*INT(C13/Piezas!$F$13),INT(C13/Piezas!$G$13),INT(C13/Piezas!$F$13)) -> 3 | I13: =IF(INT(B13/Piezas!$F$13)*INT(C13/Piezas!$G$13)>=INT(B13/Piezas!$G$13)*INT(C13/Piezas!$F$13),Piezas!$G$13,Piezas!$F$13) -> 900 | J13: =IF(F13<=Datos!$B$32,F13,B13-F13*G13) -> 289.5 | K13: =IF(AND(I13<=Datos!$B$35,F13<=Datos!$B$34),"G2","G1") -> G1 | L13: =INT(IF(K13="G2",Datos!$B$34,Datos!$B$31)/F13) -> 2 | M13: =G13+IF(K13="G1",G13*H13/L13,0) -> 2.5 | N13: =IF(K13="G2",G13*H13/L13,0) -> 0 | O13: =M13/Datos!$B$30+N13/Datos!$B$33 -> 0.25 | P13: =B13*C13*Piezas!$E$13*Datos!$B$10/1000000 -> 168.22125 | Q13: =P13*INDEX(Datos!$C$90:$C$95,MATCH(Piezas!$E$13,Datos!$A$90:$A$95,0)) -> 183.52557 | R13: =IF(C13>Datos!$B$31,"Hoja más larga que la cuchilla de G1",IF(J13>Datos!$B$32,"Franja mayor que el tope de G1",IF(AND(K13="G1",I13>Datos!$B$32),"Pieza mayor que el tope de G1: va en la hoja mixta","OK"))) -> OK
A14: Hoja mixta 70 + 100 kg | B14: =B13 -> 1500 | C14: =C13 -> 3000 | D14: =Datos!$B$25+Datos!$B$26 -> 4 | E14: =(Datos!$B$25*Piezas!$F$13*Piezas!$G$13+Datos!$B$26*Piezas!$F$12*Piezas!$G$12)/(B14*C14) -> 0.79086 | F14: =Piezas!$G$13 -> 1210.5 | G14: 1 | H14: =D14 -> 4 | I14: =MAX(Piezas!$F$13,Piezas!$F$12) -> 900 | J14: =IF(F14<=Datos!$B$32,F14,B14-F14*G14) -> 289.5 | K14: =IF(AND(I14<=Datos!$B$35,F14<=Datos!$B$34),"G2","G1") -> G1 | L14: =INT(IF(K14="G2",Datos!$B$34,Datos!$B$31)/F14) -> 2 | M14: =G14+IF(K14="G1",G14*H14/L14,0) -> 3 | N14: =IF(K14="G2",G14*H14/L14,0) -> 0 | O14: =M14/Datos!$B$30+N14/Datos!$B$33 -> 0.3 | P14: =B14*C14*Piezas!$E$13*Datos!$B$10/1000000 -> 168.22125 | Q14: =P14*INDEX(Datos!$C$90:$C$95,MATCH(Piezas!$E$13,Datos!$A$90:$A$95,0)) -> 183.52557 | R14: =IF(AND(Piezas!$G$12<=B14,Piezas!$G$13<=B14,Datos!$B$25*Piezas!$F$13+Datos!$B$26*Piezas!$F$12<=C14),"OK: 1 de 100 kg y 3 de 70 kg","No entra") -> OK: 1 de 100 kg y 3 de 70 kg
A15: 2.º corte en G2 si la pieza entra en su tope (800 mm); si no, en G1 (tope 1.000 mm). La franja más ancha que el tope de G1 se saca cortando la orilla del otro lado.
A17: B) Cuerpos en bobina de ancho estándar con línea de corte transversal (A) y a medida (Ref.)
A18: Formato | B18: Ancho de bobina (mm) | C18: Piezas por golpe | D18: Avance por golpe (mm) | E18: Aprovech. | F18: kg comprados por cuerpo | G18: USD por cuerpo | H18: Peso de bobina (t) | I18: USD por cuerpo a medida (Ref.)
A19: 1 kg | B19: 1220 | C19: =IF(INT((B19-Datos!$B$19)/Piezas!$F$6)*Piezas!$F$6/B19>=INT((B19-Datos!$B$19)/Piezas!$G$6)*Piezas!$G$6/B19,INT((B19-Datos!$B$19)/Piezas!$F$6),INT((B19-Datos!$B$19)/Piezas!$G$6)) -> 5 | D19: =IF(INT((B19-Datos!$B$19)/Piezas!$F$6)*Piezas!$F$6/B19>=INT((B19-Datos!$B$19)/Piezas!$G$6)*Piezas!$G$6/B19,Piezas!$G$6,Piezas!$F$6) -> 263.5 | E19: =MAX(INT((B19-Datos!$B$19)/Piezas!$F$6)*Piezas!$F$6/B19,INT((B19-Datos!$B$19)/Piezas!$G$6)*Piezas!$G$6/B19)*(1-Datos!$B$20) -> 0.96441598 | F19: =Piezas!$H$6/E19 -> 0.45768282 | G19: =F19*INDEX(Datos!$B$90:$B$95,MATCH(Piezas!$E$6,Datos!$A$90:$A$95,0)) -> 0.57798474 | H19: =MIN(ROUNDDOWN(MIN(B19*Datos!$B$52,Datos!$B$53)*2,0)/2,MAX(Datos!$B$49,ROUNDUP(INDEX(Demanda!$C$6:$L$6,Datos!$B$6-2025)*F19/1000/12*Datos!$B$47*2,0)/2)) -> 8 | I19: =Piezas!$H$6*INDEX(Datos!$F$90:$F$95,MATCH(Piezas!$E$6,Datos!$A$90:$A$95,0)) -> 0.59857796
A20: 2,5 kg | B20: 1220 | C20: =IF(INT((B20-Datos!$B$19)/Piezas!$F$7)*Piezas!$F$7/B20>=INT((B20-Datos!$B$19)/Piezas!$G$7)*Piezas!$G$7/B20,INT((B20-Datos!$B$19)/Piezas!$F$7),INT((B20-Datos!$B$19)/Piezas!$G$7)) -> 3 | D20: =IF(INT((B20-Datos!$B$19)/Piezas!$F$7)*Piezas!$F$7/B20>=INT((B20-Datos!$B$19)/Piezas!$G$7)*Piezas!$G$7/B20,Piezas!$G$7,Piezas!$F$7) -> 267.5 | E20: =MAX(INT((B20-Datos!$B$19)/Piezas!$F$7)*Piezas!$F$7/B20,INT((B20-Datos!$B$19)/Piezas!$G$7)*Piezas!$G$7/B20)*(1-Datos!$B$20) -> 0.94321107 | F20: =Piezas!$H$7/E20 -> 1.0755337 | G20: =F20*INDEX(Datos!$B$90:$B$95,MATCH(Piezas!$E$7,Datos!$A$90:$A$95,0)) -> 1.3450194 | H20: =MIN(ROUNDDOWN(MIN(B20*Datos!$B$52,Datos!$B$53)*2,0)/2,MAX(Datos!$B$49,ROUNDUP(INDEX(Demanda!$C$7:$L$7,Datos!$B$6-2025)*F20/1000/12*Datos!$B$47*2,0)/2)) -> 1.5 | I20: =Piezas!$H$7*INDEX(Datos!$F$90:$F$95,MATCH(Piezas!$E$7,Datos!$A$90:$A$95,0)) -> 1.4466133
A21: 5 kg | B21: 1000 | C21: =IF(INT((B21-Datos!$B$19)/Piezas!$F$8)*Piezas!$F$8/B21>=INT((B21-Datos!$B$19)/Piezas!$G$8)*Piezas!$G$8/B21,INT((B21-Datos!$B$19)/Piezas!$F$8),INT((B21-Datos!$B$19)/Piezas!$G$8)) -> 3 | D21: =IF(INT((B21-Datos!$B$19)/Piezas!$F$8)*Piezas!$F$8/B21>=INT((B21-Datos!$B$19)/Piezas!$G$8)*Piezas!$G$8/B21,Piezas!$G$8,Piezas!$F$8) -> 475.5 | E21: =MAX(INT((B21-Datos!$B$19)/Piezas!$F$8)*Piezas!$F$8/B21,INT((B21-Datos!$B$19)/Piezas!$G$8)*Piezas!$G$8/B21)*(1-Datos!$B$20) -> 0.9775875 | F21: =Piezas!$H$8/E21 -> 2.0058613 | G21: =F21*INDEX(Datos!$B$90:$B$95,MATCH(Piezas!$E$8,Datos!$A$90:$A$95,0)) -> 2.5084499 | H21: =MIN(ROUNDDOWN(MIN(B21*Datos!$B$52,Datos!$B$53)*2,0)/2,MAX(Datos!$B$49,ROUNDUP(INDEX(Demanda!$C$8:$L$8,Datos!$B$6-2025)*F21/1000/12*Datos!$B$47*2,0)/2)) -> 10 | I21: =Piezas!$H$8*INDEX(Datos!$F$90:$F$95,MATCH(Piezas!$E$8,Datos!$A$90:$A$95,0)) -> 2.8491949
A22: 10 kg | B22: 1000 | C22: =IF(INT((B22-Datos!$B$19)/Piezas!$F$9)*Piezas!$F$9/B22>=INT((B22-Datos!$B$19)/Piezas!$G$9)*Piezas!$G$9/B22,INT((B22-Datos!$B$19)/Piezas!$F$9),INT((B22-Datos!$B$19)/Piezas!$G$9)) -> 2 | D22: =IF(INT((B22-Datos!$B$19)/Piezas!$F$9)*Piezas!$F$9/B22>=INT((B22-Datos!$B$19)/Piezas!$G$9)*Piezas!$G$9/B22,Piezas!$G$9,Piezas!$F$9) -> 564 | E22: =MAX(INT((B22-Datos!$B$19)/Piezas!$F$9)*Piezas!$F$9/B22,INT((B22-Datos!$B$19)/Piezas!$G$9)*Piezas!$G$9/B22)*(1-Datos!$B$20) -> 0.98107 | F22: =Piezas!$H$9/E22 -> 4.4609849 | G22: =F22*INDEX(Datos!$B$90:$B$95,MATCH(Piezas!$E$9,Datos!$A$90:$A$95,0)) -> 5.6335548 | H22: =MIN(ROUNDDOWN(MIN(B22*Datos!$B$52,Datos!$B$53)*2,0)/2,MAX(Datos!$B$49,ROUNDUP(INDEX(Demanda!$C$9:$L$9,Datos!$B$6-2025)*F22/1000/12*Datos!$B$47*2,0)/2)) -> 1.5 | I22: =Piezas!$H$9*INDEX(Datos!$F$90:$F$95,MATCH(Piezas!$E$9,Datos!$A$90:$A$95,0)) -> 6.2540735
A23: 25 kg | B23: 1500 | C23: =IF(INT((B23-Datos!$B$19)/Piezas!$F$10)*Piezas!$F$10/B23>=INT((B23-Datos!$B$19)/Piezas!$G$10)*Piezas!$G$10/B23,INT((B23-Datos!$B$19)/Piezas!$F$10),INT((B23-Datos!$B$19)/Piezas!$G$10)) -> 3 | D23: =IF(INT((B23-Datos!$B$19)/Piezas!$F$10)*Piezas!$F$10/B23>=INT((B23-Datos!$B$19)/Piezas!$G$10)*Piezas!$G$10/B23,Piezas!$G$10,Piezas!$F$10) -> 858.5 | E23: =MAX(INT((B23-Datos!$B$19)/Piezas!$F$10)*Piezas!$F$10/B23,INT((B23-Datos!$B$19)/Piezas!$G$10)*Piezas!$G$10/B23)*(1-Datos!$B$20) -> 0.98107 | F23: =Piezas!$H$10/E23 -> 10.864555 | G23: =F23*INDEX(Datos!$B$90:$B$95,MATCH(Piezas!$E$10,Datos!$A$90:$A$95,0)) -> 12.100181 | H23: =MIN(ROUNDDOWN(MIN(B23*Datos!$B$52,Datos!$B$53)*2,0)/2,MAX(Datos!$B$49,ROUNDUP(INDEX(Demanda!$C$10:$L$10,Datos!$B$6-2025)*F23/1000/12*Datos!$B$47*2,0)/2)) -> 1 | I23: =Piezas!$H$10*INDEX(Datos!$F$90:$F$95,MATCH(Piezas!$E$10,Datos!$A$90:$A$95,0)) -> 13.387564
A24: 50 kg | B24: 1500 | C24: =IF(INT((B24-Datos!$B$19)/Piezas!$F$11)*Piezas!$F$11/B24>=INT((B24-Datos!$B$19)/Piezas!$G$11)*Piezas!$G$11/B24,INT((B24-Datos!$B$19)/Piezas!$F$11),INT((B24-Datos!$B$19)/Piezas!$G$11)) -> 2 | D24: =IF(INT((B24-Datos!$B$19)/Piezas!$F$11)*Piezas!$F$11/B24>=INT((B24-Datos!$B$19)/Piezas!$G$11)*Piezas!$G$11/B24,Piezas!$G$11,Piezas!$F$11) -> 995.5 | E24: =MAX(INT((B24-Datos!$B$19)/Piezas!$F$11)*Piezas!$F$11/B24,INT((B24-Datos!$B$19)/Piezas!$G$11)*Piezas!$G$11/B24)*(1-Datos!$B$20) -> 0.84906667 | F24: =Piezas!$H$11/E24 -> 18.897491 | G24: =F24*INDEX(Datos!$B$90:$B$95,MATCH(Piezas!$E$11,Datos!$A$90:$A$95,0)) -> 21.046703 | H24: =MIN(ROUNDDOWN(MIN(B24*Datos!$B$52,Datos!$B$53)*2,0)/2,MAX(Datos!$B$49,ROUNDUP(INDEX(Demanda!$C$11:$L$11,Datos!$B$6-2025)*F24/1000/12*Datos!$B$47*2,0)/2)) -> 3 | I24: =Piezas!$H$11*INDEX(Datos!$F$90:$F$95,MATCH(Piezas!$E$11,Datos!$A$90:$A$95,0)) -> 20.152809
A25: 70 kg | B25: 1245 | C25: =IF(INT((B25-Datos!$B$19)/Piezas!$F$12)*Piezas!$F$12/B25>=INT((B25-Datos!$B$19)/Piezas!$G$12)*Piezas!$G$12/B25,INT((B25-Datos!$B$19)/Piezas!$F$12),INT((B25-Datos!$B$19)/Piezas!$G$12)) -> 1 | D25: =IF(INT((B25-Datos!$B$19)/Piezas!$F$12)*Piezas!$F$12/B25>=INT((B25-Datos!$B$19)/Piezas!$G$12)*Piezas!$G$12/B25,Piezas!$G$12,Piezas!$F$12) -> 680 | E25: =MAX(INT((B25-Datos!$B$19)/Piezas!$F$12)*Piezas!$F$12/B25,INT((B25-Datos!$B$19)/Piezas!$G$12)*Piezas!$G$12/B25)*(1-Datos!$B$20) -> 0.96742771 | F25: =Piezas!$H$12/E25 -> 31.80706 | G25: =F25*INDEX(Datos!$B$90:$B$95,MATCH(Piezas!$E$12,Datos!$A$90:$A$95,0)) -> 35.424477 | H25: =MIN(ROUNDDOWN(MIN(B25*Datos!$B$52,Datos!$B$53)*2,0)/2,MAX(Datos!$B$49,ROUNDUP(INDEX(Demanda!$C$12:$L$12,Datos!$B$6-2025)*F25/1000/12*Datos!$B$47*2,0)/2)) -> 1 | I25: =Piezas!$H$12*INDEX(Datos!$F$90:$F$95,MATCH(Piezas!$E$12,Datos!$A$90:$A$95,0)) -> 38.032994
A26: 100 kg | B26: 1245 | C26: =IF(INT((B26-Datos!$B$19)/Piezas!$F$13)*Piezas!$F$13/B26>=INT((B26-Datos!$B$19)/Piezas!$G$13)*Piezas!$G$13/B26,INT((B26-Datos!$B$19)/Piezas!$F$13),INT((B26-Datos!$B$19)/Piezas!$G$13)) -> 1 | D26: =IF(INT((B26-Datos!$B$19)/Piezas!$F$13)*Piezas!$F$13/B26>=INT((B26-Datos!$B$19)/Piezas!$G$13)*Piezas!$G$13/B26,Piezas!$G$13,Piezas!$F$13) -> 900 | E26: =MAX(INT((B26-Datos!$B$19)/Piezas!$F$13)*Piezas!$F$13/B26,INT((B26-Datos!$B$19)/Piezas!$G$13)*Piezas!$G$13/B26)*(1-Datos!$B$20) -> 0.96742771 | F26: =Piezas!$H$13/E26 -> 42.097579 | G26: =F26*INDEX(Datos!$B$90:$B$95,MATCH(Piezas!$E$13,Datos!$A$90:$A$95,0)) -> 46.885337 | H26: =MIN(ROUNDDOWN(MIN(B26*Datos!$B$52,Datos!$B$53)*2,0)/2,MAX(Datos!$B$49,ROUNDUP(INDEX(Demanda!$C$13:$L$13,Datos!$B$6-2025)*F26/1000/12*Datos!$B$47*2,0)/2)) -> 1 | I26: =Piezas!$H$13*INDEX(Datos!$F$90:$F$95,MATCH(Piezas!$E$13,Datos!$A$90:$A$95,0)) -> 50.337787
A29: C) Cúpulas y fondos: fleje a medida (A, D, Ref.) o tiras de hoja (B)
A30: Pieza | B30: Ø disco (mm) | C30: Espesor (mm) | D30: Puente de avance (mm) | E30: Puente al borde (mm) | F30: Ancho de fleje (mm) | G30: Paso (mm) | H30: Aprovech. del fleje | I30: kg de fleje por disco | J30: USD de fleje por disco | K30: Peso de rollo (t) | L30: Hoja para tiras: ancho | M30: largo | N30: Tiras por hoja | O30: Discos por tira | P30: Discos por hoja | Q30: Aprovech. de la hoja | R30: kg de hoja por disco | S30: USD de hoja por disco
A31: Cúpula 1 kg | B31: =Piezas!$L$18 -> 89 | C31: =Piezas!$D$18 -> 0.9 | D31: =MAX(Datos!$B$21*C31,Datos!$B$22) -> 1.35 | E31: =Datos!$B$23*D31 -> 2.025 | F31: =B31+2*E31 -> 93.05 | G31: =B31+D31 -> 90.35 | H31: =PI()*B31^2/4/(F31*G31)*(1-Datos!$B$20) -> 0.73628922 | I31: =Piezas!$S$18/H31 -> 0.059846492 | J31: =I31*INDEX(Datos!$D$90:$D$95,MATCH(C31,Datos!$A$90:$A$95,0)) -> 0.075577142 | K31: =MIN(ROUNDDOWN(MIN(F31*Datos!$B$52,Datos!$B$54)*2,0)/2,MAX(Datos!$B$49,ROUNDUP(INDEX(Demanda!$C$6:$L$6,Datos!$B$6-2025)*I31/1000/12*Datos!$B$47*2,0)/2)) -> 1 | L31: 1220 | M31: 2440 | N31: =IF(INT(L31/F31)*INT((M31-D31)/G31)>=INT(M31/F31)*INT((L31-D31)/G31),INT(L31/F31),INT(M31/F31)) -> 13 | O31: =IF(INT(L31/F31)*INT((M31-D31)/G31)>=INT(M31/F31)*INT((L31-D31)/G31),INT((M31-D31)/G31),INT((L31-D31)/G31)) -> 26 | P31: =N31*O31 -> 338 | Q31: =P31*PI()*B31^2/4/(L31*M31) -> 0.70637763 | R31: =L31*M31*C31*Datos!$B$10/1000000/P31 -> 0.062380693 | S31: =R31*INDEX(Datos!$C$90:$C$95,MATCH(C31,Datos!$A$90:$A$95,0)) -> 0.084594458
A32: Fondo 1 kg | B32: =Piezas!$L$19 -> 95 | C32: =Piezas!$D$19 -> 1.25 | D32: =MAX(Datos!$B$21*C32,Datos!$B$22) -> 1.875 | E32: =Datos!$B$23*D32 -> 2.8125 | F32: =B32+2*E32 -> 100.625 | G32: =B32+D32 -> 96.875 | H32: =PI()*B32^2/4/(F32*G32)*(1-Datos!$B$20) -> 0.72350671 | I32: =Piezas!$S$19/H32 -> 0.096378303 | J32: =I32*INDEX(Datos!$D$90:$D$95,MATCH(C32,Datos!$A$90:$A$95,0)) -> 0.11430467 | K32: =MIN(ROUNDDOWN(MIN(F32*Datos!$B$52,Datos!$B$54)*2,0)/2,MAX(Datos!$B$49,ROUNDUP(INDEX(Demanda!$C$6:$L$6,Datos!$B$6-2025)*I32/1000/12*Datos!$B$47*2,0)/2)) -> 1 | L32: 1220 | M32: 2440 | N32: =IF(INT(L32/F32)*INT((M32-D32)/G32)>=INT(M32/F32)*INT((L32-D32)/G32),INT(L32/F32),INT(M32/F32)) -> 12 | O32: =IF(INT(L32/F32)*INT((M32-D32)/G32)>=INT(M32/F32)*INT((L32-D32)/G32),INT((M32-D32)/G32),INT((L32-D32)/G32)) -> 25 | P32: =N32*O32 -> 300 | Q32: =P32*PI()*B32^2/4/(L32*M32) -> 0.71434612 | R32: =L32*M32*C32*Datos!$B$10/1000000/P32 -> 0.097614233 | S32: =R32*INDEX(Datos!$C$90:$C$95,MATCH(C32,Datos!$A$90:$A$95,0)) -> 0.12595142
A33: Cúpula 2,5 kg | B33: =Piezas!$L$20 -> 156.5 | C33: =Piezas!$D$20 -> 1.25 | D33: =MAX(Datos!$B$21*C33,Datos!$B$22) -> 1.875 | E33: =Datos!$B$23*D33 -> 2.8125 | F33: =B33+2*E33 -> 162.125 | G33: =B33+D33 -> 158.375 | H33: =PI()*B33^2/4/(F33*G33)*(1-Datos!$B$20) -> 0.74542684 | I33: =Piezas!$S$20/H33 -> 0.25386234 | J33: =I33*INDEX(Datos!$D$90:$D$95,MATCH(C33,Datos!$A$90:$A$95,0)) -> 0.30108074 | K33: =MIN(ROUNDDOWN(MIN(F33*Datos!$B$52,Datos!$B$54)*2,0)/2,MAX(Datos!$B$49,ROUNDUP(INDEX(Demanda!$C$7:$L$7,Datos!$B$6-2025)*I33/1000/12*Datos!$B$47*2,0)/2)) -> 0.5 | L33: 1220 | M33: 2440 | N33: =IF(INT(L33/F33)*INT((M33-D33)/G33)>=INT(M33/F33)*INT((L33-D33)/G33),INT(L33/F33),INT(M33/F33)) -> 7 | O33: =IF(INT(L33/F33)*INT((M33-D33)/G33)>=INT(M33/F33)*INT((L33-D33)/G33),INT((M33-D33)/G33),INT((L33-D33)/G33)) -> 15 | P33: =N33*O33 -> 105 | Q33: =P33*PI()*B33^2/4/(L33*M33) -> 0.67851305 | R33: =L33*M33*C33*Datos!$B$10/1000000/P33 -> 0.27889781 | S33: =R33*INDEX(Datos!$C$90:$C$95,MATCH(C33,Datos!$A$90:$A$95,0)) -> 0.35986121
A34: Fondo 2,5 kg | B34: =Piezas!$L$21 -> 140.5 | C34: =Piezas!$D$21 -> 1.25 | D34: =MAX(Datos!$B$21*C34,Datos!$B$22) -> 1.875 | E34: =Datos!$B$23*D34 -> 2.8125 | F34: =B34+2*E34 -> 146.125 | G34: =B34+D34 -> 142.375 | H34: =PI()*B34^2/4/(F34*G34)*(1-Datos!$B$20) -> 0.7414935 | I34: =Piezas!$S$21/H34 -> 0.2056932 | J34: =I34*INDEX(Datos!$D$90:$D$95,MATCH(C34,Datos!$A$90:$A$95,0)) -> 0.24395213 | K34: =MIN(ROUNDDOWN(MIN(F34*Datos!$B$52,Datos!$B$54)*2,0)/2,MAX(Datos!$B$49,ROUNDUP(INDEX(Demanda!$C$7:$L$7,Datos!$B$6-2025)*I34/1000/12*Datos!$B$47*2,0)/2)) -> 0.5 | L34: 1220 | M34: 2440 | N34: =IF(INT(L34/F34)*INT((M34-D34)/G34)>=INT(M34/F34)*INT((L34-D34)/G34),INT(L34/F34),INT(M34/F34)) -> 8 | O34: =IF(INT(L34/F34)*INT((M34-D34)/G34)>=INT(M34/F34)*INT((L34-D34)/G34),INT((M34-D34)/G34),INT((L34-D34)/G34)) -> 17 | P34: =N34*O34 -> 136 | Q34: =P34*PI()*B34^2/4/(L34*M34) -> 0.70832371 | R34: =L34*M34*C34*Datos!$B$10/1000000/P34 -> 0.21532551 | S34: =R34*INDEX(Datos!$C$90:$C$95,MATCH(C34,Datos!$A$90:$A$95,0)) -> 0.27783402
A35: Cúpula 5 kg | B35: =Piezas!$L$22 -> 197 | C35: =Piezas!$D$22 -> 1.6 | D35: =MAX(Datos!$B$21*C35,Datos!$B$22) -> 2.4 | E35: =Datos!$B$23*D35 -> 3.6 | F35: =B35+2*E35 -> 204.2 | G35: =B35+D35 -> 199.4 | H35: =PI()*B35^2/4/(F35*G35)*(1-Datos!$B$20) -> 0.74484263 | I35: =Piezas!$S$22/H35 -> 0.51529096 | J35: =I35*INDEX(Datos!$D$90:$D$95,MATCH(C35,Datos!$A$90:$A$95,0)) -> 0.61113508 | K35: =MIN(ROUNDDOWN(MIN(F35*Datos!$B$52,Datos!$B$54)*2,0)/2,MAX(Datos!$B$49,ROUNDUP(INDEX(Demanda!$C$8:$L$8,Datos!$B$6-2025)*I35/1000/12*Datos!$B$47*2,0)/2)) -> 2.5 | L35: 1220 | M35: 2440 | N35: =IF(INT(L35/F35)*INT((M35-D35)/G35)>=INT(M35/F35)*INT((L35-D35)/G35),INT(L35/F35),INT(M35/F35)) -> 11 | O35: =IF(INT(L35/F35)*INT((M35-D35)/G35)>=INT(M35/F35)*INT((L35-D35)/G35),INT((M35-D35)/G35),INT((L35-D35)/G35)) -> 6 | P35: =N35*O35 -> 66 | Q35: =P35*PI()*B35^2/4/(L35*M35) -> 0.67579755 | R35: =L35*M35*C35*Datos!$B$10/1000000/P35 -> 0.56793736 | S35: =R35*INDEX(Datos!$C$90:$C$95,MATCH(C35,Datos!$A$90:$A$95,0)) -> 0.75394879
A36: Fondo 5 kg | B36: =Piezas!$L$23 -> 170 | C36: =Piezas!$D$23 -> 1.6 | D36: =MAX(Datos!$B$21*C36,Datos!$B$22) -> 2.4 | E36: =Datos!$B$23*D36 -> 3.6 | F36: =B36+2*E36 -> 177.2 | G36: =B36+D36 -> 172.4 | H36: =PI()*B36^2/4/(F36*G36)*(1-Datos!$B$20) -> 0.73928148 | I36: =Piezas!$S$23/H36 -> 0.38660958 | J36: =I36*INDEX(Datos!$D$90:$D$95,MATCH(C36,Datos!$A$90:$A$95,0)) -> 0.45851896 | K36: =MIN(ROUNDDOWN(MIN(F36*Datos!$B$52,Datos!$B$54)*2,0)/2,MAX(Datos!$B$49,ROUNDUP(INDEX(Demanda!$C$8:$L$8,Datos!$B$6-2025)*I36/1000/12*Datos!$B$47*2,0)/2)) -> 2 | L36: 1000 | M36: 2000 | N36: =IF(INT(L36/F36)*INT((M36-D36)/G36)>=INT(M36/F36)*INT((L36-D36)/G36),INT(L36/F36),INT(M36/F36)) -> 5 | O36: =IF(INT(L36/F36)*INT((M36-D36)/G36)>=INT(M36/F36)*INT((L36-D36)/G36),INT((M36-D36)/G36),INT((L36-D36)/G36)) -> 11 | P36: =N36*O36 -> 55 | Q36: =P36*PI()*B36^2/4/(L36*M36) -> 0.62419519 | R36: =L36*M36*C36*Datos!$B$10/1000000/P36 -> 0.45789091 | S36: =R36*INDEX(Datos!$C$90:$C$95,MATCH(C36,Datos!$A$90:$A$95,0)) -> 0.60785981
A37: Cúpula 10 kg | B37: =Piezas!$L$24 -> 231.5 | C37: =Piezas!$D$24 -> 1.6 | D37: =MAX(Datos!$B$21*C37,Datos!$B$22) -> 2.4 | E37: =Datos!$B$23*D37 -> 3.6 | F37: =B37+2*E37 -> 238.7 | G37: =B37+D37 -> 233.9 | H37: =PI()*B37^2/4/(F37*G37)*(1-Datos!$B$20) -> 0.75012271 | I37: =Piezas!$S$24/H37 -> 0.70656851 | J37: =I37*INDEX(Datos!$D$90:$D$95,MATCH(C37,Datos!$A$90:$A$95,0)) -> 0.83799025 | K37: =MIN(ROUNDDOWN(MIN(F37*Datos!$B$52,Datos!$B$54)*2,0)/2,MAX(Datos!$B$49,ROUNDUP(INDEX(Demanda!$C$9:$L$9,Datos!$B$6-2025)*I37/1000/12*Datos!$B$47*2,0)/2)) -> 0.5 | L37: 1000 | M37: 2000 | N37: =IF(INT(L37/F37)*INT((M37-D37)/G37)>=INT(M37/F37)*INT((L37-D37)/G37),INT(L37/F37),INT(M37/F37)) -> 4 | O37: =IF(INT(L37/F37)*INT((M37-D37)/G37)>=INT(M37/F37)*INT((L37-D37)/G37),INT((M37-D37)/G37),INT((L37-D37)/G37)) -> 8 | P37: =N37*O37 -> 32 | Q37: =P37*PI()*B37^2/4/(L37*M37) -> 0.67346008 | R37: =L37*M37*C37*Datos!$B$10/1000000/P37 -> 0.787 | S37: =R37*INDEX(Datos!$C$90:$C$95,MATCH(C37,Datos!$A$90:$A$95,0)) -> 1.0447591
A38: Fondo 10 kg | B38: =Piezas!$L$25 -> 196 | C38: =Piezas!$D$25 -> 2 | D38: =MAX(Datos!$B$21*C38,Datos!$B$22) -> 3 | E38: =Datos!$B$23*D38 -> 4.5 | F38: =B38+2*E38 -> 205 | G38: =B38+D38 -> 199 | H38: =PI()*B38^2/4/(F38*G38)*(1-Datos!$B$20) -> 0.73589892 | I38: =Piezas!$S$25/H38 -> 0.64534 | J38: =I38*INDEX(Datos!$D$90:$D$95,MATCH(C38,Datos!$A$90:$A$95,0)) -> 0.77311732 | K38: =MIN(ROUNDDOWN(MIN(F38*Datos!$B$52,Datos!$B$54)*2,0)/2,MAX(Datos!$B$49,ROUNDUP(INDEX(Demanda!$C$9:$L$9,Datos!$B$6-2025)*I38/1000/12*Datos!$B$47*2,0)/2)) -> 0.5 | L38: 1500 | M38: 3000 | N38: =IF(INT(L38/F38)*INT((M38-D38)/G38)>=INT(M38/F38)*INT((L38-D38)/G38),INT(L38/F38),INT(M38/F38)) -> 7 | O38: =IF(INT(L38/F38)*INT((M38-D38)/G38)>=INT(M38/F38)*INT((L38-D38)/G38),INT((M38-D38)/G38),INT((L38-D38)/G38)) -> 15 | P38: =N38*O38 -> 105 | Q38: =P38*PI()*B38^2/4/(L38*M38) -> 0.70400997 | R38: =L38*M38*C38*Datos!$B$10/1000000/P38 -> 0.67457143 | S38: =R38*INDEX(Datos!$C$90:$C$95,MATCH(C38,Datos!$A$90:$A$95,0)) -> 0.86372213
A40: Por unidad de matafuego (cúpula + fondo)
A41: Formato | B41: Masa neta (kg) | C41: kg de fleje | D41: USD de fleje | E41: kg de hoja | F41: USD de hoja | G41: Tiras de hoja
A42: 1 kg | B42: =Piezas!$S$18+Piezas!$S$19 -> 0.11379468 | C42: =I31+I32 -> 0.15622479 | D42: =J31+J32 -> 0.18988181 | E42: =R31+R32 -> 0.15999493 | F42: =S31+S32 -> 0.21054588 | G42: =1/O31+1/O32 -> 0.078461538
A43: 2,5 kg | B43: =Piezas!$S$20+Piezas!$S$21 -> 0.34175597 | C43: =I33+I34 -> 0.45955554 | D43: =J33+J34 -> 0.54503287 | E43: =R33+R34 -> 0.49422332 | F43: =S33+S34 -> 0.63769524 | G43: =1/O33+1/O34 -> 0.1254902
A44: 5 kg | B44: =Piezas!$S$22+Piezas!$S$23 -> 0.66962398 | C44: =I35+I36 -> 0.90190054 | D44: =J35+J36 -> 1.069654 | E44: =R35+R36 -> 1.0258283 | F44: =S35+S36 -> 1.3618086 | G44: =1/O35+1/O36 -> 0.25757576
A45: 10 kg | B45: =Piezas!$S$24+Piezas!$S$25 -> 1.0049181 | C45: =I37+I38 -> 1.3519085 | D45: =J37+J38 -> 1.6111076 | E45: =R37+R38 -> 1.4615714 | F45: =S37+S38 -> 1.9084812 | G45: =1/O37+1/O38 -> 0.19166667
A48: D) Bobina madre por espesor con corte longitudinal propio (C): patrones de tiras
A49: Grupo | B49: Ancho de madre (mm) | C49: Cuerpo a lo ancho (1 alto, 2 desarrollo) | D49: kg por metro | E49: USD/kg | F49: Tiras de disco por ancho | G49: Peso de madre (t) | H49: Control
A50: 0,9 mm | B50: 1220 | C50: 2 | D50: =B50*0.9*Datos!$B$10/1000 -> 8.64126 | E50: =INDEX(Datos!$E$90:$E$95,MATCH(0.9,Datos!$A$90:$A$95,0)) -> 1.26285 | F50: =H60 -> 1.5145 | G50: =MIN(ROUNDDOWN(MIN(B50*Datos!$B$52,Datos!$B$55)*2,0)/2,MAX(Datos!$B$49,ROUNDUP(INDEX(Cálculo!$C$76:$L$76,Datos!$B$6-2025)/12*Datos!$B$47*2,0)/2)) -> 9 | H50: =IF(AND(H62="Suma 100 %",COUNTIF(E64:G64,"No entra")=0),"OK","Revisar") -> OK
A51: 1,25 mm | B51: 1000 | C51: 2 | D51: =B51*1.25*Datos!$B$10/1000 -> 9.8375 | E51: =INDEX(Datos!$E$90:$E$95,MATCH(1.25,Datos!$A$90:$A$95,0)) -> 1.25056 | F51: =H69+H70+H71 -> 5.7688 | G51: =MIN(ROUNDDOWN(MIN(B51*Datos!$B$52,Datos!$B$55)*2,0)/2,MAX(Datos!$B$49,ROUNDUP(INDEX(Cálculo!$C$77:$L$77,Datos!$B$6-2025)/12*Datos!$B$47*2,0)/2)) -> 3.5 | H51: =IF(AND(H72="Suma 100 %",COUNTIF(E74:G74,"No entra")=0),"OK","Revisar") -> OK
A52: 1,6 mm | B52: 1000 | C52: 1 | D52: =B52*1.6*Datos!$B$10/1000 -> 12.592 | E52: =INDEX(Datos!$E$90:$E$95,MATCH(1.6,Datos!$A$90:$A$95,0)) -> 1.25056 | F52: =H79+H80+H81 -> 1.6455 | G52: =MIN(ROUNDDOWN(MIN(B52*Datos!$B$52,Datos!$B$55)*2,0)/2,MAX(Datos!$B$49,ROUNDUP(INDEX(Cálculo!$C$78:$L$78,Datos!$B$6-2025)/12*Datos!$B$47*2,0)/2)) -> 12 | H52: =IF(AND(H82="Suma 100 %",COUNTIF(E84:G84,"No entra")=0),"OK","Revisar") -> OK
A53: 2,0 mm | B53: 1000 | C53: 1 | D53: =B53*2*Datos!$B$10/1000 -> 15.74 | E53: =INDEX(Datos!$E$90:$E$95,MATCH(2,Datos!$A$90:$A$95,0)) -> 1.26285 | F53: =H89 -> 0.5998 | G53: =MIN(ROUNDDOWN(MIN(B53*Datos!$B$52,Datos!$B$55)*2,0)/2,MAX(Datos!$B$49,ROUNDUP(INDEX(Cálculo!$C$79:$L$79,Datos!$B$6-2025)/12*Datos!$B$47*2,0)/2)) -> 2 | H53: =IF(AND(H90="Suma 100 %",COUNTIF(E92:G92,"No entra")=0),"OK","Revisar") -> OK
A54: 3,2 mm | B54: 1500 | C54: 1 | D54: =B54*3.2*Datos!$B$10/1000 -> 37.776 | E54: =INDEX(Datos!$E$90:$E$95,MATCH(3.2,Datos!$A$90:$A$95,0)) -> 1.11373 | F54: 0 | G54: =MIN(ROUNDDOWN(MIN(B54*Datos!$B$52,Datos!$B$55)*2,0)/2,MAX(Datos!$B$49,ROUNDUP(INDEX(Cálculo!$C$80:$L$80,Datos!$B$6-2025)/12*Datos!$B$47*2,0)/2)) -> 3.5 | H54: =IF(AND(H98="Suma 100 %",COUNTIF(E100:G100,"No entra")=0),"OK","Revisar") -> OK
A55: 4,75 mm | B55: 1245 | C55: 2 (fijo) | D55: =B55*4.75*Datos!$B$10/1000 -> 46.541213 | E55: =INDEX(Datos!$E$90:$E$95,MATCH(4.75,Datos!$A$90:$A$95,0)) -> 1.11373 | F55: 0 | G55: =MIN(ROUNDDOWN(MIN(B55*Datos!$B$52,Datos!$B$55)*2,0)/2,MAX(Datos!$B$49,ROUNDUP(INDEX(Cálculo!$C$81:$L$81,Datos!$B$6-2025)/12*Datos!$B$47*2,0)/2)) -> 2 | H55: =IF(AND(H105="Suma 100 %",COUNTIF(E107:G107,"No entra")=0),"OK","Revisar") -> OK
A58: Grupo 0,9 mm
A59: Tira | B59: Formato | C59: Ancho (mm) | D59: Avance por pieza (mm) | E59: Patrón 1 | F59: Patrón 2 | G59: Patrón 3 | H59: Tiras por metro de madre
A60: Cúpula 1 kg | B60: 1 kg | C60: =F31 -> 93.05 | D60: =G31 -> 90.35 | E60: 0 | F60: 13 | G60: 0 | H60: =E60*$E$62+F60*$F$62+G60*$G$62 -> 1.5145
A61: Cuerpo 1 kg | B61: 1 kg | C61: =IF($C$50=1,Piezas!$F$6,Piezas!$G$6) -> 236.5 | D61: =IF($C$50=1,Piezas!$G$6,Piezas!$F$6) -> 263.5 | E61: 5 | F61: 0 | G61: 0 | H61: =E61*$E$62+F61*$F$62+G61*$G$62 -> 4.4175
A62: Participación (% de los metros de madre) | E62: 0.8835 | F62: 0.1165 | G62: 0 | H62: =IF(ABS(SUM(E62:G62)-1)<0.001,"Suma 100 %","Revisar: no suma 100 %") -> Suma 100 %
A63: Ancho usado (mm) | E63: =SUMPRODUCT($C$60:$C$61,E60:E61) -> 1182.5 | F63: =SUMPRODUCT($C$60:$C$61,F60:F61) -> 1209.65 | G63: =SUMPRODUCT($C$60:$C$61,G60:G61) -> 0
A64: ¿Entra en la madre? (orilla ≥ margen) | E64: =IF(E63=0,"sin uso",IF($B$50-E63>=Datos!$B$19,"OK","No entra")) -> OK | F64: =IF(F63=0,"sin uso",IF($B$50-F63>=Datos!$B$19,"OK","No entra")) -> OK | G64: =IF(G63=0,"sin uso",IF($B$50-G63>=Datos!$B$19,"OK","No entra")) -> sin uso
A66: Grupo 1,25 mm
A67: Tira | B67: Formato | C67: Ancho (mm) | D67: Avance por pieza (mm) | E67: Patrón 1 | F67: Patrón 2 | G67: Patrón 3 | H67: Tiras por metro de madre
A68: Cuerpo 2,5 kg | B68: 2,5 kg | C68: =IF($C$51=1,Piezas!$F$7,Piezas!$G$7) -> 385.5 | D68: =IF($C$51=1,Piezas!$G$7,Piezas!$F$7) -> 267.5 | E68: 1 | F68: 1 | G68: 0 | H68: =E68*$E$72+F68*$F$72+G68*$G$72 -> 0.9064
A69: Cúpula 2,5 kg | B69: 2,5 kg | C69: =F33 -> 162.125 | D69: =G33 -> 158.375 | E69: 0 | F69: 1 | G69: 4 | H69: =E69*$E$72+F69*$F$72+G69*$G$72 -> 0.5368
A70: Fondo 2,5 kg | B70: 2,5 kg | C70: =F34 -> 146.125 | D70: =G34 -> 142.375 | E70: 0 | F70: 3 | G70: 0 | H70: =E70*$E$72+F70*$F$72+G70*$G$72 -> 0.4872
A71: Fondo 1 kg | B71: 1 kg | C71: =F32 -> 100.625 | D71: =G32 -> 96.875 | E71: 6 | F71: 0 | G71: 3 | H71: =E71*$E$72+F71*$F$72+G71*$G$72 -> 4.7448
A72: Participación (% de los metros de madre) | E72: 0.744 | F72: 0.1624 | G72: 0.0936 | H72: =IF(ABS(SUM(E72:G72)-1)<0.001,"Suma 100 %","Revisar: no suma 100 %") -> Suma 100 %
A73: Ancho usado (mm) | E73: =SUMPRODUCT($C$68:$C$71,E68:E71) -> 989.25 | F73: =SUMPRODUCT($C$68:$C$71,F68:F71) -> 986 | G73: =SUMPRODUCT($C$68:$C$71,G68:G71) -> 950.375
A74: ¿Entra en la madre? (orilla ≥ margen) | E74: =IF(E73=0,"sin uso",IF($B$51-E73>=Datos!$B$19,"OK","No entra")) -> OK | F74: =IF(F73=0,"sin uso",IF($B$51-F73>=Datos!$B$19,"OK","No entra")) -> OK | G74: =IF(G73=0,"sin uso",IF($B$51-G73>=Datos!$B$19,"OK","No entra")) -> OK
A76: Grupo 1,6 mm
A77: Tira | B77: Formato | C77: Ancho (mm) | D77: Avance por pieza (mm) | E77: Patrón 1 | F77: Patrón 2 | G77: Patrón 3 | H77: Tiras por metro de madre
A78: Cuerpo 5 kg | B78: 5 kg | C78: =IF($C$52=1,Piezas!$F$8,Piezas!$G$8) -> 327.5 | D78: =IF($C$52=1,Piezas!$G$8,Piezas!$F$8) -> 475.5 | E78: 3 | F78: 0 | G78: 0 | H78: =E78*$E$82+F78*$F$82+G78*$G$82 -> 2.0127
A79: Cúpula 5 kg | B79: 5 kg | C79: =F35 -> 204.2 | D79: =G35 -> 199.4 | E79: 0 | F79: 3 | G79: 1 | H79: =E79*$E$82+F79*$F$82+G79*$G$82 -> 0.8441
A80: Fondo 5 kg | B80: 5 kg | C80: =F36 -> 177.2 | D80: =G36 -> 172.4 | E80: 0 | F80: 2 | G80: 3 | H80: =E80*$E$82+F80*$F$82+G80*$G$82 -> 0.7298
A81: Cúpula 10 kg | B81: 10 kg | C81: =F37 -> 238.7 | D81: =G37 -> 233.9 | E81: 0 | F81: 0 | G81: 1 | H81: =E81*$E$82+F81*$F$82+G81*$G$82 -> 0.0716
A82: Participación (% de los metros de madre) | E82: 0.6709 | F82: 0.2575 | G82: 0.0716 | H82: =IF(ABS(SUM(E82:G82)-1)<0.001,"Suma 100 %","Revisar: no suma 100 %") -> Suma 100 %
A83: Ancho usado (mm) | E83: =SUMPRODUCT($C$78:$C$81,E78:E81) -> 982.5 | F83: =SUMPRODUCT($C$78:$C$81,F78:F81) -> 967 | G83: =SUMPRODUCT($C$78:$C$81,G78:G81) -> 974.5
A84: ¿Entra en la madre? (orilla ≥ margen) | E84: =IF(E83=0,"sin uso",IF($B$52-E83>=Datos!$B$19,"OK","No entra")) -> OK | F84: =IF(F83=0,"sin uso",IF($B$52-F83>=Datos!$B$19,"OK","No entra")) -> OK | G84: =IF(G83=0,"sin uso",IF($B$52-G83>=Datos!$B$19,"OK","No entra")) -> OK
A86: Grupo 2,0 mm
A87: Tira | B87: Formato | C87: Ancho (mm) | D87: Avance por pieza (mm) | E87: Patrón 1 | F87: Patrón 2 | G87: Patrón 3 | H87: Tiras por metro de madre
A88: Cuerpo 10 kg | B88: 10 kg | C88: =IF($C$53=1,Piezas!$F$9,Piezas!$G$9) -> 493 | D88: =IF($C$53=1,Piezas!$G$9,Piezas!$F$9) -> 564 | E88: 2 | F88: 1 | G88: 0 | H88: =E88*$E$90+F88*$F$90+G88*$G$90 -> 1.7001
A89: Fondo 10 kg | B89: 10 kg | C89: =F38 -> 205 | D89: =G38 -> 199 | E89: 0 | F89: 2 | G89: 0 | H89: =E89*$E$90+F89*$F$90+G89*$G$90 -> 0.5998
A90: Participación (% de los metros de madre) | E90: 0.7001 | F90: 0.2999 | G90: 0 | H90: =IF(ABS(SUM(E90:G90)-1)<0.001,"Suma 100 %","Revisar: no suma 100 %") -> Suma 100 %
A91: Ancho usado (mm) | E91: =SUMPRODUCT($C$88:$C$89,E88:E89) -> 986 | F91: =SUMPRODUCT($C$88:$C$89,F88:F89) -> 903 | G91: =SUMPRODUCT($C$88:$C$89,G88:G89) -> 0
A92: ¿Entra en la madre? (orilla ≥ margen) | E92: =IF(E91=0,"sin uso",IF($B$53-E91>=Datos!$B$19,"OK","No entra")) -> OK | F92: =IF(F91=0,"sin uso",IF($B$53-F91>=Datos!$B$19,"OK","No entra")) -> OK | G92: =IF(G91=0,"sin uso",IF($B$53-G91>=Datos!$B$19,"OK","No entra")) -> sin uso
A94: Grupo 3,2 mm
A95: Tira | B95: Formato | C95: Ancho (mm) | D95: Avance por pieza (mm) | E95: Patrón 1 | F95: Patrón 2 | G95: Patrón 3 | H95: Tiras por metro de madre
A96: Cuerpo 25 kg | B96: 25 kg | C96: =IF($C$54=1,Piezas!$F$10,Piezas!$G$10) -> 493 | D96: =IF($C$54=1,Piezas!$G$10,Piezas!$F$10) -> 858.5 | E96: 0 | F96: 3 | G96: 0 | H96: =E96*$E$98+F96*$F$98+G96*$G$98 -> 0.6216
A97: Cuerpo 50 kg | B97: 50 kg | C97: =IF($C$54=1,Piezas!$F$11,Piezas!$G$11) -> 640 | D97: =IF($C$54=1,Piezas!$G$11,Piezas!$F$11) -> 995.5 | E97: 2 | F97: 0 | G97: 0 | H97: =E97*$E$98+F97*$F$98+G97*$G$98 -> 1.5856
A98: Participación (% de los metros de madre) | E98: 0.7928 | F98: 0.2072 | G98: 0 | H98: =IF(ABS(SUM(E98:G98)-1)<0.001,"Suma 100 %","Revisar: no suma 100 %") -> Suma 100 %
A99: Ancho usado (mm) | E99: =SUMPRODUCT($C$96:$C$97,E96:E97) -> 1280 | F99: =SUMPRODUCT($C$96:$C$97,F96:F97) -> 1479 | G99: =SUMPRODUCT($C$96:$C$97,G96:G97) -> 0
A100: ¿Entra en la madre? (orilla ≥ margen) | E100: =IF(E99=0,"sin uso",IF($B$54-E99>=Datos!$B$19,"OK","No entra")) -> OK | F100: =IF(F99=0,"sin uso",IF($B$54-F99>=Datos!$B$19,"OK","No entra")) -> OK | G100: =IF(G99=0,"sin uso",IF($B$54-G99>=Datos!$B$19,"OK","No entra")) -> sin uso
A102: Grupo 4,75 mm
A103: Tira | B103: Formato | C103: Ancho (mm) | D103: Avance por pieza (mm) | E103: Patrón 1 | F103: Patrón 2 | G103: Patrón 3 | H103: Tiras por metro de madre
A104: Cuerpos 70 y 100 kg (franja compartida) | B104: 70 y 100 kg | C104: =Piezas!$G$13 -> 1210.5 | D104: alto de cada uno | E104: 1 | F104: 0 | G104: 0 | H104: =E104*$E$105+F104*$F$105+G104*$G$105 -> 1
A105: Participación (% de los metros de madre) | E105: 1 | F105: 0 | G105: 0 | H105: =IF(ABS(SUM(E105:G105)-1)<0.001,"Suma 100 %","Revisar: no suma 100 %") -> Suma 100 %
A106: Ancho usado (mm) | E106: =SUMPRODUCT($C$104:$C$104,E104:E104) -> 1210.5 | F106: =SUMPRODUCT($C$104:$C$104,F104:F104) -> 0 | G106: =SUMPRODUCT($C$104:$C$104,G104:G104) -> 0
A107: ¿Entra en la madre? (orilla ≥ margen) | E107: =IF(E106=0,"sin uso",IF($B$55-E106>=Datos!$B$19,"OK","No entra")) -> OK | F107: =IF(F106=0,"sin uso",IF($B$55-F106>=Datos!$B$19,"OK","No entra")) -> sin uso | G107: =IF(G106=0,"sin uso",IF($B$55-G106>=Datos!$B$19,"OK","No entra")) -> sin uso
A108: Patrones y participaciones por programación lineal sobre la demanda 2026-2035 (mínimo acero comprado); si cambia la demanda o una medida, hay que recalcularlos.

Sheet Cálculo
A1: Cálculo año por año de cada alternativa
A2: No se edita: sale de Datos, Demanda, Piezas y Corte. Los costos van en USD sin IVA.
A4: Concepto | B4: Unidad | C4: 2026 | D4: 2027 | E4: 2028 | F4: 2029 | G4: 2030 | H4: 2031 | I4: 2032 | J4: 2033 | K4: 2034 | L4: 2035
A5: Período k (para descontar) | C5: 1 | D5: 2 | E5: 3 | F5: 4 | G5: 5 | H5: 6 | I5: 7 | J5: 8 | K5: 9 | L5: 10
A6: Factor de descuento 1/(1+i)^k | C6: =1/(1+Datos!$B$7)^C5 -> 0.89285714 | D6: =1/(1+Datos!$B$7)^D5 -> 0.79719388 | E6: =1/(1+Datos!$B$7)^E5 -> 0.71178025 | F6: =1/(1+Datos!$B$7)^F5 -> 0.63551808 | G6: =1/(1+Datos!$B$7)^G5 -> 0.56742686 | H6: =1/(1+Datos!$B$7)^H5 -> 0.50663112 | I6: =1/(1+Datos!$B$7)^I5 -> 0.45234922 | J6: =1/(1+Datos!$B$7)^J5 -> 0.40388323 | ... L6: =1/(1+Datos!$B$7)^L5 -> 0.32197324
A7: Unidades a fabricar (cuerpos)
A8: 1 kg | B8: u | C8: =Demanda!C6 -> 4178.7365 | D8: =Demanda!D6 -> 5997.304 | E8: =Demanda!E6 -> 14514.148 | F8: =Demanda!F6 -> 35161.936 | G8: =Demanda!G6 -> 62115.433 | H8: =Demanda!H6 -> 87300.453 | I8: =Demanda!I6 -> 121673.15 | J8: =Demanda!J6 -> 156133.08 | ... L8: =Demanda!L6 -> 202620.64
A9: 2,5 kg | B9: u | C9: =Demanda!C7 -> 302.03036 | D9: =Demanda!D7 -> 727.28745 | E9: =Demanda!E7 -> 1317.3881 | F9: =Demanda!F7 -> 2592.6782 | G9: =Demanda!G7 -> 4297.3877 | H9: =Demanda!H7 -> 6113.1499 | I9: =Demanda!I7 -> 8117.2755 | J9: =Demanda!J7 -> 10270.227 | ... L9: =Demanda!L7 -> 14135.378
A10: 5 kg | B10: u | C10: =Demanda!C8 -> 2286.773 | D10: =Demanda!D8 -> 3940.4589 | E10: =Demanda!E8 -> 6733.0976 | F10: =Demanda!F8 -> 12240.955 | G10: =Demanda!G8 -> 20628.467 | H10: =Demanda!H8 -> 28744.684 | I10: =Demanda!I8 -> 38699.48 | J10: =Demanda!J8 -> 48872.026 | ... L10: =Demanda!L8 -> 63882.939
A11: 10 kg | B11: u | C11: =Demanda!C9 -> 94.833182 | D11: =Demanda!D9 -> 184.4873 | E11: =Demanda!E9 -> 356.17878 | F11: =Demanda!F9 -> 693.78049 | G11: =Demanda!G9 -> 1206.3982 | H11: =Demanda!H9 -> 1743.045 | I11: =Demanda!I9 -> 2339.8005 | J11: =Demanda!J9 -> 2957.5648 | ... L11: =Demanda!L9 -> 3868.3281
A12: 25 kg | B12: u | C12: =Demanda!C10 -> 36.051791 | D12: =Demanda!D10 -> 58.622147 | E12: =Demanda!E10 -> 90.76854 | F12: =Demanda!F10 -> 153.96985 | G12: =Demanda!G10 -> 251.356 | H12: =Demanda!H10 -> 349.57448 | I12: =Demanda!I10 -> 465.46823 | J12: =Demanda!J10 -> 587.72867 | ... L12: =Demanda!L10 -> 777.31053
A13: 50 kg | B13: u | C13: =Demanda!C11 -> 76.913941 | D13: =Demanda!D11 -> 129.77672 | E13: =Demanda!E11 -> 201.49879 | F13: =Demanda!F11 -> 336.52568 | G13: =Demanda!G11 -> 554.00721 | H13: =Demanda!H11 -> 770.13586 | I13: =Demanda!I11 -> 1024.3501 | J13: =Demanda!J11 -> 1292.1071 | ... L13: =Demanda!L11 -> 1709.4352
A14: 70 kg | B14: u | C14: =Demanda!C12 -> 18.34486 | D14: =Demanda!D12 -> 28.221831 | E14: =Demanda!E12 -> 43.260099 | F14: =Demanda!F12 -> 73.814329 | G14: =Demanda!G12 -> 122.26048 | H14: =Demanda!H12 -> 167.52855 | I14: =Demanda!I12 -> 224.48075 | J14: =Demanda!J12 -> 281.64736 | ... L14: =Demanda!L12 -> 374.12986
A15: 100 kg | B15: u | C15: =Demanda!C13 -> 12.896573 | D15: =Demanda!D13 -> 18.867887 | E15: =Demanda!E13 -> 28.826733 | F15: =Demanda!F13 -> 48.329553 | G15: =Demanda!G13 -> 80.640321 | H15: =Demanda!H13 -> 111.85903 | I15: =Demanda!I13 -> 148.97383 | J15: =Demanda!J13 -> 186.51157 | ... L15: =Demanda!L13 -> 247.44657
A16: Cúpula 1 kg | B16: u | C16: =C8 -> 4178.7365 | D16: =D8 -> 5997.304 | E16: =E8 -> 14514.148 | F16: =F8 -> 35161.936 | G16: =G8 -> 62115.433 | H16: =H8 -> 87300.453 | I16: =I8 -> 121673.15 | J16: =J8 -> 156133.08 | ... L16: =L8 -> 202620.64
A17: Fondo 1 kg | B17: u | C17: =C8 -> 4178.7365 | D17: =D8 -> 5997.304 | E17: =E8 -> 14514.148 | F17: =F8 -> 35161.936 | G17: =G8 -> 62115.433 | H17: =H8 -> 87300.453 | I17: =I8 -> 121673.15 | J17: =J8 -> 156133.08 | ... L17: =L8 -> 202620.64
A18: Cúpula 2,5 kg | B18: u | C18: =C9 -> 302.03036 | D18: =D9 -> 727.28745 | E18: =E9 -> 1317.3881 | F18: =F9 -> 2592.6782 | G18: =G9 -> 4297.3877 | H18: =H9 -> 6113.1499 | I18: =I9 -> 8117.2755 | J18: =J9 -> 10270.227 | ... L18: =L9 -> 14135.378
A19: Fondo 2,5 kg | B19: u | C19: =C9 -> 302.03036 | D19: =D9 -> 727.28745 | E19: =E9 -> 1317.3881 | F19: =F9 -> 2592.6782 | G19: =G9 -> 4297.3877 | H19: =H9 -> 6113.1499 | I19: =I9 -> 8117.2755 | J19: =J9 -> 10270.227 | ... L19: =L9 -> 14135.378
A20: Cúpula 5 kg | B20: u | C20: =C10 -> 2286.773 | D20: =D10 -> 3940.4589 | E20: =E10 -> 6733.0976 | F20: =F10 -> 12240.955 | G20: =G10 -> 20628.467 | H20: =H10 -> 28744.684 | I20: =I10 -> 38699.48 | J20: =J10 -> 48872.026 | ... L20: =L10 -> 63882.939
A21: Fondo 5 kg | B21: u | C21: =C10 -> 2286.773 | D21: =D10 -> 3940.4589 | E21: =E10 -> 6733.0976 | F21: =F10 -> 12240.955 | G21: =G10 -> 20628.467 | H21: =H10 -> 28744.684 | I21: =I10 -> 38699.48 | J21: =J10 -> 48872.026 | ... L21: =L10 -> 63882.939
A22: Cúpula 10 kg | B22: u | C22: =C11 -> 94.833182 | D22: =D11 -> 184.4873 | E22: =E11 -> 356.17878 | F22: =F11 -> 693.78049 | G22: =G11 -> 1206.3982 | H22: =H11 -> 1743.045 | I22: =I11 -> 2339.8005 | J22: =J11 -> 2957.5648 | ... L22: =L11 -> 3868.3281
A23: Fondo 10 kg | B23: u | C23: =C11 -> 94.833182 | D23: =D11 -> 184.4873 | E23: =E11 -> 356.17878 | F23: =F11 -> 693.78049 | G23: =G11 -> 1206.3982 | H23: =H11 -> 1743.045 | I23: =I11 -> 2339.8005 | J23: =J11 -> 2957.5648 | ... L23: =L11 -> 3868.3281
A25: Acero neto en piezas (cuerpos + cúpulas + fondos) | B25: t | C25: =(SUMPRODUCT(C$8:C$15,Piezas!$H$6:$H$13)+SUMPRODUCT(C$16:C$23,Piezas!$S$18:$S$25))/1000 -> 11.963473 | D25: =(SUMPRODUCT(D$8:D$15,Piezas!$H$6:$H$13)+SUMPRODUCT(D$16:D$23,Piezas!$S$18:$S$25))/1000 -> 20.018287 | E25: =(SUMPRODUCT(E$8:E$15,Piezas!$H$6:$H$13)+SUMPRODUCT(E$16:E$23,Piezas!$S$18:$S$25))/1000 -> 36.178906 | F25: =(SUMPRODUCT(F$8:F$15,Piezas!$H$6:$H$13)+SUMPRODUCT(F$16:F$23,Piezas!$S$18:$S$25))/1000 -> 70.251966 | G25: =(SUMPRODUCT(G$8:G$15,Piezas!$H$6:$H$13)+SUMPRODUCT(G$16:G$23,Piezas!$S$18:$S$25))/1000 -> 119.68469 | H25: =(SUMPRODUCT(H$8:H$15,Piezas!$H$6:$H$13)+SUMPRODUCT(H$16:H$23,Piezas!$S$18:$S$25))/1000 -> 167.54674 | I25: =(SUMPRODUCT(I$8:I$15,Piezas!$H$6:$H$13)+SUMPRODUCT(I$16:I$23,Piezas!$S$18:$S$25))/1000 -> 227.32423 | J25: =(SUMPRODUCT(J$8:J$15,Piezas!$H$6:$H$13)+SUMPRODUCT(J$16:J$23,Piezas!$S$18:$S$25))/1000 -> 288.34682 | ... L25: =(SUMPRODUCT(L$8:L$15,Piezas!$H$6:$H$13)+SUMPRODUCT(L$16:L$23,Piezas!$S$18:$S$25))/1000 -> 377.83044
A27: A — Bobina por formato para cuerpos + fleje a medida para discos
A28: Acero de bobina para cuerpos | B28: t | C28: =SUMPRODUCT(C$8:C$15,Corte!$F$19:$F$26)/1000 -> 10.218956 | D28: =SUMPRODUCT(D$8:D$15,Corte!$F$19:$F$26)/1000 -> 17.035398 | E28: =SUMPRODUCT(E$8:E$15,Corte!$F$19:$F$26)/1000 -> 30.537833 | F28: =SUMPRODUCT(F$8:F$15,Corte!$F$19:$F$26)/1000 -> 58.944808 | G28: =SUMPRODUCT(G$8:G$15,Corte!$F$19:$F$26)/1000 -> 100.29445 | H28: =SUMPRODUCT(H$8:H$15,Corte!$F$19:$F$26)/1000 -> 140.35356 | I28: =SUMPRODUCT(I$8:I$15,Corte!$F$19:$F$26)/1000 -> 190.30798 | J28: =SUMPRODUCT(J$8:J$15,Corte!$F$19:$F$26)/1000 -> 241.34261 | ... L28: =SUMPRODUCT(L$8:L$15,Corte!$F$19:$F$26)/1000 -> 316.40197
A29: Costo de la bobina para cuerpos | B29: USD | C29: =SUMPRODUCT(C$8:C$15,Corte!$G$19:$G$26) -> 12401.522 | D29: =SUMPRODUCT(D$8:D$15,Corte!$G$19:$G$26) -> 20693.411 | E29: =SUMPRODUCT(E$8:E$15,Corte!$G$19:$G$26) -> 37280.278 | F29: =SUMPRODUCT(F$8:F$15,Corte!$G$19:$G$26) -> 72251.139 | G29: =SUMPRODUCT(G$8:G$15,Corte!$G$19:$G$26) -> 123036.97 | H29: =SUMPRODUCT(H$8:H$15,Corte!$G$19:$G$26) -> 172222.67 | I29: =SUMPRODUCT(I$8:I$15,Corte!$G$19:$G$26) -> 233628.47 | J29: =SUMPRODUCT(J$8:J$15,Corte!$G$19:$G$26) -> 296338.91 | ... L29: =SUMPRODUCT(L$8:L$15,Corte!$G$19:$G$26) -> 388402.13
A30: Acero de fleje para discos | B30: t | C30: =SUMPRODUCT(C$16:C$23,Corte!$I$31:$I$38)/1000 -> 2.9822696 | D30: =SUMPRODUCT(D$16:D$23,Corte!$I$31:$I$38)/1000 -> 5.0744685 | E30: =SUMPRODUCT(E$16:E$23,Corte!$I$31:$I$38)/1000 -> 9.4269882 | F30: =SUMPRODUCT(F$16:F$23,Corte!$I$31:$I$38)/1000 -> 18.662698 | G30: =SUMPRODUCT(G$16:G$23,Corte!$I$31:$I$38)/1000 -> 31.914625 | H30: =SUMPRODUCT(H$16:H$23,Corte!$I$31:$I$38)/1000 -> 44.729111 | I30: =SUMPRODUCT(I$16:I$23,Corte!$I$31:$I$38)/1000 -> 60.80498 | J30: =SUMPRODUCT(J$16:J$23,Corte!$I$31:$I$38)/1000 -> 77.187662 | ... L30: =SUMPRODUCT(L$16:L$23,Corte!$I$31:$I$38)/1000 -> 100.99604
A31: Costo del fleje para discos | B31: USD | C31: =SUMPRODUCT(C$16:C$23,Corte!$J$31:$J$38) -> 3556.925 | D31: =SUMPRODUCT(D$16:D$23,Corte!$J$31:$J$38) -> 6047.3312 | E31: =SUMPRODUCT(E$16:E$23,Corte!$J$31:$J$38) -> 11249.92 | F31: =SUMPRODUCT(F$16:F$23,Corte!$J$31:$J$38) -> 22301.049 | G31: =SUMPRODUCT(G$16:G$23,Corte!$J$31:$J$38) -> 38145.769 | H31: =SUMPRODUCT(H$16:H$23,Corte!$J$31:$J$38) -> 53463.736 | I31: =SUMPRODUCT(I$16:I$23,Corte!$J$31:$J$38) -> 72692.426 | J31: =SUMPRODUCT(J$16:J$23,Corte!$J$31:$J$38) -> 92285.558 | ... L31: =SUMPRODUCT(L$16:L$23,Corte!$J$31:$J$38) -> 120743.16
A32: Acero comprado | B32: t | C32: =C28+C30 -> 13.201226 | D32: =D28+D30 -> 22.109867 | E32: =E28+E30 -> 39.964821 | F32: =F28+F30 -> 77.607506 | G32: =G28+G30 -> 132.20907 | H32: =H28+H30 -> 185.08267 | I32: =I28+I30 -> 251.11296 | J32: =J28+J30 -> 318.53028 | ... L32: =L28+L30 -> 417.39801
A33: Costo del acero | B33: USD | C33: =C29+C31 -> 15958.447 | D33: =D29+D31 -> 26740.742 | E33: =E29+E31 -> 48530.197 | F33: =F29+F31 -> 94552.188 | G33: =G29+G31 -> 161182.74 | H33: =H29+H31 -> 225686.41 | I33: =I29+I31 -> 306320.89 | J33: =J29+J31 -> 388624.47 | ... L33: =L29+L31 -> 509145.29
A34: Scrap | B34: t | C34: =C32-C25 -> 1.237753 | D34: =D32-D25 -> 2.0915791 | E34: =E32-E25 -> 3.7859155 | F34: =F32-F25 -> 7.3555401 | G34: =G32-G25 -> 12.524381 | H34: =H32-H25 -> 17.535927 | I34: =I32-I25 -> 23.788736 | J34: =J32-J25 -> 30.183459 | ... L34: =L32-L25 -> 39.567572
A35: Venta de scrap (resta) | B35: USD | C35: =-C34*Datos!$B$9 -> -309.43824 | D35: =-D34*Datos!$B$9 -> -522.89479 | E35: =-E34*Datos!$B$9 -> -946.47889 | F35: =-F34*Datos!$B$9 -> -1838.885 | G35: =-G34*Datos!$B$9 -> -3131.0954 | H35: =-H34*Datos!$B$9 -> -4383.9817 | I35: =-I34*Datos!$B$9 -> -5947.184 | J35: =-J34*Datos!$B$9 -> -7545.8647 | ... L35: =-L34*Datos!$B$9 -> -9891.8931
A36: Stock de bobinas de cuerpo | B36: t | C36: =SUMPRODUCT((Corte!$H$19:$H$26+C$8:C$15*Corte!$F$19:$F$26/1000*Datos!$B$48/12-ABS(Corte!$H$19:$H$26-C$8:C$15*Corte!$F$19:$F$26/1000*Datos!$B$48/12))/4+C$8:C$15*Corte!$F$19:$F$26/1000*Datos!$B$45/52) -> 1.6704063 | D36: =SUMPRODUCT((Corte!$H$19:$H$26+D$8:D$15*Corte!$F$19:$F$26/1000*Datos!$B$48/12-ABS(Corte!$H$19:$H$26-D$8:D$15*Corte!$F$19:$F$26/1000*Datos!$B$48/12))/4+D$8:D$15*Corte!$F$19:$F$26/1000*Datos!$B$45/52) -> 2.7846324 | E36: =SUMPRODUCT((Corte!$H$19:$H$26+E$8:E$15*Corte!$F$19:$F$26/1000*Datos!$B$48/12-ABS(Corte!$H$19:$H$26-E$8:E$15*Corte!$F$19:$F$26/1000*Datos!$B$48/12))/4+E$8:E$15*Corte!$F$19:$F$26/1000*Datos!$B$45/52) -> 4.9917612 | F36: =SUMPRODUCT((Corte!$H$19:$H$26+F$8:F$15*Corte!$F$19:$F$26/1000*Datos!$B$48/12-ABS(Corte!$H$19:$H$26-F$8:F$15*Corte!$F$19:$F$26/1000*Datos!$B$48/12))/4+F$8:F$15*Corte!$F$19:$F$26/1000*Datos!$B$45/52) -> 9.6352091 | G36: =SUMPRODUCT((Corte!$H$19:$H$26+G$8:G$15*Corte!$F$19:$F$26/1000*Datos!$B$48/12-ABS(Corte!$H$19:$H$26-G$8:G$15*Corte!$F$19:$F$26/1000*Datos!$B$48/12))/4+G$8:G$15*Corte!$F$19:$F$26/1000*Datos!$B$45/52) -> 16.222054 | H36: =SUMPRODUCT((Corte!$H$19:$H$26+H$8:H$15*Corte!$F$19:$F$26/1000*Datos!$B$48/12-ABS(Corte!$H$19:$H$26-H$8:H$15*Corte!$F$19:$F$26/1000*Datos!$B$48/12))/4+H$8:H$15*Corte!$F$19:$F$26/1000*Datos!$B$45/52) -> 18.87296 | I36: =SUMPRODUCT((Corte!$H$19:$H$26+I$8:I$15*Corte!$F$19:$F$26/1000*Datos!$B$48/12-ABS(Corte!$H$19:$H$26-I$8:I$15*Corte!$F$19:$F$26/1000*Datos!$B$48/12))/4+I$8:I$15*Corte!$F$19:$F$26/1000*Datos!$B$45/52) -> 20.819538 | J36: =SUMPRODUCT((Corte!$H$19:$H$26+J$8:J$15*Corte!$F$19:$F$26/1000*Datos!$B$48/12-ABS(Corte!$H$19:$H$26-J$8:J$15*Corte!$F$19:$F$26/1000*Datos!$B$48/12))/4+J$8:J$15*Corte!$F$19:$F$26/1000*Datos!$B$45/52) -> 22.782408 | ... L36: =SUMPRODUCT((Corte!$H$19:$H$26+L$8:L$15*Corte!$F$19:$F$26/1000*Datos!$B$48/12-ABS(Corte!$H$19:$H$26-L$8:L$15*Corte!$F$19:$F$26/1000*Datos!$B$48/12))/4+L$8:L$15*Corte!$F$19:$F$26/1000*Datos!$B$45/52) -> 25.669307
A37: Stock de rollos de fleje | B37: t | C37: =SUMPRODUCT((Corte!$K$31:$K$38+C$16:C$23*Corte!$I$31:$I$38/1000*Datos!$B$48/12-ABS(Corte!$K$31:$K$38-C$16:C$23*Corte!$I$31:$I$38/1000*Datos!$B$48/12))/4+C$16:C$23*Corte!$I$31:$I$38/1000*Datos!$B$45/52) -> 0.48748638 | D37: =SUMPRODUCT((Corte!$K$31:$K$38+D$16:D$23*Corte!$I$31:$I$38/1000*Datos!$B$48/12-ABS(Corte!$K$31:$K$38-D$16:D$23*Corte!$I$31:$I$38/1000*Datos!$B$48/12))/4+D$16:D$23*Corte!$I$31:$I$38/1000*Datos!$B$45/52) -> 0.82948043 | E37: =SUMPRODUCT((Corte!$K$31:$K$38+E$16:E$23*Corte!$I$31:$I$38/1000*Datos!$B$48/12-ABS(Corte!$K$31:$K$38-E$16:E$23*Corte!$I$31:$I$38/1000*Datos!$B$48/12))/4+E$16:E$23*Corte!$I$31:$I$38/1000*Datos!$B$45/52) -> 1.54095 | F37: =SUMPRODUCT((Corte!$K$31:$K$38+F$16:F$23*Corte!$I$31:$I$38/1000*Datos!$B$48/12-ABS(Corte!$K$31:$K$38-F$16:F$23*Corte!$I$31:$I$38/1000*Datos!$B$48/12))/4+F$16:F$23*Corte!$I$31:$I$38/1000*Datos!$B$45/52) -> 3.0506333 | G37: =SUMPRODUCT((Corte!$K$31:$K$38+G$16:G$23*Corte!$I$31:$I$38/1000*Datos!$B$48/12-ABS(Corte!$K$31:$K$38-G$16:G$23*Corte!$I$31:$I$38/1000*Datos!$B$48/12))/4+G$16:G$23*Corte!$I$31:$I$38/1000*Datos!$B$45/52) -> 4.8897833 | H37: =SUMPRODUCT((Corte!$K$31:$K$38+H$16:H$23*Corte!$I$31:$I$38/1000*Datos!$B$48/12-ABS(Corte!$K$31:$K$38-H$16:H$23*Corte!$I$31:$I$38/1000*Datos!$B$48/12))/4+H$16:H$23*Corte!$I$31:$I$38/1000*Datos!$B$45/52) -> 5.6160716 | I37: =SUMPRODUCT((Corte!$K$31:$K$38+I$16:I$23*Corte!$I$31:$I$38/1000*Datos!$B$48/12-ABS(Corte!$K$31:$K$38-I$16:I$23*Corte!$I$31:$I$38/1000*Datos!$B$48/12))/4+I$16:I$23*Corte!$I$31:$I$38/1000*Datos!$B$45/52) -> 6.4427612 | J37: =SUMPRODUCT((Corte!$K$31:$K$38+J$16:J$23*Corte!$I$31:$I$38/1000*Datos!$B$48/12-ABS(Corte!$K$31:$K$38-J$16:J$23*Corte!$I$31:$I$38/1000*Datos!$B$48/12))/4+J$16:J$23*Corte!$I$31:$I$38/1000*Datos!$B$45/52) -> 7.2073356 | ... L37: =SUMPRODUCT((Corte!$K$31:$K$38+L$16:L$23*Corte!$I$31:$I$38/1000*Datos!$B$48/12-ABS(Corte!$K$31:$K$38-L$16:L$23*Corte!$I$31:$I$38/1000*Datos!$B$48/12))/4+L$16:L$23*Corte!$I$31:$I$38/1000*Datos!$B$45/52) -> 8.1344632
A38: Stock promedio | B38: t | C38: =C36+C37 -> 2.1578927 | D38: =D36+D37 -> 3.6141128 | E38: =E36+E37 -> 6.5327112 | F38: =F36+F37 -> 12.685842 | G38: =G36+G37 -> 21.111837 | H38: =H36+H37 -> 24.489032 | I38: =I36+I37 -> 27.262299 | J38: =J36+J37 -> 29.989744 | ... L38: =L36+L37 -> 33.80377
A39: Costo financiero del stock | B39: USD | C39: =IF(C32=0,0,C38*C33/C32*Datos!$B$7) -> 313.03107 | D39: =IF(D32=0,0,D38*D33/D32*Datos!$B$7) -> 524.52993 | E39: =IF(E32=0,0,E38*E33/E32*Datos!$B$7) -> 951.93849 | F39: =IF(F32=0,0,F38*F33/F32*Datos!$B$7) -> 1854.6775 | G39: =IF(G32=0,0,G38*G33/G32*Datos!$B$7) -> 3088.6205 | H39: =IF(H32=0,0,H38*H33/H32*Datos!$B$7) -> 3583.3771 | I39: =IF(I32=0,0,I38*I33/I32*Datos!$B$7) -> 3990.7195 | J39: =IF(J32=0,0,J38*J33/J32*Datos!$B$7) -> 4390.6966 | ... L39: =IF(L32=0,0,L38*L33/L32*Datos!$B$7) -> 4948.0916
A40: Rollos de fleje por año | B40: rollos | C40: =SUMPRODUCT(C$16:C$23*Corte!$I$31:$I$38/1000/Corte!$K$31:$K$38) -> 2.1002188 | D40: =SUMPRODUCT(D$16:D$23*Corte!$I$31:$I$38/1000/Corte!$K$31:$K$38) -> 3.6781081 | E40: =SUMPRODUCT(E$16:E$23*Corte!$I$31:$I$38/1000/Corte!$K$31:$K$38) -> 7.1306797 | F40: =SUMPRODUCT(F$16:F$23*Corte!$I$31:$I$38/1000/Corte!$K$31:$K$38) -> 14.641278 | G40: =SUMPRODUCT(G$16:G$23*Corte!$I$31:$I$38/1000/Corte!$K$31:$K$38) -> 25.155074 | H40: =SUMPRODUCT(H$16:H$23*Corte!$I$31:$I$38/1000/Corte!$K$31:$K$38) -> 35.451269 | I40: =SUMPRODUCT(I$16:I$23*Corte!$I$31:$I$38/1000/Corte!$K$31:$K$38) -> 48.252825 | J40: =SUMPRODUCT(J$16:J$23*Corte!$I$31:$I$38/1000/Corte!$K$31:$K$38) -> 61.348573 | ... L40: =SUMPRODUCT(L$16:L$23*Corte!$I$31:$I$38/1000/Corte!$K$31:$K$38) -> 80.6218
A41: Horas-hombre de corte: línea + guillotina 1 + cambios de fleje | B41: h | C41: =SUMPRODUCT(C$8:C$15/Corte!$C$19:$C$26)/Datos!$B$36+SUM(C$8:C$15)/(Datos!$B$30*60)+C40*Datos!$B$41/60 -> 13.725867 | D41: =SUMPRODUCT(D$8:D$15/Corte!$C$19:$C$26)/Datos!$B$36+SUM(D$8:D$15)/(Datos!$B$30*60)+D40*Datos!$B$41/60 -> 21.877186 | E41: =SUMPRODUCT(E$8:E$15/Corte!$C$19:$C$26)/Datos!$B$36+SUM(E$8:E$15)/(Datos!$B$30*60)+E40*Datos!$B$41/60 -> 45.564203 | F41: =SUMPRODUCT(F$8:F$15/Corte!$C$19:$C$26)/Datos!$B$36+SUM(F$8:F$15)/(Datos!$B$30*60)+F40*Datos!$B$41/60 -> 99.718261 | G41: =SUMPRODUCT(G$8:G$15/Corte!$C$19:$C$26)/Datos!$B$36+SUM(G$8:G$15)/(Datos!$B$30*60)+G40*Datos!$B$41/60 -> 173.29751 | H41: =SUMPRODUCT(H$8:H$15/Corte!$C$19:$C$26)/Datos!$B$36+SUM(H$8:H$15)/(Datos!$B$30*60)+H40*Datos!$B$41/60 -> 243.30676 | I41: =SUMPRODUCT(I$8:I$15/Corte!$C$19:$C$26)/Datos!$B$36+SUM(I$8:I$15)/(Datos!$B$30*60)+I40*Datos!$B$41/60 -> 335.01059 | J41: =SUMPRODUCT(J$8:J$15/Corte!$C$19:$C$26)/Datos!$B$36+SUM(J$8:J$15)/(Datos!$B$30*60)+J40*Datos!$B$41/60 -> 427.74663 | ... L41: =SUMPRODUCT(L$8:L$15/Corte!$C$19:$C$26)/Datos!$B$36+SUM(L$8:L$15)/(Datos!$B$30*60)+L40*Datos!$B$41/60 -> 558.01462
A42: Mano de obra de corte | B42: USD | C42: =C41*Datos!$B$15 -> 86.216616 | D42: =D41*Datos!$B$15 -> 137.41769 | E42: =E41*Datos!$B$15 -> 286.20352 | F42: =F41*Datos!$B$15 -> 626.3627 | G42: =G41*Datos!$B$15 -> 1088.5378 | H42: =H41*Datos!$B$15 -> 1528.2886 | I42: =I41*Datos!$B$15 -> 2104.3101 | J42: =J41*Datos!$B$15 -> 2686.8152 | ... L42: =L41*Datos!$B$15 -> 3505.0706
A43: Mantenimiento de equipos | B43: USD | C43: =Datos!$C$112*Datos!$B$8 -> 5034 | D43: =Datos!$C$112*Datos!$B$8 -> 5034 | E43: =Datos!$C$112*Datos!$B$8 -> 5034 | F43: =Datos!$C$112*Datos!$B$8 -> 5034 | G43: =Datos!$C$112*Datos!$B$8 -> 5034 | H43: =Datos!$C$112*Datos!$B$8 -> 5034 | I43: =Datos!$C$112*Datos!$B$8 -> 5034 | J43: =Datos!$C$112*Datos!$B$8 -> 5034 | ... L43: =Datos!$C$112*Datos!$B$8 -> 5034
A44: COSTO ANUAL A | B44: USD | C44: =C33+C35+C39+C42+C43 -> 21082.256 | D44: =D33+D35+D39+D42+D43 -> 31913.795 | E44: =E33+E35+E39+E42+E43 -> 53855.861 | F44: =F33+F35+F39+F42+F43 -> 100228.34 | G44: =G33+G35+G39+G42+G43 -> 167262.8 | H44: =H33+H35+H39+H42+H43 -> 231448.09 | I44: =I33+I35+I39+I42+I43 -> 311502.74 | J44: =J33+J35+J39+J42+J43 -> 393190.12 | ... L44: =L33+L35+L39+L42+L43 -> 512740.56
A46: B — Hojas para todo: cuerpos con dos guillotinas y discos de tiras de hoja
A47: Hojas mixtas 70 + 100 kg | B47: hojas | C47: =IF(Datos!$B$24="SI",MIN(C15/Datos!$B$25,C14/Datos!$B$26),0) -> 6.1149533 | D47: =IF(Datos!$B$24="SI",MIN(D15/Datos!$B$25,D14/Datos!$B$26),0) -> 9.4072769 | E47: =IF(Datos!$B$24="SI",MIN(E15/Datos!$B$25,E14/Datos!$B$26),0) -> 14.420033 | F47: =IF(Datos!$B$24="SI",MIN(F15/Datos!$B$25,F14/Datos!$B$26),0) -> 24.604776 | G47: =IF(Datos!$B$24="SI",MIN(G15/Datos!$B$25,G14/Datos!$B$26),0) -> 40.753494 | H47: =IF(Datos!$B$24="SI",MIN(H15/Datos!$B$25,H14/Datos!$B$26),0) -> 55.842851 | I47: =IF(Datos!$B$24="SI",MIN(I15/Datos!$B$25,I14/Datos!$B$26),0) -> 74.826917 | J47: =IF(Datos!$B$24="SI",MIN(J15/Datos!$B$25,J14/Datos!$B$26),0) -> 93.882454 | ... L47: =IF(Datos!$B$24="SI",MIN(L15/Datos!$B$25,L14/Datos!$B$26),0) -> 124.70995
A48: Hojas de 70 kg solas | B48: hojas | C48: =(C14-Datos!$B$26*C47)/Corte!$D$12 -> 0 | D48: =(D14-Datos!$B$26*D47)/Corte!$D$12 -> 0 | E48: =(E14-Datos!$B$26*E47)/Corte!$D$12 -> 0 | F48: =(F14-Datos!$B$26*F47)/Corte!$D$12 -> 0 | G48: =(G14-Datos!$B$26*G47)/Corte!$D$12 -> 0 | H48: =(H14-Datos!$B$26*H47)/Corte!$D$12 -> 0 | I48: =(I14-Datos!$B$26*I47)/Corte!$D$12 -> 0 | J48: =(J14-Datos!$B$26*J47)/Corte!$D$12 -> 0 | ... L48: =(L14-Datos!$B$26*L47)/Corte!$D$12 -> 0
A49: Hojas de 100 kg solas | B49: hojas | C49: =(C15-Datos!$B$25*C47)/Corte!$D$13 -> 2.26054 | D49: =(D15-Datos!$B$25*D47)/Corte!$D$13 -> 3.1535368 | E49: =(E15-Datos!$B$25*E47)/Corte!$D$13 -> 4.8022332 | F49: =(F15-Datos!$B$25*F47)/Corte!$D$13 -> 7.9082588 | G49: =(G15-Datos!$B$25*G47)/Corte!$D$13 -> 13.295609 | H49: =(H15-Datos!$B$25*H47)/Corte!$D$13 -> 18.672061 | I49: =(I15-Datos!$B$25*I47)/Corte!$D$13 -> 24.715639 | J49: =(J15-Datos!$B$25*J47)/Corte!$D$13 -> 30.876374 | ... L49: =(L15-Datos!$B$25*L47)/Corte!$D$13 -> 40.912206
A50: Hojas para cuerpos | B50: hojas | C50: =SUMPRODUCT(C$8:C$13/Corte!$D$6:$D$11)+C48+C49+C47 -> 326.13399 | D50: =SUMPRODUCT(D$8:D$13/Corte!$D$6:$D$11)+D48+D49+D47 -> 541.58456 | E50: =SUMPRODUCT(E$8:E$13/Corte!$D$6:$D$11)+E48+E49+E47 -> 1019.0563 | F50: =SUMPRODUCT(F$8:F$13/Corte!$D$6:$D$11)+F48+F49+F47 -> 2049.4415 | G50: =SUMPRODUCT(G$8:G$13/Corte!$D$6:$D$11)+G48+G49+G47 -> 3513.283 | H50: =SUMPRODUCT(H$8:H$13/Corte!$D$6:$D$11)+H48+H49+H47 -> 4919.7289 | I50: =SUMPRODUCT(I$8:I$13/Corte!$D$6:$D$11)+I48+I49+I47 -> 6707.4173 | J50: =SUMPRODUCT(J$8:J$13/Corte!$D$6:$D$11)+J48+J49+J47 -> 8525.2558 | ... L50: =SUMPRODUCT(L$8:L$13/Corte!$D$6:$D$11)+L48+L49+L47 -> 11144.576
A51: Acero de hojas para cuerpos | B51: t | C51: =(SUMPRODUCT(C$8:C$13/Corte!$D$6:$D$11*Corte!$P$6:$P$11)+C48*Corte!$P$12+C49*Corte!$P$13+C47*Corte!$P$14)/1000 -> 10.84815 | D51: =(SUMPRODUCT(D$8:D$13/Corte!$D$6:$D$11*Corte!$P$6:$P$11)+D48*Corte!$P$12+D49*Corte!$P$13+D47*Corte!$P$14)/1000 -> 18.042092 | E51: =(SUMPRODUCT(E$8:E$13/Corte!$D$6:$D$11*Corte!$P$6:$P$11)+E48*Corte!$P$12+E49*Corte!$P$13+E47*Corte!$P$14)/1000 -> 32.224286 | F51: =(SUMPRODUCT(F$8:F$13/Corte!$D$6:$D$11*Corte!$P$6:$P$11)+F48*Corte!$P$12+F49*Corte!$P$13+F47*Corte!$P$14)/1000 -> 62.017276 | G51: =(SUMPRODUCT(G$8:G$13/Corte!$D$6:$D$11*Corte!$P$6:$P$11)+G48*Corte!$P$12+G49*Corte!$P$13+G47*Corte!$P$14)/1000 -> 105.4753 | H51: =(SUMPRODUCT(H$8:H$13/Corte!$D$6:$D$11*Corte!$P$6:$P$11)+H48*Corte!$P$12+H49*Corte!$P$13+H47*Corte!$P$14)/1000 -> 147.57415 | I51: =(SUMPRODUCT(I$8:I$13/Corte!$D$6:$D$11*Corte!$P$6:$P$11)+I48*Corte!$P$12+I49*Corte!$P$13+I47*Corte!$P$14)/1000 -> 200.03389 | J51: =(SUMPRODUCT(J$8:J$13/Corte!$D$6:$D$11*Corte!$P$6:$P$11)+J48*Corte!$P$12+J49*Corte!$P$13+J47*Corte!$P$14)/1000 -> 253.6198 | ... L51: =(SUMPRODUCT(L$8:L$13/Corte!$D$6:$D$11*Corte!$P$6:$P$11)+L48*Corte!$P$12+L49*Corte!$P$13+L47*Corte!$P$14)/1000 -> 332.54094
A52: Costo de las hojas para cuerpos | B52: USD | C52: =SUMPRODUCT(C$8:C$13/Corte!$D$6:$D$11*Corte!$Q$6:$Q$11)+C48*Corte!$Q$12+C49*Corte!$Q$13+C47*Corte!$Q$14 -> 13660.407 | D52: =SUMPRODUCT(D$8:D$13/Corte!$D$6:$D$11*Corte!$Q$6:$Q$11)+D48*Corte!$Q$12+D49*Corte!$Q$13+D47*Corte!$Q$14 -> 22741.856 | E52: =SUMPRODUCT(E$8:E$13/Corte!$D$6:$D$11*Corte!$Q$6:$Q$11)+E48*Corte!$Q$12+E49*Corte!$Q$13+E47*Corte!$Q$14 -> 40959.055 | F52: =SUMPRODUCT(F$8:F$13/Corte!$D$6:$D$11*Corte!$Q$6:$Q$11)+F48*Corte!$Q$12+F49*Corte!$Q$13+F47*Corte!$Q$14 -> 79376.04 | G52: =SUMPRODUCT(G$8:G$13/Corte!$D$6:$D$11*Corte!$Q$6:$Q$11)+G48*Corte!$Q$12+G49*Corte!$Q$13+G47*Corte!$Q$14 -> 135185.27 | H52: =SUMPRODUCT(H$8:H$13/Corte!$D$6:$D$11*Corte!$Q$6:$Q$11)+H48*Corte!$Q$12+H49*Corte!$Q$13+H47*Corte!$Q$14 -> 189202.65 | I52: =SUMPRODUCT(I$8:I$13/Corte!$D$6:$D$11*Corte!$Q$6:$Q$11)+I48*Corte!$Q$12+I49*Corte!$Q$13+I47*Corte!$Q$14 -> 256682.38 | J52: =SUMPRODUCT(J$8:J$13/Corte!$D$6:$D$11*Corte!$Q$6:$Q$11)+J48*Corte!$Q$12+J49*Corte!$Q$13+J47*Corte!$Q$14 -> 325564.31 | ... L52: =SUMPRODUCT(L$8:L$13/Corte!$D$6:$D$11*Corte!$Q$6:$Q$11)+L48*Corte!$Q$12+L49*Corte!$Q$13+L47*Corte!$Q$14 -> 426654.87
A53: Horas de la guillotina 1 (franjas; los dos cortes en rodantes) | B53: h | C53: =(SUMPRODUCT(C$8:C$13/Corte!$D$6:$D$11*Corte!$M$6:$M$11)+C48*Corte!$M$12+C49*Corte!$M$13+C47*Corte!$M$14)/Datos!$B$30/60 -> 1.9526096 | D53: =(SUMPRODUCT(D$8:D$13/Corte!$D$6:$D$11*Corte!$M$6:$M$11)+D48*Corte!$M$12+D49*Corte!$M$13+D47*Corte!$M$14)/Datos!$B$30/60 -> 3.1730333 | E53: =(SUMPRODUCT(E$8:E$13/Corte!$D$6:$D$11*Corte!$M$6:$M$11)+E48*Corte!$M$12+E49*Corte!$M$13+E47*Corte!$M$14)/Datos!$B$30/60 -> 6.2028094 | F53: =(SUMPRODUCT(F$8:F$13/Corte!$D$6:$D$11*Corte!$M$6:$M$11)+F48*Corte!$M$12+F49*Corte!$M$13+F47*Corte!$M$14)/Datos!$B$30/60 -> 12.90667 | G53: =(SUMPRODUCT(G$8:G$13/Corte!$D$6:$D$11*Corte!$M$6:$M$11)+G48*Corte!$M$12+G49*Corte!$M$13+G47*Corte!$M$14)/Datos!$B$30/60 -> 22.257078 | H53: =(SUMPRODUCT(H$8:H$13/Corte!$D$6:$D$11*Corte!$M$6:$M$11)+H48*Corte!$M$12+H49*Corte!$M$13+H47*Corte!$M$14)/Datos!$B$30/60 -> 31.189674 | I53: =(SUMPRODUCT(I$8:I$13/Corte!$D$6:$D$11*Corte!$M$6:$M$11)+I48*Corte!$M$12+I49*Corte!$M$13+I47*Corte!$M$14)/Datos!$B$30/60 -> 42.715521 | J53: =(SUMPRODUCT(J$8:J$13/Corte!$D$6:$D$11*Corte!$M$6:$M$11)+J48*Corte!$M$12+J49*Corte!$M$13+J47*Corte!$M$14)/Datos!$B$30/60 -> 54.401003 | ... L53: =(SUMPRODUCT(L$8:L$13/Corte!$D$6:$D$11*Corte!$M$6:$M$11)+L48*Corte!$M$12+L49*Corte!$M$13+L47*Corte!$M$14)/Datos!$B$30/60 -> 71.008611
A54: Horas de la guillotina 2 (piezas, franjas en paralelo) | B54: h | C54: =(SUMPRODUCT(C$8:C$13/Corte!$D$6:$D$11*Corte!$N$6:$N$11)+C48*Corte!$N$12+C49*Corte!$N$13+C47*Corte!$N$14)/Datos!$B$33/60 -> 0.67821712 | D54: =(SUMPRODUCT(D$8:D$13/Corte!$D$6:$D$11*Corte!$N$6:$N$11)+D48*Corte!$N$12+D49*Corte!$N$13+D47*Corte!$N$14)/Datos!$B$33/60 -> 1.1006376 | E54: =(SUMPRODUCT(E$8:E$13/Corte!$D$6:$D$11*Corte!$N$6:$N$11)+E48*Corte!$N$12+E49*Corte!$N$13+E47*Corte!$N$14)/Datos!$B$33/60 -> 2.2534052 | F54: =(SUMPRODUCT(F$8:F$13/Corte!$D$6:$D$11*Corte!$N$6:$N$11)+F48*Corte!$N$12+F49*Corte!$N$13+F47*Corte!$N$14)/Datos!$B$33/60 -> 4.8631422 | G54: =(SUMPRODUCT(G$8:G$13/Corte!$D$6:$D$11*Corte!$N$6:$N$11)+G48*Corte!$N$12+G49*Corte!$N$13+G47*Corte!$N$14)/Datos!$B$33/60 -> 8.4299817 | H54: =(SUMPRODUCT(H$8:H$13/Corte!$D$6:$D$11*Corte!$N$6:$N$11)+H48*Corte!$N$12+H49*Corte!$N$13+H47*Corte!$N$14)/Datos!$B$33/60 -> 11.83658 | I54: =(SUMPRODUCT(I$8:I$13/Corte!$D$6:$D$11*Corte!$N$6:$N$11)+I48*Corte!$N$12+I49*Corte!$N$13+I47*Corte!$N$14)/Datos!$B$33/60 -> 16.263877 | J54: =(SUMPRODUCT(J$8:J$13/Corte!$D$6:$D$11*Corte!$N$6:$N$11)+J48*Corte!$N$12+J49*Corte!$N$13+J47*Corte!$N$14)/Datos!$B$33/60 -> 20.748536 | ... L54: =(SUMPRODUCT(L$8:L$13/Corte!$D$6:$D$11*Corte!$N$6:$N$11)+L48*Corte!$N$12+L49*Corte!$N$13+L47*Corte!$N$14)/Datos!$B$33/60 -> 27.098133
A55: Acero de hojas para discos | B55: t | C55: =SUMPRODUCT(C$8:C$11,Corte!$E$42:$E$45)/1000 -> 3.302289 | D55: =SUMPRODUCT(D$8:D$11,Corte!$E$42:$E$45)/1000 -> 5.6308561 | E55: =SUMPRODUCT(E$8:E$11,Corte!$E$42:$E$45)/1000 -> 10.400856 | F55: =SUMPRODUCT(F$8:F$11,Corte!$E$42:$E$45)/1000 -> 20.478221 | G55: =SUMPRODUCT(G$8:G$11,Corte!$E$42:$E$45)/1000 -> 34.986525 | H55: =SUMPRODUCT(H$8:H$11,Corte!$E$42:$E$45)/1000 -> 49.023585 | I55: =SUMPRODUCT(I$8:I$11,Corte!$E$42:$E$45)/1000 -> 66.59764 | J55: =SUMPRODUCT(J$8:J$11,Corte!$E$42:$E$45)/1000 -> 84.513284 | ... L55: =SUMPRODUCT(L$8:L$11,Corte!$E$42:$E$45)/1000 -> 110.59107
A56: Costo de las hojas para discos | B56: USD | C56: =SUMPRODUCT(C$8:C$11,Corte!$F$42:$F$45) -> 4367.5536 | D56: =SUMPRODUCT(D$8:D$11,Corte!$F$42:$F$45) -> 7444.7367 | E56: =SUMPRODUCT(E$8:E$11,Corte!$F$42:$F$45) -> 13744.937 | F56: =SUMPRODUCT(F$8:F$11,Corte!$F$42:$F$45) -> 27050.445 | G56: =SUMPRODUCT(G$8:G$11,Corte!$F$42:$F$45) -> 46212.984 | H56: =SUMPRODUCT(H$8:H$11,Corte!$F$42:$F$45) -> 64750.404 | I56: =SUMPRODUCT(I$8:I$11,Corte!$F$42:$F$45) -> 87960.879 | J56: =SUMPRODUCT(J$8:J$11,Corte!$F$42:$F$45) -> 111621.25 | ... L56: =SUMPRODUCT(L$8:L$11,Corte!$F$42:$F$45) -> 146053.97
A57: Tiras de hoja para discos | B57: tiras | C57: =SUMPRODUCT(C$8:C$11,Corte!$G$42:$G$45) -> 972.9656 | D57: =SUMPRODUCT(D$8:D$11,Corte!$G$42:$G$45) -> 1612.1519 | E57: =SUMPRODUCT(E$8:E$11,Corte!$G$42:$G$45) -> 3106.672 | F57: =SUMPRODUCT(F$8:F$11,Corte!$G$42:$G$45) -> 6370.1632 | G57: =SUMPRODUCT(G$8:G$11,Corte!$G$42:$G$45) -> 10957.572 | H57: =SUMPRODUCT(H$8:H$11,Corte!$G$42:$G$45) -> 15354.886 | I57: =SUMPRODUCT(I$8:I$11,Corte!$G$42:$G$45) -> 20981.811 | J57: =SUMPRODUCT(J$8:J$11,Corte!$G$42:$G$45) -> 26694.37 | ... L57: =SUMPRODUCT(L$8:L$11,Corte!$G$42:$G$45) -> 34867.904
A58: Acero comprado | B58: t | C58: =C51+C55 -> 14.150439 | D58: =D51+D55 -> 23.672948 | E58: =E51+E55 -> 42.625142 | F58: =F51+F55 -> 82.495498 | G58: =G51+G55 -> 140.46182 | H58: =H51+H55 -> 196.59773 | I58: =I51+I55 -> 266.63153 | J58: =J51+J55 -> 338.13309 | ... L58: =L51+L55 -> 443.13201
A59: Costo del acero | B59: USD | C59: =C52+C56 -> 18027.96 | D59: =D52+D56 -> 30186.593 | E59: =E52+E56 -> 54703.992 | F59: =F52+F56 -> 106426.48 | G59: =G52+G56 -> 181398.26 | H59: =H52+H56 -> 253953.06 | I59: =I52+I56 -> 344643.26 | J59: =J52+J56 -> 437185.56 | ... L59: =L52+L56 -> 572708.84
A60: Scrap | B60: t | C60: =C58-C25 -> 2.186966 | D60: =D58-D25 -> 3.6546605 | E60: =E58-E25 -> 6.4462367 | F60: =F58-F25 -> 12.243532 | G60: =G58-G25 -> 20.777135 | H60: =H58-H25 -> 29.050993 | I60: =I58-I25 -> 39.307304 | J60: =J58-J25 -> 49.786271 | ... L60: =L58-L25 -> 65.30157
A61: Venta de scrap (resta) | B61: USD | C61: =-C60*Datos!$B$9 -> -546.74151 | D61: =-D60*Datos!$B$9 -> -913.66514 | E61: =-E60*Datos!$B$9 -> -1611.5592 | F61: =-F60*Datos!$B$9 -> -3060.8829 | G61: =-G60*Datos!$B$9 -> -5194.2836 | H61: =-H60*Datos!$B$9 -> -7262.7483 | I61: =-I60*Datos!$B$9 -> -9826.826 | J61: =-J60*Datos!$B$9 -> -12446.568 | ... L61: =-L60*Datos!$B$9 -> -16325.392
A62: Stock promedio (hojas) | B62: t | C62: =C58*(Datos!$B$46/2/12+Datos!$B$45/52) -> 1.1338493 | D62: =D58*(Datos!$B$46/2/12+Datos!$B$45/52) -> 1.8968708 | E62: =E58*(Datos!$B$46/2/12+Datos!$B$45/52) -> 3.4154762 | F62: =F58*(Datos!$B$46/2/12+Datos!$B$45/52) -> 6.6102161 | G62: =G58*(Datos!$B$46/2/12+Datos!$B$45/52) -> 11.254954 | H62: =H58*(Datos!$B$46/2/12+Datos!$B$45/52) -> 15.753023 | I62: =I58*(Datos!$B$46/2/12+Datos!$B$45/52) -> 21.364706 | J62: =J58*(Datos!$B$46/2/12+Datos!$B$45/52) -> 27.093997 | ... L62: =L58*(Datos!$B$46/2/12+Datos!$B$45/52) -> 35.507373
A63: Costo financiero del stock | B63: USD | C63: =IF(C58=0,0,C62*C59/C58*Datos!$B$7) -> 173.34577 | D63: =IF(D58=0,0,D62*D59/D58*Datos!$B$7) -> 290.2557 | E63: =IF(E58=0,0,E62*E59/E58*Datos!$B$7) -> 525.99992 | F63: =IF(F58=0,0,F62*F59/F58*Datos!$B$7) -> 1023.3316 | G63: =IF(G58=0,0,G62*G59/G58*Datos!$B$7) -> 1744.214 | H63: =IF(H58=0,0,H62*H59/H58*Datos!$B$7) -> 2441.8563 | I63: =IF(I58=0,0,I62*I59/I58*Datos!$B$7) -> 3313.8775 | J63: =IF(J58=0,0,J62*J59/J58*Datos!$B$7) -> 4203.7073 | ... L63: =IF(L58=0,0,L62*L59/L58*Datos!$B$7) -> 5506.8157
A64: Horas-hombre de corte: guillotinas + tiras + carga manual | B64: h | C64: =C53+C54+C57/Datos!$B$30/60+C57*Datos!$B$40/3600 -> 8.3064594 | D64: =D53+D54+D57/Datos!$B$30/60+D57*Datos!$B$40/3600 -> 13.67789 | E64: =E53+E54+E57/Datos!$B$30/60+E57*Datos!$B$40/3600 -> 26.578468 | F64: =F53+F54+F57/Datos!$B$30/60+F57*Datos!$B$40/3600 -> 54.929098 | G64: =G53+G54+G57/Datos!$B$30/60+G57*Datos!$B$40/3600 -> 94.606228 | H64: =H53+H54+H57/Datos!$B$30/60+H57*Datos!$B$40/3600 -> 132.59642 | I64: =I53+I54+I57/Datos!$B$30/60+I57*Datos!$B$40/3600 -> 181.37329 | J64: =J53+J54+J57/Datos!$B$30/60+J57*Datos!$B$40/3600 -> 230.8667 | ... L64: =L53+L54+L57/Datos!$B$30/60+L57*Datos!$B$40/3600 -> 301.50285
A65: Mano de obra de corte | B65: USD | C65: =C64*Datos!$B$15 -> 52.175562 | D65: =D64*Datos!$B$15 -> 85.91526 | E65: =E64*Datos!$B$15 -> 166.94797 | F65: =F64*Datos!$B$15 -> 345.02746 | G65: =G64*Datos!$B$15 -> 594.25237 | H65: =H64*Datos!$B$15 -> 832.88107 | I65: =I64*Datos!$B$15 -> 1139.2644 | J65: =J64*Datos!$B$15 -> 1450.1485 | ... L65: =L64*Datos!$B$15 -> 1893.8371
A66: Mantenimiento de equipos | B66: USD | C66: =Datos!$D$112*Datos!$B$8 -> 2385 | D66: =Datos!$D$112*Datos!$B$8 -> 2385 | E66: =Datos!$D$112*Datos!$B$8 -> 2385 | F66: =Datos!$D$112*Datos!$B$8 -> 2385 | G66: =Datos!$D$112*Datos!$B$8 -> 2385 | H66: =Datos!$D$112*Datos!$B$8 -> 2385 | I66: =Datos!$D$112*Datos!$B$8 -> 2385 | J66: =Datos!$D$112*Datos!$B$8 -> 2385 | ... L66: =Datos!$D$112*Datos!$B$8 -> 2385
A67: COSTO ANUAL B | B67: USD | C67: =C59+C61+C63+C65+C66 -> 20091.74 | D67: =D59+D61+D63+D65+D66 -> 32034.099 | E67: =E59+E61+E63+E65+E66 -> 56170.381 | F67: =F59+F61+F63+F65+F66 -> 107118.96 | G67: =G59+G61+G63+G65+G66 -> 180927.44 | H67: =H59+H61+H63+H65+H66 -> 252350.05 | I67: =I59+I61+I63+I65+I66 -> 341654.57 | J67: =J59+J61+J63+J65+J66 -> 432777.85 | ... L67: =L59+L61+L63+L65+L66 -> 566169.1
A69: C — Bobina madre por espesor con corte longitudinal propio
A70: Metros de madre de 0,9 mm | B70: m | C70: =MAX(IF(Corte!$H$60=0,IF(C8>0,1000000000000,0),C8*Corte!$D$60/1000/Corte!$H$60),IF(Corte!$H$61=0,IF(C8>0,1000000000000,0),C8*Corte!$D$61/1000/Corte!$H$61)) -> 249.28943 | D70: =MAX(IF(Corte!$H$60=0,IF(D8>0,1000000000000,0),D8*Corte!$D$60/1000/Corte!$H$60),IF(Corte!$H$61=0,IF(D8>0,1000000000000,0),D8*Corte!$D$61/1000/Corte!$H$61)) -> 357.77908 | E70: =MAX(IF(Corte!$H$60=0,IF(E8>0,1000000000000,0),E8*Corte!$D$60/1000/Corte!$H$60),IF(Corte!$H$61=0,IF(E8>0,1000000000000,0),E8*Corte!$D$61/1000/Corte!$H$61)) -> 865.86547 | F70: =MAX(IF(Corte!$H$60=0,IF(F8>0,1000000000000,0),F8*Corte!$D$60/1000/Corte!$H$60),IF(Corte!$H$61=0,IF(F8>0,1000000000000,0),F8*Corte!$D$61/1000/Corte!$H$61)) -> 2097.6434 | G70: =MAX(IF(Corte!$H$60=0,IF(G8>0,1000000000000,0),G8*Corte!$D$60/1000/Corte!$H$60),IF(Corte!$H$61=0,IF(G8>0,1000000000000,0),G8*Corte!$D$61/1000/Corte!$H$61)) -> 3705.5988 | H70: =MAX(IF(Corte!$H$60=0,IF(H8>0,1000000000000,0),H8*Corte!$D$60/1000/Corte!$H$60),IF(Corte!$H$61=0,IF(H8>0,1000000000000,0),H8*Corte!$D$61/1000/Corte!$H$61)) -> 5208.0528 | I70: =MAX(IF(Corte!$H$60=0,IF(I8>0,1000000000000,0),I8*Corte!$D$60/1000/Corte!$H$60),IF(Corte!$H$61=0,IF(I8>0,1000000000000,0),I8*Corte!$D$61/1000/Corte!$H$61)) -> 7258.613 | J70: =MAX(IF(Corte!$H$60=0,IF(J8>0,1000000000000,0),J8*Corte!$D$60/1000/Corte!$H$60),IF(Corte!$H$61=0,IF(J8>0,1000000000000,0),J8*Corte!$D$61/1000/Corte!$H$61)) -> 9314.3768 | ... L70: =MAX(IF(Corte!$H$60=0,IF(L8>0,1000000000000,0),L8*Corte!$D$60/1000/Corte!$H$60),IF(Corte!$H$61=0,IF(L8>0,1000000000000,0),L8*Corte!$D$61/1000/Corte!$H$61)) -> 12087.669
A71: Metros de madre de 1,25 mm | B71: m | C71: =MAX(IF(Corte!$H$68=0,IF(C9>0,1000000000000,0),C9*Corte!$D$68/1000/Corte!$H$68),IF(Corte!$H$69=0,IF(C9>0,1000000000000,0),C9*Corte!$D$69/1000/Corte!$H$69),IF(Corte!$H$70=0,IF(C9>0,1000000000000,0),C9*Corte!$D$70/1000/Corte!$H$70),IF(Corte!$H$71=0,IF(C8>0,1000000000000,0),C8*Corte!$D$71/1000/Corte!$H$71)) -> 89.136276 | D71: =MAX(IF(Corte!$H$68=0,IF(D9>0,1000000000000,0),D9*Corte!$D$68/1000/Corte!$H$68),IF(Corte!$H$69=0,IF(D9>0,1000000000000,0),D9*Corte!$D$69/1000/Corte!$H$69),IF(Corte!$H$70=0,IF(D9>0,1000000000000,0),D9*Corte!$D$70/1000/Corte!$H$70),IF(Corte!$H$71=0,IF(D8>0,1000000000000,0),D8*Corte!$D$71/1000/Corte!$H$71)) -> 214.63967 | E71: =MAX(IF(Corte!$H$68=0,IF(E9>0,1000000000000,0),E9*Corte!$D$68/1000/Corte!$H$68),IF(Corte!$H$69=0,IF(E9>0,1000000000000,0),E9*Corte!$D$69/1000/Corte!$H$69),IF(Corte!$H$70=0,IF(E9>0,1000000000000,0),E9*Corte!$D$70/1000/Corte!$H$70),IF(Corte!$H$71=0,IF(E8>0,1000000000000,0),E8*Corte!$D$71/1000/Corte!$H$71)) -> 388.79226 | F71: =MAX(IF(Corte!$H$68=0,IF(F9>0,1000000000000,0),F9*Corte!$D$68/1000/Corte!$H$68),IF(Corte!$H$69=0,IF(F9>0,1000000000000,0),F9*Corte!$D$69/1000/Corte!$H$69),IF(Corte!$H$70=0,IF(F9>0,1000000000000,0),F9*Corte!$D$70/1000/Corte!$H$70),IF(Corte!$H$71=0,IF(F8>0,1000000000000,0),F8*Corte!$D$71/1000/Corte!$H$71)) -> 765.16043 | G71: =MAX(IF(Corte!$H$68=0,IF(G9>0,1000000000000,0),G9*Corte!$D$68/1000/Corte!$H$68),IF(Corte!$H$69=0,IF(G9>0,1000000000000,0),G9*Corte!$D$69/1000/Corte!$H$69),IF(Corte!$H$70=0,IF(G9>0,1000000000000,0),G9*Corte!$D$70/1000/Corte!$H$70),IF(Corte!$H$71=0,IF(G8>0,1000000000000,0),G8*Corte!$D$71/1000/Corte!$H$71)) -> 1268.2604 | H71: =MAX(IF(Corte!$H$68=0,IF(H9>0,1000000000000,0),H9*Corte!$D$68/1000/Corte!$H$68),IF(Corte!$H$69=0,IF(H9>0,1000000000000,0),H9*Corte!$D$69/1000/Corte!$H$69),IF(Corte!$H$70=0,IF(H9>0,1000000000000,0),H9*Corte!$D$70/1000/Corte!$H$70),IF(Corte!$H$71=0,IF(H8>0,1000000000000,0),H8*Corte!$D$71/1000/Corte!$H$71)) -> 1804.1346 | I71: =MAX(IF(Corte!$H$68=0,IF(I9>0,1000000000000,0),I9*Corte!$D$68/1000/Corte!$H$68),IF(Corte!$H$69=0,IF(I9>0,1000000000000,0),I9*Corte!$D$69/1000/Corte!$H$69),IF(Corte!$H$70=0,IF(I9>0,1000000000000,0),I9*Corte!$D$70/1000/Corte!$H$70),IF(Corte!$H$71=0,IF(I8>0,1000000000000,0),I8*Corte!$D$71/1000/Corte!$H$71)) -> 2484.2115 | J71: =MAX(IF(Corte!$H$68=0,IF(J9>0,1000000000000,0),J9*Corte!$D$68/1000/Corte!$H$68),IF(Corte!$H$69=0,IF(J9>0,1000000000000,0),J9*Corte!$D$69/1000/Corte!$H$69),IF(Corte!$H$70=0,IF(J9>0,1000000000000,0),J9*Corte!$D$70/1000/Corte!$H$70),IF(Corte!$H$71=0,IF(J8>0,1000000000000,0),J8*Corte!$D$71/1000/Corte!$H$71)) -> 3187.7828 | ... L71: =MAX(IF(Corte!$H$68=0,IF(L9>0,1000000000000,0),L9*Corte!$D$68/1000/Corte!$H$68),IF(Corte!$H$69=0,IF(L9>0,1000000000000,0),L9*Corte!$D$69/1000/Corte!$H$69),IF(Corte!$H$70=0,IF(L9>0,1000000000000,0),L9*Corte!$D$70/1000/Corte!$H$70),IF(Corte!$H$71=0,IF(L8>0,1000000000000,0),L8*Corte!$D$71/1000/Corte!$H$71)) -> 4171.6833
A72: Metros de madre de 1,6 mm | B72: m | C72: =MAX(IF(Corte!$H$78=0,IF(C10>0,1000000000000,0),C10*Corte!$D$78/1000/Corte!$H$78),IF(Corte!$H$79=0,IF(C10>0,1000000000000,0),C10*Corte!$D$79/1000/Corte!$H$79),IF(Corte!$H$80=0,IF(C10>0,1000000000000,0),C10*Corte!$D$80/1000/Corte!$H$80),IF(Corte!$H$81=0,IF(C11>0,1000000000000,0),C11*Corte!$D$81/1000/Corte!$H$81)) -> 540.2497 | D72: =MAX(IF(Corte!$H$78=0,IF(D10>0,1000000000000,0),D10*Corte!$D$78/1000/Corte!$H$78),IF(Corte!$H$79=0,IF(D10>0,1000000000000,0),D10*Corte!$D$79/1000/Corte!$H$79),IF(Corte!$H$80=0,IF(D10>0,1000000000000,0),D10*Corte!$D$80/1000/Corte!$H$80),IF(Corte!$H$81=0,IF(D11>0,1000000000000,0),D11*Corte!$D$81/1000/Corte!$H$81)) -> 930.93268 | E72: =MAX(IF(Corte!$H$78=0,IF(E10>0,1000000000000,0),E10*Corte!$D$78/1000/Corte!$H$78),IF(Corte!$H$79=0,IF(E10>0,1000000000000,0),E10*Corte!$D$79/1000/Corte!$H$79),IF(Corte!$H$80=0,IF(E10>0,1000000000000,0),E10*Corte!$D$80/1000/Corte!$H$80),IF(Corte!$H$81=0,IF(E11>0,1000000000000,0),E11*Corte!$D$81/1000/Corte!$H$81)) -> 1590.6931 | F72: =MAX(IF(Corte!$H$78=0,IF(F10>0,1000000000000,0),F10*Corte!$D$78/1000/Corte!$H$78),IF(Corte!$H$79=0,IF(F10>0,1000000000000,0),F10*Corte!$D$79/1000/Corte!$H$79),IF(Corte!$H$80=0,IF(F10>0,1000000000000,0),F10*Corte!$D$80/1000/Corte!$H$80),IF(Corte!$H$81=0,IF(F11>0,1000000000000,0),F11*Corte!$D$81/1000/Corte!$H$81)) -> 2891.9234 | G72: =MAX(IF(Corte!$H$78=0,IF(G10>0,1000000000000,0),G10*Corte!$D$78/1000/Corte!$H$78),IF(Corte!$H$79=0,IF(G10>0,1000000000000,0),G10*Corte!$D$79/1000/Corte!$H$79),IF(Corte!$H$80=0,IF(G10>0,1000000000000,0),G10*Corte!$D$80/1000/Corte!$H$80),IF(Corte!$H$81=0,IF(G11>0,1000000000000,0),G11*Corte!$D$81/1000/Corte!$H$81)) -> 4873.4715 | H72: =MAX(IF(Corte!$H$78=0,IF(H10>0,1000000000000,0),H10*Corte!$D$78/1000/Corte!$H$78),IF(Corte!$H$79=0,IF(H10>0,1000000000000,0),H10*Corte!$D$79/1000/Corte!$H$79),IF(Corte!$H$80=0,IF(H10>0,1000000000000,0),H10*Corte!$D$80/1000/Corte!$H$80),IF(Corte!$H$81=0,IF(H11>0,1000000000000,0),H11*Corte!$D$81/1000/Corte!$H$81)) -> 6790.9263 | I72: =MAX(IF(Corte!$H$78=0,IF(I10>0,1000000000000,0),I10*Corte!$D$78/1000/Corte!$H$78),IF(Corte!$H$79=0,IF(I10>0,1000000000000,0),I10*Corte!$D$79/1000/Corte!$H$79),IF(Corte!$H$80=0,IF(I10>0,1000000000000,0),I10*Corte!$D$80/1000/Corte!$H$80),IF(Corte!$H$81=0,IF(I11>0,1000000000000,0),I11*Corte!$D$81/1000/Corte!$H$81)) -> 9142.7449 | J72: =MAX(IF(Corte!$H$78=0,IF(J10>0,1000000000000,0),J10*Corte!$D$78/1000/Corte!$H$78),IF(Corte!$H$79=0,IF(J10>0,1000000000000,0),J10*Corte!$D$79/1000/Corte!$H$79),IF(Corte!$H$80=0,IF(J10>0,1000000000000,0),J10*Corte!$D$80/1000/Corte!$H$80),IF(Corte!$H$81=0,IF(J11>0,1000000000000,0),J11*Corte!$D$81/1000/Corte!$H$81)) -> 11546.007 | ... L72: =MAX(IF(Corte!$H$78=0,IF(L10>0,1000000000000,0),L10*Corte!$D$78/1000/Corte!$H$78),IF(Corte!$H$79=0,IF(L10>0,1000000000000,0),L10*Corte!$D$79/1000/Corte!$H$79),IF(Corte!$H$80=0,IF(L10>0,1000000000000,0),L10*Corte!$D$80/1000/Corte!$H$80),IF(Corte!$H$81=0,IF(L11>0,1000000000000,0),L11*Corte!$D$81/1000/Corte!$H$81)) -> 15092.332
A73: Metros de madre de 2,0 mm | B73: m | C73: =MAX(IF(Corte!$H$88=0,IF(C11>0,1000000000000,0),C11*Corte!$D$88/1000/Corte!$H$88),IF(Corte!$H$89=0,IF(C11>0,1000000000000,0),C11*Corte!$D$89/1000/Corte!$H$89)) -> 31.463493 | D73: =MAX(IF(Corte!$H$88=0,IF(D11>0,1000000000000,0),D11*Corte!$D$88/1000/Corte!$H$88),IF(Corte!$H$89=0,IF(D11>0,1000000000000,0),D11*Corte!$D$89/1000/Corte!$H$89)) -> 61.20869 | E73: =MAX(IF(Corte!$H$88=0,IF(E11>0,1000000000000,0),E11*Corte!$D$88/1000/Corte!$H$88),IF(Corte!$H$89=0,IF(E11>0,1000000000000,0),E11*Corte!$D$89/1000/Corte!$H$89)) -> 118.17202 | F73: =MAX(IF(Corte!$H$88=0,IF(F11>0,1000000000000,0),F11*Corte!$D$88/1000/Corte!$H$88),IF(Corte!$H$89=0,IF(F11>0,1000000000000,0),F11*Corte!$D$89/1000/Corte!$H$89)) -> 230.18059 | G73: =MAX(IF(Corte!$H$88=0,IF(G11>0,1000000000000,0),G11*Corte!$D$88/1000/Corte!$H$88),IF(Corte!$H$89=0,IF(G11>0,1000000000000,0),G11*Corte!$D$89/1000/Corte!$H$89)) -> 400.25547 | H73: =MAX(IF(Corte!$H$88=0,IF(H11>0,1000000000000,0),H11*Corte!$D$88/1000/Corte!$H$88),IF(Corte!$H$89=0,IF(H11>0,1000000000000,0),H11*Corte!$D$89/1000/Corte!$H$89)) -> 578.3027 | I73: =MAX(IF(Corte!$H$88=0,IF(I11>0,1000000000000,0),I11*Corte!$D$88/1000/Corte!$H$88),IF(Corte!$H$89=0,IF(I11>0,1000000000000,0),I11*Corte!$D$89/1000/Corte!$H$89)) -> 776.29261 | J73: =MAX(IF(Corte!$H$88=0,IF(J11>0,1000000000000,0),J11*Corte!$D$88/1000/Corte!$H$88),IF(Corte!$H$89=0,IF(J11>0,1000000000000,0),J11*Corte!$D$89/1000/Corte!$H$89)) -> 981.25275 | ... L73: =MAX(IF(Corte!$H$88=0,IF(L11>0,1000000000000,0),L11*Corte!$D$88/1000/Corte!$H$88),IF(Corte!$H$89=0,IF(L11>0,1000000000000,0),L11*Corte!$D$89/1000/Corte!$H$89)) -> 1283.4233
A74: Metros de madre de 3,2 mm | B74: m | C74: =MAX(IF(Corte!$H$96=0,IF(C12>0,1000000000000,0),C12*Corte!$D$96/1000/Corte!$H$96),IF(Corte!$H$97=0,IF(C13>0,1000000000000,0),C13*Corte!$D$97/1000/Corte!$H$97)) -> 49.791607 | D74: =MAX(IF(Corte!$H$96=0,IF(D12>0,1000000000000,0),D12*Corte!$D$96/1000/Corte!$H$96),IF(Corte!$H$97=0,IF(D13>0,1000000000000,0),D13*Corte!$D$97/1000/Corte!$H$97)) -> 81.478765 | E74: =MAX(IF(Corte!$H$96=0,IF(E12>0,1000000000000,0),E12*Corte!$D$96/1000/Corte!$H$96),IF(Corte!$H$97=0,IF(E13>0,1000000000000,0),E13*Corte!$D$97/1000/Corte!$H$97)) -> 126.5086 | F74: =MAX(IF(Corte!$H$96=0,IF(F12>0,1000000000000,0),F12*Corte!$D$96/1000/Corte!$H$96),IF(Corte!$H$97=0,IF(F13>0,1000000000000,0),F13*Corte!$D$97/1000/Corte!$H$97)) -> 212.6498 | G74: =MAX(IF(Corte!$H$96=0,IF(G12>0,1000000000000,0),G12*Corte!$D$96/1000/Corte!$H$96),IF(Corte!$H$97=0,IF(G13>0,1000000000000,0),G13*Corte!$D$97/1000/Corte!$H$97)) -> 347.8268 | H74: =MAX(IF(Corte!$H$96=0,IF(H12>0,1000000000000,0),H12*Corte!$D$96/1000/Corte!$H$96),IF(Corte!$H$97=0,IF(H13>0,1000000000000,0),H13*Corte!$D$97/1000/Corte!$H$97)) -> 483.52059 | I74: =MAX(IF(Corte!$H$96=0,IF(I12>0,1000000000000,0),I12*Corte!$D$96/1000/Corte!$H$96),IF(Corte!$H$97=0,IF(I13>0,1000000000000,0),I13*Corte!$D$97/1000/Corte!$H$97)) -> 643.12597 | J74: =MAX(IF(Corte!$H$96=0,IF(J12>0,1000000000000,0),J12*Corte!$D$96/1000/Corte!$H$96),IF(Corte!$H$97=0,IF(J13>0,1000000000000,0),J13*Corte!$D$97/1000/Corte!$H$97)) -> 811.71986 | ... L74: =MAX(IF(Corte!$H$96=0,IF(L12>0,1000000000000,0),L12*Corte!$D$96/1000/Corte!$H$96),IF(Corte!$H$97=0,IF(L13>0,1000000000000,0),L13*Corte!$D$97/1000/Corte!$H$97)) -> 1073.5539
A75: Metros de madre de 4,75 mm | B75: m | C75: =(C14*Piezas!$F$12+C15*Piezas!$F$13)/1000/Corte!$H$104 -> 24.081421 | D75: =(D14*Piezas!$F$12+D15*Piezas!$F$13)/1000/Corte!$H$104 -> 36.171943 | E75: =(E14*Piezas!$F$12+E15*Piezas!$F$13)/1000/Corte!$H$104 -> 55.360927 | F75: =(F14*Piezas!$F$12+F15*Piezas!$F$13)/1000/Corte!$H$104 -> 93.690342 | G75: =(G14*Piezas!$F$12+G15*Piezas!$F$13)/1000/Corte!$H$104 -> 155.71342 | H75: =(H14*Piezas!$F$12+H15*Piezas!$F$13)/1000/Corte!$H$104 -> 214.59255 | I75: =(I14*Piezas!$F$12+I15*Piezas!$F$13)/1000/Corte!$H$104 -> 286.72336 | J75: =(J14*Piezas!$F$12+J15*Piezas!$F$13)/1000/Corte!$H$104 -> 359.38062 | ... L75: =(L14*Piezas!$F$12+L15*Piezas!$F$13)/1000/Corte!$H$104 -> 477.11022
A76: Acero de madre de 0,9 mm | B76: t | C76: =C70*Corte!$D$50/1000/(1-Datos!$B$20) -> 2.1649998 | D76: =D70*Corte!$D$50/1000/(1-Datos!$B$20) -> 3.107198 | E76: =E70*Corte!$D$50/1000/(1-Datos!$B$20) -> 7.5197675 | F76: =F70*Corte!$D$50/1000/(1-Datos!$B$20) -> 18.217369 | G76: =G70*Corte!$D$50/1000/(1-Datos!$B$20) -> 32.181952 | H76: =H70*Corte!$D$50/1000/(1-Datos!$B$20) -> 45.23029 | I76: =I70*Corte!$D$50/1000/(1-Datos!$B$20) -> 63.038756 | J76: =J70*Corte!$D$50/1000/(1-Datos!$B$20) -> 80.892414 | ... L76: =L70*Corte!$D$50/1000/(1-Datos!$B$20) -> 104.97758
A77: Acero de madre de 1,25 mm | B77: t | C77: =C71*Corte!$D$51/1000/(1-Datos!$B$20) -> 0.88128454 | D77: =D71*Corte!$D$51/1000/(1-Datos!$B$20) -> 2.1221284 | E77: =E71*Corte!$D$51/1000/(1-Datos!$B$20) -> 3.8439637 | F77: =F71*Corte!$D$51/1000/(1-Datos!$B$20) -> 7.5650912 | G77: =G71*Corte!$D$51/1000/(1-Datos!$B$20) -> 12.539208 | H77: =H71*Corte!$D$51/1000/(1-Datos!$B$20) -> 17.837361 | I77: =I71*Corte!$D$51/1000/(1-Datos!$B$20) -> 24.561237 | J77: =J71*Corte!$D$51/1000/(1-Datos!$B$20) -> 31.517401 | ... L77: =L71*Corte!$D$51/1000/(1-Datos!$B$20) -> 41.24516
A78: Acero de madre de 1,6 mm | B78: t | C78: =C72*Corte!$D$52/1000/(1-Datos!$B$20) -> 6.8370093 | D78: =D72*Corte!$D$52/1000/(1-Datos!$B$20) -> 11.78121 | E78: =E72*Corte!$D$52/1000/(1-Datos!$B$20) -> 20.13066 | F78: =F72*Corte!$D$52/1000/(1-Datos!$B$20) -> 36.59809 | G78: =G72*Corte!$D$52/1000/(1-Datos!$B$20) -> 61.675128 | H78: =H72*Corte!$D$52/1000/(1-Datos!$B$20) -> 85.941049 | I78: =I72*Corte!$D$52/1000/(1-Datos!$B$20) -> 115.70396 | J78: =J72*Corte!$D$52/1000/(1-Datos!$B$20) -> 146.11791 | ... L78: =L72*Corte!$D$52/1000/(1-Datos!$B$20) -> 190.99764
A79: Acero de madre de 2,0 mm | B79: t | C79: =C73*Corte!$D$53/1000/(1-Datos!$B$20) -> 0.497724 | D79: =D73*Corte!$D$53/1000/(1-Datos!$B$20) -> 0.96826611 | E79: =E73*Corte!$D$53/1000/(1-Datos!$B$20) -> 1.8693745 | F79: =F73*Corte!$D$53/1000/(1-Datos!$B$20) -> 3.6412487 | G79: =G73*Corte!$D$53/1000/(1-Datos!$B$20) -> 6.3316795 | H79: =H73*Corte!$D$53/1000/(1-Datos!$B$20) -> 9.1482257 | I79: =I73*Corte!$D$53/1000/(1-Datos!$B$20) -> 12.280247 | J79: =J73*Corte!$D$53/1000/(1-Datos!$B$20) -> 15.522531 | ... L79: =L73*Corte!$D$53/1000/(1-Datos!$B$20) -> 20.302596
A80: Acero de madre de 3,2 mm | B80: t | C80: =C74*Corte!$D$54/1000/(1-Datos!$B$20) -> 1.8903796 | D80: =D74*Corte!$D$54/1000/(1-Datos!$B$20) -> 3.0934089 | E80: =E74*Corte!$D$54/1000/(1-Datos!$B$20) -> 4.8030041 | F80: =F74*Corte!$D$54/1000/(1-Datos!$B$20) -> 8.0734262 | G80: =G74*Corte!$D$54/1000/(1-Datos!$B$20) -> 13.205533 | H80: =H74*Corte!$D$54/1000/(1-Datos!$B$20) -> 18.35726 | I80: =I74*Corte!$D$54/1000/(1-Datos!$B$20) -> 24.416811 | J80: =J74*Corte!$D$54/1000/(1-Datos!$B$20) -> 30.817617 | ... L80: =L74*Corte!$D$54/1000/(1-Datos!$B$20) -> 40.758363
A81: Acero de madre de 4,75 mm | B81: t | C81: =C75*Corte!$D$55/1000/(1-Datos!$B$20) -> 1.1264106 | D81: =D75*Corte!$D$55/1000/(1-Datos!$B$20) -> 1.6919458 | E81: =E75*Corte!$D$55/1000/(1-Datos!$B$20) -> 2.5895122 | F81: =F75*Corte!$D$55/1000/(1-Datos!$B$20) -> 4.382374 | G81: =G75*Corte!$D$55/1000/(1-Datos!$B$20) -> 7.2835088 | H81: =H75*Corte!$D$55/1000/(1-Datos!$B$20) -> 10.037585 | I81: =I75*Corte!$D$55/1000/(1-Datos!$B$20) -> 13.41151 | J81: =J75*Corte!$D$55/1000/(1-Datos!$B$20) -> 16.81006 | ... L81: =L75*Corte!$D$55/1000/(1-Datos!$B$20) -> 22.316872
A82: Acero comprado | B82: t | C82: =SUM(C76:C81) -> 13.397808 | D82: =SUM(D76:D81) -> 22.764157 | E82: =SUM(E76:E81) -> 40.756282 | F82: =SUM(F76:F81) -> 78.477599 | G82: =SUM(G76:G81) -> 133.21701 | H82: =SUM(H76:H81) -> 186.55177 | I82: =SUM(I76:I81) -> 253.41252 | J82: =SUM(J76:J81) -> 321.67793 | ... L82: =SUM(L76:L81) -> 420.59821
A83: Costo del acero | B83: USD | C83: =SUMPRODUCT(C76:C81,Corte!$E$50:$E$55)*1000 -> 16374.7 | D83: =SUMPRODUCT(D76:D81,Corte!$E$50:$E$55)*1000 -> 27863.252 | E83: =SUMPRODUCT(E76:E81,Corte!$E$50:$E$55)*1000 -> 50072.051 | F83: =SUMPRODUCT(F76:F81,Corte!$E$50:$E$55)*1000 -> 96705.261 | G83: =SUMPRODUCT(G76:G81,Corte!$E$50:$E$55)*1000 -> 164265.68 | H83: =SUMPRODUCT(H76:H81,Corte!$E$50:$E$55)*1000 -> 230077.23 | I83: =SUMPRODUCT(I76:I81,Corte!$E$50:$E$55)*1000 -> 312657.19 | J83: =SUMPRODUCT(J76:J81,Corte!$E$50:$E$55)*1000 -> 396945.6 | ... L83: =SUMPRODUCT(L76:L81,Corte!$E$50:$E$55)*1000 -> 518892.4
A84: Scrap | B84: t | C84: =C82-C25 -> 1.4343348 | D84: =D82-D25 -> 2.74587 | E84: =E82-E25 -> 4.5773764 | F84: =F82-F25 -> 8.2256326 | G84: =G82-G25 -> 13.532321 | H84: =H82-H25 -> 19.005031 | I84: =I82-I25 -> 26.088298 | J84: =J82-J25 -> 33.331117 | ... L84: =L82-L25 -> 42.767767
A85: Venta de scrap (resta) | B85: USD | C85: =-C84*Datos!$B$9 -> -358.58369 | D85: =-D84*Datos!$B$9 -> -686.46751 | E85: =-E84*Datos!$B$9 -> -1144.3441 | F85: =-F84*Datos!$B$9 -> -2056.4082 | G85: =-G84*Datos!$B$9 -> -3383.0802 | H85: =-H84*Datos!$B$9 -> -4751.2578 | I85: =-I84*Datos!$B$9 -> -6522.0745 | J85: =-J84*Datos!$B$9 -> -8332.7793 | ... L85: =-L84*Datos!$B$9 -> -10691.942
A86: Stock promedio (madres y flejes en proceso) | B86: t | C86: =SUMPRODUCT((Corte!$G$50:$G$55+C76:C81*Datos!$B$48/12-ABS(Corte!$G$50:$G$55-C76:C81*Datos!$B$48/12))/2+C76:C81*Datos!$B$45/52) -> 3.8647523 | D86: =SUMPRODUCT((Corte!$G$50:$G$55+D76:D81*Datos!$B$48/12-ABS(Corte!$G$50:$G$55-D76:D81*Datos!$B$48/12))/2+D76:D81*Datos!$B$45/52) -> 6.5665839 | E86: =SUMPRODUCT((Corte!$G$50:$G$55+E76:E81*Datos!$B$48/12-ABS(Corte!$G$50:$G$55-E76:E81*Datos!$B$48/12))/2+E76:E81*Datos!$B$45/52) -> 11.75662 | F86: =SUMPRODUCT((Corte!$G$50:$G$55+F76:F81*Datos!$B$48/12-ABS(Corte!$G$50:$G$55-F76:F81*Datos!$B$48/12))/2+F76:F81*Datos!$B$45/52) -> 22.637769 | G86: =SUMPRODUCT((Corte!$G$50:$G$55+G76:G81*Datos!$B$48/12-ABS(Corte!$G$50:$G$55-G76:G81*Datos!$B$48/12))/2+G76:G81*Datos!$B$45/52) -> 35.009201 | H86: =SUMPRODUCT((Corte!$G$50:$G$55+H76:H81*Datos!$B$48/12-ABS(Corte!$G$50:$G$55-H76:H81*Datos!$B$48/12))/2+H76:H81*Datos!$B$45/52) -> 39.175068 | I86: =SUMPRODUCT((Corte!$G$50:$G$55+I76:I81*Datos!$B$48/12-ABS(Corte!$G$50:$G$55-I76:I81*Datos!$B$48/12))/2+I76:I81*Datos!$B$45/52) -> 41.746636 | J86: =SUMPRODUCT((Corte!$G$50:$G$55+J76:J81*Datos!$B$48/12-ABS(Corte!$G$50:$G$55-J76:J81*Datos!$B$48/12))/2+J76:J81*Datos!$B$45/52) -> 44.372228 | ... L86: =SUMPRODUCT((Corte!$G$50:$G$55+L76:L81*Datos!$B$48/12-ABS(Corte!$G$50:$G$55-L76:L81*Datos!$B$48/12))/2+L76:L81*Datos!$B$45/52) -> 48.176854
A87: Costo financiero del stock | B87: USD | C87: =IF(C82=0,0,C86*C83/C82*Datos!$B$7) -> 566.81654 | D87: =IF(D82=0,0,D86*D83/D82*Datos!$B$7) -> 964.49719 | E87: =IF(E82=0,0,E86*E83/E82*Datos!$B$7) -> 1733.2633 | F87: =IF(F82=0,0,F86*F83/F82*Datos!$B$7) -> 3347.4898 | G87: =IF(G82=0,0,G86*G83/G82*Datos!$B$7) -> 5180.2487 | H87: =IF(H82=0,0,H86*H83/H82*Datos!$B$7) -> 5797.8272 | I87: =IF(I82=0,0,I86*I83/I82*Datos!$B$7) -> 6180.7769 | J87: =IF(J82=0,0,J86*J83/J82*Datos!$B$7) -> 6570.5573 | ... L87: =IF(L82=0,0,L86*L83/L82*Datos!$B$7) -> 7132.2996
A88: Horas de la cortadora longitudinal (máquina) | B88: h | C88: =SUM(C70:C75)/(Datos!$B$37*60)+SUMPRODUCT(C76:C81/Corte!$G$50:$G$55)*Datos!$B$38/60 -> 2.2207132 | D88: =SUM(D70:D75)/(Datos!$B$37*60)+SUMPRODUCT(D76:D81/Corte!$G$50:$G$55)*Datos!$B$38/60 -> 3.8113746 | E88: =SUM(E70:E75)/(Datos!$B$37*60)+SUMPRODUCT(E76:E81/Corte!$G$50:$G$55)*Datos!$B$38/60 -> 6.7203979 | F88: =SUM(F70:F75)/(Datos!$B$37*60)+SUMPRODUCT(F76:F81/Corte!$G$50:$G$55)*Datos!$B$38/60 -> 12.786817 | G88: =SUM(G70:G75)/(Datos!$B$37*60)+SUMPRODUCT(G76:G81/Corte!$G$50:$G$55)*Datos!$B$38/60 -> 21.638587 | H88: =SUM(H70:H75)/(Datos!$B$37*60)+SUMPRODUCT(H76:H81/Corte!$G$50:$G$55)*Datos!$B$38/60 -> 30.374313 | I88: =SUM(I70:I75)/(Datos!$B$37*60)+SUMPRODUCT(I76:I81/Corte!$G$50:$G$55)*Datos!$B$38/60 -> 41.194312 | J88: =SUM(J70:J75)/(Datos!$B$37*60)+SUMPRODUCT(J76:J81/Corte!$G$50:$G$55)*Datos!$B$38/60 -> 52.272513 | ... L88: =SUM(L70:L75)/(Datos!$B$37*60)+SUMPRODUCT(L76:L81/Corte!$G$50:$G$55)*Datos!$B$38/60 -> 68.48404
A89: Flejes de disco generados | B89: flejes | C89: =SUMPRODUCT(C76:C81/Corte!$G$50:$G$55*Corte!$F$50:$F$55) -> 2.903672 | D89: =SUMPRODUCT(D76:D81/Corte!$G$50:$G$55*Corte!$F$50:$F$55) -> 5.9265064 | E89: =SUMPRODUCT(E76:E81/Corte!$G$50:$G$55*Corte!$F$50:$F$55) -> 10.922183 | F89: =SUMPRODUCT(F76:F81/Corte!$G$50:$G$55*Corte!$F$50:$F$55) -> 21.645101 | G89: =SUMPRODUCT(G76:G81/Corte!$G$50:$G$55*Corte!$F$50:$F$55) -> 36.43906 | H89: =SUMPRODUCT(H76:H81/Corte!$G$50:$G$55*Corte!$F$50:$F$55) -> 51.53952 | I89: =SUMPRODUCT(I76:I81/Corte!$G$50:$G$55*Corte!$F$50:$F$55) -> 70.639306 | J89: =SUMPRODUCT(J76:J81/Corte!$G$50:$G$55*Corte!$F$50:$F$55) -> 90.251901 | ... L89: =SUMPRODUCT(L76:L81/Corte!$G$50:$G$55*Corte!$F$50:$F$55) -> 117.92614
A90: Horas-hombre de corte: cortadora + línea + cambios de fleje | B90: h | C90: =C88*Datos!$B$39+SUM(C$8:C$15)/Datos!$B$36+C89*Datos!$B$41/60 -> 11.006161 | D90: =D88*Datos!$B$39+SUM(D$8:D$15)/Datos!$B$36+D89*Datos!$B$41/60 -> 18.341898 | E90: =E88*Datos!$B$39+SUM(E$8:E$15)/Datos!$B$36+E89*Datos!$B$41/60 -> 35.575647 | F90: =F88*Datos!$B$39+SUM(F$8:F$15)/Datos!$B$36+F89*Datos!$B$41/60 -> 73.736567 | G90: =G88*Datos!$B$39+SUM(G$8:G$15)/Datos!$B$36+G89*Datos!$B$41/60 -> 126.7669 | H90: =H88*Datos!$B$39+SUM(H$8:H$15)/Datos!$B$36+H89*Datos!$B$41/60 -> 178.05053 | I90: =I88*Datos!$B$39+SUM(I$8:I$15)/Datos!$B$36+I89*Datos!$B$41/60 -> 243.95927 | J90: =J88*Datos!$B$39+SUM(J$8:J$15)/Datos!$B$36+J89*Datos!$B$41/60 -> 310.92541 | ... L90: =L88*Datos!$B$39+SUM(L$8:L$15)/Datos!$B$36+L89*Datos!$B$41/60 -> 406.12929
A91: Mano de obra de corte | B91: USD | C91: =C90*Datos!$B$15 -> 69.133265 | D91: =D90*Datos!$B$15 -> 115.2114 | E91: =E90*Datos!$B$15 -> 223.46216 | F91: =F90*Datos!$B$15 -> 463.16327 | G91: =G90*Datos!$B$15 -> 796.26394 | H91: =H90*Datos!$B$15 -> 1118.3931 | I91: =I90*Datos!$B$15 -> 1532.3872 | J91: =J90*Datos!$B$15 -> 1953.0232 | ... L91: =L90*Datos!$B$15 -> 2551.0296
A92: Mantenimiento de equipos | B92: USD | C92: =Datos!$E$112*Datos!$B$8 -> 5730 | D92: =Datos!$E$112*Datos!$B$8 -> 5730 | E92: =Datos!$E$112*Datos!$B$8 -> 5730 | F92: =Datos!$E$112*Datos!$B$8 -> 5730 | G92: =Datos!$E$112*Datos!$B$8 -> 5730 | H92: =Datos!$E$112*Datos!$B$8 -> 5730 | I92: =Datos!$E$112*Datos!$B$8 -> 5730 | J92: =Datos!$E$112*Datos!$B$8 -> 5730 | ... L92: =Datos!$E$112*Datos!$B$8 -> 5730
A93: COSTO ANUAL C | B93: USD | C93: =C83+C85+C87+C91+C92 -> 22382.066 | D93: =D83+D85+D87+D91+D92 -> 33986.493 | E93: =E83+E85+E87+E91+E92 -> 56614.432 | F93: =F83+F85+F87+F91+F92 -> 104189.51 | G93: =G83+G85+G87+G91+G92 -> 172589.11 | H93: =H83+H85+H87+H91+H92 -> 237972.19 | I93: =I83+I85+I87+I91+I92 -> 319578.28 | J93: =J83+J85+J87+J91+J92 -> 402866.4 | ... L93: =L83+L85+L87+L91+L92 -> 523613.79
A95: D — Hojas para cuerpos (dos guillotinas en serie) + fleje a medida para discos
A96: Acero comprado: hojas de cuerpo + fleje | B96: t | C96: =C51+C30 -> 13.83042 | D96: =D51+D30 -> 23.11656 | E96: =E51+E30 -> 41.651274 | F96: =F51+F30 -> 80.679974 | G96: =G51+G30 -> 137.38992 | H96: =H51+H30 -> 192.30326 | I96: =I51+I30 -> 260.83887 | J96: =J51+J30 -> 330.80747 | ... L96: =L51+L30 -> 433.53698
A97: Costo del acero | B97: USD | C97: =C52+C31 -> 17217.332 | D97: =D52+D31 -> 28789.187 | E97: =E52+E31 -> 52208.975 | F97: =F52+F31 -> 101677.09 | G97: =G52+G31 -> 173331.04 | H97: =H52+H31 -> 242666.39 | I97: =I52+I31 -> 329374.8 | J97: =J52+J31 -> 417849.87 | ... L97: =L52+L31 -> 547398.02
A98: Scrap | B98: t | C98: =C96-C25 -> 1.8669467 | D98: =D96-D25 -> 3.098273 | E98: =E96-E25 -> 5.4723685 | F98: =F96-F25 -> 10.428008 | G98: =G96-G25 -> 17.705234 | H98: =H96-H25 -> 24.756519 | I98: =I96-I25 -> 33.514644 | J98: =J96-J25 -> 42.460649 | ... L98: =L96-L25 -> 55.706541
A99: Venta de scrap (resta) | B99: USD | C99: =-C98*Datos!$B$9 -> -466.73666 | D99: =-D98*Datos!$B$9 -> -774.56824 | E99: =-E98*Datos!$B$9 -> -1368.0921 | F99: =-F98*Datos!$B$9 -> -2607.0021 | G99: =-G98*Datos!$B$9 -> -4426.3085 | H99: =-H98*Datos!$B$9 -> -6189.1298 | I99: =-I98*Datos!$B$9 -> -8378.6611 | J99: =-J98*Datos!$B$9 -> -10615.162 | ... L99: =-L98*Datos!$B$9 -> -13926.635
A100: Stock promedio: hojas + rollos de fleje | B100: t | C100: =C51*(Datos!$B$46/2/12+Datos!$B$45/52)+C37 -> 1.3567292 | D100: =D51*(Datos!$B$46/2/12+Datos!$B$45/52)+D37 -> 2.2751609 | E100: =E51*(Datos!$B$46/2/12+Datos!$B$45/52)+E37 -> 4.1230242 | F100: =F51*(Datos!$B$46/2/12+Datos!$B$45/52)+F37 -> 8.0199663 | G100: =G51*(Datos!$B$46/2/12+Datos!$B$45/52)+G37 -> 13.34133 | H100: =H51*(Datos!$B$46/2/12+Datos!$B$45/52)+H37 -> 17.440923 | I100: =I51*(Datos!$B$46/2/12+Datos!$B$45/52)+I37 -> 22.471118 | J100: =J51*(Datos!$B$46/2/12+Datos!$B$45/52)+J37 -> 27.529435 | ... L100: =L51*(Datos!$B$46/2/12+Datos!$B$45/52)+L37 -> 34.780372
A101: Costo financiero del stock | B101: USD | C101: =IF(C96=0,0,C100*C97/C96*Datos!$B$7) -> 202.6772 | D101: =IF(D96=0,0,D100*D97/D96*Datos!$B$7) -> 340.01615 | E101: =IF(E96=0,0,E100*E97/E96*Datos!$B$7) -> 620.17464 | F101: =IF(F96=0,0,F100*F97/F96*Datos!$B$7) -> 1212.8613 | G101: =IF(G96=0,0,G100*G97/G96*Datos!$B$7) -> 2019.7696 | H101: =IF(H96=0,0,H100*H97/H96*Datos!$B$7) -> 2641.0322 | I101: =IF(I96=0,0,I100*I97/I96*Datos!$B$7) -> 3405.0539 | J101: =IF(J96=0,0,J100*J97/J96*Datos!$B$7) -> 4172.761 | ... L101: =IF(L96=0,0,L100*L97/L96*Datos!$B$7) -> 5269.7807
A102: Horas-hombre de corte: guillotinas 1 y 2 + cambios de fleje | B102: h | C102: =C53+C54+C40*Datos!$B$41/60 -> 3.1558814 | D102: =D53+D54+D40*Datos!$B$41/60 -> 5.193198 | E102: =E53+E54+E40*Datos!$B$41/60 -> 10.238885 | F102: =F53+F54+F40*Datos!$B$41/60 -> 21.430132 | G102: =G53+G54+G40*Datos!$B$41/60 -> 36.975828 | H102: =H53+H54+H40*Datos!$B$41/60 -> 51.889071 | I102: =I53+I54+I40*Datos!$B$41/60 -> 71.042604 | J102: =J53+J54+J40*Datos!$B$41/60 -> 90.486683 | ... L102: =L53+L54+L40*Datos!$B$41/60 -> 118.26219
A103: Mano de obra de corte | B103: USD | C103: =C102*Datos!$B$15 -> 19.823114 | D103: =D102*Datos!$B$15 -> 32.620159 | E103: =E102*Datos!$B$15 -> 64.313751 | F103: =F102*Datos!$B$15 -> 134.6096 | G103: =G102*Datos!$B$15 -> 232.25715 | H103: =H102*Datos!$B$15 -> 325.93207 | I103: =I102*Datos!$B$15 -> 446.24161 | J103: =J102*Datos!$B$15 -> 568.37617 | ... L103: =L102*Datos!$B$15 -> 742.84315
A104: Mantenimiento de equipos | B104: USD | C104: =Datos!$F$112*Datos!$B$8 -> 2790 | D104: =Datos!$F$112*Datos!$B$8 -> 2790 | E104: =Datos!$F$112*Datos!$B$8 -> 2790 | F104: =Datos!$F$112*Datos!$B$8 -> 2790 | G104: =Datos!$F$112*Datos!$B$8 -> 2790 | H104: =Datos!$F$112*Datos!$B$8 -> 2790 | I104: =Datos!$F$112*Datos!$B$8 -> 2790 | J104: =Datos!$F$112*Datos!$B$8 -> 2790 | ... L104: =Datos!$F$112*Datos!$B$8 -> 2790
A105: COSTO ANUAL D | B105: USD | C105: =C97+C99+C101+C103+C104 -> 19763.095 | D105: =D97+D99+D101+D103+D104 -> 31177.255 | E105: =E97+E99+E101+E103+E104 -> 54315.371 | F105: =F97+F99+F101+F103+F104 -> 103207.56 | G105: =G97+G99+G101+G103+G104 -> 173946.76 | H105: =H97+H99+H101+H103+H104 -> 242234.22 | I105: =I97+I99+I101+I103+I104 -> 327637.44 | J105: =J97+J99+J101+J103+J104 -> 414765.84 | ... L105: =L97+L99+L101+L103+L104 -> 542274.01
A107: Referencia — cuerpos comprados cortados a medida + fleje a medida para discos
...
