Workbook

Sheet Links
A1: Links de los IMPORTRANGE
A2: Pegar en B el link de cada Google Sheet: todos los IMPORTRANGE lo leen de acá.
A3: Archivo | B3: Link | C3: Qué se importa
A4: Aprovechamiento Recargas Planta Comercial | B4: PEGAR ACÁ EL LINK DEL GOOGLE SHEET | C4: Lo que trae la hoja Importados
A5: Aprovechamiento Recargas Planta Industrial | B5: PEGAR ACÁ EL LINK DEL GOOGLE SHEET | C5: Lo que trae la hoja Importados

Sheet Resumen
A1: Recargas — logística de las dos plantas (mes pico de 2035)
A2: Desarrollo y fuentes en el Word de justificación de recargas · § 10
A4: Concepto | B4: Comercial | C4: Industrial | D4: De dónde sale
A5: Recargas del año 2035 (u) | B5: =Importados!$N$22 -> 206230.15 | C5: =Importados!$N$56 -> 107197.37 | D5: Importados
A6: Mes pico | B6: =Cálculo!B6 -> Dic | C6: =Cálculo!C6 -> Dic | D6: Cálculo, punto 1
A7: Llegan por día en el mes pico (u) | B7: =Cálculo!F30 -> 1061.9436 | C7: =Cálculo!I30 -> 552.29771 | D7: Cálculo, punto 2
A8: Sustitutos que salen por día (u) | B8: =Cálculo!G30 -> 409.32481 | C8: =Cálculo!J30 -> 213.04298 | D8: Cálculo, punto 2
A9: Stock de sustitutos (u) | B9: =Importados!$P$22 -> 1498 | C9: =Importados!$P$56 -> 785 | D9: Aprovechamiento, paso 3
A10: Paradas por día | B10: =Cálculo!E44 -> 203.87382 | C10: =Cálculo!I44 -> 105.68545 | D10: Cálculo, punto 3
A11: Viajes por día | B11: =Cálculo!B61 -> 25 | C11: =Cálculo!C61 -> 13 | D11: Cálculo, punto 4
A12: Camiones | B12: =Cálculo!B63 -> 14 | C12: =Cálculo!C63 -> 8 | D12: Cálculo, punto 4
A13: Ocupación de la flota | B13: =Cálculo!B64 -> 0.89046945 | C13: =Cálculo!C64 -> 0.80862012 | D13: Cálculo, punto 4
A14: Posiciones del pulmón | B14: =Cálculo!E74 -> 55 | C14: =Cálculo!I74 -> 29 | D14: Cálculo, punto 5
A15: Superficie del pulmón (m²) | B15: =Cálculo!E75 -> 132 | C15: =Cálculo!I75 -> 69.6 | D15: Cálculo, punto 5
A16: Jaulas A y B a tener | B16: =Cálculo!E77 -> 140 | C16: =Cálculo!I77 -> 81 | D16: Cálculo, punto 5

Sheet Supuestos
A1: Supuestos de logística
A2: Demanda, estacionalidad, mix, lote y sustitutos vienen de Importados · § 10
A3: 1. Camión | B3: Valor | C3: Fuente / criterio
A4: Vehículo | B4: Iveco Daily 55C17 con caja de baranda rebatible | C4: Word de recargas · § 10.1
A5: Carga útil (kg) | B5: 2000 | C5: Word de recargas: aprox. 2 t
A6: Posiciones de jaula 1,2 × 1,0 m en la caja | B6: 6 | C6: 2 × 3 en caja de 3,7 × 2,1 m · § 10.1
A7: Personas a bordo (chofer + ayudante) | B7: 2 | C7: Retiro y colocación de sustitutos · § 10.1
A8: Peso por persona (kg) | B8: 75 | C8: Masa normalizada por ocupante (Dir. 2007/46/CE)
A9: Peso de una jaula (kg) | B9: 75 | C9: Jaula plegable 1,2 × 1,0 m (Palletower Hypacage)
A10: Tara de las jaulas (kg) | B10: =B6*B9 -> 450 | C10: Posiciones × peso de jaula
A11: Carga neta por viaje (kg) | B11: =B5-B7*B8-B10 -> 1400 | C11: Carga útil − personas − jaulas
A12: Precio del camión con caja (ARS) | C12: A cotizar
A14: 2. Recorrido | B14: Valor | C14: Fuente / criterio
A15: Turnos de logística por día | B15: 2 | C15: Los mismos de la planta (Ley 11.544) · § 10.2
A16: Ida y vuelta planta ↔ zona de clientes (h por viaje) | B16: 1.5 | C16: 2 × 25 km (TomTom 2024) · § 10.2
A17: Tiempo fijo por parada (min) | B17: 20 | C17: Criterio · § 10.2
A18: Manejo entre paradas (min) | B18: 15 | C18: 5 km a 20 km/h (TomTom 2024) · § 10.2
A19: Ocupación máxima de la flota | B19: 0.9 | C19: El mismo límite de los puestos · § 8
A21: 3. Pulmón | B21: Valor | C21: Fuente / criterio
A22: Días de llegada que esperan en recepción | B22: 0.5 | C22: Entra en el turno siguiente · § 10.3
A23: Días de recargados que esperan el recorrido | B23: 0.5 | C23: Sale en el turno siguiente · § 10.3
A24: Factor de jaulas a medio llenar | B24: 1.15 | C24: Jaulas por cliente y agente · § 10.3
A25: Jaulas vacías de reserva (% de las ocupadas) | B25: 0.15 | C25: Criterio · § 10.3
A26: Niveles de la estantería de sustitutos | B26: 3 | C26: Criterio · § 10.3
A27: Jaulas vacías apiladas por posición | B27: 4 | C27: Hypacage: apilable de a 4
A28: Superficie por posición con pasillo (m²) | B28: =1.2*1*2 -> 2.4 | C28: Pasillo compartido por dos filas

Sheet Importados
A1: Importados de los Aprovechamientos de recargas (IMPORTRANGE; el link va en la hoja Links)
A3: Planta comercial
A4: Tipo: perfil mensual de recargas (% del año) | B4: Ene | C4: Feb | D4: Mar | E4: Abr | F4: May | G4: Jun | H4: Jul | I4: Ago | J4: Sep | K4: Oct | L4: Nov | M4: Dic | N4: Recargas 2035 (u) | O4: Lleva sustituto (1 = sí) | P4: Stock de sustitutos 2035 (u) | Q4: Automotor | R4: Edificios | S4: Educación | T4: Hoteles | U4: Industrias / almacenes | V4: Salud | W4: Supermercados | X4: Total mix
A5: ABC 1 kg | B5: =IFERROR(__xludf.DUMMYFUNCTION("IMPORTRANGE(Links!$B$4,""parametros_recargas!E55:P72"")"),0.119877958433184) -> 0.11987796 | C5: =IFERROR(__xludf.DUMMYFUNCTION("""COMPUTED_VALUE"""),0.0954780457654631) -> 0.095478046 | D5: =IFERROR(__xludf.DUMMYFUNCTION("""COMPUTED_VALUE"""),0.0711264175844748) -> 0.071126418 | E5: =IFERROR(__xludf.DUMMYFUNCTION("""COMPUTED_VALUE"""),0.0711264175844748) -> 0.071126418 | F5: =IFERROR(__xludf.DUMMYFUNCTION("""COMPUTED_VALUE"""),0.0711747020712071) -> 0.071174702 | G5: =IFERROR(__xludf.DUMMYFUNCTION("""COMPUTED_VALUE"""),0.0711747020712071) -> 0.071174702 | H5: =IFERROR(__xludf.DUMMYFUNCTION("""COMPUTED_VALUE"""),0.0710911890912281) -> 0.071091189 | I5: =IFERROR(__xludf.DUMMYFUNCTION("""COMPUTED_VALUE"""),0.0711747020712071) -> 0.071174702 | J5: =IFERROR(__xludf.DUMMYFUNCTION("""COMPUTED_VALUE"""),0.0711681740744643) -> 0.071168174 | K5: =IFERROR(__xludf.DUMMYFUNCTION("""COMPUTED_VALUE"""),0.0711681740744643) -> 0.071168174 | L5: =IFERROR(__xludf.DUMMYFUNCTION("""COMPUTED_VALUE"""),0.0955198022554526) -> 0.095519802 | M5: =IFERROR(__xludf.DUMMYFUNCTION("""COMPUTED_VALUE"""),0.119919714923173) -> 0.11991971 | N5: =IFERROR(__xludf.DUMMYFUNCTION("IMPORTRANGE(Links!$B$4,""datos_base!K2:K18"")"),108842.626397553) -> 108842.63 | O5: =IFERROR(__xludf.DUMMYFUNCTION("IMPORTRANGE(Links!$B$4,""sobrestock_sustitutos!B30:B46"")"),0) -> 0 | P5: =IFERROR(__xludf.DUMMYFUNCTION("IMPORTRANGE(Links!$B$4,""sobrestock_sustitutos!K51:K67"")"),0) -> 0 | Q5: =IFERROR(__xludf.DUMMYFUNCTION("IMPORTRANGE(Links!$B$4,""PROY_Indexado!B57:H73"")"),2251135) -> 2251135 | R5: =IFERROR(__xludf.DUMMYFUNCTION("""COMPUTED_VALUE"""),0) -> 0 | S5: =IFERROR(__xludf.DUMMYFUNCTION("""COMPUTED_VALUE"""),0) -> 0 | T5: =IFERROR(__xludf.DUMMYFUNCTION("""COMPUTED_VALUE"""),3578.5) -> 3578.5 | U5: =IFERROR(__xludf.DUMMYFUNCTION("""COMPUTED_VALUE"""),0) -> 0 | V5: =IFERROR(__xludf.DUMMYFUNCTION("""COMPUTED_VALUE"""),0) -> 0 | W5: =IFERROR(__xludf.DUMMYFUNCTION("""COMPUTED_VALUE"""),530) -> 530 | X5: =SUM(Q5:W5) -> 2255243.5
A6: ABC 2,5 kg | B6: =IFERROR(__xludf.DUMMYFUNCTION("""COMPUTED_VALUE"""),0.0599939658092665) -> 0.059993966 | C6: =IFERROR(__xludf.DUMMYFUNCTION("""COMPUTED_VALUE"""),0.0599939658092665) -> 0.059993966 | D6: =IFERROR(__xludf.DUMMYFUNCTION("""COMPUTED_VALUE"""),0.0823418371052526) -> 0.082341837 | E6: =IFERROR(__xludf.DUMMYFUNCTION("""COMPUTED_VALUE"""),0.0958991878073455) -> 0.095899188 | F6: =IFERROR(__xludf.DUMMYFUNCTION("""COMPUTED_VALUE"""),0.10379748734495) -> 0.10379749 | G6: =IFERROR(__xludf.DUMMYFUNCTION("""COMPUTED_VALUE"""),0.102624553445736) -> 0.10262455 | H6: =IFERROR(__xludf.DUMMYFUNCTION("""COMPUTED_VALUE"""),0.0742053590647476) -> 0.074205359 | I6: =IFERROR(__xludf.DUMMYFUNCTION("""COMPUTED_VALUE"""),0.0870020477881409) -> 0.087002048 | J6: =IFERROR(__xludf.DUMMYFUNCTION("""COMPUTED_VALUE"""),0.0871913152503224) -> 0.087191315 | K6: =IFERROR(__xludf.DUMMYFUNCTION("""COMPUTED_VALUE"""),0.0871913152503224) -> 0.087191315 | L6: =IFERROR(__xludf.DUMMYFUNCTION("""COMPUTED_VALUE"""),0.0792930157127176) -> 0.079293016 | M6: =IFERROR(__xludf.DUMMYFUNCTION("""COMPUTED_VALUE"""),0.0804659496119317) -> 0.08046595 | N6: =IFERROR(__xludf.DUMMYFUNCTION("""COMPUTED_VALUE"""),9216.54014430766) -> 9216.5401 | O6: =IFERROR(__xludf.DUMMYFUNCTION("""COMPUTED_VALUE"""),1) -> 1 | P6: =IFERROR(__xludf.DUMMYFUNCTION("""COMPUTED_VALUE"""),146) -> 146 | Q6: =IFERROR(__xludf.DUMMYFUNCTION("""COMPUTED_VALUE"""),0) -> 0 | R6: =IFERROR(__xludf.DUMMYFUNCTION("""COMPUTED_VALUE"""),100435.9) -> 100435.9 | S6: =IFERROR(__xludf.DUMMYFUNCTION("""COMPUTED_VALUE"""),14173.8) -> 14173.8 | T6: =IFERROR(__xludf.DUMMYFUNCTION("""COMPUTED_VALUE"""),45655.1) -> 45655.1 | U6: =IFERROR(__xludf.DUMMYFUNCTION("""COMPUTED_VALUE"""),0) -> 0 | V6: =IFERROR(__xludf.DUMMYFUNCTION("""COMPUTED_VALUE"""),7336.9) -> 7336.9 | W6: =IFERROR(__xludf.DUMMYFUNCTION("""COMPUTED_VALUE"""),6153) -> 6153 | X6: =SUM(Q6:W6) -> 173754.7
A7: ABC 5 kg | B7: =IFERROR(__xludf.DUMMYFUNCTION("""COMPUTED_VALUE"""),0.0667556231939292) -> 0.066755623 | C7: =IFERROR(__xludf.DUMMYFUNCTION("""COMPUTED_VALUE"""),0.0651024266252983) -> 0.065102427 | D7: =IFERROR(__xludf.DUMMYFUNCTION("""COMPUTED_VALUE"""),0.0817858344236914) -> 0.081785834 | E7: =IFERROR(__xludf.DUMMYFUNCTION("""COMPUTED_VALUE"""),0.0997196200427302) -> 0.09971962 | F7: =IFERROR(__xludf.DUMMYFUNCTION("""COMPUTED_VALUE"""),0.100089910575874) -> 0.10008991 | G7: =IFERROR(__xludf.DUMMYFUNCTION("""COMPUTED_VALUE"""),0.0988243995547109) -> 0.0988244 | H7: =IFERROR(__xludf.DUMMYFUNCTION("""COMPUTED_VALUE"""),0.0797892781627565) -> 0.079789278 | I7: =IFERROR(__xludf.DUMMYFUNCTION("""COMPUTED_VALUE"""),0.0795925746996675) -> 0.079592575 | J7: =IFERROR(__xludf.DUMMYFUNCTION("""COMPUTED_VALUE"""),0.0807139532651435) -> 0.080713953 | K7: =IFERROR(__xludf.DUMMYFUNCTION("""COMPUTED_VALUE"""),0.0807139532651435) -> 0.080713953 | L7: =IFERROR(__xludf.DUMMYFUNCTION("""COMPUTED_VALUE"""),0.0819968593006307) -> 0.081996859 | M7: =IFERROR(__xludf.DUMMYFUNCTION("""COMPUTED_VALUE"""),0.0849155668904246) -> 0.084915567 | N7: =IFERROR(__xludf.DUMMYFUNCTION("""COMPUTED_VALUE"""),56059.2707104735) -> 56059.271 | O7: =IFERROR(__xludf.DUMMYFUNCTION("""COMPUTED_VALUE"""),1) -> 1 | P7: =IFERROR(__xludf.DUMMYFUNCTION("""COMPUTED_VALUE"""),855) -> 855 | Q7: =IFERROR(__xludf.DUMMYFUNCTION("""COMPUTED_VALUE"""),69628) -> 69628 | R7: =IFERROR(__xludf.DUMMYFUNCTION("""COMPUTED_VALUE"""),732591.4) -> 732591.4 | S7: =IFERROR(__xludf.DUMMYFUNCTION("""COMPUTED_VALUE"""),52786.7) -> 52786.7 | T7: =IFERROR(__xludf.DUMMYFUNCTION("""COMPUTED_VALUE"""),8847.8) -> 8847.8 | U7: =IFERROR(__xludf.DUMMYFUNCTION("""COMPUTED_VALUE"""),113431.7) -> 113431.7 | V7: =IFERROR(__xludf.DUMMYFUNCTION("""COMPUTED_VALUE"""),46903.8) -> 46903.8 | W7: =IFERROR(__xludf.DUMMYFUNCTION("""COMPUTED_VALUE"""),5342) -> 5342 | X7: =SUM(Q7:W7) -> 1029531.4
A8: ABC 10 kg | B8: =IFERROR(__xludf.DUMMYFUNCTION("""COMPUTED_VALUE"""),0.064612341974598) -> 0.064612342 | C8: =IFERROR(__xludf.DUMMYFUNCTION("""COMPUTED_VALUE"""),0.064612341974598) -> 0.064612342 | D8: =IFERROR(__xludf.DUMMYFUNCTION("""COMPUTED_VALUE"""),0.0831857089056497) -> 0.083185709 | E8: =IFERROR(__xludf.DUMMYFUNCTION("""COMPUTED_VALUE"""),0.101329540689849) -> 0.10132954 | F8: =IFERROR(__xludf.DUMMYFUNCTION("""COMPUTED_VALUE"""),0.10227719847342) -> 0.1022772 | G8: =IFERROR(__xludf.DUMMYFUNCTION("""COMPUTED_VALUE"""),0.0993233886074831) -> 0.099323389 | H8: =IFERROR(__xludf.DUMMYFUNCTION("""COMPUTED_VALUE"""),0.078066397641533) -> 0.078066398 | I8: =IFERROR(__xludf.DUMMYFUNCTION("""COMPUTED_VALUE"""),0.078743869594065) -> 0.07874387 | J8: =IFERROR(__xludf.DUMMYFUNCTION("""COMPUTED_VALUE"""),0.081697679460002) -> 0.081697679 | K8: =IFERROR(__xludf.DUMMYFUNCTION("""COMPUTED_VALUE"""),0.081697679460002) -> 0.081697679 | L8: =IFERROR(__xludf.DUMMYFUNCTION("""COMPUTED_VALUE"""),0.0807500216764314) -> 0.080750022 | M8: =IFERROR(__xludf.DUMMYFUNCTION("""COMPUTED_VALUE"""),0.0837038315423683) -> 0.083703832 | N8: =IFERROR(__xludf.DUMMYFUNCTION("""COMPUTED_VALUE"""),3319.32790518283) -> 3319.3279 | O8: =IFERROR(__xludf.DUMMYFUNCTION("""COMPUTED_VALUE"""),1) -> 1 | P8: =IFERROR(__xludf.DUMMYFUNCTION("""COMPUTED_VALUE"""),53) -> 53 | Q8: =IFERROR(__xludf.DUMMYFUNCTION("""COMPUTED_VALUE"""),0) -> 0 | R8: =IFERROR(__xludf.DUMMYFUNCTION("""COMPUTED_VALUE"""),44900.8) -> 44900.8 | S8: =IFERROR(__xludf.DUMMYFUNCTION("""COMPUTED_VALUE"""),5673.3) -> 5673.3 | T8: =IFERROR(__xludf.DUMMYFUNCTION("""COMPUTED_VALUE"""),2123.5) -> 2123.5 | U8: =IFERROR(__xludf.DUMMYFUNCTION("""COMPUTED_VALUE"""),0) -> 0 | V8: =IFERROR(__xludf.DUMMYFUNCTION("""COMPUTED_VALUE"""),6270.5) -> 6270.5 | W8: =IFERROR(__xludf.DUMMYFUNCTION("""COMPUTED_VALUE"""),0) -> 0 | X8: =SUM(Q8:W8) -> 58968.1
A9: Agua 10 l | B9: =IFERROR(__xludf.DUMMYFUNCTION("""COMPUTED_VALUE"""),0.0670768247329043) -> 0.067076825 | C9: =IFERROR(__xludf.DUMMYFUNCTION("""COMPUTED_VALUE"""),0.0670768247329043) -> 0.067076825 | D9: =IFERROR(__xludf.DUMMYFUNCTION("""COMPUTED_VALUE"""),0.0827868661277296) -> 0.082786866 | E9: =IFERROR(__xludf.DUMMYFUNCTION("""COMPUTED_VALUE"""),0.0993493196011858) -> 0.09934932 | F9: =IFERROR(__xludf.DUMMYFUNCTION("""COMPUTED_VALUE"""),0.0999705290370024) -> 0.099970529 | G9: =IFERROR(__xludf.DUMMYFUNCTION("""COMPUTED_VALUE"""),0.0970461916480882) -> 0.097046192 | H9: =IFERROR(__xludf.DUMMYFUNCTION("""COMPUTED_VALUE"""),0.0788828581851096) -> 0.078882858 | I9: =IFERROR(__xludf.DUMMYFUNCTION("""COMPUTED_VALUE"""),0.0790330223001652) -> 0.079033022 | J9: =IFERROR(__xludf.DUMMYFUNCTION("""COMPUTED_VALUE"""),0.0817739112794073) -> 0.081773911 | K9: =IFERROR(__xludf.DUMMYFUNCTION("""COMPUTED_VALUE"""),0.0817739112794073) -> 0.081773911 | L9: =IFERROR(__xludf.DUMMYFUNCTION("""COMPUTED_VALUE"""),0.0811527018435908) -> 0.081152702 | M9: =IFERROR(__xludf.DUMMYFUNCTION("""COMPUTED_VALUE"""),0.084077039232505) -> 0.084077039 | N9: =IFERROR(__xludf.DUMMYFUNCTION("""COMPUTED_VALUE"""),4686.14321768856) -> 4686.1432 | O9: =IFERROR(__xludf.DUMMYFUNCTION("""COMPUTED_VALUE"""),1) -> 1 | P9: =IFERROR(__xludf.DUMMYFUNCTION("""COMPUTED_VALUE"""),73) -> 73 | Q9: =IFERROR(__xludf.DUMMYFUNCTION("""COMPUTED_VALUE"""),0) -> 0 | R9: =IFERROR(__xludf.DUMMYFUNCTION("""COMPUTED_VALUE"""),56716.8) -> 56716.8 | S9: =IFERROR(__xludf.DUMMYFUNCTION("""COMPUTED_VALUE"""),4876.4) -> 4876.4 | T9: =IFERROR(__xludf.DUMMYFUNCTION("""COMPUTED_VALUE"""),1415.6) -> 1415.6 | U9: =IFERROR(__xludf.DUMMYFUNCTION("""COMPUTED_VALUE"""),12568.5) -> 12568.5 | V9: =IFERROR(__xludf.DUMMYFUNCTION("""COMPUTED_VALUE"""),8958.8) -> 8958.8 | W9: =IFERROR(__xludf.DUMMYFUNCTION("""COMPUTED_VALUE"""),562) -> 562 | X9: =SUM(Q9:W9) -> 85098.1
A10: AFFF 10 l | B10: =IFERROR(__xludf.DUMMYFUNCTION("""COMPUTED_VALUE"""),0.0833333333333333) -> 0.083333333 | C10: =IFERROR(__xludf.DUMMYFUNCTION("""COMPUTED_VALUE"""),0.0833333333333333) -> 0.083333333 | D10: =IFERROR(__xludf.DUMMYFUNCTION("""COMPUTED_VALUE"""),0.0833333333333333) -> 0.083333333 | E10: =IFERROR(__xludf.DUMMYFUNCTION("""COMPUTED_VALUE"""),0.0833333333333333) -> 0.083333333 | F10: =IFERROR(__xludf.DUMMYFUNCTION("""COMPUTED_VALUE"""),0.0833333333333333) -> 0.083333333 | G10: =IFERROR(__xludf.DUMMYFUNCTION("""COMPUTED_VALUE"""),0.0833333333333333) -> 0.083333333 | H10: =IFERROR(__xludf.DUMMYFUNCTION("""COMPUTED_VALUE"""),0.0833333333333333) -> 0.083333333 | I10: =IFERROR(__xludf.DUMMYFUNCTION("""COMPUTED_VALUE"""),0.0833333333333333) -> 0.083333333 | ... M10: =IFERROR(__xludf.DUMMYFUNCTION("""COMPUTED_VALUE"""),0.0833333333333333) -> 0.083333333 | N10: =IFERROR(__xludf.DUMMYFUNCTION("""COMPUTED_VALUE"""),889.694438407785) -> 889.69444 | O10: =IFERROR(__xludf.DUMMYFUNCTION("""COMPUTED_VALUE"""),1) -> 1 | P10: =IFERROR(__xludf.DUMMYFUNCTION("""COMPUTED_VALUE"""),12) -> 12 | Q10: =IFERROR(__xludf.DUMMYFUNCTION("""COMPUTED_VALUE"""),0) -> 0 | R10: =IFERROR(__xludf.DUMMYFUNCTION("""COMPUTED_VALUE"""),0) -> 0 | S10: =IFERROR(__xludf.DUMMYFUNCTION("""COMPUTED_VALUE"""),0) -> 0 | T10: =IFERROR(__xludf.DUMMYFUNCTION("""COMPUTED_VALUE"""),0) -> 0 | U10: =IFERROR(__xludf.DUMMYFUNCTION("""COMPUTED_VALUE"""),15671.5) -> 15671.5 | V10: =IFERROR(__xludf.DUMMYFUNCTION("""COMPUTED_VALUE"""),0) -> 0 | W10: =IFERROR(__xludf.DUMMYFUNCTION("""COMPUTED_VALUE"""),0) -> 0 | X10: =SUM(Q10:W10) -> 15671.5
A11: AFFF 50 l s/ruedas | B11: =IFERROR(__xludf.DUMMYFUNCTION("""COMPUTED_VALUE"""),0.0833333333333333) -> 0.083333333 | C11: =IFERROR(__xludf.DUMMYFUNCTION("""COMPUTED_VALUE"""),0.0833333333333333) -> 0.083333333 | D11: =IFERROR(__xludf.DUMMYFUNCTION("""COMPUTED_VALUE"""),0.0833333333333333) -> 0.083333333 | E11: =IFERROR(__xludf.DUMMYFUNCTION("""COMPUTED_VALUE"""),0.0833333333333333) -> 0.083333333 | F11: =IFERROR(__xludf.DUMMYFUNCTION("""COMPUTED_VALUE"""),0.0833333333333333) -> 0.083333333 | G11: =IFERROR(__xludf.DUMMYFUNCTION("""COMPUTED_VALUE"""),0.0833333333333333) -> 0.083333333 | H11: =IFERROR(__xludf.DUMMYFUNCTION("""COMPUTED_VALUE"""),0.0833333333333333) -> 0.083333333 | I11: =IFERROR(__xludf.DUMMYFUNCTION("""COMPUTED_VALUE"""),0.0833333333333333) -> 0.083333333 | ... M11: =IFERROR(__xludf.DUMMYFUNCTION("""COMPUTED_VALUE"""),0.0833333333333333) -> 0.083333333 | N11: =IFERROR(__xludf.DUMMYFUNCTION("""COMPUTED_VALUE"""),463.773030017405) -> 463.77303 | O11: =IFERROR(__xludf.DUMMYFUNCTION("""COMPUTED_VALUE"""),1) -> 1 | P11: =IFERROR(__xludf.DUMMYFUNCTION("""COMPUTED_VALUE"""),6) -> 6 | Q11: =IFERROR(__xludf.DUMMYFUNCTION("""COMPUTED_VALUE"""),0) -> 0 | R11: =IFERROR(__xludf.DUMMYFUNCTION("""COMPUTED_VALUE"""),0) -> 0 | S11: =IFERROR(__xludf.DUMMYFUNCTION("""COMPUTED_VALUE"""),0) -> 0 | T11: =IFERROR(__xludf.DUMMYFUNCTION("""COMPUTED_VALUE"""),0) -> 0 | U11: =IFERROR(__xludf.DUMMYFUNCTION("""COMPUTED_VALUE"""),9151.4) -> 9151.4 | V11: =IFERROR(__xludf.DUMMYFUNCTION("""COMPUTED_VALUE"""),0) -> 0 | W11: =IFERROR(__xludf.DUMMYFUNCTION("""COMPUTED_VALUE"""),0) -> 0 | X11: =SUM(Q11:W11) -> 9151.4
A12: BC 5 kg | B12: =IFERROR(__xludf.DUMMYFUNCTION("""COMPUTED_VALUE"""),0.0833333333333333) -> 0.083333333 | C12: =IFERROR(__xludf.DUMMYFUNCTION("""COMPUTED_VALUE"""),0.0833333333333333) -> 0.083333333 | D12: =IFERROR(__xludf.DUMMYFUNCTION("""COMPUTED_VALUE"""),0.0833333333333333) -> 0.083333333 | E12: =IFERROR(__xludf.DUMMYFUNCTION("""COMPUTED_VALUE"""),0.0833333333333333) -> 0.083333333 | F12: =IFERROR(__xludf.DUMMYFUNCTION("""COMPUTED_VALUE"""),0.0833333333333333) -> 0.083333333 | G12: =IFERROR(__xludf.DUMMYFUNCTION("""COMPUTED_VALUE"""),0.0833333333333333) -> 0.083333333 | H12: =IFERROR(__xludf.DUMMYFUNCTION("""COMPUTED_VALUE"""),0.0833333333333333) -> 0.083333333 | I12: =IFERROR(__xludf.DUMMYFUNCTION("""COMPUTED_VALUE"""),0.0833333333333333) -> 0.083333333 | ... M12: =IFERROR(__xludf.DUMMYFUNCTION("""COMPUTED_VALUE"""),0.0833333333333333) -> 0.083333333 | N12: =IFERROR(__xludf.DUMMYFUNCTION("""COMPUTED_VALUE"""),268.09876141114) -> 268.09876 | O12: =IFERROR(__xludf.DUMMYFUNCTION("""COMPUTED_VALUE"""),1) -> 1 | P12: =IFERROR(__xludf.DUMMYFUNCTION("""COMPUTED_VALUE"""),4) -> 4 | Q12: =IFERROR(__xludf.DUMMYFUNCTION("""COMPUTED_VALUE"""),0) -> 0 | R12: =IFERROR(__xludf.DUMMYFUNCTION("""COMPUTED_VALUE"""),0) -> 0 | S12: =IFERROR(__xludf.DUMMYFUNCTION("""COMPUTED_VALUE"""),0) -> 0 | T12: =IFERROR(__xludf.DUMMYFUNCTION("""COMPUTED_VALUE"""),0) -> 0 | U12: =IFERROR(__xludf.DUMMYFUNCTION("""COMPUTED_VALUE"""),4634.7) -> 4634.7 | V12: =IFERROR(__xludf.DUMMYFUNCTION("""COMPUTED_VALUE"""),0) -> 0 | W12: =IFERROR(__xludf.DUMMYFUNCTION("""COMPUTED_VALUE"""),0) -> 0 | X12: =SUM(Q12:W12) -> 4634.7
A13: Sales K 6 l | B13: =IFERROR(__xludf.DUMMYFUNCTION("""COMPUTED_VALUE"""),0.0695355190499093) -> 0.069535519 | C13: =IFERROR(__xludf.DUMMYFUNCTION("""COMPUTED_VALUE"""),0.0695355190499093) -> 0.069535519 | D13: =IFERROR(__xludf.DUMMYFUNCTION("""COMPUTED_VALUE"""),0.0838248196490894) -> 0.08382482 | E13: =IFERROR(__xludf.DUMMYFUNCTION("""COMPUTED_VALUE"""),0.0948339806026096) -> 0.094833981 | F13: =IFERROR(__xludf.DUMMYFUNCTION("""COMPUTED_VALUE"""),0.0972184056200527) -> 0.097218406 | G13: =IFERROR(__xludf.DUMMYFUNCTION("""COMPUTED_VALUE"""),0.0952240073446056) -> 0.095224007 | H13: =IFERROR(__xludf.DUMMYFUNCTION("""COMPUTED_VALUE"""),0.0780009399043672) -> 0.07800094 | I13: =IFERROR(__xludf.DUMMYFUNCTION("""COMPUTED_VALUE"""),0.0813247334874215) -> 0.081324733 | J13: =IFERROR(__xludf.DUMMYFUNCTION("""COMPUTED_VALUE"""),0.0833191317628686) -> 0.083319132 | K13: =IFERROR(__xludf.DUMMYFUNCTION("""COMPUTED_VALUE"""),0.0833191317628686) -> 0.083319132 | L13: =IFERROR(__xludf.DUMMYFUNCTION("""COMPUTED_VALUE"""),0.0809347067454255) -> 0.080934707 | M13: =IFERROR(__xludf.DUMMYFUNCTION("""COMPUTED_VALUE"""),0.0829291050208727) -> 0.082929105 | N13: =IFERROR(__xludf.DUMMYFUNCTION("""COMPUTED_VALUE"""),2310.99407344162) -> 2310.9941 | O13: =IFERROR(__xludf.DUMMYFUNCTION("""COMPUTED_VALUE"""),1) -> 1 | P13: =IFERROR(__xludf.DUMMYFUNCTION("""COMPUTED_VALUE"""),35) -> 35 | Q13: =IFERROR(__xludf.DUMMYFUNCTION("""COMPUTED_VALUE"""),0) -> 0 | R13: =IFERROR(__xludf.DUMMYFUNCTION("""COMPUTED_VALUE"""),20087.2) -> 20087.2 | S13: =IFERROR(__xludf.DUMMYFUNCTION("""COMPUTED_VALUE"""),4459) -> 4459 | T13: =IFERROR(__xludf.DUMMYFUNCTION("""COMPUTED_VALUE"""),3539.1) -> 3539.1 | U13: =IFERROR(__xludf.DUMMYFUNCTION("""COMPUTED_VALUE"""),8169.7) -> 8169.7 | V13: =IFERROR(__xludf.DUMMYFUNCTION("""COMPUTED_VALUE"""),2804.4) -> 2804.4 | W13: =IFERROR(__xludf.DUMMYFUNCTION("""COMPUTED_VALUE"""),0) -> 0 | X13: =SUM(Q13:W13) -> 39059.4
A14: CO₂ 2 kg | B14: =IFERROR(__xludf.DUMMYFUNCTION("""COMPUTED_VALUE"""),0.0616150736413202) -> 0.061615074 | C14: =IFERROR(__xludf.DUMMYFUNCTION("""COMPUTED_VALUE"""),0.0616150736413202) -> 0.061615074 | D14: =IFERROR(__xludf.DUMMYFUNCTION("""COMPUTED_VALUE"""),0.0829453490803136) -> 0.082945349 | E14: =IFERROR(__xludf.DUMMYFUNCTION("""COMPUTED_VALUE"""),0.103007646651263) -> 0.10300765 | F14: =IFERROR(__xludf.DUMMYFUNCTION("""COMPUTED_VALUE"""),0.103425871740429) -> 0.10342587 | G14: =IFERROR(__xludf.DUMMYFUNCTION("""COMPUTED_VALUE"""),0.102109899624234) -> 0.1021099 | H14: =IFERROR(__xludf.DUMMYFUNCTION("""COMPUTED_VALUE"""),0.0801282894274162) -> 0.080128289 | I14: =IFERROR(__xludf.DUMMYFUNCTION("""COMPUTED_VALUE"""),0.079881877158212) -> 0.079881877 | J14: =IFERROR(__xludf.DUMMYFUNCTION("""COMPUTED_VALUE"""),0.081197849274407) -> 0.081197849 | K14: =IFERROR(__xludf.DUMMYFUNCTION("""COMPUTED_VALUE"""),0.081197849274407) -> 0.081197849 | L14: =IFERROR(__xludf.DUMMYFUNCTION("""COMPUTED_VALUE"""),0.080779624185241) -> 0.080779624 | M14: =IFERROR(__xludf.DUMMYFUNCTION("""COMPUTED_VALUE"""),0.082095596301436) -> 0.082095596 | N14: =IFERROR(__xludf.DUMMYFUNCTION("""COMPUTED_VALUE"""),12606.7299522508) -> 12606.73 | O14: =IFERROR(__xludf.DUMMYFUNCTION("""COMPUTED_VALUE"""),1) -> 1 | P14: =IFERROR(__xludf.DUMMYFUNCTION("""COMPUTED_VALUE"""),199) -> 199 | Q14: =IFERROR(__xludf.DUMMYFUNCTION("""COMPUTED_VALUE"""),0) -> 0 | R14: =IFERROR(__xludf.DUMMYFUNCTION("""COMPUTED_VALUE"""),183147.8) -> 183147.8 | S14: =IFERROR(__xludf.DUMMYFUNCTION("""COMPUTED_VALUE"""),19050.2) -> 19050.2 | T14: =IFERROR(__xludf.DUMMYFUNCTION("""COMPUTED_VALUE"""),3539.1) -> 3539.1 | U14: =IFERROR(__xludf.DUMMYFUNCTION("""COMPUTED_VALUE"""),6402.2) -> 6402.2 | V14: =IFERROR(__xludf.DUMMYFUNCTION("""COMPUTED_VALUE"""),10549.9) -> 10549.9 | W14: =IFERROR(__xludf.DUMMYFUNCTION("""COMPUTED_VALUE"""),0) -> 0 | X14: =SUM(Q14:W14) -> 222689.2
A15: CO₂ 5 kg | B15: =IFERROR(__xludf.DUMMYFUNCTION("""COMPUTED_VALUE"""),0.0761848278176029) -> 0.076184828 | C15: =IFERROR(__xludf.DUMMYFUNCTION("""COMPUTED_VALUE"""),0.0761848278176029) -> 0.076184828 | D15: =IFERROR(__xludf.DUMMYFUNCTION("""COMPUTED_VALUE"""),0.0826686065765467) -> 0.082668607 | E15: =IFERROR(__xludf.DUMMYFUNCTION("""COMPUTED_VALUE"""),0.0916518877640263) -> 0.091651888 | F15: =IFERROR(__xludf.DUMMYFUNCTION("""COMPUTED_VALUE"""),0.0931955183643168) -> 0.093195518 | G15: =IFERROR(__xludf.DUMMYFUNCTION("""COMPUTED_VALUE"""),0.0888541224858191) -> 0.088854122 | H15: =IFERROR(__xludf.DUMMYFUNCTION("""COMPUTED_VALUE"""),0.0784912986070083) -> 0.078491299 | I15: =IFERROR(__xludf.DUMMYFUNCTION("""COMPUTED_VALUE"""),0.0795725784486681) -> 0.079572578 | J15: =IFERROR(__xludf.DUMMYFUNCTION("""COMPUTED_VALUE"""),0.0829855493601231) -> 0.082985549 | K15: =IFERROR(__xludf.DUMMYFUNCTION("""COMPUTED_VALUE"""),0.0829855493601231) -> 0.082985549 | L15: =IFERROR(__xludf.DUMMYFUNCTION("""COMPUTED_VALUE"""),0.0814419187598326) -> 0.081441919 | M15: =IFERROR(__xludf.DUMMYFUNCTION("""COMPUTED_VALUE"""),0.0857833146383303) -> 0.085783315 | N15: =IFERROR(__xludf.DUMMYFUNCTION("""COMPUTED_VALUE"""),4308.38387982745) -> 4308.3839 | O15: =IFERROR(__xludf.DUMMYFUNCTION("""COMPUTED_VALUE"""),1) -> 1 | P15: =IFERROR(__xludf.DUMMYFUNCTION("""COMPUTED_VALUE"""),64) -> 64 | Q15: =IFERROR(__xludf.DUMMYFUNCTION("""COMPUTED_VALUE"""),0) -> 0 | R15: =IFERROR(__xludf.DUMMYFUNCTION("""COMPUTED_VALUE"""),25995.2) -> 25995.2 | S15: =IFERROR(__xludf.DUMMYFUNCTION("""COMPUTED_VALUE"""),891.8) -> 891.8 | T15: =IFERROR(__xludf.DUMMYFUNCTION("""COMPUTED_VALUE"""),1769.6) -> 1769.6 | U15: =IFERROR(__xludf.DUMMYFUNCTION("""COMPUTED_VALUE"""),32678.6) -> 32678.6 | V15: =IFERROR(__xludf.DUMMYFUNCTION("""COMPUTED_VALUE"""),11830.5) -> 11830.5 | W15: =IFERROR(__xludf.DUMMYFUNCTION("""COMPUTED_VALUE"""),2530) -> 2530 | X15: =SUM(Q15:W15) -> 75695.7
A16: HCFC/HFC 5 kg | B16: =IFERROR(__xludf.DUMMYFUNCTION("""COMPUTED_VALUE"""),0.0890943915723948) -> 0.089094392 | C16: =IFERROR(__xludf.DUMMYFUNCTION("""COMPUTED_VALUE"""),0.0890943915723948) -> 0.089094392 | D16: =IFERROR(__xludf.DUMMYFUNCTION("""COMPUTED_VALUE"""),0.0833333333333333) -> 0.083333333 | E16: =IFERROR(__xludf.DUMMYFUNCTION("""COMPUTED_VALUE"""),0.0833333333333333) -> 0.083333333 | F16: =IFERROR(__xludf.DUMMYFUNCTION("""COMPUTED_VALUE"""),0.0833333333333333) -> 0.083333333 | G16: =IFERROR(__xludf.DUMMYFUNCTION("""COMPUTED_VALUE"""),0.0775722750942719) -> 0.077572275 | H16: =IFERROR(__xludf.DUMMYFUNCTION("""COMPUTED_VALUE"""),0.0775722750942719) -> 0.077572275 | I16: =IFERROR(__xludf.DUMMYFUNCTION("""COMPUTED_VALUE"""),0.0775722750942719) -> 0.077572275 | J16: =IFERROR(__xludf.DUMMYFUNCTION("""COMPUTED_VALUE"""),0.0833333333333333) -> 0.083333333 | K16: =IFERROR(__xludf.DUMMYFUNCTION("""COMPUTED_VALUE"""),0.0833333333333333) -> 0.083333333 | L16: =IFERROR(__xludf.DUMMYFUNCTION("""COMPUTED_VALUE"""),0.0833333333333333) -> 0.083333333 | M16: =IFERROR(__xludf.DUMMYFUNCTION("""COMPUTED_VALUE"""),0.0890943915723948) -> 0.089094392 | N16: =IFERROR(__xludf.DUMMYFUNCTION("""COMPUTED_VALUE"""),705.316446113659) -> 705.31645 | O16: =IFERROR(__xludf.DUMMYFUNCTION("""COMPUTED_VALUE"""),1) -> 1 | P16: =IFERROR(__xludf.DUMMYFUNCTION("""COMPUTED_VALUE"""),11) -> 11 | Q16: =IFERROR(__xludf.DUMMYFUNCTION("""COMPUTED_VALUE"""),0) -> 0 | R16: =IFERROR(__xludf.DUMMYFUNCTION("""COMPUTED_VALUE"""),0) -> 0 | S16: =IFERROR(__xludf.DUMMYFUNCTION("""COMPUTED_VALUE"""),0) -> 0 | T16: =IFERROR(__xludf.DUMMYFUNCTION("""COMPUTED_VALUE"""),0) -> 0 | U16: =IFERROR(__xludf.DUMMYFUNCTION("""COMPUTED_VALUE"""),9269.4) -> 9269.4 | V16: =IFERROR(__xludf.DUMMYFUNCTION("""COMPUTED_VALUE"""),2425.5) -> 2425.5 | W16: =IFERROR(__xludf.DUMMYFUNCTION("""COMPUTED_VALUE"""),0) -> 0 | X16: =SUM(Q16:W16) -> 11694.9
A17: Clase D 9 l | B17: =IFERROR(__xludf.DUMMYFUNCTION("""COMPUTED_VALUE"""),0.0833333333333333) -> 0.083333333 | C17: =IFERROR(__xludf.DUMMYFUNCTION("""COMPUTED_VALUE"""),0.0833333333333333) -> 0.083333333 | D17: =IFERROR(__xludf.DUMMYFUNCTION("""COMPUTED_VALUE"""),0.0833333333333333) -> 0.083333333 | E17: =IFERROR(__xludf.DUMMYFUNCTION("""COMPUTED_VALUE"""),0.0833333333333333) -> 0.083333333 | F17: =IFERROR(__xludf.DUMMYFUNCTION("""COMPUTED_VALUE"""),0.0833333333333333) -> 0.083333333 | G17: =IFERROR(__xludf.DUMMYFUNCTION("""COMPUTED_VALUE"""),0.0833333333333333) -> 0.083333333 | H17: =IFERROR(__xludf.DUMMYFUNCTION("""COMPUTED_VALUE"""),0.0833333333333333) -> 0.083333333 | I17: =IFERROR(__xludf.DUMMYFUNCTION("""COMPUTED_VALUE"""),0.0833333333333333) -> 0.083333333 | ... M17: =IFERROR(__xludf.DUMMYFUNCTION("""COMPUTED_VALUE"""),0.0833333333333333) -> 0.083333333 | N17: =IFERROR(__xludf.DUMMYFUNCTION("""COMPUTED_VALUE"""),242.151440335721) -> 242.15144 | O17: =IFERROR(__xludf.DUMMYFUNCTION("""COMPUTED_VALUE"""),1) -> 1 | P17: =IFERROR(__xludf.DUMMYFUNCTION("""COMPUTED_VALUE"""),4) -> 4 | Q17: =IFERROR(__xludf.DUMMYFUNCTION("""COMPUTED_VALUE"""),0) -> 0 | R17: =IFERROR(__xludf.DUMMYFUNCTION("""COMPUTED_VALUE"""),0) -> 0 | S17: =IFERROR(__xludf.DUMMYFUNCTION("""COMPUTED_VALUE"""),0) -> 0 | T17: =IFERROR(__xludf.DUMMYFUNCTION("""COMPUTED_VALUE"""),0) -> 0 | U17: =IFERROR(__xludf.DUMMYFUNCTION("""COMPUTED_VALUE"""),3535) -> 3535 | V17: =IFERROR(__xludf.DUMMYFUNCTION("""COMPUTED_VALUE"""),0) -> 0 | W17: =IFERROR(__xludf.DUMMYFUNCTION("""COMPUTED_VALUE"""),0) -> 0 | X17: =SUM(Q17:W17) -> 3535
A18: ABC 25 kg s/ruedas | B18: =IFERROR(__xludf.DUMMYFUNCTION("""COMPUTED_VALUE"""),0.0741713639081832) -> 0.074171364 | C18: =IFERROR(__xludf.DUMMYFUNCTION("""COMPUTED_VALUE"""),0.0741713639081832) -> 0.074171364 | D18: =IFERROR(__xludf.DUMMYFUNCTION("""COMPUTED_VALUE"""),0.0826308825789044) -> 0.082630883 | E18: =IFERROR(__xludf.DUMMYFUNCTION("""COMPUTED_VALUE"""),0.0938477438743188) -> 0.093847744 | F18: =IFERROR(__xludf.DUMMYFUNCTION("""COMPUTED_VALUE"""),0.0943031990696216) -> 0.094303199 | G18: =IFERROR(__xludf.DUMMYFUNCTION("""COMPUTED_VALUE"""),0.0905972862319092) -> 0.090597286 | H18: =IFERROR(__xludf.DUMMYFUNCTION("""COMPUTED_VALUE"""),0.0782229570370311) -> 0.078222957 | I18: =IFERROR(__xludf.DUMMYFUNCTION("""COMPUTED_VALUE"""),0.0788873099187785) -> 0.07888731 | J18: =IFERROR(__xludf.DUMMYFUNCTION("""COMPUTED_VALUE"""),0.0825932227564908) -> 0.082593223 | K18: =IFERROR(__xludf.DUMMYFUNCTION("""COMPUTED_VALUE"""),0.0825932227564908) -> 0.082593223 | L18: =IFERROR(__xludf.DUMMYFUNCTION("""COMPUTED_VALUE"""),0.082137767561188) -> 0.082137768 | M18: =IFERROR(__xludf.DUMMYFUNCTION("""COMPUTED_VALUE"""),0.0858436803989003) -> 0.08584368 | N18: =IFERROR(__xludf.DUMMYFUNCTION("""COMPUTED_VALUE"""),577.776131502584) -> 577.77613 | O18: =IFERROR(__xludf.DUMMYFUNCTION("""COMPUTED_VALUE"""),1) -> 1 | P18: =IFERROR(__xludf.DUMMYFUNCTION("""COMPUTED_VALUE"""),9) -> 9 | Q18: =IFERROR(__xludf.DUMMYFUNCTION("""COMPUTED_VALUE"""),0) -> 0 | R18: =IFERROR(__xludf.DUMMYFUNCTION("""COMPUTED_VALUE"""),4431) -> 4431 | S18: =IFERROR(__xludf.DUMMYFUNCTION("""COMPUTED_VALUE"""),199.2) -> 199.2 | T18: =IFERROR(__xludf.DUMMYFUNCTION("""COMPUTED_VALUE"""),177) -> 177 | U18: =IFERROR(__xludf.DUMMYFUNCTION("""COMPUTED_VALUE"""),4055.3) -> 4055.3 | V18: =IFERROR(__xludf.DUMMYFUNCTION("""COMPUTED_VALUE"""),1364.4) -> 1364.4 | W18: =IFERROR(__xludf.DUMMYFUNCTION("""COMPUTED_VALUE"""),0) -> 0 | X18: =SUM(Q18:W18) -> 10226.9
A19: ABC 50 kg s/ruedas | B19: =IFERROR(__xludf.DUMMYFUNCTION("""COMPUTED_VALUE"""),0.0741714575622674) -> 0.074171458 | C19: =IFERROR(__xludf.DUMMYFUNCTION("""COMPUTED_VALUE"""),0.0741714575622674) -> 0.074171458 | D19: =IFERROR(__xludf.DUMMYFUNCTION("""COMPUTED_VALUE"""),0.08263095051887) -> 0.082630951 | E19: =IFERROR(__xludf.DUMMYFUNCTION("""COMPUTED_VALUE"""),0.0938477343304375) -> 0.093847734 | F19: =IFERROR(__xludf.DUMMYFUNCTION("""COMPUTED_VALUE"""),0.0943030721576538) -> 0.094303072 | G19: =IFERROR(__xludf.DUMMYFUNCTION("""COMPUTED_VALUE"""),0.0905972613831472) -> 0.090597261 | H19: =IFERROR(__xludf.DUMMYFUNCTION("""COMPUTED_VALUE"""),0.0782232108709845) -> 0.078223211 | I19: =IFERROR(__xludf.DUMMYFUNCTION("""COMPUTED_VALUE"""),0.0788872954792544) -> 0.078887295 | J19: =IFERROR(__xludf.DUMMYFUNCTION("""COMPUTED_VALUE"""),0.082593106253761) -> 0.082593106 | K19: =IFERROR(__xludf.DUMMYFUNCTION("""COMPUTED_VALUE"""),0.082593106253761) -> 0.082593106 | L19: =IFERROR(__xludf.DUMMYFUNCTION("""COMPUTED_VALUE"""),0.0821377684265447) -> 0.082137768 | M19: =IFERROR(__xludf.DUMMYFUNCTION("""COMPUTED_VALUE"""),0.0858435792010512) -> 0.085843579 | N19: =IFERROR(__xludf.DUMMYFUNCTION("""COMPUTED_VALUE"""),1271.10748852936) -> 1271.1075 | O19: =IFERROR(__xludf.DUMMYFUNCTION("""COMPUTED_VALUE"""),1) -> 1 | P19: =IFERROR(__xludf.DUMMYFUNCTION("""COMPUTED_VALUE"""),19) -> 19 | Q19: =IFERROR(__xludf.DUMMYFUNCTION("""COMPUTED_VALUE"""),0) -> 0 | R19: =IFERROR(__xludf.DUMMYFUNCTION("""COMPUTED_VALUE"""),9748.2) -> 9748.2 | S19: =IFERROR(__xludf.DUMMYFUNCTION("""COMPUTED_VALUE"""),438.3) -> 438.3 | T19: =IFERROR(__xludf.DUMMYFUNCTION("""COMPUTED_VALUE"""),389.3) -> 389.3 | U19: =IFERROR(__xludf.DUMMYFUNCTION("""COMPUTED_VALUE"""),8921.8) -> 8921.8 | V19: =IFERROR(__xludf.DUMMYFUNCTION("""COMPUTED_VALUE"""),3001.6) -> 3001.6 | W19: =IFERROR(__xludf.DUMMYFUNCTION("""COMPUTED_VALUE"""),0) -> 0 | X19: =SUM(Q19:W19) -> 22499.2
A20: ABC 70 kg s/ruedas | B20: =IFERROR(__xludf.DUMMYFUNCTION("""COMPUTED_VALUE"""),0.0741714711262728) -> 0.074171471 | C20: =IFERROR(__xludf.DUMMYFUNCTION("""COMPUTED_VALUE"""),0.0741714711262728) -> 0.074171471 | D20: =IFERROR(__xludf.DUMMYFUNCTION("""COMPUTED_VALUE"""),0.0826308668449537) -> 0.082630867 | E20: =IFERROR(__xludf.DUMMYFUNCTION("""COMPUTED_VALUE"""),0.0938479481909226) -> 0.093847948 | F20: =IFERROR(__xludf.DUMMYFUNCTION("""COMPUTED_VALUE"""),0.0943030828496681) -> 0.094303083 | G20: =IFERROR(__xludf.DUMMYFUNCTION("""COMPUTED_VALUE"""),0.0905972288565807) -> 0.090597229 | H20: =IFERROR(__xludf.DUMMYFUNCTION("""COMPUTED_VALUE"""),0.0782233613395939) -> 0.078223361 | I20: =IFERROR(__xludf.DUMMYFUNCTION("""COMPUTED_VALUE"""),0.0788871138035579) -> 0.078887114 | J20: =IFERROR(__xludf.DUMMYFUNCTION("""COMPUTED_VALUE"""),0.0825929677966453) -> 0.082592968 | K20: =IFERROR(__xludf.DUMMYFUNCTION("""COMPUTED_VALUE"""),0.0825929677966453) -> 0.082592968 | L20: =IFERROR(__xludf.DUMMYFUNCTION("""COMPUTED_VALUE"""),0.0821378331378998) -> 0.082137833 | M20: =IFERROR(__xludf.DUMMYFUNCTION("""COMPUTED_VALUE"""),0.0858436871309872) -> 0.085843687 | N20: =IFERROR(__xludf.DUMMYFUNCTION("""COMPUTED_VALUE"""),277.332543143421) -> 277.33254 | O20: =IFERROR(__xludf.DUMMYFUNCTION("""COMPUTED_VALUE"""),1) -> 1 | P20: =IFERROR(__xludf.DUMMYFUNCTION("""COMPUTED_VALUE"""),5) -> 5 | Q20: =IFERROR(__xludf.DUMMYFUNCTION("""COMPUTED_VALUE"""),0) -> 0 | R20: =IFERROR(__xludf.DUMMYFUNCTION("""COMPUTED_VALUE"""),2126.9) -> 2126.9 | S20: =IFERROR(__xludf.DUMMYFUNCTION("""COMPUTED_VALUE"""),95.6) -> 95.6 | T20: =IFERROR(__xludf.DUMMYFUNCTION("""COMPUTED_VALUE"""),84.9) -> 84.9 | U20: =IFERROR(__xludf.DUMMYFUNCTION("""COMPUTED_VALUE"""),1946.6) -> 1946.6 | V20: =IFERROR(__xludf.DUMMYFUNCTION("""COMPUTED_VALUE"""),654.9) -> 654.9 | W20: =IFERROR(__xludf.DUMMYFUNCTION("""COMPUTED_VALUE"""),0) -> 0 | X20: =SUM(Q20:W20) -> 4908.9
A21: ABC 100 kg s/ruedas | B21: =IFERROR(__xludf.DUMMYFUNCTION("""COMPUTED_VALUE"""),0.0741721346584101) -> 0.074172135 | C21: =IFERROR(__xludf.DUMMYFUNCTION("""COMPUTED_VALUE"""),0.0741721346584101) -> 0.074172135 | D21: =IFERROR(__xludf.DUMMYFUNCTION("""COMPUTED_VALUE"""),0.0826312550911103) -> 0.082631255 | E21: =IFERROR(__xludf.DUMMYFUNCTION("""COMPUTED_VALUE"""),0.0938475454254633) -> 0.093847545 | F21: =IFERROR(__xludf.DUMMYFUNCTION("""COMPUTED_VALUE"""),0.0943026800842088) -> 0.09430268 | G21: =IFERROR(__xludf.DUMMYFUNCTION("""COMPUTED_VALUE"""),0.0905968260911214) -> 0.090596826 | H21: =IFERROR(__xludf.DUMMYFUNCTION("""COMPUTED_VALUE"""),0.0782234917229329) -> 0.078223492 | I21: =IFERROR(__xludf.DUMMYFUNCTION("""COMPUTED_VALUE"""),0.0788869863240794) -> 0.078886986 | J21: =IFERROR(__xludf.DUMMYFUNCTION("""COMPUTED_VALUE"""),0.0825928403171668) -> 0.08259284 | K21: =IFERROR(__xludf.DUMMYFUNCTION("""COMPUTED_VALUE"""),0.0825928403171668) -> 0.08259284 | L21: =IFERROR(__xludf.DUMMYFUNCTION("""COMPUTED_VALUE"""),0.0821377056584213) -> 0.082137706 | M21: =IFERROR(__xludf.DUMMYFUNCTION("""COMPUTED_VALUE"""),0.0858435596515087) -> 0.08584356 | N21: =IFERROR(__xludf.DUMMYFUNCTION("""COMPUTED_VALUE"""),184.888361725934) -> 184.88836 | O21: =IFERROR(__xludf.DUMMYFUNCTION("""COMPUTED_VALUE"""),1) -> 1 | P21: =IFERROR(__xludf.DUMMYFUNCTION("""COMPUTED_VALUE"""),3) -> 3 | Q21: =IFERROR(__xludf.DUMMYFUNCTION("""COMPUTED_VALUE"""),0) -> 0 | R21: =IFERROR(__xludf.DUMMYFUNCTION("""COMPUTED_VALUE"""),1417.9) -> 1417.9 | S21: =IFERROR(__xludf.DUMMYFUNCTION("""COMPUTED_VALUE"""),63.8) -> 63.8 | T21: =IFERROR(__xludf.DUMMYFUNCTION("""COMPUTED_VALUE"""),56.6) -> 56.6 | U21: =IFERROR(__xludf.DUMMYFUNCTION("""COMPUTED_VALUE"""),1297.7) -> 1297.7 | V21: =IFERROR(__xludf.DUMMYFUNCTION("""COMPUTED_VALUE"""),436.6) -> 436.6 | W21: =IFERROR(__xludf.DUMMYFUNCTION("""COMPUTED_VALUE"""),0) -> 0 | X21: =SUM(Q21:W21) -> 3272.6
A22: Toda la planta | B22: =IFERROR(__xludf.DUMMYFUNCTION("""COMPUTED_VALUE"""),0.094685974590863) -> 0.094685975 | C22: =IFERROR(__xludf.DUMMYFUNCTION("""COMPUTED_VALUE"""),0.0813589828439731) -> 0.081358983 | D22: =IFERROR(__xludf.DUMMYFUNCTION("""COMPUTED_VALUE"""),0.0763711312806997) -> 0.076371131 | E22: =IFERROR(__xludf.DUMMYFUNCTION("""COMPUTED_VALUE"""),0.084183445923961) -> 0.084183446 | F22: =IFERROR(__xludf.DUMMYFUNCTION("""COMPUTED_VALUE"""),0.0847815688752799) -> 0.084781569 | G22: =IFERROR(__xludf.DUMMYFUNCTION("""COMPUTED_VALUE"""),0.0840164331631308) -> 0.084016433 | H22: =IFERROR(__xludf.DUMMYFUNCTION("""COMPUTED_VALUE"""),0.0748812526033842) -> 0.074881253 | I22: =IFERROR(__xludf.DUMMYFUNCTION("""COMPUTED_VALUE"""),0.0755102802186843) -> 0.07551028 | J22: =IFERROR(__xludf.DUMMYFUNCTION("""COMPUTED_VALUE"""),0.0761652663624608) -> 0.076165266 | K22: =IFERROR(__xludf.DUMMYFUNCTION("""COMPUTED_VALUE"""),0.0761652663624608) -> 0.076165266 | L22: =IFERROR(__xludf.DUMMYFUNCTION("""COMPUTED_VALUE"""),0.0888941351580317) -> 0.088894135 | M22: =IFERROR(__xludf.DUMMYFUNCTION("""COMPUTED_VALUE"""),0.102986262617071) -> 0.10298626 | N22: =SUM(N5:N21) -> 206230.15 | P22: =SUM(P5:P21) -> 1498
A23: Lote por cliente (u.) | Q23: =IFERROR(__xludf.DUMMYFUNCTION("IMPORTRANGE(Links!$B$4,""sobrestock_sustitutos!B18:H18"")"),9) -> 9 | R23: =IFERROR(__xludf.DUMMYFUNCTION("""COMPUTED_VALUE"""),15) -> 15 | S23: =IFERROR(__xludf.DUMMYFUNCTION("""COMPUTED_VALUE"""),12) -> 12 | T23: =IFERROR(__xludf.DUMMYFUNCTION("""COMPUTED_VALUE"""),11) -> 11 | U23: =IFERROR(__xludf.DUMMYFUNCTION("""COMPUTED_VALUE"""),10) -> 10 | V23: =IFERROR(__xludf.DUMMYFUNCTION("""COMPUTED_VALUE"""),61) -> 61 | W23: =IFERROR(__xludf.DUMMYFUNCTION("""COMPUTED_VALUE"""),6) -> 6
A24: Días hábiles por mes | B24: =IFERROR(__xludf.DUMMYFUNCTION("IMPORTRANGE(Links!$B$4,""parametros_recargas!B2"")"),20) -> 20
A25: Horas productivas por turno | B25: =IFERROR(__xludf.DUMMYFUNCTION("IMPORTRANGE(Links!$B$4,""parametros_recargas!B5"")"),7.5) -> 7.5
A27: Rubro: estacionalidad (% del año) | B27: Ene | C27: Feb | D27: Mar | E27: Abr | F27: May | G27: Jun | H27: Jul | I27: Ago | J27: Sep | K27: Oct | L27: Nov | M27: Dic
A28: Automotor | B28: =IFERROR(__xludf.DUMMYFUNCTION("IMPORTRANGE(Links!$B$4,""parametros_recargas!E35:P41"")"),0.12) -> 0.12 | C28: =IFERROR(__xludf.DUMMYFUNCTION("""COMPUTED_VALUE"""),0.0955555555555556) -> 0.095555556 | D28: =IFERROR(__xludf.DUMMYFUNCTION("""COMPUTED_VALUE"""),0.0711111111111111) -> 0.071111111 | E28: =IFERROR(__xludf.DUMMYFUNCTION("""COMPUTED_VALUE"""),0.0711111111111111) -> 0.071111111 | F28: =IFERROR(__xludf.DUMMYFUNCTION("""COMPUTED_VALUE"""),0.0711111111111111) -> 0.071111111 | G28: =IFERROR(__xludf.DUMMYFUNCTION("""COMPUTED_VALUE"""),0.0711111111111111) -> 0.071111111 | H28: =IFERROR(__xludf.DUMMYFUNCTION("""COMPUTED_VALUE"""),0.0711111111111111) -> 0.071111111 | I28: =IFERROR(__xludf.DUMMYFUNCTION("""COMPUTED_VALUE"""),0.0711111111111111) -> 0.071111111 | J28: =IFERROR(__xludf.DUMMYFUNCTION("""COMPUTED_VALUE"""),0.0711111111111111) -> 0.071111111 | K28: =IFERROR(__xludf.DUMMYFUNCTION("""COMPUTED_VALUE"""),0.0711111111111111) -> 0.071111111 | L28: =IFERROR(__xludf.DUMMYFUNCTION("""COMPUTED_VALUE"""),0.0955555555555556) -> 0.095555556 | M28: =IFERROR(__xludf.DUMMYFUNCTION("""COMPUTED_VALUE"""),0.12) -> 0.12
A29: Edificios | B29: =IFERROR(__xludf.DUMMYFUNCTION("""COMPUTED_VALUE"""),0.0540540540540541) -> 0.054054054 | C29: =IFERROR(__xludf.DUMMYFUNCTION("""COMPUTED_VALUE"""),0.0540540540540541) -> 0.054054054 | D29: =IFERROR(__xludf.DUMMYFUNCTION("""COMPUTED_VALUE"""),0.0810810810810811) -> 0.081081081 | E29: =IFERROR(__xludf.DUMMYFUNCTION("""COMPUTED_VALUE"""),0.108108108108108) -> 0.10810811 | F29: =IFERROR(__xludf.DUMMYFUNCTION("""COMPUTED_VALUE"""),0.108108108108108) -> 0.10810811 | G29: =IFERROR(__xludf.DUMMYFUNCTION("""COMPUTED_VALUE"""),0.108108108108108) -> 0.10810811 | H29: =IFERROR(__xludf.DUMMYFUNCTION("""COMPUTED_VALUE"""),0.0810810810810811) -> 0.081081081 | I29: =IFERROR(__xludf.DUMMYFUNCTION("""COMPUTED_VALUE"""),0.0810810810810811) -> 0.081081081 | J29: =IFERROR(__xludf.DUMMYFUNCTION("""COMPUTED_VALUE"""),0.0810810810810811) -> 0.081081081 | K29: =IFERROR(__xludf.DUMMYFUNCTION("""COMPUTED_VALUE"""),0.0810810810810811) -> 0.081081081 | L29: =IFERROR(__xludf.DUMMYFUNCTION("""COMPUTED_VALUE"""),0.0810810810810811) -> 0.081081081 | M29: =IFERROR(__xludf.DUMMYFUNCTION("""COMPUTED_VALUE"""),0.0810810810810811) -> 0.081081081
A30: Educación | B30: =IFERROR(__xludf.DUMMYFUNCTION("""COMPUTED_VALUE"""),0.10126582278481) -> 0.10126582 | C30: =IFERROR(__xludf.DUMMYFUNCTION("""COMPUTED_VALUE"""),0.10126582278481) -> 0.10126582 | D30: =IFERROR(__xludf.DUMMYFUNCTION("""COMPUTED_VALUE"""),0.10126582278481) -> 0.10126582 | E30: =IFERROR(__xludf.DUMMYFUNCTION("""COMPUTED_VALUE"""),0.0759493670886076) -> 0.075949367 | F30: =IFERROR(__xludf.DUMMYFUNCTION("""COMPUTED_VALUE"""),0.0759493670886076) -> 0.075949367 | G30: =IFERROR(__xludf.DUMMYFUNCTION("""COMPUTED_VALUE"""),0.0759493670886076) -> 0.075949367 | H30: =IFERROR(__xludf.DUMMYFUNCTION("""COMPUTED_VALUE"""),0.0886075949367089) -> 0.088607595 | I30: =IFERROR(__xludf.DUMMYFUNCTION("""COMPUTED_VALUE"""),0.0759493670886076) -> 0.075949367 | J30: =IFERROR(__xludf.DUMMYFUNCTION("""COMPUTED_VALUE"""),0.0759493670886076) -> 0.075949367 | K30: =IFERROR(__xludf.DUMMYFUNCTION("""COMPUTED_VALUE"""),0.0759493670886076) -> 0.075949367 | L30: =IFERROR(__xludf.DUMMYFUNCTION("""COMPUTED_VALUE"""),0.0759493670886076) -> 0.075949367 | M30: =IFERROR(__xludf.DUMMYFUNCTION("""COMPUTED_VALUE"""),0.0759493670886076) -> 0.075949367
A31: Hoteles | B31: =IFERROR(__xludf.DUMMYFUNCTION("""COMPUTED_VALUE"""),0.0526315789473684) -> 0.052631579 | C31: =IFERROR(__xludf.DUMMYFUNCTION("""COMPUTED_VALUE"""),0.0526315789473684) -> 0.052631579 | D31: =IFERROR(__xludf.DUMMYFUNCTION("""COMPUTED_VALUE"""),0.0789473684210526) -> 0.078947368 | E31: =IFERROR(__xludf.DUMMYFUNCTION("""COMPUTED_VALUE"""),0.0789473684210526) -> 0.078947368 | F31: =IFERROR(__xludf.DUMMYFUNCTION("""COMPUTED_VALUE"""),0.105263157894737) -> 0.10526316 | G31: =IFERROR(__xludf.DUMMYFUNCTION("""COMPUTED_VALUE"""),0.105263157894737) -> 0.10526316 | H31: =IFERROR(__xludf.DUMMYFUNCTION("""COMPUTED_VALUE"""),0.0526315789473684) -> 0.052631579 | I31: =IFERROR(__xludf.DUMMYFUNCTION("""COMPUTED_VALUE"""),0.105263157894737) -> 0.10526316 | J31: =IFERROR(__xludf.DUMMYFUNCTION("""COMPUTED_VALUE"""),0.105263157894737) -> 0.10526316 | K31: =IFERROR(__xludf.DUMMYFUNCTION("""COMPUTED_VALUE"""),0.105263157894737) -> 0.10526316 | L31: =IFERROR(__xludf.DUMMYFUNCTION("""COMPUTED_VALUE"""),0.0789473684210526) -> 0.078947368 | M31: =IFERROR(__xludf.DUMMYFUNCTION("""COMPUTED_VALUE"""),0.0789473684210526) -> 0.078947368
A32: Industrias / almacenes | B32: =IFERROR(__xludf.DUMMYFUNCTION("""COMPUTED_VALUE"""),0.0833333333333333) -> 0.083333333 | C32: =IFERROR(__xludf.DUMMYFUNCTION("""COMPUTED_VALUE"""),0.0833333333333333) -> 0.083333333 | D32: =IFERROR(__xludf.DUMMYFUNCTION("""COMPUTED_VALUE"""),0.0833333333333333) -> 0.083333333 | E32: =IFERROR(__xludf.DUMMYFUNCTION("""COMPUTED_VALUE"""),0.0833333333333333) -> 0.083333333 | F32: =IFERROR(__xludf.DUMMYFUNCTION("""COMPUTED_VALUE"""),0.0833333333333333) -> 0.083333333 | G32: =IFERROR(__xludf.DUMMYFUNCTION("""COMPUTED_VALUE"""),0.0833333333333333) -> 0.083333333 | H32: =IFERROR(__xludf.DUMMYFUNCTION("""COMPUTED_VALUE"""),0.0833333333333333) -> 0.083333333 | I32: =IFERROR(__xludf.DUMMYFUNCTION("""COMPUTED_VALUE"""),0.0833333333333333) -> 0.083333333 | ... M32: =IFERROR(__xludf.DUMMYFUNCTION("""COMPUTED_VALUE"""),0.0833333333333333) -> 0.083333333
A33: Salud | B33: =IFERROR(__xludf.DUMMYFUNCTION("""COMPUTED_VALUE"""),0.111111111111111) -> 0.11111111 | C33: =IFERROR(__xludf.DUMMYFUNCTION("""COMPUTED_VALUE"""),0.111111111111111) -> 0.11111111 | D33: =IFERROR(__xludf.DUMMYFUNCTION("""COMPUTED_VALUE"""),0.0833333333333333) -> 0.083333333 | E33: =IFERROR(__xludf.DUMMYFUNCTION("""COMPUTED_VALUE"""),0.0833333333333333) -> 0.083333333 | F33: =IFERROR(__xludf.DUMMYFUNCTION("""COMPUTED_VALUE"""),0.0833333333333333) -> 0.083333333 | G33: =IFERROR(__xludf.DUMMYFUNCTION("""COMPUTED_VALUE"""),0.0555555555555556) -> 0.055555556 | H33: =IFERROR(__xludf.DUMMYFUNCTION("""COMPUTED_VALUE"""),0.0555555555555556) -> 0.055555556 | I33: =IFERROR(__xludf.DUMMYFUNCTION("""COMPUTED_VALUE"""),0.0555555555555556) -> 0.055555556 | J33: =IFERROR(__xludf.DUMMYFUNCTION("""COMPUTED_VALUE"""),0.0833333333333333) -> 0.083333333 | K33: =IFERROR(__xludf.DUMMYFUNCTION("""COMPUTED_VALUE"""),0.0833333333333333) -> 0.083333333 | L33: =IFERROR(__xludf.DUMMYFUNCTION("""COMPUTED_VALUE"""),0.0833333333333333) -> 0.083333333 | M33: =IFERROR(__xludf.DUMMYFUNCTION("""COMPUTED_VALUE"""),0.111111111111111) -> 0.11111111
A34: Supermercados | B34: =IFERROR(__xludf.DUMMYFUNCTION("""COMPUTED_VALUE"""),0.0555555555555556) -> 0.055555556 | C34: =IFERROR(__xludf.DUMMYFUNCTION("""COMPUTED_VALUE"""),0.0555555555555556) -> 0.055555556 | D34: =IFERROR(__xludf.DUMMYFUNCTION("""COMPUTED_VALUE"""),0.0833333333333333) -> 0.083333333 | E34: =IFERROR(__xludf.DUMMYFUNCTION("""COMPUTED_VALUE"""),0.0833333333333333) -> 0.083333333 | F34: =IFERROR(__xludf.DUMMYFUNCTION("""COMPUTED_VALUE"""),0.111111111111111) -> 0.11111111 | G34: =IFERROR(__xludf.DUMMYFUNCTION("""COMPUTED_VALUE"""),0.111111111111111) -> 0.11111111 | H34: =IFERROR(__xludf.DUMMYFUNCTION("""COMPUTED_VALUE"""),0.111111111111111) -> 0.11111111 | I34: =IFERROR(__xludf.DUMMYFUNCTION("""COMPUTED_VALUE"""),0.111111111111111) -> 0.11111111 | J34: =IFERROR(__xludf.DUMMYFUNCTION("""COMPUTED_VALUE"""),0.0833333333333333) -> 0.083333333 | K34: =IFERROR(__xludf.DUMMYFUNCTION("""COMPUTED_VALUE"""),0.0833333333333333) -> 0.083333333 | L34: =IFERROR(__xludf.DUMMYFUNCTION("""COMPUTED_VALUE"""),0.0555555555555556) -> 0.055555556 | M34: =IFERROR(__xludf.DUMMYFUNCTION("""COMPUTED_VALUE"""),0.0555555555555556) -> 0.055555556
A37: Planta industrial
A38: Tipo: perfil mensual de recargas (% del año) | B38: Ene | C38: Feb | D38: Mar | E38: Abr | F38: May | G38: Jun | H38: Jul | I38: Ago | J38: Sep | K38: Oct | L38: Nov | M38: Dic | N38: Recargas 2035 (u) | O38: Lleva sustituto (1 = sí) | P38: Stock de sustitutos 2035 (u) | Q38: Automotor | R38: Edificios | S38: Educación | T38: Hoteles | U38: Industrias / almacenes | V38: Salud | W38: Supermercados | X38: Total mix
A39: ABC 1 kg | B39: =IFERROR(__xludf.DUMMYFUNCTION("IMPORTRANGE(Links!$B$5,""parametros_recargas!E55:P72"")"),0.119895289559294) -> 0.11989529 | C39: =IFERROR(__xludf.DUMMYFUNCTION("""COMPUTED_VALUE"""),0.0954891339827875) -> 0.095489134 | D39: =IFERROR(__xludf.DUMMYFUNCTION("""COMPUTED_VALUE"""),0.071124604952686) -> 0.071124605 | E39: =IFERROR(__xludf.DUMMYFUNCTION("""COMPUTED_VALUE"""),0.071124604952686) -> 0.071124605 | F39: =IFERROR(__xludf.DUMMYFUNCTION("""COMPUTED_VALUE"""),0.0711662314990906) -> 0.071166231 | G39: =IFERROR(__xludf.DUMMYFUNCTION("""COMPUTED_VALUE"""),0.0711662314990906) -> 0.071166231 | H39: =IFERROR(__xludf.DUMMYFUNCTION("""COMPUTED_VALUE"""),0.0710984243903592) -> 0.071098424 | I39: =IFERROR(__xludf.DUMMYFUNCTION("""COMPUTED_VALUE"""),0.0711662314990906) -> 0.071166231 | J39: =IFERROR(__xludf.DUMMYFUNCTION("""COMPUTED_VALUE"""),0.0711585085070517) -> 0.071158509 | K39: =IFERROR(__xludf.DUMMYFUNCTION("""COMPUTED_VALUE"""),0.0711585085070517) -> 0.071158509 | L39: =IFERROR(__xludf.DUMMYFUNCTION("""COMPUTED_VALUE"""),0.0955230375371532) -> 0.095523038 | M39: =IFERROR(__xludf.DUMMYFUNCTION("""COMPUTED_VALUE"""),0.119929193113659) -> 0.11992919 | N39: =IFERROR(__xludf.DUMMYFUNCTION("IMPORTRANGE(Links!$B$5,""datos_base!K2:K18"")"),56575.8368575054) -> 56575.837 | O39: =IFERROR(__xludf.DUMMYFUNCTION("IMPORTRANGE(Links!$B$5,""sobrestock_sustitutos!B30:B46"")"),0) -> 0 | P39: =IFERROR(__xludf.DUMMYFUNCTION("IMPORTRANGE(Links!$B$5,""sobrestock_sustitutos!K51:K67"")"),0) -> 0 | Q39: =IFERROR(__xludf.DUMMYFUNCTION("IMPORTRANGE(Links!$B$5,""PROY_Indexado!B57:H73"")"),1188664) -> 1188664 | R39: =IFERROR(__xludf.DUMMYFUNCTION("""COMPUTED_VALUE"""),0) -> 0 | S39: =IFERROR(__xludf.DUMMYFUNCTION("""COMPUTED_VALUE"""),0) -> 0 | T39: =IFERROR(__xludf.DUMMYFUNCTION("""COMPUTED_VALUE"""),1533.8) -> 1533.8 | U39: =IFERROR(__xludf.DUMMYFUNCTION("""COMPUTED_VALUE"""),0) -> 0 | V39: =IFERROR(__xludf.DUMMYFUNCTION("""COMPUTED_VALUE"""),0) -> 0 | W39: =IFERROR(__xludf.DUMMYFUNCTION("""COMPUTED_VALUE"""),331) -> 331 | X39: =SUM(Q39:W39) -> 1190528.8
A40: ABC 2,5 kg | B40: =IFERROR(__xludf.DUMMYFUNCTION("""COMPUTED_VALUE"""),0.0608346558815601) -> 0.060834656 | C40: =IFERROR(__xludf.DUMMYFUNCTION("""COMPUTED_VALUE"""),0.0608346558815601) -> 0.060834656 | D40: =IFERROR(__xludf.DUMMYFUNCTION("""COMPUTED_VALUE"""),0.082643351275423) -> 0.082643351 | E40: =IFERROR(__xludf.DUMMYFUNCTION("""COMPUTED_VALUE"""),0.0953382202836263) -> 0.09533822 | F40: =IFERROR(__xludf.DUMMYFUNCTION("""COMPUTED_VALUE"""),0.103308847602848) -> 0.10330885 | G40: =IFERROR(__xludf.DUMMYFUNCTION("""COMPUTED_VALUE"""),0.10204440072004) -> 0.1020444 | H40: =IFERROR(__xludf.DUMMYFUNCTION("""COMPUTED_VALUE"""),0.0745034484311485) -> 0.074503448 | I40: =IFERROR(__xludf.DUMMYFUNCTION("""COMPUTED_VALUE"""),0.0869418857625907) -> 0.086941886 | J40: =IFERROR(__xludf.DUMMYFUNCTION("""COMPUTED_VALUE"""),0.0870568354792096) -> 0.087056835 | K40: =IFERROR(__xludf.DUMMYFUNCTION("""COMPUTED_VALUE"""),0.0870568354792096) -> 0.087056835 | L40: =IFERROR(__xludf.DUMMYFUNCTION("""COMPUTED_VALUE"""),0.0790862081599875) -> 0.079086208 | M40: =IFERROR(__xludf.DUMMYFUNCTION("""COMPUTED_VALUE"""),0.080350655042796) -> 0.080350655 | N40: =IFERROR(__xludf.DUMMYFUNCTION("""COMPUTED_VALUE"""),4790.71011839089) -> 4790.7101 | O40: =IFERROR(__xludf.DUMMYFUNCTION("""COMPUTED_VALUE"""),1) -> 1 | P40: =IFERROR(__xludf.DUMMYFUNCTION("""COMPUTED_VALUE"""),76) -> 76 | Q40: =IFERROR(__xludf.DUMMYFUNCTION("""COMPUTED_VALUE"""),0) -> 0 | R40: =IFERROR(__xludf.DUMMYFUNCTION("""COMPUTED_VALUE"""),51231.6) -> 51231.6 | S40: =IFERROR(__xludf.DUMMYFUNCTION("""COMPUTED_VALUE"""),8719.2) -> 8719.2 | T40: =IFERROR(__xludf.DUMMYFUNCTION("""COMPUTED_VALUE"""),23764.4) -> 23764.4 | U40: =IFERROR(__xludf.DUMMYFUNCTION("""COMPUTED_VALUE"""),0) -> 0 | V40: =IFERROR(__xludf.DUMMYFUNCTION("""COMPUTED_VALUE"""),4173.4) -> 4173.4 | W40: =IFERROR(__xludf.DUMMYFUNCTION("""COMPUTED_VALUE"""),3794) -> 3794 | X40: =SUM(Q40:W40) -> 91682.6
A41: ABC 5 kg | B41: =IFERROR(__xludf.DUMMYFUNCTION("""COMPUTED_VALUE"""),0.0669778155176287) -> 0.066977816 | C41: =IFERROR(__xludf.DUMMYFUNCTION("""COMPUTED_VALUE"""),0.0652614335824934) -> 0.065261434 | D41: =IFERROR(__xludf.DUMMYFUNCTION("""COMPUTED_VALUE"""),0.0819248891202413) -> 0.081924889 | E41: =IFERROR(__xludf.DUMMYFUNCTION("""COMPUTED_VALUE"""),0.0996461832727322) -> 0.099646183 | F41: =IFERROR(__xludf.DUMMYFUNCTION("""COMPUTED_VALUE"""),0.100150076298148) -> 0.10015008 | G41: =IFERROR(__xludf.DUMMYFUNCTION("""COMPUTED_VALUE"""),0.0987344570187928) -> 0.098734457 | H41: =IFERROR(__xludf.DUMMYFUNCTION("""COMPUTED_VALUE"""),0.0795692614778467) -> 0.079569261 | I41: =IFERROR(__xludf.DUMMYFUNCTION("""COMPUTED_VALUE"""),0.0794428932919701) -> 0.079442893 | J41: =IFERROR(__xludf.DUMMYFUNCTION("""COMPUTED_VALUE"""),0.0806840028465543) -> 0.080684003 | K41: =IFERROR(__xludf.DUMMYFUNCTION("""COMPUTED_VALUE"""),0.0806840028465543) -> 0.080684003 | L41: =IFERROR(__xludf.DUMMYFUNCTION("""COMPUTED_VALUE"""),0.0818964917562743) -> 0.081896492 | M41: =IFERROR(__xludf.DUMMYFUNCTION("""COMPUTED_VALUE"""),0.0850284929707643) -> 0.085028493 | N41: =IFERROR(__xludf.DUMMYFUNCTION("""COMPUTED_VALUE"""),29139.3203107948) -> 29139.32 | O41: =IFERROR(__xludf.DUMMYFUNCTION("""COMPUTED_VALUE"""),1) -> 1 | P41: =IFERROR(__xludf.DUMMYFUNCTION("""COMPUTED_VALUE"""),446) -> 446 | Q41: =IFERROR(__xludf.DUMMYFUNCTION("""COMPUTED_VALUE"""),36760) -> 36760 | R41: =IFERROR(__xludf.DUMMYFUNCTION("""COMPUTED_VALUE"""),373689.5) -> 373689.5 | S41: =IFERROR(__xludf.DUMMYFUNCTION("""COMPUTED_VALUE"""),32472.3) -> 32472.3 | T41: =IFERROR(__xludf.DUMMYFUNCTION("""COMPUTED_VALUE"""),6552.8) -> 6552.8 | U41: =IFERROR(__xludf.DUMMYFUNCTION("""COMPUTED_VALUE"""),44086.3) -> 44086.3 | V41: =IFERROR(__xludf.DUMMYFUNCTION("""COMPUTED_VALUE"""),26680.3) -> 26680.3 | W41: =IFERROR(__xludf.DUMMYFUNCTION("""COMPUTED_VALUE"""),3289) -> 3289 | X41: =SUM(Q41:W41) -> 523530.2
A42: ABC 10 kg | B42: =IFERROR(__xludf.DUMMYFUNCTION("""COMPUTED_VALUE"""),0.0656624516770873) -> 0.065662452 | C42: =IFERROR(__xludf.DUMMYFUNCTION("""COMPUTED_VALUE"""),0.0656624516770873) -> 0.065662452 | D42: =IFERROR(__xludf.DUMMYFUNCTION("""COMPUTED_VALUE"""),0.0834634227222184) -> 0.083463423 | E42: =IFERROR(__xludf.DUMMYFUNCTION("""COMPUTED_VALUE"""),0.100292059397134) -> 0.10029206 | F42: =IFERROR(__xludf.DUMMYFUNCTION("""COMPUTED_VALUE"""),0.101604548245527) -> 0.10160455 | G42: =IFERROR(__xludf.DUMMYFUNCTION("""COMPUTED_VALUE"""),0.0984624354955731) -> 0.098462435 | H42: =IFERROR(__xludf.DUMMYFUNCTION("""COMPUTED_VALUE"""),0.0776078419879838) -> 0.077607842 | I42: =IFERROR(__xludf.DUMMYFUNCTION("""COMPUTED_VALUE"""),0.0788318405488818) -> 0.078831841 | J42: =IFERROR(__xludf.DUMMYFUNCTION("""COMPUTED_VALUE"""),0.0819739532988352) -> 0.081973953 | K42: =IFERROR(__xludf.DUMMYFUNCTION("""COMPUTED_VALUE"""),0.0819739532988352) -> 0.081973953 | L42: =IFERROR(__xludf.DUMMYFUNCTION("""COMPUTED_VALUE"""),0.0806614644504421) -> 0.080661464 | M42: =IFERROR(__xludf.DUMMYFUNCTION("""COMPUTED_VALUE"""),0.0838035772003955) -> 0.083803577 | N42: =IFERROR(__xludf.DUMMYFUNCTION("""COMPUTED_VALUE"""),1725.36955653994) -> 1725.3696 | O42: =IFERROR(__xludf.DUMMYFUNCTION("""COMPUTED_VALUE"""),1) -> 1 | P42: =IFERROR(__xludf.DUMMYFUNCTION("""COMPUTED_VALUE"""),28) -> 28 | Q42: =IFERROR(__xludf.DUMMYFUNCTION("""COMPUTED_VALUE"""),0) -> 0 | R42: =IFERROR(__xludf.DUMMYFUNCTION("""COMPUTED_VALUE"""),22903.5) -> 22903.5 | S42: =IFERROR(__xludf.DUMMYFUNCTION("""COMPUTED_VALUE"""),3490) -> 3490 | T42: =IFERROR(__xludf.DUMMYFUNCTION("""COMPUTED_VALUE"""),1572.7) -> 1572.7 | U42: =IFERROR(__xludf.DUMMYFUNCTION("""COMPUTED_VALUE"""),0) -> 0 | V42: =IFERROR(__xludf.DUMMYFUNCTION("""COMPUTED_VALUE"""),3566.9) -> 3566.9 | W42: =IFERROR(__xludf.DUMMYFUNCTION("""COMPUTED_VALUE"""),0) -> 0 | X42: =SUM(Q42:W42) -> 31533.1
A43: Agua 10 l | B43: =IFERROR(__xludf.DUMMYFUNCTION("""COMPUTED_VALUE"""),0.0671288961017088) -> 0.067128896 | C43: =IFERROR(__xludf.DUMMYFUNCTION("""COMPUTED_VALUE"""),0.0671288961017088) -> 0.067128896 | D43: =IFERROR(__xludf.DUMMYFUNCTION("""COMPUTED_VALUE"""),0.082960331994099) -> 0.082960332 | E43: =IFERROR(__xludf.DUMMYFUNCTION("""COMPUTED_VALUE"""),0.0994555948834204) -> 0.099455595 | F43: =IFERROR(__xludf.DUMMYFUNCTION("""COMPUTED_VALUE"""),0.100324801949947) -> 0.1003248 | G43: =IFERROR(__xludf.DUMMYFUNCTION("""COMPUTED_VALUE"""),0.0970172977837637) -> 0.097017298 | H43: =IFERROR(__xludf.DUMMYFUNCTION("""COMPUTED_VALUE"""),0.0783455208911489) -> 0.078345521 | I43: =IFERROR(__xludf.DUMMYFUNCTION("""COMPUTED_VALUE"""),0.078747564791717) -> 0.078747565 | J43: =IFERROR(__xludf.DUMMYFUNCTION("""COMPUTED_VALUE"""),0.0818305013673391) -> 0.081830501 | K43: =IFERROR(__xludf.DUMMYFUNCTION("""COMPUTED_VALUE"""),0.0818305013673391) -> 0.081830501 | L43: =IFERROR(__xludf.DUMMYFUNCTION("""COMPUTED_VALUE"""),0.0809612943008125) -> 0.080961294 | M43: =IFERROR(__xludf.DUMMYFUNCTION("""COMPUTED_VALUE"""),0.0842687984669957) -> 0.084268798 | N43: =IFERROR(__xludf.DUMMYFUNCTION("""COMPUTED_VALUE"""),2435.83311933763) -> 2435.8331 | O43: =IFERROR(__xludf.DUMMYFUNCTION("""COMPUTED_VALUE"""),1) -> 1 | P43: =IFERROR(__xludf.DUMMYFUNCTION("""COMPUTED_VALUE"""),39) -> 39 | Q43: =IFERROR(__xludf.DUMMYFUNCTION("""COMPUTED_VALUE"""),0) -> 0 | R43: =IFERROR(__xludf.DUMMYFUNCTION("""COMPUTED_VALUE"""),28930.8) -> 28930.8 | S43: =IFERROR(__xludf.DUMMYFUNCTION("""COMPUTED_VALUE"""),2999.8) -> 2999.8 | T43: =IFERROR(__xludf.DUMMYFUNCTION("""COMPUTED_VALUE"""),1048.4) -> 1048.4 | U43: =IFERROR(__xludf.DUMMYFUNCTION("""COMPUTED_VALUE"""),4377.3) -> 4377.3 | V43: =IFERROR(__xludf.DUMMYFUNCTION("""COMPUTED_VALUE"""),5096) -> 5096 | W43: =IFERROR(__xludf.DUMMYFUNCTION("""COMPUTED_VALUE"""),346) -> 346 | X43: =SUM(Q43:W43) -> 42798.3
A44: AFFF 10 l | B44: =IFERROR(__xludf.DUMMYFUNCTION("""COMPUTED_VALUE"""),0.0833333333333333) -> 0.083333333 | C44: =IFERROR(__xludf.DUMMYFUNCTION("""COMPUTED_VALUE"""),0.0833333333333333) -> 0.083333333 | D44: =IFERROR(__xludf.DUMMYFUNCTION("""COMPUTED_VALUE"""),0.0833333333333333) -> 0.083333333 | E44: =IFERROR(__xludf.DUMMYFUNCTION("""COMPUTED_VALUE"""),0.0833333333333333) -> 0.083333333 | F44: =IFERROR(__xludf.DUMMYFUNCTION("""COMPUTED_VALUE"""),0.0833333333333333) -> 0.083333333 | G44: =IFERROR(__xludf.DUMMYFUNCTION("""COMPUTED_VALUE"""),0.0833333333333333) -> 0.083333333 | H44: =IFERROR(__xludf.DUMMYFUNCTION("""COMPUTED_VALUE"""),0.0833333333333333) -> 0.083333333 | I44: =IFERROR(__xludf.DUMMYFUNCTION("""COMPUTED_VALUE"""),0.0833333333333333) -> 0.083333333 | ... M44: =IFERROR(__xludf.DUMMYFUNCTION("""COMPUTED_VALUE"""),0.0833333333333333) -> 0.083333333 | N44: =IFERROR(__xludf.DUMMYFUNCTION("""COMPUTED_VALUE"""),462.458588756731) -> 462.45859 | O44: =IFERROR(__xludf.DUMMYFUNCTION("""COMPUTED_VALUE"""),1) -> 1 | P44: =IFERROR(__xludf.DUMMYFUNCTION("""COMPUTED_VALUE"""),6) -> 6 | Q44: =IFERROR(__xludf.DUMMYFUNCTION("""COMPUTED_VALUE"""),0) -> 0 | R44: =IFERROR(__xludf.DUMMYFUNCTION("""COMPUTED_VALUE"""),0) -> 0 | S44: =IFERROR(__xludf.DUMMYFUNCTION("""COMPUTED_VALUE"""),0) -> 0 | T44: =IFERROR(__xludf.DUMMYFUNCTION("""COMPUTED_VALUE"""),0) -> 0 | U44: =IFERROR(__xludf.DUMMYFUNCTION("""COMPUTED_VALUE"""),6232.7) -> 6232.7 | V44: =IFERROR(__xludf.DUMMYFUNCTION("""COMPUTED_VALUE"""),0) -> 0 | W44: =IFERROR(__xludf.DUMMYFUNCTION("""COMPUTED_VALUE"""),0) -> 0 | X44: =SUM(Q44:W44) -> 6232.7
A45: AFFF 50 l s/ruedas | B45: =IFERROR(__xludf.DUMMYFUNCTION("""COMPUTED_VALUE"""),0.0833333333333333) -> 0.083333333 | C45: =IFERROR(__xludf.DUMMYFUNCTION("""COMPUTED_VALUE"""),0.0833333333333333) -> 0.083333333 | D45: =IFERROR(__xludf.DUMMYFUNCTION("""COMPUTED_VALUE"""),0.0833333333333333) -> 0.083333333 | E45: =IFERROR(__xludf.DUMMYFUNCTION("""COMPUTED_VALUE"""),0.0833333333333333) -> 0.083333333 | F45: =IFERROR(__xludf.DUMMYFUNCTION("""COMPUTED_VALUE"""),0.0833333333333333) -> 0.083333333 | G45: =IFERROR(__xludf.DUMMYFUNCTION("""COMPUTED_VALUE"""),0.0833333333333333) -> 0.083333333 | H45: =IFERROR(__xludf.DUMMYFUNCTION("""COMPUTED_VALUE"""),0.0833333333333333) -> 0.083333333 | I45: =IFERROR(__xludf.DUMMYFUNCTION("""COMPUTED_VALUE"""),0.0833333333333333) -> 0.083333333 | ... M45: =IFERROR(__xludf.DUMMYFUNCTION("""COMPUTED_VALUE"""),0.0833333333333333) -> 0.083333333 | N45: =IFERROR(__xludf.DUMMYFUNCTION("""COMPUTED_VALUE"""),241.066833405312) -> 241.06683 | O45: =IFERROR(__xludf.DUMMYFUNCTION("""COMPUTED_VALUE"""),1) -> 1 | P45: =IFERROR(__xludf.DUMMYFUNCTION("""COMPUTED_VALUE"""),4) -> 4 | Q45: =IFERROR(__xludf.DUMMYFUNCTION("""COMPUTED_VALUE"""),0) -> 0 | R45: =IFERROR(__xludf.DUMMYFUNCTION("""COMPUTED_VALUE"""),0) -> 0 | S45: =IFERROR(__xludf.DUMMYFUNCTION("""COMPUTED_VALUE"""),0) -> 0 | T45: =IFERROR(__xludf.DUMMYFUNCTION("""COMPUTED_VALUE"""),0) -> 0 | U45: =IFERROR(__xludf.DUMMYFUNCTION("""COMPUTED_VALUE"""),3220.9) -> 3220.9 | V45: =IFERROR(__xludf.DUMMYFUNCTION("""COMPUTED_VALUE"""),0) -> 0 | W45: =IFERROR(__xludf.DUMMYFUNCTION("""COMPUTED_VALUE"""),0) -> 0 | X45: =SUM(Q45:W45) -> 3220.9
A46: BC 5 kg | B46: =IFERROR(__xludf.DUMMYFUNCTION("""COMPUTED_VALUE"""),0.0833333333333333) -> 0.083333333 | C46: =IFERROR(__xludf.DUMMYFUNCTION("""COMPUTED_VALUE"""),0.0833333333333333) -> 0.083333333 | D46: =IFERROR(__xludf.DUMMYFUNCTION("""COMPUTED_VALUE"""),0.0833333333333333) -> 0.083333333 | E46: =IFERROR(__xludf.DUMMYFUNCTION("""COMPUTED_VALUE"""),0.0833333333333333) -> 0.083333333 | F46: =IFERROR(__xludf.DUMMYFUNCTION("""COMPUTED_VALUE"""),0.0833333333333333) -> 0.083333333 | G46: =IFERROR(__xludf.DUMMYFUNCTION("""COMPUTED_VALUE"""),0.0833333333333333) -> 0.083333333 | H46: =IFERROR(__xludf.DUMMYFUNCTION("""COMPUTED_VALUE"""),0.0833333333333333) -> 0.083333333 | I46: =IFERROR(__xludf.DUMMYFUNCTION("""COMPUTED_VALUE"""),0.0833333333333333) -> 0.083333333 | ... M46: =IFERROR(__xludf.DUMMYFUNCTION("""COMPUTED_VALUE"""),0.0833333333333333) -> 0.083333333 | N46: =IFERROR(__xludf.DUMMYFUNCTION("""COMPUTED_VALUE"""),139.356355954645) -> 139.35636 | O46: =IFERROR(__xludf.DUMMYFUNCTION("""COMPUTED_VALUE"""),1) -> 1 | P46: =IFERROR(__xludf.DUMMYFUNCTION("""COMPUTED_VALUE"""),2) -> 2 | Q46: =IFERROR(__xludf.DUMMYFUNCTION("""COMPUTED_VALUE"""),0) -> 0 | R46: =IFERROR(__xludf.DUMMYFUNCTION("""COMPUTED_VALUE"""),0) -> 0 | S46: =IFERROR(__xludf.DUMMYFUNCTION("""COMPUTED_VALUE"""),0) -> 0 | T46: =IFERROR(__xludf.DUMMYFUNCTION("""COMPUTED_VALUE"""),0) -> 0 | U46: =IFERROR(__xludf.DUMMYFUNCTION("""COMPUTED_VALUE"""),1816.2) -> 1816.2 | V46: =IFERROR(__xludf.DUMMYFUNCTION("""COMPUTED_VALUE"""),0) -> 0 | W46: =IFERROR(__xludf.DUMMYFUNCTION("""COMPUTED_VALUE"""),0) -> 0 | X46: =SUM(Q46:W46) -> 1816.2
A47: Sales K 6 l | B47: =IFERROR(__xludf.DUMMYFUNCTION("""COMPUTED_VALUE"""),0.0693955234457278) -> 0.069395523 | C47: =IFERROR(__xludf.DUMMYFUNCTION("""COMPUTED_VALUE"""),0.0693955234457278) -> 0.069395523 | D47: =IFERROR(__xludf.DUMMYFUNCTION("""COMPUTED_VALUE"""),0.0840431757641277) -> 0.084043176 | E47: =IFERROR(__xludf.DUMMYFUNCTION("""COMPUTED_VALUE"""),0.0941202036639783) -> 0.094120204 | F47: =IFERROR(__xludf.DUMMYFUNCTION("""COMPUTED_VALUE"""),0.0974702272576739) -> 0.097470227 | G47: =IFERROR(__xludf.DUMMYFUNCTION("""COMPUTED_VALUE"""),0.095318136848291) -> 0.095318137 | H47: =IFERROR(__xludf.DUMMYFUNCTION("""COMPUTED_VALUE"""),0.076854716143931) -> 0.076854716 | I47: =IFERROR(__xludf.DUMMYFUNCTION("""COMPUTED_VALUE"""),0.0818684177142039) -> 0.081868418 | J47: =IFERROR(__xludf.DUMMYFUNCTION("""COMPUTED_VALUE"""),0.0840205081235868) -> 0.084020508 | K47: =IFERROR(__xludf.DUMMYFUNCTION("""COMPUTED_VALUE"""),0.0840205081235868) -> 0.084020508 | L47: =IFERROR(__xludf.DUMMYFUNCTION("""COMPUTED_VALUE"""),0.0806704845298912) -> 0.080670485 | M47: =IFERROR(__xludf.DUMMYFUNCTION("""COMPUTED_VALUE"""),0.082822574939274) -> 0.082822575 | N47: =IFERROR(__xludf.DUMMYFUNCTION("""COMPUTED_VALUE"""),1201.24282190818) -> 1201.2428 | O47: =IFERROR(__xludf.DUMMYFUNCTION("""COMPUTED_VALUE"""),1) -> 1 | P47: =IFERROR(__xludf.DUMMYFUNCTION("""COMPUTED_VALUE"""),19) -> 19 | Q47: =IFERROR(__xludf.DUMMYFUNCTION("""COMPUTED_VALUE"""),0) -> 0 | R47: =IFERROR(__xludf.DUMMYFUNCTION("""COMPUTED_VALUE"""),10246.3) -> 10246.3 | S47: =IFERROR(__xludf.DUMMYFUNCTION("""COMPUTED_VALUE"""),2743) -> 2743 | T47: =IFERROR(__xludf.DUMMYFUNCTION("""COMPUTED_VALUE"""),2621.1) -> 2621.1 | U47: =IFERROR(__xludf.DUMMYFUNCTION("""COMPUTED_VALUE"""),3384.2) -> 3384.2 | V47: =IFERROR(__xludf.DUMMYFUNCTION("""COMPUTED_VALUE"""),1595.2) -> 1595.2 | W47: =IFERROR(__xludf.DUMMYFUNCTION("""COMPUTED_VALUE"""),0) -> 0 | X47: =SUM(Q47:W47) -> 20589.8
A48: CO₂ 2 kg | B48: =IFERROR(__xludf.DUMMYFUNCTION("""COMPUTED_VALUE"""),0.0623734752667158) -> 0.062373475 | C48: =IFERROR(__xludf.DUMMYFUNCTION("""COMPUTED_VALUE"""),0.0623734752667158) -> 0.062373475 | D48: =IFERROR(__xludf.DUMMYFUNCTION("""COMPUTED_VALUE"""),0.0832322896847601) -> 0.08323229 | E48: =IFERROR(__xludf.DUMMYFUNCTION("""COMPUTED_VALUE"""),0.102381291624983) -> 0.10238129 | F48: =IFERROR(__xludf.DUMMYFUNCTION("""COMPUTED_VALUE"""),0.10297405651463) -> 0.10297406 | G48: =IFERROR(__xludf.DUMMYFUNCTION("""COMPUTED_VALUE"""),0.101541503044586) -> 0.1015415 | H48: =IFERROR(__xludf.DUMMYFUNCTION("""COMPUTED_VALUE"""),0.0799321707959588) -> 0.079932171 | I48: =IFERROR(__xludf.DUMMYFUNCTION("""COMPUTED_VALUE"""),0.0798429000461445) -> 0.0798429 | J48: =IFERROR(__xludf.DUMMYFUNCTION("""COMPUTED_VALUE"""),0.081275453516189) -> 0.081275454 | K48: =IFERROR(__xludf.DUMMYFUNCTION("""COMPUTED_VALUE"""),0.081275453516189) -> 0.081275454 | L48: =IFERROR(__xludf.DUMMYFUNCTION("""COMPUTED_VALUE"""),0.0806826886265415) -> 0.080682689 | M48: =IFERROR(__xludf.DUMMYFUNCTION("""COMPUTED_VALUE"""),0.0821152420965861) -> 0.082115242 | N48: =IFERROR(__xludf.DUMMYFUNCTION("""COMPUTED_VALUE"""),6552.91332717418) -> 6552.9133 | O48: =IFERROR(__xludf.DUMMYFUNCTION("""COMPUTED_VALUE"""),1) -> 1 | P48: =IFERROR(__xludf.DUMMYFUNCTION("""COMPUTED_VALUE"""),103) -> 103 | Q48: =IFERROR(__xludf.DUMMYFUNCTION("""COMPUTED_VALUE"""),0) -> 0 | R48: =IFERROR(__xludf.DUMMYFUNCTION("""COMPUTED_VALUE"""),93422.4) -> 93422.4 | S48: =IFERROR(__xludf.DUMMYFUNCTION("""COMPUTED_VALUE"""),11718.9) -> 11718.9 | T48: =IFERROR(__xludf.DUMMYFUNCTION("""COMPUTED_VALUE"""),2621.1) -> 2621.1 | U48: =IFERROR(__xludf.DUMMYFUNCTION("""COMPUTED_VALUE"""),2600.2) -> 2600.2 | V48: =IFERROR(__xludf.DUMMYFUNCTION("""COMPUTED_VALUE"""),6001.1) -> 6001.1 | W48: =IFERROR(__xludf.DUMMYFUNCTION("""COMPUTED_VALUE"""),0) -> 0 | X48: =SUM(Q48:W48) -> 116363.7
A49: CO₂ 5 kg | B49: =IFERROR(__xludf.DUMMYFUNCTION("""COMPUTED_VALUE"""),0.0758899515991334) -> 0.075889952 | C49: =IFERROR(__xludf.DUMMYFUNCTION("""COMPUTED_VALUE"""),0.0758899515991334) -> 0.075889952 | D49: =IFERROR(__xludf.DUMMYFUNCTION("""COMPUTED_VALUE"""),0.082635648810499) -> 0.082635649 | E49: =IFERROR(__xludf.DUMMYFUNCTION("""COMPUTED_VALUE"""),0.0919604223371936) -> 0.091960422 | F49: =IFERROR(__xludf.DUMMYFUNCTION("""COMPUTED_VALUE"""),0.094065383152575) -> 0.094065383 | G49: =IFERROR(__xludf.DUMMYFUNCTION("""COMPUTED_VALUE"""),0.0890054041756688) -> 0.089005404 | H49: =IFERROR(__xludf.DUMMYFUNCTION("""COMPUTED_VALUE"""),0.0776256551320905) -> 0.077625655 | I49: =IFERROR(__xludf.DUMMYFUNCTION("""COMPUTED_VALUE"""),0.0793046888027784) -> 0.079304689 | J49: =IFERROR(__xludf.DUMMYFUNCTION("""COMPUTED_VALUE"""),0.0831932092611961) -> 0.083193209 | K49: =IFERROR(__xludf.DUMMYFUNCTION("""COMPUTED_VALUE"""),0.0831932092611961) -> 0.083193209 | L49: =IFERROR(__xludf.DUMMYFUNCTION("""COMPUTED_VALUE"""),0.0810882484458147) -> 0.081088248 | M49: =IFERROR(__xludf.DUMMYFUNCTION("""COMPUTED_VALUE"""),0.0861482274227209) -> 0.086148227 | N49: =IFERROR(__xludf.DUMMYFUNCTION("""COMPUTED_VALUE"""),2239.47576029921) -> 2239.4758 | O49: =IFERROR(__xludf.DUMMYFUNCTION("""COMPUTED_VALUE"""),1) -> 1 | P49: =IFERROR(__xludf.DUMMYFUNCTION("""COMPUTED_VALUE"""),34) -> 34 | Q49: =IFERROR(__xludf.DUMMYFUNCTION("""COMPUTED_VALUE"""),0) -> 0 | R49: =IFERROR(__xludf.DUMMYFUNCTION("""COMPUTED_VALUE"""),13260) -> 13260 | S49: =IFERROR(__xludf.DUMMYFUNCTION("""COMPUTED_VALUE"""),548.6) -> 548.6 | T49: =IFERROR(__xludf.DUMMYFUNCTION("""COMPUTED_VALUE"""),1310.5) -> 1310.5 | U49: =IFERROR(__xludf.DUMMYFUNCTION("""COMPUTED_VALUE"""),13536.8) -> 13536.8 | V49: =IFERROR(__xludf.DUMMYFUNCTION("""COMPUTED_VALUE"""),6729.6) -> 6729.6 | W49: =IFERROR(__xludf.DUMMYFUNCTION("""COMPUTED_VALUE"""),1558) -> 1558 | X49: =SUM(Q49:W49) -> 36943.5
A50: HCFC/HFC 5 kg | B50: =IFERROR(__xludf.DUMMYFUNCTION("""COMPUTED_VALUE"""),0.0909796762566006) -> 0.090979676 | C50: =IFERROR(__xludf.DUMMYFUNCTION("""COMPUTED_VALUE"""),0.0909796762566006) -> 0.090979676 | D50: =IFERROR(__xludf.DUMMYFUNCTION("""COMPUTED_VALUE"""),0.0833333333333333) -> 0.083333333 | E50: =IFERROR(__xludf.DUMMYFUNCTION("""COMPUTED_VALUE"""),0.0833333333333333) -> 0.083333333 | F50: =IFERROR(__xludf.DUMMYFUNCTION("""COMPUTED_VALUE"""),0.0833333333333333) -> 0.083333333 | G50: =IFERROR(__xludf.DUMMYFUNCTION("""COMPUTED_VALUE"""),0.0756869904100661) -> 0.07568699 | H50: =IFERROR(__xludf.DUMMYFUNCTION("""COMPUTED_VALUE"""),0.0756869904100661) -> 0.07568699 | I50: =IFERROR(__xludf.DUMMYFUNCTION("""COMPUTED_VALUE"""),0.0756869904100661) -> 0.07568699 | J50: =IFERROR(__xludf.DUMMYFUNCTION("""COMPUTED_VALUE"""),0.0833333333333333) -> 0.083333333 | K50: =IFERROR(__xludf.DUMMYFUNCTION("""COMPUTED_VALUE"""),0.0833333333333333) -> 0.083333333 | L50: =IFERROR(__xludf.DUMMYFUNCTION("""COMPUTED_VALUE"""),0.0833333333333333) -> 0.083333333 | M50: =IFERROR(__xludf.DUMMYFUNCTION("""COMPUTED_VALUE"""),0.0909796762566006) -> 0.090979676 | N50: =IFERROR(__xludf.DUMMYFUNCTION("""COMPUTED_VALUE"""),366.61985757759) -> 366.61986 | O50: =IFERROR(__xludf.DUMMYFUNCTION("""COMPUTED_VALUE"""),1) -> 1 | P50: =IFERROR(__xludf.DUMMYFUNCTION("""COMPUTED_VALUE"""),6) -> 6 | Q50: =IFERROR(__xludf.DUMMYFUNCTION("""COMPUTED_VALUE"""),0) -> 0 | R50: =IFERROR(__xludf.DUMMYFUNCTION("""COMPUTED_VALUE"""),0) -> 0 | S50: =IFERROR(__xludf.DUMMYFUNCTION("""COMPUTED_VALUE"""),0) -> 0 | T50: =IFERROR(__xludf.DUMMYFUNCTION("""COMPUTED_VALUE"""),0) -> 0 | U50: =IFERROR(__xludf.DUMMYFUNCTION("""COMPUTED_VALUE"""),3632.5) -> 3632.5 | V50: =IFERROR(__xludf.DUMMYFUNCTION("""COMPUTED_VALUE"""),1379.7) -> 1379.7 | W50: =IFERROR(__xludf.DUMMYFUNCTION("""COMPUTED_VALUE"""),0) -> 0 | X50: =SUM(Q50:W50) -> 5012.2
A51: Clase D 9 l | B51: =IFERROR(__xludf.DUMMYFUNCTION("""COMPUTED_VALUE"""),0.0833333333333333) -> 0.083333333 | C51: =IFERROR(__xludf.DUMMYFUNCTION("""COMPUTED_VALUE"""),0.0833333333333333) -> 0.083333333 | D51: =IFERROR(__xludf.DUMMYFUNCTION("""COMPUTED_VALUE"""),0.0833333333333333) -> 0.083333333 | E51: =IFERROR(__xludf.DUMMYFUNCTION("""COMPUTED_VALUE"""),0.0833333333333333) -> 0.083333333 | F51: =IFERROR(__xludf.DUMMYFUNCTION("""COMPUTED_VALUE"""),0.0833333333333333) -> 0.083333333 | G51: =IFERROR(__xludf.DUMMYFUNCTION("""COMPUTED_VALUE"""),0.0833333333333333) -> 0.083333333 | H51: =IFERROR(__xludf.DUMMYFUNCTION("""COMPUTED_VALUE"""),0.0833333333333333) -> 0.083333333 | I51: =IFERROR(__xludf.DUMMYFUNCTION("""COMPUTED_VALUE"""),0.0833333333333333) -> 0.083333333 | ... M51: =IFERROR(__xludf.DUMMYFUNCTION("""COMPUTED_VALUE"""),0.0833333333333333) -> 0.083333333 | N51: =IFERROR(__xludf.DUMMYFUNCTION("""COMPUTED_VALUE"""),125.86907204172) -> 125.86907 | O51: =IFERROR(__xludf.DUMMYFUNCTION("""COMPUTED_VALUE"""),1) -> 1 | P51: =IFERROR(__xludf.DUMMYFUNCTION("""COMPUTED_VALUE"""),2) -> 2 | Q51: =IFERROR(__xludf.DUMMYFUNCTION("""COMPUTED_VALUE"""),0) -> 0 | R51: =IFERROR(__xludf.DUMMYFUNCTION("""COMPUTED_VALUE"""),0) -> 0 | S51: =IFERROR(__xludf.DUMMYFUNCTION("""COMPUTED_VALUE"""),0) -> 0 | T51: =IFERROR(__xludf.DUMMYFUNCTION("""COMPUTED_VALUE"""),0) -> 0 | U51: =IFERROR(__xludf.DUMMYFUNCTION("""COMPUTED_VALUE"""),1568) -> 1568 | V51: =IFERROR(__xludf.DUMMYFUNCTION("""COMPUTED_VALUE"""),0) -> 0 | W51: =IFERROR(__xludf.DUMMYFUNCTION("""COMPUTED_VALUE"""),0) -> 0 | X51: =SUM(Q51:W51) -> 1568
A52: ABC 25 kg s/ruedas | B52: =IFERROR(__xludf.DUMMYFUNCTION("""COMPUTED_VALUE"""),0.0738143198706873) -> 0.07381432 | C52: =IFERROR(__xludf.DUMMYFUNCTION("""COMPUTED_VALUE"""),0.0738143198706873) -> 0.07381432 | D52: =IFERROR(__xludf.DUMMYFUNCTION("""COMPUTED_VALUE"""),0.0826227624746291) -> 0.082622762 | E52: =IFERROR(__xludf.DUMMYFUNCTION("""COMPUTED_VALUE"""),0.0945064091827231) -> 0.094506409 | F52: =IFERROR(__xludf.DUMMYFUNCTION("""COMPUTED_VALUE"""),0.0952134923111048) -> 0.095213492 | G52: =IFERROR(__xludf.DUMMYFUNCTION("""COMPUTED_VALUE"""),0.0907950767238501) -> 0.090795077 | H52: =IFERROR(__xludf.DUMMYFUNCTION("""COMPUTED_VALUE"""),0.0771791995816322) -> 0.0771792 | I52: =IFERROR(__xludf.DUMMYFUNCTION("""COMPUTED_VALUE"""),0.0782753016610352) -> 0.078275302 | J52: =IFERROR(__xludf.DUMMYFUNCTION("""COMPUTED_VALUE"""),0.0826937172482899) -> 0.082693717 | K52: =IFERROR(__xludf.DUMMYFUNCTION("""COMPUTED_VALUE"""),0.0826937172482899) -> 0.082693717 | L52: =IFERROR(__xludf.DUMMYFUNCTION("""COMPUTED_VALUE"""),0.0819866341199082) -> 0.081986634 | M52: =IFERROR(__xludf.DUMMYFUNCTION("""COMPUTED_VALUE"""),0.0864050497071629) -> 0.08640505 | N52: =IFERROR(__xludf.DUMMYFUNCTION("""COMPUTED_VALUE"""),300.325058646191) -> 300.32506 | O52: =IFERROR(__xludf.DUMMYFUNCTION("""COMPUTED_VALUE"""),1) -> 1 | P52: =IFERROR(__xludf.DUMMYFUNCTION("""COMPUTED_VALUE"""),5) -> 5 | Q52: =IFERROR(__xludf.DUMMYFUNCTION("""COMPUTED_VALUE"""),0) -> 0 | R52: =IFERROR(__xludf.DUMMYFUNCTION("""COMPUTED_VALUE"""),2260.2) -> 2260.2 | S52: =IFERROR(__xludf.DUMMYFUNCTION("""COMPUTED_VALUE"""),122.6) -> 122.6 | T52: =IFERROR(__xludf.DUMMYFUNCTION("""COMPUTED_VALUE"""),131.1) -> 131.1 | U52: =IFERROR(__xludf.DUMMYFUNCTION("""COMPUTED_VALUE"""),1589.2) -> 1589.2 | V52: =IFERROR(__xludf.DUMMYFUNCTION("""COMPUTED_VALUE"""),776.1) -> 776.1 | W52: =IFERROR(__xludf.DUMMYFUNCTION("""COMPUTED_VALUE"""),0) -> 0 | X52: =SUM(Q52:W52) -> 4879.2
A53: ABC 50 kg s/ruedas | B53: =IFERROR(__xludf.DUMMYFUNCTION("""COMPUTED_VALUE"""),0.0738141230528446) -> 0.073814123 | C53: =IFERROR(__xludf.DUMMYFUNCTION("""COMPUTED_VALUE"""),0.0738141230528446) -> 0.073814123 | D53: =IFERROR(__xludf.DUMMYFUNCTION("""COMPUTED_VALUE"""),0.0826225891766349) -> 0.082622589 | E53: =IFERROR(__xludf.DUMMYFUNCTION("""COMPUTED_VALUE"""),0.0945068249706181) -> 0.094506825 | F53: =IFERROR(__xludf.DUMMYFUNCTION("""COMPUTED_VALUE"""),0.0952136231283829) -> 0.095213623 | G53: =IFERROR(__xludf.DUMMYFUNCTION("""COMPUTED_VALUE"""),0.0907952016698743) -> 0.090795202 | H53: =IFERROR(__xludf.DUMMYFUNCTION("""COMPUTED_VALUE"""),0.077179442745086) -> 0.077179443 | I53: =IFERROR(__xludf.DUMMYFUNCTION("""COMPUTED_VALUE"""),0.0782751122453402) -> 0.078275112 | J53: =IFERROR(__xludf.DUMMYFUNCTION("""COMPUTED_VALUE"""),0.0826935337038488) -> 0.082693534 | K53: =IFERROR(__xludf.DUMMYFUNCTION("""COMPUTED_VALUE"""),0.0826935337038488) -> 0.082693534 | L53: =IFERROR(__xludf.DUMMYFUNCTION("""COMPUTED_VALUE"""),0.081986735546084) -> 0.081986736 | M53: =IFERROR(__xludf.DUMMYFUNCTION("""COMPUTED_VALUE"""),0.0864051570045927) -> 0.086405157 | N53: =IFERROR(__xludf.DUMMYFUNCTION("""COMPUTED_VALUE"""),660.71512861809) -> 660.71513 | O53: =IFERROR(__xludf.DUMMYFUNCTION("""COMPUTED_VALUE"""),1) -> 1 | P53: =IFERROR(__xludf.DUMMYFUNCTION("""COMPUTED_VALUE"""),10) -> 10 | Q53: =IFERROR(__xludf.DUMMYFUNCTION("""COMPUTED_VALUE"""),0) -> 0 | R53: =IFERROR(__xludf.DUMMYFUNCTION("""COMPUTED_VALUE"""),4972.5) -> 4972.5 | S53: =IFERROR(__xludf.DUMMYFUNCTION("""COMPUTED_VALUE"""),269.6) -> 269.6 | T53: =IFERROR(__xludf.DUMMYFUNCTION("""COMPUTED_VALUE"""),288.3) -> 288.3 | U53: =IFERROR(__xludf.DUMMYFUNCTION("""COMPUTED_VALUE"""),3496.3) -> 3496.3 | V53: =IFERROR(__xludf.DUMMYFUNCTION("""COMPUTED_VALUE"""),1707.4) -> 1707.4 | W53: =IFERROR(__xludf.DUMMYFUNCTION("""COMPUTED_VALUE"""),0) -> 0 | X53: =SUM(Q53:W53) -> 10734.1
A54: ABC 70 kg s/ruedas | B54: =IFERROR(__xludf.DUMMYFUNCTION("""COMPUTED_VALUE"""),0.0738134657732333) -> 0.073813466 | C54: =IFERROR(__xludf.DUMMYFUNCTION("""COMPUTED_VALUE"""),0.0738134657732333) -> 0.073813466 | D54: =IFERROR(__xludf.DUMMYFUNCTION("""COMPUTED_VALUE"""),0.0826224083229981) -> 0.082622408 | E54: =IFERROR(__xludf.DUMMYFUNCTION("""COMPUTED_VALUE"""),0.0945072087101559) -> 0.094507209 | F54: =IFERROR(__xludf.DUMMYFUNCTION("""COMPUTED_VALUE"""),0.0952140122277676) -> 0.095214012 | G54: =IFERROR(__xludf.DUMMYFUNCTION("""COMPUTED_VALUE"""),0.0907957098996484) -> 0.09079571 | H54: =IFERROR(__xludf.DUMMYFUNCTION("""COMPUTED_VALUE"""),0.0771794819907101) -> 0.077179482 | I54: =IFERROR(__xludf.DUMMYFUNCTION("""COMPUTED_VALUE"""),0.0782752685393762) -> 0.078275269 | J54: =IFERROR(__xludf.DUMMYFUNCTION("""COMPUTED_VALUE"""),0.0826935708674953) -> 0.082693571 | K54: =IFERROR(__xludf.DUMMYFUNCTION("""COMPUTED_VALUE"""),0.0826935708674953) -> 0.082693571 | L54: =IFERROR(__xludf.DUMMYFUNCTION("""COMPUTED_VALUE"""),0.0819867673498837) -> 0.081986767 | M54: =IFERROR(__xludf.DUMMYFUNCTION("""COMPUTED_VALUE"""),0.0864050696780028) -> 0.08640507 | N54: =IFERROR(__xludf.DUMMYFUNCTION("""COMPUTED_VALUE"""),144.156028161701) -> 144.15603 | O54: =IFERROR(__xludf.DUMMYFUNCTION("""COMPUTED_VALUE"""),1) -> 1 | P54: =IFERROR(__xludf.DUMMYFUNCTION("""COMPUTED_VALUE"""),3) -> 3 | Q54: =IFERROR(__xludf.DUMMYFUNCTION("""COMPUTED_VALUE"""),0) -> 0 | R54: =IFERROR(__xludf.DUMMYFUNCTION("""COMPUTED_VALUE"""),1084.9) -> 1084.9 | S54: =IFERROR(__xludf.DUMMYFUNCTION("""COMPUTED_VALUE"""),58.8) -> 58.8 | T54: =IFERROR(__xludf.DUMMYFUNCTION("""COMPUTED_VALUE"""),62.9) -> 62.9 | U54: =IFERROR(__xludf.DUMMYFUNCTION("""COMPUTED_VALUE"""),762.8) -> 762.8 | V54: =IFERROR(__xludf.DUMMYFUNCTION("""COMPUTED_VALUE"""),372.5) -> 372.5 | W54: =IFERROR(__xludf.DUMMYFUNCTION("""COMPUTED_VALUE"""),0) -> 0 | X54: =SUM(Q54:W54) -> 2341.9
A55: ABC 100 kg s/ruedas | B55: =IFERROR(__xludf.DUMMYFUNCTION("""COMPUTED_VALUE"""),0.0738124965393579) -> 0.073812497 | C55: =IFERROR(__xludf.DUMMYFUNCTION("""COMPUTED_VALUE"""),0.0738124965393579) -> 0.073812497 | D55: =IFERROR(__xludf.DUMMYFUNCTION("""COMPUTED_VALUE"""),0.0826224235220467) -> 0.082622424 | E55: =IFERROR(__xludf.DUMMYFUNCTION("""COMPUTED_VALUE"""),0.0945083084729547) -> 0.094508308 | F55: =IFERROR(__xludf.DUMMYFUNCTION("""COMPUTED_VALUE"""),0.0952145803016424) -> 0.09521458 | G55: =IFERROR(__xludf.DUMMYFUNCTION("""COMPUTED_VALUE"""),0.0907966823883564) -> 0.090796682 | H55: =IFERROR(__xludf.DUMMYFUNCTION("""COMPUTED_VALUE"""),0.0771804197218833) -> 0.07718042 | I55: =IFERROR(__xludf.DUMMYFUNCTION("""COMPUTED_VALUE"""),0.0782751293210692) -> 0.078275129 | J55: =IFERROR(__xludf.DUMMYFUNCTION("""COMPUTED_VALUE"""),0.0826930272343553) -> 0.082693027 | K55: =IFERROR(__xludf.DUMMYFUNCTION("""COMPUTED_VALUE"""),0.0826930272343553) -> 0.082693027 | L55: =IFERROR(__xludf.DUMMYFUNCTION("""COMPUTED_VALUE"""),0.0819867554056675) -> 0.081986755 | M55: =IFERROR(__xludf.DUMMYFUNCTION("""COMPUTED_VALUE"""),0.0864046533189536) -> 0.086404653 | N55: =IFERROR(__xludf.DUMMYFUNCTION("""COMPUTED_VALUE"""),96.1040185823099) -> 96.104019 | O55: =IFERROR(__xludf.DUMMYFUNCTION("""COMPUTED_VALUE"""),1) -> 1 | P55: =IFERROR(__xludf.DUMMYFUNCTION("""COMPUTED_VALUE"""),2) -> 2 | Q55: =IFERROR(__xludf.DUMMYFUNCTION("""COMPUTED_VALUE"""),0) -> 0 | R55: =IFERROR(__xludf.DUMMYFUNCTION("""COMPUTED_VALUE"""),723.3) -> 723.3 | S55: =IFERROR(__xludf.DUMMYFUNCTION("""COMPUTED_VALUE"""),39.2) -> 39.2 | T55: =IFERROR(__xludf.DUMMYFUNCTION("""COMPUTED_VALUE"""),41.9) -> 41.9 | U55: =IFERROR(__xludf.DUMMYFUNCTION("""COMPUTED_VALUE"""),508.5) -> 508.5 | V55: =IFERROR(__xludf.DUMMYFUNCTION("""COMPUTED_VALUE"""),248.3) -> 248.3 | W55: =IFERROR(__xludf.DUMMYFUNCTION("""COMPUTED_VALUE"""),0) -> 0 | X55: =SUM(Q55:W55) -> 1561.2
A56: Toda la planta | B56: =IFERROR(__xludf.DUMMYFUNCTION("""COMPUTED_VALUE"""),0.0948522483704821) -> 0.094852248 | C56: =IFERROR(__xludf.DUMMYFUNCTION("""COMPUTED_VALUE"""),0.0815047861926023) -> 0.081504786 | D56: =IFERROR(__xludf.DUMMYFUNCTION("""COMPUTED_VALUE"""),0.0764490653204335) -> 0.076449065 | E56: =IFERROR(__xludf.DUMMYFUNCTION("""COMPUTED_VALUE"""),0.0840907184461371) -> 0.084090718 | F56: =IFERROR(__xludf.DUMMYFUNCTION("""COMPUTED_VALUE"""),0.0847724193282586) -> 0.084772419 | G56: =IFERROR(__xludf.DUMMYFUNCTION("""COMPUTED_VALUE"""),0.0839123144737292) -> 0.083912314 | H56: =IFERROR(__xludf.DUMMYFUNCTION("""COMPUTED_VALUE"""),0.0747579341668873) -> 0.074757934 | I56: =IFERROR(__xludf.DUMMYFUNCTION("""COMPUTED_VALUE"""),0.0754421691956102) -> 0.075442169 | J56: =IFERROR(__xludf.DUMMYFUNCTION("""COMPUTED_VALUE"""),0.0761698137204834) -> 0.076169814 | K56: =IFERROR(__xludf.DUMMYFUNCTION("""COMPUTED_VALUE"""),0.0761698137204834) -> 0.076169814 | L56: =IFERROR(__xludf.DUMMYFUNCTION("""COMPUTED_VALUE"""),0.0888355750162418) -> 0.088835575 | M56: =IFERROR(__xludf.DUMMYFUNCTION("""COMPUTED_VALUE"""),0.103043142048651) -> 0.10304314 | N56: =SUM(N39:N55) -> 107197.37 | P56: =SUM(P39:P55) -> 785
A57: Lote por cliente (u.) | Q57: =IFERROR(__xludf.DUMMYFUNCTION("IMPORTRANGE(Links!$B$5,""sobrestock_sustitutos!B18:H18"")"),9) -> 9 | R57: =IFERROR(__xludf.DUMMYFUNCTION("""COMPUTED_VALUE"""),15) -> 15 | S57: =IFERROR(__xludf.DUMMYFUNCTION("""COMPUTED_VALUE"""),12) -> 12 | T57: =IFERROR(__xludf.DUMMYFUNCTION("""COMPUTED_VALUE"""),11) -> 11 | U57: =IFERROR(__xludf.DUMMYFUNCTION("""COMPUTED_VALUE"""),10) -> 10 | V57: =IFERROR(__xludf.DUMMYFUNCTION("""COMPUTED_VALUE"""),61) -> 61 | W57: =IFERROR(__xludf.DUMMYFUNCTION("""COMPUTED_VALUE"""),6) -> 6
A58: Días hábiles por mes | B58: =IFERROR(__xludf.DUMMYFUNCTION("IMPORTRANGE(Links!$B$5,""parametros_recargas!B2"")"),20) -> 20
A59: Horas productivas por turno | B59: =IFERROR(__xludf.DUMMYFUNCTION("IMPORTRANGE(Links!$B$5,""parametros_recargas!B5"")"),7.5) -> 7.5
A61: Rubro: estacionalidad (% del año) | B61: Ene | C61: Feb | D61: Mar | E61: Abr | F61: May | G61: Jun | H61: Jul | I61: Ago | J61: Sep | K61: Oct | L61: Nov | M61: Dic
A62: Automotor | B62: =IFERROR(__xludf.DUMMYFUNCTION("IMPORTRANGE(Links!$B$5,""parametros_recargas!E35:P41"")"),0.12) -> 0.12 | C62: =IFERROR(__xludf.DUMMYFUNCTION("""COMPUTED_VALUE"""),0.0955555555555556) -> 0.095555556 | D62: =IFERROR(__xludf.DUMMYFUNCTION("""COMPUTED_VALUE"""),0.0711111111111111) -> 0.071111111 | E62: =IFERROR(__xludf.DUMMYFUNCTION("""COMPUTED_VALUE"""),0.0711111111111111) -> 0.071111111 | F62: =IFERROR(__xludf.DUMMYFUNCTION("""COMPUTED_VALUE"""),0.0711111111111111) -> 0.071111111 | G62: =IFERROR(__xludf.DUMMYFUNCTION("""COMPUTED_VALUE"""),0.0711111111111111) -> 0.071111111 | H62: =IFERROR(__xludf.DUMMYFUNCTION("""COMPUTED_VALUE"""),0.0711111111111111) -> 0.071111111 | I62: =IFERROR(__xludf.DUMMYFUNCTION("""COMPUTED_VALUE"""),0.0711111111111111) -> 0.071111111 | J62: =IFERROR(__xludf.DUMMYFUNCTION("""COMPUTED_VALUE"""),0.0711111111111111) -> 0.071111111 | K62: =IFERROR(__xludf.DUMMYFUNCTION("""COMPUTED_VALUE"""),0.0711111111111111) -> 0.071111111 | L62: =IFERROR(__xludf.DUMMYFUNCTION("""COMPUTED_VALUE"""),0.0955555555555556) -> 0.095555556 | M62: =IFERROR(__xludf.DUMMYFUNCTION("""COMPUTED_VALUE"""),0.12) -> 0.12
A63: Edificios | B63: =IFERROR(__xludf.DUMMYFUNCTION("""COMPUTED_VALUE"""),0.0540540540540541) -> 0.054054054 | C63: =IFERROR(__xludf.DUMMYFUNCTION("""COMPUTED_VALUE"""),0.0540540540540541) -> 0.054054054 | D63: =IFERROR(__xludf.DUMMYFUNCTION("""COMPUTED_VALUE"""),0.0810810810810811) -> 0.081081081 | E63: =IFERROR(__xludf.DUMMYFUNCTION("""COMPUTED_VALUE"""),0.108108108108108) -> 0.10810811 | F63: =IFERROR(__xludf.DUMMYFUNCTION("""COMPUTED_VALUE"""),0.108108108108108) -> 0.10810811 | G63: =IFERROR(__xludf.DUMMYFUNCTION("""COMPUTED_VALUE"""),0.108108108108108) -> 0.10810811 | H63: =IFERROR(__xludf.DUMMYFUNCTION("""COMPUTED_VALUE"""),0.0810810810810811) -> 0.081081081 | I63: =IFERROR(__xludf.DUMMYFUNCTION("""COMPUTED_VALUE"""),0.0810810810810811) -> 0.081081081 | J63: =IFERROR(__xludf.DUMMYFUNCTION("""COMPUTED_VALUE"""),0.0810810810810811) -> 0.081081081 | K63: =IFERROR(__xludf.DUMMYFUNCTION("""COMPUTED_VALUE"""),0.0810810810810811) -> 0.081081081 | L63: =IFERROR(__xludf.DUMMYFUNCTION("""COMPUTED_VALUE"""),0.0810810810810811) -> 0.081081081 | M63: =IFERROR(__xludf.DUMMYFUNCTION("""COMPUTED_VALUE"""),0.0810810810810811) -> 0.081081081
A64: Educación | B64: =IFERROR(__xludf.DUMMYFUNCTION("""COMPUTED_VALUE"""),0.10126582278481) -> 0.10126582 | C64: =IFERROR(__xludf.DUMMYFUNCTION("""COMPUTED_VALUE"""),0.10126582278481) -> 0.10126582 | D64: =IFERROR(__xludf.DUMMYFUNCTION("""COMPUTED_VALUE"""),0.10126582278481) -> 0.10126582 | E64: =IFERROR(__xludf.DUMMYFUNCTION("""COMPUTED_VALUE"""),0.0759493670886076) -> 0.075949367 | F64: =IFERROR(__xludf.DUMMYFUNCTION("""COMPUTED_VALUE"""),0.0759493670886076) -> 0.075949367 | G64: =IFERROR(__xludf.DUMMYFUNCTION("""COMPUTED_VALUE"""),0.0759493670886076) -> 0.075949367 | H64: =IFERROR(__xludf.DUMMYFUNCTION("""COMPUTED_VALUE"""),0.0886075949367089) -> 0.088607595 | I64: =IFERROR(__xludf.DUMMYFUNCTION("""COMPUTED_VALUE"""),0.0759493670886076) -> 0.075949367 | J64: =IFERROR(__xludf.DUMMYFUNCTION("""COMPUTED_VALUE"""),0.0759493670886076) -> 0.075949367 | K64: =IFERROR(__xludf.DUMMYFUNCTION("""COMPUTED_VALUE"""),0.0759493670886076) -> 0.075949367 | L64: =IFERROR(__xludf.DUMMYFUNCTION("""COMPUTED_VALUE"""),0.0759493670886076) -> 0.075949367 | M64: =IFERROR(__xludf.DUMMYFUNCTION("""COMPUTED_VALUE"""),0.0759493670886076) -> 0.075949367
A65: Hoteles | B65: =IFERROR(__xludf.DUMMYFUNCTION("""COMPUTED_VALUE"""),0.0526315789473684) -> 0.052631579 | C65: =IFERROR(__xludf.DUMMYFUNCTION("""COMPUTED_VALUE"""),0.0526315789473684) -> 0.052631579 | D65: =IFERROR(__xludf.DUMMYFUNCTION("""COMPUTED_VALUE"""),0.0789473684210526) -> 0.078947368 | E65: =IFERROR(__xludf.DUMMYFUNCTION("""COMPUTED_VALUE"""),0.0789473684210526) -> 0.078947368 | F65: =IFERROR(__xludf.DUMMYFUNCTION("""COMPUTED_VALUE"""),0.105263157894737) -> 0.10526316 | G65: =IFERROR(__xludf.DUMMYFUNCTION("""COMPUTED_VALUE"""),0.105263157894737) -> 0.10526316 | H65: =IFERROR(__xludf.DUMMYFUNCTION("""COMPUTED_VALUE"""),0.0526315789473684) -> 0.052631579 | I65: =IFERROR(__xludf.DUMMYFUNCTION("""COMPUTED_VALUE"""),0.105263157894737) -> 0.10526316 | J65: =IFERROR(__xludf.DUMMYFUNCTION("""COMPUTED_VALUE"""),0.105263157894737) -> 0.10526316 | K65: =IFERROR(__xludf.DUMMYFUNCTION("""COMPUTED_VALUE"""),0.105263157894737) -> 0.10526316 | L65: =IFERROR(__xludf.DUMMYFUNCTION("""COMPUTED_VALUE"""),0.0789473684210526) -> 0.078947368 | M65: =IFERROR(__xludf.DUMMYFUNCTION("""COMPUTED_VALUE"""),0.0789473684210526) -> 0.078947368
A66: Industrias / almacenes | B66: =IFERROR(__xludf.DUMMYFUNCTION("""COMPUTED_VALUE"""),0.0833333333333333) -> 0.083333333 | C66: =IFERROR(__xludf.DUMMYFUNCTION("""COMPUTED_VALUE"""),0.0833333333333333) -> 0.083333333 | D66: =IFERROR(__xludf.DUMMYFUNCTION("""COMPUTED_VALUE"""),0.0833333333333333) -> 0.083333333 | E66: =IFERROR(__xludf.DUMMYFUNCTION("""COMPUTED_VALUE"""),0.0833333333333333) -> 0.083333333 | F66: =IFERROR(__xludf.DUMMYFUNCTION("""COMPUTED_VALUE"""),0.0833333333333333) -> 0.083333333 | G66: =IFERROR(__xludf.DUMMYFUNCTION("""COMPUTED_VALUE"""),0.0833333333333333) -> 0.083333333 | H66: =IFERROR(__xludf.DUMMYFUNCTION("""COMPUTED_VALUE"""),0.0833333333333333) -> 0.083333333 | I66: =IFERROR(__xludf.DUMMYFUNCTION("""COMPUTED_VALUE"""),0.0833333333333333) -> 0.083333333 | ... M66: =IFERROR(__xludf.DUMMYFUNCTION("""COMPUTED_VALUE"""),0.0833333333333333) -> 0.083333333
A67: Salud | B67: =IFERROR(__xludf.DUMMYFUNCTION("""COMPUTED_VALUE"""),0.111111111111111) -> 0.11111111 | C67: =IFERROR(__xludf.DUMMYFUNCTION("""COMPUTED_VALUE"""),0.111111111111111) -> 0.11111111 | D67: =IFERROR(__xludf.DUMMYFUNCTION("""COMPUTED_VALUE"""),0.0833333333333333) -> 0.083333333 | E67: =IFERROR(__xludf.DUMMYFUNCTION("""COMPUTED_VALUE"""),0.0833333333333333) -> 0.083333333 | F67: =IFERROR(__xludf.DUMMYFUNCTION("""COMPUTED_VALUE"""),0.0833333333333333) -> 0.083333333 | G67: =IFERROR(__xludf.DUMMYFUNCTION("""COMPUTED_VALUE"""),0.0555555555555556) -> 0.055555556 | H67: =IFERROR(__xludf.DUMMYFUNCTION("""COMPUTED_VALUE"""),0.0555555555555556) -> 0.055555556 | I67: =IFERROR(__xludf.DUMMYFUNCTION("""COMPUTED_VALUE"""),0.0555555555555556) -> 0.055555556 | J67: =IFERROR(__xludf.DUMMYFUNCTION("""COMPUTED_VALUE"""),0.0833333333333333) -> 0.083333333 | K67: =IFERROR(__xludf.DUMMYFUNCTION("""COMPUTED_VALUE"""),0.0833333333333333) -> 0.083333333 | L67: =IFERROR(__xludf.DUMMYFUNCTION("""COMPUTED_VALUE"""),0.0833333333333333) -> 0.083333333 | M67: =IFERROR(__xludf.DUMMYFUNCTION("""COMPUTED_VALUE"""),0.111111111111111) -> 0.11111111
A68: Supermercados | B68: =IFERROR(__xludf.DUMMYFUNCTION("""COMPUTED_VALUE"""),0.0555555555555556) -> 0.055555556 | C68: =IFERROR(__xludf.DUMMYFUNCTION("""COMPUTED_VALUE"""),0.0555555555555556) -> 0.055555556 | D68: =IFERROR(__xludf.DUMMYFUNCTION("""COMPUTED_VALUE"""),0.0833333333333333) -> 0.083333333 | E68: =IFERROR(__xludf.DUMMYFUNCTION("""COMPUTED_VALUE"""),0.0833333333333333) -> 0.083333333 | F68: =IFERROR(__xludf.DUMMYFUNCTION("""COMPUTED_VALUE"""),0.111111111111111) -> 0.11111111 | G68: =IFERROR(__xludf.DUMMYFUNCTION("""COMPUTED_VALUE"""),0.111111111111111) -> 0.11111111 | H68: =IFERROR(__xludf.DUMMYFUNCTION("""COMPUTED_VALUE"""),0.111111111111111) -> 0.11111111 | I68: =IFERROR(__xludf.DUMMYFUNCTION("""COMPUTED_VALUE"""),0.111111111111111) -> 0.11111111 | J68: =IFERROR(__xludf.DUMMYFUNCTION("""COMPUTED_VALUE"""),0.0833333333333333) -> 0.083333333 | K68: =IFERROR(__xludf.DUMMYFUNCTION("""COMPUTED_VALUE"""),0.0833333333333333) -> 0.083333333 | L68: =IFERROR(__xludf.DUMMYFUNCTION("""COMPUTED_VALUE"""),0.0555555555555556) -> 0.055555556 | M68: =IFERROR(__xludf.DUMMYFUNCTION("""COMPUTED_VALUE"""),0.0555555555555556) -> 0.055555556

Sheet Cálculo
A1: Logística en el mes pico de 2035 (las dos plantas lado a lado)
A2: Cada planta en su mes pico · § 10
A4: 1. Mes pico | B4: Comercial | C4: Industrial
A5: N° del mes pico (mayor % de Toda la planta) | B5: =MATCH(MAX(Importados!$B$22:$M$22),Importados!$B$22:$M$22,0) -> 12 | C5: =MATCH(MAX(Importados!$B$56:$M$56),Importados!$B$56:$M$56,0) -> 12
A6: Mes pico | B6: =INDEX(Importados!$B$4:$M$4,B5) -> Dic | C6: =INDEX(Importados!$B$38:$M$38,C5) -> Dic
A7: % de las recargas del año en el mes pico | B7: =INDEX(Importados!$B$22:$M$22,B5) -> 0.10298626 | C7: =INDEX(Importados!$B$56:$M$56,C5) -> 0.10304314
A8: Días hábiles por mes | B8: =Importados!$B$24 -> 20 | C8: =Importados!$B$58 -> 20
A9: Horas productivas por turno | B9: =Importados!$B$25 -> 7.5 | C9: =Importados!$B$59 -> 7.5
A11: 2. Por tipo | B11: Peso lleno (kg) | C11: u. por jaula | D11: Jaula | E11: Rodante (1 = sí) | F11: Comercial | I11: Industrial | M11: Fuente del peso
A12: Tipo | F12: u/día | G12: Sustitutos por día | H12: Jaulas por día | I12: u/día | J12: Sustitutos por día | K12: Jaulas por día | M12: § 10.3
A13: ABC 1 kg | B13: 1.9 | C13: 72 | D13: A | E13: 0 | F13: =Importados!$N$5*INDEX(Importados!$B$5:$M$5,$B$5)/$B$8 -> 652.61884 | G13: =F13*Importados!$O$5 -> 0 | H13: =F13/$C13 -> 9.0641505 | I13: =Importados!$N$39*INDEX(Importados!$B$39:$M$39,$C$5)/$C$8 -> 339.25472 | J13: =I13*Importados!$O$39 -> 0 | K13: =I13/$C13 -> 4.7118712 | M13: BOM FLAMA
A14: ABC 2,5 kg | B14: 4.6 | C14: 30 | D14: B | E14: 0 | F14: =Importados!$N$6*INDEX(Importados!$B$6:$M$6,$B$5)/$B$8 -> 37.080883 | G14: =F14*Importados!$O$6 -> 37.080883 | H14: =F14/$C14 -> 1.2360294 | I14: =Importados!$N$40*INDEX(Importados!$B$40:$M$40,$C$5)/$C$8 -> 19.246835 | J14: =I14*Importados!$O$40 -> 19.246835 | K14: =I14/$C14 -> 0.64156116 | M14: BOM FLAMA
A15: ABC 5 kg | B15: 8.5 | C15: 24 | D15: B | E15: 0 | F15: =Importados!$N$7*INDEX(Importados!$B$7:$M$7,$B$5)/$B$8 -> 238.01524 | G15: =F15*Importados!$O$7 -> 238.01524 | H15: =F15/$C15 -> 9.9173016 | I15: =Importados!$N$41*INDEX(Importados!$B$41:$M$41,$C$5)/$C$8 -> 123.88362 | J15: =I15*Importados!$O$41 -> 123.88362 | K15: =I15/$C15 -> 5.1618177 | M15: BOM FLAMA
A16: ABC 10 kg | B16: 16.5 | C16: 16 | D16: B | E16: 0 | F16: =Importados!$N$8*INDEX(Importados!$B$8:$M$8,$B$5)/$B$8 -> 13.892023 | G16: =F16*Importados!$O$8 -> 13.892023 | H16: =F16/$C16 -> 0.86825145 | I16: =Importados!$N$42*INDEX(Importados!$B$42:$M$42,$C$5)/$C$8 -> 7.229607 | J16: =I16*Importados!$O$42 -> 7.229607 | K16: =I16/$C16 -> 0.45185044 | M16: BOM FLAMA
A17: Agua 10 l | B17: 12.55 | C17: 16 | D17: B | E17: 0 | F17: =Importados!$N$9*INDEX(Importados!$B$9:$M$9,$B$5)/$B$8 -> 19.699852 | G17: =F17*Importados!$O$9 -> 19.699852 | H17: =F17/$C17 -> 1.2312408 | I17: =Importados!$N$43*INDEX(Importados!$B$43:$M$43,$C$5)/$C$8 -> 10.263237 | J17: =I17*Importados!$O$43 -> 10.263237 | K17: =I17/$C17 -> 0.64145228 | M17: BOM FLAMA
A18: AFFF 10 l | B18: 12.6 | C18: 16 | D18: B | E18: 0 | F18: =Importados!$N$10*INDEX(Importados!$B$10:$M$10,$B$5)/$B$8 -> 3.7070602 | G18: =F18*Importados!$O$10 -> 3.7070602 | H18: =F18/$C18 -> 0.23169126 | I18: =Importados!$N$44*INDEX(Importados!$B$44:$M$44,$C$5)/$C$8 -> 1.9269108 | J18: =I18*Importados!$O$44 -> 1.9269108 | K18: =I18/$C18 -> 0.12043192 | M18: BOM FLAMA
A19: AFFF 50 l s/ruedas | B19: 100 | C19: 2 | D19: Rodantes | E19: 1 | F19: =Importados!$N$11*INDEX(Importados!$B$11:$M$11,$B$5)/$B$8 -> 1.9323876 | G19: =F19*Importados!$O$11 -> 1.9323876 | H19: =F19/$C19 -> 0.96619381 | I19: =Importados!$N$45*INDEX(Importados!$B$45:$M$45,$C$5)/$C$8 -> 1.0044451 | J19: =I19*Importados!$O$45 -> 1.0044451 | K19: =I19/$C19 -> 0.50222257 | M19: BOM FLAMA
A20: BC 5 kg | B20: 8.5 | C20: 24 | D20: B | E20: 0 | F20: =Importados!$N$12*INDEX(Importados!$B$12:$M$12,$B$5)/$B$8 -> 1.1170782 | G20: =F20*Importados!$O$12 -> 1.1170782 | H20: =F20/$C20 -> 0.046544924 | I20: =Importados!$N$46*INDEX(Importados!$B$46:$M$46,$C$5)/$C$8 -> 0.58065148 | J20: =I20*Importados!$O$46 -> 0.58065148 | K20: =I20/$C20 -> 0.024193812 | M20: BOM FLAMA
A21: Sales K 6 l | B21: 8.25 | C21: 16 | D21: B | E21: 0 | F21: =Importados!$N$13*INDEX(Importados!$B$13:$M$13,$B$5)/$B$8 -> 9.5824335 | G21: =F21*Importados!$O$13 -> 9.5824335 | H21: =F21/$C21 -> 0.59890209 | I21: =Importados!$N$47*INDEX(Importados!$B$47:$M$47,$C$5)/$C$8 -> 4.9745012 | J21: =I21*Importados!$O$47 -> 4.9745012 | K21: =I21/$C21 -> 0.31090632 | M21: BOM FLAMA
A22: CO₂ 2 kg | B22: 9 | C22: 30 | D22: B | E22: 0 | F22: =Importados!$N$14*INDEX(Importados!$B$14:$M$14,$B$5)/$B$8 -> 51.747851 | G22: =F22*Importados!$O$14 -> 51.747851 | H22: =F22/$C22 -> 1.7249284 | I22: =Importados!$N$48*INDEX(Importados!$B$48:$M$48,$C$5)/$C$8 -> 26.904703 | J22: =I22*Importados!$O$48 -> 26.904703 | K22: =I22/$C22 -> 0.89682344 | M22: BOM FLAMA
A23: CO₂ 5 kg | B23: 20 | C23: 16 | D23: B | E23: 0 | F23: =Importados!$N$15*INDEX(Importados!$B$15:$M$15,$B$5)/$B$8 -> 18.479372 | G23: =F23*Importados!$O$15 -> 18.479372 | H23: =F23/$C23 -> 1.1549608 | I23: =Importados!$N$49*INDEX(Importados!$B$49:$M$49,$C$5)/$C$8 -> 9.6463434 | J23: =I23*Importados!$O$49 -> 9.6463434 | K23: =I23/$C23 -> 0.60289646 | M23: BOM FLAMA
A24: HCFC/HFC 5 kg | B24: 8.5 | C24: 24 | D24: B | E24: 0 | F24: =Importados!$N$16*INDEX(Importados!$B$16:$M$16,$B$5)/$B$8 -> 3.141987 | G24: =F24*Importados!$O$16 -> 3.141987 | H24: =F24/$C24 -> 0.13091612 | I24: =Importados!$N$50*INDEX(Importados!$B$50:$M$50,$C$5)/$C$8 -> 1.6677478 | J24: =I24*Importados!$O$50 -> 1.6677478 | K24: =I24/$C24 -> 0.069489492 | M24: BOM FLAMA
A25: Clase D 9 l | B25: 16.5 | C25: 16 | D25: B | E25: 0 | F25: =Importados!$N$17*INDEX(Importados!$B$17:$M$17,$B$5)/$B$8 -> 1.0089643 | G25: =F25*Importados!$O$17 -> 1.0089643 | H25: =F25/$C25 -> 0.063060271 | I25: =Importados!$N$51*INDEX(Importados!$B$51:$M$51,$C$5)/$C$8 -> 0.52445447 | J25: =I25*Importados!$O$51 -> 0.52445447 | K25: =I25/$C25 -> 0.032778404 | M25: BOM FLAMA
A26: ABC 25 kg s/ruedas | B26: 53 | C26: 2 | D26: Rodantes | E26: 1 | F26: =Importados!$N$18*INDEX(Importados!$B$18:$M$18,$B$5)/$B$8 -> 2.4799215 | G26: =F26*Importados!$O$18 -> 2.4799215 | H26: =F26/$C26 -> 1.2399607 | I26: =Importados!$N$52*INDEX(Importados!$B$52:$M$52,$C$5)/$C$8 -> 1.2974801 | J26: =I26*Importados!$O$52 -> 1.2974801 | K26: =I26/$C26 -> 0.64874004 | M26: Word de carros, Tabla 0
A27: ABC 50 kg s/ruedas | B27: 90 | C27: 2 | D27: Rodantes | E27: 1 | F27: =Importados!$N$19*INDEX(Importados!$B$19:$M$19,$B$5)/$B$8 -> 5.4558208 | G27: =F27*Importados!$O$19 -> 5.4558208 | H27: =F27/$C27 -> 2.7279104 | I27: =Importados!$N$53*INDEX(Importados!$B$53:$M$53,$C$5)/$C$8 -> 2.8544597 | J27: =I27*Importados!$O$53 -> 2.8544597 | K27: =I27/$C27 -> 1.4272299 | M27: Word de carros, Tabla 0
A28: ABC 70 kg s/ruedas | B28: 136 | C28: 2 | D28: Rodantes | E28: 1 | F28: =Importados!$N$20*INDEX(Importados!$B$20:$M$20,$B$5)/$B$8 -> 1.1903624 | G28: =F28*Importados!$O$20 -> 1.1903624 | H28: =F28/$C28 -> 0.5951812 | I28: =Importados!$N$54*INDEX(Importados!$B$54:$M$54,$C$5)/$C$8 -> 0.62279058 | J28: =I28*Importados!$O$54 -> 0.62279058 | K28: =I28/$C28 -> 0.31139529 | M28: Word de carros, Tabla 0
A29: ABC 100 kg s/ruedas | B29: 179 | C29: 1 | D29: Rodantes | E29: 1 | F29: =Importados!$N$21*INDEX(Importados!$B$21:$M$21,$B$5)/$B$8 -> 0.79357376 | G29: =F29*Importados!$O$21 -> 0.79357376 | H29: =F29/$C29 -> 0.79357376 | I29: =Importados!$N$55*INDEX(Importados!$B$55:$M$55,$C$5)/$C$8 -> 0.41519172 | J29: =I29*Importados!$O$55 -> 0.41519172 | K29: =I29/$C29 -> 0.41519172 | M29: Word de carros, Tabla 0
A30: Total | F30: =SUM(F13:F29) -> 1061.9436 | G30: =SUM(G13:G29) -> 409.32481 | H30: =SUM(H13:H29) -> 32.590797 | I30: =SUM(I13:I29) -> 552.29771 | J30: =SUM(J13:J29) -> 213.04298 | K30: =SUM(K13:K29) -> 16.970852
A31: Peso medio por u. (kg) | F31: =SUMPRODUCT(F13:F29,$B$13:$B$29)/F30 -> 5.6911669 | I31: =SUMPRODUCT(I13:I29,$B$13:$B$29)/I30 -> 5.6989307
A35: 3. Por rubro | B35: min por u. en el cliente | C35: Comercial | G35: Industrial | M35: Fuente
A36: Rubro | C36: u/día | D36: Lote (u/cliente) | E36: Paradas por día | F36: Horas de parada | G36: u/día | H36: Lote (u/cliente) | I36: Paradas por día | J36: Horas de parada
A37: Automotor | B37: 0.5 | C37: =INDEX(Importados!$B$28:$M$28,$B$5)*SUMPRODUCT(Importados!$N$5:$N$21,Importados!$Q$5:$Q$21/Importados!$X$5:$X$21)/$B$8 -> 674.61404 | D37: =Importados!Q$23 -> 9 | E37: =2*C37/D37 -> 149.91423 | F37: =E37*(Supuestos!$B$17+Supuestos!$B$18)/60+2*C37*$B37/60 -> 98.693536 | G37: =INDEX(Importados!$B$62:$M$62,$C$5)*SUMPRODUCT(Importados!$N$39:$N$55,Importados!$Q$39:$Q$55/Importados!$X$39:$X$55)/$C$8 -> 351.19952 | H37: =Importados!Q$57 -> 9 | I37: =2*G37/H37 -> 78.044339 | J37: =I37*(Supuestos!$B$17+Supuestos!$B$18)/60+2*G37*$B37/60 -> 51.37919 | M37: Criterio · § 10.4
A38: Edificios | B38: 1.5 | C38: =INDEX(Importados!$B$29:$M$29,$B$5)*SUMPRODUCT(Importados!$N$5:$N$21,Importados!$R$5:$R$21/Importados!$X$5:$X$21)/$B$8 -> 263.13379 | D38: =Importados!R$23 -> 15 | E38: =2*C38/D38 -> 35.084505 | F38: =E38*(Supuestos!$B$17+Supuestos!$B$18)/60+2*C38*$B38/60 -> 33.62265 | G38: =INDEX(Importados!$B$63:$M$63,$C$5)*SUMPRODUCT(Importados!$N$39:$N$55,Importados!$R$39:$R$55/Importados!$X$39:$X$55)/$C$8 -> 136.1966 | H38: =Importados!R$57 -> 15 | I38: =2*G38/H38 -> 18.159546 | J38: =I38*(Supuestos!$B$17+Supuestos!$B$18)/60+2*G38*$B38/60 -> 17.402899 | M38: Criterio · § 10.4
A39: Educación | B39: 1.5 | C39: =INDEX(Importados!$B$30:$M$30,$B$5)*SUMPRODUCT(Importados!$N$5:$N$21,Importados!$S$5:$S$21/Importados!$X$5:$X$21)/$B$8 -> 21.463557 | D39: =Importados!S$23 -> 12 | E39: =2*C39/D39 -> 3.5772595 | F39: =E39*(Supuestos!$B$17+Supuestos!$B$18)/60+2*C39*$B39/60 -> 3.1599126 | G39: =INDEX(Importados!$B$64:$M$64,$C$5)*SUMPRODUCT(Importados!$N$39:$N$55,Importados!$S$39:$S$55/Importados!$X$39:$X$55)/$C$8 -> 13.321827 | H39: =Importados!S$57 -> 12 | I39: =2*G39/H39 -> 2.2203046 | J39: =I39*(Supuestos!$B$17+Supuestos!$B$18)/60+2*G39*$B39/60 -> 1.961269 | M39: Criterio · § 10.4
A40: Hoteles | B40: 1.5 | C40: =INDEX(Importados!$B$31:$M$31,$B$5)*SUMPRODUCT(Importados!$N$5:$N$21,Importados!$T$5:$T$21/Importados!$X$5:$X$21)/$B$8 -> 15.095224 | D40: =Importados!T$23 -> 11 | E40: =2*C40/D40 -> 2.7445862 | F40: =E40*(Supuestos!$B$17+Supuestos!$B$18)/60+2*C40*$B40/60 -> 2.3557698 | G40: =INDEX(Importados!$B$65:$M$65,$C$5)*SUMPRODUCT(Importados!$N$39:$N$55,Importados!$T$39:$T$55/Importados!$X$39:$X$55)/$C$8 -> 8.8315716 | H40: =Importados!T$57 -> 11 | I40: =2*G40/H40 -> 1.6057403 | J40: =I40*(Supuestos!$B$17+Supuestos!$B$18)/60+2*G40*$B40/60 -> 1.3782604 | M40: Criterio · § 10.4
A41: Industrias / almacenes | B41: 1.5 | C41: =INDEX(Importados!$B$32:$M$32,$B$5)*SUMPRODUCT(Importados!$N$5:$N$21,Importados!$U$5:$U$21/Importados!$X$5:$X$21)/$B$8 -> 53.80661 | D41: =Importados!U$23 -> 10 | E41: =2*C41/D41 -> 10.761322 | F41: =E41*(Supuestos!$B$17+Supuestos!$B$18)/60+2*C41*$B41/60 -> 8.9677683 | G41: =INDEX(Importados!$B$66:$M$66,$C$5)*SUMPRODUCT(Importados!$N$39:$N$55,Importados!$U$39:$U$55/Importados!$X$39:$X$55)/$C$8 -> 22.888048 | H41: =Importados!U$57 -> 10 | I41: =2*G41/H41 -> 4.5776095 | J41: =I41*(Supuestos!$B$17+Supuestos!$B$18)/60+2*G41*$B41/60 -> 3.8146746 | M41: Criterio · § 10.4
A42: Salud | B42: 1.5 | C42: =INDEX(Importados!$B$33:$M$33,$B$5)*SUMPRODUCT(Importados!$N$5:$N$21,Importados!$V$5:$V$21/Importados!$X$5:$X$21)/$B$8 -> 31.558811 | D42: =Importados!V$23 -> 61 | E42: =2*C42/D42 -> 1.0347151 | F42: =E42*(Supuestos!$B$17+Supuestos!$B$18)/60+2*C42*$B42/60 -> 2.1815244 | G42: =INDEX(Importados!$B$67:$M$67,$C$5)*SUMPRODUCT(Importados!$N$39:$N$55,Importados!$V$39:$V$55/Importados!$X$39:$X$55)/$C$8 -> 18.440196 | H42: =Importados!V$57 -> 61 | I42: =2*G42/H42 -> 0.6045966 | J42: =I42*(Supuestos!$B$17+Supuestos!$B$18)/60+2*G42*$B42/60 -> 1.2746912 | M42: Criterio · § 10.4
A43: Supermercados | B43: 1 | C43: =INDEX(Importados!$B$34:$M$34,$B$5)*SUMPRODUCT(Importados!$N$5:$N$21,Importados!$W$5:$W$21/Importados!$X$5:$X$21)/$B$8 -> 2.2716163 | D43: =Importados!W$23 -> 6 | E43: =2*C43/D43 -> 0.75720542 | F43: =E43*(Supuestos!$B$17+Supuestos!$B$18)/60+2*C43*$B43/60 -> 0.5174237 | G43: =INDEX(Importados!$B$68:$M$68,$C$5)*SUMPRODUCT(Importados!$N$39:$N$55,Importados!$W$39:$W$55/Importados!$X$39:$X$55)/$C$8 -> 1.4199399 | H43: =Importados!W$57 -> 6 | I43: =2*G43/H43 -> 0.47331331 | J43: =I43*(Supuestos!$B$17+Supuestos!$B$18)/60+2*G43*$B43/60 -> 0.32343076 | M43: Criterio · § 10.4
A44: Total | C44: =SUM(C37:C43) -> 1061.9436 | E44: =SUM(E37:E43) -> 203.87382 | F44: =SUM(F37:F43) -> 149.49858 | G44: =SUM(G37:G43) -> 552.29771 | I44: =SUM(I37:I43) -> 105.68545 | J44: =SUM(J37:J43) -> 77.534414
A48: 4. Camión y viajes (§ 10.5) | B48: Comercial | C48: Industrial
A49: Equipos que se retiran por día (u) | B49: =F30 -> 1061.9436 | C49: =I30 -> 552.29771
A50: Sustitutos que salen por día (u) | B50: =G30 -> 409.32481 | C50: =J30 -> 213.04298
A51: Carga por sentido por día (u) | B51: =B49+B50 -> 1471.2685 | C51: =C49+C50 -> 765.34069
A52: Peso medio por u. (kg) | B52: =F31 -> 5.6911669 | C52: =I31 -> 5.6989307
A53: Jaulas por u. | B53: =H30/F30 -> 0.030689762 | C53: =K30/I30 -> 0.030727725
A54: Capacidad por viaje por espacio (u) | B54: =Supuestos!$B$6/(B53*Supuestos!$B$24) -> 170.00429 | C54: =Supuestos!$B$6/(C53*Supuestos!$B$24) -> 169.79426
A55: Capacidad por viaje por peso (u) | B55: =Supuestos!$B$11/B52 -> 245.99525 | C55: =Supuestos!$B$11/C52 -> 245.66012
A56: Capacidad por viaje (u) | B56: =MIN(B54,B55) -> 170.00429 | C56: =MIN(C54,C55) -> 169.79426
A57: Viajes por día por carga | B57: =B51/B56 -> 8.6543017 | C57: =C51/C56 -> 4.5074592
A58: Paradas por día | B58: =E44 -> 203.87382 | C58: =I44 -> 105.68545
A59: Horas de parada y manipuleo por día | B59: =F44 -> 149.49858 | C59: =J44 -> 77.534414
A60: Viajes por día por tiempo | B60: =B59/($B$9-Supuestos!$B$16) -> 24.916431 | C60: =C59/($C$9-Supuestos!$B$16) -> 12.922402
A61: Viajes por día | B61: =ROUNDUP(MAX(B57,B60),0) -> 25 | C61: =ROUNDUP(MAX(C57,C60),0) -> 13
A62: Horas de camión por día | B62: =B61*Supuestos!$B$16+B59 -> 186.99858 | C62: =C61*Supuestos!$B$16+C59 -> 97.034414
A63: Camiones necesarios | B63: =ROUNDUP(B62/($B$9*Supuestos!$B$15*Supuestos!$B$19),0) -> 14 | C63: =ROUNDUP(C62/($C$9*Supuestos!$B$15*Supuestos!$B$19),0) -> 8
A64: Ocupación de la flota | B64: =B62/(B63*$B$9*Supuestos!$B$15) -> 0.89046945 | C64: =C62/(C63*$C$9*Supuestos!$B$15) -> 0.80862012
A65: Peso por viaje (kg) | B65: =B51*B52/B61 -> 334.92937 | C65: =C51*C52/C61 -> 335.5095
A66: Inversión en camiones (ARS) | B66: =IF(Supuestos!$B$12="","a cotizar",B63*Supuestos!$B$12) -> a cotizar | C66: =IF(Supuestos!$B$12="","a cotizar",C63*Supuestos!$B$12) -> a cotizar
A68: 5. Pulmón | B68: Comercial | F68: Industrial | M68: Dónde y cómo van
A69: Zona | B69: Matafuegos (u) | C69: Jaulas de manuales | D69: Jaulas de rodantes | E69: Posiciones 1,2 × 1,0 m | F69: Matafuegos (u) | G69: Jaulas de manuales | H69: Jaulas de rodantes | I69: Posiciones 1,2 × 1,0 m
A70: Recepción | B70: =F30*Supuestos!$B$22 -> 530.97182 | C70: =SUMPRODUCT(($E$13:$E$29=0)*H13:H29)*Supuestos!$B$22*Supuestos!$B$24 -> 15.104087 | D70: =SUMPRODUCT(($E$13:$E$29=1)*H13:H29)*Supuestos!$B$22 -> 3.16141 | E70: =ROUNDUP(C70,0)+ROUNDUP(D70,0) -> 20 | F70: =I30*Supuestos!$B$22 -> 276.14885 | G70: =SUMPRODUCT(($E$13:$E$29=0)*K13:K29)*Supuestos!$B$22*Supuestos!$B$24 -> 7.8579917 | H70: =SUMPRODUCT(($E$13:$E$29=1)*K13:K29)*Supuestos!$B$22 -> 1.6523897 | I70: =ROUNDUP(G70,0)+ROUNDUP(H70,0) -> 10 | M70: Jaulas A (1 kg) y B por cliente, en orden de llegada; rodantes en su jaula
A71: Despacho | B71: =F30*Supuestos!$B$23 -> 530.97182 | C71: =SUMPRODUCT(($E$13:$E$29=0)*H13:H29)*Supuestos!$B$23*Supuestos!$B$24 -> 15.104087 | D71: =SUMPRODUCT(($E$13:$E$29=1)*H13:H29)*Supuestos!$B$23 -> 3.16141 | E71: =ROUNDUP(C71,0)+ROUNDUP(D71,0) -> 20 | F71: =I30*Supuestos!$B$23 -> 276.14885 | G71: =SUMPRODUCT(($E$13:$E$29=0)*K13:K29)*Supuestos!$B$23*Supuestos!$B$24 -> 7.8579917 | H71: =SUMPRODUCT(($E$13:$E$29=1)*K13:K29)*Supuestos!$B$23 -> 1.6523897 | I71: =ROUNDUP(G71,0)+ROUNDUP(H71,0) -> 10 | M71: Jaulas armadas por recorrido y en el orden de entrega
A72: Sustitutos en planta | B72: =G30 -> 409.32481 | C72: =SUMPRODUCT(($E$13:$E$29=0)*G13:G29/$C$13:$C$29) -> 17.203827 | D72: =SUMPRODUCT(($E$13:$E$29=1)*G13:G29/$C$13:$C$29) -> 6.3228199 | E72: =ROUNDUP(C72/Supuestos!$B$26,0)+ROUNDUP(D72,0) -> 13 | F72: =J30 -> 213.04298 | G72: =SUMPRODUCT(($E$13:$E$29=0)*J13:J29/$C$13:$C$29) -> 8.9542014 | H72: =SUMPRODUCT(($E$13:$E$29=1)*J13:J29/$C$13:$C$29) -> 3.3047795 | I72: =ROUNDUP(G72/Supuestos!$B$26,0)+ROUNDUP(H72,0) -> 7 | M72: Estantería con faja amarilla, por tipo; rodantes en el piso
A73: Jaulas vacías | B73: — | C73: — | D73: — | E73: =ROUNDUP(SUM(E70:E72)*Supuestos!$B$25/Supuestos!$B$27,0) -> 2 | F73: — | G73: — | H73: — | I73: =ROUNDUP(SUM(I70:I72)*Supuestos!$B$25/Supuestos!$B$27,0) -> 2 | M73: Apiladas, junto a despacho
A74: Total de posiciones | E74: =SUM(E70:E73) -> 55 | I74: =SUM(I70:I73) -> 29
A75: Superficie del pulmón con pasillo (m²) | E75: =E74*Supuestos!$B$28 -> 132 | I75: =I74*Supuestos!$B$28 -> 69.6
A76: Stock de sustitutos 2035 (u) | E76: =Importados!$P$22 -> 1498 | I76: =Importados!$P$56 -> 785
A77: Jaulas A y B a tener (planta + camiones + vacías) | E77: =ROUNDUP(SUM(C70:C72),0)+B63*Supuestos!$B$6+E73*Supuestos!$B$27 -> 140 | I77: =ROUNDUP(SUM(G70:G72),0)+C63*Supuestos!$B$6+I73*Supuestos!$B$27 -> 81
