Workbook

Sheet Resumen
A1: BALANCEO DE LÍNEA SINCRONIZADO — FLAMA (manuales, carros y recargas)
A2: Con la mezcla real de modelos del mes elegido: cuánto carga cada puesto, cada cuántos días pasa cada formato por cada máquina, cuánto se hace por vez y cuánto stock queda entre puestos y en los almacenes.
A3: Año (2026 a 2035) | C3: 2035
A4: Mes (1 a 12; vacío = mes pico de producción de manuales)
A5: Mes de cálculo | C5: =IF(C4="",Carga!$N$8,C4) -> 1 | D5: =Carga!B4 -> Ene 2035
A7: CÓMO SE LEE (una hoja por paso; solo se tocan las celdas amarillas y verdes)
A8: Hoja | B8: Qué pregunta responde | F8: Qué mirar
A9: Parametros | B9: Qué supuestos y criterios se usan y de dónde sale cada número. | F9: Amarillos (criterios) y columna G (fuente).
A10: Carga (paso 1) | B10: ¿Cuánto hay que hacer por día y cuánto carga cada puesto con esa mezcla? | F10: Aprovechamiento y cuello de cada línea.
A11: Lotes (paso 2) | B11: ¿Cuánto cortar o prensar de cada formato antes de cambiar? | F11: Frecuencia, tanda y pulmón de cada formato.
A12: Rueda (paso 3) | B12: ¿Qué formato pasa cada día por cada puesto de la ola? | F12: Calendario de 20 días: nada arriba de 100 %.
A13: Pulmones (paso 4) | B13: ¿Cuánto material queda esperando y cuántos m² hay que reservar? | F13: Sección 1: total a reservar.
A14: Datos | B14: Valores pegados de las planillas de aprovechamiento. | F14: No se lee.
A16: 1) PRODUCCIÓN DEL MES DE CÁLCULO
A17: Línea | B17: Unidades por mes | C17: Unidades por día | D17: Mes pico de la línea | E17: Terminados por día | F17: Cilindros vacíos por día
A18: Manuales (recipientes, con sobrestock) | B18: =Carga!F18*DIAS -> 25601.631 | C18: =Carga!F18 -> 1280.0815 | D18: =Carga!O8 -> Ene | E18: =Carga!D18 -> 324.76052 | F18: =Carga!E18 -> 955.32102
A19: Carros (recipientes) | B19: =Carga!E26*DIAS -> 264.12238 | C19: =Carga!E26 -> 13.206119 | D19: =Carga!O9 -> Mar | E19: =Carga!C26 -> 7.7123991 | F19: =Carga!D26 -> 5.49372
A20: Recargas (equipos) | B20: =Carga!B29 -> 10822.075 | C20: =Carga!D29 -> 541.10377 | D20: =Carga!O10 -> Dic | E20: — | F20: —
A22: 2) BALANCEO DE CADA LÍNEA
A23: Línea | B23: Cuello de botella | C23: Aprovech. del cuello (mes de cálculo) | D23: Eficiencia de balanceo | E23: Aprovech. máximo con los cambios de la rueda | F23: Aprovech. del cuello en el mes pico de la línea | G23: Mes pico | H23: Estado
A24: Manuales | B24: =Carga!$C$66 -> Soldadura longitudinal — 2,5 a 10 kg | C24: =Carga!$C$67 -> 0.79491735 | D24: =Carga!$C$69 -> 0.77801978 | E24: =MAX(Rueda!Y8:Y29,Lotes!L22:L23,Lotes!H42) -> 0.81209623 | F24: =IF(MES=Carga!$N$8,MAX(Rueda!Y8:Y29,Lotes!L22:L23,Lotes!H42),"Dejar C4 vacío") -> 0.81209623 | G24: =Carga!O8 -> Ene | H24: =IF(MAX(E24,IF(ISNUMBER(F24),F24,0))<=UMBRAL,"OK","Revisar") -> OK
A25: Carros | B25: =Carga!$C$95 -> Soldadura de accesorios | C25: =Carga!$C$96 -> 0.49512771 | D25: =Carga!$C$99 -> 0.45693569 | E25: =Carga!$C$96 -> 0.49512771 | F25: =Carga!$C$97 -> 0.5230764 | G25: =Carga!O9 -> Mar | H25: =IF(MAX(E25,IF(ISNUMBER(F25),F25,0))<=UMBRAL,"OK","Revisar") -> OK
A26: Recargas | B26: {=INDEX(Carga!B104:B126,MATCH(MAX(Carga!H104:H126),Carga!H104:H126,0))} -> Ensayo de pérdidas | C26: =MAX(Carga!H104:H126) -> 0.80163521 | D26: — | E26: =MAX(Carga!H104:H126) -> 0.80163521 | F26: =MAX(Carga!I104:I126) -> 0.87268181 | G26: =Carga!O10 -> Dic | H26: =IF(MAX(E26,IF(ISNUMBER(F26),F26,0))<=UMBRAL,"OK","Revisar") -> OK
A28: 3) PLAN SINCRONIZADO: cada cuántos días pasa cada formato por cada máquina y cuánto se hace por vez
A29: Formato | B29: Por día | C29: Ola: cada (días) | D29: Ola: lote (recipientes) | E29: Guillotina: cada (días) | F29: Guillotina: hojas por tanda | G29: Embutidora: cada (días) | H29: Embutidora: piezas por tanda (cúpula o fondo) | I29: Pulmón de desarrollos (cuerpos) | J29: Supermercado (cúpulas + fondos)
A30: Manuales 1 kg | B30: =Rueda!C35 -> 911.79288 | C30: =Rueda!H35 -> 1 | D30: =Rueda!J35 -> 911.79288 | E30: =Lotes!O8 -> 1 | F30: =Lotes!P8 -> 21 | G30: =Lotes!J30 -> 4 | H30: =Lotes!K30 -> 3647.1715 | I30: =Lotes!W8 -> 909.13615 | J30: =Lotes!O30+Lotes!O31 -> 8132.6058
A31: Manuales 2,5 kg | B31: =Rueda!C36 -> 63.568523 | C31: =Rueda!H36 -> 1 | D31: =Rueda!J36 -> 63.568523 | E31: =Lotes!O9 -> 8 | F31: =Lotes!P9 -> 19 | G31: =Lotes!J32 -> 16 | H31: =Lotes!K32 -> 1017.0964 | I31: =Lotes!W9 -> 511.54499 | J31: =Lotes!O32+Lotes!O33 -> 2142.1727
A32: Manuales 5 kg | B32: =Rueda!C37 -> 287.33696 | C32: =Rueda!H37 -> 1 | D32: =Rueda!J37 -> 287.33696 | E32: =Lotes!O10 -> 1 | F32: =Lotes!P10 -> 24 | G32: =Lotes!J34 -> 8 | H32: =Lotes!K34 -> 2298.6957 | I32: =Lotes!W10 -> 292.59739 | J32: =Lotes!O34+Lotes!O35 -> 4976.3616
A33: Manuales 10 kg | B33: =Rueda!C38 -> 17.383176 | C33: =Rueda!H38 -> 2 | D33: =Rueda!J38 -> 34.766353 | E33: =Lotes!O11 -> 16 | F33: =Lotes!P11 -> 19 | G33: =Lotes!J36 -> 16 | H33: =Lotes!K36 -> 278.13082 | I33: =Lotes!W11 -> 284.74891 | J33: =Lotes!O36+Lotes!O37 -> 589.59546
A34: Carros 25 kg (hoja 3,2) | B34: =Lotes!E12 -> 3.3035698 | C34: — | D34: — | E34: =Lotes!O12 -> 4 | F34: =Lotes!P12 -> 2 | G34: — | H34: — | I34: =Lotes!W12 -> 18.364297 | J34: —
A35: Carros 50 kg (hoja 3,2) | B35: =Lotes!E13 -> 7.2608495 | C35: — | D35: — | E35: =Lotes!O13 -> 4 | F35: =Lotes!P13 -> 5 | G35: — | H35: — | I35: =Lotes!W13 -> 30.709477 | J35: —
A36: Carros 70 + 100 kg (hoja mixta 4,75) | B36: =Lotes!E14 -> 2.6416998 | C36: — | D36: — | E36: =Lotes!O14 -> 4 | F36: =Lotes!P14 -> 3 | G36: — | H36: — | I36: =Lotes!W14 -> 12.224544 | J36: —
A37: Ola = del cilindrado al embalaje todos los puestos corren el formato el mismo día. Guillotina y embutidora hacen tandas más largas y guardan lo que sobra en el pulmón de desarrollos y en el supermercado.
A39: 4) MÁQUINAS CON CAMBIO DE FORMATO CARO
A40: Recurso | B40: Cambios por día | C40: Min de cambio por día | D40: Aprovech. con cambios | E40: Estado
A41: Guillotina 1 (manuales + carros) | B41: =Lotes!H22 -> 2.9375 | C41: =Lotes!I22 -> 44.0625 | D41: =Lotes!L22 -> 0.65422385 | E41: =Lotes!M22 -> OK
A42: Guillotina 2 (manuales + carros) | B42: =Lotes!H23 -> 2.9375 | C42: =Lotes!I23 -> 14.6875 | D42: =Lotes!L23 -> 0.37584488 | E42: =Lotes!M23 -> OK
A43: Operario de corte (si atiende G1 y G2) | B43: — | C43: — | D43: =Lotes!L24 -> 1.0300687 | E43: =Lotes!M24 -> Hacen falta 2 operarios
A44: Embutidora (8 matrices) | B44: =Lotes!F42 -> 1 | C44: =Lotes!G42 -> 90 | D44: =Lotes!H42 -> 0.47928342 | E44: =Lotes!K42 -> OK
A45: Soldadura longitudinal 2,5 a 10 kg (cuello) | B45: =Rueda!W12 -> 2.5 | C45: =Rueda!X12 -> 25 | D45: =Rueda!Y12 -> 0.81209623 | E45: =Rueda!Z12 -> OK
A46: Soldadura circunferencial (marcapasos) | B46: =Rueda!W16 -> 3.5 | C46: =Rueda!X16 -> 35 | D46: =Rueda!Y16 -> 0.73060086 | E46: =Rueda!Z16 -> OK
A48: 5) SUPERFICIE A RESERVAR EN EL LAYOUT
A49: Concepto | B49: Módulos / pallets / jaulas | C49: Unidades | D49: m² | E49: Hoja
A50: =Pulmones!A8 -> Pulmones de manuales (estantes, carros de tránsito y rack de fondos y cúpulas) | B50: =Pulmones!B8 -> 44 | C50: =Pulmones!C8 -> 20801 | D50: =Pulmones!D8 -> 108.29 | E50: Pulmones
A51: =Pulmones!A9 -> Pulmones de carros (espera del pintor y pintados) | B51: =Pulmones!B9 -> — | C51: =Pulmones!C9 -> 178 | D51: =Pulmones!D9 -> 47.250264 | E51: Pulmones
A52: =Pulmones!A10 -> Recargas en planta (jaulas) | B52: =Pulmones!B10 -> 45 | C52: =Pulmones!C10 -> 778.62206 | D52: =Pulmones!D10 -> 108 | E52: Pulmones
A53: =Pulmones!A11 -> Almacén de producto terminado (con andén y carros de manipulación) | B53: =Pulmones!B11 -> 85 | C53: =Pulmones!C11 -> — | D53: =Pulmones!D11 -> 272.552 | E53: Pulmones
A54: =Pulmones!A12 -> Almacén de materia prima | B54: =Pulmones!B12 -> 119 | C54: =Pulmones!C12 -> — | D54: =Pulmones!D12 -> 221.76 | E54: Pulmones
A55: =Pulmones!A13 -> MP al pie de los puestos | B55: =Pulmones!B13 -> — | C55: =Pulmones!C13 -> — | D55: =Pulmones!D13 -> 35.45 | E55: Pulmones
A56: Total a reservar | D56: =SUM(D50:D55) -> 793.30226
A58: 6) CONTROLES
A59: Control | B59: Valor | C59: Debe dar | D59: Estado
A60: Aprovechamiento de manuales igual al de la planilla (mayor diferencia; solo con el mes pico; sin el puesto 6, que se cambió por el marcado unificado) | B60: {=IF(C4="",SUMPRODUCT(MAX(ABS(Carga!V34:V59-INDEX(Datos!B263:K288,0,ANIO-2025))*(Carga!A34:A59<>6))),"—")} -> 6.800005e-11 | C60: menos de 0,5 % | D60: =IF(B60="—","Solo con el mes pico",IF(B60<0.005,"OK","Revisar")) -> OK
A61: Puestos de la ola por encima del 90 % con la rueda | B61: =COUNTIF(Rueda!Z8:Z29,"Pasa el umbral") -> 0 | C61: 0 | D61: =IF(B61=0,"OK","Revisar") -> OK
A62: Días del calendario con un puesto por encima del 100 % | B62: =COUNTIF(Rueda!C43:V65,">1") -> 0 | C62: 0 | D62: =IF(B62=0,"OK","Mover fases") -> OK
A63: Guillotinas y embutidora dentro del 90 % | B63: =MAX(Lotes!L22:L23,Lotes!H42) -> 0.65422385 | C63: ≤ 90 % | D63: =IF(B63<=UMBRAL,"OK","Revisar") -> OK
A64: Stock de producto terminado nunca negativo | B64: =MIN(Pulmones!D56:D63) -> 18.449281 | C64: ≥ 0 | D64: =IF(B64>=0,"OK","Revisar") -> OK
A65: Carros y recargas dentro del 90 % en su propio mes pico | B65: =MAX(F25:F26) -> 0.87268181 | C65: ≤ 90 % | D65: =IF(B65<=UMBRAL,"OK","Revisar") -> OK
A67: 7) EN PALABRAS
A68: ="Ola de manuales (del cilindrado al embalaje; marca el paso la soldadura circunferencial): 1 kg "&IF(Rueda!H35<=1,"todos los días","cada "&Rueda!H35&" días")&" · 2,5 kg "&IF(Rueda!H36<=1,"todos los días","cada "&Rueda!H36&" días")&" · 5 kg "&IF(Rueda!H37<=1,"todos los días","cada "&Rueda!H37&" días")&" · 10 kg "&IF(Rueda!H38<=1,"todos los días","cada "&Rueda!H38&" días")&"." -> Ola de manuales (del cilindrado al embalaje; marca el paso la soldadura circunferencial): 1 kg todos los días · 2,5 kg todos los días · 5 kg todos los días · 10 kg cada 2 días.
A69: ="Guillotinas: 1 kg cada "&Lotes!O8&" día(s) ("&Lotes!P8&" hojas) · 2,5 kg cada "&Lotes!O9&" ("&Lotes!P9&" hojas) · 5 kg cada "&Lotes!O10&" ("&Lotes!P10&" hojas) · 10 kg cada "&Lotes!O11&" ("&Lotes!P11&" hojas) · carros cada "&Lotes!O12&" días." -> Guillotinas: 1 kg cada 1 día(s) (21 hojas) · 2,5 kg cada 8 (19 hojas) · 5 kg cada 1 (24 hojas) · 10 kg cada 16 (19 hojas) · carros cada 4 días.
A70: ="Embutidora (cúpula y fondo): 1 kg cada "&Lotes!J30&" días · 2,5 kg cada "&Lotes!J32&" · 5 kg cada "&Lotes!J34&" · 10 kg cada "&Lotes!J36&". Cambios de matriz por mes: "&FIXED(Lotes!J42,0)&" (la planilla suponía 32)." -> Embutidora (cúpula y fondo): 1 kg cada 4 días · 2,5 kg cada 16 · 5 kg cada 8 · 10 kg cada 16. Cambios de matriz por mes: 20 (la planilla suponía 32).
A71: ="Cuello: "&Carga!$C$66&" ("&FIXED(Rueda!Y12*100,0)&" % con los cambios). Por su capacidad no se puede juntar más de "&FIXED(Rueda!E36,1)&" días de 2,5 kg ni más de "&FIXED(Rueda!E38,1)&" de 10 kg." -> Cuello: Soldadura longitudinal — 2,5 a 10 kg (81 % con los cambios). Por su capacidad no se puede juntar más de 1.6 días de 2,5 kg ni más de 3.2 de 10 kg.
A72: ="Hay que reservar "&FIXED(D56,0)&" m² entre pulmones, almacenes y MP al pie de los puestos." -> Hay que reservar 793 m² entre pulmones, almacenes y MP al pie de los puestos.

Sheet Parametros
A1: PARÁMETROS — los supuestos y datos que usa todo el libro
A2: Amarillo = criterio del grupo (se puede cambiar) · Verde = dato de las planillas o de los Words (se puede corregir) · Blanco = fórmula. La columna G dice de dónde sale cada valor.
A3: ▶ Solo se tocan las celdas amarillas y verdes. Los nombres (DIAS, R_CORRIDA, S_G1…) son los que usan las fórmulas de las otras hojas.
A5: 1) JORNADA Y CAPACIDAD
A6: Parámetro | B6: Valor | C6: Unidad | G6: Fuente / criterio | H6: Nombre
A7: Días hábiles por mes | B7: 20 | C7: días | G7: Aprovechamiento Manuales / Carros / Recargas, parametros B2 | H7: DIAS
A8: Horas por turno | B8: 8 | C8: h | G8: parametros B3 de las planillas de aprovechamiento | H8: H_TURNO
A9: Refrigerio y pausas por turno | B9: 30 | C9: min | G9: parametros B4 de las planillas de aprovechamiento | H9: REFRIG
A10: Minutos productivos por turno | B10: =H_TURNO*60-REFRIG -> 450 | C10: min | G10: Horas × 60 − refrigerio (= 450 min = 7,5 h productivas) | H10: MIN_TURNO
A11: Horas productivas por mes (1 turno) | B11: =DIAS*MIN_TURNO/60 -> 150 | C11: h | G11: Días × horas productivas (= 150 h, igual que las planillas) | H11: HORAS_MES
A12: Umbral de aprovechamiento | B12: 0.9 | C12: % | G12: Límite duro del grupo (Word de recargas § 8), el mismo de las planillas | H12: UMBRAL
A14: 2) LOTES: cuánto seguir procesando antes de cambiar de formato
A15: Parámetro | B15: Valor | C15: Unidad | G15: Fuente / criterio | H15: Nombre
A16: Base de la rueda (cada cuántos días se repite el ciclo más corto) | B16: 1 | C16: días | G16: Criterio: rueda diaria; las frecuencias son 1, 2, 4, 8 o 16 días (potencias de 2 para que encajen) | H16: BASE
A17: Relación mínima corrida / cambio | B17: 3 | C17: veces | G17: Criterio del «punto de seguir procesando»: cada tanda tiene que durar al menos 3 veces lo que el cambio. Así el cambio nunca pasa del 25 % del tiempo de la tanda. Subirlo agranda los lotes y los pulmones | H17: R_CORRIDA
A18: Frecuencia máxima (cobertura máxima de un lote) | B18: 16 | C18: días | G18: Criterio: ningún lote cubre más de 16 días hábiles (menos de un mes), para no inmovilizar stock ni perder FIFO | H18: K_MAX
A20: 3) CAMBIOS DE FORMATO Y GUILLOTINAS
A21: Parámetro | B21: Valor | C21: Unidad | G21: Fuente / criterio | H21: Nombre
A22: Guillotina 1: programa del tope y primera pieza por formato | B22: 5 | C22: min | G22: parametros_manuales C53 (5 min por cambio) | H22: S_G1_PROG
A23: Guillotina 1: traer y devolver el paquete de chapa (máquina parada) | B23: 10 | C23: min | G23: Word de carros, puesto 2: 2 viajes de 5 min por paquete. Es tiempo inoperativo de la G1 | H23: S_G1_PAQ
A24: Guillotina 1: tiempo total de cambio de formato | B24: =S_G1_PROG+S_G1_PAQ -> 15 | C24: min | G24: Suma de las dos filas de arriba | H24: S_G1
A25: Guillotina 2: cambio de tope por formato | B25: 5 | C25: min | G25: parametros_manuales C54 | H25: S_G2
A26: Embutidora: cambio de matriz | B26: 90 | C26: min | G26: parametros_manuales C55 de la planilla de aprovechamiento (90 min). El Word de manuales dice «unos 120 minutos». Con 120: el 5 kg pasa a prensarse cada 16 días, la prensa queda en 50 % y los pulmones de manuales suben unos 15 m² (ver Guía). | H26: S_EMB
A27: Alistamiento de cada guillotina al empezar el turno | B27: 10 | C27: min/turno | G27: SUPUESTO: encender, verificar barreras fotoeléctricas y tope, calentar el hidráulico y preparar ventosas y EPP. Si el Excel original de PCP tiene el tpr de la guillotina, poner ese. | H27: ALIST_G
A28: Desalistamiento de cada guillotina al terminar el turno | B28: 10 | C28: min/turno | G28: SUPUESTO: limpiar la mesa de bolas, llevar las orillas al contenedor de scrap, ordenar los carros y apagar. Si el Excel original de PCP tiene el tdl, poner ese. | H28: DESALIST_G
A29: Rendimiento del operario de corte | B29: 0.85 | C29: % | G29: SUPUESTO: el tiempo por corte (0,3 min) y por hoja (2 min) es manual; como en los otros puestos (tiempo tipo = (tpr + tdl + ta) ÷ rendimiento), se divide por el rendimiento (15 % de suplementos por fatiga y necesidades). | H29: REND_CORTE
A30: Guillotina 1: tiras y piezas de accesorios de carros | B30: 8.6 | C30: min/día | G30: parametros_manuales G53 (W-CAR: placas 1,7 + patas 1,9 + 5,0 min/día en el pico) | H30: TIRAS_CARROS
A31: Guillotina 1: resto de los cortes de accesorios de carros | B31: 36.2 | C31: min/día | G31: Word de carros, puesto 2, tabla de tiempo en el pico: tiras de 40 mm 10,1 + tiras para triángulos 8,1 + piezas de accesorios a largo 18,0. La planilla solo tenía las placas y las patas (fila 23). | H31: TIRAS_EXTRA
A33: 4) PULMONES ENTRE PUESTOS
A34: Parámetro | B34: Valor | C34: Unidad | G34: Fuente / criterio | H34: Nombre
A35: Protección antes del cuello de botella (soldadura longitudinal 2,5 a 10 kg) | B35: 1 | C35: h | G35: Pulmones 2035: la protección de 1 h va solo antes del cuello (virolas de 2,5 a 10 kg). Lotes!W la sigue sumando al pulmón de cada tanda, que queda como referencia por formato (Figura 6) | H35: H_PROT
A36: Protección antes del marcapasos (soldadura circunferencial), en las dos ramas | B36: 3.75 | C36: h | G36: Medio turno (Word de manuales). Va en las cúpulas con cuello y los cuerpos bordoneados. Si se baja a 1 h, esos dos pulmones bajan a la mitad | H36: H_PROT_MARC
A37: Stock de seguridad del supermercado de cúpulas y fondos | B37: 1 | C37: días | G37: Criterio: 1 día de consumo de cada pieza por si la prensa se demora en volver al formato | H37: SS_SUPER
A38: Hojas en el pulmón de franjas (mesa elevadora 2, entre G1 y G2) | B38: 2 | C38: hojas | G38: Layout rev. 10: mesa elevadora 2 como pulmón de franjas; la G2 empieza con la primera hoja | H38: N_HOJAS_FRANJA
A39: Contenedores vacíos en retorno por pulmón | B39: 1 | C39: u | G39: Ya no se usa: desde Pulmones 2035 los vacíos vuelven en los carros de tránsito (sección 10) | H39: CONT_RET
A40: Carga útil del carro de plataforma de desarrollos | B40: 300 | C40: kg | G40: Ya no se usa: desde Pulmones 2035 los desarrollos van en bandejas (sección 7) | H40: CARGA_PLAT
A42: 5) PRODUCTO TERMINADO Y ALMACÉN
A43: Parámetro | B43: Valor | C43: Unidad | G43: Fuente / criterio | H43: Nombre
A44: Stock de seguridad de producto terminado (manuales) | B44: 5 | C44: días de venta | G44: Criterio: una semana hábil de venta promedio del modelo | H44: SS_PT
A45: Niveles de rack de pallets en el almacén de PT | B45: 3 | C45: niveles | G45: Criterio: rack selectivo de 3 niveles (el autoelevador Heli CPCD50 tiene torre de 3 a 6 m) | H45: PT_NIV
A46: Superficie por columna de rack (pallet 1,2 × 1,0 m + mitad del pasillo de 5 m) | B46: 3.7 | C46: m² | G46: Pasillo de 5 m del Word de carros (radio de giro 2,93 m + pallet + margen): 1,0 × (1,2 + 2,5) | H46: PT_M2_POS
A47: Stock de carros liberados (días de venta) | B47: 5 | C47: días | G47: Word de carros: lote semanal; se libera y se despacha | H47: DIAS_PT_CARROS
A48: Superficie por carro terminado en piso (con circulación) | B48: 0.71 | C48: m² | G48: Word de carros, depósito 16: 280 carros (180 retenidos + 100 liberados) en ≈200 m² | H48: M2_CARRO_PT
A50: 6) RECARGAS
A51: Parámetro | B51: Valor | C51: Unidad | G51: Fuente / criterio | H51: Nombre
A52: Matafuegos por jaula paletizable (1,2 × 1,0 m) | B52: 28 | C52: u | G52: Word de recargas (Anotaciones) y Detalle recargas: jaula A = 72 de 1 kg; jaula B = 30 de 2,5 kg, 24 de 5 kg o 16 de 10 kg; rodantes 1 o 2. Con la mezcla de la planta industrial en el pico (552 u/día en 16,96 jaulas/día) y el factor 1,15 de jaulas a medio llenar: 552 ÷ 16,96 ÷ 1,15 ≈ 28 por jaula. (Antes se había supuesto 40.) | H52: U_JAULA
A53: Superficie por jaula en piso (con circulación) | B53: 2.4 | C53: m² | G53: Detalle recargas, Supuestos § 3: 2,4 m² por posición con pasillo compartido por dos filas. (Antes se había supuesto 1,8.) | H53: M2_JAULA
A54: Pulmón de recepción (días de recargas que esperan entrar) | B54: 0.5 | C54: días | G54: Criterio: el lote retirado por la tarde entra a la mañana siguiente | H54: DIAS_REC_RECEP
A55: Pulmón de despacho (días de recargas listas para el recorrido) | B55: 0.5 | C55: días | G55: Criterio: el camión sale con el lote del día | H55: DIAS_REC_DESP
A56: Espera media frente a cada puesto de recargas | B56: 0.5 | C56: h | G56: Criterio para la ley de Little (WIP = ritmo × tiempo en el puesto) | H56: ESPERA_REC_H
A58: 7) UNIDADES DE CARGA DE LOS PULMONES (piezas por bandeja o cajón, niveles por módulo de estante y m² del módulo)
A59: Pieza / unidad de carga | B59: 1 kg | C59: 2,5 kg | D59: 5 kg | E59: 10 kg | F59: m² del módulo | G59: Fuente | H59: Nombre
A60: Desarrollos — por bandeja (pila sobre bandeja de 1.200 × 600, hasta 150 kg) | B60: 254 | C60: 147 | D60: 76 | E60: 34 | G60: Pulmones 2035, Unidades fila 6: pila por peso, 150 kg ÷ peso del desarrollo
A61: Desarrollos — niveles por módulo de estante | B61: 5 | C61: 5 | D61: 6 | E61: 8 | G61: Unidades fila 9: niveles cuyo piso queda a 1,6 m o menos
A62: Virolas, cuerpos y cilindros — por bandeja (parados) | B62: 105 | C62: 36 | D62: 21 | E62: 18 | G62: Unidades filas 13 y 20: (1.200 ÷ Ø) × (600 ÷ Ø), sin pasar 150 kg
A63: Virolas, cuerpos y cilindros — niveles por módulo | B63: 4 | C63: 4 | D63: 3 | E63: 3 | G63: Unidades filas 16 y 23
A64: Matafuegos — por bandeja (parados, con válvula) | B64: 72 | C64: 34 | D64: 18 | E64: 9 | G64: Unidades fila 27: en el 10 kg manda el peso (9 de 18 lugares)
A65: Matafuegos — niveles por módulo | B65: 3 | C65: 3 | D65: 3 | E65: 2 | G65: Unidades fila 30
A66: Fondos — por cajón de 600 × 400 × 300 (anidados) | B66: 288 | C66: 88 | D66: 48 | E66: 27 | G66: Unidades fila 34: columnas anidadas, sin pasar 20 kg con el cajón. Medir pollera y domo en una pieza
A67: Cúpulas — por cajón (anidadas) | B67: 288 | C67: 80 | D67: 36 | E67: 21 | G67: Unidades fila 41
A68: Cúpulas con cuello — por cajón | B68: 100 | C68: 40 | D68: 30 | E68: 19 | G68: Unidades fila 48 (Word de manuales)
A69: Módulo de estante de carga media 1,2 × 0,6 × 2,0 m: cajones por módulo (B, 4 niveles × 3) y m² con medio pasillo de 1,2 m (F) | B69: 12 | F69: 1.44 | G69: Pulmones 2035, Parametros B15 y B24: 1,2 × 0,6 + 1,2 × 0,6 de medio pasillo | H69: CAJ_MOD · M2_MOD
A71: 8) PESOS POR MODELO (kg)
A72: Pieza | B72: 1 kg | C72: 2,5 kg | D72: 5 kg | E72: 10 kg | G72: Fuente
A73: Cuerpo cortado (desarrollo) | B73: 0.59 | C73: 1.02 | D73: 1.97 | E73: 4.38 | G73: Word de manuales, tabla «Pesos de las piezas»
A74: Cúpula | B74: 0.04 | C74: 0.21 | D74: 0.42 | E74: 0.71 | G74: Word de manuales, tabla «Pesos de las piezas». Cúpula del 10 kg ajustada a 2,0 mm (0,57 × 2,0 ÷ 1,6 = 0,71 kg), decisión del grupo
A75: Fondo | B75: 0.05 | C75: 0.19 | D75: 0.34 | E75: 0.57 | G75: Word de manuales, tabla «Pesos de las piezas». Fondo del 1 kg ajustado a 0,9 mm (0,07 × 0,9 ÷ 1,25 = 0,05 kg), decisión del grupo
A76: Recipiente vacío | B76: 0.71 | C76: 1.35 | D76: 2.6 | E76: 5.48 | G76: Word de manuales, ajustado por el cambio de espesor del fondo del 1 kg (−0,02 kg) y de la cúpula del 10 kg (+0,14 kg)
A77: Matafuego terminado (con agente y válvula) | B77: 2.08 | C77: 4.3 | D77: 8.1 | E77: 15.94 | G77: Word de manuales, con el mismo ajuste de la fila 68
A79: 9) PALLETS DE PRODUCTO TERMINADO (unidades por pallet de 1.200 × 1.000 mm)
A80: Producto | B80: 1 kg | C80: 2,5 kg | D80: 5 kg | E80: 10 kg | G80: Fuente
A81: Matafuegos nuevos en caja por pallet (cajas paradas) | B81: 360 | C81: 168 | D81: 84 | E81: 60 | G81: Word de PT (PT+PINTADO-FLAMA2035, Pallets filas 7 a 18): pallet ARLOG 1.200 × 1.000, hasta 1,6 m y 1.100 kg
A82: Cilindros vacíos por pallet (parados, con cartón entre capas) | B82: 780 | C82: 288 | D82: 126 | E82: 60 | G82: Word de PT (Pallets filas 22 a 33)
A83: 10) PULMONES 2035: CARROS DE TRÁNSITO, RACK DE FONDOS Y CÚPULAS Y LÍNEA DE CARROS
A84: Parámetro | B84: Valor | C84: Unidad | G84: Fuente / criterio | H84: Nombre
A85: Carros por tramo | B85: 1 | C85: u | G85: Uno solo: pasa las bandejas al estante y vuelve; mientras viaja, el que entrega deja la bandeja en un soporte fijo. Sin estante, el carro es el pulmón (Pulmones 2035, Parametros B39) | H85: CARROS_TRAMO
A86: Bandejas por carro porta-bandejas | B86: 3 | C86: u | G86: Tres niveles a la altura de los del estante | H86: CARRO_BAND
A87: m² del lugar del carro (1,3 × 0,7 m con maniobra) | B87: 1 | C87: m² | G87: Pulmones 2035, Parametros B42 | H87: M2_CARRO
A88: Cúpulas con cuello: cada cuánto llega un carro | B88: 1 | C88: h | G88: La soldadura del cuello repone lo que la circunferencial usó (un viaje por hora) | H88: H_VIAJE_CUP
A89: Cajones por pallet (1.200 × 800, un solo modelo) | B89: 12 | C89: u | G89: 4 cajones por capa y 3 capas; 1.045 mm de alto | H89: PAL_CAJ
A90: Niveles del rack de fondos y cúpulas | B90: 3 | C90: u | G90: Primer nivel a 400 mm (picking); los de arriba, reserva | H90: RACK_NIV
A91: Pallets por nivel en un vano | B91: 3 | C91: u | G91: Vano de 2,7 m, pallets de 800 de frente | H91: RACK_PPV
A92: Frente del vano | B92: 2.7 | C92: m | H92: RACK_VANO
A93: Fondo del rack | B93: 1.2 | C93: m | G93: Pallet de 1.200 de fondo | H93: RACK_FONDO
A94: Pasillo del autoelevador (se cuenta la mitad) | B94: 3.5 | C94: m | H94: PASILLO_AE
A95: Factor de circulación para lo que espera en el piso (carros) | B95: 1.4 | C95: × | G95: Igual que en PT | H95: F_CIRC
A96: Días de espera para la pintura (envío cada 2 días) | B96: 2 | C96: días | G96: Análisis de PT (Pintura, DIAS_PINT) | H96: DIAS_ESPERA
A97: Días en el pintor | B97: 3 | C97: días | G97: Carga X87 (3 días hábiles) | H97: DIAS_PINTOR
A98: Días que espera el pintado (vuelve el envío entero junto) | B98: 2 | C98: días | G98: La Master trae de una vez los pintados de un envío y la carga de polvo hace 14 por día: el máximo es el envío entero | H98: DIAS_PINTADOS
A99: Días de retención de los carros terminados (no se retienen) | B99: 0 | C99: días | G99: Decisión del grupo: no se retiene 7 días; los terminados pasan al almacén de PT y el operario verifica en el manómetro que cada carro esté presurizado al cargarlo en el camión de despacho | H99: DIAS_RET
A100: Carros por tramo donde el que entrega no puede parar (cuello y horno de pintura) | B100: 2 | C100: u | G100: Pulmones 2035, Parametros B43: mientras un carro viaja, el otro recibe | H100: CARROS_CRIT
A101: Recipiente de carro | B101: 25 kg | C101: 50 kg | D101: 70 kg | E101: 100 kg | G101: Fuente
A102: Ø del recipiente (mm) | B102: 276.5 | C102: 320 | D102: 390 | E102: 390 | G102: Word de carros
A103: m² de piso del carro con accesorios (largo × ancho) | B103: 0.33 | C103: 0.42 | D103: 0.56 | E103: 0.6 | G103: palletizado_PT: 600 × 550, 700 × 600, 800 × 700 y 800 × 750 mm

Sheet Carga
A1: PASO 1 — CUÁNTO HAY QUE HACER Y CUÁNTO CARGA CADA PUESTO (mes de cálculo)
A2: Producción del mes por modelo (plan con sobrestock) y carga de cada puesto de manuales, carros y recargas. Carga = Σ unidades del modelo × tiempo del modelo. Aprovechamiento = carga ÷ (máquinas × turnos × 450 min).
A3: ▶ Mirá la columna V de manuales, P y Q de carros e H e I de recargas (aprovechamiento) y el cuello marcado. Ninguno debe pasar el 90 %.
A4: Mes | B4: {=INDEX($B$7:$M$7,1,MES)&" "&ANIO} -> Ene 2035
A6: 1) PRODUCCIÓN DE CADA LÍNEA POR MES (para encontrar el mes pico)
A7: Línea | B7: Ene | C7: Feb | D7: Mar | E7: Abr | F7: May | G7: Jun | H7: Jul | I7: Ago | J7: Sep | K7: Oct | L7: Nov | M7: Dic | N7: Mes pico (n.°) | O7: Mes pico
A8: Manuales (recipientes, con sobrestock) | B8: =SUMPRODUCT($B$14:$B$17,Datos!E$173:E$176) -> 25601.631 | C8: =SUMPRODUCT($B$14:$B$17,Datos!F$173:F$176) -> 24783.212 | D8: =SUMPRODUCT($B$14:$B$17,Datos!G$173:G$176) -> 23166.215 | E8: =SUMPRODUCT($B$14:$B$17,Datos!H$173:H$176) -> 22153.112 | F8: =SUMPRODUCT($B$14:$B$17,Datos!I$173:I$176) -> 20730.799 | G8: =SUMPRODUCT($B$14:$B$17,Datos!J$173:J$176) -> 20321.589 | H8: =SUMPRODUCT($B$14:$B$17,Datos!K$173:K$176) -> 21743.902 | I8: =SUMPRODUCT($B$14:$B$17,Datos!L$173:L$176) -> 24783.212 | ... M8: =SUMPRODUCT($B$14:$B$17,Datos!P$173:P$176) -> 25601.631 | N8: =MATCH(MAX(B8:M8),B8:M8,0) -> 1 | O8: =INDEX($B$7:$M$7,1,N8) -> Ene
A9: Carros (recipientes) | B9: =SUMIFS(Datos!E$90:E$169,Datos!$A$90:$A$169,ANIO) -> 264.12238 | C9: =SUMIFS(Datos!F$90:F$169,Datos!$A$90:$A$169,ANIO) -> 233.04916 | D9: =SUMIFS(Datos!G$90:G$169,Datos!$A$90:$A$169,ANIO) -> 279.65899 | E9: =SUMIFS(Datos!H$90:H$169,Datos!$A$90:$A$169,ANIO) -> 279.65899 | F9: =SUMIFS(Datos!I$90:I$169,Datos!$A$90:$A$169,ANIO) -> 279.65899 | G9: =SUMIFS(Datos!J$90:J$169,Datos!$A$90:$A$169,ANIO) -> 248.58577 | H9: =SUMIFS(Datos!K$90:K$169,Datos!$A$90:$A$169,ANIO) -> 279.65899 | I9: =SUMIFS(Datos!L$90:L$169,Datos!$A$90:$A$169,ANIO) -> 279.65899 | ... M9: =SUMIFS(Datos!P$90:P$169,Datos!$A$90:$A$169,ANIO) -> 248.58577 | N9: =MATCH(MAX(B9:M9),B9:M9,0) -> 3 | O9: =INDEX($B$7:$M$7,1,N9) -> Mar
A10: Recargas (equipos recibidos) | B10: =SUMIFS(Datos!C$312:C$541,Datos!$A$312:$A$541,"Recepción y registro",Datos!$B$312:$B$541,ANIO) -> 10822.075 | C10: =SUMIFS(Datos!D$312:D$541,Datos!$A$312:$A$541,"Recepción y registro",Datos!$B$312:$B$541,ANIO) -> 9391.2625 | D10: =SUMIFS(Datos!E$312:E$541,Datos!$A$312:$A$541,"Recepción y registro",Datos!$B$312:$B$541,ANIO) -> 8906.0301 | E10: =SUMIFS(Datos!F$312:F$541,Datos!$A$312:$A$541,"Recepción y registro",Datos!$B$312:$B$541,ANIO) -> 9801.73 | F10: =SUMIFS(Datos!G$312:G$541,Datos!$A$312:$A$541,"Recepción y registro",Datos!$B$312:$B$541,ANIO) -> 9879.3585 | G10: =SUMIFS(Datos!H$312:H$541,Datos!$A$312:$A$541,"Recepción y registro",Datos!$B$312:$B$541,ANIO) -> 9758.7033 | H10: =SUMIFS(Datos!I$312:I$541,Datos!$A$312:$A$541,"Recepción y registro",Datos!$B$312:$B$541,ANIO) -> 8689.6915 | I10: =SUMIFS(Datos!J$312:J$541,Datos!$A$312:$A$541,"Recepción y registro",Datos!$B$312:$B$541,ANIO) -> 8770.0961 | ... M10: =SUMIFS(Datos!N$312:N$541,Datos!$A$312:$A$541,"Recepción y registro",Datos!$B$312:$B$541,ANIO) -> 11781.204 | N10: =MATCH(MAX(B10:M10),B10:M10,0) -> 12 | O10: =INDEX($B$7:$M$7,1,N10) -> Dic
A12: 2) MANUALES — QUÉ HAY QUE HACER POR DÍA EN EL MES DE CÁLCULO
A13: Modelo | B13: Producción del año (u) | C13: % del año que se hace este mes | D13: Terminados por día | E13: Cilindros vacíos por día | F13: Recipientes por día | G13: Mezcla | H13: Ventas del mes (u) | I13: Sobrestock del mes (u)
A14: 1 kg | B14: =SUMIFS(Datos!$Q$7:$Q$86,Datos!$A$7:$A$86,ANIO,Datos!$D$7:$D$86,$A14) -> 202620.64 | C14: {=INDEX(Datos!$E$173:$P$173,1,MES)} -> 0.09 | D14: =SUMIFS(Datos!$Q$7:$Q$86,Datos!$A$7:$A$86,ANIO,Datos!$D$7:$D$86,$A14,Datos!$C$7:$C$86,"Terminado")*C14/DIAS -> 144.32688 | E14: =SUMIFS(Datos!$Q$7:$Q$86,Datos!$A$7:$A$86,ANIO,Datos!$D$7:$D$86,$A14,Datos!$C$7:$C$86,"Cilindro")*C14/DIAS -> 767.466 | F14: =D14+E14 -> 911.79288 | G14: =IF($F$18=0,0,F14/$F$18) -> 0.71229281 | H14: {=SUMIFS(INDEX(Datos!$E$7:$P$86,0,MES),Datos!$A$7:$A$86,ANIO,Datos!$D$7:$D$86,$A14)} -> 24314.477 | I14: =F14*DIAS-H14 -> -6078.6192
A15: 2,5 kg | B15: =SUMIFS(Datos!$Q$7:$Q$86,Datos!$A$7:$A$86,ANIO,Datos!$D$7:$D$86,$A15) -> 14126.338 | C15: {=INDEX(Datos!$E$174:$P$174,1,MES)} -> 0.09 | D15: =SUMIFS(Datos!$Q$7:$Q$86,Datos!$A$7:$A$86,ANIO,Datos!$D$7:$D$86,$A15,Datos!$C$7:$C$86,"Terminado")*C15/DIAS -> 33.464063 | E15: =SUMIFS(Datos!$Q$7:$Q$86,Datos!$A$7:$A$86,ANIO,Datos!$D$7:$D$86,$A15,Datos!$C$7:$C$86,"Cilindro")*C15/DIAS -> 30.10446 | F15: =D15+E15 -> 63.568523 | G15: =IF($F$18=0,0,F15/$F$18) -> 0.049659745 | H15: {=SUMIFS(INDEX(Datos!$E$7:$P$86,0,MES),Datos!$A$7:$A$86,ANIO,Datos!$D$7:$D$86,$A15)} -> 1412.6338 | I15: =F15*DIAS-H15 -> -141.26338
A16: 5 kg | B16: =SUMIFS(Datos!$Q$7:$Q$86,Datos!$A$7:$A$86,ANIO,Datos!$D$7:$D$86,$A16) -> 63852.659 | C16: {=INDEX(Datos!$E$175:$P$175,1,MES)} -> 0.09 | D16: =SUMIFS(Datos!$Q$7:$Q$86,Datos!$A$7:$A$86,ANIO,Datos!$D$7:$D$86,$A16,Datos!$C$7:$C$86,"Terminado")*C16/DIAS -> 138.6674 | E16: =SUMIFS(Datos!$Q$7:$Q$86,Datos!$A$7:$A$86,ANIO,Datos!$D$7:$D$86,$A16,Datos!$C$7:$C$86,"Cilindro")*C16/DIAS -> 148.66956 | F16: =D16+E16 -> 287.33696 | G16: =IF($F$18=0,0,F16/$F$18) -> 0.2244677 | H16: {=SUMIFS(INDEX(Datos!$E$7:$P$86,0,MES),Datos!$A$7:$A$86,ANIO,Datos!$D$7:$D$86,$A16)} -> 6385.2659 | I16: =F16*DIAS-H16 -> -638.52659
A17: 10 kg | B17: =SUMIFS(Datos!$Q$7:$Q$86,Datos!$A$7:$A$86,ANIO,Datos!$D$7:$D$86,$A17) -> 3862.9281 | C17: {=INDEX(Datos!$E$176:$P$176,1,MES)} -> 0.09 | D17: =SUMIFS(Datos!$Q$7:$Q$86,Datos!$A$7:$A$86,ANIO,Datos!$D$7:$D$86,$A17,Datos!$C$7:$C$86,"Terminado")*C17/DIAS -> 8.3021764 | E17: =SUMIFS(Datos!$Q$7:$Q$86,Datos!$A$7:$A$86,ANIO,Datos!$D$7:$D$86,$A17,Datos!$C$7:$C$86,"Cilindro")*C17/DIAS -> 9.081 | F17: =D17+E17 -> 17.383176 | G17: =IF($F$18=0,0,F17/$F$18) -> 0.013579741 | H17: {=SUMIFS(INDEX(Datos!$E$7:$P$86,0,MES),Datos!$A$7:$A$86,ANIO,Datos!$D$7:$D$86,$A17)} -> 386.29281 | I17: =F17*DIAS-H17 -> -38.629281
A18: Total | B18: =SUM(B14:B17) -> 284462.56 | C18: =IF(B18=0,0,F18*DIAS/B18) -> 0.09 | D18: =SUM(D14:D17) -> 324.76052 | E18: =SUM(E14:E17) -> 955.32102 | F18: =SUM(F14:F17) -> 1280.0815 | G18: =SUM(G14:G17) -> 1 | H18: =SUM(H14:H17) -> 32498.669 | I18: =SUM(I14:I17) -> -6897.0384
A19: Sobrestock del mes: positivo = se fabrica de más para guardar; negativo = sale del stock hecho antes (ver Pulmones, sección 4).
A20: 3) CARROS — QUÉ HAY QUE HACER POR DÍA EN EL MES DE CÁLCULO
A21: Modelo | B21: Producción del año (u) | C21: Terminados por día | D21: Cilindros vacíos por día | E21: Carros por día | F21: Mezcla
A22: 25 kg | B22: =SUMIFS(Datos!$Q$90:$Q$169,Datos!$A$90:$A$169,ANIO,Datos!$D$90:$D$169,$A22) -> 777.31053 | C22: {=SUMIFS(INDEX(Datos!$E$90:$P$169,0,MES),Datos!$A$90:$A$169,ANIO,Datos!$D$90:$D$169,$A22,Datos!$C$90:$C$169,"Terminado")/DIAS} -> 1.9280998 | D22: {=SUMIFS(INDEX(Datos!$E$90:$P$169,0,MES),Datos!$A$90:$A$169,ANIO,Datos!$D$90:$D$169,$A22,Datos!$C$90:$C$169,"Cilindro")/DIAS} -> 1.37547 | E22: =C22+D22 -> 3.3035698 | F22: =IF($E$26=0,0,E22/$E$26) -> 0.25015447
A23: 50 kg | B23: =SUMIFS(Datos!$Q$90:$Q$169,Datos!$A$90:$A$169,ANIO,Datos!$D$90:$D$169,$A23) -> 1708.4352 | C23: {=SUMIFS(INDEX(Datos!$E$90:$P$169,0,MES),Datos!$A$90:$A$169,ANIO,Datos!$D$90:$D$169,$A23,Datos!$C$90:$C$169,"Terminado")/DIAS} -> 4.2414795 | D23: {=SUMIFS(INDEX(Datos!$E$90:$P$169,0,MES),Datos!$A$90:$A$169,ANIO,Datos!$D$90:$D$169,$A23,Datos!$C$90:$C$169,"Cilindro")/DIAS} -> 3.01937 | E23: =C23+D23 -> 7.2608495 | F23: =IF($E$26=0,0,E23/$E$26) -> 0.54980948
A24: 70 kg | B24: =SUMIFS(Datos!$Q$90:$Q$169,Datos!$A$90:$A$169,ANIO,Datos!$D$90:$D$169,$A24) -> 374.12986 | C24: {=SUMIFS(INDEX(Datos!$E$90:$P$169,0,MES),Datos!$A$90:$A$169,ANIO,Datos!$D$90:$D$169,$A24,Datos!$C$90:$C$169,"Terminado")/DIAS} -> 0.92569189 | D24: {=SUMIFS(INDEX(Datos!$E$90:$P$169,0,MES),Datos!$A$90:$A$169,ANIO,Datos!$D$90:$D$169,$A24,Datos!$C$90:$C$169,"Cilindro")/DIAS} -> 0.66436 | E24: =C24+D24 -> 1.5900519 | F24: =IF($E$26=0,0,E24/$E$26) -> 0.12040266
A25: 100 kg | B25: =SUMIFS(Datos!$Q$90:$Q$169,Datos!$A$90:$A$169,ANIO,Datos!$D$90:$D$169,$A25) -> 247.44657 | C25: {=SUMIFS(INDEX(Datos!$E$90:$P$169,0,MES),Datos!$A$90:$A$169,ANIO,Datos!$D$90:$D$169,$A25,Datos!$C$90:$C$169,"Terminado")/DIAS} -> 0.61712793 | D25: {=SUMIFS(INDEX(Datos!$E$90:$P$169,0,MES),Datos!$A$90:$A$169,ANIO,Datos!$D$90:$D$169,$A25,Datos!$C$90:$C$169,"Cilindro")/DIAS} -> 0.43452 | E25: =C25+D25 -> 1.0516479 | F25: =IF($E$26=0,0,E25/$E$26) -> 0.079633382
A26: Total | B26: =SUM(B22:B25) -> 3107.3221 | C26: =SUM(C22:C25) -> 7.7123991 | D26: =SUM(D22:D25) -> 5.49372 | E26: =SUM(E22:E25) -> 13.206119 | F26: =SUM(F22:F25) -> 1
A28: 4) RECARGAS
A29: Equipos que entran en el mes (recargas y altas de sustitutos) | B29: {=INDEX(B10:M10,1,MES)} -> 10822.075 | C29: por día → | D29: =B29/DIAS -> 541.10377
A32: 5) MANUALES — CARGA POR PUESTO Y POR MODELO
A33: N° | B33: Puesto | C33: Rama | D33: Alcance | E33: Piezas por recipiente | F33: % que pasa | G33: t 1 kg (s/pieza) | H33: t 2,5 kg | I33: t 5 kg | J33: t 10 kg | K33: Piezas/día 1 kg | L33: 2,5 kg | M33: 5 kg | N33: 10 kg | O33: Carga propia (min/día) | P33: Carga de carros (min/día) | Q33: Carga total (min/día) | R33: Máq. | S33: Turnos | T33: Capacidad (min/día) | U33: Disponib. (planilla) | V33: Aprovech. | W33: Cuello | X33: Nota
A34: 1 | B34: Recepción de materia prima | C34: Abastecimiento | D34: Todos | E34: 1 | F34: 1 | G34: 60 | H34: 60 | I34: 60 | J34: 60 | K34: =IF(G34>0,IF($D34="Terminados",$D$14,$F$14)*$E34*$F34,0) -> 911.79288 | L34: =IF(H34>0,IF($D34="Terminados",$D$15,$F$15)*$E34*$F34,0) -> 63.568523 | M34: =IF(I34>0,IF($D34="Terminados",$D$16,$F$16)*$E34*$F34,0) -> 287.33696 | N34: =IF(J34>0,IF($D34="Terminados",$D$17,$F$17)*$E34*$F34,0) -> 17.383176 | O34: =SUMPRODUCT(G34:J34,K34:N34)/60 -> 1280.0815 | P34: 0 | Q34: =O34+P34 -> 1280.0815 | R34: {=INDEX(Datos!$B$187:$K$187,1,ANIO-2025)} -> 2 | S34: {=INDEX(Datos!$L$187:$U$187,1,ANIO-2025)} -> 2 | T34: =R34*S34*MIN_TURNO -> 1800 | U34: 1 | V34: =IF(T34=0,0,Q34/(T34*U34)) -> 0.71115641 | W34: =IF(V34=MAX($V$34:$V$59),"◀ cuello","")
A35: 2 | B35: Corte de chapa — 1.er corte en franjas (guillotina 1, manuales + carros) | C35: Cuerpo | D35: Todos | E35: 1 | F35: 1 | G35: 4.9333333 | H35: 8.2222222 | I35: 11 | J35: 14 | K35: =IF(G35>0,IF($D35="Terminados",$D$14,$F$14)*$E35*$F35,0) -> 911.79288 | L35: =IF(H35>0,IF($D35="Terminados",$D$15,$F$15)*$E35*$F35,0) -> 63.568523 | M35: =IF(I35>0,IF($D35="Terminados",$D$16,$F$16)*$E35*$F35,0) -> 287.33696 | N35: =IF(J35>0,IF($D35="Terminados",$D$17,$F$17)*$E35*$F35,0) -> 17.383176 | O35: =SUMPRODUCT(G35:J35,K35:N35)/60 -> 140.4154 | P35: =Lotes!$H$16 -> 10.572102 | Q35: =O35+P35 -> 150.9875 | R35: {=INDEX(Datos!$B$188:$K$188,1,ANIO-2025)} -> 1 | S35: {=INDEX(Datos!$L$188:$U$188,1,ANIO-2025)} -> 1 | T35: =R35*S35*MIN_TURNO -> 450 | U35: 0.97422222 | V35: =IF(T35=0,0,Q35/(T35*U35)) -> 0.34440579 | W35: =IF(V35=MAX($V$34:$V$59),"◀ cuello","") | X35: Tiempo por modelo de parametros_manuales (filas 124 a 127). La carga de carros (cuerpos) viene de Lotes; las tiras de accesorios están en la disponibilidad.
A36: 3 | B36: Corte de chapa — 2.º corte en piezas (guillotina 2, manuales + carros) | C36: Cuerpo | D36: Todos | E36: 1 | F36: 1 | G36: 3.3333333 | H36: 4.2222222 | I36: 9.5 | J36: 12 | K36: =IF(G36>0,IF($D36="Terminados",$D$14,$F$14)*$E36*$F36,0) -> 911.79288 | L36: =IF(H36>0,IF($D36="Terminados",$D$15,$F$15)*$E36*$F36,0) -> 63.568523 | M36: =IF(I36>0,IF($D36="Terminados",$D$16,$F$16)*$E36*$F36,0) -> 287.33696 | N36: =IF(J36>0,IF($D36="Terminados",$D$17,$F$17)*$E36*$F36,0) -> 17.383176 | O36: =SUMPRODUCT(G36:J36,K36:N36)/60 -> 104.10015 | P36: =Lotes!$I$16 -> 10.176136 | Q36: =O36+P36 -> 114.27629 | R36: {=INDEX(Datos!$B$189:$K$189,1,ANIO-2025)} -> 1 | S36: {=INDEX(Datos!$L$189:$U$189,1,ANIO-2025)} -> 1 | T36: =R36*S36*MIN_TURNO -> 450 | U36: 0.99333333 | V36: =IF(T36=0,0,Q36/(T36*U36)) -> 0.25565166 | W36: =IF(V36=MAX($V$34:$V$59),"◀ cuello","") | X36: Ídem: segundo corte (piezas).
A37: 4 | B37: Corte de disco y embutido (cúpula y fondo) | C37: Fondo y cúpula | D37: Todos | E37: 2 | F37: 1 | G37: 8 | H37: 8 | I37: 8 | J37: 8 | K37: =IF(G37>0,IF($D37="Terminados",$D$14,$F$14)*$E37*$F37,0) -> 1823.5858 | L37: =IF(H37>0,IF($D37="Terminados",$D$15,$F$15)*$E37*$F37,0) -> 127.13705 | M37: =IF(I37>0,IF($D37="Terminados",$D$16,$F$16)*$E37*$F37,0) -> 574.67393 | N37: =IF(J37>0,IF($D37="Terminados",$D$17,$F$17)*$E37*$F37,0) -> 34.766353 | O37: =SUMPRODUCT(G37:J37,K37:N37)/60 -> 341.35508 | P37: 0 | Q37: =O37+P37 -> 341.35508 | R37: {=INDEX(Datos!$B$190:$K$190,1,ANIO-2025)} -> 1 | S37: {=INDEX(Datos!$L$190:$U$190,1,ANIO-2025)} -> 2 | T37: =R37*S37*MIN_TURNO -> 900 | U37: 0.68 | V37: =IF(T37=0,0,Q37/(T37*U37)) -> 0.55776973 | W37: =IF(V37=MAX($V$34:$V$59),"◀ cuello","") | X37: 2 piezas por recipiente (cúpula y fondo). Los cambios de matriz se calculan en Lotes, sección 2.
A38: 5 | B38: Preparación de cuello | C38: Cúpula | D38: Todos | E38: 1 | F38: 1 | G38: 60 | H38: 60 | I38: 60 | J38: 60 | K38: =IF(G38>0,IF($D38="Terminados",$D$14,$F$14)*$E38*$F38,0) -> 911.79288 | L38: =IF(H38>0,IF($D38="Terminados",$D$15,$F$15)*$E38*$F38,0) -> 63.568523 | M38: =IF(I38>0,IF($D38="Terminados",$D$16,$F$16)*$E38*$F38,0) -> 287.33696 | N38: =IF(J38>0,IF($D38="Terminados",$D$17,$F$17)*$E38*$F38,0) -> 17.383176 | O38: =SUMPRODUCT(G38:J38,K38:N38)/60 -> 1280.0815 | P38: 0 | Q38: =O38+P38 -> 1280.0815 | R38: {=INDEX(Datos!$B$191:$K$191,1,ANIO-2025)} -> 2 | S38: {=INDEX(Datos!$L$191:$U$191,1,ANIO-2025)} -> 2 | T38: =R38*S38*MIN_TURNO -> 1800 | U38: 1 | V38: =IF(T38=0,0,Q38/(T38*U38)) -> 0.71115641 | W38: =IF(V38=MAX($V$34:$V$59),"◀ cuello","")
A39: 6 | B39: Marcado del cuerpo (manuales + carros) | C39: Cuerpo | D39: Todos | E39: 1 | F39: 1 | G39: 20 | H39: 20 | I39: 20 | J39: 20 | K39: =IF(G39>0,IF($D39="Terminados",$D$14,$F$14)*$E39*$F39,0) -> 911.79288 | L39: =IF(H39>0,IF($D39="Terminados",$D$15,$F$15)*$E39*$F39,0) -> 63.568523 | M39: =IF(I39>0,IF($D39="Terminados",$D$16,$F$16)*$E39*$F39,0) -> 287.33696 | N39: =IF(J39>0,IF($D39="Terminados",$D$17,$F$17)*$E39*$F39,0) -> 17.383176 | O39: =SUMPRODUCT(G39:J39,K39:N39)/60 -> 426.69385 | P39: =H76+K76 -> 24.601689 | Q39: =O39+P39 -> 451.29554 | R39: {=INDEX(Datos!$B$192:$K$192,1,ANIO-2025)} -> 2 | S39: {=INDEX(Datos!$L$192:$U$192,1,ANIO-2025)} -> 1 | T39: =R39*S39*MIN_TURNO -> 900 | U39: 1 | V39: =IF(T39=0,0,Q39/(T39*U39)) -> 0.50143948 | W39: =IF(V39=MAX($V$34:$V$59),"◀ cuello","") | X39: Antes: numerado de cúpula. Ahora marca el desarrollo plano de manuales (20 s) y de carros (1,5 a 1,8 min, Carga fila 76) entre la guillotina 2 y el cilindrado, tomando del pulmón de desarrollos. 2 puestos en 1 turno: uno fijo para el 1 kg y otro para 2,5 / 5 / 10 kg y carros (Datos fila 192). Cambio de formato 15 min (Rueda fila 9).
A40: 7 | B40: Soldadura del cuello a la cúpula | C40: Cúpula | D40: Todos | E40: 1 | F40: 1 | G40: 25 | H40: 25 | I40: 25 | J40: 25 | K40: =IF(G40>0,IF($D40="Terminados",$D$14,$F$14)*$E40*$F40,0) -> 911.79288 | L40: =IF(H40>0,IF($D40="Terminados",$D$15,$F$15)*$E40*$F40,0) -> 63.568523 | M40: =IF(I40>0,IF($D40="Terminados",$D$16,$F$16)*$E40*$F40,0) -> 287.33696 | N40: =IF(J40>0,IF($D40="Terminados",$D$17,$F$17)*$E40*$F40,0) -> 17.383176 | O40: =SUMPRODUCT(G40:J40,K40:N40)/60 -> 533.36731 | P40: 0 | Q40: =O40+P40 -> 533.36731 | R40: {=INDEX(Datos!$B$193:$K$193,1,ANIO-2025)} -> 1 | S40: {=INDEX(Datos!$L$193:$U$193,1,ANIO-2025)} -> 2 | T40: =R40*S40*MIN_TURNO -> 900 | U40: 0.97333333 | V40: =IF(T40=0,0,Q40/(T40*U40)) -> 0.60886679 | W40: =IF(V40=MAX($V$34:$V$59),"◀ cuello","")
A41: 8 | B41: Cilindrado | C41: Cuerpo | D41: Todos | E41: 1 | F41: 1 | G41: 15 | H41: 15 | I41: 15 | J41: 15 | K41: =IF(G41>0,IF($D41="Terminados",$D$14,$F$14)*$E41*$F41,0) -> 911.79288 | L41: =IF(H41>0,IF($D41="Terminados",$D$15,$F$15)*$E41*$F41,0) -> 63.568523 | M41: =IF(I41>0,IF($D41="Terminados",$D$16,$F$16)*$E41*$F41,0) -> 287.33696 | N41: =IF(J41>0,IF($D41="Terminados",$D$17,$F$17)*$E41*$F41,0) -> 17.383176 | O41: =SUMPRODUCT(G41:J41,K41:N41)/60 -> 320.02038 | P41: 0 | Q41: =O41+P41 -> 320.02038 | R41: {=INDEX(Datos!$B$194:$K$194,1,ANIO-2025)} -> 1 | S41: {=INDEX(Datos!$L$194:$U$194,1,ANIO-2025)} -> 1 | T41: =R41*S41*MIN_TURNO -> 450 | U41: 0.98666667 | V41: =IF(T41=0,0,Q41/(T41*U41)) -> 0.72076663 | W41: =IF(V41=MAX($V$34:$V$59),"◀ cuello","") | X41: Layout rev. 10: roladora propia para el 1 kg; en Rueda se toman 2 máquinas.
A42: 9 | B42: Soldadura longitudinal — 2,5 a 10 kg | C42: Cuerpo | D42: Todos | E42: 1 | F42: 1 | G42: 0 | H42: 115 | I42: 115 | J42: 115 | K42: =IF(G42>0,IF($D42="Terminados",$D$14,$F$14)*$E42*$F42,0) -> 0 | L42: =IF(H42>0,IF($D42="Terminados",$D$15,$F$15)*$E42*$F42,0) -> 63.568523 | M42: =IF(I42>0,IF($D42="Terminados",$D$16,$F$16)*$E42*$F42,0) -> 287.33696 | N42: =IF(J42>0,IF($D42="Terminados",$D$17,$F$17)*$E42*$F42,0) -> 17.383176 | O42: =SUMPRODUCT(G42:J42,K42:N42)/60 -> 705.88661 | P42: 0 | Q42: =O42+P42 -> 705.88661 | R42: {=INDEX(Datos!$B$195:$K$195,1,ANIO-2025)} -> 1 | S42: {=INDEX(Datos!$L$195:$U$195,1,ANIO-2025)} -> 2 | T42: =R42*S42*MIN_TURNO -> 900 | U42: 0.98666667 | V42: =IF(T42=0,0,Q42/(T42*U42)) -> 0.79491735 | W42: =IF(V42=MAX($V$34:$V$59),"◀ cuello","") -> ◀ cuello | X42: Solo 2,5 a 10 kg (115 s por cuerpo): es el cuello de la línea.
A43: 10 | B43: Soldadura longitudinal TIG — 1 kg | C43: Cuerpo | D43: Todos | E43: 1 | F43: 1 | G43: 30 | H43: 0 | I43: 0 | J43: 0 | K43: =IF(G43>0,IF($D43="Terminados",$D$14,$F$14)*$E43*$F43,0) -> 911.79288 | L43: =IF(H43>0,IF($D43="Terminados",$D$15,$F$15)*$E43*$F43,0) -> 0 | M43: =IF(I43>0,IF($D43="Terminados",$D$16,$F$16)*$E43*$F43,0) -> 0 | N43: =IF(J43>0,IF($D43="Terminados",$D$17,$F$17)*$E43*$F43,0) -> 0 | O43: =SUMPRODUCT(G43:J43,K43:N43)/60 -> 455.89644 | P43: 0 | Q43: =O43+P43 -> 455.89644 | R43: {=INDEX(Datos!$B$196:$K$196,1,ANIO-2025)} -> 1 | S43: {=INDEX(Datos!$L$196:$U$196,1,ANIO-2025)} -> 2 | T43: =R43*S43*MIN_TURNO -> 900 | U43: 1 | V43: =IF(T43=0,0,Q43/(T43*U43)) -> 0.5065516 | W43: =IF(V43=MAX($V$34:$V$59),"◀ cuello","") | X43: Exclusivo del 1 kg: no tiene cambios de formato.
A44: 11 | B44: Encastre de fondo | C44: Unión cuerpo + fondo | D44: Todos | E44: 1 | F44: 1 | G44: 30 | H44: 30 | I44: 30 | J44: 30 | K44: =IF(G44>0,IF($D44="Terminados",$D$14,$F$14)*$E44*$F44,0) -> 911.79288 | L44: =IF(H44>0,IF($D44="Terminados",$D$15,$F$15)*$E44*$F44,0) -> 63.568523 | M44: =IF(I44>0,IF($D44="Terminados",$D$16,$F$16)*$E44*$F44,0) -> 287.33696 | N44: =IF(J44>0,IF($D44="Terminados",$D$17,$F$17)*$E44*$F44,0) -> 17.383176 | O44: =SUMPRODUCT(G44:J44,K44:N44)/60 -> 640.04077 | P44: 0 | Q44: =O44+P44 -> 640.04077 | R44: {=INDEX(Datos!$B$197:$K$197,1,ANIO-2025)} -> 1 | S44: {=INDEX(Datos!$L$197:$U$197,1,ANIO-2025)} -> 2 | T44: =R44*S44*MIN_TURNO -> 900 | U44: 0.98222222 | V44: =IF(T44=0,0,Q44/(T44*U44)) -> 0.72402802 | W44: =IF(V44=MAX($V$34:$V$59),"◀ cuello","")
A45: 12 | B45: Bordoneado | C45: Cuerpo con fondo | D45: Todos | E45: 1 | F45: 1 | G45: 20 | H45: 20 | I45: 20 | J45: 20 | K45: =IF(G45>0,IF($D45="Terminados",$D$14,$F$14)*$E45*$F45,0) -> 911.79288 | L45: =IF(H45>0,IF($D45="Terminados",$D$15,$F$15)*$E45*$F45,0) -> 63.568523 | M45: =IF(I45>0,IF($D45="Terminados",$D$16,$F$16)*$E45*$F45,0) -> 287.33696 | N45: =IF(J45>0,IF($D45="Terminados",$D$17,$F$17)*$E45*$F45,0) -> 17.383176 | O45: =SUMPRODUCT(G45:J45,K45:N45)/60 -> 426.69385 | P45: 0 | Q45: =O45+P45 -> 426.69385 | R45: {=INDEX(Datos!$B$198:$K$198,1,ANIO-2025)} -> 1 | S45: {=INDEX(Datos!$L$198:$U$198,1,ANIO-2025)} -> 2 | T45: =R45*S45*MIN_TURNO -> 900 | U45: 0.98222222 | V45: =IF(T45=0,0,Q45/(T45*U45)) -> 0.48268535 | W45: =IF(V45=MAX($V$34:$V$59),"◀ cuello","")
A46: 13 | B46: Soldadura circunferencial de cúpula y fondo | C46: Unión (marcapasos) | D46: Todos | E46: 1 | F46: 1 | G46: 60 | H46: 60 | I46: 60 | J46: 60 | K46: =IF(G46>0,IF($D46="Terminados",$D$14,$F$14)*$E46*$F46,0) -> 911.79288 | L46: =IF(H46>0,IF($D46="Terminados",$D$15,$F$15)*$E46*$F46,0) -> 63.568523 | M46: =IF(I46>0,IF($D46="Terminados",$D$16,$F$16)*$E46*$F46,0) -> 287.33696 | N46: =IF(J46>0,IF($D46="Terminados",$D$17,$F$17)*$E46*$F46,0) -> 17.383176 | O46: =SUMPRODUCT(G46:J46,K46:N46)/60 -> 1280.0815 | P46: 0 | Q46: =O46+P46 -> 1280.0815 | R46: {=INDEX(Datos!$B$199:$K$199,1,ANIO-2025)} -> 2 | S46: {=INDEX(Datos!$L$199:$U$199,1,ANIO-2025)} -> 2 | T46: =R46*S46*MIN_TURNO -> 1800 | U46: 0.98222222 | V46: =IF(T46=0,0,Q46/(T46*U46)) -> 0.72402802 | W46: =IF(V46=MAX($V$34:$V$59),"◀ cuello","") | X46: Marcapasos: acá se juntan cuerpo con fondo y cúpula con cuello.
A47: 14 | B47: Control de calidad — Espesor | C47: Terminación | D47: Todos | E47: 1 | F47: 0.02 | G47: 120 | H47: 120 | I47: 120 | J47: 120 | K47: =IF(G47>0,IF($D47="Terminados",$D$14,$F$14)*$E47*$F47,0) -> 18.235858 | L47: =IF(H47>0,IF($D47="Terminados",$D$15,$F$15)*$E47*$F47,0) -> 1.2713705 | M47: =IF(I47>0,IF($D47="Terminados",$D$16,$F$16)*$E47*$F47,0) -> 5.7467393 | N47: =IF(J47>0,IF($D47="Terminados",$D$17,$F$17)*$E47*$F47,0) -> 0.34766353 | O47: =SUMPRODUCT(G47:J47,K47:N47)/60 -> 51.203262 | P47: 0 | Q47: =O47+P47 -> 51.203262 | R47: {=INDEX(Datos!$B$200:$K$200,1,ANIO-2025)} -> 1 | S47: {=INDEX(Datos!$L$200:$U$200,1,ANIO-2025)} -> 1 | T47: =R47*S47*MIN_TURNO -> 450 | U47: 1 | V47: =IF(T47=0,0,Q47/(T47*U47)) -> 0.11378503 | W47: =IF(V47=MAX($V$34:$V$59),"◀ cuello","") | X47: Muestra del 2 % (control por lote).
A48: 15 | B48: Prueba hidráulica | C48: Terminación | D48: Todos | E48: 1 | F48: 1 | G48: 60 | H48: 60 | I48: 60 | J48: 60 | K48: =IF(G48>0,IF($D48="Terminados",$D$14,$F$14)*$E48*$F48,0) -> 911.79288 | L48: =IF(H48>0,IF($D48="Terminados",$D$15,$F$15)*$E48*$F48,0) -> 63.568523 | M48: =IF(I48>0,IF($D48="Terminados",$D$16,$F$16)*$E48*$F48,0) -> 287.33696 | N48: =IF(J48>0,IF($D48="Terminados",$D$17,$F$17)*$E48*$F48,0) -> 17.383176 | O48: =SUMPRODUCT(G48:J48,K48:N48)/60 -> 1280.0815 | P48: 0 | Q48: =O48+P48 -> 1280.0815 | R48: {=INDEX(Datos!$B$201:$K$201,1,ANIO-2025)} -> 2 | S48: {=INDEX(Datos!$L$201:$U$201,1,ANIO-2025)} -> 2 | T48: =R48*S48*MIN_TURNO -> 1800 | U48: 0.98222222 | V48: =IF(T48=0,0,Q48/(T48*U48)) -> 0.72402802 | W48: =IF(V48=MAX($V$34:$V$59),"◀ cuello","")
A49: 16 | B49: Secado | C49: Terminación | D49: Todos | E49: 1 | F49: 1 | G49: 120 | H49: 120 | I49: 120 | J49: 120 | K49: =IF(G49>0,IF($D49="Terminados",$D$14,$F$14)*$E49*$F49,0) -> 911.79288 | L49: =IF(H49>0,IF($D49="Terminados",$D$15,$F$15)*$E49*$F49,0) -> 63.568523 | M49: =IF(I49>0,IF($D49="Terminados",$D$16,$F$16)*$E49*$F49,0) -> 287.33696 | N49: =IF(J49>0,IF($D49="Terminados",$D$17,$F$17)*$E49*$F49,0) -> 17.383176 | O49: =SUMPRODUCT(G49:J49,K49:N49)/60 -> 2560.1631 | P49: 0 | Q49: =O49+P49 -> 2560.1631 | R49: {=INDEX(Datos!$B$202:$K$202,1,ANIO-2025)} -> 4 | S49: {=INDEX(Datos!$L$202:$U$202,1,ANIO-2025)} -> 2 | T49: =R49*S49*MIN_TURNO -> 3600 | U49: 1 | V49: =IF(T49=0,0,Q49/(T49*U49)) -> 0.71115641 | W49: =IF(V49=MAX($V$34:$V$59),"◀ cuello","")
A50: 17 | B50: Granallado | C50: Terminación | D50: Todos | E50: 1 | F50: 1 | G50: 30 | H50: 30 | I50: 30 | J50: 30 | K50: =IF(G50>0,IF($D50="Terminados",$D$14,$F$14)*$E50*$F50,0) -> 911.79288 | L50: =IF(H50>0,IF($D50="Terminados",$D$15,$F$15)*$E50*$F50,0) -> 63.568523 | M50: =IF(I50>0,IF($D50="Terminados",$D$16,$F$16)*$E50*$F50,0) -> 287.33696 | N50: =IF(J50>0,IF($D50="Terminados",$D$17,$F$17)*$E50*$F50,0) -> 17.383176 | O50: =SUMPRODUCT(G50:J50,K50:N50)/60 -> 640.04077 | P50: 0 | Q50: =O50+P50 -> 640.04077 | R50: {=INDEX(Datos!$B$203:$K$203,1,ANIO-2025)} -> 1 | S50: {=INDEX(Datos!$L$203:$U$203,1,ANIO-2025)} -> 2 | T50: =R50*S50*MIN_TURNO -> 900 | U50: 1 | V50: =IF(T50=0,0,Q50/(T50*U50)) -> 0.71115641 | W50: =IF(V50=MAX($V$34:$V$59),"◀ cuello","")
A51: 18 | B51: Detección de defectos | C51: Terminación | D51: Todos | E51: 1 | F51: 1 | G51: 20 | H51: 20 | I51: 20 | J51: 20 | K51: =IF(G51>0,IF($D51="Terminados",$D$14,$F$14)*$E51*$F51,0) -> 911.79288 | L51: =IF(H51>0,IF($D51="Terminados",$D$15,$F$15)*$E51*$F51,0) -> 63.568523 | M51: =IF(I51>0,IF($D51="Terminados",$D$16,$F$16)*$E51*$F51,0) -> 287.33696 | N51: =IF(J51>0,IF($D51="Terminados",$D$17,$F$17)*$E51*$F51,0) -> 17.383176 | O51: =SUMPRODUCT(G51:J51,K51:N51)/60 -> 426.69385 | P51: 0 | Q51: =O51+P51 -> 426.69385 | R51: {=INDEX(Datos!$B$204:$K$204,1,ANIO-2025)} -> 1 | S51: {=INDEX(Datos!$L$204:$U$204,1,ANIO-2025)} -> 2 | T51: =R51*S51*MIN_TURNO -> 900 | U51: 1 | V51: =IF(T51=0,0,Q51/(T51*U51)) -> 0.47410427 | W51: =IF(V51=MAX($V$34:$V$59),"◀ cuello","")
A52: 19 | B52: Corrección de defectos | C52: Terminación | D52: Todos | E52: 1 | F52: 0.05 | G52: 180 | H52: 180 | I52: 180 | J52: 180 | K52: =IF(G52>0,IF($D52="Terminados",$D$14,$F$14)*$E52*$F52,0) -> 45.589644 | L52: =IF(H52>0,IF($D52="Terminados",$D$15,$F$15)*$E52*$F52,0) -> 3.1784261 | M52: =IF(I52>0,IF($D52="Terminados",$D$16,$F$16)*$E52*$F52,0) -> 14.366848 | N52: =IF(J52>0,IF($D52="Terminados",$D$17,$F$17)*$E52*$F52,0) -> 0.86915882 | O52: =SUMPRODUCT(G52:J52,K52:N52)/60 -> 192.01223 | P52: 0 | Q52: =O52+P52 -> 192.01223 | R52: {=INDEX(Datos!$B$205:$K$205,1,ANIO-2025)} -> 1 | S52: {=INDEX(Datos!$L$205:$U$205,1,ANIO-2025)} -> 1 | T52: =R52*S52*MIN_TURNO -> 450 | U52: 1 | V52: =IF(T52=0,0,Q52/(T52*U52)) -> 0.42669385 | W52: =IF(V52=MAX($V$34:$V$59),"◀ cuello","") | X52: Solo el 5 % que tiene defectos.
A53: 20 | B53: Pintura en polvo + horno | C53: Terminación | D53: Todos | E53: 1 | F53: 1 | G53: 25 | H53: 25 | I53: 25 | J53: 25 | K53: =IF(G53>0,IF($D53="Terminados",$D$14,$F$14)*$E53*$F53,0) -> 911.79288 | L53: =IF(H53>0,IF($D53="Terminados",$D$15,$F$15)*$E53*$F53,0) -> 63.568523 | M53: =IF(I53>0,IF($D53="Terminados",$D$16,$F$16)*$E53*$F53,0) -> 287.33696 | N53: =IF(J53>0,IF($D53="Terminados",$D$17,$F$17)*$E53*$F53,0) -> 17.383176 | O53: =SUMPRODUCT(G53:J53,K53:N53)/60 -> 533.36731 | P53: 0 | Q53: =O53+P53 -> 533.36731 | R53: {=INDEX(Datos!$B$206:$K$206,1,ANIO-2025)} -> 1 | S53: {=INDEX(Datos!$L$206:$U$206,1,ANIO-2025)} -> 2 | T53: =R53*S53*MIN_TURNO -> 900 | U53: 0.94666667 | V53: =IF(T53=0,0,Q53/(T53*U53)) -> 0.62601797 | W53: =IF(V53=MAX($V$34:$V$59),"◀ cuello","")
A54: 21 | B54: Carga de polvo | C54: Matafuego | D54: Terminados | E54: 1 | F54: 1 | G54: 45 | H54: 45 | I54: 45 | J54: 45 | K54: =IF(G54>0,IF($D54="Terminados",$D$14,$F$14)*$E54*$F54,0) -> 144.32688 | L54: =IF(H54>0,IF($D54="Terminados",$D$15,$F$15)*$E54*$F54,0) -> 33.464063 | M54: =IF(I54>0,IF($D54="Terminados",$D$16,$F$16)*$E54*$F54,0) -> 138.6674 | N54: =IF(J54>0,IF($D54="Terminados",$D$17,$F$17)*$E54*$F54,0) -> 8.3021764 | O54: =SUMPRODUCT(G54:J54,K54:N54)/60 -> 243.57039 | P54: 0 | Q54: =O54+P54 -> 243.57039 | R54: {=INDEX(Datos!$B$207:$K$207,1,ANIO-2025)} -> 1 | S54: {=INDEX(Datos!$L$207:$U$207,1,ANIO-2025)} -> 1 | T54: =R54*S54*MIN_TURNO -> 450 | U54: 1 | V54: =IF(T54=0,0,Q54/(T54*U54)) -> 0.54126753 | W54: =IF(V54=MAX($V$34:$V$59),"◀ cuello","")
A55: 22 | B55: Ensamblaje | C55: Matafuego | D55: Terminados | E55: 1 | F55: 1 | G55: 100 | H55: 100 | I55: 100 | J55: 100 | K55: =IF(G55>0,IF($D55="Terminados",$D$14,$F$14)*$E55*$F55,0) -> 144.32688 | L55: =IF(H55>0,IF($D55="Terminados",$D$15,$F$15)*$E55*$F55,0) -> 33.464063 | M55: =IF(I55>0,IF($D55="Terminados",$D$16,$F$16)*$E55*$F55,0) -> 138.6674 | N55: =IF(J55>0,IF($D55="Terminados",$D$17,$F$17)*$E55*$F55,0) -> 8.3021764 | O55: =SUMPRODUCT(G55:J55,K55:N55)/60 -> 541.26753 | P55: 0 | Q55: =O55+P55 -> 541.26753 | R55: {=INDEX(Datos!$B$208:$K$208,1,ANIO-2025)} -> 1 | S55: {=INDEX(Datos!$L$208:$U$208,1,ANIO-2025)} -> 2 | T55: =R55*S55*MIN_TURNO -> 900 | U55: 0.98222222 | V55: =IF(T55=0,0,Q55/(T55*U55)) -> 0.61229359 | W55: =IF(V55=MAX($V$34:$V$59),"◀ cuello","")
A56: 23 | B56: Presurización | C56: Matafuego | D56: Terminados | E56: 1 | F56: 1 | G56: 30 | H56: 30 | I56: 30 | J56: 30 | K56: =IF(G56>0,IF($D56="Terminados",$D$14,$F$14)*$E56*$F56,0) -> 144.32688 | L56: =IF(H56>0,IF($D56="Terminados",$D$15,$F$15)*$E56*$F56,0) -> 33.464063 | M56: =IF(I56>0,IF($D56="Terminados",$D$16,$F$16)*$E56*$F56,0) -> 138.6674 | N56: =IF(J56>0,IF($D56="Terminados",$D$17,$F$17)*$E56*$F56,0) -> 8.3021764 | O56: =SUMPRODUCT(G56:J56,K56:N56)/60 -> 162.38026 | P56: 0 | Q56: =O56+P56 -> 162.38026 | R56: {=INDEX(Datos!$B$209:$K$209,1,ANIO-2025)} -> 1 | S56: {=INDEX(Datos!$L$209:$U$209,1,ANIO-2025)} -> 1 | T56: =R56*S56*MIN_TURNO -> 450 | U56: 1 | V56: =IF(T56=0,0,Q56/(T56*U56)) -> 0.36084502 | W56: =IF(V56=MAX($V$34:$V$59),"◀ cuello","")
A57: 24 | B57: Control de calidad — Ensayo de pérdidas | C57: Matafuego | D57: Terminados | E57: 1 | F57: 1 | G57: 40 | H57: 40 | I57: 40 | J57: 40 | K57: =IF(G57>0,IF($D57="Terminados",$D$14,$F$14)*$E57*$F57,0) -> 144.32688 | L57: =IF(H57>0,IF($D57="Terminados",$D$15,$F$15)*$E57*$F57,0) -> 33.464063 | M57: =IF(I57>0,IF($D57="Terminados",$D$16,$F$16)*$E57*$F57,0) -> 138.6674 | N57: =IF(J57>0,IF($D57="Terminados",$D$17,$F$17)*$E57*$F57,0) -> 8.3021764 | O57: =SUMPRODUCT(G57:J57,K57:N57)/60 -> 216.50701 | P57: 0 | Q57: =O57+P57 -> 216.50701 | R57: {=INDEX(Datos!$B$210:$K$210,1,ANIO-2025)} -> 1 | S57: {=INDEX(Datos!$L$210:$U$210,1,ANIO-2025)} -> 1 | T57: =R57*S57*MIN_TURNO -> 450 | U57: 1 | V57: =IF(T57=0,0,Q57/(T57*U57)) -> 0.4811267 | W57: =IF(V57=MAX($V$34:$V$59),"◀ cuello","")
A58: 25 | B58: Etiquetado | C58: Matafuego | D58: Terminados | E58: 1 | F58: 1 | G58: 60 | H58: 60 | I58: 60 | J58: 60 | K58: =IF(G58>0,IF($D58="Terminados",$D$14,$F$14)*$E58*$F58,0) -> 144.32688 | L58: =IF(H58>0,IF($D58="Terminados",$D$15,$F$15)*$E58*$F58,0) -> 33.464063 | M58: =IF(I58>0,IF($D58="Terminados",$D$16,$F$16)*$E58*$F58,0) -> 138.6674 | N58: =IF(J58>0,IF($D58="Terminados",$D$17,$F$17)*$E58*$F58,0) -> 8.3021764 | O58: =SUMPRODUCT(G58:J58,K58:N58)/60 -> 324.76052 | P58: 0 | Q58: =O58+P58 -> 324.76052 | R58: {=INDEX(Datos!$B$211:$K$211,1,ANIO-2025)} -> 1 | S58: {=INDEX(Datos!$L$211:$U$211,1,ANIO-2025)} -> 1 | T58: =R58*S58*MIN_TURNO -> 450 | U58: 1 | V58: =IF(T58=0,0,Q58/(T58*U58)) -> 0.72169004 | W58: =IF(V58=MAX($V$34:$V$59),"◀ cuello","")
A59: 26 | B59: Embalaje y paletizado | C59: Embalaje | D59: Todos | E59: 1 | F59: 1 | G59: 45 | H59: 45 | I59: 45 | J59: 45 | K59: =IF(G59>0,IF($D59="Terminados",$D$14,$F$14)*$E59*$F59,0) -> 911.79288 | L59: =IF(H59>0,IF($D59="Terminados",$D$15,$F$15)*$E59*$F59,0) -> 63.568523 | M59: =IF(I59>0,IF($D59="Terminados",$D$16,$F$16)*$E59*$F59,0) -> 287.33696 | N59: =IF(J59>0,IF($D59="Terminados",$D$17,$F$17)*$E59*$F59,0) -> 17.383176 | O59: =SUMPRODUCT(G59:J59,K59:N59)/60 -> 960.06115 | P59: 0 | Q59: =O59+P59 -> 960.06115 | R59: {=INDEX(Datos!$B$212:$K$212,1,ANIO-2025)} -> 2 | S59: {=INDEX(Datos!$L$212:$U$212,1,ANIO-2025)} -> 2 | T59: =R59*S59*MIN_TURNO -> 1800 | U59: 0.99111111 | V59: =IF(T59=0,0,Q59/(T59*U59)) -> 0.53815087 | W59: =IF(V59=MAX($V$34:$V$59),"◀ cuello","")
B60: Total | O60: =SUM(O34:O59) -> 16066.823 | P60: =SUM(P34:P59) -> 45.349926 | Q60: =SUM(Q34:Q59) -> 16112.173
B62: Recipientes por día | C62: =F18 -> 1280.0815
B63: Takt con 1 turno (s por recipiente) = 450 × 60 ÷ recipientes | C63: =MIN_TURNO*60/F18 -> 21.092406
B64: Contenido de trabajo por recipiente (s) = carga total × 60 ÷ recipientes | C64: =Q60*60/F18 -> 755.21001
B65: Recursos-turno instalados (Σ máquinas × turnos) | C65: =SUMPRODUCT(R34:R59,S34:S59) -> 59
B66: Cuello de botella | C66: {=INDEX(B34:B59,MATCH(MAX(V34:V59),V34:V59,0))} -> Soldadura longitudinal — 2,5 a 10 kg
B67: Aprovechamiento del cuello | C67: =MAX(V34:V59) -> 0.79491735
B68: Aprovechamiento medio (ponderado por recursos-turno) | C68: =SUMPRODUCT(V34:V59,R34:R59,S34:S59)/SUMPRODUCT(R34:R59,S34:S59) -> 0.61846142
B69: Eficiencia de balanceo = medio ÷ cuello | C69: =C68/C67 -> 0.77801978
A72: 6) CARROS — CARGA POR PUESTO
A73: N° | B73: Puesto | C73: Alcance | D73: t 25 kg (min/u) | E73: t 50 kg | F73: t 70 kg | G73: t 100 kg | H73: Carga variable (min/día) | I73: Cambio (min) | J73: Cambios por día | K73: Tiempos fijos (min/día) | L73: Carga total (min/día) | M73: Máq. | N73: Turnos | O73: Capacidad (min/día) | P73: Aprovech. (mes de cálculo) | Q73: Aprovech. (mes pico de carros) | R73: Cuello | X73: Nota
A74: 1 | B74: Recepción de materia prima | C74: Todos | D74: 1.7825 | E74: 1.7825 | F74: 1.7825 | G74: 1.7825 | H74: =IF(C74="Terminados",D74*$C$22+E74*$C$23+F74*$C$24+G74*$C$25,D74*$E$22+E74*$E$23+F74*$E$24+G74*$E$25) -> 23.539907 | I74: 0 | J74: 0 | K74: 21.65 | L74: =H74+I74*J74+K74 -> 45.189907 | M74: {=INDEX(Datos!$B$216:$K$216,1,ANIO-2025)} -> 1 | N74: {=INDEX(Datos!$L$216:$U$216,1,ANIO-2025)} -> 1 | O74: =M74*N74*MIN_TURNO -> 450 | P74: =IF(O74=0,0,L74/O74) -> 0.10042202 | Q74: {=IF(O74=0,0,(H74*MAX($B$9:$M$9)/MAX(0.0001,INDEX($B$9:$M$9,1,MES))+I74*J74+K74)/O74)} -> 0.10349913 | R74: =IF(P74=MAX($P$74:$P$91),"◀ cuello","")
A75: 2 | B75: Corte de chapa (guillotina) | C75: Todos | D75: 2.6044138 | E75: 3.0478269 | F75: 6.6764493 | G75: 6.6764493 | H75: =IF(C75="Terminados",D75*$C$22+E75*$C$23+F75*$C$24+G75*$C$25,D75*$E$22+E75*$E$23+F75*$E$24+G75*$E$25) -> 48.37085 | I75: 0.5 | J75: 6 | K75: 25 | L75: =H75+I75*J75+K75 -> 76.37085 | M75: {=INDEX(Datos!$B$217:$K$217,1,ANIO-2025)} -> 1 | N75: {=INDEX(Datos!$L$217:$U$217,1,ANIO-2025)} -> 1 | O75: =M75*N75*MIN_TURNO -> 450 | P75: =IF(O75=0,0,L75/O75) -> 0.169713 | Q75: {=IF(O75=0,0,(H75*MAX($B$9:$M$9)/MAX(0.0001,INDEX($B$9:$M$9,1,MES))+I75*J75+K75)/O75)} -> 0.17603599 | R75: =IF(P75=MAX($P$74:$P$91),"◀ cuello","") | X75: Carga del operario de corte para carros. La de las máquinas está en Lotes (guillotinas compartidas).
A76: 2.1 | B76: Marcado del cuerpo | C76: Todos | D76: 1.5 | E76: 1.5 | F76: 1.8 | G76: 1.8 | H76: =IF(C76="Terminados",D76*$C$22+E76*$C$23+F76*$C$24+G76*$C$25,D76*$E$22+E76*$E$23+F76*$E$24+G76*$E$25) -> 20.601689 | I76: 0.5 | J76: 3 | K76: 4 | L76: =H76+I76*J76+K76 -> 26.101689 | M76: {=INDEX(Datos!$B$218:$K$218,1,ANIO-2025)} -> 0 | N76: {=INDEX(Datos!$L$218:$U$218,1,ANIO-2025)} -> 1 | O76: =M76*N76*MIN_TURNO -> 0 | P76: =IF(O76=0,0,L76/O76) -> 0 | Q76: {=IF(O76=0,0,(H76*MAX($B$9:$M$9)/MAX(0.0001,INDEX($B$9:$M$9,1,MES))+I76*J76+K76)/O76)} -> 0 | R76: =IF(P76=MAX($P$74:$P$91),"◀ cuello","") | X76: Absorbido por el marcado unificado (Carga fila 39, puesto 6 de manuales). Se deja con 0 máquinas (Datos fila 218) para no contar la carga dos veces; los tiempos siguen acá porque los usa la fila 39.
A77: 3 | B77: Cilindrado | C77: Todos | D77: 2.6 | E77: 2.8 | F77: 5.5434783 | G77: 6.0434783 | H77: =IF(C77="Terminados",D77*$C$22+E77*$C$23+F77*$C$24+G77*$C$25,D77*$E$22+E77*$E$23+F77*$E$24+G77*$E$25) -> 44.089689 | I77: 4 | J77: 3 | K77: 6 | L77: =H77+I77*J77+K77 -> 62.089689 | M77: {=INDEX(Datos!$B$219:$K$219,1,ANIO-2025)} -> 1 | N77: {=INDEX(Datos!$L$219:$U$219,1,ANIO-2025)} -> 1 | O77: =M77*N77*MIN_TURNO -> 450 | P77: =IF(O77=0,0,L77/O77) -> 0.13797709 | Q77: {=IF(O77=0,0,(H77*MAX($B$9:$M$9)/MAX(0.0001,INDEX($B$9:$M$9,1,MES))+I77*J77+K77)/O77)} -> 0.14374045 | R77: =IF(P77=MAX($P$74:$P$91),"◀ cuello","")
A78: 4 | B78: Punteo del cuerpo | C78: Todos | D78: 3 | E78: 3.3 | F78: 11.843478 | G78: 12.043478 | H78: =IF(C78="Terminados",D78*$C$22+E78*$C$23+F78*$C$24+G78*$C$25,D78*$E$22+E78*$E$23+F78*$E$24+G78*$E$25) -> 65.368756 | I78: 0 | J78: 0 | K78: 5 | L78: =H78+I78*J78+K78 -> 70.368756 | M78: {=INDEX(Datos!$B$220:$K$220,1,ANIO-2025)} -> 1 | N78: {=INDEX(Datos!$L$220:$U$220,1,ANIO-2025)} -> 1 | O78: =M78*N78*MIN_TURNO -> 450 | P78: =IF(O78=0,0,L78/O78) -> 0.15637501 | Q78: {=IF(O78=0,0,(H78*MAX($B$9:$M$9)/MAX(0.0001,INDEX($B$9:$M$9,1,MES))+I78*J78+K78)/O78)} -> 0.16491995 | R78: =IF(P78=MAX($P$74:$P$91),"◀ cuello","")
A79: 5 | B79: Soldadura longitudinal | C79: Todos | D79: 3 | E79: 3.3 | F79: 3.9 | G79: 4.6 | H79: =IF(C79="Terminados",D79*$C$22+E79*$C$23+F79*$C$24+G79*$C$25,D79*$E$22+E79*$E$23+F79*$E$24+G79*$E$25) -> 44.910295 | I79: 1 | J79: 3 | K79: 5 | L79: =H79+I79*J79+K79 -> 52.910295 | M79: {=INDEX(Datos!$B$221:$K$221,1,ANIO-2025)} -> 1 | N79: {=INDEX(Datos!$L$221:$U$221,1,ANIO-2025)} -> 1 | O79: =M79*N79*MIN_TURNO -> 450 | P79: =IF(O79=0,0,L79/O79) -> 0.11757843 | Q79: {=IF(O79=0,0,(H79*MAX($B$9:$M$9)/MAX(0.0001,INDEX($B$9:$M$9,1,MES))+I79*J79+K79)/O79)} -> 0.12344906 | R79: =IF(P79=MAX($P$74:$P$91),"◀ cuello","")
A80: 6 | B80: Soldadura de cupla en la cúpula | C80: Todos | D80: 3.2 | E80: 3.2 | F80: 4 | G80: 4 | H80: =IF(C80="Terminados",D80*$C$22+E80*$C$23+F80*$C$24+G80*$C$25,D80*$E$22+E80*$E$23+F80*$E$24+G80*$E$25) -> 44.372941 | I80: 2 | J80: 2 | K80: 5 | L80: =H80+I80*J80+K80 -> 53.372941 | M80: {=INDEX(Datos!$B$222:$K$222,1,ANIO-2025)} -> 1 | N80: {=INDEX(Datos!$L$222:$U$222,1,ANIO-2025)} -> 1 | O80: =M80*N80*MIN_TURNO -> 450 | P80: =IF(O80=0,0,L80/O80) -> 0.11860654 | Q80: {=IF(O80=0,0,(H80*MAX($B$9:$M$9)/MAX(0.0001,INDEX($B$9:$M$9,1,MES))+I80*J80+K80)/O80)} -> 0.12440692 | R80: =IF(P80=MAX($P$74:$P$91),"◀ cuello","")
A81: 7 | B81: Armado y soldadura circunferencial | C81: Todos | D81: 14.6 | E81: 15.2 | F81: 19.4 | G81: 19.4 | H81: =IF(C81="Terminados",D81*$C$22+E81*$C$23+F81*$C$24+G81*$C$25,D81*$E$22+E81*$E$23+F81*$E$24+G81*$E$25) -> 209.84601 | I81: 2 | J81: 2 | K81: 5 | L81: =H81+I81*J81+K81 -> 218.84601 | M81: {=INDEX(Datos!$B$223:$K$223,1,ANIO-2025)} -> 1 | N81: {=INDEX(Datos!$L$223:$U$223,1,ANIO-2025)} -> 1 | O81: =M81*N81*MIN_TURNO -> 450 | P81: =IF(O81=0,0,L81/O81) -> 0.48632446 | Q81: {=IF(O81=0,0,(H81*MAX($B$9:$M$9)/MAX(0.0001,INDEX($B$9:$M$9,1,MES))+I81*J81+K81)/O81)} -> 0.51375531 | R81: =IF(P81=MAX($P$74:$P$91),"◀ cuello","")
A82: 8 | B82: Soldadura de accesorios | C82: Todos | D82: 15.7 | E82: 15.9 | F82: 17.6 | G82: 17.6 | H82: =IF(C82="Terminados",D82*$C$22+E82*$C$23+F82*$C$24+G82*$C$25,D82*$E$22+E82*$E$23+F82*$E$24+G82*$E$25) -> 213.80747 | I82: 2 | J82: 2 | K82: 5 | L82: =H82+I82*J82+K82 -> 222.80747 | M82: {=INDEX(Datos!$B$224:$K$224,1,ANIO-2025)} -> 1 | N82: {=INDEX(Datos!$L$224:$U$224,1,ANIO-2025)} -> 1 | O82: =M82*N82*MIN_TURNO -> 450 | P82: =IF(O82=0,0,L82/O82) -> 0.49512771 | Q82: {=IF(O82=0,0,(H82*MAX($B$9:$M$9)/MAX(0.0001,INDEX($B$9:$M$9,1,MES))+I82*J82+K82)/O82)} -> 0.5230764 | R82: =IF(P82=MAX($P$74:$P$91),"◀ cuello","") -> ◀ cuello
A83: 8.1 | B83: Fabricación de accesorios | C83: Todos | D83: 11 | E83: 11 | F83: 11 | G83: 11 | H83: =IF(C83="Terminados",D83*$C$22+E83*$C$23+F83*$C$24+G83*$C$25,D83*$E$22+E83*$E$23+F83*$E$24+G83*$E$25) -> 145.26731 | I83: 2 | J83: 3 | K83: 9 | L83: =H83+I83*J83+K83 -> 160.26731 | M83: {=INDEX(Datos!$B$225:$K$225,1,ANIO-2025)} -> 1 | N83: {=INDEX(Datos!$L$225:$U$225,1,ANIO-2025)} -> 1 | O83: =M83*N83*MIN_TURNO -> 450 | P83: =IF(O83=0,0,L83/O83) -> 0.35614958 | Q83: {=IF(O83=0,0,(H83*MAX($B$9:$M$9)/MAX(0.0001,INDEX($B$9:$M$9,1,MES))+I83*J83+K83)/O83)} -> 0.37513877 | R83: =IF(P83=MAX($P$74:$P$91),"◀ cuello","")
A84: 9 | B84: Prueba hidráulica | C84: Todos | D84: 8.38 | E84: 9.18 | F84: 9.18 | G84: 9.18 | H84: =IF(C84="Terminados",D84*$C$22+E84*$C$23+F84*$C$24+G84*$C$25,D84*$E$22+E84*$E$23+F84*$E$24+G84*$E$25) -> 118.58932 | I84: 0 | J84: 0 | K84: 10 | L84: =H84+I84*J84+K84 -> 128.58932 | M84: {=INDEX(Datos!$B$226:$K$226,1,ANIO-2025)} -> 1 | N84: {=INDEX(Datos!$L$226:$U$226,1,ANIO-2025)} -> 1 | O84: =M84*N84*MIN_TURNO -> 450 | P84: =IF(O84=0,0,L84/O84) -> 0.28575404 | Q84: {=IF(O84=0,0,(H84*MAX($B$9:$M$9)/MAX(0.0001,INDEX($B$9:$M$9,1,MES))+I84*J84+K84)/O84)} -> 0.30125591 | R84: =IF(P84=MAX($P$74:$P$91),"◀ cuello","")
A85: 10 | B85: Secado | C85: Todos | D85: 8 | E85: 10 | F85: 12 | G85: 14 | H85: =IF(C85="Terminados",D85*$C$22+E85*$C$23+F85*$C$24+G85*$C$25,D85*$E$22+E85*$E$23+F85*$E$24+G85*$E$25) -> 132.84075 | I85: 0 | J85: 0 | K85: 0 | L85: =H85+I85*J85+K85 -> 132.84075 | M85: {=INDEX(Datos!$B$227:$K$227,1,ANIO-2025)} -> 1 | N85: {=INDEX(Datos!$L$227:$U$227,1,ANIO-2025)} -> 1 | O85: =M85*N85*MIN_TURNO -> 450 | P85: =IF(O85=0,0,L85/O85) -> 0.29520166 | Q85: {=IF(O85=0,0,(H85*MAX($B$9:$M$9)/MAX(0.0001,INDEX($B$9:$M$9,1,MES))+I85*J85+K85)/O85)} -> 0.31256646 | R85: =IF(P85=MAX($P$74:$P$91),"◀ cuello","")
A86: 11 | B86: Pulmón de despacho y carga a pintura | C86: Todos | D86: 1.45 | E86: 1.45 | F86: 2.2 | G86: 2.2 | H86: =IF(C86="Terminados",D86*$C$22+E86*$C$23+F86*$C$24+G86*$C$25,D86*$E$22+E86*$E$23+F86*$E$24+G86*$E$25) -> 21.130148 | I86: 0 | J86: 0 | K86: 4 | L86: =H86+I86*J86+K86 -> 25.130148 | M86: {=INDEX(Datos!$B$228:$K$228,1,ANIO-2025)} -> 1 | N86: {=INDEX(Datos!$L$228:$U$228,1,ANIO-2025)} -> 1 | O86: =M86*N86*MIN_TURNO -> 450 | P86: =IF(O86=0,0,L86/O86) -> 0.055844772 | Q86: {=IF(O86=0,0,(H86*MAX($B$9:$M$9)/MAX(0.0001,INDEX($B$9:$M$9,1,MES))+I86*J86+K86)/O86)} -> 0.058606883 | R86: =IF(P86=MAX($P$74:$P$91),"◀ cuello","")
A87: 12 | B87: Recepción de pintados y cambio de juego | C87: Todos | D87: 2.95 | E87: 2.95 | F87: 3.85 | G87: 3.85 | H87: =IF(C87="Terminados",D87*$C$22+E87*$C$23+F87*$C$24+G87*$C$25,D87*$E$22+E87*$E$23+F87*$E$24+G87*$E$25) -> 41.335581 | I87: 0 | J87: 0 | K87: 4 | L87: =H87+I87*J87+K87 -> 45.335581 | M87: {=INDEX(Datos!$B$229:$K$229,1,ANIO-2025)} -> 1 | N87: {=INDEX(Datos!$L$229:$U$229,1,ANIO-2025)} -> 1 | O87: =M87*N87*MIN_TURNO -> 450 | P87: =IF(O87=0,0,L87/O87) -> 0.10074574 | Q87: {=IF(O87=0,0,(H87*MAX($B$9:$M$9)/MAX(0.0001,INDEX($B$9:$M$9,1,MES))+I87*J87+K87)/O87)} -> 0.10614908 | R87: =IF(P87=MAX($P$74:$P$91),"◀ cuello","") | X87: La pintura es tercerizada: 3 días hábiles ida y vuelta.
A88: 13 B | B88: Carga de polvo y presurización | C88: Terminados | D88: 8.3 | E88: 11.3 | F88: 13.8 | G88: 17.3 | H88: =IF(C88="Terminados",D88*$C$22+E88*$C$23+F88*$C$24+G88*$C$25,D88*$E$22+E88*$E$23+F88*$E$24+G88*$E$25) -> 87.382807 | I88: 0 | J88: 0 | K88: 48 | L88: =H88+I88*J88+K88 -> 135.38281 | M88: {=INDEX(Datos!$B$230:$K$230,1,ANIO-2025)} -> 1 | N88: {=INDEX(Datos!$L$230:$U$230,1,ANIO-2025)} -> 1 | O88: =M88*N88*MIN_TURNO -> 450 | P88: =IF(O88=0,0,L88/O88) -> 0.30085068 | Q88: {=IF(O88=0,0,(H88*MAX($B$9:$M$9)/MAX(0.0001,INDEX($B$9:$M$9,1,MES))+I88*J88+K88)/O88)} -> 0.31227327 | R88: =IF(P88=MAX($P$74:$P$91),"◀ cuello","")
A89: 13 A-C / 15 | B89: Montaje, manga, precinto y etiquetado | C89: Terminados | D89: 6.1 | E89: 6.1 | F89: 6.8 | G89: 7.8 | H89: =IF(C89="Terminados",D89*$C$22+E89*$C$23+F89*$C$24+G89*$C$25,D89*$E$22+E89*$E$23+F89*$E$24+G89*$E$25) -> 48.742736 | I89: 0 | J89: 0 | K89: 21 | L89: =H89+I89*J89+K89 -> 69.742736 | M89: {=INDEX(Datos!$B$231:$K$231,1,ANIO-2025)} -> 1 | N89: {=INDEX(Datos!$L$231:$U$231,1,ANIO-2025)} -> 1 | O89: =M89*N89*MIN_TURNO -> 450 | P89: =IF(O89=0,0,L89/O89) -> 0.15498386 | Q89: {=IF(O89=0,0,(H89*MAX($B$9:$M$9)/MAX(0.0001,INDEX($B$9:$M$9,1,MES))+I89*J89+K89)/O89)} -> 0.16135546 | R89: =IF(P89=MAX($P$74:$P$91),"◀ cuello","")
A90: 14-17 | B90: Calidad: pérdidas, inspección final, liberación y ensayos de lote | C90: Terminados | D90: 4.79 | E90: 4.79 | F90: 4.79 | G90: 4.79 | H90: =IF(C90="Terminados",D90*$C$22+E90*$C$23+F90*$C$24+G90*$C$25,D90*$E$22+E90*$E$23+F90*$E$24+G90*$E$25) -> 36.942392 | I90: 0 | J90: 0 | K90: 166.6 | L90: =H90+I90*J90+K90 -> 203.54239 | M90: {=INDEX(Datos!$B$232:$K$232,1,ANIO-2025)} -> 1 | N90: {=INDEX(Datos!$L$232:$U$232,1,ANIO-2025)} -> 1 | O90: =M90*N90*MIN_TURNO -> 450 | P90: =IF(O90=0,0,L90/O90) -> 0.45231643 | Q90: {=IF(O90=0,0,(H90*MAX($B$9:$M$9)/MAX(0.0001,INDEX($B$9:$M$9,1,MES))+I90*J90+K90)/O90)} -> 0.4571455 | R90: =IF(P90=MAX($P$74:$P$91),"◀ cuello","") | X90: Casi todo es fijo por día (actas, ensayos de lote): no depende del volumen.
A91: 16 | B91: Depósito de producto terminado y despacho | C91: Todos | D91: 1.2 | E91: 1.2 | F91: 2 | G91: 2 | H91: =IF(C91="Terminados",D91*$C$22+E91*$C$23+F91*$C$24+G91*$C$25,D91*$E$22+E91*$E$23+F91*$E$24+G91*$E$25) -> 17.960703 | I91: 0 | J91: 0 | K91: 10 | L91: =H91+I91*J91+K91 -> 27.960703 | M91: {=INDEX(Datos!$B$233:$K$233,1,ANIO-2025)} -> 1 | N91: {=INDEX(Datos!$L$233:$U$233,1,ANIO-2025)} -> 1 | O91: =M91*N91*MIN_TURNO -> 450 | P91: =IF(O91=0,0,L91/O91) -> 0.062134895 | Q91: {=IF(O91=0,0,(H91*MAX($B$9:$M$9)/MAX(0.0001,INDEX($B$9:$M$9,1,MES))+I91*J91+K91)/O91)} -> 0.064482699 | R91: =IF(P91=MAX($P$74:$P$91),"◀ cuello","")
B93: Carros por día | C93: =E26 -> 13.206119
B94: Takt con 1 turno (min por carro) | C94: =MIN_TURNO/E26 -> 34.075113
B95: Cuello de botella | C95: {=INDEX(B74:B91,MATCH(MAX(P74:P91),P74:P91,0))} -> Soldadura de accesorios
B96: Aprovechamiento del cuello (mes de cálculo) | C96: =MAX(P74:P91) -> 0.49512771
B97: Aprovechamiento del cuello (mes pico de carros) | C97: =MAX(Q74:Q91) -> 0.5230764
B98: Aprovechamiento medio | C98: =SUMPRODUCT(P74:P91,M74:M91,N74:N91)/SUMPRODUCT(M74:M91,N74:N91) -> 0.22624152
B99: Eficiencia de balanceo = medio ÷ cuello | C99: =C98/C96 -> 0.45693569
A102: 7) RECARGAS — CARGA POR PUESTO Y EQUIPOS EN PLANTA (es un servicio: el lote entra y sale en el día, no se arma en lotes por formato)
A103: N° | B103: Puesto | C103: t (s/equipo) | D103: Equipos/mes | E103: Equipos/día | F103: Máq. | G103: Turnos | H103: Aprovech. (mes de cálculo) | I103: Aprovech. (mes pico de recargas) | J103: Cuello | K103: Espera media (h) | L103: Equipos en el puesto | M103: Jaulas | N103: m²
A104: 1 | B104: Recepción y registro | C104: 75 | D104: {=SUMIFS(INDEX(Datos!$C$312:$N$541,0,MES),Datos!$A$312:$A$541,$B104,Datos!$B$312:$B$541,ANIO)} -> 10822.075 | E104: =D104/DIAS -> 541.10377 | F104: {=INDEX(Datos!$B$237:$K$237,1,ANIO-2025)} -> 2 | G104: {=INDEX(Datos!$L$237:$U$237,1,ANIO-2025)} -> 1 | H104: =IF(F104*G104=0,0,D104*C104/3600/(HORAS_MES*F104*G104)) -> 0.75153301 | I104: {=IF(F104*G104=0,0,SUMIFS(INDEX(Datos!$C$312:$N$541,0,$N$10),Datos!$A$312:$A$541,$B104,Datos!$B$312:$B$541,ANIO)*C104/3600/(HORAS_MES*F104*G104))} -> 0.81813919 | J104: =IF(H104=MAX($H$104:$H$126),"◀ cuello","") | K104: =ESPERA_REC_H -> 0.5 | L104: =IF(G104=0,0,E104/(G104*MIN_TURNO/60)*(C104/3600+K104)) -> 37.576651 | M104: =IF(L104=0,0,ROUNDUP(L104/U_JAULA,0)) -> 2 | N104: =M104*M2_JAULA -> 4.8
A105: 2 | B105: Inspección visual | C105: 90 | D105: {=SUMIFS(INDEX(Datos!$C$312:$N$541,0,MES),Datos!$A$312:$A$541,$B105,Datos!$B$312:$B$541,ANIO)} -> 10822.075 | E105: =D105/DIAS -> 541.10377 | F105: {=INDEX(Datos!$B$238:$K$238,1,ANIO-2025)} -> 2 | G105: {=INDEX(Datos!$L$238:$U$238,1,ANIO-2025)} -> 2 | H105: =IF(F105*G105=0,0,D105*C105/3600/(HORAS_MES*F105*G105)) -> 0.45091981 | I105: {=IF(F105*G105=0,0,SUMIFS(INDEX(Datos!$C$312:$N$541,0,$N$10),Datos!$A$312:$A$541,$B105,Datos!$B$312:$B$541,ANIO)*C105/3600/(HORAS_MES*F105*G105))} -> 0.49088352 | J105: =IF(H105=MAX($H$104:$H$126),"◀ cuello","") | K105: =ESPERA_REC_H -> 0.5 | L105: =IF(G105=0,0,E105/(G105*MIN_TURNO/60)*(C105/3600+K105)) -> 18.938632 | M105: =IF(L105=0,0,ROUNDUP(L105/U_JAULA,0)) -> 1 | N105: =M105*M2_JAULA -> 2.4
A106: 3 | B106: Descarga ABC — ruta recuperable | C106: 85 | D106: {=SUMIFS(INDEX(Datos!$C$312:$N$541,0,MES),Datos!$A$312:$A$541,$B106,Datos!$B$312:$B$541,ANIO)} -> 8342.0782 | E106: =D106/DIAS -> 417.10391 | F106: {=INDEX(Datos!$B$239:$K$239,1,ANIO-2025)} -> 1 | G106: {=INDEX(Datos!$L$239:$U$239,1,ANIO-2025)} -> 2 | H106: =IF(F106*G106=0,0,D106*C106/3600/(HORAS_MES*F106*G106)) -> 0.65655245 | I106: {=IF(F106*G106=0,0,SUMIFS(INDEX(Datos!$C$312:$N$541,0,$N$10),Datos!$A$312:$A$541,$B106,Datos!$B$312:$B$541,ANIO)*C106/3600/(HORAS_MES*F106*G106))} -> 0.7069479 | J106: =IF(H106=MAX($H$104:$H$126),"◀ cuello","") | K106: =ESPERA_REC_H -> 0.5 | L106: =IF(G106=0,0,E106/(G106*MIN_TURNO/60)*(C106/3600+K106)) -> 14.560016 | M106: =IF(L106=0,0,ROUNDUP(L106/U_JAULA,0)) -> 1 | N106: =M106*M2_JAULA -> 2.4
A107: 4 | B107: Descarga a descarte (ABC, BC y Clase D) | C107: 85 | D107: {=SUMIFS(INDEX(Datos!$C$312:$N$541,0,MES),Datos!$A$312:$A$541,$B107,Datos!$B$312:$B$541,ANIO)} -> 948.21126 | E107: =D107/DIAS -> 47.410563 | F107: {=INDEX(Datos!$B$240:$K$240,1,ANIO-2025)} -> 1 | G107: {=INDEX(Datos!$L$240:$U$240,1,ANIO-2025)} -> 1 | H107: =IF(F107*G107=0,0,D107*C107/3600/(HORAS_MES*F107*G107)) -> 0.14925548 | I107: {=IF(F107*G107=0,0,SUMIFS(INDEX(Datos!$C$312:$N$541,0,$N$10),Datos!$A$312:$A$541,$B107,Datos!$B$312:$B$541,ANIO)*C107/3600/(HORAS_MES*F107*G107))} -> 0.16045446 | J107: =IF(H107=MAX($H$104:$H$126),"◀ cuello","") | K107: =ESPERA_REC_H -> 0.5 | L107: =IF(G107=0,0,E107/(G107*MIN_TURNO/60)*(C107/3600+K107)) -> 3.3099597 | M107: =IF(L107=0,0,ROUNDUP(L107/U_JAULA,0)) -> 1 | N107: =M107*M2_JAULA -> 2.4
A108: 5 | B108: Descarga y carga de agua / AFFF / sales K | C108: 205 | D108: {=SUMIFS(INDEX(Datos!$C$312:$N$541,0,MES),Datos!$A$312:$A$541,$B108,Datos!$B$312:$B$541,ANIO)} -> 398.71817 | E108: =D108/DIAS -> 19.935909 | F108: {=INDEX(Datos!$B$241:$K$241,1,ANIO-2025)} -> 1 | G108: {=INDEX(Datos!$L$241:$U$241,1,ANIO-2025)} -> 1 | H108: =IF(F108*G108=0,0,D108*C108/3600/(HORAS_MES*F108*G108)) -> 0.15136523 | I108: {=IF(F108*G108=0,0,SUMIFS(INDEX(Datos!$C$312:$N$541,0,$N$10),Datos!$A$312:$A$541,$B108,Datos!$B$312:$B$541,ANIO)*C108/3600/(HORAS_MES*F108*G108))} -> 0.17223922 | J108: =IF(H108=MAX($H$104:$H$126),"◀ cuello","") | K108: =ESPERA_REC_H -> 0.5 | L108: =IF(G108=0,0,E108/(G108*MIN_TURNO/60)*(C108/3600+K108)) -> 1.4804258 | M108: =IF(L108=0,0,ROUNDUP(L108/U_JAULA,0)) -> 1 | N108: =M108*M2_JAULA -> 2.4
A109: 6 | B109: Recuperación y carga de CO₂ | C109: 240 | D109: {=SUMIFS(INDEX(Datos!$C$312:$N$541,0,MES),Datos!$A$312:$A$541,$B109,Datos!$B$312:$B$541,ANIO)} -> 357.24192 | E109: =D109/DIAS -> 17.862096 | F109: {=INDEX(Datos!$B$242:$K$242,1,ANIO-2025)} -> 1 | G109: {=INDEX(Datos!$L$242:$U$242,1,ANIO-2025)} -> 1 | H109: =IF(F109*G109=0,0,D109*C109/3600/(HORAS_MES*F109*G109)) -> 0.15877419 | I109: {=IF(F109*G109=0,0,SUMIFS(INDEX(Datos!$C$312:$N$541,0,$N$10),Datos!$A$312:$A$541,$B109,Datos!$B$312:$B$541,ANIO)*C109/3600/(HORAS_MES*F109*G109))} -> 0.19982115 | J109: =IF(H109=MAX($H$104:$H$126),"◀ cuello","") | K109: =ESPERA_REC_H -> 0.5 | L109: =IF(G109=0,0,E109/(G109*MIN_TURNO/60)*(C109/3600+K109)) -> 1.3495806 | M109: =IF(L109=0,0,ROUNDUP(L109/U_JAULA,0)) -> 1 | N109: =M109*M2_JAULA -> 2.4
A110: 7 | B110: Recuperación y carga de halogenado | C110: 895 | D110: {=SUMIFS(INDEX(Datos!$C$312:$N$541,0,MES),Datos!$A$312:$A$541,$B110,Datos!$B$312:$B$541,ANIO)} -> 11.849235 | E110: =D110/DIAS -> 0.59246173 | F110: {=INDEX(Datos!$B$243:$K$243,1,ANIO-2025)} -> 1 | G110: {=INDEX(Datos!$L$243:$U$243,1,ANIO-2025)} -> 1 | H110: =IF(F110*G110=0,0,D110*C110/3600/(HORAS_MES*F110*G110)) -> 0.019639009 | I110: {=IF(F110*G110=0,0,SUMIFS(INDEX(Datos!$C$312:$N$541,0,$N$10),Datos!$A$312:$A$541,$B110,Datos!$B$312:$B$541,ANIO)*C110/3600/(HORAS_MES*F110*G110))} -> 0.019639009 | J110: =IF(H110=MAX($H$104:$H$126),"◀ cuello","") | K110: =ESPERA_REC_H -> 0.5 | L110: =IF(G110=0,0,E110/(G110*MIN_TURNO/60)*(C110/3600+K110)) -> 0.059136458 | M110: =IF(L110=0,0,ROUNDUP(L110/U_JAULA,0)) -> 1 | N110: =M110*M2_JAULA -> 2.4
A111: 8 | B111: Desarme y limpieza — recinto | C111: 105 | D111: {=SUMIFS(INDEX(Datos!$C$312:$N$541,0,MES),Datos!$A$312:$A$541,$B111,Datos!$B$312:$B$541,ANIO)} -> 9779.2521 | E111: =D111/DIAS -> 488.9626 | F111: {=INDEX(Datos!$B$244:$K$244,1,ANIO-2025)} -> 2 | G111: {=INDEX(Datos!$L$244:$U$244,1,ANIO-2025)} -> 2 | H111: =IF(F111*G111=0,0,D111*C111/3600/(HORAS_MES*F111*G111)) -> 0.47538031 | I111: {=IF(F111*G111=0,0,SUMIFS(INDEX(Datos!$C$312:$N$541,0,$N$10),Datos!$A$312:$A$541,$B111,Datos!$B$312:$B$541,ANIO)*C111/3600/(HORAS_MES*F111*G111))} -> 0.51178569 | J111: =IF(H111=MAX($H$104:$H$126),"◀ cuello","") | K111: =ESPERA_REC_H -> 0.5 | L111: =IF(G111=0,0,E111/(G111*MIN_TURNO/60)*(C111/3600+K111)) -> 17.249514 | M111: =IF(L111=0,0,ROUNDUP(L111/U_JAULA,0)) -> 1 | N111: =M111*M2_JAULA -> 2.4
...

Sheet Lotes
A1: PASO 2 — CUÁNTO HACER POR VEZ EN LAS MÁQUINAS CON CAMBIO CARO (guillotinas y embutidora)
A2: Regla del «punto de seguir procesando»: una tanda tiene que durar al menos 3 veces lo que lleva el cambio de formato (el cambio nunca pasa del 25 % de la tanda). Si el formato se consume más lento, se corta o se prensa cada varios días y lo que sobra queda en un pulmón.
A3: ▶ Guillotinas: columnas O (cada cuántos días), P (hojas por tanda) y W (pulmón). Embutidora: J (cada cuántos días), K (piezas por tanda) y O (supermercado). Capacidad en las filas 22 a 24 y 42.
A4: Mes | B4: =Carga!B4 -> Ene 2035
A6: 1) GUILLOTINAS G1 (franjas) Y G2 (piezas) — compartidas por manuales y carros
A7: Formato | B7: Línea | C7: Hoja (mm) | D7: Cuerpos por hoja | E7: Cuerpos por día | F7: G1 (min/cuerpo) | G7: G2 (min/cuerpo) | H7: Corrida G1 (min/día) = E × F | I7: Corte G2 (min/día) = E × G | J7: Frec. mínima (días) = 3 × cambio ÷ H | K7: Frec. del modelo en la ola (días) | L7: Tope por espacio (días) | M7: Frec. calculada (días) | N7: Frec. elegida (vacío = calculada) | O7: Frec. final (días) | P7: Hojas por tanda | Q7: Cuerpos por tanda | R7: Cobertura (días) | S7: Corrida de la tanda en G1 (min) | T7: Cambio ÷ tanda | U7: Cambios por día | V7: Fase (día) | W7: Pulmón de desarrollos (cuerpos) | X7: kg por hoja | Y7: Paquete de chapa (kg) | Z7: Lectura
A8: Manuales 1 kg | B8: Manuales | C8: 1.220 × 2.440 × 0,9 | D8: 45 | E8: =Carga!$F$14 -> 911.79288 | F8: =Carga!G$35/60 -> 0.082222222 | G8: =Carga!G$36/60 -> 0.055555556 | H8: =E8*F8 -> 74.969636 | I8: =E8*G8 -> 50.65516 | J8: =IF(H8=0,0,R_CORRIDA*S_G1/H8) -> 0.60024301 | K8: =Rueda!$H$35 -> 1 | L8: =K_MAX -> 16 | M8: =MAX(K8,MIN(MIN(K_MAX,BASE*2^MAX(0,ROUNDUP(LOG(MAX(1,(MAX(J8,K8))/BASE),2)-0.000001,0))),MIN(K_MAX,BASE*2^MAX(0,ROUNDDOWN(LOG(MAX(BASE,L8)/BASE,2)+0.000001,0))))) -> 1 | O8: =IF(N8="",M8,N8) -> 1 | P8: =ROUNDUP(E8*O8/D8,0) -> 21 | Q8: =P8*D8 -> 945 | R8: =IF(E8=0,0,Q8/E8) -> 1.0364196 | S8: =Q8*F8 -> 77.7 | T8: =IF(S8+S_G1=0,0,S_G1/(S_G1+S8)) -> 0.1618123 | U8: =IF(E8=0,0,1/O8) -> 1 | V8: 0 | W8: =IF(Q8=0,0,Q8*(1-E8*S8/(Q8*MIN_TURNO))+E8*H_PROT*60/MIN_TURNO) -> 909.13615 | X8: 21.0311 | Y8: =P8*X8 -> 441.6531 | Z8: =IF(E8=0,"Sin producción este mes",IF(O8<=BASE,"Se corta todos los días: "&P8&" hojas","Se corta cada "&O8&" días: "&P8&" hojas por tanda; entre tandas sale del pulmón")) -> Se corta todos los días: 21 hojas
A9: Manuales 2,5 kg | B9: Manuales | C9: 1.220 × 2.440 × 1,25 | D9: 27 | E9: =Carga!$F$15 -> 63.568523 | F9: =Carga!H$35/60 -> 0.13703704 | G9: =Carga!H$36/60 -> 0.07037037 | H9: =E9*F9 -> 8.711242 | I9: =E9*G9 -> 4.4733405 | J9: =IF(H9=0,0,R_CORRIDA*S_G1/H9) -> 5.1657387 | K9: =Rueda!$H$36 -> 1 | L9: =K_MAX -> 16 | M9: =MAX(K9,MIN(MIN(K_MAX,BASE*2^MAX(0,ROUNDUP(LOG(MAX(1,(MAX(J9,K9))/BASE),2)-0.000001,0))),MIN(K_MAX,BASE*2^MAX(0,ROUNDDOWN(LOG(MAX(BASE,L9)/BASE,2)+0.000001,0))))) -> 8 | O9: =IF(N9="",M9,N9) -> 8 | P9: =ROUNDUP(E9*O9/D9,0) -> 19 | Q9: =P9*D9 -> 513 | R9: =IF(E9=0,0,Q9/E9) -> 8.0700318 | S9: =Q9*F9 -> 70.3 | T9: =IF(S9+S_G1=0,0,S_G1/(S_G1+S9)) -> 0.17584994 | U9: =IF(E9=0,0,1/O9) -> 0.125 | V9: 0 | W9: =IF(Q9=0,0,Q9*(1-E9*S9/(Q9*MIN_TURNO))+E9*H_PROT*60/MIN_TURNO) -> 511.54499 | X9: 29.2098 | Y9: =P9*X9 -> 554.9862 | Z9: =IF(E9=0,"Sin producción este mes",IF(O9<=BASE,"Se corta todos los días: "&P9&" hojas","Se corta cada "&O9&" días: "&P9&" hojas por tanda; entre tandas sale del pulmón")) -> Se corta cada 8 días: 19 hojas por tanda; entre tandas sale del pulmón
A10: Manuales 5 kg | B10: Manuales | C10: 1.000 × 2.000 × 1,6 | D10: 12 | E10: =Carga!$F$16 -> 287.33696 | F10: =Carga!I$35/60 -> 0.18333333 | G10: =Carga!I$36/60 -> 0.15833333 | H10: =E10*F10 -> 52.678443 | I10: =E10*G10 -> 45.495019 | J10: =IF(H10=0,0,R_CORRIDA*S_G1/H10) -> 0.85423936 | K10: =Rueda!$H$37 -> 1 | L10: =K_MAX -> 16 | M10: =MAX(K10,MIN(MIN(K_MAX,BASE*2^MAX(0,ROUNDUP(LOG(MAX(1,(MAX(J10,K10))/BASE),2)-0.000001,0))),MIN(K_MAX,BASE*2^MAX(0,ROUNDDOWN(LOG(MAX(BASE,L10)/BASE,2)+0.000001,0))))) -> 1 | O10: =IF(N10="",M10,N10) -> 1 | P10: =ROUNDUP(E10*O10/D10,0) -> 24 | Q10: =P10*D10 -> 288 | R10: =IF(E10=0,0,Q10/E10) -> 1.0023075 | S10: =Q10*F10 -> 52.8 | T10: =IF(S10+S_G1=0,0,S_G1/(S_G1+S10)) -> 0.22123894 | U10: =IF(E10=0,0,1/O10) -> 1 | V10: 0 | W10: =IF(Q10=0,0,Q10*(1-E10*S10/(Q10*MIN_TURNO))+E10*H_PROT*60/MIN_TURNO) -> 292.59739 | X10: 25.12 | Y10: =P10*X10 -> 602.88 | Z10: =IF(E10=0,"Sin producción este mes",IF(O10<=BASE,"Se corta todos los días: "&P10&" hojas","Se corta cada "&O10&" días: "&P10&" hojas por tanda; entre tandas sale del pulmón")) -> Se corta todos los días: 24 hojas
A11: Manuales 10 kg | B11: Manuales | C11: 1.500 × 3.000 × 2,0 | D11: 15 | E11: =Carga!$F$17 -> 17.383176 | F11: =Carga!J$35/60 -> 0.23333333 | G11: =Carga!J$36/60 -> 0.2 | H11: =E11*F11 -> 4.0560745 | I11: =E11*G11 -> 3.4766353 | J11: =IF(H11=0,0,R_CORRIDA*S_G1/H11) -> 11.094471 | K11: =Rueda!$H$38 -> 2 | L11: =K_MAX -> 16 | M11: =MAX(K11,MIN(MIN(K_MAX,BASE*2^MAX(0,ROUNDUP(LOG(MAX(1,(MAX(J11,K11))/BASE),2)-0.000001,0))),MIN(K_MAX,BASE*2^MAX(0,ROUNDDOWN(LOG(MAX(BASE,L11)/BASE,2)+0.000001,0))))) -> 16 | O11: =IF(N11="",M11,N11) -> 16 | P11: =ROUNDUP(E11*O11/D11,0) -> 19 | Q11: =P11*D11 -> 285 | R11: =IF(E11=0,0,Q11/E11) -> 16.395162 | S11: =Q11*F11 -> 66.5 | T11: =IF(S11+S_G1=0,0,S_G1/(S_G1+S11)) -> 0.18404908 | U11: =IF(E11=0,0,1/O11) -> 0.0625 | V11: 2 | W11: =IF(Q11=0,0,Q11*(1-E11*S11/(Q11*MIN_TURNO))+E11*H_PROT*60/MIN_TURNO) -> 284.74891 | X11: 70.65 | Y11: =P11*X11 -> 1342.35 | Z11: =IF(E11=0,"Sin producción este mes",IF(O11<=BASE,"Se corta todos los días: "&P11&" hojas","Se corta cada "&O11&" días: "&P11&" hojas por tanda; entre tandas sale del pulmón")) -> Se corta cada 16 días: 19 hojas por tanda; entre tandas sale del pulmón
A12: Carros 25 kg (hoja 3,2) | B12: Carros | C12: 1.500 × 3.000 × 3,2 | D12: 9 | E12: =Carga!$E$22 -> 3.3035698 | F12: 0.57649171 | G12: 0.63903315 | H12: =E12*F12 -> 1.9044806 | I12: =E12*G12 -> 2.1110906 | J12: =IF(H12=0,0,R_CORRIDA*S_G1/H12) -> 23.62849 | K12: =BASE -> 1 | L12: 4 | M12: =MAX(K12,MIN(MIN(K_MAX,BASE*2^MAX(0,ROUNDUP(LOG(MAX(1,(MAX(J12,K12))/BASE),2)-0.000001,0))),MIN(K_MAX,BASE*2^MAX(0,ROUNDDOWN(LOG(MAX(BASE,L12)/BASE,2)+0.000001,0))))) -> 4 | O12: =IF(N12="",M12,N12) -> 4 | P12: =ROUNDUP(E12*O12/D12,0) -> 2 | Q12: =P12*D12 -> 18 | R12: =IF(E12=0,0,Q12/E12) -> 5.4486514 | S12: =Q12*F12 -> 10.376851 | T12: =IF(S12+S_G1=0,0,S_G1/(S_G1+S12)) -> 0.59108989 | U12: =IF(E12=0,0,1/O12) -> 0.25 | V12: 1 | W12: =IF(Q12=0,0,Q12*(1-E12*S12/(Q12*MIN_TURNO))+E12*H_PROT*60/MIN_TURNO) -> 18.364297 | X12: 113.04 | Y12: =P12*X12 -> 226.08 | Z12: =IF(E12=0,"Sin producción este mes",IF(O12<=BASE,"Se corta todos los días: "&P12&" hojas","Se corta cada "&O12&" días: "&P12&" hojas por tanda; entre tandas sale del pulmón")) -> Se corta cada 4 días: 2 hojas por tanda; entre tandas sale del pulmón
A13: Carros 50 kg (hoja 3,2) | B13: Carros | C13: 1.500 × 3.000 × 3,2 | D13: 6 | E13: =Carga!$E$23 -> 7.2608495 | F13: 0.53430939 | G13: 0.59685083 | H13: =E13*F13 -> 3.8795401 | I13: =E13*G13 -> 4.333644 | J13: =IF(H13=0,0,R_CORRIDA*S_G1/H13) -> 11.599313 | K13: =BASE -> 1 | L13: 4 | M13: =MAX(K13,MIN(MIN(K_MAX,BASE*2^MAX(0,ROUNDUP(LOG(MAX(1,(MAX(J13,K13))/BASE),2)-0.000001,0))),MIN(K_MAX,BASE*2^MAX(0,ROUNDDOWN(LOG(MAX(BASE,L13)/BASE,2)+0.000001,0))))) -> 4 | O13: =IF(N13="",M13,N13) -> 4 | P13: =ROUNDUP(E13*O13/D13,0) -> 5 | Q13: =P13*D13 -> 30 | R13: =IF(E13=0,0,Q13/E13) -> 4.131748 | S13: =Q13*F13 -> 16.029282 | T13: =IF(S13+S_G1=0,0,S_G1/(S_G1+S13)) -> 0.48341435 | U13: =IF(E13=0,0,1/O13) -> 0.25 | V13: 2 | W13: =IF(Q13=0,0,Q13*(1-E13*S13/(Q13*MIN_TURNO))+E13*H_PROT*60/MIN_TURNO) -> 30.709477 | X13: 113.04 | Y13: =P13*X13 -> 565.2 | Z13: =IF(E13=0,"Sin producción este mes",IF(O13<=BASE,"Se corta todos los días: "&P13&" hojas","Se corta cada "&O13&" días: "&P13&" hojas por tanda; entre tandas sale del pulmón")) -> Se corta cada 4 días: 5 hojas por tanda; entre tandas sale del pulmón
A14: Carros 70 + 100 kg (hoja mixta 4,75) | B14: Carros | C14: 1.500 × 3.000 × 4,75 | D14: 4 | E14: =Carga!$E$24+Carga!$E$25 -> 2.6416998 | F14: 1.8125 | G14: 1.4125 | H14: =E14*F14 -> 4.7880809 | I14: =E14*G14 -> 3.731401 | J14: =IF(H14=0,0,R_CORRIDA*S_G1/H14) -> 9.3983374 | K14: =BASE -> 1 | L14: 4 | M14: =MAX(K14,MIN(MIN(K_MAX,BASE*2^MAX(0,ROUNDUP(LOG(MAX(1,(MAX(J14,K14))/BASE),2)-0.000001,0))),MIN(K_MAX,BASE*2^MAX(0,ROUNDDOWN(LOG(MAX(BASE,L14)/BASE,2)+0.000001,0))))) -> 4 | O14: =IF(N14="",M14,N14) -> 4 | P14: =ROUNDUP(E14*O14/D14,0) -> 3 | Q14: =P14*D14 -> 12 | R14: =IF(E14=0,0,Q14/E14) -> 4.5425298 | S14: =Q14*F14 -> 21.75 | T14: =IF(S14+S_G1=0,0,S_G1/(S_G1+S14)) -> 0.40816327 | U14: =IF(E14=0,0,1/O14) -> 0.25 | V14: 3 | W14: =IF(Q14=0,0,Q14*(1-E14*S14/(Q14*MIN_TURNO))+E14*H_PROT*60/MIN_TURNO) -> 12.224544 | X14: 167.7937 | Y14: =P14*X14 -> 503.3811 | Z14: =IF(E14=0,"Sin producción este mes",IF(O14<=BASE,"Se corta todos los días: "&P14&" hojas","Se corta cada "&O14&" días: "&P14&" hojas por tanda; entre tandas sale del pulmón")) -> Se corta cada 4 días: 3 hojas por tanda; entre tandas sale del pulmón
A15: Carros: tiras y piezas de accesorios (fijo por día) | H15: =TIRAS_CARROS+TIRAS_EXTRA -> 44.8 | I15: 0
A16: Subtotal carros (cuerpos) | H16: =SUM(H12:H14) -> 10.572102 | I16: =SUM(I12:I14) -> 10.176136
A17: Subtotal manuales | H17: =SUM(H8:H11) -> 140.4154 | I17: =SUM(I8:I11) -> 104.10015
A18: Total | U18: =SUM(U8:U14) -> 2.9375 | W18: =SUM(W8:W14) -> 2059.3258
A20: Capacidad de las guillotinas con cambios, alistamiento y rendimiento del operario
A21: Recurso | B21: Máq. | C21: Turnos | D21: Capacidad (min/día) | E21: Corte manuales (min/día) | F21: Corte carros + accesorios (min/día) | G21: Corte ÷ rendimiento (min/día) | H21: Cambios por día | I21: Min de cambio por día | J21: Alistamiento + desalistamiento (min/día) | K21: Carga total (min/día) | L21: Aprovech. | M21: Estado
A22: Guillotina 1 — franjas (Ermaksan HGS 2600-6) | B22: =Carga!R35 -> 1 | C22: =Carga!S35 -> 1 | D22: =B22*C22*MIN_TURNO -> 450 | E22: =H17 -> 140.4154 | F22: =H16+H15 -> 55.372102 | G22: =(E22+F22)/REND_CORTE -> 230.33823 | H22: =U18 -> 2.9375 | I22: =H22*S_G1 -> 44.0625 | J22: =B22*C22*(ALIST_G+DESALIST_G) -> 20 | K22: =G22+I22+J22 -> 294.40073 | L22: =K22/D22 -> 0.65422385 | M22: =IF(L22<=UMBRAL,"OK","Pasa el umbral") -> OK
A23: Guillotina 2 — piezas (QC12Y 6 × 2500) | B23: =Carga!R36 -> 1 | C23: =Carga!S36 -> 1 | D23: =B23*C23*MIN_TURNO -> 450 | E23: =I17 -> 104.10015 | F23: =I16 -> 10.176136 | G23: =(E23+F23)/REND_CORTE -> 134.44269 | H23: =U18 -> 2.9375 | I23: =H23*S_G2 -> 14.6875 | J23: =B23*C23*(ALIST_G+DESALIST_G) -> 20 | K23: =G23+I23+J23 -> 169.13019 | L23: =K23/D23 -> 0.37584488 | M23: =IF(L23<=UMBRAL,"OK","Pasa el umbral") -> OK
A24: Operario de corte, si una persona atiende G1 y G2 | D24: =MIN_TURNO*MAX(C22,C23) -> 450 | K24: =K22+K23 -> 463.53093 | L24: =K24/D24 -> 1.0300687 | M24: =IF(L24<=UMBRAL,"OK con 1 operario","Hacen falta 2 operarios") -> Hacen falta 2 operarios
A25: Carga = (cortes + manipulación por hoja) ÷ rendimiento del operario (85 %) + cambios de formato (15 min G1: programa 5 + traer y devolver el paquete 10; 5 min G2) + 20 min por turno de alistamiento y desalistamiento.
A28: 2) EMBUTIDORA — 8 matrices (cúpula y fondo de cada modelo), cambio de 90 min: trabaja contra un supermercado
A29: Matriz | B29: Modelo | C29: Pieza | D29: Piezas por día | E29: s por golpe | F29: Corrida (min/día) = D × E ÷ 60 | G29: Frec. mínima (días) = 3 × cambio ÷ F | H29: Frec. calculada (días) | I29: Frec. elegida (vacío = calculada) | J29: Frec. final (días) | K29: Piezas por tanda = D × J | L29: Prensa por tanda (min) | M29: Cambio ÷ tanda | N29: Fase (día) | O29: Supermercado máximo (piezas) | P29: Cajones como máximo (plan, Pulmones filas 22–23) | Q29: Pallets en el rack (12 cajones, un modelo) | R29: kg de fleje por pieza | S29: Rollo de fleje = tanda (kg) | T29: Lectura
A30: C1 | B30: 1 kg | C30: Cúpula | D30: =Carga!K$37/Carga!$E$37 -> 911.79288 | E30: =Carga!G$37 -> 8 | F30: =D30*E30/60 -> 121.57238 | G30: =IF(F30=0,0,R_CORRIDA*S_EMB/F30) -> 2.2208991 | H30: =MIN(K_MAX,BASE*2^MAX(0,ROUNDUP(LOG(MAX(1,(G30)/BASE),2)-0.000001,0))) -> 4 | J30: =IF(I30="",H30,I30) -> 4 | K30: =D30*J30 -> 3647.1715 | L30: =K30*E30/60 -> 486.28953 | M30: =IF(L30+S_EMB=0,0,S_EMB/(S_EMB+L30)) -> 0.1561715 | N30: 0 | O30: =K30*(1-IF($D$42=0,0,F30/$D$42))+D30*SS_SUPER -> 4066.3029 | P30: =IF(Pulmones!$H$23=0,0,ROUNDUP(Pulmones!$H$23/Parametros!$B$67,0)) -> 15 | Q30: =IF(P30=0,0,ROUNDUP(P30/PAL_CAJ,0)) -> 2 | R30: 0.059694404 | S30: =K30*R30 -> 217.71573 | T30: =IF(D30=0,"Sin producción este mes","Se prensa cada "&J30&" días: "&FIXED(K30,0)&" piezas en "&FIXED(L30/60,1)&" h") -> Se prensa cada 4 días: 3,647 piezas en 8.1 h
A31: F1 | B31: 1 kg | C31: Fondo | D31: =Carga!K$37/Carga!$E$37 -> 911.79288 | E31: =Carga!G$37 -> 8 | F31: =D31*E31/60 -> 121.57238 | G31: =IF(F31=0,0,R_CORRIDA*S_EMB/F31) -> 2.2208991 | H31: =MIN(K_MAX,BASE*2^MAX(0,ROUNDUP(LOG(MAX(1,(G31)/BASE),2)-0.000001,0))) -> 4 | J31: =IF(I31="",H31,I31) -> 4 | K31: =D31*J31 -> 3647.1715 | L31: =K31*E31/60 -> 486.28953 | M31: =IF(L31+S_EMB=0,0,S_EMB/(S_EMB+L31)) -> 0.1561715 | N31: 1 | O31: =K31*(1-IF($D$42=0,0,F31/$D$42))+D31*SS_SUPER -> 4066.3029 | P31: =IF(Pulmones!$H$22=0,0,ROUNDUP(Pulmones!$H$22/Parametros!$B$66,0)) -> 14 | Q31: =IF(P31=0,0,ROUNDUP(P31/PAL_CAJ,0)) -> 2 | R31: 0.069216049 | S31: =K31*R31 -> 252.4428 | T31: =IF(D31=0,"Sin producción este mes","Se prensa cada "&J31&" días: "&FIXED(K31,0)&" piezas en "&FIXED(L31/60,1)&" h") -> Se prensa cada 4 días: 3,647 piezas en 8.1 h
A32: C2,5 | B32: 2,5 kg | C32: Cúpula | D32: =Carga!L$37/Carga!$E$37 -> 63.568523 | E32: =Carga!H$37 -> 8 | F32: =D32*E32/60 -> 8.4758031 | G32: =IF(F32=0,0,R_CORRIDA*S_EMB/F32) -> 31.855389 | H32: =MIN(K_MAX,BASE*2^MAX(0,ROUNDUP(LOG(MAX(1,(G32)/BASE),2)-0.000001,0))) -> 16 | J32: =IF(I32="",H32,I32) -> 16 | K32: =D32*J32 -> 1017.0964 | L32: =K32*E32/60 -> 135.61285 | M32: =IF(L32+S_EMB=0,0,S_EMB/(S_EMB+L32)) -> 0.39891345 | N32: 6 | O32: =K32*(1-IF($D$42=0,0,F32/$D$42))+D32*SS_SUPER -> 1071.0863 | P32: =IF(Pulmones!$I$23=0,0,ROUNDUP(Pulmones!$I$23/Parametros!$C$67,0)) -> 8 | Q32: =IF(P32=0,0,ROUNDUP(P32/PAL_CAJ,0)) -> 1 | R32: 0.2532172 | S32: =K32*R32 -> 257.5463 | T32: =IF(D32=0,"Sin producción este mes","Se prensa cada "&J32&" días: "&FIXED(K32,0)&" piezas en "&FIXED(L32/60,1)&" h") -> Se prensa cada 16 días: 1,017 piezas en 2.3 h
A33: F2,5 | B33: 2,5 kg | C33: Fondo | D33: =Carga!L$37/Carga!$E$37 -> 63.568523 | E33: =Carga!H$37 -> 8 | F33: =D33*E33/60 -> 8.4758031 | G33: =IF(F33=0,0,R_CORRIDA*S_EMB/F33) -> 31.855389 | H33: =MIN(K_MAX,BASE*2^MAX(0,ROUNDUP(LOG(MAX(1,(G33)/BASE),2)-0.000001,0))) -> 16 | J33: =IF(I33="",H33,I33) -> 16 | K33: =D33*J33 -> 1017.0964 | L33: =K33*E33/60 -> 135.61285 | M33: =IF(L33+S_EMB=0,0,S_EMB/(S_EMB+L33)) -> 0.39891345 | N33: 7 | O33: =K33*(1-IF($D$42=0,0,F33/$D$42))+D33*SS_SUPER -> 1071.0863 | P33: =IF(Pulmones!$I$22=0,0,ROUNDUP(Pulmones!$I$22/Parametros!$C$66,0)) -> 8 | Q33: =IF(P33=0,0,ROUNDUP(P33/PAL_CAJ,0)) -> 1 | R33: 0.20517047 | S33: =K33*R33 -> 208.67814 | T33: =IF(D33=0,"Sin producción este mes","Se prensa cada "&J33&" días: "&FIXED(K33,0)&" piezas en "&FIXED(L33/60,1)&" h") -> Se prensa cada 16 días: 1,017 piezas en 2.3 h
A34: C5 | B34: 5 kg | C34: Cúpula | D34: =Carga!M$37/Carga!$E$37 -> 287.33696 | E34: =Carga!I$37 -> 8 | F34: =D34*E34/60 -> 38.311595 | G34: =IF(F34=0,0,R_CORRIDA*S_EMB/F34) -> 7.0474747 | H34: =MIN(K_MAX,BASE*2^MAX(0,ROUNDUP(LOG(MAX(1,(G34)/BASE),2)-0.000001,0))) -> 8 | J34: =IF(I34="",H34,I34) -> 8 | K34: =D34*J34 -> 2298.6957 | L34: =K34*E34/60 -> 306.49276 | M34: =IF(L34+S_EMB=0,0,S_EMB/(S_EMB+L34)) -> 0.22699027 | N34: 2 | O34: =K34*(1-IF($D$42=0,0,F34/$D$42))+D34*SS_SUPER -> 2488.1808 | P34: =IF(Pulmones!$J$23=0,0,ROUNDUP(Pulmones!$J$23/Parametros!$D$67,0)) -> 55 | Q34: =IF(P34=0,0,ROUNDUP(P34/PAL_CAJ,0)) -> 5 | R34: 0.51398146 | S34: =K34*R34 -> 1181.487 | T34: =IF(D34=0,"Sin producción este mes","Se prensa cada "&J34&" días: "&FIXED(K34,0)&" piezas en "&FIXED(L34/60,1)&" h") -> Se prensa cada 8 días: 2,299 piezas en 5.1 h
A35: F5 | B35: 5 kg | C35: Fondo | D35: =Carga!M$37/Carga!$E$37 -> 287.33696 | E35: =Carga!I$37 -> 8 | F35: =D35*E35/60 -> 38.311595 | G35: =IF(F35=0,0,R_CORRIDA*S_EMB/F35) -> 7.0474747 | H35: =MIN(K_MAX,BASE*2^MAX(0,ROUNDUP(LOG(MAX(1,(G35)/BASE),2)-0.000001,0))) -> 8 | J35: =IF(I35="",H35,I35) -> 8 | K35: =D35*J35 -> 2298.6957 | L35: =K35*E35/60 -> 306.49276 | M35: =IF(L35+S_EMB=0,0,S_EMB/(S_EMB+L35)) -> 0.22699027 | N35: 3 | O35: =K35*(1-IF($D$42=0,0,F35/$D$42))+D35*SS_SUPER -> 2488.1808 | P35: =IF(Pulmones!$J$22=0,0,ROUNDUP(Pulmones!$J$22/Parametros!$D$66,0)) -> 41 | Q35: =IF(P35=0,0,ROUNDUP(P35/PAL_CAJ,0)) -> 4 | R35: 0.38562709 | S35: =K35*R35 -> 886.43934 | T35: =IF(D35=0,"Sin producción este mes","Se prensa cada "&J35&" días: "&FIXED(K35,0)&" piezas en "&FIXED(L35/60,1)&" h") -> Se prensa cada 8 días: 2,299 piezas en 5.1 h
A36: C10 | B36: 10 kg | C36: Cúpula | D36: =Carga!N$37/Carga!$E$37 -> 17.383176 | E36: =Carga!J$37 -> 8 | F36: =D36*E36/60 -> 2.3177568 | G36: =IF(F36=0,0,R_CORRIDA*S_EMB/F36) -> 116.49194 | H36: =MIN(K_MAX,BASE*2^MAX(0,ROUNDUP(LOG(MAX(1,(G36)/BASE),2)-0.000001,0))) -> 16 | J36: =IF(I36="",H36,I36) -> 16 | K36: =D36*J36 -> 278.13082 | L36: =K36*E36/60 -> 37.08411 | M36: =IF(L36+S_EMB=0,0,S_EMB/(S_EMB+L36)) -> 0.7081924 | N36: 14 | O36: =K36*(1-IF($D$42=0,0,F36/$D$42))+D36*SS_SUPER -> 294.79773 | P36: =IF(Pulmones!$K$23=0,0,ROUNDUP(Pulmones!$K$23/Parametros!$E$67,0)) -> 2 | Q36: =IF(P36=0,0,ROUNDUP(P36/PAL_CAJ,0)) -> 1 | R36: 0.88096644 | S36: =K36*R36 -> 245.02392 | T36: =IF(D36=0,"Sin producción este mes","Se prensa cada "&J36&" días: "&FIXED(K36,0)&" piezas en "&FIXED(L36/60,1)&" h") -> Se prensa cada 16 días: 278 piezas en 0.6 h
A37: F10 | B37: 10 kg | C37: Fondo | D37: =Carga!N$37/Carga!$E$37 -> 17.383176 | E37: =Carga!J$37 -> 8 | F37: =D37*E37/60 -> 2.3177568 | G37: =IF(F37=0,0,R_CORRIDA*S_EMB/F37) -> 116.49194 | H37: =MIN(K_MAX,BASE*2^MAX(0,ROUNDUP(LOG(MAX(1,(G37)/BASE),2)-0.000001,0))) -> 16 | J37: =IF(I37="",H37,I37) -> 16 | K37: =D37*J37 -> 278.13082 | L37: =K37*E37/60 -> 37.08411 | M37: =IF(L37+S_EMB=0,0,S_EMB/(S_EMB+L37)) -> 0.7081924 | N37: 15 | O37: =K37*(1-IF($D$42=0,0,F37/$D$42))+D37*SS_SUPER -> 294.79773 | P37: =IF(Pulmones!$K$22=0,0,ROUNDUP(Pulmones!$K$22/Parametros!$E$66,0)) -> 2 | Q37: =IF(P37=0,0,ROUNDUP(P37/PAL_CAJ,0)) -> 1 | R37: 0.6437 | S37: =K37*R37 -> 179.03281 | T37: =IF(D37=0,"Sin producción este mes","Se prensa cada "&J37&" días: "&FIXED(K37,0)&" piezas en "&FIXED(L37/60,1)&" h") -> Se prensa cada 16 días: 278 piezas en 0.6 h
A38: Total | F38: =SUM(F30:F37) -> 341.35508 | O38: =SUM(O30:O37) -> 15840.735 | P38: =SUM(P30:P37) -> 145 | Q38: =SUM(Q30:Q37) -> 17
A39: Supermercado = tanda × (1 − consumo ÷ ritmo de la prensa) + 1 día de seguridad. Cúpula y fondo de un mismo modelo se prensan en días seguidos (fases) para que lleguen juntos y ningún día pase la capacidad.
A41: Recurso | B41: Máq. | C41: Turnos | D41: Capacidad (min/día) | E41: Golpes (min/día) | F41: Cambios por día | G41: Min de cambio por día | H41: Aprovech. con cambios | I41: Aprovech. de la planilla | J41: Cambios por mes | K41: Estado
A42: Prensa Sangiacomo | B42: =Carga!R37 -> 1 | C42: =Carga!S37 -> 2 | D42: =B42*C42*MIN_TURNO -> 900 | E42: =F38 -> 341.35508 | F42: =SUMPRODUCT(--(D30:D37>0),1/J30:J37) -> 1 | G42: =F42*S_EMB -> 90 | H42: =(E42+G42)/D42 -> 0.47928342 | I42: =Carga!V37 -> 0.55776973 | J42: =F42*DIAS -> 20 | K42: =IF(H42<=UMBRAL,"OK","Pasa el umbral") -> OK
A43: La planilla de aprovechamiento supone 32 cambios por mes (4 cúpulas y 4 fondos por semana). Con la regla de la corrida mínima quedan menos cambios y la disponibilidad sube.

Sheet Rueda
A1: PASO 3 — LA RUEDA: qué formato pasa cada día por cada puesto (ola del cilindrado al embalaje)
A2: Marcapasos: soldadura circunferencial, donde se juntan el cuerpo con fondo y la cúpula con cuello. Todos los puestos de la ola corren el mismo formato el mismo día, uno detrás del otro: así los pulmones entre ellos quedan chicos.
A3: ▶ Sección 2: cada cuántos días pasa cada modelo (columna H). Sección 3: el calendario de 20 días; ninguna celda de carga debe pasar el 100 %.
A4: Mes | B4: =Carga!B4 -> Ene 2035
A6: 1) PUESTOS DE LA OLA: cambios de formato y aprovechamiento con la rueda
A7: N° | B7: Puesto | C7: Cambio (min) | D7: ¿Cambia por formato? | E7: 1 kg en máquina propia | F7: Máq. | G7: Turnos | H7: Capacidad (min/día) | I7: Carga (min/día) | J7: Carga del 1 kg (min/día) | K7: Corrida 1 kg (min/día) | L7: Corrida 2,5 kg | M7: Corrida 5 kg | N7: Corrida 10 kg | O7: Frec. mín. 1 kg (días) | P7: Frec. mín. 2,5 kg | Q7: Frec. mín. 5 kg | R7: Frec. mín. 10 kg | S7: Frec. máx. 1 kg (días) | T7: Frec. máx. 2,5 kg | U7: Frec. máx. 5 kg | V7: Frec. máx. 10 kg | W7: Cambios por día | X7: Min de cambio por día | Y7: Aprovech. con la rueda | Z7: Estado | AA7: Nota
A8: 5 | B8: =Carga!B38 -> Preparación de cuello | C8: 0 | D8: No | E8: No | F8: =Carga!R38 -> 2 | G8: =Carga!S38 -> 2 | H8: =F8*G8*MIN_TURNO -> 1800 | I8: =Carga!Q38 -> 1280.0815 | J8: =Carga!K38*Carga!G38/60 -> 911.79288 | K8: =Carga!K38*Carga!G38/60 -> 911.79288 | L8: =Carga!L38*Carga!H38/60 -> 63.568523 | M8: =Carga!M38*Carga!I38/60 -> 287.33696 | N8: =Carga!N38*Carga!J38/60 -> 17.383176 | O8: =IF(OR($D8="No",K8=0,AND($E8="Sí",$F8>=2)),0,R_CORRIDA*$C8/K8) -> 0 | P8: =IF(OR($D8="No",L8=0,FALSE()),0,R_CORRIDA*$C8/L8) -> 0 | Q8: =IF(OR($D8="No",M8=0,FALSE()),0,R_CORRIDA*$C8/M8) -> 0 | R8: =IF(OR($D8="No",N8=0,FALSE()),0,R_CORRIDA*$C8/N8) -> 0 | S8: =IF(OR($D8="No",K8=0),99,MAX(0,IF(AND($E8="Sí",$F8>=2),99*K8,$H8*UMBRAL-($I8-K8)-$C8*COUNTIF($K8:$N8,">0")))/K8) -> 99 | T8: =IF(OR($D8="No",L8=0),99,MAX(0,IF(AND($E8="Sí",$F8>=2),($F8-1)*$G8*MIN_TURNO*UMBRAL-($I8-$J8-L8)-$C8*(COUNTIF($K8:$N8,">0")-1),$H8*UMBRAL-($I8-L8)-$C8*COUNTIF($K8:$N8,">0")))/L8) -> 99 | U8: =IF(OR($D8="No",M8=0),99,MAX(0,IF(AND($E8="Sí",$F8>=2),($F8-1)*$G8*MIN_TURNO*UMBRAL-($I8-$J8-M8)-$C8*(COUNTIF($K8:$N8,">0")-1),$H8*UMBRAL-($I8-M8)-$C8*COUNTIF($K8:$N8,">0")))/M8) -> 99 | V8: =IF(OR($D8="No",N8=0),99,MAX(0,IF(AND($E8="Sí",$F8>=2),($F8-1)*$G8*MIN_TURNO*UMBRAL-($I8-$J8-N8)-$C8*(COUNTIF($K8:$N8,">0")-1),$H8*UMBRAL-($I8-N8)-$C8*COUNTIF($K8:$N8,">0")))/N8) -> 99 | W8: =IF(OR($D8="No",K8=0,AND($E8="Sí",$F8>=2)),0,1/$H$35)+IF(OR($D8="No",L8=0),0,1/$H$36)+IF(OR($D8="No",M8=0),0,1/$H$37)+IF(OR($D8="No",N8=0),0,1/$H$38) -> 0 | X8: =W8*C8 -> 0 | Y8: =IF(H8=0,0,IF(AND(E8="Sí",F8>=2),MAX(J8/(G8*MIN_TURNO),(I8-J8+X8)/((F8-1)*G8*MIN_TURNO)),(I8+X8)/H8)) -> 0.71115641 | Z8: =IF(Y8<=UMBRAL,"OK","Pasa el umbral") -> OK
A9: 6 | B9: =Carga!B39 -> Marcado del cuerpo (manuales + carros) | C9: 15 | D9: Sí | E9: Sí | F9: =Carga!R39 -> 2 | G9: =Carga!S39 -> 1 | H9: =F9*G9*MIN_TURNO -> 900 | I9: =Carga!Q39 -> 451.29554 | J9: =Carga!K39*Carga!G39/60 -> 303.93096 | K9: =Carga!K39*Carga!G39/60 -> 303.93096 | L9: =Carga!L39*Carga!H39/60 -> 21.189508 | M9: =Carga!M39*Carga!I39/60 -> 95.778988 | N9: =Carga!N39*Carga!J39/60 -> 5.7943921 | O9: 0 | P9: 0 | Q9: 0 | R9: 0 | S9: 99 | T9: 99 | U9: 99 | V9: 99 | W9: =IF(AND($E9="Sí",$F9>=2),0,Lotes!$U$8)+SUM(Lotes!$U$9:$U$14) -> 1.9375 | X9: =W9*C9 -> 29.0625 | Y9: =IF(H9=0,0,(I9+X9)/H9) -> 0.53373115 | Z9: =IF(Y9<=UMBRAL,"OK","Pasa el umbral") -> OK | AA9: Marcado unificado: trabaja desde el pulmón de desarrollos, así que no limita la frecuencia de la ola (O a V fijos). Cambia cuando cambia la tanda de la guillotina: cambios por día = Lotes columna U (manuales 2,5 a 10 kg y carros; el 1 kg tiene puesto propio). Aprovechamiento como un solo puesto: carga total + cambios ÷ capacidad de todas las máquinas.
A10: 7 | B10: =Carga!B40 -> Soldadura del cuello a la cúpula | C10: 15 | D10: Sí | E10: No | F10: =Carga!R40 -> 1 | G10: =Carga!S40 -> 2 | H10: =F10*G10*MIN_TURNO -> 900 | I10: =Carga!Q40 -> 533.36731 | J10: =Carga!K40*Carga!G40/60 -> 379.9137 | K10: =Carga!K40*Carga!G40/60 -> 379.9137 | L10: =Carga!L40*Carga!H40/60 -> 26.486885 | M10: =Carga!M40*Carga!I40/60 -> 119.72374 | N10: =Carga!N40*Carga!J40/60 -> 7.2429901 | O10: =IF(OR($D10="No",K10=0,AND($E10="Sí",$F10>=2)),0,R_CORRIDA*$C10/K10) -> 0.11844795 | P10: =IF(OR($D10="No",L10=0,FALSE()),0,R_CORRIDA*$C10/L10) -> 1.6989541 | Q10: =IF(OR($D10="No",M10=0,FALSE()),0,R_CORRIDA*$C10/M10) -> 0.37586532 | R10: =IF(OR($D10="No",N10=0,FALSE()),0,R_CORRIDA*$C10/N10) -> 6.2129037 | S10: =IF(OR($D10="No",K10=0),99,MAX(0,IF(AND($E10="Sí",$F10>=2),99*K10,$H10*UMBRAL-($I10-K10)-$C10*COUNTIF($K10:$N10,">0")))/K10) -> 1.5702155 | T10: =IF(OR($D10="No",L10=0),99,MAX(0,IF(AND($E10="Sí",$F10>=2),($F10-1)*$G10*MIN_TURNO*UMBRAL-($I10-$J10-L10)-$C10*(COUNTIF($K10:$N10,">0")-1),$H10*UMBRAL-($I10-L10)-$C10*COUNTIF($K10:$N10,">0")))/L10) -> 9.1788665 | U10: =IF(OR($D10="No",M10=0),99,MAX(0,IF(AND($E10="Sí",$F10>=2),($F10-1)*$G10*MIN_TURNO*UMBRAL-($I10-$J10-M10)-$C10*(COUNTIF($K10:$N10,">0")-1),$H10*UMBRAL-($I10-M10)-$C10*COUNTIF($K10:$N10,">0")))/M10) -> 2.8094381 | V10: =IF(OR($D10="No",N10=0),99,MAX(0,IF(AND($E10="Sí",$F10>=2),($F10-1)*$G10*MIN_TURNO*UMBRAL-($I10-$J10-N10)-$C10*(COUNTIF($K10:$N10,">0")-1),$H10*UMBRAL-($I10-N10)-$C10*COUNTIF($K10:$N10,">0")))/N10) -> 30.90929 | W10: =IF(OR($D10="No",K10=0,AND($E10="Sí",$F10>=2)),0,1/$H$35)+IF(OR($D10="No",L10=0),0,1/$H$36)+IF(OR($D10="No",M10=0),0,1/$H$37)+IF(OR($D10="No",N10=0),0,1/$H$38) -> 3.5 | X10: =W10*C10 -> 52.5 | Y10: =IF(H10=0,0,IF(AND(E10="Sí",F10>=2),MAX(J10/(G10*MIN_TURNO),(I10-J10+X10)/((F10-1)*G10*MIN_TURNO)),(I10+X10)/H10)) -> 0.65096368 | Z10: =IF(Y10<=UMBRAL,"OK","Pasa el umbral") -> OK
A11: 8 | B11: =Carga!B41 -> Cilindrado | C11: 10 | D11: Sí | E11: Sí | F11: =MAX(2,Carga!R41) -> 2 | G11: =Carga!S41 -> 1 | H11: =F11*G11*MIN_TURNO -> 900 | I11: =Carga!Q41 -> 320.02038 | J11: =Carga!K41*Carga!G41/60 -> 227.94822 | K11: =Carga!K41*Carga!G41/60 -> 227.94822 | L11: =Carga!L41*Carga!H41/60 -> 15.892131 | M11: =Carga!M41*Carga!I41/60 -> 71.834241 | N11: =Carga!N41*Carga!J41/60 -> 4.3457941 | O11: =IF(OR($D11="No",K11=0,AND($E11="Sí",$F11>=2)),0,R_CORRIDA*$C11/K11) -> 0 | P11: =IF(OR($D11="No",L11=0,FALSE()),0,R_CORRIDA*$C11/L11) -> 1.8877267 | Q11: =IF(OR($D11="No",M11=0,FALSE()),0,R_CORRIDA*$C11/M11) -> 0.41762813 | R11: =IF(OR($D11="No",N11=0,FALSE()),0,R_CORRIDA*$C11/N11) -> 6.9032263 | S11: =IF(OR($D11="No",K11=0),99,MAX(0,IF(AND($E11="Sí",$F11>=2),99*K11,$H11*UMBRAL-($I11-K11)-$C11*COUNTIF($K11:$N11,">0")))/K11) -> 99 | T11: =IF(OR($D11="No",L11=0),99,MAX(0,IF(AND($E11="Sí",$F11>=2),($F11-1)*$G11*MIN_TURNO*UMBRAL-($I11-$J11-L11)-$C11*(COUNTIF($K11:$N11,">0")-1),$H11*UMBRAL-($I11-L11)-$C11*COUNTIF($K11:$N11,">0")))/L11) -> 18.803014 | U11: =IF(OR($D11="No",M11=0),99,MAX(0,IF(AND($E11="Sí",$F11>=2),($F11-1)*$G11*MIN_TURNO*UMBRAL-($I11-$J11-M11)-$C11*(COUNTIF($K11:$N11,">0")-1),$H11*UMBRAL-($I11-M11)-$C11*COUNTIF($K11:$N11,">0")))/M11) -> 4.9386208 | V11: =IF(OR($D11="No",N11=0),99,MAX(0,IF(AND($E11="Sí",$F11>=2),($F11-1)*$G11*MIN_TURNO*UMBRAL-($I11-$J11-N11)-$C11*(COUNTIF($K11:$N11,">0")-1),$H11*UMBRAL-($I11-N11)-$C11*COUNTIF($K11:$N11,">0")))/N11) -> 66.103829 | W11: =IF(OR($D11="No",K11=0,AND($E11="Sí",$F11>=2)),0,1/$H$35)+IF(OR($D11="No",L11=0),0,1/$H$36)+IF(OR($D11="No",M11=0),0,1/$H$37)+IF(OR($D11="No",N11=0),0,1/$H$38) -> 2.5 | X11: =W11*C11 -> 25 | Y11: =IF(H11=0,0,IF(AND(E11="Sí",F11>=2),MAX(J11/(G11*MIN_TURNO),(I11-J11+X11)/((F11-1)*G11*MIN_TURNO)),(I11+X11)/H11)) -> 0.5065516 | Z11: =IF(Y11<=UMBRAL,"OK","Pasa el umbral") -> OK | AA11: Dos roladoras (layout rev. 10): una fija para el 1 kg, la otra rota 2,5 / 5 / 10 kg (editable).
A12: 9 | B12: =Carga!B42 -> Soldadura longitudinal — 2,5 a 10 kg | C12: 10 | D12: Sí | E12: No | F12: =Carga!R42 -> 1 | G12: =Carga!S42 -> 2 | H12: =F12*G12*MIN_TURNO -> 900 | I12: =Carga!Q42 -> 705.88661 | J12: =Carga!K42*Carga!G42/60 -> 0 | K12: =Carga!K42*Carga!G42/60 -> 0 | L12: =Carga!L42*Carga!H42/60 -> 121.83967 | M12: =Carga!M42*Carga!I42/60 -> 550.72918 | N12: =Carga!N42*Carga!J42/60 -> 33.317755 | O12: =IF(OR($D12="No",K12=0,AND($E12="Sí",$F12>=2)),0,R_CORRIDA*$C12/K12) -> 0 | P12: =IF(OR($D12="No",L12=0,FALSE()),0,R_CORRIDA*$C12/L12) -> 0.24622523 | Q12: =IF(OR($D12="No",M12=0,FALSE()),0,R_CORRIDA*$C12/M12) -> 0.054473235 | R12: =IF(OR($D12="No",N12=0,FALSE()),0,R_CORRIDA*$C12/N12) -> 0.90042082 | S12: =IF(OR($D12="No",K12=0),99,MAX(0,IF(AND($E12="Sí",$F12>=2),99*K12,$H12*UMBRAL-($I12-K12)-$C12*COUNTIF($K12:$N12,">0")))/K12) -> 99 | T12: =IF(OR($D12="No",L12=0),99,MAX(0,IF(AND($E12="Sí",$F12>=2),($F12-1)*$G12*MIN_TURNO*UMBRAL-($I12-$J12-L12)-$C12*(COUNTIF($K12:$N12,">0")-1),$H12*UMBRAL-($I12-L12)-$C12*COUNTIF($K12:$N12,">0")))/L12) -> 1.6082862 | U12: =IF(OR($D12="No",M12=0),99,MAX(0,IF(AND($E12="Sí",$F12>=2),($F12-1)*$G12*MIN_TURNO*UMBRAL-($I12-$J12-M12)-$C12*(COUNTIF($K12:$N12,">0")-1),$H12*UMBRAL-($I12-M12)-$C12*COUNTIF($K12:$N12,">0")))/M12) -> 1.1345732 | V12: =IF(OR($D12="No",N12=0),99,MAX(0,IF(AND($E12="Sí",$F12>=2),($F12-1)*$G12*MIN_TURNO*UMBRAL-($I12-$J12-N12)-$C12*(COUNTIF($K12:$N12,">0")-1),$H12*UMBRAL-($I12-N12)-$C12*COUNTIF($K12:$N12,">0")))/N12) -> 3.2244415 | W12: =IF(OR($D12="No",K12=0,AND($E12="Sí",$F12>=2)),0,1/$H$35)+IF(OR($D12="No",L12=0),0,1/$H$36)+IF(OR($D12="No",M12=0),0,1/$H$37)+IF(OR($D12="No",N12=0),0,1/$H$38) -> 2.5 | X12: =W12*C12 -> 25 | Y12: =IF(H12=0,0,IF(AND(E12="Sí",F12>=2),MAX(J12/(G12*MIN_TURNO),(I12-J12+X12)/((F12-1)*G12*MIN_TURNO)),(I12+X12)/H12)) -> 0.81209623 | Z12: =IF(Y12<=UMBRAL,"OK","Pasa el umbral") -> OK | AA12: CUELLO: solo 2,5 a 10 kg; es el puesto que limita el tamaño de los lotes de la ola.
A13: 10 | B13: =Carga!B43 -> Soldadura longitudinal TIG — 1 kg | C13: 0 | D13: No | E13: No | F13: =Carga!R43 -> 1 | G13: =Carga!S43 -> 2 | H13: =F13*G13*MIN_TURNO -> 900 | I13: =Carga!Q43 -> 455.89644 | J13: =Carga!K43*Carga!G43/60 -> 455.89644 | K13: =Carga!K43*Carga!G43/60 -> 455.89644 | L13: =Carga!L43*Carga!H43/60 -> 0 | M13: =Carga!M43*Carga!I43/60 -> 0 | N13: =Carga!N43*Carga!J43/60 -> 0 | O13: =IF(OR($D13="No",K13=0,AND($E13="Sí",$F13>=2)),0,R_CORRIDA*$C13/K13) -> 0 | P13: =IF(OR($D13="No",L13=0,FALSE()),0,R_CORRIDA*$C13/L13) -> 0 | Q13: =IF(OR($D13="No",M13=0,FALSE()),0,R_CORRIDA*$C13/M13) -> 0 | R13: =IF(OR($D13="No",N13=0,FALSE()),0,R_CORRIDA*$C13/N13) -> 0 | S13: =IF(OR($D13="No",K13=0),99,MAX(0,IF(AND($E13="Sí",$F13>=2),99*K13,$H13*UMBRAL-($I13-K13)-$C13*COUNTIF($K13:$N13,">0")))/K13) -> 99 | T13: =IF(OR($D13="No",L13=0),99,MAX(0,IF(AND($E13="Sí",$F13>=2),($F13-1)*$G13*MIN_TURNO*UMBRAL-($I13-$J13-L13)-$C13*(COUNTIF($K13:$N13,">0")-1),$H13*UMBRAL-($I13-L13)-$C13*COUNTIF($K13:$N13,">0")))/L13) -> 99 | U13: =IF(OR($D13="No",M13=0),99,MAX(0,IF(AND($E13="Sí",$F13>=2),($F13-1)*$G13*MIN_TURNO*UMBRAL-($I13-$J13-M13)-$C13*(COUNTIF($K13:$N13,">0")-1),$H13*UMBRAL-($I13-M13)-$C13*COUNTIF($K13:$N13,">0")))/M13) -> 99 | V13: =IF(OR($D13="No",N13=0),99,MAX(0,IF(AND($E13="Sí",$F13>=2),($F13-1)*$G13*MIN_TURNO*UMBRAL-($I13-$J13-N13)-$C13*(COUNTIF($K13:$N13,">0")-1),$H13*UMBRAL-($I13-N13)-$C13*COUNTIF($K13:$N13,">0")))/N13) -> 99 | W13: =IF(OR($D13="No",K13=0,AND($E13="Sí",$F13>=2)),0,1/$H$35)+IF(OR($D13="No",L13=0),0,1/$H$36)+IF(OR($D13="No",M13=0),0,1/$H$37)+IF(OR($D13="No",N13=0),0,1/$H$38) -> 0 | X13: =W13*C13 -> 0 | Y13: =IF(H13=0,0,IF(AND(E13="Sí",F13>=2),MAX(J13/(G13*MIN_TURNO),(I13-J13+X13)/((F13-1)*G13*MIN_TURNO)),(I13+X13)/H13)) -> 0.5065516 | Z13: =IF(Y13<=UMBRAL,"OK","Pasa el umbral") -> OK | AA13: Exclusiva del 1 kg: no cambia de formato.
A14: 11 | B14: =Carga!B44 -> Encastre de fondo | C14: 10 | D14: Sí | E14: No | F14: =Carga!R44 -> 1 | G14: =Carga!S44 -> 2 | H14: =F14*G14*MIN_TURNO -> 900 | I14: =Carga!Q44 -> 640.04077 | J14: =Carga!K44*Carga!G44/60 -> 455.89644 | K14: =Carga!K44*Carga!G44/60 -> 455.89644 | L14: =Carga!L44*Carga!H44/60 -> 31.784261 | M14: =Carga!M44*Carga!I44/60 -> 143.66848 | N14: =Carga!N44*Carga!J44/60 -> 8.6915882 | O14: =IF(OR($D14="No",K14=0,AND($E14="Sí",$F14>=2)),0,R_CORRIDA*$C14/K14) -> 0.065804418 | P14: =IF(OR($D14="No",L14=0,FALSE()),0,R_CORRIDA*$C14/L14) -> 0.94386336 | Q14: =IF(OR($D14="No",M14=0,FALSE()),0,R_CORRIDA*$C14/M14) -> 0.20881407 | R14: =IF(OR($D14="No",N14=0,FALSE()),0,R_CORRIDA*$C14/N14) -> 3.4516131 | S14: =IF(OR($D14="No",K14=0),99,MAX(0,IF(AND($E14="Sí",$F14>=2),99*K14,$H14*UMBRAL-($I14-K14)-$C14*COUNTIF($K14:$N14,">0")))/K14) -> 1.2850631 | T14: =IF(OR($D14="No",L14=0),99,MAX(0,IF(AND($E14="Sí",$F14>=2),($F14-1)*$G14*MIN_TURNO*UMBRAL-($I14-$J14-L14)-$C14*(COUNTIF($K14:$N14,">0")-1),$H14*UMBRAL-($I14-L14)-$C14*COUNTIF($K14:$N14,">0")))/L14) -> 5.0887919 | U14: =IF(OR($D14="No",M14=0),99,MAX(0,IF(AND($E14="Sí",$F14>=2),($F14-1)*$G14*MIN_TURNO*UMBRAL-($I14-$J14-M14)-$C14*(COUNTIF($K14:$N14,">0")-1),$H14*UMBRAL-($I14-M14)-$C14*COUNTIF($K14:$N14,">0")))/M14) -> 1.9045772 | V14: =IF(OR($D14="No",N14=0),99,MAX(0,IF(AND($E14="Sí",$F14>=2),($F14-1)*$G14*MIN_TURNO*UMBRAL-($I14-$J14-N14)-$C14*(COUNTIF($K14:$N14,">0")-1),$H14*UMBRAL-($I14-N14)-$C14*COUNTIF($K14:$N14,">0")))/N14) -> 15.9523 | W14: =IF(OR($D14="No",K14=0,AND($E14="Sí",$F14>=2)),0,1/$H$35)+IF(OR($D14="No",L14=0),0,1/$H$36)+IF(OR($D14="No",M14=0),0,1/$H$37)+IF(OR($D14="No",N14=0),0,1/$H$38) -> 3.5 | X14: =W14*C14 -> 35 | Y14: =IF(H14=0,0,IF(AND(E14="Sí",F14>=2),MAX(J14/(G14*MIN_TURNO),(I14-J14+X14)/((F14-1)*G14*MIN_TURNO)),(I14+X14)/H14)) -> 0.7500453 | Z14: =IF(Y14<=UMBRAL,"OK","Pasa el umbral") -> OK
A15: 12 | B15: =Carga!B45 -> Bordoneado | C15: 10 | D15: Sí | E15: No | F15: =Carga!R45 -> 1 | G15: =Carga!S45 -> 2 | H15: =F15*G15*MIN_TURNO -> 900 | I15: =Carga!Q45 -> 426.69385 | J15: =Carga!K45*Carga!G45/60 -> 303.93096 | K15: =Carga!K45*Carga!G45/60 -> 303.93096 | L15: =Carga!L45*Carga!H45/60 -> 21.189508 | M15: =Carga!M45*Carga!I45/60 -> 95.778988 | N15: =Carga!N45*Carga!J45/60 -> 5.7943921 | O15: =IF(OR($D15="No",K15=0,AND($E15="Sí",$F15>=2)),0,R_CORRIDA*$C15/K15) -> 0.098706628 | P15: =IF(OR($D15="No",L15=0,FALSE()),0,R_CORRIDA*$C15/L15) -> 1.415795 | Q15: =IF(OR($D15="No",M15=0,FALSE()),0,R_CORRIDA*$C15/M15) -> 0.3132211 | R15: =IF(OR($D15="No",N15=0,FALSE()),0,R_CORRIDA*$C15/N15) -> 5.1774197 | S15: =IF(OR($D15="No",K15=0),99,MAX(0,IF(AND($E15="Sí",$F15>=2),99*K15,$H15*UMBRAL-($I15-K15)-$C15*COUNTIF($K15:$N15,">0")))/K15) -> 2.1295531 | T15: =IF(OR($D15="No",L15=0),99,MAX(0,IF(AND($E15="Sí",$F15>=2),($F15-1)*$G15*MIN_TURNO*UMBRAL-($I15-$J15-L15)-$C15*(COUNTIF($K15:$N15,">0")-1),$H15*UMBRAL-($I15-L15)-$C15*COUNTIF($K15:$N15,">0")))/L15) -> 17.201705 | U15: =IF(OR($D15="No",M15=0),99,MAX(0,IF(AND($E15="Sí",$F15>=2),($F15-1)*$G15*MIN_TURNO*UMBRAL-($I15-$J15-M15)-$C15*(COUNTIF($K15:$N15,">0")-1),$H15*UMBRAL-($I15-M15)-$C15*COUNTIF($K15:$N15,">0")))/M15) -> 4.5843577 | V15: =IF(OR($D15="No",N15=0),99,MAX(0,IF(AND($E15="Sí",$F15>=2),($F15-1)*$G15*MIN_TURNO*UMBRAL-($I15-$J15-N15)-$C15*(COUNTIF($K15:$N15,">0")-1),$H15*UMBRAL-($I15-N15)-$C15*COUNTIF($K15:$N15,">0")))/N15) -> 60.248002 | W15: =IF(OR($D15="No",K15=0,AND($E15="Sí",$F15>=2)),0,1/$H$35)+IF(OR($D15="No",L15=0),0,1/$H$36)+IF(OR($D15="No",M15=0),0,1/$H$37)+IF(OR($D15="No",N15=0),0,1/$H$38) -> 3.5 | X15: =W15*C15 -> 35 | Y15: =IF(H15=0,0,IF(AND(E15="Sí",F15>=2),MAX(J15/(G15*MIN_TURNO),(I15-J15+X15)/((F15-1)*G15*MIN_TURNO)),(I15+X15)/H15)) -> 0.51299316 | Z15: =IF(Y15<=UMBRAL,"OK","Pasa el umbral") -> OK
A16: 13 | B16: =Carga!B46 -> Soldadura circunferencial de cúpula y fondo | C16: 10 | D16: Sí | E16: No | F16: =Carga!R46 -> 2 | G16: =Carga!S46 -> 2 | H16: =F16*G16*MIN_TURNO -> 1800 | I16: =Carga!Q46 -> 1280.0815 | J16: =Carga!K46*Carga!G46/60 -> 911.79288 | K16: =Carga!K46*Carga!G46/60 -> 911.79288 | L16: =Carga!L46*Carga!H46/60 -> 63.568523 | M16: =Carga!M46*Carga!I46/60 -> 287.33696 | N16: =Carga!N46*Carga!J46/60 -> 17.383176 | O16: =IF(OR($D16="No",K16=0,AND($E16="Sí",$F16>=2)),0,R_CORRIDA*$C16/K16) -> 0.032902209 | P16: =IF(OR($D16="No",L16=0,FALSE()),0,R_CORRIDA*$C16/L16) -> 0.47193168 | Q16: =IF(OR($D16="No",M16=0,FALSE()),0,R_CORRIDA*$C16/M16) -> 0.10440703 | R16: =IF(OR($D16="No",N16=0,FALSE()),0,R_CORRIDA*$C16/N16) -> 1.7258066 | S16: =IF(OR($D16="No",K16=0),99,MAX(0,IF(AND($E16="Sí",$F16>=2),99*K16,$H16*UMBRAL-($I16-K16)-$C16*COUNTIF($K16:$N16,">0")))/K16) -> 1.3289327 | T16: =IF(OR($D16="No",L16=0),99,MAX(0,IF(AND($E16="Sí",$F16>=2),($F16-1)*$G16*MIN_TURNO*UMBRAL-($I16-$J16-L16)-$C16*(COUNTIF($K16:$N16,">0")-1),$H16*UMBRAL-($I16-L16)-$C16*COUNTIF($K16:$N16,">0")))/L16) -> 5.7180341 | U16: =IF(OR($D16="No",M16=0),99,MAX(0,IF(AND($E16="Sí",$F16>=2),($F16-1)*$G16*MIN_TURNO*UMBRAL-($I16-$J16-M16)-$C16*(COUNTIF($K16:$N16,">0")-1),$H16*UMBRAL-($I16-M16)-$C16*COUNTIF($K16:$N16,">0")))/M16) -> 2.0437866 | V16: =IF(OR($D16="No",N16=0),99,MAX(0,IF(AND($E16="Sí",$F16>=2),($F16-1)*$G16*MIN_TURNO*UMBRAL-($I16-$J16-N16)-$C16*(COUNTIF($K16:$N16,">0")-1),$H16*UMBRAL-($I16-N16)-$C16*COUNTIF($K16:$N16,">0")))/N16) -> 18.253375 | W16: =IF(OR($D16="No",K16=0,AND($E16="Sí",$F16>=2)),0,1/$H$35)+IF(OR($D16="No",L16=0),0,1/$H$36)+IF(OR($D16="No",M16=0),0,1/$H$37)+IF(OR($D16="No",N16=0),0,1/$H$38) -> 3.5 | X16: =W16*C16 -> 35 | Y16: =IF(H16=0,0,IF(AND(E16="Sí",F16>=2),MAX(J16/(G16*MIN_TURNO),(I16-J16+X16)/((F16-1)*G16*MIN_TURNO)),(I16+X16)/H16)) -> 0.73060086 | Z16: =IF(Y16<=UMBRAL,"OK","Pasa el umbral") -> OK | AA16: MARCAPASOS. El 1 kg ocupa más de una máquina, por eso las 2 soldadoras rotan formatos.
A17: 14 | B17: =Carga!B47 -> Control de calidad — Espesor | C17: 0 | D17: No | E17: No | F17: =Carga!R47 -> 1 | G17: =Carga!S47 -> 1 | H17: =F17*G17*MIN_TURNO -> 450 | I17: =Carga!Q47 -> 51.203262 | J17: =Carga!K47*Carga!G47/60 -> 36.471715 | K17: =Carga!K47*Carga!G47/60 -> 36.471715 | L17: =Carga!L47*Carga!H47/60 -> 2.5427409 | M17: =Carga!M47*Carga!I47/60 -> 11.493479 | N17: =Carga!N47*Carga!J47/60 -> 0.69532705 | O17: =IF(OR($D17="No",K17=0,AND($E17="Sí",$F17>=2)),0,R_CORRIDA*$C17/K17) -> 0 | P17: =IF(OR($D17="No",L17=0,FALSE()),0,R_CORRIDA*$C17/L17) -> 0 | Q17: =IF(OR($D17="No",M17=0,FALSE()),0,R_CORRIDA*$C17/M17) -> 0 | R17: =IF(OR($D17="No",N17=0,FALSE()),0,R_CORRIDA*$C17/N17) -> 0 | S17: =IF(OR($D17="No",K17=0),99,MAX(0,IF(AND($E17="Sí",$F17>=2),99*K17,$H17*UMBRAL-($I17-K17)-$C17*COUNTIF($K17:$N17,">0")))/K17) -> 99 | T17: =IF(OR($D17="No",L17=0),99,MAX(0,IF(AND($E17="Sí",$F17>=2),($F17-1)*$G17*MIN_TURNO*UMBRAL-($I17-$J17-L17)-$C17*(COUNTIF($K17:$N17,">0")-1),$H17*UMBRAL-($I17-L17)-$C17*COUNTIF($K17:$N17,">0")))/L17) -> 99 | U17: =IF(OR($D17="No",M17=0),99,MAX(0,IF(AND($E17="Sí",$F17>=2),($F17-1)*$G17*MIN_TURNO*UMBRAL-($I17-$J17-M17)-$C17*(COUNTIF($K17:$N17,">0")-1),$H17*UMBRAL-($I17-M17)-$C17*COUNTIF($K17:$N17,">0")))/M17) -> 99 | V17: =IF(OR($D17="No",N17=0),99,MAX(0,IF(AND($E17="Sí",$F17>=2),($F17-1)*$G17*MIN_TURNO*UMBRAL-($I17-$J17-N17)-$C17*(COUNTIF($K17:$N17,">0")-1),$H17*UMBRAL-($I17-N17)-$C17*COUNTIF($K17:$N17,">0")))/N17) -> 99 | W17: =IF(OR($D17="No",K17=0,AND($E17="Sí",$F17>=2)),0,1/$H$35)+IF(OR($D17="No",L17=0),0,1/$H$36)+IF(OR($D17="No",M17=0),0,1/$H$37)+IF(OR($D17="No",N17=0),0,1/$H$38) -> 0 | X17: =W17*C17 -> 0 | Y17: =IF(H17=0,0,IF(AND(E17="Sí",F17>=2),MAX(J17/(G17*MIN_TURNO),(I17-J17+X17)/((F17-1)*G17*MIN_TURNO)),(I17+X17)/H17)) -> 0.11378503 | Z17: =IF(Y17<=UMBRAL,"OK","Pasa el umbral") -> OK
A18: 15 | B18: =Carga!B48 -> Prueba hidráulica | C18: 10 | D18: Sí | E18: No | F18: =Carga!R48 -> 2 | G18: =Carga!S48 -> 2 | H18: =F18*G18*MIN_TURNO -> 1800 | I18: =Carga!Q48 -> 1280.0815 | J18: =Carga!K48*Carga!G48/60 -> 911.79288 | K18: =Carga!K48*Carga!G48/60 -> 911.79288 | L18: =Carga!L48*Carga!H48/60 -> 63.568523 | M18: =Carga!M48*Carga!I48/60 -> 287.33696 | N18: =Carga!N48*Carga!J48/60 -> 17.383176 | O18: =IF(OR($D18="No",K18=0,AND($E18="Sí",$F18>=2)),0,R_CORRIDA*$C18/K18) -> 0.032902209 | P18: =IF(OR($D18="No",L18=0,FALSE()),0,R_CORRIDA*$C18/L18) -> 0.47193168 | Q18: =IF(OR($D18="No",M18=0,FALSE()),0,R_CORRIDA*$C18/M18) -> 0.10440703 | R18: =IF(OR($D18="No",N18=0,FALSE()),0,R_CORRIDA*$C18/N18) -> 1.7258066 | S18: =IF(OR($D18="No",K18=0),99,MAX(0,IF(AND($E18="Sí",$F18>=2),99*K18,$H18*UMBRAL-($I18-K18)-$C18*COUNTIF($K18:$N18,">0")))/K18) -> 1.3289327 | T18: =IF(OR($D18="No",L18=0),99,MAX(0,IF(AND($E18="Sí",$F18>=2),($F18-1)*$G18*MIN_TURNO*UMBRAL-($I18-$J18-L18)-$C18*(COUNTIF($K18:$N18,">0")-1),$H18*UMBRAL-($I18-L18)-$C18*COUNTIF($K18:$N18,">0")))/L18) -> 5.7180341 | U18: =IF(OR($D18="No",M18=0),99,MAX(0,IF(AND($E18="Sí",$F18>=2),($F18-1)*$G18*MIN_TURNO*UMBRAL-($I18-$J18-M18)-$C18*(COUNTIF($K18:$N18,">0")-1),$H18*UMBRAL-($I18-M18)-$C18*COUNTIF($K18:$N18,">0")))/M18) -> 2.0437866 | V18: =IF(OR($D18="No",N18=0),99,MAX(0,IF(AND($E18="Sí",$F18>=2),($F18-1)*$G18*MIN_TURNO*UMBRAL-($I18-$J18-N18)-$C18*(COUNTIF($K18:$N18,">0")-1),$H18*UMBRAL-($I18-N18)-$C18*COUNTIF($K18:$N18,">0")))/N18) -> 18.253375 | W18: =IF(OR($D18="No",K18=0,AND($E18="Sí",$F18>=2)),0,1/$H$35)+IF(OR($D18="No",L18=0),0,1/$H$36)+IF(OR($D18="No",M18=0),0,1/$H$37)+IF(OR($D18="No",N18=0),0,1/$H$38) -> 3.5 | X18: =W18*C18 -> 35 | Y18: =IF(H18=0,0,IF(AND(E18="Sí",F18>=2),MAX(J18/(G18*MIN_TURNO),(I18-J18+X18)/((F18-1)*G18*MIN_TURNO)),(I18+X18)/H18)) -> 0.73060086 | Z18: =IF(Y18<=UMBRAL,"OK","Pasa el umbral") -> OK
A19: 16 | B19: =Carga!B49 -> Secado | C19: 0 | D19: No | E19: No | F19: =Carga!R49 -> 4 | G19: =Carga!S49 -> 2 | H19: =F19*G19*MIN_TURNO -> 3600 | I19: =Carga!Q49 -> 2560.1631 | J19: =Carga!K49*Carga!G49/60 -> 1823.5858 | K19: =Carga!K49*Carga!G49/60 -> 1823.5858 | L19: =Carga!L49*Carga!H49/60 -> 127.13705 | M19: =Carga!M49*Carga!I49/60 -> 574.67393 | N19: =Carga!N49*Carga!J49/60 -> 34.766353 | O19: =IF(OR($D19="No",K19=0,AND($E19="Sí",$F19>=2)),0,R_CORRIDA*$C19/K19) -> 0 | P19: =IF(OR($D19="No",L19=0,FALSE()),0,R_CORRIDA*$C19/L19) -> 0 | Q19: =IF(OR($D19="No",M19=0,FALSE()),0,R_CORRIDA*$C19/M19) -> 0 | R19: =IF(OR($D19="No",N19=0,FALSE()),0,R_CORRIDA*$C19/N19) -> 0 | S19: =IF(OR($D19="No",K19=0),99,MAX(0,IF(AND($E19="Sí",$F19>=2),99*K19,$H19*UMBRAL-($I19-K19)-$C19*COUNTIF($K19:$N19,">0")))/K19) -> 99 | T19: =IF(OR($D19="No",L19=0),99,MAX(0,IF(AND($E19="Sí",$F19>=2),($F19-1)*$G19*MIN_TURNO*UMBRAL-($I19-$J19-L19)-$C19*(COUNTIF($K19:$N19,">0")-1),$H19*UMBRAL-($I19-L19)-$C19*COUNTIF($K19:$N19,">0")))/L19) -> 99 | U19: =IF(OR($D19="No",M19=0),99,MAX(0,IF(AND($E19="Sí",$F19>=2),($F19-1)*$G19*MIN_TURNO*UMBRAL-($I19-$J19-M19)-$C19*(COUNTIF($K19:$N19,">0")-1),$H19*UMBRAL-($I19-M19)-$C19*COUNTIF($K19:$N19,">0")))/M19) -> 99 | V19: =IF(OR($D19="No",N19=0),99,MAX(0,IF(AND($E19="Sí",$F19>=2),($F19-1)*$G19*MIN_TURNO*UMBRAL-($I19-$J19-N19)-$C19*(COUNTIF($K19:$N19,">0")-1),$H19*UMBRAL-($I19-N19)-$C19*COUNTIF($K19:$N19,">0")))/N19) -> 99 | W19: =IF(OR($D19="No",K19=0,AND($E19="Sí",$F19>=2)),0,1/$H$35)+IF(OR($D19="No",L19=0),0,1/$H$36)+IF(OR($D19="No",M19=0),0,1/$H$37)+IF(OR($D19="No",N19=0),0,1/$H$38) -> 0 | X19: =W19*C19 -> 0 | Y19: =IF(H19=0,0,IF(AND(E19="Sí",F19>=2),MAX(J19/(G19*MIN_TURNO),(I19-J19+X19)/((F19-1)*G19*MIN_TURNO)),(I19+X19)/H19)) -> 0.71115641 | Z19: =IF(Y19<=UMBRAL,"OK","Pasa el umbral") -> OK
A20: 17 | B20: =Carga!B50 -> Granallado | C20: 10 | D20: No | E20: No | F20: =Carga!R50 -> 1 | G20: =Carga!S50 -> 2 | H20: =F20*G20*MIN_TURNO -> 900 | I20: =Carga!Q50 -> 640.04077 | J20: =Carga!K50*Carga!G50/60 -> 455.89644 | K20: =Carga!K50*Carga!G50/60 -> 455.89644 | L20: =Carga!L50*Carga!H50/60 -> 31.784261 | M20: =Carga!M50*Carga!I50/60 -> 143.66848 | N20: =Carga!N50*Carga!J50/60 -> 8.6915882 | O20: =IF(OR($D20="No",K20=0,AND($E20="Sí",$F20>=2)),0,R_CORRIDA*$C20/K20) -> 0 | P20: =IF(OR($D20="No",L20=0,FALSE()),0,R_CORRIDA*$C20/L20) -> 0 | Q20: =IF(OR($D20="No",M20=0,FALSE()),0,R_CORRIDA*$C20/M20) -> 0 | R20: =IF(OR($D20="No",N20=0,FALSE()),0,R_CORRIDA*$C20/N20) -> 0 | S20: =IF(OR($D20="No",K20=0),99,MAX(0,IF(AND($E20="Sí",$F20>=2),99*K20,$H20*UMBRAL-($I20-K20)-$C20*COUNTIF($K20:$N20,">0")))/K20) -> 99 | T20: =IF(OR($D20="No",L20=0),99,MAX(0,IF(AND($E20="Sí",$F20>=2),($F20-1)*$G20*MIN_TURNO*UMBRAL-($I20-$J20-L20)-$C20*(COUNTIF($K20:$N20,">0")-1),$H20*UMBRAL-($I20-L20)-$C20*COUNTIF($K20:$N20,">0")))/L20) -> 99 | U20: =IF(OR($D20="No",M20=0),99,MAX(0,IF(AND($E20="Sí",$F20>=2),($F20-1)*$G20*MIN_TURNO*UMBRAL-($I20-$J20-M20)-$C20*(COUNTIF($K20:$N20,">0")-1),$H20*UMBRAL-($I20-M20)-$C20*COUNTIF($K20:$N20,">0")))/M20) -> 99 | V20: =IF(OR($D20="No",N20=0),99,MAX(0,IF(AND($E20="Sí",$F20>=2),($F20-1)*$G20*MIN_TURNO*UMBRAL-($I20-$J20-N20)-$C20*(COUNTIF($K20:$N20,">0")-1),$H20*UMBRAL-($I20-N20)-$C20*COUNTIF($K20:$N20,">0")))/N20) -> 99 | W20: =IF(OR($D20="No",K20=0,AND($E20="Sí",$F20>=2)),0,1/$H$35)+IF(OR($D20="No",L20=0),0,1/$H$36)+IF(OR($D20="No",M20=0),0,1/$H$37)+IF(OR($D20="No",N20=0),0,1/$H$38) -> 0 | X20: =W20*C20 -> 0 | Y20: =IF(H20=0,0,IF(AND(E20="Sí",F20>=2),MAX(J20/(G20*MIN_TURNO),(I20-J20+X20)/((F20-1)*G20*MIN_TURNO)),(I20+X20)/H20)) -> 0.71115641 | Z20: =IF(Y20<=UMBRAL,"OK","Pasa el umbral") -> OK
A21: 18 | B21: =Carga!B51 -> Detección de defectos | C21: 0 | D21: No | E21: No | F21: =Carga!R51 -> 1 | G21: =Carga!S51 -> 2 | H21: =F21*G21*MIN_TURNO -> 900 | I21: =Carga!Q51 -> 426.69385 | J21: =Carga!K51*Carga!G51/60 -> 303.93096 | K21: =Carga!K51*Carga!G51/60 -> 303.93096 | L21: =Carga!L51*Carga!H51/60 -> 21.189508 | M21: =Carga!M51*Carga!I51/60 -> 95.778988 | N21: =Carga!N51*Carga!J51/60 -> 5.7943921 | O21: =IF(OR($D21="No",K21=0,AND($E21="Sí",$F21>=2)),0,R_CORRIDA*$C21/K21) -> 0 | P21: =IF(OR($D21="No",L21=0,FALSE()),0,R_CORRIDA*$C21/L21) -> 0 | Q21: =IF(OR($D21="No",M21=0,FALSE()),0,R_CORRIDA*$C21/M21) -> 0 | R21: =IF(OR($D21="No",N21=0,FALSE()),0,R_CORRIDA*$C21/N21) -> 0 | S21: =IF(OR($D21="No",K21=0),99,MAX(0,IF(AND($E21="Sí",$F21>=2),99*K21,$H21*UMBRAL-($I21-K21)-$C21*COUNTIF($K21:$N21,">0")))/K21) -> 99 | T21: =IF(OR($D21="No",L21=0),99,MAX(0,IF(AND($E21="Sí",$F21>=2),($F21-1)*$G21*MIN_TURNO*UMBRAL-($I21-$J21-L21)-$C21*(COUNTIF($K21:$N21,">0")-1),$H21*UMBRAL-($I21-L21)-$C21*COUNTIF($K21:$N21,">0")))/L21) -> 99 | U21: =IF(OR($D21="No",M21=0),99,MAX(0,IF(AND($E21="Sí",$F21>=2),($F21-1)*$G21*MIN_TURNO*UMBRAL-($I21-$J21-M21)-$C21*(COUNTIF($K21:$N21,">0")-1),$H21*UMBRAL-($I21-M21)-$C21*COUNTIF($K21:$N21,">0")))/M21) -> 99 | V21: =IF(OR($D21="No",N21=0),99,MAX(0,IF(AND($E21="Sí",$F21>=2),($F21-1)*$G21*MIN_TURNO*UMBRAL-($I21-$J21-N21)-$C21*(COUNTIF($K21:$N21,">0")-1),$H21*UMBRAL-($I21-N21)-$C21*COUNTIF($K21:$N21,">0")))/N21) -> 99 | W21: =IF(OR($D21="No",K21=0,AND($E21="Sí",$F21>=2)),0,1/$H$35)+IF(OR($D21="No",L21=0),0,1/$H$36)+IF(OR($D21="No",M21=0),0,1/$H$37)+IF(OR($D21="No",N21=0),0,1/$H$38) -> 0 | X21: =W21*C21 -> 0 | Y21: =IF(H21=0,0,IF(AND(E21="Sí",F21>=2),MAX(J21/(G21*MIN_TURNO),(I21-J21+X21)/((F21-1)*G21*MIN_TURNO)),(I21+X21)/H21)) -> 0.47410427 | Z21: =IF(Y21<=UMBRAL,"OK","Pasa el umbral") -> OK
A22: 19 | B22: =Carga!B52 -> Corrección de defectos | C22: 0 | D22: No | E22: No | F22: =Carga!R52 -> 1 | G22: =Carga!S52 -> 1 | H22: =F22*G22*MIN_TURNO -> 450 | I22: =Carga!Q52 -> 192.01223 | J22: =Carga!K52*Carga!G52/60 -> 136.76893 | K22: =Carga!K52*Carga!G52/60 -> 136.76893 | L22: =Carga!L52*Carga!H52/60 -> 9.5352784 | M22: =Carga!M52*Carga!I52/60 -> 43.100545 | N22: =Carga!N52*Carga!J52/60 -> 2.6074765 | O22: =IF(OR($D22="No",K22=0,AND($E22="Sí",$F22>=2)),0,R_CORRIDA*$C22/K22) -> 0 | P22: =IF(OR($D22="No",L22=0,FALSE()),0,R_CORRIDA*$C22/L22) -> 0 | Q22: =IF(OR($D22="No",M22=0,FALSE()),0,R_CORRIDA*$C22/M22) -> 0 | R22: =IF(OR($D22="No",N22=0,FALSE()),0,R_CORRIDA*$C22/N22) -> 0 | S22: =IF(OR($D22="No",K22=0),99,MAX(0,IF(AND($E22="Sí",$F22>=2),99*K22,$H22*UMBRAL-($I22-K22)-$C22*COUNTIF($K22:$N22,">0")))/K22) -> 99 | T22: =IF(OR($D22="No",L22=0),99,MAX(0,IF(AND($E22="Sí",$F22>=2),($F22-1)*$G22*MIN_TURNO*UMBRAL-($I22-$J22-L22)-$C22*(COUNTIF($K22:$N22,">0")-1),$H22*UMBRAL-($I22-L22)-$C22*COUNTIF($K22:$N22,">0")))/L22) -> 99 | U22: =IF(OR($D22="No",M22=0),99,MAX(0,IF(AND($E22="Sí",$F22>=2),($F22-1)*$G22*MIN_TURNO*UMBRAL-($I22-$J22-M22)-$C22*(COUNTIF($K22:$N22,">0")-1),$H22*UMBRAL-($I22-M22)-$C22*COUNTIF($K22:$N22,">0")))/M22) -> 99 | V22: =IF(OR($D22="No",N22=0),99,MAX(0,IF(AND($E22="Sí",$F22>=2),($F22-1)*$G22*MIN_TURNO*UMBRAL-($I22-$J22-N22)-$C22*(COUNTIF($K22:$N22,">0")-1),$H22*UMBRAL-($I22-N22)-$C22*COUNTIF($K22:$N22,">0")))/N22) -> 99 | W22: =IF(OR($D22="No",K22=0,AND($E22="Sí",$F22>=2)),0,1/$H$35)+IF(OR($D22="No",L22=0),0,1/$H$36)+IF(OR($D22="No",M22=0),0,1/$H$37)+IF(OR($D22="No",N22=0),0,1/$H$38) -> 0 | X22: =W22*C22 -> 0 | Y22: =IF(H22=0,0,IF(AND(E22="Sí",F22>=2),MAX(J22/(G22*MIN_TURNO),(I22-J22+X22)/((F22-1)*G22*MIN_TURNO)),(I22+X22)/H22)) -> 0.42669385 | Z22: =IF(Y22<=UMBRAL,"OK","Pasa el umbral") -> OK
A23: 20 | B23: =Carga!B53 -> Pintura en polvo + horno | C23: 30 | D23: Sí | E23: No | F23: =Carga!R53 -> 1 | G23: =Carga!S53 -> 2 | H23: =F23*G23*MIN_TURNO -> 900 | I23: =Carga!Q53 -> 533.36731 | J23: =Carga!K53*Carga!G53/60 -> 379.9137 | K23: =Carga!K53*Carga!G53/60 -> 379.9137 | L23: =Carga!L53*Carga!H53/60 -> 26.486885 | M23: =Carga!M53*Carga!I53/60 -> 119.72374 | N23: =Carga!N53*Carga!J53/60 -> 7.2429901 | O23: =IF(OR($D23="No",K23=0,AND($E23="Sí",$F23>=2)),0,R_CORRIDA*$C23/K23) -> 0.23689591 | P23: =IF(OR($D23="No",L23=0,FALSE()),0,R_CORRIDA*$C23/L23) -> 3.3979081 | Q23: =IF(OR($D23="No",M23=0,FALSE()),0,R_CORRIDA*$C23/M23) -> 0.75173064 | R23: =IF(OR($D23="No",N23=0,FALSE()),0,R_CORRIDA*$C23/N23) -> 12.425807 | S23: =IF(OR($D23="No",K23=0),99,MAX(0,IF(AND($E23="Sí",$F23>=2),99*K23,$H23*UMBRAL-($I23-K23)-$C23*COUNTIF($K23:$N23,">0")))/K23) -> 1.4122849 | T23: =IF(OR($D23="No",L23=0),99,MAX(0,IF(AND($E23="Sí",$F23>=2),($F23-1)*$G23*MIN_TURNO*UMBRAL-($I23-$J23-L23)-$C23*(COUNTIF($K23:$N23,">0")-1),$H23*UMBRAL-($I23-L23)-$C23*COUNTIF($K23:$N23,">0")))/L23) -> 6.9135944 | U23: =IF(OR($D23="No",M23=0),99,MAX(0,IF(AND($E23="Sí",$F23>=2),($F23-1)*$G23*MIN_TURNO*UMBRAL-($I23-$J23-M23)-$C23*(COUNTIF($K23:$N23,">0")-1),$H23*UMBRAL-($I23-M23)-$C23*COUNTIF($K23:$N23,">0")))/M23) -> 2.3082844 | V23: =IF(OR($D23="No",N23=0),99,MAX(0,IF(AND($E23="Sí",$F23>=2),($F23-1)*$G23*MIN_TURNO*UMBRAL-($I23-$J23-N23)-$C23*(COUNTIF($K23:$N23,">0")-1),$H23*UMBRAL-($I23-N23)-$C23*COUNTIF($K23:$N23,">0")))/N23) -> 22.625418 | W23: =IF(OR($D23="No",K23=0,AND($E23="Sí",$F23>=2)),0,1/$H$35)+IF(OR($D23="No",L23=0),0,1/$H$36)+IF(OR($D23="No",M23=0),0,1/$H$37)+IF(OR($D23="No",N23=0),0,1/$H$38) -> 3.5 | X23: =W23*C23 -> 105 | Y23: =IF(H23=0,0,IF(AND(E23="Sí",F23>=2),MAX(J23/(G23*MIN_TURNO),(I23-J23+X23)/((F23-1)*G23*MIN_TURNO)),(I23+X23)/H23)) -> 0.70929701 | Z23: =IF(Y23<=UMBRAL,"OK","Pasa el umbral") -> OK | AA23: Cambio de ganchos por formato (30 min).
A24: 21 | B24: =Carga!B54 -> Carga de polvo | C24: 0 | D24: No | E24: No | F24: =Carga!R54 -> 1 | G24: =Carga!S54 -> 1 | H24: =F24*G24*MIN_TURNO -> 450 | I24: =Carga!Q54 -> 243.57039 | J24: =Carga!K54*Carga!G54/60 -> 108.24516 | K24: =Carga!K54*Carga!G54/60 -> 108.24516 | L24: =Carga!L54*Carga!H54/60 -> 25.098047 | M24: =Carga!M54*Carga!I54/60 -> 104.00055 | N24: =Carga!N54*Carga!J54/60 -> 6.2266323 | O24: =IF(OR($D24="No",K24=0,AND($E24="Sí",$F24>=2)),0,R_CORRIDA*$C24/K24) -> 0 | P24: =IF(OR($D24="No",L24=0,FALSE()),0,R_CORRIDA*$C24/L24) -> 0 | Q24: =IF(OR($D24="No",M24=0,FALSE()),0,R_CORRIDA*$C24/M24) -> 0 | R24: =IF(OR($D24="No",N24=0,FALSE()),0,R_CORRIDA*$C24/N24) -> 0 | S24: =IF(OR($D24="No",K24=0),99,MAX(0,IF(AND($E24="Sí",$F24>=2),99*K24,$H24*UMBRAL-($I24-K24)-$C24*COUNTIF($K24:$N24,">0")))/K24) -> 99 | T24: =IF(OR($D24="No",L24=0),99,MAX(0,IF(AND($E24="Sí",$F24>=2),($F24-1)*$G24*MIN_TURNO*UMBRAL-($I24-$J24-L24)-$C24*(COUNTIF($K24:$N24,">0")-1),$H24*UMBRAL-($I24-L24)-$C24*COUNTIF($K24:$N24,">0")))/L24) -> 99 | U24: =IF(OR($D24="No",M24=0),99,MAX(0,IF(AND($E24="Sí",$F24>=2),($F24-1)*$G24*MIN_TURNO*UMBRAL-($I24-$J24-M24)-$C24*(COUNTIF($K24:$N24,">0")-1),$H24*UMBRAL-($I24-M24)-$C24*COUNTIF($K24:$N24,">0")))/M24) -> 99 | V24: =IF(OR($D24="No",N24=0),99,MAX(0,IF(AND($E24="Sí",$F24>=2),($F24-1)*$G24*MIN_TURNO*UMBRAL-($I24-$J24-N24)-$C24*(COUNTIF($K24:$N24,">0")-1),$H24*UMBRAL-($I24-N24)-$C24*COUNTIF($K24:$N24,">0")))/N24) -> 99 | W24: =IF(OR($D24="No",K24=0,AND($E24="Sí",$F24>=2)),0,1/$H$35)+IF(OR($D24="No",L24=0),0,1/$H$36)+IF(OR($D24="No",M24=0),0,1/$H$37)+IF(OR($D24="No",N24=0),0,1/$H$38) -> 0 | X24: =W24*C24 -> 0 | Y24: =IF(H24=0,0,IF(AND(E24="Sí",F24>=2),MAX(J24/(G24*MIN_TURNO),(I24-J24+X24)/((F24-1)*G24*MIN_TURNO)),(I24+X24)/H24)) -> 0.54126753 | Z24: =IF(Y24<=UMBRAL,"OK","Pasa el umbral") -> OK
A25: 22 | B25: =Carga!B55 -> Ensamblaje | C25: 10 | D25: Sí | E25: No | F25: =Carga!R55 -> 1 | G25: =Carga!S55 -> 2 | H25: =F25*G25*MIN_TURNO -> 900 | I25: =Carga!Q55 -> 541.26753 | J25: =Carga!K55*Carga!G55/60 -> 240.54479 | K25: =Carga!K55*Carga!G55/60 -> 240.54479 | L25: =Carga!L55*Carga!H55/60 -> 55.773438 | M25: =Carga!M55*Carga!I55/60 -> 231.11234 | N25: =Carga!N55*Carga!J55/60 -> 13.836961 | O25: =IF(OR($D25="No",K25=0,AND($E25="Sí",$F25>=2)),0,R_CORRIDA*$C25/K25) -> 0.1247169 | P25: =IF(OR($D25="No",L25=0,FALSE()),0,R_CORRIDA*$C25/L25) -> 0.53789045 | Q25: =IF(OR($D25="No",M25=0,FALSE()),0,R_CORRIDA*$C25/M25) -> 0.129807 | R25: =IF(OR($D25="No",N25=0,FALSE()),0,R_CORRIDA*$C25/N25) -> 2.1681062 | S25: =IF(OR($D25="No",K25=0),99,MAX(0,IF(AND($E25="Sí",$F25>=2),99*K25,$H25*UMBRAL-($I25-K25)-$C25*COUNTIF($K25:$N25,">0")))/K25) -> 1.9508934 | T25: =IF(OR($D25="No",L25=0),99,MAX(0,IF(AND($E25="Sí",$F25>=2),($F25-1)*$G25*MIN_TURNO*UMBRAL-($I25-$J25-L25)-$C25*(COUNTIF($K25:$N25,">0")-1),$H25*UMBRAL-($I25-L25)-$C25*COUNTIF($K25:$N25,">0")))/L25) -> 5.1011003 | U25: =IF(OR($D25="No",M25=0),99,MAX(0,IF(AND($E25="Sí",$F25>=2),($F25-1)*$G25*MIN_TURNO*UMBRAL-($I25-$J25-M25)-$C25*(COUNTIF($K25:$N25,">0")-1),$H25*UMBRAL-($I25-M25)-$C25*COUNTIF($K25:$N25,">0")))/M25) -> 1.9897025 | V25: =IF(OR($D25="No",N25=0),99,MAX(0,IF(AND($E25="Sí",$F25>=2),($F25-1)*$G25*MIN_TURNO*UMBRAL-($I25-$J25-N25)-$C25*(COUNTIF($K25:$N25,">0")-1),$H25*UMBRAL-($I25-N25)-$C25*COUNTIF($K25:$N25,">0")))/N25) -> 17.530543 | W25: =IF(OR($D25="No",K25=0,AND($E25="Sí",$F25>=2)),0,1/$H$35)+IF(OR($D25="No",L25=0),0,1/$H$36)+IF(OR($D25="No",M25=0),0,1/$H$37)+IF(OR($D25="No",N25=0),0,1/$H$38) -> 3.5 | X25: =W25*C25 -> 35 | Y25: =IF(H25=0,0,IF(AND(E25="Sí",F25>=2),MAX(J25/(G25*MIN_TURNO),(I25-J25+X25)/((F25-1)*G25*MIN_TURNO)),(I25+X25)/H25)) -> 0.64029726 | Z25: =IF(Y25<=UMBRAL,"OK","Pasa el umbral") -> OK
A26: 23 | B26: =Carga!B56 -> Presurización | C26: 0 | D26: No | E26: No | F26: =Carga!R56 -> 1 | G26: =Carga!S56 -> 1 | H26: =F26*G26*MIN_TURNO -> 450 | I26: =Carga!Q56 -> 162.38026 | J26: =Carga!K56*Carga!G56/60 -> 72.163438 | K26: =Carga!K56*Carga!G56/60 -> 72.163438 | L26: =Carga!L56*Carga!H56/60 -> 16.732031 | M26: =Carga!M56*Carga!I56/60 -> 69.333702 | N26: =Carga!N56*Carga!J56/60 -> 4.1510882 | O26: =IF(OR($D26="No",K26=0,AND($E26="Sí",$F26>=2)),0,R_CORRIDA*$C26/K26) -> 0 | P26: =IF(OR($D26="No",L26=0,FALSE()),0,R_CORRIDA*$C26/L26) -> 0 | Q26: =IF(OR($D26="No",M26=0,FALSE()),0,R_CORRIDA*$C26/M26) -> 0 | R26: =IF(OR($D26="No",N26=0,FALSE()),0,R_CORRIDA*$C26/N26) -> 0 | S26: =IF(OR($D26="No",K26=0),99,MAX(0,IF(AND($E26="Sí",$F26>=2),99*K26,$H26*UMBRAL-($I26-K26)-$C26*COUNTIF($K26:$N26,">0")))/K26) -> 99 | T26: =IF(OR($D26="No",L26=0),99,MAX(0,IF(AND($E26="Sí",$F26>=2),($F26-1)*$G26*MIN_TURNO*UMBRAL-($I26-$J26-L26)-$C26*(COUNTIF($K26:$N26,">0")-1),$H26*UMBRAL-($I26-L26)-$C26*COUNTIF($K26:$N26,">0")))/L26) -> 99 | U26: =IF(OR($D26="No",M26=0),99,MAX(0,IF(AND($E26="Sí",$F26>=2),($F26-1)*$G26*MIN_TURNO*UMBRAL-($I26-$J26-M26)-$C26*(COUNTIF($K26:$N26,">0")-1),$H26*UMBRAL-($I26-M26)-$C26*COUNTIF($K26:$N26,">0")))/M26) -> 99 | V26: =IF(OR($D26="No",N26=0),99,MAX(0,IF(AND($E26="Sí",$F26>=2),($F26-1)*$G26*MIN_TURNO*UMBRAL-($I26-$J26-N26)-$C26*(COUNTIF($K26:$N26,">0")-1),$H26*UMBRAL-($I26-N26)-$C26*COUNTIF($K26:$N26,">0")))/N26) -> 99 | W26: =IF(OR($D26="No",K26=0,AND($E26="Sí",$F26>=2)),0,1/$H$35)+IF(OR($D26="No",L26=0),0,1/$H$36)+IF(OR($D26="No",M26=0),0,1/$H$37)+IF(OR($D26="No",N26=0),0,1/$H$38) -> 0 | X26: =W26*C26 -> 0 | Y26: =IF(H26=0,0,IF(AND(E26="Sí",F26>=2),MAX(J26/(G26*MIN_TURNO),(I26-J26+X26)/((F26-1)*G26*MIN_TURNO)),(I26+X26)/H26)) -> 0.36084502 | Z26: =IF(Y26<=UMBRAL,"OK","Pasa el umbral") -> OK
A27: 24 | B27: =Carga!B57 -> Control de calidad — Ensayo de pérdidas | C27: 0 | D27: No | E27: No | F27: =Carga!R57 -> 1 | G27: =Carga!S57 -> 1 | H27: =F27*G27*MIN_TURNO -> 450 | I27: =Carga!Q57 -> 216.50701 | J27: =Carga!K57*Carga!G57/60 -> 96.217917 | K27: =Carga!K57*Carga!G57/60 -> 96.217917 | L27: =Carga!L57*Carga!H57/60 -> 22.309375 | M27: =Carga!M57*Carga!I57/60 -> 92.444936 | N27: =Carga!N57*Carga!J57/60 -> 5.5347842 | O27: =IF(OR($D27="No",K27=0,AND($E27="Sí",$F27>=2)),0,R_CORRIDA*$C27/K27) -> 0 | P27: =IF(OR($D27="No",L27=0,FALSE()),0,R_CORRIDA*$C27/L27) -> 0 | Q27: =IF(OR($D27="No",M27=0,FALSE()),0,R_CORRIDA*$C27/M27) -> 0 | R27: =IF(OR($D27="No",N27=0,FALSE()),0,R_CORRIDA*$C27/N27) -> 0 | S27: =IF(OR($D27="No",K27=0),99,MAX(0,IF(AND($E27="Sí",$F27>=2),99*K27,$H27*UMBRAL-($I27-K27)-$C27*COUNTIF($K27:$N27,">0")))/K27) -> 99 | T27: =IF(OR($D27="No",L27=0),99,MAX(0,IF(AND($E27="Sí",$F27>=2),($F27-1)*$G27*MIN_TURNO*UMBRAL-($I27-$J27-L27)-$C27*(COUNTIF($K27:$N27,">0")-1),$H27*UMBRAL-($I27-L27)-$C27*COUNTIF($K27:$N27,">0")))/L27) -> 99 | U27: =IF(OR($D27="No",M27=0),99,MAX(0,IF(AND($E27="Sí",$F27>=2),($F27-1)*$G27*MIN_TURNO*UMBRAL-($I27-$J27-M27)-$C27*(COUNTIF($K27:$N27,">0")-1),$H27*UMBRAL-($I27-M27)-$C27*COUNTIF($K27:$N27,">0")))/M27) -> 99 | V27: =IF(OR($D27="No",N27=0),99,MAX(0,IF(AND($E27="Sí",$F27>=2),($F27-1)*$G27*MIN_TURNO*UMBRAL-($I27-$J27-N27)-$C27*(COUNTIF($K27:$N27,">0")-1),$H27*UMBRAL-($I27-N27)-$C27*COUNTIF($K27:$N27,">0")))/N27) -> 99 | W27: =IF(OR($D27="No",K27=0,AND($E27="Sí",$F27>=2)),0,1/$H$35)+IF(OR($D27="No",L27=0),0,1/$H$36)+IF(OR($D27="No",M27=0),0,1/$H$37)+IF(OR($D27="No",N27=0),0,1/$H$38) -> 0 | X27: =W27*C27 -> 0 | Y27: =IF(H27=0,0,IF(AND(E27="Sí",F27>=2),MAX(J27/(G27*MIN_TURNO),(I27-J27+X27)/((F27-1)*G27*MIN_TURNO)),(I27+X27)/H27)) -> 0.4811267 | Z27: =IF(Y27<=UMBRAL,"OK","Pasa el umbral") -> OK
A28: 25 | B28: =Carga!B58 -> Etiquetado | C28: 0 | D28: No | E28: No | F28: =Carga!R58 -> 1 | G28: =Carga!S58 -> 1 | H28: =F28*G28*MIN_TURNO -> 450 | I28: =Carga!Q58 -> 324.76052 | J28: =Carga!K58*Carga!G58/60 -> 144.32688 | K28: =Carga!K58*Carga!G58/60 -> 144.32688 | L28: =Carga!L58*Carga!H58/60 -> 33.464063 | M28: =Carga!M58*Carga!I58/60 -> 138.6674 | N28: =Carga!N58*Carga!J58/60 -> 8.3021764 | O28: =IF(OR($D28="No",K28=0,AND($E28="Sí",$F28>=2)),0,R_CORRIDA*$C28/K28) -> 0 | P28: =IF(OR($D28="No",L28=0,FALSE()),0,R_CORRIDA*$C28/L28) -> 0 | Q28: =IF(OR($D28="No",M28=0,FALSE()),0,R_CORRIDA*$C28/M28) -> 0 | R28: =IF(OR($D28="No",N28=0,FALSE()),0,R_CORRIDA*$C28/N28) -> 0 | S28: =IF(OR($D28="No",K28=0),99,MAX(0,IF(AND($E28="Sí",$F28>=2),99*K28,$H28*UMBRAL-($I28-K28)-$C28*COUNTIF($K28:$N28,">0")))/K28) -> 99 | T28: =IF(OR($D28="No",L28=0),99,MAX(0,IF(AND($E28="Sí",$F28>=2),($F28-1)*$G28*MIN_TURNO*UMBRAL-($I28-$J28-L28)-$C28*(COUNTIF($K28:$N28,">0")-1),$H28*UMBRAL-($I28-L28)-$C28*COUNTIF($K28:$N28,">0")))/L28) -> 99 | U28: =IF(OR($D28="No",M28=0),99,MAX(0,IF(AND($E28="Sí",$F28>=2),($F28-1)*$G28*MIN_TURNO*UMBRAL-($I28-$J28-M28)-$C28*(COUNTIF($K28:$N28,">0")-1),$H28*UMBRAL-($I28-M28)-$C28*COUNTIF($K28:$N28,">0")))/M28) -> 99 | V28: =IF(OR($D28="No",N28=0),99,MAX(0,IF(AND($E28="Sí",$F28>=2),($F28-1)*$G28*MIN_TURNO*UMBRAL-($I28-$J28-N28)-$C28*(COUNTIF($K28:$N28,">0")-1),$H28*UMBRAL-($I28-N28)-$C28*COUNTIF($K28:$N28,">0")))/N28) -> 99 | W28: =IF(OR($D28="No",K28=0,AND($E28="Sí",$F28>=2)),0,1/$H$35)+IF(OR($D28="No",L28=0),0,1/$H$36)+IF(OR($D28="No",M28=0),0,1/$H$37)+IF(OR($D28="No",N28=0),0,1/$H$38) -> 0 | X28: =W28*C28 -> 0 | Y28: =IF(H28=0,0,IF(AND(E28="Sí",F28>=2),MAX(J28/(G28*MIN_TURNO),(I28-J28+X28)/((F28-1)*G28*MIN_TURNO)),(I28+X28)/H28)) -> 0.72169004 | Z28: =IF(Y28<=UMBRAL,"OK","Pasa el umbral") -> OK
A29: 26 | B29: =Carga!B59 -> Embalaje y paletizado | C29: 5 | D29: Sí | E29: Sí | F29: =Carga!R59 -> 2 | G29: =Carga!S59 -> 2 | H29: =F29*G29*MIN_TURNO -> 1800 | I29: =Carga!Q59 -> 960.06115 | J29: =Carga!K59*Carga!G59/60 -> 683.84466 | K29: =Carga!K59*Carga!G59/60 -> 683.84466 | L29: =Carga!L59*Carga!H59/60 -> 47.676392 | M29: =Carga!M59*Carga!I59/60 -> 215.50272 | N29: =Carga!N59*Carga!J59/60 -> 13.037382 | O29: =IF(OR($D29="No",K29=0,AND($E29="Sí",$F29>=2)),0,R_CORRIDA*$C29/K29) -> 0 | P29: =IF(OR($D29="No",L29=0,FALSE()),0,R_CORRIDA*$C29/L29) -> 0.31462112 | Q29: =IF(OR($D29="No",M29=0,FALSE()),0,R_CORRIDA*$C29/M29) -> 0.069604689 | R29: =IF(OR($D29="No",N29=0,FALSE()),0,R_CORRIDA*$C29/N29) -> 1.1505377 | S29: =IF(OR($D29="No",K29=0),99,MAX(0,IF(AND($E29="Sí",$F29>=2),99*K29,$H29*UMBRAL-($I29-K29)-$C29*COUNTIF($K29:$N29,">0")))/K29) -> 99 | T29: =IF(OR($D29="No",L29=0),99,MAX(0,IF(AND($E29="Sí",$F29>=2),($F29-1)*$G29*MIN_TURNO*UMBRAL-($I29-$J29-L29)-$C29*(COUNTIF($K29:$N29,">0")-1),$H29*UMBRAL-($I29-L29)-$C29*COUNTIF($K29:$N29,">0")))/L29) -> 11.88135 | U29: =IF(OR($D29="No",M29=0),99,MAX(0,IF(AND($E29="Sí",$F29>=2),($F29-1)*$G29*MIN_TURNO*UMBRAL-($I29-$J29-M29)-$C29*(COUNTIF($K29:$N29,">0")-1),$H29*UMBRAL-($I29-M29)-$C29*COUNTIF($K29:$N29,">0")))/M29) -> 3.4073176 | V29: =IF(OR($D29="No",N29=0),99,MAX(0,IF(AND($E29="Sí",$F29>=2),($F29-1)*$G29*MIN_TURNO*UMBRAL-($I29-$J29-N29)-$C29*(COUNTIF($K29:$N29,">0")-1),$H29*UMBRAL-($I29-N29)-$C29*COUNTIF($K29:$N29,">0")))/N29) -> 40.791999 | W29: =IF(OR($D29="No",K29=0,AND($E29="Sí",$F29>=2)),0,1/$H$35)+IF(OR($D29="No",L29=0),0,1/$H$36)+IF(OR($D29="No",M29=0),0,1/$H$37)+IF(OR($D29="No",N29=0),0,1/$H$38) -> 2.5 | X29: =W29*C29 -> 12.5 | Y29: =IF(H29=0,0,IF(AND(E29="Sí",F29>=2),MAX(J29/(G29*MIN_TURNO),(I29-J29+X29)/((F29-1)*G29*MIN_TURNO)),(I29+X29)/H29)) -> 0.7598274 | Z29: =IF(Y29<=UMBRAL,"OK","Pasa el umbral") -> OK | AA29: Dos puestos: uno embala solo el 1 kg (armadora regulada para su caja).
B30: Total | W30: =SUM(W8:W29) -> 33.9375 | X30: =SUM(X8:X29) -> 424.0625
A31: Frec. mín. = 3 × cambio ÷ corrida diaria del modelo en el puesto. Frec. máx. = cuántos días del modelo entran juntos en un día del puesto (90 % de la capacidad menos la carga de los otros modelos y sus cambios).
A33: 2) CADA CUÁNTOS DÍAS PASA CADA MODELO POR TODA LA OLA
B34: Modelo | C34: Recipientes por día | D34: Frec. mínima por corrida (días) | E34: Frec. máxima por capacidad del día (días) | F34: Frec. calculada (días) | G34: Frec. elegida (vacío = calculada) | H34: Frec. final (días) | I34: Fase en el marcapasos (día) | J34: Lote de la ola (recipientes) | K34: Cambios por día en el marcapasos | L34: Lectura
B35: 1 kg | C35: =Carga!F14 -> 911.79288 | D35: =MAX(O8:O29) -> 0.23689591 | E35: =MIN(S8:S29) -> 1.2850631 | F35: =MIN(MIN(K_MAX,BASE*2^MAX(0,ROUNDUP(LOG(MAX(1,(D35)/BASE),2)-0.000001,0))),MIN(K_MAX,BASE*2^MAX(0,ROUNDDOWN(LOG(MAX(BASE,E35)/BASE,2)+0.000001,0)))) -> 1 | H35: =IF(G35="",F35,G35) -> 1 | I35: 0 | J35: =C35*H35 -> 911.79288 | K35: =IF(OR(K16=0,AND(E16="Sí",F16>=2)),0,1/H35) -> 1 | L35: =IF(H35<=BASE,"Todos los días","Cada "&H35&" días: lote de "&FIXED(J35,0)&" recipientes")&IF(D35>E35+0.001," · la corrida mínima pediría "&FIXED(D35,1)&" días, pero la capacidad del día lo limita a "&FIXED(E35,1),"") -> Todos los días
B36: 2,5 kg | C36: =Carga!F15 -> 63.568523 | D36: =MAX(P8:P29) -> 3.3979081 | E36: =MIN(T8:T29) -> 1.6082862 | F36: =MIN(MIN(K_MAX,BASE*2^MAX(0,ROUNDUP(LOG(MAX(1,(D36)/BASE),2)-0.000001,0))),MIN(K_MAX,BASE*2^MAX(0,ROUNDDOWN(LOG(MAX(BASE,E36)/BASE,2)+0.000001,0)))) -> 1 | H36: =IF(G36="",F36,G36) -> 1 | I36: 1 | J36: =C36*H36 -> 63.568523 | K36: =IF(OR(K16=0,FALSE()),0,1/H36) -> 1 | L36: =IF(H36<=BASE,"Todos los días","Cada "&H36&" días: lote de "&FIXED(J36,0)&" recipientes")&IF(D36>E36+0.001," · la corrida mínima pediría "&FIXED(D36,1)&" días, pero la capacidad del día lo limita a "&FIXED(E36,1),"") -> Todos los días · la corrida mínima pediría 3.4 días, pero la capacidad del día lo limita a 1.6
B37: 5 kg | C37: =Carga!F16 -> 287.33696 | D37: =MAX(Q8:Q29) -> 0.75173064 | E37: =MIN(U8:U29) -> 1.1345732 | F37: =MIN(MIN(K_MAX,BASE*2^MAX(0,ROUNDUP(LOG(MAX(1,(D37)/BASE),2)-0.000001,0))),MIN(K_MAX,BASE*2^MAX(0,ROUNDDOWN(LOG(MAX(BASE,E37)/BASE,2)+0.000001,0)))) -> 1 | H37: =IF(G37="",F37,G37) -> 1 | I37: 0 | J37: =C37*H37 -> 287.33696 | K37: =IF(OR(K16=0,FALSE()),0,1/H37) -> 1 | L37: =IF(H37<=BASE,"Todos los días","Cada "&H37&" días: lote de "&FIXED(J37,0)&" recipientes")&IF(D37>E37+0.001," · la corrida mínima pediría "&FIXED(D37,1)&" días, pero la capacidad del día lo limita a "&FIXED(E37,1),"") -> Todos los días
B38: 10 kg | C38: =Carga!F17 -> 17.383176 | D38: =MAX(R8:R29) -> 12.425807 | E38: =MIN(V8:V29) -> 3.2244415 | F38: =MIN(MIN(K_MAX,BASE*2^MAX(0,ROUNDUP(LOG(MAX(1,(D38)/BASE),2)-0.000001,0))),MIN(K_MAX,BASE*2^MAX(0,ROUNDDOWN(LOG(MAX(BASE,E38)/BASE,2)+0.000001,0)))) -> 2 | H38: =IF(G38="",F38,G38) -> 2 | I38: 3 | J38: =C38*H38 -> 34.766353 | K38: =IF(OR(K16=0,FALSE()),0,1/H38) -> 0.5 | L38: =IF(H38<=BASE,"Todos los días","Cada "&H38&" días: lote de "&FIXED(J38,0)&" recipientes")&IF(D38>E38+0.001," · la corrida mínima pediría "&FIXED(D38,1)&" días, pero la capacidad del día lo limita a "&FIXED(E38,1),"") -> Cada 2 días: lote de 35 recipientes · la corrida mínima pediría 12.4 días, pero la capacidad del día lo limita a 3.2
A40: 3) CALENDARIO DE 20 DÍAS HÁBILES: formatos de cada día y carga del puesto
B41: Puesto | C41: 1 | D41: 2 | E41: 3 | F41: 4 | G41: 5 | H41: 6 | I41: 7 | J41: 8 | K41: 9 | L41: 10 | M41: 11 | N41: 12 | O41: 13 | P41: 14 | Q41: 15 | R41: 16 | S41: 17 | T41: 18 | U41: 19 | V41: 20
B42: Guillotina 1 — formatos | C42: =IF(AND(Lotes!$E$8>0,MOD(C$41-1-Lotes!$V$8,Lotes!$O$8)=0),"1 ","")&IF(AND(Lotes!$E$9>0,MOD(C$41-1-Lotes!$V$9,Lotes!$O$9)=0),"2,5 ","")&IF(AND(Lotes!$E$10>0,MOD(C$41-1-Lotes!$V$10,Lotes!$O$10)=0),"5 ","")&IF(AND(Lotes!$E$11>0,MOD(C$41-1-Lotes!$V$11,Lotes!$O$11)=0),"10 ","")&IF(AND(Lotes!$E$12>0,MOD(C$41-1-Lotes!$V$12,Lotes!$O$12)=0),"C25 ","")&IF(AND(Lotes!$E$13>0,MOD(C$41-1-Lotes!$V$13,Lotes!$O$13)=0),"C50 ","")&IF(AND(Lotes!$E$14>0,MOD(C$41-1-Lotes!$V$14,Lotes!$O$14)=0),"CM ","") -> 1 2,5 5 | D42: =IF(AND(Lotes!$E$8>0,MOD(D$41-1-Lotes!$V$8,Lotes!$O$8)=0),"1 ","")&IF(AND(Lotes!$E$9>0,MOD(D$41-1-Lotes!$V$9,Lotes!$O$9)=0),"2,5 ","")&IF(AND(Lotes!$E$10>0,MOD(D$41-1-Lotes!$V$10,Lotes!$O$10)=0),"5 ","")&IF(AND(Lotes!$E$11>0,MOD(D$41-1-Lotes!$V$11,Lotes!$O$11)=0),"10 ","")&IF(AND(Lotes!$E$12>0,MOD(D$41-1-Lotes!$V$12,Lotes!$O$12)=0),"C25 ","")&IF(AND(Lotes!$E$13>0,MOD(D$41-1-Lotes!$V$13,Lotes!$O$13)=0),"C50 ","")&IF(AND(Lotes!$E$14>0,MOD(D$41-1-Lotes!$V$14,Lotes!$O$14)=0),"CM ","") -> 1 5 C25 | E42: =IF(AND(Lotes!$E$8>0,MOD(E$41-1-Lotes!$V$8,Lotes!$O$8)=0),"1 ","")&IF(AND(Lotes!$E$9>0,MOD(E$41-1-Lotes!$V$9,Lotes!$O$9)=0),"2,5 ","")&IF(AND(Lotes!$E$10>0,MOD(E$41-1-Lotes!$V$10,Lotes!$O$10)=0),"5 ","")&IF(AND(Lotes!$E$11>0,MOD(E$41-1-Lotes!$V$11,Lotes!$O$11)=0),"10 ","")&IF(AND(Lotes!$E$12>0,MOD(E$41-1-Lotes!$V$12,Lotes!$O$12)=0),"C25 ","")&IF(AND(Lotes!$E$13>0,MOD(E$41-1-Lotes!$V$13,Lotes!$O$13)=0),"C50 ","")&IF(AND(Lotes!$E$14>0,MOD(E$41-1-Lotes!$V$14,Lotes!$O$14)=0),"CM ","") -> 1 5 10 C50 | F42: =IF(AND(Lotes!$E$8>0,MOD(F$41-1-Lotes!$V$8,Lotes!$O$8)=0),"1 ","")&IF(AND(Lotes!$E$9>0,MOD(F$41-1-Lotes!$V$9,Lotes!$O$9)=0),"2,5 ","")&IF(AND(Lotes!$E$10>0,MOD(F$41-1-Lotes!$V$10,Lotes!$O$10)=0),"5 ","")&IF(AND(Lotes!$E$11>0,MOD(F$41-1-Lotes!$V$11,Lotes!$O$11)=0),"10 ","")&IF(AND(Lotes!$E$12>0,MOD(F$41-1-Lotes!$V$12,Lotes!$O$12)=0),"C25 ","")&IF(AND(Lotes!$E$13>0,MOD(F$41-1-Lotes!$V$13,Lotes!$O$13)=0),"C50 ","")&IF(AND(Lotes!$E$14>0,MOD(F$41-1-Lotes!$V$14,Lotes!$O$14)=0),"CM ","") -> 1 5 CM | G42: =IF(AND(Lotes!$E$8>0,MOD(G$41-1-Lotes!$V$8,Lotes!$O$8)=0),"1 ","")&IF(AND(Lotes!$E$9>0,MOD(G$41-1-Lotes!$V$9,Lotes!$O$9)=0),"2,5 ","")&IF(AND(Lotes!$E$10>0,MOD(G$41-1-Lotes!$V$10,Lotes!$O$10)=0),"5 ","")&IF(AND(Lotes!$E$11>0,MOD(G$41-1-Lotes!$V$11,Lotes!$O$11)=0),"10 ","")&IF(AND(Lotes!$E$12>0,MOD(G$41-1-Lotes!$V$12,Lotes!$O$12)=0),"C25 ","")&IF(AND(Lotes!$E$13>0,MOD(G$41-1-Lotes!$V$13,Lotes!$O$13)=0),"C50 ","")&IF(AND(Lotes!$E$14>0,MOD(G$41-1-Lotes!$V$14,Lotes!$O$14)=0),"CM ","") -> 1 5 | H42: =IF(AND(Lotes!$E$8>0,MOD(H$41-1-Lotes!$V$8,Lotes!$O$8)=0),"1 ","")&IF(AND(Lotes!$E$9>0,MOD(H$41-1-Lotes!$V$9,Lotes!$O$9)=0),"2,5 ","")&IF(AND(Lotes!$E$10>0,MOD(H$41-1-Lotes!$V$10,Lotes!$O$10)=0),"5 ","")&IF(AND(Lotes!$E$11>0,MOD(H$41-1-Lotes!$V$11,Lotes!$O$11)=0),"10 ","")&IF(AND(Lotes!$E$12>0,MOD(H$41-1-Lotes!$V$12,Lotes!$O$12)=0),"C25 ","")&IF(AND(Lotes!$E$13>0,MOD(H$41-1-Lotes!$V$13,Lotes!$O$13)=0),"C50 ","")&IF(AND(Lotes!$E$14>0,MOD(H$41-1-Lotes!$V$14,Lotes!$O$14)=0),"CM ","") -> 1 5 C25 | I42: =IF(AND(Lotes!$E$8>0,MOD(I$41-1-Lotes!$V$8,Lotes!$O$8)=0),"1 ","")&IF(AND(Lotes!$E$9>0,MOD(I$41-1-Lotes!$V$9,Lotes!$O$9)=0),"2,5 ","")&IF(AND(Lotes!$E$10>0,MOD(I$41-1-Lotes!$V$10,Lotes!$O$10)=0),"5 ","")&IF(AND(Lotes!$E$11>0,MOD(I$41-1-Lotes!$V$11,Lotes!$O$11)=0),"10 ","")&IF(AND(Lotes!$E$12>0,MOD(I$41-1-Lotes!$V$12,Lotes!$O$12)=0),"C25 ","")&IF(AND(Lotes!$E$13>0,MOD(I$41-1-Lotes!$V$13,Lotes!$O$13)=0),"C50 ","")&IF(AND(Lotes!$E$14>0,MOD(I$41-1-Lotes!$V$14,Lotes!$O$14)=0),"CM ","") -> 1 5 C50 | J42: =IF(AND(Lotes!$E$8>0,MOD(J$41-1-Lotes!$V$8,Lotes!$O$8)=0),"1 ","")&IF(AND(Lotes!$E$9>0,MOD(J$41-1-Lotes!$V$9,Lotes!$O$9)=0),"2,5 ","")&IF(AND(Lotes!$E$10>0,MOD(J$41-1-Lotes!$V$10,Lotes!$O$10)=0),"5 ","")&IF(AND(Lotes!$E$11>0,MOD(J$41-1-Lotes!$V$11,Lotes!$O$11)=0),"10 ","")&IF(AND(Lotes!$E$12>0,MOD(J$41-1-Lotes!$V$12,Lotes!$O$12)=0),"C25 ","")&IF(AND(Lotes!$E$13>0,MOD(J$41-1-Lotes!$V$13,Lotes!$O$13)=0),"C50 ","")&IF(AND(Lotes!$E$14>0,MOD(J$41-1-Lotes!$V$14,Lotes!$O$14)=0),"CM ","") -> 1 5 CM | ... V42: =IF(AND(Lotes!$E$8>0,MOD(V$41-1-Lotes!$V$8,Lotes!$O$8)=0),"1 ","")&IF(AND(Lotes!$E$9>0,MOD(V$41-1-Lotes!$V$9,Lotes!$O$9)=0),"2,5 ","")&IF(AND(Lotes!$E$10>0,MOD(V$41-1-Lotes!$V$10,Lotes!$O$10)=0),"5 ","")&IF(AND(Lotes!$E$11>0,MOD(V$41-1-Lotes!$V$11,Lotes!$O$11)=0),"10 ","")&IF(AND(Lotes!$E$12>0,MOD(V$41-1-Lotes!$V$12,Lotes!$O$12)=0),"C25 ","")&IF(AND(Lotes!$E$13>0,MOD(V$41-1-Lotes!$V$13,Lotes!$O$13)=0),"C50 ","")&IF(AND(Lotes!$E$14>0,MOD(V$41-1-Lotes!$V$14,Lotes!$O$14)=0),"CM ","") -> 1 5 CM
B43: carga | C43: =(IF(AND(Lotes!$E$8>0,MOD(C$41-1-Lotes!$V$8,Lotes!$O$8)=0),Lotes!$S$8/REND_CORTE+S_G1,0)+IF(AND(Lotes!$E$9>0,MOD(C$41-1-Lotes!$V$9,Lotes!$O$9)=0),Lotes!$S$9/REND_CORTE+S_G1,0)+IF(AND(Lotes!$E$10>0,MOD(C$41-1-Lotes!$V$10,Lotes!$O$10)=0),Lotes!$S$10/REND_CORTE+S_G1,0)+IF(AND(Lotes!$E$11>0,MOD(C$41-1-Lotes!$V$11,Lotes!$O$11)=0),Lotes!$S$11/REND_CORTE+S_G1,0)+IF(AND(Lotes!$E$12>0,MOD(C$41-1-Lotes!$V$12,Lotes!$O$12)=0),Lotes!$S$12/REND_CORTE+S_G1,0)+IF(AND(Lotes!$E$13>0,MOD(C$41-1-Lotes!$V$13,Lotes!$O$13)=0),Lotes!$S$13/REND_CORTE+S_G1,0)+IF(AND(Lotes!$E$14>0,MOD(C$41-1-Lotes!$V$14,Lotes!$O$14)=0),Lotes!$S$14/REND_CORTE+S_G1,0)+(TIRAS_CARROS+TIRAS_EXTRA)/REND_CORTE+(ALIST_G+DESALIST_G)*Lotes!$C$22)/Lotes!$D$22 -> 0.78653595 | D43: =(IF(AND(Lotes!$E$8>0,MOD(D$41-1-Lotes!$V$8,Lotes!$O$8)=0),Lotes!$S$8/REND_CORTE+S_G1,0)+IF(AND(Lotes!$E$9>0,MOD(D$41-1-Lotes!$V$9,Lotes!$O$9)=0),Lotes!$S$9/REND_CORTE+S_G1,0)+IF(AND(Lotes!$E$10>0,MOD(D$41-1-Lotes!$V$10,Lotes!$O$10)=0),Lotes!$S$10/REND_CORTE+S_G1,0)+IF(AND(Lotes!$E$11>0,MOD(D$41-1-Lotes!$V$11,Lotes!$O$11)=0),Lotes!$S$11/REND_CORTE+S_G1,0)+IF(AND(Lotes!$E$12>0,MOD(D$41-1-Lotes!$V$12,Lotes!$O$12)=0),Lotes!$S$12/REND_CORTE+S_G1,0)+IF(AND(Lotes!$E$13>0,MOD(D$41-1-Lotes!$V$13,Lotes!$O$13)=0),Lotes!$S$13/REND_CORTE+S_G1,0)+IF(AND(Lotes!$E$14>0,MOD(D$41-1-Lotes!$V$14,Lotes!$O$14)=0),Lotes!$S$14/REND_CORTE+S_G1,0)+(TIRAS_CARROS+TIRAS_EXTRA)/REND_CORTE+(ALIST_G+DESALIST_G)*Lotes!$C$22)/Lotes!$D$22 -> 0.62987412 | E43: =(IF(AND(Lotes!$E$8>0,MOD(E$41-1-Lotes!$V$8,Lotes!$O$8)=0),Lotes!$S$8/REND_CORTE+S_G1,0)+IF(AND(Lotes!$E$9>0,MOD(E$41-1-Lotes!$V$9,Lotes!$O$9)=0),Lotes!$S$9/REND_CORTE+S_G1,0)+IF(AND(Lotes!$E$10>0,MOD(E$41-1-Lotes!$V$10,Lotes!$O$10)=0),Lotes!$S$10/REND_CORTE+S_G1,0)+IF(AND(Lotes!$E$11>0,MOD(E$41-1-Lotes!$V$11,Lotes!$O$11)=0),Lotes!$S$11/REND_CORTE+S_G1,0)+IF(AND(Lotes!$E$12>0,MOD(E$41-1-Lotes!$V$12,Lotes!$O$12)=0),Lotes!$S$12/REND_CORTE+S_G1,0)+IF(AND(Lotes!$E$13>0,MOD(E$41-1-Lotes!$V$13,Lotes!$O$13)=0),Lotes!$S$13/REND_CORTE+S_G1,0)+IF(AND(Lotes!$E$14>0,MOD(E$41-1-Lotes!$V$14,Lotes!$O$14)=0),Lotes!$S$14/REND_CORTE+S_G1,0)+(TIRAS_CARROS+TIRAS_EXTRA)/REND_CORTE+(ALIST_G+DESALIST_G)*Lotes!$C$22)/Lotes!$D$22 -> 0.85184126 | F43: =(IF(AND(Lotes!$E$8>0,MOD(F$41-1-Lotes!$V$8,Lotes!$O$8)=0),Lotes!$S$8/REND_CORTE+S_G1,0)+IF(AND(Lotes!$E$9>0,MOD(F$41-1-Lotes!$V$9,Lotes!$O$9)=0),Lotes!$S$9/REND_CORTE+S_G1,0)+IF(AND(Lotes!$E$10>0,MOD(F$41-1-Lotes!$V$10,Lotes!$O$10)=0),Lotes!$S$10/REND_CORTE+S_G1,0)+IF(AND(Lotes!$E$11>0,MOD(F$41-1-Lotes!$V$11,Lotes!$O$11)=0),Lotes!$S$11/REND_CORTE+S_G1,0)+IF(AND(Lotes!$E$12>0,MOD(F$41-1-Lotes!$V$12,Lotes!$O$12)=0),Lotes!$S$12/REND_CORTE+S_G1,0)+IF(AND(Lotes!$E$13>0,MOD(F$41-1-Lotes!$V$13,Lotes!$O$13)=0),Lotes!$S$13/REND_CORTE+S_G1,0)+IF(AND(Lotes!$E$14>0,MOD(F$41-1-Lotes!$V$14,Lotes!$O$14)=0),Lotes!$S$14/REND_CORTE+S_G1,0)+(TIRAS_CARROS+TIRAS_EXTRA)/REND_CORTE+(ALIST_G+DESALIST_G)*Lotes!$C$22)/Lotes!$D$22 -> 0.65960784 | G43: =(IF(AND(Lotes!$E$8>0,MOD(G$41-1-Lotes!$V$8,Lotes!$O$8)=0),Lotes!$S$8/REND_CORTE+S_G1,0)+IF(AND(Lotes!$E$9>0,MOD(G$41-1-Lotes!$V$9,Lotes!$O$9)=0),Lotes!$S$9/REND_CORTE+S_G1,0)+IF(AND(Lotes!$E$10>0,MOD(G$41-1-Lotes!$V$10,Lotes!$O$10)=0),Lotes!$S$10/REND_CORTE+S_G1,0)+IF(AND(Lotes!$E$11>0,MOD(G$41-1-Lotes!$V$11,Lotes!$O$11)=0),Lotes!$S$11/REND_CORTE+S_G1,0)+IF(AND(Lotes!$E$12>0,MOD(G$41-1-Lotes!$V$12,Lotes!$O$12)=0),Lotes!$S$12/REND_CORTE+S_G1,0)+IF(AND(Lotes!$E$13>0,MOD(G$41-1-Lotes!$V$13,Lotes!$O$13)=0),Lotes!$S$13/REND_CORTE+S_G1,0)+IF(AND(Lotes!$E$14>0,MOD(G$41-1-Lotes!$V$14,Lotes!$O$14)=0),Lotes!$S$14/REND_CORTE+S_G1,0)+(TIRAS_CARROS+TIRAS_EXTRA)/REND_CORTE+(ALIST_G+DESALIST_G)*Lotes!$C$22)/Lotes!$D$22 -> 0.56941176 | H43: =(IF(AND(Lotes!$E$8>0,MOD(H$41-1-Lotes!$V$8,Lotes!$O$8)=0),Lotes!$S$8/REND_CORTE+S_G1,0)+IF(AND(Lotes!$E$9>0,MOD(H$41-1-Lotes!$V$9,Lotes!$O$9)=0),Lotes!$S$9/REND_CORTE+S_G1,0)+IF(AND(Lotes!$E$10>0,MOD(H$41-1-Lotes!$V$10,Lotes!$O$10)=0),Lotes!$S$10/REND_CORTE+S_G1,0)+IF(AND(Lotes!$E$11>0,MOD(H$41-1-Lotes!$V$11,Lotes!$O$11)=0),Lotes!$S$11/REND_CORTE+S_G1,0)+IF(AND(Lotes!$E$12>0,MOD(H$41-1-Lotes!$V$12,Lotes!$O$12)=0),Lotes!$S$12/REND_CORTE+S_G1,0)+IF(AND(Lotes!$E$13>0,MOD(H$41-1-Lotes!$V$13,Lotes!$O$13)=0),Lotes!$S$13/REND_CORTE+S_G1,0)+IF(AND(Lotes!$E$14>0,MOD(H$41-1-Lotes!$V$14,Lotes!$O$14)=0),Lotes!$S$14/REND_CORTE+S_G1,0)+(TIRAS_CARROS+TIRAS_EXTRA)/REND_CORTE+(ALIST_G+DESALIST_G)*Lotes!$C$22)/Lotes!$D$22 -> 0.62987412 | I43: =(IF(AND(Lotes!$E$8>0,MOD(I$41-1-Lotes!$V$8,Lotes!$O$8)=0),Lotes!$S$8/REND_CORTE+S_G1,0)+IF(AND(Lotes!$E$9>0,MOD(I$41-1-Lotes!$V$9,Lotes!$O$9)=0),Lotes!$S$9/REND_CORTE+S_G1,0)+IF(AND(Lotes!$E$10>0,MOD(I$41-1-Lotes!$V$10,Lotes!$O$10)=0),Lotes!$S$10/REND_CORTE+S_G1,0)+IF(AND(Lotes!$E$11>0,MOD(I$41-1-Lotes!$V$11,Lotes!$O$11)=0),Lotes!$S$11/REND_CORTE+S_G1,0)+IF(AND(Lotes!$E$12>0,MOD(I$41-1-Lotes!$V$12,Lotes!$O$12)=0),Lotes!$S$12/REND_CORTE+S_G1,0)+IF(AND(Lotes!$E$13>0,MOD(I$41-1-Lotes!$V$13,Lotes!$O$13)=0),Lotes!$S$13/REND_CORTE+S_G1,0)+IF(AND(Lotes!$E$14>0,MOD(I$41-1-Lotes!$V$14,Lotes!$O$14)=0),Lotes!$S$14/REND_CORTE+S_G1,0)+(TIRAS_CARROS+TIRAS_EXTRA)/REND_CORTE+(ALIST_G+DESALIST_G)*Lotes!$C$22)/Lotes!$D$22 -> 0.64465172 | J43: =(IF(AND(Lotes!$E$8>0,MOD(J$41-1-Lotes!$V$8,Lotes!$O$8)=0),Lotes!$S$8/REND_CORTE+S_G1,0)+IF(AND(Lotes!$E$9>0,MOD(J$41-1-Lotes!$V$9,Lotes!$O$9)=0),Lotes!$S$9/REND_CORTE+S_G1,0)+IF(AND(Lotes!$E$10>0,MOD(J$41-1-Lotes!$V$10,Lotes!$O$10)=0),Lotes!$S$10/REND_CORTE+S_G1,0)+IF(AND(Lotes!$E$11>0,MOD(J$41-1-Lotes!$V$11,Lotes!$O$11)=0),Lotes!$S$11/REND_CORTE+S_G1,0)+IF(AND(Lotes!$E$12>0,MOD(J$41-1-Lotes!$V$12,Lotes!$O$12)=0),Lotes!$S$12/REND_CORTE+S_G1,0)+IF(AND(Lotes!$E$13>0,MOD(J$41-1-Lotes!$V$13,Lotes!$O$13)=0),Lotes!$S$13/REND_CORTE+S_G1,0)+IF(AND(Lotes!$E$14>0,MOD(J$41-1-Lotes!$V$14,Lotes!$O$14)=0),Lotes!$S$14/REND_CORTE+S_G1,0)+(TIRAS_CARROS+TIRAS_EXTRA)/REND_CORTE+(ALIST_G+DESALIST_G)*Lotes!$C$22)/Lotes!$D$22 -> 0.65960784 | ... V43: =(IF(AND(Lotes!$E$8>0,MOD(V$41-1-Lotes!$V$8,Lotes!$O$8)=0),Lotes!$S$8/REND_CORTE+S_G1,0)+IF(AND(Lotes!$E$9>0,MOD(V$41-1-Lotes!$V$9,Lotes!$O$9)=0),Lotes!$S$9/REND_CORTE+S_G1,0)+IF(AND(Lotes!$E$10>0,MOD(V$41-1-Lotes!$V$10,Lotes!$O$10)=0),Lotes!$S$10/REND_CORTE+S_G1,0)+IF(AND(Lotes!$E$11>0,MOD(V$41-1-Lotes!$V$11,Lotes!$O$11)=0),Lotes!$S$11/REND_CORTE+S_G1,0)+IF(AND(Lotes!$E$12>0,MOD(V$41-1-Lotes!$V$12,Lotes!$O$12)=0),Lotes!$S$12/REND_CORTE+S_G1,0)+IF(AND(Lotes!$E$13>0,MOD(V$41-1-Lotes!$V$13,Lotes!$O$13)=0),Lotes!$S$13/REND_CORTE+S_G1,0)+IF(AND(Lotes!$E$14>0,MOD(V$41-1-Lotes!$V$14,Lotes!$O$14)=0),Lotes!$S$14/REND_CORTE+S_G1,0)+(TIRAS_CARROS+TIRAS_EXTRA)/REND_CORTE+(ALIST_G+DESALIST_G)*Lotes!$C$22)/Lotes!$D$22 -> 0.65960784
B44: Embutidora — matrices | C44: =IF(AND(Lotes!$D$30>0,MOD(C$41-1-Lotes!$N$30,Lotes!$J$30)=0),Lotes!$A$30&" ","")&IF(AND(Lotes!$D$31>0,MOD(C$41-1-Lotes!$N$31,Lotes!$J$31)=0),Lotes!$A$31&" ","")&IF(AND(Lotes!$D$32>0,MOD(C$41-1-Lotes!$N$32,Lotes!$J$32)=0),Lotes!$A$32&" ","")&IF(AND(Lotes!$D$33>0,MOD(C$41-1-Lotes!$N$33,Lotes!$J$33)=0),Lotes!$A$33&" ","")&IF(AND(Lotes!$D$34>0,MOD(C$41-1-Lotes!$N$34,Lotes!$J$34)=0),Lotes!$A$34&" ","")&IF(AND(Lotes!$D$35>0,MOD(C$41-1-Lotes!$N$35,Lotes!$J$35)=0),Lotes!$A$35&" ","")&IF(AND(Lotes!$D$36>0,MOD(C$41-1-Lotes!$N$36,Lotes!$J$36)=0),Lotes!$A$36&" ","")&IF(AND(Lotes!$D$37>0,MOD(C$41-1-Lotes!$N$37,Lotes!$J$37)=0),Lotes!$A$37&" ","") -> C1 | D44: =IF(AND(Lotes!$D$30>0,MOD(D$41-1-Lotes!$N$30,Lotes!$J$30)=0),Lotes!$A$30&" ","")&IF(AND(Lotes!$D$31>0,MOD(D$41-1-Lotes!$N$31,Lotes!$J$31)=0),Lotes!$A$31&" ","")&IF(AND(Lotes!$D$32>0,MOD(D$41-1-Lotes!$N$32,Lotes!$J$32)=0),Lotes!$A$32&" ","")&IF(AND(Lotes!$D$33>0,MOD(D$41-1-Lotes!$N$33,Lotes!$J$33)=0),Lotes!$A$33&" ","")&IF(AND(Lotes!$D$34>0,MOD(D$41-1-Lotes!$N$34,Lotes!$J$34)=0),Lotes!$A$34&" ","")&IF(AND(Lotes!$D$35>0,MOD(D$41-1-Lotes!$N$35,Lotes!$J$35)=0),Lotes!$A$35&" ","")&IF(AND(Lotes!$D$36>0,MOD(D$41-1-Lotes!$N$36,Lotes!$J$36)=0),Lotes!$A$36&" ","")&IF(AND(Lotes!$D$37>0,MOD(D$41-1-Lotes!$N$37,Lotes!$J$37)=0),Lotes!$A$37&" ","") -> F1 | E44: =IF(AND(Lotes!$D$30>0,MOD(E$41-1-Lotes!$N$30,Lotes!$J$30)=0),Lotes!$A$30&" ","")&IF(AND(Lotes!$D$31>0,MOD(E$41-1-Lotes!$N$31,Lotes!$J$31)=0),Lotes!$A$31&" ","")&IF(AND(Lotes!$D$32>0,MOD(E$41-1-Lotes!$N$32,Lotes!$J$32)=0),Lotes!$A$32&" ","")&IF(AND(Lotes!$D$33>0,MOD(E$41-1-Lotes!$N$33,Lotes!$J$33)=0),Lotes!$A$33&" ","")&IF(AND(Lotes!$D$34>0,MOD(E$41-1-Lotes!$N$34,Lotes!$J$34)=0),Lotes!$A$34&" ","")&IF(AND(Lotes!$D$35>0,MOD(E$41-1-Lotes!$N$35,Lotes!$J$35)=0),Lotes!$A$35&" ","")&IF(AND(Lotes!$D$36>0,MOD(E$41-1-Lotes!$N$36,Lotes!$J$36)=0),Lotes!$A$36&" ","")&IF(AND(Lotes!$D$37>0,MOD(E$41-1-Lotes!$N$37,Lotes!$J$37)=0),Lotes!$A$37&" ","") -> C5 | F44: =IF(AND(Lotes!$D$30>0,MOD(F$41-1-Lotes!$N$30,Lotes!$J$30)=0),Lotes!$A$30&" ","")&IF(AND(Lotes!$D$31>0,MOD(F$41-1-Lotes!$N$31,Lotes!$J$31)=0),Lotes!$A$31&" ","")&IF(AND(Lotes!$D$32>0,MOD(F$41-1-Lotes!$N$32,Lotes!$J$32)=0),Lotes!$A$32&" ","")&IF(AND(Lotes!$D$33>0,MOD(F$41-1-Lotes!$N$33,Lotes!$J$33)=0),Lotes!$A$33&" ","")&IF(AND(Lotes!$D$34>0,MOD(F$41-1-Lotes!$N$34,Lotes!$J$34)=0),Lotes!$A$34&" ","")&IF(AND(Lotes!$D$35>0,MOD(F$41-1-Lotes!$N$35,Lotes!$J$35)=0),Lotes!$A$35&" ","")&IF(AND(Lotes!$D$36>0,MOD(F$41-1-Lotes!$N$36,Lotes!$J$36)=0),Lotes!$A$36&" ","")&IF(AND(Lotes!$D$37>0,MOD(F$41-1-Lotes!$N$37,Lotes!$J$37)=0),Lotes!$A$37&" ","") -> F5 | G44: =IF(AND(Lotes!$D$30>0,MOD(G$41-1-Lotes!$N$30,Lotes!$J$30)=0),Lotes!$A$30&" ","")&IF(AND(Lotes!$D$31>0,MOD(G$41-1-Lotes!$N$31,Lotes!$J$31)=0),Lotes!$A$31&" ","")&IF(AND(Lotes!$D$32>0,MOD(G$41-1-Lotes!$N$32,Lotes!$J$32)=0),Lotes!$A$32&" ","")&IF(AND(Lotes!$D$33>0,MOD(G$41-1-Lotes!$N$33,Lotes!$J$33)=0),Lotes!$A$33&" ","")&IF(AND(Lotes!$D$34>0,MOD(G$41-1-Lotes!$N$34,Lotes!$J$34)=0),Lotes!$A$34&" ","")&IF(AND(Lotes!$D$35>0,MOD(G$41-1-Lotes!$N$35,Lotes!$J$35)=0),Lotes!$A$35&" ","")&IF(AND(Lotes!$D$36>0,MOD(G$41-1-Lotes!$N$36,Lotes!$J$36)=0),Lotes!$A$36&" ","")&IF(AND(Lotes!$D$37>0,MOD(G$41-1-Lotes!$N$37,Lotes!$J$37)=0),Lotes!$A$37&" ","") -> C1 | H44: =IF(AND(Lotes!$D$30>0,MOD(H$41-1-Lotes!$N$30,Lotes!$J$30)=0),Lotes!$A$30&" ","")&IF(AND(Lotes!$D$31>0,MOD(H$41-1-Lotes!$N$31,Lotes!$J$31)=0),Lotes!$A$31&" ","")&IF(AND(Lotes!$D$32>0,MOD(H$41-1-Lotes!$N$32,Lotes!$J$32)=0),Lotes!$A$32&" ","")&IF(AND(Lotes!$D$33>0,MOD(H$41-1-Lotes!$N$33,Lotes!$J$33)=0),Lotes!$A$33&" ","")&IF(AND(Lotes!$D$34>0,MOD(H$41-1-Lotes!$N$34,Lotes!$J$34)=0),Lotes!$A$34&" ","")&IF(AND(Lotes!$D$35>0,MOD(H$41-1-Lotes!$N$35,Lotes!$J$35)=0),Lotes!$A$35&" ","")&IF(AND(Lotes!$D$36>0,MOD(H$41-1-Lotes!$N$36,Lotes!$J$36)=0),Lotes!$A$36&" ","")&IF(AND(Lotes!$D$37>0,MOD(H$41-1-Lotes!$N$37,Lotes!$J$37)=0),Lotes!$A$37&" ","") -> F1 | I44: =IF(AND(Lotes!$D$30>0,MOD(I$41-1-Lotes!$N$30,Lotes!$J$30)=0),Lotes!$A$30&" ","")&IF(AND(Lotes!$D$31>0,MOD(I$41-1-Lotes!$N$31,Lotes!$J$31)=0),Lotes!$A$31&" ","")&IF(AND(Lotes!$D$32>0,MOD(I$41-1-Lotes!$N$32,Lotes!$J$32)=0),Lotes!$A$32&" ","")&IF(AND(Lotes!$D$33>0,MOD(I$41-1-Lotes!$N$33,Lotes!$J$33)=0),Lotes!$A$33&" ","")&IF(AND(Lotes!$D$34>0,MOD(I$41-1-Lotes!$N$34,Lotes!$J$34)=0),Lotes!$A$34&" ","")&IF(AND(Lotes!$D$35>0,MOD(I$41-1-Lotes!$N$35,Lotes!$J$35)=0),Lotes!$A$35&" ","")&IF(AND(Lotes!$D$36>0,MOD(I$41-1-Lotes!$N$36,Lotes!$J$36)=0),Lotes!$A$36&" ","")&IF(AND(Lotes!$D$37>0,MOD(I$41-1-Lotes!$N$37,Lotes!$J$37)=0),Lotes!$A$37&" ","") -> C2,5 | J44: =IF(AND(Lotes!$D$30>0,MOD(J$41-1-Lotes!$N$30,Lotes!$J$30)=0),Lotes!$A$30&" ","")&IF(AND(Lotes!$D$31>0,MOD(J$41-1-Lotes!$N$31,Lotes!$J$31)=0),Lotes!$A$31&" ","")&IF(AND(Lotes!$D$32>0,MOD(J$41-1-Lotes!$N$32,Lotes!$J$32)=0),Lotes!$A$32&" ","")&IF(AND(Lotes!$D$33>0,MOD(J$41-1-Lotes!$N$33,Lotes!$J$33)=0),Lotes!$A$33&" ","")&IF(AND(Lotes!$D$34>0,MOD(J$41-1-Lotes!$N$34,Lotes!$J$34)=0),Lotes!$A$34&" ","")&IF(AND(Lotes!$D$35>0,MOD(J$41-1-Lotes!$N$35,Lotes!$J$35)=0),Lotes!$A$35&" ","")&IF(AND(Lotes!$D$36>0,MOD(J$41-1-Lotes!$N$36,Lotes!$J$36)=0),Lotes!$A$36&" ","")&IF(AND(Lotes!$D$37>0,MOD(J$41-1-Lotes!$N$37,Lotes!$J$37)=0),Lotes!$A$37&" ","") -> F2,5 | ... V44: =IF(AND(Lotes!$D$30>0,MOD(V$41-1-Lotes!$N$30,Lotes!$J$30)=0),Lotes!$A$30&" ","")&IF(AND(Lotes!$D$31>0,MOD(V$41-1-Lotes!$N$31,Lotes!$J$31)=0),Lotes!$A$31&" ","")&IF(AND(Lotes!$D$32>0,MOD(V$41-1-Lotes!$N$32,Lotes!$J$32)=0),Lotes!$A$32&" ","")&IF(AND(Lotes!$D$33>0,MOD(V$41-1-Lotes!$N$33,Lotes!$J$33)=0),Lotes!$A$33&" ","")&IF(AND(Lotes!$D$34>0,MOD(V$41-1-Lotes!$N$34,Lotes!$J$34)=0),Lotes!$A$34&" ","")&IF(AND(Lotes!$D$35>0,MOD(V$41-1-Lotes!$N$35,Lotes!$J$35)=0),Lotes!$A$35&" ","")&IF(AND(Lotes!$D$36>0,MOD(V$41-1-Lotes!$N$36,Lotes!$J$36)=0),Lotes!$A$36&" ","")&IF(AND(Lotes!$D$37>0,MOD(V$41-1-Lotes!$N$37,Lotes!$J$37)=0),Lotes!$A$37&" ","") -> F5
B45: carga | C45: =(IF(AND(Lotes!$D$30>0,MOD(C$41-1-Lotes!$N$30,Lotes!$J$30)=0),Lotes!$L$30+S_EMB,0)+IF(AND(Lotes!$D$31>0,MOD(C$41-1-Lotes!$N$31,Lotes!$J$31)=0),Lotes!$L$31+S_EMB,0)+IF(AND(Lotes!$D$32>0,MOD(C$41-1-Lotes!$N$32,Lotes!$J$32)=0),Lotes!$L$32+S_EMB,0)+IF(AND(Lotes!$D$33>0,MOD(C$41-1-Lotes!$N$33,Lotes!$J$33)=0),Lotes!$L$33+S_EMB,0)+IF(AND(Lotes!$D$34>0,MOD(C$41-1-Lotes!$N$34,Lotes!$J$34)=0),Lotes!$L$34+S_EMB,0)+IF(AND(Lotes!$D$35>0,MOD(C$41-1-Lotes!$N$35,Lotes!$J$35)=0),Lotes!$L$35+S_EMB,0)+IF(AND(Lotes!$D$36>0,MOD(C$41-1-Lotes!$N$36,Lotes!$J$36)=0),Lotes!$L$36+S_EMB,0)+IF(AND(Lotes!$D$37>0,MOD(C$41-1-Lotes!$N$37,Lotes!$J$37)=0),Lotes!$L$37+S_EMB,0))/Lotes!$D$42 -> 0.6403217 | D45: =(IF(AND(Lotes!$D$30>0,MOD(D$41-1-Lotes!$N$30,Lotes!$J$30)=0),Lotes!$L$30+S_EMB,0)+IF(AND(Lotes!$D$31>0,MOD(D$41-1-Lotes!$N$31,Lotes!$J$31)=0),Lotes!$L$31+S_EMB,0)+IF(AND(Lotes!$D$32>0,MOD(D$41-1-Lotes!$N$32,Lotes!$J$32)=0),Lotes!$L$32+S_EMB,0)+IF(AND(Lotes!$D$33>0,MOD(D$41-1-Lotes!$N$33,Lotes!$J$33)=0),Lotes!$L$33+S_EMB,0)+IF(AND(Lotes!$D$34>0,MOD(D$41-1-Lotes!$N$34,Lotes!$J$34)=0),Lotes!$L$34+S_EMB,0)+IF(AND(Lotes!$D$35>0,MOD(D$41-1-Lotes!$N$35,Lotes!$J$35)=0),Lotes!$L$35+S_EMB,0)+IF(AND(Lotes!$D$36>0,MOD(D$41-1-Lotes!$N$36,Lotes!$J$36)=0),Lotes!$L$36+S_EMB,0)+IF(AND(Lotes!$D$37>0,MOD(D$41-1-Lotes!$N$37,Lotes!$J$37)=0),Lotes!$L$37+S_EMB,0))/Lotes!$D$42 -> 0.6403217 | E45: =(IF(AND(Lotes!$D$30>0,MOD(E$41-1-Lotes!$N$30,Lotes!$J$30)=0),Lotes!$L$30+S_EMB,0)+IF(AND(Lotes!$D$31>0,MOD(E$41-1-Lotes!$N$31,Lotes!$J$31)=0),Lotes!$L$31+S_EMB,0)+IF(AND(Lotes!$D$32>0,MOD(E$41-1-Lotes!$N$32,Lotes!$J$32)=0),Lotes!$L$32+S_EMB,0)+IF(AND(Lotes!$D$33>0,MOD(E$41-1-Lotes!$N$33,Lotes!$J$33)=0),Lotes!$L$33+S_EMB,0)+IF(AND(Lotes!$D$34>0,MOD(E$41-1-Lotes!$N$34,Lotes!$J$34)=0),Lotes!$L$34+S_EMB,0)+IF(AND(Lotes!$D$35>0,MOD(E$41-1-Lotes!$N$35,Lotes!$J$35)=0),Lotes!$L$35+S_EMB,0)+IF(AND(Lotes!$D$36>0,MOD(E$41-1-Lotes!$N$36,Lotes!$J$36)=0),Lotes!$L$36+S_EMB,0)+IF(AND(Lotes!$D$37>0,MOD(E$41-1-Lotes!$N$37,Lotes!$J$37)=0),Lotes!$L$37+S_EMB,0))/Lotes!$D$42 -> 0.44054751 | F45: =(IF(AND(Lotes!$D$30>0,MOD(F$41-1-Lotes!$N$30,Lotes!$J$30)=0),Lotes!$L$30+S_EMB,0)+IF(AND(Lotes!$D$31>0,MOD(F$41-1-Lotes!$N$31,Lotes!$J$31)=0),Lotes!$L$31+S_EMB,0)+IF(AND(Lotes!$D$32>0,MOD(F$41-1-Lotes!$N$32,Lotes!$J$32)=0),Lotes!$L$32+S_EMB,0)+IF(AND(Lotes!$D$33>0,MOD(F$41-1-Lotes!$N$33,Lotes!$J$33)=0),Lotes!$L$33+S_EMB,0)+IF(AND(Lotes!$D$34>0,MOD(F$41-1-Lotes!$N$34,Lotes!$J$34)=0),Lotes!$L$34+S_EMB,0)+IF(AND(Lotes!$D$35>0,MOD(F$41-1-Lotes!$N$35,Lotes!$J$35)=0),Lotes!$L$35+S_EMB,0)+IF(AND(Lotes!$D$36>0,MOD(F$41-1-Lotes!$N$36,Lotes!$J$36)=0),Lotes!$L$36+S_EMB,0)+IF(AND(Lotes!$D$37>0,MOD(F$41-1-Lotes!$N$37,Lotes!$J$37)=0),Lotes!$L$37+S_EMB,0))/Lotes!$D$42 -> 0.44054751 | G45: =(IF(AND(Lotes!$D$30>0,MOD(G$41-1-Lotes!$N$30,Lotes!$J$30)=0),Lotes!$L$30+S_EMB,0)+IF(AND(Lotes!$D$31>0,MOD(G$41-1-Lotes!$N$31,Lotes!$J$31)=0),Lotes!$L$31+S_EMB,0)+IF(AND(Lotes!$D$32>0,MOD(G$41-1-Lotes!$N$32,Lotes!$J$32)=0),Lotes!$L$32+S_EMB,0)+IF(AND(Lotes!$D$33>0,MOD(G$41-1-Lotes!$N$33,Lotes!$J$33)=0),Lotes!$L$33+S_EMB,0)+IF(AND(Lotes!$D$34>0,MOD(G$41-1-Lotes!$N$34,Lotes!$J$34)=0),Lotes!$L$34+S_EMB,0)+IF(AND(Lotes!$D$35>0,MOD(G$41-1-Lotes!$N$35,Lotes!$J$35)=0),Lotes!$L$35+S_EMB,0)+IF(AND(Lotes!$D$36>0,MOD(G$41-1-Lotes!$N$36,Lotes!$J$36)=0),Lotes!$L$36+S_EMB,0)+IF(AND(Lotes!$D$37>0,MOD(G$41-1-Lotes!$N$37,Lotes!$J$37)=0),Lotes!$L$37+S_EMB,0))/Lotes!$D$42 -> 0.6403217 | H45: =(IF(AND(Lotes!$D$30>0,MOD(H$41-1-Lotes!$N$30,Lotes!$J$30)=0),Lotes!$L$30+S_EMB,0)+IF(AND(Lotes!$D$31>0,MOD(H$41-1-Lotes!$N$31,Lotes!$J$31)=0),Lotes!$L$31+S_EMB,0)+IF(AND(Lotes!$D$32>0,MOD(H$41-1-Lotes!$N$32,Lotes!$J$32)=0),Lotes!$L$32+S_EMB,0)+IF(AND(Lotes!$D$33>0,MOD(H$41-1-Lotes!$N$33,Lotes!$J$33)=0),Lotes!$L$33+S_EMB,0)+IF(AND(Lotes!$D$34>0,MOD(H$41-1-Lotes!$N$34,Lotes!$J$34)=0),Lotes!$L$34+S_EMB,0)+IF(AND(Lotes!$D$35>0,MOD(H$41-1-Lotes!$N$35,Lotes!$J$35)=0),Lotes!$L$35+S_EMB,0)+IF(AND(Lotes!$D$36>0,MOD(H$41-1-Lotes!$N$36,Lotes!$J$36)=0),Lotes!$L$36+S_EMB,0)+IF(AND(Lotes!$D$37>0,MOD(H$41-1-Lotes!$N$37,Lotes!$J$37)=0),Lotes!$L$37+S_EMB,0))/Lotes!$D$42 -> 0.6403217 | I45: =(IF(AND(Lotes!$D$30>0,MOD(I$41-1-Lotes!$N$30,Lotes!$J$30)=0),Lotes!$L$30+S_EMB,0)+IF(AND(Lotes!$D$31>0,MOD(I$41-1-Lotes!$N$31,Lotes!$J$31)=0),Lotes!$L$31+S_EMB,0)+IF(AND(Lotes!$D$32>0,MOD(I$41-1-Lotes!$N$32,Lotes!$J$32)=0),Lotes!$L$32+S_EMB,0)+IF(AND(Lotes!$D$33>0,MOD(I$41-1-Lotes!$N$33,Lotes!$J$33)=0),Lotes!$L$33+S_EMB,0)+IF(AND(Lotes!$D$34>0,MOD(I$41-1-Lotes!$N$34,Lotes!$J$34)=0),Lotes!$L$34+S_EMB,0)+IF(AND(Lotes!$D$35>0,MOD(I$41-1-Lotes!$N$35,Lotes!$J$35)=0),Lotes!$L$35+S_EMB,0)+IF(AND(Lotes!$D$36>0,MOD(I$41-1-Lotes!$N$36,Lotes!$J$36)=0),Lotes!$L$36+S_EMB,0)+IF(AND(Lotes!$D$37>0,MOD(I$41-1-Lotes!$N$37,Lotes!$J$37)=0),Lotes!$L$37+S_EMB,0))/Lotes!$D$42 -> 0.25068094 | J45: =(IF(AND(Lotes!$D$30>0,MOD(J$41-1-Lotes!$N$30,Lotes!$J$30)=0),Lotes!$L$30+S_EMB,0)+IF(AND(Lotes!$D$31>0,MOD(J$41-1-Lotes!$N$31,Lotes!$J$31)=0),Lotes!$L$31+S_EMB,0)+IF(AND(Lotes!$D$32>0,MOD(J$41-1-Lotes!$N$32,Lotes!$J$32)=0),Lotes!$L$32+S_EMB,0)+IF(AND(Lotes!$D$33>0,MOD(J$41-1-Lotes!$N$33,Lotes!$J$33)=0),Lotes!$L$33+S_EMB,0)+IF(AND(Lotes!$D$34>0,MOD(J$41-1-Lotes!$N$34,Lotes!$J$34)=0),Lotes!$L$34+S_EMB,0)+IF(AND(Lotes!$D$35>0,MOD(J$41-1-Lotes!$N$35,Lotes!$J$35)=0),Lotes!$L$35+S_EMB,0)+IF(AND(Lotes!$D$36>0,MOD(J$41-1-Lotes!$N$36,Lotes!$J$36)=0),Lotes!$L$36+S_EMB,0)+IF(AND(Lotes!$D$37>0,MOD(J$41-1-Lotes!$N$37,Lotes!$J$37)=0),Lotes!$L$37+S_EMB,0))/Lotes!$D$42 -> 0.25068094 | ... V45: =(IF(AND(Lotes!$D$30>0,MOD(V$41-1-Lotes!$N$30,Lotes!$J$30)=0),Lotes!$L$30+S_EMB,0)+IF(AND(Lotes!$D$31>0,MOD(V$41-1-Lotes!$N$31,Lotes!$J$31)=0),Lotes!$L$31+S_EMB,0)+IF(AND(Lotes!$D$32>0,MOD(V$41-1-Lotes!$N$32,Lotes!$J$32)=0),Lotes!$L$32+S_EMB,0)+IF(AND(Lotes!$D$33>0,MOD(V$41-1-Lotes!$N$33,Lotes!$J$33)=0),Lotes!$L$33+S_EMB,0)+IF(AND(Lotes!$D$34>0,MOD(V$41-1-Lotes!$N$34,Lotes!$J$34)=0),Lotes!$L$34+S_EMB,0)+IF(AND(Lotes!$D$35>0,MOD(V$41-1-Lotes!$N$35,Lotes!$J$35)=0),Lotes!$L$35+S_EMB,0)+IF(AND(Lotes!$D$36>0,MOD(V$41-1-Lotes!$N$36,Lotes!$J$36)=0),Lotes!$L$36+S_EMB,0)+IF(AND(Lotes!$D$37>0,MOD(V$41-1-Lotes!$N$37,Lotes!$J$37)=0),Lotes!$L$37+S_EMB,0))/Lotes!$D$42 -> 0.44054751
B46: =Carga!B41 -> Cilindrado | C46: =IF(AND($K$11>0,MOD(C$41-1-$I$35,$H$35)=0),"1 ","")&IF(AND($L$11>0,MOD(C$41-1-$I$36,$H$36)=0),"2,5 ","")&IF(AND($M$11>0,MOD(C$41-1-$I$37,$H$37)=0),"5 ","")&IF(AND($N$11>0,MOD(C$41-1-$I$38,$H$38)=0),"10 ","") -> 1 2,5 5 | D46: =IF(AND($K$11>0,MOD(D$41-1-$I$35,$H$35)=0),"1 ","")&IF(AND($L$11>0,MOD(D$41-1-$I$36,$H$36)=0),"2,5 ","")&IF(AND($M$11>0,MOD(D$41-1-$I$37,$H$37)=0),"5 ","")&IF(AND($N$11>0,MOD(D$41-1-$I$38,$H$38)=0),"10 ","") -> 1 2,5 5 10 | E46: =IF(AND($K$11>0,MOD(E$41-1-$I$35,$H$35)=0),"1 ","")&IF(AND($L$11>0,MOD(E$41-1-$I$36,$H$36)=0),"2,5 ","")&IF(AND($M$11>0,MOD(E$41-1-$I$37,$H$37)=0),"5 ","")&IF(AND($N$11>0,MOD(E$41-1-$I$38,$H$38)=0),"10 ","") -> 1 2,5 5 | F46: =IF(AND($K$11>0,MOD(F$41-1-$I$35,$H$35)=0),"1 ","")&IF(AND($L$11>0,MOD(F$41-1-$I$36,$H$36)=0),"2,5 ","")&IF(AND($M$11>0,MOD(F$41-1-$I$37,$H$37)=0),"5 ","")&IF(AND($N$11>0,MOD(F$41-1-$I$38,$H$38)=0),"10 ","") -> 1 2,5 5 10 | G46: =IF(AND($K$11>0,MOD(G$41-1-$I$35,$H$35)=0),"1 ","")&IF(AND($L$11>0,MOD(G$41-1-$I$36,$H$36)=0),"2,5 ","")&IF(AND($M$11>0,MOD(G$41-1-$I$37,$H$37)=0),"5 ","")&IF(AND($N$11>0,MOD(G$41-1-$I$38,$H$38)=0),"10 ","") -> 1 2,5 5 | H46: =IF(AND($K$11>0,MOD(H$41-1-$I$35,$H$35)=0),"1 ","")&IF(AND($L$11>0,MOD(H$41-1-$I$36,$H$36)=0),"2,5 ","")&IF(AND($M$11>0,MOD(H$41-1-$I$37,$H$37)=0),"5 ","")&IF(AND($N$11>0,MOD(H$41-1-$I$38,$H$38)=0),"10 ","") -> 1 2,5 5 10 | I46: =IF(AND($K$11>0,MOD(I$41-1-$I$35,$H$35)=0),"1 ","")&IF(AND($L$11>0,MOD(I$41-1-$I$36,$H$36)=0),"2,5 ","")&IF(AND($M$11>0,MOD(I$41-1-$I$37,$H$37)=0),"5 ","")&IF(AND($N$11>0,MOD(I$41-1-$I$38,$H$38)=0),"10 ","") -> 1 2,5 5 | J46: =IF(AND($K$11>0,MOD(J$41-1-$I$35,$H$35)=0),"1 ","")&IF(AND($L$11>0,MOD(J$41-1-$I$36,$H$36)=0),"2,5 ","")&IF(AND($M$11>0,MOD(J$41-1-$I$37,$H$37)=0),"5 ","")&IF(AND($N$11>0,MOD(J$41-1-$I$38,$H$38)=0),"10 ","") -> 1 2,5 5 10 | ... V46: =IF(AND($K$11>0,MOD(V$41-1-$I$35,$H$35)=0),"1 ","")&IF(AND($L$11>0,MOD(V$41-1-$I$36,$H$36)=0),"2,5 ","")&IF(AND($M$11>0,MOD(V$41-1-$I$37,$H$37)=0),"5 ","")&IF(AND($N$11>0,MOD(V$41-1-$I$38,$H$38)=0),"10 ","") -> 1 2,5 5 10
B47: carga | C47: =IF($H$11=0,0,(IF(AND($K$11>0,MOD(C$41-1-$I$35,$H$35)=0),$K$11*$H$35+IF(OR($D$11="No",AND($E$11="Sí",$F$11>=2)),0,$C$11),0)+IF(AND($L$11>0,MOD(C$41-1-$I$36,$H$36)=0),$L$11*$H$36+IF(OR($D$11="No"),0,$C$11),0)+IF(AND($M$11>0,MOD(C$41-1-$I$37,$H$37)=0),$M$11*$H$37+IF(OR($D$11="No"),0,$C$11),0)+IF(AND($N$11>0,MOD(C$41-1-$I$38,$H$38)=0),$N$11*$H$38+IF(OR($D$11="No"),0,$C$11),0))/$H$11) -> 0.37297177 | D47: =IF($H$11=0,0,(IF(AND($K$11>0,MOD(D$41-1-$I$35,$H$35)=0),$K$11*$H$35+IF(OR($D$11="No",AND($E$11="Sí",$F$11>=2)),0,$C$11),0)+IF(AND($L$11>0,MOD(D$41-1-$I$36,$H$36)=0),$L$11*$H$36+IF(OR($D$11="No"),0,$C$11),0)+IF(AND($M$11>0,MOD(D$41-1-$I$37,$H$37)=0),$M$11*$H$37+IF(OR($D$11="No"),0,$C$11),0)+IF(AND($N$11>0,MOD(D$41-1-$I$38,$H$38)=0),$N$11*$H$38+IF(OR($D$11="No"),0,$C$11),0))/$H$11) -> 0.3937402 | E47: =IF($H$11=0,0,(IF(AND($K$11>0,MOD(E$41-1-$I$35,$H$35)=0),$K$11*$H$35+IF(OR($D$11="No",AND($E$11="Sí",$F$11>=2)),0,$C$11),0)+IF(AND($L$11>0,MOD(E$41-1-$I$36,$H$36)=0),$L$11*$H$36+IF(OR($D$11="No"),0,$C$11),0)+IF(AND($M$11>0,MOD(E$41-1-$I$37,$H$37)=0),$M$11*$H$37+IF(OR($D$11="No"),0,$C$11),0)+IF(AND($N$11>0,MOD(E$41-1-$I$38,$H$38)=0),$N$11*$H$38+IF(OR($D$11="No"),0,$C$11),0))/$H$11) -> 0.37297177 | F47: =IF($H$11=0,0,(IF(AND($K$11>0,MOD(F$41-1-$I$35,$H$35)=0),$K$11*$H$35+IF(OR($D$11="No",AND($E$11="Sí",$F$11>=2)),0,$C$11),0)+IF(AND($L$11>0,MOD(F$41-1-$I$36,$H$36)=0),$L$11*$H$36+IF(OR($D$11="No"),0,$C$11),0)+IF(AND($M$11>0,MOD(F$41-1-$I$37,$H$37)=0),$M$11*$H$37+IF(OR($D$11="No"),0,$C$11),0)+IF(AND($N$11>0,MOD(F$41-1-$I$38,$H$38)=0),$N$11*$H$38+IF(OR($D$11="No"),0,$C$11),0))/$H$11) -> 0.3937402 | G47: =IF($H$11=0,0,(IF(AND($K$11>0,MOD(G$41-1-$I$35,$H$35)=0),$K$11*$H$35+IF(OR($D$11="No",AND($E$11="Sí",$F$11>=2)),0,$C$11),0)+IF(AND($L$11>0,MOD(G$41-1-$I$36,$H$36)=0),$L$11*$H$36+IF(OR($D$11="No"),0,$C$11),0)+IF(AND($M$11>0,MOD(G$41-1-$I$37,$H$37)=0),$M$11*$H$37+IF(OR($D$11="No"),0,$C$11),0)+IF(AND($N$11>0,MOD(G$41-1-$I$38,$H$38)=0),$N$11*$H$38+IF(OR($D$11="No"),0,$C$11),0))/$H$11) -> 0.37297177 | H47: =IF($H$11=0,0,(IF(AND($K$11>0,MOD(H$41-1-$I$35,$H$35)=0),$K$11*$H$35+IF(OR($D$11="No",AND($E$11="Sí",$F$11>=2)),0,$C$11),0)+IF(AND($L$11>0,MOD(H$41-1-$I$36,$H$36)=0),$L$11*$H$36+IF(OR($D$11="No"),0,$C$11),0)+IF(AND($M$11>0,MOD(H$41-1-$I$37,$H$37)=0),$M$11*$H$37+IF(OR($D$11="No"),0,$C$11),0)+IF(AND($N$11>0,MOD(H$41-1-$I$38,$H$38)=0),$N$11*$H$38+IF(OR($D$11="No"),0,$C$11),0))/$H$11) -> 0.3937402 | I47: =IF($H$11=0,0,(IF(AND($K$11>0,MOD(I$41-1-$I$35,$H$35)=0),$K$11*$H$35+IF(OR($D$11="No",AND($E$11="Sí",$F$11>=2)),0,$C$11),0)+IF(AND($L$11>0,MOD(I$41-1-$I$36,$H$36)=0),$L$11*$H$36+IF(OR($D$11="No"),0,$C$11),0)+IF(AND($M$11>0,MOD(I$41-1-$I$37,$H$37)=0),$M$11*$H$37+IF(OR($D$11="No"),0,$C$11),0)+IF(AND($N$11>0,MOD(I$41-1-$I$38,$H$38)=0),$N$11*$H$38+IF(OR($D$11="No"),0,$C$11),0))/$H$11) -> 0.37297177 | J47: =IF($H$11=0,0,(IF(AND($K$11>0,MOD(J$41-1-$I$35,$H$35)=0),$K$11*$H$35+IF(OR($D$11="No",AND($E$11="Sí",$F$11>=2)),0,$C$11),0)+IF(AND($L$11>0,MOD(J$41-1-$I$36,$H$36)=0),$L$11*$H$36+IF(OR($D$11="No"),0,$C$11),0)+IF(AND($M$11>0,MOD(J$41-1-$I$37,$H$37)=0),$M$11*$H$37+IF(OR($D$11="No"),0,$C$11),0)+IF(AND($N$11>0,MOD(J$41-1-$I$38,$H$38)=0),$N$11*$H$38+IF(OR($D$11="No"),0,$C$11),0))/$H$11) -> 0.3937402 | ... V47: =IF($H$11=0,0,(IF(AND($K$11>0,MOD(V$41-1-$I$35,$H$35)=0),$K$11*$H$35+IF(OR($D$11="No",AND($E$11="Sí",$F$11>=2)),0,$C$11),0)+IF(AND($L$11>0,MOD(V$41-1-$I$36,$H$36)=0),$L$11*$H$36+IF(OR($D$11="No"),0,$C$11),0)+IF(AND($M$11>0,MOD(V$41-1-$I$37,$H$37)=0),$M$11*$H$37+IF(OR($D$11="No"),0,$C$11),0)+IF(AND($N$11>0,MOD(V$41-1-$I$38,$H$38)=0),$N$11*$H$38+IF(OR($D$11="No"),0,$C$11),0))/$H$11) -> 0.3937402
B48: =Carga!B42 -> Soldadura longitudinal — 2,5 a 10 kg | C48: =IF(AND($K$12>0,MOD(C$41-1-$I$35,$H$35)=0),"1 ","")&IF(AND($L$12>0,MOD(C$41-1-$I$36,$H$36)=0),"2,5 ","")&IF(AND($M$12>0,MOD(C$41-1-$I$37,$H$37)=0),"5 ","")&IF(AND($N$12>0,MOD(C$41-1-$I$38,$H$38)=0),"10 ","") -> 2,5 5 | D48: =IF(AND($K$12>0,MOD(D$41-1-$I$35,$H$35)=0),"1 ","")&IF(AND($L$12>0,MOD(D$41-1-$I$36,$H$36)=0),"2,5 ","")&IF(AND($M$12>0,MOD(D$41-1-$I$37,$H$37)=0),"5 ","")&IF(AND($N$12>0,MOD(D$41-1-$I$38,$H$38)=0),"10 ","") -> 2,5 5 10 | E48: =IF(AND($K$12>0,MOD(E$41-1-$I$35,$H$35)=0),"1 ","")&IF(AND($L$12>0,MOD(E$41-1-$I$36,$H$36)=0),"2,5 ","")&IF(AND($M$12>0,MOD(E$41-1-$I$37,$H$37)=0),"5 ","")&IF(AND($N$12>0,MOD(E$41-1-$I$38,$H$38)=0),"10 ","") -> 2,5 5 | F48: =IF(AND($K$12>0,MOD(F$41-1-$I$35,$H$35)=0),"1 ","")&IF(AND($L$12>0,MOD(F$41-1-$I$36,$H$36)=0),"2,5 ","")&IF(AND($M$12>0,MOD(F$41-1-$I$37,$H$37)=0),"5 ","")&IF(AND($N$12>0,MOD(F$41-1-$I$38,$H$38)=0),"10 ","") -> 2,5 5 10 | G48: =IF(AND($K$12>0,MOD(G$41-1-$I$35,$H$35)=0),"1 ","")&IF(AND($L$12>0,MOD(G$41-1-$I$36,$H$36)=0),"2,5 ","")&IF(AND($M$12>0,MOD(G$41-1-$I$37,$H$37)=0),"5 ","")&IF(AND($N$12>0,MOD(G$41-1-$I$38,$H$38)=0),"10 ","") -> 2,5 5 | H48: =IF(AND($K$12>0,MOD(H$41-1-$I$35,$H$35)=0),"1 ","")&IF(AND($L$12>0,MOD(H$41-1-$I$36,$H$36)=0),"2,5 ","")&IF(AND($M$12>0,MOD(H$41-1-$I$37,$H$37)=0),"5 ","")&IF(AND($N$12>0,MOD(H$41-1-$I$38,$H$38)=0),"10 ","") -> 2,5 5 10 | I48: =IF(AND($K$12>0,MOD(I$41-1-$I$35,$H$35)=0),"1 ","")&IF(AND($L$12>0,MOD(I$41-1-$I$36,$H$36)=0),"2,5 ","")&IF(AND($M$12>0,MOD(I$41-1-$I$37,$H$37)=0),"5 ","")&IF(AND($N$12>0,MOD(I$41-1-$I$38,$H$38)=0),"10 ","") -> 2,5 5 | J48: =IF(AND($K$12>0,MOD(J$41-1-$I$35,$H$35)=0),"1 ","")&IF(AND($L$12>0,MOD(J$41-1-$I$36,$H$36)=0),"2,5 ","")&IF(AND($M$12>0,MOD(J$41-1-$I$37,$H$37)=0),"5 ","")&IF(AND($N$12>0,MOD(J$41-1-$I$38,$H$38)=0),"10 ","") -> 2,5 5 10 | ... V48: =IF(AND($K$12>0,MOD(V$41-1-$I$35,$H$35)=0),"1 ","")&IF(AND($L$12>0,MOD(V$41-1-$I$36,$H$36)=0),"2,5 ","")&IF(AND($M$12>0,MOD(V$41-1-$I$37,$H$37)=0),"5 ","")&IF(AND($N$12>0,MOD(V$41-1-$I$38,$H$38)=0),"10 ","") -> 2,5 5 10
B49: carga | C49: =IF($H$12=0,0,(IF(AND($K$12>0,MOD(C$41-1-$I$35,$H$35)=0),$K$12*$H$35+IF(OR($D$12="No",AND($E$12="Sí",$F$12>=2)),0,$C$12),0)+IF(AND($L$12>0,MOD(C$41-1-$I$36,$H$36)=0),$L$12*$H$36+IF(OR($D$12="No"),0,$C$12),0)+IF(AND($M$12>0,MOD(C$41-1-$I$37,$H$37)=0),$M$12*$H$37+IF(OR($D$12="No"),0,$C$12),0)+IF(AND($N$12>0,MOD(C$41-1-$I$38,$H$38)=0),$N$12*$H$38+IF(OR($D$12="No"),0,$C$12),0))/$H$12) -> 0.76952095 | D49: =IF($H$12=0,0,(IF(AND($K$12>0,MOD(D$41-1-$I$35,$H$35)=0),$K$12*$H$35+IF(OR($D$12="No",AND($E$12="Sí",$F$12>=2)),0,$C$12),0)+IF(AND($L$12>0,MOD(D$41-1-$I$36,$H$36)=0),$L$12*$H$36+IF(OR($D$12="No"),0,$C$12),0)+IF(AND($M$12>0,MOD(D$41-1-$I$37,$H$37)=0),$M$12*$H$37+IF(OR($D$12="No"),0,$C$12),0)+IF(AND($N$12>0,MOD(D$41-1-$I$38,$H$38)=0),$N$12*$H$38+IF(OR($D$12="No"),0,$C$12),0))/$H$12) -> 0.85467151 | E49: =IF($H$12=0,0,(IF(AND($K$12>0,MOD(E$41-1-$I$35,$H$35)=0),$K$12*$H$35+IF(OR($D$12="No",AND($E$12="Sí",$F$12>=2)),0,$C$12),0)+IF(AND($L$12>0,MOD(E$41-1-$I$36,$H$36)=0),$L$12*$H$36+IF(OR($D$12="No"),0,$C$12),0)+IF(AND($M$12>0,MOD(E$41-1-$I$37,$H$37)=0),$M$12*$H$37+IF(OR($D$12="No"),0,$C$12),0)+IF(AND($N$12>0,MOD(E$41-1-$I$38,$H$38)=0),$N$12*$H$38+IF(OR($D$12="No"),0,$C$12),0))/$H$12) -> 0.76952095 | F49: =IF($H$12=0,0,(IF(AND($K$12>0,MOD(F$41-1-$I$35,$H$35)=0),$K$12*$H$35+IF(OR($D$12="No",AND($E$12="Sí",$F$12>=2)),0,$C$12),0)+IF(AND($L$12>0,MOD(F$41-1-$I$36,$H$36)=0),$L$12*$H$36+IF(OR($D$12="No"),0,$C$12),0)+IF(AND($M$12>0,MOD(F$41-1-$I$37,$H$37)=0),$M$12*$H$37+IF(OR($D$12="No"),0,$C$12),0)+IF(AND($N$12>0,MOD(F$41-1-$I$38,$H$38)=0),$N$12*$H$38+IF(OR($D$12="No"),0,$C$12),0))/$H$12) -> 0.85467151 | G49: =IF($H$12=0,0,(IF(AND($K$12>0,MOD(G$41-1-$I$35,$H$35)=0),$K$12*$H$35+IF(OR($D$12="No",AND($E$12="Sí",$F$12>=2)),0,$C$12),0)+IF(AND($L$12>0,MOD(G$41-1-$I$36,$H$36)=0),$L$12*$H$36+IF(OR($D$12="No"),0,$C$12),0)+IF(AND($M$12>0,MOD(G$41-1-$I$37,$H$37)=0),$M$12*$H$37+IF(OR($D$12="No"),0,$C$12),0)+IF(AND($N$12>0,MOD(G$41-1-$I$38,$H$38)=0),$N$12*$H$38+IF(OR($D$12="No"),0,$C$12),0))/$H$12) -> 0.76952095 | H49: =IF($H$12=0,0,(IF(AND($K$12>0,MOD(H$41-1-$I$35,$H$35)=0),$K$12*$H$35+IF(OR($D$12="No",AND($E$12="Sí",$F$12>=2)),0,$C$12),0)+IF(AND($L$12>0,MOD(H$41-1-$I$36,$H$36)=0),$L$12*$H$36+IF(OR($D$12="No"),0,$C$12),0)+IF(AND($M$12>0,MOD(H$41-1-$I$37,$H$37)=0),$M$12*$H$37+IF(OR($D$12="No"),0,$C$12),0)+IF(AND($N$12>0,MOD(H$41-1-$I$38,$H$38)=0),$N$12*$H$38+IF(OR($D$12="No"),0,$C$12),0))/$H$12) -> 0.85467151 | I49: =IF($H$12=0,0,(IF(AND($K$12>0,MOD(I$41-1-$I$35,$H$35)=0),$K$12*$H$35+IF(OR($D$12="No",AND($E$12="Sí",$F$12>=2)),0,$C$12),0)+IF(AND($L$12>0,MOD(I$41-1-$I$36,$H$36)=0),$L$12*$H$36+IF(OR($D$12="No"),0,$C$12),0)+IF(AND($M$12>0,MOD(I$41-1-$I$37,$H$37)=0),$M$12*$H$37+IF(OR($D$12="No"),0,$C$12),0)+IF(AND($N$12>0,MOD(I$41-1-$I$38,$H$38)=0),$N$12*$H$38+IF(OR($D$12="No"),0,$C$12),0))/$H$12) -> 0.76952095 | J49: =IF($H$12=0,0,(IF(AND($K$12>0,MOD(J$41-1-$I$35,$H$35)=0),$K$12*$H$35+IF(OR($D$12="No",AND($E$12="Sí",$F$12>=2)),0,$C$12),0)+IF(AND($L$12>0,MOD(J$41-1-$I$36,$H$36)=0),$L$12*$H$36+IF(OR($D$12="No"),0,$C$12),0)+IF(AND($M$12>0,MOD(J$41-1-$I$37,$H$37)=0),$M$12*$H$37+IF(OR($D$12="No"),0,$C$12),0)+IF(AND($N$12>0,MOD(J$41-1-$I$38,$H$38)=0),$N$12*$H$38+IF(OR($D$12="No"),0,$C$12),0))/$H$12) -> 0.85467151 | ... V49: =IF($H$12=0,0,(IF(AND($K$12>0,MOD(V$41-1-$I$35,$H$35)=0),$K$12*$H$35+IF(OR($D$12="No",AND($E$12="Sí",$F$12>=2)),0,$C$12),0)+IF(AND($L$12>0,MOD(V$41-1-$I$36,$H$36)=0),$L$12*$H$36+IF(OR($D$12="No"),0,$C$12),0)+IF(AND($M$12>0,MOD(V$41-1-$I$37,$H$37)=0),$M$12*$H$37+IF(OR($D$12="No"),0,$C$12),0)+IF(AND($N$12>0,MOD(V$41-1-$I$38,$H$38)=0),$N$12*$H$38+IF(OR($D$12="No"),0,$C$12),0))/$H$12) -> 0.85467151
B50: =Carga!B43 -> Soldadura longitudinal TIG — 1 kg | C50: =IF(AND($K$13>0,MOD(C$41-1-$I$35,$H$35)=0),"1 ","")&IF(AND($L$13>0,MOD(C$41-1-$I$36,$H$36)=0),"2,5 ","")&IF(AND($M$13>0,MOD(C$41-1-$I$37,$H$37)=0),"5 ","")&IF(AND($N$13>0,MOD(C$41-1-$I$38,$H$38)=0),"10 ","") -> 1 | D50: =IF(AND($K$13>0,MOD(D$41-1-$I$35,$H$35)=0),"1 ","")&IF(AND($L$13>0,MOD(D$41-1-$I$36,$H$36)=0),"2,5 ","")&IF(AND($M$13>0,MOD(D$41-1-$I$37,$H$37)=0),"5 ","")&IF(AND($N$13>0,MOD(D$41-1-$I$38,$H$38)=0),"10 ","") -> 1 | E50: =IF(AND($K$13>0,MOD(E$41-1-$I$35,$H$35)=0),"1 ","")&IF(AND($L$13>0,MOD(E$41-1-$I$36,$H$36)=0),"2,5 ","")&IF(AND($M$13>0,MOD(E$41-1-$I$37,$H$37)=0),"5 ","")&IF(AND($N$13>0,MOD(E$41-1-$I$38,$H$38)=0),"10 ","") -> 1 | F50: =IF(AND($K$13>0,MOD(F$41-1-$I$35,$H$35)=0),"1 ","")&IF(AND($L$13>0,MOD(F$41-1-$I$36,$H$36)=0),"2,5 ","")&IF(AND($M$13>0,MOD(F$41-1-$I$37,$H$37)=0),"5 ","")&IF(AND($N$13>0,MOD(F$41-1-$I$38,$H$38)=0),"10 ","") -> 1 | G50: =IF(AND($K$13>0,MOD(G$41-1-$I$35,$H$35)=0),"1 ","")&IF(AND($L$13>0,MOD(G$41-1-$I$36,$H$36)=0),"2,5 ","")&IF(AND($M$13>0,MOD(G$41-1-$I$37,$H$37)=0),"5 ","")&IF(AND($N$13>0,MOD(G$41-1-$I$38,$H$38)=0),"10 ","") -> 1 | H50: =IF(AND($K$13>0,MOD(H$41-1-$I$35,$H$35)=0),"1 ","")&IF(AND($L$13>0,MOD(H$41-1-$I$36,$H$36)=0),"2,5 ","")&IF(AND($M$13>0,MOD(H$41-1-$I$37,$H$37)=0),"5 ","")&IF(AND($N$13>0,MOD(H$41-1-$I$38,$H$38)=0),"10 ","") -> 1 | I50: =IF(AND($K$13>0,MOD(I$41-1-$I$35,$H$35)=0),"1 ","")&IF(AND($L$13>0,MOD(I$41-1-$I$36,$H$36)=0),"2,5 ","")&IF(AND($M$13>0,MOD(I$41-1-$I$37,$H$37)=0),"5 ","")&IF(AND($N$13>0,MOD(I$41-1-$I$38,$H$38)=0),"10 ","") -> 1 | J50: =IF(AND($K$13>0,MOD(J$41-1-$I$35,$H$35)=0),"1 ","")&IF(AND($L$13>0,MOD(J$41-1-$I$36,$H$36)=0),"2,5 ","")&IF(AND($M$13>0,MOD(J$41-1-$I$37,$H$37)=0),"5 ","")&IF(AND($N$13>0,MOD(J$41-1-$I$38,$H$38)=0),"10 ","") -> 1 | ... V50: =IF(AND($K$13>0,MOD(V$41-1-$I$35,$H$35)=0),"1 ","")&IF(AND($L$13>0,MOD(V$41-1-$I$36,$H$36)=0),"2,5 ","")&IF(AND($M$13>0,MOD(V$41-1-$I$37,$H$37)=0),"5 ","")&IF(AND($N$13>0,MOD(V$41-1-$I$38,$H$38)=0),"10 ","") -> 1
B51: carga | C51: =IF($H$13=0,0,(IF(AND($K$13>0,MOD(C$41-1-$I$35,$H$35)=0),$K$13*$H$35+IF(OR($D$13="No",AND($E$13="Sí",$F$13>=2)),0,$C$13),0)+IF(AND($L$13>0,MOD(C$41-1-$I$36,$H$36)=0),$L$13*$H$36+IF(OR($D$13="No"),0,$C$13),0)+IF(AND($M$13>0,MOD(C$41-1-$I$37,$H$37)=0),$M$13*$H$37+IF(OR($D$13="No"),0,$C$13),0)+IF(AND($N$13>0,MOD(C$41-1-$I$38,$H$38)=0),$N$13*$H$38+IF(OR($D$13="No"),0,$C$13),0))/$H$13) -> 0.5065516 | D51: =IF($H$13=0,0,(IF(AND($K$13>0,MOD(D$41-1-$I$35,$H$35)=0),$K$13*$H$35+IF(OR($D$13="No",AND($E$13="Sí",$F$13>=2)),0,$C$13),0)+IF(AND($L$13>0,MOD(D$41-1-$I$36,$H$36)=0),$L$13*$H$36+IF(OR($D$13="No"),0,$C$13),0)+IF(AND($M$13>0,MOD(D$41-1-$I$37,$H$37)=0),$M$13*$H$37+IF(OR($D$13="No"),0,$C$13),0)+IF(AND($N$13>0,MOD(D$41-1-$I$38,$H$38)=0),$N$13*$H$38+IF(OR($D$13="No"),0,$C$13),0))/$H$13) -> 0.5065516 | E51: =IF($H$13=0,0,(IF(AND($K$13>0,MOD(E$41-1-$I$35,$H$35)=0),$K$13*$H$35+IF(OR($D$13="No",AND($E$13="Sí",$F$13>=2)),0,$C$13),0)+IF(AND($L$13>0,MOD(E$41-1-$I$36,$H$36)=0),$L$13*$H$36+IF(OR($D$13="No"),0,$C$13),0)+IF(AND($M$13>0,MOD(E$41-1-$I$37,$H$37)=0),$M$13*$H$37+IF(OR($D$13="No"),0,$C$13),0)+IF(AND($N$13>0,MOD(E$41-1-$I$38,$H$38)=0),$N$13*$H$38+IF(OR($D$13="No"),0,$C$13),0))/$H$13) -> 0.5065516 | F51: =IF($H$13=0,0,(IF(AND($K$13>0,MOD(F$41-1-$I$35,$H$35)=0),$K$13*$H$35+IF(OR($D$13="No",AND($E$13="Sí",$F$13>=2)),0,$C$13),0)+IF(AND($L$13>0,MOD(F$41-1-$I$36,$H$36)=0),$L$13*$H$36+IF(OR($D$13="No"),0,$C$13),0)+IF(AND($M$13>0,MOD(F$41-1-$I$37,$H$37)=0),$M$13*$H$37+IF(OR($D$13="No"),0,$C$13),0)+IF(AND($N$13>0,MOD(F$41-1-$I$38,$H$38)=0),$N$13*$H$38+IF(OR($D$13="No"),0,$C$13),0))/$H$13) -> 0.5065516 | G51: =IF($H$13=0,0,(IF(AND($K$13>0,MOD(G$41-1-$I$35,$H$35)=0),$K$13*$H$35+IF(OR($D$13="No",AND($E$13="Sí",$F$13>=2)),0,$C$13),0)+IF(AND($L$13>0,MOD(G$41-1-$I$36,$H$36)=0),$L$13*$H$36+IF(OR($D$13="No"),0,$C$13),0)+IF(AND($M$13>0,MOD(G$41-1-$I$37,$H$37)=0),$M$13*$H$37+IF(OR($D$13="No"),0,$C$13),0)+IF(AND($N$13>0,MOD(G$41-1-$I$38,$H$38)=0),$N$13*$H$38+IF(OR($D$13="No"),0,$C$13),0))/$H$13) -> 0.5065516 | H51: =IF($H$13=0,0,(IF(AND($K$13>0,MOD(H$41-1-$I$35,$H$35)=0),$K$13*$H$35+IF(OR($D$13="No",AND($E$13="Sí",$F$13>=2)),0,$C$13),0)+IF(AND($L$13>0,MOD(H$41-1-$I$36,$H$36)=0),$L$13*$H$36+IF(OR($D$13="No"),0,$C$13),0)+IF(AND($M$13>0,MOD(H$41-1-$I$37,$H$37)=0),$M$13*$H$37+IF(OR($D$13="No"),0,$C$13),0)+IF(AND($N$13>0,MOD(H$41-1-$I$38,$H$38)=0),$N$13*$H$38+IF(OR($D$13="No"),0,$C$13),0))/$H$13) -> 0.5065516 | I51: =IF($H$13=0,0,(IF(AND($K$13>0,MOD(I$41-1-$I$35,$H$35)=0),$K$13*$H$35+IF(OR($D$13="No",AND($E$13="Sí",$F$13>=2)),0,$C$13),0)+IF(AND($L$13>0,MOD(I$41-1-$I$36,$H$36)=0),$L$13*$H$36+IF(OR($D$13="No"),0,$C$13),0)+IF(AND($M$13>0,MOD(I$41-1-$I$37,$H$37)=0),$M$13*$H$37+IF(OR($D$13="No"),0,$C$13),0)+IF(AND($N$13>0,MOD(I$41-1-$I$38,$H$38)=0),$N$13*$H$38+IF(OR($D$13="No"),0,$C$13),0))/$H$13) -> 0.5065516 | J51: =IF($H$13=0,0,(IF(AND($K$13>0,MOD(J$41-1-$I$35,$H$35)=0),$K$13*$H$35+IF(OR($D$13="No",AND($E$13="Sí",$F$13>=2)),0,$C$13),0)+IF(AND($L$13>0,MOD(J$41-1-$I$36,$H$36)=0),$L$13*$H$36+IF(OR($D$13="No"),0,$C$13),0)+IF(AND($M$13>0,MOD(J$41-1-$I$37,$H$37)=0),$M$13*$H$37+IF(OR($D$13="No"),0,$C$13),0)+IF(AND($N$13>0,MOD(J$41-1-$I$38,$H$38)=0),$N$13*$H$38+IF(OR($D$13="No"),0,$C$13),0))/$H$13) -> 0.5065516 | ... V51: =IF($H$13=0,0,(IF(AND($K$13>0,MOD(V$41-1-$I$35,$H$35)=0),$K$13*$H$35+IF(OR($D$13="No",AND($E$13="Sí",$F$13>=2)),0,$C$13),0)+IF(AND($L$13>0,MOD(V$41-1-$I$36,$H$36)=0),$L$13*$H$36+IF(OR($D$13="No"),0,$C$13),0)+IF(AND($M$13>0,MOD(V$41-1-$I$37,$H$37)=0),$M$13*$H$37+IF(OR($D$13="No"),0,$C$13),0)+IF(AND($N$13>0,MOD(V$41-1-$I$38,$H$38)=0),$N$13*$H$38+IF(OR($D$13="No"),0,$C$13),0))/$H$13) -> 0.5065516
B52: =Carga!B44 -> Encastre de fondo | C52: =IF(AND($K$14>0,MOD(C$41-1-$I$35,$H$35)=0),"1 ","")&IF(AND($L$14>0,MOD(C$41-1-$I$36,$H$36)=0),"2,5 ","")&IF(AND($M$14>0,MOD(C$41-1-$I$37,$H$37)=0),"5 ","")&IF(AND($N$14>0,MOD(C$41-1-$I$38,$H$38)=0),"10 ","") -> 1 2,5 5 | D52: =IF(AND($K$14>0,MOD(D$41-1-$I$35,$H$35)=0),"1 ","")&IF(AND($L$14>0,MOD(D$41-1-$I$36,$H$36)=0),"2,5 ","")&IF(AND($M$14>0,MOD(D$41-1-$I$37,$H$37)=0),"5 ","")&IF(AND($N$14>0,MOD(D$41-1-$I$38,$H$38)=0),"10 ","") -> 1 2,5 5 10 | E52: =IF(AND($K$14>0,MOD(E$41-1-$I$35,$H$35)=0),"1 ","")&IF(AND($L$14>0,MOD(E$41-1-$I$36,$H$36)=0),"2,5 ","")&IF(AND($M$14>0,MOD(E$41-1-$I$37,$H$37)=0),"5 ","")&IF(AND($N$14>0,MOD(E$41-1-$I$38,$H$38)=0),"10 ","") -> 1 2,5 5 | F52: =IF(AND($K$14>0,MOD(F$41-1-$I$35,$H$35)=0),"1 ","")&IF(AND($L$14>0,MOD(F$41-1-$I$36,$H$36)=0),"2,5 ","")&IF(AND($M$14>0,MOD(F$41-1-$I$37,$H$37)=0),"5 ","")&IF(AND($N$14>0,MOD(F$41-1-$I$38,$H$38)=0),"10 ","") -> 1 2,5 5 10 | G52: =IF(AND($K$14>0,MOD(G$41-1-$I$35,$H$35)=0),"1 ","")&IF(AND($L$14>0,MOD(G$41-1-$I$36,$H$36)=0),"2,5 ","")&IF(AND($M$14>0,MOD(G$41-1-$I$37,$H$37)=0),"5 ","")&IF(AND($N$14>0,MOD(G$41-1-$I$38,$H$38)=0),"10 ","") -> 1 2,5 5 | H52: =IF(AND($K$14>0,MOD(H$41-1-$I$35,$H$35)=0),"1 ","")&IF(AND($L$14>0,MOD(H$41-1-$I$36,$H$36)=0),"2,5 ","")&IF(AND($M$14>0,MOD(H$41-1-$I$37,$H$37)=0),"5 ","")&IF(AND($N$14>0,MOD(H$41-1-$I$38,$H$38)=0),"10 ","") -> 1 2,5 5 10 | I52: =IF(AND($K$14>0,MOD(I$41-1-$I$35,$H$35)=0),"1 ","")&IF(AND($L$14>0,MOD(I$41-1-$I$36,$H$36)=0),"2,5 ","")&IF(AND($M$14>0,MOD(I$41-1-$I$37,$H$37)=0),"5 ","")&IF(AND($N$14>0,MOD(I$41-1-$I$38,$H$38)=0),"10 ","") -> 1 2,5 5 | J52: =IF(AND($K$14>0,MOD(J$41-1-$I$35,$H$35)=0),"1 ","")&IF(AND($L$14>0,MOD(J$41-1-$I$36,$H$36)=0),"2,5 ","")&IF(AND($M$14>0,MOD(J$41-1-$I$37,$H$37)=0),"5 ","")&IF(AND($N$14>0,MOD(J$41-1-$I$38,$H$38)=0),"10 ","") -> 1 2,5 5 10 | ... V52: =IF(AND($K$14>0,MOD(V$41-1-$I$35,$H$35)=0),"1 ","")&IF(AND($L$14>0,MOD(V$41-1-$I$36,$H$36)=0),"2,5 ","")&IF(AND($M$14>0,MOD(V$41-1-$I$37,$H$37)=0),"5 ","")&IF(AND($N$14>0,MOD(V$41-1-$I$38,$H$38)=0),"10 ","") -> 1 2,5 5 10
B53: carga | C53: =IF($H$14=0,0,(IF(AND($K$14>0,MOD(C$41-1-$I$35,$H$35)=0),$K$14*$H$35+IF(OR($D$14="No",AND($E$14="Sí",$F$14>=2)),0,$C$14),0)+IF(AND($L$14>0,MOD(C$41-1-$I$36,$H$36)=0),$L$14*$H$36+IF(OR($D$14="No"),0,$C$14),0)+IF(AND($M$14>0,MOD(C$41-1-$I$37,$H$37)=0),$M$14*$H$37+IF(OR($D$14="No"),0,$C$14),0)+IF(AND($N$14>0,MOD(C$41-1-$I$38,$H$38)=0),$N$14*$H$38+IF(OR($D$14="No"),0,$C$14),0))/$H$14) -> 0.73483242 | D53: =IF($H$14=0,0,(IF(AND($K$14>0,MOD(D$41-1-$I$35,$H$35)=0),$K$14*$H$35+IF(OR($D$14="No",AND($E$14="Sí",$F$14>=2)),0,$C$14),0)+IF(AND($L$14>0,MOD(D$41-1-$I$36,$H$36)=0),$L$14*$H$36+IF(OR($D$14="No"),0,$C$14),0)+IF(AND($M$14>0,MOD(D$41-1-$I$37,$H$37)=0),$M$14*$H$37+IF(OR($D$14="No"),0,$C$14),0)+IF(AND($N$14>0,MOD(D$41-1-$I$38,$H$38)=0),$N$14*$H$38+IF(OR($D$14="No"),0,$C$14),0))/$H$14) -> 0.76525818 | E53: =IF($H$14=0,0,(IF(AND($K$14>0,MOD(E$41-1-$I$35,$H$35)=0),$K$14*$H$35+IF(OR($D$14="No",AND($E$14="Sí",$F$14>=2)),0,$C$14),0)+IF(AND($L$14>0,MOD(E$41-1-$I$36,$H$36)=0),$L$14*$H$36+IF(OR($D$14="No"),0,$C$14),0)+IF(AND($M$14>0,MOD(E$41-1-$I$37,$H$37)=0),$M$14*$H$37+IF(OR($D$14="No"),0,$C$14),0)+IF(AND($N$14>0,MOD(E$41-1-$I$38,$H$38)=0),$N$14*$H$38+IF(OR($D$14="No"),0,$C$14),0))/$H$14) -> 0.73483242 | F53: =IF($H$14=0,0,(IF(AND($K$14>0,MOD(F$41-1-$I$35,$H$35)=0),$K$14*$H$35+IF(OR($D$14="No",AND($E$14="Sí",$F$14>=2)),0,$C$14),0)+IF(AND($L$14>0,MOD(F$41-1-$I$36,$H$36)=0),$L$14*$H$36+IF(OR($D$14="No"),0,$C$14),0)+IF(AND($M$14>0,MOD(F$41-1-$I$37,$H$37)=0),$M$14*$H$37+IF(OR($D$14="No"),0,$C$14),0)+IF(AND($N$14>0,MOD(F$41-1-$I$38,$H$38)=0),$N$14*$H$38+IF(OR($D$14="No"),0,$C$14),0))/$H$14) -> 0.76525818 | G53: =IF($H$14=0,0,(IF(AND($K$14>0,MOD(G$41-1-$I$35,$H$35)=0),$K$14*$H$35+IF(OR($D$14="No",AND($E$14="Sí",$F$14>=2)),0,$C$14),0)+IF(AND($L$14>0,MOD(G$41-1-$I$36,$H$36)=0),$L$14*$H$36+IF(OR($D$14="No"),0,$C$14),0)+IF(AND($M$14>0,MOD(G$41-1-$I$37,$H$37)=0),$M$14*$H$37+IF(OR($D$14="No"),0,$C$14),0)+IF(AND($N$14>0,MOD(G$41-1-$I$38,$H$38)=0),$N$14*$H$38+IF(OR($D$14="No"),0,$C$14),0))/$H$14) -> 0.73483242 | H53: =IF($H$14=0,0,(IF(AND($K$14>0,MOD(H$41-1-$I$35,$H$35)=0),$K$14*$H$35+IF(OR($D$14="No",AND($E$14="Sí",$F$14>=2)),0,$C$14),0)+IF(AND($L$14>0,MOD(H$41-1-$I$36,$H$36)=0),$L$14*$H$36+IF(OR($D$14="No"),0,$C$14),0)+IF(AND($M$14>0,MOD(H$41-1-$I$37,$H$37)=0),$M$14*$H$37+IF(OR($D$14="No"),0,$C$14),0)+IF(AND($N$14>0,MOD(H$41-1-$I$38,$H$38)=0),$N$14*$H$38+IF(OR($D$14="No"),0,$C$14),0))/$H$14) -> 0.76525818 | I53: =IF($H$14=0,0,(IF(AND($K$14>0,MOD(I$41-1-$I$35,$H$35)=0),$K$14*$H$35+IF(OR($D$14="No",AND($E$14="Sí",$F$14>=2)),0,$C$14),0)+IF(AND($L$14>0,MOD(I$41-1-$I$36,$H$36)=0),$L$14*$H$36+IF(OR($D$14="No"),0,$C$14),0)+IF(AND($M$14>0,MOD(I$41-1-$I$37,$H$37)=0),$M$14*$H$37+IF(OR($D$14="No"),0,$C$14),0)+IF(AND($N$14>0,MOD(I$41-1-$I$38,$H$38)=0),$N$14*$H$38+IF(OR($D$14="No"),0,$C$14),0))/$H$14) -> 0.73483242 | J53: =IF($H$14=0,0,(IF(AND($K$14>0,MOD(J$41-1-$I$35,$H$35)=0),$K$14*$H$35+IF(OR($D$14="No",AND($E$14="Sí",$F$14>=2)),0,$C$14),0)+IF(AND($L$14>0,MOD(J$41-1-$I$36,$H$36)=0),$L$14*$H$36+IF(OR($D$14="No"),0,$C$14),0)+IF(AND($M$14>0,MOD(J$41-1-$I$37,$H$37)=0),$M$14*$H$37+IF(OR($D$14="No"),0,$C$14),0)+IF(AND($N$14>0,MOD(J$41-1-$I$38,$H$38)=0),$N$14*$H$38+IF(OR($D$14="No"),0,$C$14),0))/$H$14) -> 0.76525818 | ... V53: =IF($H$14=0,0,(IF(AND($K$14>0,MOD(V$41-1-$I$35,$H$35)=0),$K$14*$H$35+IF(OR($D$14="No",AND($E$14="Sí",$F$14>=2)),0,$C$14),0)+IF(AND($L$14>0,MOD(V$41-1-$I$36,$H$36)=0),$L$14*$H$36+IF(OR($D$14="No"),0,$C$14),0)+IF(AND($M$14>0,MOD(V$41-1-$I$37,$H$37)=0),$M$14*$H$37+IF(OR($D$14="No"),0,$C$14),0)+IF(AND($N$14>0,MOD(V$41-1-$I$38,$H$38)=0),$N$14*$H$38+IF(OR($D$14="No"),0,$C$14),0))/$H$14) -> 0.76525818
B54: =Carga!B40 -> Soldadura del cuello a la cúpula | C54: =IF(AND($K$10>0,MOD(C$41-1-$I$35,$H$35)=0),"1 ","")&IF(AND($L$10>0,MOD(C$41-1-$I$36,$H$36)=0),"2,5 ","")&IF(AND($M$10>0,MOD(C$41-1-$I$37,$H$37)=0),"5 ","")&IF(AND($N$10>0,MOD(C$41-1-$I$38,$H$38)=0),"10 ","") -> 1 2,5 5 | D54: =IF(AND($K$10>0,MOD(D$41-1-$I$35,$H$35)=0),"1 ","")&IF(AND($L$10>0,MOD(D$41-1-$I$36,$H$36)=0),"2,5 ","")&IF(AND($M$10>0,MOD(D$41-1-$I$37,$H$37)=0),"5 ","")&IF(AND($N$10>0,MOD(D$41-1-$I$38,$H$38)=0),"10 ","") -> 1 2,5 5 10 | E54: =IF(AND($K$10>0,MOD(E$41-1-$I$35,$H$35)=0),"1 ","")&IF(AND($L$10>0,MOD(E$41-1-$I$36,$H$36)=0),"2,5 ","")&IF(AND($M$10>0,MOD(E$41-1-$I$37,$H$37)=0),"5 ","")&IF(AND($N$10>0,MOD(E$41-1-$I$38,$H$38)=0),"10 ","") -> 1 2,5 5 | F54: =IF(AND($K$10>0,MOD(F$41-1-$I$35,$H$35)=0),"1 ","")&IF(AND($L$10>0,MOD(F$41-1-$I$36,$H$36)=0),"2,5 ","")&IF(AND($M$10>0,MOD(F$41-1-$I$37,$H$37)=0),"5 ","")&IF(AND($N$10>0,MOD(F$41-1-$I$38,$H$38)=0),"10 ","") -> 1 2,5 5 10 | G54: =IF(AND($K$10>0,MOD(G$41-1-$I$35,$H$35)=0),"1 ","")&IF(AND($L$10>0,MOD(G$41-1-$I$36,$H$36)=0),"2,5 ","")&IF(AND($M$10>0,MOD(G$41-1-$I$37,$H$37)=0),"5 ","")&IF(AND($N$10>0,MOD(G$41-1-$I$38,$H$38)=0),"10 ","") -> 1 2,5 5 | H54: =IF(AND($K$10>0,MOD(H$41-1-$I$35,$H$35)=0),"1 ","")&IF(AND($L$10>0,MOD(H$41-1-$I$36,$H$36)=0),"2,5 ","")&IF(AND($M$10>0,MOD(H$41-1-$I$37,$H$37)=0),"5 ","")&IF(AND($N$10>0,MOD(H$41-1-$I$38,$H$38)=0),"10 ","") -> 1 2,5 5 10 | I54: =IF(AND($K$10>0,MOD(I$41-1-$I$35,$H$35)=0),"1 ","")&IF(AND($L$10>0,MOD(I$41-1-$I$36,$H$36)=0),"2,5 ","")&IF(AND($M$10>0,MOD(I$41-1-$I$37,$H$37)=0),"5 ","")&IF(AND($N$10>0,MOD(I$41-1-$I$38,$H$38)=0),"10 ","") -> 1 2,5 5 | J54: =IF(AND($K$10>0,MOD(J$41-1-$I$35,$H$35)=0),"1 ","")&IF(AND($L$10>0,MOD(J$41-1-$I$36,$H$36)=0),"2,5 ","")&IF(AND($M$10>0,MOD(J$41-1-$I$37,$H$37)=0),"5 ","")&IF(AND($N$10>0,MOD(J$41-1-$I$38,$H$38)=0),"10 ","") -> 1 2,5 5 10 | ... V54: =IF(AND($K$10>0,MOD(V$41-1-$I$35,$H$35)=0),"1 ","")&IF(AND($L$10>0,MOD(V$41-1-$I$36,$H$36)=0),"2,5 ","")&IF(AND($M$10>0,MOD(V$41-1-$I$37,$H$37)=0),"5 ","")&IF(AND($N$10>0,MOD(V$41-1-$I$38,$H$38)=0),"10 ","") -> 1 2,5 5 10
B55: carga | C55: =IF($H$10=0,0,(IF(AND($K$10>0,MOD(C$41-1-$I$35,$H$35)=0),$K$10*$H$35+IF(OR($D$10="No",AND($E$10="Sí",$F$10>=2)),0,$C$10),0)+IF(AND($L$10>0,MOD(C$41-1-$I$36,$H$36)=0),$L$10*$H$36+IF(OR($D$10="No"),0,$C$10),0)+IF(AND($M$10>0,MOD(C$41-1-$I$37,$H$37)=0),$M$10*$H$37+IF(OR($D$10="No"),0,$C$10),0)+IF(AND($N$10>0,MOD(C$41-1-$I$38,$H$38)=0),$N$10*$H$38+IF(OR($D$10="No"),0,$C$10),0))/$H$10) -> 0.63458258 | D55: =IF($H$10=0,0,(IF(AND($K$10>0,MOD(D$41-1-$I$35,$H$35)=0),$K$10*$H$35+IF(OR($D$10="No",AND($E$10="Sí",$F$10>=2)),0,$C$10),0)+IF(AND($L$10>0,MOD(D$41-1-$I$36,$H$36)=0),$L$10*$H$36+IF(OR($D$10="No"),0,$C$10),0)+IF(AND($M$10>0,MOD(D$41-1-$I$37,$H$37)=0),$M$10*$H$37+IF(OR($D$10="No"),0,$C$10),0)+IF(AND($N$10>0,MOD(D$41-1-$I$38,$H$38)=0),$N$10*$H$38+IF(OR($D$10="No"),0,$C$10),0))/$H$10) -> 0.66734478 | E55: =IF($H$10=0,0,(IF(AND($K$10>0,MOD(E$41-1-$I$35,$H$35)=0),$K$10*$H$35+IF(OR($D$10="No",AND($E$10="Sí",$F$10>=2)),0,$C$10),0)+IF(AND($L$10>0,MOD(E$41-1-$I$36,$H$36)=0),$L$10*$H$36+IF(OR($D$10="No"),0,$C$10),0)+IF(AND($M$10>0,MOD(E$41-1-$I$37,$H$37)=0),$M$10*$H$37+IF(OR($D$10="No"),0,$C$10),0)+IF(AND($N$10>0,MOD(E$41-1-$I$38,$H$38)=0),$N$10*$H$38+IF(OR($D$10="No"),0,$C$10),0))/$H$10) -> 0.63458258 | F55: =IF($H$10=0,0,(IF(AND($K$10>0,MOD(F$41-1-$I$35,$H$35)=0),$K$10*$H$35+IF(OR($D$10="No",AND($E$10="Sí",$F$10>=2)),0,$C$10),0)+IF(AND($L$10>0,MOD(F$41-1-$I$36,$H$36)=0),$L$10*$H$36+IF(OR($D$10="No"),0,$C$10),0)+IF(AND($M$10>0,MOD(F$41-1-$I$37,$H$37)=0),$M$10*$H$37+IF(OR($D$10="No"),0,$C$10),0)+IF(AND($N$10>0,MOD(F$41-1-$I$38,$H$38)=0),$N$10*$H$38+IF(OR($D$10="No"),0,$C$10),0))/$H$10) -> 0.66734478 | G55: =IF($H$10=0,0,(IF(AND($K$10>0,MOD(G$41-1-$I$35,$H$35)=0),$K$10*$H$35+IF(OR($D$10="No",AND($E$10="Sí",$F$10>=2)),0,$C$10),0)+IF(AND($L$10>0,MOD(G$41-1-$I$36,$H$36)=0),$L$10*$H$36+IF(OR($D$10="No"),0,$C$10),0)+IF(AND($M$10>0,MOD(G$41-1-$I$37,$H$37)=0),$M$10*$H$37+IF(OR($D$10="No"),0,$C$10),0)+IF(AND($N$10>0,MOD(G$41-1-$I$38,$H$38)=0),$N$10*$H$38+IF(OR($D$10="No"),0,$C$10),0))/$H$10) -> 0.63458258 | H55: =IF($H$10=0,0,(IF(AND($K$10>0,MOD(H$41-1-$I$35,$H$35)=0),$K$10*$H$35+IF(OR($D$10="No",AND($E$10="Sí",$F$10>=2)),0,$C$10),0)+IF(AND($L$10>0,MOD(H$41-1-$I$36,$H$36)=0),$L$10*$H$36+IF(OR($D$10="No"),0,$C$10),0)+IF(AND($M$10>0,MOD(H$41-1-$I$37,$H$37)=0),$M$10*$H$37+IF(OR($D$10="No"),0,$C$10),0)+IF(AND($N$10>0,MOD(H$41-1-$I$38,$H$38)=0),$N$10*$H$38+IF(OR($D$10="No"),0,$C$10),0))/$H$10) -> 0.66734478 | I55: =IF($H$10=0,0,(IF(AND($K$10>0,MOD(I$41-1-$I$35,$H$35)=0),$K$10*$H$35+IF(OR($D$10="No",AND($E$10="Sí",$F$10>=2)),0,$C$10),0)+IF(AND($L$10>0,MOD(I$41-1-$I$36,$H$36)=0),$L$10*$H$36+IF(OR($D$10="No"),0,$C$10),0)+IF(AND($M$10>0,MOD(I$41-1-$I$37,$H$37)=0),$M$10*$H$37+IF(OR($D$10="No"),0,$C$10),0)+IF(AND($N$10>0,MOD(I$41-1-$I$38,$H$38)=0),$N$10*$H$38+IF(OR($D$10="No"),0,$C$10),0))/$H$10) -> 0.63458258 | J55: =IF($H$10=0,0,(IF(AND($K$10>0,MOD(J$41-1-$I$35,$H$35)=0),$K$10*$H$35+IF(OR($D$10="No",AND($E$10="Sí",$F$10>=2)),0,$C$10),0)+IF(AND($L$10>0,MOD(J$41-1-$I$36,$H$36)=0),$L$10*$H$36+IF(OR($D$10="No"),0,$C$10),0)+IF(AND($M$10>0,MOD(J$41-1-$I$37,$H$37)=0),$M$10*$H$37+IF(OR($D$10="No"),0,$C$10),0)+IF(AND($N$10>0,MOD(J$41-1-$I$38,$H$38)=0),$N$10*$H$38+IF(OR($D$10="No"),0,$C$10),0))/$H$10) -> 0.66734478 | ... V55: =IF($H$10=0,0,(IF(AND($K$10>0,MOD(V$41-1-$I$35,$H$35)=0),$K$10*$H$35+IF(OR($D$10="No",AND($E$10="Sí",$F$10>=2)),0,$C$10),0)+IF(AND($L$10>0,MOD(V$41-1-$I$36,$H$36)=0),$L$10*$H$36+IF(OR($D$10="No"),0,$C$10),0)+IF(AND($M$10>0,MOD(V$41-1-$I$37,$H$37)=0),$M$10*$H$37+IF(OR($D$10="No"),0,$C$10),0)+IF(AND($N$10>0,MOD(V$41-1-$I$38,$H$38)=0),$N$10*$H$38+IF(OR($D$10="No"),0,$C$10),0))/$H$10) -> 0.66734478
B56: =Carga!B46 -> Soldadura circunferencial de cúpula y fondo | C56: =IF(AND($K$16>0,MOD(C$41-1-$I$35,$H$35)=0),"1 ","")&IF(AND($L$16>0,MOD(C$41-1-$I$36,$H$36)=0),"2,5 ","")&IF(AND($M$16>0,MOD(C$41-1-$I$37,$H$37)=0),"5 ","")&IF(AND($N$16>0,MOD(C$41-1-$I$38,$H$38)=0),"10 ","") -> 1 2,5 5 | D56: =IF(AND($K$16>0,MOD(D$41-1-$I$35,$H$35)=0),"1 ","")&IF(AND($L$16>0,MOD(D$41-1-$I$36,$H$36)=0),"2,5 ","")&IF(AND($M$16>0,MOD(D$41-1-$I$37,$H$37)=0),"5 ","")&IF(AND($N$16>0,MOD(D$41-1-$I$38,$H$38)=0),"10 ","") -> 1 2,5 5 10 | E56: =IF(AND($K$16>0,MOD(E$41-1-$I$35,$H$35)=0),"1 ","")&IF(AND($L$16>0,MOD(E$41-1-$I$36,$H$36)=0),"2,5 ","")&IF(AND($M$16>0,MOD(E$41-1-$I$37,$H$37)=0),"5 ","")&IF(AND($N$16>0,MOD(E$41-1-$I$38,$H$38)=0),"10 ","") -> 1 2,5 5 | F56: =IF(AND($K$16>0,MOD(F$41-1-$I$35,$H$35)=0),"1 ","")&IF(AND($L$16>0,MOD(F$41-1-$I$36,$H$36)=0),"2,5 ","")&IF(AND($M$16>0,MOD(F$41-1-$I$37,$H$37)=0),"5 ","")&IF(AND($N$16>0,MOD(F$41-1-$I$38,$H$38)=0),"10 ","") -> 1 2,5 5 10 | G56: =IF(AND($K$16>0,MOD(G$41-1-$I$35,$H$35)=0),"1 ","")&IF(AND($L$16>0,MOD(G$41-1-$I$36,$H$36)=0),"2,5 ","")&IF(AND($M$16>0,MOD(G$41-1-$I$37,$H$37)=0),"5 ","")&IF(AND($N$16>0,MOD(G$41-1-$I$38,$H$38)=0),"10 ","") -> 1 2,5 5 | H56: =IF(AND($K$16>0,MOD(H$41-1-$I$35,$H$35)=0),"1 ","")&IF(AND($L$16>0,MOD(H$41-1-$I$36,$H$36)=0),"2,5 ","")&IF(AND($M$16>0,MOD(H$41-1-$I$37,$H$37)=0),"5 ","")&IF(AND($N$16>0,MOD(H$41-1-$I$38,$H$38)=0),"10 ","") -> 1 2,5 5 10 | I56: =IF(AND($K$16>0,MOD(I$41-1-$I$35,$H$35)=0),"1 ","")&IF(AND($L$16>0,MOD(I$41-1-$I$36,$H$36)=0),"2,5 ","")&IF(AND($M$16>0,MOD(I$41-1-$I$37,$H$37)=0),"5 ","")&IF(AND($N$16>0,MOD(I$41-1-$I$38,$H$38)=0),"10 ","") -> 1 2,5 5 | J56: =IF(AND($K$16>0,MOD(J$41-1-$I$35,$H$35)=0),"1 ","")&IF(AND($L$16>0,MOD(J$41-1-$I$36,$H$36)=0),"2,5 ","")&IF(AND($M$16>0,MOD(J$41-1-$I$37,$H$37)=0),"5 ","")&IF(AND($N$16>0,MOD(J$41-1-$I$38,$H$38)=0),"10 ","") -> 1 2,5 5 10 | ... V56: =IF(AND($K$16>0,MOD(V$41-1-$I$35,$H$35)=0),"1 ","")&IF(AND($L$16>0,MOD(V$41-1-$I$36,$H$36)=0),"2,5 ","")&IF(AND($M$16>0,MOD(V$41-1-$I$37,$H$37)=0),"5 ","")&IF(AND($N$16>0,MOD(V$41-1-$I$38,$H$38)=0),"10 ","") -> 1 2,5 5 10
B57: carga | C57: =IF($H$16=0,0,(IF(AND($K$16>0,MOD(C$41-1-$I$35,$H$35)=0),$K$16*$H$35+IF(OR($D$16="No",AND($E$16="Sí",$F$16>=2)),0,$C$16),0)+IF(AND($L$16>0,MOD(C$41-1-$I$36,$H$36)=0),$L$16*$H$36+IF(OR($D$16="No"),0,$C$16),0)+IF(AND($M$16>0,MOD(C$41-1-$I$37,$H$37)=0),$M$16*$H$37+IF(OR($D$16="No"),0,$C$16),0)+IF(AND($N$16>0,MOD(C$41-1-$I$38,$H$38)=0),$N$16*$H$38+IF(OR($D$16="No"),0,$C$16),0))/$H$16) -> 0.71816576 | D57: =IF($H$16=0,0,(IF(AND($K$16>0,MOD(D$41-1-$I$35,$H$35)=0),$K$16*$H$35+IF(OR($D$16="No",AND($E$16="Sí",$F$16>=2)),0,$C$16),0)+IF(AND($L$16>0,MOD(D$41-1-$I$36,$H$36)=0),$L$16*$H$36+IF(OR($D$16="No"),0,$C$16),0)+IF(AND($M$16>0,MOD(D$41-1-$I$37,$H$37)=0),$M$16*$H$37+IF(OR($D$16="No"),0,$C$16),0)+IF(AND($N$16>0,MOD(D$41-1-$I$38,$H$38)=0),$N$16*$H$38+IF(OR($D$16="No"),0,$C$16),0))/$H$16) -> 0.74303595 | E57: =IF($H$16=0,0,(IF(AND($K$16>0,MOD(E$41-1-$I$35,$H$35)=0),$K$16*$H$35+IF(OR($D$16="No",AND($E$16="Sí",$F$16>=2)),0,$C$16),0)+IF(AND($L$16>0,MOD(E$41-1-$I$36,$H$36)=0),$L$16*$H$36+IF(OR($D$16="No"),0,$C$16),0)+IF(AND($M$16>0,MOD(E$41-1-$I$37,$H$37)=0),$M$16*$H$37+IF(OR($D$16="No"),0,$C$16),0)+IF(AND($N$16>0,MOD(E$41-1-$I$38,$H$38)=0),$N$16*$H$38+IF(OR($D$16="No"),0,$C$16),0))/$H$16) -> 0.71816576 | F57: =IF($H$16=0,0,(IF(AND($K$16>0,MOD(F$41-1-$I$35,$H$35)=0),$K$16*$H$35+IF(OR($D$16="No",AND($E$16="Sí",$F$16>=2)),0,$C$16),0)+IF(AND($L$16>0,MOD(F$41-1-$I$36,$H$36)=0),$L$16*$H$36+IF(OR($D$16="No"),0,$C$16),0)+IF(AND($M$16>0,MOD(F$41-1-$I$37,$H$37)=0),$M$16*$H$37+IF(OR($D$16="No"),0,$C$16),0)+IF(AND($N$16>0,MOD(F$41-1-$I$38,$H$38)=0),$N$16*$H$38+IF(OR($D$16="No"),0,$C$16),0))/$H$16) -> 0.74303595 | G57: =IF($H$16=0,0,(IF(AND($K$16>0,MOD(G$41-1-$I$35,$H$35)=0),$K$16*$H$35+IF(OR($D$16="No",AND($E$16="Sí",$F$16>=2)),0,$C$16),0)+IF(AND($L$16>0,MOD(G$41-1-$I$36,$H$36)=0),$L$16*$H$36+IF(OR($D$16="No"),0,$C$16),0)+IF(AND($M$16>0,MOD(G$41-1-$I$37,$H$37)=0),$M$16*$H$37+IF(OR($D$16="No"),0,$C$16),0)+IF(AND($N$16>0,MOD(G$41-1-$I$38,$H$38)=0),$N$16*$H$38+IF(OR($D$16="No"),0,$C$16),0))/$H$16) -> 0.71816576 | H57: =IF($H$16=0,0,(IF(AND($K$16>0,MOD(H$41-1-$I$35,$H$35)=0),$K$16*$H$35+IF(OR($D$16="No",AND($E$16="Sí",$F$16>=2)),0,$C$16),0)+IF(AND($L$16>0,MOD(H$41-1-$I$36,$H$36)=0),$L$16*$H$36+IF(OR($D$16="No"),0,$C$16),0)+IF(AND($M$16>0,MOD(H$41-1-$I$37,$H$37)=0),$M$16*$H$37+IF(OR($D$16="No"),0,$C$16),0)+IF(AND($N$16>0,MOD(H$41-1-$I$38,$H$38)=0),$N$16*$H$38+IF(OR($D$16="No"),0,$C$16),0))/$H$16) -> 0.74303595 | I57: =IF($H$16=0,0,(IF(AND($K$16>0,MOD(I$41-1-$I$35,$H$35)=0),$K$16*$H$35+IF(OR($D$16="No",AND($E$16="Sí",$F$16>=2)),0,$C$16),0)+IF(AND($L$16>0,MOD(I$41-1-$I$36,$H$36)=0),$L$16*$H$36+IF(OR($D$16="No"),0,$C$16),0)+IF(AND($M$16>0,MOD(I$41-1-$I$37,$H$37)=0),$M$16*$H$37+IF(OR($D$16="No"),0,$C$16),0)+IF(AND($N$16>0,MOD(I$41-1-$I$38,$H$38)=0),$N$16*$H$38+IF(OR($D$16="No"),0,$C$16),0))/$H$16) -> 0.71816576 | J57: =IF($H$16=0,0,(IF(AND($K$16>0,MOD(J$41-1-$I$35,$H$35)=0),$K$16*$H$35+IF(OR($D$16="No",AND($E$16="Sí",$F$16>=2)),0,$C$16),0)+IF(AND($L$16>0,MOD(J$41-1-$I$36,$H$36)=0),$L$16*$H$36+IF(OR($D$16="No"),0,$C$16),0)+IF(AND($M$16>0,MOD(J$41-1-$I$37,$H$37)=0),$M$16*$H$37+IF(OR($D$16="No"),0,$C$16),0)+IF(AND($N$16>0,MOD(J$41-1-$I$38,$H$38)=0),$N$16*$H$38+IF(OR($D$16="No"),0,$C$16),0))/$H$16) -> 0.74303595 | ... V57: =IF($H$16=0,0,(IF(AND($K$16>0,MOD(V$41-1-$I$35,$H$35)=0),$K$16*$H$35+IF(OR($D$16="No",AND($E$16="Sí",$F$16>=2)),0,$C$16),0)+IF(AND($L$16>0,MOD(V$41-1-$I$36,$H$36)=0),$L$16*$H$36+IF(OR($D$16="No"),0,$C$16),0)+IF(AND($M$16>0,MOD(V$41-1-$I$37,$H$37)=0),$M$16*$H$37+IF(OR($D$16="No"),0,$C$16),0)+IF(AND($N$16>0,MOD(V$41-1-$I$38,$H$38)=0),$N$16*$H$38+IF(OR($D$16="No"),0,$C$16),0))/$H$16) -> 0.74303595
