Workbook

Sheet Resumen
A1: MATERIA PRIMA 2035 — cómo se pide, cuánto se guarda y cómo se dispone en el almacén
A2: Paquetes y rollos atados al balanceo limpio (Balanceo2035.xlsx), stock de las 125 MP con el pico de producción y almacén dimensionado con la estantería que menos lugar ocupa.
A3: ▶ Una hoja por paso: Chapa_fleje → Stock_MP → Almacenes → Pedidos → Equipos. Datos = valores pegados.
A5: 1) LO PRINCIPAL
A6: Concepto | B6: Antes (v10) | C6: Ahora | D6: Hoja
A7: Superficie del almacén de MP (m²) | B7: =Datos!D47 -> 207.49 | C7: =Almacenes!G33 -> 221.7636 | D7: Almacenes
A8: Chapa y flejes (m²) | B8: =Almacenes!H19 -> 101.16 | C8: =Almacenes!G19+Almacenes!G20 -> 117.6236 | D8: Chapa_fleje 2 y 5
A9: Chapa: pilas | B9: — | C9: =Chapa_fleje!K24 -> 7 | D9: Chapa_fleje 2
A10: Chapa: alto máximo de una pila (m) | B10: 1.2 | C10: =MAX(Chapa_fleje!M18:M23) -> 2.4969 | D10: Chapa_fleje 2
A11: Flejes: rack + estación de volteo (m²) | B11: — | C11: =Chapa_fleje!G72 -> 25.56 | D11: Chapa_fleje 5
A12: Flejes: módulos de rack | B12: 3 cunas | C12: =Chapa_fleje!G68 -> 2 | D12: Chapa_fleje 5
A13: Apilador con pinza («volteador») | B13: — | C13: =Chapa_fleje!L52 -> Tymbia M103070075 en apilador eléctrico de 2,5 t | D13: Chapa_fleje 4
A14: Equipos de almacén, con IVA | B14: 20477058 | C14: =Equipos!G32 -> 21644111 | D14: Equipos
A15: Pedidos por año (todos los proveedores) | B15: — | C15: =Pedidos!D45 -> 596 | D15: Pedidos
A16: MP al pie de los puestos (m², sin cambios) | B16: 35.5 | C16: =Datos!D48 -> 35.5 | D16: Datos
A17: Antes = Balanceo_Sincronizado v10 y Almacenamiento_MP (almacén + fabricación propia + demarcación, con cunas; sin los equipos de la línea).
A19: 2) PAQUETE Y ROLLO DE CADA FORMATO (= una tanda del balanceo)
A20: Material | B20: Bulto (hojas o kg) | C20: Se pide cada (días) | D20: Stock máximo (bultos)
A21: =Chapa_fleje!A7&" · "&Chapa_fleje!B7 -> MP-01 · Hoja LAF 0,9 × 1220 × 2440 mm (cuerpo 1 kg) | B21: ="Paquete de "&Chapa_fleje!L7&" hojas ("&TEXT(Chapa_fleje!M7,"#,##0")&" kg)" -> Paquete de 21 hojas (442 kg) | C21: =Chapa_fleje!T7 -> 20 | D21: =Chapa_fleje!V7 -> 21
A22: =Chapa_fleje!A8&" · "&Chapa_fleje!B8 -> MP-02 · Hoja LAF 1,25 × 1220 × 2440 mm | B22: ="Paquete de "&Chapa_fleje!L8&" hojas ("&TEXT(Chapa_fleje!M8,"#,##0")&" kg)" -> Paquete de 19 hojas (555 kg) | C22: =Chapa_fleje!T8 -> 20 | D22: =Chapa_fleje!V8 -> 4
A23: =Chapa_fleje!A9&" · "&Chapa_fleje!B9 -> MP-03 · Hoja LAF 1,6 × 1000 × 2000 mm | B23: ="Paquete de "&Chapa_fleje!L9&" hojas ("&TEXT(Chapa_fleje!M9,"#,##0")&" kg)" -> Paquete de 24 hojas (603 kg) | C23: =Chapa_fleje!T9 -> 20 | D23: =Chapa_fleje!V9 -> 23
A24: =Chapa_fleje!A10&" · "&Chapa_fleje!B10 -> MP-04 · Hoja LAF 2,0 × 1500 × 3000 mm | B24: ="Paquete de "&Chapa_fleje!L10&" hojas ("&TEXT(Chapa_fleje!M10,"#,##0")&" kg)" -> Paquete de 19 hojas (1,342 kg) | C24: =Chapa_fleje!T10 -> 20 | D24: =Chapa_fleje!V10 -> 3
A25: =Chapa_fleje!A11&" · "&Chapa_fleje!B11 -> MP-11 · Hoja LAC 3,2 × 1500 × 3000 mm | B25: ="Paquete de "&Chapa_fleje!L11&" hojas ("&TEXT(Chapa_fleje!M11,"#,##0")&" kg)" -> Paquete de 7 hojas (791 kg) | C25: =Chapa_fleje!T11 -> 20 | D25: =Chapa_fleje!V11 -> 6
A26: =Chapa_fleje!A12&" · "&Chapa_fleje!B12 -> MP-12 · Hoja LAC 4,75 × 1500 × 3000 mm | B26: ="Paquete de "&Chapa_fleje!L12&" hojas ("&TEXT(Chapa_fleje!M12,"#,##0")&" kg)" -> Paquete de 3 hojas (503 kg) | C26: =Chapa_fleje!T12 -> 20 | D26: =Chapa_fleje!V12 -> 6
A27: =Chapa_fleje!A34&" · "&Chapa_fleje!B34 -> MP-05 · Fleje LAF 0,9 × 93,05 mm (cúpula 1 kg) | B27: ="Rollo de "&TEXT(Chapa_fleje!M34,"#,##0")&" kg · Ø "&TEXT(Chapa_fleje!N34,"#,##0") -> Rollo de 218 kg · Ø 798 | C27: =Chapa_fleje!T34 -> 20 | D27: =Chapa_fleje!V34 -> 6
A28: =Chapa_fleje!A35&" · "&Chapa_fleje!B35 -> MP-13 · Fleje LAF 0,9 × 100,6 mm (fondo 1 kg) | B28: ="Rollo de "&TEXT(Chapa_fleje!M35,"#,##0")&" kg · Ø "&TEXT(Chapa_fleje!N35,"#,##0") -> Rollo de 252 kg · Ø 816 | C28: =Chapa_fleje!T35 -> 20 | D28: =Chapa_fleje!V35 -> 6
A29: =Chapa_fleje!A36&" · "&Chapa_fleje!B36 -> MP-06 · Fleje LAF 1,25 × 162,1 mm (cúpula 2,5 kg) | B29: ="Rollo de "&TEXT(Chapa_fleje!M36,"#,##0")&" kg · Ø "&TEXT(Chapa_fleje!N36,"#,##0") -> Rollo de 258 kg · Ø 718 | C29: =Chapa_fleje!T36 -> 10 | D29: =Chapa_fleje!V36 -> 2
A30: =Chapa_fleje!A37&" · "&Chapa_fleje!B37 -> MP-14 · Fleje LAF 1,25 × 146,1 mm (fondo 2,5 kg) | B30: ="Rollo de "&TEXT(Chapa_fleje!M37,"#,##0")&" kg · Ø "&TEXT(Chapa_fleje!N37,"#,##0") -> Rollo de 209 kg · Ø 700 | C30: =Chapa_fleje!T37 -> 10 | D30: =Chapa_fleje!V37 -> 2
A31: =Chapa_fleje!A38&" · "&Chapa_fleje!B38 -> MP-07 · Fleje LAF 1,6 × 204,2 mm (cúpula 5 kg) | B31: ="Rollo de "&TEXT(Chapa_fleje!M38,"#,##0")&" kg · Ø "&TEXT(Chapa_fleje!N38,"#,##0") -> Rollo de 1,181 kg · Ø 1,094 | C31: =Chapa_fleje!T38 -> 10 | D31: =Chapa_fleje!V38 -> 3
A32: =Chapa_fleje!A39&" · "&Chapa_fleje!B39 -> MP-08 · Fleje LAF 1,6 × 177,2 mm (fondo 5 kg) | B32: ="Rollo de "&TEXT(Chapa_fleje!M39,"#,##0")&" kg · Ø "&TEXT(Chapa_fleje!N39,"#,##0") -> Rollo de 886 kg · Ø 1,034 | C32: =Chapa_fleje!T39 -> 10 | D32: =Chapa_fleje!V39 -> 3
A33: =Chapa_fleje!A40&" · "&Chapa_fleje!B40 -> MP-09 · Fleje LAF 2,0 × 238,7 mm (cúpula 10 kg) | B33: ="Rollo de "&TEXT(Chapa_fleje!M40,"#,##0")&" kg · Ø "&TEXT(Chapa_fleje!N40,"#,##0") -> Rollo de 245 kg · Ø 652 | C33: =Chapa_fleje!T40 -> 10 | D33: =Chapa_fleje!V40 -> 2
A34: =Chapa_fleje!A41&" · "&Chapa_fleje!B41 -> MP-10 · Fleje LAF 2,0 × 205 mm (fondo 10 kg) | B34: ="Rollo de "&TEXT(Chapa_fleje!M41,"#,##0")&" kg · Ø "&TEXT(Chapa_fleje!N41,"#,##0") -> Rollo de 179 kg · Ø 632 | C34: =Chapa_fleje!T41 -> 10 | D34: =Chapa_fleje!V41 -> 2
A36: 3) CONTROLES
A37: Control | B37: Valor | C37: Estado | D37: Debe dar
A38: Paquetes que pasan la mesa elevadora o el autoelevador | B38: =COUNTIF(Chapa_fleje!X7:X12,"<>OK") -> 0 | C38: =IF(B38=0,"OK","Revisar") -> OK | D38: 0
A39: Pilas con más carga que el piso (t/m²) | B39: =MAX(Chapa_fleje!O18:O23) -> 3.61728 | C39: =IF(B39<=Q_PISO,"OK","Revisar") -> OK | D39: ≤ Q_PISO
A40: Pilas que pasan la altura del autoelevador (m) | B40: =MAX(Chapa_fleje!M18:M23) -> 2.4969 | C40: =IF(B40*1000<=H_ELEV,"OK","Revisar") -> OK | D40: ≤ H_ELEV
A41: Presión máxima en los tacos (MPa) | B41: =MAX(Chapa_fleje!P18:P23) -> 0.24859268 | C41: =IF(B41<=SIG_MAD,"OK","Revisar") -> OK | D41: ≤ SIG_MAD
A42: Rollos que pasan el desbobinador | B42: =COUNTIF(Chapa_fleje!X34:X41,"<>OK") -> 0 | C42: =IF(B42=0,"OK","Revisar") -> OK | D42: 0
A43: Lugares de rack de flejes que faltan | B43: =MAX(0,Chapa_fleje!K65-Chapa_fleje!G69) -> 0 | C43: =IF(B43=0,"OK","Revisar") -> OK | D43: 0
A44: Apilador con pinza que sirve | B44: =Chapa_fleje!L52 -> Tymbia M103070075 en apilador eléctrico de 2,5 t | C44: =IF(LEFT(B44,7)="Ninguno","Revisar","OK") -> OK | D44: un equipo
A46: 4) LO QUE ESTABA MAL EN LOS ARCHIVOS ANTERIORES
A47: 1. Stock_MP (v10) calculaba los lugares de chapa con las hojas por lugar del MRP viejo (136), no con el paquete de una tanda: daba 94,5 m².
A48: 2. Almacenamiento_MP ponía las pilas de chapa en 1,2 m sin mirar el autoelevador ni el piso, y los flejes en cunas (apoyados de canto se ovalan).
A49: 3. El Word de chapa decía que el almacén pasaba de 295 a 273 m² y que chapa tenía 26 lugares: no coincide con el Word de MP (272,8 → 207,5 m²).
A50: 4. Embutido (v10) decía que las cúpulas las toma el numerado: con el marcado unificado las toma la soldadura del cuello.
A51: 5. La calle de chapa de carros iba aparte: ahora sus paquetes van en la misma zona de pilas, con la misma calle.

Sheet Datos
A1: DATOS IMPORTADOS (valores pegados)
A2: Del balanceo limpio Balanceo2035.xlsx (hoja Lotes y Carga, enero 2035) y del MRP (FLAMA_MRP, POLITICA_STOCK, tal como estaba en Balanceo_Sincronizado_FLAMA_2035 v10, hoja Stock_MP). Si cambian, volver a pegar.
A3: ▶ Esta hoja no se lee: guarda los datos. Verde = dato.
A5: 1) GUILLOTINA — tandas del balanceo (Balanceo2035.xlsx, Lotes filas 8 a 14)
A6: Fila Lotes | B6: Formato | C6: Cuerpos por hoja | D6: Cuerpos por día | E6: Cada (días) | F6: Hojas por tanda
A7: 8 | B7: Manuales 1 kg | C7: 45 | D7: 911.79288 | E7: 1 | F7: 21
A8: 9 | B8: Manuales 2,5 kg | C8: 27 | D8: 63.568523 | E8: 8 | F8: 19
A9: 10 | B9: Manuales 5 kg | C9: 12 | D9: 287.33696 | E9: 1 | F9: 24
A10: 11 | B10: Manuales 10 kg | C10: 15 | D10: 17.383176 | E10: 16 | F10: 19
A11: 12 | B11: Carros 25 kg (hoja 3,2) | C11: 9 | D11: 3.3035698 | E11: 4 | F11: 2
A12: 13 | B12: Carros 50 kg (hoja 3,2) | C12: 6 | D12: 7.2608495 | E12: 4 | F12: 5
A13: 14 | B13: Carros 70 + 100 kg (hoja mixta 4,75) | C13: 4 | D13: 2.6416998 | E13: 4 | F13: 3
A15: 2) EMBUTIDORA — tandas del balanceo (Lotes filas 30 a 37)
A16: Fila Lotes | B16: Matriz | C16: Modelo | D16: Piezas por día | E16: Cada (días) | F16: Piezas por tanda | G16: Piezas del año
A17: 30 | B17: C1 | C17: 1 kg | D17: 911.79288 | E17: 4 | F17: 3647.1715 | G17: 202620.64
A18: 31 | B18: F1 | C18: 1 kg | D18: 911.79288 | E18: 4 | F18: 3647.1715 | G18: 202620.64
A19: 32 | B19: C2,5 | C19: 2,5 kg | D19: 63.568523 | E19: 16 | F19: 1017.0964 | G19: 14126.338
A20: 33 | B20: F2,5 | C20: 2,5 kg | D20: 63.568523 | E20: 16 | F20: 1017.0964 | G20: 14126.338
A21: 34 | B21: C5 | C21: 5 kg | D21: 287.33696 | E21: 8 | F21: 2298.6957 | G21: 63852.659
A22: 35 | B22: F5 | C22: 5 kg | D22: 287.33696 | E22: 8 | F22: 2298.6957 | G22: 63852.659
A23: 36 | B23: C10 | C23: 10 kg | D23: 17.383176 | E23: 16 | F23: 278.13082 | G23: 3862.928
A24: 37 | B24: F10 | C24: 10 kg | D24: 17.383176 | E24: 16 | F24: 278.13082 | G24: 3862.928
A25: Piezas del año = recipientes del año de cada modelo (Balanceo2035, Carga B14:B17).
A27: 3) PRODUCCIÓN DE CADA MES (Balanceo2035, Carga filas 8 a 10) — para el factor de pico
A28: Línea | B28: Ene | C28: Feb | D28: Mar | E28: Abr | F28: May | G28: Jun | H28: Jul | I28: Ago | J28: Sep | K28: Oct | L28: Nov | M28: Dic
A29: Manuales | B29: 25601.631 | C29: 24783.212 | D29: 23166.215 | E29: 22153.112 | F29: 20730.799 | G29: 20321.589 | H29: 21743.902 | I29: 24783.212 | J29: 24783.212 | K29: 25192.421 | L29: 25601.631 | M29: 25601.631
A30: Carros | B30: 264.12238 | C30: 233.04916 | D30: 279.65899 | E30: 279.65899 | F30: 279.65899 | G30: 248.58577 | H30: 279.65899 | I30: 279.65899 | J30: 264.12238 | K30: 233.04916 | L30: 217.51255 | M30: 248.58577
A31: Recargas | B31: 10822.075 | C31: 9391.2625 | D31: 8906.0301 | E31: 9801.73 | F31: 9879.3585 | G31: 9758.7033 | H31: 8689.6915 | I31: 8770.0961 | J31: 8876.5519 | K31: 8876.5519 | L31: 10229.736 | M31: 11781.204
A33: 4) ALMACÉN DE MP ANTES DE ESTE ANÁLISIS (Balanceo_Sincronizado v10, Stock_MP sección 1)
A34: Almacén | C34: Lugares | D34: m²
A35: Calle de chapa (carros) | C35: 2 | D35: 6.66
A36: Cantilever de caños y barras | C36: 2 | D36: 4
A37: Chapa y fleje (manuales) | C37: 21 | D37: 94.5
A38: Depósito de polvo químico | C38: 8 | D38: 8
A39: Embalaje | C39: 27 | D39: 33.21
A40: Identificación | C40: 7 | D40: 3.5
A41: Insumos de montaje (manuales) | C41: 19 | D41: 23.37
A42: Insumos de recargas | C42: 7 | D42: 8.61
A43: Insumos de soldadura y superficie | C43: 5 | D43: 6.15
A44: Jaula de gases | C44: 7 | D44: 7
A45: Rack de casquetes y cuplas (carros) | C45: 9 | D45: 6.57
A46: Rack de insumos de montaje (carros) | C46: 8 | D46: 5.92
A47: Total almacén de MP (v10) | C47: =SUM(C35:C46) -> 122 | D47: =SUM(D35:D46) -> 207.49
A48: MP al pie de los puestos (v10, MP_en_linea): no cambia en este análisis | D48: 35.5
A50: 5) MRP POR MATERIAL (FLAMA_MRP, POLITICA_STOCK; unidad y frecuencia revisadas en el Word de MP)
A51: Ref. | B51: Material | C51: Código | D51: Proveedor | E51: Consumo del año | F51: UM | G51: Plazo mín. | H51: Plazo máx. | I51: Unidad de compra | J51: Contenido | K51: Cada (días) | L51: Almacén (v10) | M51: Cuánto entra en un lugar | N51: Línea | O51: Origen del formato | P51: Pico reventa (u/día)
A52: P01 | B52: Hoja LAF 0,9 × 1220 × 2440 mm (cuerpo 1 kg) | C52: MP-01 | D52: Hierros Parrotta | E52: 4502.681 | F52: hoja | G52: 10 | H52: 10 | I52: Paquete de 21 hojas (1 tanda) | J52: 21 | K52: 20 | L52: Chapa y fleje (manuales) | M52: 136 | N52: Manuales | O52: Unidad óptima (hoja Compra_MP): paquete = 1 tanda de corte. Consumo pico = producción con sobrestock (no ventas). Antes: Paquete de 50 hojas
A53: P02 | B53: Hoja LAF 1,25 × 1220 × 2440 mm | C53: MP-02 | D53: Pradecon | E53: 523.198 | F53: hoja | G53: 7 | H53: 10 | I53: Paquete de 19 hojas (1 tanda) | J53: 19 | K53: 20 | L53: Chapa y fleje (manuales) | M53: 136 | N53: Manuales | O53: Unidad óptima (hoja Compra_MP): paquete = 1 tanda de corte. Consumo pico = producción con sobrestock (no ventas). Antes: Paquete de 50 hojas
A54: P03 | B54: Hoja LAF 1,6 × 1000 × 2000 mm | C54: MP-03 | D54: Pradecon | E54: 5321.055 | F54: hoja | G54: 7 | H54: 10 | I54: Paquete de 24 hojas (1 tanda) | J54: 24 | K54: 20 | L54: Chapa y fleje (manuales) | M54: 158 | N54: Manuales | O54: Unidad óptima (hoja Compra_MP): paquete = 1 tanda de corte. Consumo pico = producción con sobrestock (no ventas). Antes: Paquete de 80 hojas
A55: P04 | B55: Hoja LAF 2,0 × 1500 × 3000 mm | C55: MP-04 | D55: Pradecon | E55: 257.529 | F55: hoja | G55: 7 | H55: 10 | I55: Paquete de 19 hojas (1 tanda) | J55: 19 | K55: 20 | L55: Chapa y fleje (manuales) | M55: 56 | N55: Manuales | O55: Unidad óptima (hoja Compra_MP): paquete = 1 tanda de corte. Consumo pico = producción con sobrestock (no ventas). Antes: Paquete de 20 hojas
A56: P05 | B56: Fleje LAF 0,9 × 93,05 mm (cúpula 1 kg) | C56: MP-05 | D56: Pradecon | E56: 12095.318 | F56: kg | G56: 7 | H56: 10 | I56: Rollo de 218 kg (1 tanda) | J56: 217.716 | K56: 20 | L56: Chapa y fleje (manuales) | M56: 1000 | N56: Manuales | O56: Unidad óptima (hoja Compra_MP): rollo = 1 tanda de la matriz. Consumo pico = producción con sobrestock (no ventas). Antes: Rollo de 1.900 kg
A57: P06 | B57: Fleje LAF 0,9 × 100,6 mm (fondo 1 kg) | C57: MP-13 | D57: Pradecon | E57: 14024.6 | F57: kg | G57: 7 | H57: 10 | I57: Rollo de 252 kg (1 tanda) | J57: 252.443 | K57: 20 | L57: Chapa y fleje (manuales) | M57: 1000 | N57: Manuales | O57: DECISIÓN DEL GRUPO: fondo del 1 kg pasa de 1,25 a 0,9 mm (mismo espesor que la cúpula). Consumo del año = MRP × 0.72 (el disco tiene el mismo diámetro; el peso del fleje cambia con el espesor). Hay que actualizar BOM, MRP y plano. Unidad óptima (hoja Compra_MP): rollo = 1 tanda de la matriz. Consumo pico = producción con sobrestock (no ventas). Antes: Rollo de 1.900 kg
A58: P07 | B58: Fleje LAF 1,25 × 162,1 mm (cúpula 2,5 kg) | C58: MP-06 | D58: Pacheco Chapas | E58: 3577.032 | F58: kg | G58: 7 | H58: 10 | I58: Rollo de 258 kg (1 tanda) | J58: 257.546 | K58: 10 | L58: Chapa y fleje (manuales) | M58: 492 | N58: Manuales | O58: Unidad óptima (hoja Compra_MP): rollo = 1 tanda de la matriz. Consumo pico = producción con sobrestock (no ventas). Antes: Rollo de 492 kg
A59: P08 | B59: Fleje LAF 1,25 × 146,1 mm (fondo 2,5 kg) | C59: MP-14 | D59: Pacheco Chapas | E59: 2898.307 | F59: kg | G59: 7 | H59: 10 | I59: Rollo de 209 kg (1 tanda) | J59: 208.678 | K59: 10 | L59: Chapa y fleje (manuales) | M59: 492 | N59: Manuales | O59: Unidad óptima (hoja Compra_MP): rollo = 1 tanda de la matriz. Consumo pico = producción con sobrestock (no ventas). Antes: Rollo de 492 kg
A60: P09 | B60: Fleje LAF 1,6 × 204,2 mm (cúpula 5 kg) | C60: MP-07 | D60: Pacheco Chapas | E60: 32819.082 | F60: kg | G60: 7 | H60: 10 | I60: Rollo de 1181 kg (1 tanda) | J60: 1181.487 | K60: 10 | L60: Chapa y fleje (manuales) | M60: 615 | N60: Manuales | O60: Unidad óptima (hoja Compra_MP): rollo = 1 tanda de la matriz. Consumo pico = producción con sobrestock (no ventas). Antes: Rollo de 615 kg
A61: P10 | B61: Fleje LAF 1,6 × 177,2 mm (fondo 5 kg) | C61: MP-08 | D61: Pacheco Chapas | E61: 24623.315 | F61: kg | G61: 7 | H61: 10 | I61: Rollo de 886 kg (1 tanda) | J61: 886.439 | K61: 10 | L61: Chapa y fleje (manuales) | M61: 492 | N61: Manuales | O61: Unidad óptima (hoja Compra_MP): rollo = 1 tanda de la matriz. Consumo pico = producción con sobrestock (no ventas). Antes: Rollo de 492 kg
A62: P11 | B62: Fleje LAF 2,0 × 238,7 mm (cúpula 10 kg) | C62: MP-09 | D62: Pacheco Chapas | E62: 3403.11 | F62: kg | G62: 7 | H62: 10 | I62: Rollo de 245 kg (1 tanda) | J62: 245.024 | K62: 10 | L62: Chapa y fleje (manuales) | M62: 738 | N62: Manuales | O62: DECISIÓN DEL GRUPO: cúpula del 10 kg pasa de 1,6 a 2,0 mm (mismo espesor que el fondo). Consumo del año = MRP × 1.25 (el disco tiene el mismo diámetro; el peso del fleje cambia con el espesor). Hay que actualizar BOM, MRP y plano. Unidad óptima (hoja Compra_MP): rollo = 1 tanda de la matriz. Consumo pico = producción con sobrestock (no ventas). Antes: Rollo de 590 kg
A63: P12 | B63: Fleje LAF 2,0 × 205 mm (fondo 10 kg) | C63: MP-10 | D63: Pacheco Chapas | E63: 2486.567 | F63: kg | G63: 7 | H63: 10 | I63: Rollo de 179 kg (1 tanda) | J63: 179.033 | K63: 10 | L63: Chapa y fleje (manuales) | M63: 498 | N63: Manuales | O63: Unidad óptima (hoja Compra_MP): rollo = 1 tanda de la matriz. Consumo pico = producción con sobrestock (no ventas). Antes: Rollo de 498 kg
... A65: P14 | B65: Hoja LAC 4,75 × 1500 × 3000 mm | C65: MP-12 | D65: Pradecon | E65: 165.622 | F65: hoja | G65: 7 | H65: 10 | I65: Paquete de 3 hojas (1 tanda) | J65: 3 | K65: 20 | L65: Calle de chapa (carros) | M65: 30 | N65: Carros | O65: Unidad óptima (hoja Compra_MP): paquete = 1 tanda de corte. Consumo pico = producción con sobrestock (no ventas). Antes: Paquete de 15 hojas
A66: P15 | B66: Casquete 10" × 3,2 mm (carro 25 kg) | C66: MP-15 | D66: NOVA Ruedas | E66: 1554.621 | F66: u | G66: =CQ_PMIN -> 25 | H66: =CQ_PMAX -> 32 | I66: ="Contenedor de "&Casquetes!N27&" u ("&Casquetes!O27&" cúpulas + "&Casquetes!P27&" fondos, ≈ "&ROUND(Casquetes!S27,-1)&" kg)" -> Contenedor de 360 u (180 cúpulas + 180 fondos, ≈ 1000 kg) | J66: =Casquetes!N27 -> 360 | K66: =CQ_CADA -> 20 | L66: Rack de casquetes y cuplas (carros) | M66: =Casquetes!N27 -> 360 | N66: Carros | O66: Como Fadesa: compra nacional, llega en contenedores, demora ≈ 40 días y se pide según la demanda. Contenedor dimensionado en la hoja Casquetes. Antes: importado (China), pallet de 400/300/150 u, contenedor de 20' cada 50 días.
A67: P16 | B67: Casquete 12" × 3,2 mm (carro 50 kg) | C67: MP-16 | D67: NOVA Ruedas | E67: 3416.87 | F67: u | G67: =CQ_PMIN -> 25 | H67: =CQ_PMAX -> 32 | I67: ="Contenedor de "&Casquetes!N28&" u ("&Casquetes!O28&" cúpulas + "&Casquetes!P28&" fondos, ≈ "&ROUND(Casquetes!S28,-1)&" kg)" -> Contenedor de 260 u (130 cúpulas + 130 fondos, ≈ 990 kg) | J67: =Casquetes!N28 -> 260 | K67: =CQ_CADA -> 20 | L67: Rack de casquetes y cuplas (carros) | M67: =Casquetes!N28 -> 260 | N67: Carros | O67: Como Fadesa: compra nacional, llega en contenedores, demora ≈ 40 días y se pide según la demanda. Contenedor dimensionado en la hoja Casquetes. Antes: importado (China), pallet de 400/300/150 u, contenedor de 20' cada 50 días.
A68: P17 | B68: Casquete 15" × 4,75 mm (carros 70 y 100 kg) | C68: MP-17 | D68: NOVA Ruedas | E68: 1243.153 | F68: u | G68: =CQ_PMIN -> 25 | H68: =CQ_PMAX -> 32 | I68: ="Contenedor de "&Casquetes!N29&" u ("&Casquetes!O29&" cúpulas + "&Casquetes!P29&" fondos, ≈ "&ROUND(Casquetes!S29,-1)&" kg)" -> Contenedor de 116 u (58 cúpulas + 58 fondos, ≈ 890 kg) | J68: =Casquetes!N29 -> 116 | K68: =CQ_CADA -> 20 | L68: Rack de casquetes y cuplas (carros) | M68: =Casquetes!N29 -> 116 | N68: Carros | O68: Como Fadesa: compra nacional, llega en contenedores, demora ≈ 40 días y se pide según la demanda. Contenedor dimensionado en la hoja Casquetes. Antes: importado (China), pallet de 400/300/150 u, contenedor de 20' cada 50 días.
A69: P18 | B69: Asiento de válvula M22 × 1,5 (1 kg) | C69: MP-18 | D69: Eli-Met | E69: 202620.64 | F69: u | G69: 25 | H69: 29 | I69: Caja de 500 u (≈ 16 kg, un turno) | J69: 500 | K69: 20 | L69: Insumos de montaje (manuales) | M69: 12000 | N69: Manuales | O69: La caja de 1.000 pesa ≈ 31 kg (más de 25 kg para una persona). La de 500 pesa ≈ 16 kg y es lo que usa un turno (≈ 456 u). Llegan en pallet de cajas. Antes (MRP): Caja de 1.000 u, cada 20 días.
A70: P19 | B70: Asiento de válvula M30 × 1,5 (2,5 a 10 kg) | C70: MP-19 | D70: Eli-Met | E70: 81841.925 | F70: u | G70: 25 | H70: 29 | I70: Caja de 500 u (≈ 15 kg) | J70: 500 | K70: 20 | L70: Insumos de montaje (manuales) | M70: 8000 | N70: Manuales | O70: Misma caja que el M22, para que Eli-Met mande un solo formato. Antes (MRP): Caja de 1.000 u, cada 20 días.
A71: P20 | B71: Cupla M30 × 1,5 (carros 25 y 50 kg) | C71: MP-20 | D71: Eli-Met | E71: 2485.746 | F71: u | G71: 25 | H71: 29 | I71: Caja de 100 u (25 kg) | J71: 100 | K71: 20 | L71: Rack de casquetes y cuplas (carros) | M71: 600 | N71: Carros | O71: Caja del Word (25 kg, una persona). Va en el pedido mensual de Eli-Met junto con los asientos. Antes (MRP): Caja de 100 u, cada 40 días.
A72: P21 | B72: Cupla 2½" BSP (carros 70 y 100 kg) | C72: MP-21 | D72: Eli-Met | E72: 621.576 | F72: u | G72: 25 | H72: 29 | I72: Caja de 40 u (24 kg) | J72: 40 | K72: 20 | L72: Rack de casquetes y cuplas (carros) | M72: 160 | N72: Carros | O72: Caja del Word. Va en el pedido mensual de Eli-Met. Antes (MRP): Caja de 40 u, cada 40 días.
A73: P22 | B73: Caño SAE 1010 1" × 2,0 × 6 m (manija; caño del eje 25 kg) | C73: MP-66 | D73: Centrosider | E73: 510.181 | F73: barra | G73: 5 | H73: 5 | I73: Barra de 6 m (un atado por pedido) | J73: 1 | K73: 20 | L73: Cantilever de caños y barras | M73: 60 | N73: Carros | O73: Se compra por barra entera. Cada 20 días alcanza (el proveedor entrega en 5): baja el stock y libera cantilever. Antes (MRP): Barra de 6 m, cada 60 días.
A74: P23 | B74: Caño SAE 1010 1¼" × 2,0 × 6 m (caño del eje 50 a 100 kg) | C74: MP-67 | D74: Centrosider | E74: 89.621 | F74: barra | G74: 5 | H74: 5 | I74: Barra de 6 m (un atado por pedido) | J74: 1 | K74: 20 | L74: Cantilever de caños y barras | M74: 60 | N74: Carros | O74: Ídem MP-66, mismo pedido a Centrosider. Antes (MRP): Barra de 6 m, cada 60 días.
A75: P24 | B75: Barra trefilada SAE 1045 3/4" × 4 m (eje 25 kg) | C75: MP-68 | D75: Vladimirsky | E75: 56.709 | F75: barra | G75: 1 | H75: 3 | I75: Barra de 4 m | J75: 1 | K75: 20 | L75: Cantilever de caños y barras | M75: 60 | N75: Carros | O75: Ídem, pedido mensual a Vladimirsky. Antes (MRP): Barra de 4 m, cada 60 días.
A76: P25 | B76: Barra trefilada SAE 1045 1" × 6 m (eje 50 a 100 kg) | C76: MP-69 | D76: Vladimirsky | E76: 127.028 | F76: barra | G76: 1 | H76: 3 | I76: Barra de 6 m | J76: 1 | K76: 20 | L76: Cantilever de caños y barras | M76: 60 | N76: Carros | O76: Ídem, pedido mensual a Vladimirsky. Antes (MRP): Barra de 6 m, cada 60 días.
A77: P26 | B77: Arandela de tope del eje | C77: MP-70 | D77: Würth Argentina | E77: 7258.729 | F77: u | G77: 3 | H77: 5 | I77: Bolsa de 1.000 u | J77: 1000 | K77: 20 | L77: Rack de insumos de montaje (carros) | M77: 20000 | N77: Carros | O77: Se mantiene: una bolsa dura ≈ 30 días.
A78: P27 | B78: Pasador partido del eje | C78: MP-71 | D78: Würth Argentina | E78: 3629.364 | F78: u | G78: 3 | H78: 5 | I78: Bolsa de 1.000 u | J78: 1000 | K78: 20 | L78: Rack de insumos de montaje (carros) | M78: 20000 | N78: Carros | O78: Se mantiene: es chica y barata, dura ≈ 60 días.
A79: P28 | B79: Rueda Ø300 × 50, buje 3/4" (carro 25 kg) | C79: MP-54/300 | D79: Ruedar | E79: 907.341 | F79: u | G79: 3 | H79: 5 | I79: Pallet de 72 u | J79: 72 | K79: 20 | L79: Rack de insumos de montaje (carros) | M79: 144 | N79: Carros | O79: Se mantiene el pallet del proveedor (dura ≈ 17 días).
A80: P29 | B80: Rueda Ø350 × 60, buje 1" (carro 50 kg) | C80: MP-54/350 | D80: Ruedar | E80: 1995.99 | F80: u | G80: 3 | H80: 5 | I80: Pallet de 72 u | J80: 72 | K80: 20 | L80: Rack de insumos de montaje (carros) | M80: 144 | N80: Carros | O80: Se mantiene el pallet del proveedor (dura ≈ 8 días).
... A167: P116 | B167: Etiqueta de pallet | C167: MP-90 | D167: Rotolan (Lanús) | E167: 1532.704 | F167: u | G167: 3 | H167: 7 | I167: Rollo de 1.000 u | J167: 1000 | K167: 20 | L167: Embalaje | M167: 20000 | N167: Manuales | O167: Se mantiene.
A168: P117 | B168: Matafuego Agua 10 l (reventa) | C168: RV-AGUA_10l | D168: Maxiseguridad (Munro) | E168: 2908.236 | F168: u | G168: 3 | H168: 7 | I168: Unidad | J168: 1 | K168: 20 | L168: Almacén de producto terminado | M168: 180 | N168: Reventa | O168: Reventa: se usa el pico de ventas del MRP (no se fabrica). Se mantiene la unidad del MRP. | P168: 15.995
A169: P118 | B169: Matafuego AFFF 10 l (reventa) | C169: RV-AFFF_10l | D169: Maxiseguridad (Munro) | E169: 971.251 | F169: u | G169: 3 | H169: 7 | I169: Unidad | J169: 1 | K169: 20 | L169: Almacén de producto terminado | M169: 180 | N169: Reventa | O169: Reventa: se usa el pico de ventas del MRP (no se fabrica). Se mantiene la unidad del MRP. | P169: 5.342
A170: P119 | B170: Matafuego AFFF 50 l (reventa) | C170: RV-AFFF_50l | D170: Maxiseguridad (Munro) | E170: 416.16 | F170: u | G170: 3 | H170: 7 | I170: Unidad | J170: 1 | K170: 20 | L170: Almacén de producto terminado | M170: 60 | N170: Reventa | O170: Reventa: se usa el pico de ventas del MRP (no se fabrica). Se mantiene la unidad del MRP. | P170: 1.873
A171: P120 | B171: Matafuego BC 5 kg (reventa) | C171: RV-BC_5kg | D171: Maxiseguridad (Munro) | E171: 277.43 | F171: u | G171: 3 | H171: 7 | I171: Unidad | J171: 1 | K171: 20 | L171: Almacén de producto terminado | M171: 180 | N171: Reventa | O171: Reventa: se usa el pico de ventas del MRP (no se fabrica). Se mantiene la unidad del MRP. | P171: 1.526
A172: P121 | B172: Matafuego Clase K 6 l (reventa) | C172: RV-SALESK_6l | D172: Matafuegos Rodo | E172: 1650.661 | F172: u | G172: 1 | H172: 2 | I172: Unidad | J172: 1 | K172: 20 | L172: Almacén de producto terminado | M172: 180 | N172: Reventa | O172: Reventa: se usa el pico de ventas del MRP (no se fabrica). Se mantiene la unidad del MRP. | P172: 9.079
A173: P122 | B173: Matafuego CO₂ 2 kg (reventa) | C173: RV-CO2_2kg | D173: Maxiseguridad (Munro) | E173: 7005.277 | F173: u | G173: 3 | H173: 7 | I173: Unidad | J173: 1 | K173: 20 | L173: Almacén de producto terminado | M173: 180 | N173: Reventa | O173: Reventa: se usa el pico de ventas del MRP (no se fabrica). Se mantiene la unidad del MRP. | P173: 38.529
A174: P123 | B174: Matafuego CO₂ 5 kg (reventa) | C174: RV-CO2_5kg | D174: Matafuegos Rodo | E174: 3776.555 | F174: u | G174: 1 | H174: 2 | I174: Unidad | J174: 1 | K174: 20 | L174: Almacén de producto terminado | M174: 180 | N174: Reventa | O174: Reventa: se usa el pico de ventas del MRP (no se fabrica). Se mantiene la unidad del MRP. | P174: 20.771
A175: P124 | B175: Matafuego HCFC 5 kg (reventa) | C175: RV-HCFC-HFC_5kg | D175: Matafuegos Rodo | E175: 744.135 | F175: u | G175: 1 | H175: 2 | I175: Unidad | J175: 1 | K175: 20 | L175: Almacén de producto terminado | M175: 180 | N175: Reventa | O175: Reventa: se usa el pico de ventas del MRP (no se fabrica). Se mantiene la unidad del MRP. | P175: 4.093
A176: P125 | B176: Matafuego Clase D 9 l (reventa) | C176: RV-CLASED_9l | D176: Fabricante nacional | E176: 277.704 | F176: u | G176: 3 | H176: 7 | I176: Unidad | J176: 1 | K176: 20 | L176: Almacén de producto terminado | M176: 180 | N176: Reventa | O176: Reventa: se usa el pico de ventas del MRP (no se fabrica). Se mantiene la unidad del MRP. | P176: 1.527
A179: 6) PRECIOS RELEVADOS (Almacenamiento_MP_FLAMA_2035.xlsx, hoja Precios, 21/10/2026, con IVA)
A180: Id | B180: Producto | C180: Precio con IVA | D180: Tienda | E180: Link
A181: R1I | B181: Rack selectivo 2,30 × 1,00 × 3 m, 2 niveles, 2.000 kg/nivel — módulo inicial | C181: 856540 | D181: Estanterías Boyacá | E181: https://estanterias.com.ar/tienda/racks/racks-para-paletizacion/racks-selectivos-pallets-230x100-x-3mts-de-alto-c-2-niveles-2000kg-inicial/
A182: R1A | B182: Ídem 2.000 kg/nivel — módulo adicional | C182: 655590 | D182: Estanterías Boyacá | E182: https://estanterias.com.ar/tienda/racks/racks-para-paletizacion/racks-selectivos-pallets-230x100-x-3mts-de-alto-c-2-niveles-2000kg-adicional/
A183: R2I | B183: Ídem 1.000 kg/nivel — módulo inicial | C183: 650040 | D183: Estanterías Boyacá | E183: https://estanterias.com.ar/tienda/racks/racks-para-paletizacion/racks-selectivos-pallets-230x100-x-3mts-de-alto-c-2-niveles-1000kg-inicial/
A184: R2A | B184: Ídem 1.000 kg/nivel — módulo adicional | C184: 449090 | D184: Estanterías Boyacá | E184: https://estanterias.com.ar/tienda/racks/racks-para-paletizacion/racks-selectivos-pallets-230x100-x-3mts-de-alto-c-2-niveles-1000kg-adicional/
A185: R3I | B185: Ídem 500 kg/nivel — módulo inicial | C185: 606940 | D185: Estanterías Boyacá | E185: https://estanterias.com.ar/tienda/racks/racks-para-paletizacion/racks-selectivos-pallets-230x100-x-3mts-de-alto-c-2-niveles-500kg-inicial/
A186: R3A | B186: Ídem 500 kg/nivel — módulo adicional | C186: 405990 | D186: Estanterías Boyacá | E186: https://estanterias.com.ar/tienda/racks/racks-para-paletizacion/racks-selectivos-pallets-230x100-x-3mts-de-alto-c-2-niveles-500kg-adicional/
A187: E1 | B187: Estantería encastrable 110 × 50 × 200 cm, 5 estantes | C187: 683968 | D187: Storage Compat | E187: https://www.storagecompatshop.com.ar/productos/estanteria-encastrable-uninorm-50cm-color-azul/
A188: A1 | B188: Pallet antiderrame para 4 tambores de 200 L | C188: 495713 | D188: Paimun Industrial | E188: https://www.e-paimun.com.ar/producto/pallet-antiderrame-para-4-tambores-de-200-lts-reforzada/
A189: A2 | B189: Bandeja de contención inox (bidones de 20 L) | C189: 54250 | D189: Cuben | E189: https://www.tienda.cuben.com.ar/productos/pallet-antiderrame-metalico-para-4-tambores-de-200-l/
A190: G1 | B190: Gabinete para 8 cilindros de gases | C190: 4882500 | D190: Cuben | E190: https://www.tienda.cuben.com.ar/productos/gabinete-para-cilindro-de-gases/
A191: M1 | B191: Malla electrosoldada galvanizada, rollo de 12,5 m | C191: 98649 | D191: Easy | E191: https://www.easy.com.ar/malla-electrosoldada-cal-1-6-50x100x12-5/p
A192: S1 | B192: Perfil UPN 100, barra de 12 m | C192: 384169 | D192: Ropelato | E192: https://www.ropelato.com.ar/perfiles-upn/47106-perfil-upn-100-barra-x-12m.html
... A195: X7 | B195: Larguero pesado 2,30 m, 2.000 kg (par) | C195: 95900 | D195: Rapiestantes | E195: https://rapiestantesweb.com.ar/producto/larguero-pesado-2-30-mts/
A196: V1 | B196: Apilador eléctrico con pinza giratoria para bobinas (≥ 1,3 t, Ø hasta 1.100) — a cotizar. Referencia: Huizelift 1 t, US$ 6.000 a 7.500 | D196: Huizelift / Tymbia | E196: https://es.made-in-china.com/co_huizelift/product_Fully-Automatic-Stacker-Electric-Roll-Lifter-with-Rotating-Clamp-for-PVC-Coils_ysusrseiey.html

Sheet Parametros
A1: PARÁMETROS — supuestos y criterios del almacén de MP
A2: Amarillo = criterio (se puede cambiar). Verde = dato. Blanco = fórmula. La columna E es el nombre que usan las fórmulas.
A3: ▶ Solo se tocan las celdas amarillas.
A5: 1) CONSUMO DEL DÍA PICO
A6: Parámetro | B6: Valor | C6: Unidad | D6: Fuente / criterio | E6: Nombre
A7: Días hábiles por año | B7: 240 | C7: días | D7: Balanceo: 20 días por mes × 12 | E7: DIAS_ANIO
A8: Factor de pico de manuales (mes pico ÷ mes promedio) | B8: =MAX(Datos!B29:M29)/AVERAGE(Datos!B29:M29) -> 1.08 | C8: × | D8: Producción con sobrestock (no ventas): enero | E8: FAC_MAN
A9: Factor de pico de carros | B9: =MAX(Datos!B30:M30)/AVERAGE(Datos!B30:M30) -> 1.08 | C9: × | D9: Marzo | E9: FAC_CAR
A10: Factor de pico de recargas | B10: =MAX(Datos!B31:M31)/AVERAGE(Datos!B31:M31) -> 1.2210295 | C10: × | D10: Diciembre | E10: FAC_REC
A12: 2) AUTOELEVADOR Y PISO (limitan la altura de las pilas de chapa)
A13: Parámetro | B13: Valor | C13: Unidad | D13: Fuente / criterio | E13: Nombre
A14: Altura de elevación del autoelevador | B14: 3000 | C14: mm | D14: Heli CPCD50. El autoelevador lleva mástil de 4,5 m porque lo pide el rack de PT (Word de PT); para las pilas de chapa se mantiene 3 m como tope de trabajo: con 4,5 m las pilas no cambian (casi todas entran en una) | E14: H_ELEV
A15: Capacidad nominal del autoelevador | B15: 5000 | C15: kg | D15: Heli CPCD50 (Words de manuales y carros) | E15: CAP_AUTO
A16: Centro de carga de la capacidad nominal | B16: 600 | C16: mm | D16: Heli CPCD50 (lectura-specs.com) | E16: CC_AUTO
A17: Capacidad de la mesa elevadora de la guillotina | B17: 3000 | C17: kg | D17: Word de manuales: mesa de tijera de 3 t | E17: CAP_MESA
A18: Carga admisible del piso del almacén | B18: 5 | C18: t/m² | D18: SUPUESTO: losa industrial común. Confirmar con el cálculo del piso; si es menor, las pilas bajan solas | E18: Q_PISO
A19: Alto máximo de una pila ÷ su lado menor | B19: 3 | C19: × | D19: Criterio de estabilidad de pilas sueltas: no más de 3 veces la base más angosta | E19: REL_PILA
A21: 3) PAQUETES DE CHAPA
A22: Parámetro | B22: Valor | C22: Unidad | D22: Fuente / criterio | E22: Nombre
A23: Densidad del acero | B23: 7.85 | C23: kg/dm³ | D23: Acero al carbono | E23: DENS
A24: Alto del taco de madera bajo cada paquete | B24: 100 | C24: mm | D24: Las uñas del CPCD50 (≈ 50 mm) entran sin rozar la hoja de abajo (especificación de compra) | E24: H_TACO
A25: Tacos por paquete | B25: 3 | C25: u | D25: A lo ancho del paquete, alineados en columna en la pila | E25: N_TACO
A26: Ancho de apoyo de cada taco | B26: 100 | C26: mm | D26: Taco de 100 × 100 mm | E26: A_TACO
A27: Compresión admisible de la madera (perpendicular a la fibra) | B27: 2 | C27: MPa | D27: SUPUESTO conservador para pino o eucalipto seco | E27: SIG_MAD
A28: Separación entre pilas | B28: 0.5 | C28: m | D28: Para leer la etiqueta, cortar flejes y que no se toquen las uñas | E28: SEP_PILA
A29: Ancho de la calle del autoelevador | B29: 5 | C29: m | D29: Word de carros: radio de giro 2,93 m + fondo del paquete + margen | E29: CALLE
A31: 4) FLEJES: RACK SELECTIVO + ZONA DE ARMADO CON EL APILADOR DE PINZA
A32: Parámetro | B32: Valor | C32: Unidad | D32: Fuente / criterio | E32: Nombre
A33: Diámetro interior del rollo | B33: 508 | C33: mm | D33: Estándar de 20" (Compra de chapa y fleje) | E33: DI_ROLLO
A34: Peso máximo del rollo que admite el desbobinador | B34: 1350 | C34: kg | D34: SUPUESTO (Compra de chapa y fleje): confirmar con Cena | E34: CAP_DESB
A35: Carga máxima por posición de pallet en los niveles altos | B35: 1000 | C35: kg | D35: Rack de 2.000 kg por nivel con 2 pallets de frente (módulo R1) | E35: KG_POS
A36: Alto útil de un nivel del rack de flejes | B36: 700 | C36: mm | D36: Pallet (150 mm) + pila de rollos; largueros cada 750 mm | E36: H_NIV
A37: Niveles del rack de flejes (piso + 3 largueros) | B37: 4 | C37: u | D37: Los rollos acostados son bajos: con largueros a 0,75 / 1,50 / 2,25 m el último queda a 2,25 m, dentro de los 3 m del autoelevador y del bastidor | E37: NIV_FLEJE
A38: Separador de madera entre rollos (y bajo el primero) | B38: 25 | C38: mm | D38: Listón: la paleta de la pinza baja hasta el borde de abajo del rollo sin tocar el de abajo ni el pallet | E38: SEP_ROLLO
A39: Alto máximo de la pila de rollos ÷ Ø exterior | B39: 1 | C39: × | D39: Estabilidad: la pila no más alta que su diámetro | E39: REL_ROLLO
A40: Posiciones de pallet por nivel de un módulo | B40: 2 | C40: u | D40: Módulo de 2,30 m | E40: POS_NIV
A41: Niveles por módulo (piso + 2 largueros) | B41: 3 | C41: u | D41: Rack de 3 m: el CPCD50 llega con holgura al 2.º larguero | E41: NIV
A42: Frente de un módulo | B42: 2.3 | C42: m | D42: Rack selectivo de 2,30 m | E42: MOD_FRENTE
A43: Fondo del rack | B43: 1.1 | C43: m | D43: Pallet de 1.000 de fondo + 100 mm | E43: MOD_FONDO
A44: Superficie de la zona de armado (pallet en el piso + brazos de la pinza + maniobra) | B44: 9 | C44: m² | D44: SUPUESTO: 3 × 3 m al lado del rack de flejes; ahí la pinza arma y desarma los pallets | E44: M2_VOLTEO
... A48: Lugar de cada brazo de la pinza al costado del rollo (espesor + holgura) | B48: 80 | C48: mm | D48: SUPUESTO: brazo de 60 mm + 20 mm de holgura. Confirmar con el fabricante | E48: PINZA_BRAZO
A50: 5) RACK SELECTIVO DE LOS DEMÁS ALMACENES
A51: Parámetro | B51: Valor | C51: Unidad | D51: Fuente / criterio | E51: Nombre
A52: Lugares de pallet por módulo | B52: =POS_NIV*NIV -> 6 | C52: u | D52: 2 pallets × 3 alturas | E52: LUG_MOD
A54: 6) APILADOR CON PINZA GIRATORIA («volteador»): agarra el rollo parado por afuera, lo lleva y lo gira 90°
A55: Equipo | B55: Capacidad (kg) | C55: Ø máximo que abre la pinza (mm) | D55: ¿Sirve? (capacidad ≥ rollo más pesado y Ø ≥ Ø mayor) | E55: Nota
A56: Huizelift CDD1016-Z-11 (apilador 1 t con pinza giratoria) | B56: 1000 | D56: =IF(B56<Chapa_fleje!$L$50,"No: capacidad",IF(C56="","Falta el Ø",IF(C56>=Chapa_fleje!$L$51,"Sí","No: Ø"))) -> No: capacidad | E56: El del link: para bobinas de PVC; Ø no publicado. US$ 6.000 a 7.500
A57: Manuvit (apilador con pinza para bobinas) | B57: 500 | C57: 1270 | D57: =IF(B57<Chapa_fleje!$L$50,"No: capacidad",IF(C57="","Falta el Ø",IF(C57>=Chapa_fleje!$L$51,"Sí","No: Ø"))) -> No: capacidad | E57: Abre de Ø 120 a 1.270 mm
A58: Huizelift versión 1,5 t (a pedir) | B58: 1500 | D58: =IF(B58<Chapa_fleje!$L$50,"No: capacidad",IF(C58="","Falta el Ø",IF(C58>=Chapa_fleje!$L$51,"Sí","No: Ø"))) -> Falta el Ø | E58: Pedir con brazos para acero y apertura hasta 1.150 mm
A59: Tymbia M103070075 en apilador eléctrico de 2,5 t | B59: 1300 | C59: 1100 | D59: =IF(B59<Chapa_fleje!$L$50,"No: capacidad",IF(C59="","Falta el Ø",IF(C59>=Chapa_fleje!$L$51,"Sí","No: Ø"))) -> Sí | E59: Pinza giratoria 360°, 1.300 kg a 550 mm, Ø 250 a 1.100, pesa 560 kg
A60: Fuentes: made-in-china.com (Huizelift), directindustry.com (Manuvit), tymbia.com (pinza M103070075). Capacidad: la del equipo con la pinza puesta.

Sheet Chapa_fleje
A1: CHAPA Y FLEJE — el paquete y el rollo son una tanda del balanceo, y cómo se guardan
A2: Paquete de hojas = tanda de corte de la guillotina; rollo de fleje = tanda de la matriz. Tandas y frecuencias del balanceo limpio (Datos 1 y 2). Las pilas de chapa suben hasta lo que permiten el autoelevador, el piso y la estabilidad.
A3: ▶ Sección 1 (paquete, pedido y stock), 2 (pilas), 3 (rollos), 4 (rack de flejes) y 5 (volteador y superficie).
A5: 1) HOJAS: UN PAQUETE = UNA TANDA DE CORTE
A6: Código | B6: Material | C6: Proveedor | D6: Espesor (mm) | E6: Ancho (mm) | F6: Largo (mm) | G6: kg por hoja | H6: Hojas por día | I6: Hojas por tanda | J6: Se corta cada (días) | K6: Paquete elegido (vacío = tanda) | L6: Paquete (hojas) | M6: Peso del paquete (kg) | N6: Alto del paquete (mm) | O6: Días que dura | P6: Plazo mín. | Q6: Plazo máx. | R6: Consumo promedio (hojas/día) | S6: Seguridad (paquetes) | T6: Días entre pedidos | U6: Paquetes por pedido | V6: Stock máximo (paquetes) | W6: Stock máximo (t) | X6: Control de peso
A7: MP-01 | B7: =Datos!B52 -> Hoja LAF 0,9 × 1220 × 2440 mm (cuerpo 1 kg) | C7: =Datos!D52 -> Hierros Parrotta | D7: 0.9 | E7: 1220 | F7: 2440 | G7: =DENS*D7*E7*F7/1000000 -> 21.031092 | H7: =Datos!D7/Datos!C7 -> 20.262064 | I7: =Datos!F7 -> 21 | J7: =Datos!E7 -> 1 | L7: =IF(K7="",I7,K7) -> 21 | M7: =L7*G7 -> 441.65293 | N7: =L7*D7+H_TACO -> 118.9 | O7: =IF(H7=0,0,L7/H7) -> 1.0364196 | P7: =Datos!G52 -> 10 | Q7: =Datos!H52 -> 10 | R7: =Datos!E52/DIAS_ANIO -> 18.761171 | S7: =MAX(1,ROUNDUP(MAX(0,H7*Q7-R7*(P7+Q7)/2)/L7,0)) -> 1 | T7: =VLOOKUP(C7,Pedidos!$A$7:$C$60,3,FALSE()) -> 20 | U7: =ROUNDUP(H7*T7/L7,0) -> 20 | V7: =S7+U7 -> 21 | W7: =V7*M7/1000 -> 9.2747116 | X7: =IF(M7<=MIN(CAP_MESA,CAP_AUTO),"OK","Pasa la mesa") -> OK
A8: MP-02 | B8: =Datos!B53 -> Hoja LAF 1,25 × 1220 × 2440 mm | C8: =Datos!D53 -> Pradecon | D8: 1.25 | E8: 1220 | F8: 2440 | G8: =DENS*D8*E8*F8/1000000 -> 29.20985 | H8: =Datos!D8/Datos!C8 -> 2.3543897 | I8: =Datos!F8 -> 19 | J8: =Datos!E8 -> 8 | L8: =IF(K8="",I8,K8) -> 19 | M8: =L8*G8 -> 554.98715 | N8: =L8*D8+H_TACO -> 123.75 | O8: =IF(H8=0,0,L8/H8) -> 8.0700318 | P8: =Datos!G53 -> 7 | Q8: =Datos!H53 -> 10 | R8: =Datos!E53/DIAS_ANIO -> 2.1799917 | S8: =MAX(1,ROUNDUP(MAX(0,H8*Q8-R8*(P8+Q8)/2)/L8,0)) -> 1 | T8: =VLOOKUP(C8,Pedidos!$A$7:$C$60,3,FALSE()) -> 20 | U8: =ROUNDUP(H8*T8/L8,0) -> 3 | V8: =S8+U8 -> 4 | W8: =V8*M8/1000 -> 2.2199486 | X8: =IF(M8<=MIN(CAP_MESA,CAP_AUTO),"OK","Pasa la mesa") -> OK
A9: MP-03 | B9: =Datos!B54 -> Hoja LAF 1,6 × 1000 × 2000 mm | C9: =Datos!D54 -> Pradecon | D9: 1.6 | E9: 1000 | F9: 2000 | G9: =DENS*D9*E9*F9/1000000 -> 25.12 | H9: =Datos!D9/Datos!C9 -> 23.944747 | I9: =Datos!F9 -> 24 | J9: =Datos!E9 -> 1 | L9: =IF(K9="",I9,K9) -> 24 | M9: =L9*G9 -> 602.88 | N9: =L9*D9+H_TACO -> 138.4 | O9: =IF(H9=0,0,L9/H9) -> 1.0023075 | P9: =Datos!G54 -> 7 | Q9: =Datos!H54 -> 10 | R9: =Datos!E54/DIAS_ANIO -> 22.171063 | S9: =MAX(1,ROUNDUP(MAX(0,H9*Q9-R9*(P9+Q9)/2)/L9,0)) -> 3 | T9: =VLOOKUP(C9,Pedidos!$A$7:$C$60,3,FALSE()) -> 20 | U9: =ROUNDUP(H9*T9/L9,0) -> 20 | V9: =S9+U9 -> 23 | W9: =V9*M9/1000 -> 13.86624 | X9: =IF(M9<=MIN(CAP_MESA,CAP_AUTO),"OK","Pasa la mesa") -> OK
A10: MP-04 | B10: =Datos!B55 -> Hoja LAF 2,0 × 1500 × 3000 mm | C10: =Datos!D55 -> Pradecon | D10: 2 | E10: 1500 | F10: 3000 | G10: =DENS*D10*E10*F10/1000000 -> 70.65 | H10: =Datos!D10/Datos!C10 -> 1.1588784 | I10: =Datos!F10 -> 19 | J10: =Datos!E10 -> 16 | L10: =IF(K10="",I10,K10) -> 19 | M10: =L10*G10 -> 1342.35 | N10: =L10*D10+H_TACO -> 138 | O10: =IF(H10=0,0,L10/H10) -> 16.395162 | P10: =Datos!G55 -> 7 | Q10: =Datos!H55 -> 10 | R10: =Datos!E55/DIAS_ANIO -> 1.0730375 | S10: =MAX(1,ROUNDUP(MAX(0,H10*Q10-R10*(P10+Q10)/2)/L10,0)) -> 1 | T10: =VLOOKUP(C10,Pedidos!$A$7:$C$60,3,FALSE()) -> 20 | U10: =ROUNDUP(H10*T10/L10,0) -> 2 | V10: =S10+U10 -> 3 | W10: =V10*M10/1000 -> 4.02705 | X10: =IF(M10<=MIN(CAP_MESA,CAP_AUTO),"OK","Pasa la mesa") -> OK
A11: MP-11 | B11: =Datos!B64 -> Hoja LAC 3,2 × 1500 × 3000 mm | C11: =Datos!D64 -> Pradecon | D11: 3.2 | E11: 1500 | F11: 3000 | G11: =DENS*D11*E11*F11/1000000 -> 113.04 | H11: =Datos!D11/Datos!C11+Datos!D12/Datos!C12 -> 1.5772049 | I11: =Datos!F11+Datos!F12 -> 7 | J11: =Datos!E11 -> 4 | L11: =IF(K11="",I11,K11) -> 7 | M11: =L11*G11 -> 791.28 | N11: =L11*D11+H_TACO -> 122.4 | O11: =IF(H11=0,0,L11/H11) -> 4.4382312 | P11: =Datos!G64 -> 7 | Q11: =Datos!H64 -> 10 | R11: =Datos!E64/DIAS_ANIO -> 1.4563125 | S11: =MAX(1,ROUNDUP(MAX(0,H11*Q11-R11*(P11+Q11)/2)/L11,0)) -> 1 | T11: =VLOOKUP(C11,Pedidos!$A$7:$C$60,3,FALSE()) -> 20 | U11: =ROUNDUP(H11*T11/L11,0) -> 5 | V11: =S11+U11 -> 6 | W11: =V11*M11/1000 -> 4.74768 | X11: =IF(M11<=MIN(CAP_MESA,CAP_AUTO),"OK","Pasa la mesa") -> OK
A12: MP-12 | B12: =Datos!B65 -> Hoja LAC 4,75 × 1500 × 3000 mm | C12: =Datos!D65 -> Pradecon | D12: 4.75 | E12: 1500 | F12: 3000 | G12: =DENS*D12*E12*F12/1000000 -> 167.79375 | H12: =Datos!D13/Datos!C13 -> 0.66042495 | I12: =Datos!F13 -> 3 | J12: =Datos!E13 -> 4 | L12: =IF(K12="",I12,K12) -> 3 | M12: =L12*G12 -> 503.38125 | N12: =L12*D12+H_TACO -> 114.25 | O12: =IF(H12=0,0,L12/H12) -> 4.5425298 | P12: =Datos!G65 -> 7 | Q12: =Datos!H65 -> 10 | R12: =Datos!E65/DIAS_ANIO -> 0.69009167 | S12: =MAX(1,ROUNDUP(MAX(0,H12*Q12-R12*(P12+Q12)/2)/L12,0)) -> 1 | T12: =VLOOKUP(C12,Pedidos!$A$7:$C$60,3,FALSE()) -> 20 | U12: =ROUNDUP(H12*T12/L12,0) -> 5 | V12: =S12+U12 -> 6 | W12: =V12*M12/1000 -> 3.0202875 | X12: =IF(M12<=MIN(CAP_MESA,CAP_AUTO),"OK","Pasa la mesa") -> OK
B13: Total | V13: =SUM(V7:V12) -> 63 | W13: =SUM(W7:W12) -> 37.155918
A14: Hojas por día = cuerpos por día ÷ cuerpos por hoja (MP-11: 25 y 50 kg comparten la hoja de 3,2). Seguridad = (hojas por día × plazo máx. − promedio × plazo medio) ÷ paquete, mínimo 1. Pedido = lo que falta hasta el máximo; en promedio, hojas por día × días entre pedidos.
A16: 2) PILAS DE CHAPA EN EL PISO: lo más alto que permiten el autoelevador, el piso y la estabilidad
A17: Código | B17: Formato (mm) | C17: Paquetes en el stock máx. | D17: Alto del paquete (mm) | E17: Peso del paquete (kg) | F17: Base (m²) | G17: Máx. por altura del autoelevador | H17: Máx. por estabilidad | I17: Máx. por carga del piso | J17: Máx. por pila | K17: Pilas | L17: Paquetes por pila | M17: Alto de la pila (m) | N17: Peso de la pila (t) | O17: Carga en el piso (t/m²) | P17: Presión en los tacos (MPa) | Q17: Control tacos | R17: Centro de carga (mm) | S17: Capacidad del autoelevador a ese centro (kg) | T17: Control autoelevador | U17: Frente con separación (m) | V17: Fondo con separación (m) | W17: m² de las pilas | X17: Qué limita
A18: =A7 -> MP-01 | B18: =TEXT(F7,"#,##0")&" × "&TEXT(E7,"#,##0") -> 2,440 × 1,220 | C18: =V7 -> 21 | D18: =N7 -> 118.9 | E18: =M7 -> 441.65293 | F18: =E7*F7/1000000 -> 2.9768 | G18: =INT(H_ELEV/D18) -> 25 | H18: =INT(REL_PILA*MIN(E7,F7)/D18) -> 30 | I18: =INT(Q_PISO*F18*1000/E18) -> 33 | J18: =MAX(1,MIN(G18,H18,I18)) -> 25 | K18: =MAX(1,ROUNDUP(C18/J18,0)) -> 1 | L18: =ROUNDUP(C18/K18,0) -> 21 | M18: =L18*D18/1000 -> 2.4969 | N18: =L18*E18/1000 -> 9.2747116 | O18: =N18/F18 -> 3.115665 | P18: =L18*E18*9.81/(N_TACO*A_TACO/1000*E7/1000)/1000000 -> 0.24859268 | Q18: =IF(P18<=SIG_MAD,"OK","Revisar") -> OK | R18: =E7/2 -> 610 | S18: =CAP_AUTO*CC_AUTO/MAX(CC_AUTO,R18) -> 4918.0328 | T18: =IF(E18<=S18,"OK","No levanta") -> OK | U18: =F7/1000+SEP_PILA -> 2.94 | V18: =E7/1000+SEP_PILA -> 1.72 | W18: =K18*U18*(V18+CALLE/2) -> 12.4068 | X18: =IF(C18<=J18,"Entra en 1 pila",IF(J18=G18,"Altura del autoelevador",IF(J18=I18,"Carga del piso","Estabilidad"))) -> Entra en 1 pila
A19: =A8 -> MP-02 | B19: =TEXT(F8,"#,##0")&" × "&TEXT(E8,"#,##0") -> 2,440 × 1,220 | C19: =V8 -> 4 | D19: =N8 -> 123.75 | E19: =M8 -> 554.98715 | F19: =E8*F8/1000000 -> 2.9768 | G19: =INT(H_ELEV/D19) -> 24 | H19: =INT(REL_PILA*MIN(E8,F8)/D19) -> 29 | I19: =INT(Q_PISO*F19*1000/E19) -> 26 | J19: =MAX(1,MIN(G19,H19,I19)) -> 24 | K19: =MAX(1,ROUNDUP(C19/J19,0)) -> 1 | L19: =ROUNDUP(C19/K19,0) -> 4 | M19: =L19*D19/1000 -> 0.495 | N19: =L19*E19/1000 -> 2.2199486 | O19: =N19/F19 -> 0.74575 | P19: =L19*E19*9.81/(N_TACO*A_TACO/1000*E8/1000)/1000000 -> 0.059501901 | Q19: =IF(P19<=SIG_MAD,"OK","Revisar") -> OK | R19: =E8/2 -> 610 | S19: =CAP_AUTO*CC_AUTO/MAX(CC_AUTO,R19) -> 4918.0328 | T19: =IF(E19<=S19,"OK","No levanta") -> OK | U19: =F8/1000+SEP_PILA -> 2.94 | V19: =E8/1000+SEP_PILA -> 1.72 | W19: =K19*U19*(V19+CALLE/2) -> 12.4068 | X19: =IF(C19<=J19,"Entra en 1 pila",IF(J19=G19,"Altura del autoelevador",IF(J19=I19,"Carga del piso","Estabilidad"))) -> Entra en 1 pila
A20: =A9 -> MP-03 | B20: =TEXT(F9,"#,##0")&" × "&TEXT(E9,"#,##0") -> 2,000 × 1,000 | C20: =V9 -> 23 | D20: =N9 -> 138.4 | E20: =M9 -> 602.88 | F20: =E9*F9/1000000 -> 2 | G20: =INT(H_ELEV/D20) -> 21 | H20: =INT(REL_PILA*MIN(E9,F9)/D20) -> 21 | I20: =INT(Q_PISO*F20*1000/E20) -> 16 | J20: =MAX(1,MIN(G20,H20,I20)) -> 16 | K20: =MAX(1,ROUNDUP(C20/J20,0)) -> 2 | L20: =ROUNDUP(C20/K20,0) -> 12 | M20: =L20*D20/1000 -> 1.6608 | N20: =L20*E20/1000 -> 7.23456 | O20: =N20/F20 -> 3.61728 | P20: =L20*E20*9.81/(N_TACO*A_TACO/1000*E9/1000)/1000000 -> 0.23657011 | Q20: =IF(P20<=SIG_MAD,"OK","Revisar") -> OK | R20: =E9/2 -> 500 | S20: =CAP_AUTO*CC_AUTO/MAX(CC_AUTO,R20) -> 5000 | T20: =IF(E20<=S20,"OK","No levanta") -> OK | U20: =F9/1000+SEP_PILA -> 2.5 | V20: =E9/1000+SEP_PILA -> 1.5 | W20: =K20*U20*(V20+CALLE/2) -> 20 | X20: =IF(C20<=J20,"Entra en 1 pila",IF(J20=G20,"Altura del autoelevador",IF(J20=I20,"Carga del piso","Estabilidad"))) -> Carga del piso
A21: =A10 -> MP-04 | B21: =TEXT(F10,"#,##0")&" × "&TEXT(E10,"#,##0") -> 3,000 × 1,500 | C21: =V10 -> 3 | D21: =N10 -> 138 | E21: =M10 -> 1342.35 | F21: =E10*F10/1000000 -> 4.5 | G21: =INT(H_ELEV/D21) -> 21 | H21: =INT(REL_PILA*MIN(E10,F10)/D21) -> 32 | I21: =INT(Q_PISO*F21*1000/E21) -> 16 | J21: =MAX(1,MIN(G21,H21,I21)) -> 16 | K21: =MAX(1,ROUNDUP(C21/J21,0)) -> 1 | L21: =ROUNDUP(C21/K21,0) -> 3 | M21: =L21*D21/1000 -> 0.414 | N21: =L21*E21/1000 -> 4.02705 | O21: =N21/F21 -> 0.8949 | P21: =L21*E21*9.81/(N_TACO*A_TACO/1000*E10/1000)/1000000 -> 0.08778969 | Q21: =IF(P21<=SIG_MAD,"OK","Revisar") -> OK | R21: =E10/2 -> 750 | S21: =CAP_AUTO*CC_AUTO/MAX(CC_AUTO,R21) -> 4000 | T21: =IF(E21<=S21,"OK","No levanta") -> OK | U21: =F10/1000+SEP_PILA -> 3.5 | V21: =E10/1000+SEP_PILA -> 2 | W21: =K21*U21*(V21+CALLE/2) -> 15.75 | X21: =IF(C21<=J21,"Entra en 1 pila",IF(J21=G21,"Altura del autoelevador",IF(J21=I21,"Carga del piso","Estabilidad"))) -> Entra en 1 pila
A22: =A11 -> MP-11 | B22: =TEXT(F11,"#,##0")&" × "&TEXT(E11,"#,##0") -> 3,000 × 1,500 | C22: =V11 -> 6 | D22: =N11 -> 122.4 | E22: =M11 -> 791.28 | F22: =E11*F11/1000000 -> 4.5 | G22: =INT(H_ELEV/D22) -> 24 | H22: =INT(REL_PILA*MIN(E11,F11)/D22) -> 36 | I22: =INT(Q_PISO*F22*1000/E22) -> 28 | J22: =MAX(1,MIN(G22,H22,I22)) -> 24 | K22: =MAX(1,ROUNDUP(C22/J22,0)) -> 1 | L22: =ROUNDUP(C22/K22,0) -> 6 | M22: =L22*D22/1000 -> 0.7344 | N22: =L22*E22/1000 -> 4.74768 | O22: =N22/F22 -> 1.05504 | P22: =L22*E22*9.81/(N_TACO*A_TACO/1000*E11/1000)/1000000 -> 0.10349942 | Q22: =IF(P22<=SIG_MAD,"OK","Revisar") -> OK | R22: =E11/2 -> 750 | S22: =CAP_AUTO*CC_AUTO/MAX(CC_AUTO,R22) -> 4000 | T22: =IF(E22<=S22,"OK","No levanta") -> OK | U22: =F11/1000+SEP_PILA -> 3.5 | V22: =E11/1000+SEP_PILA -> 2 | W22: =K22*U22*(V22+CALLE/2) -> 15.75 | X22: =IF(C22<=J22,"Entra en 1 pila",IF(J22=G22,"Altura del autoelevador",IF(J22=I22,"Carga del piso","Estabilidad"))) -> Entra en 1 pila
A23: =A12 -> MP-12 | B23: =TEXT(F12,"#,##0")&" × "&TEXT(E12,"#,##0") -> 3,000 × 1,500 | C23: =V12 -> 6 | D23: =N12 -> 114.25 | E23: =M12 -> 503.38125 | F23: =E12*F12/1000000 -> 4.5 | G23: =INT(H_ELEV/D23) -> 26 | H23: =INT(REL_PILA*MIN(E12,F12)/D23) -> 39 | I23: =INT(Q_PISO*F23*1000/E23) -> 44 | J23: =MAX(1,MIN(G23,H23,I23)) -> 26 | K23: =MAX(1,ROUNDUP(C23/J23,0)) -> 1 | L23: =ROUNDUP(C23/K23,0) -> 6 | M23: =L23*D23/1000 -> 0.6855 | N23: =L23*E23/1000 -> 3.0202875 | O23: =N23/F23 -> 0.671175 | P23: =L23*E23*9.81/(N_TACO*A_TACO/1000*E12/1000)/1000000 -> 0.065842267 | Q23: =IF(P23<=SIG_MAD,"OK","Revisar") -> OK | R23: =E12/2 -> 750 | S23: =CAP_AUTO*CC_AUTO/MAX(CC_AUTO,R23) -> 4000 | T23: =IF(E23<=S23,"OK","No levanta") -> OK | U23: =F12/1000+SEP_PILA -> 3.5 | V23: =E12/1000+SEP_PILA -> 2 | W23: =K23*U23*(V23+CALLE/2) -> 15.75 | X23: =IF(C23<=J23,"Entra en 1 pila",IF(J23=G23,"Altura del autoelevador",IF(J23=I23,"Carga del piso","Estabilidad"))) -> Entra en 1 pila
A24: Total | K24: =SUM(K18:K23) -> 7 | W24: =SUM(W18:W23) -> 92.0636
B26: Frente total de las pilas (m) | E26: =SUMPRODUCT(K18:K23,U18:U23) -> 21.38
B27: Solo el piso de las pilas, sin calle (m²) | E27: =SUMPRODUCT(K18:K23,U18:U23,V18:V23) -> 38.6136
B28: Calle compartida: la mitad que le toca a la chapa (m²) | E28: =E26*CALLE/2 -> 53.45
B29: Superficie de la chapa (pilas + media calle, mismo criterio que los racks) (m²) | E29: =E27+E28 -> 92.0636
A30: Una pila por formato si entra; si no, varias. Siempre se toma el paquete de arriba. Al recibir, el remanente se pasa arriba de la entrega nueva (FIFO por colada). Los tacos van alineados en columna: el peso baja por los tacos y la hoja no se dobla.
A32: 3) FLEJES: UN ROLLO = UNA TANDA DE LA MATRIZ
A33: Código | B33: Material | C33: Proveedor | D33: Espesor (mm) | E33: Ancho (mm) | F33: Matriz (fila Datos) | G33: kg de fleje por pieza | H33: Piezas por día | I33: kg por día | J33: Tanda (piezas) | K33: Se prensa cada (días) | L33: Tandas por rollo | M33: Peso del rollo (kg) | N33: Ø exterior (mm) | O33: Días que dura | P33: Plazo mín. | Q33: Plazo máx. | R33: Consumo promedio (kg/día) | S33: Seguridad (rollos) | T33: Días entre pedidos | U33: Rollos por pedido | V33: Stock máximo (rollos) | W33: Stock máximo (t) | X33: Control desbobinador
A34: MP-05 | B34: =Datos!B56 -> Fleje LAF 0,9 × 93,05 mm (cúpula 1 kg) | C34: =Datos!D56 -> Pradecon | D34: 0.9 | E34: 93.05 | F34: =Datos!B17 -> C1 | G34: =Datos!E56/Datos!G17 -> 0.059694403 | H34: =Datos!D17 -> 911.79288 | I34: =H34*G34 -> 54.428931 | J34: =Datos!F17 -> 3647.1715 | K34: =Datos!E17 -> 4 | L34: 1 | M34: =J34*G34*L34 -> 217.71572 | N34: =SQRT(DI_ROLLO^2+4*M34/(PI()*E34*DENS/1000000)) -> 798.4772 | O34: =M34/I34 -> 4 | P34: =Datos!G56 -> 7 | Q34: =Datos!H56 -> 10 | R34: =Datos!E56/DIAS_ANIO -> 50.397158 | S34: =MAX(1,ROUNDUP(MAX(0,I34*Q34-R34*(P34+Q34)/2)/M34,0)) -> 1 | T34: =VLOOKUP(C34,Pedidos!$A$7:$C$60,3,FALSE()) -> 20 | U34: =ROUNDUP(I34*T34/M34,0) -> 5 | V34: =S34+U34 -> 6 | W34: =V34*M34/1000 -> 1.3062943 | X34: =IF(M34<=CAP_DESB,"OK","Pasa el desbobinador") -> OK
A35: MP-13 | B35: =Datos!B57 -> Fleje LAF 0,9 × 100,6 mm (fondo 1 kg) | C35: =Datos!D57 -> Pradecon | D35: 0.9 | E35: 100.6 | F35: =Datos!B18 -> F1 | G35: =Datos!E57/Datos!G18 -> 0.069216049 | H35: =Datos!D18 -> 911.79288 | I35: =H35*G35 -> 63.1107 | J35: =Datos!F18 -> 3647.1715 | K35: =Datos!E18 -> 4 | L35: 1 | M35: =J35*G35*L35 -> 252.4428 | N35: =SQRT(DI_ROLLO^2+4*M35/(PI()*E35*DENS/1000000)) -> 815.52092 | O35: =M35/I35 -> 4 | P35: =Datos!G57 -> 7 | Q35: =Datos!H57 -> 10 | R35: =Datos!E57/DIAS_ANIO -> 58.435833 | S35: =MAX(1,ROUNDUP(MAX(0,I35*Q35-R35*(P35+Q35)/2)/M35,0)) -> 1 | T35: =VLOOKUP(C35,Pedidos!$A$7:$C$60,3,FALSE()) -> 20 | U35: =ROUNDUP(I35*T35/M35,0) -> 5 | V35: =S35+U35 -> 6 | W35: =V35*M35/1000 -> 1.5146568 | X35: =IF(M35<=CAP_DESB,"OK","Pasa el desbobinador") -> OK
A36: MP-06 | B36: =Datos!B58 -> Fleje LAF 1,25 × 162,1 mm (cúpula 2,5 kg) | C36: =Datos!D58 -> Pacheco Chapas | D36: 1.25 | E36: 162.1 | F36: =Datos!B19 -> C2,5 | G36: =Datos!E58/Datos!G19 -> 0.25321722 | H36: =Datos!D19 -> 63.568523 | I36: =H36*G36 -> 16.096645 | J36: =Datos!F19 -> 1017.0964 | K36: =Datos!E19 -> 16 | L36: 1 | M36: =J36*G36*L36 -> 257.54631 | N36: =SQRT(DI_ROLLO^2+4*M36/(PI()*E36*DENS/1000000)) -> 718.16644 | O36: =M36/I36 -> 16 | P36: =Datos!G58 -> 7 | Q36: =Datos!H58 -> 10 | R36: =Datos!E58/DIAS_ANIO -> 14.9043 | S36: =MAX(1,ROUNDUP(MAX(0,I36*Q36-R36*(P36+Q36)/2)/M36,0)) -> 1 | T36: =VLOOKUP(C36,Pedidos!$A$7:$C$60,3,FALSE()) -> 10 | U36: =ROUNDUP(I36*T36/M36,0) -> 1 | V36: =S36+U36 -> 2 | W36: =V36*M36/1000 -> 0.51509262 | X36: =IF(M36<=CAP_DESB,"OK","Pasa el desbobinador") -> OK
A37: MP-14 | B37: =Datos!B59 -> Fleje LAF 1,25 × 146,1 mm (fondo 2,5 kg) | C37: =Datos!D59 -> Pacheco Chapas | D37: 1.25 | E37: 146.1 | F37: =Datos!B20 -> F2,5 | G37: =Datos!E59/Datos!G20 -> 0.20517044 | H37: =Datos!D20 -> 63.568523 | I37: =H37*G37 -> 13.042382 | J37: =Datos!F20 -> 1017.0964 | K37: =Datos!E20 -> 16 | L37: 1 | M37: =J37*G37*L37 -> 208.67811 | N37: =SQRT(DI_ROLLO^2+4*M37/(PI()*E37*DENS/1000000)) -> 699.80896 | O37: =M37/I37 -> 16 | P37: =Datos!G59 -> 7 | Q37: =Datos!H59 -> 10 | R37: =Datos!E59/DIAS_ANIO -> 12.076279 | S37: =MAX(1,ROUNDUP(MAX(0,I37*Q37-R37*(P37+Q37)/2)/M37,0)) -> 1 | T37: =VLOOKUP(C37,Pedidos!$A$7:$C$60,3,FALSE()) -> 10 | U37: =ROUNDUP(I37*T37/M37,0) -> 1 | V37: =S37+U37 -> 2 | W37: =V37*M37/1000 -> 0.41735622 | X37: =IF(M37<=CAP_DESB,"OK","Pasa el desbobinador") -> OK
A38: MP-07 | B38: =Datos!B60 -> Fleje LAF 1,6 × 204,2 mm (cúpula 5 kg) | C38: =Datos!D60 -> Pacheco Chapas | D38: 1.6 | E38: 204.2 | F38: =Datos!B21 -> C5 | G38: =Datos!E60/Datos!G21 -> 0.51398145 | H38: =Datos!D21 -> 287.33696 | I38: =H38*G38 -> 147.68587 | J38: =Datos!F21 -> 2298.6957 | K38: =Datos!E21 -> 8 | L38: 1 | M38: =J38*G38*L38 -> 1181.4869 | N38: =SQRT(DI_ROLLO^2+4*M38/(PI()*E38*DENS/1000000)) -> 1093.8553 | O38: =M38/I38 -> 8 | P38: =Datos!G60 -> 7 | Q38: =Datos!H60 -> 10 | R38: =Datos!E60/DIAS_ANIO -> 136.74617 | S38: =MAX(1,ROUNDUP(MAX(0,I38*Q38-R38*(P38+Q38)/2)/M38,0)) -> 1 | T38: =VLOOKUP(C38,Pedidos!$A$7:$C$60,3,FALSE()) -> 10 | U38: =ROUNDUP(I38*T38/M38,0) -> 2 | V38: =S38+U38 -> 3 | W38: =V38*M38/1000 -> 3.5444608 | X38: =IF(M38<=CAP_DESB,"OK","Pasa el desbobinador") -> OK
A39: MP-08 | B39: =Datos!B61 -> Fleje LAF 1,6 × 177,2 mm (fondo 5 kg) | C39: =Datos!D61 -> Pacheco Chapas | D39: 1.6 | E39: 177.2 | F39: =Datos!B22 -> F5 | G39: =Datos!E61/Datos!G22 -> 0.38562709 | H39: =Datos!D22 -> 287.33696 | I39: =H39*G39 -> 110.80492 | J39: =Datos!F22 -> 2298.6957 | K39: =Datos!E22 -> 8 | L39: 1 | M39: =J39*G39*L39 -> 886.43934 | N39: =SQRT(DI_ROLLO^2+4*M39/(PI()*E39*DENS/1000000)) -> 1034.1406 | O39: =M39/I39 -> 8 | P39: =Datos!G61 -> 7 | Q39: =Datos!H61 -> 10 | R39: =Datos!E61/DIAS_ANIO -> 102.59715 | S39: =MAX(1,ROUNDUP(MAX(0,I39*Q39-R39*(P39+Q39)/2)/M39,0)) -> 1 | T39: =VLOOKUP(C39,Pedidos!$A$7:$C$60,3,FALSE()) -> 10 | U39: =ROUNDUP(I39*T39/M39,0) -> 2 | V39: =S39+U39 -> 3 | W39: =V39*M39/1000 -> 2.659318 | X39: =IF(M39<=CAP_DESB,"OK","Pasa el desbobinador") -> OK
A40: MP-09 | B40: =Datos!B62 -> Fleje LAF 2,0 × 238,7 mm (cúpula 10 kg) | C40: =Datos!D62 -> Pacheco Chapas | D40: 2 | E40: 238.7 | F40: =Datos!B23 -> C10 | G40: =Datos!E62/Datos!G23 -> 0.88096646 | H40: =Datos!D23 -> 17.383176 | I40: =H40*G40 -> 15.313995 | J40: =Datos!F23 -> 278.13082 | K40: =Datos!E23 -> 16 | L40: 1 | M40: =J40*G40*L40 -> 245.02392 | N40: =SQRT(DI_ROLLO^2+4*M40/(PI()*E40*DENS/1000000)) -> 651.58055 | O40: =M40/I40 -> 16 | P40: =Datos!G62 -> 7 | Q40: =Datos!H62 -> 10 | R40: =Datos!E62/DIAS_ANIO -> 14.179625 | S40: =MAX(1,ROUNDUP(MAX(0,I40*Q40-R40*(P40+Q40)/2)/M40,0)) -> 1 | T40: =VLOOKUP(C40,Pedidos!$A$7:$C$60,3,FALSE()) -> 10 | U40: =ROUNDUP(I40*T40/M40,0) -> 1 | V40: =S40+U40 -> 2 | W40: =V40*M40/1000 -> 0.49004785 | X40: =IF(M40<=CAP_DESB,"OK","Pasa el desbobinador") -> OK
A41: MP-10 | B41: =Datos!B63 -> Fleje LAF 2,0 × 205 mm (fondo 10 kg) | C41: =Datos!D63 -> Pacheco Chapas | D41: 2 | E41: 205 | F41: =Datos!B24 -> F10 | G41: =Datos!E63/Datos!G24 -> 0.64370006 | H41: =Datos!D24 -> 17.383176 | I41: =H41*G41 -> 11.189552 | J41: =Datos!F24 -> 278.13082 | K41: =Datos!E24 -> 16 | L41: 1 | M41: =J41*G41*L41 -> 179.03283 | N41: =SQRT(DI_ROLLO^2+4*M41/(PI()*E41*DENS/1000000)) -> 632.23008 | O41: =M41/I41 -> 16 | P41: =Datos!G63 -> 7 | Q41: =Datos!H63 -> 10 | R41: =Datos!E63/DIAS_ANIO -> 10.360696 | S41: =MAX(1,ROUNDUP(MAX(0,I41*Q41-R41*(P41+Q41)/2)/M41,0)) -> 1 | T41: =VLOOKUP(C41,Pedidos!$A$7:$C$60,3,FALSE()) -> 10 | U41: =ROUNDUP(I41*T41/M41,0) -> 1 | V41: =S41+U41 -> 2 | W41: =V41*M41/1000 -> 0.35806566 | X41: =IF(M41<=CAP_DESB,"OK","Pasa el desbobinador") -> OK
B42: Total | V42: =SUM(V34:V41) -> 26 | W42: =SUM(W34:W41) -> 10.805292
A43: kg por pieza = consumo del año del MRP ÷ piezas del año (incluye el esqueleto entre discos). Ø exterior = √(Øint² + 4 × peso ÷ (π × ancho × densidad)).
A45: 4) APILADOR CON PINZA GIRATORIA («volteador»): el rollo más pesado y el más grande fijan el equipo
B46: Para qué: los rollos llegan y se usan parados (ojo horizontal) y se guardan acostados (ojo al cielo), que es como no se deforman. La pinza los agarra por afuera, los lleva y los gira 90°.
B47: Recepción: la pluma baja el rollo del camión a la zona de descarga → el apilador con pinza lo agarra parado, lo lleva a la zona de armado, lo gira 90° y lo apoya acostado en el pallet → el autoelevador con uñas sube el pallet al rack.
B48: A la línea: el autoelevador baja el pallet a la zona de armado → la pinza toma el rollo de arriba, lo gira 90° (parado) y lo carga en el desbobinador. El pallet con los que quedan vuelve al rack.
B50: Rollo más pesado (kg) | L50: =MAX(M34:M41) -> 1181.4869
B51: Ø exterior mayor (mm) | L51: =MAX(N34:N41) -> 1093.8553
B52: Equipo elegido (el primero que sirve, Parametros sección 6) | L52: =IFERROR(INDEX(Parametros!$A$56:$A$59,MATCH("Sí",Parametros!$D$56:$D$59,0)),"Ninguno: pedir a medida") -> Tymbia M103070075 en apilador eléctrico de 2,5 t
B53: Capacidad y plataforma del elegido | L53: =IFERROR(TEXT(INDEX(Parametros!$B$56:$B$59,MATCH("Sí",Parametros!$D$56:$D$59,0)),"#,##0")&" kg · Ø hasta "&TEXT(INDEX(Parametros!$C$56:$C$59,MATCH("Sí",Parametros!$D$56:$D$59,0)),"#,##0")&" mm","—") -> 1,300 kg · Ø hasta 1,100 mm
B54: Ancho que ocupa el rollo más grande con los dos brazos (mm) | L54: =L51+2*PINZA_BRAZO -> 1253.8553
A55: 5) RACK SELECTIVO DE FLEJES: rollos ojo al cielo en pallets, un código por pallet
A56: Código | B56: Peso del rollo (kg) | C56: Ancho = alto acostado (mm) | D56: Ø exterior (mm) | E56: Rollos en el stock máx. | F56: Rollos por pallet por peso | G56: Por alto del nivel | H56: Por estabilidad | I56: Rollos por pallet | J56: Dónde va | K56: Pallets | L56: Peso del pallet lleno (kg) | M56: Presión sobre el rollo de abajo (kPa) | N56: Alto de la pila (mm) | O56: Vuelo del rollo fuera del pallet, por lado (mm) | P56: Lo que ocupa el rollo del pallet (%) | Q56: Control del diámetro | R56: Ancho con los brazos de la pinza (mm)
A57: =A34 -> MP-05 | B57: =M34 -> 217.71572 | C57: =E34 -> 93.05 | D57: =N34 -> 798.4772 | E57: =V34 -> 6 | F57: =INT(KG_POS/B57) -> 4 | G57: =INT(H_NIV/(C57+SEP_ROLLO)) -> 5 | H57: =INT(REL_ROLLO*D57/(C57+SEP_ROLLO)) -> 6 | I57: =MAX(1,MIN(F57,G57,H57)) -> 4 | J57: =IF(B57<=KG_POS,"Niveles altos","Solo en el piso") -> Niveles altos | K57: =ROUNDUP(E57/I57,0) -> 2 | L57: =MIN(E57,I57)*B57 -> 870.8629 | M57: =(MIN(E57,I57)-1)*B57*9.81/(PI()/4*(D57^2-DI_ROLLO^2)/1000000)/1000 -> 21.496923 | N57: =MIN(E57,I57)*(C57+SEP_ROLLO) -> 472.2 | O57: =MAX(0,(D57-PAL_FRENTE)/2) -> 0 | P57: =PI()/4*D57^2/(PAL_FRENTE*PAL_FONDO) -> 0.41728586 | Q57: =IF(D57<=PAL_FRENTE,"Entra en el pallet",IF(O57<=HUECO/2,"Vuela "&TEXT(O57,"0")&" mm por lado, dentro del hueco","No entra: pallet de 1.200 de frente")) -> Entra en el pallet | R57: =D57+2*PINZA_BRAZO -> 958.4772
A58: =A35 -> MP-13 | B58: =M35 -> 252.4428 | C58: =E35 -> 100.6 | D58: =N35 -> 815.52092 | E58: =V35 -> 6 | F58: =INT(KG_POS/B58) -> 3 | G58: =INT(H_NIV/(C58+SEP_ROLLO)) -> 5 | H58: =INT(REL_ROLLO*D58/(C58+SEP_ROLLO)) -> 6 | I58: =MAX(1,MIN(F58,G58,H58)) -> 3 | J58: =IF(B58<=KG_POS,"Niveles altos","Solo en el piso") -> Niveles altos | K58: =ROUNDUP(E58/I58,0) -> 2 | L58: =MIN(E58,I58)*B58 -> 757.3284 | M58: =(MIN(E58,I58)-1)*B58*9.81/(PI()/4*(D58^2-DI_ROLLO^2)/1000000)/1000 -> 15.49411 | N58: =MIN(E58,I58)*(C58+SEP_ROLLO) -> 376.8 | O58: =MAX(0,(D58-PAL_FRENTE)/2) -> 0 | P58: =PI()/4*D58^2/(PAL_FRENTE*PAL_FONDO) -> 0.43529015 | Q58: =IF(D58<=PAL_FRENTE,"Entra en el pallet",IF(O58<=HUECO/2,"Vuela "&TEXT(O58,"0")&" mm por lado, dentro del hueco","No entra: pallet de 1.200 de frente")) -> Entra en el pallet | R58: =D58+2*PINZA_BRAZO -> 975.52092
A59: =A36 -> MP-06 | B59: =M36 -> 257.54631 | C59: =E36 -> 162.1 | D59: =N36 -> 718.16644 | E59: =V36 -> 2 | F59: =INT(KG_POS/B59) -> 3 | G59: =INT(H_NIV/(C59+SEP_ROLLO)) -> 3 | H59: =INT(REL_ROLLO*D59/(C59+SEP_ROLLO)) -> 3 | I59: =MAX(1,MIN(F59,G59,H59)) -> 3 | J59: =IF(B59<=KG_POS,"Niveles altos","Solo en el piso") -> Niveles altos | K59: =ROUNDUP(E59/I59,0) -> 1 | L59: =MIN(E59,I59)*B59 -> 515.09262 | M59: =(MIN(E59,I59)-1)*B59*9.81/(PI()/4*(D59^2-DI_ROLLO^2)/1000000)/1000 -> 12.483078 | N59: =MIN(E59,I59)*(C59+SEP_ROLLO) -> 374.2 | O59: =MAX(0,(D59-PAL_FRENTE)/2) -> 0 | P59: =PI()/4*D59^2/(PAL_FRENTE*PAL_FONDO) -> 0.33756611 | Q59: =IF(D59<=PAL_FRENTE,"Entra en el pallet",IF(O59<=HUECO/2,"Vuela "&TEXT(O59,"0")&" mm por lado, dentro del hueco","No entra: pallet de 1.200 de frente")) -> Entra en el pallet | R59: =D59+2*PINZA_BRAZO -> 878.16644
A60: =A37 -> MP-14 | B60: =M37 -> 208.67811 | C60: =E37 -> 146.1 | D60: =N37 -> 699.80896 | E60: =V37 -> 2 | F60: =INT(KG_POS/B60) -> 4 | G60: =INT(H_NIV/(C60+SEP_ROLLO)) -> 4 | H60: =INT(REL_ROLLO*D60/(C60+SEP_ROLLO)) -> 4 | I60: =MAX(1,MIN(F60,G60,H60)) -> 4 | J60: =IF(B60<=KG_POS,"Niveles altos","Solo en el piso") -> Niveles altos | K60: =ROUNDUP(E60/I60,0) -> 1 | L60: =MIN(E60,I60)*B60 -> 417.35622 | M60: =(MIN(E60,I60)-1)*B60*9.81/(PI()/4*(D60^2-DI_ROLLO^2)/1000000)/1000 -> 11.250942 | N60: =MIN(E60,I60)*(C60+SEP_ROLLO) -> 342.2 | O60: =MAX(0,(D60-PAL_FRENTE)/2) -> 0 | P60: =PI()/4*D60^2/(PAL_FRENTE*PAL_FONDO) -> 0.32052923 | Q60: =IF(D60<=PAL_FRENTE,"Entra en el pallet",IF(O60<=HUECO/2,"Vuela "&TEXT(O60,"0")&" mm por lado, dentro del hueco","No entra: pallet de 1.200 de frente")) -> Entra en el pallet | R60: =D60+2*PINZA_BRAZO -> 859.80896
A61: =A38 -> MP-07 | B61: =M38 -> 1181.4869 | C61: =E38 -> 204.2 | D61: =N38 -> 1093.8553 | E61: =V38 -> 3 | F61: =INT(KG_POS/B61) -> 0 | G61: =INT(H_NIV/(C61+SEP_ROLLO)) -> 3 | H61: =INT(REL_ROLLO*D61/(C61+SEP_ROLLO)) -> 4 | I61: =MAX(1,MIN(F61,G61,H61)) -> 1 | J61: =IF(B61<=KG_POS,"Niveles altos","Solo en el piso") -> Solo en el piso | K61: =ROUNDUP(E61/I61,0) -> 3 | L61: =MIN(E61,I61)*B61 -> 1181.4869 | M61: =(MIN(E61,I61)-1)*B61*9.81/(PI()/4*(D61^2-DI_ROLLO^2)/1000000)/1000 -> 0 | N61: =MIN(E61,I61)*(C61+SEP_ROLLO) -> 229.2 | O61: =MAX(0,(D61-PAL_FRENTE)/2) -> 46.927653 | P61: =PI()/4*D61^2/(PAL_FRENTE*PAL_FONDO) -> 0.78312014 | Q61: =IF(D61<=PAL_FRENTE,"Entra en el pallet",IF(O61<=HUECO/2,"Vuela "&TEXT(O61,"0")&" mm por lado, dentro del hueco","No entra: pallet de 1.200 de frente")) -> Vuela 47 mm por lado, dentro del hueco | R61: =D61+2*PINZA_BRAZO -> 1253.8553
A62: =A39 -> MP-08 | B62: =M39 -> 886.43934 | C62: =E39 -> 177.2 | D62: =N39 -> 1034.1406 | E62: =V39 -> 3 | F62: =INT(KG_POS/B62) -> 1 | G62: =INT(H_NIV/(C62+SEP_ROLLO)) -> 3 | H62: =INT(REL_ROLLO*D62/(C62+SEP_ROLLO)) -> 5 | I62: =MAX(1,MIN(F62,G62,H62)) -> 1 | J62: =IF(B62<=KG_POS,"Niveles altos","Solo en el piso") -> Niveles altos | K62: =ROUNDUP(E62/I62,0) -> 3 | L62: =MIN(E62,I62)*B62 -> 886.43934 | M62: =(MIN(E62,I62)-1)*B62*9.81/(PI()/4*(D62^2-DI_ROLLO^2)/1000000)/1000 -> 0 | N62: =MIN(E62,I62)*(C62+SEP_ROLLO) -> 202.2 | O62: =MAX(0,(D62-PAL_FRENTE)/2) -> 17.07029 | P62: =PI()/4*D62^2/(PAL_FRENTE*PAL_FONDO) -> 0.69995125 | Q62: =IF(D62<=PAL_FRENTE,"Entra en el pallet",IF(O62<=HUECO/2,"Vuela "&TEXT(O62,"0")&" mm por lado, dentro del hueco","No entra: pallet de 1.200 de frente")) -> Vuela 17 mm por lado, dentro del hueco | R62: =D62+2*PINZA_BRAZO -> 1194.1406
A63: =A40 -> MP-09 | B63: =M40 -> 245.02392 | C63: =E40 -> 238.7 | D63: =N40 -> 651.58055 | E63: =V40 -> 2 | F63: =INT(KG_POS/B63) -> 4 | G63: =INT(H_NIV/(C63+SEP_ROLLO)) -> 2 | H63: =INT(REL_ROLLO*D63/(C63+SEP_ROLLO)) -> 2 | I63: =MAX(1,MIN(F63,G63,H63)) -> 2 | J63: =IF(B63<=KG_POS,"Niveles altos","Solo en el piso") -> Niveles altos | K63: =ROUNDUP(E63/I63,0) -> 1 | L63: =MIN(E63,I63)*B63 -> 490.04785 | M63: =(MIN(E63,I63)-1)*B63*9.81/(PI()/4*(D63^2-DI_ROLLO^2)/1000000)/1000 -> 18.381929 | N63: =MIN(E63,I63)*(C63+SEP_ROLLO) -> 527.4 | O63: =MAX(0,(D63-PAL_FRENTE)/2) -> 0 | P63: =PI()/4*D63^2/(PAL_FRENTE*PAL_FONDO) -> 0.27787205 | Q63: =IF(D63<=PAL_FRENTE,"Entra en el pallet",IF(O63<=HUECO/2,"Vuela "&TEXT(O63,"0")&" mm por lado, dentro del hueco","No entra: pallet de 1.200 de frente")) -> Entra en el pallet | R63: =D63+2*PINZA_BRAZO -> 811.58055
A64: =A41 -> MP-10 | B64: =M41 -> 179.03283 | C64: =E41 -> 205 | D64: =N41 -> 632.23008 | E64: =V41 -> 2 | F64: =INT(KG_POS/B64) -> 5 | G64: =INT(H_NIV/(C64+SEP_ROLLO)) -> 3 | H64: =INT(REL_ROLLO*D64/(C64+SEP_ROLLO)) -> 2 | I64: =MAX(1,MIN(F64,G64,H64)) -> 2 | J64: =IF(B64<=KG_POS,"Niveles altos","Solo en el piso") -> Niveles altos | K64: =ROUNDUP(E64/I64,0) -> 1 | L64: =MIN(E64,I64)*B64 -> 358.06566 | M64: =(MIN(E64,I64)-1)*B64*9.81/(PI()/4*(D64^2-DI_ROLLO^2)/1000000)/1000 -> 15.786743 | N64: =MIN(E64,I64)*(C64+SEP_ROLLO) -> 460 | O64: =MAX(0,(D64-PAL_FRENTE)/2) -> 0 | P64: =PI()/4*D64^2/(PAL_FRENTE*PAL_FONDO) -> 0.26161278 | Q64: =IF(D64<=PAL_FRENTE,"Entra en el pallet",IF(O64<=HUECO/2,"Vuela "&TEXT(O64,"0")&" mm por lado, dentro del hueco","No entra: pallet de 1.200 de frente")) -> Entra en el pallet | R64: =D64+2*PINZA_BRAZO -> 792.23008
A65: Total | K65: =SUM(K57:K64) -> 14
B67: Pallets que solo pueden ir en el piso (rollos de más de KG_POS) | G67: =SUMIF(J57:J64,"Solo en el piso",K57:K64) -> 3
B68: Módulos de rack = el mayor entre (pallets ÷ lugares por módulo) y (pallets de piso ÷ posiciones por nivel) | G68: =MAX(ROUNDUP(K65/(POS_NIV*NIV_FLEJE),0),ROUNDUP(G67/POS_NIV,0)) -> 2
B69: Lugares que da el rack | G69: =G68*POS_NIV*NIV_FLEJE -> 16
B70: m² del rack con media calle (comparte la calle de la chapa) | G70: =G68*MOD_FRENTE*(MOD_FONDO+CALLE/2) -> 16.56
B71: m² de la zona de armado (la pinza arma y desarma los pallets en el piso) | G71: =M2_VOLTEO -> 9
B72: Superficie de flejes (rack + zona de armado) | G72: =G70+G71 -> 25.56
A73: Presión sobre el rollo de abajo = peso de los de arriba ÷ cara del rollo. Es de pocos kPa (el acero aguanta cientos de MPa): acostados no se deforman. Lo que limita es la carga del larguero, el alto del nivel y que la pila no sea más alta que su diámetro.
A74: Ø exterior contra el pallet: el rollo va centrado y entra entero en el lado de 1.000 si mide hasta 1.000 mm. Los del 5 kg miden más: vuelan unos mm por lado sobre el hueco de 100 mm entre pallets, sin tocar el vecino.
A75: 6) OPCIONES PARA GUARDAR LOS FLEJES (m² con su calle o pasillo)
A76: Opción | B76: Cómo es | I76: m² | J76: Elegida
A77: Cunas en el piso (ojo horizontal) | B77: Rollos parados en cunas de UPN de 2,5 m (propuesta anterior): 3 cunas + calle. Se manipulan sin volteador, pero apoyados de canto se ovalan si esperan (coil slump) y no se apilan. | I77: =3*2.5*(1.2+CALLE/2) -> 27.75 | J77: No
A78: Pallets ojo al cielo en el piso | B78: Los mismos pallets del rack, en el piso (sin rack). Más barato, pero ocupa una posición de piso por pallet. | I78: =K65*(1.2+SEP_PILA)*(1+SEP_PILA)+K65*(1.2+SEP_PILA)*CALLE/2 -> 95.2 | J78: No
A79: Rack selectivo + pinza (elegida) | B79: Pallets por código en 4 alturas: los pesados abajo, el stock arriba. El apilador con pinza giratoria arma los pallets en una zona al lado del rack. | I79: =G72 -> 25.56 | J79: Sí
A80: Rack cantilever para rollos | B80: Brazos con rollos colgados del ojo. Para rollos anchos y pesados; con 8 anchos chicos desperdicia brazos y es caro. | I80: ="Más que el selectivo" -> Más que el selectivo | J80: No

Sheet Casquetes
A1: CASQUETES DE CARROS — cómo vienen las cúpulas y los fondos (como Fadesa)
A2: Compra nacional en contenedores, ≈ 40 días de demora, se pide según la demanda. Acá se dimensiona el contenedor: cuántas cúpulas y fondos entran, cuánto pesa y cada cuánto se pide.
A3: ▶ Columna N: casquetes por contenedor. Columna S: peso. Columna V: contenedores por pedido.
A5: 1) CÓMO LO HACE FADESA (consulta a Pablo Delmas)
A6: Casquetes de 10", 12" y 15" × 3,20 mm y 15" × 4,75 mm: las pulgadas son el diámetro. Son los mismos tres de FLAMA (MP-15, MP-16 y MP-17).
A7: Vienen en contenedores e ingresan según la necesidad, atada a la demanda (los pedidos). Demora: unos 40 días. Proveedor: NOVA Ruedas. Contenedor retornable.
A8: Antes (MRP y Word de carros): importados de China, pallet de 400 / 300 / 150 u, contenedor de 20' cada 50 días hábiles y 54 a 68 días hábiles de plazo. Se corrige.
A10: 2) SUPUESTOS DEL CONTENEDOR Y DEL PEDIDO
A11: Parámetro | B11: Valor | C11: Unidad | D11: Nombre | E11: Fuente / criterio
A12: Demora del proveedor | B12: 40 | C12: días corridos | D12: CQ_PLAZO | E12: Fadesa: «40 días aproximadamente la demora»
A13: Variación de la demora (±) | B13: 5 | C13: días corridos | D13: CQ_VAR | E13: Supuesto
A14: Plazo mínimo | B14: =ROUND((CQ_PLAZO-CQ_VAR)*5/7,0) -> 25 | C14: días hábiles | D14: CQ_PMIN | E14: 5 días hábiles por cada 7 corridos
A15: Plazo máximo | B15: =ROUND((CQ_PLAZO+CQ_VAR)*5/7,0) -> 32 | C15: días hábiles | D15: CQ_PMAX | E15: Ídem
A16: Días entre pedidos | B16: 20 | C16: días hábiles | D16: CQ_CADA | E16: Un pedido por mes con las tres medidas; se pide solo lo que falta (como Fadesa, según demanda)
A17: Contenedor: largo interior | B17: 1160 | C17: mm | D17: CQ_LARGO | E17: Contenedor metálico de 1.200 × 1.000 (la base del pallet de flejes), paredes de 20 mm
A18: Contenedor: ancho interior | B18: 960 | C18: mm | D18: CQ_ANCHO | E18: Ídem
A19: Alto útil de carga | B19: 800 | C19: mm | D19: CQ_ALTO | E19: Con el contenedor en el piso, la pieza de arriba queda a ≈ 0,95 m: se saca a mano sin agacharse ni subir
A20: Base del contenedor (patas, entrada de uñas) | B20: 150 | C20: mm | D20: CQ_BASE | E20: Supuesto
A21: Peso bruto máximo | B21: 1000 | C21: kg | D21: CQ_KG | E21: Rack de 2.000 kg por nivel con 2 contenedores; mismo límite que el pallet de flejes
A22: Tara del contenedor | B22: 120 | C22: kg | D22: CQ_TARA | E22: Contenedor metálico apilable, supuesto
A23: Alto del borde recto del casquete (pollera) | B23: 20 | C23: mm | D23: CQ_POLL | E23: Supuesto: el tramo cilíndrico del borde, antes de que empiece la curva; es lo que encastra en el cuerpo. Medir en una muestra
A25: 3) CUÁNTO ENTRA EN UN CONTENEDOR — columnas anidadas, mitad cúpulas y mitad fondos
A26: Código | B26: Casquete | C26: Ø (mm) | D26: Profundidad (mm) | E26: Espesor (mm) | F26: Peso (kg) | G26: Paso de anidado (mm) | H26: Columnas a lo largo | I26: Columnas a lo ancho | J26: Columnas | K26: Piezas por columna | L26: Por alto | M26: Por peso | N26: Por contenedor | O26: Cúpulas | P26: Fondos | Q26: Manda | R26: Alto de la carga (mm) | S26: Peso bruto (kg) | T26: Consumo pico (u/día) | U26: Días que dura (pico) | V26: Contenedores por pedido | W26: Stock máx. (contenedores)
A27: MP-15 | B27: Casquete 10" × 3,2 (carro 25 kg) | C27: 276.5 | D27: 87 | E27: 3.2 | F27: 2.44 | G27: =CQ_POLL+E27 -> 23.2 | H27: =INT(CQ_LARGO/C27) -> 4 | I27: =INT(CQ_ANCHO/C27) -> 3 | J27: =H27*I27 -> 12 | K27: =1+INT((CQ_ALTO-D27)/G27) -> 31 | L27: =J27*K27 -> 372 | M27: =INT((CQ_KG-CQ_TARA)/F27) -> 360 | N27: =2*INT(MIN(L27,M27)/2) -> 360 | O27: =N27/2 -> 180 | P27: =N27/2 -> 180 | Q27: =IF(L27<=M27,"El alto","El peso") -> El peso | R27: =D27+(ROUNDUP(N27/J27,0)-1)*G27 -> 759.8 | S27: =N27*F27+CQ_TARA -> 998.4 | T27: =INDEX(Stock_MP!$H:$H,MATCH($A27,Stock_MP!$B:$B,0)) -> 6.9957945 | U27: =N27/T27 -> 51.459488 | V27: =INDEX(Stock_MP!$P:$P,MATCH($A27,Stock_MP!$B:$B,0)) -> 1 | W27: =INDEX(Stock_MP!$S:$S,MATCH($A27,Stock_MP!$B:$B,0))/N27 -> 1.1090394
A28: MP-16 | B28: Casquete 12" × 3,2 (carro 50 kg) | C28: 320 | D28: 105 | E28: 3.2 | F28: 3.36 | G28: =CQ_POLL+E28 -> 23.2 | H28: =INT(CQ_LARGO/C28) -> 3 | I28: =INT(CQ_ANCHO/C28) -> 3 | J28: =H28*I28 -> 9 | K28: =1+INT((CQ_ALTO-D28)/G28) -> 30 | L28: =J28*K28 -> 270 | M28: =INT((CQ_KG-CQ_TARA)/F28) -> 261 | N28: =2*INT(MIN(L28,M28)/2) -> 260 | O28: =N28/2 -> 130 | P28: =N28/2 -> 130 | Q28: =IF(L28<=M28,"El alto","El peso") -> El peso | R28: =D28+(ROUNDUP(N28/J28,0)-1)*G28 -> 754.6 | S28: =N28*F28+CQ_TARA -> 993.6 | T28: =INDEX(Stock_MP!$H:$H,MATCH($A28,Stock_MP!$B:$B,0)) -> 15.375915 | U28: =N28/T28 -> 16.909563 | V28: =INDEX(Stock_MP!$P:$P,MATCH($A28,Stock_MP!$B:$B,0)) -> 2 | W28: =INDEX(Stock_MP!$S:$S,MATCH($A28,Stock_MP!$B:$B,0))/N28 -> 2.3318306
A29: MP-17 | B29: Casquete 15" × 4,75 (carros 70 y 100 kg) | C29: 390 | D29: 105 | E29: 4.75 | F29: 6.64 | G29: =CQ_POLL+E29 -> 24.75 | H29: =INT(CQ_LARGO/C29) -> 2 | I29: =INT(CQ_ANCHO/C29) -> 2 | J29: =H29*I29 -> 4 | K29: =1+INT((CQ_ALTO-D29)/G29) -> 29 | L29: =J29*K29 -> 116 | M29: =INT((CQ_KG-CQ_TARA)/F29) -> 132 | N29: =2*INT(MIN(L29,M29)/2) -> 116 | O29: =N29/2 -> 58 | P29: =N29/2 -> 58 | Q29: =IF(L29<=M29,"El alto","El peso") -> El alto | R29: =D29+(ROUNDUP(N29/J29,0)-1)*G29 -> 798 | S29: =N29*F29+CQ_TARA -> 890.24 | T29: =INDEX(Stock_MP!$H:$H,MATCH($A29,Stock_MP!$B:$B,0)) -> 5.5941885 | U29: =N29/T29 -> 20.735805 | V29: =INDEX(Stock_MP!$P:$P,MATCH($A29,Stock_MP!$B:$B,0)) -> 1 | W29: =INDEX(Stock_MP!$S:$S,MATCH($A29,Stock_MP!$B:$B,0))/N29 -> 1.2706001
A31: Ø y profundidad: Word de carros (tabla de piezas del carro; la profundidad del 15" es estimada). Peso: Word de carros, recepción. Ø = diámetro del recipiente (el casquete encastra en el cuerpo).
A32: Cada columna lleva casquetes de una sola clase: las cúpulas (perforadas) en unas columnas y los fondos en otras, así no se mezclan. Si las columnas son impares, la del medio lleva fondos abajo y cúpulas arriba, con un cartón entre medio.
A33: El contenedor es retornable: se devuelve vacío en el camión del pedido siguiente, y es la unidad que se guarda en el rack y se baja al piso para ir sacando piezas.
A35: 4) PEDIDOS A NOVA RUEDAS EN EL AÑO — un pedido por mes con las tres medidas juntas; de cada una se piden solo los contenedores que faltan
A36: Concepto | B36: Ene | C36: Feb | D36: Mar | E36: Abr | F36: May | G36: Jun | H36: Jul | I36: Ago | J36: Sep | K36: Oct | L36: Nov | M36: Dic | N36: Año
A37: Recipientes de carros del mes (balanceo) | B37: =Datos!B30 -> 264.12238 | C37: =Datos!C30 -> 233.04916 | D37: =Datos!D30 -> 279.65899 | E37: =Datos!E30 -> 279.65899 | F37: =Datos!F30 -> 279.65899 | G37: =Datos!G30 -> 248.58577 | H37: =Datos!H30 -> 279.65899 | I37: =Datos!I30 -> 279.65899 | ... M37: =Datos!M30 -> 248.58577 | N37: =SUM(B37:M37) -> 3107.3221
A38: MP-15 · consumo del mes (u) | B38: =INDEX(Stock_MP!$F:$F,MATCH("MP-15",Stock_MP!$B:$B,0))*B$37/$N$37 -> 132.14279 | C38: =INDEX(Stock_MP!$F:$F,MATCH("MP-15",Stock_MP!$B:$B,0))*C$37/$N$37 -> 116.59658 | D38: =INDEX(Stock_MP!$F:$F,MATCH("MP-15",Stock_MP!$B:$B,0))*D$37/$N$37 -> 139.91589 | E38: =INDEX(Stock_MP!$F:$F,MATCH("MP-15",Stock_MP!$B:$B,0))*E$37/$N$37 -> 139.91589 | F38: =INDEX(Stock_MP!$F:$F,MATCH("MP-15",Stock_MP!$B:$B,0))*F$37/$N$37 -> 139.91589 | G38: =INDEX(Stock_MP!$F:$F,MATCH("MP-15",Stock_MP!$B:$B,0))*G$37/$N$37 -> 124.36968 | H38: =INDEX(Stock_MP!$F:$F,MATCH("MP-15",Stock_MP!$B:$B,0))*H$37/$N$37 -> 139.91589 | I38: =INDEX(Stock_MP!$F:$F,MATCH("MP-15",Stock_MP!$B:$B,0))*I$37/$N$37 -> 139.91589 | ... M38: =INDEX(Stock_MP!$F:$F,MATCH("MP-15",Stock_MP!$B:$B,0))*M$37/$N$37 -> 124.36968 | N38: =SUM(B38:M38) -> 1554.621
A39: MP-15 · contenedores en el pedido | B39: =MAX(0,ROUNDUP((INDEX(Stock_MP!$L:$L,MATCH("MP-15",Stock_MP!$B:$B,0))+SUM($B38:C38)-(INDEX(Stock_MP!$L:$L,MATCH("MP-15",Stock_MP!$B:$B,0))+$B38)-$N$27*0)/$N$27,0)) -> 1 | C39: =MAX(0,ROUNDUP((INDEX(Stock_MP!$L:$L,MATCH("MP-15",Stock_MP!$B:$B,0))+SUM($B38:D38)-(INDEX(Stock_MP!$L:$L,MATCH("MP-15",Stock_MP!$B:$B,0))+$B38)-$N$27*SUM($A39:B39))/$N$27,0)) -> 0 | D39: =MAX(0,ROUNDUP((INDEX(Stock_MP!$L:$L,MATCH("MP-15",Stock_MP!$B:$B,0))+SUM($B38:E38)-(INDEX(Stock_MP!$L:$L,MATCH("MP-15",Stock_MP!$B:$B,0))+$B38)-$N$27*SUM($A39:C39))/$N$27,0)) -> 1 | E39: =MAX(0,ROUNDUP((INDEX(Stock_MP!$L:$L,MATCH("MP-15",Stock_MP!$B:$B,0))+SUM($B38:F38)-(INDEX(Stock_MP!$L:$L,MATCH("MP-15",Stock_MP!$B:$B,0))+$B38)-$N$27*SUM($A39:D39))/$N$27,0)) -> 0 | F39: =MAX(0,ROUNDUP((INDEX(Stock_MP!$L:$L,MATCH("MP-15",Stock_MP!$B:$B,0))+SUM($B38:G38)-(INDEX(Stock_MP!$L:$L,MATCH("MP-15",Stock_MP!$B:$B,0))+$B38)-$N$27*SUM($A39:E39))/$N$27,0)) -> 0 | G39: =MAX(0,ROUNDUP((INDEX(Stock_MP!$L:$L,MATCH("MP-15",Stock_MP!$B:$B,0))+SUM($B38:H38)-(INDEX(Stock_MP!$L:$L,MATCH("MP-15",Stock_MP!$B:$B,0))+$B38)-$N$27*SUM($A39:F39))/$N$27,0)) -> 1 | H39: =MAX(0,ROUNDUP((INDEX(Stock_MP!$L:$L,MATCH("MP-15",Stock_MP!$B:$B,0))+SUM($B38:I38)-(INDEX(Stock_MP!$L:$L,MATCH("MP-15",Stock_MP!$B:$B,0))+$B38)-$N$27*SUM($A39:G39))/$N$27,0)) -> 0 | I39: =MAX(0,ROUNDUP((INDEX(Stock_MP!$L:$L,MATCH("MP-15",Stock_MP!$B:$B,0))+SUM($B38:J38)-(INDEX(Stock_MP!$L:$L,MATCH("MP-15",Stock_MP!$B:$B,0))+$B38)-$N$27*SUM($A39:H39))/$N$27,0)) -> 0 | J39: =MAX(0,ROUNDUP((INDEX(Stock_MP!$L:$L,MATCH("MP-15",Stock_MP!$B:$B,0))+SUM($B38:K38)-(INDEX(Stock_MP!$L:$L,MATCH("MP-15",Stock_MP!$B:$B,0))+$B38)-$N$27*SUM($A39:I39))/$N$27,0)) -> 1 | ... L39: =MAX(0,ROUNDUP((INDEX(Stock_MP!$L:$L,MATCH("MP-15",Stock_MP!$B:$B,0))+SUM($B38:M38)-(INDEX(Stock_MP!$L:$L,MATCH("MP-15",Stock_MP!$B:$B,0))+$B38)-$N$27*SUM($A39:K39))/$N$27,0)) -> 0 | M39: =MAX(0,ROUNDUP((INDEX(Stock_MP!$L:$L,MATCH("MP-15",Stock_MP!$B:$B,0))+(SUM($B38:$M38)+$B38)-(INDEX(Stock_MP!$L:$L,MATCH("MP-15",Stock_MP!$B:$B,0))+$B38)-$N$27*SUM($A39:L39))/$N$27,0)) -> 1 | N39: =SUM(B39:M39) -> 5
A40: MP-15 · stock a fin de mes (u) | B40: =(INDEX(Stock_MP!$L:$L,MATCH("MP-15",Stock_MP!$B:$B,0))+$B38)+$N$27*0-SUM($B38:B38) -> 39.25418 | C40: =(INDEX(Stock_MP!$L:$L,MATCH("MP-15",Stock_MP!$B:$B,0))+$B38)+$N$27*SUM($A39:B39)-SUM($B38:C38) -> 282.65761 | D40: =(INDEX(Stock_MP!$L:$L,MATCH("MP-15",Stock_MP!$B:$B,0))+$B38)+$N$27*SUM($A39:C39)-SUM($B38:D38) -> 142.74172 | E40: =(INDEX(Stock_MP!$L:$L,MATCH("MP-15",Stock_MP!$B:$B,0))+$B38)+$N$27*SUM($A39:D39)-SUM($B38:E38) -> 362.82583 | F40: =(INDEX(Stock_MP!$L:$L,MATCH("MP-15",Stock_MP!$B:$B,0))+$B38)+$N$27*SUM($A39:E39)-SUM($B38:F38) -> 222.90994 | G40: =(INDEX(Stock_MP!$L:$L,MATCH("MP-15",Stock_MP!$B:$B,0))+$B38)+$N$27*SUM($A39:F39)-SUM($B38:G38) -> 98.540255 | H40: =(INDEX(Stock_MP!$L:$L,MATCH("MP-15",Stock_MP!$B:$B,0))+$B38)+$N$27*SUM($A39:G39)-SUM($B38:H38) -> 318.62437 | I40: =(INDEX(Stock_MP!$L:$L,MATCH("MP-15",Stock_MP!$B:$B,0))+$B38)+$N$27*SUM($A39:H39)-SUM($B38:I38) -> 178.70848 | J40: =(INDEX(Stock_MP!$L:$L,MATCH("MP-15",Stock_MP!$B:$B,0))+$B38)+$N$27*SUM($A39:I39)-SUM($B38:J38) -> 46.56569 | ... M40: =(INDEX(Stock_MP!$L:$L,MATCH("MP-15",Stock_MP!$B:$B,0))+$B38)+$N$27*SUM($A39:L39)-SUM($B38:M38) -> 56.775965 | N40: =MIN(B40:M40) -> 39.25418
A42: MP-16 · consumo del mes (u) | B42: =INDEX(Stock_MP!$F:$F,MATCH("MP-16",Stock_MP!$B:$B,0))*B$37/$N$37 -> 290.43395 | C42: =INDEX(Stock_MP!$F:$F,MATCH("MP-16",Stock_MP!$B:$B,0))*C$37/$N$37 -> 256.26525 | D42: =INDEX(Stock_MP!$F:$F,MATCH("MP-16",Stock_MP!$B:$B,0))*D$37/$N$37 -> 307.5183 | E42: =INDEX(Stock_MP!$F:$F,MATCH("MP-16",Stock_MP!$B:$B,0))*E$37/$N$37 -> 307.5183 | F42: =INDEX(Stock_MP!$F:$F,MATCH("MP-16",Stock_MP!$B:$B,0))*F$37/$N$37 -> 307.5183 | G42: =INDEX(Stock_MP!$F:$F,MATCH("MP-16",Stock_MP!$B:$B,0))*G$37/$N$37 -> 273.3496 | H42: =INDEX(Stock_MP!$F:$F,MATCH("MP-16",Stock_MP!$B:$B,0))*H$37/$N$37 -> 307.5183 | I42: =INDEX(Stock_MP!$F:$F,MATCH("MP-16",Stock_MP!$B:$B,0))*I$37/$N$37 -> 307.5183 | ... M42: =INDEX(Stock_MP!$F:$F,MATCH("MP-16",Stock_MP!$B:$B,0))*M$37/$N$37 -> 273.3496 | N42: =SUM(B42:M42) -> 3416.87
A43: MP-16 · contenedores en el pedido | B43: =MAX(0,ROUNDUP((INDEX(Stock_MP!$L:$L,MATCH("MP-16",Stock_MP!$B:$B,0))+SUM($B42:C42)-(INDEX(Stock_MP!$L:$L,MATCH("MP-16",Stock_MP!$B:$B,0))+$B42)-$N$28*0)/$N$28,0)) -> 1 | C43: =MAX(0,ROUNDUP((INDEX(Stock_MP!$L:$L,MATCH("MP-16",Stock_MP!$B:$B,0))+SUM($B42:D42)-(INDEX(Stock_MP!$L:$L,MATCH("MP-16",Stock_MP!$B:$B,0))+$B42)-$N$28*SUM($A43:B43))/$N$28,0)) -> 2 | D43: =MAX(0,ROUNDUP((INDEX(Stock_MP!$L:$L,MATCH("MP-16",Stock_MP!$B:$B,0))+SUM($B42:E42)-(INDEX(Stock_MP!$L:$L,MATCH("MP-16",Stock_MP!$B:$B,0))+$B42)-$N$28*SUM($A43:C43))/$N$28,0)) -> 1 | E43: =MAX(0,ROUNDUP((INDEX(Stock_MP!$L:$L,MATCH("MP-16",Stock_MP!$B:$B,0))+SUM($B42:F42)-(INDEX(Stock_MP!$L:$L,MATCH("MP-16",Stock_MP!$B:$B,0))+$B42)-$N$28*SUM($A43:D43))/$N$28,0)) -> 1 | F43: =MAX(0,ROUNDUP((INDEX(Stock_MP!$L:$L,MATCH("MP-16",Stock_MP!$B:$B,0))+SUM($B42:G42)-(INDEX(Stock_MP!$L:$L,MATCH("MP-16",Stock_MP!$B:$B,0))+$B42)-$N$28*SUM($A43:E43))/$N$28,0)) -> 1 | G43: =MAX(0,ROUNDUP((INDEX(Stock_MP!$L:$L,MATCH("MP-16",Stock_MP!$B:$B,0))+SUM($B42:H42)-(INDEX(Stock_MP!$L:$L,MATCH("MP-16",Stock_MP!$B:$B,0))+$B42)-$N$28*SUM($A43:F43))/$N$28,0)) -> 1 | H43: =MAX(0,ROUNDUP((INDEX(Stock_MP!$L:$L,MATCH("MP-16",Stock_MP!$B:$B,0))+SUM($B42:I42)-(INDEX(Stock_MP!$L:$L,MATCH("MP-16",Stock_MP!$B:$B,0))+$B42)-$N$28*SUM($A43:G43))/$N$28,0)) -> 1 | I43: =MAX(0,ROUNDUP((INDEX(Stock_MP!$L:$L,MATCH("MP-16",Stock_MP!$B:$B,0))+SUM($B42:J42)-(INDEX(Stock_MP!$L:$L,MATCH("MP-16",Stock_MP!$B:$B,0))+$B42)-$N$28*SUM($A43:H43))/$N$28,0)) -> 2 | J43: =MAX(0,ROUNDUP((INDEX(Stock_MP!$L:$L,MATCH("MP-16",Stock_MP!$B:$B,0))+SUM($B42:K42)-(INDEX(Stock_MP!$L:$L,MATCH("MP-16",Stock_MP!$B:$B,0))+$B42)-$N$28*SUM($A43:I43))/$N$28,0)) -> 1 | ... L43: =MAX(0,ROUNDUP((INDEX(Stock_MP!$L:$L,MATCH("MP-16",Stock_MP!$B:$B,0))+SUM($B42:M42)-(INDEX(Stock_MP!$L:$L,MATCH("MP-16",Stock_MP!$B:$B,0))+$B42)-$N$28*SUM($A43:K43))/$N$28,0)) -> 2 | M43: =MAX(0,ROUNDUP((INDEX(Stock_MP!$L:$L,MATCH("MP-16",Stock_MP!$B:$B,0))+(SUM($B42:$M42)+$B42)-(INDEX(Stock_MP!$L:$L,MATCH("MP-16",Stock_MP!$B:$B,0))+$B42)-$N$28*SUM($A43:L43))/$N$28,0)) -> 1 | N43: =SUM(B43:M43) -> 14
A44: MP-16 · stock a fin de mes (u) | B44: =(INDEX(Stock_MP!$L:$L,MATCH("MP-16",Stock_MP!$B:$B,0))+$B42)+$N$28*0-SUM($B42:B42) -> 86.275967 | C44: =(INDEX(Stock_MP!$L:$L,MATCH("MP-16",Stock_MP!$B:$B,0))+$B42)+$N$28*SUM($A43:B43)-SUM($B42:C42) -> 90.010717 | D44: =(INDEX(Stock_MP!$L:$L,MATCH("MP-16",Stock_MP!$B:$B,0))+$B42)+$N$28*SUM($A43:C43)-SUM($B42:D42) -> 302.49242 | E44: =(INDEX(Stock_MP!$L:$L,MATCH("MP-16",Stock_MP!$B:$B,0))+$B42)+$N$28*SUM($A43:D43)-SUM($B42:E42) -> 254.97412 | F44: =(INDEX(Stock_MP!$L:$L,MATCH("MP-16",Stock_MP!$B:$B,0))+$B42)+$N$28*SUM($A43:E43)-SUM($B42:F42) -> 207.45582 | G44: =(INDEX(Stock_MP!$L:$L,MATCH("MP-16",Stock_MP!$B:$B,0))+$B42)+$N$28*SUM($A43:F43)-SUM($B42:G42) -> 194.10622 | H44: =(INDEX(Stock_MP!$L:$L,MATCH("MP-16",Stock_MP!$B:$B,0))+$B42)+$N$28*SUM($A43:G43)-SUM($B42:H42) -> 146.58792 | I44: =(INDEX(Stock_MP!$L:$L,MATCH("MP-16",Stock_MP!$B:$B,0))+$B42)+$N$28*SUM($A43:H43)-SUM($B42:I42) -> 99.069618 | J44: =(INDEX(Stock_MP!$L:$L,MATCH("MP-16",Stock_MP!$B:$B,0))+$B42)+$N$28*SUM($A43:I43)-SUM($B42:J42) -> 328.63567 | ... M44: =(INDEX(Stock_MP!$L:$L,MATCH("MP-16",Stock_MP!$B:$B,0))+$B42)+$N$28*SUM($A43:L43)-SUM($B42:M42) -> 339.83992 | N44: =MIN(B44:M44) -> 86.275967
A46: MP-17 · consumo del mes (u) | B46: =INDEX(Stock_MP!$F:$F,MATCH("MP-17",Stock_MP!$B:$B,0))*B$37/$N$37 -> 105.66801 | C46: =INDEX(Stock_MP!$F:$F,MATCH("MP-17",Stock_MP!$B:$B,0))*C$37/$N$37 -> 93.236475 | D46: =INDEX(Stock_MP!$F:$F,MATCH("MP-17",Stock_MP!$B:$B,0))*D$37/$N$37 -> 111.88377 | E46: =INDEX(Stock_MP!$F:$F,MATCH("MP-17",Stock_MP!$B:$B,0))*E$37/$N$37 -> 111.88377 | F46: =INDEX(Stock_MP!$F:$F,MATCH("MP-17",Stock_MP!$B:$B,0))*F$37/$N$37 -> 111.88377 | G46: =INDEX(Stock_MP!$F:$F,MATCH("MP-17",Stock_MP!$B:$B,0))*G$37/$N$37 -> 99.45224 | H46: =INDEX(Stock_MP!$F:$F,MATCH("MP-17",Stock_MP!$B:$B,0))*H$37/$N$37 -> 111.88377 | I46: =INDEX(Stock_MP!$F:$F,MATCH("MP-17",Stock_MP!$B:$B,0))*I$37/$N$37 -> 111.88377 | ... M46: =INDEX(Stock_MP!$F:$F,MATCH("MP-17",Stock_MP!$B:$B,0))*M$37/$N$37 -> 99.45224 | N46: =SUM(B46:M46) -> 1243.153
A47: MP-17 · contenedores en el pedido | B47: =MAX(0,ROUNDUP((INDEX(Stock_MP!$L:$L,MATCH("MP-17",Stock_MP!$B:$B,0))+SUM($B46:C46)-(INDEX(Stock_MP!$L:$L,MATCH("MP-17",Stock_MP!$B:$B,0))+$B46)-$N$29*0)/$N$29,0)) -> 1 | C47: =MAX(0,ROUNDUP((INDEX(Stock_MP!$L:$L,MATCH("MP-17",Stock_MP!$B:$B,0))+SUM($B46:D46)-(INDEX(Stock_MP!$L:$L,MATCH("MP-17",Stock_MP!$B:$B,0))+$B46)-$N$29*SUM($A47:B47))/$N$29,0)) -> 1 | D47: =MAX(0,ROUNDUP((INDEX(Stock_MP!$L:$L,MATCH("MP-17",Stock_MP!$B:$B,0))+SUM($B46:E46)-(INDEX(Stock_MP!$L:$L,MATCH("MP-17",Stock_MP!$B:$B,0))+$B46)-$N$29*SUM($A47:C47))/$N$29,0)) -> 1 | E47: =MAX(0,ROUNDUP((INDEX(Stock_MP!$L:$L,MATCH("MP-17",Stock_MP!$B:$B,0))+SUM($B46:F46)-(INDEX(Stock_MP!$L:$L,MATCH("MP-17",Stock_MP!$B:$B,0))+$B46)-$N$29*SUM($A47:D47))/$N$29,0)) -> 1 | F47: =MAX(0,ROUNDUP((INDEX(Stock_MP!$L:$L,MATCH("MP-17",Stock_MP!$B:$B,0))+SUM($B46:G46)-(INDEX(Stock_MP!$L:$L,MATCH("MP-17",Stock_MP!$B:$B,0))+$B46)-$N$29*SUM($A47:E47))/$N$29,0)) -> 1 | G47: =MAX(0,ROUNDUP((INDEX(Stock_MP!$L:$L,MATCH("MP-17",Stock_MP!$B:$B,0))+SUM($B46:H46)-(INDEX(Stock_MP!$L:$L,MATCH("MP-17",Stock_MP!$B:$B,0))+$B46)-$N$29*SUM($A47:F47))/$N$29,0)) -> 1 | H47: =MAX(0,ROUNDUP((INDEX(Stock_MP!$L:$L,MATCH("MP-17",Stock_MP!$B:$B,0))+SUM($B46:I46)-(INDEX(Stock_MP!$L:$L,MATCH("MP-17",Stock_MP!$B:$B,0))+$B46)-$N$29*SUM($A47:G47))/$N$29,0)) -> 1 | I47: =MAX(0,ROUNDUP((INDEX(Stock_MP!$L:$L,MATCH("MP-17",Stock_MP!$B:$B,0))+SUM($B46:J46)-(INDEX(Stock_MP!$L:$L,MATCH("MP-17",Stock_MP!$B:$B,0))+$B46)-$N$29*SUM($A47:H47))/$N$29,0)) -> 1 | J47: =MAX(0,ROUNDUP((INDEX(Stock_MP!$L:$L,MATCH("MP-17",Stock_MP!$B:$B,0))+SUM($B46:K46)-(INDEX(Stock_MP!$L:$L,MATCH("MP-17",Stock_MP!$B:$B,0))+$B46)-$N$29*SUM($A47:I47))/$N$29,0)) -> 1 | ... L47: =MAX(0,ROUNDUP((INDEX(Stock_MP!$L:$L,MATCH("MP-17",Stock_MP!$B:$B,0))+SUM($B46:M46)-(INDEX(Stock_MP!$L:$L,MATCH("MP-17",Stock_MP!$B:$B,0))+$B46)-$N$29*SUM($A47:K47))/$N$29,0)) -> 1 | M47: =MAX(0,ROUNDUP((INDEX(Stock_MP!$L:$L,MATCH("MP-17",Stock_MP!$B:$B,0))+(SUM($B46:$M46)+$B46)-(INDEX(Stock_MP!$L:$L,MATCH("MP-17",Stock_MP!$B:$B,0))+$B46)-$N$29*SUM($A47:L47))/$N$29,0)) -> 1 | N47: =SUM(B47:M47) -> 11
A48: MP-17 · stock a fin de mes (u) | B48: =(INDEX(Stock_MP!$L:$L,MATCH("MP-17",Stock_MP!$B:$B,0))+$B46)+$N$29*0-SUM($B46:B46) -> 31.389613 | C48: =(INDEX(Stock_MP!$L:$L,MATCH("MP-17",Stock_MP!$B:$B,0))+$B46)+$N$29*SUM($A47:B47)-SUM($B46:C46) -> 54.153138 | D48: =(INDEX(Stock_MP!$L:$L,MATCH("MP-17",Stock_MP!$B:$B,0))+$B46)+$N$29*SUM($A47:C47)-SUM($B46:D46) -> 58.269368 | E48: =(INDEX(Stock_MP!$L:$L,MATCH("MP-17",Stock_MP!$B:$B,0))+$B46)+$N$29*SUM($A47:D47)-SUM($B46:E46) -> 62.385598 | F48: =(INDEX(Stock_MP!$L:$L,MATCH("MP-17",Stock_MP!$B:$B,0))+$B46)+$N$29*SUM($A47:E47)-SUM($B46:F46) -> 66.501828 | G48: =(INDEX(Stock_MP!$L:$L,MATCH("MP-17",Stock_MP!$B:$B,0))+$B46)+$N$29*SUM($A47:F47)-SUM($B46:G46) -> 83.049588 | H48: =(INDEX(Stock_MP!$L:$L,MATCH("MP-17",Stock_MP!$B:$B,0))+$B46)+$N$29*SUM($A47:G47)-SUM($B46:H46) -> 87.165818 | I48: =(INDEX(Stock_MP!$L:$L,MATCH("MP-17",Stock_MP!$B:$B,0))+$B46)+$N$29*SUM($A47:H47)-SUM($B46:I46) -> 91.282048 | J48: =(INDEX(Stock_MP!$L:$L,MATCH("MP-17",Stock_MP!$B:$B,0))+$B46)+$N$29*SUM($A47:I47)-SUM($B46:J46) -> 101.61404 | ... M48: =(INDEX(Stock_MP!$L:$L,MATCH("MP-17",Stock_MP!$B:$B,0))+$B46)+$N$29*SUM($A47:L47)-SUM($B46:M46) -> 53.904618 | N48: =MIN(B48:M48) -> 31.389613
A50: Contenedores en el pedido a NOVA Ruedas | B50: =B39+B43+B47 -> 3 | C50: =C39+C43+C47 -> 3 | D50: =D39+D43+D47 -> 3 | E50: =E39+E43+E47 -> 2 | F50: =F39+F43+F47 -> 2 | G50: =G39+G43+G47 -> 3 | H50: =H39+H43+H47 -> 2 | I50: =I39+I43+I47 -> 3 | ... N50: =N39+N43+N47 -> 30
A51: Peso del pedido (t) | B51: =(B39*$S$27+B43*$S$28+B47*$S$29)/1000 -> 2.88224 | C51: =(C39*$S$27+C43*$S$28+C47*$S$29)/1000 -> 2.87744 | D51: =(D39*$S$27+D43*$S$28+D47*$S$29)/1000 -> 2.88224 | E51: =(E39*$S$27+E43*$S$28+E47*$S$29)/1000 -> 1.88384 | F51: =(F39*$S$27+F43*$S$28+F47*$S$29)/1000 -> 1.88384 | G51: =(G39*$S$27+G43*$S$28+G47*$S$29)/1000 -> 2.88224 | H51: =(H39*$S$27+H43*$S$28+H47*$S$29)/1000 -> 1.88384 | I51: =(I39*$S$27+I43*$S$28+I47*$S$29)/1000 -> 2.87744 | ... N51: =(N39*$S$27+N43*$S$28+N47*$S$29)/1000 -> 28.69504
A53: Cómo se calcula: el pedido de cada mes llega al mes siguiente (40 días corridos). Se pide lo que falta para cubrir la seguridad y el consumo hasta fin del mes siguiente, en contenedores enteros. Columna N de la fila de stock = el mínimo del año (no baja de la seguridad).
A54: Consumo del mes = consumo del año (Stock_MP) repartido según los recipientes de carros de cada mes. Empieza en enero con la seguridad + el consumo de enero.

Sheet Stock_MP
A1: STOCK DE CADA MATERIA PRIMA — consumo pico, seguridad, pedido y stock máximo (las 125 MP)
A2: Una fila por MP. Consumo pico = producción con sobrestock (factor de la línea), no ventas. Chapa y fleje salen de Chapa_fleje (en paquetes y rollos enteros).
A3: ▶ Columnas M, N, O (cómo se compra), S (stock máximo), U (lugares) y V (cómo se guarda).
A5: Ref. | B5: Código | C5: Material | D5: UM | E5: Proveedor | F5: Consumo del año | G5: Consumo por día (prom.) | H5: Consumo por día (pico) | I5: Plazo mín. | J5: Plazo máx. | K5: Consumo mientras llega | L5: Stock de seguridad | M5: Unidad de compra | N5: Contenido | O5: Cada (días) | P5: Por pedido (unid. de compra) | Q5: Pedidos por año | R5: Almacén | S5: Stock máximo | T5: Cuánto entra en un lugar | U5: Lugares | V5: Cómo se guarda | W5: Línea
A6: =Datos!A52 -> P01 | B6: =Datos!C52 -> MP-01 | C6: =Datos!B52 -> Hoja LAF 0,9 × 1220 × 2440 mm (cuerpo 1 kg) | D6: =Datos!F52 -> hoja | E6: =Datos!D52 -> Hierros Parrotta | F6: =Datos!E52 -> 4502.681 | G6: =F6/DIAS_ANIO -> 18.761171 | H6: =Chapa_fleje!H7 -> 20.262064 | I6: =Datos!G52 -> 10 | J6: =Datos!H52 -> 10 | K6: =G6*(I6+J6)/2 -> 187.61171 | L6: =Chapa_fleje!S7*Chapa_fleje!L7 -> 21 | M6: ="Paquete de "&Chapa_fleje!L7&" hojas (1 tanda)" -> Paquete de 21 hojas (1 tanda) | N6: =Chapa_fleje!L7 -> 21 | O6: =Chapa_fleje!T7 -> 20 | P6: =Chapa_fleje!U7 -> 20 | Q6: =IF(P6*N6=0,0,F6/(P6*N6)) -> 10.720669 | R6: Chapa (pilas en el piso) | S6: =Chapa_fleje!V7*Chapa_fleje!L7 -> 441 | T6: — | U6: =Chapa_fleje!K18 -> 1 | V6: =IFERROR(VLOOKUP(R6,Almacenes!$A$19:$I$32,9,FALSE()),"") -> Paquete sobre sus 3 tacos, una pila por formato hasta el alto que permiten el autoelevador, el piso y la estabilidad (Chapa_fleje sección 2). Se toma el de arriba; al recibir, el remanente pasa arriba (FIFO por colada). Pilas demarcadas con su código, 2 filas enfrentadas sobre la calle. | W6: Manuales
A7: =Datos!A53 -> P02 | B7: =Datos!C53 -> MP-02 | C7: =Datos!B53 -> Hoja LAF 1,25 × 1220 × 2440 mm | D7: =Datos!F53 -> hoja | E7: =Datos!D53 -> Pradecon | F7: =Datos!E53 -> 523.198 | G7: =F7/DIAS_ANIO -> 2.1799917 | H7: =Chapa_fleje!H8 -> 2.3543897 | I7: =Datos!G53 -> 7 | J7: =Datos!H53 -> 10 | K7: =G7*(I7+J7)/2 -> 18.529929 | L7: =Chapa_fleje!S8*Chapa_fleje!L8 -> 19 | M7: ="Paquete de "&Chapa_fleje!L8&" hojas (1 tanda)" -> Paquete de 19 hojas (1 tanda) | N7: =Chapa_fleje!L8 -> 19 | O7: =Chapa_fleje!T8 -> 20 | P7: =Chapa_fleje!U8 -> 3 | Q7: =IF(P7*N7=0,0,F7/(P7*N7)) -> 9.1789123 | R7: Chapa (pilas en el piso) | S7: =Chapa_fleje!V8*Chapa_fleje!L8 -> 76 | T7: — | U7: =Chapa_fleje!K19 -> 1 | V7: =IFERROR(VLOOKUP(R7,Almacenes!$A$19:$I$32,9,FALSE()),"") -> Paquete sobre sus 3 tacos, una pila por formato hasta el alto que permiten el autoelevador, el piso y la estabilidad (Chapa_fleje sección 2). Se toma el de arriba; al recibir, el remanente pasa arriba (FIFO por colada). Pilas demarcadas con su código, 2 filas enfrentadas sobre la calle. | W7: Manuales
A8: =Datos!A54 -> P03 | B8: =Datos!C54 -> MP-03 | C8: =Datos!B54 -> Hoja LAF 1,6 × 1000 × 2000 mm | D8: =Datos!F54 -> hoja | E8: =Datos!D54 -> Pradecon | F8: =Datos!E54 -> 5321.055 | G8: =F8/DIAS_ANIO -> 22.171063 | H8: =Chapa_fleje!H9 -> 23.944747 | I8: =Datos!G54 -> 7 | J8: =Datos!H54 -> 10 | K8: =G8*(I8+J8)/2 -> 188.45403 | L8: =Chapa_fleje!S9*Chapa_fleje!L9 -> 72 | M8: ="Paquete de "&Chapa_fleje!L9&" hojas (1 tanda)" -> Paquete de 24 hojas (1 tanda) | N8: =Chapa_fleje!L9 -> 24 | O8: =Chapa_fleje!T9 -> 20 | P8: =Chapa_fleje!U9 -> 20 | Q8: =IF(P8*N8=0,0,F8/(P8*N8)) -> 11.085531 | R8: Chapa (pilas en el piso) | S8: =Chapa_fleje!V9*Chapa_fleje!L9 -> 552 | T8: — | U8: =Chapa_fleje!K20 -> 2 | V8: =IFERROR(VLOOKUP(R8,Almacenes!$A$19:$I$32,9,FALSE()),"") -> Paquete sobre sus 3 tacos, una pila por formato hasta el alto que permiten el autoelevador, el piso y la estabilidad (Chapa_fleje sección 2). Se toma el de arriba; al recibir, el remanente pasa arriba (FIFO por colada). Pilas demarcadas con su código, 2 filas enfrentadas sobre la calle. | W8: Manuales
A9: =Datos!A55 -> P04 | B9: =Datos!C55 -> MP-04 | C9: =Datos!B55 -> Hoja LAF 2,0 × 1500 × 3000 mm | D9: =Datos!F55 -> hoja | E9: =Datos!D55 -> Pradecon | F9: =Datos!E55 -> 257.529 | G9: =F9/DIAS_ANIO -> 1.0730375 | H9: =Chapa_fleje!H10 -> 1.1588784 | I9: =Datos!G55 -> 7 | J9: =Datos!H55 -> 10 | K9: =G9*(I9+J9)/2 -> 9.1208187 | L9: =Chapa_fleje!S10*Chapa_fleje!L10 -> 19 | M9: ="Paquete de "&Chapa_fleje!L10&" hojas (1 tanda)" -> Paquete de 19 hojas (1 tanda) | N9: =Chapa_fleje!L10 -> 19 | O9: =Chapa_fleje!T10 -> 20 | P9: =Chapa_fleje!U10 -> 2 | Q9: =IF(P9*N9=0,0,F9/(P9*N9)) -> 6.7770789 | R9: Chapa (pilas en el piso) | S9: =Chapa_fleje!V10*Chapa_fleje!L10 -> 57 | T9: — | U9: =Chapa_fleje!K21 -> 1 | V9: =IFERROR(VLOOKUP(R9,Almacenes!$A$19:$I$32,9,FALSE()),"") -> Paquete sobre sus 3 tacos, una pila por formato hasta el alto que permiten el autoelevador, el piso y la estabilidad (Chapa_fleje sección 2). Se toma el de arriba; al recibir, el remanente pasa arriba (FIFO por colada). Pilas demarcadas con su código, 2 filas enfrentadas sobre la calle. | W9: Manuales
A10: =Datos!A56 -> P05 | B10: =Datos!C56 -> MP-05 | C10: =Datos!B56 -> Fleje LAF 0,9 × 93,05 mm (cúpula 1 kg) | D10: =Datos!F56 -> kg | E10: =Datos!D56 -> Pradecon | F10: =Datos!E56 -> 12095.318 | G10: =F10/DIAS_ANIO -> 50.397158 | H10: =Chapa_fleje!I34 -> 54.428931 | I10: =Datos!G56 -> 7 | J10: =Datos!H56 -> 10 | K10: =G10*(I10+J10)/2 -> 428.37585 | L10: =Chapa_fleje!S34*Chapa_fleje!M34 -> 217.71572 | M10: ="Rollo de "&TEXT(Chapa_fleje!M34,"#,##0")&" kg (1 tanda)" -> Rollo de 218 kg (1 tanda) | N10: =Chapa_fleje!M34 -> 217.71572 | O10: =Chapa_fleje!T34 -> 20 | P10: =Chapa_fleje!U34 -> 5 | Q10: =IF(P10*N10=0,0,F10/(P10*N10)) -> 11.111111 | R10: Flejes (rack + volteador) | S10: =Chapa_fleje!W34*1000 -> 1306.2943 | T10: — | U10: =Chapa_fleje!K57 -> 2 | V10: =IFERROR(VLOOKUP(R10,Almacenes!$A$19:$I$32,9,FALSE()),"") -> Rollos ojo al cielo, un código por pallet, con listones entre rollos. Los de más de 1.000 kg (5 kg) en el piso del rack; el resto arriba. La pinza giratoria arma el pallet en la zona de armado y el autoelevador con uñas lo sube al rack; a la línea, al revés: la pinza deja el rollo parado en el desbobinador. | W10: Manuales
A11: =Datos!A57 -> P06 | B11: =Datos!C57 -> MP-13 | C11: =Datos!B57 -> Fleje LAF 0,9 × 100,6 mm (fondo 1 kg) | D11: =Datos!F57 -> kg | E11: =Datos!D57 -> Pradecon | F11: =Datos!E57 -> 14024.6 | G11: =F11/DIAS_ANIO -> 58.435833 | H11: =Chapa_fleje!I35 -> 63.1107 | I11: =Datos!G57 -> 7 | J11: =Datos!H57 -> 10 | K11: =G11*(I11+J11)/2 -> 496.70458 | L11: =Chapa_fleje!S35*Chapa_fleje!M35 -> 252.4428 | M11: ="Rollo de "&TEXT(Chapa_fleje!M35,"#,##0")&" kg (1 tanda)" -> Rollo de 252 kg (1 tanda) | N11: =Chapa_fleje!M35 -> 252.4428 | O11: =Chapa_fleje!T35 -> 20 | P11: =Chapa_fleje!U35 -> 5 | Q11: =IF(P11*N11=0,0,F11/(P11*N11)) -> 11.111111 | R11: Flejes (rack + volteador) | S11: =Chapa_fleje!W35*1000 -> 1514.6568 | T11: — | U11: =Chapa_fleje!K58 -> 2 | V11: =IFERROR(VLOOKUP(R11,Almacenes!$A$19:$I$32,9,FALSE()),"") -> Rollos ojo al cielo, un código por pallet, con listones entre rollos. Los de más de 1.000 kg (5 kg) en el piso del rack; el resto arriba. La pinza giratoria arma el pallet en la zona de armado y el autoelevador con uñas lo sube al rack; a la línea, al revés: la pinza deja el rollo parado en el desbobinador. | W11: Manuales
A12: =Datos!A58 -> P07 | B12: =Datos!C58 -> MP-06 | C12: =Datos!B58 -> Fleje LAF 1,25 × 162,1 mm (cúpula 2,5 kg) | D12: =Datos!F58 -> kg | E12: =Datos!D58 -> Pacheco Chapas | F12: =Datos!E58 -> 3577.032 | G12: =F12/DIAS_ANIO -> 14.9043 | H12: =Chapa_fleje!I36 -> 16.096645 | I12: =Datos!G58 -> 7 | J12: =Datos!H58 -> 10 | K12: =G12*(I12+J12)/2 -> 126.68655 | L12: =Chapa_fleje!S36*Chapa_fleje!M36 -> 257.54631 | M12: ="Rollo de "&TEXT(Chapa_fleje!M36,"#,##0")&" kg (1 tanda)" -> Rollo de 258 kg (1 tanda) | N12: =Chapa_fleje!M36 -> 257.54631 | O12: =Chapa_fleje!T36 -> 10 | P12: =Chapa_fleje!U36 -> 1 | Q12: =IF(P12*N12=0,0,F12/(P12*N12)) -> 13.888888 | R12: Flejes (rack + volteador) | S12: =Chapa_fleje!W36*1000 -> 515.09262 | T12: — | U12: =Chapa_fleje!K59 -> 1 | V12: =IFERROR(VLOOKUP(R12,Almacenes!$A$19:$I$32,9,FALSE()),"") -> Rollos ojo al cielo, un código por pallet, con listones entre rollos. Los de más de 1.000 kg (5 kg) en el piso del rack; el resto arriba. La pinza giratoria arma el pallet en la zona de armado y el autoelevador con uñas lo sube al rack; a la línea, al revés: la pinza deja el rollo parado en el desbobinador. | W12: Manuales
A13: =Datos!A59 -> P08 | B13: =Datos!C59 -> MP-14 | C13: =Datos!B59 -> Fleje LAF 1,25 × 146,1 mm (fondo 2,5 kg) | D13: =Datos!F59 -> kg | E13: =Datos!D59 -> Pacheco Chapas | F13: =Datos!E59 -> 2898.307 | G13: =F13/DIAS_ANIO -> 12.076279 | H13: =Chapa_fleje!I37 -> 13.042382 | I13: =Datos!G59 -> 7 | J13: =Datos!H59 -> 10 | K13: =G13*(I13+J13)/2 -> 102.64837 | L13: =Chapa_fleje!S37*Chapa_fleje!M37 -> 208.67811 | M13: ="Rollo de "&TEXT(Chapa_fleje!M37,"#,##0")&" kg (1 tanda)" -> Rollo de 209 kg (1 tanda) | N13: =Chapa_fleje!M37 -> 208.67811 | O13: =Chapa_fleje!T37 -> 10 | P13: =Chapa_fleje!U37 -> 1 | Q13: =IF(P13*N13=0,0,F13/(P13*N13)) -> 13.888888 | R13: Flejes (rack + volteador) | S13: =Chapa_fleje!W37*1000 -> 417.35622 | T13: — | U13: =Chapa_fleje!K60 -> 1 | V13: =IFERROR(VLOOKUP(R13,Almacenes!$A$19:$I$32,9,FALSE()),"") -> Rollos ojo al cielo, un código por pallet, con listones entre rollos. Los de más de 1.000 kg (5 kg) en el piso del rack; el resto arriba. La pinza giratoria arma el pallet en la zona de armado y el autoelevador con uñas lo sube al rack; a la línea, al revés: la pinza deja el rollo parado en el desbobinador. | W13: Manuales
A14: =Datos!A60 -> P09 | B14: =Datos!C60 -> MP-07 | C14: =Datos!B60 -> Fleje LAF 1,6 × 204,2 mm (cúpula 5 kg) | D14: =Datos!F60 -> kg | E14: =Datos!D60 -> Pacheco Chapas | F14: =Datos!E60 -> 32819.082 | G14: =F14/DIAS_ANIO -> 136.74617 | H14: =Chapa_fleje!I38 -> 147.68587 | I14: =Datos!G60 -> 7 | J14: =Datos!H60 -> 10 | K14: =G14*(I14+J14)/2 -> 1162.3425 | L14: =Chapa_fleje!S38*Chapa_fleje!M38 -> 1181.4869 | M14: ="Rollo de "&TEXT(Chapa_fleje!M38,"#,##0")&" kg (1 tanda)" -> Rollo de 1,181 kg (1 tanda) | N14: =Chapa_fleje!M38 -> 1181.4869 | O14: =Chapa_fleje!T38 -> 10 | P14: =Chapa_fleje!U38 -> 2 | Q14: =IF(P14*N14=0,0,F14/(P14*N14)) -> 13.888889 | R14: Flejes (rack + volteador) | S14: =Chapa_fleje!W38*1000 -> 3544.4608 | T14: — | U14: =Chapa_fleje!K61 -> 3 | V14: =IFERROR(VLOOKUP(R14,Almacenes!$A$19:$I$32,9,FALSE()),"") -> Rollos ojo al cielo, un código por pallet, con listones entre rollos. Los de más de 1.000 kg (5 kg) en el piso del rack; el resto arriba. La pinza giratoria arma el pallet en la zona de armado y el autoelevador con uñas lo sube al rack; a la línea, al revés: la pinza deja el rollo parado en el desbobinador. | W14: Manuales
A15: =Datos!A61 -> P10 | B15: =Datos!C61 -> MP-08 | C15: =Datos!B61 -> Fleje LAF 1,6 × 177,2 mm (fondo 5 kg) | D15: =Datos!F61 -> kg | E15: =Datos!D61 -> Pacheco Chapas | F15: =Datos!E61 -> 24623.315 | G15: =F15/DIAS_ANIO -> 102.59715 | H15: =Chapa_fleje!I39 -> 110.80492 | I15: =Datos!G61 -> 7 | J15: =Datos!H61 -> 10 | K15: =G15*(I15+J15)/2 -> 872.07574 | L15: =Chapa_fleje!S39*Chapa_fleje!M39 -> 886.43934 | M15: ="Rollo de "&TEXT(Chapa_fleje!M39,"#,##0")&" kg (1 tanda)" -> Rollo de 886 kg (1 tanda) | N15: =Chapa_fleje!M39 -> 886.43934 | O15: =Chapa_fleje!T39 -> 10 | P15: =Chapa_fleje!U39 -> 2 | Q15: =IF(P15*N15=0,0,F15/(P15*N15)) -> 13.888889 | R15: Flejes (rack + volteador) | S15: =Chapa_fleje!W39*1000 -> 2659.318 | T15: — | U15: =Chapa_fleje!K62 -> 3 | V15: =IFERROR(VLOOKUP(R15,Almacenes!$A$19:$I$32,9,FALSE()),"") -> Rollos ojo al cielo, un código por pallet, con listones entre rollos. Los de más de 1.000 kg (5 kg) en el piso del rack; el resto arriba. La pinza giratoria arma el pallet en la zona de armado y el autoelevador con uñas lo sube al rack; a la línea, al revés: la pinza deja el rollo parado en el desbobinador. | W15: Manuales
A16: =Datos!A62 -> P11 | B16: =Datos!C62 -> MP-09 | C16: =Datos!B62 -> Fleje LAF 2,0 × 238,7 mm (cúpula 10 kg) | D16: =Datos!F62 -> kg | E16: =Datos!D62 -> Pacheco Chapas | F16: =Datos!E62 -> 3403.11 | G16: =F16/DIAS_ANIO -> 14.179625 | H16: =Chapa_fleje!I40 -> 15.313995 | I16: =Datos!G62 -> 7 | J16: =Datos!H62 -> 10 | K16: =G16*(I16+J16)/2 -> 120.52681 | L16: =Chapa_fleje!S40*Chapa_fleje!M40 -> 245.02392 | M16: ="Rollo de "&TEXT(Chapa_fleje!M40,"#,##0")&" kg (1 tanda)" -> Rollo de 245 kg (1 tanda) | N16: =Chapa_fleje!M40 -> 245.02392 | O16: =Chapa_fleje!T40 -> 10 | P16: =Chapa_fleje!U40 -> 1 | Q16: =IF(P16*N16=0,0,F16/(P16*N16)) -> 13.888889 | R16: Flejes (rack + volteador) | S16: =Chapa_fleje!W40*1000 -> 490.04785 | T16: — | U16: =Chapa_fleje!K63 -> 1 | V16: =IFERROR(VLOOKUP(R16,Almacenes!$A$19:$I$32,9,FALSE()),"") -> Rollos ojo al cielo, un código por pallet, con listones entre rollos. Los de más de 1.000 kg (5 kg) en el piso del rack; el resto arriba. La pinza giratoria arma el pallet en la zona de armado y el autoelevador con uñas lo sube al rack; a la línea, al revés: la pinza deja el rollo parado en el desbobinador. | W16: Manuales
A17: =Datos!A63 -> P12 | B17: =Datos!C63 -> MP-10 | C17: =Datos!B63 -> Fleje LAF 2,0 × 205 mm (fondo 10 kg) | D17: =Datos!F63 -> kg | E17: =Datos!D63 -> Pacheco Chapas | F17: =Datos!E63 -> 2486.567 | G17: =F17/DIAS_ANIO -> 10.360696 | H17: =Chapa_fleje!I41 -> 11.189552 | I17: =Datos!G63 -> 7 | J17: =Datos!H63 -> 10 | K17: =G17*(I17+J17)/2 -> 88.065915 | L17: =Chapa_fleje!S41*Chapa_fleje!M41 -> 179.03283 | M17: ="Rollo de "&TEXT(Chapa_fleje!M41,"#,##0")&" kg (1 tanda)" -> Rollo de 179 kg (1 tanda) | N17: =Chapa_fleje!M41 -> 179.03283 | O17: =Chapa_fleje!T41 -> 10 | P17: =Chapa_fleje!U41 -> 1 | Q17: =IF(P17*N17=0,0,F17/(P17*N17)) -> 13.888889 | R17: Flejes (rack + volteador) | S17: =Chapa_fleje!W41*1000 -> 358.06566 | T17: — | U17: =Chapa_fleje!K64 -> 1 | V17: =IFERROR(VLOOKUP(R17,Almacenes!$A$19:$I$32,9,FALSE()),"") -> Rollos ojo al cielo, un código por pallet, con listones entre rollos. Los de más de 1.000 kg (5 kg) en el piso del rack; el resto arriba. La pinza giratoria arma el pallet en la zona de armado y el autoelevador con uñas lo sube al rack; a la línea, al revés: la pinza deja el rollo parado en el desbobinador. | W17: Manuales
A18: =Datos!A64 -> P13 | B18: =Datos!C64 -> MP-11 | C18: =Datos!B64 -> Hoja LAC 3,2 × 1500 × 3000 mm | D18: =Datos!F64 -> hoja | E18: =Datos!D64 -> Pradecon | F18: =Datos!E64 -> 349.515 | G18: =F18/DIAS_ANIO -> 1.4563125 | H18: =Chapa_fleje!H11 -> 1.5772049 | I18: =Datos!G64 -> 7 | J18: =Datos!H64 -> 10 | K18: =G18*(I18+J18)/2 -> 12.378656 | L18: =Chapa_fleje!S11*Chapa_fleje!L11 -> 7 | M18: ="Paquete de "&Chapa_fleje!L11&" hojas (1 tanda)" -> Paquete de 7 hojas (1 tanda) | N18: =Chapa_fleje!L11 -> 7 | O18: =Chapa_fleje!T11 -> 20 | P18: =Chapa_fleje!U11 -> 5 | Q18: =IF(P18*N18=0,0,F18/(P18*N18)) -> 9.9861429 | R18: Chapa (pilas en el piso) | S18: =Chapa_fleje!V11*Chapa_fleje!L11 -> 42 | T18: — | U18: =Chapa_fleje!K22 -> 1 | V18: =IFERROR(VLOOKUP(R18,Almacenes!$A$19:$I$32,9,FALSE()),"") -> Paquete sobre sus 3 tacos, una pila por formato hasta el alto que permiten el autoelevador, el piso y la estabilidad (Chapa_fleje sección 2). Se toma el de arriba; al recibir, el remanente pasa arriba (FIFO por colada). Pilas demarcadas con su código, 2 filas enfrentadas sobre la calle. | W18: Carros
A19: =Datos!A65 -> P14 | B19: =Datos!C65 -> MP-12 | C19: =Datos!B65 -> Hoja LAC 4,75 × 1500 × 3000 mm | D19: =Datos!F65 -> hoja | E19: =Datos!D65 -> Pradecon | F19: =Datos!E65 -> 165.622 | G19: =F19/DIAS_ANIO -> 0.69009167 | H19: =Chapa_fleje!H12 -> 0.66042495 | I19: =Datos!G65 -> 7 | J19: =Datos!H65 -> 10 | K19: =G19*(I19+J19)/2 -> 5.8657792 | L19: =Chapa_fleje!S12*Chapa_fleje!L12 -> 3 | M19: ="Paquete de "&Chapa_fleje!L12&" hojas (1 tanda)" -> Paquete de 3 hojas (1 tanda) | N19: =Chapa_fleje!L12 -> 3 | O19: =Chapa_fleje!T12 -> 20 | P19: =Chapa_fleje!U12 -> 5 | Q19: =IF(P19*N19=0,0,F19/(P19*N19)) -> 11.041467 | R19: Chapa (pilas en el piso) | S19: =Chapa_fleje!V12*Chapa_fleje!L12 -> 18 | T19: — | U19: =Chapa_fleje!K23 -> 1 | V19: =IFERROR(VLOOKUP(R19,Almacenes!$A$19:$I$32,9,FALSE()),"") -> Paquete sobre sus 3 tacos, una pila por formato hasta el alto que permiten el autoelevador, el piso y la estabilidad (Chapa_fleje sección 2). Se toma el de arriba; al recibir, el remanente pasa arriba (FIFO por colada). Pilas demarcadas con su código, 2 filas enfrentadas sobre la calle. | W19: Carros
A20: =Datos!A66 -> P15 | B20: =Datos!C66 -> MP-15 | C20: =Datos!B66 -> Casquete 10" × 3,2 mm (carro 25 kg) | D20: =Datos!F66 -> u | E20: =Datos!D66 -> NOVA Ruedas | F20: =Datos!E66 -> 1554.621 | G20: =F20/DIAS_ANIO -> 6.4775875 | H20: =G20*FAC_CAR -> 6.9957945 | I20: =Datos!G66 -> 25 | J20: =Datos!H66 -> 32 | K20: =G20*(I20+J20)/2 -> 184.61124 | L20: =H20*J20-K20 -> 39.25418 | M20: =Datos!I66 -> Contenedor de 360 u (180 cúpulas + 180 fondos, ≈ 1000 kg) | N20: =Datos!J66 -> 360 | O20: =Datos!K66 -> 20 | P20: =MAX(1,ROUNDUP(H20*O20/N20,0)) -> 1 | Q20: =IF(P20*N20=0,0,F20/(P20*N20)) -> 4.3183917 | R20: Rack de casquetes y cuplas (carros) | S20: =L20+P20*N20 -> 399.25418 | T20: =Datos!M66 -> 360 | U20: =IF(T20=0,0,S20/T20) -> 1.1090394 | V20: =IFERROR(VLOOKUP(R20,Almacenes!$A$19:$I$32,9,FALSE()),"") -> Un contenedor por medida de casquete (cúpulas y fondos en columnas separadas); el que está en uso en el piso; cajas de cuplas arriba. | W20: Carros
A21: =Datos!A67 -> P16 | B21: =Datos!C67 -> MP-16 | C21: =Datos!B67 -> Casquete 12" × 3,2 mm (carro 50 kg) | D21: =Datos!F67 -> u | E21: =Datos!D67 -> NOVA Ruedas | F21: =Datos!E67 -> 3416.87 | G21: =F21/DIAS_ANIO -> 14.236958 | H21: =G21*FAC_CAR -> 15.375915 | I21: =Datos!G67 -> 25 | J21: =Datos!H67 -> 32 | K21: =G21*(I21+J21)/2 -> 405.75331 | L21: =H21*J21-K21 -> 86.275967 | M21: =Datos!I67 -> Contenedor de 260 u (130 cúpulas + 130 fondos, ≈ 990 kg) | N21: =Datos!J67 -> 260 | O21: =Datos!K67 -> 20 | P21: =MAX(1,ROUNDUP(H21*O21/N21,0)) -> 2 | Q21: =IF(P21*N21=0,0,F21/(P21*N21)) -> 6.5709038 | R21: Rack de casquetes y cuplas (carros) | S21: =L21+P21*N21 -> 606.27597 | T21: =Datos!M67 -> 260 | U21: =IF(T21=0,0,S21/T21) -> 2.3318306 | V21: =IFERROR(VLOOKUP(R21,Almacenes!$A$19:$I$32,9,FALSE()),"") -> Un contenedor por medida de casquete (cúpulas y fondos en columnas separadas); el que está en uso en el piso; cajas de cuplas arriba. | W21: Carros
A22: =Datos!A68 -> P17 | B22: =Datos!C68 -> MP-17 | C22: =Datos!B68 -> Casquete 15" × 4,75 mm (carros 70 y 100 kg) | D22: =Datos!F68 -> u | E22: =Datos!D68 -> NOVA Ruedas | F22: =Datos!E68 -> 1243.153 | G22: =F22/DIAS_ANIO -> 5.1798042 | H22: =G22*FAC_CAR -> 5.5941885 | I22: =Datos!G68 -> 25 | J22: =Datos!H68 -> 32 | K22: =G22*(I22+J22)/2 -> 147.62442 | L22: =H22*J22-K22 -> 31.389613 | M22: =Datos!I68 -> Contenedor de 116 u (58 cúpulas + 58 fondos, ≈ 890 kg) | N22: =Datos!J68 -> 116 | O22: =Datos!K68 -> 20 | P22: =MAX(1,ROUNDUP(H22*O22/N22,0)) -> 1 | Q22: =IF(P22*N22=0,0,F22/(P22*N22)) -> 10.716836 | R22: Rack de casquetes y cuplas (carros) | S22: =L22+P22*N22 -> 147.38961 | T22: =Datos!M68 -> 116 | U22: =IF(T22=0,0,S22/T22) -> 1.2706001 | V22: =IFERROR(VLOOKUP(R22,Almacenes!$A$19:$I$32,9,FALSE()),"") -> Un contenedor por medida de casquete (cúpulas y fondos en columnas separadas); el que está en uso en el piso; cajas de cuplas arriba. | W22: Carros
A23: =Datos!A69 -> P18 | B23: =Datos!C69 -> MP-18 | C23: =Datos!B69 -> Asiento de válvula M22 × 1,5 (1 kg) | D23: =Datos!F69 -> u | E23: =Datos!D69 -> Eli-Met | F23: =Datos!E69 -> 202620.64 | G23: =F23/DIAS_ANIO -> 844.25266 | H23: =G23*FAC_MAN -> 911.79288 | I23: =Datos!G69 -> 25 | J23: =Datos!H69 -> 29 | K23: =G23*(I23+J23)/2 -> 22794.822 | L23: =H23*J23-K23 -> 3647.1715 | M23: =Datos!I69 -> Caja de 500 u (≈ 16 kg, un turno) | N23: =Datos!J69 -> 500 | O23: =Datos!K69 -> 20 | P23: =MAX(1,ROUNDUP(H23*O23/N23,0)) -> 37 | Q23: =IF(P23*N23=0,0,F23/(P23*N23)) -> 10.952467 | R23: Insumos de montaje (manuales) | S23: =L23+P23*N23 -> 22147.172 | T23: =Datos!M69 -> 12000 | U23: =IF(T23=0,0,S23/T23) -> 1.8455976 | V23: =IFERROR(VLOOKUP(R23,Almacenes!$A$19:$I$32,9,FALSE()),"") -> Abajo el pallet o la caja en uso (de ahí sale el carro de abastecimiento), arriba la reposición del pedido mensual. | W23: Manuales
A24: =Datos!A70 -> P19 | B24: =Datos!C70 -> MP-19 | C24: =Datos!B70 -> Asiento de válvula M30 × 1,5 (2,5 a 10 kg) | D24: =Datos!F70 -> u | E24: =Datos!D70 -> Eli-Met | F24: =Datos!E70 -> 81841.925 | G24: =F24/DIAS_ANIO -> 341.00802 | H24: =G24*FAC_MAN -> 368.28866 | I24: =Datos!G70 -> 25 | J24: =Datos!H70 -> 29 | K24: =G24*(I24+J24)/2 -> 9207.2166 | L24: =H24*J24-K24 -> 1473.1546 | M24: =Datos!I70 -> Caja de 500 u (≈ 15 kg) | N24: =Datos!J70 -> 500 | O24: =Datos!K70 -> 20 | P24: =MAX(1,ROUNDUP(H24*O24/N24,0)) -> 15 | Q24: =IF(P24*N24=0,0,F24/(P24*N24)) -> 10.912257 | R24: Insumos de montaje (manuales) | S24: =L24+P24*N24 -> 8973.1547 | T24: =Datos!M70 -> 8000 | U24: =IF(T24=0,0,S24/T24) -> 1.1216443 | V24: =IFERROR(VLOOKUP(R24,Almacenes!$A$19:$I$32,9,FALSE()),"") -> Abajo el pallet o la caja en uso (de ahí sale el carro de abastecimiento), arriba la reposición del pedido mensual. | W24: Manuales
A25: =Datos!A71 -> P20 | B25: =Datos!C71 -> MP-20 | C25: =Datos!B71 -> Cupla M30 × 1,5 (carros 25 y 50 kg) | D25: =Datos!F71 -> u | E25: =Datos!D71 -> Eli-Met | F25: =Datos!E71 -> 2485.746 | G25: =F25/DIAS_ANIO -> 10.357275 | H25: =G25*FAC_CAR -> 11.185857 | I25: =Datos!G71 -> 25 | J25: =Datos!H71 -> 29 | K25: =G25*(I25+J25)/2 -> 279.64643 | L25: =H25*J25-K25 -> 44.743428 | M25: =Datos!I71 -> Caja de 100 u (25 kg) | N25: =Datos!J71 -> 100 | O25: =Datos!K71 -> 20 | P25: =MAX(1,ROUNDUP(H25*O25/N25,0)) -> 3 | Q25: =IF(P25*N25=0,0,F25/(P25*N25)) -> 8.28582 | R25: Rack de casquetes y cuplas (carros) | S25: =L25+P25*N25 -> 344.74343 | T25: =Datos!M71 -> 600 | U25: =IF(T25=0,0,S25/T25) -> 0.57457238 | V25: =IFERROR(VLOOKUP(R25,Almacenes!$A$19:$I$32,9,FALSE()),"") -> Un contenedor por medida de casquete (cúpulas y fondos en columnas separadas); el que está en uso en el piso; cajas de cuplas arriba. | W25: Carros
A26: =Datos!A72 -> P21 | B26: =Datos!C72 -> MP-21 | C26: =Datos!B72 -> Cupla 2½" BSP (carros 70 y 100 kg) | D26: =Datos!F72 -> u | E26: =Datos!D72 -> Eli-Met | F26: =Datos!E72 -> 621.576 | G26: =F26/DIAS_ANIO -> 2.5899 | H26: =G26*FAC_CAR -> 2.797092 | I26: =Datos!G72 -> 25 | J26: =Datos!H72 -> 29 | K26: =G26*(I26+J26)/2 -> 69.9273 | L26: =H26*J26-K26 -> 11.188368 | M26: =Datos!I72 -> Caja de 40 u (24 kg) | N26: =Datos!J72 -> 40 | O26: =Datos!K72 -> 20 | P26: =MAX(1,ROUNDUP(H26*O26/N26,0)) -> 2 | Q26: =IF(P26*N26=0,0,F26/(P26*N26)) -> 7.7697 | R26: Rack de casquetes y cuplas (carros) | S26: =L26+P26*N26 -> 91.188368 | T26: =Datos!M72 -> 160 | U26: =IF(T26=0,0,S26/T26) -> 0.5699273 | V26: =IFERROR(VLOOKUP(R26,Almacenes!$A$19:$I$32,9,FALSE()),"") -> Un contenedor por medida de casquete (cúpulas y fondos en columnas separadas); el que está en uso en el piso; cajas de cuplas arriba. | W26: Carros
A27: =Datos!A73 -> P22 | B27: =Datos!C73 -> MP-66 | C27: =Datos!B73 -> Caño SAE 1010 1" × 2,0 × 6 m (manija; caño del eje 25 kg) | D27: =Datos!F73 -> barra | E27: =Datos!D73 -> Centrosider | F27: =Datos!E73 -> 510.181 | G27: =F27/DIAS_ANIO -> 2.1257542 | H27: =G27*FAC_CAR -> 2.2958145 | I27: =Datos!G73 -> 5 | J27: =Datos!H73 -> 5 | K27: =G27*(I27+J27)/2 -> 10.628771 | L27: =H27*J27-K27 -> 0.85030167 | M27: =Datos!I73 -> Barra de 6 m (un atado por pedido) | N27: =Datos!J73 -> 1 | O27: =Datos!K73 -> 20 | P27: =MAX(1,ROUNDUP(H27*O27/N27,0)) -> 46 | Q27: =IF(P27*N27=0,0,F27/(P27*N27)) -> 11.090891 | R27: Cantilever de caños y barras | S27: =L27+P27*N27 -> 46.850302 | T27: =Datos!M73 -> 60 | U27: =IF(T27=0,0,S27/T27) -> 0.78083836 | V27: =IFERROR(VLOOKUP(R27,Almacenes!$A$19:$I$32,9,FALSE()),"") -> Un atado por brazo y una medida por nivel; las barras de 6 m con los brazos a 1,5 m. | W27: Carros
A28: =Datos!A74 -> P23 | B28: =Datos!C74 -> MP-67 | C28: =Datos!B74 -> Caño SAE 1010 1¼" × 2,0 × 6 m (caño del eje 50 a 100 kg) | D28: =Datos!F74 -> barra | E28: =Datos!D74 -> Centrosider | F28: =Datos!E74 -> 89.621 | G28: =F28/DIAS_ANIO -> 0.37342083 | H28: =G28*FAC_CAR -> 0.4032945 | I28: =Datos!G74 -> 5 | J28: =Datos!H74 -> 5 | K28: =G28*(I28+J28)/2 -> 1.8671042 | L28: =H28*J28-K28 -> 0.14936833 | M28: =Datos!I74 -> Barra de 6 m (un atado por pedido) | N28: =Datos!J74 -> 1 | O28: =Datos!K74 -> 20 | P28: =MAX(1,ROUNDUP(H28*O28/N28,0)) -> 9 | Q28: =IF(P28*N28=0,0,F28/(P28*N28)) -> 9.9578889 | R28: Cantilever de caños y barras | S28: =L28+P28*N28 -> 9.1493683 | T28: =Datos!M74 -> 60 | U28: =IF(T28=0,0,S28/T28) -> 0.15248947 | V28: =IFERROR(VLOOKUP(R28,Almacenes!$A$19:$I$32,9,FALSE()),"") -> Un atado por brazo y una medida por nivel; las barras de 6 m con los brazos a 1,5 m. | W28: Carros
A29: =Datos!A75 -> P24 | B29: =Datos!C75 -> MP-68 | C29: =Datos!B75 -> Barra trefilada SAE 1045 3/4" × 4 m (eje 25 kg) | D29: =Datos!F75 -> barra | E29: =Datos!D75 -> Vladimirsky | F29: =Datos!E75 -> 56.709 | G29: =F29/DIAS_ANIO -> 0.2362875 | H29: =G29*FAC_CAR -> 0.2551905 | I29: =Datos!G75 -> 1 | J29: =Datos!H75 -> 3 | K29: =G29*(I29+J29)/2 -> 0.472575 | L29: =H29*J29-K29 -> 0.2929965 | M29: =Datos!I75 -> Barra de 4 m | N29: =Datos!J75 -> 1 | O29: =Datos!K75 -> 20 | P29: =MAX(1,ROUNDUP(H29*O29/N29,0)) -> 6 | Q29: =IF(P29*N29=0,0,F29/(P29*N29)) -> 9.4515 | R29: Cantilever de caños y barras | S29: =L29+P29*N29 -> 6.2929965 | T29: =Datos!M75 -> 60 | U29: =IF(T29=0,0,S29/T29) -> 0.10488327 | V29: =IFERROR(VLOOKUP(R29,Almacenes!$A$19:$I$32,9,FALSE()),"") -> Un atado por brazo y una medida por nivel; las barras de 6 m con los brazos a 1,5 m. | W29: Carros
A30: =Datos!A76 -> P25 | B30: =Datos!C76 -> MP-69 | C30: =Datos!B76 -> Barra trefilada SAE 1045 1" × 6 m (eje 50 a 100 kg) | D30: =Datos!F76 -> barra | E30: =Datos!D76 -> Vladimirsky | F30: =Datos!E76 -> 127.028 | G30: =F30/DIAS_ANIO -> 0.52928333 | H30: =G30*FAC_CAR -> 0.571626 | I30: =Datos!G76 -> 1 | J30: =Datos!H76 -> 3 | K30: =G30*(I30+J30)/2 -> 1.0585667 | L30: =H30*J30-K30 -> 0.65631133 | M30: =Datos!I76 -> Barra de 6 m | N30: =Datos!J76 -> 1 | O30: =Datos!K76 -> 20 | P30: =MAX(1,ROUNDUP(H30*O30/N30,0)) -> 12 | Q30: =IF(P30*N30=0,0,F30/(P30*N30)) -> 10.585667 | R30: Cantilever de caños y barras | S30: =L30+P30*N30 -> 12.656311 | T30: =Datos!M76 -> 60 | U30: =IF(T30=0,0,S30/T30) -> 0.21093852 | V30: =IFERROR(VLOOKUP(R30,Almacenes!$A$19:$I$32,9,FALSE()),"") -> Un atado por brazo y una medida por nivel; las barras de 6 m con los brazos a 1,5 m. | W30: Carros
A31: =Datos!A77 -> P26 | B31: =Datos!C77 -> MP-70 | C31: =Datos!B77 -> Arandela de tope del eje | D31: =Datos!F77 -> u | E31: =Datos!D77 -> Würth Argentina | F31: =Datos!E77 -> 7258.729 | G31: =F31/DIAS_ANIO -> 30.244704 | H31: =G31*FAC_CAR -> 32.66428 | I31: =Datos!G77 -> 3 | J31: =Datos!H77 -> 5 | K31: =G31*(I31+J31)/2 -> 120.97882 | L31: =H31*J31-K31 -> 42.342586 | M31: =Datos!I77 -> Bolsa de 1.000 u | N31: =Datos!J77 -> 1000 | O31: =Datos!K77 -> 20 | P31: =MAX(1,ROUNDUP(H31*O31/N31,0)) -> 1 | Q31: =IF(P31*N31=0,0,F31/(P31*N31)) -> 7.258729 | R31: Rack de insumos de montaje (carros) | S31: =L31+P31*N31 -> 1042.3426 | T31: =Datos!M77 -> 20000 | U31: =IF(T31=0,0,S31/T31) -> 0.052117129 | V31: =IFERROR(VLOOKUP(R31,Almacenes!$A$19:$I$32,9,FALSE()),"") -> Ruedas en pallet abajo; cajas arriba. | W31: Carros
A32: =Datos!A78 -> P27 | B32: =Datos!C78 -> MP-71 | C32: =Datos!B78 -> Pasador partido del eje | D32: =Datos!F78 -> u | E32: =Datos!D78 -> Würth Argentina | F32: =Datos!E78 -> 3629.364 | G32: =F32/DIAS_ANIO -> 15.12235 | H32: =G32*FAC_CAR -> 16.332138 | I32: =Datos!G78 -> 3 | J32: =Datos!H78 -> 5 | K32: =G32*(I32+J32)/2 -> 60.4894 | L32: =H32*J32-K32 -> 21.17129 | M32: =Datos!I78 -> Bolsa de 1.000 u | N32: =Datos!J78 -> 1000 | O32: =Datos!K78 -> 20 | P32: =MAX(1,ROUNDUP(H32*O32/N32,0)) -> 1 | Q32: =IF(P32*N32=0,0,F32/(P32*N32)) -> 3.629364 | R32: Rack de insumos de montaje (carros) | S32: =L32+P32*N32 -> 1021.1713 | T32: =Datos!M78 -> 20000 | U32: =IF(T32=0,0,S32/T32) -> 0.051058564 | V32: =IFERROR(VLOOKUP(R32,Almacenes!$A$19:$I$32,9,FALSE()),"") -> Ruedas en pallet abajo; cajas arriba. | W32: Carros
A33: =Datos!A79 -> P28 | B33: =Datos!C79 -> MP-54/300 | C33: =Datos!B79 -> Rueda Ø300 × 50, buje 3/4" (carro 25 kg) | D33: =Datos!F79 -> u | E33: =Datos!D79 -> Ruedar | F33: =Datos!E79 -> 907.341 | G33: =F33/DIAS_ANIO -> 3.7805875 | H33: =G33*FAC_CAR -> 4.0830345 | I33: =Datos!G79 -> 3 | J33: =Datos!H79 -> 5 | K33: =G33*(I33+J33)/2 -> 15.12235 | L33: =H33*J33-K33 -> 5.2928225 | M33: =Datos!I79 -> Pallet de 72 u | N33: =Datos!J79 -> 72 | O33: =Datos!K79 -> 20 | P33: =MAX(1,ROUNDUP(H33*O33/N33,0)) -> 2 | Q33: =IF(P33*N33=0,0,F33/(P33*N33)) -> 6.3009792 | R33: Rack de insumos de montaje (carros) | S33: =L33+P33*N33 -> 149.29282 | T33: =Datos!M79 -> 144 | U33: =IF(T33=0,0,S33/T33) -> 1.0367557 | V33: =IFERROR(VLOOKUP(R33,Almacenes!$A$19:$I$32,9,FALSE()),"") -> Ruedas en pallet abajo; cajas arriba. | W33: Carros
A34: =Datos!A80 -> P29 | B34: =Datos!C80 -> MP-54/350 | C34: =Datos!B80 -> Rueda Ø350 × 60, buje 1" (carro 50 kg) | D34: =Datos!F80 -> u | E34: =Datos!D80 -> Ruedar | F34: =Datos!E80 -> 1995.99 | G34: =F34/DIAS_ANIO -> 8.316625 | H34: =G34*FAC_CAR -> 8.981955 | I34: =Datos!G80 -> 3 | J34: =Datos!H80 -> 5 | K34: =G34*(I34+J34)/2 -> 33.2665 | L34: =H34*J34-K34 -> 11.643275 | M34: =Datos!I80 -> Pallet de 72 u | N34: =Datos!J80 -> 72 | O34: =Datos!K80 -> 20 | P34: =MAX(1,ROUNDUP(H34*O34/N34,0)) -> 3 | Q34: =IF(P34*N34=0,0,F34/(P34*N34)) -> 9.2406944 | R34: Rack de insumos de montaje (carros) | S34: =L34+P34*N34 -> 227.64327 | T34: =Datos!M80 -> 144 | U34: =IF(T34=0,0,S34/T34) -> 1.5808561 | V34: =IFERROR(VLOOKUP(R34,Almacenes!$A$19:$I$32,9,FALSE()),"") -> Ruedas en pallet abajo; cajas arriba. | W34: Carros
A35: =Datos!A81 -> P30 | B35: =Datos!C81 -> MP-54/400 | C35: =Datos!B81 -> Rueda Ø400 × 60, buje 1" (carros 70 y 100 kg) | D35: =Datos!F81 -> u | E35: =Datos!D81 -> Escanort | F35: =Datos!E81 -> 726.033 | G35: =F35/DIAS_ANIO -> 3.0251375 | H35: =G35*FAC_CAR -> 3.2671485 | I35: =Datos!G81 -> 3 | J35: =Datos!H81 -> 5 | K35: =G35*(I35+J35)/2 -> 12.10055 | L35: =H35*J35-K35 -> 4.2351925 | M35: =Datos!I81 -> Pallet de 72 u | N35: =Datos!J81 -> 72 | O35: =Datos!K81 -> 20 | P35: =MAX(1,ROUNDUP(H35*O35/N35,0)) -> 1 | Q35: =IF(P35*N35=0,0,F35/(P35*N35)) -> 10.083792 | R35: Rack de insumos de montaje (carros) | S35: =L35+P35*N35 -> 76.235192 | T35: =Datos!M81 -> 144 | U35: =IF(T35=0,0,S35/T35) -> 0.52941106 | V35: =IFERROR(VLOOKUP(R35,Almacenes!$A$19:$I$32,9,FALSE()),"") -> Ruedas en pallet abajo; cajas arriba. | W35: Carros
A36: =Datos!A82 -> P31 | B36: =Datos!C82 -> MP-23 | C36: =Datos!B82 -> Alambre MAG ER70S-6 Ø0,9 mm (manuales) | D36: =Datos!F82 -> kg | E36: =Datos!D82 -> Soldanet | F36: =Datos!E82 -> 5990.038 | G36: =F36/DIAS_ANIO -> 24.958492 | H36: =G36*FAC_MAN -> 26.955171 | I36: =Datos!G82 -> 4 | J36: =Datos!H82 -> 5 | K36: =G36*(I36+J36)/2 -> 112.31321 | L36: =H36*J36-K36 -> 22.462643 | M36: =Datos!I82 -> Pallet de 60 bobinas de 15 kg (900 kg) | N36: =Datos!J82 -> 900 | O36: =Datos!K82 -> 20 | P36: =MAX(1,ROUNDUP(H36*O36/N36,0)) -> 1 | Q36: =IF(P36*N36=0,0,F36/(P36*N36)) -> 6.6555978 | R36: Insumos de soldadura y superficie | S36: =L36+P36*N36 -> 922.46264 | T36: =Datos!M82 -> 900 | U36: =IF(T36=0,0,S36/T36) -> 1.0249585 | V36: =IFERROR(VLOOKUP(R36,Almacenes!$A$19:$I$32,9,FALSE()),"") -> Granalla en el piso del rack; alambre y pintura arriba; insumos chicos en caja. | W36: Manuales
A37: =Datos!A83 -> P32 | B37: =Datos!C83 -> MP-24 | C37: =Datos!B83 -> Alambre MAG ER70S-6 Ø1,0 mm (carros) | D37: =Datos!F83 -> kg | E37: =Datos!D83 -> Soldanet | F37: =Datos!E83 -> 1390.597 | G37: =F37/DIAS_ANIO -> 5.7941542 | H37: =G37*FAC_CAR -> 6.2576865 | I37: =Datos!G83 -> 4 | J37: =Datos!H83 -> 5 | K37: =G37*(I37+J37)/2 -> 26.073694 | L37: =H37*J37-K37 -> 5.2147387 | M37: =Datos!I83 -> Bobina de 15 kg | N37: =Datos!J83 -> 15 | O37: =Datos!K83 -> 20 | P37: =MAX(1,ROUNDUP(H37*O37/N37,0)) -> 9 | Q37: =IF(P37*N37=0,0,F37/(P37*N37)) -> 10.300719 | R37: Rack de insumos de montaje (carros) | S37: =L37+P37*N37 -> 140.21474 | T37: =Datos!M83 -> 900 | U37: =IF(T37=0,0,S37/T37) -> 0.15579415 | V37: =IFERROR(VLOOKUP(R37,Almacenes!$A$19:$I$32,9,FALSE()),"") -> Ruedas en pallet abajo; cajas arriba. | W37: Carros
A38: =Datos!A84 -> P33 | B38: =Datos!C84 -> MP-25 | C38: =Datos!B84 -> Gas MAG Ar + 8 % CO₂ (Arcal 21) | D38: =Datos!F84 -> m³ | E38: =Datos!D84 -> Air Liquide | F38: =Datos!E84 -> 7959.639 | G38: =F38/DIAS_ANIO -> 33.165163 | H38: =G38*FAC_MAN -> 35.818376 | I38: =Datos!G84 -> 1 | J38: =Datos!H84 -> 1 | K38: =G38*(I38+J38)/2 -> 33.165163 | L38: =H38*J38-K38 -> 2.653213 | M38: =Datos!I84 -> Batería de 11 cilindros con manifold (115,5 m³) | N38: =Datos!J84 -> 115.5 | O38: =Datos!K84 -> 5 | P38: =MAX(1,ROUNDUP(H38*O38/N38,0)) -> 2 | Q38: =IF(P38*N38=0,0,F38/(P38*N38)) -> 34.457312 | R38: Jaula de gases | S38: =L38+P38*N38 -> 233.65321 | T38: =Datos!M84 -> 115.5 | U38: =IF(T38=0,0,S38/T38) -> 2.0229715 | V38: =IFERROR(VLOOKUP(R38,Almacenes!$A$19:$I$32,9,FALSE()),"") -> Baterías y pack con manifold conectados a la cañería; cilindros sueltos encadenados en gabinete. | W38: Manuales
A39: =Datos!A85 -> P34 | B39: =Datos!C85 -> MP-26 | C39: =Datos!B85 -> Argón puro EN ISO 14175 I1 (costura longitudinal TIG del 1 kg) | D39: =Datos!F85 -> m³ | E39: =Datos!D85 -> Air Liquide | F39: =Datos!E85 -> 800.554 | G39: =F39/DIAS_ANIO -> 3.3356417 | H39: =G39*FAC_MAN -> 3.602493 | I39: =Datos!G85 -> 1 | J39: =Datos!H85 -> 1 | K39: =G39*(I39+J39)/2 -> 3.3356417 | L39: =H39*J39-K39 -> 0.26685133 | M39: =Datos!I85 -> Cilindro de 10,5 m³ | N39: =Datos!J85 -> 10.5 | O39: =Datos!K85 -> 5 | P39: =MAX(1,ROUNDUP(H39*O39/N39,0)) -> 2 | Q39: =IF(P39*N39=0,0,F39/(P39*N39)) -> 38.121619 | R39: Jaula de gases | S39: =L39+P39*N39 -> 21.266851 | T39: =Datos!M85 -> 115.5 | U39: =IF(T39=0,0,S39/T39) -> 0.18412858 | V39: =IFERROR(VLOOKUP(R39,Almacenes!$A$19:$I$32,9,FALSE()),"") -> Baterías y pack con manifold conectados a la cañería; cilindros sueltos encadenados en gabinete. | W39: Manuales
A40: =Datos!A86 -> P35 | B40: =Datos!C86 -> MP-29 | C40: =Datos!B86 -> Electrodo de tungsteno lantanado 2 % (WL20) Ø2,4 × 175 mm | D40: =Datos!F86 -> u | E40: =Datos!D86 -> Würth Argentina | F40: =Datos!E86 -> 166.629 | G40: =F40/DIAS_ANIO -> 0.6942875 | H40: =G40*FAC_MAN -> 0.7498305 | I40: =Datos!G86 -> 3 | J40: =Datos!H86 -> 5 | K40: =G40*(I40+J40)/2 -> 2.77715 | L40: =H40*J40-K40 -> 0.9720025 | M40: =Datos!I86 -> Caja de 10 u | N40: =Datos!J86 -> 10 | O40: =Datos!K86 -> 20 | P40: =MAX(1,ROUNDUP(H40*O40/N40,0)) -> 2 | Q40: =IF(P40*N40=0,0,F40/(P40*N40)) -> 8.33145 | R40: Insumos de soldadura y superficie | S40: =L40+P40*N40 -> 20.972002 | T40: =Datos!M86 -> 250 | U40: =IF(T40=0,0,S40/T40) -> 0.08388801 | V40: =IFERROR(VLOOKUP(R40,Almacenes!$A$19:$I$32,9,FALSE()),"") -> Granalla en el piso del rack; alambre y pintura arriba; insumos chicos en caja. | W40: Manuales
A41: =Datos!A87 -> P36 | B41: =Datos!C87 -> MP-92 | C41: =Datos!B87 -> Disco de sensitiva 355 mm | D41: =Datos!F87 -> u | E41: =Datos!D87 -> Würth Argentina | F41: =Datos!E87 -> 27.22 | G41: =F41/DIAS_ANIO -> 0.11341667 | H41: =G41*FAC_MAN -> 0.12249 | I41: =Datos!G87 -> 3 | J41: =Datos!H87 -> 5 | K41: =G41*(I41+J41)/2 -> 0.45366667 | L41: =H41*J41-K41 -> 0.15878333 | M41: =Datos!I87 -> Caja de 10 u | N41: =Datos!J87 -> 10 | O41: =Datos!K87 -> 60 | P41: =MAX(1,ROUNDUP(H41*O41/N41,0)) -> 1 | Q41: =IF(P41*N41=0,0,F41/(P41*N41)) -> 2.722 | R41: Insumos de soldadura y superficie | S41: =L41+P41*N41 -> 10.158783 | T41: =Datos!M87 -> 250 | U41: =IF(T41=0,0,S41/T41) -> 0.040635133 | V41: =IFERROR(VLOOKUP(R41,Almacenes!$A$19:$I$32,9,FALSE()),"") -> Granalla en el piso del rack; alambre y pintura arriba; insumos chicos en caja. | W41: Manuales
A42: =Datos!A88 -> P37 | B42: =Datos!C88 -> MP-27 | C42: =Datos!B88 -> Disco de corte 115 × 1,0 mm | D42: =Datos!F88 -> u | E42: =Datos!D88 -> Espacio Industria | F42: =Datos!E88 -> 99.755 | G42: =F42/DIAS_ANIO -> 0.41564583 | H42: =G42*FAC_MAN -> 0.4488975 | I42: =Datos!G88 -> 1 | J42: =Datos!H88 -> 1 | K42: =G42*(I42+J42)/2 -> 0.41564583 | L42: =H42*J42-K42 -> 0.033251667 | M42: =Datos!I88 -> Caja de 25 u | N42: =Datos!J88 -> 25 | O42: =Datos!K88 -> 60 | P42: =MAX(1,ROUNDUP(H42*O42/N42,0)) -> 2 | Q42: =IF(P42*N42=0,0,F42/(P42*N42)) -> 1.9951 | R42: Insumos de soldadura y superficie | S42: =L42+P42*N42 -> 50.033252 | T42: =Datos!M88 -> 250 | U42: =IF(T42=0,0,S42/T42) -> 0.20013301 | V42: =IFERROR(VLOOKUP(R42,Almacenes!$A$19:$I$32,9,FALSE()),"") -> Granalla en el piso del rack; alambre y pintura arriba; insumos chicos en caja. | W42: Manuales
A43: =Datos!A89 -> P38 | B43: =Datos!C89 -> MP-93 | C43: =Datos!B89 -> Disco flap 115 mm grano 60 | D43: =Datos!F89 -> u | E43: =Datos!D89 -> Würth Argentina | F43: =Datos!E89 -> 22.67 | G43: =F43/DIAS_ANIO -> 0.094458333 | H43: =G43*FAC_MAN -> 0.102015 | I43: =Datos!G89 -> 3 | J43: =Datos!H89 -> 5 | K43: =G43*(I43+J43)/2 -> 0.37783333 | L43: =H43*J43-K43 -> 0.13224167 | M43: =Datos!I89 -> Caja de 10 u | N43: =Datos!J89 -> 10 | O43: =Datos!K89 -> 60 | P43: =MAX(1,ROUNDUP(H43*O43/N43,0)) -> 1 | Q43: =IF(P43*N43=0,0,F43/(P43*N43)) -> 2.267 | R43: Insumos de soldadura y superficie | S43: =L43+P43*N43 -> 10.132242 | T43: =Datos!M89 -> 250 | U43: =IF(T43=0,0,S43/T43) -> 0.040528967 | V43: =IFERROR(VLOOKUP(R43,Almacenes!$A$19:$I$32,9,FALSE()),"") -> Granalla en el piso del rack; alambre y pintura arriba; insumos chicos en caja. | W43: Manuales
A44: =Datos!A90 -> P39 | B44: =Datos!C90 -> MP-94 | C44: =Datos!B90 -> Mecha de acero rápido 4,5 mm | D44: =Datos!F90 -> u | E44: =Datos!D90 -> Espacio Industria | F44: =Datos!E90 -> 18.147 | G44: =F44/DIAS_ANIO -> 0.0756125 | H44: =G44*FAC_MAN -> 0.0816615 | I44: =Datos!G90 -> 1 | J44: =Datos!H90 -> 1 | K44: =G44*(I44+J44)/2 -> 0.0756125 | L44: =H44*J44-K44 -> 0.006049 | M44: =Datos!I90 -> Caja de 10 u | N44: =Datos!J90 -> 10 | O44: =Datos!K90 -> 60 | P44: =MAX(1,ROUNDUP(H44*O44/N44,0)) -> 1 | Q44: =IF(P44*N44=0,0,F44/(P44*N44)) -> 1.8147 | R44: Insumos de soldadura y superficie | S44: =L44+P44*N44 -> 10.006049 | T44: =Datos!M90 -> 250 | U44: =IF(T44=0,0,S44/T44) -> 0.040024196 | V44: =IFERROR(VLOOKUP(R44,Almacenes!$A$19:$I$32,9,FALSE()),"") -> Granalla en el piso del rack; alambre y pintura arriba; insumos chicos en caja. | W44: Manuales
A45: =Datos!A91 -> P40 | B45: =Datos!C91 -> MP-95 | C45: =Datos!B91 -> Spray antiproyecciones 400 ml | D45: =Datos!F91 -> u | E45: =Datos!D91 -> Würth Argentina | F45: =Datos!E91 -> 7.768 | G45: =F45/DIAS_ANIO -> 0.032366667 | H45: =G45*FAC_MAN -> 0.034956 | I45: =Datos!G91 -> 3 | J45: =Datos!H91 -> 5 | K45: =G45*(I45+J45)/2 -> 0.12946667 | L45: =H45*J45-K45 -> 0.045313333 | M45: =Datos!I91 -> Unidad (aerosol de 400 ml) | N45: =Datos!J91 -> 1 | O45: =Datos!K91 -> 60 | P45: =MAX(1,ROUNDUP(H45*O45/N45,0)) -> 3 | Q45: =IF(P45*N45=0,0,F45/(P45*N45)) -> 2.5893333 | R45: Insumos de soldadura y superficie | S45: =L45+P45*N45 -> 3.0453133 | T45: =Datos!M91 -> 250 | U45: =IF(T45=0,0,S45/T45) -> 0.012181253 | V45: =IFERROR(VLOOKUP(R45,Almacenes!$A$19:$I$32,9,FALSE()),"") -> Granalla en el piso del rack; alambre y pintura arriba; insumos chicos en caja. | W45: Manuales
A46: =Datos!A92 -> P41 | B46: =Datos!C92 -> MP-28 | C46: =Datos!B92 -> Granalla de acero S330 / S390 | D46: =Datos!F92 -> kg | E46: =Datos!D92 -> CyM Materiales | F46: =Datos!E92 -> 22757.005 | G46: =F46/DIAS_ANIO -> 94.820854 | H46: =G46*FAC_MAN -> 102.40652 | I46: =Datos!G92 -> 1 | J46: =Datos!H92 -> 1 | K46: =G46*(I46+J46)/2 -> 94.820854 | L46: =H46*J46-K46 -> 7.5856683 | M46: =Datos!I92 -> Pallet de 1.000 kg (40 bolsas de 25 kg) | N46: =Datos!J92 -> 1000 | O46: =Datos!K92 -> 20 | P46: =MAX(1,ROUNDUP(H46*O46/N46,0)) -> 3 | Q46: =IF(P46*N46=0,0,F46/(P46*N46)) -> 7.5856683 | R46: Insumos de soldadura y superficie | S46: =L46+P46*N46 -> 3007.5857 | T46: =Datos!M92 -> 1000 | U46: =IF(T46=0,0,S46/T46) -> 3.0075857 | V46: =IFERROR(VLOOKUP(R46,Almacenes!$A$19:$I$32,9,FALSE()),"") -> Granalla en el piso del rack; alambre y pintura arriba; insumos chicos en caja. | W46: Manuales
A47: =Datos!A93 -> P42 | B47: =Datos!C93 -> MP-31 | C47: =Datos!B93 -> Pintura en polvo poliéster rojo 03-1-050 | D47: =Datos!F93 -> kg | E47: =Datos!D93 -> Sinteplast | F47: =Datos!E93 -> 3581.935 | G47: =F47/DIAS_ANIO -> 14.924729 | H47: =G47*FAC_MAN -> 16.118707 | I47: =Datos!G93 -> 1 | J47: =Datos!H93 -> 1 | K47: =G47*(I47+J47)/2 -> 14.924729 | L47: =H47*J47-K47 -> 1.1939783 | M47: =Datos!I93 -> Caja de 25 kg | N47: =Datos!J93 -> 25 | O47: =Datos!K93 -> 20 | P47: =MAX(1,ROUNDUP(H47*O47/N47,0)) -> 13 | Q47: =IF(P47*N47=0,0,F47/(P47*N47)) -> 11.021338 | R47: Depósito de polvo químico | S47: =L47+P47*N47 -> 326.19398 | T47: =Datos!M93 -> 600 | U47: =IF(T47=0,0,S47/T47) -> 0.54365663 | V47: =IFERROR(VLOOKUP(R47,Almacenes!$A$19:$I$32,9,FALSE()),"") -> Big bags de 1 × 1 m en el piso, de a 2, por fecha de llegada; bolsas de 25 kg y cajas de pintura sobre pallet plástico. Depósito seco. | W47: Manuales
A48: =Datos!A94 -> P43 | B48: =Datos!C94 -> MP-33 | C48: =Datos!B94 -> Polvo ABC 60 (manuales y sus recargas) | D48: =Datos!F94 -> kg | E48: =Datos!D94 -> DEMSA | F48: =Datos!E94 -> 272378.17 | G48: =F48/DIAS_ANIO -> 1134.909 | H48: =G48*MAX(FAC_MAN,FAC_REC) -> 1385.7575 | I48: =Datos!G94 -> 3 | J48: =Datos!H94 -> 6 | K48: =G48*(I48+J48)/2 -> 5107.0907 | L48: =H48*J48-K48 -> 3207.4541 | M48: =Datos!I94 -> Big bag de 1.000 kg | N48: =Datos!J94 -> 1000 | O48: =Datos!K94 -> 5 | P48: =MAX(1,ROUNDUP(H48*O48/N48,0)) -> 7 | Q48: =IF(P48*N48=0,0,F48/(P48*N48)) -> 38.911167 | R48: Depósito de polvo químico | S48: =L48+P48*N48 -> 10207.454 | T48: =Datos!M94 -> 2000 | U48: =IF(T48=0,0,S48/T48) -> 5.103727 | V48: =IFERROR(VLOOKUP(R48,Almacenes!$A$19:$I$32,9,FALSE()),"") -> Big bags de 1 × 1 m en el piso, de a 2, por fecha de llegada; bolsas de 25 kg y cajas de pintura sobre pallet plástico. Depósito seco. | W48: Manuales y recargas
A49: =Datos!A95 -> P44 | B49: =Datos!C95 -> MP-33B | C49: =Datos!B95 -> Polvo ABC 90 (carros y sus recargas) | D49: =Datos!F95 -> kg | E49: =Datos!D95 -> DEMSA | F49: =Datos!E95 -> 102532.95 | G49: =F49/DIAS_ANIO -> 427.22063 | H49: =G49*MAX(FAC_CAR,FAC_REC) -> 521.64901 | I49: =Datos!G95 -> 3 | J49: =Datos!H95 -> 6 | K49: =G49*(I49+J49)/2 -> 1922.4928 | L49: =H49*J49-K49 -> 1207.4012 | M49: =Datos!I95 -> Big bag de 1.000 kg | N49: =Datos!J95 -> 1000 | O49: =Datos!K95 -> 5 | P49: =MAX(1,ROUNDUP(H49*O49/N49,0)) -> 3 | Q49: =IF(P49*N49=0,0,F49/(P49*N49)) -> 34.17765 | R49: Depósito de polvo químico | S49: =L49+P49*N49 -> 4207.4012 | T49: =Datos!M95 -> 2000 | U49: =IF(T49=0,0,S49/T49) -> 2.1037006 | V49: =IFERROR(VLOOKUP(R49,Almacenes!$A$19:$I$32,9,FALSE()),"") -> Big bags de 1 × 1 m en el piso, de a 2, por fecha de llegada; bolsas de 25 kg y cajas de pintura sobre pallet plástico. Depósito seco. | W49: Carros y recargas
A50: =Datos!A96 -> P45 | B50: =Datos!C96 -> MP-34 | C50: =Datos!B96 -> Nitrógeno seco | D50: =Datos!F96 -> m³ | E50: =Datos!D96 -> Air Liquide | F50: =Datos!E96 -> 3652.274 | G50: =F50/DIAS_ANIO -> 15.217808 | H50: =G50*MAX(FAC_MAN,FAC_REC) -> 18.581393 | I50: =Datos!G96 -> 1 | J50: =Datos!H96 -> 1 | K50: =G50*(I50+J50)/2 -> 15.217808 | L50: =H50*J50-K50 -> 3.3635851 | M50: =Datos!I96 -> Pack de 12 cilindros con manifold (110 m³) | N50: =Datos!J96 -> 110 | O50: =Datos!K96 -> 5 | P50: =MAX(1,ROUNDUP(H50*O50/N50,0)) -> 1 | Q50: =IF(P50*N50=0,0,F50/(P50*N50)) -> 33.202491 | R50: Jaula de gases | S50: =L50+P50*N50 -> 113.36359 | T50: =Datos!M96 -> 103 | U50: =IF(T50=0,0,S50/T50) -> 1.1006173 | V50: =IFERROR(VLOOKUP(R50,Almacenes!$A$19:$I$32,9,FALSE()),"") -> Baterías y pack con manifold conectados a la cañería; cilindros sueltos encadenados en gabinete. | W50: Manuales y recargas
A51: =Datos!A97 -> P46 | B51: =Datos!C97 -> MP-35 | C51: =Datos!B97 -> Polvo BC (recargas) | D51: =Datos!F97 -> kg | E51: =Datos!D97 -> Polvex | F51: =Datos!E97 -> 727.985 | G51: =F51/DIAS_ANIO -> 3.0332708 | H51: =G51*FAC_REC -> 3.7037133 | I51: =Datos!G97 -> 3 | J51: =Datos!H97 -> 6 | K51: =G51*(I51+J51)/2 -> 13.649719 | L51: =H51*J51-K51 -> 8.5725609 | M51: =Datos!I97 -> Bolsa de 25 kg | N51: =Datos!J97 -> 25 | O51: =Datos!K97 -> 20 | P51: =MAX(1,ROUNDUP(H51*O51/N51,0)) -> 3 | Q51: =IF(P51*N51=0,0,F51/(P51*N51)) -> 9.7064667 | R51: Depósito de polvo químico | S51: =L51+P51*N51 -> 83.572561 | T51: =Datos!M97 -> 1000 | U51: =IF(T51=0,0,S51/T51) -> 0.083572561 | V51: =IFERROR(VLOOKUP(R51,Almacenes!$A$19:$I$32,9,FALSE()),"") -> Big bags de 1 × 1 m en el piso, de a 2, por fecha de llegada; bolsas de 25 kg y cajas de pintura sobre pallet plástico. Depósito seco. | W51: Recargas
A52: =Datos!A98 -> P47 | B52: =Datos!C98 -> MP-36 | C52: =Datos!B98 -> Polvo clase D (recargas) | D52: =Datos!F98 -> kg | E52: =Datos!D98 -> DEMSA | F52: =Datos!E98 -> 1170.002 | G52: =F52/DIAS_ANIO -> 4.8750083 | H52: =G52*FAC_REC -> 5.9525292 | I52: =Datos!G98 -> 3 | J52: =Datos!H98 -> 6 | K52: =G52*(I52+J52)/2 -> 21.937538 | L52: =H52*J52-K52 -> 13.777637 | M52: =Datos!I98 -> Bolsa de 25 kg | N52: =Datos!J98 -> 25 | O52: =Datos!K98 -> 20 | P52: =MAX(1,ROUNDUP(H52*O52/N52,0)) -> 5 | Q52: =IF(P52*N52=0,0,F52/(P52*N52)) -> 9.360016 | R52: Depósito de polvo químico | S52: =L52+P52*N52 -> 138.77764 | T52: =Datos!M98 -> 1000 | U52: =IF(T52=0,0,S52/T52) -> 0.13877764 | V52: =IFERROR(VLOOKUP(R52,Almacenes!$A$19:$I$32,9,FALSE()),"") -> Big bags de 1 × 1 m en el piso, de a 2, por fecha de llegada; bolsas de 25 kg y cajas de pintura sobre pallet plástico. Depósito seco. | W52: Recargas
A53: =Datos!A99 -> P48 | B53: =Datos!C99 -> MP-37 | C53: =Datos!B99 -> CO₂ líquido (recargas) | D53: =Datos!F99 -> kg | E53: =Datos!D99 -> Air Liquide | F53: =Datos!E99 -> 2465.021 | G53: =F53/DIAS_ANIO -> 10.270921 | H53: =G53*FAC_REC -> 12.541098 | I53: =Datos!G99 -> 1 | J53: =Datos!H99 -> 1 | K53: =G53*(I53+J53)/2 -> 10.270921 | L53: =H53*J53-K53 -> 2.2701769 | M53: =Datos!I99 -> Cilindro de 25 kg | N53: =Datos!J99 -> 25 | O53: =Datos!K99 -> 5 | P53: =MAX(1,ROUNDUP(H53*O53/N53,0)) -> 3 | Q53: =IF(P53*N53=0,0,F53/(P53*N53)) -> 32.866947 | R53: Jaula de gases | S53: =L53+P53*N53 -> 77.270177 | T53: =Datos!M99 -> 25 | U53: =IF(T53=0,0,S53/T53) -> 3.0908071 | V53: =IFERROR(VLOOKUP(R53,Almacenes!$A$19:$I$32,9,FALSE()),"") -> Baterías y pack con manifold conectados a la cañería; cilindros sueltos encadenados en gabinete. | W53: Recargas
A54: =Datos!A100 -> P49 | B54: =Datos!C100 -> MP-38 | C54: =Datos!B100 -> Agente limpio HCFC-123 (recargas) | D54: =Datos!F100 -> kg | E54: =Datos!D100 -> Polvex / DEMSA | F54: =Datos!E100 -> 186.31 | G54: =F54/DIAS_ANIO -> 0.77629167 | H54: =G54*FAC_REC -> 0.94787505 | I54: =Datos!G100 -> 3 | J54: =Datos!H100 -> 6 | K54: =G54*(I54+J54)/2 -> 3.4933125 | L54: =H54*J54-K54 -> 2.1939378 | M54: =Datos!I100 -> Cilindro de 50 kg | N54: =Datos!J100 -> 50 | O54: =Datos!K100 -> 20 | P54: =MAX(1,ROUNDUP(H54*O54/N54,0)) -> 1 | Q54: =IF(P54*N54=0,0,F54/(P54*N54)) -> 3.7262 | R54: Insumos de recargas | S54: =L54+P54*N54 -> 52.193938 | T54: =Datos!M100 -> 50 | U54: =IF(T54=0,0,S54/T54) -> 1.0438788 | V54: =IFERROR(VLOOKUP(R54,Almacenes!$A$19:$I$32,9,FALSE()),"") -> Tambores de 200 L en el piso sobre pallet antiderrame; bidones en bandeja; cajas en los niveles. | W54: Recargas
A55: =Datos!A101 -> P50 | B55: =Datos!C101 -> MP-40 | C55: =Datos!B101 -> Concentrado AFFF 3 % (recargas) | D55: =Datos!F101 -> L | E55: =Datos!D101 -> Polvex | F55: =Datos!E101 -> 506.638 | G55: =F55/DIAS_ANIO -> 2.1109917 | H55: =G55*FAC_REC -> 2.5775832 | I55: =Datos!G101 -> 1 | J55: =Datos!H101 -> 1 | K55: =G55*(I55+J55)/2 -> 2.1109917 | L55: =H55*J55-K55 -> 0.46659151 | M55: =Datos!I101 -> Bidón de 20 L | N55: =Datos!J101 -> 20 | O55: =Datos!K101 -> 20 | P55: =MAX(1,ROUNDUP(H55*O55/N55,0)) -> 3 | Q55: =IF(P55*N55=0,0,F55/(P55*N55)) -> 8.4439667 | R55: Insumos de recargas | S55: =L55+P55*N55 -> 60.466592 | T55: =Datos!M101 -> 480 | U55: =IF(T55=0,0,S55/T55) -> 0.12597207 | V55: =IFERROR(VLOOKUP(R55,Almacenes!$A$19:$I$32,9,FALSE()),"") -> Tambores de 200 L en el piso sobre pallet antiderrame; bidones en bandeja; cajas en los niveles. | W55: Recargas
A56: =Datos!A102 -> P51 | B56: =Datos!C102 -> MP-41 | C56: =Datos!B102 -> Acetato de potasio Gastro K (recargas) | D56: =Datos!F102 -> L | E56: =Datos!D102 -> Polvex | F56: =Datos!E102 -> 7419.099 | G56: =F56/DIAS_ANIO -> 30.912913 | H56: =G56*FAC_REC -> 37.745579 | I56: =Datos!G102 -> 3 | J56: =Datos!H102 -> 6 | K56: =G56*(I56+J56)/2 -> 139.10811 | L56: =H56*J56-K56 -> 87.365369 | M56: =Datos!I102 -> Tambor de 200 L (4 por pallet) | N56: =Datos!J102 -> 200 | O56: =Datos!K102 -> 20 | P56: =MAX(1,ROUNDUP(H56*O56/N56,0)) -> 4 | Q56: =IF(P56*N56=0,0,F56/(P56*N56)) -> 9.2738737 | R56: Insumos de recargas | S56: =L56+P56*N56 -> 887.36537 | T56: =Datos!M102 -> 800 | U56: =IF(T56=0,0,S56/T56) -> 1.1092067 | V56: =IFERROR(VLOOKUP(R56,Almacenes!$A$19:$I$32,9,FALSE()),"") -> Tambores de 200 L en el piso sobre pallet antiderrame; bidones en bandeja; cajas en los niveles. | W56: Recargas
A57: =Datos!A103 -> P52 | B57: =Datos!C103 -> MP-42 | C57: =Datos!B103 -> Válvula HZ M-22 con tubo de pesca (1 kg) | D57: =Datos!F103 -> u | E57: =Datos!D103 -> Polvex (HZ) | F57: =Datos!E103 -> 32072.639 | G57: =F57/DIAS_ANIO -> 133.636 | H57: =G57*FAC_MAN -> 144.32688 | I57: =Datos!G103 -> 4 | J57: =Datos!H103 -> 7 | K57: =G57*(I57+J57)/2 -> 734.99798 | L57: =H57*J57-K57 -> 275.29015 | M57: =Datos!I103 -> Pallet de 3.000 u | N57: =Datos!J103 -> 3000 | O57: =Datos!K103 -> 20 | P57: =MAX(1,ROUNDUP(H57*O57/N57,0)) -> 1 | Q57: =IF(P57*N57=0,0,F57/(P57*N57)) -> 10.69088 | R57: Insumos de montaje (manuales) | S57: =L57+P57*N57 -> 3275.2902 | T57: =Datos!M103 -> 3000 | U57: =IF(T57=0,0,S57/T57) -> 1.0917634 | V57: =IFERROR(VLOOKUP(R57,Almacenes!$A$19:$I$32,9,FALSE()),"") -> Abajo el pallet o la caja en uso (de ahí sale el carro de abastecimiento), arriba la reposición del pedido mensual. | W57: Manuales
A58: =Datos!A104 -> P53 | B58: =Datos!C104 -> MP-43 | C58: =Datos!B104 -> Válvula HZ M-30 con resorte, sin tubo pescante (2,5 a 10 kg) | D58: =Datos!F104 -> u | E58: =Datos!D104 -> Polvex (HZ) | F58: =Datos!E104 -> 40096.365 | G58: =F58/DIAS_ANIO -> 167.06819 | H58: =G58*FAC_MAN -> 180.43364 | I58: =Datos!G104 -> 4 | J58: =Datos!H104 -> 7 | K58: =G58*(I58+J58)/2 -> 918.87503 | L58: =H58*J58-K58 -> 344.16047 | M58: =Datos!I104 -> Pallet de 1.500 u | N58: =Datos!J104 -> 1500 | O58: =Datos!K104 -> 20 | P58: =MAX(1,ROUNDUP(H58*O58/N58,0)) -> 3 | Q58: =IF(P58*N58=0,0,F58/(P58*N58)) -> 8.9103033 | R58: Insumos de montaje (manuales) | S58: =L58+P58*N58 -> 4844.1605 | T58: =Datos!M104 -> 1500 | U58: =IF(T58=0,0,S58/T58) -> 3.2294403 | V58: =IFERROR(VLOOKUP(R58,Almacenes!$A$19:$I$32,9,FALSE()),"") -> Abajo el pallet o la caja en uso (de ahí sale el carro de abastecimiento), arriba la reposición del pedido mensual. | W58: Manuales
A59: =Datos!A105 -> P54 | B59: =Datos!C105 -> MP-44/25 | C59: =Datos!B105 -> Válvula HZ de carro 25 kg, sin tubo pescante | D59: =Datos!F105 -> u | E59: =Datos!D105 -> Polvex (HZ) | F59: =Datos!E105 -> 453.671 | G59: =F59/DIAS_ANIO -> 1.8902958 | H59: =G59*FAC_CAR -> 2.0415195 | I59: =Datos!G105 -> 4 | J59: =Datos!H105 -> 7 | K59: =G59*(I59+J59)/2 -> 10.396627 | L59: =H59*J59-K59 -> 3.8940094 | M59: =Datos!I105 -> Caja de 10 u | N59: =Datos!J105 -> 10 | O59: =Datos!K105 -> 20 | P59: =MAX(1,ROUNDUP(H59*O59/N59,0)) -> 5 | Q59: =IF(P59*N59=0,0,F59/(P59*N59)) -> 9.07342 | R59: Rack de insumos de montaje (carros) | S59: =L59+P59*N59 -> 53.894009 | T59: =Datos!M105 -> 200 | U59: =IF(T59=0,0,S59/T59) -> 0.26947005 | V59: =IFERROR(VLOOKUP(R59,Almacenes!$A$19:$I$32,9,FALSE()),"") -> Ruedas en pallet abajo; cajas arriba. | W59: Carros
A60: =Datos!A106 -> P55 | B60: =Datos!C106 -> MP-44/50 | C60: =Datos!B106 -> Válvula HZ de carro 50-70-100 kg, sin tubo pescante | D60: =Datos!F106 -> u | E60: =Datos!D106 -> Polvex (HZ) | F60: =Datos!E106 -> 1361.012 | G60: =F60/DIAS_ANIO -> 5.6708833 | H60: =G60*FAC_CAR -> 6.124554 | I60: =Datos!G106 -> 4 | J60: =Datos!H106 -> 7 | K60: =G60*(I60+J60)/2 -> 31.189858 | L60: =H60*J60-K60 -> 11.68202 | M60: =Datos!I106 -> Caja de 10 u | N60: =Datos!J106 -> 10 | O60: =Datos!K106 -> 20 | P60: =MAX(1,ROUNDUP(H60*O60/N60,0)) -> 13 | Q60: =IF(P60*N60=0,0,F60/(P60*N60)) -> 10.469323 | R60: Rack de insumos de montaje (carros) | S60: =L60+P60*N60 -> 141.68202 | T60: =Datos!M106 -> 200 | U60: =IF(T60=0,0,S60/T60) -> 0.7084101 | V60: =IFERROR(VLOOKUP(R60,Almacenes!$A$19:$I$32,9,FALSE()),"") -> Ruedas en pallet abajo; cajas arriba. | W60: Carros
A61: =Datos!A107 -> P56 | B61: =Datos!C107 -> MP-45 | C61: =Datos!B107 -> Manómetro 1,4 MPa | D61: =Datos!F107 -> u | E61: =Datos!D107 -> Yukon | F61: =Datos!E107 -> 73983.687 | G61: =F61/DIAS_ANIO -> 308.26536 | H61: =G61*FAC_MAN -> 332.92659 | I61: =Datos!G107 -> 4 | J61: =Datos!H107 -> 7 | K61: =G61*(I61+J61)/2 -> 1695.4595 | L61: =H61*J61-K61 -> 635.02665 | M61: =Datos!I107 -> Caja de 100 u | N61: =Datos!J107 -> 100 | O61: =Datos!K107 -> 20 | P61: =MAX(1,ROUNDUP(H61*O61/N61,0)) -> 67 | Q61: =IF(P61*N61=0,0,F61/(P61*N61)) -> 11.042341 | R61: Insumos de montaje (manuales) | S61: =L61+P61*N61 -> 7335.0266 | T61: =Datos!M107 -> 3000 | U61: =IF(T61=0,0,S61/T61) -> 2.4450089 | V61: =IFERROR(VLOOKUP(R61,Almacenes!$A$19:$I$32,9,FALSE()),"") -> Abajo el pallet o la caja en uso (de ahí sale el carro de abastecimiento), arriba la reposición del pedido mensual. | W61: Manuales
A62: =Datos!A108 -> P57 | B62: =Datos!C108 -> MP-46/ABC2.5 | C62: =Datos!B108 -> Tubo pescante de PVC rígido, ABC 2,5 kg | D62: =Datos!F108 -> u | E62: =Datos!D108 -> Alt. 1 Esinex (Billinghurst) / Alt. 2 Securitá | F62: =Datos!E108 -> 7436.458 | G62: =F62/DIAS_ANIO -> 30.985242 | H62: =G62*FAC_MAN -> 33.464061 | I62: =Datos!G108 -> 4 | J62: =Datos!H108 -> 7 | K62: =G62*(I62+J62)/2 -> 170.41883 | L62: =H62*J62-K62 -> 63.829598 | M62: =Datos!I108 -> Caja de 200 u | N62: =Datos!J108 -> 200 | O62: =Datos!K108 -> 20 | P62: =MAX(1,ROUNDUP(H62*O62/N62,0)) -> 4 | Q62: =IF(P62*N62=0,0,F62/(P62*N62)) -> 9.2955725 | R62: Insumos de montaje (manuales) | S62: =L62+P62*N62 -> 863.8296 | T62: =Datos!M108 -> 6000 | U62: =IF(T62=0,0,S62/T62) -> 0.1439716 | V62: =IFERROR(VLOOKUP(R62,Almacenes!$A$19:$I$32,9,FALSE()),"") -> Abajo el pallet o la caja en uso (de ahí sale el carro de abastecimiento), arriba la reposición del pedido mensual. | W62: Manuales
A63: =Datos!A109 -> P58 | B63: =Datos!C109 -> MP-46/ABC5 | C63: =Datos!B109 -> Tubo pescante de PVC rígido, ABC 5 kg | D63: =Datos!F109 -> u | E63: =Datos!D109 -> Alt. 1 Esinex (Billinghurst) / Alt. 2 Securitá | F63: =Datos!E109 -> 30814.979 | G63: =F63/DIAS_ANIO -> 128.39575 | H63: =G63*FAC_MAN -> 138.66741 | I63: =Datos!G109 -> 4 | J63: =Datos!H109 -> 7 | K63: =G63*(I63+J63)/2 -> 706.1766 | L63: =H63*J63-K63 -> 264.49524 | M63: =Datos!I109 -> Caja de 200 u | N63: =Datos!J109 -> 200 | O63: =Datos!K109 -> 20 | P63: =MAX(1,ROUNDUP(H63*O63/N63,0)) -> 14 | Q63: =IF(P63*N63=0,0,F63/(P63*N63)) -> 11.00535 | R63: Insumos de montaje (manuales) | S63: =L63+P63*N63 -> 3064.4952 | T63: =Datos!M109 -> 6000 | U63: =IF(T63=0,0,S63/T63) -> 0.51074921 | V63: =IFERROR(VLOOKUP(R63,Almacenes!$A$19:$I$32,9,FALSE()),"") -> Abajo el pallet o la caja en uso (de ahí sale el carro de abastecimiento), arriba la reposición del pedido mensual. | W63: Manuales
A64: =Datos!A110 -> P59 | B64: =Datos!C110 -> MP-46/ABC10 | C64: =Datos!B110 -> Tubo pescante de PVC rígido, ABC 10 kg | D64: =Datos!F110 -> u | E64: =Datos!D110 -> Alt. 1 Esinex (Billinghurst) / Alt. 2 Securitá | F64: =Datos!E110 -> 1844.928 | G64: =F64/DIAS_ANIO -> 7.6872 | H64: =G64*FAC_MAN -> 8.302176 | I64: =Datos!G110 -> 4 | J64: =Datos!H110 -> 7 | K64: =G64*(I64+J64)/2 -> 42.2796 | L64: =H64*J64-K64 -> 15.835632 | M64: =Datos!I110 -> Caja de 200 u | N64: =Datos!J110 -> 200 | O64: =Datos!K110 -> 20 | P64: =MAX(1,ROUNDUP(H64*O64/N64,0)) -> 1 | Q64: =IF(P64*N64=0,0,F64/(P64*N64)) -> 9.22464 | R64: Insumos de montaje (manuales) | S64: =L64+P64*N64 -> 215.83563 | T64: =Datos!M110 -> 6000 | U64: =IF(T64=0,0,S64/T64) -> 0.035972605 | V64: =IFERROR(VLOOKUP(R64,Almacenes!$A$19:$I$32,9,FALSE()),"") -> Abajo el pallet o la caja en uso (de ahí sale el carro de abastecimiento), arriba la reposición del pedido mensual. | W64: Manuales
A65: =Datos!A111 -> P60 | B65: =Datos!C111 -> MP-47/ABC25 | C65: =Datos!B111 -> Tubo pescante de acero SAE 1010, carro 25 kg | D65: =Datos!F111 -> u | E65: =Datos!D111 -> Alt. 1 Mozart (V. Alsina) / Alt. 2 Georgia (CABA) | F65: =Datos!E111 -> 453.671 | G65: =F65/DIAS_ANIO -> 1.8902958 | H65: =G65*FAC_CAR -> 2.0415195 | I65: =Datos!G111 -> 4 | J65: =Datos!H111 -> 7 | K65: =G65*(I65+J65)/2 -> 10.396627 | L65: =H65*J65-K65 -> 3.8940094 | M65: =Datos!I111 -> Caja de 20 u | N65: =Datos!J111 -> 20 | O65: =Datos!K111 -> 20 | P65: =MAX(1,ROUNDUP(H65*O65/N65,0)) -> 3 | Q65: =IF(P65*N65=0,0,F65/(P65*N65)) -> 7.5611833 | R65: Rack de insumos de montaje (carros) | S65: =L65+P65*N65 -> 63.894009 | T65: =Datos!M111 -> 200 | U65: =IF(T65=0,0,S65/T65) -> 0.31947005 | V65: =IFERROR(VLOOKUP(R65,Almacenes!$A$19:$I$32,9,FALSE()),"") -> Ruedas en pallet abajo; cajas arriba. | W65: Carros
A66: =Datos!A112 -> P61 | B66: =Datos!C112 -> MP-47/ABC50 | C66: =Datos!B112 -> Tubo pescante de acero SAE 1010, carro 50 kg | D66: =Datos!F112 -> u | E66: =Datos!D112 -> Alt. 1 Mozart (V. Alsina) / Alt. 2 Georgia (CABA) | F66: =Datos!E112 -> 997.995 | G66: =F66/DIAS_ANIO -> 4.1583125 | H66: =G66*FAC_CAR -> 4.4909775 | I66: =Datos!G112 -> 4 | J66: =Datos!H112 -> 7 | K66: =G66*(I66+J66)/2 -> 22.870719 | L66: =H66*J66-K66 -> 8.5661237 | M66: =Datos!I112 -> Caja de 20 u | N66: =Datos!J112 -> 20 | O66: =Datos!K112 -> 20 | P66: =MAX(1,ROUNDUP(H66*O66/N66,0)) -> 5 | Q66: =IF(P66*N66=0,0,F66/(P66*N66)) -> 9.97995 | R66: Rack de insumos de montaje (carros) | S66: =L66+P66*N66 -> 108.56612 | T66: =Datos!M112 -> 200 | U66: =IF(T66=0,0,S66/T66) -> 0.54283062 | V66: =IFERROR(VLOOKUP(R66,Almacenes!$A$19:$I$32,9,FALSE()),"") -> Ruedas en pallet abajo; cajas arriba. | W66: Carros
A67: =Datos!A113 -> P62 | B67: =Datos!C113 -> MP-47/ABC70 | C67: =Datos!B113 -> Tubo pescante de acero SAE 1010, carro 70 kg | D67: =Datos!F113 -> u | E67: =Datos!D113 -> Alt. 1 Mozart (V. Alsina) / Alt. 2 Georgia (CABA) | F67: =Datos!E113 -> 217.81 | G67: =F67/DIAS_ANIO -> 0.90754167 | H67: =G67*FAC_CAR -> 0.980145 | I67: =Datos!G113 -> 4 | J67: =Datos!H113 -> 7 | K67: =G67*(I67+J67)/2 -> 4.9914792 | L67: =H67*J67-K67 -> 1.8695358 | M67: =Datos!I113 -> Caja de 20 u | N67: =Datos!J113 -> 20 | O67: =Datos!K113 -> 20 | P67: =MAX(1,ROUNDUP(H67*O67/N67,0)) -> 1 | Q67: =IF(P67*N67=0,0,F67/(P67*N67)) -> 10.8905 | R67: Rack de insumos de montaje (carros) | S67: =L67+P67*N67 -> 21.869536 | T67: =Datos!M113 -> 200 | U67: =IF(T67=0,0,S67/T67) -> 0.10934768 | V67: =IFERROR(VLOOKUP(R67,Almacenes!$A$19:$I$32,9,FALSE()),"") -> Ruedas en pallet abajo; cajas arriba. | W67: Carros
A68: =Datos!A114 -> P63 | B68: =Datos!C114 -> MP-47/ABC100 | C68: =Datos!B114 -> Tubo pescante de acero SAE 1010, carro 100 kg | D68: =Datos!F114 -> u | E68: =Datos!D114 -> Alt. 1 Mozart (V. Alsina) / Alt. 2 Georgia (CABA) | F68: =Datos!E114 -> 145.207 | G68: =F68/DIAS_ANIO -> 0.60502917 | H68: =G68*FAC_CAR -> 0.6534315 | I68: =Datos!G114 -> 4 | J68: =Datos!H114 -> 7 | K68: =G68*(I68+J68)/2 -> 3.3276604 | L68: =H68*J68-K68 -> 1.2463601 | M68: =Datos!I114 -> Caja de 20 u | N68: =Datos!J114 -> 20 | O68: =Datos!K114 -> 20 | P68: =MAX(1,ROUNDUP(H68*O68/N68,0)) -> 1 | Q68: =IF(P68*N68=0,0,F68/(P68*N68)) -> 7.26035 | R68: Rack de insumos de montaje (carros) | S68: =L68+P68*N68 -> 21.24636 | T68: =Datos!M114 -> 200 | U68: =IF(T68=0,0,S68/T68) -> 0.1062318 | V68: =IFERROR(VLOOKUP(R68,Almacenes!$A$19:$I$32,9,FALSE()),"") -> Ruedas en pallet abajo; cajas arriba. | W68: Carros
A69: =Datos!A115 -> P64 | B69: =Datos!C115 -> MP-48/ABC1 | C69: =Datos!B115 -> Tobera ABC 1 kg | D69: =Datos!F115 -> u | E69: =Datos!D115 -> Yukon | F69: =Datos!E115 -> 32072.639 | G69: =F69/DIAS_ANIO -> 133.636 | H69: =G69*FAC_MAN -> 144.32688 | I69: =Datos!G115 -> 4 | J69: =Datos!H115 -> 7 | K69: =G69*(I69+J69)/2 -> 734.99798 | L69: =H69*J69-K69 -> 275.29015 | M69: =Datos!I115 -> Caja de 50 u | N69: =Datos!J115 -> 50 | O69: =Datos!K115 -> 20 | P69: =MAX(1,ROUNDUP(H69*O69/N69,0)) -> 58 | Q69: =IF(P69*N69=0,0,F69/(P69*N69)) -> 11.059531 | R69: Insumos de montaje (manuales) | S69: =L69+P69*N69 -> 3175.2902 | T69: =Datos!M115 -> 1500 | U69: =IF(T69=0,0,S69/T69) -> 2.1168601 | V69: =IFERROR(VLOOKUP(R69,Almacenes!$A$19:$I$32,9,FALSE()),"") -> Abajo el pallet o la caja en uso (de ahí sale el carro de abastecimiento), arriba la reposición del pedido mensual. | W69: Manuales
A70: =Datos!A116 -> P65 | B70: =Datos!C116 -> MP-48/ABC2.5 | C70: =Datos!B116 -> Manguera con tobera ABC 2,5 kg | D70: =Datos!F116 -> u | E70: =Datos!D116 -> Yukon | F70: =Datos!E116 -> 7436.458 | G70: =F70/DIAS_ANIO -> 30.985242 | H70: =G70*FAC_MAN -> 33.464061 | I70: =Datos!G116 -> 4 | J70: =Datos!H116 -> 7 | K70: =G70*(I70+J70)/2 -> 170.41883 | L70: =H70*J70-K70 -> 63.829598 | M70: =Datos!I116 -> Caja de 50 u | N70: =Datos!J116 -> 50 | O70: =Datos!K116 -> 20 | P70: =MAX(1,ROUNDUP(H70*O70/N70,0)) -> 14 | Q70: =IF(P70*N70=0,0,F70/(P70*N70)) -> 10.623511 | R70: Insumos de montaje (manuales) | S70: =L70+P70*N70 -> 763.8296 | T70: =Datos!M116 -> 1500 | U70: =IF(T70=0,0,S70/T70) -> 0.50921973 | V70: =IFERROR(VLOOKUP(R70,Almacenes!$A$19:$I$32,9,FALSE()),"") -> Abajo el pallet o la caja en uso (de ahí sale el carro de abastecimiento), arriba la reposición del pedido mensual. | W70: Manuales
A71: =Datos!A117 -> P66 | B71: =Datos!C117 -> MP-48/ABC5 | C71: =Datos!B117 -> Manguera con tobera ABC 5 kg | D71: =Datos!F117 -> u | E71: =Datos!D117 -> Yukon | F71: =Datos!E117 -> 30814.979 | G71: =F71/DIAS_ANIO -> 128.39575 | H71: =G71*FAC_MAN -> 138.66741 | I71: =Datos!G117 -> 4 | J71: =Datos!H117 -> 7 | K71: =G71*(I71+J71)/2 -> 706.1766 | L71: =H71*J71-K71 -> 264.49524 | M71: =Datos!I117 -> Caja de 50 u | N71: =Datos!J117 -> 50 | O71: =Datos!K117 -> 20 | P71: =MAX(1,ROUNDUP(H71*O71/N71,0)) -> 56 | Q71: =IF(P71*N71=0,0,F71/(P71*N71)) -> 11.00535 | R71: Insumos de montaje (manuales) | S71: =L71+P71*N71 -> 3064.4952 | T71: =Datos!M117 -> 1500 | U71: =IF(T71=0,0,S71/T71) -> 2.0429968 | V71: =IFERROR(VLOOKUP(R71,Almacenes!$A$19:$I$32,9,FALSE()),"") -> Abajo el pallet o la caja en uso (de ahí sale el carro de abastecimiento), arriba la reposición del pedido mensual. | W71: Manuales
A72: =Datos!A118 -> P67 | B72: =Datos!C118 -> MP-48/ABC10 | C72: =Datos!B118 -> Manguera con tobera ABC 10 kg | D72: =Datos!F118 -> u | E72: =Datos!D118 -> Yukon | F72: =Datos!E118 -> 1844.928 | G72: =F72/DIAS_ANIO -> 7.6872 | H72: =G72*FAC_MAN -> 8.302176 | I72: =Datos!G118 -> 4 | J72: =Datos!H118 -> 7 | K72: =G72*(I72+J72)/2 -> 42.2796 | L72: =H72*J72-K72 -> 15.835632 | M72: =Datos!I118 -> Caja de 50 u | N72: =Datos!J118 -> 50 | O72: =Datos!K118 -> 20 | P72: =MAX(1,ROUNDUP(H72*O72/N72,0)) -> 4 | Q72: =IF(P72*N72=0,0,F72/(P72*N72)) -> 9.22464 | R72: Insumos de montaje (manuales) | S72: =L72+P72*N72 -> 215.83563 | T72: =Datos!M118 -> 1500 | U72: =IF(T72=0,0,S72/T72) -> 0.14389042 | V72: =IFERROR(VLOOKUP(R72,Almacenes!$A$19:$I$32,9,FALSE()),"") -> Abajo el pallet o la caja en uso (de ahí sale el carro de abastecimiento), arriba la reposición del pedido mensual. | W72: Manuales
A73: =Datos!A119 -> P68 | B73: =Datos!C119 -> MP-49/ABC25 | C73: =Datos!B119 -> Manguera con válvula esférica y tobera, carro 25 kg | D73: =Datos!F119 -> u | E73: =Datos!D119 -> Yukon | F73: =Datos!E119 -> 453.671 | G73: =F73/DIAS_ANIO -> 1.8902958 | H73: =G73*FAC_CAR -> 2.0415195 | I73: =Datos!G119 -> 4 | J73: =Datos!H119 -> 7 | K73: =G73*(I73+J73)/2 -> 10.396627 | L73: =H73*J73-K73 -> 3.8940094 | M73: =Datos!I119 -> Caja de 10 u | N73: =Datos!J119 -> 10 | O73: =Datos!K119 -> 20 | P73: =MAX(1,ROUNDUP(H73*O73/N73,0)) -> 5 | Q73: =IF(P73*N73=0,0,F73/(P73*N73)) -> 9.07342 | R73: Rack de insumos de montaje (carros) | S73: =L73+P73*N73 -> 53.894009 | T73: =Datos!M119 -> 120 | U73: =IF(T73=0,0,S73/T73) -> 0.44911675 | V73: =IFERROR(VLOOKUP(R73,Almacenes!$A$19:$I$32,9,FALSE()),"") -> Ruedas en pallet abajo; cajas arriba. | W73: Carros
A74: =Datos!A120 -> P69 | B74: =Datos!C120 -> MP-49/ABC50 | C74: =Datos!B120 -> Manguera con válvula esférica y tobera, carro 50 kg | D74: =Datos!F120 -> u | E74: =Datos!D120 -> Yukon | F74: =Datos!E120 -> 997.995 | G74: =F74/DIAS_ANIO -> 4.1583125 | H74: =G74*FAC_CAR -> 4.4909775 | I74: =Datos!G120 -> 4 | J74: =Datos!H120 -> 7 | K74: =G74*(I74+J74)/2 -> 22.870719 | L74: =H74*J74-K74 -> 8.5661237 | M74: =Datos!I120 -> Caja de 10 u | N74: =Datos!J120 -> 10 | O74: =Datos!K120 -> 20 | P74: =MAX(1,ROUNDUP(H74*O74/N74,0)) -> 9 | Q74: =IF(P74*N74=0,0,F74/(P74*N74)) -> 11.088833 | R74: Rack de insumos de montaje (carros) | S74: =L74+P74*N74 -> 98.566124 | T74: =Datos!M120 -> 120 | U74: =IF(T74=0,0,S74/T74) -> 0.82138436 | V74: =IFERROR(VLOOKUP(R74,Almacenes!$A$19:$I$32,9,FALSE()),"") -> Ruedas en pallet abajo; cajas arriba. | W74: Carros
A75: =Datos!A121 -> P70 | B75: =Datos!C121 -> MP-49/ABC70 | C75: =Datos!B121 -> Manguera con válvula esférica y tobera, carro 70 kg | D75: =Datos!F121 -> u | E75: =Datos!D121 -> Yukon | F75: =Datos!E121 -> 217.81 | G75: =F75/DIAS_ANIO -> 0.90754167 | H75: =G75*FAC_CAR -> 0.980145 | I75: =Datos!G121 -> 4 | J75: =Datos!H121 -> 7 | K75: =G75*(I75+J75)/2 -> 4.9914792 | L75: =H75*J75-K75 -> 1.8695358 | M75: =Datos!I121 -> Caja de 10 u | N75: =Datos!J121 -> 10 | O75: =Datos!K121 -> 20 | P75: =MAX(1,ROUNDUP(H75*O75/N75,0)) -> 2 | Q75: =IF(P75*N75=0,0,F75/(P75*N75)) -> 10.8905 | R75: Rack de insumos de montaje (carros) | S75: =L75+P75*N75 -> 21.869536 | T75: =Datos!M121 -> 120 | U75: =IF(T75=0,0,S75/T75) -> 0.18224613 | V75: =IFERROR(VLOOKUP(R75,Almacenes!$A$19:$I$32,9,FALSE()),"") -> Ruedas en pallet abajo; cajas arriba. | W75: Carros
A76: =Datos!A122 -> P71 | B76: =Datos!C122 -> MP-49/ABC100 | C76: =Datos!B122 -> Manguera con válvula esférica y tobera, carro 100 kg | D76: =Datos!F122 -> u | E76: =Datos!D122 -> Yukon | F76: =Datos!E122 -> 145.207 | G76: =F76/DIAS_ANIO -> 0.60502917 | H76: =G76*FAC_CAR -> 0.6534315 | I76: =Datos!G122 -> 4 | J76: =Datos!H122 -> 7 | K76: =G76*(I76+J76)/2 -> 3.3276604 | L76: =H76*J76-K76 -> 1.2463601 | M76: =Datos!I122 -> Caja de 10 u | N76: =Datos!J122 -> 10 | O76: =Datos!K122 -> 20 | P76: =MAX(1,ROUNDUP(H76*O76/N76,0)) -> 2 | Q76: =IF(P76*N76=0,0,F76/(P76*N76)) -> 7.26035 | R76: Rack de insumos de montaje (carros) | S76: =L76+P76*N76 -> 21.24636 | T76: =Datos!M122 -> 120 | U76: =IF(T76=0,0,S76/T76) -> 0.177053 | V76: =IFERROR(VLOOKUP(R76,Almacenes!$A$19:$I$32,9,FALSE()),"") -> Ruedas en pallet abajo; cajas arriba. | W76: Carros
A77: =Datos!A123 -> P72 | B77: =Datos!C123 -> MP-50/M22 | C77: =Datos!B123 -> Junta tórica del cuello M22 | D77: =Datos!F123 -> u | E77: =Datos!D123 -> Argensold | F77: =Datos!E123 -> 32072.639 | G77: =F77/DIAS_ANIO -> 133.636 | H77: =G77*FAC_MAN -> 144.32688 | I77: =Datos!G123 -> 3 | J77: =Datos!H123 -> 5 | K77: =G77*(I77+J77)/2 -> 534.54398 | L77: =H77*J77-K77 -> 187.09039 | M77: =Datos!I123 -> Bolsa de 1.000 u | N77: =Datos!J123 -> 1000 | O77: =Datos!K123 -> 20 | P77: =MAX(1,ROUNDUP(H77*O77/N77,0)) -> 3 | Q77: =IF(P77*N77=0,0,F77/(P77*N77)) -> 10.69088 | R77: Insumos de montaje (manuales) | S77: =L77+P77*N77 -> 3187.0904 | T77: =Datos!M123 -> 20000 | U77: =IF(T77=0,0,S77/T77) -> 0.15935452 | V77: =IFERROR(VLOOKUP(R77,Almacenes!$A$19:$I$32,9,FALSE()),"") -> Abajo el pallet o la caja en uso (de ahí sale el carro de abastecimiento), arriba la reposición del pedido mensual. | W77: Manuales
A78: =Datos!A124 -> P73 | B78: =Datos!C124 -> MP-50/M30 | C78: =Datos!B124 -> Junta tórica del cuello M30 | D78: =Datos!F124 -> u | E78: =Datos!D124 -> Argensold | F78: =Datos!E124 -> 41548.031 | G78: =F78/DIAS_ANIO -> 173.1168 | H78: =G78*FAC_MAN -> 186.96614 | I78: =Datos!G124 -> 3 | J78: =Datos!H124 -> 5 | K78: =G78*(I78+J78)/2 -> 692.46718 | L78: =H78*J78-K78 -> 242.36351 | M78: =Datos!I124 -> Bolsa de 1.000 u | N78: =Datos!J124 -> 1000 | O78: =Datos!K124 -> 20 | P78: =MAX(1,ROUNDUP(H78*O78/N78,0)) -> 4 | Q78: =IF(P78*N78=0,0,F78/(P78*N78)) -> 10.387008 | R78: Insumos de montaje (manuales) | S78: =L78+P78*N78 -> 4242.3635 | T78: =Datos!M124 -> 20000 | U78: =IF(T78=0,0,S78/T78) -> 0.21211818 | V78: =IFERROR(VLOOKUP(R78,Almacenes!$A$19:$I$32,9,FALSE()),"") -> Abajo el pallet o la caja en uso (de ahí sale el carro de abastecimiento), arriba la reposición del pedido mensual. | W78: Manuales
A79: =Datos!A125 -> P74 | B79: =Datos!C125 -> MP-50/2½ | C79: =Datos!B125 -> Junta tórica del cuello 2½" | D79: =Datos!F125 -> u | E79: =Datos!D125 -> Argensold | F79: =Datos!E125 -> 363.016 | G79: =F79/DIAS_ANIO -> 1.5125667 | H79: =G79*FAC_CAR -> 1.633572 | I79: =Datos!G125 -> 3 | J79: =Datos!H125 -> 5 | K79: =G79*(I79+J79)/2 -> 6.0502667 | L79: =H79*J79-K79 -> 2.1175933 | M79: =Datos!I125 -> Bolsa de 100 u | N79: =Datos!J125 -> 100 | O79: =Datos!K125 -> 60 | P79: =MAX(1,ROUNDUP(H79*O79/N79,0)) -> 1 | Q79: =IF(P79*N79=0,0,F79/(P79*N79)) -> 3.63016 | R79: Rack de insumos de montaje (carros) | S79: =L79+P79*N79 -> 102.11759 | T79: =Datos!M125 -> 20000 | U79: =IF(T79=0,0,S79/T79) -> 0.0051058797 | V79: =IFERROR(VLOOKUP(R79,Almacenes!$A$19:$I$32,9,FALSE()),"") -> Ruedas en pallet abajo; cajas arriba. | W79: Carros
A80: =Datos!A126 -> P75 | B80: =Datos!C126 -> MP-50/OT | C80: =Datos!B126 -> Junta tórica del cuello (recargas, surtido por medida) | D80: =Datos!F126 -> u | E80: =Datos!D126 -> Würth Argentina | F80: =Datos!E126 -> 101887.57 | G80: =F80/DIAS_ANIO -> 424.53153 | H80: =G80*FAC_REC -> 518.36554 | I80: =Datos!G126 -> 3 | J80: =Datos!H126 -> 5 | K80: =G80*(I80+J80)/2 -> 1698.1261 | L80: =H80*J80-K80 -> 893.70156 | M80: =Datos!I126 -> Bolsa de 1.000 u (surtido por medida) | N80: =Datos!J126 -> 1000 | O80: =Datos!K126 -> 20 | P80: =MAX(1,ROUNDUP(H80*O80/N80,0)) -> 11 | Q80: =IF(P80*N80=0,0,F80/(P80*N80)) -> 9.2625061 | R80: Insumos de recargas | S80: =L80+P80*N80 -> 11893.702 | T80: =Datos!M126 -> 20000 | U80: =IF(T80=0,0,S80/T80) -> 0.59468508 | V80: =IFERROR(VLOOKUP(R80,Almacenes!$A$19:$I$32,9,FALSE()),"") -> Tambores de 200 L en el piso sobre pallet antiderrame; bidones en bandeja; cajas en los niveles. | W80: Recargas
A81: =Datos!A127 -> P76 | B81: =Datos!C127 -> MP-52/ABC2.5 | C81: =Datos!B127 -> Soporte de pared ABC 2,5 kg | D81: =Datos!F127 -> u | E81: =Datos!D127 -> Matafuegos Aconcagua (J. C. Paz) | F81: =Datos!E127 -> 7436.458 | G81: =F81/DIAS_ANIO -> 30.985242 | H81: =G81*FAC_MAN -> 33.464061 | I81: =Datos!G127 -> 3 | J81: =Datos!H127 -> 7 | K81: =G81*(I81+J81)/2 -> 154.92621 | L81: =H81*J81-K81 -> 79.322219 | M81: =Datos!I127 -> Caja de 100 u | N81: =Datos!J127 -> 100 | O81: =Datos!K127 -> 20 | P81: =MAX(1,ROUNDUP(H81*O81/N81,0)) -> 7 | Q81: =IF(P81*N81=0,0,F81/(P81*N81)) -> 10.623511 | R81: Insumos de montaje (manuales) | S81: =L81+P81*N81 -> 779.32222 | T81: =Datos!M127 -> 3000 | U81: =IF(T81=0,0,S81/T81) -> 0.25977407 | V81: =IFERROR(VLOOKUP(R81,Almacenes!$A$19:$I$32,9,FALSE()),"") -> Abajo el pallet o la caja en uso (de ahí sale el carro de abastecimiento), arriba la reposición del pedido mensual. | W81: Manuales
A82: =Datos!A128 -> P77 | B82: =Datos!C128 -> MP-52/ABC5 | C82: =Datos!B128 -> Soporte de pared ABC 5 kg | D82: =Datos!F128 -> u | E82: =Datos!D128 -> Matafuegos Aconcagua (J. C. Paz) | F82: =Datos!E128 -> 30814.979 | G82: =F82/DIAS_ANIO -> 128.39575 | H82: =G82*FAC_MAN -> 138.66741 | I82: =Datos!G128 -> 3 | J82: =Datos!H128 -> 7 | K82: =G82*(I82+J82)/2 -> 641.97873 | L82: =H82*J82-K82 -> 328.69311 | M82: =Datos!I128 -> Caja de 100 u | N82: =Datos!J128 -> 100 | O82: =Datos!K128 -> 20 | P82: =MAX(1,ROUNDUP(H82*O82/N82,0)) -> 28 | Q82: =IF(P82*N82=0,0,F82/(P82*N82)) -> 11.00535 | R82: Insumos de montaje (manuales) | S82: =L82+P82*N82 -> 3128.6931 | T82: =Datos!M128 -> 3000 | U82: =IF(T82=0,0,S82/T82) -> 1.0428977 | V82: =IFERROR(VLOOKUP(R82,Almacenes!$A$19:$I$32,9,FALSE()),"") -> Abajo el pallet o la caja en uso (de ahí sale el carro de abastecimiento), arriba la reposición del pedido mensual. | W82: Manuales
A83: =Datos!A129 -> P78 | B83: =Datos!C129 -> MP-52/ABC10 | C83: =Datos!B129 -> Soporte de pared ABC 10 kg | D83: =Datos!F129 -> u | E83: =Datos!D129 -> Matafuegos Aconcagua (J. C. Paz) | F83: =Datos!E129 -> 1844.928 | G83: =F83/DIAS_ANIO -> 7.6872 | H83: =G83*FAC_MAN -> 8.302176 | I83: =Datos!G129 -> 3 | J83: =Datos!H129 -> 7 | K83: =G83*(I83+J83)/2 -> 38.436 | L83: =H83*J83-K83 -> 19.679232 | M83: =Datos!I129 -> Caja de 100 u | N83: =Datos!J129 -> 100 | O83: =Datos!K129 -> 20 | P83: =MAX(1,ROUNDUP(H83*O83/N83,0)) -> 2 | Q83: =IF(P83*N83=0,0,F83/(P83*N83)) -> 9.22464 | R83: Insumos de montaje (manuales) | S83: =L83+P83*N83 -> 219.67923 | T83: =Datos!M129 -> 3000 | U83: =IF(T83=0,0,S83/T83) -> 0.073226411 | V83: =IFERROR(VLOOKUP(R83,Almacenes!$A$19:$I$32,9,FALSE()),"") -> Abajo el pallet o la caja en uso (de ahí sale el carro de abastecimiento), arriba la reposición del pedido mensual. | W83: Manuales
A84: =Datos!A130 -> P79 | B84: =Datos!C130 -> MP-87 | C84: =Datos!B130 -> Soporte vehicular (1 kg) | D84: =Datos!F130 -> u | E84: =Datos!D130 -> Matafuegos Aconcagua (J. C. Paz) | F84: =Datos!E130 -> 32072.639 | G84: =F84/DIAS_ANIO -> 133.636 | H84: =G84*FAC_MAN -> 144.32688 | I84: =Datos!G130 -> 3 | J84: =Datos!H130 -> 7 | K84: =G84*(I84+J84)/2 -> 668.17998 | L84: =H84*J84-K84 -> 342.10815 | M84: =Datos!I130 -> Caja de 100 u | N84: =Datos!J130 -> 100 | O84: =Datos!K130 -> 20 | P84: =MAX(1,ROUNDUP(H84*O84/N84,0)) -> 29 | Q84: =IF(P84*N84=0,0,F84/(P84*N84)) -> 11.059531 | R84: Insumos de montaje (manuales) | S84: =L84+P84*N84 -> 3242.1081 | T84: =Datos!M130 -> 3000 | U84: =IF(T84=0,0,S84/T84) -> 1.0807027 | V84: =IFERROR(VLOOKUP(R84,Almacenes!$A$19:$I$32,9,FALSE()),"") -> Abajo el pallet o la caja en uso (de ahí sale el carro de abastecimiento), arriba la reposición del pedido mensual. | W84: Manuales
A85: =Datos!A131 -> P80 | B85: =Datos!C131 -> MP-86 | C85: =Datos!B131 -> Tornillo y tarugo de fijación | D85: =Datos!F131 -> u | E85: =Datos!D131 -> Würth Argentina | F85: =Datos!E131 -> 80192.73 | G85: =F85/DIAS_ANIO -> 334.13637 | H85: =G85*FAC_MAN -> 360.86728 | I85: =Datos!G131 -> 3 | J85: =Datos!H131 -> 5 | K85: =G85*(I85+J85)/2 -> 1336.5455 | L85: =H85*J85-K85 -> 467.79093 | M85: =Datos!I131 -> Bolsa de 1.000 u | N85: =Datos!J131 -> 1000 | O85: =Datos!K131 -> 20 | P85: =MAX(1,ROUNDUP(H85*O85/N85,0)) -> 8 | Q85: =IF(P85*N85=0,0,F85/(P85*N85)) -> 10.024091 | R85: Insumos de montaje (manuales) | S85: =L85+P85*N85 -> 8467.7909 | T85: =Datos!M131 -> 20000 | U85: =IF(T85=0,0,S85/T85) -> 0.42338955 | V85: =IFERROR(VLOOKUP(R85,Almacenes!$A$19:$I$32,9,FALSE()),"") -> Abajo el pallet o la caja en uso (de ahí sale el carro de abastecimiento), arriba la reposición del pedido mensual. | W85: Manuales
A86: =Datos!A132 -> P81 | B86: =Datos!C132 -> MP-55 | C86: =Datos!B132 -> Conjunto de seguridad de CO₂ (recargas) | D86: =Datos!F132 -> u | E86: =Datos!D132 -> Georgia | F86: =Datos!E132 -> 3121.786 | G86: =F86/DIAS_ANIO -> 13.007442 | H86: =G86*FAC_REC -> 15.88247 | I86: =Datos!G132 -> 4 | J86: =Datos!H132 -> 7 | K86: =G86*(I86+J86)/2 -> 71.540929 | L86: =H86*J86-K86 -> 39.636364 | M86: =Datos!I132 -> Bolsa de 100 u | N86: =Datos!J132 -> 100 | O86: =Datos!K132 -> 20 | P86: =MAX(1,ROUNDUP(H86*O86/N86,0)) -> 4 | Q86: =IF(P86*N86=0,0,F86/(P86*N86)) -> 7.804465 | R86: Insumos de recargas | S86: =L86+P86*N86 -> 439.63636 | T86: =Datos!M132 -> 2000 | U86: =IF(T86=0,0,S86/T86) -> 0.21981818 | V86: =IFERROR(VLOOKUP(R86,Almacenes!$A$19:$I$32,9,FALSE()),"") -> Tambores de 200 L en el piso sobre pallet antiderrame; bidones en bandeja; cajas en los niveles. | W86: Recargas
A87: =Datos!A133 -> P82 | B87: =Datos!C133 -> MP-56/ABC1 | C87: =Datos!B133 -> Etiqueta de características ABC 1 kg | D87: =Datos!F133 -> u | E87: =Datos!D133 -> Rotolan (Lanús) | F87: =Datos!E133 -> 32072.639 | G87: =F87/DIAS_ANIO -> 133.636 | H87: =G87*FAC_MAN -> 144.32688 | I87: =Datos!G133 -> 3 | J87: =Datos!H133 -> 7 | K87: =G87*(I87+J87)/2 -> 668.17998 | L87: =H87*J87-K87 -> 342.10815 | M87: =Datos!I133 -> Rollo de 1.000 u | N87: =Datos!J133 -> 1000 | O87: =Datos!K133 -> 20 | P87: =MAX(1,ROUNDUP(H87*O87/N87,0)) -> 3 | Q87: =IF(P87*N87=0,0,F87/(P87*N87)) -> 10.69088 | R87: Identificación | S87: =L87+P87*N87 -> 3342.1081 | T87: =Datos!M133 -> 20000 | U87: =IF(T87=0,0,S87/T87) -> 0.16710541 | V87: =IFERROR(VLOOKUP(R87,Almacenes!$A$19:$I$32,9,FALSE()),"") -> Un estante por familia; obleas y estampillas (valores) en estante con candado. | W87: Manuales
A88: =Datos!A134 -> P83 | B88: =Datos!C134 -> MP-56/ABC2.5 | C88: =Datos!B134 -> Etiqueta de características ABC 2,5 kg | D88: =Datos!F134 -> u | E88: =Datos!D134 -> Rotolan (Lanús) | F88: =Datos!E134 -> 7436.458 | G88: =F88/DIAS_ANIO -> 30.985242 | H88: =G88*FAC_MAN -> 33.464061 | I88: =Datos!G134 -> 3 | J88: =Datos!H134 -> 7 | K88: =G88*(I88+J88)/2 -> 154.92621 | L88: =H88*J88-K88 -> 79.322219 | M88: =Datos!I134 -> Rollo de 1.000 u | N88: =Datos!J134 -> 1000 | O88: =Datos!K134 -> 20 | P88: =MAX(1,ROUNDUP(H88*O88/N88,0)) -> 1 | Q88: =IF(P88*N88=0,0,F88/(P88*N88)) -> 7.436458 | R88: Identificación | S88: =L88+P88*N88 -> 1079.3222 | T88: =Datos!M134 -> 20000 | U88: =IF(T88=0,0,S88/T88) -> 0.053966111 | V88: =IFERROR(VLOOKUP(R88,Almacenes!$A$19:$I$32,9,FALSE()),"") -> Un estante por familia; obleas y estampillas (valores) en estante con candado. | W88: Manuales
A89: =Datos!A135 -> P84 | B89: =Datos!C135 -> MP-56/ABC5 | C89: =Datos!B135 -> Etiqueta de características ABC 5 kg | D89: =Datos!F135 -> u | E89: =Datos!D135 -> Rotolan (Lanús) | F89: =Datos!E135 -> 30814.979 | G89: =F89/DIAS_ANIO -> 128.39575 | H89: =G89*FAC_MAN -> 138.66741 | I89: =Datos!G135 -> 3 | J89: =Datos!H135 -> 7 | K89: =G89*(I89+J89)/2 -> 641.97873 | L89: =H89*J89-K89 -> 328.69311 | M89: =Datos!I135 -> Rollo de 1.000 u | N89: =Datos!J135 -> 1000 | O89: =Datos!K135 -> 20 | P89: =MAX(1,ROUNDUP(H89*O89/N89,0)) -> 3 | Q89: =IF(P89*N89=0,0,F89/(P89*N89)) -> 10.27166 | R89: Identificación | S89: =L89+P89*N89 -> 3328.6931 | T89: =Datos!M135 -> 20000 | U89: =IF(T89=0,0,S89/T89) -> 0.16643466 | V89: =IFERROR(VLOOKUP(R89,Almacenes!$A$19:$I$32,9,FALSE()),"") -> Un estante por familia; obleas y estampillas (valores) en estante con candado. | W89: Manuales
A90: =Datos!A136 -> P85 | B90: =Datos!C136 -> MP-56/ABC10 | C90: =Datos!B136 -> Etiqueta de características ABC 10 kg | D90: =Datos!F136 -> u | E90: =Datos!D136 -> RotulArte (CABA) | F90: =Datos!E136 -> 1844.928 | G90: =F90/DIAS_ANIO -> 7.6872 | H90: =G90*FAC_MAN -> 8.302176 | I90: =Datos!G136 -> 1 | J90: =Datos!H136 -> 2 | K90: =G90*(I90+J90)/2 -> 11.5308 | L90: =H90*J90-K90 -> 5.073552 | M90: =Datos!I136 -> Rollo de 1.000 u | N90: =Datos!J136 -> 1000 | O90: =Datos!K136 -> 60 | P90: =MAX(1,ROUNDUP(H90*O90/N90,0)) -> 1 | Q90: =IF(P90*N90=0,0,F90/(P90*N90)) -> 1.844928 | R90: Identificación | S90: =L90+P90*N90 -> 1005.0736 | T90: =Datos!M136 -> 20000 | U90: =IF(T90=0,0,S90/T90) -> 0.050253678 | V90: =IFERROR(VLOOKUP(R90,Almacenes!$A$19:$I$32,9,FALSE()),"") -> Un estante por familia; obleas y estampillas (valores) en estante con candado. | W90: Manuales
A91: =Datos!A137 -> P86 | B91: =Datos!C137 -> MP-56/ABC25 | C91: =Datos!B137 -> Etiqueta de características ABC 25 kg | D91: =Datos!F137 -> u | E91: =Datos!D137 -> RotulArte (CABA) | F91: =Datos!E137 -> 453.671 | G91: =F91/DIAS_ANIO -> 1.8902958 | H91: =G91*FAC_CAR -> 2.0415195 | I91: =Datos!G137 -> 1 | J91: =Datos!H137 -> 2 | K91: =G91*(I91+J91)/2 -> 2.8354438 | L91: =H91*J91-K91 -> 1.2475952 | M91: =Datos!I137 -> Rollo de 500 u | N91: =Datos!J137 -> 500 | O91: =Datos!K137 -> 60 | P91: =MAX(1,ROUNDUP(H91*O91/N91,0)) -> 1 | Q91: =IF(P91*N91=0,0,F91/(P91*N91)) -> 0.907342 | R91: Identificación | S91: =L91+P91*N91 -> 501.2476 | T91: =Datos!M137 -> 20000 | U91: =IF(T91=0,0,S91/T91) -> 0.02506238 | V91: =IFERROR(VLOOKUP(R91,Almacenes!$A$19:$I$32,9,FALSE()),"") -> Un estante por familia; obleas y estampillas (valores) en estante con candado. | W91: Carros
A92: =Datos!A138 -> P87 | B92: =Datos!C138 -> MP-56/ABC50 | C92: =Datos!B138 -> Etiqueta de características ABC 50 kg | D92: =Datos!F138 -> u | E92: =Datos!D138 -> RotulArte (CABA) | F92: =Datos!E138 -> 997.995 | G92: =F92/DIAS_ANIO -> 4.1583125 | H92: =G92*FAC_CAR -> 4.4909775 | I92: =Datos!G138 -> 1 | J92: =Datos!H138 -> 2 | K92: =G92*(I92+J92)/2 -> 6.2374687 | L92: =H92*J92-K92 -> 2.7444862 | M92: =Datos!I138 -> Rollo de 1.000 u | N92: =Datos!J138 -> 1000 | O92: =Datos!K138 -> 60 | P92: =MAX(1,ROUNDUP(H92*O92/N92,0)) -> 1 | Q92: =IF(P92*N92=0,0,F92/(P92*N92)) -> 0.997995 | R92: Identificación | S92: =L92+P92*N92 -> 1002.7445 | T92: =Datos!M138 -> 20000 | U92: =IF(T92=0,0,S92/T92) -> 0.050137224 | V92: =IFERROR(VLOOKUP(R92,Almacenes!$A$19:$I$32,9,FALSE()),"") -> Un estante por familia; obleas y estampillas (valores) en estante con candado. | W92: Carros
A93: =Datos!A139 -> P88 | B93: =Datos!C139 -> MP-56/ABC70 | C93: =Datos!B139 -> Etiqueta de características ABC 70 kg | D93: =Datos!F139 -> u | E93: =Datos!D139 -> RotulArte (CABA) | F93: =Datos!E139 -> 217.81 | G93: =F93/DIAS_ANIO -> 0.90754167 | H93: =G93*FAC_CAR -> 0.980145 | I93: =Datos!G139 -> 1 | J93: =Datos!H139 -> 2 | K93: =G93*(I93+J93)/2 -> 1.3613125 | L93: =H93*J93-K93 -> 0.5989775 | M93: =Datos!I139 -> Rollo de 250 u | N93: =Datos!J139 -> 250 | O93: =Datos!K139 -> 60 | P93: =MAX(1,ROUNDUP(H93*O93/N93,0)) -> 1 | Q93: =IF(P93*N93=0,0,F93/(P93*N93)) -> 0.87124 | R93: Identificación | S93: =L93+P93*N93 -> 250.59898 | T93: =Datos!M139 -> 20000 | U93: =IF(T93=0,0,S93/T93) -> 0.012529949 | V93: =IFERROR(VLOOKUP(R93,Almacenes!$A$19:$I$32,9,FALSE()),"") -> Un estante por familia; obleas y estampillas (valores) en estante con candado. | W93: Carros
A94: =Datos!A140 -> P89 | B94: =Datos!C140 -> MP-56/ABC100 | C94: =Datos!B140 -> Etiqueta de características ABC 100 kg | D94: =Datos!F140 -> u | E94: =Datos!D140 -> RotulArte (CABA) | F94: =Datos!E140 -> 145.207 | G94: =F94/DIAS_ANIO -> 0.60502917 | H94: =G94*FAC_CAR -> 0.6534315 | I94: =Datos!G140 -> 1 | J94: =Datos!H140 -> 2 | K94: =G94*(I94+J94)/2 -> 0.90754375 | L94: =H94*J94-K94 -> 0.39931925 | M94: =Datos!I140 -> Rollo de 250 u | N94: =Datos!J140 -> 250 | O94: =Datos!K140 -> 60 | P94: =MAX(1,ROUNDUP(H94*O94/N94,0)) -> 1 | Q94: =IF(P94*N94=0,0,F94/(P94*N94)) -> 0.580828 | R94: Identificación | S94: =L94+P94*N94 -> 250.39932 | T94: =Datos!M140 -> 20000 | U94: =IF(T94=0,0,S94/T94) -> 0.012519966 | V94: =IFERROR(VLOOKUP(R94,Almacenes!$A$19:$I$32,9,FALSE()),"") -> Un estante por familia; obleas y estampillas (valores) en estante con candado. | W94: Carros
A95: =Datos!A141 -> P90 | B95: =Datos!C141 -> MP-78 | C95: =Datos!B141 -> Oblea de fabricación (PBA) | D95: =Datos!F141 -> u | E95: =Datos!D141 -> DPS (PBA) | F95: =Datos!E141 -> 56507.618 | G95: =F95/DIAS_ANIO -> 235.44841 | H95: =G95*FAC_MAN -> 254.28428 | I95: =Datos!G141 -> 1 | J95: =Datos!H141 -> 1 | K95: =G95*(I95+J95)/2 -> 235.44841 | L95: =H95*J95-K95 -> 18.835873 | M95: =Datos!I141 -> Paquete de 500 u | N95: =Datos!J141 -> 500 | O95: =Datos!K141 -> 20 | P95: =MAX(1,ROUNDUP(H95*O95/N95,0)) -> 11 | Q95: =IF(P95*N95=0,0,F95/(P95*N95)) -> 10.274112 | R95: Identificación | S95: =L95+P95*N95 -> 5518.8359 | T95: =Datos!M141 -> 10000 | U95: =IF(T95=0,0,S95/T95) -> 0.55188359 | V95: =IFERROR(VLOOKUP(R95,Almacenes!$A$19:$I$32,9,FALSE()),"") -> Un estante por familia; obleas y estampillas (valores) en estante con candado. | W95: Manuales
A96: =Datos!A142 -> P91 | B96: =Datos!C142 -> MP-79 | C96: =Datos!B142 -> Estampilla IRAM de conformidad | D96: =Datos!F142 -> u | E96: =Datos!D142 -> IRAM | F96: =Datos!E142 -> 73983.687 | G96: =F96/DIAS_ANIO -> 308.26536 | H96: =G96*FAC_MAN -> 332.92659 | I96: =Datos!G142 -> 21 | J96: =Datos!H142 -> 21 | K96: =G96*(I96+J96)/2 -> 6473.5726 | L96: =H96*J96-K96 -> 517.88581 | M96: =Datos!I142 -> Paquete de 500 u | N96: =Datos!J142 -> 500 | O96: =Datos!K142 -> 20 | P96: =MAX(1,ROUNDUP(H96*O96/N96,0)) -> 14 | Q96: =IF(P96*N96=0,0,F96/(P96*N96)) -> 10.569098 | R96: Identificación | S96: =L96+P96*N96 -> 7517.8858 | T96: =Datos!M142 -> 10000 | U96: =IF(T96=0,0,S96/T96) -> 0.75178858 | V96: =IFERROR(VLOOKUP(R96,Almacenes!$A$19:$I$32,9,FALSE()),"") -> Un estante por familia; obleas y estampillas (valores) en estante con candado. | W96: Manuales
A97: =Datos!A143 -> P92 | B97: =Datos!C143 -> MP-77 | C97: =Datos!B143 -> Tarjeta de identificación AGC (CABA) | D97: =Datos!F143 -> u | E97: =Datos!D143 -> AGC (CABA) | F97: =Datos!E143 -> 36556.377 | G97: =F97/DIAS_ANIO -> 152.31824 | H97: =G97*FAC_MAN -> 164.5037 | I97: =Datos!G143 -> 1 | J97: =Datos!H143 -> 1 | K97: =G97*(I97+J97)/2 -> 152.31824 | L97: =H97*J97-K97 -> 12.185459 | M97: =Datos!I143 -> Paquete de 500 u | N97: =Datos!J143 -> 500 | O97: =Datos!K143 -> 20 | P97: =MAX(1,ROUNDUP(H97*O97/N97,0)) -> 7 | Q97: =IF(P97*N97=0,0,F97/(P97*N97)) -> 10.444679 | R97: Identificación | S97: =L97+P97*N97 -> 3512.1855 | T97: =Datos!M143 -> 10000 | U97: =IF(T97=0,0,S97/T97) -> 0.35121855 | V97: =IFERROR(VLOOKUP(R97,Almacenes!$A$19:$I$32,9,FALSE()),"") -> Un estante por familia; obleas y estampillas (valores) en estante con candado. | W97: Manuales
A98: =Datos!A144 -> P93 | B98: =Datos!C144 -> MP-80 | C98: =Datos!B144 -> Etiqueta de n° de serie GS1 | D98: =Datos!F144 -> u | E98: =Datos!D144 -> Rotolan (Lanús) | F98: =Datos!E144 -> 73983.687 | G98: =F98/DIAS_ANIO -> 308.26536 | H98: =G98*FAC_MAN -> 332.92659 | I98: =Datos!G144 -> 3 | J98: =Datos!H144 -> 7 | K98: =G98*(I98+J98)/2 -> 1541.3268 | L98: =H98*J98-K98 -> 789.15933 | M98: =Datos!I144 -> Rollo de 1.000 u | N98: =Datos!J144 -> 1000 | O98: =Datos!K144 -> 20 | P98: =MAX(1,ROUNDUP(H98*O98/N98,0)) -> 7 | Q98: =IF(P98*N98=0,0,F98/(P98*N98)) -> 10.569098 | R98: Identificación | S98: =L98+P98*N98 -> 7789.1593 | T98: =Datos!M144 -> 20000 | U98: =IF(T98=0,0,S98/T98) -> 0.38945797 | V98: =IFERROR(VLOOKUP(R98,Almacenes!$A$19:$I$32,9,FALSE()),"") -> Un estante por familia; obleas y estampillas (valores) en estante con candado. | W98: Manuales
A99: =Datos!A145 -> P94 | B99: =Datos!C145 -> MP-81 | C99: =Datos!B145 -> Faja de garantía válvula-cuello | D99: =Datos!F145 -> u | E99: =Datos!D145 -> Rotolan (Lanús) | F99: =Datos!E145 -> 73983.687 | G99: =F99/DIAS_ANIO -> 308.26536 | H99: =G99*FAC_MAN -> 332.92659 | I99: =Datos!G145 -> 3 | J99: =Datos!H145 -> 7 | K99: =G99*(I99+J99)/2 -> 1541.3268 | L99: =H99*J99-K99 -> 789.15933 | M99: =Datos!I145 -> Rollo de 1.000 u | N99: =Datos!J145 -> 1000 | O99: =Datos!K145 -> 20 | P99: =MAX(1,ROUNDUP(H99*O99/N99,0)) -> 7 | Q99: =IF(P99*N99=0,0,F99/(P99*N99)) -> 10.569098 | R99: Identificación | S99: =L99+P99*N99 -> 7789.1593 | T99: =Datos!M145 -> 20000 | U99: =IF(T99=0,0,S99/T99) -> 0.38945797 | V99: =IFERROR(VLOOKUP(R99,Almacenes!$A$19:$I$32,9,FALSE()),"") -> Un estante por familia; obleas y estampillas (valores) en estante con candado. | W99: Manuales
A100: =Datos!A146 -> P95 | B100: =Datos!C146 -> MP-51 | C100: =Datos!B146 -> Precinto de fábrica | D100: =Datos!F146 -> u | E100: =Datos!D146 -> SonFuertes | F100: =Datos!E146 -> 73983.687 | G100: =F100/DIAS_ANIO -> 308.26536 | H100: =G100*FAC_MAN -> 332.92659 | I100: =Datos!G146 -> 3 | J100: =Datos!H146 -> 5 | K100: =G100*(I100+J100)/2 -> 1233.0614 | L100: =H100*J100-K100 -> 431.57151 | M100: =Datos!I146 -> Bolsa de 1.000 u | N100: =Datos!J146 -> 1000 | O100: =Datos!K146 -> 20 | P100: =MAX(1,ROUNDUP(H100*O100/N100,0)) -> 7 | Q100: =IF(P100*N100=0,0,F100/(P100*N100)) -> 10.569098 | R100: Identificación | S100: =L100+P100*N100 -> 7431.5715 | T100: =Datos!M146 -> 20000 | U100: =IF(T100=0,0,S100/T100) -> 0.37157858 | V100: =IFERROR(VLOOKUP(R100,Almacenes!$A$19:$I$32,9,FALSE()),"") -> Un estante por familia; obleas y estampillas (valores) en estante con candado. | W100: Manuales
A101: =Datos!A147 -> P96 | B101: =Datos!C147 -> MP-88 | C101: =Datos!B147 -> Etiqueta del cilindro suelto | D101: =Datos!F147 -> u | E101: =Datos!D147 -> Rotolan (Lanús) | F101: =Datos!E147 -> 213586.2 | G101: =F101/DIAS_ANIO -> 889.9425 | H101: =G101*FAC_MAN -> 961.1379 | I101: =Datos!G147 -> 3 | J101: =Datos!H147 -> 7 | K101: =G101*(I101+J101)/2 -> 4449.7125 | L101: =H101*J101-K101 -> 2278.2528 | M101: =Datos!I147 -> Rollo de 1.000 u | N101: =Datos!J147 -> 1000 | O101: =Datos!K147 -> 20 | P101: =MAX(1,ROUNDUP(H101*O101/N101,0)) -> 20 | Q101: =IF(P101*N101=0,0,F101/(P101*N101)) -> 10.67931 | R101: Identificación | S101: =L101+P101*N101 -> 22278.253 | T101: =Datos!M147 -> 20000 | U101: =IF(T101=0,0,S101/T101) -> 1.1139126 | V101: =IFERROR(VLOOKUP(R101,Almacenes!$A$19:$I$32,9,FALSE()),"") -> Un estante por familia; obleas y estampillas (valores) en estante con candado. | W101: Manuales
...

Sheet Almacenes
A1: ALMACENES DE MP — qué estantería se eligió para cada uno y cómo se dispone cada material
A2: Primero se comparan los tipos de estantería industrial; después, para cada almacén, el tipo elegido, los lugares que ocupa el stock máximo de sus MP (Stock_MP) y los m².
A3: ▶ Sección 2: columnas E (lugares), G (m²) e I (cómo se dispone).
A5: 1) TIPOS DE ESTANTERÍA INDUSTRIAL
A6: Tipo | B6: Cómo es | C6: Acceso y rotación | D6: Cuándo conviene | E6: m² por pallet (con pasillo) | I6: Se usa en FLAMA para
A7: Rack selectivo (como la foto) | B7: Bastidores y largueros; cada pallet en su posición | C7: Acceso directo a todos; FIFO por código | D7: Muchos códigos con pocos pallets cada uno | E7: 1.23 | I7: Embalaje, montaje, recargas, soldadura, casquetes, insumos de carros y flejes
A8: Drive-in / compacto | B8: Calles dentro del rack; pallets uno detrás de otro | C8: Último que entra, primero que sale | D8: Muchos pallets de un mismo código (> 20) | E8: 0.7 | I8: No: ningún código pasa de 14 pallets y las cajas cambian todas las semanas
A9: Dinámico (por gravedad) | B9: Rodillos inclinados; carga atrás, descarga adelante | C9: FIFO perfecto | D9: Alta rotación de pocos códigos | E9: 0.8 | I9: No: caro para el volumen de FLAMA
A10: Push-back | B10: Carros que se empujan | C10: Último que entra, primero que sale | D10: 2 a 4 pallets por código, poco espacio | E10: 0.9 | I10: No: pierde el FIFO
A11: Cantilever | B11: Columnas con brazos, sin parante adelante | C11: Cargas largas | D11: Barras, caños y perfiles | E11: 2 | I11: Caños y barras de carros
A12: Estantería liviana / gavetas | B12: Estantes metálicos de 80 a 150 kg | C12: A mano | D12: Cajas chicas, rollos de etiquetas | E12: 0.5 | I12: Identificación y estantes de los puestos
A13: Apilado en bloque (piso) | B13: Bultos uno sobre otro, sin estructura | C13: Se toma el de arriba | D13: Bultos planos y pesados que se apilan solos | I13: Paquetes de chapa (hasta lo que dejan el autoelevador y el piso) y big bags
A14: m² por pallet orientativos (pallet 1.200 × 1.000, 3 alturas, calle de autoelevador contrapesado). El selectivo usa más piso por pallet que el drive-in, pero FLAMA tiene muchos códigos y pocos pallets de cada uno: con drive-in quedarían calles medio vacías.
A16: 2) CADA ALMACÉN: ESTANTERÍA ELEGIDA, LUGARES, m² Y CÓMO SE DISPONE
A18: Almacén | B18: Qué guarda | C18: Estantería elegida | D18: Por qué | E18: Lugares | F18: m² por lugar | G18: m² | H18: Antes (v10, m²) | I18: Cómo se dispone
A19: Chapa (pilas en el piso) | B19: Paquetes de hojas de manuales y de carros | C19: Apilado en bloque | D19: El paquete va entero a la mesa elevadora; no entra en un rack de 2,30 m | E19: =Chapa_fleje!K24 -> 7 | G19: =Chapa_fleje!E29 -> 92.0636 | H19: =Datos!D37+Datos!D35 -> 101.16 | I19: Paquete sobre sus 3 tacos, una pila por formato hasta el alto que permiten el autoelevador, el piso y la estabilidad (Chapa_fleje sección 2). Se toma el de arriba; al recibir, el remanente pasa arriba (FIFO por colada). Pilas demarcadas con su código, 2 filas enfrentadas sobre la calle.
A20: Flejes (rack + volteador) | B20: Rollos de fleje de las 8 matrices | C20: Rack selectivo 2.000 kg/nivel | D20: Los rollos acostados no se deforman y se apilan; el rack usa la altura | E20: =Chapa_fleje!G69 -> 16 | G20: =Chapa_fleje!G72 -> 25.56 | H20: (en la fila de arriba) | I20: Rollos ojo al cielo, un código por pallet, con listones entre rollos. Los de más de 1.000 kg (5 kg) en el piso del rack; el resto arriba. La pinza giratoria arma el pallet en la zona de armado y el autoelevador con uñas lo sube al rack; a la línea, al revés: la pinza deja el rollo parado en el desbobinador.
A21: Cantilever de caños y barras | B21: Caños y barras de carros | C21: Cantilever (fabricación propia) | D21: Cargas largas de 4 y 6 m | E21: =ROUNDUP(SUMIFS(Stock_MP!$U:$U,Stock_MP!$R:$R,A21),0) -> 2 | F21: 2 | G21: =E21*F21 -> 4 | H21: =Datos!D36 -> 4 | I21: Un atado por brazo y una medida por nivel; las barras de 6 m con los brazos a 1,5 m.
A22: Depósito de polvo químico | B22: Big bags de polvo ABC, bolsas de BC y clase D | C22: Apilado en bloque | D22: El big bag se apila de a 2 y no necesita rack | E22: =ROUNDUP(SUMIFS(Stock_MP!$U:$U,Stock_MP!$R:$R,A22),0) -> 8 | F22: 1 | G22: =E22*F22 -> 8 | H22: =Datos!D38 -> 8 | I22: Big bags de 1 × 1 m en el piso, de a 2, por fecha de llegada; bolsas de 25 kg y cajas de pintura sobre pallet plástico. Depósito seco.
A23: Embalaje | B23: Cajas plegadas, pallets, tapones | C23: Rack selectivo 500 kg/nivel | D23: Pallets livianos (< 300 kg), muchos códigos | E23: =ROUNDUP(SUMIFS(Stock_MP!$U:$U,Stock_MP!$R:$R,A23),0) -> 27 | F23: 1.23 | G23: =E23*F23 -> 33.21 | H23: =Datos!D39 -> 33.21 | I23: Abajo el pallet que se está usando, arriba la entrega de la semana. La pila de pallets de madera va en el piso.
A24: Identificación | B24: Etiquetas, obleas, estampillas, impresos | C24: Estantería liviana | D24: Cajas y rollos chicos que se toman a mano | E24: =ROUNDUP(SUMIFS(Stock_MP!$U:$U,Stock_MP!$R:$R,A24),0) -> 7 | F24: 0.5 | G24: =E24*F24 -> 3.5 | H24: =Datos!D40 -> 3.5 | I24: Un estante por familia; obleas y estampillas (valores) en estante con candado.
A25: Insumos de montaje (manuales) | B25: Válvulas, manómetros, toberas, juntas, asientos | C25: Rack selectivo 1.000 kg/nivel | D25: Pallets de válvulas de hasta ≈ 600 kg | E25: =ROUNDUP(SUMIFS(Stock_MP!$U:$U,Stock_MP!$R:$R,A25),0) -> 19 | F25: 1.23 | G25: =E25*F25 -> 23.37 | H25: =Datos!D41 -> 23.37 | I25: Abajo el pallet o la caja en uso (de ahí sale el carro de abastecimiento), arriba la reposición del pedido mensual.
A26: Insumos de recargas | B26: Tambores de acetato, AFFF, CO₂, HCFC, juntas | C26: Rack selectivo 1.000 kg/nivel | D26: Mezcla de tambores y cajas | E26: =ROUNDUP(SUMIFS(Stock_MP!$U:$U,Stock_MP!$R:$R,A26),0) -> 7 | F26: 1.23 | G26: =E26*F26 -> 8.61 | H26: =Datos!D42 -> 8.61 | I26: Tambores de 200 L en el piso sobre pallet antiderrame; bidones en bandeja; cajas en los niveles.
A27: Insumos de soldadura y superficie | B27: Alambre, granalla, pintura, discos | C27: Rack selectivo 1.000 kg/nivel | D27: Pallets de alambre (900 kg) y granalla (1.000 kg) | E27: =ROUNDUP(SUMIFS(Stock_MP!$U:$U,Stock_MP!$R:$R,A27),0) -> 5 | F27: 1.23 | G27: =E27*F27 -> 6.15 | H27: =Datos!D43 -> 6.15 | I27: Granalla en el piso del rack; alambre y pintura arriba; insumos chicos en caja.
A28: Jaula de gases | B28: Baterías MAG, pack de N₂, cilindros | C28: Jaula exterior ventilada | D28: Norma de gases a presión: afuera y ventilado | E28: =ROUNDUP(SUMIFS(Stock_MP!$U:$U,Stock_MP!$R:$R,A28),0) -> 7 | F28: 1 | G28: =E28*F28 -> 7 | H28: =Datos!D44 -> 7 | I28: Baterías y pack con manifold conectados a la cañería; cilindros sueltos encadenados en gabinete.
A29: Rack de casquetes y cuplas (carros) | B29: Casquetes (contenedores), cuplas | C29: Rack selectivo 2.000 kg/nivel | D29: Contenedores de casquetes de ≈ 1 t | E29: =ROUNDUP(SUMIFS(Stock_MP!$U:$U,Stock_MP!$R:$R,A29),0) -> 6 | F29: 0.73 | G29: =E29*F29 -> 4.38 | H29: =Datos!D45 -> 6.57 | I29: Un contenedor por medida de casquete (cúpulas y fondos en columnas separadas); el que está en uso en el piso; cajas de cuplas arriba.
A30: Rack de insumos de montaje (carros) | B30: Ruedas, válvulas, mangueras, ejes | C30: Rack selectivo 500 kg/nivel | D30: Pallets de ruedas (≈ 300 kg) y cajas | E30: =ROUNDUP(SUMIFS(Stock_MP!$U:$U,Stock_MP!$R:$R,A30),0) -> 8 | F30: 0.74 | G30: =E30*F30 -> 5.92 | H30: =Datos!D46 -> 5.92 | I30: Ruedas en pallet abajo; cajas arriba.
A31: Almacén de producto terminado | B31: Matafuegos de reventa | C31: — (va en el almacén de PT) | D31: No es MP | E31: — | I31: En el almacén de producto terminado (Balanceo2035, Pulmones sección 6).
A33: Total almacén de MP | E33: =SUM(E19:E30) -> 119 | G33: =SUM(G19:G30) -> 221.7636 | H33: =SUM(H19:H30) -> 207.49
A34: Antes (v10): chapa y fleje iban juntos (94,5 m², con las hojas por lugar del MRP viejo) más la calle de chapa de carros (6,7 m²). Los lugares de chapa son pilas y los de flejes posiciones de rack.

Sheet Pedidos
A1: UN PEDIDO POR PROVEEDOR — cada cuánto se pide
A2: Cada proveedor recibe un solo pedido con todo lo suyo. Los días entre pedidos de chapa y fleje se editan acá (amarillo); los del resto están en Stock_MP, columna O.
A3: ▶ Columna C: cada cuántos días hábiles se le pide a cada proveedor.
A6: Proveedor | B6: Materiales | C6: Cada (días hábiles) | D6: Pedidos por año | E6: Qué se le pide
A7: Hierros Parrotta | B7: =COUNTIF(Stock_MP!$E$6:$E$130,A7) -> 1 | C7: 20 | D7: =DIAS_ANIO/C7 -> 12 | E7: MP-01
A8: Pradecon | B8: =COUNTIF(Stock_MP!$E$6:$E$130,A8) -> 7 | C8: 20 | D8: =DIAS_ANIO/C8 -> 12 | E8: MP-02, MP-03, MP-04, MP-05, MP-13, MP-11, MP-12
A9: Pacheco Chapas | B9: =COUNTIF(Stock_MP!$E$6:$E$130,A9) -> 6 | C9: 10 | D9: =DIAS_ANIO/C9 -> 24 | E9: MP-06, MP-14, MP-07, MP-08, MP-09, MP-10
A10: NOVA Ruedas | B10: =COUNTIF(Stock_MP!$E$6:$E$130,A10) -> 3 | C10: =_xlfn.MINIFS(Stock_MP!$O$6:$O$130,Stock_MP!$E$6:$E$130,A10) -> 20 | D10: =DIAS_ANIO/C10 -> 12 | E10: MP-15, MP-16, MP-17
A11: Eli-Met | B11: =COUNTIF(Stock_MP!$E$6:$E$130,A11) -> 4 | C11: =_xlfn.MINIFS(Stock_MP!$O$6:$O$130,Stock_MP!$E$6:$E$130,A11) -> 20 | D11: =DIAS_ANIO/C11 -> 12 | E11: MP-18, MP-19, MP-20, MP-21
A12: Centrosider | B12: =COUNTIF(Stock_MP!$E$6:$E$130,A12) -> 2 | C12: =_xlfn.MINIFS(Stock_MP!$O$6:$O$130,Stock_MP!$E$6:$E$130,A12) -> 20 | D12: =DIAS_ANIO/C12 -> 12 | E12: MP-66, MP-67
A13: Vladimirsky | B13: =COUNTIF(Stock_MP!$E$6:$E$130,A13) -> 2 | C13: =_xlfn.MINIFS(Stock_MP!$O$6:$O$130,Stock_MP!$E$6:$E$130,A13) -> 20 | D13: =DIAS_ANIO/C13 -> 12 | E13: MP-68, MP-69
A14: Würth Argentina | B14: =COUNTIF(Stock_MP!$E$6:$E$130,A14) -> 8 | C14: =_xlfn.MINIFS(Stock_MP!$O$6:$O$130,Stock_MP!$E$6:$E$130,A14) -> 20 | D14: =DIAS_ANIO/C14 -> 12 | E14: MP-70, MP-71, MP-29, MP-92, MP-93, MP-95, MP-50/OT, MP-86
A15: Ruedar | B15: =COUNTIF(Stock_MP!$E$6:$E$130,A15) -> 2 | C15: =_xlfn.MINIFS(Stock_MP!$O$6:$O$130,Stock_MP!$E$6:$E$130,A15) -> 20 | D15: =DIAS_ANIO/C15 -> 12 | E15: MP-54/300, MP-54/350
A16: Escanort | B16: =COUNTIF(Stock_MP!$E$6:$E$130,A16) -> 1 | C16: =_xlfn.MINIFS(Stock_MP!$O$6:$O$130,Stock_MP!$E$6:$E$130,A16) -> 20 | D16: =DIAS_ANIO/C16 -> 12 | E16: MP-54/400
A17: Soldanet | B17: =COUNTIF(Stock_MP!$E$6:$E$130,A17) -> 2 | C17: =_xlfn.MINIFS(Stock_MP!$O$6:$O$130,Stock_MP!$E$6:$E$130,A17) -> 20 | D17: =DIAS_ANIO/C17 -> 12 | E17: MP-23, MP-24
A18: Air Liquide | B18: =COUNTIF(Stock_MP!$E$6:$E$130,A18) -> 4 | C18: =_xlfn.MINIFS(Stock_MP!$O$6:$O$130,Stock_MP!$E$6:$E$130,A18) -> 5 | D18: =DIAS_ANIO/C18 -> 48 | E18: MP-25, MP-26, MP-34, MP-37
A19: Espacio Industria | B19: =COUNTIF(Stock_MP!$E$6:$E$130,A19) -> 2 | C19: =_xlfn.MINIFS(Stock_MP!$O$6:$O$130,Stock_MP!$E$6:$E$130,A19) -> 60 | D19: =DIAS_ANIO/C19 -> 4 | E19: MP-27, MP-94
A20: CyM Materiales | B20: =COUNTIF(Stock_MP!$E$6:$E$130,A20) -> 1 | C20: =_xlfn.MINIFS(Stock_MP!$O$6:$O$130,Stock_MP!$E$6:$E$130,A20) -> 20 | D20: =DIAS_ANIO/C20 -> 12 | E20: MP-28
A21: Sinteplast | B21: =COUNTIF(Stock_MP!$E$6:$E$130,A21) -> 2 | C21: =_xlfn.MINIFS(Stock_MP!$O$6:$O$130,Stock_MP!$E$6:$E$130,A21) -> 20 | D21: =DIAS_ANIO/C21 -> 12 | E21: MP-31, MP-65
... A44: Fabricante nacional | B44: =COUNTIF(Stock_MP!$E$6:$E$130,A44) -> 1 | C44: =_xlfn.MINIFS(Stock_MP!$O$6:$O$130,Stock_MP!$E$6:$E$130,A44) -> 20 | D44: =DIAS_ANIO/C44 -> 12 | E44: RV-CLASED_9l
A45: Total de pedidos por año | D45: =SUM(D7:D44) -> 596
A47: Pacheco Chapas va cada 10 días porque sus rollos del 5 kg pesan más de 1 t: pedirlos una vez por mes subiría mucho el stock. Si un proveedor tiene materiales con distinta frecuencia, el pedido va con la más corta y en cada uno se pide solo lo que falta.

Sheet Equipos
A1: EQUIPOS PARA GUARDAR LA MP — cuántos hacen falta y cuánto cuestan
A2: Cantidades con fórmula desde Almacenes y Chapa_fleje; precios de Datos sección 6 (con IVA, 21/10/2026). Los flejes ya no van en cunas.
A3: ▶ Columna G: subtotal por equipo y total al pie.
A6: Zona | B6: Almacén | C6: Equipo | D6: Id | E6: Cantidad | F6: Precio unitario | G6: Subtotal | H6: Cómo se calculó
A7: Almacén | B7: Flejes (rack + volteador) | C7: Rack 2.000 kg/nivel — módulo inicial | D7: R1I | E7: =IF(Chapa_fleje!G68>0,1,0) -> 1 | F7: =IFERROR(VLOOKUP(D7,PRECIOS,3,FALSE()),0) -> 856540 | G7: =E7*F7 -> 856540 | H7: 1 por fila de rack
A8: Almacén | B8: Flejes (rack + volteador) | C8: Rack 2.000 kg/nivel — módulo adicional | D8: R1A | E8: =MAX(0,Chapa_fleje!G68-1) -> 1 | F8: =IFERROR(VLOOKUP(D8,PRECIOS,3,FALSE()),0) -> 655590 | G8: =E8*F8 -> 655590 | H8: Módulos de Chapa_fleje G68
A9: Almacén | B9: Flejes (rack + volteador) | C9: Apilador con pinza giratoria («volteador») | D9: V1 | E9: 1 | F9: =IFERROR(VLOOKUP(D9,PRECIOS,3,FALSE()),0) -> 0 | G9: =E9*F9 -> 0 | H9: =Chapa_fleje!L52&" — "&Chapa_fleje!L53 -> Tymbia M103070075 en apilador eléctrico de 2,5 t — 1,300 kg · Ø hasta 1,100 mm
A10: Almacén | B10: Flejes (rack + volteador) | C10: Pallet plástico para los rollos de hasta 1.000 kg | D10: PL | E10: =Chapa_fleje!K65-Chapa_fleje!G67 -> 11 | F10: =IFERROR(VLOOKUP(D10,PRECIOS,3,FALSE()),0) -> 117999 | G10: =E10*F10 -> 1297989 | H10: Los rollos del 5 kg (más de 1.000 kg) van sobre pallet de madera de 4 entradas del pedido de IndusPallets (MP-60)
A11: Almacén | B11: Rack de casquetes y cuplas (carros) | C11: Rack 2.000 kg/nivel — inicial | D11: R1I | E11: 1 | F11: =IFERROR(VLOOKUP(D11,PRECIOS,3,FALSE()),0) -> 856540 | G11: =E11*F11 -> 856540
A12: Almacén | B12: Rack de casquetes y cuplas (carros) | C12: Rack 2.000 kg/nivel — adicional | D12: R1A | E12: =MAX(0,ROUNDUP(Almacenes!E29/LUG_MOD,0)-1) -> 0 | F12: =IFERROR(VLOOKUP(D12,PRECIOS,3,FALSE()),0) -> 655590 | G12: =E12*F12 -> 0 | H12: Lugares ÷ 6
A13: Almacén | B13: Embalaje | C13: Rack 500 kg/nivel — inicial | D13: R3I | E13: 1 | F13: =IFERROR(VLOOKUP(D13,PRECIOS,3,FALSE()),0) -> 606940 | G13: =E13*F13 -> 606940
A14: Almacén | B14: Embalaje | C14: Rack 500 kg/nivel — adicional | D14: R3A | E14: =MAX(0,ROUNDUP(Almacenes!E23/LUG_MOD,0)-1) -> 4 | F14: =IFERROR(VLOOKUP(D14,PRECIOS,3,FALSE()),0) -> 405990 | G14: =E14*F14 -> 1623960 | H14: Lugares ÷ 6
A15: Almacén | B15: Rack de insumos de montaje (carros) | C15: Rack 500 kg/nivel — inicial | D15: R3I | E15: 1 | F15: =IFERROR(VLOOKUP(D15,PRECIOS,3,FALSE()),0) -> 606940 | G15: =E15*F15 -> 606940
A16: Almacén | B16: Rack de insumos de montaje (carros) | C16: Rack 500 kg/nivel — adicional | D16: R3A | E16: =MAX(0,ROUNDUP(Almacenes!E30/LUG_MOD,0)-1) -> 1 | F16: =IFERROR(VLOOKUP(D16,PRECIOS,3,FALSE()),0) -> 405990 | G16: =E16*F16 -> 405990 | H16: Lugares ÷ 6
A17: Almacén | B17: Insumos de montaje (manuales) | C17: Rack 1.000 kg/nivel — inicial | D17: R2I | E17: 1 | F17: =IFERROR(VLOOKUP(D17,PRECIOS,3,FALSE()),0) -> 650040 | G17: =E17*F17 -> 650040
A18: Almacén | B18: Insumos de montaje (manuales) | C18: Rack 1.000 kg/nivel — adicional | D18: R2A | E18: =MAX(0,ROUNDUP(Almacenes!E25/LUG_MOD,0)-1) -> 3 | F18: =IFERROR(VLOOKUP(D18,PRECIOS,3,FALSE()),0) -> 449090 | G18: =E18*F18 -> 1347270 | H18: Lugares ÷ 6
A19: Almacén | B19: Insumos de recargas | C19: Rack 1.000 kg/nivel — inicial | D19: R2I | E19: 1 | F19: =IFERROR(VLOOKUP(D19,PRECIOS,3,FALSE()),0) -> 650040 | G19: =E19*F19 -> 650040
A20: Almacén | B20: Insumos de recargas | C20: Rack 1.000 kg/nivel — adicional | D20: R2A | E20: =MAX(0,ROUNDUP(Almacenes!E26/LUG_MOD,0)-1) -> 1 | F20: =IFERROR(VLOOKUP(D20,PRECIOS,3,FALSE()),0) -> 449090 | G20: =E20*F20 -> 449090 | H20: Lugares ÷ 6
A21: Almacén | B21: Insumos de soldadura y superficie | C21: Rack 1.000 kg/nivel — inicial | D21: R2I | E21: 1 | F21: =IFERROR(VLOOKUP(D21,PRECIOS,3,FALSE()),0) -> 650040 | G21: =E21*F21 -> 650040
A22: Almacén | B22: Insumos de soldadura y superficie | C22: Rack 1.000 kg/nivel — adicional | D22: R2A | E22: =MAX(0,ROUNDUP(Almacenes!E27/LUG_MOD,0)-1) -> 0 | F22: =IFERROR(VLOOKUP(D22,PRECIOS,3,FALSE()),0) -> 449090 | G22: =E22*F22 -> 0 | H22: Lugares ÷ 6
A23: Almacén | B23: Insumos de recargas | C23: Pallet antiderrame 4 tambores | D23: A1 | E23: 2 | F23: =IFERROR(VLOOKUP(D23,PRECIOS,3,FALSE()),0) -> 495713 | G23: =E23*F23 -> 991426 | H23: Uno en el almacén y otro al pie del puesto 5
A24: Almacén | B24: Insumos de recargas | C24: Bandeja de contención | D24: A2 | E24: 2 | F24: =IFERROR(VLOOKUP(D24,PRECIOS,3,FALSE()),0) -> 54250 | G24: =E24*F24 -> 108500 | H24: Almacén y puesto 5
A25: Almacén | B25: Identificación | C25: Estantería encastrable 110 × 50 | D25: E1 | E25: =ROUNDUP(Almacenes!G24/1.1,0) -> 4 | F25: =IFERROR(VLOOKUP(D25,PRECIOS,3,FALSE()),0) -> 683968 | G25: =E25*F25 -> 2735872 | H25: m² ÷ 1,1 m² por estantería con pasillo
A26: Almacén | B26: Depósito de polvo químico | C26: Pallet plástico (pintura y bolsas) | D26: PL | E26: 2 | F26: =IFERROR(VLOOKUP(D26,PRECIOS,3,FALSE()),0) -> 117999 | G26: =E26*F26 -> 235998 | H26: 1 por material
A27: Almacén | B27: Jaula de gases | C27: Malla electrosoldada (rollo) | D27: M1 | E27: 2 | F27: =IFERROR(VLOOKUP(D27,PRECIOS,3,FALSE()),0) -> 98649 | G27: =E27*F27 -> 197298 | H27: Cerco de la jaula
A28: Almacén | B28: Jaula de gases | C28: Gabinete para 8 cilindros | D28: G1 | E28: 1 | F28: =IFERROR(VLOOKUP(D28,PRECIOS,3,FALSE()),0) -> 4882500 | G28: =E28*F28 -> 4882500 | H28: CO₂ y argón sueltos
A29: Almacén | B29: Flejes (rack + volteador) | C29: Par de largueros extra 2,30 m (4.º nivel) | D29: X7 | E29: =Chapa_fleje!G68 -> 2 | F29: =IFERROR(VLOOKUP(D29,PRECIOS,3,FALSE()),0) -> 95900 | G29: =E29*F29 -> 191800 | H29: 1 por módulo: el rack de flejes tiene piso + 3 niveles
A30: Fabricación propia | B30: Cantilever y jaula | C30: Perfil UPN 100 × 12 m | D30: S1 | E30: 4 | F30: =IFERROR(VLOOKUP(D30,PRECIOS,3,FALSE()),0) -> 384169 | G30: =E30*F30 -> 1536676 | H30: Cantilever (17,4 m) + postes de la jaula (14 m) + 10 %: ya no hay cunas
A31: General | B31: Chapa y almacén | C31: Cinta demarcatoria | D31: D1 | E31: 8 | F31: =IFERROR(VLOOKUP(D31,PRECIOS,3,FALSE()),0) -> 13384 | G31: =E31*F31 -> 107072 | H31: Pilas de chapa, rack de flejes, estación de volteo, big bags
C32: Total con IVA (sin el apilador con pinza, a cotizar) | G32: =SUM(G7:G31) -> 21644111
A34: No incluye: autoelevador y pluma (ya están en los Words), estantes de cajones y carros de abastecimiento de la línea (MP al pie de los puestos) ni el almacén de PT.
