Workbook

Sheet Indice
A1: Corte de chapa para cuerpos, cúpulas y fondos — Bobina, hojas, bobina madre y fleje a medida
A2: FLAMA S.A. — aprovechamiento, proceso y costos 2026–2035
A4: Hoja | B4: Contenido
A5: Supuestos | B5: Datos editables: parámetros, bobinas/stock, productividad, cotizaciones de acero recibidas, precio por espesor y forma de compra, y equipos por opción.
A6: Demanda | B6: Unidades por formato y año (terminados + cilindros), del Excel V2.
A7: Nesting | B7: Cuerpos y discos: piezas por hoja, por bobina y por fleje; aprovechamientos. Medidas y formatos editables.
A8: BobinaMadre | B8: Opción C: ancho de madre, patrones de corte longitudinal (tiras y % de uso) y cálculo anual por espesor.
A9: Bobinas | B9: Peso de bobina por SKU: recomendado según la demanda y ELEGIDO (editable), largo, días que dura y bobinas por año.
A10: Calculo | B10: Cálculo anual de toneladas, scrap, stock, horas y costos de cada opción.
A11: Proceso | B11: Cómo funciona cada opción: flujo, máquinas, materia prima, consumo, manejo y personal.
A12: Comparacion | B12: Resumen, valor actual, ranking, puntos de equilibrio, sensibilidades y gráficos.
A13: Decision | B13: Por qué se elige la opción D, con los números que la sostienen y cuándo habría que revisarla.
A14: Resumen D | B14: Todos los datos de la opción elegida año por año: costos, acero comprado, compras, stock, personal, equipos y proveedores.
A16: Colores
A17: 250 | B17: Azul con fondo amarillo: dato editable. Ej.: precio del scrap en USD/t.
A18: =1+1 -> 2 | B18: Negro: fórmula, no editar.
A19: =Supuestos!$C$84 -> 1.3561 | B19: Verde: vínculo a otra hoja (ej.: precio de hoja de 0,9 mm en USD/kg).
A21: Opciones
A22: • A — Bobina por formato: cuerpos desde bobinas de ancho estándar (línea de corte transversal); cúpulas y fondos desde flejes comprados cortados.
A23: • B — Hojas: todo desde hojas estándar; cuerpos en guillotina; discos desde tiras cargadas a mano en el balancín.
A24: • C — Bobina madre: una bobina ancha por espesor, corte longitudinal propio en flejes de cuerpo y de disco.
A25: • D — Hojas + fleje a medida: cuerpos desde hojas en guillotina; cúpulas y fondos desde bobinas angostas hechas a medida para cada disco.
A26: • Referencia: situación actual (cuerpos cortados a medida), solo para comparar.

Sheet Supuestos
A1: Supuestos editables
A2: Texto azul con fondo amarillo = dato editable. Todo lo demás se calcula.
A4: Concepto | B4: Valor | C4: Unidad | D4: Fuente / nota
A6: 1. Scrap y materia prima (los precios de acero están en la sección 7, tomados de las cotizaciones)
A7: Precio de venta del scrap | B7: 250 | C7: USD/t | D7: Ref.: acero reciclado $300–1.200/kg (Reaquila, mar-2026) con dólar ~$1.480 ≈ USD 0,20–0,80/kg.
A9: 2. Parámetros técnicos de corte
A10: Densidad del acero SAE 1010 | B10: 7.87 | C10: g/cm³ | D10: Planilla 'Dimensiones de chapa'.
A11: Margen mínimo de borde a lo ancho de la bobina | B11: 10 | C11: mm | D11: Bordes de laminación y tolerancia de ancho.
A12: Despunte de cabeza y cola de bobina | B12: 0.005 | C12: % | D12: Supuesto.
A13: Puente entre discos y al borde del fleje (s) | B13: 3 | C13: mm | D13: Supuesto (≈ 1,5–3 × espesor). Ancho de fleje = D + 2s; paso = D + s.
A14: ¿Mezclar 70 y 100 kg en la misma hoja? (SI/NO) | B14: SI | C14: SI/NO | D14: Solo opción hojas. Ver bloque en Nesting.
A16: 3. Financieros
A17: Tasa de descuento anual (USD) | B17: 0.12 | C17: % | D17: Igual a la Evaluación Económica del Excel V2 (12% real).
A18: Mantenimiento anual de equipos | B18: 0.03 | C18: % de la inversión | D18: SUPUESTO.
A20: 4. Bobinas y stock
A21: Año de referencia para recomendar pesos de bobina | B21: 2035 | C21: año | D21: Los pesos recomendados se calculan con el consumo de este año.
A22: Cobertura objetivo de una bobina | B22: 1 | C22: meses de consumo | D22: Criterio de recomendación: una bobina dura ~1 mes.
A23: Peso mínimo de bobina que se compra | B23: 0.5 | C23: t | D23: Mínimo razonable de un fraccionado.
A24: Diámetro exterior máximo de bobina aceptado | B24: 1500 | C24: mm | D24: Limita el peso según el ancho (bobinas angostas pesan poco).
A25: Diámetro interior de bobina | B25: 508 | C25: mm | D25: Estándar de mercado.
A26: Capacidad del desbobinador de la línea de corte transversal | B26: 10 | C26: t | D26: Especificar al comprar la línea.
A27: Capacidad del desbobinador de fleje del balancín (discos) | B27: 3 | C27: t | D27: Especificar al comprar.
A28: Capacidad del desbobinador de la cortadora longitudinal | B28: 14 | C28: t | D28: Pradecon: la bobina madre completa pesa 13–14 t.
A29: Cobertura máxima de stock por bobina | B29: 3 | C29: meses | D29: En años de poca demanda se compran bobinas más chicas: el stock por SKU no supera este consumo.
A30: Stock de seguridad | B30: 2 | C30: semanas de consumo | D30: Supuesto.
A31: Lote de compra de hojas / chapa a medida | B31: 1 | C31: meses de consumo | D31: Supuesto: compra mensual.
A32: Días hábiles por año | B32: 240 | C32: días | D32: 20 días/mes × 12 (Excel V2).
A34: 5. Productividad y mano de obra
A35: Línea de corte transversal: golpes efectivos por hora | B35: =20*60 -> 1200 | C35: golpes/h | D35: Supuesto.
A36: Guillotina: cortes efectivos por hora | B36: 180 | C36: cortes/h | D36: Supuesto (3 cortes/min con carga manual).
A37: Carga manual de una tira de hoja en el balancín (opción B) | B37: 15 | C37: s/tira | D37: Supuesto.
A38: Cambio de fleje en el desbobinador del balancín | B38: 15 | C38: min/fleje | D38: Supuesto.
A39: Cortadora longitudinal: velocidad efectiva | B39: 40 | C39: m/min | D39: Supuesto (máquinas de 60–120 m/min nominales).
A40: Cortadora: armado de cuchillas por bobina madre | B40: 45 | C40: min/bobina | D40: Supuesto (cambio de patrón).
A41: Operarios en la cortadora longitudinal | B41: 2 | C41: personas | D41: Supuesto.
A42: Horas productivas por operario y año | B42: 1800 | C42: h/año | D42: 150 h/mes × 12 (Excel V2).
A43: Costo mensual operario con cargas (P2) | B43: 1337922 | C43: ARS/mes | D43: Planilla 'Costo oportunidad operario-maquina', CCT 260/75 ago-2026.
A44: Horas por mes | B44: 150 | C44: h/mes | D44: Excel V2.
A45: Tipo de cambio | B45: 1420 | C45: ARS/USD | D45: Dólar BNA billete usado por Pradecon en sus presupuestos del 28/09/2026.
A46: Guillotina Molinari HG 6×3200 (referencia): precio sin IVA | B46: 36651584 | C46: ARS | D46: MercadoLibre, Molinari Maquinarias S.A.: $40,5 M con IVA 10,5%. Falta confirmar recorrido del tope trasero.
A47: Bobina madre: diferencia de precio sobre la bobina flejada | B47: 0 | C47: % | D47: ESTIMADO. Pradecon (mail 28/09/2026): la bobina completa cuesta lo mismo que la flejada (no cobran el flejado).
A48: Costo hora operario | B48: =$B$43/$B$44/$B$45 -> 6.2813239 | C48: USD/h | D48: Calculado.
A49: Peso máximo por mm de ancho (por diámetro exterior) | B49: =PI()/4*($B$24^2-$B$25^2)*$B$10/1000000/1000 -> 0.012312323 | C49: t por mm de ancho | D49: Calculado.
A51: 7. Cotizaciones de acero recibidas (precios sin IVA)
A52: Proveedor / documento | B52: Producto | C52: Espesor (mm) | D52: Formato / ancho | E52: Moneda | F52: Precio por kg | G52: TC de la cotización | H52: USD por kg | I52: Nota
A53: Q1 · Pradecon 173170 | B53: Bobina LAF flejada | C53: 0.9 | D53: Ancho 1.220 | E53: USD | F53: 1.26285 | G53: 1545 | H53: =IF(E53="USD",F53,F53/G53) -> 1.26285 | I53: Flejado sin cargo: sirve también como fleje a medida.
A54: Q2 · Pradecon 173170 | B54: Bobina LAF flejada | C54: 1.25 | D54: Ancho 1.220 | E54: USD | F54: 1.25056 | G54: 1545 | H54: =IF(E54="USD",F54,F54/G54) -> 1.25056
A55: Q3 · Pradecon 173170 | B55: Bobina LAF flejada | C55: 1.6 | D55: Ancho 1.220 (también 1.000) | E55: USD | F55: 1.25056 | G55: 1545 | H55: =IF(E55="USD",F55,F55/G55) -> 1.25056
A56: Q4 · Pradecon 173170 | B56: Bobina LAF flejada | C56: 2 | D56: Ancho 1.220 (también 1.000) | E56: USD | F56: 1.26285 | G56: 1545 | H56: =IF(E56="USD",F56,F56/G56) -> 1.26285
A57: Q5 · Pradecon 173170 | B57: Bobina LAC flejada | C57: 3.2 | D57: Ancho 1.245 (también 1.500) | E57: USD | F57: 1.11373 | G57: 1545 | H57: =IF(E57="USD",F57,F57/G57) -> 1.11373
A58: Q6 · Pradecon 173170 | B58: Hoja LAC | C58: 4.75 | D58: 1500 × 3000 | E58: USD | F58: 1.05792 | G58: 1545 | H58: =IF(E58="USD",F58,F58/G58) -> 1.05792 | I58: Mismo producto que Q11 cotizado en USD.
A59: Q7 · Pradecon 173195 | B59: Hoja LAF (C16) | C59: 1.6 | D59: 1000 × 2000 | E59: ARS | F59: 2051.02 | G59: 1545 | H59: =IF(E59="USD",F59,F59/G59) -> 1.327521
A60: Q8 · Pradecon 173195 | B60: Hoja LAF (C18) | C60: 1.25 | D60: 1220 × 2440 | E60: ARS | F60: 1993.51 | G60: 1545 | H60: =IF(E60="USD",F60,F60/G60) -> 1.2902977
A61: Q9 · Pradecon 173195 | B61: Hoja LAF (C14) | C61: 2 | D61: 1500 × 3000 | E61: ARS | F61: 1978.22 | G61: 1545 | H61: =IF(E61="USD",F61,F61/G61) -> 1.2804013
A62: Q10 · Pradecon 173195 | B62: Hoja LAC (1/8) | C62: 3.2 | D62: 1500 × 3000 | E62: ARS | F62: 1702.49 | G62: 1545 | H62: =IF(E62="USD",F62,F62/G62) -> 1.1019353
A63: Q11 · Pradecon 173195 | B63: Hoja LAC (3/16) | C63: 4.75 | D63: 1500 × 3000 | E63: ARS | F63: 1685.56 | G63: 1545 | H63: =IF(E63="USD",F63,F63/G63) -> 1.0909773
A64: Q12 · Hierros Parrotta 413329 | B64: Hoja doble decapada N°20 | C64: 0.9 | D64: 1220 × 2440 | E64: USD | F64: 1.3561 | G64: 1 | H64: =IF(E64="USD",F64,F64/G64) -> 1.3561 | I64: Neto con 6,84% de descuento, pago contado.
A65: Q13 · Hierros Parrotta 413329 | B65: Hoja doble decapada N°20 | C65: 0.9 | D65: 1000 × 2000 | E65: USD | F65: 1.3993 | G65: 1 | H65: =IF(E65="USD",F65,F65/G65) -> 1.3993
A66: Q14 · Hierros Parrotta 413329 | B66: Hoja doble decapada N°18 (1,2) | C66: 1.25 | D66: 1220 × 2440 | E66: USD | F66: 1.3464 | G66: 1 | H66: =IF(E66="USD",F66,F66/G66) -> 1.3464
A67: Q15 · Hierros Parrotta 413329 | B67: Hoja doble decapada N°16 | C67: 1.6 | D67: 1220 × 2440 | E67: USD | F67: 1.3443 | G67: 1 | H67: =IF(E67="USD",F67,F67/G67) -> 1.3443
A68: Q16 · Hierros Parrotta 413329 | B68: Hoja doble decapada N°14 | C68: 2 | D68: 1220 × 2440 | E68: USD | F68: 1.3605 | G68: 1 | H68: =IF(E68="USD",F68,F68/G68) -> 1.3605
A69: Q17 · Hierros Parrotta 413329 | B69: Hoja LAC 1/8 | C69: 3.2 | D69: 1500 × 3000 | E69: USD | F69: 1.1607 | G69: 1 | H69: =IF(E69="USD",F69,F69/G69) -> 1.1607
A70: Q18 · Hierros Parrotta 413329 | B70: Hoja LAC 3/16 | C70: 4.75 | D70: 1500 × 3000 | E70: USD | F70: 1.1678 | G70: 1 | H70: =IF(E70="USD",F70,F70/G70) -> 1.1678
A71: Q19 · Pacheco Chapas PR 42021 | B71: Rollo LAF (fleje) | C71: 1.25 | D71: Ancho 200 | E71: USD | F71: 1.186 | G71: 1530 | H71: =IF(E71="USD",F71,F71/G71) -> 1.186 | I71: Discos 2,5 kg. 6 rollos en 2.951 kg (~0,5 t c/u).
A72: Q20 · Pacheco Chapas PR 42021 | B72: Rollo LAF (fleje) | C72: 1.6 | D72: Ancho 200 y 250 | E72: USD | F72: 1.186 | G72: 1530 | H72: =IF(E72="USD",F72,F72/G72) -> 1.186 | I72: Discos 5 kg. Rollos de ~0,5 y ~0,6 t.
A73: Q21 · Pacheco Chapas PR 42021 | B73: Rollo LAF (fleje) | C73: 2 | D73: Ancho 249 y 300 | E73: USD | F73: 1.198 | G73: 1530 | H73: =IF(E73="USD",F73,F73/G73) -> 1.198 | I73: Discos 10 kg. Rollos de ~0,5 y ~0,74 t.
A74: Q22 · Pacheco Chapas PR 42021 | B74: Plancha cortada a medida LAF | C74: 1.25 | D74: 1220 × 540 (3×2 cuerpos) | E74: USD | F74: 1.426 | G74: 1530 | H74: =IF(E74="USD",F74,F74/G74) -> 1.426 | I74: Referencia: chapa a medida.
A75: Q23 · Pacheco Chapas PR 42021 | B75: Plancha cortada a medida LAF | C75: 1.6 | D75: 1000 × 475 (3 cuerpos) | E75: USD | F75: 1.453 | G75: 1530 | H75: =IF(E75="USD",F75,F75/G75) -> 1.453
A76: Q24 · Pacheco Chapas PR 42021 | B76: Plancha cortada a medida LAF | C76: 2 | D76: 1500 × 563 (3 cuerpos) | E76: USD | F76: 1.429 | G76: 1530 | H76: =IF(E76="USD",F76,F76/G76) -> 1.429
A77: Q25 · Pacheco Chapas PR 42021 | B77: Plancha cortada a medida LAC | C77: 3.2 | D77: 1500 × 2584 / 1988 | E77: USD | F77: 1.256 | G77: 1530 | H77: =IF(E77="USD",F77,F77/G77) -> 1.256
A78: Q26 · Pacheco Chapas PR 42024 | B78: Plancha cortada a medida LAC | C78: 4.75 | D78: 1245 × 1360 / 1800 | E78: USD | F78: 1.236 | G78: 1530 | H78: =IF(E78="USD",F78,F78/G78) -> 1.236
A80: Bobina madre: sin cotización todavía (se usa el precio de la bobina flejada más la diferencia de la sección 4). Polimetal (chapa a medida) quedó descartado y no se usa.
A82: 8. Precio del acero por espesor y forma de compra (USD por kg) — lo que usa el cálculo
A83: Espesor (mm) | B83: Bobina ancho estándar (A, cuerpos) | C83: Hoja estándar (B y D) | D83: Fleje a medida (discos A, D y referencia) | E83: Bobina madre (C) | F83: Chapa cortada a medida (referencia) | G83: Diferencia hoja vs. bobina | H83: Fuente
A84: 0.9 | B84: =$H$53 -> 1.26285 | C84: =$H$64 -> 1.3561 | D84: =$H$53 -> 1.26285 | E84: =B84*(1+$B$47) -> 1.26285 | F84: =$H$53 -> 1.26285 | G84: =C84/B84-1 -> 0.073840915 | H84: Bobina y fleje: Pradecon Q1 · Hoja: Parrotta Q12 · A medida: no aplica (se usa fleje)
A85: 1.25 | B85: =$H$54 -> 1.25056 | C85: =$H$60 -> 1.2902977 | D85: =$H$71 -> 1.186 | E85: =B85*(1+$B$47) -> 1.25056 | F85: =$H$74 -> 1.426 | G85: =C85/B85-1 -> 0.031775952 | H85: Bobina: Pradecon Q2 · Hoja: Pradecon Q8 · Fleje: Pacheco Q19 · A medida: Pacheco Q22
A86: 1.6 | B86: =$H$55 -> 1.25056 | C86: =$H$59 -> 1.327521 | D86: =$H$72 -> 1.186 | E86: =B86*(1+$B$47) -> 1.25056 | F86: =$H$75 -> 1.453 | G86: =C86/B86-1 -> 0.061541258 | H86: Bobina: Pradecon Q3 · Hoja: Pradecon Q7 · Fleje: Pacheco Q20 · A medida: Pacheco Q23
A87: 2 | B87: =$H$56 -> 1.26285 | C87: =$H$61 -> 1.2804013 | D87: =$H$73 -> 1.198 | E87: =B87*(1+$B$47) -> 1.26285 | F87: =$H$76 -> 1.429 | G87: =C87/B87-1 -> 0.013898162 | H87: Bobina: Pradecon Q4 · Hoja: Pradecon Q9 · Fleje: Pacheco Q21 · A medida: Pacheco Q24
A88: 3.2 | B88: =$H$57 -> 1.11373 | C88: =$H$62 -> 1.1019353 | D88: =$H$57 -> 1.11373 | E88: =B88*(1+$B$47) -> 1.11373 | F88: =$H$77 -> 1.256 | G88: =C88/B88-1 -> -0.010590291 | H88: Bobina: Pradecon Q5 · Hoja: Pradecon Q10 · Fleje: no aplica · A medida: Pacheco Q25
A89: 4.75 | B89: 1.11373 | C89: =$H$63 -> 1.0909773 | D89: =$H$57 -> 1.11373 | E89: =B89*(1+$B$47) -> 1.11373 | F89: =$H$78 -> 1.236 | G89: =C89/B89-1 -> -0.020429237 | H89: Bobina: ESTIMADO (sin cotización; igual a LAC 3,2) · Hoja: Pradecon Q11 · A medida: Pacheco Q26
A90: Si cambia un espesor en Nesting, tiene que existir la misma fila acá (el cálculo busca el precio por espesor).
A92: 6. Equipos e inversión (precios y cantidades editables)
A93: ¿El puente grúa ya está previsto en el layout por otro motivo? (SI/NO) | B93: NO | D93: Si es SI, no se carga a las opciones A y C (la cátedra ya recomendó puente grúa para descargar chapa).
A95: Equipo | B95: Precio unitario (USD) | C95: Cant. A: bobina por formato | D95: Cant. B: hojas | E95: Cant. C: bobina madre | F95: Cant. D: hojas + fleje | G95: Cant. referencia (a medida) | H95: Subtotal A | I95: Subtotal B | J95: Subtotal C | K95: Subtotal D | L95: Subtotal referencia | M95: Fuente / nota
A96: Línea de corte transversal 1–6 mm × 1.600 (desbobinador, aplanadora, alimentador servo, cizalla) | B96: 80000 | C96: 1 | D96: 0 | E96: 1 | F96: 0 | G96: 0 | H96: =$B96*C96 -> 80000 | I96: =$B96*D96 -> 0 | J96: =$B96*E96 -> 80000 | K96: =$B96*F96 -> 0 | L96: =$B96*G96 -> 0 | M96: ESTIMADO. Hener publica USD 45.000 para 0,2–3 mm × 1.250; con rodantes (hasta 4,75 mm) se requiere una línea más pesada. Cotizar.
A97: Guillotina hidráulica 6 × 3.200 mm con tope motorizado | B97: =$B$46/$B$45 -> 25810.975 | C97: 1 | D97: 1 | E97: 0 | F97: 1 | G97: 0 | H97: =$B97*C97 -> 25810.975 | I97: =$B97*D97 -> 25810.975 | J97: =$B97*E97 -> 0 | K97: =$B97*F97 -> 25810.975 | L97: =$B97*G97 -> 0 | M97: Molinari HG 6×3200 (MercadoLibre), sin IVA, convertido al TC de Supuestos. En A separa las tiras de la línea.
A98: Cortadora longitudinal (slitter) 0,3–3,2 × 1.600 | B98: 60000 | C98: 0 | D98: 0 | E98: 1 | F98: 0 | G98: 0 | H98: =$B98*C98 -> 0 | I98: =$B98*D98 -> 0 | J98: =$B98*E98 -> 60000 | K98: =$B98*F98 -> 0 | L98: =$B98*G98 -> 0 | M98: ESTIMADO. Cangzhou Zunsheng publica USD 28.600–59.620 FOB (0,3–3,0 mm × 1.500, 10 t).
A99: Puente grúa monoviga 10 t (incluye carrilera) | B99: 30000 | C99: =IF($B$93="SI",0,1) -> 1 | D99: 0 | E99: =IF($B$93="SI",0,1) -> 1 | F99: 0 | G99: 0 | H99: =$B99*C99 -> 30000 | I99: =$B99*D99 -> 0 | J99: =$B99*E99 -> 30000 | K99: =$B99*F99 -> 0 | L99: =$B99*G99 -> 0 | M99: Dongqi Crane: 10 t básico USD 10.000–50.000. Cantidad automática según 'ya previsto'.
A100: Pinza en C portabobinas + cunas | B100: 6000 | C100: 1 | D100: 0 | E100: 1 | F100: 0 | G100: 0 | H100: =$B100*C100 -> 6000 | I100: =$B100*D100 -> 0 | J100: =$B100*E100 -> 6000 | K100: =$B100*F100 -> 0 | L100: =$B100*G100 -> 0 | M100: ESTIMADO.
A101: Desbobinador + enderezador + alimentador servo para la prensa de discos | B101: 12000 | C101: 1 | D101: 0 | E101: 1 | F101: 1 | G101: 1 | H101: =$B101*C101 -> 12000 | I101: =$B101*D101 -> 0 | J101: =$B101*E101 -> 12000 | K101: =$B101*F101 -> 12000 | L101: =$B101*G101 -> 12000 | M101: ESTIMADO. En cotización (Cena, Henli, AEK, King Jime, Segura Llunell).
A102: Estantería porta-flejes | B102: 3000 | C102: 1 | D102: 0 | E102: 1 | F102: 1 | G102: 1 | H102: =$B102*C102 -> 3000 | I102: =$B102*D102 -> 0 | J102: =$B102*E102 -> 3000 | K102: =$B102*F102 -> 3000 | L102: =$B102*G102 -> 3000 | M102: ESTIMADO.
A103: Autoelevador eléctrico 2,5 t | B103: 20000 | C103: 0 | D103: 1 | E103: 0 | F103: 1 | G103: 0 | H103: =$B103*C103 -> 0 | I103: =$B103*D103 -> 20000 | J103: =$B103*E103 -> 0 | K103: =$B103*F103 -> 20000 | L103: =$B103*G103 -> 0 | M103: MercadoLibre GBA, nuevos 2026: USD 13.700–26.700 (EISEN).
A104: Mesa elevadora de tijera 1500 × 3000 mm, 3 t, elevación ~1 m (paquete de hojas a la altura de la guillotina) | B104: 7000 | C104: 0 | D104: 1 | E104: 0 | F104: 1 | G104: 0 | H104: =$B104*C104 -> 0 | I104: =$B104*D104 -> 7000 | J104: =$B104*E104 -> 0 | K104: =$B104*F104 -> 7000 | L104: =$B104*G104 -> 0 | M104: ESTIMADO. Referencia: mesas de 3 t con plataforma 3500 × 1500 y 3,5 m de elevación ~EUR 11.750 (SIA Suministros); una de ~1 m de elevación es más barata. Cotizar.
A105: Apoyos con bolas (mesa de bolas) entre la mesa elevadora y la guillotina | B105: 1500 | C105: 0 | D105: 1 | E105: 0 | F105: 1 | G105: 0 | H105: =$B105*C105 -> 0 | I105: =$B105*D105 -> 1500 | J105: =$B105*E105 -> 0 | K105: =$B105*F105 -> 1500 | L105: =$B105*G105 -> 0 | M105: ESTIMADO. Consultar si la guillotina trae brazos delanteros con bolas: en ese caso no hace falta.
A106: Racks por espesor en el almacén de MP y carros porta-desarrollos | B106: 2000 | C106: 0 | D106: 1 | E106: 0 | F106: 1 | G106: 0 | H106: =$B106*C106 -> 0 | I106: =$B106*D106 -> 2000 | J106: =$B106*E106 -> 0 | K106: =$B106*F106 -> 2000 | L106: =$B106*G106 -> 0 | M106: ESTIMADO.
A107: Mesa de alimentación de tiras al balancín | B107: 1500 | C107: 0 | D107: 1 | E107: 0 | F107: 0 | G107: 0 | H107: =$B107*C107 -> 0 | I107: =$B107*D107 -> 1500 | J107: =$B107*E107 -> 0 | K107: =$B107*F107 -> 0 | L107: =$B107*G107 -> 0 | M107: ESTIMADO. Discos desde tiras de hoja (opción B).
A108: TOTAL | H108: =SUM(H96:H107) -> 156810.97 | I108: =SUM(I96:I107) -> 57810.975 | J108: =SUM(J96:J107) -> 191000 | K108: =SUM(K96:K107) -> 71310.975 | L108: =SUM(L96:L107) -> 15000
A110: Precios en USD sin IVA. El balancín/prensa de discos y la cilindradora existen en todas las opciones y no se incluyen.

Sheet Demanda
A1: Demanda por formato (unidades/año)
A2: Fuente: Dimensionamiento_TecnicoV2.xlsx, hoja datos_base. Cada unidad lleva 1 cuerpo, 1 cúpula y 1 fondo (el 1 kg lleva cuerpo de tubo comprado).
A4: Matafuegos terminados
A5: Formato | B5: Línea | D5: 2026 | E5: 2027 | F5: 2028 | G5: 2029 | H5: 2030 | I5: 2031 | J5: 2032 | K5: 2033 | L5: 2034 | M5: 2035
A6: 1 kg | B6: Manual | D6: 4179 | E6: 5997 | F6: 6852 | G6: 8467 | H6: 12681 | I6: 15620 | J6: 20333 | K6: 25132 | L6: 28573 | M6: 32073
A7: 2,5 kg | B7: Manual | D7: 295 | E7: 709 | F7: 987 | G7: 1501 | H7: 2312 | I7: 3252 | J7: 4103 | K7: 5105 | L7: 6195 | M7: 7425
A8: 5 kg | B8: Manual | D8: 2256 | E8: 3847 | F8: 5094 | G8: 6823 | H8: 10819 | I8: 14606 | J8: 18878 | K8: 23368 | L8: 26968 | M8: 30751
A9: 10 kg | B9: Manual | D9: 92 | E9: 177 | F9: 253 | G9: 358 | H9: 603 | I9: 872 | J9: 1127 | K9: 1395 | L9: 1612 | M9: 1841
A10: 25 kg | B10: Rodante | D10: 34 | E10: 58 | F10: 76 | G10: 100 | H10: 156 | I10: 212 | J10: 273 | K10: 338 | L10: 393 | M10: 453
A11: 50 kg | B11: Rodante | D11: 75 | E11: 128 | F11: 166 | G11: 221 | H11: 343 | I11: 466 | J11: 599 | K11: 743 | L11: 866 | M11: 997
A12: 70 kg | B12: Rodante | D12: 16 | E12: 29 | F12: 36 | G12: 48 | H12: 74 | I12: 101 | J12: 131 | K12: 163 | L12: 189 | M12: 218
A13: 100 kg | B13: Rodante | D13: 11 | E13: 18 | F13: 24 | G13: 33 | H13: 50 | I13: 67 | J13: 87 | K13: 108 | L13: 126 | M13: 145
A14: TOTAL | D14: =SUM(D6:D13) -> 6958 | E14: =SUM(E6:E13) -> 10963 | F14: =SUM(F6:F13) -> 13488 | G14: =SUM(G6:G13) -> 17551 | H14: =SUM(H6:H13) -> 27038 | I14: =SUM(I6:I13) -> 35196 | J14: =SUM(J6:J13) -> 45531 | K14: =SUM(K6:K13) -> 56352 | ... M14: =SUM(M6:M13) -> 73903
A16: Cilindros vendidos vacíos
A17: Formato | B17: Línea | D17: 2026 | E17: 2027 | F17: 2028 | G17: 2029 | H17: 2030 | I17: 2031 | J17: 2032 | K17: 2033 | L17: 2034 | M17: 2035
A18: 1 kg | B18: Manual | D18: 0 | E18: 0 | F18: 7662 | G18: 26695 | H18: 49435 | I18: 71680 | J18: 101341 | K18: 131001 | L18: 146820 | M18: 170548
A19: 2,5 kg | B19: Manual | D19: 0 | E19: 0 | F19: 300 | G19: 1044 | H19: 1933 | I19: 2803 | J19: 3963 | K19: 5123 | L19: 5741 | M19: 6669
A20: 5 kg | B20: Manual | D20: 0 | E20: 0 | F20: 1479 | G20: 5152 | H20: 9541 | I20: 13834 | J20: 19559 | K20: 25283 | L20: 28336 | M20: 32915
A21: 10 kg | B21: Manual | D21: 0 | E21: 0 | F21: 90 | G21: 315 | H21: 583 | I21: 846 | J21: 1195 | K21: 1545 | L21: 1731 | M21: 2011
A22: 25 kg | B22: Rodante | D22: 0 | E22: 0 | F22: 14 | G22: 50 | H22: 93 | I22: 135 | J22: 191 | K22: 247 | L22: 277 | M22: 322
A23: 50 kg | B23: Rodante | D23: 0 | E23: 0 | F23: 32 | G23: 111 | H23: 205 | I23: 298 | J23: 421 | K23: 544 | L23: 610 | M23: 708
A24: 70 kg | B24: Rodante | D24: 0 | E24: 0 | F24: 7 | G24: 24 | H24: 45 | I24: 65 | J24: 92 | K24: 119 | L24: 133 | M24: 155
A25: 100 kg | B25: Rodante | D25: 0 | E25: 0 | F25: 5 | G25: 16 | H25: 30 | I25: 43 | J25: 60 | K25: 78 | L25: 88 | M25: 102
A26: TOTAL | D26: =SUM(D18:D25) -> 0 | E26: =SUM(E18:E25) -> 0 | F26: =SUM(F18:F25) -> 9589 | G26: =SUM(G18:G25) -> 33407 | H26: =SUM(H18:H25) -> 61865 | I26: =SUM(I18:I25) -> 89704 | J26: =SUM(J18:J25) -> 126822 | K26: =SUM(K18:K25) -> 163940 | ... M26: =SUM(M18:M25) -> 213430
A28: TOTAL UNIDADES A FABRICAR
A29: Formato | B29: Línea | D29: 2026 | E29: 2027 | F29: 2028 | G29: 2029 | H29: 2030 | I29: 2031 | J29: 2032 | K29: 2033 | L29: 2034 | M29: 2035
A30: 1 kg | B30: Manual | D30: =D6+D18 -> 4179 | E30: =E6+E18 -> 5997 | F30: =F6+F18 -> 14514 | G30: =G6+G18 -> 35162 | H30: =H6+H18 -> 62116 | I30: =I6+I18 -> 87300 | J30: =J6+J18 -> 121674 | K30: =K6+K18 -> 156133 | ... M30: =M6+M18 -> 202621
A31: 2,5 kg | B31: Manual | D31: =D7+D19 -> 295 | E31: =E7+E19 -> 709 | F31: =F7+F19 -> 1287 | G31: =G7+G19 -> 2545 | H31: =H7+H19 -> 4245 | I31: =I7+I19 -> 6055 | J31: =J7+J19 -> 8066 | K31: =K7+K19 -> 10228 | ... M31: =M7+M19 -> 14094
A32: 5 kg | B32: Manual | D32: =D8+D20 -> 2256 | E32: =E8+E20 -> 3847 | F32: =F8+F20 -> 6573 | G32: =G8+G20 -> 11975 | H32: =H8+H20 -> 20360 | I32: =I8+I20 -> 28440 | J32: =J8+J20 -> 38437 | K32: =K8+K20 -> 48651 | ... M32: =M8+M20 -> 63666
A33: 10 kg | B33: Manual | D33: =D9+D21 -> 92 | E33: =E9+E21 -> 177 | F33: =F9+F21 -> 343 | G33: =G9+G21 -> 673 | H33: =H9+H21 -> 1186 | I33: =I9+I21 -> 1718 | J33: =J9+J21 -> 2322 | K33: =K9+K21 -> 2940 | ... M33: =M9+M21 -> 3852
A34: 25 kg | B34: Rodante | D34: =D10+D22 -> 34 | E34: =E10+E22 -> 58 | F34: =F10+F22 -> 90 | G34: =G10+G22 -> 150 | H34: =H10+H22 -> 249 | I34: =I10+I22 -> 347 | J34: =J10+J22 -> 464 | K34: =K10+K22 -> 585 | ... M34: =M10+M22 -> 775
A35: 50 kg | B35: Rodante | D35: =D11+D23 -> 75 | E35: =E11+E23 -> 128 | F35: =F11+F23 -> 198 | G35: =G11+G23 -> 332 | H35: =H11+H23 -> 548 | I35: =I11+I23 -> 764 | J35: =J11+J23 -> 1020 | K35: =K11+K23 -> 1287 | ... M35: =M11+M23 -> 1705
A36: 70 kg | B36: Rodante | D36: =D12+D24 -> 16 | E36: =E12+E24 -> 29 | F36: =F12+F24 -> 43 | G36: =G12+G24 -> 72 | H36: =H12+H24 -> 119 | I36: =I12+I24 -> 166 | J36: =J12+J24 -> 223 | K36: =K12+K24 -> 282 | ... M36: =M12+M24 -> 373
A37: 100 kg | B37: Rodante | D37: =D13+D25 -> 11 | E37: =E13+E25 -> 18 | F37: =F13+F25 -> 29 | G37: =G13+G25 -> 49 | H37: =H13+H25 -> 80 | I37: =I13+I25 -> 110 | J37: =J13+J25 -> 147 | K37: =K13+K25 -> 186 | ... M37: =M13+M25 -> 247
A38: TOTAL | D38: =SUM(D30:D37) -> 6958 | E38: =SUM(E30:E37) -> 10963 | F38: =SUM(F30:F37) -> 23077 | G38: =SUM(G30:G37) -> 50958 | H38: =SUM(H30:H37) -> 88903 | I38: =SUM(I30:I37) -> 124900 | J38: =SUM(J30:J37) -> 172353 | K38: =SUM(K30:K37) -> 220292 | ... M38: =SUM(M30:M37) -> 287333
A40: Discos de rodantes (25–100 kg): se compran tercerizados embutidos, no entran en este análisis.

Sheet Nesting
A1: Nesting: cuántas piezas salen de cada hoja, bobina y fleje
A2: Editables: medidas de piezas, formato de hoja y ancho de bobina de cada formato.
A4: A) CUERPOS | H4: Hoja estándar + guillotina (opción B) | P4: Bobina de ancho estándar + línea de corte (opción A)
A5: Formato | B5: Línea | C5: Alto cuerpo (mm) | D5: Perímetro = largo desarrollo (mm) | E5: Espesor (mm) | F5: Acero | G5: Masa del desarrollo (kg) | H5: HOJA ancho (mm) | I5: HOJA largo (mm) | J5: Piezas orient. 1 | K5: Piezas orient. 2 | L5: Piezas por hoja | M5: Aprovech. hoja | N5: Masa hoja (kg) | O5: Cortes guillotina por hoja | P5: BOBINA ancho (mm) | Q5: Piezas a lo ancho (alto cruzado) | R5: Aprov. (alto cruzado) | S5: Piezas a lo ancho (perím. cruzado) | T5: Aprov. (perím. cruzado) | U5: Piezas por golpe | V5: Avance por golpe (mm) | W5: Aprovech. bobina | X5: Orientación
A6: 2,5 kg | B6: Manual | C6: 269.5 | D6: 385.5 | E6: 1.25 | F6: LAF | G6: =C6*D6*E6*Supuestos!$B$10/1000000 -> 1.02204 | H6: 1220 | I6: 2440 | J6: =INT(H6/C6)*INT(I6/D6) -> 24 | K6: =INT(H6/D6)*INT(I6/C6) -> 27 | L6: =MAX(J6,K6) -> 27 | M6: =L6*C6*D6/(H6*I6) -> 0.94231751 | N6: =H6*I6*E6*Supuestos!$B$10/1000000 -> 29.28427 | O6: =IF(J6>=K6,INT(H6/C6)*(1+INT(I6/D6)),INT(H6/D6)*(1+INT(I6/C6))) -> 30 | P6: 1220 | Q6: =INT((P6-Supuestos!$B$11)/C6) -> 4 | R6: =Q6*C6/P6 -> 0.88360656 | S6: =INT((P6-Supuestos!$B$11)/D6) -> 3 | T6: =S6*D6/P6 -> 0.94795082 | U6: =IF(R6>=T6,Q6,S6) -> 3 | V6: =IF(R6>=T6,D6,C6) -> 269.5 | W6: =MAX(R6,T6)*(1-Supuestos!$B$12) -> 0.94321107 | X6: =IF(R6>=T6,"Alto a lo ancho","Perímetro a lo ancho") -> Perímetro a lo ancho
A7: 5 kg | B7: Manual | C7: 330 | D7: 474.5 | E7: 1.6 | F7: LAF | G7: =C7*D7*E7*Supuestos!$B$10/1000000 -> 1.9717183 | H7: 1000 | I7: 2000 | J7: =INT(H7/C7)*INT(I7/D7) -> 12 | K7: =INT(H7/D7)*INT(I7/C7) -> 12 | L7: =MAX(J7,K7) -> 12 | M7: =L7*C7*D7/(H7*I7) -> 0.93951 | N7: =H7*I7*E7*Supuestos!$B$10/1000000 -> 25.184 | O7: =IF(J7>=K7,INT(H7/C7)*(1+INT(I7/D7)),INT(H7/D7)*(1+INT(I7/C7))) -> 15 | P7: 1000 | Q7: =INT((P7-Supuestos!$B$11)/C7) -> 3 | R7: =Q7*C7/P7 -> 0.99 | S7: =INT((P7-Supuestos!$B$11)/D7) -> 2 | T7: =S7*D7/P7 -> 0.949 | U7: =IF(R7>=T7,Q7,S7) -> 3 | V7: =IF(R7>=T7,D7,C7) -> 474.5 | W7: =MAX(R7,T7)*(1-Supuestos!$B$12) -> 0.98505 | X7: =IF(R7>=T7,"Alto a lo ancho","Perímetro a lo ancho") -> Alto a lo ancho
A8: 10 kg | B8: Manual | C8: 495 | D8: 563 | E8: 2 | F8: LAF | G8: =C8*D8*E8*Supuestos!$B$10/1000000 -> 4.3865019 | H8: 1500 | I8: 3000 | J8: =INT(H8/C8)*INT(I8/D8) -> 15 | K8: =INT(H8/D8)*INT(I8/C8) -> 12 | L8: =MAX(J8,K8) -> 15 | M8: =L8*C8*D8/(H8*I8) -> 0.92895 | N8: =H8*I8*E8*Supuestos!$B$10/1000000 -> 70.83 | O8: =IF(J8>=K8,INT(H8/C8)*(1+INT(I8/D8)),INT(H8/D8)*(1+INT(I8/C8))) -> 18 | P8: 1000 | Q8: =INT((P8-Supuestos!$B$11)/C8) -> 2 | R8: =Q8*C8/P8 -> 0.99 | S8: =INT((P8-Supuestos!$B$11)/D8) -> 1 | T8: =S8*D8/P8 -> 0.563 | U8: =IF(R8>=T8,Q8,S8) -> 2 | V8: =IF(R8>=T8,D8,C8) -> 563 | W8: =MAX(R8,T8)*(1-Supuestos!$B$12) -> 0.98505 | X8: =IF(R8>=T8,"Alto a lo ancho","Perímetro a lo ancho") -> Alto a lo ancho
A9: 25 kg | B9: Rodante | C9: 490 | D9: 858 | E9: 3.2 | F9: LAC | G9: =C9*D9*E9*Supuestos!$B$10/1000000 -> 10.587857 | H9: 1500 | I9: 3000 | J9: =INT(H9/C9)*INT(I9/D9) -> 9 | K9: =INT(H9/D9)*INT(I9/C9) -> 6 | L9: =MAX(J9,K9) -> 9 | M9: =L9*C9*D9/(H9*I9) -> 0.84084 | N9: =H9*I9*E9*Supuestos!$B$10/1000000 -> 113.328 | O9: =IF(J9>=K9,INT(H9/C9)*(1+INT(I9/D9)),INT(H9/D9)*(1+INT(I9/C9))) -> 12 | P9: 1500 | Q9: =INT((P9-Supuestos!$B$11)/C9) -> 3 | R9: =Q9*C9/P9 -> 0.98 | S9: =INT((P9-Supuestos!$B$11)/D9) -> 1 | T9: =S9*D9/P9 -> 0.572 | U9: =IF(R9>=T9,Q9,S9) -> 3 | V9: =IF(R9>=T9,D9,C9) -> 858 | W9: =MAX(R9,T9)*(1-Supuestos!$B$12) -> 0.9751 | X9: =IF(R9>=T9,"Alto a lo ancho","Perímetro a lo ancho") -> Alto a lo ancho
A10: 50 kg | B10: Rodante | C10: 640 | D10: 994 | E10: 3.2 | F10: LAC | G10: =C10*D10*E10*Supuestos!$B$10/1000000 -> 16.021053 | H10: 1500 | I10: 3000 | J10: =INT(H10/C10)*INT(I10/D10) -> 6 | K10: =INT(H10/D10)*INT(I10/C10) -> 4 | L10: =MAX(J10,K10) -> 6 | M10: =L10*C10*D10/(H10*I10) -> 0.84821333 | N10: =H10*I10*E10*Supuestos!$B$10/1000000 -> 113.328 | O10: =IF(J10>=K10,INT(H10/C10)*(1+INT(I10/D10)),INT(H10/D10)*(1+INT(I10/C10))) -> 8 | P10: 1500 | Q10: =INT((P10-Supuestos!$B$11)/C10) -> 2 | R10: =Q10*C10/P10 -> 0.85333333 | S10: =INT((P10-Supuestos!$B$11)/D10) -> 1 | T10: =S10*D10/P10 -> 0.66266667 | U10: =IF(R10>=T10,Q10,S10) -> 2 | V10: =IF(R10>=T10,D10,C10) -> 994 | W10: =MAX(R10,T10)*(1-Supuestos!$B$12) -> 0.84906667 | X10: =IF(R10>=T10,"Alto a lo ancho","Perímetro a lo ancho") -> Alto a lo ancho
A11: 70 kg | B11: Rodante | C11: 680 | D11: 1212 | E11: 4.75 | F11: LAC | G11: =C11*D11*E11*Supuestos!$B$10/1000000 -> 30.809161 | H11: 1500 | I11: 3000 | J11: =INT(H11/C11)*INT(I11/D11) -> 4 | K11: =INT(H11/D11)*INT(I11/C11) -> 4 | L11: =MAX(J11,K11) -> 4 | M11: =L11*C11*D11/(H11*I11) -> 0.73258667 | N11: =H11*I11*E11*Supuestos!$B$10/1000000 -> 168.22125 | O11: =IF(J11>=K11,INT(H11/C11)*(1+INT(I11/D11)),INT(H11/D11)*(1+INT(I11/C11))) -> 6 | P11: 1245 | Q11: =INT((P11-Supuestos!$B$11)/C11) -> 1 | R11: =Q11*C11/P11 -> 0.54618474 | S11: =INT((P11-Supuestos!$B$11)/D11) -> 1 | T11: =S11*D11/P11 -> 0.97349398 | U11: =IF(R11>=T11,Q11,S11) -> 1 | V11: =IF(R11>=T11,D11,C11) -> 680 | W11: =MAX(R11,T11)*(1-Supuestos!$B$12) -> 0.96862651 | X11: =IF(R11>=T11,"Alto a lo ancho","Perímetro a lo ancho") -> Perímetro a lo ancho
A12: 100 kg | B12: Rodante | C12: 900 | D12: 1212 | E12: 4.75 | F12: LAC | G12: =C12*D12*E12*Supuestos!$B$10/1000000 -> 40.776831 | H12: 1500 | I12: 3000 | J12: =INT(H12/C12)*INT(I12/D12) -> 2 | K12: =INT(H12/D12)*INT(I12/C12) -> 3 | L12: =MAX(J12,K12) -> 3 | M12: =L12*C12*D12/(H12*I12) -> 0.7272 | N12: =H12*I12*E12*Supuestos!$B$10/1000000 -> 168.22125 | O12: =IF(J12>=K12,INT(H12/C12)*(1+INT(I12/D12)),INT(H12/D12)*(1+INT(I12/C12))) -> 4 | P12: 1245 | Q12: =INT((P12-Supuestos!$B$11)/C12) -> 1 | R12: =Q12*C12/P12 -> 0.72289157 | S12: =INT((P12-Supuestos!$B$11)/D12) -> 1 | T12: =S12*D12/P12 -> 0.97349398 | U12: =IF(R12>=T12,Q12,S12) -> 1 | V12: =IF(R12>=T12,D12,C12) -> 900 | W12: =MAX(R12,T12)*(1-Supuestos!$B$12) -> 0.96862651 | X12: =IF(R12>=T12,"Alto a lo ancho","Perímetro a lo ancho") -> Perímetro a lo ancho
A14: Mezcla de 70 y 100 kg en la misma hoja (usa el formato de hoja del 70 kg)
A15: Cuerpos de 100 kg por hoja mixta | G15: 1
A16: Cuerpos de 70 kg por hoja mixta | G16: 3
A17: Largo ocupado (mm) | G17: =G15*C12+G16*C11 -> 2940
A18: ¿Entra? (perímetros a lo ancho, altos a lo largo, mismo espesor) | G18: =IF(AND(D11<=H11,D12<=H11,G17<=I11,E11=E12),"SI","NO") -> SI
A19: Aprovechamiento hoja mixta | G19: =(G15*C12*D12+G16*C11*D11)/(H11*I11) -> 0.79184
A20: Masa hoja mixta (kg) | G20: =N11 -> 168.22125
A21: Cortes por hoja mixta | G21: =1+G15+G16 -> 5
A22: Mezcla activa en el cálculo | G22: =IF(AND(Supuestos!$B$14="SI",G18="SI"),"SI","NO") -> SI
A24: B) CÚPULAS Y FONDOS (discos de manuales) | J24: Hoja estándar → tiras en guillotina → balancín (opción B)
A25: Formato | B25: Pieza | C25: Diámetro del disco (mm) | D25: Espesor (mm) | E25: Acero | F25: Masa del disco (kg) | G25: Ancho de fleje = D+2s (mm) | H25: Paso = D+s (mm) | I25: Aprovech. fleje (1 fila) | J25: HOJA ancho (mm) | K25: HOJA largo (mm) | L25: Tiras orient. 1 | M25: Discos/tira o.1 | N25: Piezas o.1 | O25: Tiras orient. 2 | P25: Discos/tira o.2 | Q25: Piezas o.2 | R25: Discos por hoja | S25: Aprovech. hoja | T25: Masa hoja (kg) | U25: Tiras por hoja | V25: Discos por tira | W25: FLEJE COMPRADO: ancho (mm) | X25: Aprovech. fleje comprado | Y25: Nota
A26: 1 kg | B26: Cúpula | C26: 108 | D26: 0.9 | E26: LAF | F26: =PI()*C26^2/4*D26*Supuestos!$B$10/1000000 -> 0.064886543 | G26: =C26+2*Supuestos!$B$13 -> 114 | H26: =C26+Supuestos!$B$13 -> 111 | I26: =PI()*C26^2/4/(G26*H26)*(1-Supuestos!$B$12) -> 0.72033189 | J26: 1220 | K26: 2440 | L26: =INT(J26/G26) -> 10 | M26: =INT((K26-Supuestos!$B$13)/H26) -> 21 | N26: =L26*M26 -> 210 | O26: =INT(K26/G26) -> 21 | P26: =INT((J26-Supuestos!$B$13)/H26) -> 10 | Q26: =O26*P26 -> 210 | R26: =MAX(N26,Q26) -> 210 | S26: =R26*PI()*C26^2/4/(J26*K26) -> 0.64625963 | T26: =J26*K26*D26*Supuestos!$B$10/1000000 -> 21.084674 | U26: =IF(N26>=Q26,L26,O26) -> 10 | V26: =IF(N26>=Q26,M26,P26) -> 21 | W26: 114 | X26: =IF(W26<C26,0,PI()*C26^2/4/(W26*H26)*(1-Supuestos!$B$12)) -> 0.72033189 | Y26: ESTIMADO: deducido de la masa de pieza del registro (0,0461 kg) / 0,71 (relación pieza/disco de las otras cúpulas). Confirmar. Fleje: estimado D+2s (Pradecon corta a medida sin cargo).
A27: 1 kg | B27: Fondo | C27: 100 | D27: 0.9 | E27: LAF | F27: =PI()*C27^2/4*D27*Supuestos!$B$10/1000000 -> 0.055629752 | G27: =C27+2*Supuestos!$B$13 -> 106 | H27: =C27+Supuestos!$B$13 -> 103 | I27: =PI()*C27^2/4/(G27*H27)*(1-Supuestos!$B$12) -> 0.71576403 | J27: 1000 | K27: 2000 | L27: =INT(J27/G27) -> 9 | M27: =INT((K27-Supuestos!$B$13)/H27) -> 19 | N27: =L27*M27 -> 171 | O27: =INT(K27/G27) -> 18 | P27: =INT((J27-Supuestos!$B$13)/H27) -> 9 | Q27: =O27*P27 -> 162 | R27: =MAX(N27,Q27) -> 171 | S27: =R27*PI()*C27^2/4/(J27*K27) -> 0.67151543 | T27: =J27*K27*D27*Supuestos!$B$10/1000000 -> 14.166 | U27: =IF(N27>=Q27,L27,O27) -> 9 | V27: =IF(N27>=Q27,M27,P27) -> 19 | W27: 106 | X27: =IF(W27<C27,0,PI()*C27^2/4/(W27*H27)*(1-Supuestos!$B$12)) -> 0.71576403 | Y27: ESTIMADO: deducido de la masa de pieza (0,0497 kg) / 0,90 (relación de los otros fondos). Confirmar. Fleje: estimado D+2s (Pradecon corta a medida sin cargo).
A28: 2,5 kg | B28: Cúpula | C28: 179 | D28: 1.25 | E28: LAF | F28: =PI()*C28^2/4*D28*Supuestos!$B$10/1000000 -> 0.24756012 | G28: =C28+2*Supuestos!$B$13 -> 185 | H28: =C28+Supuestos!$B$13 -> 182 | I28: =PI()*C28^2/4/(G28*H28)*(1-Supuestos!$B$12) -> 0.74366254 | J28: 1220 | K28: 2440 | L28: =INT(J28/G28) -> 6 | M28: =INT((K28-Supuestos!$B$13)/H28) -> 13 | N28: =L28*M28 -> 78 | O28: =INT(K28/G28) -> 13 | P28: =INT((J28-Supuestos!$B$13)/H28) -> 6 | Q28: =O28*P28 -> 78 | R28: =MAX(N28,Q28) -> 78 | S28: =R28*PI()*C28^2/4/(J28*K28) -> 0.65938777 | T28: =J28*K28*D28*Supuestos!$B$10/1000000 -> 29.28427 | U28: =IF(N28>=Q28,L28,O28) -> 6 | V28: =IF(N28>=Q28,M28,P28) -> 13 | W28: 200 | X28: =IF(W28<C28,0,PI()*C28^2/4/(W28*H28)*(1-Supuestos!$B$12)) -> 0.68788785 | Y28: Planilla 'Dimensiones de chapa'. Fleje: Pacheco Chapas.
A29: 2,5 kg | B29: Fondo | C29: 148 | D29: 1.25 | E29: LAF | F29: =PI()*C29^2/4*D29*Supuestos!$B$10/1000000 -> 0.16923807 | G29: =C29+2*Supuestos!$B$13 -> 154 | H29: =C29+Supuestos!$B$13 -> 151 | I29: =PI()*C29^2/4/(G29*H29)*(1-Supuestos!$B$12) -> 0.73610323 | J29: 1220 | K29: 2440 | L29: =INT(J29/G29) -> 7 | M29: =INT((K29-Supuestos!$B$13)/H29) -> 16 | N29: =L29*M29 -> 112 | O29: =INT(K29/G29) -> 15 | P29: =INT((J29-Supuestos!$B$13)/H29) -> 8 | Q29: =O29*P29 -> 120 | R29: =MAX(N29,Q29) -> 120 | S29: =R29*PI()*C29^2/4/(J29*K29) -> 0.6934975 | T29: =J29*K29*D29*Supuestos!$B$10/1000000 -> 29.28427 | U29: =IF(N29>=Q29,L29,O29) -> 15 | V29: =IF(N29>=Q29,M29,P29) -> 8 | W29: 200 | X29: =IF(W29<C29,0,PI()*C29^2/4/(W29*H29)*(1-Supuestos!$B$12)) -> 0.56679949 | Y29: Planilla 'Dimensiones de chapa'. Fleje: Pacheco Chapas.
A30: 5 kg | B30: Cúpula | C30: 221 | D30: 1.6 | E30: LAF | F30: =PI()*C30^2/4*D30*Supuestos!$B$10/1000000 -> 0.48302448 | G30: =C30+2*Supuestos!$B$13 -> 227 | H30: =C30+Supuestos!$B$13 -> 224 | I30: =PI()*C30^2/4/(G30*H30)*(1-Supuestos!$B$12) -> 0.75062605 | J30: 1220 | K30: 2440 | L30: =INT(J30/G30) -> 5 | M30: =INT((K30-Supuestos!$B$13)/H30) -> 10 | N30: =L30*M30 -> 50 | O30: =INT(K30/G30) -> 10 | P30: =INT((J30-Supuestos!$B$13)/H30) -> 5 | Q30: =O30*P30 -> 50 | R30: =MAX(N30,Q30) -> 50 | S30: =R30*PI()*C30^2/4/(J30*K30) -> 0.64430986 | T30: =J30*K30*D30*Supuestos!$B$10/1000000 -> 37.483866 | U30: =IF(N30>=Q30,L30,O30) -> 5 | V30: =IF(N30>=Q30,M30,P30) -> 10 | W30: 250 | X30: =IF(W30<C30,0,PI()*C30^2/4/(W30*H30)*(1-Supuestos!$B$12)) -> 0.68156846 | Y30: Planilla 'Dimensiones de chapa'. Fleje: Pacheco Chapas.
A31: 5 kg | B31: Fondo | C31: 177 | D31: 1.6 | E31: LAF | F31: =PI()*C31^2/4*D31*Supuestos!$B$10/1000000 -> 0.30983547 | G31: =C31+2*Supuestos!$B$13 -> 183 | H31: =C31+Supuestos!$B$13 -> 180 | I31: =PI()*C31^2/4/(G31*H31)*(1-Supuestos!$B$12) -> 0.74325168 | J31: 1000 | K31: 2000 | L31: =INT(J31/G31) -> 5 | M31: =INT((K31-Supuestos!$B$13)/H31) -> 11 | N31: =L31*M31 -> 55 | O31: =INT(K31/G31) -> 10 | P31: =INT((J31-Supuestos!$B$13)/H31) -> 5 | Q31: =O31*P31 -> 50 | R31: =MAX(N31,Q31) -> 55 | S31: =R31*PI()*C31^2/4/(J31*K31) -> 0.67665782 | T31: =J31*K31*D31*Supuestos!$B$10/1000000 -> 25.184 | U31: =IF(N31>=Q31,L31,O31) -> 5 | V31: =IF(N31>=Q31,M31,P31) -> 11 | W31: 200 | X31: =IF(W31<C31,0,PI()*C31^2/4/(W31*H31)*(1-Supuestos!$B$12)) -> 0.68007529 | Y31: Planilla 'Dimensiones de chapa'. Fleje: Pacheco Chapas.
A32: 10 kg | B32: Cúpula | C32: 258 | D32: 2 | E32: LAF | F32: =PI()*C32^2/4*D32*Supuestos!$B$10/1000000 -> 0.82287529 | G32: =C32+2*Supuestos!$B$13 -> 264 | H32: =C32+Supuestos!$B$13 -> 261 | I32: =PI()*C32^2/4/(G32*H32)*(1-Supuestos!$B$12) -> 0.75493218 | J32: 1500 | K32: 3000 | L32: =INT(J32/G32) -> 5 | M32: =INT((K32-Supuestos!$B$13)/H32) -> 11 | N32: =L32*M32 -> 55 | O32: =INT(K32/G32) -> 11 | P32: =INT((J32-Supuestos!$B$13)/H32) -> 5 | Q32: =O32*P32 -> 55 | R32: =MAX(N32,Q32) -> 55 | S32: =R32*PI()*C32^2/4/(J32*K32) -> 0.63896853 | T32: =J32*K32*D32*Supuestos!$B$10/1000000 -> 70.83 | U32: =IF(N32>=Q32,L32,O32) -> 5 | V32: =IF(N32>=Q32,M32,P32) -> 11 | W32: 300 | X32: =IF(W32<C32,0,PI()*C32^2/4/(W32*H32)*(1-Supuestos!$B$12)) -> 0.66434032 | Y32: Registro de referencia (FADESA) usa 1,6 mm en la cúpula del 10 kg; se toma 2,0 mm según tabla FLAMA. Editable. Fleje: Pacheco Chapas.
A33: 10 kg | B33: Fondo | C33: 205 | D33: 2 | E33: LAF | F33: =PI()*C33^2/4*D33*Supuestos!$B$10/1000000 -> 0.51952007 | G33: =C33+2*Supuestos!$B$13 -> 211 | H33: =C33+Supuestos!$B$13 -> 208 | I33: =PI()*C33^2/4/(G33*H33)*(1-Supuestos!$B$12) -> 0.74829853 | J33: 1500 | K33: 3000 | L33: =INT(J33/G33) -> 7 | M33: =INT((K33-Supuestos!$B$13)/H33) -> 14 | N33: =L33*M33 -> 98 | O33: =INT(K33/G33) -> 14 | P33: =INT((J33-Supuestos!$B$13)/H33) -> 7 | Q33: =O33*P33 -> 98 | R33: =MAX(N33,Q33) -> 98 | S33: =R33*PI()*C33^2/4/(J33*K33) -> 0.71880513 | T33: =J33*K33*D33*Supuestos!$B$10/1000000 -> 70.83 | U33: =IF(N33>=Q33,L33,O33) -> 7 | V33: =IF(N33>=Q33,M33,P33) -> 14 | W33: 249 | X33: =IF(W33<C33,0,PI()*C33^2/4/(W33*H33)*(1-Supuestos!$B$12)) -> 0.63410036 | Y33: Tabla FLAMA ('Dimensiones de chapa'). Fleje: Pacheco Chapas.
A35: Ancho de fleje D+2s (columna G) = el que cortan ustedes (opciones B y C). Ancho comprado (columna W) = el cotizado a Pacheco para A, D y referencia; si es más ancho que D+2s, baja el aprovechamiento. Los discos se cortan en una fila por fleje (troquel simple). Un troquel de 2 filas escalonadas mejora el aprovechamiento ~8–10 puntos; queda como mejora futura.

Sheet BobinaMadre
A1: Opción C — Bobina madre de ancho estándar + corte longitudinal propio
A2: Se compra una bobina ancha por espesor y se corta en flejes: de cuerpo (van a la línea de corte transversal) y de disco (van al balancín).
A3: Patrones y participaciones optimizados por programación lineal sobre la demanda 2026–2035 (mínimo acero comprado). Editables: ancho de madre, orientación, tiras por patrón y % de cada patrón.
A5: Grupo 0,9 mm
A6: Ancho de bobina madre (mm) | B6: 1220 | C6: Espesor (mm) | D6: =Nesting!$D$26 -> 0.9 | E6: Acero | F6: =Nesting!$E$26 -> LAF | G6: kg por metro de madre | H6: =B6*D6*Supuestos!$B$10/1000 -> 8.64126
A7: Tira (fleje) | B7: Orientación (1 = alto a lo ancho, 2 = perímetro a lo ancho) | C7: Ancho de tira (mm) | D7: Avance por unidad (mm) | E7: Patrón 1 (tiras) | F7: Patrón 2 (tiras) | G7: Patrón 3 (tiras) | H7: Tiras por metro de madre (ponderado)
A8: Cúpula 1 kg | B8: — | C8: =Nesting!$G$26 -> 114 | D8: =Nesting!$H$26 -> 111 | E8: 5 | F8: 10 | G8: 0 | H8: =E8*$E$10+F8*$F$10+G8*$G$10 -> 5.6395
A9: Fondo 1 kg | B9: — | C9: =Nesting!$G$27 -> 106 | D9: =Nesting!$H$27 -> 103 | E9: 6 | F9: 0 | G9: 0 | H9: =E9*$E$10+F9*$F$10+G9*$G$10 -> 5.2326
A10: Participación de cada patrón (% de los metros de madre) | E10: 0.8721 | F10: 0.1279 | G10: 0 | H10: =IF(ABS(SUM(E10:G10)-1)<0.001,"Suma 100% OK","REVISAR: no suma 100%") -> Suma 100% OK
A11: Ancho usado por patrón (mm) | E11: =SUMPRODUCT($C$8:$C$9,E8:E9) -> 1206 | F11: =SUMPRODUCT($C$8:$C$9,F8:F9) -> 1140 | G11: =SUMPRODUCT($C$8:$C$9,G8:G9) -> 0
A12: Orilla (scrap de borde) por patrón (mm) | E12: =IF(E11=0,0,$B$6-E11) -> 14 | F12: =IF(F11=0,0,$B$6-F11) -> 80 | G12: =IF(G11=0,0,$B$6-G11) -> 0
A13: ¿Entra en la madre? (orilla ≥ margen) | E13: =IF(E11=0,"sin uso",IF($B$6-E11>=Supuestos!$B$11,"OK","NO ENTRA")) -> OK | F13: =IF(F11=0,"sin uso",IF($B$6-F11>=Supuestos!$B$11,"OK","NO ENTRA")) -> OK | G13: =IF(G11=0,"sin uso",IF($B$6-G11>=Supuestos!$B$11,"OK","NO ENTRA")) -> sin uso
A15: Cálculo anual | D15: 2026 | E15: 2027 | F15: 2028 | G15: 2029 | H15: 2030 | I15: 2031 | J15: 2032 | K15: 2033 | L15: 2034 | M15: 2035
A16: Metros necesarios: Cúpula 1 kg | D16: =Calculo!D8*$D$8/1000 -> 463.869 | E16: =Calculo!E8*$D$8/1000 -> 665.667 | F16: =Calculo!F8*$D$8/1000 -> 1611.054 | G16: =Calculo!G8*$D$8/1000 -> 3902.982 | H16: =Calculo!H8*$D$8/1000 -> 6894.876 | I16: =Calculo!I8*$D$8/1000 -> 9690.3 | J16: =Calculo!J8*$D$8/1000 -> 13505.814 | K16: =Calculo!K8*$D$8/1000 -> 17330.763 | ... M16: =Calculo!M8*$D$8/1000 -> 22490.931
A17: Metros necesarios: Fondo 1 kg | D17: =Calculo!D8*$D$9/1000 -> 430.437 | E17: =Calculo!E8*$D$9/1000 -> 617.691 | F17: =Calculo!F8*$D$9/1000 -> 1494.942 | G17: =Calculo!G8*$D$9/1000 -> 3621.686 | H17: =Calculo!H8*$D$9/1000 -> 6397.948 | I17: =Calculo!I8*$D$9/1000 -> 8991.9 | J17: =Calculo!J8*$D$9/1000 -> 12532.422 | K17: =Calculo!K8*$D$9/1000 -> 16081.699 | ... M17: =Calculo!M8*$D$9/1000 -> 20869.963
A18: Metros de bobina madre a cortar | D18: =MAX(IF($H$8=0,IF(D16>0,1000000000000,0),D16/$H$8),IF($H$9=0,IF(D17>0,1000000000000,0),D17/$H$9)) -> 82.260635 | E18: =MAX(IF($H$8=0,IF(E16>0,1000000000000,0),E16/$H$8),IF($H$9=0,IF(E17>0,1000000000000,0),E17/$H$9)) -> 118.04667 | F18: =MAX(IF($H$8=0,IF(F16>0,1000000000000,0),F16/$H$8),IF($H$9=0,IF(F17>0,1000000000000,0),F17/$H$9)) -> 285.69774 | G18: =MAX(IF($H$8=0,IF(G16>0,1000000000000,0),G16/$H$8),IF($H$9=0,IF(G17>0,1000000000000,0),G17/$H$9)) -> 692.1389 | H18: =MAX(IF($H$8=0,IF(H16>0,1000000000000,0),H16/$H$8),IF($H$9=0,IF(H17>0,1000000000000,0),H17/$H$9)) -> 1222.7092 | I18: =MAX(IF($H$8=0,IF(I16>0,1000000000000,0),I16/$H$8),IF($H$9=0,IF(I17>0,1000000000000,0),I17/$H$9)) -> 1718.4383 | J18: =MAX(IF($H$8=0,IF(J16>0,1000000000000,0),J16/$H$8),IF($H$9=0,IF(J17>0,1000000000000,0),J17/$H$9)) -> 2395.0659 | K18: =MAX(IF($H$8=0,IF(K16>0,1000000000000,0),K16/$H$8),IF($H$9=0,IF(K17>0,1000000000000,0),K17/$H$9)) -> 3073.3668 | ... M18: =MAX(IF($H$8=0,IF(M16>0,1000000000000,0),M16/$H$8),IF($H$9=0,IF(M17>0,1000000000000,0),M17/$H$9)) -> 3988.4499
A19: Acero de madre comprado (t) | D19: =D18*$H$6/1000/(1-Supuestos!$B$12) -> 0.71440757 | E19: =E18*$H$6/1000/(1-Supuestos!$B$12) -> 1.0251979 | F19: =F18*$H$6/1000/(1-Supuestos!$B$12) -> 2.4811944 | G19: =G18*$H$6/1000/(1-Supuestos!$B$12) -> 6.0110072 | H19: =H18*$H$6/1000/(1-Supuestos!$B$12) -> 10.618842 | I19: =I18*$H$6/1000/(1-Supuestos!$B$12) -> 14.924092 | J19: =J18*$H$6/1000/(1-Supuestos!$B$12) -> 20.800389 | K19: =K18*$H$6/1000/(1-Supuestos!$B$12) -> 26.691217 | ... M19: =M18*$H$6/1000/(1-Supuestos!$B$12) -> 34.638425
A20: Acero neto en piezas del grupo (t) | D20: =Calculo!D31+Calculo!D32 -> 0.50363759 | E20: =Calculo!E31+Calculo!E32 -> 0.72273622 | F20: =Calculo!F31+Calculo!F32 -> 1.7491735 | G20: =Calculo!G31+Calculo!G32 -> 4.2375939 | H20: =Calculo!H31+Calculo!H32 -> 7.4859902 | I20: =Calculo!I31+Calculo!I32 -> 10.521073 | J20: =Calculo!J31+Calculo!J32 -> 14.6637 | K20: =Calculo!K31+Calculo!K32 -> 18.816571 | ... M20: =Calculo!M31+Calculo!M32 -> 24.419132
A21: Aprovechamiento del grupo | D21: =IF(D19=0,0,D20/D19) -> 0.70497236 | E21: =IF(E19=0,0,E20/E19) -> 0.70497236 | F21: =IF(F19=0,0,F20/F19) -> 0.70497236 | G21: =IF(G19=0,0,G20/G19) -> 0.70497236 | H21: =IF(H19=0,0,H20/H19) -> 0.70497236 | I21: =IF(I19=0,0,I20/I19) -> 0.70497236 | J21: =IF(J19=0,0,J20/J19) -> 0.70497236 | K21: =IF(K19=0,0,K20/K19) -> 0.70497236 | ... M21: =IF(M19=0,0,M20/M19) -> 0.70497236
A22: Bobinas madre por año | D22: =IF(Bobinas!$K$24=0,0,D19/Bobinas!$K$24) -> 0.23813586 | E22: =IF(Bobinas!$K$24=0,0,E19/Bobinas!$K$24) -> 0.34173265 | F22: =IF(Bobinas!$K$24=0,0,F19/Bobinas!$K$24) -> 0.82706481 | G22: =IF(Bobinas!$K$24=0,0,G19/Bobinas!$K$24) -> 2.0036691 | H22: =IF(Bobinas!$K$24=0,0,H19/Bobinas!$K$24) -> 3.539614 | I22: =IF(Bobinas!$K$24=0,0,I19/Bobinas!$K$24) -> 4.9746974 | J22: =IF(Bobinas!$K$24=0,0,J19/Bobinas!$K$24) -> 6.9334631 | K22: =IF(Bobinas!$K$24=0,0,K19/Bobinas!$K$24) -> 8.8970725 | ... M22: =IF(Bobinas!$K$24=0,0,M19/Bobinas!$K$24) -> 11.546142
A23: Flejes de disco generados por año | D23: =D22*($H$8+$H$9) -> 2.5890369 | E23: =E22*($H$8+$H$9) -> 3.7153515 | F23: =F22*($H$8+$H$9) -> 8.9919313 | G23: =G22*($H$8+$H$9) -> 21.784091 | H23: =H22*($H$8+$H$9) -> 38.483038 | I23: =I22*($H$8+$H$9) -> 54.085408 | J23: =J22*($H$8+$H$9) -> 75.381304 | K23: =K22*($H$8+$H$9) -> 96.729862 | ... M23: =M22*($H$8+$H$9) -> 125.53081
A24: Horas de corte longitudinal | D24: =D18/(Supuestos!$B$39*60)+D22*Supuestos!$B$40/60 -> 0.21287716 | E24: =E18/(Supuestos!$B$39*60)+E22*Supuestos!$B$40/60 -> 0.3054856 | F24: =F18/(Supuestos!$B$39*60)+F22*Supuestos!$B$40/60 -> 0.73933933 | G24: =G18/(Supuestos!$B$39*60)+G22*Supuestos!$B$40/60 -> 1.791143 | H24: =H18/(Supuestos!$B$39*60)+H22*Supuestos!$B$40/60 -> 3.1641727 | I24: =I18/(Supuestos!$B$39*60)+I22*Supuestos!$B$40/60 -> 4.447039 | J24: =J18/(Supuestos!$B$39*60)+J22*Supuestos!$B$40/60 -> 6.1980415 | K24: =K18/(Supuestos!$B$39*60)+K22*Supuestos!$B$40/60 -> 7.9533739 | ... M24: =M18/(Supuestos!$B$39*60)+M22*Supuestos!$B$40/60 -> 10.32146
A27: Grupo 1,25 mm
A28: Ancho de bobina madre (mm) | B28: 1000 | C28: Espesor (mm) | D28: =Nesting!$E$6 -> 1.25 | E28: Acero | F28: =Nesting!$F$6 -> LAF | G28: kg por metro de madre | H28: =B28*D28*Supuestos!$B$10/1000 -> 9.8375
A29: Tira (fleje) | B29: Orientación (1 = alto a lo ancho, 2 = perímetro a lo ancho) | C29: Ancho de tira (mm) | D29: Avance por unidad (mm) | E29: Patrón 1 (tiras) | F29: Patrón 2 (tiras) | G29: Patrón 3 (tiras) | H29: Tiras por metro de madre (ponderado)
A30: Cuerpo 2,5 kg | B30: 1 | C30: =IF(B30=1,Nesting!$C$6,Nesting!$D$6) -> 269.5 | D30: =IF(B30=1,Nesting!$D$6,Nesting!$C$6) -> 385.5 | E30: 1 | F30: 2 | G30: 3 | H30: =E30*$E$33+F30*$F$33+G30*$G$33 -> 2.3064
A31: Cúpula 2,5 kg | B31: — | C31: =Nesting!$G$28 -> 185 | D31: =Nesting!$H$28 -> 182 | E31: 3 | F31: 2 | G31: 0 | H31: =E31*$E$33+F31*$F$33+G31*$G$33 -> 1.0887
A32: Fondo 2,5 kg | B32: — | C32: =Nesting!$G$29 -> 154 | D32: =Nesting!$H$29 -> 151 | E32: 1 | F32: 0 | G32: 1 | H32: =E32*$E$33+F32*$F$33+G32*$G$33 -> 0.9034
A33: Participación de cada patrón (% de los metros de madre) | E33: 0.2985 | F33: 0.0966 | G33: 0.6049 | H33: =IF(ABS(SUM(E33:G33)-1)<0.001,"Suma 100% OK","REVISAR: no suma 100%") -> Suma 100% OK
A34: Ancho usado por patrón (mm) | E34: =SUMPRODUCT($C$30:$C$32,E30:E32) -> 978.5 | F34: =SUMPRODUCT($C$30:$C$32,F30:F32) -> 909 | G34: =SUMPRODUCT($C$30:$C$32,G30:G32) -> 962.5
A35: Orilla (scrap de borde) por patrón (mm) | E35: =IF(E34=0,0,$B$28-E34) -> 21.5 | F35: =IF(F34=0,0,$B$28-F34) -> 91 | G35: =IF(G34=0,0,$B$28-G34) -> 37.5
A36: ¿Entra en la madre? (orilla ≥ margen) | E36: =IF(E34=0,"sin uso",IF($B$28-E34>=Supuestos!$B$11,"OK","NO ENTRA")) -> OK | F36: =IF(F34=0,"sin uso",IF($B$28-F34>=Supuestos!$B$11,"OK","NO ENTRA")) -> OK | G36: =IF(G34=0,"sin uso",IF($B$28-G34>=Supuestos!$B$11,"OK","NO ENTRA")) -> OK
A38: Cálculo anual | D38: 2026 | E38: 2027 | F38: 2028 | G38: 2029 | H38: 2030 | I38: 2031 | J38: 2032 | K38: 2033 | L38: 2034 | M38: 2035
A39: Metros necesarios: Cuerpo 2,5 kg | D39: =Calculo!D9*$D$30/1000 -> 113.7225 | E39: =Calculo!E9*$D$30/1000 -> 273.3195 | F39: =Calculo!F9*$D$30/1000 -> 496.1385 | G39: =Calculo!G9*$D$30/1000 -> 981.0975 | H39: =Calculo!H9*$D$30/1000 -> 1636.4475 | I39: =Calculo!I9*$D$30/1000 -> 2334.2025 | J39: =Calculo!J9*$D$30/1000 -> 3109.443 | K39: =Calculo!K9*$D$30/1000 -> 3942.894 | ... M39: =Calculo!M9*$D$30/1000 -> 5433.237
A40: Metros necesarios: Cúpula 2,5 kg | D40: =Calculo!D9*$D$31/1000 -> 53.69 | E40: =Calculo!E9*$D$31/1000 -> 129.038 | F40: =Calculo!F9*$D$31/1000 -> 234.234 | G40: =Calculo!G9*$D$31/1000 -> 463.19 | H40: =Calculo!H9*$D$31/1000 -> 772.59 | I40: =Calculo!I9*$D$31/1000 -> 1102.01 | J40: =Calculo!J9*$D$31/1000 -> 1468.012 | K40: =Calculo!K9*$D$31/1000 -> 1861.496 | ... M40: =Calculo!M9*$D$31/1000 -> 2565.108
A41: Metros necesarios: Fondo 2,5 kg | D41: =Calculo!D9*$D$32/1000 -> 44.545 | E41: =Calculo!E9*$D$32/1000 -> 107.059 | F41: =Calculo!F9*$D$32/1000 -> 194.337 | G41: =Calculo!G9*$D$32/1000 -> 384.295 | H41: =Calculo!H9*$D$32/1000 -> 640.995 | I41: =Calculo!I9*$D$32/1000 -> 914.305 | J41: =Calculo!J9*$D$32/1000 -> 1217.966 | K41: =Calculo!K9*$D$32/1000 -> 1544.428 | ... M41: =Calculo!M9*$D$32/1000 -> 2128.194
A42: Metros de bobina madre a cortar | D42: =MAX(IF($H$30=0,IF(D39>0,1000000000000,0),D39/$H$30),IF($H$31=0,IF(D40>0,1000000000000,0),D40/$H$31),IF($H$32=0,IF(D41>0,1000000000000,0),D41/$H$32)) -> 49.315698 | E42: =MAX(IF($H$30=0,IF(E39>0,1000000000000,0),E39/$H$30),IF($H$31=0,IF(E40>0,1000000000000,0),E40/$H$31),IF($H$32=0,IF(E41>0,1000000000000,0),E41/$H$32)) -> 118.52485 | F42: =MAX(IF($H$30=0,IF(F39>0,1000000000000,0),F39/$H$30),IF($H$31=0,IF(F40>0,1000000000000,0),F40/$H$31),IF($H$32=0,IF(F41>0,1000000000000,0),F41/$H$32)) -> 215.15018 | G42: =MAX(IF($H$30=0,IF(G39>0,1000000000000,0),G39/$H$30),IF($H$31=0,IF(G40>0,1000000000000,0),G40/$H$31),IF($H$32=0,IF(G41>0,1000000000000,0),G41/$H$32)) -> 425.45237 | H42: =MAX(IF($H$30=0,IF(H39>0,1000000000000,0),H39/$H$30),IF($H$31=0,IF(H40>0,1000000000000,0),H40/$H$31),IF($H$32=0,IF(H41>0,1000000000000,0),H41/$H$32)) -> 709.64453 | I42: =MAX(IF($H$30=0,IF(I39>0,1000000000000,0),I39/$H$30),IF($H$31=0,IF(I40>0,1000000000000,0),I40/$H$31),IF($H$32=0,IF(I41>0,1000000000000,0),I41/$H$32)) -> 1012.2256 | J42: =MAX(IF($H$30=0,IF(J39>0,1000000000000,0),J39/$H$30),IF($H$31=0,IF(J40>0,1000000000000,0),J40/$H$31),IF($H$32=0,IF(J41>0,1000000000000,0),J41/$H$32)) -> 1348.4082 | K42: =MAX(IF($H$30=0,IF(K39>0,1000000000000,0),K39/$H$30),IF($H$31=0,IF(K40>0,1000000000000,0),K40/$H$31),IF($H$32=0,IF(K41>0,1000000000000,0),K41/$H$32)) -> 1709.8337 | ... M42: =MAX(IF($H$30=0,IF(M39>0,1000000000000,0),M39/$H$30),IF($H$31=0,IF(M40>0,1000000000000,0),M40/$H$31),IF($H$32=0,IF(M41>0,1000000000000,0),M41/$H$32)) -> 2356.1201
A43: Acero de madre comprado (t) | D43: =D42*$H$28/1000/(1-Supuestos!$B$12) -> 0.48758108 | E43: =E42*$H$28/1000/(1-Supuestos!$B$12) -> 1.1718474 | F43: =F42*$H$28/1000/(1-Supuestos!$B$12) -> 2.1271758 | G43: =G42*$H$28/1000/(1-Supuestos!$B$12) -> 4.2064198 | H43: =H42*$H$28/1000/(1-Supuestos!$B$12) -> 7.0162091 | I43: =I42*$H$28/1000/(1-Supuestos!$B$12) -> 10.007808 | J43: =J42*$H$28/1000/(1-Supuestos!$B$12) -> 13.331624 | K43: =K42*$H$28/1000/(1-Supuestos!$B$12) -> 16.905015 | ... M43: =M42*$H$28/1000/(1-Supuestos!$B$12) -> 23.294806
A44: Acero neto en piezas del grupo (t) | D44: =Calculo!D19+Calculo!D33+Calculo!D34 -> 0.42445727 | E44: =Calculo!E19+Calculo!E33+Calculo!E34 -> 1.0201363 | F44: =Calculo!F19+Calculo!F33+Calculo!F34 -> 1.8517848 | G44: =Calculo!G19+Calculo!G33+Calculo!G34 -> 3.6618432 | H44: =Calculo!H19+Calculo!H33+Calculo!H34 -> 6.1078682 | I44: =Calculo!I19+Calculo!I33+Calculo!I34 -> 8.7121653 | J44: =Calculo!J19+Calculo!J33+Calculo!J34 -> 11.605669 | K44: =Calculo!K19+Calculo!K33+Calculo!K34 -> 14.716437 | ... M44: =Calculo!M19+Calculo!M33+Calculo!M34 -> 20.278986
A45: Aprovechamiento del grupo | D45: =IF(D43=0,0,D44/D43) -> 0.87053679 | E45: =IF(E43=0,0,E44/E43) -> 0.87053679 | F45: =IF(F43=0,0,F44/F43) -> 0.87053679 | G45: =IF(G43=0,0,G44/G43) -> 0.87053679 | H45: =IF(H43=0,0,H44/H43) -> 0.87053679 | I45: =IF(I43=0,0,I44/I43) -> 0.87053679 | J45: =IF(J43=0,0,J44/J43) -> 0.87053679 | K45: =IF(K43=0,0,K44/K43) -> 0.87053679 | ... M45: =IF(M43=0,0,M44/M43) -> 0.87053679
A46: Bobinas madre por año | D46: =IF(Bobinas!$K$25=0,0,D43/Bobinas!$K$25) -> 0.24379054 | E46: =IF(Bobinas!$K$25=0,0,E43/Bobinas!$K$25) -> 0.58592371 | F46: =IF(Bobinas!$K$25=0,0,F43/Bobinas!$K$25) -> 1.0635879 | G46: =IF(Bobinas!$K$25=0,0,G43/Bobinas!$K$25) -> 2.1032099 | H46: =IF(Bobinas!$K$25=0,0,H43/Bobinas!$K$25) -> 3.5081046 | I46: =IF(Bobinas!$K$25=0,0,I43/Bobinas!$K$25) -> 5.0039041 | J46: =IF(Bobinas!$K$25=0,0,J43/Bobinas!$K$25) -> 6.6658119 | K46: =IF(Bobinas!$K$25=0,0,K43/Bobinas!$K$25) -> 8.4525073 | ... M46: =IF(Bobinas!$K$25=0,0,M43/Bobinas!$K$25) -> 11.647403
A47: Flejes de disco generados por año | D47: =D46*($H$31+$H$32) -> 0.48565514 | E47: =E46*($H$31+$H$32) -> 1.1672186 | F47: =F46*($H$31+$H$32) -> 2.1187734 | G47: =G46*($H$31+$H$32) -> 4.1898045 | H47: =H46*($H$31+$H$32) -> 6.9884951 | I47: =I46*($H$31+$H$32) -> 9.9682774 | J47: =J46*($H$31+$H$32) -> 13.278964 | K47: =K46*($H$31+$H$32) -> 16.83824 | ... M47: =M46*($H$31+$H$32) -> 23.202791
A48: Horas de corte longitudinal | D48: =D42/(Supuestos!$B$39*60)+D46*Supuestos!$B$40/60 -> 0.20339111 | E48: =E42/(Supuestos!$B$39*60)+E46*Supuestos!$B$40/60 -> 0.48882813 | F48: =F42/(Supuestos!$B$39*60)+F46*Supuestos!$B$40/60 -> 0.88733682 | G48: =G42/(Supuestos!$B$39*60)+G46*Supuestos!$B$40/60 -> 1.7546793 | H48: =H42/(Supuestos!$B$39*60)+H46*Supuestos!$B$40/60 -> 2.9267636 | I48: =I42/(Supuestos!$B$39*60)+I46*Supuestos!$B$40/60 -> 4.1746888 | J48: =J42/(Supuestos!$B$39*60)+J46*Supuestos!$B$40/60 -> 5.5611956 | K48: =K42/(Supuestos!$B$39*60)+K46*Supuestos!$B$40/60 -> 7.0518112 | ... M48: =M42/(Supuestos!$B$39*60)+M46*Supuestos!$B$40/60 -> 9.717269
A51: Grupo 1,6 mm
A52: Ancho de bobina madre (mm) | B52: 1000 | C52: Espesor (mm) | D52: =Nesting!$E$7 -> 1.6 | E52: Acero | F52: =Nesting!$F$7 -> LAF | G52: kg por metro de madre | H52: =B52*D52*Supuestos!$B$10/1000 -> 12.592
A53: Tira (fleje) | B53: Orientación (1 = alto a lo ancho, 2 = perímetro a lo ancho) | C53: Ancho de tira (mm) | D53: Avance por unidad (mm) | E53: Patrón 1 (tiras) | F53: Patrón 2 (tiras) | G53: Patrón 3 (tiras) | H53: Tiras por metro de madre (ponderado)
A54: Cuerpo 5 kg | B54: 1 | C54: =IF(B54=1,Nesting!$C$7,Nesting!$D$7) -> 330 | D54: =IF(B54=1,Nesting!$D$7,Nesting!$C$7) -> 474.5 | E54: 0 | F54: 1 | G54: 3 | H54: =E54*$E$57+F54*$F$57+G54*$G$57 -> 1.9306
A55: Cúpula 5 kg | B55: — | C55: =Nesting!$G$30 -> 227 | D55: =Nesting!$H$30 -> 224 | E55: 1 | F55: 2 | G55: 0 | H55: =E55*$E$57+F55*$F$57+G55*$G$57 -> 0.9114
A56: Fondo 5 kg | B56: — | C56: =Nesting!$G$31 -> 183 | D56: =Nesting!$H$31 -> 180 | E56: 4 | F56: 1 | G56: 0 | H56: =E56*$E$57+F56*$F$57+G56*$G$57 -> 0.7322
A57: Participación de cada patrón (% de los metros de madre) | E57: 0.079 | F57: 0.4162 | G57: 0.5048 | H57: =IF(ABS(SUM(E57:G57)-1)<0.001,"Suma 100% OK","REVISAR: no suma 100%") -> Suma 100% OK
A58: Ancho usado por patrón (mm) | E58: =SUMPRODUCT($C$54:$C$56,E54:E56) -> 959 | F58: =SUMPRODUCT($C$54:$C$56,F54:F56) -> 967 | G58: =SUMPRODUCT($C$54:$C$56,G54:G56) -> 990
A59: Orilla (scrap de borde) por patrón (mm) | E59: =IF(E58=0,0,$B$52-E58) -> 41 | F59: =IF(F58=0,0,$B$52-F58) -> 33 | G59: =IF(G58=0,0,$B$52-G58) -> 10
A60: ¿Entra en la madre? (orilla ≥ margen) | E60: =IF(E58=0,"sin uso",IF($B$52-E58>=Supuestos!$B$11,"OK","NO ENTRA")) -> OK | F60: =IF(F58=0,"sin uso",IF($B$52-F58>=Supuestos!$B$11,"OK","NO ENTRA")) -> OK | G60: =IF(G58=0,"sin uso",IF($B$52-G58>=Supuestos!$B$11,"OK","NO ENTRA")) -> OK
A62: Cálculo anual | D62: 2026 | E62: 2027 | F62: 2028 | G62: 2029 | H62: 2030 | I62: 2031 | J62: 2032 | K62: 2033 | L62: 2034 | M62: 2035
A63: Metros necesarios: Cuerpo 5 kg | D63: =Calculo!D10*$D$54/1000 -> 1070.472 | E63: =Calculo!E10*$D$54/1000 -> 1825.4015 | F63: =Calculo!F10*$D$54/1000 -> 3118.8885 | G63: =Calculo!G10*$D$54/1000 -> 5682.1375 | H63: =Calculo!H10*$D$54/1000 -> 9660.82 | I63: =Calculo!I10*$D$54/1000 -> 13494.78 | J63: =Calculo!J10*$D$54/1000 -> 18238.357 | K63: =Calculo!K10*$D$54/1000 -> 23084.899 | ... M63: =Calculo!M10*$D$54/1000 -> 30209.517
A64: Metros necesarios: Cúpula 5 kg | D64: =Calculo!D10*$D$55/1000 -> 505.344 | E64: =Calculo!E10*$D$55/1000 -> 861.728 | F64: =Calculo!F10*$D$55/1000 -> 1472.352 | G64: =Calculo!G10*$D$55/1000 -> 2682.4 | H64: =Calculo!H10*$D$55/1000 -> 4560.64 | I64: =Calculo!I10*$D$55/1000 -> 6370.56 | J64: =Calculo!J10*$D$55/1000 -> 8609.888 | K64: =Calculo!K10*$D$55/1000 -> 10897.824 | ... M64: =Calculo!M10*$D$55/1000 -> 14261.184
A65: Metros necesarios: Fondo 5 kg | D65: =Calculo!D10*$D$56/1000 -> 406.08 | E65: =Calculo!E10*$D$56/1000 -> 692.46 | F65: =Calculo!F10*$D$56/1000 -> 1183.14 | G65: =Calculo!G10*$D$56/1000 -> 2155.5 | H65: =Calculo!H10*$D$56/1000 -> 3664.8 | I65: =Calculo!I10*$D$56/1000 -> 5119.2 | J65: =Calculo!J10*$D$56/1000 -> 6918.66 | K65: =Calculo!K10*$D$56/1000 -> 8757.18 | ... M65: =Calculo!M10*$D$56/1000 -> 11459.88
A66: Metros de bobina madre a cortar | D66: =MAX(IF($H$54=0,IF(D63>0,1000000000000,0),D63/$H$54),IF($H$55=0,IF(D64>0,1000000000000,0),D64/$H$55),IF($H$56=0,IF(D65>0,1000000000000,0),D65/$H$56)) -> 554.60257 | E66: =MAX(IF($H$54=0,IF(E63>0,1000000000000,0),E63/$H$54),IF($H$55=0,IF(E64>0,1000000000000,0),E64/$H$55),IF($H$56=0,IF(E65>0,1000000000000,0),E65/$H$56)) -> 945.72521 | F66: =MAX(IF($H$54=0,IF(F63>0,1000000000000,0),F63/$H$54),IF($H$55=0,IF(F64>0,1000000000000,0),F64/$H$55),IF($H$56=0,IF(F65>0,1000000000000,0),F65/$H$56)) -> 1615.87 | G66: =MAX(IF($H$54=0,IF(G63>0,1000000000000,0),G63/$H$54),IF($H$55=0,IF(G64>0,1000000000000,0),G64/$H$55),IF($H$56=0,IF(G65>0,1000000000000,0),G65/$H$56)) -> 2943.8678 | H66: =MAX(IF($H$54=0,IF(H63>0,1000000000000,0),H63/$H$54),IF($H$55=0,IF(H64>0,1000000000000,0),H64/$H$55),IF($H$56=0,IF(H65>0,1000000000000,0),H65/$H$56)) -> 5005.1898 | I66: =MAX(IF($H$54=0,IF(I63>0,1000000000000,0),I63/$H$54),IF($H$55=0,IF(I64>0,1000000000000,0),I64/$H$55),IF($H$56=0,IF(I65>0,1000000000000,0),I65/$H$56)) -> 6991.5324 | J66: =MAX(IF($H$54=0,IF(J63>0,1000000000000,0),J63/$H$54),IF($H$55=0,IF(J64>0,1000000000000,0),J64/$H$55),IF($H$56=0,IF(J65>0,1000000000000,0),J65/$H$56)) -> 9449.1396 | K66: =MAX(IF($H$54=0,IF(K63>0,1000000000000,0),K63/$H$54),IF($H$55=0,IF(K64>0,1000000000000,0),K64/$H$55),IF($H$56=0,IF(K65>0,1000000000000,0),K65/$H$56)) -> 11960.093 | ... M66: =MAX(IF($H$54=0,IF(M63>0,1000000000000,0),M63/$H$54),IF($H$55=0,IF(M64>0,1000000000000,0),M64/$H$55),IF($H$56=0,IF(M65>0,1000000000000,0),M65/$H$56)) -> 15651.297
A67: Acero de madre comprado (t) | D67: =D66*$H$52/1000/(1-Supuestos!$B$12) -> 7.0186488 | E67: =E66*$H$52/1000/(1-Supuestos!$B$12) -> 11.968414 | F67: =F66*$H$52/1000/(1-Supuestos!$B$12) -> 20.449281 | G67: =G66*$H$52/1000/(1-Supuestos!$B$12) -> 37.255461 | H67: =H66*$H$52/1000/(1-Supuestos!$B$12) -> 63.342061 | I67: =I66*$H$52/1000/(1-Supuestos!$B$12) -> 88.479774 | J67: =J66*$H$52/1000/(1-Supuestos!$B$12) -> 119.58147 | K67: =K66*$H$52/1000/(1-Supuestos!$B$12) -> 151.35828 | ... M67: =M66*$H$52/1000/(1-Supuestos!$B$12) -> 198.0715
A68: Acero neto en piezas del grupo (t) | D68: =Calculo!D20+Calculo!D35+Calculo!D36 -> 6.2368886 | E68: =Calculo!E20+Calculo!E35+Calculo!E36 -> 10.635333 | F68: =Calculo!F20+Calculo!F35+Calculo!F36 -> 18.171573 | G68: =Calculo!G20+Calculo!G35+Calculo!G36 -> 33.105825 | H68: =Calculo!H20+Calculo!H35+Calculo!H36 -> 56.286814 | I68: =Calculo!I20+Calculo!I35+Calculo!I36 -> 78.624606 | J68: =Calculo!J20+Calculo!J35+Calculo!J36 -> 106.26209 | K68: =Calculo!K20+Calculo!K35+Calculo!K36 -> 134.4995 | ... M68: =Calculo!M20+Calculo!M35+Calculo!M36 -> 176.00964
A69: Aprovechamiento del grupo | D69: =IF(D67=0,0,D68/D67) -> 0.88861671 | E69: =IF(E67=0,0,E68/E67) -> 0.88861671 | F69: =IF(F67=0,0,F68/F67) -> 0.88861671 | G69: =IF(G67=0,0,G68/G67) -> 0.88861671 | H69: =IF(H67=0,0,H68/H67) -> 0.88861671 | I69: =IF(I67=0,0,I68/I67) -> 0.88861671 | J69: =IF(J67=0,0,J68/J67) -> 0.88861671 | K69: =IF(K67=0,0,K68/K67) -> 0.88861671 | ... M69: =IF(M67=0,0,M68/M67) -> 0.88861671
A70: Bobinas madre por año | D70: =IF(Bobinas!$K$26=0,0,D67/Bobinas!$K$26) -> 0.5848874 | E70: =IF(Bobinas!$K$26=0,0,E67/Bobinas!$K$26) -> 0.99736783 | F70: =IF(Bobinas!$K$26=0,0,F67/Bobinas!$K$26) -> 1.7041068 | G70: =IF(Bobinas!$K$26=0,0,G67/Bobinas!$K$26) -> 3.1046217 | H70: =IF(Bobinas!$K$26=0,0,H67/Bobinas!$K$26) -> 5.2785051 | I70: =IF(Bobinas!$K$26=0,0,I67/Bobinas!$K$26) -> 7.3733145 | J70: =IF(Bobinas!$K$26=0,0,J67/Bobinas!$K$26) -> 9.9651227 | K70: =IF(Bobinas!$K$26=0,0,K67/Bobinas!$K$26) -> 12.61319 | ... M70: =IF(Bobinas!$K$26=0,0,M67/Bobinas!$K$26) -> 16.505958
A71: Flejes de disco generados por año | D71: =D70*($H$55+$H$56) -> 0.96132093 | E71: =E70*($H$55+$H$56) -> 1.6392738 | F71: =F70*($H$55+$H$56) -> 2.8008699 | G71: =G70*($H$55+$H$56) -> 5.1027563 | H71: =H70*($H$55+$H$56) -> 8.6757509 | I71: =I70*($H$55+$H$56) -> 12.11878 | J71: =J70*($H$55+$H$56) -> 16.378676 | K71: =K70*($H$55+$H$56) -> 20.731039 | ... M71: =M70*($H$55+$H$56) -> 27.129192
A72: Horas de corte longitudinal | D72: =D66/(Supuestos!$B$39*60)+D70*Supuestos!$B$40/60 -> 0.66974995 | E72: =E66/(Supuestos!$B$39*60)+E70*Supuestos!$B$40/60 -> 1.142078 | F72: =F66/(Supuestos!$B$39*60)+F70*Supuestos!$B$40/60 -> 1.9513592 | G72: =G66/(Supuestos!$B$39*60)+G70*Supuestos!$B$40/60 -> 3.5550779 | H72: =H66/(Supuestos!$B$39*60)+H70*Supuestos!$B$40/60 -> 6.0443746 | I72: =I66/(Supuestos!$B$39*60)+I70*Supuestos!$B$40/60 -> 8.4431244 | J72: =J66/(Supuestos!$B$39*60)+J70*Supuestos!$B$40/60 -> 11.410984 | K72: =K66/(Supuestos!$B$39*60)+K70*Supuestos!$B$40/60 -> 14.443265 | ... M72: =M66/(Supuestos!$B$39*60)+M70*Supuestos!$B$40/60 -> 18.900842
A75: Grupo 2,0 mm
A76: Ancho de bobina madre (mm) | B76: 1000 | C76: Espesor (mm) | D76: =Nesting!$E$8 -> 2 | E76: Acero | F76: =Nesting!$F$8 -> LAF | G76: kg por metro de madre | H76: =B76*D76*Supuestos!$B$10/1000 -> 15.74
A77: Tira (fleje) | B77: Orientación (1 = alto a lo ancho, 2 = perímetro a lo ancho) | C77: Ancho de tira (mm) | D77: Avance por unidad (mm) | E77: Patrón 1 (tiras) | F77: Patrón 2 (tiras) | G77: Patrón 3 (tiras) | H77: Tiras por metro de madre (ponderado)
A78: Cuerpo 10 kg | B78: 1 | C78: =IF(B78=1,Nesting!$C$8,Nesting!$D$8) -> 495 | D78: =IF(B78=1,Nesting!$D$8,Nesting!$C$8) -> 563 | E78: 0 | F78: 0 | G78: 2 | H78: =E78*$E$81+F78*$F$81+G78*$G$81 -> 1.3964
A79: Cúpula 10 kg | B79: — | C79: =Nesting!$G$32 -> 264 | D79: =Nesting!$H$32 -> 261 | E79: 2 | F79: 3 | G79: 0 | H79: =E79*$E$81+F79*$F$81+G79*$G$81 -> 0.6474
A80: Fondo 10 kg | B80: — | C80: =Nesting!$G$33 -> 211 | D80: =Nesting!$H$33 -> 208 | E80: 2 | F80: 0 | G80: 0 | H80: =E80*$E$81+F80*$F$81+G80*$G$81 -> 0.516
A81: Participación de cada patrón (% de los metros de madre) | E81: 0.258 | F81: 0.0438 | G81: 0.6982 | H81: =IF(ABS(SUM(E81:G81)-1)<0.001,"Suma 100% OK","REVISAR: no suma 100%") -> Suma 100% OK
A82: Ancho usado por patrón (mm) | E82: =SUMPRODUCT($C$78:$C$80,E78:E80) -> 950 | F82: =SUMPRODUCT($C$78:$C$80,F78:F80) -> 792 | G82: =SUMPRODUCT($C$78:$C$80,G78:G80) -> 990
A83: Orilla (scrap de borde) por patrón (mm) | E83: =IF(E82=0,0,$B$76-E82) -> 50 | F83: =IF(F82=0,0,$B$76-F82) -> 208 | G83: =IF(G82=0,0,$B$76-G82) -> 10
A84: ¿Entra en la madre? (orilla ≥ margen) | E84: =IF(E82=0,"sin uso",IF($B$76-E82>=Supuestos!$B$11,"OK","NO ENTRA")) -> OK | F84: =IF(F82=0,"sin uso",IF($B$76-F82>=Supuestos!$B$11,"OK","NO ENTRA")) -> OK | G84: =IF(G82=0,"sin uso",IF($B$76-G82>=Supuestos!$B$11,"OK","NO ENTRA")) -> OK
A86: Cálculo anual | D86: 2026 | E86: 2027 | F86: 2028 | G86: 2029 | H86: 2030 | I86: 2031 | J86: 2032 | K86: 2033 | L86: 2034 | M86: 2035
A87: Metros necesarios: Cuerpo 10 kg | D87: =Calculo!D11*$D$78/1000 -> 51.796 | E87: =Calculo!E11*$D$78/1000 -> 99.651 | F87: =Calculo!F11*$D$78/1000 -> 193.109 | G87: =Calculo!G11*$D$78/1000 -> 378.899 | H87: =Calculo!H11*$D$78/1000 -> 667.718 | I87: =Calculo!I11*$D$78/1000 -> 967.234 | J87: =Calculo!J11*$D$78/1000 -> 1307.286 | K87: =Calculo!K11*$D$78/1000 -> 1655.22 | ... M87: =Calculo!M11*$D$78/1000 -> 2168.676
A88: Metros necesarios: Cúpula 10 kg | D88: =Calculo!D11*$D$79/1000 -> 24.012 | E88: =Calculo!E11*$D$79/1000 -> 46.197 | F88: =Calculo!F11*$D$79/1000 -> 89.523 | G88: =Calculo!G11*$D$79/1000 -> 175.653 | H88: =Calculo!H11*$D$79/1000 -> 309.546 | I88: =Calculo!I11*$D$79/1000 -> 448.398 | J88: =Calculo!J11*$D$79/1000 -> 606.042 | K88: =Calculo!K11*$D$79/1000 -> 767.34 | ... M88: =Calculo!M11*$D$79/1000 -> 1005.372
A89: Metros necesarios: Fondo 10 kg | D89: =Calculo!D11*$D$80/1000 -> 19.136 | E89: =Calculo!E11*$D$80/1000 -> 36.816 | F89: =Calculo!F11*$D$80/1000 -> 71.344 | G89: =Calculo!G11*$D$80/1000 -> 139.984 | H89: =Calculo!H11*$D$80/1000 -> 246.688 | I89: =Calculo!I11*$D$80/1000 -> 357.344 | J89: =Calculo!J11*$D$80/1000 -> 482.976 | K89: =Calculo!K11*$D$80/1000 -> 611.52 | ... M89: =Calculo!M11*$D$80/1000 -> 801.216
A90: Metros de bobina madre a cortar | D90: =MAX(IF($H$78=0,IF(D87>0,1000000000000,0),D87/$H$78),IF($H$79=0,IF(D88>0,1000000000000,0),D88/$H$79),IF($H$80=0,IF(D89>0,1000000000000,0),D89/$H$80)) -> 37.092524 | E90: =MAX(IF($H$78=0,IF(E87>0,1000000000000,0),E87/$H$78),IF($H$79=0,IF(E88>0,1000000000000,0),E88/$H$79),IF($H$80=0,IF(E89>0,1000000000000,0),E89/$H$80)) -> 71.36279 | F90: =MAX(IF($H$78=0,IF(F87>0,1000000000000,0),F87/$H$78),IF($H$79=0,IF(F88>0,1000000000000,0),F88/$H$79),IF($H$80=0,IF(F89>0,1000000000000,0),F89/$H$80)) -> 138.2906 | G90: =MAX(IF($H$78=0,IF(G87>0,1000000000000,0),G87/$H$78),IF($H$79=0,IF(G88>0,1000000000000,0),G88/$H$79),IF($H$80=0,IF(G89>0,1000000000000,0),G89/$H$80)) -> 271.33987 | H90: =MAX(IF($H$78=0,IF(H87>0,1000000000000,0),H87/$H$78),IF($H$79=0,IF(H88>0,1000000000000,0),H88/$H$79),IF($H$80=0,IF(H89>0,1000000000000,0),H89/$H$80)) -> 478.17101 | I90: =MAX(IF($H$78=0,IF(I87>0,1000000000000,0),I87/$H$78),IF($H$79=0,IF(I88>0,1000000000000,0),I88/$H$79),IF($H$80=0,IF(I89>0,1000000000000,0),I89/$H$80)) -> 692.66256 | J90: =MAX(IF($H$78=0,IF(J87>0,1000000000000,0),J87/$H$78),IF($H$79=0,IF(J88>0,1000000000000,0),J88/$H$79),IF($H$80=0,IF(J89>0,1000000000000,0),J89/$H$80)) -> 936.18304 | K90: =MAX(IF($H$78=0,IF(K87>0,1000000000000,0),K87/$H$78),IF($H$79=0,IF(K88>0,1000000000000,0),K88/$H$79),IF($H$80=0,IF(K89>0,1000000000000,0),K89/$H$80)) -> 1185.348 | ... M90: =MAX(IF($H$78=0,IF(M87>0,1000000000000,0),M87/$H$78),IF($H$79=0,IF(M88>0,1000000000000,0),M88/$H$79),IF($H$80=0,IF(M89>0,1000000000000,0),M89/$H$80)) -> 1553.0478
A91: Acero de madre comprado (t) | D91: =D90*$H$76/1000/(1-Supuestos!$B$12) -> 0.58677017 | E91: =E90*$H$76/1000/(1-Supuestos!$B$12) -> 1.1288948 | F91: =F90*$H$76/1000/(1-Supuestos!$B$12) -> 2.1876323 | G91: =G90*$H$76/1000/(1-Supuestos!$B$12) -> 4.2923514 | H91: =H90*$H$76/1000/(1-Supuestos!$B$12) -> 7.5642329 | I91: =I90*$H$76/1000/(1-Supuestos!$B$12) -> 10.957295 | J91: =J90*$H$76/1000/(1-Supuestos!$B$12) -> 14.809569 | K91: =K90*$H$76/1000/(1-Supuestos!$B$12) -> 18.751134 | ... M91: =M90*$H$76/1000/(1-Supuestos!$B$12) -> 24.567812
A92: Acero neto en piezas del grupo (t) | D92: =Calculo!D21+Calculo!D37+Calculo!D38 -> 0.52705855 | E92: =Calculo!E21+Calculo!E37+Calculo!E38 -> 1.0140148 | F92: =Calculo!F21+Calculo!F37+Calculo!F38 -> 1.9650118 | G92: =Calculo!G21+Calculo!G37+Calculo!G38 -> 3.8555479 | H92: =Calculo!H21+Calculo!H37+Calculo!H38 -> 6.7944722 | I92: =Calculo!I21+Calculo!I37+Calculo!I38 -> 9.8422455 | J92: =Calculo!J21+Calculo!J37+Calculo!J38 -> 13.302499 | K92: =Calculo!K21+Calculo!K37+Calculo!K38 -> 16.842958 | ... M92: =Calculo!M21+Calculo!M37+Calculo!M38 -> 22.067712
A93: Aprovechamiento del grupo | D93: =IF(D91=0,0,D92/D91) -> 0.89823678 | E93: =IF(E91=0,0,E92/E91) -> 0.89823678 | F93: =IF(F91=0,0,F92/F91) -> 0.89823678 | G93: =IF(G91=0,0,G92/G91) -> 0.89823678 | H93: =IF(H91=0,0,H92/H91) -> 0.89823678 | I93: =IF(I91=0,0,I92/I91) -> 0.89823678 | J93: =IF(J91=0,0,J92/J91) -> 0.89823678 | K93: =IF(K91=0,0,K92/K91) -> 0.89823678 | ... M93: =IF(M91=0,0,M92/M91) -> 0.89823678
A94: Bobinas madre por año | D94: =IF(Bobinas!$K$27=0,0,D91/Bobinas!$K$27) -> 0.23470807 | E94: =IF(Bobinas!$K$27=0,0,E91/Bobinas!$K$27) -> 0.45155792 | F94: =IF(Bobinas!$K$27=0,0,F91/Bobinas!$K$27) -> 0.87505291 | G94: =IF(Bobinas!$K$27=0,0,G91/Bobinas!$K$27) -> 1.7169405 | H94: =IF(Bobinas!$K$27=0,0,H91/Bobinas!$K$27) -> 3.0256932 | I94: =IF(Bobinas!$K$27=0,0,I91/Bobinas!$K$27) -> 4.3829181 | J94: =IF(Bobinas!$K$27=0,0,J91/Bobinas!$K$27) -> 5.9238276 | K94: =IF(Bobinas!$K$27=0,0,K91/Bobinas!$K$27) -> 7.5004535 | ... M94: =IF(Bobinas!$K$27=0,0,M91/Bobinas!$K$27) -> 9.8271248
A95: Flejes de disco generados por año | D95: =D94*($H$79+$H$80) -> 0.27305937 | E95: =E94*($H$79+$H$80) -> 0.52534248 | F95: =F94*($H$79+$H$80) -> 1.0180366 | G95: =G94*($H$79+$H$80) -> 1.9974886 | H95: =H94*($H$79+$H$80) -> 3.5200914 | I95: =I94*($H$79+$H$80) -> 5.0990869 | J95: =J94*($H$79+$H$80) -> 6.891781 | K95: =K94*($H$79+$H$80) -> 8.7260276 | ... M95: =M94*($H$79+$H$80) -> 11.432877
A96: Horas de corte longitudinal | D96: =D90/(Supuestos!$B$39*60)+D94*Supuestos!$B$40/60 -> 0.19148627 | E96: =E90/(Supuestos!$B$39*60)+E94*Supuestos!$B$40/60 -> 0.36840293 | F96: =F90/(Supuestos!$B$39*60)+F94*Supuestos!$B$40/60 -> 0.71391077 | G96: =G90/(Supuestos!$B$39*60)+G94*Supuestos!$B$40/60 -> 1.4007637 | H96: =H90/(Supuestos!$B$39*60)+H94*Supuestos!$B$40/60 -> 2.4685078 | I96: =I90/(Supuestos!$B$39*60)+I94*Supuestos!$B$40/60 -> 3.575798 | J96: =J90/(Supuestos!$B$39*60)+J94*Supuestos!$B$40/60 -> 4.8329469 | K96: =K90/(Supuestos!$B$39*60)+K94*Supuestos!$B$40/60 -> 6.1192352 | ... M96: =M90/(Supuestos!$B$39*60)+M94*Supuestos!$B$40/60 -> 8.0174469
A99: Grupo 3,2 mm
A100: Ancho de bobina madre (mm) | B100: 1500 | C100: Espesor (mm) | D100: =Nesting!$E$9 -> 3.2 | E100: Acero | F100: =Nesting!$F$9 -> LAC | G100: kg por metro de madre | H100: =B100*D100*Supuestos!$B$10/1000 -> 37.776
A101: Tira (fleje) | B101: Orientación (1 = alto a lo ancho, 2 = perímetro a lo ancho) | C101: Ancho de tira (mm) | D101: Avance por unidad (mm) | E101: Patrón 1 (tiras) | F101: Patrón 2 (tiras) | G101: Patrón 3 (tiras) | H101: Tiras por metro de madre (ponderado)
A102: Cuerpo 25 kg | B102: 1 | C102: =IF(B102=1,Nesting!$C$9,Nesting!$D$9) -> 490 | D102: =IF(B102=1,Nesting!$D$9,Nesting!$C$9) -> 858 | E102: 0 | F102: 3 | G102: 0 | H102: =E102*$E$104+F102*$F$104+G102*$G$104 -> 0.6216
A103: Cuerpo 50 kg | B103: 1 | C103: =IF(B103=1,Nesting!$C$10,Nesting!$D$10) -> 640 | D103: =IF(B103=1,Nesting!$D$10,Nesting!$C$10) -> 994 | E103: 2 | F103: 0 | G103: 0 | H103: =E103*$E$104+F103*$F$104+G103*$G$104 -> 1.5856
A104: Participación de cada patrón (% de los metros de madre) | E104: 0.7928 | F104: 0.2072 | G104: 0 | H104: =IF(ABS(SUM(E104:G104)-1)<0.001,"Suma 100% OK","REVISAR: no suma 100%") -> Suma 100% OK
A105: Ancho usado por patrón (mm) | E105: =SUMPRODUCT($C$102:$C$103,E102:E103) -> 1280 | F105: =SUMPRODUCT($C$102:$C$103,F102:F103) -> 1470 | G105: =SUMPRODUCT($C$102:$C$103,G102:G103) -> 0
A106: Orilla (scrap de borde) por patrón (mm) | E106: =IF(E105=0,0,$B$100-E105) -> 220 | F106: =IF(F105=0,0,$B$100-F105) -> 30 | G106: =IF(G105=0,0,$B$100-G105) -> 0
A107: ¿Entra en la madre? (orilla ≥ margen) | E107: =IF(E105=0,"sin uso",IF($B$100-E105>=Supuestos!$B$11,"OK","NO ENTRA")) -> OK | F107: =IF(F105=0,"sin uso",IF($B$100-F105>=Supuestos!$B$11,"OK","NO ENTRA")) -> OK | G107: =IF(G105=0,"sin uso",IF($B$100-G105>=Supuestos!$B$11,"OK","NO ENTRA")) -> sin uso
A109: Cálculo anual | D109: 2026 | E109: 2027 | F109: 2028 | G109: 2029 | H109: 2030 | I109: 2031 | J109: 2032 | K109: 2033 | L109: 2034 | M109: 2035
A110: Metros necesarios: Cuerpo 25 kg | D110: =Calculo!D12*$D$102/1000 -> 29.172 | E110: =Calculo!E12*$D$102/1000 -> 49.764 | F110: =Calculo!F12*$D$102/1000 -> 77.22 | G110: =Calculo!G12*$D$102/1000 -> 128.7 | H110: =Calculo!H12*$D$102/1000 -> 213.642 | I110: =Calculo!I12*$D$102/1000 -> 297.726 | J110: =Calculo!J12*$D$102/1000 -> 398.112 | K110: =Calculo!K12*$D$102/1000 -> 501.93 | ... M110: =Calculo!M12*$D$102/1000 -> 664.95
A111: Metros necesarios: Cuerpo 50 kg | D111: =Calculo!D13*$D$103/1000 -> 74.55 | E111: =Calculo!E13*$D$103/1000 -> 127.232 | F111: =Calculo!F13*$D$103/1000 -> 196.812 | G111: =Calculo!G13*$D$103/1000 -> 330.008 | H111: =Calculo!H13*$D$103/1000 -> 544.712 | I111: =Calculo!I13*$D$103/1000 -> 759.416 | J111: =Calculo!J13*$D$103/1000 -> 1013.88 | K111: =Calculo!K13*$D$103/1000 -> 1279.278 | ... M111: =Calculo!M13*$D$103/1000 -> 1694.77
A112: Metros de bobina madre a cortar | D112: =MAX(IF($H$102=0,IF(D110>0,1000000000000,0),D110/$H$102),IF($H$103=0,IF(D111>0,1000000000000,0),D111/$H$103)) -> 47.016902 | E112: =MAX(IF($H$102=0,IF(E110>0,1000000000000,0),E110/$H$102),IF($H$103=0,IF(E111>0,1000000000000,0),E111/$H$103)) -> 80.24218 | F112: =MAX(IF($H$102=0,IF(F110>0,1000000000000,0),F110/$H$102),IF($H$103=0,IF(F111>0,1000000000000,0),F111/$H$103)) -> 124.2278 | G112: =MAX(IF($H$102=0,IF(G110>0,1000000000000,0),G110/$H$102),IF($H$103=0,IF(G111>0,1000000000000,0),G111/$H$103)) -> 208.12815 | H112: =MAX(IF($H$102=0,IF(H110>0,1000000000000,0),H110/$H$102),IF($H$103=0,IF(H111>0,1000000000000,0),H111/$H$103)) -> 343.69691 | I112: =MAX(IF($H$102=0,IF(I110>0,1000000000000,0),I110/$H$102),IF($H$103=0,IF(I111>0,1000000000000,0),I111/$H$103)) -> 478.96718 | J112: =MAX(IF($H$102=0,IF(J110>0,1000000000000,0),J110/$H$102),IF($H$103=0,IF(J111>0,1000000000000,0),J111/$H$103)) -> 640.46332 | K112: =MAX(IF($H$102=0,IF(K110>0,1000000000000,0),K110/$H$102),IF($H$103=0,IF(K111>0,1000000000000,0),K111/$H$103)) -> 807.48069 | ... M112: =MAX(IF($H$102=0,IF(M110>0,1000000000000,0),M110/$H$102),IF($H$103=0,IF(M111>0,1000000000000,0),M111/$H$103)) -> 1069.7394
A113: Acero de madre comprado (t) | D113: =D112*$H$100/1000/(1-Supuestos!$B$12) -> 1.7850357 | E113: =E112*$H$100/1000/(1-Supuestos!$B$12) -> 3.0464609 | F113: =F112*$H$100/1000/(1-Supuestos!$B$12) -> 4.7164114 | G113: =G112*$H$100/1000/(1-Supuestos!$B$12) -> 7.9017579 | H113: =H112*$H$100/1000/(1-Supuestos!$B$12) -> 13.048738 | I113: =I112*$H$100/1000/(1-Supuestos!$B$12) -> 18.184386 | J113: =J112*$H$100/1000/(1-Supuestos!$B$12) -> 24.315721 | K113: =K112*$H$100/1000/(1-Supuestos!$B$12) -> 30.656674 | ... M113: =M112*$H$100/1000/(1-Supuestos!$B$12) -> 40.613543
A114: Acero neto en piezas del grupo (t) | D114: =Calculo!D22+Calculo!D23 -> 1.5615662 | E114: =Calculo!E22+Calculo!E23 -> 2.6647906 | F114: =Calculo!F22+Calculo!F23 -> 4.1250757 | G114: =Calculo!G22+Calculo!G23 -> 6.9071683 | H114: =Calculo!H22+Calculo!H23 -> 11.415914 | I114: =Calculo!I22+Calculo!I23 -> 15.914071 | J114: =Calculo!J22+Calculo!J23 -> 21.25424 | K114: =Calculo!K22+Calculo!K23 -> 26.812992 | ... M114: =Calculo!M22+Calculo!M23 -> 35.521486
...

Sheet Bobinas
A1: Peso de bobina por SKU: recomendado según la demanda y elegido (editable)
A2: Recomendado = consumo mensual del año de referencia × cobertura objetivo, redondeado a 0,5 t, entre el peso mínimo y el máximo que permiten el diámetro exterior y el desbobinador.
A4: Opción A — bobinas de cuerpo (ancho estándar) y flejes de disco (cortados por el proveedor)
A5: SKU | B5: Tipo | C5: Espesor (mm) | D5: Ancho (mm) | E5: kg por metro | F5: Consumo año de referencia (t) | G5: Consumo mensual (t) | H5: Máx. por diámetro exterior (t) | I5: Capacidad del desbobinador (t) | J5: PESO RECOMENDADO (t) | K5: PESO ELEGIDO (t) | L5: Largo de la bobina (m) | M5: Piezas por bobina | N5: Días que dura | O5: Bobinas por año
A6: Cuerpo 2,5 kg | B6: Bobina cuerpo | C6: =Nesting!$E$6 -> 1.25 | D6: =Nesting!$P$6 -> 1220 | E6: =D6*C6*Supuestos!$B$10/1000 -> 12.00175 | F6: {=INDEX(Calculo!$D$44:$M$44,MATCH(Supuestos!$B$21,Calculo!$D$4:$M$4,0))} -> 15.271907 | G6: =F6/12 -> 1.2726589 | H6: =D6*Supuestos!$B$49 -> 15.021034 | I6: =Supuestos!$B$26 -> 10 | J6: =MIN(ROUNDDOWN(MIN(H6,I6)*2,0)/2,MAX(Supuestos!$B$23,ROUNDUP(G6*Supuestos!$B$22*2,0)/2)) -> 1.5 | K6: 1.5 | L6: =K6*1000/E6 -> 124.98177 | M6: =L6*1000/Nesting!$V$6*Nesting!$U$6 -> 1391.2628 | N6: =IF(F6=0,0,K6/F6*Supuestos!$B$32) -> 23.572694 | O6: =IF(K6=0,0,F6/K6) -> 10.181271
A7: Cuerpo 5 kg | B7: Bobina cuerpo | C7: =Nesting!$E$7 -> 1.6 | D7: =Nesting!$P$7 -> 1000 | E7: =D7*C7*Supuestos!$B$10/1000 -> 12.592 | F7: {=INDEX(Calculo!$D$45:$M$45,MATCH(Supuestos!$B$21,Calculo!$D$4:$M$4,0))} -> 127.4366 | G7: =F7/12 -> 10.619716 | H7: =D7*Supuestos!$B$49 -> 12.312323 | I7: =Supuestos!$B$26 -> 10 | J7: =MIN(ROUNDDOWN(MIN(H7,I7)*2,0)/2,MAX(Supuestos!$B$23,ROUNDUP(G7*Supuestos!$B$22*2,0)/2)) -> 10 | K7: 10 | L7: =K7*1000/E7 -> 794.15502 | M7: =L7*1000/Nesting!$V$7*Nesting!$U$7 -> 5021.0012 | N7: =IF(F7=0,0,K7/F7*Supuestos!$B$32) -> 18.832895 | O7: =IF(K7=0,0,F7/K7) -> 12.74366
A8: Cuerpo 10 kg | B8: Bobina cuerpo | C8: =Nesting!$E$8 -> 2 | D8: =Nesting!$P$8 -> 1000 | E8: =D8*C8*Supuestos!$B$10/1000 -> 15.74 | F8: {=INDEX(Calculo!$D$46:$M$46,MATCH(Supuestos!$B$21,Calculo!$D$4:$M$4,0))} -> 17.153246 | G8: =F8/12 -> 1.4294372 | H8: =D8*Supuestos!$B$49 -> 12.312323 | I8: =Supuestos!$B$26 -> 10 | J8: =MIN(ROUNDDOWN(MIN(H8,I8)*2,0)/2,MAX(Supuestos!$B$23,ROUNDUP(G8*Supuestos!$B$22*2,0)/2)) -> 1.5 | K8: 1.5 | L8: =K8*1000/E8 -> 95.298602 | M8: =L8*1000/Nesting!$V$8*Nesting!$U$8 -> 338.53855 | N8: =IF(F8=0,0,K8/F8*Supuestos!$B$32) -> 20.987281 | O8: =IF(K8=0,0,F8/K8) -> 11.435498
A9: Cuerpo 25 kg | B9: Bobina cuerpo | C9: =Nesting!$E$9 -> 3.2 | D9: =Nesting!$P$9 -> 1500 | E9: =D9*C9*Supuestos!$B$10/1000 -> 37.776 | F9: {=INDEX(Calculo!$D$47:$M$47,MATCH(Supuestos!$B$21,Calculo!$D$4:$M$4,0))} -> 8.415126 | G9: =F9/12 -> 0.7012605 | H9: =D9*Supuestos!$B$49 -> 18.468484 | I9: =Supuestos!$B$26 -> 10 | J9: =MIN(ROUNDDOWN(MIN(H9,I9)*2,0)/2,MAX(Supuestos!$B$23,ROUNDUP(G9*Supuestos!$B$22*2,0)/2)) -> 1 | K9: 1 | L9: =K9*1000/E9 -> 26.471834 | M9: =L9*1000/Nesting!$V$9*Nesting!$U$9 -> 92.55886 | N9: =IF(F9=0,0,K9/F9*Supuestos!$B$32) -> 28.520072 | O9: =IF(K9=0,0,F9/K9) -> 8.415126
A10: Cuerpo 50 kg | B10: Bobina cuerpo | C10: =Nesting!$E$10 -> 3.2 | D10: =Nesting!$P$10 -> 1500 | E10: =D10*C10*Supuestos!$B$10/1000 -> 37.776 | F10: {=INDEX(Calculo!$D$48:$M$48,MATCH(Supuestos!$B$21,Calculo!$D$4:$M$4,0))} -> 32.171674 | G10: =F10/12 -> 2.6809728 | H10: =D10*Supuestos!$B$49 -> 18.468484 | I10: =Supuestos!$B$26 -> 10 | J10: =MIN(ROUNDDOWN(MIN(H10,I10)*2,0)/2,MAX(Supuestos!$B$23,ROUNDUP(G10*Supuestos!$B$22*2,0)/2)) -> 3 | K10: 3 | L10: =K10*1000/E10 -> 79.415502 | M10: =L10*1000/Nesting!$V$10*Nesting!$U$10 -> 159.78974 | N10: =IF(F10=0,0,K10/F10*Supuestos!$B$32) -> 22.379936 | O10: =IF(K10=0,0,F10/K10) -> 10.723891
A11: Cuerpo 70 kg | B11: Bobina cuerpo | C11: =Nesting!$E$11 -> 4.75 | D11: =Nesting!$P$11 -> 1245 | E11: =D11*C11*Supuestos!$B$10/1000 -> 46.541213 | F11: {=INDEX(Calculo!$D$49:$M$49,MATCH(Supuestos!$B$21,Calculo!$D$4:$M$4,0))} -> 11.864033 | G11: =F11/12 -> 0.98866944 | H11: =D11*Supuestos!$B$49 -> 15.328842 | I11: =Supuestos!$B$26 -> 10 | J11: =MIN(ROUNDDOWN(MIN(H11,I11)*2,0)/2,MAX(Supuestos!$B$23,ROUNDUP(G11*Supuestos!$B$22*2,0)/2)) -> 1 | K11: 1 | L11: =K11*1000/E11 -> 21.486333 | M11: =L11*1000/Nesting!$V$11*Nesting!$U$11 -> 31.597549 | N11: =IF(F11=0,0,K11/F11*Supuestos!$B$32) -> 20.229208 | O11: =IF(K11=0,0,F11/K11) -> 11.864033
A12: Cuerpo 100 kg | B12: Bobina cuerpo | C12: =Nesting!$E$12 -> 4.75 | D12: =Nesting!$P$12 -> 1245 | E12: =D12*C12*Supuestos!$B$10/1000 -> 46.541213 | F12: {=INDEX(Calculo!$D$50:$M$50,MATCH(Supuestos!$B$21,Calculo!$D$4:$M$4,0))} -> 10.398102 | G12: =F12/12 -> 0.8665085 | H12: =D12*Supuestos!$B$49 -> 15.328842 | I12: =Supuestos!$B$26 -> 10 | J12: =MIN(ROUNDDOWN(MIN(H12,I12)*2,0)/2,MAX(Supuestos!$B$23,ROUNDUP(G12*Supuestos!$B$22*2,0)/2)) -> 1 | K12: 1 | L12: =K12*1000/E12 -> 21.486333 | M12: =L12*1000/Nesting!$V$12*Nesting!$U$12 -> 23.873704 | N12: =IF(F12=0,0,K12/F12*Supuestos!$B$32) -> 23.081135 | O12: =IF(K12=0,0,F12/K12) -> 10.398102
A13: Fleje Cúpula 1 kg | B13: Fleje disco | C13: =Nesting!$D$26 -> 0.9 | D13: =Nesting!$W$26 -> 114 | E13: =D13*C13*Supuestos!$B$10/1000 -> 0.807462 | F13: {=INDEX(Calculo!$D$66:$M$66,MATCH(Supuestos!$B$21,Calculo!$D$4:$M$4,0))} -> 18.251831 | G13: =F13/12 -> 1.5209859 | H13: =D13*Supuestos!$B$49 -> 1.4036048 | I13: =Supuestos!$B$27 -> 3 | J13: =MIN(ROUNDDOWN(MIN(H13,I13)*2,0)/2,MAX(Supuestos!$B$23,ROUNDUP(G13*Supuestos!$B$22*2,0)/2)) -> 1 | K13: 1 | L13: =K13*1000/E13 -> 1238.4484 | M13: =L13*1000/Nesting!$H$26 -> 11157.193 | N13: =IF(F13=0,0,K13/F13*Supuestos!$B$32) -> 13.149365 | O13: =IF(K13=0,0,F13/K13) -> 18.251831
A14: Fleje Fondo 1 kg | B14: Fleje disco | C14: =Nesting!$D$27 -> 0.9 | D14: =Nesting!$W$27 -> 106 | E14: =D14*C14*Supuestos!$B$10/1000 -> 0.750798 | F14: {=INDEX(Calculo!$D$67:$M$67,MATCH(Supuestos!$B$21,Calculo!$D$4:$M$4,0))} -> 15.747866 | G14: =F14/12 -> 1.3123222 | H14: =D14*Supuestos!$B$49 -> 1.3051062 | I14: =Supuestos!$B$27 -> 3 | J14: =MIN(ROUNDDOWN(MIN(H14,I14)*2,0)/2,MAX(Supuestos!$B$23,ROUNDUP(G14*Supuestos!$B$22*2,0)/2)) -> 1 | K14: 1 | L14: =K14*1000/E14 -> 1331.9162 | M14: =L14*1000/Nesting!$H$27 -> 12931.225 | N14: =IF(F14=0,0,K14/F14*Supuestos!$B$32) -> 15.24016 | O14: =IF(K14=0,0,F14/K14) -> 15.747866
A15: Fleje Cúpula 2,5 kg | B15: Fleje disco | C15: =Nesting!$D$28 -> 1.25 | D15: =Nesting!$W$28 -> 200 | E15: =D15*C15*Supuestos!$B$10/1000 -> 1.9675 | F15: {=INDEX(Calculo!$D$68:$M$68,MATCH(Supuestos!$B$21,Calculo!$D$4:$M$4,0))} -> 5.072211 | G15: =F15/12 -> 0.42268425 | H15: =D15*Supuestos!$B$49 -> 2.4624646 | I15: =Supuestos!$B$27 -> 3 | J15: =MIN(ROUNDDOWN(MIN(H15,I15)*2,0)/2,MAX(Supuestos!$B$23,ROUNDUP(G15*Supuestos!$B$22*2,0)/2)) -> 0.5 | K15: 0.5 | L15: =K15*1000/E15 -> 254.12961 | M15: =L15*1000/Nesting!$H$28 -> 1396.3165 | N15: =IF(F15=0,0,K15/F15*Supuestos!$B$32) -> 23.658322 | O15: =IF(K15=0,0,F15/K15) -> 10.144422
A16: Fleje Fondo 2,5 kg | B16: Fleje disco | C16: =Nesting!$D$29 -> 1.25 | D16: =Nesting!$W$29 -> 200 | E16: =D16*C16*Supuestos!$B$10/1000 -> 1.9675 | F16: {=INDEX(Calculo!$D$69:$M$69,MATCH(Supuestos!$B$21,Calculo!$D$4:$M$4,0))} -> 4.208263 | G16: =F16/12 -> 0.35068858 | H16: =D16*Supuestos!$B$49 -> 2.4624646 | I16: =Supuestos!$B$27 -> 3 | J16: =MIN(ROUNDDOWN(MIN(H16,I16)*2,0)/2,MAX(Supuestos!$B$23,ROUNDUP(G16*Supuestos!$B$22*2,0)/2)) -> 0.5 | K16: 0.5 | L16: =K16*1000/E16 -> 254.12961 | M16: =L16*1000/Nesting!$H$29 -> 1682.9775 | N16: =IF(F16=0,0,K16/F16*Supuestos!$B$32) -> 28.515328 | O16: =IF(K16=0,0,F16/K16) -> 8.416526
A17: Fleje Cúpula 5 kg | B17: Fleje disco | C17: =Nesting!$D$30 -> 1.6 | D17: =Nesting!$W$30 -> 250 | E17: =D17*C17*Supuestos!$B$10/1000 -> 3.148 | F17: {=INDEX(Calculo!$D$70:$M$70,MATCH(Supuestos!$B$21,Calculo!$D$4:$M$4,0))} -> 45.119806 | G17: =F17/12 -> 3.7599839 | H17: =D17*Supuestos!$B$49 -> 3.0780807 | I17: =Supuestos!$B$27 -> 3 | J17: =MIN(ROUNDDOWN(MIN(H17,I17)*2,0)/2,MAX(Supuestos!$B$23,ROUNDUP(G17*Supuestos!$B$22*2,0)/2)) -> 3 | K17: 0.6 | L17: =K17*1000/E17 -> 190.5972 | M17: =L17*1000/Nesting!$H$30 -> 850.88038 | N17: =IF(F17=0,0,K17/F17*Supuestos!$B$32) -> 3.1915031 | O17: =IF(K17=0,0,F17/K17) -> 75.199677
A18: Fleje Fondo 5 kg | B18: Fleje disco | C18: =Nesting!$D$31 -> 1.6 | D18: =Nesting!$W$31 -> 200 | E18: =D18*C18*Supuestos!$B$10/1000 -> 2.5184 | F18: {=INDEX(Calculo!$D$71:$M$71,MATCH(Supuestos!$B$21,Calculo!$D$4:$M$4,0))} -> 29.00559 | G18: =F18/12 -> 2.4171325 | H18: =D18*Supuestos!$B$49 -> 2.4624646 | I18: =Supuestos!$B$27 -> 3 | J18: =MIN(ROUNDDOWN(MIN(H18,I18)*2,0)/2,MAX(Supuestos!$B$23,ROUNDUP(G18*Supuestos!$B$22*2,0)/2)) -> 2 | K18: 0.5 | L18: =K18*1000/E18 -> 198.53875 | M18: =L18*1000/Nesting!$H$31 -> 1102.9931 | N18: =IF(F18=0,0,K18/F18*Supuestos!$B$32) -> 4.1371336 | O18: =IF(K18=0,0,F18/K18) -> 58.011179
A19: Fleje Cúpula 10 kg | B19: Fleje disco | C19: =Nesting!$D$32 -> 2 | D19: =Nesting!$W$32 -> 300 | E19: =D19*C19*Supuestos!$B$10/1000 -> 4.722 | F19: {=INDEX(Calculo!$D$72:$M$72,MATCH(Supuestos!$B$21,Calculo!$D$4:$M$4,0))} -> 4.7712227 | G19: =F19/12 -> 0.39760189 | H19: =D19*Supuestos!$B$49 -> 3.6936968 | I19: =Supuestos!$B$27 -> 3 | J19: =MIN(ROUNDDOWN(MIN(H19,I19)*2,0)/2,MAX(Supuestos!$B$23,ROUNDUP(G19*Supuestos!$B$22*2,0)/2)) -> 0.5 | K19: 0.75 | L19: =K19*1000/E19 -> 158.831 | M19: =L19*1000/Nesting!$H$32 -> 608.54791 | N19: =IF(F19=0,0,K19/F19*Supuestos!$B$32) -> 37.726179 | O19: =IF(K19=0,0,F19/K19) -> 6.3616303
A20: Fleje Fondo 10 kg | B20: Fleje disco | C20: =Nesting!$D$33 -> 2 | D20: =Nesting!$W$33 -> 249 | E20: =D20*C20*Supuestos!$B$10/1000 -> 3.91926 | F20: {=INDEX(Calculo!$D$73:$M$73,MATCH(Supuestos!$B$21,Calculo!$D$4:$M$4,0))} -> 3.1559536 | G20: =F20/12 -> 0.26299613 | H20: =D20*Supuestos!$B$49 -> 3.0657684 | I20: =Supuestos!$B$27 -> 3 | J20: =MIN(ROUNDDOWN(MIN(H20,I20)*2,0)/2,MAX(Supuestos!$B$23,ROUNDUP(G20*Supuestos!$B$22*2,0)/2)) -> 0.5 | K20: 0.5 | L20: =K20*1000/E20 -> 127.5751 | M20: =L20*1000/Nesting!$H$33 -> 613.34184 | N20: =IF(F20=0,0,K20/F20*Supuestos!$B$32) -> 38.023373 | O20: =IF(K20=0,0,F20/K20) -> 6.3119072
A22: Opción C — bobinas madre (una por espesor)
A23: SKU | B23: Tipo | C23: Espesor (mm) | D23: Ancho (mm) | E23: kg por metro | F23: Consumo año de referencia (t) | G23: Consumo mensual (t) | H23: Máx. por diámetro exterior (t) | I23: Capacidad del desbobinador (t) | J23: PESO RECOMENDADO (t) | K23: PESO ELEGIDO (t) | L23: Largo de la bobina (m) | M23: Piezas por bobina | N23: Días hábiles que dura | O23: Bobinas por año
A24: Madre 0,9 mm | B24: Bobina madre | C24: =BobinaMadre!$D$6 -> 0.9 | D24: =BobinaMadre!$B$6 -> 1220 | E24: =D24*C24*Supuestos!$B$10/1000 -> 8.64126 | F24: {=INDEX(BobinaMadre!$D$19:$M$19,MATCH(Supuestos!$B$21,Calculo!$D$4:$M$4,0))} -> 34.638425 | G24: =F24/12 -> 2.8865354 | H24: =D24*Supuestos!$B$49 -> 15.021034 | I24: =Supuestos!$B$28 -> 14 | J24: =MIN(ROUNDDOWN(MIN(H24,I24)*2,0)/2,MAX(Supuestos!$B$23,ROUNDUP(G24*Supuestos!$B$22*2,0)/2)) -> 3 | K24: 3 | L24: =K24*1000/E24 -> 347.17159 | M24: según patrón | N24: =IF(F24=0,0,K24/F24*Supuestos!$B$32) -> 20.786165 | O24: =IF(K24=0,0,F24/K24) -> 11.546142
A25: Madre 1,25 mm | B25: Bobina madre | C25: =BobinaMadre!$D$28 -> 1.25 | D25: =BobinaMadre!$B$28 -> 1000 | E25: =D25*C25*Supuestos!$B$10/1000 -> 9.8375 | F25: {=INDEX(BobinaMadre!$D$43:$M$43,MATCH(Supuestos!$B$21,Calculo!$D$4:$M$4,0))} -> 23.294806 | G25: =F25/12 -> 1.9412338 | H25: =D25*Supuestos!$B$49 -> 12.312323 | I25: =Supuestos!$B$28 -> 14 | J25: =MIN(ROUNDDOWN(MIN(H25,I25)*2,0)/2,MAX(Supuestos!$B$23,ROUNDUP(G25*Supuestos!$B$22*2,0)/2)) -> 2 | K25: 2 | L25: =K25*1000/E25 -> 203.30368 | M25: según patrón | N25: =IF(F25=0,0,K25/F25*Supuestos!$B$32) -> 20.605452 | O25: =IF(K25=0,0,F25/K25) -> 11.647403
A26: Madre 1,6 mm | B26: Bobina madre | C26: =BobinaMadre!$D$52 -> 1.6 | D26: =BobinaMadre!$B$52 -> 1000 | E26: =D26*C26*Supuestos!$B$10/1000 -> 12.592 | F26: {=INDEX(BobinaMadre!$D$67:$M$67,MATCH(Supuestos!$B$21,Calculo!$D$4:$M$4,0))} -> 198.0715 | G26: =F26/12 -> 16.505958 | H26: =D26*Supuestos!$B$49 -> 12.312323 | I26: =Supuestos!$B$28 -> 14 | J26: =MIN(ROUNDDOWN(MIN(H26,I26)*2,0)/2,MAX(Supuestos!$B$23,ROUNDUP(G26*Supuestos!$B$22*2,0)/2)) -> 12 | K26: 12 | L26: =K26*1000/E26 -> 952.98602 | M26: según patrón | N26: =IF(F26=0,0,K26/F26*Supuestos!$B$32) -> 14.540204 | O26: =IF(K26=0,0,F26/K26) -> 16.505958
A27: Madre 2,0 mm | B27: Bobina madre | C27: =BobinaMadre!$D$76 -> 2 | D27: =BobinaMadre!$B$76 -> 1000 | E27: =D27*C27*Supuestos!$B$10/1000 -> 15.74 | F27: {=INDEX(BobinaMadre!$D$91:$M$91,MATCH(Supuestos!$B$21,Calculo!$D$4:$M$4,0))} -> 24.567812 | G27: =F27/12 -> 2.0473177 | H27: =D27*Supuestos!$B$49 -> 12.312323 | I27: =Supuestos!$B$28 -> 14 | J27: =MIN(ROUNDDOWN(MIN(H27,I27)*2,0)/2,MAX(Supuestos!$B$23,ROUNDUP(G27*Supuestos!$B$22*2,0)/2)) -> 2.5 | K27: 2.5 | L27: =K27*1000/E27 -> 158.831 | M27: según patrón | N27: =IF(F27=0,0,K27/F27*Supuestos!$B$32) -> 24.422199 | O27: =IF(K27=0,0,F27/K27) -> 9.8271248
A28: Madre 3,2 mm | B28: Bobina madre | C28: =BobinaMadre!$D$100 -> 3.2 | D28: =BobinaMadre!$B$100 -> 1500 | E28: =D28*C28*Supuestos!$B$10/1000 -> 37.776 | F28: {=INDEX(BobinaMadre!$D$113:$M$113,MATCH(Supuestos!$B$21,Calculo!$D$4:$M$4,0))} -> 40.613543 | G28: =F28/12 -> 3.3844619 | H28: =D28*Supuestos!$B$49 -> 18.468484 | I28: =Supuestos!$B$28 -> 14 | J28: =MIN(ROUNDDOWN(MIN(H28,I28)*2,0)/2,MAX(Supuestos!$B$23,ROUNDUP(G28*Supuestos!$B$22*2,0)/2)) -> 3.5 | K28: 3.5 | L28: =K28*1000/E28 -> 92.651419 | M28: según patrón | N28: =IF(F28=0,0,K28/F28*Supuestos!$B$32) -> 20.682756 | O28: =IF(K28=0,0,F28/K28) -> 11.603869
A29: Madre 4,75 mm | B29: Bobina madre | C29: =BobinaMadre!$D$122 -> 4.75 | D29: =BobinaMadre!$B$122 -> 1245 | E29: =D29*C29*Supuestos!$B$10/1000 -> 46.541213 | F29: {=INDEX(BobinaMadre!$D$133:$M$133,MATCH(Supuestos!$B$21,Calculo!$D$4:$M$4,0))} -> 22.262135 | G29: =F29/12 -> 1.8551779 | H29: =D29*Supuestos!$B$49 -> 15.328842 | I29: =Supuestos!$B$28 -> 14 | J29: =MIN(ROUNDDOWN(MIN(H29,I29)*2,0)/2,MAX(Supuestos!$B$23,ROUNDUP(G29*Supuestos!$B$22*2,0)/2)) -> 2 | K29: 2 | L29: =K29*1000/E29 -> 42.972666 | M29: según patrón | N29: =IF(F29=0,0,K29/F29*Supuestos!$B$32) -> 21.561274 | O29: =IF(K29=0,0,F29/K29) -> 11.131068
A31: • Cómo leerlo: si una bobina dura muy poco (pocos días) conviene subir el peso; si dura muchos meses, bajarlo para no inmovilizar stock.
A32: • El peso elegido es el máximo que se compra: en los primeros años, con poca demanda, el stock se calcula con bobinas más chicas (cobertura máxima en Supuestos).
A33: • Las bobinas angostas (flejes de disco) quedan limitadas por el diámetro exterior: a igual diámetro, un fleje de 200 mm pesa ~5 veces menos que una bobina de 1.000 mm.

Sheet Calculo
A1: Cálculo anual por opción
A2: No editar: todo sale de Supuestos, Demanda, Nesting, BobinaMadre y Bobinas.
A4: Concepto | B4: Espesor (mm) | C4: Acero | D4: 2026 | E4: 2027 | F4: 2028 | G4: 2029 | H4: 2030 | I4: 2031 | J4: 2032 | K4: 2033 | L4: 2034 | M4: 2035
A5: Período k (para descontar) | D5: 1 | E5: 2 | F5: 3 | G5: 4 | H5: 5 | I5: 6 | J5: 7 | K5: 8 | L5: 9 | M5: 10
A7: Unidades a fabricar
A8: 1 kg | D8: =Demanda!D30 -> 4179 | E8: =Demanda!E30 -> 5997 | F8: =Demanda!F30 -> 14514 | G8: =Demanda!G30 -> 35162 | H8: =Demanda!H30 -> 62116 | I8: =Demanda!I30 -> 87300 | J8: =Demanda!J30 -> 121674 | K8: =Demanda!K30 -> 156133 | ... M8: =Demanda!M30 -> 202621
A9: 2,5 kg | D9: =Demanda!D31 -> 295 | E9: =Demanda!E31 -> 709 | F9: =Demanda!F31 -> 1287 | G9: =Demanda!G31 -> 2545 | H9: =Demanda!H31 -> 4245 | I9: =Demanda!I31 -> 6055 | J9: =Demanda!J31 -> 8066 | K9: =Demanda!K31 -> 10228 | ... M9: =Demanda!M31 -> 14094
A10: 5 kg | D10: =Demanda!D32 -> 2256 | E10: =Demanda!E32 -> 3847 | F10: =Demanda!F32 -> 6573 | G10: =Demanda!G32 -> 11975 | H10: =Demanda!H32 -> 20360 | I10: =Demanda!I32 -> 28440 | J10: =Demanda!J32 -> 38437 | K10: =Demanda!K32 -> 48651 | ... M10: =Demanda!M32 -> 63666
A11: 10 kg | D11: =Demanda!D33 -> 92 | E11: =Demanda!E33 -> 177 | F11: =Demanda!F33 -> 343 | G11: =Demanda!G33 -> 673 | H11: =Demanda!H33 -> 1186 | I11: =Demanda!I33 -> 1718 | J11: =Demanda!J33 -> 2322 | K11: =Demanda!K33 -> 2940 | ... M11: =Demanda!M33 -> 3852
A12: 25 kg | D12: =Demanda!D34 -> 34 | E12: =Demanda!E34 -> 58 | F12: =Demanda!F34 -> 90 | G12: =Demanda!G34 -> 150 | H12: =Demanda!H34 -> 249 | I12: =Demanda!I34 -> 347 | J12: =Demanda!J34 -> 464 | K12: =Demanda!K34 -> 585 | ... M12: =Demanda!M34 -> 775
A13: 50 kg | D13: =Demanda!D35 -> 75 | E13: =Demanda!E35 -> 128 | F13: =Demanda!F35 -> 198 | G13: =Demanda!G35 -> 332 | H13: =Demanda!H35 -> 548 | I13: =Demanda!I35 -> 764 | J13: =Demanda!J35 -> 1020 | K13: =Demanda!K35 -> 1287 | ... M13: =Demanda!M35 -> 1705
A14: 70 kg | D14: =Demanda!D36 -> 16 | E14: =Demanda!E36 -> 29 | F14: =Demanda!F36 -> 43 | G14: =Demanda!G36 -> 72 | H14: =Demanda!H36 -> 119 | I14: =Demanda!I36 -> 166 | J14: =Demanda!J36 -> 223 | K14: =Demanda!K36 -> 282 | ... M14: =Demanda!M36 -> 373
A15: 100 kg | D15: =Demanda!D37 -> 11 | E15: =Demanda!E37 -> 18 | F15: =Demanda!F37 -> 29 | G15: =Demanda!G37 -> 49 | H15: =Demanda!H37 -> 80 | I15: =Demanda!I37 -> 110 | J15: =Demanda!J37 -> 147 | K15: =Demanda!K37 -> 186 | ... M15: =Demanda!M37 -> 247
A16: Total | D16: =SUM(D8:D15) -> 6958 | E16: =SUM(E8:E15) -> 10963 | F16: =SUM(F8:F15) -> 23077 | G16: =SUM(G8:G15) -> 50958 | H16: =SUM(H8:H15) -> 88903 | I16: =SUM(I8:I15) -> 124900 | J16: =SUM(J8:J15) -> 172353 | K16: =SUM(K8:K15) -> 220292 | ... M16: =SUM(M8:M15) -> 287333
A18: Acero neto en CUERPOS (t) — precio: chapa cortada a medida (referencia) | N18: USD/kg
A19: 2,5 kg | B19: =Nesting!$E$6 -> 1.25 | C19: =Nesting!$F$6 -> LAF | D19: =D9*Nesting!$G$6/1000 -> 0.3015018 | E19: =E9*Nesting!$G$6/1000 -> 0.72462637 | F19: =F9*Nesting!$G$6/1000 -> 1.3153655 | G19: =G9*Nesting!$G$6/1000 -> 2.6010918 | H19: =H9*Nesting!$G$6/1000 -> 4.3385598 | I19: =I9*Nesting!$G$6/1000 -> 6.1884523 | J19: =J9*Nesting!$G$6/1000 -> 8.2437747 | K19: =K9*Nesting!$G$6/1000 -> 10.453425 | ... M19: =M9*Nesting!$G$6/1000 -> 14.404632 | N19: {=INDEX(Supuestos!$F$84:$F$89,MATCH($B19,Supuestos!$A$84:$A$89,0))} -> 1.426
A20: 5 kg | B20: =Nesting!$E$7 -> 1.6 | C20: =Nesting!$F$7 -> LAF | D20: =D10*Nesting!$G$7/1000 -> 4.4481965 | E20: =E10*Nesting!$G$7/1000 -> 7.5852004 | F20: =F10*Nesting!$G$7/1000 -> 12.960105 | G20: =G10*Nesting!$G$7/1000 -> 23.611327 | H20: =H10*Nesting!$G$7/1000 -> 40.144185 | I20: =I10*Nesting!$G$7/1000 -> 56.075669 | J20: =J10*Nesting!$G$7/1000 -> 75.786937 | K20: =K10*Nesting!$G$7/1000 -> 95.926068 | ... M20: =M10*Nesting!$G$7/1000 -> 125.53142 | N20: {=INDEX(Supuestos!$F$84:$F$89,MATCH($B20,Supuestos!$A$84:$A$89,0))} -> 1.453
A21: 10 kg | B21: =Nesting!$E$8 -> 2 | C21: =Nesting!$F$8 -> LAF | D21: =D11*Nesting!$G$8/1000 -> 0.40355817 | E21: =E11*Nesting!$G$8/1000 -> 0.77641084 | F21: =F11*Nesting!$G$8/1000 -> 1.5045702 | G21: =G11*Nesting!$G$8/1000 -> 2.9521158 | H21: =H11*Nesting!$G$8/1000 -> 5.2023913 | I21: =I11*Nesting!$G$8/1000 -> 7.5360103 | J21: =J11*Nesting!$G$8/1000 -> 10.185457 | K21: =K11*Nesting!$G$8/1000 -> 12.896316 | ... M21: =M11*Nesting!$G$8/1000 -> 16.896805 | N21: {=INDEX(Supuestos!$F$84:$F$89,MATCH($B21,Supuestos!$A$84:$A$89,0))} -> 1.429
A22: 25 kg | B22: =Nesting!$E$9 -> 3.2 | C22: =Nesting!$F$9 -> LAC | D22: =D12*Nesting!$G$9/1000 -> 0.35998715 | E22: =E12*Nesting!$G$9/1000 -> 0.61409572 | F22: =F12*Nesting!$G$9/1000 -> 0.95290716 | G22: =G12*Nesting!$G$9/1000 -> 1.5881786 | H22: =H12*Nesting!$G$9/1000 -> 2.6363765 | I22: =I12*Nesting!$G$9/1000 -> 3.6739865 | J22: =J12*Nesting!$G$9/1000 -> 4.9127658 | K22: =K12*Nesting!$G$9/1000 -> 6.1938965 | ... M22: =M12*Nesting!$G$9/1000 -> 8.2055894 | N22: {=INDEX(Supuestos!$F$84:$F$89,MATCH($B22,Supuestos!$A$84:$A$89,0))} -> 1.256
A23: 50 kg | B23: =Nesting!$E$10 -> 3.2 | C23: =Nesting!$F$10 -> LAC | D23: =D13*Nesting!$G$10/1000 -> 1.201579 | E23: =E13*Nesting!$G$10/1000 -> 2.0506948 | F23: =F13*Nesting!$G$10/1000 -> 3.1721686 | G23: =G13*Nesting!$G$10/1000 -> 5.3189897 | H23: =H13*Nesting!$G$10/1000 -> 8.7795373 | I23: =I13*Nesting!$G$10/1000 -> 12.240085 | J23: =J13*Nesting!$G$10/1000 -> 16.341475 | K23: =K13*Nesting!$G$10/1000 -> 20.619096 | ... M23: =M13*Nesting!$G$10/1000 -> 27.315896 | N23: {=INDEX(Supuestos!$F$84:$F$89,MATCH($B23,Supuestos!$A$84:$A$89,0))} -> 1.256
A24: 70 kg | B24: =Nesting!$E$11 -> 4.75 | C24: =Nesting!$F$11 -> LAC | D24: =D14*Nesting!$G$11/1000 -> 0.49294658 | E24: =E14*Nesting!$G$11/1000 -> 0.89346567 | F24: =F14*Nesting!$G$11/1000 -> 1.3247939 | G24: =G14*Nesting!$G$11/1000 -> 2.2182596 | H24: =H14*Nesting!$G$11/1000 -> 3.6662902 | I24: =I14*Nesting!$G$11/1000 -> 5.1143208 | J24: =J14*Nesting!$G$11/1000 -> 6.8704429 | K24: =K14*Nesting!$G$11/1000 -> 8.6881835 | ... M24: =M14*Nesting!$G$11/1000 -> 11.491817 | N24: {=INDEX(Supuestos!$F$84:$F$89,MATCH($B24,Supuestos!$A$84:$A$89,0))} -> 1.236
A25: 100 kg | B25: =Nesting!$E$12 -> 4.75 | C25: =Nesting!$F$12 -> LAC | D25: =D15*Nesting!$G$12/1000 -> 0.44854514 | E25: =E15*Nesting!$G$12/1000 -> 0.73398296 | F25: =F15*Nesting!$G$12/1000 -> 1.1825281 | G25: =G15*Nesting!$G$12/1000 -> 1.9980647 | H25: =H15*Nesting!$G$12/1000 -> 3.2621465 | I25: =I15*Nesting!$G$12/1000 -> 4.4854514 | J25: =J15*Nesting!$G$12/1000 -> 5.9941942 | K25: =K15*Nesting!$G$12/1000 -> 7.5844906 | ... M25: =M15*Nesting!$G$12/1000 -> 10.071877 | N25: {=INDEX(Supuestos!$F$84:$F$89,MATCH($B25,Supuestos!$A$84:$A$89,0))} -> 1.236
A26: Total | D26: =SUM(D19:D25) -> 7.6563144 | E26: =SUM(E19:E25) -> 13.378477 | F26: =SUM(F19:F25) -> 22.412438 | G26: =SUM(G19:G25) -> 40.288027 | H26: =SUM(H19:H25) -> 68.029487 | I26: =SUM(I19:I25) -> 95.313975 | J26: =SUM(J19:J25) -> 128.33505 | K26: =SUM(K19:K25) -> 162.36148 | ... M26: =SUM(M19:M25) -> 213.91804
A27: de los cuales LAF | D27: =SUMIF($C$19:$C$25,"LAF",D19:D25) -> 5.1532565 | E27: =SUMIF($C$19:$C$25,"LAF",E19:E25) -> 9.0862376 | F27: =SUMIF($C$19:$C$25,"LAF",F19:F25) -> 15.78004 | G27: =SUMIF($C$19:$C$25,"LAF",G19:G25) -> 29.164534 | H27: =SUMIF($C$19:$C$25,"LAF",H19:H25) -> 49.685136 | I27: =SUMIF($C$19:$C$25,"LAF",I19:I25) -> 69.800132 | J27: =SUMIF($C$19:$C$25,"LAF",J19:J25) -> 94.216169 | K27: =SUMIF($C$19:$C$25,"LAF",K19:K25) -> 119.27581 | ... M27: =SUMIF($C$19:$C$25,"LAF",M19:M25) -> 156.83286
A28: de los cuales LAC | D28: =SUMIF($C$19:$C$25,"LAC",D19:D25) -> 2.5030579 | E28: =SUMIF($C$19:$C$25,"LAC",E19:E25) -> 4.2922392 | F28: =SUMIF($C$19:$C$25,"LAC",F19:F25) -> 6.6323978 | G28: =SUMIF($C$19:$C$25,"LAC",G19:G25) -> 11.123493 | H28: =SUMIF($C$19:$C$25,"LAC",H19:H25) -> 18.34435 | I28: =SUMIF($C$19:$C$25,"LAC",I19:I25) -> 25.513843 | J28: =SUMIF($C$19:$C$25,"LAC",J19:J25) -> 34.118877 | K28: =SUMIF($C$19:$C$25,"LAC",K19:K25) -> 43.085666 | ... M28: =SUMIF($C$19:$C$25,"LAC",M19:M25) -> 57.08518
A30: Acero neto en CÚPULAS Y FONDOS (t)
A31: Cúpula 1 kg | B31: =Nesting!$D$26 -> 0.9 | C31: =Nesting!$E$26 -> LAF | D31: =D8*Nesting!$F$26/1000 -> 0.27116086 | E31: =E8*Nesting!$F$26/1000 -> 0.3891246 | F31: =F8*Nesting!$F$26/1000 -> 0.94176328 | G31: =G8*Nesting!$F$26/1000 -> 2.2815406 | H31: =H8*Nesting!$F$26/1000 -> 4.0304925 | I31: =I8*Nesting!$F$26/1000 -> 5.6645952 | J31: =J8*Nesting!$F$26/1000 -> 7.8950052 | K31: =K8*Nesting!$F$26/1000 -> 10.130931 | ... M31: =M8*Nesting!$F$26/1000 -> 13.147376
A32: Fondo 1 kg | B32: =Nesting!$D$27 -> 0.9 | C32: =Nesting!$E$27 -> LAF | D32: =D8*Nesting!$F$27/1000 -> 0.23247673 | E32: =E8*Nesting!$F$27/1000 -> 0.33361162 | F32: =F8*Nesting!$F$27/1000 -> 0.80741022 | G32: =G8*Nesting!$F$27/1000 -> 1.9560533 | H32: =H8*Nesting!$F$27/1000 -> 3.4554977 | I32: =I8*Nesting!$F$27/1000 -> 4.8564773 | J32: =J8*Nesting!$F$27/1000 -> 6.7686944 | K32: =K8*Nesting!$F$27/1000 -> 8.6856401 | ... M32: =M8*Nesting!$F$27/1000 -> 11.271756
A33: Cúpula 2,5 kg | B33: =Nesting!$D$28 -> 1.25 | C33: =Nesting!$E$28 -> LAF | D33: =D9*Nesting!$F$28/1000 -> 0.073030236 | E33: =E9*Nesting!$F$28/1000 -> 0.17552013 | F33: =F9*Nesting!$F$28/1000 -> 0.31860988 | G33: =G9*Nesting!$F$28/1000 -> 0.63004051 | H33: =H9*Nesting!$F$28/1000 -> 1.0508927 | I33: =I9*Nesting!$F$28/1000 -> 1.4989765 | J33: =J9*Nesting!$F$28/1000 -> 1.9968199 | K33: =K9*Nesting!$F$28/1000 -> 2.5320449 | ... M33: =M9*Nesting!$F$28/1000 -> 3.4891124
A34: Fondo 2,5 kg | B34: =Nesting!$D$29 -> 1.25 | C34: =Nesting!$E$29 -> LAF | D34: =D9*Nesting!$F$29/1000 -> 0.04992523 | E34: =E9*Nesting!$F$29/1000 -> 0.11998979 | F34: =F9*Nesting!$F$29/1000 -> 0.21780939 | G34: =G9*Nesting!$F$29/1000 -> 0.43071088 | H34: =H9*Nesting!$F$29/1000 -> 0.7184156 | I34: =I9*Nesting!$F$29/1000 -> 1.0247365 | J34: =J9*Nesting!$F$29/1000 -> 1.3650743 | K34: =K9*Nesting!$F$29/1000 -> 1.730967 | ... M34: =M9*Nesting!$F$29/1000 -> 2.3852413
A35: Cúpula 5 kg | B35: =Nesting!$D$30 -> 1.6 | C35: =Nesting!$E$30 -> LAF | D35: =D10*Nesting!$F$30/1000 -> 1.0897032 | E35: =E10*Nesting!$F$30/1000 -> 1.8581952 | F35: =F10*Nesting!$F$30/1000 -> 3.1749199 | G35: =G10*Nesting!$F$30/1000 -> 5.7842182 | H35: =H10*Nesting!$F$30/1000 -> 9.8343785 | I35: =I10*Nesting!$F$30/1000 -> 13.737216 | J35: =J10*Nesting!$F$30/1000 -> 18.566012 | K35: =K10*Nesting!$F$30/1000 -> 23.499624 | ... M35: =M10*Nesting!$F$30/1000 -> 30.752237
A36: Fondo 5 kg | B36: =Nesting!$D$31 -> 1.6 | C36: =Nesting!$E$31 -> LAF | D36: =D10*Nesting!$F$31/1000 -> 0.69898881 | E36: =E10*Nesting!$F$31/1000 -> 1.191937 | F36: =F10*Nesting!$F$31/1000 -> 2.0365485 | G36: =G10*Nesting!$F$31/1000 -> 3.7102797 | H36: =H10*Nesting!$F$31/1000 -> 6.3082501 | I36: =I10*Nesting!$F$31/1000 -> 8.8117207 | J36: =J10*Nesting!$F$31/1000 -> 11.909146 | K36: =K10*Nesting!$F$31/1000 -> 15.073805 | ... M36: =M10*Nesting!$F$31/1000 -> 19.725985
A37: Cúpula 10 kg | B37: =Nesting!$D$32 -> 2 | C37: =Nesting!$E$32 -> LAF | D37: =D11*Nesting!$F$32/1000 -> 0.075704527 | E37: =E11*Nesting!$F$32/1000 -> 0.14564893 | F37: =F11*Nesting!$F$32/1000 -> 0.28224622 | G37: =G11*Nesting!$F$32/1000 -> 0.55379507 | H37: =H11*Nesting!$F$32/1000 -> 0.97593009 | I37: =I11*Nesting!$F$32/1000 -> 1.4136997 | J37: =J11*Nesting!$F$32/1000 -> 1.9107164 | K37: =K11*Nesting!$F$32/1000 -> 2.4192534 | ... M37: =M11*Nesting!$F$32/1000 -> 3.1697156
A38: Fondo 10 kg | B38: =Nesting!$D$33 -> 2 | C38: =Nesting!$E$33 -> LAF | D38: =D11*Nesting!$F$33/1000 -> 0.047795847 | E38: =E11*Nesting!$F$33/1000 -> 0.091955053 | F38: =F11*Nesting!$F$33/1000 -> 0.17819538 | G38: =G11*Nesting!$F$33/1000 -> 0.34963701 | H38: =H11*Nesting!$F$33/1000 -> 0.61615081 | I38: =I11*Nesting!$F$33/1000 -> 0.89253548 | J38: =J11*Nesting!$F$33/1000 -> 1.2063256 | K38: =K11*Nesting!$F$33/1000 -> 1.527389 | ... M38: =M11*Nesting!$F$33/1000 -> 2.0011913
A39: Total | D39: =SUM(D31:D38) -> 2.5387855 | E39: =SUM(E31:E38) -> 4.3059823 | F39: =SUM(F31:F38) -> 7.9575028 | G39: =SUM(G31:G38) -> 15.696275 | H39: =SUM(H31:H38) -> 26.990008 | I39: =SUM(I31:I38) -> 37.899958 | J39: =SUM(J31:J38) -> 51.617794 | K39: =SUM(K31:K38) -> 65.599654 | ... M39: =SUM(M31:M38) -> 85.942614
A41: ACERO NETO TOTAL EN PIEZAS (t) | D41: =D26+D39 -> 10.1951 | E41: =E26+E39 -> 17.684459 | F41: =F26+F39 -> 30.369941 | G41: =G26+G39 -> 55.984302 | H41: =H26+H39 -> 95.019494 | I41: =I26+I39 -> 133.21393 | J41: =J26+J39 -> 179.95284 | K41: =K26+K39 -> 227.96113 | ... M41: =M26+M39 -> 299.86065
A43: OPCIÓN A — cuerpos: bobina de ancho estándar comprada (t) | N43: USD/kg
A44: cuerpo 2,5 kg | B44: =Nesting!$E$6 -> 1.25 | C44: =Nesting!$F$6 -> LAF | D44: =D19/Nesting!$W$6 -> 0.31965465 | E44: =E19/Nesting!$W$6 -> 0.76825473 | F44: =F19/Nesting!$W$6 -> 1.3945611 | G44: =G19/Nesting!$W$6 -> 2.7576986 | H44: =H19/Nesting!$W$6 -> 4.5997762 | I44: =I19/Nesting!$W$6 -> 6.5610471 | J44: =J19/Nesting!$W$6 -> 8.7401166 | K44: =K19/Nesting!$W$6 -> 11.082806 | ... M44: =M19/Nesting!$W$6 -> 15.271907 | N44: {=INDEX(Supuestos!$B$84:$B$89,MATCH($B44,Supuestos!$A$84:$A$89,0))} -> 1.25056
A45: cuerpo 5 kg | B45: =Nesting!$E$7 -> 1.6 | C45: =Nesting!$F$7 -> LAF | D45: =D20/Nesting!$W$7 -> 4.5157063 | E45: =E20/Nesting!$W$7 -> 7.7003202 | F45: =F20/Nesting!$W$7 -> 13.156799 | G45: =G20/Nesting!$W$7 -> 23.969673 | H45: =H20/Nesting!$W$7 -> 40.753449 | I45: =I20/Nesting!$W$7 -> 56.926724 | J45: =J20/Nesting!$W$7 -> 76.937147 | K45: =K20/Nesting!$W$7 -> 97.381928 | ... M45: =M20/Nesting!$W$7 -> 127.4366 | N45: {=INDEX(Supuestos!$B$84:$B$89,MATCH($B45,Supuestos!$A$84:$A$89,0))} -> 1.25056
A46: cuerpo 10 kg | B46: =Nesting!$E$8 -> 2 | C46: =Nesting!$F$8 -> LAF | D46: =D21/Nesting!$W$8 -> 0.40968293 | E46: =E21/Nesting!$W$8 -> 0.78819434 | F46: =F21/Nesting!$W$8 -> 1.5274049 | G46: =G21/Nesting!$W$8 -> 2.9969197 | H46: =H21/Nesting!$W$8 -> 5.2813474 | I46: =I21/Nesting!$W$8 -> 7.6503835 | J46: =J21/Nesting!$W$8 -> 10.340041 | K46: =K21/Nesting!$W$8 -> 13.092042 | ... M46: =M21/Nesting!$W$8 -> 17.153246 | N46: {=INDEX(Supuestos!$B$84:$B$89,MATCH($B46,Supuestos!$A$84:$A$89,0))} -> 1.26285
A47: cuerpo 25 kg | B47: =Nesting!$E$9 -> 3.2 | C47: =Nesting!$F$9 -> LAC | D47: =D22/Nesting!$W$9 -> 0.36917972 | E47: =E22/Nesting!$W$9 -> 0.62977717 | F47: =F22/Nesting!$W$9 -> 0.97724044 | G47: =G22/Nesting!$W$9 -> 1.6287341 | H47: =H22/Nesting!$W$9 -> 2.7036986 | I47: =I22/Nesting!$W$9 -> 3.7678048 | J47: =J22/Nesting!$W$9 -> 5.0382174 | K47: =K22/Nesting!$W$9 -> 6.3520629 | ... M47: =M22/Nesting!$W$9 -> 8.415126 | N47: {=INDEX(Supuestos!$B$84:$B$89,MATCH($B47,Supuestos!$A$84:$A$89,0))} -> 1.11373
A48: cuerpo 50 kg | B48: =Nesting!$E$10 -> 3.2 | C48: =Nesting!$F$10 -> LAC | D48: =D23/Nesting!$W$10 -> 1.4151763 | E48: =E23/Nesting!$W$10 -> 2.4152342 | F48: =F23/Nesting!$W$10 -> 3.7360654 | G48: =G23/Nesting!$W$10 -> 6.2645137 | H48: =H23/Nesting!$W$10 -> 10.340221 | I48: =I23/Nesting!$W$10 -> 14.415929 | J48: =J23/Nesting!$W$10 -> 19.246397 | K48: =K23/Nesting!$W$10 -> 24.284425 | ... M48: =M23/Nesting!$W$10 -> 32.171674 | N48: {=INDEX(Supuestos!$B$84:$B$89,MATCH($B48,Supuestos!$A$84:$A$89,0))} -> 1.11373
A49: cuerpo 70 kg | B49: =Nesting!$E$11 -> 4.75 | C49: =Nesting!$F$11 -> LAC | D49: =D24/Nesting!$W$11 -> 0.50891296 | E49: =E24/Nesting!$W$11 -> 0.92240473 | F49: =F24/Nesting!$W$11 -> 1.3677036 | G49: =G24/Nesting!$W$11 -> 2.2901083 | H49: =H24/Nesting!$W$11 -> 3.7850401 | I49: =I24/Nesting!$W$11 -> 5.2799719 | J49: =J24/Nesting!$W$11 -> 7.0929743 | K49: =K24/Nesting!$W$11 -> 8.9695909 | ... M49: =M24/Nesting!$W$11 -> 11.864033 | N49: {=INDEX(Supuestos!$B$84:$B$89,MATCH($B49,Supuestos!$A$84:$A$89,0))} -> 1.11373
A50: cuerpo 100 kg | B50: =Nesting!$E$12 -> 4.75 | C50: =Nesting!$F$12 -> LAC | D50: =D25/Nesting!$W$12 -> 0.46307337 | E50: =E25/Nesting!$W$12 -> 0.75775642 | F50: =F25/Nesting!$W$12 -> 1.2208298 | G50: =G25/Nesting!$W$12 -> 2.0627814 | H50: =H25/Nesting!$W$12 -> 3.3678063 | I50: =I25/Nesting!$W$12 -> 4.6307337 | J50: =J25/Nesting!$W$12 -> 6.1883441 | K50: =K25/Nesting!$W$12 -> 7.8301497 | ... M50: =M25/Nesting!$W$12 -> 10.398102 | N50: {=INDEX(Supuestos!$B$84:$B$89,MATCH($B50,Supuestos!$A$84:$A$89,0))} -> 1.11373
A51: Total | D51: =SUM(D44:D50) -> 8.0013863 | E51: =SUM(E44:E50) -> 13.981942 | F51: =SUM(F44:F50) -> 23.380604 | G51: =SUM(G44:G50) -> 41.970429 | H51: =SUM(H44:H50) -> 70.831339 | I51: =SUM(I44:I50) -> 99.232594 | J51: =SUM(J44:J50) -> 133.58324 | K51: =SUM(K44:K50) -> 168.993 | ... M51: =SUM(M44:M50) -> 222.71068
A52: de los cuales LAF | D52: =SUMIF($C$44:$C$50,"LAF",D44:D50) -> 5.2450439 | E52: =SUMIF($C$44:$C$50,"LAF",E44:E50) -> 9.2567692 | F52: =SUMIF($C$44:$C$50,"LAF",F44:F50) -> 16.078765 | G52: =SUMIF($C$44:$C$50,"LAF",G44:G50) -> 29.724292 | H52: =SUMIF($C$44:$C$50,"LAF",H44:H50) -> 50.634573 | I52: =SUMIF($C$44:$C$50,"LAF",I44:I50) -> 71.138154 | J52: =SUMIF($C$44:$C$50,"LAF",J44:J50) -> 96.017305 | K52: =SUMIF($C$44:$C$50,"LAF",K44:K50) -> 121.55678 | ... M52: =SUMIF($C$44:$C$50,"LAF",M44:M50) -> 159.86175
A53: de los cuales LAC | D53: =SUMIF($C$44:$C$50,"LAC",D44:D50) -> 2.7563423 | E53: =SUMIF($C$44:$C$50,"LAC",E44:E50) -> 4.7251725 | F53: =SUMIF($C$44:$C$50,"LAC",F44:F50) -> 7.3018392 | G53: =SUMIF($C$44:$C$50,"LAC",G44:G50) -> 12.246137 | H53: =SUMIF($C$44:$C$50,"LAC",H44:H50) -> 20.196766 | I53: =SUMIF($C$44:$C$50,"LAC",I44:I50) -> 28.09444 | J53: =SUMIF($C$44:$C$50,"LAC",J44:J50) -> 37.565933 | K53: =SUMIF($C$44:$C$50,"LAC",K44:K50) -> 47.436228 | ... M53: =SUMIF($C$44:$C$50,"LAC",M44:M50) -> 62.848936
A55: OPCIÓN A — golpes de la línea de corte
A56: 2,5 kg | B56: =Nesting!$E$6 -> 1.25 | C56: =Nesting!$F$6 -> LAF | D56: =D9/Nesting!$U$6 -> 98.333333 | E56: =E9/Nesting!$U$6 -> 236.33333 | F56: =F9/Nesting!$U$6 -> 429 | G56: =G9/Nesting!$U$6 -> 848.33333 | H56: =H9/Nesting!$U$6 -> 1415 | I56: =I9/Nesting!$U$6 -> 2018.3333 | J56: =J9/Nesting!$U$6 -> 2688.6667 | K56: =K9/Nesting!$U$6 -> 3409.3333 | ... M56: =M9/Nesting!$U$6 -> 4698
A57: 5 kg | B57: =Nesting!$E$7 -> 1.6 | C57: =Nesting!$F$7 -> LAF | D57: =D10/Nesting!$U$7 -> 752 | E57: =E10/Nesting!$U$7 -> 1282.3333 | F57: =F10/Nesting!$U$7 -> 2191 | G57: =G10/Nesting!$U$7 -> 3991.6667 | H57: =H10/Nesting!$U$7 -> 6786.6667 | I57: =I10/Nesting!$U$7 -> 9480 | J57: =J10/Nesting!$U$7 -> 12812.333 | K57: =K10/Nesting!$U$7 -> 16217 | ... M57: =M10/Nesting!$U$7 -> 21222
A58: 10 kg | B58: =Nesting!$E$8 -> 2 | C58: =Nesting!$F$8 -> LAF | D58: =D11/Nesting!$U$8 -> 46 | E58: =E11/Nesting!$U$8 -> 88.5 | F58: =F11/Nesting!$U$8 -> 171.5 | G58: =G11/Nesting!$U$8 -> 336.5 | H58: =H11/Nesting!$U$8 -> 593 | I58: =I11/Nesting!$U$8 -> 859 | J58: =J11/Nesting!$U$8 -> 1161 | K58: =K11/Nesting!$U$8 -> 1470 | ... M58: =M11/Nesting!$U$8 -> 1926
A59: 25 kg | B59: =Nesting!$E$9 -> 3.2 | C59: =Nesting!$F$9 -> LAC | D59: =D12/Nesting!$U$9 -> 11.333333 | E59: =E12/Nesting!$U$9 -> 19.333333 | F59: =F12/Nesting!$U$9 -> 30 | G59: =G12/Nesting!$U$9 -> 50 | H59: =H12/Nesting!$U$9 -> 83 | I59: =I12/Nesting!$U$9 -> 115.66667 | J59: =J12/Nesting!$U$9 -> 154.66667 | K59: =K12/Nesting!$U$9 -> 195 | ... M59: =M12/Nesting!$U$9 -> 258.33333
A60: 50 kg | B60: =Nesting!$E$10 -> 3.2 | C60: =Nesting!$F$10 -> LAC | D60: =D13/Nesting!$U$10 -> 37.5 | E60: =E13/Nesting!$U$10 -> 64 | F60: =F13/Nesting!$U$10 -> 99 | G60: =G13/Nesting!$U$10 -> 166 | H60: =H13/Nesting!$U$10 -> 274 | I60: =I13/Nesting!$U$10 -> 382 | J60: =J13/Nesting!$U$10 -> 510 | K60: =K13/Nesting!$U$10 -> 643.5 | ... M60: =M13/Nesting!$U$10 -> 852.5
A61: 70 kg | B61: =Nesting!$E$11 -> 4.75 | C61: =Nesting!$F$11 -> LAC | D61: =D14/Nesting!$U$11 -> 16 | E61: =E14/Nesting!$U$11 -> 29 | F61: =F14/Nesting!$U$11 -> 43 | G61: =G14/Nesting!$U$11 -> 72 | H61: =H14/Nesting!$U$11 -> 119 | I61: =I14/Nesting!$U$11 -> 166 | J61: =J14/Nesting!$U$11 -> 223 | K61: =K14/Nesting!$U$11 -> 282 | ... M61: =M14/Nesting!$U$11 -> 373
A62: 100 kg | B62: =Nesting!$E$12 -> 4.75 | C62: =Nesting!$F$12 -> LAC | D62: =D15/Nesting!$U$12 -> 11 | E62: =E15/Nesting!$U$12 -> 18 | F62: =F15/Nesting!$U$12 -> 29 | G62: =G15/Nesting!$U$12 -> 49 | H62: =H15/Nesting!$U$12 -> 80 | I62: =I15/Nesting!$U$12 -> 110 | J62: =J15/Nesting!$U$12 -> 147 | K62: =K15/Nesting!$U$12 -> 186 | ... M62: =M15/Nesting!$U$12 -> 247
A63: Total | D63: =SUM(D56:D62) -> 972.16667 | E63: =SUM(E56:E62) -> 1737.5 | F63: =SUM(F56:F62) -> 2992.5 | G63: =SUM(G56:G62) -> 5513.5 | H63: =SUM(H56:H62) -> 9350.6667 | I63: =SUM(I56:I62) -> 13131 | J63: =SUM(J56:J62) -> 17696.667 | K63: =SUM(K56:K62) -> 22402.833 | ... M63: =SUM(M56:M62) -> 29576.833
A65: OPCIÓN A, D y REFERENCIA — discos: fleje a medida comprado (t) | N65: USD/kg
A66: fleje Cúpula 1 kg | B66: =Nesting!$D$26 -> 0.9 | C66: =Nesting!$E$26 -> LAF | D66: =D31/Nesting!$X$26 -> 0.37643878 | E66: =E31/Nesting!$X$26 -> 0.54020182 | F66: =F31/Nesting!$X$26 -> 1.3074019 | G66: =G31/Nesting!$X$26 -> 3.1673464 | H66: =H31/Nesting!$X$26 -> 5.595327 | I66: =I31/Nesting!$X$26 -> 7.8638684 | J66: =J31/Nesting!$X$26 -> 10.960233 | K66: =K31/Nesting!$X$26 -> 14.064254 | ... M66: =M31/Nesting!$X$26 -> 18.251831 | N66: {=INDEX(Supuestos!$D$84:$D$89,MATCH($B66,Supuestos!$A$84:$A$89,0))} -> 1.26285
A67: fleje Fondo 1 kg | B67: =Nesting!$D$27 -> 0.9 | C67: =Nesting!$E$27 -> LAF | D67: =D32/Nesting!$X$27 -> 0.32479521 | E67: =E32/Nesting!$X$27 -> 0.46609163 | F67: =F32/Nesting!$X$27 -> 1.1280397 | G67: =G32/Nesting!$X$27 -> 2.7328187 | H67: =H32/Nesting!$X$27 -> 4.8277051 | I67: =I32/Nesting!$X$27 -> 6.7850257 | J67: =J32/Nesting!$X$27 -> 9.4566004 | K67: =K32/Nesting!$X$27 -> 12.134781 | ... M67: =M32/Nesting!$X$27 -> 15.747866 | N67: {=INDEX(Supuestos!$D$84:$D$89,MATCH($B67,Supuestos!$A$84:$A$89,0))} -> 1.26285
A68: fleje Cúpula 2,5 kg | B68: =Nesting!$D$28 -> 1.25 | C68: =Nesting!$E$28 -> LAF | D68: =D33/Nesting!$X$28 -> 0.1061659 | E68: =E33/Nesting!$X$28 -> 0.25515806 | F68: =F33/Nesting!$X$28 -> 0.46317125 | G68: =G33/Nesting!$X$28 -> 0.91590585 | H68: =H33/Nesting!$X$28 -> 1.5277094 | I68: =I33/Nesting!$X$28 -> 2.1791002 | J68: =J33/Nesting!$X$28 -> 2.9028277 | K68: =K33/Nesting!$X$28 -> 3.6808979 | ... M68: =M33/Nesting!$X$28 -> 5.072211 | N68: {=INDEX(Supuestos!$D$84:$D$89,MATCH($B68,Supuestos!$A$84:$A$89,0))} -> 1.186
A69: fleje Fondo 2,5 kg | B69: =Nesting!$D$29 -> 1.25 | C69: =Nesting!$E$29 -> LAF | D69: =D34/Nesting!$X$29 -> 0.088082701 | E69: =E34/Nesting!$X$29 -> 0.21169707 | F69: =F34/Nesting!$X$29 -> 0.38427944 | G69: =G34/Nesting!$X$29 -> 0.75989991 | H69: =H34/Nesting!$X$29 -> 1.2674951 | I69: =I34/Nesting!$X$29 -> 1.8079348 | J69: =J34/Nesting!$X$29 -> 2.4083901 | K69: =K34/Nesting!$X$29 -> 3.0539317 | ... M69: =M34/Nesting!$X$29 -> 4.208263 | N69: {=INDEX(Supuestos!$D$84:$D$89,MATCH($B69,Supuestos!$A$84:$A$89,0))} -> 1.186
A70: fleje Cúpula 5 kg | B70: =Nesting!$D$30 -> 1.6 | C70: =Nesting!$E$30 -> LAF | D70: =D35/Nesting!$X$30 -> 1.598817 | E70: =E35/Nesting!$X$30 -> 2.7263515 | F70: =F35/Nesting!$X$30 -> 4.6582554 | G70: =G35/Nesting!$X$30 -> 8.4866283 | H70: =H35/Nesting!$X$30 -> 14.42904 | I70: =I35/Nesting!$X$30 -> 20.155299 | J70: =J35/Nesting!$X$30 -> 27.240128 | K70: =K35/Nesting!$X$30 -> 34.478744 | ... M70: =M35/Nesting!$X$30 -> 45.119806 | N70: {=INDEX(Supuestos!$D$84:$D$89,MATCH($B70,Supuestos!$A$84:$A$89,0))} -> 1.186
A71: fleje Fondo 5 kg | B71: =Nesting!$D$31 -> 1.6 | C71: =Nesting!$E$31 -> LAF | D71: =D36/Nesting!$X$31 -> 1.0278109 | E71: =E36/Nesting!$X$31 -> 1.7526545 | F71: =F36/Nesting!$X$31 -> 2.9945927 | G71: =G36/Nesting!$X$31 -> 5.4556896 | H71: =H36/Nesting!$X$31 -> 9.2758114 | I71: =I36/Nesting!$X$31 -> 12.956978 | J71: =J36/Nesting!$X$31 -> 17.511511 | K71: =K36/Nesting!$X$31 -> 22.164907 | ... M71: =M36/Nesting!$X$31 -> 29.00559 | N71: {=INDEX(Supuestos!$D$84:$D$89,MATCH($B71,Supuestos!$A$84:$A$89,0))} -> 1.186
A72: fleje Cúpula 10 kg | B72: =Nesting!$D$32 -> 2 | C72: =Nesting!$E$32 -> LAF | D72: =D37/Nesting!$X$32 -> 0.11395444 | E72: =E37/Nesting!$X$32 -> 0.21923843 | F72: =F37/Nesting!$X$32 -> 0.42485187 | G72: =G37/Nesting!$X$32 -> 0.83360147 | H72: =H37/Nesting!$X$32 -> 1.4690213 | I72: =I37/Nesting!$X$32 -> 2.1279752 | J72: =J37/Nesting!$X$32 -> 2.8761109 | K72: =K37/Nesting!$X$32 -> 3.6415874 | ... M72: =M37/Nesting!$X$32 -> 4.7712227 | N72: {=INDEX(Supuestos!$D$84:$D$89,MATCH($B72,Supuestos!$A$84:$A$89,0))} -> 1.198
A73: fleje Fondo 10 kg | B73: =Nesting!$D$33 -> 2 | C73: =Nesting!$E$33 -> LAF | D73: =D38/Nesting!$X$33 -> 0.075375839 | E73: =E38/Nesting!$X$33 -> 0.14501656 | F73: =F38/Nesting!$X$33 -> 0.28102079 | G73: =G38/Nesting!$X$33 -> 0.55139065 | H73: =H38/Nesting!$X$33 -> 0.97169288 | I73: =I38/Nesting!$X$33 -> 1.4075619 | J73: =J38/Nesting!$X$33 -> 1.9024206 | K73: =K38/Nesting!$X$33 -> 2.4087496 | ... M73: =M38/Nesting!$X$33 -> 3.1559536 | N73: {=INDEX(Supuestos!$D$84:$D$89,MATCH($B73,Supuestos!$A$84:$A$89,0))} -> 1.198
A74: Total | D74: =SUM(D66:D73) -> 3.7114408 | E74: =SUM(E66:E73) -> 6.3164096 | F74: =SUM(F66:F73) -> 11.641613 | G74: =SUM(G66:G73) -> 22.903281 | H74: =SUM(H66:H73) -> 39.363802 | I74: =SUM(I66:I73) -> 55.283744 | J74: =SUM(J66:J73) -> 75.258221 | K74: =SUM(K66:K73) -> 95.627852 | ... M74: =SUM(M66:M73) -> 125.33274
A76: OPCIÓN B — hojas mixtas 70/100 kg (cantidad)
A77: Hojas mixtas | B77: =Nesting!$E$11 -> 4.75 | C77: =Nesting!$F$11 -> LAC | D77: =IF(Nesting!$G$22="SI",MIN(D15/Nesting!$G$15,D14/Nesting!$G$16),0) -> 5.3333333 | E77: =IF(Nesting!$G$22="SI",MIN(E15/Nesting!$G$15,E14/Nesting!$G$16),0) -> 9.6666667 | F77: =IF(Nesting!$G$22="SI",MIN(F15/Nesting!$G$15,F14/Nesting!$G$16),0) -> 14.333333 | G77: =IF(Nesting!$G$22="SI",MIN(G15/Nesting!$G$15,G14/Nesting!$G$16),0) -> 24 | H77: =IF(Nesting!$G$22="SI",MIN(H15/Nesting!$G$15,H14/Nesting!$G$16),0) -> 39.666667 | I77: =IF(Nesting!$G$22="SI",MIN(I15/Nesting!$G$15,I14/Nesting!$G$16),0) -> 55.333333 | J77: =IF(Nesting!$G$22="SI",MIN(J15/Nesting!$G$15,J14/Nesting!$G$16),0) -> 74.333333 | K77: =IF(Nesting!$G$22="SI",MIN(K15/Nesting!$G$15,K14/Nesting!$G$16),0) -> 94 | ... M77: =IF(Nesting!$G$22="SI",MIN(M15/Nesting!$G$15,M14/Nesting!$G$16),0) -> 124.33333
A79: OPCIÓN B — hojas para cuerpos (cantidad)
A80: cuerpo 2,5 kg | B80: =Nesting!$E$6 -> 1.25 | C80: =Nesting!$F$6 -> LAF | D80: =D9/Nesting!$L$6 -> 10.925926 | E80: =E9/Nesting!$L$6 -> 26.259259 | F80: =F9/Nesting!$L$6 -> 47.666667 | G80: =G9/Nesting!$L$6 -> 94.259259 | H80: =H9/Nesting!$L$6 -> 157.22222 | I80: =I9/Nesting!$L$6 -> 224.25926 | J80: =J9/Nesting!$L$6 -> 298.74074 | K80: =K9/Nesting!$L$6 -> 378.81481 | ... M80: =M9/Nesting!$L$6 -> 522
A81: cuerpo 5 kg | B81: =Nesting!$E$7 -> 1.6 | C81: =Nesting!$F$7 -> LAF | D81: =D10/Nesting!$L$7 -> 188 | E81: =E10/Nesting!$L$7 -> 320.58333 | F81: =F10/Nesting!$L$7 -> 547.75 | G81: =G10/Nesting!$L$7 -> 997.91667 | H81: =H10/Nesting!$L$7 -> 1696.6667 | I81: =I10/Nesting!$L$7 -> 2370 | J81: =J10/Nesting!$L$7 -> 3203.0833 | K81: =K10/Nesting!$L$7 -> 4054.25 | ... M81: =M10/Nesting!$L$7 -> 5305.5
A82: cuerpo 10 kg | B82: =Nesting!$E$8 -> 2 | C82: =Nesting!$F$8 -> LAF | D82: =D11/Nesting!$L$8 -> 6.1333333 | E82: =E11/Nesting!$L$8 -> 11.8 | F82: =F11/Nesting!$L$8 -> 22.866667 | G82: =G11/Nesting!$L$8 -> 44.866667 | H82: =H11/Nesting!$L$8 -> 79.066667 | I82: =I11/Nesting!$L$8 -> 114.53333 | J82: =J11/Nesting!$L$8 -> 154.8 | K82: =K11/Nesting!$L$8 -> 196 | ... M82: =M11/Nesting!$L$8 -> 256.8
A83: cuerpo 25 kg | B83: =Nesting!$E$9 -> 3.2 | C83: =Nesting!$F$9 -> LAC | D83: =D12/Nesting!$L$9 -> 3.7777778 | E83: =E12/Nesting!$L$9 -> 6.4444444 | F83: =F12/Nesting!$L$9 -> 10 | G83: =G12/Nesting!$L$9 -> 16.666667 | H83: =H12/Nesting!$L$9 -> 27.666667 | I83: =I12/Nesting!$L$9 -> 38.555556 | J83: =J12/Nesting!$L$9 -> 51.555556 | K83: =K12/Nesting!$L$9 -> 65 | ... M83: =M12/Nesting!$L$9 -> 86.111111
A84: cuerpo 50 kg | B84: =Nesting!$E$10 -> 3.2 | C84: =Nesting!$F$10 -> LAC | D84: =D13/Nesting!$L$10 -> 12.5 | E84: =E13/Nesting!$L$10 -> 21.333333 | F84: =F13/Nesting!$L$10 -> 33 | G84: =G13/Nesting!$L$10 -> 55.333333 | H84: =H13/Nesting!$L$10 -> 91.333333 | I84: =I13/Nesting!$L$10 -> 127.33333 | J84: =J13/Nesting!$L$10 -> 170 | K84: =K13/Nesting!$L$10 -> 214.5 | ... M84: =M13/Nesting!$L$10 -> 284.16667
A85: cuerpo 70 kg | B85: =Nesting!$E$11 -> 4.75 | C85: =Nesting!$F$11 -> LAC | D85: =(D14-Nesting!$G$16*D77)/Nesting!$L$11 -> 0 | E85: =(E14-Nesting!$G$16*E77)/Nesting!$L$11 -> 0 | F85: =(F14-Nesting!$G$16*F77)/Nesting!$L$11 -> 0 | G85: =(G14-Nesting!$G$16*G77)/Nesting!$L$11 -> 0 | H85: =(H14-Nesting!$G$16*H77)/Nesting!$L$11 -> 0 | I85: =(I14-Nesting!$G$16*I77)/Nesting!$L$11 -> 0 | J85: =(J14-Nesting!$G$16*J77)/Nesting!$L$11 -> 0 | K85: =(K14-Nesting!$G$16*K77)/Nesting!$L$11 -> 0 | ... M85: =(M14-Nesting!$G$16*M77)/Nesting!$L$11 -> 0
A86: cuerpo 100 kg | B86: =Nesting!$E$12 -> 4.75 | C86: =Nesting!$F$12 -> LAC | D86: =(D15-Nesting!$G$15*D77)/Nesting!$L$12 -> 1.8888889 | E86: =(E15-Nesting!$G$15*E77)/Nesting!$L$12 -> 2.7777778 | F86: =(F15-Nesting!$G$15*F77)/Nesting!$L$12 -> 4.8888889 | G86: =(G15-Nesting!$G$15*G77)/Nesting!$L$12 -> 8.3333333 | H86: =(H15-Nesting!$G$15*H77)/Nesting!$L$12 -> 13.444444 | I86: =(I15-Nesting!$G$15*I77)/Nesting!$L$12 -> 18.222222 | J86: =(J15-Nesting!$G$15*J77)/Nesting!$L$12 -> 24.222222 | K86: =(K15-Nesting!$G$15*K77)/Nesting!$L$12 -> 30.666667 | ... M86: =(M15-Nesting!$G$15*M77)/Nesting!$L$12 -> 40.888889
A87: Hojas mixtas 70/100 | B87: =Nesting!$E$11 -> 4.75 | C87: =Nesting!$F$11 -> LAC | D87: =D77 -> 5.3333333 | E87: =E77 -> 9.6666667 | F87: =F77 -> 14.333333 | G87: =G77 -> 24 | H87: =H77 -> 39.666667 | I87: =I77 -> 55.333333 | J87: =J77 -> 74.333333 | K87: =K77 -> 94 | ... M87: =M77 -> 124.33333
A88: Total | D88: =SUM(D80:D87) -> 228.55926 | E88: =SUM(E80:E87) -> 398.86481 | F88: =SUM(F80:F87) -> 680.50556 | G88: =SUM(G80:G87) -> 1241.3759 | H88: =SUM(H80:H87) -> 2105.0667 | I88: =SUM(I80:I87) -> 2948.237 | J88: =SUM(J80:J87) -> 3976.7352 | K88: =SUM(K80:K87) -> 5033.2315 | ... M88: =SUM(M80:M87) -> 6619.8
A90: OPCIÓN B — acero en hojas para cuerpos (t) | N90: USD/kg
A91: cuerpo 2,5 kg | B91: =Nesting!$E$6 -> 1.25 | C91: =Nesting!$F$6 -> LAF | D91: =D80*Nesting!$N$6/1000 -> 0.31995776 | E91: =E80*Nesting!$N$6/1000 -> 0.76898324 | F91: =F80*Nesting!$N$6/1000 -> 1.3958835 | G91: =G80*Nesting!$N$6/1000 -> 2.7603136 | H91: =H80*Nesting!$N$6/1000 -> 4.604138 | I91: =I80*Nesting!$N$6/1000 -> 6.5672687 | J91: =J80*Nesting!$N$6/1000 -> 8.7484045 | K91: =K80*Nesting!$N$6/1000 -> 11.093315 | ... M91: =M80*Nesting!$N$6/1000 -> 15.286389 | N91: {=INDEX(Supuestos!$C$84:$C$89,MATCH($B91,Supuestos!$A$84:$A$89,0))} -> 1.2902977
A92: cuerpo 5 kg | B92: =Nesting!$E$7 -> 1.6 | C92: =Nesting!$F$7 -> LAF | D92: =D81*Nesting!$N$7/1000 -> 4.734592 | E92: =E81*Nesting!$N$7/1000 -> 8.0735707 | F92: =F81*Nesting!$N$7/1000 -> 13.794536 | G92: =G81*Nesting!$N$7/1000 -> 25.131533 | H92: =H81*Nesting!$N$7/1000 -> 42.728853 | I92: =I81*Nesting!$N$7/1000 -> 59.68608 | J92: =J81*Nesting!$N$7/1000 -> 80.666451 | K92: =K81*Nesting!$N$7/1000 -> 102.10223 | ... M92: =M81*Nesting!$N$7/1000 -> 133.61371 | N92: {=INDEX(Supuestos!$C$84:$C$89,MATCH($B92,Supuestos!$A$84:$A$89,0))} -> 1.327521
A93: cuerpo 10 kg | B93: =Nesting!$E$8 -> 2 | C93: =Nesting!$F$8 -> LAF | D93: =D82*Nesting!$N$8/1000 -> 0.434424 | E93: =E82*Nesting!$N$8/1000 -> 0.835794 | F93: =F82*Nesting!$N$8/1000 -> 1.619646 | G93: =G82*Nesting!$N$8/1000 -> 3.177906 | H93: =H82*Nesting!$N$8/1000 -> 5.600292 | I93: =I82*Nesting!$N$8/1000 -> 8.112396 | J93: =J82*Nesting!$N$8/1000 -> 10.964484 | K93: =K82*Nesting!$N$8/1000 -> 13.88268 | ... M93: =M82*Nesting!$N$8/1000 -> 18.189144 | N93: {=INDEX(Supuestos!$C$84:$C$89,MATCH($B93,Supuestos!$A$84:$A$89,0))} -> 1.2804013
A94: cuerpo 25 kg | B94: =Nesting!$E$9 -> 3.2 | C94: =Nesting!$F$9 -> LAC | D94: =D83*Nesting!$N$9/1000 -> 0.428128 | E94: =E83*Nesting!$N$9/1000 -> 0.730336 | F94: =F83*Nesting!$N$9/1000 -> 1.13328 | G94: =G83*Nesting!$N$9/1000 -> 1.8888 | H94: =H83*Nesting!$N$9/1000 -> 3.135408 | I94: =I83*Nesting!$N$9/1000 -> 4.369424 | J94: =J83*Nesting!$N$9/1000 -> 5.842688 | K94: =K83*Nesting!$N$9/1000 -> 7.36632 | ... M94: =M83*Nesting!$N$9/1000 -> 9.7588 | N94: {=INDEX(Supuestos!$C$84:$C$89,MATCH($B94,Supuestos!$A$84:$A$89,0))} -> 1.1019353
A95: cuerpo 50 kg | B95: =Nesting!$E$10 -> 3.2 | C95: =Nesting!$F$10 -> LAC | D95: =D84*Nesting!$N$10/1000 -> 1.4166 | E95: =E84*Nesting!$N$10/1000 -> 2.417664 | F95: =F84*Nesting!$N$10/1000 -> 3.739824 | G95: =G84*Nesting!$N$10/1000 -> 6.270816 | H95: =H84*Nesting!$N$10/1000 -> 10.350624 | I95: =I84*Nesting!$N$10/1000 -> 14.430432 | J95: =J84*Nesting!$N$10/1000 -> 19.26576 | K95: =K84*Nesting!$N$10/1000 -> 24.308856 | ... M95: =M84*Nesting!$N$10/1000 -> 32.20404 | N95: {=INDEX(Supuestos!$C$84:$C$89,MATCH($B95,Supuestos!$A$84:$A$89,0))} -> 1.1019353
A96: cuerpo 70 kg | B96: =Nesting!$E$11 -> 4.75 | C96: =Nesting!$F$11 -> LAC | D96: =D85*Nesting!$N$11/1000 -> 0 | E96: =E85*Nesting!$N$11/1000 -> 0 | F96: =F85*Nesting!$N$11/1000 -> 0 | G96: =G85*Nesting!$N$11/1000 -> 0 | H96: =H85*Nesting!$N$11/1000 -> 0 | I96: =I85*Nesting!$N$11/1000 -> 0 | J96: =J85*Nesting!$N$11/1000 -> 0 | K96: =K85*Nesting!$N$11/1000 -> 0 | ... M96: =M85*Nesting!$N$11/1000 -> 0 | N96: {=INDEX(Supuestos!$C$84:$C$89,MATCH($B96,Supuestos!$A$84:$A$89,0))} -> 1.0909773
A97: cuerpo 100 kg | B97: =Nesting!$E$12 -> 4.75 | C97: =Nesting!$F$12 -> LAC | D97: =D86*Nesting!$N$12/1000 -> 0.31775125 | E97: =E86*Nesting!$N$12/1000 -> 0.46728125 | F97: =F86*Nesting!$N$12/1000 -> 0.822415 | G97: =G86*Nesting!$N$12/1000 -> 1.4018438 | H97: =H86*Nesting!$N$12/1000 -> 2.2616412 | I97: =I86*Nesting!$N$12/1000 -> 3.065365 | J97: =J86*Nesting!$N$12/1000 -> 4.0746925 | K97: =K86*Nesting!$N$12/1000 -> 5.158785 | ... M97: =M86*Nesting!$N$12/1000 -> 6.87838 | N97: {=INDEX(Supuestos!$C$84:$C$89,MATCH($B97,Supuestos!$A$84:$A$89,0))} -> 1.0909773
A98: Hojas mixtas 70/100 | B98: =Nesting!$E$11 -> 4.75 | C98: =Nesting!$F$11 -> LAC | D98: =D87*Nesting!$G$20/1000 -> 0.89718 | E98: =E87*Nesting!$G$20/1000 -> 1.6261387 | F98: =F87*Nesting!$G$20/1000 -> 2.4111713 | G98: =G87*Nesting!$G$20/1000 -> 4.03731 | H98: =H87*Nesting!$G$20/1000 -> 6.6727763 | I98: =I87*Nesting!$G$20/1000 -> 9.3082425 | J98: =J87*Nesting!$G$20/1000 -> 12.504446 | K98: =K87*Nesting!$G$20/1000 -> 15.812798 | ... M98: =M87*Nesting!$G$20/1000 -> 20.915509 | N98: {=INDEX(Supuestos!$C$84:$C$89,MATCH($B98,Supuestos!$A$84:$A$89,0))} -> 1.0909773
A99: Total | D99: =SUM(D91:D98) -> 8.548633 | E99: =SUM(E91:E98) -> 14.919768 | F99: =SUM(F91:F98) -> 24.916756 | G99: =SUM(G91:G98) -> 44.668523 | H99: =SUM(H91:H98) -> 75.353733 | I99: =SUM(I91:I98) -> 105.53921 | J99: =SUM(J91:J98) -> 142.06693 | K99: =SUM(K91:K98) -> 179.72499 | ... M99: =SUM(M91:M98) -> 236.84597
A100: de los cuales LAF | D100: =SUMIF($C$91:$C$98,"LAF",D91:D98) -> 5.4889738 | E100: =SUMIF($C$91:$C$98,"LAF",E91:E98) -> 9.6783479 | F100: =SUMIF($C$91:$C$98,"LAF",F91:F98) -> 16.810066 | G100: =SUMIF($C$91:$C$98,"LAF",G91:G98) -> 31.069753 | H100: =SUMIF($C$91:$C$98,"LAF",H91:H98) -> 52.933283 | I100: =SUMIF($C$91:$C$98,"LAF",I91:I98) -> 74.365745 | J100: =SUMIF($C$91:$C$98,"LAF",J91:J98) -> 100.37934 | K100: =SUMIF($C$91:$C$98,"LAF",K91:K98) -> 127.07823 | ... M100: =SUMIF($C$91:$C$98,"LAF",M91:M98) -> 167.08924
A101: de los cuales LAC | D101: =SUMIF($C$91:$C$98,"LAC",D91:D98) -> 3.0596593 | E101: =SUMIF($C$91:$C$98,"LAC",E91:E98) -> 5.24142 | F101: =SUMIF($C$91:$C$98,"LAC",F91:F98) -> 8.1066902 | G101: =SUMIF($C$91:$C$98,"LAC",G91:G98) -> 13.59877 | H101: =SUMIF($C$91:$C$98,"LAC",H91:H98) -> 22.42045 | I101: =SUMIF($C$91:$C$98,"LAC",I91:I98) -> 31.173464 | J101: =SUMIF($C$91:$C$98,"LAC",J91:J98) -> 41.687587 | K101: =SUMIF($C$91:$C$98,"LAC",K91:K98) -> 52.646758 | ... M101: =SUMIF($C$91:$C$98,"LAC",M91:M98) -> 69.756729
A103: OPCIÓN B — cortes de guillotina en cuerpos
A104: cuerpo 2,5 kg | B104: =Nesting!$E$6 -> 1.25 | C104: =Nesting!$F$6 -> LAF | D104: =D80*Nesting!$O$6 -> 327.77778 | E104: =E80*Nesting!$O$6 -> 787.77778 | F104: =F80*Nesting!$O$6 -> 1430 | G104: =G80*Nesting!$O$6 -> 2827.7778 | H104: =H80*Nesting!$O$6 -> 4716.6667 | I104: =I80*Nesting!$O$6 -> 6727.7778 | J104: =J80*Nesting!$O$6 -> 8962.2222 | K104: =K80*Nesting!$O$6 -> 11364.444 | ... M104: =M80*Nesting!$O$6 -> 15660
A105: cuerpo 5 kg | B105: =Nesting!$E$7 -> 1.6 | C105: =Nesting!$F$7 -> LAF | D105: =D81*Nesting!$O$7 -> 2820 | E105: =E81*Nesting!$O$7 -> 4808.75 | F105: =F81*Nesting!$O$7 -> 8216.25 | G105: =G81*Nesting!$O$7 -> 14968.75 | H105: =H81*Nesting!$O$7 -> 25450 | I105: =I81*Nesting!$O$7 -> 35550 | J105: =J81*Nesting!$O$7 -> 48046.25 | K105: =K81*Nesting!$O$7 -> 60813.75 | ... M105: =M81*Nesting!$O$7 -> 79582.5
A106: cuerpo 10 kg | B106: =Nesting!$E$8 -> 2 | C106: =Nesting!$F$8 -> LAF | D106: =D82*Nesting!$O$8 -> 110.4 | E106: =E82*Nesting!$O$8 -> 212.4 | F106: =F82*Nesting!$O$8 -> 411.6 | G106: =G82*Nesting!$O$8 -> 807.6 | H106: =H82*Nesting!$O$8 -> 1423.2 | I106: =I82*Nesting!$O$8 -> 2061.6 | J106: =J82*Nesting!$O$8 -> 2786.4 | K106: =K82*Nesting!$O$8 -> 3528 | ... M106: =M82*Nesting!$O$8 -> 4622.4
A107: cuerpo 25 kg | B107: =Nesting!$E$9 -> 3.2 | C107: =Nesting!$F$9 -> LAC | D107: =D83*Nesting!$O$9 -> 45.333333 | E107: =E83*Nesting!$O$9 -> 77.333333 | F107: =F83*Nesting!$O$9 -> 120 | G107: =G83*Nesting!$O$9 -> 200 | H107: =H83*Nesting!$O$9 -> 332 | I107: =I83*Nesting!$O$9 -> 462.66667 | J107: =J83*Nesting!$O$9 -> 618.66667 | K107: =K83*Nesting!$O$9 -> 780 | ... M107: =M83*Nesting!$O$9 -> 1033.3333
A108: cuerpo 50 kg | B108: =Nesting!$E$10 -> 3.2 | C108: =Nesting!$F$10 -> LAC | D108: =D84*Nesting!$O$10 -> 100 | E108: =E84*Nesting!$O$10 -> 170.66667 | F108: =F84*Nesting!$O$10 -> 264 | G108: =G84*Nesting!$O$10 -> 442.66667 | H108: =H84*Nesting!$O$10 -> 730.66667 | I108: =I84*Nesting!$O$10 -> 1018.6667 | J108: =J84*Nesting!$O$10 -> 1360 | K108: =K84*Nesting!$O$10 -> 1716 | ... M108: =M84*Nesting!$O$10 -> 2273.3333
A109: cuerpo 70 kg | B109: =Nesting!$E$11 -> 4.75 | C109: =Nesting!$F$11 -> LAC | D109: =D85*Nesting!$O$11 -> 0 | E109: =E85*Nesting!$O$11 -> 0 | F109: =F85*Nesting!$O$11 -> 0 | G109: =G85*Nesting!$O$11 -> 0 | H109: =H85*Nesting!$O$11 -> 0 | I109: =I85*Nesting!$O$11 -> 0 | J109: =J85*Nesting!$O$11 -> 0 | K109: =K85*Nesting!$O$11 -> 0 | ... M109: =M85*Nesting!$O$11 -> 0
A110: cuerpo 100 kg | B110: =Nesting!$E$12 -> 4.75 | C110: =Nesting!$F$12 -> LAC | D110: =D86*Nesting!$O$12 -> 7.5555556 | E110: =E86*Nesting!$O$12 -> 11.111111 | F110: =F86*Nesting!$O$12 -> 19.555556 | G110: =G86*Nesting!$O$12 -> 33.333333 | H110: =H86*Nesting!$O$12 -> 53.777778 | I110: =I86*Nesting!$O$12 -> 72.888889 | J110: =J86*Nesting!$O$12 -> 96.888889 | K110: =K86*Nesting!$O$12 -> 122.66667 | ... M110: =M86*Nesting!$O$12 -> 163.55556
A111: Hojas mixtas 70/100 | B111: =Nesting!$E$11 -> 4.75 | C111: =Nesting!$F$11 -> LAC | D111: =D87*Nesting!$G$21 -> 26.666667 | E111: =E87*Nesting!$G$21 -> 48.333333 | F111: =F87*Nesting!$G$21 -> 71.666667 | G111: =G87*Nesting!$G$21 -> 120 | H111: =H87*Nesting!$G$21 -> 198.33333 | I111: =I87*Nesting!$G$21 -> 276.66667 | J111: =J87*Nesting!$G$21 -> 371.66667 | K111: =K87*Nesting!$G$21 -> 470 | ... M111: =M87*Nesting!$G$21 -> 621.66667
A112: Total | D112: =SUM(D104:D111) -> 3437.7333 | E112: =SUM(E104:E111) -> 6116.3722 | F112: =SUM(F104:F111) -> 10533.072 | G112: =SUM(G104:G111) -> 19400.128 | H112: =SUM(H104:H111) -> 32904.644 | I112: =SUM(I104:I111) -> 46170.267 | J112: =SUM(J104:J111) -> 62242.094 | K112: =SUM(K104:K111) -> 78794.861 | ... M112: =SUM(M104:M111) -> 103956.79
...

Sheet Proceso
A1: Cómo sería el proceso en cada opción
A2: Los números se calculan solos. Salvo aclaración, corresponden al año de referencia de Supuestos.
B3: ="Año de referencia: "&Supuestos!$B$21 -> Año de referencia: 2035
B5: OPCIÓN A — BOBINA DE ANCHO ESTÁNDAR POR FORMATO (cuerpos) + FLEJE A MEDIDA (cúpulas y fondos)
B6: Idea: para cada cuerpo se compra una bobina del ancho comercial que mejor se aprovecha (ver Nesting) y se corta al largo en la línea de corte transversal. Para cúpulas y fondos se compran flejes ya cortados por el proveedor al ancho del disco (D + 2s) y alimentan el balancín en continuo.
B7: Flujo del proceso — cuerpos
A8: 1 | B8: Recepción: el puente grúa con pinza en C baja cada bobina y la apoya en cunas por espesor. Control de recepción (Nivel 1 SGC): certificado, espesor ±0,1 mm.
A9: 2 | B9: Carga en el desbobinador de la línea con el puente grúa.
A10: 3 | B10: Aplanado: la aplanadora saca la curvatura de bobina; el despunte inicial va a scrap.
A11: 4 | B11: Corte transversal: el alimentador servo avanza el largo programado y la cizalla corta una tira con 1 a 3 desarrollos de ancho.
A12: 5 | B12: Separación en guillotina de los desarrollos de la tira y refilado de orillas.
A13: 6 | B13: Apilado en carros → grabado de lote → cilindradora. Scrap a contenedor con salida al exterior.
B14: Flujo del proceso — cúpulas y fondos
A15: 1 | B15: Recepción de flejes (bobinas angostas) con el puente grúa; se guardan en la estantería porta-flejes por diámetro de disco.
A16: 2 | B16: Carga del fleje en el desbobinador del balancín; el alimentador servo avanza un paso (D + s) por golpe.
A17: 3 | B17: El balancín corta el disco; el esqueleto del fleje se trocea y va a scrap (~25%, inherente al disco).
A18: 4 | B18: Los discos pasan al embutido (cúpula/fondo) según el proceso ya definido en el Doc.
B19: Máquinas y equipos
B20: Equipo | F20: Cantidad | G20: Precio unit. (USD) | H20: Subtotal (USD)
B21: =Supuestos!A96 -> Línea de corte transversal 1–6 mm × 1.600 (desbobinador, aplanadora, alimentador servo, cizalla) | F21: =Supuestos!C96 -> 1 | G21: =Supuestos!B96 -> 80000 | H21: =F21*G21 -> 80000
B22: =Supuestos!A97 -> Guillotina hidráulica 6 × 3.200 mm con tope motorizado | F22: =Supuestos!C97 -> 1 | G22: =Supuestos!B97 -> 25810.975 | H22: =F22*G22 -> 25810.975
B23: =Supuestos!A98 -> Cortadora longitudinal (slitter) 0,3–3,2 × 1.600 | F23: =Supuestos!C98 -> 0 | G23: =Supuestos!B98 -> 60000 | H23: =F23*G23 -> 0
B24: =Supuestos!A99 -> Puente grúa monoviga 10 t (incluye carrilera) | F24: =Supuestos!C99 -> 1 | G24: =Supuestos!B99 -> 30000 | H24: =F24*G24 -> 30000
B25: =Supuestos!A100 -> Pinza en C portabobinas + cunas | F25: =Supuestos!C100 -> 1 | G25: =Supuestos!B100 -> 6000 | H25: =F25*G25 -> 6000
B26: =Supuestos!A101 -> Desbobinador + enderezador + alimentador servo para la prensa de discos | F26: =Supuestos!C101 -> 1 | G26: =Supuestos!B101 -> 12000 | H26: =F26*G26 -> 12000
B27: =Supuestos!A102 -> Estantería porta-flejes | F27: =Supuestos!C102 -> 1 | G27: =Supuestos!B102 -> 3000 | H27: =F27*G27 -> 3000
B28: =Supuestos!A103 -> Autoelevador eléctrico 2,5 t | F28: =Supuestos!C103 -> 0 | G28: =Supuestos!B103 -> 20000 | H28: =F28*G28 -> 0
B29: =Supuestos!A104 -> Mesa elevadora de tijera 1500 × 3000 mm, 3 t, elevación ~1 m (paquete de hojas a la altura de la guillotina) | F29: =Supuestos!C104 -> 0 | G29: =Supuestos!B104 -> 7000 | H29: =F29*G29 -> 0
B30: =Supuestos!A105 -> Apoyos con bolas (mesa de bolas) entre la mesa elevadora y la guillotina | F30: =Supuestos!C105 -> 0 | G30: =Supuestos!B105 -> 1500 | H30: =F30*G30 -> 0
B31: =Supuestos!A106 -> Racks por espesor en el almacén de MP y carros porta-desarrollos | F31: =Supuestos!C106 -> 0 | G31: =Supuestos!B106 -> 2000 | H31: =F31*G31 -> 0
B32: =Supuestos!A107 -> Mesa de alimentación de tiras al balancín | F32: =Supuestos!C107 -> 0 | G32: =Supuestos!B107 -> 1500 | H32: =F32*G32 -> 0
B33: TOTAL OPCIÓN A | H33: =SUM(H21:H32) -> 156810.97
B35: Materia prima, peso de bobina y consumo
B36: SKU | C36: Ancho (mm) | D36: Espesor (mm) | E36: Peso elegido (t) | F36: Consumo (t/año) | G36: Bobinas por año | H36: Días que dura cada bobina | I36: Piezas por bobina
B37: =Bobinas!A6 -> Cuerpo 2,5 kg | C37: =Bobinas!D6 -> 1220 | D37: =Bobinas!C6 -> 1.25 | E37: =Bobinas!K6 -> 1.5 | F37: =Bobinas!F6 -> 15.271907 | G37: =Bobinas!O6 -> 10.181271 | H37: =Bobinas!N6 -> 23.572694 | I37: =Bobinas!M6 -> 1391.2628
B38: =Bobinas!A7 -> Cuerpo 5 kg | C38: =Bobinas!D7 -> 1000 | D38: =Bobinas!C7 -> 1.6 | E38: =Bobinas!K7 -> 10 | F38: =Bobinas!F7 -> 127.4366 | G38: =Bobinas!O7 -> 12.74366 | H38: =Bobinas!N7 -> 18.832895 | I38: =Bobinas!M7 -> 5021.0012
B39: =Bobinas!A8 -> Cuerpo 10 kg | C39: =Bobinas!D8 -> 1000 | D39: =Bobinas!C8 -> 2 | E39: =Bobinas!K8 -> 1.5 | F39: =Bobinas!F8 -> 17.153246 | G39: =Bobinas!O8 -> 11.435498 | H39: =Bobinas!N8 -> 20.987281 | I39: =Bobinas!M8 -> 338.53855
B40: =Bobinas!A9 -> Cuerpo 25 kg | C40: =Bobinas!D9 -> 1500 | D40: =Bobinas!C9 -> 3.2 | E40: =Bobinas!K9 -> 1 | F40: =Bobinas!F9 -> 8.415126 | G40: =Bobinas!O9 -> 8.415126 | H40: =Bobinas!N9 -> 28.520072 | I40: =Bobinas!M9 -> 92.55886
B41: =Bobinas!A10 -> Cuerpo 50 kg | C41: =Bobinas!D10 -> 1500 | D41: =Bobinas!C10 -> 3.2 | E41: =Bobinas!K10 -> 3 | F41: =Bobinas!F10 -> 32.171674 | G41: =Bobinas!O10 -> 10.723891 | H41: =Bobinas!N10 -> 22.379936 | I41: =Bobinas!M10 -> 159.78974
B42: =Bobinas!A11 -> Cuerpo 70 kg | C42: =Bobinas!D11 -> 1245 | D42: =Bobinas!C11 -> 4.75 | E42: =Bobinas!K11 -> 1 | F42: =Bobinas!F11 -> 11.864033 | G42: =Bobinas!O11 -> 11.864033 | H42: =Bobinas!N11 -> 20.229208 | I42: =Bobinas!M11 -> 31.597549
B43: =Bobinas!A12 -> Cuerpo 100 kg | C43: =Bobinas!D12 -> 1245 | D43: =Bobinas!C12 -> 4.75 | E43: =Bobinas!K12 -> 1 | F43: =Bobinas!F12 -> 10.398102 | G43: =Bobinas!O12 -> 10.398102 | H43: =Bobinas!N12 -> 23.081135 | I43: =Bobinas!M12 -> 23.873704
B44: =Bobinas!A13 -> Fleje Cúpula 1 kg | C44: =Bobinas!D13 -> 114 | D44: =Bobinas!C13 -> 0.9 | E44: =Bobinas!K13 -> 1 | F44: =Bobinas!F13 -> 18.251831 | G44: =Bobinas!O13 -> 18.251831 | H44: =Bobinas!N13 -> 13.149365 | I44: =Bobinas!M13 -> 11157.193
B45: =Bobinas!A14 -> Fleje Fondo 1 kg | C45: =Bobinas!D14 -> 106 | D45: =Bobinas!C14 -> 0.9 | E45: =Bobinas!K14 -> 1 | F45: =Bobinas!F14 -> 15.747866 | G45: =Bobinas!O14 -> 15.747866 | H45: =Bobinas!N14 -> 15.24016 | I45: =Bobinas!M14 -> 12931.225
B46: =Bobinas!A15 -> Fleje Cúpula 2,5 kg | C46: =Bobinas!D15 -> 200 | D46: =Bobinas!C15 -> 1.25 | E46: =Bobinas!K15 -> 0.5 | F46: =Bobinas!F15 -> 5.072211 | G46: =Bobinas!O15 -> 10.144422 | H46: =Bobinas!N15 -> 23.658322 | I46: =Bobinas!M15 -> 1396.3165
B47: =Bobinas!A16 -> Fleje Fondo 2,5 kg | C47: =Bobinas!D16 -> 200 | D47: =Bobinas!C16 -> 1.25 | E47: =Bobinas!K16 -> 0.5 | F47: =Bobinas!F16 -> 4.208263 | G47: =Bobinas!O16 -> 8.416526 | H47: =Bobinas!N16 -> 28.515328 | I47: =Bobinas!M16 -> 1682.9775
B48: =Bobinas!A17 -> Fleje Cúpula 5 kg | C48: =Bobinas!D17 -> 250 | D48: =Bobinas!C17 -> 1.6 | E48: =Bobinas!K17 -> 0.6 | F48: =Bobinas!F17 -> 45.119806 | G48: =Bobinas!O17 -> 75.199677 | H48: =Bobinas!N17 -> 3.1915031 | I48: =Bobinas!M17 -> 850.88038
... B51: =Bobinas!A20 -> Fleje Fondo 10 kg | C51: =Bobinas!D20 -> 249 | D51: =Bobinas!C20 -> 2 | E51: =Bobinas!K20 -> 0.5 | F51: =Bobinas!F20 -> 3.1559536 | G51: =Bobinas!O20 -> 6.3119072 | H51: =Bobinas!N20 -> 38.023373 | I51: =Bobinas!M20 -> 613.34184
B53: Manejo, personal y stock
B54: Acero comprado (t/año) | F54: {=INDEX(Calculo!$D$223:$M$223,MATCH(Supuestos!$B$21,Calculo!$D$4:$M$4,0))} -> 348.04343
B55: Scrap (t/año) | F55: {=INDEX(Calculo!$D$224:$M$224,MATCH(Supuestos!$B$21,Calculo!$D$4:$M$4,0))} -> 48.182778
B56: Stock promedio (t) | F56: {=INDEX(Calculo!$D$226:$M$226,MATCH(Supuestos!$B$21,Calculo!$D$4:$M$4,0))} -> 25.561286
B57: Horas-hombre de corte por año | F57: {=INDEX(Calculo!$D$228:$M$228,MATCH(Supuestos!$B$21,Calculo!$D$4:$M$4,0))} -> 544.88084
B58: Operarios equivalentes | F58: {=INDEX(Calculo!$D$228:$M$228,MATCH(Supuestos!$B$21,Calculo!$D$4:$M$4,0))/Supuestos!$B$42} -> 0.30271158
B59: Costo anual (USD) | F59: {=INDEX(Calculo!$D$231:$M$231,MATCH(Supuestos!$B$21,Calculo!$D$4:$M$4,0))} -> 421272.65
B61: Ventajas: excelente aprovechamiento en cuerpos, cortes exactos, cambio de formato sin herramental, discos en continuo. Desventajas: la inversión más alta de las opciones sin slitter (línea de corte + puente grúa), 15 SKUs distintos en stock, bobinas pesadas y una línea de 12–15 m.
B63: OPCIÓN B — HOJAS ESTÁNDAR (cuerpos, cúpulas y fondos)
B64: Idea: todo se compra en hojas de medida comercial. Los cuerpos se cortan en guillotina (franjas y piezas). Para los discos, la hoja se corta en tiras de ancho D + 2s y cada tira se carga a mano en el balancín.
B65: Flujo del proceso
A66: 1 | B66: Recepción de paquetes (2–3 t) con autoelevador; racks por espesor y formato.
A67: 2 | B67: Cuerpos: el paquete se apoya en la mesa elevadora de tijera; la hoja de arriba se desliza por la mesa de bolas hasta la guillotina, que corta franjas y luego desarrollos; sobrante a scrap; carros a cilindrado.
A68: 3 | B68: Discos: la guillotina corta la hoja en tiras; las tiras se apilan en la mesa de alimentación del balancín.
A69: 4 | B69: El operario carga cada tira en el balancín y la avanza contra tope; el balancín corta los discos; el esqueleto y la punta de tira van a scrap.
A70: 5 | B70: Cambio de formato: reprogramar el tope trasero de la guillotina y cambiar de paquete.
B71: Máquinas y equipos
B72: Equipo | F72: Cantidad | G72: Precio unit. (USD) | H72: Subtotal (USD)
B73: =Supuestos!A96 -> Línea de corte transversal 1–6 mm × 1.600 (desbobinador, aplanadora, alimentador servo, cizalla) | F73: =Supuestos!D96 -> 0 | G73: =Supuestos!B96 -> 80000 | H73: =F73*G73 -> 0
B74: =Supuestos!A97 -> Guillotina hidráulica 6 × 3.200 mm con tope motorizado | F74: =Supuestos!D97 -> 1 | G74: =Supuestos!B97 -> 25810.975 | H74: =F74*G74 -> 25810.975
B75: =Supuestos!A98 -> Cortadora longitudinal (slitter) 0,3–3,2 × 1.600 | F75: =Supuestos!D98 -> 0 | G75: =Supuestos!B98 -> 60000 | H75: =F75*G75 -> 0
B76: =Supuestos!A99 -> Puente grúa monoviga 10 t (incluye carrilera) | F76: =Supuestos!D99 -> 0 | G76: =Supuestos!B99 -> 30000 | H76: =F76*G76 -> 0
B77: =Supuestos!A100 -> Pinza en C portabobinas + cunas | F77: =Supuestos!D100 -> 0 | G77: =Supuestos!B100 -> 6000 | H77: =F77*G77 -> 0
B78: =Supuestos!A101 -> Desbobinador + enderezador + alimentador servo para la prensa de discos | F78: =Supuestos!D101 -> 0 | G78: =Supuestos!B101 -> 12000 | H78: =F78*G78 -> 0
B79: =Supuestos!A102 -> Estantería porta-flejes | F79: =Supuestos!D102 -> 0 | G79: =Supuestos!B102 -> 3000 | H79: =F79*G79 -> 0
B80: =Supuestos!A103 -> Autoelevador eléctrico 2,5 t | F80: =Supuestos!D103 -> 1 | G80: =Supuestos!B103 -> 20000 | H80: =F80*G80 -> 20000
B81: =Supuestos!A104 -> Mesa elevadora de tijera 1500 × 3000 mm, 3 t, elevación ~1 m (paquete de hojas a la altura de la guillotina) | F81: =Supuestos!D104 -> 1 | G81: =Supuestos!B104 -> 7000 | H81: =F81*G81 -> 7000
B82: =Supuestos!A105 -> Apoyos con bolas (mesa de bolas) entre la mesa elevadora y la guillotina | F82: =Supuestos!D105 -> 1 | G82: =Supuestos!B105 -> 1500 | H82: =F82*G82 -> 1500
B83: =Supuestos!A106 -> Racks por espesor en el almacén de MP y carros porta-desarrollos | F83: =Supuestos!D106 -> 1 | G83: =Supuestos!B106 -> 2000 | H83: =F83*G83 -> 2000
B84: =Supuestos!A107 -> Mesa de alimentación de tiras al balancín | F84: =Supuestos!D107 -> 1 | G84: =Supuestos!B107 -> 1500 | H84: =F84*G84 -> 1500
B85: TOTAL OPCIÓN B | H85: =SUM(H73:H84) -> 57810.975
B87: Materia prima y consumo
B88: Pieza | C88: Hoja (mm) | D88: Espesor (mm) | E88: Piezas por hoja | F88: Aprovech. | G88: Hojas por año | H88: Acero (t/año) | I88: Tiras por año
B89: Cuerpo 2,5 kg | C89: =Nesting!H6&" × "&Nesting!I6 -> 1220 × 2440 | D89: =Nesting!E6 -> 1.25 | E89: =Nesting!L6 -> 27 | F89: =Nesting!M6 -> 0.94231751 | G89: {=INDEX(Calculo!$D$80:$M$80,MATCH(Supuestos!$B$21,Calculo!$D$4:$M$4,0))} -> 522 | H89: {=INDEX(Calculo!$D$91:$M$91,MATCH(Supuestos!$B$21,Calculo!$D$4:$M$4,0))} -> 15.286389 | I89: —
B90: Cuerpo 5 kg | C90: =Nesting!H7&" × "&Nesting!I7 -> 1000 × 2000 | D90: =Nesting!E7 -> 1.6 | E90: =Nesting!L7 -> 12 | F90: =Nesting!M7 -> 0.93951 | G90: {=INDEX(Calculo!$D$81:$M$81,MATCH(Supuestos!$B$21,Calculo!$D$4:$M$4,0))} -> 5305.5 | H90: {=INDEX(Calculo!$D$92:$M$92,MATCH(Supuestos!$B$21,Calculo!$D$4:$M$4,0))} -> 133.61371 | I90: —
B91: Cuerpo 10 kg | C91: =Nesting!H8&" × "&Nesting!I8 -> 1500 × 3000 | D91: =Nesting!E8 -> 2 | E91: =Nesting!L8 -> 15 | F91: =Nesting!M8 -> 0.92895 | G91: {=INDEX(Calculo!$D$82:$M$82,MATCH(Supuestos!$B$21,Calculo!$D$4:$M$4,0))} -> 256.8 | H91: {=INDEX(Calculo!$D$93:$M$93,MATCH(Supuestos!$B$21,Calculo!$D$4:$M$4,0))} -> 18.189144 | I91: —
B92: Cuerpo 25 kg | C92: =Nesting!H9&" × "&Nesting!I9 -> 1500 × 3000 | D92: =Nesting!E9 -> 3.2 | E92: =Nesting!L9 -> 9 | F92: =Nesting!M9 -> 0.84084 | G92: {=INDEX(Calculo!$D$83:$M$83,MATCH(Supuestos!$B$21,Calculo!$D$4:$M$4,0))} -> 86.111111 | H92: {=INDEX(Calculo!$D$94:$M$94,MATCH(Supuestos!$B$21,Calculo!$D$4:$M$4,0))} -> 9.7588 | I92: —
B93: Cuerpo 50 kg | C93: =Nesting!H10&" × "&Nesting!I10 -> 1500 × 3000 | D93: =Nesting!E10 -> 3.2 | E93: =Nesting!L10 -> 6 | F93: =Nesting!M10 -> 0.84821333 | G93: {=INDEX(Calculo!$D$84:$M$84,MATCH(Supuestos!$B$21,Calculo!$D$4:$M$4,0))} -> 284.16667 | H93: {=INDEX(Calculo!$D$95:$M$95,MATCH(Supuestos!$B$21,Calculo!$D$4:$M$4,0))} -> 32.20404 | I93: —
B94: Cuerpo 70 kg | C94: =Nesting!H11&" × "&Nesting!I11 -> 1500 × 3000 | D94: =Nesting!E11 -> 4.75 | E94: =Nesting!L11 -> 4 | F94: =Nesting!M11 -> 0.73258667 | G94: {=INDEX(Calculo!$D$85:$M$85,MATCH(Supuestos!$B$21,Calculo!$D$4:$M$4,0))} -> 0 | H94: {=INDEX(Calculo!$D$96:$M$96,MATCH(Supuestos!$B$21,Calculo!$D$4:$M$4,0))} -> 0 | I94: —
B95: Cuerpo 100 kg | C95: =Nesting!H12&" × "&Nesting!I12 -> 1500 × 3000 | D95: =Nesting!E12 -> 4.75 | E95: =Nesting!L12 -> 3 | F95: =Nesting!M12 -> 0.7272 | G95: {=INDEX(Calculo!$D$86:$M$86,MATCH(Supuestos!$B$21,Calculo!$D$4:$M$4,0))} -> 40.888889 | H95: {=INDEX(Calculo!$D$97:$M$97,MATCH(Supuestos!$B$21,Calculo!$D$4:$M$4,0))} -> 6.87838 | I95: —
B96: Hojas mixtas 70/100 | C96: =Nesting!H11&" × "&Nesting!I11 -> 1500 × 3000 | D96: =Nesting!E11 -> 4.75 | E96: =Nesting!$G$15+Nesting!$G$16 -> 4 | F96: =Nesting!$G$19 -> 0.79184 | G96: {=INDEX(Calculo!$D$87:$M$87,MATCH(Supuestos!$B$21,Calculo!$D$4:$M$4,0))} -> 124.33333 | H96: {=INDEX(Calculo!$D$98:$M$98,MATCH(Supuestos!$B$21,Calculo!$D$4:$M$4,0))} -> 20.915509 | I96: —
B97: Cúpula 1 kg | C97: =Nesting!J26&" × "&Nesting!K26 -> 1220 × 2440 | D97: =Nesting!D26 -> 0.9 | E97: =Nesting!R26 -> 210 | F97: =Nesting!S26 -> 0.64625963 | G97: {=INDEX(Calculo!$D$115:$M$115,MATCH(Supuestos!$B$21,Calculo!$D$4:$M$4,0))} -> 964.8619 | H97: {=INDEX(Calculo!$D$126:$M$126,MATCH(Supuestos!$B$21,Calculo!$D$4:$M$4,0))} -> 20.343799 | I97: {=INDEX(Calculo!$D$137:$M$137,MATCH(Supuestos!$B$21,Calculo!$D$4:$M$4,0))} -> 9648.619
B98: Fondo 1 kg | C98: =Nesting!J27&" × "&Nesting!K27 -> 1000 × 2000 | D98: =Nesting!D27 -> 0.9 | E98: =Nesting!R27 -> 171 | F98: =Nesting!S27 -> 0.67151543 | G98: {=INDEX(Calculo!$D$116:$M$116,MATCH(Supuestos!$B$21,Calculo!$D$4:$M$4,0))} -> 1184.9181 | H98: {=INDEX(Calculo!$D$127:$M$127,MATCH(Supuestos!$B$21,Calculo!$D$4:$M$4,0))} -> 16.78555 | I98: {=INDEX(Calculo!$D$138:$M$138,MATCH(Supuestos!$B$21,Calculo!$D$4:$M$4,0))} -> 10664.263
B99: Cúpula 2,5 kg | C99: =Nesting!J28&" × "&Nesting!K28 -> 1220 × 2440 | D99: =Nesting!D28 -> 1.25 | E99: =Nesting!R28 -> 78 | F99: =Nesting!S28 -> 0.65938777 | G99: {=INDEX(Calculo!$D$117:$M$117,MATCH(Supuestos!$B$21,Calculo!$D$4:$M$4,0))} -> 180.69231 | H99: {=INDEX(Calculo!$D$128:$M$128,MATCH(Supuestos!$B$21,Calculo!$D$4:$M$4,0))} -> 5.2914423 | I99: {=INDEX(Calculo!$D$139:$M$139,MATCH(Supuestos!$B$21,Calculo!$D$4:$M$4,0))} -> 1084.1538
B100: Fondo 2,5 kg | C100: =Nesting!J29&" × "&Nesting!K29 -> 1220 × 2440 | D100: =Nesting!D29 -> 1.25 | E100: =Nesting!R29 -> 120 | F100: =Nesting!S29 -> 0.6934975 | G100: {=INDEX(Calculo!$D$118:$M$118,MATCH(Supuestos!$B$21,Calculo!$D$4:$M$4,0))} -> 117.45 | H100: {=INDEX(Calculo!$D$129:$M$129,MATCH(Supuestos!$B$21,Calculo!$D$4:$M$4,0))} -> 3.4394375 | I100: {=INDEX(Calculo!$D$140:$M$140,MATCH(Supuestos!$B$21,Calculo!$D$4:$M$4,0))} -> 1761.75
B101: Cúpula 5 kg | C101: =Nesting!J30&" × "&Nesting!K30 -> 1220 × 2440 | D101: =Nesting!D30 -> 1.6 | E101: =Nesting!R30 -> 50 | F101: =Nesting!S30 -> 0.64430986 | G101: {=INDEX(Calculo!$D$119:$M$119,MATCH(Supuestos!$B$21,Calculo!$D$4:$M$4,0))} -> 1273.32 | H101: {=INDEX(Calculo!$D$130:$M$130,MATCH(Supuestos!$B$21,Calculo!$D$4:$M$4,0))} -> 47.728956 | I101: {=INDEX(Calculo!$D$141:$M$141,MATCH(Supuestos!$B$21,Calculo!$D$4:$M$4,0))} -> 6366.6
B102: Fondo 5 kg | C102: =Nesting!J31&" × "&Nesting!K31 -> 1000 × 2000 | D102: =Nesting!D31 -> 1.6 | E102: =Nesting!R31 -> 55 | F102: =Nesting!S31 -> 0.67665782 | G102: {=INDEX(Calculo!$D$120:$M$120,MATCH(Supuestos!$B$21,Calculo!$D$4:$M$4,0))} -> 1157.5636 | H102: {=INDEX(Calculo!$D$131:$M$131,MATCH(Supuestos!$B$21,Calculo!$D$4:$M$4,0))} -> 29.152083 | I102: {=INDEX(Calculo!$D$142:$M$142,MATCH(Supuestos!$B$21,Calculo!$D$4:$M$4,0))} -> 5787.8182
B103: Cúpula 10 kg | C103: =Nesting!J32&" × "&Nesting!K32 -> 1500 × 3000 | D103: =Nesting!D32 -> 2 | E103: =Nesting!R32 -> 55 | F103: =Nesting!S32 -> 0.63896853 | G103: {=INDEX(Calculo!$D$121:$M$121,MATCH(Supuestos!$B$21,Calculo!$D$4:$M$4,0))} -> 70.036364 | H103: {=INDEX(Calculo!$D$132:$M$132,MATCH(Supuestos!$B$21,Calculo!$D$4:$M$4,0))} -> 4.9606756 | I103: {=INDEX(Calculo!$D$143:$M$143,MATCH(Supuestos!$B$21,Calculo!$D$4:$M$4,0))} -> 350.18182
B104: Fondo 10 kg | C104: =Nesting!J33&" × "&Nesting!K33 -> 1500 × 3000 | D104: =Nesting!D33 -> 2 | E104: =Nesting!R33 -> 98 | F104: =Nesting!S33 -> 0.71880513 | G104: {=INDEX(Calculo!$D$122:$M$122,MATCH(Supuestos!$B$21,Calculo!$D$4:$M$4,0))} -> 39.306122 | H104: {=INDEX(Calculo!$D$133:$M$133,MATCH(Supuestos!$B$21,Calculo!$D$4:$M$4,0))} -> 2.7840527 | I104: {=INDEX(Calculo!$D$144:$M$144,MATCH(Supuestos!$B$21,Calculo!$D$4:$M$4,0))} -> 275.14286
B106: Manejo, personal y stock
B107: Acero comprado (t/año) | F107: {=INDEX(Calculo!$D$235:$M$235,MATCH(Supuestos!$B$21,Calculo!$D$4:$M$4,0))} -> 367.33197
B108: Scrap (t/año) | F108: {=INDEX(Calculo!$D$236:$M$236,MATCH(Supuestos!$B$21,Calculo!$D$4:$M$4,0))} -> 67.47132
B109: Stock promedio (t) | F109: {=INDEX(Calculo!$D$238:$M$238,MATCH(Supuestos!$B$21,Calculo!$D$4:$M$4,0))} -> 29.433651
...

Sheet Comparacion
A1: Comparación de opciones (cuerpos + cúpulas + fondos)
A2: Horizonte 2026–2035, con los precios de acero cotizados. VA = valor actual de costos + inversiones (menor es mejor).
A4: Indicador | B4: A: bobina por formato + fleje | C4: B: hojas (todo) | D4: C: bobina madre | E4: D: hojas + fleje | F4: Referencia a medida | G4: Unidad / nota
A5: Inversión inicial | B5: =Supuestos!$H$108 -> 156810.97 | C5: =Supuestos!$I$108 -> 57810.975 | D5: =Supuestos!$J$108 -> 191000 | E5: =Supuestos!$K$108 -> 71310.975 | F5: =Supuestos!$L$108 -> 15000 | G5: USD
A6: Acero comprado 2026–2035 | B6: =SUM(Calculo!$D$223:$M$223) -> 1519.5795 | C6: =SUM(Calculo!$D$235:$M$235) -> 1604.0846 | D6: =SUM(Calculo!$D$159:$M$159) -> 1499.5628 | E6: =SUM(Calculo!$D$259:$M$259) -> 1581.7317 | F6: =SUM(Calculo!$D$271:$M$271) -> 1480.9868 | G6: t
A7: Scrap generado 2026–2035 | B7: =B6-SUM(Calculo!$D$41:$M$41) -> 209.59427 | C7: =C6-SUM(Calculo!$D$41:$M$41) -> 294.09937 | D7: =D6-SUM(Calculo!$D$41:$M$41) -> 189.5776 | E7: =E6-SUM(Calculo!$D$41:$M$41) -> 271.74648 | F7: =F6-SUM(Calculo!$D$41:$M$41) -> 171.00164 | G7: t
A8: Aprovechamiento global de chapa | B8: =SUM(Calculo!$D$41:$M$41)/B6 -> 0.86207087 | C8: =SUM(Calculo!$D$41:$M$41)/C6 -> 0.81665594 | D8: =SUM(Calculo!$D$41:$M$41)/D6 -> 0.87357809 | E8: =SUM(Calculo!$D$41:$M$41)/E6 -> 0.82819685 | F8: =SUM(Calculo!$D$41:$M$41)/F6 -> 0.88453534 | G8: acero en piezas / acero comprado
A9: Costo del acero acumulado 10 años (nominal) | B9: =SUM(Calculo!$D$222:$M$222) -> 1839705.6 | C9: =SUM(Calculo!$D$234:$M$234) -> 2054099.6 | D9: =SUM(Calculo!$D$246:$M$246) -> 1840424.9 | E9: =SUM(Calculo!$D$258:$M$258) -> 1957422.8 | F9: =SUM(Calculo!$D$270:$M$270) -> 1963235.2 | G9: USD
A10: Costo anual en el año de referencia | B10: {=INDEX(Calculo!$D$231:$M$231,MATCH(Supuestos!$B$21,Calculo!$D$4:$M$4,0))} -> 421272.65 | C10: {=INDEX(Calculo!$D$243:$M$243,MATCH(Supuestos!$B$21,Calculo!$D$4:$M$4,0))} -> 465758.73 | D10: {=INDEX(Calculo!$D$255:$M$255,MATCH(Supuestos!$B$21,Calculo!$D$4:$M$4,0))} -> 423638.67 | E10: {=INDEX(Calculo!$D$267:$M$267,MATCH(Supuestos!$B$21,Calculo!$D$4:$M$4,0))} -> 442735.29 | F10: {=INDEX(Calculo!$D$279:$M$279,MATCH(Supuestos!$B$21,Calculo!$D$4:$M$4,0))} -> 444537.03 | G10: USD/año
A11: Costo operativo acumulado 10 años (nominal) | B11: =SUM(Calculo!$D$231:$M$231) -> 1870310.6 | C11: =SUM(Calculo!$D$243:$M$243) -> 2042947.5 | D11: =SUM(Calculo!$D$255:$M$255) -> 1892177.9 | E11: =SUM(Calculo!$D$267:$M$267) -> 1946376.6 | F11: =SUM(Calculo!$D$279:$M$279) -> 1944677.9 | G11: USD, sin inversión
A12: VALOR ACTUAL 10 AÑOS (costos + inversión) | B12: =B5+SUMPRODUCT(Calculo!$D$231:$M$231,Calculo!$D$282:$M$282) -> 970647.56 | C12: =C5+SUMPRODUCT(Calculo!$D$243:$M$243,Calculo!$D$282:$M$282) -> 941470.02 | D12: =D5+SUMPRODUCT(Calculo!$D$255:$M$255,Calculo!$D$282:$M$282) -> 1016372.2 | E12: =E5+SUMPRODUCT(Calculo!$D$267:$M$267,Calculo!$D$282:$M$282) -> 914216.35 | F12: =F5+SUMPRODUCT(Calculo!$D$279:$M$279,Calculo!$D$282:$M$282) -> 854876.91 | G12: USD. Menor = más conveniente
A13: Ranking por VA (1 = más barata) | B13: =RANK(B12,$B$12:$F$12,1) -> 4 | C13: =RANK(C12,$B$12:$F$12,1) -> 3 | D13: =RANK(D12,$B$12:$F$12,1) -> 5 | E13: =RANK(E12,$B$12:$F$12,1) -> 2 | F13: =RANK(F12,$B$12:$F$12,1) -> 1
A14: Ranking entre opciones que cortan en planta (sin referencia) | B14: =RANK(B12,$B$12:$E$12,1) -> 3 | C14: =RANK(C12,$B$12:$E$12,1) -> 2 | D14: =RANK(D12,$B$12:$E$12,1) -> 4 | E14: =RANK(E12,$B$12:$E$12,1) -> 1 | F14: ="—" -> —
A15: Diferencia de VA contra la opción D | B15: =B12-$E$12 -> 56431.209 | C15: =C12-$E$12 -> 27253.666 | D15: =D12-$E$12 -> 102155.89 | E15: =E12-$E$12 -> 0 | F15: =F12-$E$12 -> -59339.447 | G15: USD. Positivo = cuesta más que D
A16: Stock promedio en el año de referencia | B16: {=INDEX(Calculo!$D$226:$M$226,MATCH(Supuestos!$B$21,Calculo!$D$4:$M$4,0))} -> 25.561286 | C16: {=INDEX(Calculo!$D$238:$M$238,MATCH(Supuestos!$B$21,Calculo!$D$4:$M$4,0))} -> 29.433651 | D16: {=INDEX(Calculo!$D$249:$M$249,MATCH(Supuestos!$B$21,Calculo!$D$4:$M$4,0))} -> 38.209547 | E16: {=INDEX(Calculo!$D$262:$M$262,MATCH(Supuestos!$B$21,Calculo!$D$4:$M$4,0))} -> 26.473533 | F16: {=INDEX(Calculo!$D$274:$M$274,MATCH(Supuestos!$B$21,Calculo!$D$4:$M$4,0))} -> 24.636358 | G16: t
A17: Horas-hombre de corte en el año de referencia | B17: {=INDEX(Calculo!$D$228:$M$228,MATCH(Supuestos!$B$21,Calculo!$D$4:$M$4,0))} -> 544.88084 | C17: {=INDEX(Calculo!$D$240:$M$240,MATCH(Supuestos!$B$21,Calculo!$D$4:$M$4,0))} -> 926.94008 | D17: {=INDEX(Calculo!$D$252:$M$252,MATCH(Supuestos!$B$21,Calculo!$D$4:$M$4,0))} -> 246.72176 | E17: {=INDEX(Calculo!$D$264:$M$264,MATCH(Supuestos!$B$21,Calculo!$D$4:$M$4,0))} -> 627.14898 | F17: {=INDEX(Calculo!$D$276:$M$276,MATCH(Supuestos!$B$21,Calculo!$D$4:$M$4,0))} -> 49.61126 | G17: h/año
A18: Operarios de corte equivalentes | B18: =B17/Supuestos!$B$42 -> 0.30271158 | C18: =C17/Supuestos!$B$42 -> 0.51496671 | D18: =D17/Supuestos!$B$42 -> 0.13706764 | E18: =E17/Supuestos!$B$42 -> 0.3484161 | F18: =F17/Supuestos!$B$42 -> 0.027561811 | G18: personas
A20: Opción más conveniente que corta en planta | B20: {=INDEX($B$4:$E$4,MATCH(1,$B$14:$E$14,0))} -> D: hojas + fleje
A21: Suba del precio de las hojas que iguala D con A (equilibrio) | B21: =(B12-E12)/SUMPRODUCT(Calculo!$D$216:$M$216,Calculo!$D$282:$M$282) -> 0.10031448
A22: Suba del precio del fleje que iguala D con B (equilibrio) | B22: =(C12-E12)/SUMPRODUCT(Calculo!$D$215:$M$215,Calculo!$D$282:$M$282) -> 0.09661584
A24: Solo cúpulas y fondos: ¿fleje a medida o tiras de hoja? (año de referencia)
A25: Fuente de los discos | B25: Acero comprado (t/año) | C25: Aprovech. | D25: Costo del acero (USD/año) | E25: Scrap (t/año) | F25: Horas-hombre (h/año) | G25: Costo neto (USD/año)
A26: Fleje a medida (A, D, referencia) | B26: {=INDEX(Calculo!$D$74:$M$74,MATCH(Supuestos!$B$21,Calculo!$D$4:$M$4,0))} -> 125.33274 | C26: {=INDEX(Calculo!$D$39:$M$39,MATCH(Supuestos!$B$21,Calculo!$D$4:$M$4,0))/B26} -> 0.68571558 | D26: {=INDEX(Calculo!$D$215:$M$215,MATCH(Supuestos!$B$21,Calculo!$D$4:$M$4,0))} -> 151352.64 | E26: {=B26-INDEX(Calculo!$D$39:$M$39,MATCH(Supuestos!$B$21,Calculo!$D$4:$M$4,0))} -> 39.390129 | F26: {=INDEX(Calculo!$D$210:$M$210,MATCH(Supuestos!$B$21,Calculo!$D$4:$M$4,0))*Supuestos!$B$38/60} -> 49.61126 | G26: =D26-E26*Supuestos!$B$7+F26*Supuestos!$B$48 -> 141816.73
A27: Tiras cortadas de hojas (B) | B27: {=INDEX(Calculo!$D$134:$M$134,MATCH(Supuestos!$B$21,Calculo!$D$4:$M$4,0))} -> 130.486 | C27: {=INDEX(Calculo!$D$39:$M$39,MATCH(Supuestos!$B$21,Calculo!$D$4:$M$4,0))/B27} -> 0.65863477 | D27: {=INDEX(Calculo!$D$217:$M$217,MATCH(Supuestos!$B$21,Calculo!$D$4:$M$4,0))} -> 173594.1 | E27: {=B27-INDEX(Calculo!$D$39:$M$39,MATCH(Supuestos!$B$21,Calculo!$D$4:$M$4,0))} -> 44.543382 | F27: {=INDEX(Calculo!$D$156:$M$156,MATCH(Supuestos!$B$21,Calculo!$D$4:$M$4,0))/Supuestos!$B$36+INDEX(Calculo!$D$145:$M$145,MATCH(Supuestos!$B$21,Calculo!$D$4:$M$4,0))*Supuestos!$B$37/3600} -> 349.40236 | G27: =D27-E27*Supuestos!$B$7+F27*Supuestos!$B$48 -> 164652.96
A28: Diferencia a favor del fleje (USD/año) | G28: =G27-G26 -> 22836.236
A29: No incluye inversión ni stock. La bobina madre (C) mezcla discos y cuerpos y se ve en la tabla general.
A31: Sensibilidad 1: variación del precio de las hojas (mueve B y D)
A32: Variación precio hoja | B32: A | C32: B | D32: C | E32: D | F32: Más barata
A33: -0.1 | B33: =$B$12 -> 970647.56 | C33: =$C$12+A33*SUMPRODUCT(Calculo!$D$234:$M$234,Calculo!$D$282:$M$282) -> 852854.47 | D33: =$D$12 -> 1016372.2 | E33: =$E$12+A33*SUMPRODUCT(Calculo!$D$216:$M$216,Calculo!$D$282:$M$282) -> 857962.05 | F33: =INDEX($B$32:$E$32,MATCH(MIN(B33:E33),B33:E33,0)) -> B
A34: -0.05 | B34: =$B$12 -> 970647.56 | C34: =$C$12+A34*SUMPRODUCT(Calculo!$D$234:$M$234,Calculo!$D$282:$M$282) -> 897162.24 | D34: =$D$12 -> 1016372.2 | E34: =$E$12+A34*SUMPRODUCT(Calculo!$D$216:$M$216,Calculo!$D$282:$M$282) -> 886089.2 | F34: =INDEX($B$32:$E$32,MATCH(MIN(B34:E34),B34:E34,0)) -> D
A35: 0 | B35: =$B$12 -> 970647.56 | C35: =$C$12+A35*SUMPRODUCT(Calculo!$D$234:$M$234,Calculo!$D$282:$M$282) -> 941470.02 | D35: =$D$12 -> 1016372.2 | E35: =$E$12+A35*SUMPRODUCT(Calculo!$D$216:$M$216,Calculo!$D$282:$M$282) -> 914216.35 | F35: =INDEX($B$32:$E$32,MATCH(MIN(B35:E35),B35:E35,0)) -> D
A36: 0.05 | B36: =$B$12 -> 970647.56 | C36: =$C$12+A36*SUMPRODUCT(Calculo!$D$234:$M$234,Calculo!$D$282:$M$282) -> 985777.8 | D36: =$D$12 -> 1016372.2 | E36: =$E$12+A36*SUMPRODUCT(Calculo!$D$216:$M$216,Calculo!$D$282:$M$282) -> 942343.51 | F36: =INDEX($B$32:$E$32,MATCH(MIN(B36:E36),B36:E36,0)) -> D
A37: 0.1 | B37: =$B$12 -> 970647.56 | C37: =$C$12+A37*SUMPRODUCT(Calculo!$D$234:$M$234,Calculo!$D$282:$M$282) -> 1030085.6 | D37: =$D$12 -> 1016372.2 | E37: =$E$12+A37*SUMPRODUCT(Calculo!$D$216:$M$216,Calculo!$D$282:$M$282) -> 970470.66 | F37: =INDEX($B$32:$E$32,MATCH(MIN(B37:E37),B37:E37,0)) -> D
A38: 0.15 | B38: =$B$12 -> 970647.56 | C38: =$C$12+A38*SUMPRODUCT(Calculo!$D$234:$M$234,Calculo!$D$282:$M$282) -> 1074393.3 | D38: =$D$12 -> 1016372.2 | E38: =$E$12+A38*SUMPRODUCT(Calculo!$D$216:$M$216,Calculo!$D$282:$M$282) -> 998597.81 | F38: =INDEX($B$32:$E$32,MATCH(MIN(B38:E38),B38:E38,0)) -> A
A39: 0.2 | B39: =$B$12 -> 970647.56 | C39: =$C$12+A39*SUMPRODUCT(Calculo!$D$234:$M$234,Calculo!$D$282:$M$282) -> 1118701.1 | D39: =$D$12 -> 1016372.2 | E39: =$E$12+A39*SUMPRODUCT(Calculo!$D$216:$M$216,Calculo!$D$282:$M$282) -> 1026725 | F39: =INDEX($B$32:$E$32,MATCH(MIN(B39:E39),B39:E39,0)) -> A
A41: Sensibilidad 2: variación del precio del fleje (mueve A y D)
A42: Variación precio fleje | B42: A | C42: B | D42: C | E42: D | F42: Más barata
A43: -0.1 | B43: =$B$12+A43*SUMPRODUCT(Calculo!$D$215:$M$215,Calculo!$D$282:$M$282) -> 942439.28 | C43: =$C$12 -> 941470.02 | D43: =$D$12 -> 1016372.2 | E43: =$E$12+A43*SUMPRODUCT(Calculo!$D$215:$M$215,Calculo!$D$282:$M$282) -> 886008.07 | F43: =INDEX($B$42:$E$42,MATCH(MIN(B43:E43),B43:E43,0)) -> D
A44: 0 | B44: =$B$12+A44*SUMPRODUCT(Calculo!$D$215:$M$215,Calculo!$D$282:$M$282) -> 970647.56 | C44: =$C$12 -> 941470.02 | D44: =$D$12 -> 1016372.2 | E44: =$E$12+A44*SUMPRODUCT(Calculo!$D$215:$M$215,Calculo!$D$282:$M$282) -> 914216.35 | F44: =INDEX($B$42:$E$42,MATCH(MIN(B44:E44),B44:E44,0)) -> D
A45: 0.1 | B45: =$B$12+A45*SUMPRODUCT(Calculo!$D$215:$M$215,Calculo!$D$282:$M$282) -> 998855.84 | C45: =$C$12 -> 941470.02 | D45: =$D$12 -> 1016372.2 | E45: =$E$12+A45*SUMPRODUCT(Calculo!$D$215:$M$215,Calculo!$D$282:$M$282) -> 942424.63 | F45: =INDEX($B$42:$E$42,MATCH(MIN(B45:E45),B45:E45,0)) -> B
A46: 0.2 | B46: =$B$12+A46*SUMPRODUCT(Calculo!$D$215:$M$215,Calculo!$D$282:$M$282) -> 1027064.1 | C46: =$C$12 -> 941470.02 | D46: =$D$12 -> 1016372.2 | E46: =$E$12+A46*SUMPRODUCT(Calculo!$D$215:$M$215,Calculo!$D$282:$M$282) -> 970632.91 | F46: =INDEX($B$42:$E$42,MATCH(MIN(B46:E46),B46:E46,0)) -> B
A47: 0.3 | B47: =$B$12+A47*SUMPRODUCT(Calculo!$D$215:$M$215,Calculo!$D$282:$M$282) -> 1055272.4 | C47: =$C$12 -> 941470.02 | D47: =$D$12 -> 1016372.2 | E47: =$E$12+A47*SUMPRODUCT(Calculo!$D$215:$M$215,Calculo!$D$282:$M$282) -> 998841.19 | F47: =INDEX($B$42:$E$42,MATCH(MIN(B47:E47),B47:E47,0)) -> B
A49: Sensibilidad 3: precio de la línea de corte transversal (mueve A y C)
A50: Precio línea (USD) | B50: A | C50: B | D50: C | E50: D | F50: Más barata
A51: 40000 | B51: =$B$12+(A51-Supuestos!$B$96)*Supuestos!$C$96*(1+Supuestos!$B$18*SUM(Calculo!$D$282:$M$282)) -> 923867.3 | C51: =$C$12 -> 941470.02 | D51: =$D$12+(A51-Supuestos!$B$96)*Supuestos!$E$96*(1+Supuestos!$B$18*SUM(Calculo!$D$282:$M$282)) -> 969591.98 | E51: =$E$12 -> 914216.35 | F51: =INDEX($B$50:$E$50,MATCH(MIN(B51:E51),B51:E51,0)) -> D
A52: 60000 | B52: =$B$12+(A52-Supuestos!$B$96)*Supuestos!$C$96*(1+Supuestos!$B$18*SUM(Calculo!$D$282:$M$282)) -> 947257.43 | C52: =$C$12 -> 941470.02 | D52: =$D$12+(A52-Supuestos!$B$96)*Supuestos!$E$96*(1+Supuestos!$B$18*SUM(Calculo!$D$282:$M$282)) -> 992982.11 | E52: =$E$12 -> 914216.35 | F52: =INDEX($B$50:$E$50,MATCH(MIN(B52:E52),B52:E52,0)) -> D
A53: 80000 | B53: =$B$12+(A53-Supuestos!$B$96)*Supuestos!$C$96*(1+Supuestos!$B$18*SUM(Calculo!$D$282:$M$282)) -> 970647.56 | C53: =$C$12 -> 941470.02 | D53: =$D$12+(A53-Supuestos!$B$96)*Supuestos!$E$96*(1+Supuestos!$B$18*SUM(Calculo!$D$282:$M$282)) -> 1016372.2 | E53: =$E$12 -> 914216.35 | F53: =INDEX($B$50:$E$50,MATCH(MIN(B53:E53),B53:E53,0)) -> D
A54: 100000 | B54: =$B$12+(A54-Supuestos!$B$96)*Supuestos!$C$96*(1+Supuestos!$B$18*SUM(Calculo!$D$282:$M$282)) -> 994037.7 | C54: =$C$12 -> 941470.02 | D54: =$D$12+(A54-Supuestos!$B$96)*Supuestos!$E$96*(1+Supuestos!$B$18*SUM(Calculo!$D$282:$M$282)) -> 1039762.4 | E54: =$E$12 -> 914216.35 | F54: =INDEX($B$50:$E$50,MATCH(MIN(B54:E54),B54:E54,0)) -> D
A55: 130000 | B55: =$B$12+(A55-Supuestos!$B$96)*Supuestos!$C$96*(1+Supuestos!$B$18*SUM(Calculo!$D$282:$M$282)) -> 1029122.9 | C55: =$C$12 -> 941470.02 | D55: =$D$12+(A55-Supuestos!$B$96)*Supuestos!$E$96*(1+Supuestos!$B$18*SUM(Calculo!$D$282:$M$282)) -> 1074847.6 | E55: =$E$12 -> 914216.35 | F55: =INDEX($B$50:$E$50,MATCH(MIN(B55:E55),B55:E55,0)) -> D
A57: Sensibilidad 4: precio de la cortadora longitudinal (mueve C)
A58: Precio cortadora (USD) | B58: A | C58: B | D58: C | E58: D | F58: Más barata
A59: 30000 | B59: =$B$12 -> 970647.56 | C59: =$C$12 -> 941470.02 | D59: =$D$12+(A59-Supuestos!$B$98)*Supuestos!$E$98*(1+Supuestos!$B$18*SUM(Calculo!$D$282:$M$282)) -> 981287.05 | E59: =$E$12 -> 914216.35 | F59: =INDEX($B$58:$E$58,MATCH(MIN(B59:E59),B59:E59,0)) -> D
A60: 45000 | B60: =$B$12 -> 970647.56 | C60: =$C$12 -> 941470.02 | D60: =$D$12+(A60-Supuestos!$B$98)*Supuestos!$E$98*(1+Supuestos!$B$18*SUM(Calculo!$D$282:$M$282)) -> 998829.65 | E60: =$E$12 -> 914216.35 | F60: =INDEX($B$58:$E$58,MATCH(MIN(B60:E60),B60:E60,0)) -> D
A61: 60000 | B61: =$B$12 -> 970647.56 | C61: =$C$12 -> 941470.02 | D61: =$D$12+(A61-Supuestos!$B$98)*Supuestos!$E$98*(1+Supuestos!$B$18*SUM(Calculo!$D$282:$M$282)) -> 1016372.2 | E61: =$E$12 -> 914216.35 | F61: =INDEX($B$58:$E$58,MATCH(MIN(B61:E61),B61:E61,0)) -> D
A62: 90000 | B62: =$B$12 -> 970647.56 | C62: =$C$12 -> 941470.02 | D62: =$D$12+(A62-Supuestos!$B$98)*Supuestos!$E$98*(1+Supuestos!$B$18*SUM(Calculo!$D$282:$M$282)) -> 1051457.4 | E62: =$E$12 -> 914216.35 | F62: =INDEX($B$58:$E$58,MATCH(MIN(B62:E62),B62:E62,0)) -> D
A63: 120000 | B63: =$B$12 -> 970647.56 | C63: =$C$12 -> 941470.02 | D63: =$D$12+(A63-Supuestos!$B$98)*Supuestos!$E$98*(1+Supuestos!$B$18*SUM(Calculo!$D$282:$M$282)) -> 1086542.6 | E63: =$E$12 -> 914216.35 | F63: =INDEX($B$58:$E$58,MATCH(MIN(B63:E63),B63:E63,0)) -> D
A65: Sensibilidades aproximadas: no recalculan el costo financiero del stock.

Sheet Decision
A1: Decisión: opción D — hojas estándar para cuerpos + fleje a medida para cúpulas y fondos
A2: Todo se recalcula con Supuestos. Si cambian los precios, la primera fila avisa si la decisión sigue en pie.
A4: =IF(Comparacion!$B$20="D: hojas + fleje","✔ Con los precios cargados, la opción D sigue siendo la más conveniente de las que cortan en planta.","⚠ Con los precios cargados conviene: "&Comparacion!$B$20&". Revisar la decisión.") -> ✔ Con los precios cargados, la opción D sigue siendo la más conveniente de las que cortan en planta.
A6: 1. Cifras clave
A7: Indicador | B7: D: hojas + fleje | C7: A: bobina + fleje | D7: B: hojas (todo) | E7: C: bobina madre | F7: Unidad
A8: Valor actual 10 años (costos + inversión) | B8: =Comparacion!$E$12 -> 914216.35 | C8: =Comparacion!$B$12 -> 970647.56 | D8: =Comparacion!$C$12 -> 941470.02 | E8: =Comparacion!$D$12 -> 1016372.2 | F8: USD
A9: Diferencia contra D | B9: =Comparacion!$E$15 -> 0 | C9: =Comparacion!$B$15 -> 56431.209 | D9: =Comparacion!$C$15 -> 27253.666 | E9: =Comparacion!$D$15 -> 102155.89 | F9: USD (positivo = más caro que D)
A10: Inversión inicial | B10: =Comparacion!$E$5 -> 71310.975 | C10: =Comparacion!$B$5 -> 156810.97 | D10: =Comparacion!$C$5 -> 57810.975 | E10: =Comparacion!$D$5 -> 191000 | F10: USD
A11: Aprovechamiento global de chapa | B11: =Comparacion!$E$8 -> 0.82819685 | C11: =Comparacion!$B$8 -> 0.86207087 | D11: =Comparacion!$C$8 -> 0.81665594 | E11: =Comparacion!$D$8 -> 0.87357809 | F11: %
A12: Costo del acero acumulado 10 años | B12: =Comparacion!$E$9 -> 1957422.8 | C12: =Comparacion!$B$9 -> 1839705.6 | D12: =Comparacion!$C$9 -> 2054099.6 | E12: =Comparacion!$D$9 -> 1840424.9 | F12: USD
A13: Costo anual en el año de referencia | B13: =Comparacion!$E$10 -> 442735.29 | C13: =Comparacion!$B$10 -> 421272.65 | D13: =Comparacion!$C$10 -> 465758.73 | E13: =Comparacion!$D$10 -> 423638.67 | F13: USD/año
A14: Stock promedio en el año de referencia | B14: =Comparacion!$E$16 -> 26.473533 | C14: =Comparacion!$B$16 -> 25.561286 | D14: =Comparacion!$C$16 -> 29.433651 | E14: =Comparacion!$D$16 -> 38.209547 | F14: t
A15: Horas-hombre de corte en el año de referencia | B15: =Comparacion!$E$17 -> 627.14898 | C15: =Comparacion!$B$17 -> 544.88084 | D15: =Comparacion!$C$17 -> 926.94008 | E15: =Comparacion!$D$17 -> 246.72176 | F15: h/año
A17: 2. Por qué D
A18: 1 | B18: Es la de menor valor actual a 10 años entre las opciones que cortan en planta. Ahorro frente a A (bobina + fleje): | F18: =Comparacion!$B$15 -> 56431.209
B19: Ahorro frente a B (todo en hojas): | F19: =Comparacion!$C$15 -> 27253.666
B20: Ahorro frente a C (bobina madre, precio estimado): | F20: =Comparacion!$D$15 -> 102155.89
A21: 2 | B21: Invierte mucho menos que las opciones con bobina: no necesita línea de corte ni puente grúa. Inversión de D: | F21: =Supuestos!$K$108 -> 71310.975
B22: Inversión adicional que requeriría A: | F22: =Supuestos!$H$108-Supuestos!$K$108 -> 85500
A23: 3 | B23: Según las cotizaciones, la hoja cuesta casi lo mismo que la bobina, así que la bobina no compensa su mayor inversión con acero más barato. Diferencia hoja vs. bobina, mínima y máxima entre los espesores de cuerpo (1,25 a 4,75 mm): | F23: =TEXT(MIN(Supuestos!$G$85:$G$89),"0.0%")&" a "&TEXT(MAX(Supuestos!$G$85:$G$89),"0.0%") -> -2,0% a 6,2%
A24: 4 | B24: Margen de seguridad: el precio de las hojas tendría que subir este porcentaje (manteniendo el de la bobina) para que A iguale a D: | F24: =Comparacion!$B$21 -> 0.10031448
A25: 5 | B25: Cúpulas y fondos desde fleje a medida: la prensa se alimenta sola (sin cargar tiras a mano, más seguro) y aprovecha mejor la chapa que las tiras de hoja. Ahorro anual frente a tiras de hoja en el año de referencia: | F25: =Comparacion!$G$28 -> 22836.236
A26: 6 | B26: Una sola guillotina 6 × 3.200 mm corta todos los cuerpos, de 1,25 a 4,75 mm, incluidos los rodantes. Horas-hombre de corte por año: | F26: =Comparacion!$E$17 -> 627.14898
A27: 7 | B27: Stock parecido al de A, pero comprado en paquetes mensuales de hojas en lugar de bobinas de hasta 10 t, que exigen puente grúa y depósito propio. Stock de D contra A: | F27: =TEXT(Comparacion!$E$16,"0.0")&" t contra "&TEXT(Comparacion!$B$16,"0.0")&" t" -> 26,5 t contra 25,6 t
A28: 8 | B28: Cumple la consigna de cortar en planta y es la más simple de operar, mantener y ubicar en el layout (una guillotina de ~4 m contra una línea de 12–15 m con depósito de bobinas).
A30: 3. Qué resigna D
A31: • | B31: Aprovecha menos chapa que A en los cuerpos (dos bordes perdidos por hoja). Aprovechamiento global D contra A: | F31: =TEXT(Comparacion!$E$8,"0.0%")&" contra "&TEXT(Comparacion!$B$8,"0.0%") -> 82,8% contra 86,2%
A32: • | B32: Scrap adicional frente a A en 10 años (t): | F32: =Comparacion!$E$7-Comparacion!$B$7 -> 62.152207
A33: • | B33: Más manipulación de hojas: las de 71 a 170 kg (2 a 4,75 mm × 1500 × 3000) no se pueden mover a mano; se resuelve con la mesa elevadora de tijera y la mesa de bolas, deslizando la hoja sin levantarla.
A35: 4. Cuándo habría que revisar la decisión
A36: • | B36: Si el precio de las hojas sube respecto del de la bobina más que este porcentaje (A pasaría a convenir): | F36: =Comparacion!$B$21 -> 0.10031448
A37: • | B37: Si el precio del fleje sube más que este porcentaje (B pasaría a convenir): | F37: =Comparacion!$B$22 -> 0.09661584
A38: • | B38: Si la línea de corte transversal o el puente grúa resultan mucho más baratos de lo estimado, o el puente grúa ya está previsto en el layout (ver Sensibilidad 3 en Comparacion y la celda 'ya previsto' en Supuestos).
A39: • | B39: Si la demanda crece bastante más de lo previsto: la bobina escala mejor con volumen.
A41: 5. Datos todavía estimados (reemplazar cuando lleguen las cotizaciones)
A42: • | B42: Guillotina: se usa la Molinari HG 6×3200 como referencia; falta confirmar el recorrido del tope trasero (≥ 900–1.000 mm).
A43: • | B43: Desbobinador + alimentador de la prensa de discos, mesa elevadora de tijera, mesa de bolas y autoelevador: precios estimados.
A44: • | B44: Bobina LAC 4,75 mm (solo afecta a A): sin cotización, se toma igual a la de 3,2 mm.
A45: • | B45: Bobina madre (opción C): sin cotización; Pradecon indicó que cuesta lo mismo que la bobina flejada.
A46: • | B46: Diámetros de los discos del 1 kg y espesor de la cúpula del 10 kg: a confirmar con los planos.

Sheet Resumen D
A1: Resumen de la opción elegida: D — hojas estándar para cuerpos + fleje a medida para cúpulas y fondos
A2: Todo vinculado al cálculo. Años 2026–2035; la columna N suma los 10 años.
A4: 1. Indicadores principales
A5: Indicador | B5: Valor | C5: Unidad
A6: Valor actual 10 años (costos + inversión, tasa de Supuestos) | B6: =Comparacion!$E$12 -> 914216.35 | C6: USD
A7: Inversión inicial en equipos | B7: =Supuestos!$K$108 -> 71310.975 | C7: USD
A8: Costo operativo acumulado 10 años (nominal) | B8: =Comparacion!$E$11 -> 1946376.6 | C8: USD
A9: Acero comprado en 10 años | B9: =Comparacion!$E$6 -> 1581.7317 | C9: t
A10: Scrap generado en 10 años | B10: =Comparacion!$E$7 -> 271.74648 | C10: t
A11: Aprovechamiento global de chapa | B11: =Comparacion!$E$8 -> 0.82819685 | C11: %
A12: Costo anual en el año de referencia | B12: =Comparacion!$E$10 -> 442735.29 | C12: USD/año
A13: Stock promedio en el año de referencia | B13: =Comparacion!$E$16 -> 26.473533 | C13: t
A14: Horas-hombre de corte en el año de referencia | B14: =Comparacion!$E$17 -> 627.14898 | C14: h/año
A15: Operarios de corte equivalentes | B15: =Comparacion!$E$18 -> 0.3484161 | C15: personas
A16: Ahorro de VA frente a A / B / C | B16: =TEXT(Comparacion!$B$15,"#,##0")&" / "&TEXT(Comparacion!$C$15,"#,##0")&" / "&TEXT(Comparacion!$D$15,"#,##0") -> 56.431 / 27.254 / 102.156 | C16: USD
A17: Año de referencia | B17: =Supuestos!$B$21 -> 2035
A19: 2. Costos anuales (USD)
A20: Concepto | B20: Unidad | D20: 2026 | E20: 2027 | F20: 2028 | G20: 2029 | H20: 2030 | I20: 2031 | J20: 2032 | K20: 2033 | L20: 2034 | M20: 2035 | N20: Total 10 años
A21: Acero: hojas para cuerpos | B21: USD | D21: =Calculo!D216 -> 10612.582 | E21: =Calculo!E216 -> 18532.97 | F21: =Calculo!F216 -> 31085.053 | G21: =Calculo!G216 -> 55918.623 | H21: =Calculo!H216 -> 94442.763 | I21: =Calculo!I216 -> 132310.93 | J21: =Calculo!J216 -> 178168.75 | K21: =Calculo!K216 -> 225415.46 | ... M21: =Calculo!M216 -> 296951.25 | N21: =SUM(D21:M21) -> 1300673.5
A22: Acero: fleje para cúpulas y fondos | B22: USD | D22: =Calculo!D215 -> 4457.9306 | E22: =Calculo!E215 -> 7572.9665 | F22: =Calculo!F215 -> 14002.587 | G22: =Calculo!G215 -> 27633.339 | H22: =Calculo!H215 -> 47515.768 | I22: =Calculo!I215 -> 66734.714 | J22: =Calculo!J215 -> 90882.627 | K22: =Calculo!K215 -> 115500.63 | ... M22: =Calculo!M215 -> 151352.64 | N22: =SUM(D22:M22) -> 656749.29
A23: Venta de scrap (resta) | B23: USD | D23: =Calculo!D261 -> -516.24349 | E23: =Calculo!E261 -> -887.9296 | F23: =Calculo!F261 -> -1547.107 | G23: =Calculo!G261 -> -2896.8753 | H23: =Calculo!H261 -> -4924.5101 | I23: =Calculo!I261 -> -6902.2548 | J23: =Calculo!J261 -> -9343.0768 | K23: =Calculo!K261 -> -11847.927 | ... M23: =Calculo!M261 -> -15579.517 | N23: =SUM(D23:M23) -> -67936.62
A24: Costo financiero del stock | B24: USD | D24: =Calculo!D263 -> 190.5311 | E24: =Calculo!E263 -> 322.64932 | F24: =Calculo!F263 -> 516.93533 | G24: =Calculo!G263 -> 909.59644 | H24: =Calculo!H263 -> 1448.7865 | I24: =Calculo!I263 -> 1938.3238 | J24: =Calculo!J263 -> 2514.4686 | K24: =Calculo!K263 -> 3083.4842 | ... M24: =Calculo!M263 -> 3932.2645 | N24: =SUM(D24:M24) -> 18316.435
A25: Mano de obra de corte | B25: USD | D25: =Calculo!D265 -> 129.56301 | E25: =Calculo!E265 -> 230.0393 | F25: =Calculo!F265 -> 397.41948 | G25: =Calculo!G265 -> 734.34289 | H25: =Calculo!H265 -> 1246.4186 | I25: =Calculo!I265 -> 1749.0149 | J25: =Calculo!J265 -> 2359.0451 | K25: =Calculo!K265 -> 2986.9783 | ... M25: =Calculo!M265 -> 3939.3259 | N25: =SUM(D25:M25) -> 17180.739
A26: Mantenimiento de equipos | B26: USD | D26: =Calculo!D266 -> 2139.3292 | E26: =Calculo!E266 -> 2139.3292 | F26: =Calculo!F266 -> 2139.3292 | G26: =Calculo!G266 -> 2139.3292 | H26: =Calculo!H266 -> 2139.3292 | I26: =Calculo!I266 -> 2139.3292 | J26: =Calculo!J266 -> 2139.3292 | K26: =Calculo!K266 -> 2139.3292 | ... M26: =Calculo!M266 -> 2139.3292 | N26: =SUM(D26:M26) -> 21393.292
A27: COSTO ANUAL TOTAL | B27: USD | D27: =Calculo!D267 -> 17013.692 | E27: =Calculo!E267 -> 27910.025 | F27: =Calculo!F267 -> 46594.218 | G27: =Calculo!G267 -> 84438.355 | H27: =Calculo!H267 -> 141868.56 | I27: =Calculo!I267 -> 197970.06 | J27: =Calculo!J267 -> 266721.14 | K27: =Calculo!K267 -> 337277.95 | ... M27: =Calculo!M267 -> 442735.29 | N27: =SUM(D27:M27) -> 1946376.6
A28: Factor de descuento | D28: =Calculo!D282 -> 0.89285714 | E28: =Calculo!E282 -> 0.79719388 | F28: =Calculo!F282 -> 0.71178025 | G28: =Calculo!G282 -> 0.63551808 | H28: =Calculo!H282 -> 0.56742686 | I28: =Calculo!I282 -> 0.50663112 | J28: =Calculo!J282 -> 0.45234922 | K28: =Calculo!K282 -> 0.40388323 | ... M28: =Calculo!M282 -> 0.32197324
A29: Costo anual descontado | B29: USD | D29: =D27*D28 -> 15190.797 | E29: =E27*E28 -> 22249.701 | F29: =F27*F28 -> 33164.844 | G29: =G27*G28 -> 53662.101 | H29: =H27*H28 -> 80500.028 | I29: =I27*I28 -> 100297.79 | J29: =J27*J28 -> 120651.1 | K29: =K27*K28 -> 136220.91 | ... M29: =M27*M28 -> 142548.91 | N29: =SUM(D29:M29) -> 842905.38
A30: Valor actual = inversión inicial + suma de costos descontados | N30: =Supuestos!$K$108+N29 -> 914216.35
A32: 3. Producción y costo de acero por unidad
A33: Concepto | B33: Unidad | D33: 2026 | E33: 2027 | F33: 2028 | G33: 2029 | H33: 2030 | I33: 2031 | J33: 2032 | K33: 2033 | L33: 2034 | M33: 2035 | N33: Total 10 años
A34: Unidades fabricadas (matafuegos + cilindros, todos los formatos) | B34: u | D34: =SUM(Calculo!D8:D15) -> 6958 | E34: =SUM(Calculo!E8:E15) -> 10963 | F34: =SUM(Calculo!F8:F15) -> 23077 | G34: =SUM(Calculo!G8:G15) -> 50958 | H34: =SUM(Calculo!H8:H15) -> 88903 | I34: =SUM(Calculo!I8:I15) -> 124900 | J34: =SUM(Calculo!J8:J15) -> 172353 | K34: =SUM(Calculo!K8:K15) -> 220292 | ... M34: =SUM(Calculo!M8:M15) -> 287333 | N34: =SUM(D34:M34) -> 1234395
A35: Costo de acero por unidad (promedio) | B35: USD/u | D35: =IF(D34=0,0,(D21+D22)/D34) -> 2.1659259 | E35: =IF(E34=0,0,(E21+E22)/E34) -> 2.3812767 | F35: =IF(F34=0,0,(F21+F22)/F34) -> 1.9537912 | G35: =IF(G34=0,0,(G21+G22)/G34) -> 1.639624 | H35: =IF(H34=0,0,(H21+H22)/H34) -> 1.59678 | I35: =IF(I34=0,0,(I21+I22)/I34) -> 1.5936401 | J35: =IF(J34=0,0,(J21+J22)/J34) -> 1.5610484 | K35: =IF(K34=0,0,(K21+K22)/K34) -> 1.5475645 | ... M35: =IF(M34=0,0,(M21+M22)/M34) -> 1.5602241
A36: Costo total por unidad: acero − scrap + stock + corte + mantenimiento (promedio) | B36: USD/u | D36: =IF(D34=0,0,D27/D34) -> 2.4451986 | E36: =IF(E34=0,0,E27/E34) -> 2.5458383 | F36: =IF(F34=0,0,F27/F34) -> 2.019076 | G36: =IF(G34=0,0,G27/G34) -> 1.6570186 | H36: =IF(H34=0,0,H27/H34) -> 1.5957679 | I36: =IF(I34=0,0,I27/I34) -> 1.5850285 | J36: =IF(J34=0,0,J27/J34) -> 1.5475283 | K36: =IF(K34=0,0,K27/K34) -> 1.5310495 | ... M36: =IF(M34=0,0,M27/M34) -> 1.5408438
A38: 4. Acero comprado (t)
A39: Concepto | B39: Unidad | D39: 2026 | E39: 2027 | F39: 2028 | G39: 2029 | H39: 2030 | I39: 2031 | J39: 2032 | K39: 2033 | L39: 2034 | M39: 2035 | N39: Total 10 años
A40: Hojas cuerpo 2,5 kg | B40: t | D40: =Calculo!D91 -> 0.31995776 | E40: =Calculo!E91 -> 0.76898324 | F40: =Calculo!F91 -> 1.3958835 | G40: =Calculo!G91 -> 2.7603136 | H40: =Calculo!H91 -> 4.604138 | I40: =Calculo!I91 -> 6.5672687 | J40: =Calculo!J91 -> 8.7484045 | K40: =Calculo!K91 -> 11.093315 | ... M40: =Calculo!M91 -> 15.286389 | N40: =SUM(D40:M40) -> 64.49047
A41: Hojas cuerpo 5 kg | B41: t | D41: =Calculo!D92 -> 4.734592 | E41: =Calculo!E92 -> 8.0735707 | F41: =Calculo!F92 -> 13.794536 | G41: =Calculo!G92 -> 25.131533 | H41: =Calculo!H92 -> 42.728853 | I41: =Calculo!I92 -> 59.68608 | J41: =Calculo!J92 -> 80.666451 | K41: =Calculo!K92 -> 102.10223 | ... M41: =Calculo!M92 -> 133.61371 | N41: =SUM(D41:M41) -> 586.59622
A42: Hojas cuerpo 10 kg | B42: t | D42: =Calculo!D93 -> 0.434424 | E42: =Calculo!E93 -> 0.835794 | F42: =Calculo!F93 -> 1.619646 | G42: =Calculo!G93 -> 3.177906 | H42: =Calculo!H93 -> 5.600292 | I42: =Calculo!I93 -> 8.112396 | J42: =Calculo!J93 -> 10.964484 | K42: =Calculo!K93 -> 13.88268 | ... M42: =Calculo!M93 -> 18.189144 | N42: =SUM(D42:M42) -> 78.602412
A43: Hojas cuerpo 25 kg | B43: t | D43: =Calculo!D94 -> 0.428128 | E43: =Calculo!E94 -> 0.730336 | F43: =Calculo!F94 -> 1.13328 | G43: =Calculo!G94 -> 1.8888 | H43: =Calculo!H94 -> 3.135408 | I43: =Calculo!I94 -> 4.369424 | J43: =Calculo!J94 -> 5.842688 | K43: =Calculo!K94 -> 7.36632 | ... M43: =Calculo!M94 -> 9.7588 | N43: =SUM(D43:M43) -> 43.089824
A44: Hojas cuerpo 50 kg | B44: t | D44: =Calculo!D95 -> 1.4166 | E44: =Calculo!E95 -> 2.417664 | F44: =Calculo!F95 -> 3.739824 | G44: =Calculo!G95 -> 6.270816 | H44: =Calculo!H95 -> 10.350624 | I44: =Calculo!I95 -> 14.430432 | J44: =Calculo!J95 -> 19.26576 | K44: =Calculo!K95 -> 24.308856 | ... M44: =Calculo!M95 -> 32.20404 | N44: =SUM(D44:M44) -> 142.2833
A45: Hojas cuerpo 70 kg | B45: t | D45: =Calculo!D96 -> 0 | E45: =Calculo!E96 -> 0 | F45: =Calculo!F96 -> 0 | G45: =Calculo!G96 -> 0 | H45: =Calculo!H96 -> 0 | I45: =Calculo!I96 -> 0 | J45: =Calculo!J96 -> 0 | K45: =Calculo!K96 -> 0 | ... M45: =Calculo!M96 -> 0 | N45: =SUM(D45:M45) -> 0
A46: Hojas cuerpo 100 kg | B46: t | D46: =Calculo!D97 -> 0.31775125 | E46: =Calculo!E97 -> 0.46728125 | F46: =Calculo!F97 -> 0.822415 | G46: =Calculo!G97 -> 1.4018438 | H46: =Calculo!H97 -> 2.2616412 | I46: =Calculo!I97 -> 3.065365 | J46: =Calculo!J97 -> 4.0746925 | K46: =Calculo!K97 -> 5.158785 | ... M46: =Calculo!M97 -> 6.87838 | N46: =SUM(D46:M46) -> 30.429355
A47: Hojas mixtas 70/100 | B47: t | D47: =Calculo!D98 -> 0.89718 | E47: =Calculo!E98 -> 1.6261387 | F47: =Calculo!F98 -> 2.4111713 | G47: =Calculo!G98 -> 4.03731 | H47: =Calculo!H98 -> 6.6727763 | I47: =Calculo!I98 -> 9.3082425 | J47: =Calculo!J98 -> 12.504446 | K47: =Calculo!K98 -> 15.812798 | ... M47: =Calculo!M98 -> 20.915509 | N47: =SUM(D47:M47) -> 92.241319
A48: Fleje Cúpula 1 kg | B48: t | D48: =Calculo!D66 -> 0.37643878 | E48: =Calculo!E66 -> 0.54020182 | F48: =Calculo!F66 -> 1.3074019 | G48: =Calculo!G66 -> 3.1673464 | H48: =Calculo!H66 -> 5.595327 | I48: =Calculo!I66 -> 7.8638684 | J48: =Calculo!J66 -> 10.960233 | K48: =Calculo!K66 -> 14.064254 | ... M48: =Calculo!M66 -> 18.251831 | N48: =SUM(D48:M48) -> 77.926071
A49: Fleje Fondo 1 kg | B49: t | D49: =Calculo!D67 -> 0.32479521 | E49: =Calculo!E67 -> 0.46609163 | F49: =Calculo!F67 -> 1.1280397 | G49: =Calculo!G67 -> 2.7328187 | H49: =Calculo!H67 -> 4.8277051 | I49: =Calculo!I67 -> 6.7850257 | J49: =Calculo!J67 -> 9.4566004 | K49: =Calculo!K67 -> 12.134781 | ... M49: =Calculo!M67 -> 15.747866 | N49: =SUM(D49:M49) -> 67.235407
A50: Fleje Cúpula 2,5 kg | B50: t | D50: =Calculo!D68 -> 0.1061659 | E50: =Calculo!E68 -> 0.25515806 | F50: =Calculo!F68 -> 0.46317125 | G50: =Calculo!G68 -> 0.91590585 | H50: =Calculo!H68 -> 1.5277094 | I50: =Calculo!I68 -> 2.1791002 | J50: =Calculo!J68 -> 2.9028277 | K50: =Calculo!K68 -> 3.6808979 | ... M50: =Calculo!M68 -> 5.072211 | N50: =SUM(D50:M50) -> 21.398728
A51: Fleje Fondo 2,5 kg | B51: t | D51: =Calculo!D69 -> 0.088082701 | E51: =Calculo!E69 -> 0.21169707 | F51: =Calculo!F69 -> 0.38427944 | G51: =Calculo!G69 -> 0.75989991 | H51: =Calculo!H69 -> 1.2674951 | I51: =Calculo!I69 -> 1.8079348 | J51: =Calculo!J69 -> 2.4083901 | K51: =Calculo!K69 -> 3.0539317 | ... M51: =Calculo!M69 -> 4.208263 | N51: =SUM(D51:M51) -> 17.753889
A52: Fleje Cúpula 5 kg | B52: t | D52: =Calculo!D70 -> 1.598817 | E52: =Calculo!E70 -> 2.7263515 | F52: =Calculo!F70 -> 4.6582554 | G52: =Calculo!G70 -> 8.4866283 | H52: =Calculo!H70 -> 14.42904 | I52: =Calculo!I70 -> 20.155299 | J52: =Calculo!J70 -> 27.240128 | K52: =Calculo!K70 -> 34.478744 | ... M52: =Calculo!M70 -> 45.119806 | N52: =SUM(D52:M52) -> 198.08676
A53: Fleje Fondo 5 kg | B53: t | D53: =Calculo!D71 -> 1.0278109 | E53: =Calculo!E71 -> 1.7526545 | F53: =Calculo!F71 -> 2.9945927 | G53: =Calculo!G71 -> 5.4556896 | H53: =Calculo!H71 -> 9.2758114 | I53: =Calculo!I71 -> 12.956978 | J53: =Calculo!J71 -> 17.511511 | K53: =Calculo!K71 -> 22.164907 | ... M53: =Calculo!M71 -> 29.00559 | N53: =SUM(D53:M53) -> 127.34149
A54: Fleje Cúpula 10 kg | B54: t | D54: =Calculo!D72 -> 0.11395444 | E54: =Calculo!E72 -> 0.21923843 | F54: =Calculo!F72 -> 0.42485187 | G54: =Calculo!G72 -> 0.83360147 | H54: =Calculo!H72 -> 1.4690213 | I54: =Calculo!I72 -> 2.1279752 | J54: =Calculo!J72 -> 2.8761109 | K54: =Calculo!K72 -> 3.6415874 | ... M54: =Calculo!M72 -> 4.7712227 | N54: =SUM(D54:M54) -> 20.618321
A55: Fleje Fondo 10 kg | B55: t | D55: =Calculo!D73 -> 0.075375839 | E55: =Calculo!E73 -> 0.14501656 | F55: =Calculo!F73 -> 0.28102079 | G55: =Calculo!G73 -> 0.55139065 | H55: =Calculo!H73 -> 0.97169288 | I55: =Calculo!I73 -> 1.4075619 | J55: =Calculo!J73 -> 1.9024206 | K55: =Calculo!K73 -> 2.4087496 | ... M55: =Calculo!M73 -> 3.1559536 | N55: =SUM(D55:M55) -> 13.638111
A56: TOTAL ACERO COMPRADO | B56: t | D56: =Calculo!D259 -> 12.260074 | E56: =Calculo!E259 -> 21.236177 | F56: =Calculo!F259 -> 36.558369 | G56: =Calculo!G259 -> 67.571804 | H56: =Calculo!H259 -> 114.71753 | I56: =Calculo!I259 -> 160.82295 | J56: =Calculo!J259 -> 217.32515 | K56: =Calculo!K259 -> 275.35284 | ... M56: =Calculo!M259 -> 362.17872 | N56: =SUM(D56:M56) -> 1581.7317
A57: Acero neto en piezas | B57: t | D57: =Calculo!D41 -> 10.1951 | E57: =Calculo!E41 -> 17.684459 | F57: =Calculo!F41 -> 30.369941 | G57: =Calculo!G41 -> 55.984302 | H57: =Calculo!H41 -> 95.019494 | I57: =Calculo!I41 -> 133.21393 | J57: =Calculo!J41 -> 179.95284 | K57: =Calculo!K41 -> 227.96113 | ... M57: =Calculo!M41 -> 299.86065 | N57: =SUM(D57:M57) -> 1309.9852
A58: Scrap | B58: t | D58: =Calculo!D260 -> 2.064974 | E58: =Calculo!E260 -> 3.5517184 | F58: =Calculo!F260 -> 6.1884281 | G58: =Calculo!G260 -> 11.587501 | H58: =Calculo!H260 -> 19.698041 | I58: =Calculo!I260 -> 27.609019 | J58: =Calculo!J260 -> 37.372307 | K58: =Calculo!K260 -> 47.391709 | ... M58: =Calculo!M260 -> 62.318067 | N58: =SUM(D58:M58) -> 271.74648
A59: Aprovechamiento | B59: % | D59: =IF(Calculo!D259=0,0,Calculo!D41/Calculo!D259) -> 0.83156921 | E59: =IF(Calculo!E259=0,0,Calculo!E41/Calculo!E259) -> 0.83275152 | F59: =IF(Calculo!F259=0,0,Calculo!F41/Calculo!F259) -> 0.83072472 | G59: =IF(Calculo!G259=0,0,Calculo!G41/Calculo!G259) -> 0.82851573 | H59: =IF(Calculo!H259=0,0,Calculo!H41/Calculo!H259) -> 0.82829094 | I59: =IF(Calculo!I259=0,0,Calculo!I41/Calculo!I259) -> 0.82832662 | J59: =IF(Calculo!J259=0,0,Calculo!J41/Calculo!J259) -> 0.82803505 | K59: =IF(Calculo!K259=0,0,Calculo!K41/Calculo!K259) -> 0.82788734 | ... M59: =IF(Calculo!M259=0,0,Calculo!M41/Calculo!M259) -> 0.82793559
A61: 5. Compras en unidades
A62: Concepto | B62: Unidad | D62: 2026 | E62: 2027 | F62: 2028 | G62: 2029 | H62: 2030 | I62: 2031 | J62: 2032 | K62: 2033 | L62: 2034 | M62: 2035 | N62: Total 10 años
A63: Hojas cuerpo 2,5 kg | B63: hojas | D63: =Calculo!D80 -> 10.925926 | E63: =Calculo!E80 -> 26.259259 | F63: =Calculo!F80 -> 47.666667 | G63: =Calculo!G80 -> 94.259259 | H63: =Calculo!H80 -> 157.22222 | I63: =Calculo!I80 -> 224.25926 | J63: =Calculo!J80 -> 298.74074 | K63: =Calculo!K80 -> 378.81481 | ... M63: =Calculo!M80 -> 522 | N63: =SUM(D63:M63) -> 2202.2222
A64: Hojas cuerpo 5 kg | B64: hojas | D64: =Calculo!D81 -> 188 | E64: =Calculo!E81 -> 320.58333 | F64: =Calculo!F81 -> 547.75 | G64: =Calculo!G81 -> 997.91667 | H64: =Calculo!H81 -> 1696.6667 | I64: =Calculo!I81 -> 2370 | J64: =Calculo!J81 -> 3203.0833 | K64: =Calculo!K81 -> 4054.25 | ... M64: =Calculo!M81 -> 5305.5 | N64: =SUM(D64:M64) -> 23292.417
A65: Hojas cuerpo 10 kg | B65: hojas | D65: =Calculo!D82 -> 6.1333333 | E65: =Calculo!E82 -> 11.8 | F65: =Calculo!F82 -> 22.866667 | G65: =Calculo!G82 -> 44.866667 | H65: =Calculo!H82 -> 79.066667 | I65: =Calculo!I82 -> 114.53333 | J65: =Calculo!J82 -> 154.8 | K65: =Calculo!K82 -> 196 | ... M65: =Calculo!M82 -> 256.8 | N65: =SUM(D65:M65) -> 1109.7333
A66: Hojas cuerpo 25 kg | B66: hojas | D66: =Calculo!D83 -> 3.7777778 | E66: =Calculo!E83 -> 6.4444444 | F66: =Calculo!F83 -> 10 | G66: =Calculo!G83 -> 16.666667 | H66: =Calculo!H83 -> 27.666667 | I66: =Calculo!I83 -> 38.555556 | J66: =Calculo!J83 -> 51.555556 | K66: =Calculo!K83 -> 65 | ... M66: =Calculo!M83 -> 86.111111 | N66: =SUM(D66:M66) -> 380.22222
A67: Hojas cuerpo 50 kg | B67: hojas | D67: =Calculo!D84 -> 12.5 | E67: =Calculo!E84 -> 21.333333 | F67: =Calculo!F84 -> 33 | G67: =Calculo!G84 -> 55.333333 | H67: =Calculo!H84 -> 91.333333 | I67: =Calculo!I84 -> 127.33333 | J67: =Calculo!J84 -> 170 | K67: =Calculo!K84 -> 214.5 | ... M67: =Calculo!M84 -> 284.16667 | N67: =SUM(D67:M67) -> 1255.5
A68: Hojas cuerpo 70 kg | B68: hojas | D68: =Calculo!D85 -> 0 | E68: =Calculo!E85 -> 0 | F68: =Calculo!F85 -> 0 | G68: =Calculo!G85 -> 0 | H68: =Calculo!H85 -> 0 | I68: =Calculo!I85 -> 0 | J68: =Calculo!J85 -> 0 | K68: =Calculo!K85 -> 0 | ... M68: =Calculo!M85 -> 0 | N68: =SUM(D68:M68) -> 0
A69: Hojas cuerpo 100 kg | B69: hojas | D69: =Calculo!D86 -> 1.8888889 | E69: =Calculo!E86 -> 2.7777778 | F69: =Calculo!F86 -> 4.8888889 | G69: =Calculo!G86 -> 8.3333333 | H69: =Calculo!H86 -> 13.444444 | I69: =Calculo!I86 -> 18.222222 | J69: =Calculo!J86 -> 24.222222 | K69: =Calculo!K86 -> 30.666667 | ... M69: =Calculo!M86 -> 40.888889 | N69: =SUM(D69:M69) -> 180.88889
A70: Hojas mixtas 70/100 | B70: hojas | D70: =Calculo!D87 -> 5.3333333 | E70: =Calculo!E87 -> 9.6666667 | F70: =Calculo!F87 -> 14.333333 | G70: =Calculo!G87 -> 24 | H70: =Calculo!H87 -> 39.666667 | I70: =Calculo!I87 -> 55.333333 | J70: =Calculo!J87 -> 74.333333 | K70: =Calculo!K87 -> 94 | ... M70: =Calculo!M87 -> 124.33333 | N70: =SUM(D70:M70) -> 548.33333
A71: Rollos fleje Cúpula 1 kg | B71: rollos | D71: =Calculo!D202 -> 0.37643878 | E71: =Calculo!E202 -> 0.54020182 | F71: =Calculo!F202 -> 1.3074019 | G71: =Calculo!G202 -> 3.1673464 | H71: =Calculo!H202 -> 5.595327 | I71: =Calculo!I202 -> 7.8638684 | J71: =Calculo!J202 -> 10.960233 | K71: =Calculo!K202 -> 14.064254 | ... M71: =Calculo!M202 -> 18.251831 | N71: =SUM(D71:M71) -> 77.926071
A72: Rollos fleje Fondo 1 kg | B72: rollos | D72: =Calculo!D203 -> 0.32479521 | E72: =Calculo!E203 -> 0.46609163 | F72: =Calculo!F203 -> 1.1280397 | G72: =Calculo!G203 -> 2.7328187 | H72: =Calculo!H203 -> 4.8277051 | I72: =Calculo!I203 -> 6.7850257 | J72: =Calculo!J203 -> 9.4566004 | K72: =Calculo!K203 -> 12.134781 | ... M72: =Calculo!M203 -> 15.747866 | N72: =SUM(D72:M72) -> 67.235407
A73: Rollos fleje Cúpula 2,5 kg | B73: rollos | D73: =Calculo!D204 -> 0.21233181 | E73: =Calculo!E204 -> 0.51031611 | F73: =Calculo!F204 -> 0.9263425 | G73: =Calculo!G204 -> 1.8318117 | H73: =Calculo!H204 -> 3.0554187 | I73: =Calculo!I204 -> 4.3582004 | J73: =Calculo!J204 -> 5.8056555 | K73: =Calculo!K204 -> 7.3617957 | ... M73: =Calculo!M204 -> 10.144422 | N73: =SUM(D73:M73) -> 42.797455
A74: Rollos fleje Fondo 2,5 kg | B74: rollos | D74: =Calculo!D205 -> 0.1761654 | E74: =Calculo!E205 -> 0.42339414 | F74: =Calculo!F205 -> 0.76855889 | G74: =Calculo!G205 -> 1.5197998 | H74: =Calculo!H205 -> 2.5349903 | I74: =Calculo!I205 -> 3.6158695 | J74: =Calculo!J205 -> 4.8167801 | K74: =Calculo!K205 -> 6.1078635 | ... M74: =Calculo!M205 -> 8.416526 | N74: =SUM(D74:M74) -> 35.507779
A75: Rollos fleje Cúpula 5 kg | B75: rollos | D75: =Calculo!D206 -> 2.664695 | E75: =Calculo!E206 -> 4.5439192 | F75: =Calculo!F206 -> 7.763759 | G75: =Calculo!G206 -> 14.144381 | H75: =Calculo!H206 -> 24.0484 | I75: =Calculo!I206 -> 33.592166 | J75: =Calculo!J206 -> 45.400213 | K75: =Calculo!K206 -> 57.464573 | ... M75: =Calculo!M206 -> 75.199677 | N75: =SUM(D75:M75) -> 330.14461
A76: Rollos fleje Fondo 5 kg | B76: rollos | D76: =Calculo!D207 -> 2.0556219 | E76: =Calculo!E207 -> 3.5053091 | F76: =Calculo!F207 -> 5.9891855 | G76: =Calculo!G207 -> 10.911379 | H76: =Calculo!H207 -> 18.551623 | I76: =Calculo!I207 -> 25.913956 | J76: =Calculo!J207 -> 35.023022 | K76: =Calculo!K207 -> 44.329813 | ... M76: =Calculo!M207 -> 58.011179 | N76: =SUM(D76:M76) -> 254.68298
A77: Rollos fleje Cúpula 10 kg | B77: rollos | D77: =Calculo!D208 -> 0.15193925 | E77: =Calculo!E208 -> 0.2923179 | F77: =Calculo!F208 -> 0.56646915 | G77: =Calculo!G208 -> 1.1114686 | H77: =Calculo!H208 -> 1.9586951 | I77: =Calculo!I208 -> 2.8373003 | J77: =Calculo!J208 -> 3.8348145 | K77: =Calculo!K208 -> 4.8554499 | ... M77: =Calculo!M208 -> 6.3616303 | N77: =SUM(D77:M77) -> 27.491095
A78: Rollos fleje Fondo 10 kg | B78: rollos | D78: =Calculo!D209 -> 0.15075168 | E78: =Calculo!E209 -> 0.29003312 | F78: =Calculo!F209 -> 0.56204158 | G78: =Calculo!G209 -> 1.1027813 | H78: =Calculo!H209 -> 1.9433858 | I78: =Calculo!I209 -> 2.8151237 | J78: =Calculo!J209 -> 3.8048412 | K78: =Calculo!K209 -> 4.8174992 | ... M78: =Calculo!M209 -> 6.3119072 | N78: =SUM(D78:M78) -> 27.276222
A80: 6. Stock, operación y personal
A81: Concepto | B81: Unidad | D81: 2026 | E81: 2027 | F81: 2028 | G81: 2029 | H81: 2030 | I81: 2031 | J81: 2032 | K81: 2033 | L81: 2034 | M81: 2035 | N81: Total 10 años
A82: Stock promedio (hojas + flejes) | B82: t | D82: =Calculo!D262 -> 1.2916644 | E82: =Calculo!E262 -> 2.1871903 | F82: =Calculo!F262 -> 3.4928849 | G82: =Calculo!G262 -> 6.1302243 | H82: =Calculo!H262 -> 9.7564416 | I82: =Calculo!I262 -> 13.050899 | J82: =Calculo!J262 -> 16.925431 | K82: =Calculo!K262 -> 20.754035 | ... M82: =Calculo!M262 -> 26.473533
A83: Cortes de guillotina | B83: cortes | D83: =Calculo!D112 -> 3437.7333 | E83: =Calculo!E112 -> 6116.3722 | F83: =Calculo!F112 -> 10533.072 | G83: =Calculo!G112 -> 19400.128 | H83: =Calculo!H112 -> 32904.644 | I83: =Calculo!I112 -> 46170.267 | J83: =Calculo!J112 -> 62242.094 | K83: =Calculo!K112 -> 78794.861 | ... M83: =Calculo!M112 -> 103956.79 | N83: =SUM(D83:M83) -> 453500.01
A84: Horas-hombre de corte (guillotina + cambios de fleje) | B84: h | D84: =Calculo!D264 -> 20.626703 | E84: =Calculo!E264 -> 36.622741 | F84: =Calculo!F264 -> 63.270017 | G84: =Calculo!G264 -> 116.90893 | H84: =Calculo!H264 -> 198.43247 | I84: =Calculo!I264 -> 278.44686 | J84: =Calculo!J264 -> 375.56495 | K84: =Calculo!K264 -> 475.53324 | ... M84: =Calculo!M264 -> 627.14898 | N84: =SUM(D84:M84) -> 2735.2099
A85: Operarios de corte equivalentes | B85: personas | D85: =Calculo!D264/Supuestos!$B$42 -> 0.01145928 | E85: =Calculo!E264/Supuestos!$B$42 -> 0.020345967 | F85: =Calculo!F264/Supuestos!$B$42 -> 0.03515001 | G85: =Calculo!G264/Supuestos!$B$42 -> 0.064949408 | H85: =Calculo!H264/Supuestos!$B$42 -> 0.11024026 | I85: =Calculo!I264/Supuestos!$B$42 -> 0.1546927 | J85: =Calculo!J264/Supuestos!$B$42 -> 0.2086472 | K85: =Calculo!K264/Supuestos!$B$42 -> 0.26418513 | ... M85: =Calculo!M264/Supuestos!$B$42 -> 0.3484161
A87: 7. Equipos de la opción D
A88: Equipo | B88: Cantidad | C88: Precio unitario (USD) | D88: Subtotal (USD)
A89: =IF(Supuestos!F96=0,"",Supuestos!A96) | B89: =Supuestos!F96 -> 0 | C89: =Supuestos!B96 -> 80000 | D89: =B89*C89 -> 0
A90: =IF(Supuestos!F97=0,"",Supuestos!A97) -> Guillotina hidráulica 6 × 3.200 mm con tope motorizado | B90: =Supuestos!F97 -> 1 | C90: =Supuestos!B97 -> 25810.975 | D90: =B90*C90 -> 25810.975
A91: =IF(Supuestos!F98=0,"",Supuestos!A98) | B91: =Supuestos!F98 -> 0 | C91: =Supuestos!B98 -> 60000 | D91: =B91*C91 -> 0
A92: =IF(Supuestos!F99=0,"",Supuestos!A99) | B92: =Supuestos!F99 -> 0 | C92: =Supuestos!B99 -> 30000 | D92: =B92*C92 -> 0
A93: =IF(Supuestos!F100=0,"",Supuestos!A100) | B93: =Supuestos!F100 -> 0 | C93: =Supuestos!B100 -> 6000 | D93: =B93*C93 -> 0
A94: =IF(Supuestos!F101=0,"",Supuestos!A101) -> Desbobinador + enderezador + alimentador servo para la prensa de discos | B94: =Supuestos!F101 -> 1 | C94: =Supuestos!B101 -> 12000 | D94: =B94*C94 -> 12000
A95: =IF(Supuestos!F102=0,"",Supuestos!A102) -> Estantería porta-flejes | B95: =Supuestos!F102 -> 1 | C95: =Supuestos!B102 -> 3000 | D95: =B95*C95 -> 3000
A96: =IF(Supuestos!F103=0,"",Supuestos!A103) -> Autoelevador eléctrico 2,5 t | B96: =Supuestos!F103 -> 1 | C96: =Supuestos!B103 -> 20000 | D96: =B96*C96 -> 20000
A97: =IF(Supuestos!F104=0,"",Supuestos!A104) -> Mesa elevadora de tijera 1500 × 3000 mm, 3 t, elevación ~1 m (paquete de hojas a la altura de la guillotina) | B97: =Supuestos!F104 -> 1 | C97: =Supuestos!B104 -> 7000 | D97: =B97*C97 -> 7000
A98: =IF(Supuestos!F105=0,"",Supuestos!A105) -> Apoyos con bolas (mesa de bolas) entre la mesa elevadora y la guillotina | B98: =Supuestos!F105 -> 1 | C98: =Supuestos!B105 -> 1500 | D98: =B98*C98 -> 1500
A99: =IF(Supuestos!F106=0,"",Supuestos!A106) -> Racks por espesor en el almacén de MP y carros porta-desarrollos | B99: =Supuestos!F106 -> 1 | C99: =Supuestos!B106 -> 2000 | D99: =B99*C99 -> 2000
A100: =IF(Supuestos!F107=0,"",Supuestos!A107) | B100: =Supuestos!F107 -> 0 | C100: =Supuestos!B107 -> 1500 | D100: =B100*C100 -> 0
A101: TOTAL | D101: =SUM(D89:D100) -> 71310.975
A102: Las filas en blanco son equipos que no usa la opción D.
A104: 8. Materia prima: formato, proveedor y precio
A105: Pieza | B105: Compra | C105: Espesor (mm) | D105: USD/kg | E105: Proveedor de referencia | F105: Consumo año de referencia (t)
A106: Cuerpo 2,5 kg | B106: ="Hoja "&Nesting!H6&" × "&Nesting!I6 -> Hoja 1220 × 2440 | C106: =Nesting!E6 -> 1.25 | D106: =Calculo!$N$91 -> 1.2902977 | E106: Pradecon | F106: {=INDEX(Calculo!$D$91:$M$91,MATCH(Supuestos!$B$21,Calculo!$D$4:$M$4,0))} -> 15.286389
A107: Cuerpo 5 kg | B107: ="Hoja "&Nesting!H7&" × "&Nesting!I7 -> Hoja 1000 × 2000 | C107: =Nesting!E7 -> 1.6 | D107: =Calculo!$N$92 -> 1.327521 | E107: Pradecon | F107: {=INDEX(Calculo!$D$92:$M$92,MATCH(Supuestos!$B$21,Calculo!$D$4:$M$4,0))} -> 133.61371
A108: Cuerpo 10 kg | B108: ="Hoja "&Nesting!H8&" × "&Nesting!I8 -> Hoja 1500 × 3000 | C108: =Nesting!E8 -> 2 | D108: =Calculo!$N$93 -> 1.2804013 | E108: Pradecon | F108: {=INDEX(Calculo!$D$93:$M$93,MATCH(Supuestos!$B$21,Calculo!$D$4:$M$4,0))} -> 18.189144
...
