Workbook

Sheet PARAMETROS
A1: PARÁMETROS SALARIALES Y FINANCIEROS | CCT N°260/75 UOM — Acta agosto 2026
A2: Editá las celdas con borde grueso. Todo el modelo se recalcula. Los parámetros de cada máquina van en CONSOLIDADO.
A4: A. Salarios — editables
A5: Concepto | B5: Valor | C5: Unidad | D5: Fuente / Nota
A6: Valor hora base ingresante Rama 17 | B6: 4485.97 | C6: ARS/h | D6: Cláusula SEGUNDA, acta agosto 2026 — vigente desde 1/8/2026
A7: Horas mensuales (jornada legal) | B7: 200 | C7: h/mes | D7: 8 hs/día × 25 días — LCT
A8: Gratificación extraordinaria | B8: 40000 | C8: ARS/mes | D8: Cláusula TERCERA — varía por mes según el acta, editable
A9: Compensación extraordinaria | B9: 70000 | C9: ARS/mes | D9: Cláusula CUARTA — cuota 2/3 (agosto, septiembre, octubre 2026)
A10: Contribuciones patronales TOTAL | B10: 0.24 | C10: % | D10: 18% Decreto 814/01 MiPyME industrial + 6% OS = 24%. Agregar ART cuando se cotice (~2,5%).
A11: Recargo hora extra 50% | B11: 0.5 | C11: % | D11: LCT art. 201 — primeras 2 horas extra por día
A12: Recargo hora extra 100% | B12: 1 | C12: % | D12: LCT art. 201 — tercera hora en adelante o días inhábiles
A13: Horas extra mensuales estimadas | B13: 40 | C13: h/mes | D13: Referencia: 2 hs extra × 20 días hábiles — editable
A15: B. Costo de capital — editable
A16: Concepto | B16: Valor | C16: Unidad | D16: Fuente / Nota
A17: Tasa costo de capital mensual | B17: 0.05 | C17: % | D17: Costo de oportunidad del dinero inmovilizado. Usar: tasa SGR si hay financiamiento, o tasa plazo fijo si es capital propio. Referencia sep 2026: ~5% mensual. EDITABLE.
A19: C. Categorías salariales (calculado)
A20: Categoría | B20: Factor CCT | C20: Hora (ARS) | D20: Básico/mes | E20: Total bruto/mes | F20: Costo empresa/mes | G20: Descripción
A21: P1 — Ayudante | B21: 1 | C21: =$B$6*B21 -> 4485.97 | D21: =C21*$B$7 -> 897194 | E21: =D21+$B$8+$B$9 -> 1007194 | F21: =E21*(1+$B$10) -> 1248920.6 | G21: Tareas auxiliares sin calificación.
A22: P2 — Semiespecializado | B22: 1.08 | C22: =$B$6*B22 -> 4844.8476 | D22: =C22*$B$7 -> 968969.52 | E22: =D22+$B$8+$B$9 -> 1078969.5 | F22: =E22*(1+$B$10) -> 1337922.2 | G22: Granallado, etiquetado, embalaje.
A23: P3 — Especializado | B23: 1.14 | C23: =$B$6*B23 -> 5114.0058 | D23: =C23*$B$7 -> 1022801.2 | E23: =D23+$B$8+$B$9 -> 1132801.2 | F23: =E23*(1+$B$10) -> 1404673.4 | G23: Prensa, rolado, bordoneado, PH, pintura, llenado, ensamblaje. MÁS FRECUENTE EN FLAMA.
A24: P4 — Oficial | B24: 1.23 | C24: =$B$6*B24 -> 5517.7431 | D24: =C24*$B$7 -> 1103548.6 | E24: =D24+$B$8+$B$9 -> 1213548.6 | F24: =E24*(1+$B$10) -> 1504800.3 | G24: Soldador MIG/MAG longitudinal y circunferencial.
A25: P5 — Oficial esp. | B25: 1.32 | C25: =$B$6*B25 -> 5921.4804 | D25: =C25*$B$7 -> 1184296.1 | E25: =D25+$B$8+$B$9 -> 1294296.1 | F25: =E25*(1+$B$10) -> 1604927.1 | G25: Múltiples procesos complejos.
A27: Agregar ART a las cargas cuando se cotice (~2,5% para metalúrgica). Tasa de capital: ajustar según fuente de financiamiento. Acta vigente hasta 1/10/2026.

Sheet CONSOLIDADO
A1: CONSOLIDADO — ANÁLISIS COMPLETO POR PUESTO | Máquina vs. Operario vs. Turno Extra
A2: Borde grueso = input. Col C desde PARAMETROS (salarios). Cols D–J: datos de la máquina por puesto. Todo lo demás calculado.
C3: DECISIÓN
A4: Puesto operativo | B4: Categoría CCT | C4: Costo operario (ARS/mes c/cargas) | D4: Precio (USD) | E4: TC (ARS/USD) | F4: Precio (ARS) | G4: Vida útil (años) | H4: VR % | I4: Energía (ARS/mes) | J4: Mant. (ARS/mes) | K4: Amort.+op. máq. (ARS/mes) | L4: Costo oport. capital (ARS/mes) | M4: COSTO TOTAL máq. (ARS/mes) | N4: Ahorro real (ARS/mes) | O4: PI real (meses) | P4: PI real (años) | Q4: Acum. 12m Operario | R4: Acum. 12m Máquina real | S4: Acum. 36m Operario | T4: Acum. 36m Máquina real | U4: Turno extra 50% (ARS/mes) | V4: Turno extra 100% (ARS/mes) | W4: Decisión (PI real)
A5: Operario de prensa (preparacion de cuello) | B5: P2 — Semiespecializado | C5: =PARAMETROS!F22 -> 1337922.2 | D5: 2000 | E5: 1420 | F5: =IF(D5="","-",D5*E5) -> 2840000 | G5: 10 | H5: 0.1 | I5: 50000 | J5: 30000 | K5: =IF(OR(D5="",F5="-"),"-",(F5*(1-H5))/(G5*12)+I5+J5) -> 101300 | L5: =IF(OR(D5="",F5="-"),"-",F5*PARAMETROS!$B$17) -> 142000 | M5: =IF(K5="-","-",K5+L5) -> 243300 | N5: =IF(M5="-","-",C5-M5) -> 1094622.2 | O5: =IF(OR(N5="-",N5<=0),"-",F5/N5) -> 2.5945025 | P5: =IF(O5="-","-",O5/12) -> 0.21620854 | Q5: =C5*12 -> 16055066 | R5: =IF(F5="-","-",F5+M5*12) -> 5759600 | S5: =C5*36 -> 48165199 | T5: =IF(F5="-","-",F5+M5*36) -> 11598800 | U5: =PARAMETROS!C21*(1+PARAMETROS!$B$11)*PARAMETROS!$B$13*(1+PARAMETROS!$B$10) -> 333756.17 | V5: =PARAMETROS!C21*(1+PARAMETROS!$B$12)*PARAMETROS!$B$13*(1+PARAMETROS!$B$10) -> 445008.22 | W5: =IF(O5="-","Sin precio",IF(O5<12,"Comprar — PI < 1 año",IF(O5<36,"Conveniente — PI < 3 años",IF(O5<60,"Analizar — PI 3-5 años","No conviene — PI > 5 años")))) -> Comprar — PI < 1 año
A6: Operario de prensa (numerado) | B6: P2 — Semiespecializado | C6: =PARAMETROS!F22 -> 1337922.2 | D6: 2000 | E6: 1420 | F6: =IF(D6="","-",D6*E6) -> 2840000 | G6: 10 | H6: 0.1 | I6: 50000 | J6: 30000 | K6: =IF(OR(D6="",F6="-"),"-",(F6*(1-H6))/(G6*12)+I6+J6) -> 101300 | L6: =IF(OR(D6="",F6="-"),"-",F6*PARAMETROS!$B$17) -> 142000 | M6: =IF(K6="-","-",K6+L6) -> 243300 | N6: =IF(M6="-","-",C6-M6) -> 1094622.2 | O6: =IF(OR(N6="-",N6<=0),"-",F6/N6) -> 2.5945025 | P6: =IF(O6="-","-",O6/12) -> 0.21620854 | Q6: =C6*12 -> 16055066 | R6: =IF(F6="-","-",F6+M6*12) -> 5759600 | S6: =C6*36 -> 48165199 | T6: =IF(F6="-","-",F6+M6*36) -> 11598800 | U6: =PARAMETROS!C22*(1+PARAMETROS!$B$11)*PARAMETROS!$B$13*(1+PARAMETROS!$B$10) -> 360456.66 | V6: =PARAMETROS!C22*(1+PARAMETROS!$B$12)*PARAMETROS!$B$13*(1+PARAMETROS!$B$10) -> 480608.88 | W6: =IF(O6="-","Sin precio",IF(O6<12,"Comprar — PI < 1 año",IF(O6<36,"Conveniente — PI < 3 años",IF(O6<60,"Analizar — PI 3-5 años","No conviene — PI > 5 años")))) -> Comprar — PI < 1 año
A7: Operario de prensa (embutido) | B7: P2 — Semiespecializado | C7: =PARAMETROS!F22 -> 1337922.2 | D7: 39056 | E7: 1420 | F7: =IF(D7="","-",D7*E7) -> 55459520 | G7: 10 | H7: 0.1 | I7: 50000 | J7: 30000 | K7: =IF(OR(D7="",F7="-"),"-",(F7*(1-H7))/(G7*12)+I7+J7) -> 495946.4 | L7: =IF(OR(D7="",F7="-"),"-",F7*PARAMETROS!$B$17) -> 2772976 | M7: =IF(K7="-","-",K7+L7) -> 3268922.4 | N7: =IF(M7="-","-",C7-M7) -> -1931000.2 | O7: =IF(OR(N7="-",N7<=0),"-",F7/N7) -> - | P7: =IF(O7="-","-",O7/12) -> - | Q7: =C7*12 -> 16055066 | R7: =IF(F7="-","-",F7+M7*12) -> 94686589 | S7: =C7*36 -> 48165199 | T7: =IF(F7="-","-",F7+M7*36) -> 1.7314073e+08 | U7: =PARAMETROS!C23*(1+PARAMETROS!$B$11)*PARAMETROS!$B$13*(1+PARAMETROS!$B$10) -> 380482.03 | V7: =PARAMETROS!C23*(1+PARAMETROS!$B$12)*PARAMETROS!$B$13*(1+PARAMETROS!$B$10) -> 507309.38 | W7: =IF(O7="-","Sin precio",IF(O7<12,"Comprar — PI < 1 año",IF(O7<36,"Conveniente — PI < 3 años",IF(O7<60,"Analizar — PI 3-5 años","No conviene — PI > 5 años")))) -> Sin precio
A8: Operario de rolado (cilindradora) | B8: P3 — Especializado | C8: =PARAMETROS!F23 -> 1404673.4 | D8: 6880 | E8: 1420 | F8: =IF(D8="","-",D8*E8) -> 9769600 | G8: 10 | H8: 0.1 | I8: 50000 | J8: 30000 | K8: =IF(OR(D8="",F8="-"),"-",(F8*(1-H8))/(G8*12)+I8+J8) -> 153272 | L8: =IF(OR(D8="",F8="-"),"-",F8*PARAMETROS!$B$17) -> 488480 | M8: =IF(K8="-","-",K8+L8) -> 641752 | N8: =IF(M8="-","-",C8-M8) -> 762921.44 | O8: =IF(OR(N8="-",N8<=0),"-",F8/N8) -> 12.805512 | P8: =IF(O8="-","-",O8/12) -> 1.067126 | Q8: =C8*12 -> 16856081 | R8: =IF(F8="-","-",F8+M8*12) -> 17470624 | S8: =C8*36 -> 50568244 | T8: =IF(F8="-","-",F8+M8*36) -> 32872672 | U8: =PARAMETROS!C23*(1+PARAMETROS!$B$11)*PARAMETROS!$B$13*(1+PARAMETROS!$B$10) -> 380482.03 | V8: =PARAMETROS!C23*(1+PARAMETROS!$B$12)*PARAMETROS!$B$13*(1+PARAMETROS!$B$10) -> 507309.38 | W8: =IF(O8="-","Sin precio",IF(O8<12,"Comprar — PI < 1 año",IF(O8<36,"Conveniente — PI < 3 años",IF(O8<60,"Analizar — PI 3-5 años","No conviene — PI > 5 años")))) -> Conveniente — PI < 3 años
A9: Soldador longitudinal MIG/MAG GETWELD | B9: P4 — Oficial | C9: =PARAMETROS!F24 -> 1504800.3 | D9: 30500 | E9: 1420 | F9: =IF(D9="","-",D9*E9) -> 43310000 | G9: 10 | H9: 0.1 | I9: 50000 | J9: 30000 | K9: =IF(OR(D9="",F9="-"),"-",(F9*(1-H9))/(G9*12)+I9+J9) -> 404825 | L9: =IF(OR(D9="",F9="-"),"-",F9*PARAMETROS!$B$17) -> 2165500 | M9: =IF(K9="-","-",K9+L9) -> 2570325 | N9: =IF(M9="-","-",C9-M9) -> -1065524.7 | O9: =IF(OR(N9="-",N9<=0),"-",F9/N9) -> - | P9: =IF(O9="-","-",O9/12) -> - | Q9: =C9*12 -> 18057603 | R9: =IF(F9="-","-",F9+M9*12) -> 74153900 | S9: =C9*36 -> 54172810 | T9: =IF(F9="-","-",F9+M9*36) -> 135841700 | U9: =PARAMETROS!C24*(1+PARAMETROS!$B$11)*PARAMETROS!$B$13*(1+PARAMETROS!$B$10) -> 410520.09 | V9: =PARAMETROS!C24*(1+PARAMETROS!$B$12)*PARAMETROS!$B$13*(1+PARAMETROS!$B$10) -> 547360.12 | W9: =IF(O9="-","Sin precio",IF(O9<12,"Comprar — PI < 1 año",IF(O9<36,"Conveniente — PI < 3 años",IF(O9<60,"Analizar — PI 3-5 años","No conviene — PI > 5 años")))) -> Sin precio
A10: Soldador longitudinal MIG/MAG MITUSA | B10: P4 — Oficial | C10: =PARAMETROS!F24 -> 1504800.3 | D10: 166700 | E10: 1420 | F10: =IF(D10="","-",D10*E10) -> 236714000 | G10: 10 | H10: 0.1 | I10: 50000 | J10: 30000 | K10: =IF(OR(D10="",F10="-"),"-",(F10*(1-H10))/(G10*12)+I10+J10) -> 1855355 | L10: =IF(OR(D10="",F10="-"),"-",F10*PARAMETROS!$B$17) -> 11835700 | M10: =IF(K10="-","-",K10+L10) -> 13691055 | N10: =IF(M10="-","-",C10-M10) -> -12186255 | O10: =IF(OR(N10="-",N10<=0),"-",F10/N10) -> - | P10: =IF(O10="-","-",O10/12) -> - | Q10: =C10*12 -> 18057603 | R10: =IF(F10="-","-",F10+M10*12) -> 401006660 | S10: =C10*36 -> 54172810 | T10: =IF(F10="-","-",F10+M10*36) -> 729591980 | U10: =PARAMETROS!C25*(1+PARAMETROS!$B$11)*PARAMETROS!$B$13*(1+PARAMETROS!$B$10) -> 440558.14 | V10: =PARAMETROS!C25*(1+PARAMETROS!$B$12)*PARAMETROS!$B$13*(1+PARAMETROS!$B$10) -> 587410.86 | W10: =IF(O10="-","Sin precio",IF(O10<12,"Comprar — PI < 1 año",IF(O10<36,"Conveniente — PI < 3 años",IF(O10<60,"Analizar — PI 3-5 años","No conviene — PI > 5 años")))) -> Sin precio
A11: Soldador longitudinal MIG/MAG Firesafer | B11: P4 — Oficial | C11: =PARAMETROS!F24 -> 1504800.3 | D11: 22450 | E11: 1420 | F11: =IF(D11="","-",D11*E11) -> 31879000 | G11: 10 | H11: 0.1 | I11: 50000 | J11: 30000 | K11: =IF(OR(D11="",F11="-"),"-",(F11*(1-H11))/(G11*12)+I11+J11) -> 319092.5 | L11: =IF(OR(D11="",F11="-"),"-",F11*PARAMETROS!$B$17) -> 1593950 | M11: =IF(K11="-","-",K11+L11) -> 1913042.5 | N11: =IF(M11="-","-",C11-M11) -> -408242.21 | O11: =IF(OR(N11="-",N11<=0),"-",F11/N11) -> - | P11: =IF(O11="-","-",O11/12) -> - | Q11: =C11*12 -> 18057603 | R11: =IF(F11="-","-",F11+M11*12) -> 54835510 | S11: =C11*36 -> 54172810 | T11: =IF(F11="-","-",F11+M11*36) -> 100748530 | U11: =PARAMETROS!C26*(1+PARAMETROS!$B$11)*PARAMETROS!$B$13*(1+PARAMETROS!$B$10) -> 0 | V11: =PARAMETROS!C26*(1+PARAMETROS!$B$12)*PARAMETROS!$B$13*(1+PARAMETROS!$B$10) -> 0 | W11: =IF(O11="-","Sin precio",IF(O11<12,"Comprar — PI < 1 año",IF(O11<36,"Conveniente — PI < 3 años",IF(O11<60,"Analizar — PI 3-5 años","No conviene — PI > 5 años")))) -> Sin precio
A12: Operario Encastre de Fondo | B12: P3 — Especializado | C12: =PARAMETROS!F23 -> 1404673.4 | D12: 5718 | E12: 1420 | F12: =IF(D12="","-",D12*E12) -> 8119560 | G12: 10 | H12: 0.1 | I12: 50000 | J12: 30000 | K12: =IF(OR(D12="",F12="-"),"-",(F12*(1-H12))/(G12*12)+I12+J12) -> 140896.7 | L12: =IF(OR(D12="",F12="-"),"-",F12*PARAMETROS!$B$17) -> 405978 | M12: =IF(K12="-","-",K12+L12) -> 546874.7 | N12: =IF(M12="-","-",C12-M12) -> 857798.74 | O12: =IF(OR(N12="-",N12<=0),"-",F12/N12) -> 9.465577 | P12: =IF(O12="-","-",O12/12) -> 0.78879808 | Q12: =C12*12 -> 16856081 | R12: =IF(F12="-","-",F12+M12*12) -> 14682056 | S12: =C12*36 -> 50568244 | T12: =IF(F12="-","-",F12+M12*36) -> 27807049 | U12: =PARAMETROS!C23*(1+PARAMETROS!$B$11)*PARAMETROS!$B$13*(1+PARAMETROS!$B$10) -> 380482.03 | V12: =PARAMETROS!C23*(1+PARAMETROS!$B$12)*PARAMETROS!$B$13*(1+PARAMETROS!$B$10) -> 507309.38 | W12: =IF(O12="-","Sin precio",IF(O12<12,"Comprar — PI < 1 año",IF(O12<36,"Conveniente — PI < 3 años",IF(O12<60,"Analizar — PI 3-5 años","No conviene — PI > 5 años")))) -> Comprar — PI < 1 año
A13: Soldador circunferencial MIG/MAG | B13: P4 — Oficial | C13: =PARAMETROS!F24 -> 1504800.3 | D13: 15578 | E13: 1420 | F13: =IF(D13="","-",D13*E13) -> 22120760 | G13: 10 | H13: 0.1 | I13: 50000 | J13: 30000 | K13: =IF(OR(D13="",F13="-"),"-",(F13*(1-H13))/(G13*12)+I13+J13) -> 245905.7 | L13: =IF(OR(D13="",F13="-"),"-",F13*PARAMETROS!$B$17) -> 1106038 | M13: =IF(K13="-","-",K13+L13) -> 1351943.7 | N13: =IF(M13="-","-",C13-M13) -> 152856.59 | O13: =IF(OR(N13="-",N13<=0),"-",F13/N13) -> 144.71578 | P13: =IF(O13="-","-",O13/12) -> 12.059648 | Q13: =C13*12 -> 18057603 | R13: =IF(F13="-","-",F13+M13*12) -> 38344084 | S13: =C13*36 -> 54172810 | T13: =IF(F13="-","-",F13+M13*36) -> 70790733 | U13: =PARAMETROS!C24*(1+PARAMETROS!$B$11)*PARAMETROS!$B$13*(1+PARAMETROS!$B$10) -> 410520.09 | V13: =PARAMETROS!C24*(1+PARAMETROS!$B$12)*PARAMETROS!$B$13*(1+PARAMETROS!$B$10) -> 547360.12 | W13: =IF(O13="-","Sin precio",IF(O13<12,"Comprar — PI < 1 año",IF(O13<36,"Conveniente — PI < 3 años",IF(O13<60,"Analizar — PI 3-5 años","No conviene — PI > 5 años")))) -> No conviene — PI > 5 años
A14: Soldador de cuello MIG | B14: P4 — Oficial | C14: =PARAMETROS!F24 -> 1504800.3 | E14: 1420 | F14: =IF(D14="","-",D14*E14) -> - | G14: 10 | H14: 0.1 | I14: 50000 | J14: 30000 | K14: =IF(OR(D14="",F14="-"),"-",(F14*(1-H14))/(G14*12)+I14+J14) -> - | L14: =IF(OR(D14="",F14="-"),"-",F14*PARAMETROS!$B$17) -> - | M14: =IF(K14="-","-",K14+L14) -> - | N14: =IF(M14="-","-",C14-M14) -> - | O14: =IF(OR(N14="-",N14<=0),"-",F14/N14) -> - | P14: =IF(O14="-","-",O14/12) -> - | Q14: =C14*12 -> 18057603 | R14: =IF(F14="-","-",F14+M14*12) -> - | S14: =C14*36 -> 54172810 | T14: =IF(F14="-","-",F14+M14*36) -> - | U14: =PARAMETROS!C24*(1+PARAMETROS!$B$11)*PARAMETROS!$B$13*(1+PARAMETROS!$B$10) -> 410520.09 | V14: =PARAMETROS!C24*(1+PARAMETROS!$B$12)*PARAMETROS!$B$13*(1+PARAMETROS!$B$10) -> 547360.12 | W14: =IF(O14="-","Sin precio",IF(O14<12,"Comprar — PI < 1 año",IF(O14<36,"Conveniente — PI < 3 años",IF(O14<60,"Analizar — PI 3-5 años","No conviene — PI > 5 años")))) -> Sin precio
A15: Operario de bordoneado | B15: P3 — Especializado | C15: =PARAMETROS!F23 -> 1404673.4 | D15: 21123 | E15: 1420 | F15: =IF(D15="","-",D15*E15) -> 29994660 | G15: 10 | H15: 0.1 | I15: 50000 | J15: 30000 | K15: =IF(OR(D15="",F15="-"),"-",(F15*(1-H15))/(G15*12)+I15+J15) -> 304959.95 | L15: =IF(OR(D15="",F15="-"),"-",F15*PARAMETROS!$B$17) -> 1499733 | M15: =IF(K15="-","-",K15+L15) -> 1804692.9 | N15: =IF(M15="-","-",C15-M15) -> -400019.51 | O15: =IF(OR(N15="-",N15<=0),"-",F15/N15) -> - | P15: =IF(O15="-","-",O15/12) -> - | Q15: =C15*12 -> 16856081 | R15: =IF(F15="-","-",F15+M15*12) -> 51650975 | S15: =C15*36 -> 50568244 | T15: =IF(F15="-","-",F15+M15*36) -> 94963606 | U15: =PARAMETROS!C23*(1+PARAMETROS!$B$11)*PARAMETROS!$B$13*(1+PARAMETROS!$B$10) -> 380482.03 | V15: =PARAMETROS!C23*(1+PARAMETROS!$B$12)*PARAMETROS!$B$13*(1+PARAMETROS!$B$10) -> 507309.38 | W15: =IF(O15="-","Sin precio",IF(O15<12,"Comprar — PI < 1 año",IF(O15<36,"Conveniente — PI < 3 años",IF(O15<60,"Analizar — PI 3-5 años","No conviene — PI > 5 años")))) -> Sin precio
A16: Operario de prueba hidráulica | B16: P3 — Especializado | C16: =PARAMETROS!F23 -> 1404673.4 | D16: 15578 | E16: 1420 | F16: =IF(D16="","-",D16*E16) -> 22120760 | G16: 10 | H16: 0.1 | I16: 50000 | J16: 30000 | K16: =IF(OR(D16="",F16="-"),"-",(F16*(1-H16))/(G16*12)+I16+J16) -> 245905.7 | L16: =IF(OR(D16="",F16="-"),"-",F16*PARAMETROS!$B$17) -> 1106038 | M16: =IF(K16="-","-",K16+L16) -> 1351943.7 | N16: =IF(M16="-","-",C16-M16) -> 52729.738 | O16: =IF(OR(N16="-",N16<=0),"-",F16/N16) -> 419.51204 | P16: =IF(O16="-","-",O16/12) -> 34.959336 | Q16: =C16*12 -> 16856081 | R16: =IF(F16="-","-",F16+M16*12) -> 38344084 | S16: =C16*36 -> 50568244 | T16: =IF(F16="-","-",F16+M16*36) -> 70790733 | U16: =PARAMETROS!C23*(1+PARAMETROS!$B$11)*PARAMETROS!$B$13*(1+PARAMETROS!$B$10) -> 380482.03 | V16: =PARAMETROS!C23*(1+PARAMETROS!$B$12)*PARAMETROS!$B$13*(1+PARAMETROS!$B$10) -> 507309.38 | W16: =IF(O16="-","Sin precio",IF(O16<12,"Comprar — PI < 1 año",IF(O16<36,"Conveniente — PI < 3 años",IF(O16<60,"Analizar — PI 3-5 años","No conviene — PI > 5 años")))) -> No conviene — PI > 5 años
A17: Operario de granallado | B17: P2 — Semiespecializado | C17: =PARAMETROS!F22 -> 1337922.2 | E17: 1420 | F17: =IF(D17="","-",D17*E17) -> - | G17: 10 | H17: 0.1 | I17: 50000 | J17: 30000 | K17: =IF(OR(D17="",F17="-"),"-",(F17*(1-H17))/(G17*12)+I17+J17) -> - | L17: =IF(OR(D17="",F17="-"),"-",F17*PARAMETROS!$B$17) -> - | M17: =IF(K17="-","-",K17+L17) -> - | N17: =IF(M17="-","-",C17-M17) -> - | O17: =IF(OR(N17="-",N17<=0),"-",F17/N17) -> - | P17: =IF(O17="-","-",O17/12) -> - | Q17: =C17*12 -> 16055066 | R17: =IF(F17="-","-",F17+M17*12) -> - | S17: =C17*36 -> 48165199 | T17: =IF(F17="-","-",F17+M17*36) -> - | U17: =PARAMETROS!C22*(1+PARAMETROS!$B$11)*PARAMETROS!$B$13*(1+PARAMETROS!$B$10) -> 360456.66 | V17: =PARAMETROS!C22*(1+PARAMETROS!$B$12)*PARAMETROS!$B$13*(1+PARAMETROS!$B$10) -> 480608.88 | W17: =IF(O17="-","Sin precio",IF(O17<12,"Comprar — PI < 1 año",IF(O17<36,"Conveniente — PI < 3 años",IF(O17<60,"Analizar — PI 3-5 años","No conviene — PI > 5 años")))) -> Sin precio
A18: Operario de pintura electrostática | B18: P3 — Especializado | C18: =PARAMETROS!F23*2 -> 2809346.9 | E18: 1420 | F18: =IF(D18="","-",D18*E18) -> - | G18: 10 | H18: 0.1 | I18: 50000 | J18: 30000 | K18: =IF(OR(D18="",F18="-"),"-",(F18*(1-H18))/(G18*12)+I18+J18) -> - | L18: =IF(OR(D18="",F18="-"),"-",F18*PARAMETROS!$B$17) -> - | M18: =IF(K18="-","-",K18+L18) -> - | N18: =IF(M18="-","-",C18-M18) -> - | O18: =IF(OR(N18="-",N18<=0),"-",F18/N18) -> - | P18: =IF(O18="-","-",O18/12) -> - | Q18: =C18*12 -> 33712163 | R18: =IF(F18="-","-",F18+M18*12) -> - | S18: =C18*36 -> 1.0113649e+08 | T18: =IF(F18="-","-",F18+M18*36) -> - | U18: =PARAMETROS!C23*(1+PARAMETROS!$B$11)*PARAMETROS!$B$13*(1+PARAMETROS!$B$10) -> 380482.03 | V18: =PARAMETROS!C23*(1+PARAMETROS!$B$12)*PARAMETROS!$B$13*(1+PARAMETROS!$B$10) -> 507309.38 | W18: =IF(O18="-","Sin precio",IF(O18<12,"Comprar — PI < 1 año",IF(O18<36,"Conveniente — PI < 3 años",IF(O18<60,"Analizar — PI 3-5 años","No conviene — PI > 5 años")))) -> Sin precio
A19: Operario de llenado de polvo | B19: P3 — Especializado | C19: =PARAMETROS!F23 -> 1404673.4 | D19: 2500 | E19: 1420 | F19: =IF(D19="","-",D19*E19) -> 3550000 | G19: 10 | H19: 0.1 | I19: 50000 | J19: 30000 | K19: =IF(OR(D19="",F19="-"),"-",(F19*(1-H19))/(G19*12)+I19+J19) -> 106625 | L19: =IF(OR(D19="",F19="-"),"-",F19*PARAMETROS!$B$17) -> 177500 | M19: =IF(K19="-","-",K19+L19) -> 284125 | N19: =IF(M19="-","-",C19-M19) -> 1120548.4 | O19: =IF(OR(N19="-",N19<=0),"-",F19/N19) -> 3.1680915 | P19: =IF(O19="-","-",O19/12) -> 0.26400763 | Q19: =C19*12 -> 16856081 | R19: =IF(F19="-","-",F19+M19*12) -> 6959500 | S19: =C19*36 -> 50568244 | T19: =IF(F19="-","-",F19+M19*36) -> 13778500 | U19: =PARAMETROS!C23*(1+PARAMETROS!$B$11)*PARAMETROS!$B$13*(1+PARAMETROS!$B$10) -> 380482.03 | V19: =PARAMETROS!C23*(1+PARAMETROS!$B$12)*PARAMETROS!$B$13*(1+PARAMETROS!$B$10) -> 507309.38 | W19: =IF(O19="-","Sin precio",IF(O19<12,"Comprar — PI < 1 año",IF(O19<36,"Conveniente — PI < 3 años",IF(O19<60,"Analizar — PI 3-5 años","No conviene — PI > 5 años")))) -> Comprar — PI < 1 año
A20: Operario de ensamblaje y presurización | B20: P3 — Especializado | C20: =PARAMETROS!F23 -> 1404673.4 | E20: 1420 | F20: =IF(D20="","-",D20*E20) -> - | G20: 10 | H20: 0.1 | I20: 50000 | J20: 30000 | K20: =IF(OR(D20="",F20="-"),"-",(F20*(1-H20))/(G20*12)+I20+J20) -> - | L20: =IF(OR(D20="",F20="-"),"-",F20*PARAMETROS!$B$17) -> - | M20: =IF(K20="-","-",K20+L20) -> - | N20: =IF(M20="-","-",C20-M20) -> - | O20: =IF(OR(N20="-",N20<=0),"-",F20/N20) -> - | P20: =IF(O20="-","-",O20/12) -> - | Q20: =C20*12 -> 16856081 | R20: =IF(F20="-","-",F20+M20*12) -> - | S20: =C20*36 -> 50568244 | T20: =IF(F20="-","-",F20+M20*36) -> - | U20: =PARAMETROS!C23*(1+PARAMETROS!$B$11)*PARAMETROS!$B$13*(1+PARAMETROS!$B$10) -> 380482.03 | V20: =PARAMETROS!C23*(1+PARAMETROS!$B$12)*PARAMETROS!$B$13*(1+PARAMETROS!$B$10) -> 507309.38 | W20: =IF(O20="-","Sin precio",IF(O20<12,"Comprar — PI < 1 año",IF(O20<36,"Conveniente — PI < 3 años",IF(O20<60,"Analizar — PI 3-5 años","No conviene — PI > 5 años")))) -> Sin precio
A21: Operario de etiquetado y embalaje | B21: P2 — Semiespecializado | C21: =PARAMETROS!F22 -> 1337922.2 | E21: 1420 | F21: =IF(D21="","-",D21*E21) -> - | G21: 10 | H21: 0.1 | I21: 50000 | J21: 30000 | K21: =IF(OR(D21="",F21="-"),"-",(F21*(1-H21))/(G21*12)+I21+J21) -> - | L21: =IF(OR(D21="",F21="-"),"-",F21*PARAMETROS!$B$17) -> - | M21: =IF(K21="-","-",K21+L21) -> - | N21: =IF(M21="-","-",C21-M21) -> - | O21: =IF(OR(N21="-",N21<=0),"-",F21/N21) -> - | P21: =IF(O21="-","-",O21/12) -> - | Q21: =C21*12 -> 16055066 | R21: =IF(F21="-","-",F21+M21*12) -> - | S21: =C21*36 -> 48165199 | T21: =IF(F21="-","-",F21+M21*36) -> - | U21: =PARAMETROS!C22*(1+PARAMETROS!$B$11)*PARAMETROS!$B$13*(1+PARAMETROS!$B$10) -> 360456.66 | V21: =PARAMETROS!C22*(1+PARAMETROS!$B$12)*PARAMETROS!$B$13*(1+PARAMETROS!$B$10) -> 480608.88 | W21: =IF(O21="-","Sin precio",IF(O21<12,"Comprar — PI < 1 año",IF(O21<36,"Conveniente — PI < 3 años",IF(O21<60,"Analizar — PI 3-5 años","No conviene — PI > 5 años")))) -> Sin precio
A22: Operario de cortadora plasma | B22: P3 — Especializado | C22: =PARAMETROS!F25 -> 1604927.1 | D22: 15731 | E22: 1420 | F22: =IF(D22="","-",D22*E22) -> 22338020 | G22: 10 | H22: 0.1 | I22: 50000 | J22: 30000 | K22: =IF(OR(D22="",F22="-"),"-",(F22*(1-H22))/(G22*12)+I22+J22) -> 247535.15 | L22: =IF(OR(D22="",F22="-"),"-",F22*PARAMETROS!$B$17) -> 1116901 | M22: =IF(K22="-","-",K22+L22) -> 1364436.1 | N22: =IF(M22="-","-",C22-M22) -> 240490.99 | O22: =IF(OR(N22="-",N22<=0),"-",F22/N22) -> 92.88506 | P22: =IF(O22="-","-",O22/12) -> 7.7404217 | Q22: =C22*12 -> 19259126 | R22: =IF(F22="-","-",F22+M22*12) -> 38711254 | S22: =C22*36 -> 57777377 | T22: =IF(F22="-","-",F22+M22*36) -> 71457721 | U22: =PARAMETROS!C23*(1+PARAMETROS!$B$11)*PARAMETROS!$B$13*(1+PARAMETROS!$B$10) -> 380482.03 | V22: =PARAMETROS!C23*(1+PARAMETROS!$B$12)*PARAMETROS!$B$13*(1+PARAMETROS!$B$10) -> 507309.38 | W22: =IF(O22="-","Sin precio",IF(O22<12,"Comprar — PI < 1 año",IF(O22<36,"Conveniente — PI < 3 años",IF(O22<60,"Analizar — PI 3-5 años","No conviene — PI > 5 años")))) -> No conviene — PI > 5 años
A23: COSTO OPORTUNIDAD CAPITAL: precio_ARS × tasa mensual (PARAMETROS B financiero). Representa el rendimiento alternativo perdido por inmovilizar ese capital. Es conservador (aplica sobre el total, no el saldo decreciente). Para mayor precisión usar VPN — esta es una aproximación lineal. TURNO EXTRA: costo mensual de cubrir la misma función con horas extra al 50% o 100%, a las horas extra estimadas en PARAMETROS. Comparar col U/V con col C para ver cuánto cuesta el turno extra vs. el operario regular. DECISIÓN: basada en PI real (incluye costo de capital).

Sheet OPERARIO COMUN P3
A1: COSTO DE OPORTUNIDAD — OPERARIO P3 (Especializado) | CCT N°260/75 Rama 17
A2: Detalle línea por línea del costo mensual del operario P3. Todo referenciado a PARAMETROS.
A4: Concepto | B4: Valor | C4: Unidad | D4: Fuente / Nota
A5: Valor hora base ingresante | B5: =PARAMETROS!B6 -> 4485.97 | C5: ARS/h | D5: Acta agosto 2026 — cláusula SEGUNDA
A6: Factor categoría P3 | B6: =PARAMETROS!B23 -> 1.14 | D6: CCT N°260/75
A7: Valor hora P3 | B7: =PARAMETROS!C23 -> 5114.0058 | C7: ARS/h | D7: Hora base x factor P3
A8: Horas mensuales | B8: =PARAMETROS!B7 -> 200 | C8: h/mes | D8: Jornada legal 8 hs × 25 días
A9: Salario básico mensual | B9: =PARAMETROS!D23 -> 1022801.2 | C9: ARS/mes | D9: Hora P3 x horas mensuales
A10: Gratificación extraordinaria | B10: =PARAMETROS!B8 -> 40000 | C10: ARS/mes | D10: Cláusula TERCERA del acta
A11: Compensación extraordinaria | B11: =PARAMETROS!B9 -> 70000 | C11: ARS/mes | D11: Cláusula CUARTA del acta — cuota 2/3
A12: TOTAL BRUTO MENSUAL | B12: =PARAMETROS!E23 -> 1132801.2 | C12: ARS/mes | D12: Basico + gratificacion + compensacion
A13: Contribuciones patronales (24%) | B13: =PARAMETROS!E23*PARAMETROS!B10 -> 271872.28 | C13: ARS/mes | D13: Total bruto x 24%
A14: COSTO TOTAL EMPRESA | B14: =PARAMETROS!F23 -> 1404673.4 | C14: ARS/mes | D14: Total bruto x (1 + 24%)
A16: Hora extra 50% (costo empresa) | B16: =PARAMETROS!C23*(1+PARAMETROS!B11)*(1+PARAMETROS!B10) -> 9512.0508 | C16: ARS/h | D16: Hora P3 x 1.50 x (1 + cargas)
A17: Hora extra 100% (costo empresa) | B17: =PARAMETROS!C23*(1+PARAMETROS!B12)*(1+PARAMETROS!B10) -> 12682.734 | C17: ARS/h | D17: Hora P3 x 2.00 x (1 + cargas)
A18: Costo turno extra 50% mensual (40hs est.) | B18: =PARAMETROS!C23*(1+PARAMETROS!B11)*PARAMETROS!B13*(1+PARAMETROS!B10) -> 380482.03 | C18: ARS/mes | D18: Hora extra 50% x horas estimadas
A19: Costo turno extra 100% mensual (40hs est.) | B19: =PARAMETROS!C23*(1+PARAMETROS!B12)*PARAMETROS!B13*(1+PARAMETROS!B10) -> 507309.38 | C19: ARS/mes | D19: Hora extra 100% x horas estimadas

Sheet SOLDADOR P4
A1: COSTO DE OPORTUNIDAD — SOLDADOR OFICIAL P4 | CCT N°260/75 Rama 17
A2: Detalle línea por línea del costo mensual del soldador P4. Todo referenciado a PARAMETROS.
A4: Concepto | B4: Valor | C4: Unidad | D4: Fuente / Nota
A5: Valor hora base ingresante | B5: =PARAMETROS!B6 -> 4485.97 | C5: ARS/h | D5: Acta agosto 2026 — cláusula SEGUNDA
A6: Factor categoría P4 | B6: =PARAMETROS!B24 -> 1.23 | D6: CCT N°260/75
A7: Valor hora P4 | B7: =PARAMETROS!C24 -> 5517.7431 | C7: ARS/h | D7: Hora base x factor P4
A8: Horas mensuales | B8: =PARAMETROS!B7 -> 200 | C8: h/mes | D8: Jornada legal 8 hs × 25 días
A9: Salario básico mensual | B9: =PARAMETROS!D24 -> 1103548.6 | C9: ARS/mes | D9: Hora P4 x horas mensuales
A10: Gratificación extraordinaria | B10: =PARAMETROS!B8 -> 40000 | C10: ARS/mes | D10: Cláusula TERCERA del acta
A11: Compensación extraordinaria | B11: =PARAMETROS!B9 -> 70000 | C11: ARS/mes | D11: Cláusula CUARTA del acta — cuota 2/3
A12: TOTAL BRUTO MENSUAL | B12: =PARAMETROS!E24 -> 1213548.6 | C12: ARS/mes | D12: Basico + gratificacion + compensacion
A13: Contribuciones patronales (24%) | B13: =PARAMETROS!E24*PARAMETROS!B10 -> 291251.67 | C13: ARS/mes | D13: Total bruto x 24%
A14: COSTO TOTAL EMPRESA | B14: =PARAMETROS!F24 -> 1504800.3 | C14: ARS/mes | D14: Total bruto x (1 + 24%)
A16: Hora extra 50% (costo empresa) | B16: =PARAMETROS!C24*(1+PARAMETROS!B11)*(1+PARAMETROS!B10) -> 10263.002 | C16: ARS/h | D16: Hora P4 x 1.50 x (1 + cargas)
A17: Hora extra 100% (costo empresa) | B17: =PARAMETROS!C24*(1+PARAMETROS!B12)*(1+PARAMETROS!B10) -> 13684.003 | C17: ARS/h | D17: Hora P4 x 2.00 x (1 + cargas)
A18: Costo turno extra 50% mensual (40hs est.) | B18: =PARAMETROS!C24*(1+PARAMETROS!B11)*PARAMETROS!B13*(1+PARAMETROS!B10) -> 410520.09 | C18: ARS/mes | D18: Hora extra 50% x horas estimadas
A19: Costo turno extra 100% mensual (40hs est.) | B19: =PARAMETROS!C24*(1+PARAMETROS!B12)*PARAMETROS!B13*(1+PARAMETROS!B10) -> 547360.12 | C19: ARS/mes | D19: Hora extra 100% x horas estimadas
