Workbook

Sheet Resumen General
A1: RESUMEN GENERAL
A3: Indicador | B3: Valor | D3: Referencias
A4: Dotación año 10 (personas, con choferes) | B4: ='Servicios y Oficinas'!K42+'Almacen PT'!K105 -> 71 | D4: Dato | E4: Número azul = dato editable
A5: Máquinas de producción año 10 | B5: ='Resumen Capacidad'!K49+'Resumen Capacidad'!K228 -> 40 | E5: Pasa de manual a automática
A6: Máquinas de recargas año 10 | B6: ='Resumen Capacidad'!K299 -> 22 | E6: Agrega máquina
A7: Año del 2° turno | B7: ='Resumen Capacidad'!H50 -> 2032 | E7: Agrega turno
E8: Agrega operario
E9: Tercerizado
A11: Concepto | B11: 2026 | C11: 2027 | D11: 2028 | E11: 2029 | F11: 2030 | G11: 2031 | H11: 2032 | I11: 2033 | J11: 2034 | K11: 2035
A12: Demanda
A13: Matafuegos terminados (u) | B13: =SUM(datos_base!B3:B10) -> 6958 | C13: =SUM(datos_base!C3:C10) -> 10963 | D13: =SUM(datos_base!D3:D10) -> 13488 | E13: =SUM(datos_base!E3:E10) -> 17551 | F13: =SUM(datos_base!F3:F10) -> 27038 | G13: =SUM(datos_base!G3:G10) -> 35196 | H13: =SUM(datos_base!H3:H10) -> 45531 | I13: =SUM(datos_base!I3:I10) -> 56352 | ... K13: =SUM(datos_base!K3:K10) -> 73903
A14: Cilindros vendidos (u) | B14: =SUM(datos_base!B15:B22) -> 0 | C14: =SUM(datos_base!C15:C22) -> 0 | D14: =SUM(datos_base!D15:D22) -> 9589 | E14: =SUM(datos_base!E15:E22) -> 33407 | F14: =SUM(datos_base!F15:F22) -> 61865 | G14: =SUM(datos_base!G15:G22) -> 89704 | H14: =SUM(datos_base!H15:H22) -> 126822 | I14: =SUM(datos_base!I15:I22) -> 163940 | ... K14: =SUM(datos_base!K15:K22) -> 213430
A15: Recargas planta industrial (u) | B15: =datos_base!B73-datos_base!B66 -> 2338.1989 | C15: =datos_base!C73-datos_base!C66 -> 10498.783 | D15: =datos_base!D73-datos_base!D66 -> 21052.007 | E15: =datos_base!E73-datos_base!E66 -> 39050.558 | F15: =datos_base!F73-datos_base!F66 -> 57477.441 | G15: =datos_base!G73-datos_base!G66 -> 78232.252 | H15: =datos_base!H73-datos_base!H66 -> 97163.137 | I15: =datos_base!I73-datos_base!I66 -> 110459.95 | ... K15: =datos_base!K73-datos_base!K66 -> 127338.88
A16: Capacidad
A17: Turnos | B17: ='Resumen Capacidad'!B85 -> 1 | C17: ='Resumen Capacidad'!C85 -> 1 | D17: ='Resumen Capacidad'!D85 -> 1 | E17: ='Resumen Capacidad'!E85 -> 1 | F17: ='Resumen Capacidad'!F85 -> 1 | G17: ='Resumen Capacidad'!G85 -> 1 | H17: ='Resumen Capacidad'!H85 -> 2 | I17: ='Resumen Capacidad'!I85 -> 2 | ... K17: ='Resumen Capacidad'!K85 -> 2
A18: Máquinas producción 1–10 kg | B18: ='Resumen Capacidad'!B49 -> 19 | C18: ='Resumen Capacidad'!C49 -> 19 | D18: ='Resumen Capacidad'!D49 -> 19 | E18: ='Resumen Capacidad'!E49 -> 20 | F18: ='Resumen Capacidad'!F49 -> 24 | G18: ='Resumen Capacidad'!G49 -> 30 | H18: ='Resumen Capacidad'!H49 -> 30 | I18: ='Resumen Capacidad'!I49 -> 30 | ... K18: ='Resumen Capacidad'!K49 -> 31
A19: Máquinas línea de carros | B19: ='Resumen Capacidad'!B228 -> 8 | C19: ='Resumen Capacidad'!C228 -> 8 | D19: ='Resumen Capacidad'!D228 -> 8 | E19: ='Resumen Capacidad'!E228 -> 8 | F19: ='Resumen Capacidad'!F228 -> 8 | G19: ='Resumen Capacidad'!G228 -> 8 | H19: ='Resumen Capacidad'!H228 -> 8 | I19: ='Resumen Capacidad'!I228 -> 8 | ... K19: ='Resumen Capacidad'!K228 -> 9
A20: Guillotinas (corte de chapa) | B20: ='Resumen Capacidad'!B235 -> 1 | C20: ='Resumen Capacidad'!C235 -> 1 | D20: ='Resumen Capacidad'!D235 -> 1 | E20: ='Resumen Capacidad'!E235 -> 1 | F20: ='Resumen Capacidad'!F235 -> 1 | G20: ='Resumen Capacidad'!G235 -> 1 | H20: ='Resumen Capacidad'!H235 -> 1 | I20: ='Resumen Capacidad'!I235 -> 1 | ... K20: ='Resumen Capacidad'!K235 -> 1
A21: Máquinas recargas | B21: ='Resumen Capacidad'!B299 -> 17 | C21: ='Resumen Capacidad'!C299 -> 17 | D21: ='Resumen Capacidad'!D299 -> 17 | E21: ='Resumen Capacidad'!E299 -> 18 | F21: ='Resumen Capacidad'!F299 -> 19 | G21: ='Resumen Capacidad'!G299 -> 22 | H21: ='Resumen Capacidad'!H299 -> 22 | I21: ='Resumen Capacidad'!I299 -> 22 | ... K21: ='Resumen Capacidad'!K299 -> 22
A22: Ocupación pico máx. producción | B22: =MAX('Resumen Capacidad'!B5:B24) -> 0.23509265 | C22: =MAX('Resumen Capacidad'!C5:C24) -> 0.36805691 | D22: =MAX('Resumen Capacidad'!D5:D24) -> 0.78462444 | E22: =MAX('Resumen Capacidad'!E5:E24) -> 0.8045128 | F22: =MAX('Resumen Capacidad'!F5:F24) -> 0.84179365 | G22: =MAX('Resumen Capacidad'!G5:G24) -> 0.79461389 | H22: =MAX('Resumen Capacidad'!H5:H24) -> 0.85919407 | I22: =MAX('Resumen Capacidad'!I5:I24) -> 0.8866684 | ... K22: =MAX('Resumen Capacidad'!K5:K24) -> 0.87176973
A23: Dotación
A24: Producción 1–10 kg y carros (mañana) | B24: ='Dotacion Planta'!B102 -> 5 | C24: ='Dotacion Planta'!C102 -> 5 | D24: ='Dotacion Planta'!D102 -> 5 | E24: ='Dotacion Planta'!E102 -> 6 | F24: ='Dotacion Planta'!F102 -> 10 | G24: ='Dotacion Planta'!G102 -> 14 | H24: ='Dotacion Planta'!H102 -> 18 | I24: ='Dotacion Planta'!I102 -> 23 | ... K24: ='Dotacion Planta'!K102 -> 30
A25: Recargas (mañana) | B25: ='Dotacion Planta'!B103 -> 0 | C25: ='Dotacion Planta'!C103 -> 2 | D25: ='Dotacion Planta'!D103 -> 3 | E25: ='Dotacion Planta'!E103 -> 6 | F25: ='Dotacion Planta'!F103 -> 9 | G25: ='Dotacion Planta'!G103 -> 12 | H25: ='Dotacion Planta'!H103 -> 14 | I25: ='Dotacion Planta'!I103 -> 16 | ... K25: ='Dotacion Planta'!K103 -> 16
A26: Recargas (tarde: mostrador + recargas) | B26: ='Dotacion Planta'!B105 -> 0 | C26: ='Dotacion Planta'!C105 -> 0 | D26: ='Dotacion Planta'!D105 -> 0 | E26: ='Dotacion Planta'!E105 -> 0 | F26: ='Dotacion Planta'!F105 -> 0 | G26: ='Dotacion Planta'!G105 -> 0 | H26: ='Dotacion Planta'!H105 -> 2 | I26: ='Dotacion Planta'!I105 -> 2 | ... K26: ='Dotacion Planta'!K105 -> 2
A27: Turno tarde (pool de producción) | B27: ='Dotacion Planta'!B104 -> 0 | C27: ='Dotacion Planta'!C104 -> 0 | D27: ='Dotacion Planta'!D104 -> 0 | E27: ='Dotacion Planta'!E104 -> 0 | F27: ='Dotacion Planta'!F104 -> 0 | G27: ='Dotacion Planta'!G104 -> 0 | H27: ='Dotacion Planta'!H104 -> 1 | I27: ='Dotacion Planta'!I104 -> 2 | ... K27: ='Dotacion Planta'!K104 -> 6
A28: Encargados | B28: ='Dotacion Planta'!B106 -> 1 | C28: ='Dotacion Planta'!C106 -> 1 | D28: ='Dotacion Planta'!D106 -> 1 | E28: ='Dotacion Planta'!E106 -> 1 | F28: ='Dotacion Planta'!F106 -> 1 | G28: ='Dotacion Planta'!G106 -> 1 | H28: ='Dotacion Planta'!H106 -> 2 | I28: ='Dotacion Planta'!I106 -> 2 | ... K28: ='Dotacion Planta'!K106 -> 2
A29: Administración | B29: ='Servicios y Oficinas'!B29+'Servicios y Oficinas'!B30 -> 4 | C29: ='Servicios y Oficinas'!C29+'Servicios y Oficinas'!C30 -> 4 | D29: ='Servicios y Oficinas'!D29+'Servicios y Oficinas'!D30 -> 5 | E29: ='Servicios y Oficinas'!E29+'Servicios y Oficinas'!E30 -> 5 | F29: ='Servicios y Oficinas'!F29+'Servicios y Oficinas'!F30 -> 6 | G29: ='Servicios y Oficinas'!G29+'Servicios y Oficinas'!G30 -> 6 | H29: ='Servicios y Oficinas'!H29+'Servicios y Oficinas'!H30 -> 7 | I29: ='Servicios y Oficinas'!I29+'Servicios y Oficinas'!I30 -> 7 | ... K29: ='Servicios y Oficinas'!K29+'Servicios y Oficinas'!K30 -> 7
A30: Choferes de reparto | B30: ='Almacen PT'!B105 -> 2 | C30: ='Almacen PT'!C105 -> 2 | D30: ='Almacen PT'!D105 -> 2 | E30: ='Almacen PT'!E105 -> 3 | F30: ='Almacen PT'!F105 -> 4 | G30: ='Almacen PT'!G105 -> 5 | H30: ='Almacen PT'!H105 -> 6 | I30: ='Almacen PT'!I105 -> 7 | ... K30: ='Almacen PT'!K105 -> 8
A31: TOTAL PERSONAS | B31: =SUM(B24:B30) -> 12 | C31: =SUM(C24:C30) -> 14 | D31: =SUM(D24:D30) -> 16 | E31: =SUM(E24:E30) -> 21 | F31: =SUM(F24:F30) -> 30 | G31: =SUM(G24:G30) -> 38 | H31: =SUM(H24:H30) -> 50 | I31: =SUM(I24:I30) -> 59 | ... K31: =SUM(K24:K30) -> 71
A32: Horas extra por operario (h/año) | B32: ='Dotacion Planta'!B109 -> 0 | C32: ='Dotacion Planta'!C109 -> 0 | D32: ='Dotacion Planta'!D109 -> 13.573322 | E32: ='Dotacion Planta'!E109 -> 34.681861 | F32: ='Dotacion Planta'!F109 -> 32.097911 | G32: ='Dotacion Planta'!G109 -> 38.330056 | H32: ='Dotacion Planta'!H109 -> 37.306187 | I32: ='Dotacion Planta'!I109 -> 28.314623 | ... K32: ='Dotacion Planta'!K109 -> 21.867371
A33: Días de vacaciones promedio por persona | B33: ='Dotacion Planta'!B112 -> 14 | C33: ='Dotacion Planta'!C112 -> 14 | D33: ='Dotacion Planta'!D112 -> 14 | E33: ='Dotacion Planta'!E112 -> 14 | F33: ='Dotacion Planta'!F112 -> 14 | G33: ='Dotacion Planta'!G112 -> 16.121212 | H33: ='Dotacion Planta'!H112 -> 15.909091 | I33: ='Dotacion Planta'!I112 -> 15.884615 | ... K33: ='Dotacion Planta'!K112 -> 16.888889
A34: Horas de vacaciones de operarios (h/año) | B34: ='Dotacion Planta'!B111 -> 375 | C34: ='Dotacion Planta'!C111 -> 525 | D34: ='Dotacion Planta'!D111 -> 600 | E34: ='Dotacion Planta'!E111 -> 900 | F34: ='Dotacion Planta'!F111 -> 1425 | G34: ='Dotacion Planta'!G111 -> 2137.5 | H34: ='Dotacion Planta'!H111 -> 2887.5 | I34: ='Dotacion Planta'!I111 -> 3525 | ... K34: ='Dotacion Planta'!K111 -> 4762.5
A35: Stock
A36: Stock fabricado en oct–nov (u) | B36: ='Dotacion Planta'!B110 -> 792.21 | C36: ='Dotacion Planta'!C110 -> 1240.27 | D36: ='Dotacion Planta'!D110 -> 1765.1765 | E36: ='Dotacion Planta'!E110 -> 1771.7008 | F36: ='Dotacion Planta'!F110 -> 2810.6038 | G36: ='Dotacion Planta'!G110 -> 3950.6811 | H36: ='Dotacion Planta'!H110 -> 3738.0405 | I36: ='Dotacion Planta'!I110 -> 5096.5847 | ... K36: ='Dotacion Planta'!K110 -> 6343.1351
A37: Stock máximo de carros (u) | B37: ='Resumen Capacidad'!B198 -> 0 | C37: ='Resumen Capacidad'!C198 -> 0 | D37: ='Resumen Capacidad'!D198 -> 0 | E37: ='Resumen Capacidad'!E198 -> 0 | F37: ='Resumen Capacidad'!F198 -> 0 | G37: ='Resumen Capacidad'!G198 -> 0 | H37: ='Resumen Capacidad'!H198 -> 0 | I37: ='Resumen Capacidad'!I198 -> 0 | ... K37: ='Resumen Capacidad'!K198 -> 0
A38: Stock promedio de carros (u) | B38: ='Analisis de operaciones'!P2061 -> 0 | C38: ='Analisis de operaciones'!P2152 -> 0 | D38: ='Analisis de operaciones'!P2243 -> 0 | E38: ='Analisis de operaciones'!P2334 -> 0 | F38: ='Analisis de operaciones'!P2425 -> 0 | G38: ='Analisis de operaciones'!P2516 -> 0 | H38: ='Analisis de operaciones'!P2607 -> 0 | I38: ='Analisis de operaciones'!P2698 -> 0 | J38: ='Analisis de operaciones'!P2789 -> 0 | K38: ='Analisis de operaciones'!P2880 -> 0
A39: m² para el stock de carros | B39: ='Resumen Capacidad'!B199 -> 0 | C39: ='Resumen Capacidad'!C199 -> 0 | D39: ='Resumen Capacidad'!D199 -> 0 | E39: ='Resumen Capacidad'!E199 -> 0 | F39: ='Resumen Capacidad'!F199 -> 0 | G39: ='Resumen Capacidad'!G199 -> 0 | H39: ='Resumen Capacidad'!H199 -> 0 | I39: ='Resumen Capacidad'!I199 -> 0 | ... K39: ='Resumen Capacidad'!K199 -> 0
A40: Equipos de intercambio (flota, u) | B40: ='Almacen PT'!B85 -> 20 | C40: ='Almacen PT'!C85 -> 77 | D40: ='Almacen PT'!D85 -> 171 | E40: ='Almacen PT'!E85 -> 318 | F40: ='Almacen PT'!F85 -> 457 | G40: ='Almacen PT'!G85 -> 608 | H40: ='Almacen PT'!H85 -> 744 | I40: ='Almacen PT'!I85 -> 826 | ... K40: ='Almacen PT'!K85 -> 958
A41: Vehículos de reparto (milk run) | B41: ='Almacen PT'!B104 -> 2 | C41: ='Almacen PT'!C104 -> 2 | D41: ='Almacen PT'!D104 -> 2 | E41: ='Almacen PT'!E104 -> 3 | F41: ='Almacen PT'!F104 -> 4 | G41: ='Almacen PT'!G104 -> 5 | H41: ='Almacen PT'!H104 -> 6 | I41: ='Almacen PT'!I104 -> 7 | ... K41: ='Almacen PT'!K104 -> 8
A42: m² de almacén de PT + recargas de clientes | B42: ='Almacen PT'!B130 -> 36.878083 | C42: ='Almacen PT'!C130 -> 45.547648 | D42: ='Almacen PT'!D130 -> 56.933822 | E42: ='Almacen PT'!E130 -> 78.899847 | F42: ='Almacen PT'!F130 -> 120.92463 | G42: ='Almacen PT'!G130 -> 154.45928 | H42: ='Almacen PT'!H130 -> 182.85789 | I42: ='Almacen PT'!I130 -> 225.97466 | ... K42: ='Almacen PT'!K130 -> 273.64033

Sheet Parametros
B1: PERFILES DE ESTACIONALIDAD
A2: Perfil | B2: Enero | C2: Febrero | D2: marzo | E2: abril | F2: mayo | G2: junio | H2: julio | I2: agosto | J2: septiembre | K2: octubre | L2: noviembre | M2: diciembre | N2: Total | O2: Justificación del ajuste (sept. 2026)
A3: Automovilístico (1 kg) | B3: 0.12 | C3: 0.09 | D3: 0.08 | E3: 0.075 | F3: 0.07 | G3: 0.07 | H3: 0.075 | I3: 0.075 | J3: 0.075 | K3: 0.075 | L3: 0.075 | M3: 0.12 | N3: =SUM(B3:M3) -> 1
A4: Manual comercial (2,5 / 5 / 10 kg) | B4: 0.1 | C4: 0.08 | D4: 0.085 | E4: 0.085 | F4: 0.08 | G4: 0.075 | H4: 0.08 | I4: 0.08 | J4: 0.08 | K4: 0.075 | L4: 0.07 | M4: 0.11 | N4: =SUM(B4:M4) -> 1
A5: Industrial s/ruedas (25 – 100 kg) | B5: 0.085 | C5: 0.075 | D5: 0.09 | E5: 0.09 | F5: 0.09 | G5: 0.08 | H5: 0.09 | I5: 0.09 | J5: 0.085 | K5: 0.075 | L5: 0.07 | M5: 0.08 | N5: =SUM(B5:M5) -> 1
A6: Perfil ORIGINAL (referencia, reemplazado por el ajuste de arriba) → | B6: 0.16 | C6: 0.12 | D6: 0.09 | E6: 0.07 | F6: 0.05 | G6: 0.04 | H6: 0.05 | I6: 0.05 | J6: 0.06 | K6: 0.05 | L6: 0.04 | M6: 0.22 | N6: =SUM(B6:M6) -> 1
B7: 0.1 | C7: 0.08 | D7: 0.09 | E7: 0.09 | F7: 0.08 | G7: 0.07 | H7: 0.08 | I7: 0.08 | J7: 0.08 | K7: 0.06 | L7: 0.05 | M7: 0.14 | N7: =SUM(B7:M7) -> 1
B8: 0.08 | C8: 0.07 | D8: 0.09 | E8: 0.09 | F8: 0.09 | G8: 0.08 | H8: 0.09 | I8: 0.09 | J8: 0.08 | K8: 0.07 | L8: 0.06 | M8: 0.11 | N8: =SUM(B8:M8) -> 1
B9: MATRIZ POR TIPO
A10: Tipo | B10: Enero | C10: Febrero | D10: marzo | E10: abril | F10: mayo | G10: junio | H10: julio | I10: agosto | J10: septiembre | K10: octubre | L10: noviembre | M10: diciembre | N10: Total
A11: ABC 1 kg | B11: =B3 -> 0.12 | C11: =C3 -> 0.09 | D11: =D3 -> 0.08 | E11: =E3 -> 0.075 | F11: =F3 -> 0.07 | G11: =G3 -> 0.07 | H11: =H3 -> 0.075 | I11: =I3 -> 0.075 | ... M11: =M3 -> 0.12 | N11: =SUM(B11:M11) -> 1
A12: ABC 2,5 kg | B12: =B4 -> 0.1 | C12: =C4 -> 0.08 | D12: =D4 -> 0.085 | E12: =E4 -> 0.085 | F12: =F4 -> 0.08 | G12: =G4 -> 0.075 | H12: =H4 -> 0.08 | I12: =I4 -> 0.08 | ... M12: =M4 -> 0.11 | N12: =SUM(B12:M12) -> 1
A13: ABC 5 kg | B13: =B4 -> 0.1 | C13: =C4 -> 0.08 | D13: =D4 -> 0.085 | E13: =E4 -> 0.085 | F13: =F4 -> 0.08 | G13: =G4 -> 0.075 | H13: =H4 -> 0.08 | I13: =I4 -> 0.08 | ... M13: =M4 -> 0.11 | N13: =SUM(B13:M13) -> 1
A14: ABC 10 kg | B14: =B4 -> 0.1 | C14: =C4 -> 0.08 | D14: =D4 -> 0.085 | E14: =E4 -> 0.085 | F14: =F4 -> 0.08 | G14: =G4 -> 0.075 | H14: =H4 -> 0.08 | I14: =I4 -> 0.08 | ... M14: =M4 -> 0.11 | N14: =SUM(B14:M14) -> 1
A15: ABC 25 kg s/ruedas | B15: =B5 -> 0.085 | C15: =C5 -> 0.075 | D15: =D5 -> 0.09 | E15: =E5 -> 0.09 | F15: =F5 -> 0.09 | G15: =G5 -> 0.08 | H15: =H5 -> 0.09 | I15: =I5 -> 0.09 | ... M15: =M5 -> 0.08 | N15: =SUM(B15:M15) -> 1
A16: ABC 50 kg s/ruedas | B16: =B5 -> 0.085 | C16: =C5 -> 0.075 | D16: =D5 -> 0.09 | E16: =E5 -> 0.09 | F16: =F5 -> 0.09 | G16: =G5 -> 0.08 | H16: =H5 -> 0.09 | I16: =I5 -> 0.09 | ... M16: =M5 -> 0.08 | N16: =SUM(B16:M16) -> 1
A17: ABC 70 kg s/ruedas | B17: =B5 -> 0.085 | C17: =C5 -> 0.075 | D17: =D5 -> 0.09 | E17: =E5 -> 0.09 | F17: =F5 -> 0.09 | G17: =G5 -> 0.08 | H17: =H5 -> 0.09 | I17: =I5 -> 0.09 | ... M17: =M5 -> 0.08 | N17: =SUM(B17:M17) -> 1
A18: ABC 100 kg s/ruedas | B18: =B5 -> 0.085 | C18: =C5 -> 0.075 | D18: =D5 -> 0.09 | E18: =E5 -> 0.09 | F18: =F5 -> 0.09 | G18: =G5 -> 0.08 | H18: =H5 -> 0.09 | I18: =I5 -> 0.09 | ... M18: =M5 -> 0.08 | N18: =SUM(B18:M18) -> 1
A19: Cilindros ABC 1 kg | B19: =B3 -> 0.12 | C19: =C3 -> 0.09 | D19: =D3 -> 0.08 | E19: =E3 -> 0.075 | F19: =F3 -> 0.07 | G19: =G3 -> 0.07 | H19: =H3 -> 0.075 | I19: =I3 -> 0.075 | ... M19: =M3 -> 0.12 | N19: =SUM(B19:M19) -> 1
A20: Cilindros ABC 2,5 kg | B20: =B4 -> 0.1 | C20: =C4 -> 0.08 | D20: =D4 -> 0.085 | E20: =E4 -> 0.085 | F20: =F4 -> 0.08 | G20: =G4 -> 0.075 | H20: =H4 -> 0.08 | I20: =I4 -> 0.08 | ... M20: =M4 -> 0.11 | N20: =SUM(B20:M20) -> 1
A21: Cilindros ABC 5 kg | B21: =B4 -> 0.1 | C21: =C4 -> 0.08 | D21: =D4 -> 0.085 | E21: =E4 -> 0.085 | F21: =F4 -> 0.08 | G21: =G4 -> 0.075 | H21: =H4 -> 0.08 | I21: =I4 -> 0.08 | ... M21: =M4 -> 0.11 | N21: =SUM(B21:M21) -> 1
A22: Cilindros ABC 10 kg | B22: =B4 -> 0.1 | C22: =C4 -> 0.08 | D22: =D4 -> 0.085 | E22: =E4 -> 0.085 | F22: =F4 -> 0.08 | G22: =G4 -> 0.075 | H22: =H4 -> 0.08 | I22: =I4 -> 0.08 | ... M22: =M4 -> 0.11 | N22: =SUM(B22:M22) -> 1
A23: Cilindros ABC 25 kg | B23: =B5 -> 0.085 | C23: =C5 -> 0.075 | D23: =D5 -> 0.09 | E23: =E5 -> 0.09 | F23: =F5 -> 0.09 | G23: =G5 -> 0.08 | H23: =H5 -> 0.09 | I23: =I5 -> 0.09 | ... M23: =M5 -> 0.08 | N23: =SUM(B23:M23) -> 1
A24: Cilindros ABC 50 kg | B24: =B5 -> 0.085 | C24: =C5 -> 0.075 | D24: =D5 -> 0.09 | E24: =E5 -> 0.09 | F24: =F5 -> 0.09 | G24: =G5 -> 0.08 | H24: =H5 -> 0.09 | I24: =I5 -> 0.09 | ... M24: =M5 -> 0.08 | N24: =SUM(B24:M24) -> 1
A25: Cilindros ABC 70 kg | B25: =B5 -> 0.085 | C25: =C5 -> 0.075 | D25: =D5 -> 0.09 | E25: =E5 -> 0.09 | F25: =F5 -> 0.09 | G25: =G5 -> 0.08 | H25: =H5 -> 0.09 | I25: =I5 -> 0.09 | ... M25: =M5 -> 0.08 | N25: =SUM(B25:M25) -> 1
A26: Cilindros ABC 100 kg | B26: =B5 -> 0.085 | C26: =C5 -> 0.075 | D26: =D5 -> 0.09 | E26: =E5 -> 0.09 | F26: =F5 -> 0.09 | G26: =G5 -> 0.08 | H26: =H5 -> 0.09 | I26: =I5 -> 0.09 | ... M26: =M5 -> 0.08 | N26: =SUM(B26:M26) -> 1
B36: CAPACIDAD REAL POR PUESTO — ÍNDICE MAESTRO (Tiempo Total de Operación PCP + líneas Firesafer)
A37: Días hábiles/mes: | B37: 20 | C37: Horas/día (1 turno): | D37: 8 | E37: Horas productivas/mes: | F37: =B37*J37 -> 150 | G37: Refrigerio (min/turno) — CCT 260/75 art. 20: | H37: 30 | I37: Horas productivas/turno: | J37: =D37-H37/60 -> 7.5
A38: Puesto | B38: Proceso | C38: Máquina | D38: ta — T. operación (seg/u) | E38: u/seg | F38: u/min | G38: Cap. nominal (u/h) | H38: tpr — Preparación (seg/unid) | I38: tdl — Desalist. (seg/unid) | J38: Rendim. (n) | K38: Tt operación (seg/u) | L38: Tiempo tipo (seg/u) | M38: Cap. real (u/h) | N38: Cap. real (u/mes) | O38: APLICA | P38: Cambio de matriz (min/cambio) | Q38: N° cambios/mes (est.) | R38: Pérdida por cambios (h/mes) | S38: Disponibilidad (cambios) | T38: Observaciones
A39: Preparación de cuello | B39: Punzonado del alojamiento de válvula y preparación de la boca en la cúpula | C39: https://www.pannier.com/es/marking/stamp-marking-machines/benchtop-presses/ | D39: =1/E39 -> 60 | E39: =F39/60 -> 0.016666667 | F39: 1 | G39: 240 | H39: 20 | I39: 10 | J39: 0.85 | K39: =I39+H39+3600/G39 -> 45 | L39: =K39/J39 -> 52.941176 | M39: =3600/L39*S39 -> 68 | N39: =$F$37*M39 -> 10200 | O39: 1,2.5,5,10 | P39: 0 | Q39: 0 | R39: =P39*Q39/60 -> 0 | S39: =MAX(0,1-R39/$F$37) -> 1
A40: Soldadura circunferencial cuello | B40: Soldadura del asiento de válvula a la cúpula (plato indexado) | C40: Soldadura manual | D40: =1/E40 -> 60 | E40: =F40/60 -> 0.016666667 | F40: 1 | G40: 80 | H40: 10 | I40: 5 | J40: 0.7 | K40: =I40+H40+3600/G40 -> 60 | L40: =K40/J40 -> 85.714286 | M40: =3600/L40*S40 -> 40.88 | N40: =$F$37*M40 -> 6132 | O40: Manuales | P40: 15 | Q40: 16 | R40: =P40*Q40/60 -> 4 | S40: =MAX(0,1-R40/$F$37) -> 0.97333333
A41: Corte de disco y embutido (cúpula y fondo) | B41: Corte de disco y embutido profundo de cúpula y fondo (2 piezas por matafuego) | C41: https://www.directindustry.es/prod/sangiacomo-presse/product-16556-37404.html | D41: =1/E41 -> 10 | E41: =F41/60 -> 0.1 | F41: =60/10 -> 6 | G41: 1200 | H41: =30*60/1000 -> 1.8 | I41: =6*60/1000 -> 0.36 | J41: 0.85 | K41: =I41+H41+3600/G41 -> 5.16 | L41: =K41/J41 -> 6.0705882 | M41: =3600/L41*S41 -> 466.51163 | N41: =$F$37*M41 -> 69976.744 | O41: Manuales | P41: 120 | Q41: 16 | R41: =P41*Q41/60 -> 32 | S41: =MAX(0,1-R41/$F$37) -> 0.78666667
A42: Numerado de cuerpo | B42: Grabado/rolado del número de serie sobre el cuerpo | C42: https://www.pannier.com/es/marking/stamp-marking-machines/benchtop-presses/ | D42: =1/E42 -> 20 | E42: =F42/60 -> 0.05 | F42: 3 | G42: 240 | H42: 10 | I42: 5 | J42: 0.8 | K42: =I42+H42+3600/G42 -> 30 | L42: =K42/J42 -> 37.5 | M42: =3600/L42*S42 -> 96 | N42: =$F$37*M42 -> 14400 | O42: 2.5,5,10 | P42: 0 | Q42: 0 | R42: =P42*Q42/60 -> 0 | S42: =MAX(0,1-R42/$F$37) -> 1 | T42: Incluye el 1 kg: se graba la cúpula con cabezal numerador automático (IRAM 3523 5.1).
A43: Cilindrado | B43: Curvado de la chapa a forma cilíndrica (rodillos) | C43: FS-RM01 | D43: =1/E43 -> 80 | E43: =F43/60 -> 0.0125 | F43: =45/60 -> 0.75 | G43: 130 | H43: 5 | I43: 5 | J43: 0.85 | K43: =I43+H43+3600/G43 -> 37.692308 | L43: =K43/J43 -> 44.343891 | M43: =3600/L43*S43 -> 80.101224 | N43: =$F$37*M43 -> 12015.184 | O43: 2,5 a 10 | P43: 10 | Q43: 12 | R43: =P43*Q43/60 -> 2 | S43: =MAX(0,1-R43/$F$37) -> 0.98666667
A44: Soldadura longitudinal | B44: Soldadura MAG (ER70S-6) de la costura longitudinal del cuerpo | C44: Soldadura manual | D44: =1/E44 -> 120 | E44: =F44/60 -> 0.0083333333 | F44: 0.5 | G44: 40 | H44: 30 | I44: 15 | J44: 0.7 | K44: =I44+H44+3600/G44 -> 135 | L44: =K44/J44 -> 192.85714 | M44: =3600/L44*S44 -> 18.542222 | N44: =$F$37*M44 -> 2781.3333 | O44: 2,5 a 10 | P44: 5 | Q44: 12 | R44: =P44*Q44/60 -> 1 | S44: =MAX(0,1-R44/$F$37) -> 0.99333333 | T44: Automática desde el año 1 (IRAM 3523 3.2.4.2).
A45: Encastre de fondo | B45: Reducción/encastre del extremo para alojar el fondo | C45: Prensa Hidráulica Motorizada | D45: =1/E45 -> 30 | E45: =F45/60 -> 0.033333333 | F45: 2 | G45: 120 | H45: 15 | I45: 5 | J45: 0.85 | K45: =I45+H45+3600/G45 -> 50 | L45: =K45/J45 -> 58.823529 | M45: =3600/L45*S45 -> 60.656 | N45: =$F$37*M45 -> 9098.4 | O45: Manuales | P45: 5 | Q45: 16 | R45: =P45*Q45/60 -> 1.3333333 | S45: =MAX(0,1-R45/$F$37) -> 0.99111111
A46: Bordoneado | B46: Bordoneado/rebordeado del cuerpo y del aro de base | C46: Bordoneadora Pilman | D46: =1/E46 -> 45 | E46: =F46/60 -> 0.022222222 | F46: =60/45 -> 1.3333333 | G46: 600 | H46: 5 | I46: 5 | J46: 0.85 | K46: =I46+H46+3600/G46 -> 16 | L46: =K46/J46 -> 18.823529 | M46: =3600/L46*S46 -> 187.425 | N46: =$F$37*M46 -> 28113.75 | O46: Manuales | P46: 15 | Q46: 12 | R46: =P46*Q46/60 -> 3 | S46: =MAX(0,1-R46/$F$37) -> 0.98
A47: Soldadura circunferencial (cúpula y fondo) | B47: Soldadura circunferencial segmentada cúpula–cuerpo–fondo | C47: Soldadura manual | D47: =1/E47 -> 200 | E47: =F47/60 -> 0.005 | F47: 0.3 | G47: 30 | H47: 30 | I47: 5 | J47: 0.7 | K47: =I47+H47+3600/G47 -> 155 | L47: =K47/J47 -> 221.42857 | M47: =3600/L47*S47 -> 15.969032 | N47: =$F$37*M47 -> 2395.3548 | O47: Manuales | P47: 10 | Q47: 16 | R47: =P47*Q47/60 -> 2.6666667 | S47: =MAX(0,1-R47/$F$37) -> 0.98222222 | T47: Automática desde el año 1 (IRAM 3523 3.2.4.2).
A48: Prueba hidráulica | B48: Ensayo hidráulico a presión (tanque multiposición) | C48: Yukon M-000200 | D48: 120 | E48: =F48/60 -> 0.0083333333 | F48: 0.5 | G48: 30 | H48: 10 | I48: 5 | J48: 0.85 | K48: =I48+H48+3600/G48 -> 135 | L48: =K48/J48 -> 158.82353 | M48: =3600/L48*S48 -> 22.465185 | N48: =$F$37*M48 -> 3369.7778 | O48: Manuales | P48: 5 | Q48: 16 | R48: =P48*Q48/60 -> 1.3333333 | S48: =MAX(0,1-R48/$F$37) -> 0.99111111
A49: Granallado | B49: Granallado centrífugo S330/S390 (línea power & free) CyM | C49: G-100 (Blastair) | D49: =1/E49 -> 30 | E49: =F49/60 -> 0.033333333 | F49: 2 | G49: 200 | H49: 10 | I49: 15 | J49: 0.85 | K49: =I49+H49+3600/G49 -> 43 | L49: =K49/J49 -> 50.588235 | M49: =3600/L49*S49 -> 71.162791 | N49: =$F$37*M49 -> 10674.419 | O49: Manuales | P49: 0 | Q49: 16 | R49: =P49*Q49/60 -> 0 | S49: =MAX(0,1-R49/$F$37) -> 1
A50: Detección de defectos | B50: Amolado/pulido del cordón y retoque de defectos | C50: MANUAL | D50: =1/E50 -> 5 | E50: =F50/60 -> 0.2 | F50: =60/5 -> 12 | G50: 720 | H50: 5 | I50: 5 | J50: 0.8 | K50: =I50+H50+3600/G50 -> 15 | L50: =K50/J50 -> 18.75 | M50: =3600/L50*S50 -> 192 | N50: =$F$37*M50 -> 28800 | O50: Manuales | P50: 0 | Q50: 16 | R50: =P50*Q50/60 -> 0 | S50: =MAX(0,1-R50/$F$37) -> 1
A51: Pintura + Horno | B51: Pintura en polvo poliéster termofija + curado en horno (continuo) | C51: Firesafer Powder Coating Line | D51: 14.4 | E51: =1/D51 -> 0.069444444 | F51: =60/D51 -> 4.1666667 | G51: 700 | H51: 10 | I51: 10 | J51: 0.95 | K51: =I51+H51+3600/G51 -> 25.142857 | L51: =K51/J51 -> 26.466165 | M51: =3600/L51*S51 -> 136.02273 | N51: =$F$37*M51 -> 20403.409 | O51: Manuales | P51: 0 | Q51: 0 | R51: =P51*Q51/60 -> 0 | S51: =MAX(0,1-R51/$F$37) -> 1
A52: Carga de polvo | B52: Llenado de polvo químico seco | C52: FS-A10 | D52: =1/E52 -> 42.857143 | E52: =F52/60 -> 0.023333333 | F52: 1.4 | G52: 110 | H52: 10 | I52: 5 | J52: 0.8 | K52: =I52+H52+3600/G52 -> 47.727273 | L52: =K52/J52 -> 59.659091 | M52: =3600/L52*S52 -> 60.342857 | N52: =$F$37*M52 -> 9051.4286 | O52: Manuales | P52: 0 | Q52: 16 | R52: =P52*Q52/60 -> 0 | S52: =MAX(0,1-R52/$F$37) -> 1
A53: Ensamblaje | B53: Roscado de válvula + manómetro + tubo sifón | C53: MANUAL | D53: =1/E53 -> 60 | E53: =F53/60 -> 0.016666667 | F53: 1 | G53: =3600/90 -> 40 | H53: 5 | I53: 5 | J53: 0.7 | K53: =I53+H53+3600/G53 -> 100 | L53: =K53/J53 -> 142.85714 | M53: =3600/L53*S53 -> 25.2 | N53: =$F$37*M53 -> 3780 | O53: Manuales | P53: 0 | Q53: 16 | R53: =P53*Q53/60 -> 0 | S53: =MAX(0,1-R53/$F$37) -> 1
A54: Presurización | B54: Presurización con nitrógeno seco | C54: MANUAL | D54: 55 | E54: =F54/60 -> 0.025 | F54: =60/40 -> 1.5 | G54: =3600/D54 -> 65.454545 | H54: 5 | I54: 5 | J54: 0.75 | K54: =I54+H54+3600/G54 -> 65 | L54: =K54/J54 -> 86.666667 | M54: =3600/L54*S54 -> 41.538462 | N54: =$F$37*M54 -> 6230.7692 | O54: Manuales | P54: 0 | Q54: 16 | R54: =P54*Q54/60 -> 0 | S54: =MAX(0,1-R54/$F$37) -> 1 | T54: Incluye control de pérdidas con agua y detergente (IRAM 3523 3.11): +15 s.
A55: Etiquetado | B55: Etiquetado automático del cuerpo | C55: MANUAL | D55: =1/E55 -> 40 | E55: =F55/60 -> 0.025 | F55: =60/40 -> 1.5 | G55: =3600/40 -> 90 | H55: 10 | I55: 5 | J55: 0.7 | K55: =I55+H55+3600/G55 -> 55 | L55: =K55/J55 -> 78.571429 | M55: =3600/L55*S55 -> 45.818182 | N55: =$F$37*M55 -> 6872.7273 | O55: Manuales | P55: 0 | Q55: 16 | R55: =P55*Q55/60 -> 0 | S55: =MAX(0,1-R55/$F$37) -> 1
A56: Embalaje y palletizado | B56: Encajonado y palletizado | C56: MANUAL | D56: 34 | E56: =F56/60 -> 0.022222222 | F56: =60/45 -> 1.3333333 | G56: =3600/D56 -> 105.88235 | H56: 20 | I56: 5 | J56: 0.8 | K56: =I56+H56+3600/G56 -> 59 | L56: =K56/J56 -> 73.75 | M56: =3600/L56*S56 -> 48.813559 | N56: =$F$37*M56 -> 7322.0339 | O56: Manuales | P56: 0 | Q56: 16 | R56: =P56*Q56/60 -> 0 | S56: =MAX(0,1-R56/$F$37) -> 1 | T56: Antes 24 s. +10 s de armado de caja individual (IRAM 3523 5.4).
A58: Teoría PCP (Tiempo Total de Operación): ta = tiempo de operación (ciclo) · tpr = preparación · tdl = desalistamiento · Q = lote · n = rendimiento. u/seg=1/ta · u/min=60/ta · Cap. nominal (u/h)=3600/ta (solo operación). Ttopi/lote (min) = (tpr+tdl) + ta·Q/n /60 · Tiempo tipo (seg/u) = ta/n + (tpr+tdl)·60/Q = Ttopi·60/Q. Cap. real (u/h) = 3600 / Tiempo tipo · Cap. real total = ×N° máq · Cap. real (u/mes) = ×horas/mes. AZUL/amarillo = editable. Las hojas 2026–2028 toman Cap. nominal, Cap. real y N° máq por INDEX/MATCH.
A67: Ocupación objetivo por operario (%) | B67: 0.9
A68: Piso mínimo de plantel (arranque) | B68: 5
A69: Carros: fabricación de cada mes (% de los carros vendidos en el año) | B69: Ene | C69: Feb | D69: Mar | E69: Abr | F69: May | G69: Jun | H69: Jul | I69: Ago | J69: Sep | K69: Oct | L69: Nov | M69: Dic | N69: Total
A70: Distribución elegida = perfil de ventas de carros (fila 5): stock 0 | B70: =B5 -> 0.085 | C70: =C5 -> 0.075 | D70: =D5 -> 0.09 | E70: =E5 -> 0.09 | F70: =F5 -> 0.09 | G70: =G5 -> 0.08 | H70: =H5 -> 0.09 | I70: =I5 -> 0.09 | ... M70: =M5 -> 0.08 | N70: =SUM(B70:M70) -> 1 | O70: =IF(ROUND(N70,4)=1,"OK","Tiene que sumar 100 %") -> OK | P70: Los carros los fabrica el plantel de producción. Ver tabla CARROS y costos en "Sensibilidad Stock" para elegir el reparto.
A71: m² por carro en stock (con pasillo) | B71: 0.5 | C71: SUPUESTO: carros no se apilan.
A72: Factor carros en puestos comunes (carga de polvo, ensamblaje, presurización, etiquetado) | B72: 3
A73: Plantel mínimo de recargas (si hay recargas) | B73: 2 | C73: Con un solo operario de recargas, en su mes de vacaciones se pasan las 30 h extra por mes (Dec. 484/00).
A74: VER TEMA DE MAQUINA DE MAYOR VOLUMEN DE Carga de polvo+Enrosque de valvula+Nitrogeno PARA PLANTA COMERCIAL
A75: maquinas analizadas en reinversión
A76: CAPACIDAD REAL POR PUESTO — ÍNDICE MAESTRO (Tiempo Total de Operación PCP + líneas Firesafer)
A77: Días hábiles/mes: | B77: 20 | C77: Horas/día (1 turno): | D77: 8 | E77: Horas/mes: | F77: =B77*D77 -> 160
A78: Puesto | B78: Proceso | C78: Máquina | D78: ta — T. operación (seg/u) | E78: u/seg | F78: u/min | G78: Cap. nominal (u/h) | H78: tpr — Preparación (seg/unid) | I78: tdl — Desalist. (seg/unid) | J78: Rendim. (n) | K78: Tt operación (seg/u) | L78: Tiempo tipo (seg/u) | M78: Cap. real (u/h) | N78: Cap. real (u/mes) | O78: APLICA | P78: Cambio de matriz (min/cambio) | Q78: N° cambios/mes (est.) | R78: Pérdida por cambios (h/mes) | S78: Disponibilidad (cambios)
A79: Cortadora de plasma (1kg) | C79: Shandong Dato | G79: 240 | H79: =60*10/26 -> 23.076923 | I79: 5 | J79: 0.9 | K79: =I79+H79+3600/G79 -> 43.076923 | L79: =K79/J79 -> 47.863248 | M79: =3600/L79*S79 -> 75.214286 | N79: =$F$37*M79 -> 11282.143 | O79: 1 Kg | P79: 0 | Q79: 16 | R79: =P79*Q79/60 -> 0 | S79: =MAX(0,1-R79/$F$37) -> 1
A80: Soldadura circunferencial cuello | C80: FS-HFM1 - Firesafer | G80: 220 | H80: 10 | I80: 5 | J80: 0.8 | K80: =I80+H80+3600/G80 -> 31.363636 | L80: =K80/J80 -> 39.204545 | M80: =3600/L80*S80 -> 90.193623 | N80: =$F$37*M80 -> 13529.043 | O80: Manuales | P80: 10 | Q80: 16 | R80: =P80*Q80/60 -> 2.6666667 | S80: =MAX(0,1-R80/$F$37) -> 0.98222222
A81: Soldadora de cúpula y fondo al cuerpo | C81: SCWELDING | G81: 40 | H81: 30 | I81: 5 | J81: 0.8 | K81: =I81+H81+3600/G81 -> 125 | L81: =K81/J81 -> 156.25 | M81: =3600/L81*S81 -> 22.6304 | N81: =$F$37*M81 -> 3394.56 | O81: Manuales | P81: 10 | Q81: 16 | R81: =P81*Q81/60 -> 2.6666667 | S81: =MAX(0,1-R81/$F$37) -> 0.98222222
A82: Soldadora de cúpula y fondo al cuerpo | C82: Firesafer | G82: 120 | H82: 15 | I82: 5 | J82: 0.9 | K82: =I82+H82+3600/G82 -> 50 | L82: =K82/J82 -> 55.555556 | M82: =3600/L82*S82 -> 63.648 | N82: =$F$37*M82 -> 9547.2 | O82: Manuales | P82: 10 | Q82: 16 | R82: =P82*Q82/60 -> 2.6666667 | S82: =MAX(0,1-R82/$F$37) -> 0.98222222
A83: Prueba Hidraulica | C83: FS-JD12A - Firesafer | G83: 180 | H83: 10 | I83: 5 | J83: 0.85 | K83: =I83+H83+3600/G83 -> 35 | L83: =K83/J83 -> 41.176471 | M83: =3600/L83*S83 -> 86.651429 | N83: =$F$37*M83 -> 12997.714 | O83: Manuales | P83: 5 | Q83: 16 | R83: =P83*Q83/60 -> 1.3333333 | S83: =MAX(0,1-R83/$F$37) -> 0.99111111
A84: Maquina de Secado | C84: Yukon | G84: 24 | H84: 10 | I84: 5 | J84: 0.8 | K84: =I84+H84+3600/G84 -> 165 | L84: =K84/J84 -> 206.25 | M84: =3600/L84*S84 -> 17.454545 | N84: =$F$37*M84 -> 2618.1818 | O84: Manuales | P84: 0 | Q84: 16 | R84: =P84*Q84/60 -> 0 | S84: =MAX(0,1-R84/$F$37) -> 1
A85: Soldadura Longitudinal | C85: GETWELD | G85: 80 | H85: 30 | I85: 5 | J85: 0.8 | K85: =I85+H85+3600/G85 -> 80 | L85: =K85/J85 -> 100 | M85: =3600/L85*S85 -> 35.36 | N85: =$F$37*M85 -> 5304 | O85: 2,5 a 10 kg | P85: 10 | Q85: 16 | R85: =P85*Q85/60 -> 2.6666667 | S85: =MAX(0,1-R85/$F$37) -> 0.98222222
A86: Soldadura Longitudinal | C86: MITUSA | G86: 102.9 | H86: 30 | I86: 5 | J86: 0.8 | K86: =I86+H86+3600/G86 -> 69.985423 | L86: =K86/J86 -> 87.481778 | M86: =3600/L86*S86 -> 40.419846 | N86: =$F$37*M86 -> 6062.9769 | O86: 2,5 a 10 kg | P86: 10 | Q86: 16 | R86: =P86*Q86/60 -> 2.6666667 | S86: =MAX(0,1-R86/$F$37) -> 0.98222222
A87: Soldadura Longitudinal | C87: Firesafer | G87: 240 | H87: 30 | I87: 5 | J87: 0.8 | K87: =I87+H87+3600/G87 -> 50 | L87: =K87/J87 -> 62.5 | M87: =3600/L87*S87 -> 56.576 | N87: =$F$37*M87 -> 8486.4 | O87: 2,5 a 10 kg | P87: 10 | Q87: 16 | R87: =P87*Q87/60 -> 2.6666667 | S87: =MAX(0,1-R87/$F$37) -> 0.98222222
A88: Corrección de defectos | C88: Cortahierro + Masa | G88: 35 | H88: 10 | I88: 10 | J88: 0.7 | K88: =I88+H88+3600/G88 -> 122.85714 | L88: =K88/J88 -> 175.5102 | M88: =3600/L88*S88 -> 20.511628 | N88: =$F$37*M88 -> 3076.7442 | O88: Manuales | P88: 0 | Q88: 16 | R88: =P88*Q88/60 -> 0 | S88: =MAX(0,1-R88/$F$37) -> 1
A89: Granalladora | C89: Airblast | G89: 200 | H89: 10 | I89: 15 | J89: 0.85 | K89: =I89+H89+3600/G89 -> 43 | L89: =K89/J89 -> 50.588235 | M89: =3600/L89*S89 -> 71.162791 | N89: =$F$37*M89 -> 10674.419 | O89: Manuales | P89: 0 | Q89: 16 | R89: =P89*Q89/60 -> 0 | S89: =MAX(0,1-R89/$F$37) -> 1 | U89: Cortes por cuerpo
A90: Corte de chapa (guillotina) | B90: Corte de hojas en franjas y desarrollos de cuerpo: 2,5–10 kg y carros (opción D) | C90: CENA 8×3200 (opción 1.000 mm) | G90: =60*10/U90 -> 487.80488 | H90: 10 | I90: 7 | J90: 0.85 | K90: =I90+H90+3600/G90 -> 24.38 | L90: =K90/J90 -> 28.682353 | M90: =3600/L90*S90 -> 124.39705 | N90: =$F$37*M90 -> 18659.557 | O90: Cuerpos 2,5–10 kg y carros | P90: 5 | Q90: 16 | R90: =P90*Q90/60 -> 1.3333333 | S90: =MAX(0,1-R90/$F$37) -> 0.99111111 | T90: Cap. nominal = 10 golpes/min × 60 ÷ cortes por cuerpo (U90). tpr: carga de la hoja y avance contra el tope; tdl: retiro y apilado en el carro. | U90: 1.23 | V90: Opción D (Comparacion_corte): 103.957 cortes para ~84.700 cuerpos en 2035 = 1,23 cortes por cuerpo.
A96: Puesto | B96: Proceso | C96: Máquina | D96: ta — T. operación (seg/u) | E96: u/seg | F96: u/min | G96: Cap. nominal (u/h) | H96: tpr — Preparación (seg/unid) | I96: tdl — Desalist. (seg/unid) | J96: Rendim. (n) | K96: Tt operación (seg/u) | L96: Tiempo tipo (seg/u) | M96: Cap. real (u/h) | N96: Cap. real (u/mes) | O96: APLICA | P96: Cambio de matriz (min/cambio) | Q96: N° cambios/mes (est.) | R96: Pérdida por cambios (h/mes) | S96: Disponibilidad (cambios)
A97: Recepcion y clasificacion | C97: Manual
A98: Inspeccion visual | C98: Manual
A99: Ensayo de funcionamiento (descarga ABC) (%)
A100: Ensayo de funcionamiento (descarga AFFF) (%)
A101: Ensayo de funcionamiento (descarga Halon) (%)
A102: Desarme de matafuego | C102: Manual | G102: 60 | H102: 15 | I102: 15 | J102: 0.8 | K102: =I102+H102+3600/G102 -> 90 | L102: =K102/J102 -> 112.5 | M102: =3600/L102*S102 -> 32 | N102: =$F$37*M102 -> 4800 | O102: TODOS | P102: 0 | Q102: 16 | R102: =P102*Q102/60 -> 0 | S102: =MAX(0,1-R102/$F$37) -> 1
A103: Prueba Puffer
A104: Ensamblaje | C104: Manual | G104: 40 | H104: 15 | I104: 10 | J104: 0.8 | K104: =I104+H104+3600/G104 -> 115 | L104: =K104/J104 -> 143.75 | M104: =3600/L104*S104 -> 25.043478 | N104: =$F$37*M104 -> 3756.5217 | O104: TODOS | P104: 0 | Q104: 16 | R104: =P104*Q104/60 -> 0 | S104: =MAX(0,1-R104/$F$37) -> 1
A105: Despacho | C105: Manual | G105: 120 | H105: 10 | I105: 10 | J105: 0.8 | K105: =I105+H105+3600/G105 -> 50 | L105: =K105/J105 -> 62.5 | M105: =3600/L105*S105 -> 57.6 | N105: =$F$37*M105 -> 8640 | O105: TODOS | P105: 0 | Q105: 16 | R105: =P105*Q105/60 -> 0 | S105: =MAX(0,1-R105/$F$37) -> 1
A106: Ensayo de peso
A107: Ensayo de hermeticidad
A110: CAPACIDAD REAL — LÍNEA DE CARROS 25–100 kg (cuerpo propio; fondo y cúpula comprados estampados; pintura tercerizada) — ET's Máquinas "Rodantes"
A111: Puesto | B111: Proceso | C111: Máquina | D111: ta — T. operación (seg/u) | E111: u/seg | F111: u/min | G111: Cap. nominal (u/h) | H111: tpr — Preparación (seg/unid) | I111: tdl — Desalist. (seg/unid) | J111: Rendim. (n) | K111: Tt operación (seg/u) | L111: Tiempo tipo (seg/u) | M111: Cap. real (u/h) | N111: Cap. real (u/mes) | O111: APLICA | T111: Observaciones
A112: Carros — cilindrado de chapa | B112: Rolado de la chapa cortada en la guillotina propia (hojas, opción D) a cilindro de 25–100 kg | C112: Roladora de 4 rodillos Getweld (5 m/min) | D112: 150 | E112: =1/D112 -> 0.0066666667 | F112: =60/D112 -> 0.4 | G112: =3600/D112 -> 24 | H112: 30 | I112: 15 | J112: 0.85 | K112: =D112+H112+I112 -> 195 | L112: =K112/J112 -> 229.41176 | M112: =3600/L112 -> 15.692308 | N112: =M112*$F$37 -> 2353.8462 | O112: 25, 50, 70 y 100 kg
A113: Carros — punteo, refuerzo y estructura del carro | B113: Punteo del cilindro en dispositivo, soldadura del refuerzo (según modelo) y de la estructura con ruedas | C113: Soldadora Pampa 300 (manual, 2,5 p/h) | D113: 1440 | E113: =1/D113 -> 0.00069444444 | F113: =60/D113 -> 0.041666667 | G113: =3600/D113 -> 2.5 | H113: 60 | I113: 30 | J113: 0.8 | K113: =D113+H113+I113 -> 1530 | L113: =K113/J113 -> 1912.5 | M113: =3600/L113 -> 1.8823529 | N113: =M113*$F$37 -> 282.35294 | O113: 25, 50, 70 y 100 kg
A114: Carros — soldadura longitudinal | B114: Costura longitudinal MAG automática del cuerpo | C114: Soldadora longitudinal ZF-1000 Getweld (28,75 p/h) | D114: 125 | E114: =1/D114 -> 0.008 | F114: =60/D114 -> 0.48 | G114: =3600/D114 -> 28.8 | H114: 20 | I114: 10 | J114: 0.85 | K114: =D114+H114+I114 -> 155 | L114: =K114/J114 -> 182.35294 | M114: =3600/L114 -> 19.741935 | N114: =M114*$F$37 -> 2961.2903 | O114: 25, 50, 70 y 100 kg
A115: Carros — soldadura circunferencial fondo y cúpula | B115: Unión del fondo y la cúpula comprados estampados al cuerpo (doble cabezal) | C115: Soldadora circunferencial ZNC750X2 Getweld (42,5 p/h) | D115: 85 | E115: =1/D115 -> 0.011764706 | F115: =60/D115 -> 0.70588235 | G115: =3600/D115 -> 42.352941 | H115: 20 | I115: 10 | J115: 0.85 | K115: =D115+H115+I115 -> 115 | L115: =K115/J115 -> 135.29412 | M115: =3600/L115 -> 26.608696 | N115: =M115*$F$37 -> 3991.3043 | O115: 25, 50, 70 y 100 kg
A116: Carros — inspección de costuras int. y ext. | B116: Inspección visual de costuras internas (lámpara/cámara) y externas en todos los recipientes (IRAM 3550 6.1.2) | C116: Lámpara + cámara de inspección (SUPUESTO USD 500) | D116: 60 | E116: =1/D116 -> 0.016666667 | F116: =60/D116 -> 1 | G116: =3600/D116 -> 60 | H116: 10 | I116: 10 | J116: 0.85 | K116: =D116+H116+I116 -> 80 | L116: =K116/J116 -> 94.117647 | M116: =3600/L116 -> 38.25 | N116: =M116*$F$37 -> 5737.5 | O116: 25, 50, 70 y 100 kg
A117: Carros — prueba hidráulica (IRAM 3550, 4,0 MPa) | B117: Llenado, presurización a 4,0 MPa, sostenimiento y vaciado | C117: Banco de prueba hidráulica SAITU (20 p/h) | D117: 180 | E117: =1/D117 -> 0.0055555556 | F117: =60/D117 -> 0.33333333 | G117: =3600/D117 -> 20 | H117: 15 | I117: 10 | J117: 0.85 | K117: =D117+H117+I117 -> 205 | L117: =K117/J117 -> 241.17647 | M117: =3600/L117 -> 14.926829 | N117: =M117*$F$37 -> 2239.0244 | O117: 25, 50, 70 y 100 kg
A118: Carros — marcado del recipiente | B118: Grabado de fabricante, número de serie, presión de ensayo y año (IRAM 3550 5.1) | C118: Lápiz vibratorio eléctrico + cuños (SUPUESTO USD 300) | D118: 60 | E118: =1/D118 -> 0.016666667 | F118: =60/D118 -> 1 | G118: =3600/D118 -> 60 | H118: 10 | I118: 10 | J118: 0.85 | K118: =D118+H118+I118 -> 80 | L118: =K118/J118 -> 94.117647 | M118: =3600/L118 -> 38.25 | N118: =M118*$F$37 -> 5737.5 | O118: 25, 50, 70 y 100 kg
A119: Carros — probetas de soldadura | B119: Separar la placa testigo, troquelar 2 probetas y ensayar tracción y plegado (IRAM 3550 6.1.5, IRAM 609) | C119: Máquina universal de ensayos 100 kN WDW-100 con plegado | D119: 480 | E119: =1/D119 -> 0.0020833333 | F119: =60/D119 -> 0.125 | G119: =3600/D119 -> 7.5 | H119: 30 | I119: 30 | J119: 0.85 | K119: =D119+H119+I119 -> 540 | L119: =K119/J119 -> 635.29412 | M119: =3600/L119 -> 5.6666667 | N119: =M119*$F$37 -> 850 | O119: 25, 50, 70 y 100 kg
A120: Carros — pintura

Sheet Resumen Capacidad
A1: RESUMEN DE CAPACIDAD Y DECISIONES DE MÁQUINA (pico mensual por año)
A2: Ocupación pico = demanda del mes pico ÷ (cap. real × máquinas × turnos del puesto). Sin color = solo cambió la demanda.
A4: Puesto | B4: 2026 | C4: 2027 | D4: 2028 | E4: 2029 | F4: 2030 | G4: 2031 | H4: 2032 | I4: 2033 | J4: 2034 | K4: 2035
A5: Preparación de cuello | B5: =MAX('Analisis de operaciones'!C11:N11) -> 0.077667647 | C5: =MAX('Analisis de operaciones'!C194:N194) -> 0.1215951 | D5: =MAX('Analisis de operaciones'!C377:N377) -> 0.25921667 | E5: =MAX('Analisis de operaciones'!C560:N560) -> 0.57751667 | F5: =MAX('Analisis de operaciones'!C743:N743) -> 0.50445735 | G5: =MAX('Analisis de operaciones'!C926:N926) -> 0.70879559 | H5: =MAX('Analisis de operaciones'!C1109:N1109) -> 0.48950074 | I5: =MAX('Analisis de operaciones'!C1292:N1292) -> 0.62588358 | J5: =MAX('Analisis de operaciones'!C1475:N1475) -> 0.70615907 | K5: =MAX('Analisis de operaciones'!C1658:N1658) -> 0.81597647
A6: Soldadura circunferencial cuello (rosca) | B6: =MAX('Analisis de operaciones'!C21:N21) -> 0.12919276 | C6: =MAX('Analisis de operaciones'!C204:N204) -> 0.2022619 | D6: =MAX('Analisis de operaciones'!C387:N387) -> 0.43118232 | E6: =MAX('Analisis de operaciones'!C570:N570) -> 0.4354092 | F6: =MAX('Analisis de operaciones'!C753:N753) -> 0.76065466 | G6: =MAX('Analisis de operaciones'!C936:N936) -> 0.53438479 | H6: =MAX('Analisis de operaciones'!C1119:N1119) -> 0.73810207 | I6: =MAX('Analisis de operaciones'!C1302:N1302) -> 0.47187464 | J6: =MAX('Analisis de operaciones'!C1485:N1485) -> 0.53239703 | K6: =MAX('Analisis de operaciones'!C1668:N1668) -> 0.61519205
A7: Corte de disco y embutido (cúpula y fondo) | B7: =MAX('Analisis de operaciones'!C31:N31) -> 0.022642094 | C7: =MAX('Analisis de operaciones'!C214:N214) -> 0.035448062 | D7: =MAX('Analisis de operaciones'!C397:N397) -> 0.075568249 | E7: =MAX('Analisis de operaciones'!C580:N580) -> 0.16836079 | F7: =MAX('Analisis de operaciones'!C763:N763) -> 0.29412429 | G7: =MAX('Analisis de operaciones'!C946:N946) -> 0.41326387 | H7: =MAX('Analisis de operaciones'!C1129:N1129) -> 0.57080764 | I7: =MAX('Analisis de operaciones'!C1312:N1312) -> 0.7298439 | J7: =MAX('Analisis de operaciones'!C1495:N1495) -> 0.82345329 | K7: =MAX('Analisis de operaciones'!C1678:N1678) -> 0.47575577
A8: Numerado de cuerpo | B8: =MAX('Analisis de operaciones'!C41:N41) -> 0.055014583 | C8: =MAX('Analisis de operaciones'!C224:N224) -> 0.086129861 | D8: =MAX('Analisis de operaciones'!C407:N407) -> 0.18361181 | E8: =MAX('Analisis de operaciones'!C590:N590) -> 0.40907431 | F8: =MAX('Analisis de operaciones'!C773:N773) -> 0.71464792 | G8: =MAX('Analisis de operaciones'!C956:N956) -> 0.50206354 | H8: =MAX('Analisis de operaciones'!C1139:N1139) -> 0.69345937 | I8: =MAX('Analisis de operaciones'!C1322:N1322) -> 0.8866684 | J8: =MAX('Analisis de operaciones'!C1505:N1505) -> 0.50019601 | K8: =MAX('Analisis de operaciones'!C1688:N1688) -> 0.57798333
A9: Cilindrado | B9: =MAX('Analisis de operaciones'!C51:N51) -> 0.024196884 | C9: =MAX('Analisis de operaciones'!C234:N234) -> 0.043331006 | D9: =MAX('Analisis de operaciones'!C417:N417) -> 0.075099143 | E9: =MAX('Analisis de operaciones'!C600:N600) -> 0.13909317 | F9: =MAX('Analisis de operaciones'!C783:N783) -> 0.23611874 | G9: =MAX('Analisis de operaciones'!C966:N966) -> 0.33153301 | H9: =MAX('Analisis de operaciones'!C1149:N1149) -> 0.44699691 | I9: =MAX('Analisis de operaciones'!C1332:N1332) -> 0.56595806 | J9: =MAX('Analisis de operaciones'!C1515:N1515) -> 0.6461932 | K9: =MAX('Analisis de operaciones'!C1698:N1698) -> 0.74716461
A10: Soldadura longitudinal | B10: =MAX('Analisis de operaciones'!C61:N61) -> 0.034258343 | C10: =MAX('Analisis de operaciones'!C244:N244) -> 0.061348746 | D10: =MAX('Analisis de operaciones'!C427:N427) -> 0.10632659 | E10: =MAX('Analisis de operaciones'!C610:N610) -> 0.19693038 | F10: =MAX('Analisis de operaciones'!C793:N793) -> 0.33430076 | G10: =MAX('Analisis de operaciones'!C976:N976) -> 0.46938985 | H10: =MAX('Analisis de operaciones'!C1159:N1159) -> 0.63286553 | I10: =MAX('Analisis de operaciones'!C1342:N1342) -> 0.80129266 | J10: =MAX('Analisis de operaciones'!C1525:N1525) -> 0.45744544 | K10: =MAX('Analisis de operaciones'!C1708:N1708) -> 0.52892393
A11: Encastre de fondo | B11: =MAX('Analisis de operaciones'!C71:N71) -> 0.087071353 | C11: =MAX('Analisis de operaciones'!C254:N254) -> 0.13631737 | D11: =MAX('Analisis de operaciones'!C437:N437) -> 0.29060164 | E11: =MAX('Analisis de operaciones'!C620:N620) -> 0.64744021 | F11: =MAX('Analisis de operaciones'!C803:N803) -> 0.56553515 | G11: =MAX('Analisis de operaciones'!C986:N986) -> 0.79461389 | H11: =MAX('Analisis de operaciones'!C1169:N1169) -> 0.54876764 | I11: =MAX('Analisis de operaciones'!C1352:N1352) -> 0.7016632 | J11: =MAX('Analisis de operaciones'!C1535:N1535) -> 0.79165815 | K11: =MAX('Analisis de operaciones'!C1718:N1718) -> 0.60984789
A12: Bordoneado | B12: =MAX('Analisis de operaciones'!C81:N81) -> 0.028178738 | C12: =MAX('Analisis de operaciones'!C264:N264) -> 0.044116135 | D12: =MAX('Analisis de operaciones'!C447:N447) -> 0.094046863 | E12: =MAX('Analisis de operaciones'!C630:N630) -> 0.20952986 | F12: =MAX('Analisis de operaciones'!C813:N813) -> 0.36604615 | G12: =MAX('Analisis de operaciones'!C996:N996) -> 0.51431879 | H12: =MAX('Analisis de operaciones'!C1179:N1179) -> 0.71038655 | I12: =MAX('Analisis de operaciones'!C1362:N1362) -> 0.45415588 | J12: =MAX('Analisis de operaciones'!C1545:N1545) -> 0.51240567 | K12: =MAX('Analisis de operaciones'!C1728:N1728) -> 0.59209177 | N12: Pasa de manual a automática
A13: Soldadura circunferencial (cúpula y fondo) | B13: =MAX('Analisis de operaciones'!C91:N91) -> 0.082978255 | C13: =MAX('Analisis de operaciones'!C274:N274) -> 0.12990929 | D13: =MAX('Analisis de operaciones'!C457:N457) -> 0.27694088 | E13: =MAX('Analisis de operaciones'!C640:N640) -> 0.61700499 | F13: =MAX('Analisis de operaciones'!C823:N823) -> 0.53895016 | G13: =MAX('Analisis de operaciones'!C1006:N1006) -> 0.75726024 | H13: =MAX('Analisis de operaciones'!C1189:N1189) -> 0.52297087 | I13: =MAX('Analisis de operaciones'!C1372:N1372) -> 0.66867904 | J13: =MAX('Analisis de operaciones'!C1555:N1555) -> 0.75444345 | K13: =MAX('Analisis de operaciones'!C1738:N1738) -> 0.87176973 | N13: Agrega máquina
A14: Prueba hidráulica | B14: =MAX('Analisis de operaciones'!C101:N101) -> 0.23509265 | C14: =MAX('Analisis de operaciones'!C284:N284) -> 0.36805691 | D14: =MAX('Analisis de operaciones'!C467:N467) -> 0.78462444 | E14: =MAX('Analisis de operaciones'!C650:N650) -> 0.45320815 | F14: =MAX('Analisis de operaciones'!C833:N833) -> 0.79174921 | G14: =MAX('Analisis de operaciones'!C1016:N1016) -> 0.55622972 | H14: =MAX('Analisis de operaciones'!C1199:N1199) -> 0.7682747 | I14: =MAX('Analisis de operaciones'!C1382:N1382) -> 0.49116424 | J14: =MAX('Analisis de operaciones'!C1565:N1565) -> 0.5541607 | K14: =MAX('Analisis de operaciones'!C1748:N1748) -> 0.64034028 | N14: Agrega turno
A15: Granallado | B15: =MAX('Analisis de operaciones'!C111:N111) -> 0.027236144 | C15: =MAX('Analisis de operaciones'!C294:N294) -> 0.048773617 | D15: =MAX('Analisis de operaciones'!C477:N477) -> 0.084532004 | E15: =MAX('Analisis de operaciones'!C660:N660) -> 0.15656403 | F15: =MAX('Analisis de operaciones'!C843:N843) -> 0.26577654 | G15: =MAX('Analisis de operaciones'!C1026:N1026) -> 0.37317536 | H15: =MAX('Analisis de operaciones'!C1209:N1209) -> 0.50314216 | I15: =MAX('Analisis de operaciones'!C1392:N1392) -> 0.63704547 | J15: =MAX('Analisis de operaciones'!C1575:N1575) -> 0.72735858 | K15: =MAX('Analisis de operaciones'!C1758:N1758) -> 0.84101255 | N15: Agrega operario (puesto manual)
A16: Detección de defectos (CC) | B16: =MAX('Analisis de operaciones'!C121:N121) -> 0.027507292 | C16: =MAX('Analisis de operaciones'!C304:N304) -> 0.043064931 | D16: =MAX('Analisis de operaciones'!C487:N487) -> 0.091805903 | E16: =MAX('Analisis de operaciones'!C670:N670) -> 0.20453715 | F16: =MAX('Analisis de operaciones'!C853:N853) -> 0.35732396 | G16: =MAX('Analisis de operaciones'!C1036:N1036) -> 0.50206354 | H16: =MAX('Analisis de operaciones'!C1219:N1219) -> 0.69345937 | I16: =MAX('Analisis de operaciones'!C1402:N1402) -> 0.8866684 | J16: =MAX('Analisis de operaciones'!C1585:N1585) -> 0.50019601 | K16: =MAX('Analisis de operaciones'!C1768:N1768) -> 0.57798333 | N16: Tercerizado
A17: Corrección de defectos | B17: =MAX('Analisis de operaciones'!C1841:N1841) -> 0.012874161 | C17: =MAX('Analisis de operaciones'!C1863:N1863) -> 0.020155559 | D17: =MAX('Analisis de operaciones'!C1885:N1885) -> 0.042967661 | E17: =MAX('Analisis de operaciones'!C1907:N1907) -> 0.095728953 | F17: =MAX('Analisis de operaciones'!C1929:N1929) -> 0.16723734 | G17: =MAX('Analisis de operaciones'!C1951:N1951) -> 0.2349794 | H17: =MAX('Analisis de operaciones'!C1973:N1973) -> 0.32455786 | I17: =MAX('Analisis de operaciones'!C1995:N1995) -> 0.41498494 | J17: =MAX('Analisis de operaciones'!C2017:N2017) -> 0.46821068 | K17: =MAX('Analisis de operaciones'!C2039:N2039) -> 0.54102385 | N17: Sin color: solo cambió la demanda
A18: Pintura + Horno (cil. 1–10 kg; carros tercerizados) | B18: =IF(B42=0,"Tercerizado",MAX('Analisis de operaciones'!C131:N131)) -> Tercerizado | C18: =IF(C42=0,"Tercerizado",MAX('Analisis de operaciones'!C314:N314)) -> Tercerizado | D18: =IF(D42=0,"Tercerizado",MAX('Analisis de operaciones'!C497:N497)) -> Tercerizado | E18: =IF(E42=0,"Tercerizado",MAX('Analisis de operaciones'!C680:N680)) -> 0.28871009 | F18: =IF(F42=0,"Tercerizado",MAX('Analisis de operaciones'!C863:N863)) -> 0.50437307 | G18: =IF(G42=0,"Tercerizado",MAX('Analisis de operaciones'!C1046:N1046)) -> 0.70867716 | H18: =IF(H42=0,"Tercerizado",MAX('Analisis de operaciones'!C1229:N1229)) -> 0.48941895 | I18: =IF(I42=0,"Tercerizado",MAX('Analisis de operaciones'!C1412:N1412)) -> 0.625779 | J18: =IF(J42=0,"Tercerizado",MAX('Analisis de operaciones'!C1595:N1595)) -> 0.70604108 | K18: =IF(K42=0,"Tercerizado",MAX('Analisis de operaciones'!C1778:N1778)) -> 0.81584013
A19: Carga de polvo | B19: =MAX('Analisis de operaciones'!C141:N141) -> 0.091129261 | C19: =MAX('Analisis de operaciones'!C324:N324) -> 0.14320281 | D19: =MAX('Analisis de operaciones'!C507:N507) -> 0.17582418 | E19: =MAX('Analisis de operaciones'!C690:N690) -> 0.2284214 | F19: =MAX('Analisis de operaciones'!C873:N873) -> 0.35154451 | G19: =MAX('Analisis de operaciones'!C1056:N1056) -> 0.45713668 | H19: =MAX('Analisis de operaciones'!C1239:N1239) -> 0.59144697 | I19: =MAX('Analisis de operaciones'!C1422:N1422) -> 0.73201705 | J19: =MAX('Analisis de operaciones'!C1605:N1605) -> 0.84315641 | K19: =MAX('Analisis de operaciones'!C1788:N1788) -> 0.47979995
A20: Ensamblaje | B20: =MAX('Analisis de operaciones'!C151:N151) -> 0.21821429 | C20: =MAX('Analisis de operaciones'!C334:N334) -> 0.34290741 | D20: =MAX('Analisis de operaciones'!C517:N517) -> 0.42102116 | E20: =MAX('Analisis de operaciones'!C700:N700) -> 0.54696825 | F20: =MAX('Analisis de operaciones'!C883:N883) -> 0.84179365 | G20: =MAX('Analisis de operaciones'!C1066:N1066) -> 0.54732011 | H20: =MAX('Analisis de operaciones'!C1249:N1249) -> 0.70812698 | I20: =MAX('Analisis de operaciones'!C1432:N1432) -> 0.87642857 | J20: =MAX('Analisis de operaciones'!C1615:N1615) -> 0.50474669 | K20: =MAX('Analisis de operaciones'!C1798:N1798) -> 0.57445437
A21: Presurización | B21: =MAX('Analisis de operaciones'!C161:N161) -> 0.13238333 | C21: =MAX('Analisis de operaciones'!C344:N344) -> 0.20803049 | D21: =MAX('Analisis de operaciones'!C527:N527) -> 0.25541951 | E21: =MAX('Analisis de operaciones'!C710:N710) -> 0.33182741 | F21: =MAX('Analisis de operaciones'!C893:N893) -> 0.51068815 | G21: =MAX('Analisis de operaciones'!C1076:N1076) -> 0.66408173 | H21: =MAX('Analisis de operaciones'!C1259:N1259) -> 0.85919407 | I21: =MAX('Analisis de operaciones'!C1442:N1442) -> 0.5317 | J21: =MAX('Analisis de operaciones'!C1625:N1625) -> 0.61242599 | K21: =MAX('Analisis de operaciones'!C1808:N1808) -> 0.69700463
A22: Etiquetado | B22: =MAX('Analisis de operaciones'!C171:N171) -> 0.12001786 | C22: =MAX('Analisis de operaciones'!C354:N354) -> 0.18859907 | D22: =MAX('Analisis de operaciones'!C537:N537) -> 0.23156164 | E22: =MAX('Analisis de operaciones'!C720:N720) -> 0.30083254 | F22: =MAX('Analisis de operaciones'!C903:N903) -> 0.46298651 | G22: =MAX('Analisis de operaciones'!C1086:N1086) -> 0.60205212 | H22: =MAX('Analisis de operaciones'!C1269:N1269) -> 0.77893968 | I22: =MAX('Analisis de operaciones'!C1452:N1452) -> 0.48203571 | J22: =MAX('Analisis de operaciones'!C1635:N1635) -> 0.55522136 | K22: =MAX('Analisis de operaciones'!C1818:N1818) -> 0.6318998
A23: Embalaje y palletizado | B23: =MAX('Analisis de operaciones'!C181:N181) -> 0.10819535 | C23: =MAX('Analisis de operaciones'!C364:N364) -> 0.16938873 | D23: =MAX('Analisis de operaciones'!C547:N547) -> 0.36110322 | E23: =MAX('Analisis de operaciones'!C730:N730) -> 0.8045128 | F23: =MAX('Analisis de operaciones'!C913:N913) -> 0.70273712 | G23: =MAX('Analisis de operaciones'!C1096:N1096) -> 0.65826109 | H23: =MAX('Analisis de operaciones'!C1279:N1279) -> 0.45460115 | I23: =MAX('Analisis de operaciones'!C1462:N1462) -> 0.5812604 | J23: =MAX('Analisis de operaciones'!C1645:N1645) -> 0.65581254 | K23: =MAX('Analisis de operaciones'!C1828:N1828) -> 0.75780037
A24: Cortadora de plasma (1kg) | B24: =MAX('Analisis de operaciones'!C1851:N1851) -> 0.044449003 | C24: =MAX('Analisis de operaciones'!C1873:N1873) -> 0.063785755 | D24: =MAX('Analisis de operaciones'!C1895:N1895) -> 0.15437493 | E24: =MAX('Analisis de operaciones'!C1917:N1917) -> 0.37399278 | F24: =MAX('Analisis de operaciones'!C1939:N1939) -> 0.660683 | G24: =MAX('Analisis de operaciones'!C1961:N1961) -> 0.4642735 | H24: =MAX('Analisis de operaciones'!C1983:N1983) -> 0.6470792 | I24: =MAX('Analisis de operaciones'!C2005:N2005) -> 0.83033694 | J24: =MAX('Analisis de operaciones'!C2027:N2027) -> 0.46638215 | K24: =MAX('Analisis de operaciones'!C2049:N2049) -> 0.53878329
A26: MÁQUINAS
A28: Puesto | B28: 2026 | C28: 2027 | D28: 2028 | E28: 2029 | F28: 2030 | G28: 2031 | H28: 2032 | I28: 2033 | J28: 2034 | K28: 2035
A29: Preparación de cuello | B29: =MAX(1,B133) -> 1 | C29: =MAX(B29,C133) -> 1 | D29: =MAX(C29,D133) -> 1 | E29: =MAX(D29,E133) -> 1 | F29: =MAX(E29,F133) -> 2 | G29: =MAX(F29,G133) -> 2 | H29: =MAX(G29,H133) -> 2 | I29: =MAX(H29,I133) -> 2 | J29: =MAX(I29,J133) -> 2 | K29: =MAX(J29,K133) -> 2
A30: Soldadura circunferencial cuello (rosca) | B30: =MAX(1,B134) -> 1 | C30: =IF(AND(C55="Automática",B55="Manual"),C134,MAX(B30,C134)) -> 1 | D30: =IF(AND(D55="Automática",C55="Manual"),D134,MAX(C30,D134)) -> 1 | E30: =IF(AND(E55="Automática",D55="Manual"),E134,MAX(D30,E134)) -> 1 | F30: =IF(AND(F55="Automática",E55="Manual"),F134,MAX(E30,F134)) -> 1 | G30: =IF(AND(G55="Automática",F55="Manual"),G134,MAX(F30,G134)) -> 2 | H30: =IF(AND(H55="Automática",G55="Manual"),H134,MAX(G30,H134)) -> 2 | I30: =IF(AND(I55="Automática",H55="Manual"),I134,MAX(H30,I134)) -> 2 | J30: =IF(AND(J55="Automática",I55="Manual"),J134,MAX(I30,J134)) -> 2 | K30: =IF(AND(K55="Automática",J55="Manual"),K134,MAX(J30,K134)) -> 2
A31: Corte de disco y embutido (cúpula y fondo) | B31: =MAX(1,B135) -> 1 | C31: =MAX(B31,C135) -> 1 | D31: =MAX(C31,D135) -> 1 | E31: =MAX(D31,E135) -> 1 | F31: =MAX(E31,F135) -> 1 | G31: =MAX(F31,G135) -> 1 | H31: =MAX(G31,H135) -> 1 | I31: =MAX(H31,I135) -> 1 | J31: =MAX(I31,J135) -> 1 | K31: =MAX(J31,K135) -> 1
A32: Numerado de cuerpo | B32: =MAX(1,B136) -> 1 | C32: =MAX(B32,C136) -> 1 | D32: =MAX(C32,D136) -> 1 | E32: =MAX(D32,E136) -> 1 | F32: =MAX(E32,F136) -> 1 | G32: =MAX(F32,G136) -> 2 | H32: =MAX(G32,H136) -> 2 | I32: =MAX(H32,I136) -> 2 | J32: =MAX(I32,J136) -> 2 | K32: =MAX(J32,K136) -> 2
A33: Cilindrado | B33: =MAX(1,B137) -> 1 | C33: =MAX(B33,C137) -> 1 | D33: =MAX(C33,D137) -> 1 | E33: =MAX(D33,E137) -> 1 | F33: =MAX(E33,F137) -> 1 | G33: =MAX(F33,G137) -> 1 | H33: =MAX(G33,H137) -> 1 | I33: =MAX(H33,I137) -> 1 | J33: =MAX(I33,J137) -> 1 | K33: =MAX(J33,K137) -> 1
A34: Soldadura longitudinal | B34: =MAX(1,B138) -> 1 | C34: =MAX(B34,C138) -> 1 | D34: =MAX(C34,D138) -> 1 | E34: =MAX(D34,E138) -> 1 | F34: =MAX(E34,F138) -> 1 | G34: =MAX(F34,G138) -> 1 | H34: =MAX(G34,H138) -> 1 | I34: =MAX(H34,I138) -> 1 | J34: =MAX(I34,J138) -> 1 | K34: =MAX(J34,K138) -> 1
A35: Encastre de fondo | B35: =MAX(1,B139) -> 1 | C35: =MAX(B35,C139) -> 1 | D35: =MAX(C35,D139) -> 1 | E35: =MAX(D35,E139) -> 1 | F35: =MAX(E35,F139) -> 2 | G35: =MAX(F35,G139) -> 2 | H35: =MAX(G35,H139) -> 2 | I35: =MAX(H35,I139) -> 2 | J35: =MAX(I35,J139) -> 2 | K35: =MAX(J35,K139) -> 3
A36: Bordoneado | B36: =MAX(1,B140) -> 1 | C36: =MAX(B36,C140) -> 1 | D36: =MAX(C36,D140) -> 1 | E36: =MAX(D36,E140) -> 1 | F36: =MAX(E36,F140) -> 1 | G36: =MAX(F36,G140) -> 1 | H36: =MAX(G36,H140) -> 1 | I36: =MAX(H36,I140) -> 1 | J36: =MAX(I36,J140) -> 1 | K36: =MAX(J36,K140) -> 1
A37: Soldadura circunferencial (cúpula y fondo) | B37: =MAX(1,B141) -> 1 | C37: =MAX(B37,C141) -> 1 | D37: =MAX(C37,D141) -> 1 | E37: =MAX(D37,E141) -> 1 | F37: =MAX(E37,F141) -> 2 | G37: =MAX(F37,G141) -> 2 | H37: =MAX(G37,H141) -> 2 | I37: =MAX(H37,I141) -> 2 | J37: =MAX(I37,J141) -> 2 | K37: =MAX(J37,K141) -> 2
A38: Prueba hidráulica | B38: =MAX(1,B142) -> 1 | C38: =IF(AND(C58="Automática",B58="Manual"),C142,MAX(B38,C142)) -> 1 | D38: =IF(AND(D58="Automática",C58="Manual"),D142,MAX(C38,D142)) -> 1 | E38: =IF(AND(E58="Automática",D58="Manual"),E142,MAX(D38,E142)) -> 1 | F38: =IF(AND(F58="Automática",E58="Manual"),F142,MAX(E38,F142)) -> 1 | G38: =IF(AND(G58="Automática",F58="Manual"),G142,MAX(F38,G142)) -> 2 | H38: =IF(AND(H58="Automática",G58="Manual"),H142,MAX(G38,H142)) -> 2 | I38: =IF(AND(I58="Automática",H58="Manual"),I142,MAX(H38,I142)) -> 2 | J38: =IF(AND(J58="Automática",I58="Manual"),J142,MAX(I38,J142)) -> 2 | K38: =IF(AND(K58="Automática",J58="Manual"),K142,MAX(J38,K142)) -> 2
A39: Granallado | B39: =MAX(1,B143) -> 1 | C39: =MAX(B39,C143) -> 1 | D39: =MAX(C39,D143) -> 1 | E39: =MAX(D39,E143) -> 1 | F39: =MAX(E39,F143) -> 1 | G39: =MAX(F39,G143) -> 1 | H39: =MAX(G39,H143) -> 1 | I39: =MAX(H39,I143) -> 1 | J39: =MAX(I39,J143) -> 1 | K39: =MAX(J39,K143) -> 1
A40: Detección de defectos (CC) | B40: =MAX(1,B144) -> 1 | C40: =MAX(B40,C144) -> 1 | D40: =MAX(C40,D144) -> 1 | E40: =MAX(D40,E144) -> 1 | F40: =MAX(E40,F144) -> 1 | G40: =MAX(F40,G144) -> 1 | H40: =MAX(G40,H144) -> 1 | I40: =MAX(H40,I144) -> 1 | J40: =MAX(I40,J144) -> 1 | K40: =MAX(J40,K144) -> 1
A41: Corrección de defectos | B41: =MAX(1,B145) -> 1 | C41: =MAX(B41,C145) -> 1 | D41: =MAX(C41,D145) -> 1 | E41: =MAX(D41,E145) -> 1 | F41: =MAX(E41,F145) -> 1 | G41: =MAX(F41,G145) -> 1 | H41: =MAX(G41,H145) -> 1 | I41: =MAX(H41,I145) -> 1 | J41: =MAX(I41,J145) -> 1 | K41: =MAX(J41,K145) -> 1
A42: Pintura + Horno (cil. 1–10 kg) | B42: =IF(B$28<$B$51,0,MAX(1,B146)) -> 0 | C42: =IF(C$28<$B$51,0,MAX(1,B42,C146)) -> 0 | D42: =IF(D$28<$B$51,0,MAX(1,C42,D146)) -> 0 | E42: =IF(E$28<$B$51,0,MAX(1,D42,E146)) -> 1 | F42: =IF(F$28<$B$51,0,MAX(1,E42,F146)) -> 1 | G42: =IF(G$28<$B$51,0,MAX(1,F42,G146)) -> 1 | H42: =IF(H$28<$B$51,0,MAX(1,G42,H146)) -> 1 | I42: =IF(I$28<$B$51,0,MAX(1,H42,I146)) -> 1 | J42: =IF(J$28<$B$51,0,MAX(1,I42,J146)) -> 1 | K42: =IF(K$28<$B$51,0,MAX(1,J42,K146)) -> 1
A43: Carga de polvo | B43: =MAX(1,B147) -> 1 | C43: =MAX(B43,C147) -> 1 | D43: =MAX(C43,D147) -> 1 | E43: =MAX(D43,E147) -> 1 | F43: =MAX(E43,F147) -> 1 | G43: =MAX(F43,G147) -> 1 | H43: =MAX(G43,H147) -> 1 | I43: =MAX(H43,I147) -> 1 | J43: =MAX(I43,J147) -> 1 | K43: =MAX(J43,K147) -> 1
A44: Ensamblaje | B44: =MAX(1,B148) -> 1 | C44: =MAX(B44,C148) -> 1 | D44: =MAX(C44,D148) -> 1 | E44: =MAX(D44,E148) -> 1 | F44: =MAX(E44,F148) -> 1 | G44: =MAX(F44,G148) -> 2 | H44: =MAX(G44,H148) -> 2 | I44: =MAX(H44,I148) -> 2 | J44: =MAX(I44,J148) -> 2 | K44: =MAX(J44,K148) -> 2
A45: Presurización | B45: =MAX(1,B149) -> 1 | C45: =MAX(B45,C149) -> 1 | D45: =MAX(C45,D149) -> 1 | E45: =MAX(D45,E149) -> 1 | F45: =MAX(E45,F149) -> 1 | G45: =MAX(F45,G149) -> 1 | H45: =MAX(G45,H149) -> 1 | I45: =MAX(H45,I149) -> 1 | J45: =MAX(I45,J149) -> 1 | K45: =MAX(J45,K149) -> 1
A46: Etiquetado | B46: =MAX(1,B150) -> 1 | C46: =MAX(B46,C150) -> 1 | D46: =MAX(C46,D150) -> 1 | E46: =MAX(D46,E150) -> 1 | F46: =MAX(E46,F150) -> 1 | G46: =MAX(F46,G150) -> 1 | H46: =MAX(G46,H150) -> 1 | I46: =MAX(H46,I150) -> 1 | J46: =MAX(I46,J150) -> 1 | K46: =MAX(J46,K150) -> 1
A47: Embalaje y palletizado | B47: =MAX(1,B151) -> 1 | C47: =MAX(B47,C151) -> 1 | D47: =MAX(C47,D151) -> 1 | E47: =MAX(D47,E151) -> 1 | F47: =MAX(E47,F151) -> 2 | G47: =MAX(F47,G151) -> 3 | H47: =MAX(G47,H151) -> 3 | I47: =MAX(H47,I151) -> 3 | J47: =MAX(I47,J151) -> 3 | K47: =MAX(J47,K151) -> 3
A48: Cortadora de plasma (1kg) | B48: =MAX(1,B152) -> 1 | C48: =MAX(B48,C152) -> 1 | D48: =MAX(C48,D152) -> 1 | E48: =MAX(D48,E152) -> 1 | F48: =MAX(E48,F152) -> 1 | G48: =MAX(F48,G152) -> 2 | H48: =MAX(G48,H152) -> 2 | I48: =MAX(H48,I152) -> 2 | J48: =MAX(I48,J152) -> 2 | K48: =MAX(J48,K152) -> 2
A49: TOTAL máquinas / puestos de producción | B49: =SUM(B29:B48) -> 19 | C49: =SUM(C29:C48) -> 19 | D49: =SUM(D29:D48) -> 19 | E49: =SUM(E29:E48) -> 20 | F49: =SUM(F29:F48) -> 24 | G49: =SUM(G29:G48) -> 30 | H49: =SUM(H29:H48) -> 30 | I49: =SUM(I29:I48) -> 30 | ... K49: =SUM(K29:K48) -> 31
A50: Umbral: ocupación pico máxima por máquina | B50: 0.9 | D50: Año de inicio del 2° turno (antes: más máquinas) | H50: 2032
A51: Año de pintura propia (antes tercerizada) | B51: 2029
A53: TECNOLOGÍA — soldaduras y prueba hidráulica (se CAMBIA la manual por la automática, no se ponen en paralelo)
A54: Puesto | B54: 2026 | C54: 2027 | D54: 2028 | E54: 2029 | F54: 2030 | G54: 2031 | H54: 2032 | I54: 2033 | J54: 2034 | K54: 2035
A55: Soldadura circunferencial cuello (rosca) → FS-HFM1 Firesafer | B55: =IF(B59>1,"Automática","Manual") -> Manual | C55: =IF(OR(B55="Automática",C59>B30),"Automática","Manual") -> Manual | D55: =IF(OR(C55="Automática",D59>C30),"Automática","Manual") -> Manual | E55: =IF(OR(D55="Automática",E59>D30),"Automática","Manual") -> Automática | F55: =IF(OR(E55="Automática",F59>E30),"Automática","Manual") -> Automática | G55: =IF(OR(F55="Automática",G59>F30),"Automática","Manual") -> Automática | H55: =IF(OR(G55="Automática",H59>G30),"Automática","Manual") -> Automática | I55: =IF(OR(H55="Automática",I59>H30),"Automática","Manual") -> Automática | J55: =IF(OR(I55="Automática",J59>I30),"Automática","Manual") -> Automática | K55: =IF(OR(J55="Automática",K59>J30),"Automática","Manual") -> Automática
A56: Soldadura longitudinal → Firesafer | B56: Automática | C56: Automática | D56: Automática | E56: Automática | F56: Automática | G56: Automática | H56: Automática | I56: Automática | J56: Automática | K56: Automática
A57: Soldadura circunferencial (cúpula y fondo) → Firesafer | B57: Automática | C57: Automática | D57: Automática | E57: Automática | F57: Automática | G57: Automática | H57: Automática | I57: Automática | J57: Automática | K57: Automática
A58: Prueba hidráulica → FS-JD12A Firesafer | B58: =IF(B60>1,"Automática","Manual") -> Manual | C58: =IF(OR(B58="Automática",C60>B38),"Automática","Manual") -> Manual | D58: =IF(OR(C58="Automática",D60>C38),"Automática","Manual") -> Manual | E58: =IF(OR(D58="Automática",E60>D38),"Automática","Manual") -> Automática | F58: =IF(OR(E58="Automática",F60>E38),"Automática","Manual") -> Automática | G58: =IF(OR(F58="Automática",G60>F38),"Automática","Manual") -> Automática | H58: =IF(OR(G58="Automática",H60>G38),"Automática","Manual") -> Automática | I58: =IF(OR(H58="Automática",I60>H38),"Automática","Manual") -> Automática | J58: =IF(OR(I58="Automática",J60>I38),"Automática","Manual") -> Automática | K58: =IF(OR(J58="Automática",K60>J38),"Automática","Manual") -> Automática
A59: Soldadura circunferencial cuello (rosca): máquinas necesarias si sigue manual | B59: =ROUNDUP(B90/(Parametros!$M$40*B$64*$B$50),0) -> 1 | C59: =ROUNDUP(C90/(Parametros!$M$40*C$64*$B$50),0) -> 1 | D59: =ROUNDUP(D90/(Parametros!$M$40*D$64*$B$50),0) -> 1 | E59: =ROUNDUP(E90/(Parametros!$M$40*E$64*$B$50),0) -> 2 | F59: =ROUNDUP(F90/(Parametros!$M$40*F$64*$B$50),0) -> 2 | G59: =ROUNDUP(G90/(Parametros!$M$40*G$64*$B$50),0) -> 3 | H59: =ROUNDUP(H90/(Parametros!$M$40*H$64*$B$50),0) -> 2 | I59: =ROUNDUP(I90/(Parametros!$M$40*I$64*$B$50),0) -> 3 | ... K59: =ROUNDUP(K90/(Parametros!$M$40*K$64*$B$50),0) -> 4
A60: Prueba hidráulica: máquinas necesarias si sigue manual | B60: =ROUNDUP(B98/(Parametros!$M$48*B$64*$B$50),0) -> 1 | C60: =ROUNDUP(C98/(Parametros!$M$48*C$64*$B$50),0) -> 1 | D60: =ROUNDUP(D98/(Parametros!$M$48*D$64*$B$50),0) -> 1 | E60: =ROUNDUP(E98/(Parametros!$M$48*E$64*$B$50),0) -> 2 | F60: =ROUNDUP(F98/(Parametros!$M$48*F$64*$B$50),0) -> 4 | G60: =ROUNDUP(G98/(Parametros!$M$48*G$64*$B$50),0) -> 5 | H60: =ROUNDUP(H98/(Parametros!$M$48*H$64*$B$50),0) -> 4 | I60: =ROUNDUP(I98/(Parametros!$M$48*I$64*$B$50),0) -> 5 | ... K60: =ROUNDUP(K98/(Parametros!$M$48*K$64*$B$50),0) -> 6
A62: TURNOS — desde el año H50 el puesto pasa a 2 turnos solo si con 1 turno supera el umbral (0 = tercerizado)
A63: Puesto | B63: 2026 | C63: 2027 | D63: 2028 | E63: 2029 | F63: 2030 | G63: 2031 | H63: 2032 | I63: 2033 | J63: 2034 | K63: 2035
A64: Turnos disponibles de planta | B64: =IF(B$28>=$H$50,2,1) -> 1 | C64: =IF(C$28>=$H$50,2,1) -> 1 | D64: =IF(D$28>=$H$50,2,1) -> 1 | E64: =IF(E$28>=$H$50,2,1) -> 1 | F64: =IF(F$28>=$H$50,2,1) -> 1 | G64: =IF(G$28>=$H$50,2,1) -> 1 | H64: =IF(H$28>=$H$50,2,1) -> 2 | I64: =IF(I$28>=$H$50,2,1) -> 2 | ... K64: =IF(K$28>=$H$50,2,1) -> 2
A65: Preparación de cuello | B65: =IF(B29=0,0,IF(B$64=1,1,IF(B89/(B111*B29*$B$50)>1,2,1))) -> 1 | C65: =IF(C29=0,0,IF(C$64=1,1,IF(C89/(C111*C29*$B$50)>1,2,1))) -> 1 | D65: =IF(D29=0,0,IF(D$64=1,1,IF(D89/(D111*D29*$B$50)>1,2,1))) -> 1 | E65: =IF(E29=0,0,IF(E$64=1,1,IF(E89/(E111*E29*$B$50)>1,2,1))) -> 1 | F65: =IF(F29=0,0,IF(F$64=1,1,IF(F89/(F111*F29*$B$50)>1,2,1))) -> 1 | G65: =IF(G29=0,0,IF(G$64=1,1,IF(G89/(G111*G29*$B$50)>1,2,1))) -> 1 | H65: =IF(H29=0,0,IF(H$64=1,1,IF(H89/(H111*H29*$B$50)>1,2,1))) -> 2 | I65: =IF(I29=0,0,IF(I$64=1,1,IF(I89/(I111*I29*$B$50)>1,2,1))) -> 2 | ... K65: =IF(K29=0,0,IF(K$64=1,1,IF(K89/(K111*K29*$B$50)>1,2,1))) -> 2
A66: Soldadura circunferencial cuello (rosca) | B66: =IF(B30=0,0,IF(B$64=1,1,IF(B90/(B112*B30*$B$50)>1,2,1))) -> 1 | C66: =IF(C30=0,0,IF(C$64=1,1,IF(C90/(C112*C30*$B$50)>1,2,1))) -> 1 | D66: =IF(D30=0,0,IF(D$64=1,1,IF(D90/(D112*D30*$B$50)>1,2,1))) -> 1 | E66: =IF(E30=0,0,IF(E$64=1,1,IF(E90/(E112*E30*$B$50)>1,2,1))) -> 1 | F66: =IF(F30=0,0,IF(F$64=1,1,IF(F90/(F112*F30*$B$50)>1,2,1))) -> 1 | G66: =IF(G30=0,0,IF(G$64=1,1,IF(G90/(G112*G30*$B$50)>1,2,1))) -> 1 | H66: =IF(H30=0,0,IF(H$64=1,1,IF(H90/(H112*H30*$B$50)>1,2,1))) -> 1 | I66: =IF(I30=0,0,IF(I$64=1,1,IF(I90/(I112*I30*$B$50)>1,2,1))) -> 2 | ... K66: =IF(K30=0,0,IF(K$64=1,1,IF(K90/(K112*K30*$B$50)>1,2,1))) -> 2
A67: Corte de disco y embutido (cúpula y fondo) | B67: =IF(B31=0,0,IF(B$64=1,1,IF(B91/(B113*B31*$B$50)>1,2,1))) -> 1 | C67: =IF(C31=0,0,IF(C$64=1,1,IF(C91/(C113*C31*$B$50)>1,2,1))) -> 1 | D67: =IF(D31=0,0,IF(D$64=1,1,IF(D91/(D113*D31*$B$50)>1,2,1))) -> 1 | E67: =IF(E31=0,0,IF(E$64=1,1,IF(E91/(E113*E31*$B$50)>1,2,1))) -> 1 | F67: =IF(F31=0,0,IF(F$64=1,1,IF(F91/(F113*F31*$B$50)>1,2,1))) -> 1 | G67: =IF(G31=0,0,IF(G$64=1,1,IF(G91/(G113*G31*$B$50)>1,2,1))) -> 1 | H67: =IF(H31=0,0,IF(H$64=1,1,IF(H91/(H113*H31*$B$50)>1,2,1))) -> 1 | I67: =IF(I31=0,0,IF(I$64=1,1,IF(I91/(I113*I31*$B$50)>1,2,1))) -> 1 | ... K67: =IF(K31=0,0,IF(K$64=1,1,IF(K91/(K113*K31*$B$50)>1,2,1))) -> 2
A68: Numerado de cuerpo | B68: =IF(B32=0,0,IF(B$64=1,1,IF(B92/(B114*B32*$B$50)>1,2,1))) -> 1 | C68: =IF(C32=0,0,IF(C$64=1,1,IF(C92/(C114*C32*$B$50)>1,2,1))) -> 1 | D68: =IF(D32=0,0,IF(D$64=1,1,IF(D92/(D114*D32*$B$50)>1,2,1))) -> 1 | E68: =IF(E32=0,0,IF(E$64=1,1,IF(E92/(E114*E32*$B$50)>1,2,1))) -> 1 | F68: =IF(F32=0,0,IF(F$64=1,1,IF(F92/(F114*F32*$B$50)>1,2,1))) -> 1 | G68: =IF(G32=0,0,IF(G$64=1,1,IF(G92/(G114*G32*$B$50)>1,2,1))) -> 1 | H68: =IF(H32=0,0,IF(H$64=1,1,IF(H92/(H114*H32*$B$50)>1,2,1))) -> 1 | I68: =IF(I32=0,0,IF(I$64=1,1,IF(I92/(I114*I32*$B$50)>1,2,1))) -> 1 | ... K68: =IF(K32=0,0,IF(K$64=1,1,IF(K92/(K114*K32*$B$50)>1,2,1))) -> 2
A69: Cilindrado | B69: =IF(B33=0,0,IF(B$64=1,1,IF(B93/(B115*B33*$B$50)>1,2,1))) -> 1 | C69: =IF(C33=0,0,IF(C$64=1,1,IF(C93/(C115*C33*$B$50)>1,2,1))) -> 1 | D69: =IF(D33=0,0,IF(D$64=1,1,IF(D93/(D115*D33*$B$50)>1,2,1))) -> 1 | E69: =IF(E33=0,0,IF(E$64=1,1,IF(E93/(E115*E33*$B$50)>1,2,1))) -> 1 | F69: =IF(F33=0,0,IF(F$64=1,1,IF(F93/(F115*F33*$B$50)>1,2,1))) -> 1 | G69: =IF(G33=0,0,IF(G$64=1,1,IF(G93/(G115*G33*$B$50)>1,2,1))) -> 1 | H69: =IF(H33=0,0,IF(H$64=1,1,IF(H93/(H115*H33*$B$50)>1,2,1))) -> 1 | I69: =IF(I33=0,0,IF(I$64=1,1,IF(I93/(I115*I33*$B$50)>1,2,1))) -> 1 | ... K69: =IF(K33=0,0,IF(K$64=1,1,IF(K93/(K115*K33*$B$50)>1,2,1))) -> 1
A70: Soldadura longitudinal | B70: =IF(B34=0,0,IF(B$64=1,1,IF(B94/(B116*B34*$B$50)>1,2,1))) -> 1 | C70: =IF(C34=0,0,IF(C$64=1,1,IF(C94/(C116*C34*$B$50)>1,2,1))) -> 1 | D70: =IF(D34=0,0,IF(D$64=1,1,IF(D94/(D116*D34*$B$50)>1,2,1))) -> 1 | E70: =IF(E34=0,0,IF(E$64=1,1,IF(E94/(E116*E34*$B$50)>1,2,1))) -> 1 | F70: =IF(F34=0,0,IF(F$64=1,1,IF(F94/(F116*F34*$B$50)>1,2,1))) -> 1 | G70: =IF(G34=0,0,IF(G$64=1,1,IF(G94/(G116*G34*$B$50)>1,2,1))) -> 1 | H70: =IF(H34=0,0,IF(H$64=1,1,IF(H94/(H116*H34*$B$50)>1,2,1))) -> 1 | I70: =IF(I34=0,0,IF(I$64=1,1,IF(I94/(I116*I34*$B$50)>1,2,1))) -> 1 | ... K70: =IF(K34=0,0,IF(K$64=1,1,IF(K94/(K116*K34*$B$50)>1,2,1))) -> 2
A71: Encastre de fondo | B71: =IF(B35=0,0,IF(B$64=1,1,IF(B95/(B117*B35*$B$50)>1,2,1))) -> 1 | C71: =IF(C35=0,0,IF(C$64=1,1,IF(C95/(C117*C35*$B$50)>1,2,1))) -> 1 | D71: =IF(D35=0,0,IF(D$64=1,1,IF(D95/(D117*D35*$B$50)>1,2,1))) -> 1 | E71: =IF(E35=0,0,IF(E$64=1,1,IF(E95/(E117*E35*$B$50)>1,2,1))) -> 1 | F71: =IF(F35=0,0,IF(F$64=1,1,IF(F95/(F117*F35*$B$50)>1,2,1))) -> 1 | G71: =IF(G35=0,0,IF(G$64=1,1,IF(G95/(G117*G35*$B$50)>1,2,1))) -> 1 | H71: =IF(H35=0,0,IF(H$64=1,1,IF(H95/(H117*H35*$B$50)>1,2,1))) -> 2 | I71: =IF(I35=0,0,IF(I$64=1,1,IF(I95/(I117*I35*$B$50)>1,2,1))) -> 2 | ... K71: =IF(K35=0,0,IF(K$64=1,1,IF(K95/(K117*K35*$B$50)>1,2,1))) -> 2
A72: Bordoneado | B72: =IF(B36=0,0,IF(B$64=1,1,IF(B96/(B118*B36*$B$50)>1,2,1))) -> 1 | C72: =IF(C36=0,0,IF(C$64=1,1,IF(C96/(C118*C36*$B$50)>1,2,1))) -> 1 | D72: =IF(D36=0,0,IF(D$64=1,1,IF(D96/(D118*D36*$B$50)>1,2,1))) -> 1 | E72: =IF(E36=0,0,IF(E$64=1,1,IF(E96/(E118*E36*$B$50)>1,2,1))) -> 1 | F72: =IF(F36=0,0,IF(F$64=1,1,IF(F96/(F118*F36*$B$50)>1,2,1))) -> 1 | G72: =IF(G36=0,0,IF(G$64=1,1,IF(G96/(G118*G36*$B$50)>1,2,1))) -> 1 | H72: =IF(H36=0,0,IF(H$64=1,1,IF(H96/(H118*H36*$B$50)>1,2,1))) -> 1 | I72: =IF(I36=0,0,IF(I$64=1,1,IF(I96/(I118*I36*$B$50)>1,2,1))) -> 2 | ... K72: =IF(K36=0,0,IF(K$64=1,1,IF(K96/(K118*K36*$B$50)>1,2,1))) -> 2
A73: Soldadura circunferencial (cúpula y fondo) | B73: =IF(B37=0,0,IF(B$64=1,1,IF(B97/(B119*B37*$B$50)>1,2,1))) -> 1 | C73: =IF(C37=0,0,IF(C$64=1,1,IF(C97/(C119*C37*$B$50)>1,2,1))) -> 1 | D73: =IF(D37=0,0,IF(D$64=1,1,IF(D97/(D119*D37*$B$50)>1,2,1))) -> 1 | E73: =IF(E37=0,0,IF(E$64=1,1,IF(E97/(E119*E37*$B$50)>1,2,1))) -> 1 | F73: =IF(F37=0,0,IF(F$64=1,1,IF(F97/(F119*F37*$B$50)>1,2,1))) -> 1 | G73: =IF(G37=0,0,IF(G$64=1,1,IF(G97/(G119*G37*$B$50)>1,2,1))) -> 1 | H73: =IF(H37=0,0,IF(H$64=1,1,IF(H97/(H119*H37*$B$50)>1,2,1))) -> 2 | I73: =IF(I37=0,0,IF(I$64=1,1,IF(I97/(I119*I37*$B$50)>1,2,1))) -> 2 | ... K73: =IF(K37=0,0,IF(K$64=1,1,IF(K97/(K119*K37*$B$50)>1,2,1))) -> 2
A74: Prueba hidráulica | B74: =IF(B38=0,0,IF(B$64=1,1,IF(B98/(B120*B38*$B$50)>1,2,1))) -> 1 | C74: =IF(C38=0,0,IF(C$64=1,1,IF(C98/(C120*C38*$B$50)>1,2,1))) -> 1 | D74: =IF(D38=0,0,IF(D$64=1,1,IF(D98/(D120*D38*$B$50)>1,2,1))) -> 1 | E74: =IF(E38=0,0,IF(E$64=1,1,IF(E98/(E120*E38*$B$50)>1,2,1))) -> 1 | F74: =IF(F38=0,0,IF(F$64=1,1,IF(F98/(F120*F38*$B$50)>1,2,1))) -> 1 | G74: =IF(G38=0,0,IF(G$64=1,1,IF(G98/(G120*G38*$B$50)>1,2,1))) -> 1 | H74: =IF(H38=0,0,IF(H$64=1,1,IF(H98/(H120*H38*$B$50)>1,2,1))) -> 1 | I74: =IF(I38=0,0,IF(I$64=1,1,IF(I98/(I120*I38*$B$50)>1,2,1))) -> 2 | ... K74: =IF(K38=0,0,IF(K$64=1,1,IF(K98/(K120*K38*$B$50)>1,2,1))) -> 2
A75: Granallado | B75: =IF(B39=0,0,IF(B$64=1,1,IF(B99/(B121*B39*$B$50)>1,2,1))) -> 1 | C75: =IF(C39=0,0,IF(C$64=1,1,IF(C99/(C121*C39*$B$50)>1,2,1))) -> 1 | D75: =IF(D39=0,0,IF(D$64=1,1,IF(D99/(D121*D39*$B$50)>1,2,1))) -> 1 | E75: =IF(E39=0,0,IF(E$64=1,1,IF(E99/(E121*E39*$B$50)>1,2,1))) -> 1 | F75: =IF(F39=0,0,IF(F$64=1,1,IF(F99/(F121*F39*$B$50)>1,2,1))) -> 1 | G75: =IF(G39=0,0,IF(G$64=1,1,IF(G99/(G121*G39*$B$50)>1,2,1))) -> 1 | H75: =IF(H39=0,0,IF(H$64=1,1,IF(H99/(H121*H39*$B$50)>1,2,1))) -> 1 | I75: =IF(I39=0,0,IF(I$64=1,1,IF(I99/(I121*I39*$B$50)>1,2,1))) -> 1 | ... K75: =IF(K39=0,0,IF(K$64=1,1,IF(K99/(K121*K39*$B$50)>1,2,1))) -> 1
A76: Detección de defectos (CC) | B76: =IF(B40=0,0,IF(B$64=1,1,IF(B100/(B122*B40*$B$50)>1,2,1))) -> 1 | C76: =IF(C40=0,0,IF(C$64=1,1,IF(C100/(C122*C40*$B$50)>1,2,1))) -> 1 | D76: =IF(D40=0,0,IF(D$64=1,1,IF(D100/(D122*D40*$B$50)>1,2,1))) -> 1 | E76: =IF(E40=0,0,IF(E$64=1,1,IF(E100/(E122*E40*$B$50)>1,2,1))) -> 1 | F76: =IF(F40=0,0,IF(F$64=1,1,IF(F100/(F122*F40*$B$50)>1,2,1))) -> 1 | G76: =IF(G40=0,0,IF(G$64=1,1,IF(G100/(G122*G40*$B$50)>1,2,1))) -> 1 | H76: =IF(H40=0,0,IF(H$64=1,1,IF(H100/(H122*H40*$B$50)>1,2,1))) -> 1 | I76: =IF(I40=0,0,IF(I$64=1,1,IF(I100/(I122*I40*$B$50)>1,2,1))) -> 1 | ... K76: =IF(K40=0,0,IF(K$64=1,1,IF(K100/(K122*K40*$B$50)>1,2,1))) -> 2
... A84: Cortadora de plasma (1kg) | B84: =IF(B48=0,0,IF(B$64=1,1,IF(B108/(B130*B48*$B$50)>1,2,1))) -> 1 | C84: =IF(C48=0,0,IF(C$64=1,1,IF(C108/(C130*C48*$B$50)>1,2,1))) -> 1 | D84: =IF(D48=0,0,IF(D$64=1,1,IF(D108/(D130*D48*$B$50)>1,2,1))) -> 1 | E84: =IF(E48=0,0,IF(E$64=1,1,IF(E108/(E130*E48*$B$50)>1,2,1))) -> 1 | F84: =IF(F48=0,0,IF(F$64=1,1,IF(F108/(F130*F48*$B$50)>1,2,1))) -> 1 | G84: =IF(G48=0,0,IF(G$64=1,1,IF(G108/(G130*G48*$B$50)>1,2,1))) -> 1 | H84: =IF(H48=0,0,IF(H$64=1,1,IF(H108/(H130*H48*$B$50)>1,2,1))) -> 1 | I84: =IF(I48=0,0,IF(I$64=1,1,IF(I108/(I130*I48*$B$50)>1,2,1))) -> 1 | ... K84: =IF(K48=0,0,IF(K$64=1,1,IF(K108/(K130*K48*$B$50)>1,2,1))) -> 2
A85: Turnos de planta (se usa en recargas y dotación) | B85: =MAX(B65:B84) -> 1 | C85: =MAX(C65:C84) -> 1 | D85: =MAX(D65:D84) -> 1 | E85: =MAX(E65:E84) -> 1 | F85: =MAX(F65:F84) -> 1 | G85: =MAX(G65:G84) -> 1 | H85: =MAX(H65:H84) -> 2 | I85: =MAX(I65:I84) -> 2 | ... K85: =MAX(K65:K84) -> 2
A87: CÁLCULO DE MÁQUINAS — necesarias = REDONDEAR.MAS(demanda pico ÷ (cap. real × turnos disponibles × umbral))
A88: Demanda pico (u/h) | B88: 2026 | C88: 2027 | D88: 2028 | E88: 2029 | F88: 2030 | G88: 2031 | H88: 2032 | I88: 2033 | J88: 2034 | K88: 2035
A89: Preparación de cuello | B89: =MAX('Analisis de operaciones'!C7:N7) -> 5.2814 | C89: =MAX('Analisis de operaciones'!C190:N190) -> 8.2684667 | D89: =MAX('Analisis de operaciones'!C373:N373) -> 17.626733 | E89: =MAX('Analisis de operaciones'!C556:N556) -> 39.271133 | F89: =MAX('Analisis de operaciones'!C739:N739) -> 68.6062 | G89: =MAX('Analisis de operaciones'!C922:N922) -> 96.3962 | H89: =MAX('Analisis de operaciones'!C1105:N1105) -> 133.1442 | I89: =MAX('Analisis de operaciones'!C1288:N1288) -> 170.24033 | J89: =MAX('Analisis de operaciones'!C1471:N1471) -> 192.07527 | K89: =MAX('Analisis de operaciones'!C1654:N1654) -> 221.9456
A90: Soldadura circunferencial cuello (rosca) | B90: =MAX('Analisis de operaciones'!C17:N17) -> 5.2814 | C90: =MAX('Analisis de operaciones'!C200:N200) -> 8.2684667 | D90: =MAX('Analisis de operaciones'!C383:N383) -> 17.626733 | E90: =MAX('Analisis de operaciones'!C566:N566) -> 39.271133 | F90: =MAX('Analisis de operaciones'!C749:N749) -> 68.6062 | G90: =MAX('Analisis de operaciones'!C932:N932) -> 96.3962 | H90: =MAX('Analisis de operaciones'!C1115:N1115) -> 133.1442 | I90: =MAX('Analisis de operaciones'!C1298:N1298) -> 170.24033 | J90: =MAX('Analisis de operaciones'!C1481:N1481) -> 192.07527 | K90: =MAX('Analisis de operaciones'!C1664:N1664) -> 221.9456
A91: Corte de disco y embutido (cúpula y fondo) | B91: =MAX('Analisis de operaciones'!C27:N27) -> 10.5628 | C91: =MAX('Analisis de operaciones'!C210:N210) -> 16.536933 | D91: =MAX('Analisis de operaciones'!C393:N393) -> 35.253467 | E91: =MAX('Analisis de operaciones'!C576:N576) -> 78.542267 | F91: =MAX('Analisis de operaciones'!C759:N759) -> 137.2124 | G91: =MAX('Analisis de operaciones'!C942:N942) -> 192.7924 | H91: =MAX('Analisis de operaciones'!C1125:N1125) -> 266.2884 | I91: =MAX('Analisis de operaciones'!C1308:N1308) -> 340.48067 | J91: =MAX('Analisis de operaciones'!C1491:N1491) -> 384.15053 | K91: =MAX('Analisis de operaciones'!C1674:N1674) -> 443.8912
A92: Numerado de cuerpo | B92: =MAX('Analisis de operaciones'!C37:N37) -> 5.2814 | C92: =MAX('Analisis de operaciones'!C220:N220) -> 8.2684667 | D92: =MAX('Analisis de operaciones'!C403:N403) -> 17.626733 | E92: =MAX('Analisis de operaciones'!C586:N586) -> 39.271133 | F92: =MAX('Analisis de operaciones'!C769:N769) -> 68.6062 | G92: =MAX('Analisis de operaciones'!C952:N952) -> 96.3962 | H92: =MAX('Analisis de operaciones'!C1135:N1135) -> 133.1442 | I92: =MAX('Analisis de operaciones'!C1318:N1318) -> 170.24033 | J92: =MAX('Analisis de operaciones'!C1501:N1501) -> 192.07527 | K92: =MAX('Analisis de operaciones'!C1684:N1684) -> 221.9456
A93: Cilindrado | B93: =MAX('Analisis de operaciones'!C47:N47) -> 1.9382 | C93: =MAX('Analisis de operaciones'!C230:N230) -> 3.4708667 | D93: =MAX('Analisis de operaciones'!C413:N413) -> 6.0155333 | E93: =MAX('Analisis de operaciones'!C596:N596) -> 11.141533 | F93: =MAX('Analisis de operaciones'!C779:N779) -> 18.9134 | G93: =MAX('Analisis de operaciones'!C962:N962) -> 26.5562 | H93: =MAX('Analisis de operaciones'!C1145:N1145) -> 35.805 | I93: =MAX('Analisis de operaciones'!C1328:N1328) -> 45.333933 | J93: =MAX('Analisis de operaciones'!C1511:N1511) -> 51.760867 | K93: =MAX('Analisis de operaciones'!C1694:N1694) -> 59.8488
A94: Soldadura longitudinal | B94: =MAX('Analisis de operaciones'!C57:N57) -> 1.9382 | C94: =MAX('Analisis de operaciones'!C240:N240) -> 3.4708667 | D94: =MAX('Analisis de operaciones'!C423:N423) -> 6.0155333 | E94: =MAX('Analisis de operaciones'!C606:N606) -> 11.141533 | F94: =MAX('Analisis de operaciones'!C789:N789) -> 18.9134 | G94: =MAX('Analisis de operaciones'!C972:N972) -> 26.5562 | H94: =MAX('Analisis de operaciones'!C1155:N1155) -> 35.805 | I94: =MAX('Analisis de operaciones'!C1338:N1338) -> 45.333933 | J94: =MAX('Analisis de operaciones'!C1521:N1521) -> 51.760867 | K94: =MAX('Analisis de operaciones'!C1704:N1704) -> 59.8488
A95: Encastre de fondo | B95: =MAX('Analisis de operaciones'!C67:N67) -> 5.2814 | C95: =MAX('Analisis de operaciones'!C250:N250) -> 8.2684667 | D95: =MAX('Analisis de operaciones'!C433:N433) -> 17.626733 | E95: =MAX('Analisis de operaciones'!C616:N616) -> 39.271133 | F95: =MAX('Analisis de operaciones'!C799:N799) -> 68.6062 | G95: =MAX('Analisis de operaciones'!C982:N982) -> 96.3962 | H95: =MAX('Analisis de operaciones'!C1165:N1165) -> 133.1442 | I95: =MAX('Analisis de operaciones'!C1348:N1348) -> 170.24033 | J95: =MAX('Analisis de operaciones'!C1531:N1531) -> 192.07527 | K95: =MAX('Analisis de operaciones'!C1714:N1714) -> 221.9456
A96: Bordoneado | B96: =MAX('Analisis de operaciones'!C77:N77) -> 5.2814 | C96: =MAX('Analisis de operaciones'!C260:N260) -> 8.2684667 | D96: =MAX('Analisis de operaciones'!C443:N443) -> 17.626733 | E96: =MAX('Analisis de operaciones'!C626:N626) -> 39.271133 | F96: =MAX('Analisis de operaciones'!C809:N809) -> 68.6062 | G96: =MAX('Analisis de operaciones'!C992:N992) -> 96.3962 | H96: =MAX('Analisis de operaciones'!C1175:N1175) -> 133.1442 | I96: =MAX('Analisis de operaciones'!C1358:N1358) -> 170.24033 | J96: =MAX('Analisis de operaciones'!C1541:N1541) -> 192.07527 | K96: =MAX('Analisis de operaciones'!C1724:N1724) -> 221.9456
A97: Soldadura circunferencial (cúpula y fondo) | B97: =MAX('Analisis de operaciones'!C87:N87) -> 5.2814 | C97: =MAX('Analisis de operaciones'!C270:N270) -> 8.2684667 | D97: =MAX('Analisis de operaciones'!C453:N453) -> 17.626733 | E97: =MAX('Analisis de operaciones'!C636:N636) -> 39.271133 | F97: =MAX('Analisis de operaciones'!C819:N819) -> 68.6062 | G97: =MAX('Analisis de operaciones'!C1002:N1002) -> 96.3962 | H97: =MAX('Analisis de operaciones'!C1185:N1185) -> 133.1442 | I97: =MAX('Analisis de operaciones'!C1368:N1368) -> 170.24033 | J97: =MAX('Analisis de operaciones'!C1551:N1551) -> 192.07527 | K97: =MAX('Analisis de operaciones'!C1734:N1734) -> 221.9456
A98: Prueba hidráulica | B98: =MAX('Analisis de operaciones'!C97:N97) -> 5.2814 | C98: =MAX('Analisis de operaciones'!C280:N280) -> 8.2684667 | D98: =MAX('Analisis de operaciones'!C463:N463) -> 17.626733 | E98: =MAX('Analisis de operaciones'!C646:N646) -> 39.271133 | F98: =MAX('Analisis de operaciones'!C829:N829) -> 68.6062 | G98: =MAX('Analisis de operaciones'!C1012:N1012) -> 96.3962 | H98: =MAX('Analisis de operaciones'!C1195:N1195) -> 133.1442 | I98: =MAX('Analisis de operaciones'!C1378:N1378) -> 170.24033 | J98: =MAX('Analisis de operaciones'!C1561:N1561) -> 192.07527 | K98: =MAX('Analisis de operaciones'!C1744:N1744) -> 221.9456
A99: Granallado | B99: =MAX('Analisis de operaciones'!C107:N107) -> 1.9382 | C99: =MAX('Analisis de operaciones'!C290:N290) -> 3.4708667 | D99: =MAX('Analisis de operaciones'!C473:N473) -> 6.0155333 | E99: =MAX('Analisis de operaciones'!C656:N656) -> 11.141533 | F99: =MAX('Analisis de operaciones'!C839:N839) -> 18.9134 | G99: =MAX('Analisis de operaciones'!C1022:N1022) -> 26.5562 | H99: =MAX('Analisis de operaciones'!C1205:N1205) -> 35.805 | I99: =MAX('Analisis de operaciones'!C1388:N1388) -> 45.333933 | J99: =MAX('Analisis de operaciones'!C1571:N1571) -> 51.760867 | K99: =MAX('Analisis de operaciones'!C1754:N1754) -> 59.8488
A100: Detección de defectos (CC) | B100: =MAX('Analisis de operaciones'!C117:N117) -> 5.2814 | C100: =MAX('Analisis de operaciones'!C300:N300) -> 8.2684667 | D100: =MAX('Analisis de operaciones'!C483:N483) -> 17.626733 | E100: =MAX('Analisis de operaciones'!C666:N666) -> 39.271133 | F100: =MAX('Analisis de operaciones'!C849:N849) -> 68.6062 | G100: =MAX('Analisis de operaciones'!C1032:N1032) -> 96.3962 | H100: =MAX('Analisis de operaciones'!C1215:N1215) -> 133.1442 | I100: =MAX('Analisis de operaciones'!C1398:N1398) -> 170.24033 | J100: =MAX('Analisis de operaciones'!C1581:N1581) -> 192.07527 | K100: =MAX('Analisis de operaciones'!C1764:N1764) -> 221.9456
A101: Corrección de defectos | B101: =MAX('Analisis de operaciones'!C1837:N1837) -> 0.26407 | C101: =MAX('Analisis de operaciones'!C1859:N1859) -> 0.41342333 | D101: =MAX('Analisis de operaciones'!C1881:N1881) -> 0.88133667 | E101: =MAX('Analisis de operaciones'!C1903:N1903) -> 1.9635567 | F101: =MAX('Analisis de operaciones'!C1925:N1925) -> 3.43031 | G101: =MAX('Analisis de operaciones'!C1947:N1947) -> 4.81981 | H101: =MAX('Analisis de operaciones'!C1969:N1969) -> 6.65721 | I101: =MAX('Analisis de operaciones'!C1991:N1991) -> 8.5120167 | J101: =MAX('Analisis de operaciones'!C2013:N2013) -> 9.6037633 | K101: =MAX('Analisis de operaciones'!C2035:N2035) -> 11.09728
A102: Pintura + Horno | B102: =MAX('Analisis de operaciones'!C127:N127) -> 5.2814 | C102: =MAX('Analisis de operaciones'!C310:N310) -> 8.2684667 | D102: =MAX('Analisis de operaciones'!C493:N493) -> 17.626733 | E102: =MAX('Analisis de operaciones'!C676:N676) -> 39.271133 | F102: =MAX('Analisis de operaciones'!C859:N859) -> 68.6062 | G102: =MAX('Analisis de operaciones'!C1042:N1042) -> 96.3962 | H102: =MAX('Analisis de operaciones'!C1225:N1225) -> 133.1442 | I102: =MAX('Analisis de operaciones'!C1408:N1408) -> 170.24033 | J102: =MAX('Analisis de operaciones'!C1591:N1591) -> 192.07527 | K102: =MAX('Analisis de operaciones'!C1774:N1774) -> 221.9456
A103: Carga de polvo | B103: =MAX('Analisis de operaciones'!C137:N137) -> 5.499 | C103: =MAX('Analisis de operaciones'!C320:N320) -> 8.6412667 | D103: =MAX('Analisis de operaciones'!C503:N503) -> 10.609733 | E103: =MAX('Analisis de operaciones'!C686:N686) -> 13.7836 | F103: =MAX('Analisis de operaciones'!C869:N869) -> 21.2132 | G103: =MAX('Analisis de operaciones'!C1052:N1052) -> 27.584933 | H103: =MAX('Analisis de operaciones'!C1235:N1235) -> 35.6896 | I103: =MAX('Analisis de operaciones'!C1418:N1418) -> 44.172 | J103: =MAX('Analisis de operaciones'!C1601:N1601) -> 50.878467 | K103: =MAX('Analisis de operaciones'!C1784:N1784) -> 57.905
A104: Ensamblaje | B104: =MAX('Analisis de operaciones'!C147:N147) -> 5.499 | C104: =MAX('Analisis de operaciones'!C330:N330) -> 8.6412667 | D104: =MAX('Analisis de operaciones'!C513:N513) -> 10.609733 | E104: =MAX('Analisis de operaciones'!C696:N696) -> 13.7836 | F104: =MAX('Analisis de operaciones'!C879:N879) -> 21.2132 | G104: =MAX('Analisis de operaciones'!C1062:N1062) -> 27.584933 | H104: =MAX('Analisis de operaciones'!C1245:N1245) -> 35.6896 | I104: =MAX('Analisis de operaciones'!C1428:N1428) -> 44.172 | J104: =MAX('Analisis de operaciones'!C1611:N1611) -> 50.878467 | K104: =MAX('Analisis de operaciones'!C1794:N1794) -> 57.905
A105: Presurización | B105: =MAX('Analisis de operaciones'!C157:N157) -> 5.499 | C105: =MAX('Analisis de operaciones'!C340:N340) -> 8.6412667 | D105: =MAX('Analisis de operaciones'!C523:N523) -> 10.609733 | E105: =MAX('Analisis de operaciones'!C706:N706) -> 13.7836 | F105: =MAX('Analisis de operaciones'!C889:N889) -> 21.2132 | G105: =MAX('Analisis de operaciones'!C1072:N1072) -> 27.584933 | H105: =MAX('Analisis de operaciones'!C1255:N1255) -> 35.6896 | I105: =MAX('Analisis de operaciones'!C1438:N1438) -> 44.172 | J105: =MAX('Analisis de operaciones'!C1621:N1621) -> 50.878467 | K105: =MAX('Analisis de operaciones'!C1804:N1804) -> 57.905
A106: Etiquetado | B106: =MAX('Analisis de operaciones'!C167:N167) -> 5.499 | C106: =MAX('Analisis de operaciones'!C350:N350) -> 8.6412667 | D106: =MAX('Analisis de operaciones'!C533:N533) -> 10.609733 | E106: =MAX('Analisis de operaciones'!C716:N716) -> 13.7836 | F106: =MAX('Analisis de operaciones'!C899:N899) -> 21.2132 | G106: =MAX('Analisis de operaciones'!C1082:N1082) -> 27.584933 | H106: =MAX('Analisis de operaciones'!C1265:N1265) -> 35.6896 | I106: =MAX('Analisis de operaciones'!C1448:N1448) -> 44.172 | J106: =MAX('Analisis de operaciones'!C1631:N1631) -> 50.878467 | K106: =MAX('Analisis de operaciones'!C1814:N1814) -> 57.905
A107: Embalaje y palletizado | B107: =MAX('Analisis de operaciones'!C177:N177) -> 5.2814 | C107: =MAX('Analisis de operaciones'!C360:N360) -> 8.2684667 | D107: =MAX('Analisis de operaciones'!C543:N543) -> 17.626733 | E107: =MAX('Analisis de operaciones'!C726:N726) -> 39.271133 | F107: =MAX('Analisis de operaciones'!C909:N909) -> 68.6062 | G107: =MAX('Analisis de operaciones'!C1092:N1092) -> 96.3962 | H107: =MAX('Analisis de operaciones'!C1275:N1275) -> 133.1442 | I107: =MAX('Analisis de operaciones'!C1458:N1458) -> 170.24033 | J107: =MAX('Analisis de operaciones'!C1641:N1641) -> 192.07527 | K107: =MAX('Analisis de operaciones'!C1824:N1824) -> 221.9456
A108: Cortadora de plasma (1kg) | B108: =MAX('Analisis de operaciones'!C1847:N1847) -> 3.3432 | C108: =MAX('Analisis de operaciones'!C1869:N1869) -> 4.7976 | D108: =MAX('Analisis de operaciones'!C1891:N1891) -> 11.6112 | E108: =MAX('Analisis de operaciones'!C1913:N1913) -> 28.1296 | F108: =MAX('Analisis de operaciones'!C1935:N1935) -> 49.6928 | G108: =MAX('Analisis de operaciones'!C1957:N1957) -> 69.84 | H108: =MAX('Analisis de operaciones'!C1979:N1979) -> 97.3392 | I108: =MAX('Analisis de operaciones'!C2001:N2001) -> 124.9064 | J108: =MAX('Analisis de operaciones'!C2023:N2023) -> 140.3144 | K108: =MAX('Analisis de operaciones'!C2045:N2045) -> 162.0968
A110: Capacidad real por máquina (u/h) | B110: 2026 | C110: 2027 | D110: 2028 | E110: 2029 | F110: 2030 | G110: 2031 | H110: 2032 | I110: 2033 | J110: 2034 | K110: 2035
A111: Preparación de cuello | B111: =Parametros!$M$39 -> 68 | C111: =Parametros!$M$39 -> 68 | D111: =Parametros!$M$39 -> 68 | E111: =Parametros!$M$39 -> 68 | F111: =Parametros!$M$39 -> 68 | G111: =Parametros!$M$39 -> 68 | H111: =Parametros!$M$39 -> 68 | I111: =Parametros!$M$39 -> 68 | ... K111: =Parametros!$M$39 -> 68
A112: Soldadura circunferencial cuello (rosca) | B112: =IF(B55="Automática",Parametros!$M$80,Parametros!$M$40) -> 40.88 | C112: =IF(C55="Automática",Parametros!$M$80,Parametros!$M$40) -> 40.88 | D112: =IF(D55="Automática",Parametros!$M$80,Parametros!$M$40) -> 40.88 | E112: =IF(E55="Automática",Parametros!$M$80,Parametros!$M$40) -> 90.193623 | F112: =IF(F55="Automática",Parametros!$M$80,Parametros!$M$40) -> 90.193623 | G112: =IF(G55="Automática",Parametros!$M$80,Parametros!$M$40) -> 90.193623 | H112: =IF(H55="Automática",Parametros!$M$80,Parametros!$M$40) -> 90.193623 | I112: =IF(I55="Automática",Parametros!$M$80,Parametros!$M$40) -> 90.193623 | ... K112: =IF(K55="Automática",Parametros!$M$80,Parametros!$M$40) -> 90.193623
A113: Corte de disco y embutido (cúpula y fondo) | B113: =Parametros!$M$41 -> 466.51163 | C113: =Parametros!$M$41 -> 466.51163 | D113: =Parametros!$M$41 -> 466.51163 | E113: =Parametros!$M$41 -> 466.51163 | F113: =Parametros!$M$41 -> 466.51163 | G113: =Parametros!$M$41 -> 466.51163 | H113: =Parametros!$M$41 -> 466.51163 | I113: =Parametros!$M$41 -> 466.51163 | ... K113: =Parametros!$M$41 -> 466.51163
A114: Numerado de cuerpo | B114: =Parametros!$M$42 -> 96 | C114: =Parametros!$M$42 -> 96 | D114: =Parametros!$M$42 -> 96 | E114: =Parametros!$M$42 -> 96 | F114: =Parametros!$M$42 -> 96 | G114: =Parametros!$M$42 -> 96 | H114: =Parametros!$M$42 -> 96 | I114: =Parametros!$M$42 -> 96 | ... K114: =Parametros!$M$42 -> 96
...

Sheet Dotacion Planta
A1: DOTACIÓN DE PLANTA — producción 1–10 kg, recargas y línea de carros
A2: Personas = horas-hombre del mes pico ÷ horas por operario. Horas-hombre de un puesto = demanda ÷ cap. real × coef. hombre–máquina. Los carros los hace el plantel de producción (especializado); el de recargas solo hace recargas. Reparto de carros por mes: Parametros fila 70.
A4: PARÁMETROS | B4: Valor
A5: Stock oct–nov para diciembre (1 = sí, 0 = no) | B5: 1
A6: Rendimiento de un operario de producción en recargas | B6: 0.9 | C6: Menos práctica en el puesto.
A7: Ocupación objetivo por operario | B7: =Parametros!$B$67 -> 0.9 | C7: Parametros B67.
A8: Horas por operario al mes (1 turno) | B8: =Parametros!$F$37 -> 150 | C8: Parametros F37 (20 días × 7,5 h).
A9: Horas efectivas por operario (h/mes) | B9: =B8*B7*(1-B14) -> 130.95 | C9: Horas × ocupación × (1 − ausentismo).
A10: Horas extra permitidas por operario (h/mes) | B10: 30 | C10: Dec. 484/00: máx. 30 h/mes.
A11: Horas máximas por operario en el mes pico (h/mes) | B11: =B9+B10 -> 160.95 | C11: Efectivas + extra.
A12: Tope de horas extra por año (h) | B12: 200 | C12: Dec. 484/00: máx. 200 h/año.
A13: Plantel mínimo de producción (arranque) | B13: =Parametros!$B$68 -> 5 | C13: Parametros B68.
A14: Ausentismo (enfermedad, licencias) | B14: 0.03 | C14: Se descuenta de las horas de todos los meses.
A15: Particulares 1 kg que vienen a la tarde (mostrador) | B15: 0.4 | C15: Con 2 turnos el mostrador atiende mañana y tarde: 60 % mañana / 40 % tarde. Con 1 turno, todo a la mañana.
A16: COEFICIENTE HOMBRE–MÁQUINA (horas de operario por hora de máquina; 0,5 = un operario atiende 2 máquinas)
A17: Puesto | B17: Manual | C17: Automática
A18: Preparación de cuello | B18: 1 | C18: —
A19: Soldadura circunferencial cuello (rosca) | B19: 1 | C19: 0.5 | D19: La máquina suelda sola; el operario carga la pieza siguiente.
A20: Corte de disco y embutido (cúpula y fondo) | B20: 1 | C20: —
A21: Numerado de cuerpo | B21: 1 | C21: —
A22: Cilindrado | B22: 1 | C22: —
A23: Soldadura longitudinal | B23: 1 | C23: 0.5 | D23: Ciclo automático; el operario carga el cuerpo siguiente.
A24: Encastre de fondo | B24: 1 | C24: —
A25: Bordoneado | B25: 1 | C25: —
A26: Soldadura circunferencial (cúpula y fondo) | B26: 1 | C26: 0.5 | D26: Gira y suelda sola; 1 operario atiende 2 cabezales.
A27: Prueba hidráulica | B27: 1 | C27: 0.5 | D27: Sostenimiento automático; el operario atiende el secado.
A28: Granallado | B28: 0.5 | C28: — | D28: Ciclo automático; cuelga el lote siguiente.
A29: Detección de defectos (CC) | B29: 1 | C29: —
A30: Corrección de defectos | B30: 1 | C30: —
A31: Pintura + Horno | B31: 0.5 | C31: — | D31: Línea continua; compartido con granallado.
A32: Carga de polvo | B32: 0.5 | C32: — | D32: Dosifica por peso; atiende la presurización.
A33: Ensamblaje | B33: 1 | C33: —
A34: Presurización | B34: 1 | C34: —
A35: Etiquetado | B35: 1 | C35: —
A36: Embalaje y palletizado | B36: 1 | C36: —
A37: Cortadora de plasma (1kg) | B37: 0.5 | C37: — | D37: CNC; el operario descarga y atiende otro puesto.
A38: Carros — cilindrado de chapa | B38: 1 | C38: —
A39: Carros — punteo, refuerzo y estructura del carro | B39: 1 | C39: —
A40: Carros — soldadura longitudinal | B40: 0.5 | C40: —
A41: Carros — soldadura circunferencial fondo y cúpula | B41: 0.5 | C41: — | D41: preguntar si es por tiempo o por actividad
A42: Carros — inspección de costuras int. y ext. | B42: 1 | C42: —
A43: Carros — prueba hidráulica (IRAM 3550, 4,0 MPa) | B43: 0.5 | C43: —
A44: Carros — marcado del recipiente | B44: 1 | C44: —
A45: Carros — probetas de soldadura | B45: 1 | C45: —
A48: VACACIONES — LCT art. 150: 14 días corridos hasta 5 años de antigüedad, 21 hasta 10, 28 hasta 20 (antigüedad al 31/12) | G48: LCT (art. 154) pide dar las vacaciones entre el 1 de octubre y el 30 de abril, salvo autorización por la característica de la actividad.
A49: Días hábiles por cada día corrido de vacaciones | B49: =5/7 -> 0.71428571 | C49: 5 días hábiles por semana. | G49: Pedir autorización para dar parte de las vacaciones fuera de la ventana. El mismo art. 154 permite que la autoridad de aplicación autorice otros períodos cuando lo requiere la característica de la actividad.
A50: Horas por día hábil | B50: =Parametros!$J$37 -> 7.5
A52: Distribución de las vacaciones en el año (%) | B52: Ene | C52: Feb | D52: Mar | E52: Abr | F52: May | G52: Jun | H52: Jul | I52: Ago | J52: Sep | K52: Oct | L52: Nov | M52: Dic | N52: Total
A53: Producción (turno mañana y tarde) | B53: 0 | C53: 0.15 | D53: 0.2 | E53: 0.2 | F53: 0 | G53: 0 | H53: 0.25 | I53: 0 | J53: 0 | K53: 0.1 | L53: 0.1 | M53: 0 | N53: =SUM(B53:M53) -> 1
A54: Recargas | B54: 0 | C54: 0.15 | D54: 0.15 | E54: 0.15 | F54: 0 | G54: 0 | H54: 0.25 | I54: 0 | J54: 0 | K54: 0.15 | L54: 0.15 | M54: 0 | N54: =SUM(B54:M54) -> 1
A55: Oficinas y encargados | B55: 0 | C55: 0.25 | D55: 0.15 | E55: 0.1 | F55: 0 | G55: 0 | H55: 0.3 | I55: 0 | J55: 0 | K55: 0.1 | L55: 0.1 | M55: 0 | N55: =SUM(B55:M55) -> 1
A56: Oct–abr según LCT art. 154; julio con autorización de la autoridad de aplicación (art. 154). Dic–ene no: es el pico. Supuesto: cada uno ingresa el 1/1 del año en que aparece y no hay bajas.
A58: Días por persona: año (fila) × año de ingreso (columna) | B58: 2026 | C58: 2027 | D58: 2028 | E58: 2029 | F58: 2030 | G58: 2031 | H58: 2032 | I58: 2033 | J58: 2034 | K58: 2035
A59: 2026 | B59: =IF(B$58>$A59,0,IF($A59-B$58+1<=5,14,IF($A59-B$58+1<=10,21,28))) -> 14 | C59: =IF(C$58>$A59,0,IF($A59-C$58+1<=5,14,IF($A59-C$58+1<=10,21,28))) -> 0 | D59: =IF(D$58>$A59,0,IF($A59-D$58+1<=5,14,IF($A59-D$58+1<=10,21,28))) -> 0 | E59: =IF(E$58>$A59,0,IF($A59-E$58+1<=5,14,IF($A59-E$58+1<=10,21,28))) -> 0 | F59: =IF(F$58>$A59,0,IF($A59-F$58+1<=5,14,IF($A59-F$58+1<=10,21,28))) -> 0 | G59: =IF(G$58>$A59,0,IF($A59-G$58+1<=5,14,IF($A59-G$58+1<=10,21,28))) -> 0 | H59: =IF(H$58>$A59,0,IF($A59-H$58+1<=5,14,IF($A59-H$58+1<=10,21,28))) -> 0 | I59: =IF(I$58>$A59,0,IF($A59-I$58+1<=5,14,IF($A59-I$58+1<=10,21,28))) -> 0 | ... K59: =IF(K$58>$A59,0,IF($A59-K$58+1<=5,14,IF($A59-K$58+1<=10,21,28))) -> 0
A60: 2027 | B60: =IF(B$58>$A60,0,IF($A60-B$58+1<=5,14,IF($A60-B$58+1<=10,21,28))) -> 14 | C60: =IF(C$58>$A60,0,IF($A60-C$58+1<=5,14,IF($A60-C$58+1<=10,21,28))) -> 14 | D60: =IF(D$58>$A60,0,IF($A60-D$58+1<=5,14,IF($A60-D$58+1<=10,21,28))) -> 0 | E60: =IF(E$58>$A60,0,IF($A60-E$58+1<=5,14,IF($A60-E$58+1<=10,21,28))) -> 0 | F60: =IF(F$58>$A60,0,IF($A60-F$58+1<=5,14,IF($A60-F$58+1<=10,21,28))) -> 0 | G60: =IF(G$58>$A60,0,IF($A60-G$58+1<=5,14,IF($A60-G$58+1<=10,21,28))) -> 0 | H60: =IF(H$58>$A60,0,IF($A60-H$58+1<=5,14,IF($A60-H$58+1<=10,21,28))) -> 0 | I60: =IF(I$58>$A60,0,IF($A60-I$58+1<=5,14,IF($A60-I$58+1<=10,21,28))) -> 0 | ... K60: =IF(K$58>$A60,0,IF($A60-K$58+1<=5,14,IF($A60-K$58+1<=10,21,28))) -> 0
A61: 2028 | B61: =IF(B$58>$A61,0,IF($A61-B$58+1<=5,14,IF($A61-B$58+1<=10,21,28))) -> 14 | C61: =IF(C$58>$A61,0,IF($A61-C$58+1<=5,14,IF($A61-C$58+1<=10,21,28))) -> 14 | D61: =IF(D$58>$A61,0,IF($A61-D$58+1<=5,14,IF($A61-D$58+1<=10,21,28))) -> 14 | E61: =IF(E$58>$A61,0,IF($A61-E$58+1<=5,14,IF($A61-E$58+1<=10,21,28))) -> 0 | F61: =IF(F$58>$A61,0,IF($A61-F$58+1<=5,14,IF($A61-F$58+1<=10,21,28))) -> 0 | G61: =IF(G$58>$A61,0,IF($A61-G$58+1<=5,14,IF($A61-G$58+1<=10,21,28))) -> 0 | H61: =IF(H$58>$A61,0,IF($A61-H$58+1<=5,14,IF($A61-H$58+1<=10,21,28))) -> 0 | I61: =IF(I$58>$A61,0,IF($A61-I$58+1<=5,14,IF($A61-I$58+1<=10,21,28))) -> 0 | ... K61: =IF(K$58>$A61,0,IF($A61-K$58+1<=5,14,IF($A61-K$58+1<=10,21,28))) -> 0
A62: 2029 | B62: =IF(B$58>$A62,0,IF($A62-B$58+1<=5,14,IF($A62-B$58+1<=10,21,28))) -> 14 | C62: =IF(C$58>$A62,0,IF($A62-C$58+1<=5,14,IF($A62-C$58+1<=10,21,28))) -> 14 | D62: =IF(D$58>$A62,0,IF($A62-D$58+1<=5,14,IF($A62-D$58+1<=10,21,28))) -> 14 | E62: =IF(E$58>$A62,0,IF($A62-E$58+1<=5,14,IF($A62-E$58+1<=10,21,28))) -> 14 | F62: =IF(F$58>$A62,0,IF($A62-F$58+1<=5,14,IF($A62-F$58+1<=10,21,28))) -> 0 | G62: =IF(G$58>$A62,0,IF($A62-G$58+1<=5,14,IF($A62-G$58+1<=10,21,28))) -> 0 | H62: =IF(H$58>$A62,0,IF($A62-H$58+1<=5,14,IF($A62-H$58+1<=10,21,28))) -> 0 | I62: =IF(I$58>$A62,0,IF($A62-I$58+1<=5,14,IF($A62-I$58+1<=10,21,28))) -> 0 | ... K62: =IF(K$58>$A62,0,IF($A62-K$58+1<=5,14,IF($A62-K$58+1<=10,21,28))) -> 0
A63: 2030 | B63: =IF(B$58>$A63,0,IF($A63-B$58+1<=5,14,IF($A63-B$58+1<=10,21,28))) -> 14 | C63: =IF(C$58>$A63,0,IF($A63-C$58+1<=5,14,IF($A63-C$58+1<=10,21,28))) -> 14 | D63: =IF(D$58>$A63,0,IF($A63-D$58+1<=5,14,IF($A63-D$58+1<=10,21,28))) -> 14 | E63: =IF(E$58>$A63,0,IF($A63-E$58+1<=5,14,IF($A63-E$58+1<=10,21,28))) -> 14 | F63: =IF(F$58>$A63,0,IF($A63-F$58+1<=5,14,IF($A63-F$58+1<=10,21,28))) -> 14 | G63: =IF(G$58>$A63,0,IF($A63-G$58+1<=5,14,IF($A63-G$58+1<=10,21,28))) -> 0 | H63: =IF(H$58>$A63,0,IF($A63-H$58+1<=5,14,IF($A63-H$58+1<=10,21,28))) -> 0 | I63: =IF(I$58>$A63,0,IF($A63-I$58+1<=5,14,IF($A63-I$58+1<=10,21,28))) -> 0 | ... K63: =IF(K$58>$A63,0,IF($A63-K$58+1<=5,14,IF($A63-K$58+1<=10,21,28))) -> 0
A64: 2031 | B64: =IF(B$58>$A64,0,IF($A64-B$58+1<=5,14,IF($A64-B$58+1<=10,21,28))) -> 21 | C64: =IF(C$58>$A64,0,IF($A64-C$58+1<=5,14,IF($A64-C$58+1<=10,21,28))) -> 14 | D64: =IF(D$58>$A64,0,IF($A64-D$58+1<=5,14,IF($A64-D$58+1<=10,21,28))) -> 14 | E64: =IF(E$58>$A64,0,IF($A64-E$58+1<=5,14,IF($A64-E$58+1<=10,21,28))) -> 14 | F64: =IF(F$58>$A64,0,IF($A64-F$58+1<=5,14,IF($A64-F$58+1<=10,21,28))) -> 14 | G64: =IF(G$58>$A64,0,IF($A64-G$58+1<=5,14,IF($A64-G$58+1<=10,21,28))) -> 14 | H64: =IF(H$58>$A64,0,IF($A64-H$58+1<=5,14,IF($A64-H$58+1<=10,21,28))) -> 0 | I64: =IF(I$58>$A64,0,IF($A64-I$58+1<=5,14,IF($A64-I$58+1<=10,21,28))) -> 0 | ... K64: =IF(K$58>$A64,0,IF($A64-K$58+1<=5,14,IF($A64-K$58+1<=10,21,28))) -> 0
A65: 2032 | B65: =IF(B$58>$A65,0,IF($A65-B$58+1<=5,14,IF($A65-B$58+1<=10,21,28))) -> 21 | C65: =IF(C$58>$A65,0,IF($A65-C$58+1<=5,14,IF($A65-C$58+1<=10,21,28))) -> 21 | D65: =IF(D$58>$A65,0,IF($A65-D$58+1<=5,14,IF($A65-D$58+1<=10,21,28))) -> 14 | E65: =IF(E$58>$A65,0,IF($A65-E$58+1<=5,14,IF($A65-E$58+1<=10,21,28))) -> 14 | F65: =IF(F$58>$A65,0,IF($A65-F$58+1<=5,14,IF($A65-F$58+1<=10,21,28))) -> 14 | G65: =IF(G$58>$A65,0,IF($A65-G$58+1<=5,14,IF($A65-G$58+1<=10,21,28))) -> 14 | H65: =IF(H$58>$A65,0,IF($A65-H$58+1<=5,14,IF($A65-H$58+1<=10,21,28))) -> 14 | I65: =IF(I$58>$A65,0,IF($A65-I$58+1<=5,14,IF($A65-I$58+1<=10,21,28))) -> 0 | ... K65: =IF(K$58>$A65,0,IF($A65-K$58+1<=5,14,IF($A65-K$58+1<=10,21,28))) -> 0
A66: 2033 | B66: =IF(B$58>$A66,0,IF($A66-B$58+1<=5,14,IF($A66-B$58+1<=10,21,28))) -> 21 | C66: =IF(C$58>$A66,0,IF($A66-C$58+1<=5,14,IF($A66-C$58+1<=10,21,28))) -> 21 | D66: =IF(D$58>$A66,0,IF($A66-D$58+1<=5,14,IF($A66-D$58+1<=10,21,28))) -> 21 | E66: =IF(E$58>$A66,0,IF($A66-E$58+1<=5,14,IF($A66-E$58+1<=10,21,28))) -> 14 | F66: =IF(F$58>$A66,0,IF($A66-F$58+1<=5,14,IF($A66-F$58+1<=10,21,28))) -> 14 | G66: =IF(G$58>$A66,0,IF($A66-G$58+1<=5,14,IF($A66-G$58+1<=10,21,28))) -> 14 | H66: =IF(H$58>$A66,0,IF($A66-H$58+1<=5,14,IF($A66-H$58+1<=10,21,28))) -> 14 | I66: =IF(I$58>$A66,0,IF($A66-I$58+1<=5,14,IF($A66-I$58+1<=10,21,28))) -> 14 | ... K66: =IF(K$58>$A66,0,IF($A66-K$58+1<=5,14,IF($A66-K$58+1<=10,21,28))) -> 0
A67: 2034 | B67: =IF(B$58>$A67,0,IF($A67-B$58+1<=5,14,IF($A67-B$58+1<=10,21,28))) -> 21 | C67: =IF(C$58>$A67,0,IF($A67-C$58+1<=5,14,IF($A67-C$58+1<=10,21,28))) -> 21 | D67: =IF(D$58>$A67,0,IF($A67-D$58+1<=5,14,IF($A67-D$58+1<=10,21,28))) -> 21 | E67: =IF(E$58>$A67,0,IF($A67-E$58+1<=5,14,IF($A67-E$58+1<=10,21,28))) -> 21 | F67: =IF(F$58>$A67,0,IF($A67-F$58+1<=5,14,IF($A67-F$58+1<=10,21,28))) -> 14 | G67: =IF(G$58>$A67,0,IF($A67-G$58+1<=5,14,IF($A67-G$58+1<=10,21,28))) -> 14 | H67: =IF(H$58>$A67,0,IF($A67-H$58+1<=5,14,IF($A67-H$58+1<=10,21,28))) -> 14 | I67: =IF(I$58>$A67,0,IF($A67-I$58+1<=5,14,IF($A67-I$58+1<=10,21,28))) -> 14 | ... K67: =IF(K$58>$A67,0,IF($A67-K$58+1<=5,14,IF($A67-K$58+1<=10,21,28))) -> 0
A68: 2035 | B68: =IF(B$58>$A68,0,IF($A68-B$58+1<=5,14,IF($A68-B$58+1<=10,21,28))) -> 21 | C68: =IF(C$58>$A68,0,IF($A68-C$58+1<=5,14,IF($A68-C$58+1<=10,21,28))) -> 21 | D68: =IF(D$58>$A68,0,IF($A68-D$58+1<=5,14,IF($A68-D$58+1<=10,21,28))) -> 21 | E68: =IF(E$58>$A68,0,IF($A68-E$58+1<=5,14,IF($A68-E$58+1<=10,21,28))) -> 21 | F68: =IF(F$58>$A68,0,IF($A68-F$58+1<=5,14,IF($A68-F$58+1<=10,21,28))) -> 21 | G68: =IF(G$58>$A68,0,IF($A68-G$58+1<=5,14,IF($A68-G$58+1<=10,21,28))) -> 14 | H68: =IF(H$58>$A68,0,IF($A68-H$58+1<=5,14,IF($A68-H$58+1<=10,21,28))) -> 14 | I68: =IF(I$58>$A68,0,IF($A68-I$58+1<=5,14,IF($A68-I$58+1<=10,21,28))) -> 14 | ... K68: =IF(K$58>$A68,0,IF($A68-K$58+1<=5,14,IF($A68-K$58+1<=10,21,28))) -> 14
A70: Vacaciones por grupo | B70: 2026 | C70: 2027 | D70: 2028 | E70: 2029 | F70: 2030 | G70: 2031 | H70: 2032 | I70: 2033 | J70: 2034 | K70: 2035
A71: Producción 1–10 kg y carros, turno mañana — personas | B71: =B102 -> 5 | C71: =C102 -> 5 | D71: =D102 -> 5 | E71: =E102 -> 6 | F71: =F102 -> 10 | G71: =G102 -> 14 | H71: =H102 -> 18 | I71: =I102 -> 23 | ... K71: =K102 -> 30
A72: Producción 1–10 kg y carros, turno mañana — ingresan en el año | B72: =B71 -> 5 | C72: =MAX(0,C71-B71) -> 0 | D72: =MAX(0,D71-C71) -> 0 | E72: =MAX(0,E71-D71) -> 1 | F72: =MAX(0,F71-E71) -> 4 | G72: =MAX(0,G71-F71) -> 4 | H72: =MAX(0,H71-G71) -> 4 | I72: =MAX(0,I71-H71) -> 5 | J72: =MAX(0,J71-I71) -> 3 | K72: =MAX(0,K71-J71) -> 4
A73: Producción 1–10 kg y carros, turno mañana — días de vacaciones | B73: =SUMPRODUCT($B72:$K72,$B59:$K59) -> 70 | C73: =SUMPRODUCT($B72:$K72,$B60:$K60) -> 70 | D73: =SUMPRODUCT($B72:$K72,$B61:$K61) -> 70 | E73: =SUMPRODUCT($B72:$K72,$B62:$K62) -> 84 | F73: =SUMPRODUCT($B72:$K72,$B63:$K63) -> 140 | G73: =SUMPRODUCT($B72:$K72,$B64:$K64) -> 231 | H73: =SUMPRODUCT($B72:$K72,$B65:$K65) -> 287 | I73: =SUMPRODUCT($B72:$K72,$B66:$K66) -> 357 | J73: =SUMPRODUCT($B72:$K72,$B67:$K67) -> 406 | K73: =SUMPRODUCT($B72:$K72,$B68:$K68) -> 490
A74: Producción 1–10 kg y carros, turno mañana — horas de vacaciones (h) | B74: =B73*$B$49*$B$50 -> 375 | C74: =C73*$B$49*$B$50 -> 375 | D74: =D73*$B$49*$B$50 -> 375 | E74: =E73*$B$49*$B$50 -> 450 | F74: =F73*$B$49*$B$50 -> 750 | G74: =G73*$B$49*$B$50 -> 1237.5 | H74: =H73*$B$49*$B$50 -> 1537.5 | I74: =I73*$B$49*$B$50 -> 1912.5 | ... K74: =K73*$B$49*$B$50 -> 2625
A75: Turno tarde — personas | B75: =B104 -> 0 | C75: =C104 -> 0 | D75: =D104 -> 0 | E75: =E104 -> 0 | F75: =F104 -> 0 | G75: =G104 -> 0 | H75: =H104 -> 1 | I75: =I104 -> 2 | ... K75: =K104 -> 6
A76: Turno tarde — ingresan en el año | B76: =B75 -> 0 | C76: =MAX(0,C75-B75) -> 0 | D76: =MAX(0,D75-C75) -> 0 | E76: =MAX(0,E75-D75) -> 0 | F76: =MAX(0,F75-E75) -> 0 | G76: =MAX(0,G75-F75) -> 0 | H76: =MAX(0,H75-G75) -> 1 | I76: =MAX(0,I75-H75) -> 1 | J76: =MAX(0,J75-I75) -> 2 | K76: =MAX(0,K75-J75) -> 2
A77: Turno tarde — días de vacaciones | B77: =SUMPRODUCT($B76:$K76,$B59:$K59) -> 0 | C77: =SUMPRODUCT($B76:$K76,$B60:$K60) -> 0 | D77: =SUMPRODUCT($B76:$K76,$B61:$K61) -> 0 | E77: =SUMPRODUCT($B76:$K76,$B62:$K62) -> 0 | F77: =SUMPRODUCT($B76:$K76,$B63:$K63) -> 0 | G77: =SUMPRODUCT($B76:$K76,$B64:$K64) -> 0 | H77: =SUMPRODUCT($B76:$K76,$B65:$K65) -> 14 | I77: =SUMPRODUCT($B76:$K76,$B66:$K66) -> 28 | J77: =SUMPRODUCT($B76:$K76,$B67:$K67) -> 56 | K77: =SUMPRODUCT($B76:$K76,$B68:$K68) -> 84
A78: Turno tarde — horas de vacaciones (h) | B78: =B77*$B$49*$B$50 -> 0 | C78: =C77*$B$49*$B$50 -> 0 | D78: =D77*$B$49*$B$50 -> 0 | E78: =E77*$B$49*$B$50 -> 0 | F78: =F77*$B$49*$B$50 -> 0 | G78: =G77*$B$49*$B$50 -> 0 | H78: =H77*$B$49*$B$50 -> 75 | I78: =I77*$B$49*$B$50 -> 150 | ... K78: =K77*$B$49*$B$50 -> 450
A79: Recargas — personas | B79: =B103 -> 0 | C79: =C103 -> 2 | D79: =D103 -> 3 | E79: =E103 -> 6 | F79: =F103 -> 9 | G79: =G103 -> 12 | H79: =H103 -> 14 | I79: =I103 -> 16 | ... K79: =K103 -> 16
A80: Recargas — ingresan en el año | B80: =B79 -> 0 | C80: =MAX(0,C79-B79) -> 2 | D80: =MAX(0,D79-C79) -> 1 | E80: =MAX(0,E79-D79) -> 3 | F80: =MAX(0,F79-E79) -> 3 | G80: =MAX(0,G79-F79) -> 3 | H80: =MAX(0,H79-G79) -> 2 | I80: =MAX(0,I79-H79) -> 2 | J80: =MAX(0,J79-I79) -> 0 | K80: =MAX(0,K79-J79) -> 0
A81: Recargas — días de vacaciones | B81: =SUMPRODUCT($B80:$K80,$B59:$K59) -> 0 | C81: =SUMPRODUCT($B80:$K80,$B60:$K60) -> 28 | D81: =SUMPRODUCT($B80:$K80,$B61:$K61) -> 42 | E81: =SUMPRODUCT($B80:$K80,$B62:$K62) -> 84 | F81: =SUMPRODUCT($B80:$K80,$B63:$K63) -> 126 | G81: =SUMPRODUCT($B80:$K80,$B64:$K64) -> 168 | H81: =SUMPRODUCT($B80:$K80,$B65:$K65) -> 210 | I81: =SUMPRODUCT($B80:$K80,$B66:$K66) -> 245 | J81: =SUMPRODUCT($B80:$K80,$B67:$K67) -> 266 | K81: =SUMPRODUCT($B80:$K80,$B68:$K68) -> 287
A82: Recargas — horas de vacaciones (h) | B82: =B81*$B$49*$B$50 -> 0 | C82: =C81*$B$49*$B$50 -> 150 | D82: =D81*$B$49*$B$50 -> 225 | E82: =E81*$B$49*$B$50 -> 450 | F82: =F81*$B$49*$B$50 -> 675 | G82: =G81*$B$49*$B$50 -> 900 | H82: =H81*$B$49*$B$50 -> 1125 | I82: =I81*$B$49*$B$50 -> 1312.5 | ... K82: =K81*$B$49*$B$50 -> 1537.5
A83: Recargas turno tarde — personas | B83: =B105 -> 0 | C83: =C105 -> 0 | D83: =D105 -> 0 | E83: =E105 -> 0 | F83: =F105 -> 0 | G83: =G105 -> 0 | H83: =H105 -> 2 | I83: =I105 -> 2 | ... K83: =K105 -> 2
A84: Recargas turno tarde — ingresan en el año | B84: =B83 -> 0 | C84: =MAX(0,C83-B83) -> 0 | D84: =MAX(0,D83-C83) -> 0 | E84: =MAX(0,E83-D83) -> 0 | F84: =MAX(0,F83-E83) -> 0 | G84: =MAX(0,G83-F83) -> 0 | H84: =MAX(0,H83-G83) -> 2 | I84: =MAX(0,I83-H83) -> 0 | J84: =MAX(0,J83-I83) -> 0 | K84: =MAX(0,K83-J83) -> 0
A85: Recargas turno tarde — días de vacaciones | B85: =SUMPRODUCT($B84:$K84,$B59:$K59) -> 0 | C85: =SUMPRODUCT($B84:$K84,$B60:$K60) -> 0 | D85: =SUMPRODUCT($B84:$K84,$B61:$K61) -> 0 | E85: =SUMPRODUCT($B84:$K84,$B62:$K62) -> 0 | F85: =SUMPRODUCT($B84:$K84,$B63:$K63) -> 0 | G85: =SUMPRODUCT($B84:$K84,$B64:$K64) -> 0 | H85: =SUMPRODUCT($B84:$K84,$B65:$K65) -> 28 | I85: =SUMPRODUCT($B84:$K84,$B66:$K66) -> 28 | J85: =SUMPRODUCT($B84:$K84,$B67:$K67) -> 28 | K85: =SUMPRODUCT($B84:$K84,$B68:$K68) -> 28
A86: Recargas turno tarde — horas de vacaciones (h) | B86: =B85*$B$49*$B$50 -> 0 | C86: =C85*$B$49*$B$50 -> 0 | D86: =D85*$B$49*$B$50 -> 0 | E86: =E85*$B$49*$B$50 -> 0 | F86: =F85*$B$49*$B$50 -> 0 | G86: =G85*$B$49*$B$50 -> 0 | H86: =H85*$B$49*$B$50 -> 150 | I86: =I85*$B$49*$B$50 -> 150 | ... K86: =K85*$B$49*$B$50 -> 150
A87: Encargados — personas | B87: =B106 -> 1 | C87: =C106 -> 1 | D87: =D106 -> 1 | E87: =E106 -> 1 | F87: =F106 -> 1 | G87: =G106 -> 1 | H87: =H106 -> 2 | I87: =I106 -> 2 | ... K87: =K106 -> 2
A88: Encargados — ingresan en el año | B88: =B87 -> 1 | C88: =MAX(0,C87-B87) -> 0 | D88: =MAX(0,D87-C87) -> 0 | E88: =MAX(0,E87-D87) -> 0 | F88: =MAX(0,F87-E87) -> 0 | G88: =MAX(0,G87-F87) -> 0 | H88: =MAX(0,H87-G87) -> 1 | I88: =MAX(0,I87-H87) -> 0 | J88: =MAX(0,J87-I87) -> 0 | K88: =MAX(0,K87-J87) -> 0
A89: Encargados — días de vacaciones | B89: =SUMPRODUCT($B88:$K88,$B59:$K59) -> 14 | C89: =SUMPRODUCT($B88:$K88,$B60:$K60) -> 14 | D89: =SUMPRODUCT($B88:$K88,$B61:$K61) -> 14 | E89: =SUMPRODUCT($B88:$K88,$B62:$K62) -> 14 | F89: =SUMPRODUCT($B88:$K88,$B63:$K63) -> 14 | G89: =SUMPRODUCT($B88:$K88,$B64:$K64) -> 21 | H89: =SUMPRODUCT($B88:$K88,$B65:$K65) -> 35 | I89: =SUMPRODUCT($B88:$K88,$B66:$K66) -> 35 | J89: =SUMPRODUCT($B88:$K88,$B67:$K67) -> 35 | K89: =SUMPRODUCT($B88:$K88,$B68:$K68) -> 35
A90: Encargados — horas de vacaciones (h) | B90: =B89*$B$49*$B$50 -> 75 | C90: =C89*$B$49*$B$50 -> 75 | D90: =D89*$B$49*$B$50 -> 75 | E90: =E89*$B$49*$B$50 -> 75 | F90: =F89*$B$49*$B$50 -> 75 | G90: =G89*$B$49*$B$50 -> 112.5 | H90: =H89*$B$49*$B$50 -> 187.5 | I90: =I89*$B$49*$B$50 -> 187.5 | ... K90: =K89*$B$49*$B$50 -> 187.5
A91: Administración — personas | B91: ='Servicios y Oficinas'!B29+'Servicios y Oficinas'!B30 -> 4 | C91: ='Servicios y Oficinas'!C29+'Servicios y Oficinas'!C30 -> 4 | D91: ='Servicios y Oficinas'!D29+'Servicios y Oficinas'!D30 -> 5 | E91: ='Servicios y Oficinas'!E29+'Servicios y Oficinas'!E30 -> 5 | F91: ='Servicios y Oficinas'!F29+'Servicios y Oficinas'!F30 -> 6 | G91: ='Servicios y Oficinas'!G29+'Servicios y Oficinas'!G30 -> 6 | H91: ='Servicios y Oficinas'!H29+'Servicios y Oficinas'!H30 -> 7 | I91: ='Servicios y Oficinas'!I29+'Servicios y Oficinas'!I30 -> 7 | ... K91: ='Servicios y Oficinas'!K29+'Servicios y Oficinas'!K30 -> 7
A92: Administración — ingresan en el año | B92: =B91 -> 4 | C92: =MAX(0,C91-B91) -> 0 | D92: =MAX(0,D91-C91) -> 1 | E92: =MAX(0,E91-D91) -> 0 | F92: =MAX(0,F91-E91) -> 1 | G92: =MAX(0,G91-F91) -> 0 | H92: =MAX(0,H91-G91) -> 1 | I92: =MAX(0,I91-H91) -> 0 | J92: =MAX(0,J91-I91) -> 0 | K92: =MAX(0,K91-J91) -> 0
A93: Administración — días de vacaciones | B93: =SUMPRODUCT($B92:$K92,$B59:$K59) -> 56 | C93: =SUMPRODUCT($B92:$K92,$B60:$K60) -> 56 | D93: =SUMPRODUCT($B92:$K92,$B61:$K61) -> 70 | E93: =SUMPRODUCT($B92:$K92,$B62:$K62) -> 70 | F93: =SUMPRODUCT($B92:$K92,$B63:$K63) -> 84 | G93: =SUMPRODUCT($B92:$K92,$B64:$K64) -> 112 | H93: =SUMPRODUCT($B92:$K92,$B65:$K65) -> 126 | I93: =SUMPRODUCT($B92:$K92,$B66:$K66) -> 133 | J93: =SUMPRODUCT($B92:$K92,$B67:$K67) -> 133 | K93: =SUMPRODUCT($B92:$K92,$B68:$K68) -> 140
A94: Administración — horas de vacaciones (h) | B94: =B93*$B$49*$B$50 -> 300 | C94: =C93*$B$49*$B$50 -> 300 | D94: =D93*$B$49*$B$50 -> 375 | E94: =E93*$B$49*$B$50 -> 375 | F94: =F93*$B$49*$B$50 -> 450 | G94: =G93*$B$49*$B$50 -> 600 | H94: =H93*$B$49*$B$50 -> 675 | I94: =I93*$B$49*$B$50 -> 712.5 | ... K94: =K93*$B$49*$B$50 -> 750
A95: TOTAL personas (planta + administración) | B95: =B71+B75+B79+B83+B87+B91 -> 10 | C95: =C71+C75+C79+C83+C87+C91 -> 12 | D95: =D71+D75+D79+D83+D87+D91 -> 14 | E95: =E71+E75+E79+E83+E87+E91 -> 18 | F95: =F71+F75+F79+F83+F87+F91 -> 26 | G95: =G71+G75+G79+G83+G87+G91 -> 33 | H95: =H71+H75+H79+H83+H87+H91 -> 44 | I95: =I71+I75+I79+I83+I87+I91 -> 52 | ... K95: =K71+K75+K79+K83+K87+K91 -> 63
A96: TOTAL días de vacaciones en el año | B96: =B73+B77+B81+B85+B89+B93 -> 140 | C96: =C73+C77+C81+C85+C89+C93 -> 168 | D96: =D73+D77+D81+D85+D89+D93 -> 196 | E96: =E73+E77+E81+E85+E89+E93 -> 252 | F96: =F73+F77+F81+F85+F89+F93 -> 364 | G96: =G73+G77+G81+G85+G89+G93 -> 532 | H96: =H73+H77+H81+H85+H89+H93 -> 700 | I96: =I73+I77+I81+I85+I89+I93 -> 826 | ... K96: =K73+K77+K81+K85+K89+K93 -> 1064
A97: Días de vacaciones promedio por persona | B97: =IFERROR(B96/B95,0) -> 14 | C97: =IFERROR(C96/C95,0) -> 14 | D97: =IFERROR(D96/D95,0) -> 14 | E97: =IFERROR(E96/E95,0) -> 14 | F97: =IFERROR(F96/F95,0) -> 14 | G97: =IFERROR(G96/G95,0) -> 16.121212 | H97: =IFERROR(H96/H95,0) -> 15.909091 | I97: =IFERROR(I96/I95,0) -> 15.884615 | ... K97: =IFERROR(K96/K95,0) -> 16.888889
A100: RESUMEN POR AÑO | B100: 2026 | C100: 2027 | D100: 2028 | E100: 2029 | F100: 2030 | G100: 2031 | H100: 2032 | I100: 2033 | J100: 2034 | K100: 2035
A101: Turnos de planta | B101: =B116 -> 1 | C101: =B209 -> 1 | D101: =B302 -> 1 | E101: =B395 -> 1 | F101: =B488 -> 1 | G101: =B581 -> 1 | H101: =B674 -> 2 | I101: =B767 -> 2 | J101: =B860 -> 2 | K101: =B953 -> 2
A102: Producción 1–10 kg y carros — operarios turno mañana | B102: =B118 -> 5 | C102: =B211 -> 5 | D102: =B304 -> 5 | E102: =B397 -> 6 | F102: =B490 -> 10 | G102: =B583 -> 14 | H102: =B676 -> 18 | I102: =B769 -> 23 | J102: =B862 -> 26 | K102: =B955 -> 30
A103: Recargas — operarios propios turno mañana | B103: =B120 -> 0 | C103: =B213 -> 2 | D103: =B306 -> 3 | E103: =B399 -> 6 | F103: =B492 -> 9 | G103: =B585 -> 12 | H103: =B678 -> 14 | I103: =B771 -> 16 | J103: =B864 -> 16 | K103: =B957 -> 16
A104: Turno tarde — operarios (producción + recargas) | B104: =B119 -> 0 | C104: =B212 -> 0 | D104: =B305 -> 0 | E104: =B398 -> 0 | F104: =B491 -> 0 | G104: =B584 -> 0 | H104: =B677 -> 1 | I104: =B770 -> 2 | J104: =B863 -> 4 | K104: =B956 -> 6
A105: Recargas — operarios turno tarde (mostrador + recargas) | B105: =B121 -> 0 | C105: =B214 -> 0 | D105: =B307 -> 0 | E105: =B400 -> 0 | F105: =B493 -> 0 | G105: =B586 -> 0 | H105: =B679 -> 2 | I105: =B772 -> 2 | J105: =B865 -> 2 | K105: =B958 -> 2
A106: Encargados (1 por turno) | B106: =B116 -> 1 | C106: =B209 -> 1 | D106: =B302 -> 1 | E106: =B395 -> 1 | F106: =B488 -> 1 | G106: =B581 -> 1 | H106: =B674 -> 2 | I106: =B767 -> 2 | J106: =B860 -> 2 | K106: =B953 -> 2
A107: TOTAL DOTACIÓN PLANTA | B107: =SUM(B102:B106) -> 6 | C107: =SUM(C102:C106) -> 8 | D107: =SUM(D102:D106) -> 9 | E107: =SUM(E102:E106) -> 13 | F107: =SUM(F102:F106) -> 20 | G107: =SUM(G102:G106) -> 27 | H107: =SUM(H102:H106) -> 37 | I107: =SUM(I102:I106) -> 45 | ... K107: =SUM(K102:K106) -> 56
A108: Horas extra en el año (h) | B108: =N152 -> 0 | C108: =N245 -> 0 | D108: =N338 -> 108.58658 | E108: =N431 -> 416.18234 | F108: =N524 -> 609.86031 | G108: =N617 -> 996.58145 | H108: =N710 -> 1305.7166 | I108: =N803 -> 1217.5288 | J108: =N896 -> 1217.4981 | K108: =N989 -> 1180.838
...

Sheet Analisis Recargas
A1: ANÁLISIS DE CAPACIDAD — RECARGAS PLANTA INDUSTRIAL
A2: Horas por mes de 1 turno (Parametros Recargas F4) | B2: ='Parametros Recargas'!$F$4 -> 150 | D2: Carga (u/h) = Σ (demanda de la familia × % que pasa por el puesto) ÷ horas del mes. N° máq. = máx(año anterior; REDONDEAR.MAS(pico ÷ (cap. × turnos de planta × umbral))).
D3: Turnos del puesto = 2 solo si con 1 turno supera el umbral. h-hombre por u = coef. hombre–máquina ÷ cap. real.
A4: AÑO 2026
A5: Demanda por tipo (u. eq./mes) | B5: Familia | C5: Ene | D5: Feb | E5: Mar | F5: Abr | G5: May | H5: Jun | I5: Jul | J5: Ago | K5: Sep | L5: Oct | M5: Nov | N5: Dic | O5: Total
A6: =datos_base!$A$55 -> ABC 1 kg | B6: Polvo ABC | C6: =datos_base!$B$55*'Parametros Recargas'!D$33*'Parametros Recargas'!$Q$33 -> 119.0499 | D6: =datos_base!$B$55*'Parametros Recargas'!E$33*'Parametros Recargas'!$Q$33 -> 92.85892 | E6: =datos_base!$B$55*'Parametros Recargas'!F$33*'Parametros Recargas'!$Q$33 -> 92.85892 | F6: =datos_base!$B$55*'Parametros Recargas'!G$33*'Parametros Recargas'!$Q$33 -> 92.85892 | G6: =datos_base!$B$55*'Parametros Recargas'!H$33*'Parametros Recargas'!$Q$33 -> 92.85892 | H6: =datos_base!$B$55*'Parametros Recargas'!I$33*'Parametros Recargas'!$Q$33 -> 92.85892 | I6: =datos_base!$B$55*'Parametros Recargas'!J$33*'Parametros Recargas'!$Q$33 -> 92.85892 | J6: =datos_base!$B$55*'Parametros Recargas'!K$33*'Parametros Recargas'!$Q$33 -> 92.85892 | ... N6: =datos_base!$B$55*'Parametros Recargas'!O$33*'Parametros Recargas'!$Q$33 -> 142.85988 | O6: =SUM(C6:N6) -> 1190.499
A7: =datos_base!$A$56 -> ABC 2,5 kg | B7: Polvo ABC | C7: =datos_base!$B$56*'Parametros Recargas'!D$34*'Parametros Recargas'!$Q$34 -> 10.169059 | D7: =datos_base!$B$56*'Parametros Recargas'!E$34*'Parametros Recargas'!$Q$34 -> 9.0391639 | E7: =datos_base!$B$56*'Parametros Recargas'!F$34*'Parametros Recargas'!$Q$34 -> 9.6041117 | F7: =datos_base!$B$56*'Parametros Recargas'!G$34*'Parametros Recargas'!$Q$34 -> 9.0391639 | G7: =datos_base!$B$56*'Parametros Recargas'!H$34*'Parametros Recargas'!$Q$34 -> 8.4742162 | H7: =datos_base!$B$56*'Parametros Recargas'!I$34*'Parametros Recargas'!$Q$34 -> 7.9092684 | I7: =datos_base!$B$56*'Parametros Recargas'!J$34*'Parametros Recargas'!$Q$34 -> 9.0391639 | J7: =datos_base!$B$56*'Parametros Recargas'!K$34*'Parametros Recargas'!$Q$34 -> 9.6041117 | ... N7: =datos_base!$B$56*'Parametros Recargas'!O$34*'Parametros Recargas'!$Q$34 -> 12.42885 | O7: =SUM(C7:N7) -> 112.98955
A8: =datos_base!$A$57 -> ABC 5 kg | B8: Polvo ABC | C8: =datos_base!$B$57*'Parametros Recargas'!D$35*'Parametros Recargas'!$Q$35 -> 60.089896 | D8: =datos_base!$B$57*'Parametros Recargas'!E$35*'Parametros Recargas'!$Q$35 -> 53.413241 | E8: =datos_base!$B$57*'Parametros Recargas'!F$35*'Parametros Recargas'!$Q$35 -> 56.751569 | F8: =datos_base!$B$57*'Parametros Recargas'!G$35*'Parametros Recargas'!$Q$35 -> 53.413241 | G8: =datos_base!$B$57*'Parametros Recargas'!H$35*'Parametros Recargas'!$Q$35 -> 50.074914 | H8: =datos_base!$B$57*'Parametros Recargas'!I$35*'Parametros Recargas'!$Q$35 -> 46.736586 | I8: =datos_base!$B$57*'Parametros Recargas'!J$35*'Parametros Recargas'!$Q$35 -> 53.413241 | J8: =datos_base!$B$57*'Parametros Recargas'!K$35*'Parametros Recargas'!$Q$35 -> 56.751569 | ... N8: =datos_base!$B$57*'Parametros Recargas'!O$35*'Parametros Recargas'!$Q$35 -> 73.443207 | O8: =SUM(C8:N8) -> 667.66552
A9: =datos_base!$A$58 -> ABC 10 kg | B9: Polvo ABC | C9: =datos_base!$B$58*'Parametros Recargas'!D$36*'Parametros Recargas'!$Q$36 -> 3.6362091 | D9: =datos_base!$B$58*'Parametros Recargas'!E$36*'Parametros Recargas'!$Q$36 -> 3.2321859 | E9: =datos_base!$B$58*'Parametros Recargas'!F$36*'Parametros Recargas'!$Q$36 -> 3.4341975 | F9: =datos_base!$B$58*'Parametros Recargas'!G$36*'Parametros Recargas'!$Q$36 -> 3.2321859 | G9: =datos_base!$B$58*'Parametros Recargas'!H$36*'Parametros Recargas'!$Q$36 -> 3.0301743 | H9: =datos_base!$B$58*'Parametros Recargas'!I$36*'Parametros Recargas'!$Q$36 -> 2.8281626 | I9: =datos_base!$B$58*'Parametros Recargas'!J$36*'Parametros Recargas'!$Q$36 -> 3.2321859 | J9: =datos_base!$B$58*'Parametros Recargas'!K$36*'Parametros Recargas'!$Q$36 -> 3.4341975 | ... N9: =datos_base!$B$58*'Parametros Recargas'!O$36*'Parametros Recargas'!$Q$36 -> 4.4442556 | O9: =SUM(C9:N9) -> 40.402324
A10: =datos_base!$A$69 -> ABC 25 kg s/ruedas | B10: Polvo ABC | C10: =datos_base!$B$69*'Parametros Recargas'!D$37*'Parametros Recargas'!$Q$37 -> 1.8489199 | D10: =datos_base!$B$69*'Parametros Recargas'!E$37*'Parametros Recargas'!$Q$37 -> 1.4791359 | E10: =datos_base!$B$69*'Parametros Recargas'!F$37*'Parametros Recargas'!$Q$37 -> 1.5715819 | F10: =datos_base!$B$69*'Parametros Recargas'!G$37*'Parametros Recargas'!$Q$37 -> 1.5715819 | G10: =datos_base!$B$69*'Parametros Recargas'!H$37*'Parametros Recargas'!$Q$37 -> 1.4791359 | H10: =datos_base!$B$69*'Parametros Recargas'!I$37*'Parametros Recargas'!$Q$37 -> 1.3866899 | I10: =datos_base!$B$69*'Parametros Recargas'!J$37*'Parametros Recargas'!$Q$37 -> 1.6640279 | J10: =datos_base!$B$69*'Parametros Recargas'!K$37*'Parametros Recargas'!$Q$37 -> 1.4791359 | ... N10: =datos_base!$B$69*'Parametros Recargas'!O$37*'Parametros Recargas'!$Q$37 -> 1.6640279 | O10: =SUM(C10:N10) -> 18.489199
A11: =datos_base!$A$70 -> ABC 50 kg s/ruedas | B11: Polvo ABC | C11: =datos_base!$B$70*'Parametros Recargas'!D$38*'Parametros Recargas'!$Q$38 -> 4.0059931 | D11: =datos_base!$B$70*'Parametros Recargas'!E$38*'Parametros Recargas'!$Q$38 -> 3.2047945 | E11: =datos_base!$B$70*'Parametros Recargas'!F$38*'Parametros Recargas'!$Q$38 -> 3.4050941 | F11: =datos_base!$B$70*'Parametros Recargas'!G$38*'Parametros Recargas'!$Q$38 -> 3.4050941 | G11: =datos_base!$B$70*'Parametros Recargas'!H$38*'Parametros Recargas'!$Q$38 -> 3.2047945 | H11: =datos_base!$B$70*'Parametros Recargas'!I$38*'Parametros Recargas'!$Q$38 -> 3.0044948 | I11: =datos_base!$B$70*'Parametros Recargas'!J$38*'Parametros Recargas'!$Q$38 -> 3.6053938 | J11: =datos_base!$B$70*'Parametros Recargas'!K$38*'Parametros Recargas'!$Q$38 -> 3.2047945 | ... N11: =datos_base!$B$70*'Parametros Recargas'!O$38*'Parametros Recargas'!$Q$38 -> 3.6053938 | O11: =SUM(C11:N11) -> 40.059931
A12: =datos_base!$A$71 -> ABC 70 kg s/ruedas | B12: Polvo ABC | C12: =datos_base!$B$71*'Parametros Recargas'!D$39*'Parametros Recargas'!$Q$39 -> 0.82174217 | D12: =datos_base!$B$71*'Parametros Recargas'!E$39*'Parametros Recargas'!$Q$39 -> 0.65739374 | E12: =datos_base!$B$71*'Parametros Recargas'!F$39*'Parametros Recargas'!$Q$39 -> 0.69848085 | F12: =datos_base!$B$71*'Parametros Recargas'!G$39*'Parametros Recargas'!$Q$39 -> 0.69848085 | G12: =datos_base!$B$71*'Parametros Recargas'!H$39*'Parametros Recargas'!$Q$39 -> 0.65739374 | H12: =datos_base!$B$71*'Parametros Recargas'!I$39*'Parametros Recargas'!$Q$39 -> 0.61630663 | I12: =datos_base!$B$71*'Parametros Recargas'!J$39*'Parametros Recargas'!$Q$39 -> 0.73956796 | J12: =datos_base!$B$71*'Parametros Recargas'!K$39*'Parametros Recargas'!$Q$39 -> 0.65739374 | ... N12: =datos_base!$B$71*'Parametros Recargas'!O$39*'Parametros Recargas'!$Q$39 -> 0.73956796 | O12: =SUM(C12:N12) -> 8.2174217
A13: =datos_base!$A$72 -> ABC 100 kg s/ruedas | B13: Polvo ABC | C13: =datos_base!$B$72*'Parametros Recargas'!D$40*'Parametros Recargas'!$Q$40 -> 0.61630663 | D13: =datos_base!$B$72*'Parametros Recargas'!E$40*'Parametros Recargas'!$Q$40 -> 0.4930453 | E13: =datos_base!$B$72*'Parametros Recargas'!F$40*'Parametros Recargas'!$Q$40 -> 0.52386064 | F13: =datos_base!$B$72*'Parametros Recargas'!G$40*'Parametros Recargas'!$Q$40 -> 0.52386064 | G13: =datos_base!$B$72*'Parametros Recargas'!H$40*'Parametros Recargas'!$Q$40 -> 0.4930453 | H13: =datos_base!$B$72*'Parametros Recargas'!I$40*'Parametros Recargas'!$Q$40 -> 0.46222997 | I13: =datos_base!$B$72*'Parametros Recargas'!J$40*'Parametros Recargas'!$Q$40 -> 0.55467597 | J13: =datos_base!$B$72*'Parametros Recargas'!K$40*'Parametros Recargas'!$Q$40 -> 0.4930453 | ... N13: =datos_base!$B$72*'Parametros Recargas'!O$40*'Parametros Recargas'!$Q$40 -> 0.55467597 | O13: =SUM(C13:N13) -> 6.1630663
A14: =datos_base!$A$62 -> BC 5 kg | B14: Polvo BC | C14: =datos_base!$B$62*'Parametros Recargas'!D$41*'Parametros Recargas'!$Q$41 -> 0.21570732 | D14: =datos_base!$B$62*'Parametros Recargas'!E$41*'Parametros Recargas'!$Q$41 -> 0.19173984 | E14: =datos_base!$B$62*'Parametros Recargas'!F$41*'Parametros Recargas'!$Q$41 -> 0.20372358 | F14: =datos_base!$B$62*'Parametros Recargas'!G$41*'Parametros Recargas'!$Q$41 -> 0.19173984 | G14: =datos_base!$B$62*'Parametros Recargas'!H$41*'Parametros Recargas'!$Q$41 -> 0.1797561 | H14: =datos_base!$B$62*'Parametros Recargas'!I$41*'Parametros Recargas'!$Q$41 -> 0.16777236 | I14: =datos_base!$B$62*'Parametros Recargas'!J$41*'Parametros Recargas'!$Q$41 -> 0.19173984 | J14: =datos_base!$B$62*'Parametros Recargas'!K$41*'Parametros Recargas'!$Q$41 -> 0.20372358 | ... N14: =datos_base!$B$62*'Parametros Recargas'!O$41*'Parametros Recargas'!$Q$41 -> 0.26364228 | O14: =SUM(C14:N14) -> 2.396748
A15: =datos_base!$A$68 -> Clase D 9 l | B15: Polvo Clase D | C15: =datos_base!$B$68*'Parametros Recargas'!D$42*'Parametros Recargas'!$Q$42 -> 0.21570732 | D15: =datos_base!$B$68*'Parametros Recargas'!E$42*'Parametros Recargas'!$Q$42 -> 0.19173984 | E15: =datos_base!$B$68*'Parametros Recargas'!F$42*'Parametros Recargas'!$Q$42 -> 0.20372358 | F15: =datos_base!$B$68*'Parametros Recargas'!G$42*'Parametros Recargas'!$Q$42 -> 0.19173984 | G15: =datos_base!$B$68*'Parametros Recargas'!H$42*'Parametros Recargas'!$Q$42 -> 0.1797561 | H15: =datos_base!$B$68*'Parametros Recargas'!I$42*'Parametros Recargas'!$Q$42 -> 0.16777236 | I15: =datos_base!$B$68*'Parametros Recargas'!J$42*'Parametros Recargas'!$Q$42 -> 0.19173984 | J15: =datos_base!$B$68*'Parametros Recargas'!K$42*'Parametros Recargas'!$Q$42 -> 0.20372358 | ... N15: =datos_base!$B$68*'Parametros Recargas'!O$42*'Parametros Recargas'!$Q$42 -> 0.26364228 | O15: =SUM(C15:N15) -> 2.396748
A16: =datos_base!$A$59 -> Agua 10 l | B16: Líquidos | C16: =datos_base!$B$59*'Parametros Recargas'!D$43*'Parametros Recargas'!$Q$43 -> 4.8996377 | D16: =datos_base!$B$59*'Parametros Recargas'!E$43*'Parametros Recargas'!$Q$43 -> 4.3552335 | E16: =datos_base!$B$59*'Parametros Recargas'!F$43*'Parametros Recargas'!$Q$43 -> 4.6274356 | F16: =datos_base!$B$59*'Parametros Recargas'!G$43*'Parametros Recargas'!$Q$43 -> 4.3552335 | G16: =datos_base!$B$59*'Parametros Recargas'!H$43*'Parametros Recargas'!$Q$43 -> 4.0830314 | H16: =datos_base!$B$59*'Parametros Recargas'!I$43*'Parametros Recargas'!$Q$43 -> 3.8108293 | I16: =datos_base!$B$59*'Parametros Recargas'!J$43*'Parametros Recargas'!$Q$43 -> 4.3552335 | J16: =datos_base!$B$59*'Parametros Recargas'!K$43*'Parametros Recargas'!$Q$43 -> 4.6274356 | ... N16: =datos_base!$B$59*'Parametros Recargas'!O$43*'Parametros Recargas'!$Q$43 -> 5.9884461 | O16: =SUM(C16:N16) -> 54.440419
A17: =datos_base!$A$60 -> AFFF 10 l | B17: Líquidos | C17: =datos_base!$B$60*'Parametros Recargas'!D$44*'Parametros Recargas'!$Q$44 -> 0.70875263 | D17: =datos_base!$B$60*'Parametros Recargas'!E$44*'Parametros Recargas'!$Q$44 -> 0.63000233 | E17: =datos_base!$B$60*'Parametros Recargas'!F$44*'Parametros Recargas'!$Q$44 -> 0.66937748 | F17: =datos_base!$B$60*'Parametros Recargas'!G$44*'Parametros Recargas'!$Q$44 -> 0.63000233 | G17: =datos_base!$B$60*'Parametros Recargas'!H$44*'Parametros Recargas'!$Q$44 -> 0.59062719 | H17: =datos_base!$B$60*'Parametros Recargas'!I$44*'Parametros Recargas'!$Q$44 -> 0.55125204 | I17: =datos_base!$B$60*'Parametros Recargas'!J$44*'Parametros Recargas'!$Q$44 -> 0.63000233 | J17: =datos_base!$B$60*'Parametros Recargas'!K$44*'Parametros Recargas'!$Q$44 -> 0.66937748 | ... N17: =datos_base!$B$60*'Parametros Recargas'!O$44*'Parametros Recargas'!$Q$44 -> 0.86625321 | O17: =SUM(C17:N17) -> 7.8750292
A18: =datos_base!$A$63 -> Sales K 6 l | B18: Líquidos | C18: =datos_base!$B$63*'Parametros Recargas'!D$45*'Parametros Recargas'!$Q$45 -> 2.5268572 | D18: =datos_base!$B$63*'Parametros Recargas'!E$45*'Parametros Recargas'!$Q$45 -> 2.2460953 | E18: =datos_base!$B$63*'Parametros Recargas'!F$45*'Parametros Recargas'!$Q$45 -> 2.3864762 | F18: =datos_base!$B$63*'Parametros Recargas'!G$45*'Parametros Recargas'!$Q$45 -> 2.2460953 | G18: =datos_base!$B$63*'Parametros Recargas'!H$45*'Parametros Recargas'!$Q$45 -> 2.1057143 | H18: =datos_base!$B$63*'Parametros Recargas'!I$45*'Parametros Recargas'!$Q$45 -> 1.9653334 | I18: =datos_base!$B$63*'Parametros Recargas'!J$45*'Parametros Recargas'!$Q$45 -> 2.2460953 | J18: =datos_base!$B$63*'Parametros Recargas'!K$45*'Parametros Recargas'!$Q$45 -> 2.3864762 | ... N18: =datos_base!$B$63*'Parametros Recargas'!O$45*'Parametros Recargas'!$Q$45 -> 3.088381 | O18: =SUM(C18:N18) -> 28.076191
A19: =datos_base!$A$61 -> AFFF 50 l s/ruedas | B19: Líquidos | C19: =datos_base!$B$61*'Parametros Recargas'!D$46*'Parametros Recargas'!$Q$46 -> 1.1298955 | D19: =datos_base!$B$61*'Parametros Recargas'!E$46*'Parametros Recargas'!$Q$46 -> 0.90391639 | E19: =datos_base!$B$61*'Parametros Recargas'!F$46*'Parametros Recargas'!$Q$46 -> 0.96041117 | F19: =datos_base!$B$61*'Parametros Recargas'!G$46*'Parametros Recargas'!$Q$46 -> 0.96041117 | G19: =datos_base!$B$61*'Parametros Recargas'!H$46*'Parametros Recargas'!$Q$46 -> 0.90391639 | H19: =datos_base!$B$61*'Parametros Recargas'!I$46*'Parametros Recargas'!$Q$46 -> 0.84742162 | I19: =datos_base!$B$61*'Parametros Recargas'!J$46*'Parametros Recargas'!$Q$46 -> 1.0169059 | J19: =datos_base!$B$61*'Parametros Recargas'!K$46*'Parametros Recargas'!$Q$46 -> 0.90391639 | ... N19: =datos_base!$B$61*'Parametros Recargas'!O$46*'Parametros Recargas'!$Q$46 -> 1.0169059 | O19: =SUM(C19:N19) -> 11.298955
A20: =datos_base!$A$64 -> CO₂ 2 kg | B20: CO₂ | C20: =datos_base!$B$64*'Parametros Recargas'!D$47*'Parametros Recargas'!$Q$47 -> 13.897715 | D20: =datos_base!$B$64*'Parametros Recargas'!E$47*'Parametros Recargas'!$Q$47 -> 12.353524 | E20: =datos_base!$B$64*'Parametros Recargas'!F$47*'Parametros Recargas'!$Q$47 -> 13.125619 | F20: =datos_base!$B$64*'Parametros Recargas'!G$47*'Parametros Recargas'!$Q$47 -> 12.353524 | G20: =datos_base!$B$64*'Parametros Recargas'!H$47*'Parametros Recargas'!$Q$47 -> 11.581429 | H20: =datos_base!$B$64*'Parametros Recargas'!I$47*'Parametros Recargas'!$Q$47 -> 10.809334 | I20: =datos_base!$B$64*'Parametros Recargas'!J$47*'Parametros Recargas'!$Q$47 -> 12.353524 | J20: =datos_base!$B$64*'Parametros Recargas'!K$47*'Parametros Recargas'!$Q$47 -> 13.125619 | ... N20: =datos_base!$B$64*'Parametros Recargas'!O$47*'Parametros Recargas'!$Q$47 -> 16.986096 | O20: =SUM(C20:N20) -> 154.41905
A21: =datos_base!$A$65 -> CO₂ 5 kg | B21: CO₂ | C21: =datos_base!$B$65*'Parametros Recargas'!D$48*'Parametros Recargas'!$Q$48 -> 3.8519164 | D21: =datos_base!$B$65*'Parametros Recargas'!E$48*'Parametros Recargas'!$Q$48 -> 3.4239257 | E21: =datos_base!$B$65*'Parametros Recargas'!F$48*'Parametros Recargas'!$Q$48 -> 3.6379211 | F21: =datos_base!$B$65*'Parametros Recargas'!G$48*'Parametros Recargas'!$Q$48 -> 3.4239257 | G21: =datos_base!$B$65*'Parametros Recargas'!H$48*'Parametros Recargas'!$Q$48 -> 3.2099304 | H21: =datos_base!$B$65*'Parametros Recargas'!I$48*'Parametros Recargas'!$Q$48 -> 2.995935 | I21: =datos_base!$B$65*'Parametros Recargas'!J$48*'Parametros Recargas'!$Q$48 -> 3.4239257 | J21: =datos_base!$B$65*'Parametros Recargas'!K$48*'Parametros Recargas'!$Q$48 -> 3.6379211 | ... N21: =datos_base!$B$65*'Parametros Recargas'!O$48*'Parametros Recargas'!$Q$48 -> 4.7078979 | O21: =SUM(C21:N21) -> 42.799072
A22: =datos_base!$A$67 -> HCFC/HFC 5 kg | B22: Agente limpio | C22: =datos_base!$B$67*'Parametros Recargas'!D$49*'Parametros Recargas'!$Q$49 -> 0.55467597 | D22: =datos_base!$B$67*'Parametros Recargas'!E$49*'Parametros Recargas'!$Q$49 -> 0.4930453 | E22: =datos_base!$B$67*'Parametros Recargas'!F$49*'Parametros Recargas'!$Q$49 -> 0.52386064 | F22: =datos_base!$B$67*'Parametros Recargas'!G$49*'Parametros Recargas'!$Q$49 -> 0.4930453 | G22: =datos_base!$B$67*'Parametros Recargas'!H$49*'Parametros Recargas'!$Q$49 -> 0.46222997 | H22: =datos_base!$B$67*'Parametros Recargas'!I$49*'Parametros Recargas'!$Q$49 -> 0.43141464 | I22: =datos_base!$B$67*'Parametros Recargas'!J$49*'Parametros Recargas'!$Q$49 -> 0.4930453 | J22: =datos_base!$B$67*'Parametros Recargas'!K$49*'Parametros Recargas'!$Q$49 -> 0.52386064 | ... N22: =datos_base!$B$67*'Parametros Recargas'!O$49*'Parametros Recargas'!$Q$49 -> 0.67793729 | O22: =SUM(C22:N22) -> 6.1630663
A23: Demanda por familia (u. eq./mes) | C23: Ene | D23: Feb | E23: Mar | F23: Abr | G23: May | H23: Jun | I23: Jul | J23: Ago | K23: Sep | L23: Oct | M23: Nov | N23: Dic | O23: Total
A24: Polvo ABC | B24: u/mes | C24: =SUM(C6:C13) -> 200.23802 | D24: =SUM(D6:D13) -> 164.37788 | E24: =SUM(E6:E13) -> 168.84782 | F24: =SUM(F6:F13) -> 164.74253 | G24: =SUM(G6:G13) -> 160.27259 | H24: =SUM(H6:H13) -> 155.80266 | I24: =SUM(I6:I13) -> 165.10718 | J24: =SUM(J6:J13) -> 168.48317 | ... N24: =SUM(N6:N13) -> 239.73986 | O24: =SUM(C24:N24) -> 2084.486
A25: Polvo BC | B25: u/mes | C25: =SUM(C14) -> 0.21570732 | D25: =SUM(D14) -> 0.19173984 | E25: =SUM(E14) -> 0.20372358 | F25: =SUM(F14) -> 0.19173984 | G25: =SUM(G14) -> 0.1797561 | H25: =SUM(H14) -> 0.16777236 | I25: =SUM(I14) -> 0.19173984 | J25: =SUM(J14) -> 0.20372358 | ... N25: =SUM(N14) -> 0.26364228 | O25: =SUM(C25:N25) -> 2.396748
A26: Polvo Clase D | B26: u/mes | C26: =SUM(C15) -> 0.21570732 | D26: =SUM(D15) -> 0.19173984 | E26: =SUM(E15) -> 0.20372358 | F26: =SUM(F15) -> 0.19173984 | G26: =SUM(G15) -> 0.1797561 | H26: =SUM(H15) -> 0.16777236 | I26: =SUM(I15) -> 0.19173984 | J26: =SUM(J15) -> 0.20372358 | ... N26: =SUM(N15) -> 0.26364228 | O26: =SUM(C26:N26) -> 2.396748
A27: Líquidos | B27: u/mes | C27: =SUM(C16:C19) -> 9.265143 | D27: =SUM(D16:D19) -> 8.1352475 | E27: =SUM(E16:E19) -> 8.6437005 | F27: =SUM(F16:F19) -> 8.1917423 | G27: =SUM(G16:G19) -> 7.6832893 | H27: =SUM(H16:H19) -> 7.1748364 | I27: =SUM(I16:I19) -> 8.2482371 | J27: =SUM(J16:J19) -> 8.5872057 | ... N27: =SUM(N16:N19) -> 10.959986 | O27: =SUM(C27:N27) -> 101.69059
A28: CO₂ | B28: u/mes | C28: =SUM(C20:C21) -> 17.749631 | D28: =SUM(D20:D21) -> 15.77745 | E28: =SUM(E20:E21) -> 16.76354 | F28: =SUM(F20:F21) -> 15.77745 | G28: =SUM(G20:G21) -> 14.791359 | H28: =SUM(H20:H21) -> 13.805269 | I28: =SUM(I20:I21) -> 15.77745 | J28: =SUM(J20:J21) -> 16.76354 | ... N28: =SUM(N20:N21) -> 21.693993 | O28: =SUM(C28:N28) -> 197.21812
A29: Agente limpio | B29: u/mes | C29: =SUM(C22) -> 0.55467597 | D29: =SUM(D22) -> 0.4930453 | E29: =SUM(E22) -> 0.52386064 | F29: =SUM(F22) -> 0.4930453 | G29: =SUM(G22) -> 0.46222997 | H29: =SUM(H22) -> 0.43141464 | I29: =SUM(I22) -> 0.4930453 | J29: =SUM(J22) -> 0.52386064 | ... N29: =SUM(N22) -> 0.67793729 | O29: =SUM(C29:N29) -> 6.1630663
A30: Carga por puesto | B30: unidad | C30: Ene | D30: Feb | E30: Mar | F30: Abr | G30: May | H30: Jun | I30: Jul | J30: Ago | K30: Sep | L30: Oct | M30: Nov | N30: Dic | O30: Pico (u/h) | P30: Cap. real (u/h) | Q30: N° máq. | R30: Turnos | S30: % Aprov. | T30: ABC | U30: BC | V30: D | W30: Líq. | X30: CO₂ | Y30: HC | Z30: h-hombre por u
A31: Recepción y clasificación (común) | B31: u/h | C31: =($T31*C$24+$U31*C$25+$V31*C$26+$W31*C$27+$X31*C$28+$Y31*C$29)/$B$2 -> 1.5215926 | D31: =($T31*D$24+$U31*D$25+$V31*D$26+$W31*D$27+$X31*D$28+$Y31*D$29)/$B$2 -> 1.261114 | E31: =($T31*E$24+$U31*E$25+$V31*E$26+$W31*E$27+$X31*E$28+$Y31*E$29)/$B$2 -> 1.3012424 | F31: =($T31*F$24+$U31*F$25+$V31*F$26+$W31*F$27+$X31*F$28+$Y31*F$29)/$B$2 -> 1.2639216 | G31: =($T31*G$24+$U31*G$25+$V31*G$26+$W31*G$27+$X31*G$28+$Y31*G$29)/$B$2 -> 1.2237932 | H31: =($T31*H$24+$U31*H$25+$V31*H$26+$W31*H$27+$X31*H$28+$Y31*H$29)/$B$2 -> 1.1836648 | I31: =($T31*I$24+$U31*I$25+$V31*I$26+$W31*I$27+$X31*I$28+$Y31*I$29)/$B$2 -> 1.2667293 | J31: =($T31*J$24+$U31*J$25+$V31*J$26+$W31*J$27+$X31*J$28+$Y31*J$29)/$B$2 -> 1.2984348 | ... N31: =($T31*N$24+$U31*N$25+$V31*N$26+$W31*N$27+$X31*N$28+$Y31*N$29)/$B$2 -> 1.8239937 | O31: =MAX(C31:N31) -> 1.8239937 | P31: ='Parametros Recargas'!$M$85 -> 72 | Q31: =MAX(1,ROUNDUP(O31/(P31*'Parametros Recargas'!B$8*'Parametros Recargas'!$B$19),0)) -> 1 | R31: =IF(AND('Parametros Recargas'!B$8=2,O31/(P31*Q31*'Parametros Recargas'!$B$19)>1),2,1) -> 1 | S31: =O31/(P31*Q31*R31) -> 0.025333246 | T31: ='Parametros Recargas'!D54 -> 1 | U31: ='Parametros Recargas'!E54 -> 1 | V31: ='Parametros Recargas'!F54 -> 1 | W31: ='Parametros Recargas'!G54 -> 1 | X31: ='Parametros Recargas'!H54 -> 1 | Y31: ='Parametros Recargas'!I54 -> 1 | Z31: ='Parametros Recargas'!$U$85/P31 -> 0.013888889
A32: Inspección visual (común) | B32: u/h | C32: =($T32*C$24+$U32*C$25+$V32*C$26+$W32*C$27+$X32*C$28+$Y32*C$29)/$B$2 -> 1.5215926 | D32: =($T32*D$24+$U32*D$25+$V32*D$26+$W32*D$27+$X32*D$28+$Y32*D$29)/$B$2 -> 1.261114 | E32: =($T32*E$24+$U32*E$25+$V32*E$26+$W32*E$27+$X32*E$28+$Y32*E$29)/$B$2 -> 1.3012424 | F32: =($T32*F$24+$U32*F$25+$V32*F$26+$W32*F$27+$X32*F$28+$Y32*F$29)/$B$2 -> 1.2639216 | G32: =($T32*G$24+$U32*G$25+$V32*G$26+$W32*G$27+$X32*G$28+$Y32*G$29)/$B$2 -> 1.2237932 | H32: =($T32*H$24+$U32*H$25+$V32*H$26+$W32*H$27+$X32*H$28+$Y32*H$29)/$B$2 -> 1.1836648 | I32: =($T32*I$24+$U32*I$25+$V32*I$26+$W32*I$27+$X32*I$28+$Y32*I$29)/$B$2 -> 1.2667293 | J32: =($T32*J$24+$U32*J$25+$V32*J$26+$W32*J$27+$X32*J$28+$Y32*J$29)/$B$2 -> 1.2984348 | ... N32: =($T32*N$24+$U32*N$25+$V32*N$26+$W32*N$27+$X32*N$28+$Y32*N$29)/$B$2 -> 1.8239937 | O32: =MAX(C32:N32) -> 1.8239937 | P32: ='Parametros Recargas'!$M$86 -> 52.363636 | Q32: =MAX(1,ROUNDUP(O32/(P32*'Parametros Recargas'!B$8*'Parametros Recargas'!$B$19),0)) -> 1 | R32: =IF(AND('Parametros Recargas'!B$8=2,O32/(P32*Q32*'Parametros Recargas'!$B$19)>1),2,1) -> 1 | S32: =O32/(P32*Q32*R32) -> 0.034833213 | T32: ='Parametros Recargas'!D55 -> 1 | U32: ='Parametros Recargas'!E55 -> 1 | V32: ='Parametros Recargas'!F55 -> 1 | W32: ='Parametros Recargas'!G55 -> 1 | X32: ='Parametros Recargas'!H55 -> 1 | Y32: ='Parametros Recargas'!I55 -> 1 | Z32: ='Parametros Recargas'!$U$86/P32 -> 0.019097222
A33: Ensayo de funcionamiento — descarga polvo ABC (equipo exclusivo) | B33: u/h | C33: =($T33*C$24+$U33*C$25+$V33*C$26+$W33*C$27+$X33*C$28+$Y33*C$29)/$B$2 -> 1.3349202 | D33: =($T33*D$24+$U33*D$25+$V33*D$26+$W33*D$27+$X33*D$28+$Y33*D$29)/$B$2 -> 1.0958525 | E33: =($T33*E$24+$U33*E$25+$V33*E$26+$W33*E$27+$X33*E$28+$Y33*E$29)/$B$2 -> 1.1256521 | F33: =($T33*F$24+$U33*F$25+$V33*F$26+$W33*F$27+$X33*F$28+$Y33*F$29)/$B$2 -> 1.0982835 | G33: =($T33*G$24+$U33*G$25+$V33*G$26+$W33*G$27+$X33*G$28+$Y33*G$29)/$B$2 -> 1.068484 | H33: =($T33*H$24+$U33*H$25+$V33*H$26+$W33*H$27+$X33*H$28+$Y33*H$29)/$B$2 -> 1.0386844 | I33: =($T33*I$24+$U33*I$25+$V33*I$26+$W33*I$27+$X33*I$28+$Y33*I$29)/$B$2 -> 1.1007145 | J33: =($T33*J$24+$U33*J$25+$V33*J$26+$W33*J$27+$X33*J$28+$Y33*J$29)/$B$2 -> 1.1232211 | ... N33: =($T33*N$24+$U33*N$25+$V33*N$26+$W33*N$27+$X33*N$28+$Y33*N$29)/$B$2 -> 1.5982657 | O33: =MAX(C33:N33) -> 1.5982657 | P33: ='Parametros Recargas'!$M$87 -> 29.142857 | Q33: =MAX(1,ROUNDUP(O33/(P33*'Parametros Recargas'!B$8*'Parametros Recargas'!$B$19),0)) -> 1 | R33: =IF(AND('Parametros Recargas'!B$8=2,O33/(P33*Q33*'Parametros Recargas'!$B$19)>1),2,1) -> 1 | S33: =O33/(P33*Q33*R33) -> 0.054842451 | T33: ='Parametros Recargas'!D56 -> 1 | U33: ='Parametros Recargas'!E56 -> 0 | V33: ='Parametros Recargas'!F56 -> 0 | W33: ='Parametros Recargas'!G56 -> 0 | X33: ='Parametros Recargas'!H56 -> 0 | Y33: ='Parametros Recargas'!I56 -> 0 | Z33: ='Parametros Recargas'!$U$87/P33 -> 0.017156863
A34: Ensayo de funcionamiento — descarga polvo BC (equipo exclusivo) | B34: u/h | C34: =($T34*C$24+$U34*C$25+$V34*C$26+$W34*C$27+$X34*C$28+$Y34*C$29)/$B$2 -> 0.0014380488 | D34: =($T34*D$24+$U34*D$25+$V34*D$26+$W34*D$27+$X34*D$28+$Y34*D$29)/$B$2 -> 0.0012782656 | E34: =($T34*E$24+$U34*E$25+$V34*E$26+$W34*E$27+$X34*E$28+$Y34*E$29)/$B$2 -> 0.0013581572 | F34: =($T34*F$24+$U34*F$25+$V34*F$26+$W34*F$27+$X34*F$28+$Y34*F$29)/$B$2 -> 0.0012782656 | G34: =($T34*G$24+$U34*G$25+$V34*G$26+$W34*G$27+$X34*G$28+$Y34*G$29)/$B$2 -> 0.001198374 | H34: =($T34*H$24+$U34*H$25+$V34*H$26+$W34*H$27+$X34*H$28+$Y34*H$29)/$B$2 -> 0.0011184824 | I34: =($T34*I$24+$U34*I$25+$V34*I$26+$W34*I$27+$X34*I$28+$Y34*I$29)/$B$2 -> 0.0012782656 | J34: =($T34*J$24+$U34*J$25+$V34*J$26+$W34*J$27+$X34*J$28+$Y34*J$29)/$B$2 -> 0.0013581572 | ... N34: =($T34*N$24+$U34*N$25+$V34*N$26+$W34*N$27+$X34*N$28+$Y34*N$29)/$B$2 -> 0.0017576152 | O34: =MAX(C34:N34) -> 0.0017576152 | P34: ='Parametros Recargas'!$M$88 -> 29.142857 | Q34: =MAX(1,ROUNDUP(O34/(P34*'Parametros Recargas'!B$8*'Parametros Recargas'!$B$19),0)) -> 1 | R34: =IF(AND('Parametros Recargas'!B$8=2,O34/(P34*Q34*'Parametros Recargas'!$B$19)>1),2,1) -> 1 | S34: =O34/(P34*Q34*R34) -> 6.0310326e-05 | T34: ='Parametros Recargas'!D57 -> 0 | U34: ='Parametros Recargas'!E57 -> 1 | V34: ='Parametros Recargas'!F57 -> 0 | W34: ='Parametros Recargas'!G57 -> 0 | X34: ='Parametros Recargas'!H57 -> 0 | Y34: ='Parametros Recargas'!I57 -> 0 | Z34: ='Parametros Recargas'!$U$88/P34 -> 0.034313725
A35: Descarga polvo Clase D (manual, recipiente exclusivo) | B35: u/h | C35: =($T35*C$24+$U35*C$25+$V35*C$26+$W35*C$27+$X35*C$28+$Y35*C$29)/$B$2 -> 0.0014380488 | D35: =($T35*D$24+$U35*D$25+$V35*D$26+$W35*D$27+$X35*D$28+$Y35*D$29)/$B$2 -> 0.0012782656 | E35: =($T35*E$24+$U35*E$25+$V35*E$26+$W35*E$27+$X35*E$28+$Y35*E$29)/$B$2 -> 0.0013581572 | F35: =($T35*F$24+$U35*F$25+$V35*F$26+$W35*F$27+$X35*F$28+$Y35*F$29)/$B$2 -> 0.0012782656 | G35: =($T35*G$24+$U35*G$25+$V35*G$26+$W35*G$27+$X35*G$28+$Y35*G$29)/$B$2 -> 0.001198374 | H35: =($T35*H$24+$U35*H$25+$V35*H$26+$W35*H$27+$X35*H$28+$Y35*H$29)/$B$2 -> 0.0011184824 | I35: =($T35*I$24+$U35*I$25+$V35*I$26+$W35*I$27+$X35*I$28+$Y35*I$29)/$B$2 -> 0.0012782656 | J35: =($T35*J$24+$U35*J$25+$V35*J$26+$W35*J$27+$X35*J$28+$Y35*J$29)/$B$2 -> 0.0013581572 | ... N35: =($T35*N$24+$U35*N$25+$V35*N$26+$W35*N$27+$X35*N$28+$Y35*N$29)/$B$2 -> 0.0017576152 | O35: =MAX(C35:N35) -> 0.0017576152 | P35: ='Parametros Recargas'!$M$89 -> 13.5 | Q35: =MAX(1,ROUNDUP(O35/(P35*'Parametros Recargas'!B$8*'Parametros Recargas'!$B$19),0)) -> 1 | R35: =IF(AND('Parametros Recargas'!B$8=2,O35/(P35*Q35*'Parametros Recargas'!$B$19)>1),2,1) -> 1 | S35: =O35/(P35*Q35*R35) -> 0.00013019372 | T35: ='Parametros Recargas'!D58 -> 0 | U35: ='Parametros Recargas'!E58 -> 0 | V35: ='Parametros Recargas'!F58 -> 1 | W35: ='Parametros Recargas'!G58 -> 0 | X35: ='Parametros Recargas'!H58 -> 0 | Y35: ='Parametros Recargas'!I58 -> 0 | Z35: ='Parametros Recargas'!$U$89/P35 -> 0.074074074
A36: Ensayo de funcionamiento — descarga líquidos | B36: u/h | C36: =($T36*C$24+$U36*C$25+$V36*C$26+$W36*C$27+$X36*C$28+$Y36*C$29)/$B$2 -> 0.06176762 | D36: =($T36*D$24+$U36*D$25+$V36*D$26+$W36*D$27+$X36*D$28+$Y36*D$29)/$B$2 -> 0.054234983 | E36: =($T36*E$24+$U36*E$25+$V36*E$26+$W36*E$27+$X36*E$28+$Y36*E$29)/$B$2 -> 0.05762467 | F36: =($T36*F$24+$U36*F$25+$V36*F$26+$W36*F$27+$X36*F$28+$Y36*F$29)/$B$2 -> 0.054611615 | G36: =($T36*G$24+$U36*G$25+$V36*G$26+$W36*G$27+$X36*G$28+$Y36*G$29)/$B$2 -> 0.051221929 | H36: =($T36*H$24+$U36*H$25+$V36*H$26+$W36*H$27+$X36*H$28+$Y36*H$29)/$B$2 -> 0.047832242 | I36: =($T36*I$24+$U36*I$25+$V36*I$26+$W36*I$27+$X36*I$28+$Y36*I$29)/$B$2 -> 0.054988247 | J36: =($T36*J$24+$U36*J$25+$V36*J$26+$W36*J$27+$X36*J$28+$Y36*J$29)/$B$2 -> 0.057248038 | ... N36: =($T36*N$24+$U36*N$25+$V36*N$26+$W36*N$27+$X36*N$28+$Y36*N$29)/$B$2 -> 0.073066575 | O36: =MAX(C36:N36) -> 0.073066575 | P36: ='Parametros Recargas'!$M$90 -> 22.666667 | Q36: =MAX(1,ROUNDUP(O36/(P36*'Parametros Recargas'!B$8*'Parametros Recargas'!$B$19),0)) -> 1 | R36: =IF(AND('Parametros Recargas'!B$8=2,O36/(P36*Q36*'Parametros Recargas'!$B$19)>1),2,1) -> 1 | S36: =O36/(P36*Q36*R36) -> 0.0032235254 | T36: ='Parametros Recargas'!D59 -> 0 | U36: ='Parametros Recargas'!E59 -> 0 | V36: ='Parametros Recargas'!F59 -> 0 | W36: ='Parametros Recargas'!G59 -> 1 | X36: ='Parametros Recargas'!H59 -> 0 | Y36: ='Parametros Recargas'!I59 -> 0 | Z36: ='Parametros Recargas'!$U$90/P36 -> 0.044117647
A37: Ensayo de funcionamiento — descarga CO₂ (muestreo) | B37: u/h | C37: =($T37*C$24+$U37*C$25+$V37*C$26+$W37*C$27+$X37*C$28+$Y37*C$29)/$B$2 -> 0.029582718 | D37: =($T37*D$24+$U37*D$25+$V37*D$26+$W37*D$27+$X37*D$28+$Y37*D$29)/$B$2 -> 0.02629575 | E37: =($T37*E$24+$U37*E$25+$V37*E$26+$W37*E$27+$X37*E$28+$Y37*E$29)/$B$2 -> 0.027939234 | F37: =($T37*F$24+$U37*F$25+$V37*F$26+$W37*F$27+$X37*F$28+$Y37*F$29)/$B$2 -> 0.02629575 | G37: =($T37*G$24+$U37*G$25+$V37*G$26+$W37*G$27+$X37*G$28+$Y37*G$29)/$B$2 -> 0.024652265 | H37: =($T37*H$24+$U37*H$25+$V37*H$26+$W37*H$27+$X37*H$28+$Y37*H$29)/$B$2 -> 0.023008781 | I37: =($T37*I$24+$U37*I$25+$V37*I$26+$W37*I$27+$X37*I$28+$Y37*I$29)/$B$2 -> 0.02629575 | J37: =($T37*J$24+$U37*J$25+$V37*J$26+$W37*J$27+$X37*J$28+$Y37*J$29)/$B$2 -> 0.027939234 | ... N37: =($T37*N$24+$U37*N$25+$V37*N$26+$W37*N$27+$X37*N$28+$Y37*N$29)/$B$2 -> 0.036156656 | O37: =MAX(C37:N37) -> 0.036156656 | P37: ='Parametros Recargas'!$M$91 -> 29.142857 | Q37: =MAX(1,ROUNDUP(O37/(P37*'Parametros Recargas'!B$8*'Parametros Recargas'!$B$19),0)) -> 1 | R37: =IF(AND('Parametros Recargas'!B$8=2,O37/(P37*Q37*'Parametros Recargas'!$B$19)>1),2,1) -> 1 | S37: =O37/(P37*Q37*R37) -> 0.0012406696 | T37: ='Parametros Recargas'!D60 -> 0 | U37: ='Parametros Recargas'!E60 -> 0 | V37: ='Parametros Recargas'!F60 -> 0 | W37: ='Parametros Recargas'!G60 -> 0 | X37: ='Parametros Recargas'!H60 -> 0.25 | Y37: ='Parametros Recargas'!I60 -> 0 | Z37: ='Parametros Recargas'!$U$91/P37 -> 0.034313725
A38: Ensayo de funcionamiento — descarga agente limpio (muestreo) | B38: u/h | C38: =($T38*C$24+$U38*C$25+$V38*C$26+$W38*C$27+$X38*C$28+$Y38*C$29)/$B$2 -> 0.00092445995 | D38: =($T38*D$24+$U38*D$25+$V38*D$26+$W38*D$27+$X38*D$28+$Y38*D$29)/$B$2 -> 0.00082174217 | E38: =($T38*E$24+$U38*E$25+$V38*E$26+$W38*E$27+$X38*E$28+$Y38*E$29)/$B$2 -> 0.00087310106 | F38: =($T38*F$24+$U38*F$25+$V38*F$26+$W38*F$27+$X38*F$28+$Y38*F$29)/$B$2 -> 0.00082174217 | G38: =($T38*G$24+$U38*G$25+$V38*G$26+$W38*G$27+$X38*G$28+$Y38*G$29)/$B$2 -> 0.00077038329 | H38: =($T38*H$24+$U38*H$25+$V38*H$26+$W38*H$27+$X38*H$28+$Y38*H$29)/$B$2 -> 0.0007190244 | I38: =($T38*I$24+$U38*I$25+$V38*I$26+$W38*I$27+$X38*I$28+$Y38*I$29)/$B$2 -> 0.00082174217 | J38: =($T38*J$24+$U38*J$25+$V38*J$26+$W38*J$27+$X38*J$28+$Y38*J$29)/$B$2 -> 0.00087310106 | ... N38: =($T38*N$24+$U38*N$25+$V38*N$26+$W38*N$27+$X38*N$28+$Y38*N$29)/$B$2 -> 0.0011298955 | O38: =MAX(C38:N38) -> 0.0011298955 | P38: ='Parametros Recargas'!$M$92 -> 18.545455 | Q38: =MAX(1,ROUNDUP(O38/(P38*'Parametros Recargas'!B$8*'Parametros Recargas'!$B$19),0)) -> 1 | R38: =IF(AND('Parametros Recargas'!B$8=2,O38/(P38*Q38*'Parametros Recargas'!$B$19)>1),2,1) -> 1 | S38: =O38/(P38*Q38*R38) -> 6.0925737e-05 | T38: ='Parametros Recargas'!D61 -> 0 | U38: ='Parametros Recargas'!E61 -> 0 | V38: ='Parametros Recargas'!F61 -> 0 | W38: ='Parametros Recargas'!G61 -> 0 | X38: ='Parametros Recargas'!H61 -> 0 | Y38: ='Parametros Recargas'!I61 -> 0.25 | Z38: ='Parametros Recargas'!$U$92/P38 -> 0.053921569
A39: Desarme de matafuego (común) | B39: u/h | C39: =($T39*C$24+$U39*C$25+$V39*C$26+$W39*C$27+$X39*C$28+$Y39*C$29)/$B$2 -> 1.4422739 | D39: =($T39*D$24+$U39*D$25+$V39*D$26+$W39*D$27+$X39*D$28+$Y39*D$29)/$B$2 -> 1.1906085 | E39: =($T39*E$24+$U39*E$25+$V39*E$26+$W39*E$27+$X39*E$28+$Y39*E$29)/$B$2 -> 1.2263304 | F39: =($T39*F$24+$U39*F$25+$V39*F$26+$W39*F$27+$X39*F$28+$Y39*F$29)/$B$2 -> 1.1934162 | G39: =($T39*G$24+$U39*G$25+$V39*G$26+$W39*G$27+$X39*G$28+$Y39*G$29)/$B$2 -> 1.1576943 | H39: =($T39*H$24+$U39*H$25+$V39*H$26+$W39*H$27+$X39*H$28+$Y39*H$29)/$B$2 -> 1.1219725 | I39: =($T39*I$24+$U39*I$25+$V39*I$26+$W39*I$27+$X39*I$28+$Y39*I$29)/$B$2 -> 1.1962238 | J39: =($T39*J$24+$U39*J$25+$V39*J$26+$W39*J$27+$X39*J$28+$Y39*J$29)/$B$2 -> 1.2235227 | ... N39: =($T39*N$24+$U39*N$25+$V39*N$26+$W39*N$27+$X39*N$28+$Y39*N$29)/$B$2 -> 1.7270487 | O39: =MAX(C39:N39) -> 1.7270487 | P39: ='Parametros Recargas'!$M$93 -> 32 | Q39: =MAX(1,ROUNDUP(O39/(P39*'Parametros Recargas'!B$8*'Parametros Recargas'!$B$19),0)) -> 1 | R39: =IF(AND('Parametros Recargas'!B$8=2,O39/(P39*Q39*'Parametros Recargas'!$B$19)>1),2,1) -> 1 | S39: =O39/(P39*Q39*R39) -> 0.053970271 | T39: ='Parametros Recargas'!D62 -> 1 | U39: ='Parametros Recargas'!E62 -> 1 | V39: ='Parametros Recargas'!F62 -> 1 | W39: ='Parametros Recargas'!G62 -> 1 | X39: ='Parametros Recargas'!H62 -> 0.35 | Y39: ='Parametros Recargas'!I62 -> 0.35 | Z39: ='Parametros Recargas'!$U$93/P39 -> 0.03125
A40: Prueba Puffer (IRAM 3672) | B40: u/h | C40: =($T40*C$24+$U40*C$25+$V40*C$26+$W40*C$27+$X40*C$28+$Y40*C$29)/$B$2 -> 0.13363582 | D40: =($T40*D$24+$U40*D$25+$V40*D$26+$W40*D$27+$X40*D$28+$Y40*D$29)/$B$2 -> 0.10971308 | E40: =($T40*E$24+$U40*E$25+$V40*E$26+$W40*E$27+$X40*E$28+$Y40*E$29)/$B$2 -> 0.11270103 | F40: =($T40*F$24+$U40*F$25+$V40*F$26+$W40*F$27+$X40*F$28+$Y40*F$29)/$B$2 -> 0.10995618 | G40: =($T40*G$24+$U40*G$25+$V40*G$26+$W40*G$27+$X40*G$28+$Y40*G$29)/$B$2 -> 0.10696823 | H40: =($T40*H$24+$U40*H$25+$V40*H$26+$W40*H$27+$X40*H$28+$Y40*H$29)/$B$2 -> 0.10398029 | I40: =($T40*I$24+$U40*I$25+$V40*I$26+$W40*I$27+$X40*I$28+$Y40*I$29)/$B$2 -> 0.11019928 | J40: =($T40*J$24+$U40*J$25+$V40*J$26+$W40*J$27+$X40*J$28+$Y40*J$29)/$B$2 -> 0.11245793 | ... N40: =($T40*N$24+$U40*N$25+$V40*N$26+$W40*N$27+$X40*N$28+$Y40*N$29)/$B$2 -> 0.16000233 | O40: =MAX(C40:N40) -> 0.16000233 | P40: ='Parametros Recargas'!$M$94 -> 6.375 | Q40: =MAX(1,ROUNDUP(O40/(P40*'Parametros Recargas'!B$8*'Parametros Recargas'!$B$19),0)) -> 1 | R40: =IF(AND('Parametros Recargas'!B$8=2,O40/(P40*Q40*'Parametros Recargas'!$B$19)>1),2,1) -> 1 | S40: =O40/(P40*Q40*R40) -> 0.025098405 | T40: ='Parametros Recargas'!D63 -> 0.1 | U40: ='Parametros Recargas'!E63 -> 0.1 | V40: ='Parametros Recargas'!F63 -> 0 | W40: ='Parametros Recargas'!G63 -> 0 | X40: ='Parametros Recargas'!H63 -> 0 | Y40: ='Parametros Recargas'!I63 -> 0 | Z40: ='Parametros Recargas'!$U$94/P40 -> 0.078431373
A41: Lavado interior de cilindro | B41: u/h | C41: =($T41*C$24+$U41*C$25+$V41*C$26+$W41*C$27+$X41*C$28+$Y41*C$29)/$B$2 -> 0.06176762 | D41: =($T41*D$24+$U41*D$25+$V41*D$26+$W41*D$27+$X41*D$28+$Y41*D$29)/$B$2 -> 0.054234983 | E41: =($T41*E$24+$U41*E$25+$V41*E$26+$W41*E$27+$X41*E$28+$Y41*E$29)/$B$2 -> 0.05762467 | F41: =($T41*F$24+$U41*F$25+$V41*F$26+$W41*F$27+$X41*F$28+$Y41*F$29)/$B$2 -> 0.054611615 | G41: =($T41*G$24+$U41*G$25+$V41*G$26+$W41*G$27+$X41*G$28+$Y41*G$29)/$B$2 -> 0.051221929 | H41: =($T41*H$24+$U41*H$25+$V41*H$26+$W41*H$27+$X41*H$28+$Y41*H$29)/$B$2 -> 0.047832242 | I41: =($T41*I$24+$U41*I$25+$V41*I$26+$W41*I$27+$X41*I$28+$Y41*I$29)/$B$2 -> 0.054988247 | J41: =($T41*J$24+$U41*J$25+$V41*J$26+$W41*J$27+$X41*J$28+$Y41*J$29)/$B$2 -> 0.057248038 | ... N41: =($T41*N$24+$U41*N$25+$V41*N$26+$W41*N$27+$X41*N$28+$Y41*N$29)/$B$2 -> 0.073066575 | O41: =MAX(C41:N41) -> 0.073066575 | P41: ='Parametros Recargas'!$M$95 -> 28.8 | Q41: =MAX(1,ROUNDUP(O41/(P41*'Parametros Recargas'!B$8*'Parametros Recargas'!$B$19),0)) -> 1 | R41: =IF(AND('Parametros Recargas'!B$8=2,O41/(P41*Q41*'Parametros Recargas'!$B$19)>1),2,1) -> 1 | S41: =O41/(P41*Q41*R41) -> 0.0025370339 | T41: ='Parametros Recargas'!D64 -> 0 | U41: ='Parametros Recargas'!E64 -> 0 | V41: ='Parametros Recargas'!F64 -> 0 | W41: ='Parametros Recargas'!G64 -> 1 | X41: ='Parametros Recargas'!H64 -> 0 | Y41: ='Parametros Recargas'!I64 -> 0 | Z41: ='Parametros Recargas'!$U$95/P41 -> 0.034722222
A42: Prueba hidráulica (común) | B42: u/h | C42: =($T42*C$24+$U42*C$25+$V42*C$26+$W42*C$27+$X42*C$28+$Y42*C$29)/$B$2 -> 0.39584005 | D42: =($T42*D$24+$U42*D$25+$V42*D$26+$W42*D$27+$X42*D$28+$Y42*D$29)/$B$2 -> 0.32883725 | E42: =($T42*E$24+$U42*E$25+$V42*E$26+$W42*E$27+$X42*E$28+$Y42*E$29)/$B$2 -> 0.33971677 | F42: =($T42*F$24+$U42*F$25+$V42*F$26+$W42*F$27+$X42*F$28+$Y42*F$29)/$B$2 -> 0.32963331 | G42: =($T42*G$24+$U42*G$25+$V42*G$26+$W42*G$27+$X42*G$28+$Y42*G$29)/$B$2 -> 0.31875379 | H42: =($T42*H$24+$U42*H$25+$V42*H$26+$W42*H$27+$X42*H$28+$Y42*H$29)/$B$2 -> 0.30787427 | I42: =($T42*I$24+$U42*I$25+$V42*I$26+$W42*I$27+$X42*I$28+$Y42*I$29)/$B$2 -> 0.33042938 | J42: =($T42*J$24+$U42*J$25+$V42*J$26+$W42*J$27+$X42*J$28+$Y42*J$29)/$B$2 -> 0.33892071 | ... N42: =($T42*N$24+$U42*N$25+$V42*N$26+$W42*N$27+$X42*N$28+$Y42*N$29)/$B$2 -> 0.47426507 | O42: =MAX(C42:N42) -> 0.47426507 | P42: ='Parametros Recargas'!$M$96 -> 28.88381 | Q42: =MAX(1,ROUNDUP(O42/(P42*'Parametros Recargas'!B$8*'Parametros Recargas'!$B$19),0)) -> 1 | R42: =IF(AND('Parametros Recargas'!B$8=2,O42/(P42*Q42*'Parametros Recargas'!$B$19)>1),2,1) -> 1 | S42: =O42/(P42*Q42*R42) -> 0.016419755 | T42: ='Parametros Recargas'!D65 -> 0.25 | U42: ='Parametros Recargas'!E65 -> 0.25 | V42: ='Parametros Recargas'!F65 -> 0.25 | W42: ='Parametros Recargas'!G65 -> 0.5 | X42: ='Parametros Recargas'!H65 -> 0.25 | Y42: ='Parametros Recargas'!I65 -> 0.25 | Z42: ='Parametros Recargas'!$U$96/P42 -> 0.017310736
A43: Secado de cilindros (común) | B43: u/h | C43: =($T43*C$24+$U43*C$25+$V43*C$26+$W43*C$27+$X43*C$28+$Y43*C$29)/$B$2 -> 0.36495624 | D43: =($T43*D$24+$U43*D$25+$V43*D$26+$W43*D$27+$X43*D$28+$Y43*D$29)/$B$2 -> 0.30171976 | E43: =($T43*E$24+$U43*E$25+$V43*E$26+$W43*E$27+$X43*E$28+$Y43*E$29)/$B$2 -> 0.31090444 | F43: =($T43*F$24+$U43*F$25+$V43*F$26+$W43*F$27+$X43*F$28+$Y43*F$29)/$B$2 -> 0.30232751 | G43: =($T43*G$24+$U43*G$25+$V43*G$26+$W43*G$27+$X43*G$28+$Y43*G$29)/$B$2 -> 0.29314282 | H43: =($T43*H$24+$U43*H$25+$V43*H$26+$W43*H$27+$X43*H$28+$Y43*H$29)/$B$2 -> 0.28395814 | I43: =($T43*I$24+$U43*I$25+$V43*I$26+$W43*I$27+$X43*I$28+$Y43*I$29)/$B$2 -> 0.30293525 | J43: =($T43*J$24+$U43*J$25+$V43*J$26+$W43*J$27+$X43*J$28+$Y43*J$29)/$B$2 -> 0.31029669 | ... N43: =($T43*N$24+$U43*N$25+$V43*N$26+$W43*N$27+$X43*N$28+$Y43*N$29)/$B$2 -> 0.43773178 | O43: =MAX(C43:N43) -> 0.43773178 | P43: ='Parametros Recargas'!$M$97 -> 18.545455 | Q43: =MAX(1,ROUNDUP(O43/(P43*'Parametros Recargas'!B$8*'Parametros Recargas'!$B$19),0)) -> 1 | R43: =IF(AND('Parametros Recargas'!B$8=2,O43/(P43*Q43*'Parametros Recargas'!$B$19)>1),2,1) -> 1 | S43: =O43/(P43*Q43*R43) -> 0.023603184 | T43: ='Parametros Recargas'!D66 -> 0.25 | U43: ='Parametros Recargas'!E66 -> 0.25 | V43: ='Parametros Recargas'!F66 -> 0.25 | W43: ='Parametros Recargas'!G66 -> 0 | X43: ='Parametros Recargas'!H66 -> 0.25 | Y43: ='Parametros Recargas'!I66 -> 0.25 | Z43: ='Parametros Recargas'!$U$97/P43 -> 0.013480392
A44: Carga de polvo ABC (vacío, circuito cerrado, equipo exclusivo) | B44: u/h | C44: =($T44*C$24+$U44*C$25+$V44*C$26+$W44*C$27+$X44*C$28+$Y44*C$29)/$B$2 -> 1.3349202 | D44: =($T44*D$24+$U44*D$25+$V44*D$26+$W44*D$27+$X44*D$28+$Y44*D$29)/$B$2 -> 1.0958525 | E44: =($T44*E$24+$U44*E$25+$V44*E$26+$W44*E$27+$X44*E$28+$Y44*E$29)/$B$2 -> 1.1256521 | F44: =($T44*F$24+$U44*F$25+$V44*F$26+$W44*F$27+$X44*F$28+$Y44*F$29)/$B$2 -> 1.0982835 | G44: =($T44*G$24+$U44*G$25+$V44*G$26+$W44*G$27+$X44*G$28+$Y44*G$29)/$B$2 -> 1.068484 | H44: =($T44*H$24+$U44*H$25+$V44*H$26+$W44*H$27+$X44*H$28+$Y44*H$29)/$B$2 -> 1.0386844 | I44: =($T44*I$24+$U44*I$25+$V44*I$26+$W44*I$27+$X44*I$28+$Y44*I$29)/$B$2 -> 1.1007145 | J44: =($T44*J$24+$U44*J$25+$V44*J$26+$W44*J$27+$X44*J$28+$Y44*J$29)/$B$2 -> 1.1232211 | ... N44: =($T44*N$24+$U44*N$25+$V44*N$26+$W44*N$27+$X44*N$28+$Y44*N$29)/$B$2 -> 1.5982657 | O44: =MAX(C44:N44) -> 1.5982657 | P44: ='Parametros Recargas'!$M$98 -> 34 | Q44: =MAX(1,ROUNDUP(O44/(P44*'Parametros Recargas'!B$8*'Parametros Recargas'!$B$19),0)) -> 1 | R44: =IF(AND('Parametros Recargas'!B$8=2,O44/(P44*Q44*'Parametros Recargas'!$B$19)>1),2,1) -> 1 | S44: =O44/(P44*Q44*R44) -> 0.047007815 | T44: ='Parametros Recargas'!D67 -> 1 | U44: ='Parametros Recargas'!E67 -> 0 | V44: ='Parametros Recargas'!F67 -> 0 | W44: ='Parametros Recargas'!G67 -> 0 | X44: ='Parametros Recargas'!H67 -> 0 | Y44: ='Parametros Recargas'!I67 -> 0 | Z44: ='Parametros Recargas'!$U$98/P44 -> 0.014705882
A45: Carga de polvo BC (equipo exclusivo) | B45: u/h | C45: =($T45*C$24+$U45*C$25+$V45*C$26+$W45*C$27+$X45*C$28+$Y45*C$29)/$B$2 -> 0.0014380488 | D45: =($T45*D$24+$U45*D$25+$V45*D$26+$W45*D$27+$X45*D$28+$Y45*D$29)/$B$2 -> 0.0012782656 | E45: =($T45*E$24+$U45*E$25+$V45*E$26+$W45*E$27+$X45*E$28+$Y45*E$29)/$B$2 -> 0.0013581572 | F45: =($T45*F$24+$U45*F$25+$V45*F$26+$W45*F$27+$X45*F$28+$Y45*F$29)/$B$2 -> 0.0012782656 | G45: =($T45*G$24+$U45*G$25+$V45*G$26+$W45*G$27+$X45*G$28+$Y45*G$29)/$B$2 -> 0.001198374 | H45: =($T45*H$24+$U45*H$25+$V45*H$26+$W45*H$27+$X45*H$28+$Y45*H$29)/$B$2 -> 0.0011184824 | I45: =($T45*I$24+$U45*I$25+$V45*I$26+$W45*I$27+$X45*I$28+$Y45*I$29)/$B$2 -> 0.0012782656 | J45: =($T45*J$24+$U45*J$25+$V45*J$26+$W45*J$27+$X45*J$28+$Y45*J$29)/$B$2 -> 0.0013581572 | ... N45: =($T45*N$24+$U45*N$25+$V45*N$26+$W45*N$27+$X45*N$28+$Y45*N$29)/$B$2 -> 0.0017576152 | O45: =MAX(C45:N45) -> 0.0017576152 | P45: ='Parametros Recargas'!$M$99 -> 34 | Q45: =MAX(1,ROUNDUP(O45/(P45*'Parametros Recargas'!B$8*'Parametros Recargas'!$B$19),0)) -> 1 | R45: =IF(AND('Parametros Recargas'!B$8=2,O45/(P45*Q45*'Parametros Recargas'!$B$19)>1),2,1) -> 1 | S45: =O45/(P45*Q45*R45) -> 5.1694565e-05 | T45: ='Parametros Recargas'!D68 -> 0 | U45: ='Parametros Recargas'!E68 -> 1 | V45: ='Parametros Recargas'!F68 -> 0 | W45: ='Parametros Recargas'!G68 -> 0 | X45: ='Parametros Recargas'!H68 -> 0 | Y45: ='Parametros Recargas'!I68 -> 0 | Z45: ='Parametros Recargas'!$U$99/P45 -> 0.029411765
A46: Carga manual Clase D (embudo) | B46: u/h | C46: =($T46*C$24+$U46*C$25+$V46*C$26+$W46*C$27+$X46*C$28+$Y46*C$29)/$B$2 -> 0.0014380488 | D46: =($T46*D$24+$U46*D$25+$V46*D$26+$W46*D$27+$X46*D$28+$Y46*D$29)/$B$2 -> 0.0012782656 | E46: =($T46*E$24+$U46*E$25+$V46*E$26+$W46*E$27+$X46*E$28+$Y46*E$29)/$B$2 -> 0.0013581572 | F46: =($T46*F$24+$U46*F$25+$V46*F$26+$W46*F$27+$X46*F$28+$Y46*F$29)/$B$2 -> 0.0012782656 | G46: =($T46*G$24+$U46*G$25+$V46*G$26+$W46*G$27+$X46*G$28+$Y46*G$29)/$B$2 -> 0.001198374 | H46: =($T46*H$24+$U46*H$25+$V46*H$26+$W46*H$27+$X46*H$28+$Y46*H$29)/$B$2 -> 0.0011184824 | I46: =($T46*I$24+$U46*I$25+$V46*I$26+$W46*I$27+$X46*I$28+$Y46*I$29)/$B$2 -> 0.0012782656 | J46: =($T46*J$24+$U46*J$25+$V46*J$26+$W46*J$27+$X46*J$28+$Y46*J$29)/$B$2 -> 0.0013581572 | ... N46: =($T46*N$24+$U46*N$25+$V46*N$26+$W46*N$27+$X46*N$28+$Y46*N$29)/$B$2 -> 0.0017576152 | O46: =MAX(C46:N46) -> 0.0017576152 | P46: ='Parametros Recargas'!$M$100 -> 8.4375 | Q46: =MAX(1,ROUNDUP(O46/(P46*'Parametros Recargas'!B$8*'Parametros Recargas'!$B$19),0)) -> 1 | R46: =IF(AND('Parametros Recargas'!B$8=2,O46/(P46*Q46*'Parametros Recargas'!$B$19)>1),2,1) -> 1 | S46: =O46/(P46*Q46*R46) -> 0.00020830995 | T46: ='Parametros Recargas'!D69 -> 0 | U46: ='Parametros Recargas'!E69 -> 0 | V46: ='Parametros Recargas'!F69 -> 1 | W46: ='Parametros Recargas'!G69 -> 0 | X46: ='Parametros Recargas'!H69 -> 0 | Y46: ='Parametros Recargas'!I69 -> 0 | Z46: ='Parametros Recargas'!$U$100/P46 -> 0.11851852
A47: Llenado de agente líquido (agua / AFFF / K) | B47: u/h | C47: =($T47*C$24+$U47*C$25+$V47*C$26+$W47*C$27+$X47*C$28+$Y47*C$29)/$B$2 -> 0.06176762 | D47: =($T47*D$24+$U47*D$25+$V47*D$26+$W47*D$27+$X47*D$28+$Y47*D$29)/$B$2 -> 0.054234983 | E47: =($T47*E$24+$U47*E$25+$V47*E$26+$W47*E$27+$X47*E$28+$Y47*E$29)/$B$2 -> 0.05762467 | F47: =($T47*F$24+$U47*F$25+$V47*F$26+$W47*F$27+$X47*F$28+$Y47*F$29)/$B$2 -> 0.054611615 | G47: =($T47*G$24+$U47*G$25+$V47*G$26+$W47*G$27+$X47*G$28+$Y47*G$29)/$B$2 -> 0.051221929 | H47: =($T47*H$24+$U47*H$25+$V47*H$26+$W47*H$27+$X47*H$28+$Y47*H$29)/$B$2 -> 0.047832242 | I47: =($T47*I$24+$U47*I$25+$V47*I$26+$W47*I$27+$X47*I$28+$Y47*I$29)/$B$2 -> 0.054988247 | J47: =($T47*J$24+$U47*J$25+$V47*J$26+$W47*J$27+$X47*J$28+$Y47*J$29)/$B$2 -> 0.057248038 | ... N47: =($T47*N$24+$U47*N$25+$V47*N$26+$W47*N$27+$X47*N$28+$Y47*N$29)/$B$2 -> 0.073066575 | O47: =MAX(C47:N47) -> 0.073066575 | P47: ='Parametros Recargas'!$M$101 -> 18.298182 | Q47: =MAX(1,ROUNDUP(O47/(P47*'Parametros Recargas'!B$8*'Parametros Recargas'!$B$19),0)) -> 1 | R47: =IF(AND('Parametros Recargas'!B$8=2,O47/(P47*Q47*'Parametros Recargas'!$B$19)>1),2,1) -> 1 | S47: =O47/(P47*Q47*R47) -> 0.0039931057 | T47: ='Parametros Recargas'!D70 -> 0 | U47: ='Parametros Recargas'!E70 -> 0 | V47: ='Parametros Recargas'!F70 -> 0 | W47: ='Parametros Recargas'!G70 -> 1 | X47: ='Parametros Recargas'!H70 -> 0 | Y47: ='Parametros Recargas'!I70 -> 0 | Z47: ='Parametros Recargas'!$U$101/P47 -> 0.054650238
A48: Carga de CO₂ (trasvasador) | B48: u/h | C48: =($T48*C$24+$U48*C$25+$V48*C$26+$W48*C$27+$X48*C$28+$Y48*C$29)/$B$2 -> 0.041415806 | D48: =($T48*D$24+$U48*D$25+$V48*D$26+$W48*D$27+$X48*D$28+$Y48*D$29)/$B$2 -> 0.036814049 | E48: =($T48*E$24+$U48*E$25+$V48*E$26+$W48*E$27+$X48*E$28+$Y48*E$29)/$B$2 -> 0.039114927 | F48: =($T48*F$24+$U48*F$25+$V48*F$26+$W48*F$27+$X48*F$28+$Y48*F$29)/$B$2 -> 0.036814049 | G48: =($T48*G$24+$U48*G$25+$V48*G$26+$W48*G$27+$X48*G$28+$Y48*G$29)/$B$2 -> 0.034513171 | H48: =($T48*H$24+$U48*H$25+$V48*H$26+$W48*H$27+$X48*H$28+$Y48*H$29)/$B$2 -> 0.032212293 | I48: =($T48*I$24+$U48*I$25+$V48*I$26+$W48*I$27+$X48*I$28+$Y48*I$29)/$B$2 -> 0.036814049 | J48: =($T48*J$24+$U48*J$25+$V48*J$26+$W48*J$27+$X48*J$28+$Y48*J$29)/$B$2 -> 0.039114927 | ... N48: =($T48*N$24+$U48*N$25+$V48*N$26+$W48*N$27+$X48*N$28+$Y48*N$29)/$B$2 -> 0.050619318 | O48: =MAX(C48:N48) -> 0.050619318 | P48: ='Parametros Recargas'!$M$102 -> 15.692308 | Q48: =MAX(1,ROUNDUP(O48/(P48*'Parametros Recargas'!B$8*'Parametros Recargas'!$B$19),0)) -> 1 | R48: =IF(AND('Parametros Recargas'!B$8=2,O48/(P48*Q48*'Parametros Recargas'!$B$19)>1),2,1) -> 1 | S48: =O48/(P48*Q48*R48) -> 0.0032257408 | T48: ='Parametros Recargas'!D71 -> 0 | U48: ='Parametros Recargas'!E71 -> 0 | V48: ='Parametros Recargas'!F71 -> 0 | W48: ='Parametros Recargas'!G71 -> 0 | X48: ='Parametros Recargas'!H71 -> 0.35 | Y48: ='Parametros Recargas'!I71 -> 0 | Z48: ='Parametros Recargas'!$U$102/P48 -> 0.06372549
A49: Carga de agente limpio | B49: u/h | C49: =($T49*C$24+$U49*C$25+$V49*C$26+$W49*C$27+$X49*C$28+$Y49*C$29)/$B$2 -> 0.0012942439 | D49: =($T49*D$24+$U49*D$25+$V49*D$26+$W49*D$27+$X49*D$28+$Y49*D$29)/$B$2 -> 0.001150439 | E49: =($T49*E$24+$U49*E$25+$V49*E$26+$W49*E$27+$X49*E$28+$Y49*E$29)/$B$2 -> 0.0012223415 | F49: =($T49*F$24+$U49*F$25+$V49*F$26+$W49*F$27+$X49*F$28+$Y49*F$29)/$B$2 -> 0.001150439 | G49: =($T49*G$24+$U49*G$25+$V49*G$26+$W49*G$27+$X49*G$28+$Y49*G$29)/$B$2 -> 0.0010785366 | H49: =($T49*H$24+$U49*H$25+$V49*H$26+$W49*H$27+$X49*H$28+$Y49*H$29)/$B$2 -> 0.0010066342 | I49: =($T49*I$24+$U49*I$25+$V49*I$26+$W49*I$27+$X49*I$28+$Y49*I$29)/$B$2 -> 0.001150439 | J49: =($T49*J$24+$U49*J$25+$V49*J$26+$W49*J$27+$X49*J$28+$Y49*J$29)/$B$2 -> 0.0012223415 | ... N49: =($T49*N$24+$U49*N$25+$V49*N$26+$W49*N$27+$X49*N$28+$Y49*N$29)/$B$2 -> 0.0015818537 | O49: =MAX(C49:N49) -> 0.0015818537 | P49: ='Parametros Recargas'!$M$103 -> 12 | Q49: =MAX(1,ROUNDUP(O49/(P49*'Parametros Recargas'!B$8*'Parametros Recargas'!$B$19),0)) -> 1 | R49: =IF(AND('Parametros Recargas'!B$8=2,O49/(P49*Q49*'Parametros Recargas'!$B$19)>1),2,1) -> 1 | S49: =O49/(P49*Q49*R49) -> 0.00013182114 | T49: ='Parametros Recargas'!D72 -> 0 | U49: ='Parametros Recargas'!E72 -> 0 | V49: ='Parametros Recargas'!F72 -> 0 | W49: ='Parametros Recargas'!G72 -> 0 | X49: ='Parametros Recargas'!H72 -> 0 | Y49: ='Parametros Recargas'!I72 -> 0.35 | Z49: ='Parametros Recargas'!$U$103/P49 -> 0.083333333
A50: Ensamblaje (común) | B50: u/h | C50: =($T50*C$24+$U50*C$25+$V50*C$26+$W50*C$27+$X50*C$28+$Y50*C$29)/$B$2 -> 1.4422739 | D50: =($T50*D$24+$U50*D$25+$V50*D$26+$W50*D$27+$X50*D$28+$Y50*D$29)/$B$2 -> 1.1906085 | E50: =($T50*E$24+$U50*E$25+$V50*E$26+$W50*E$27+$X50*E$28+$Y50*E$29)/$B$2 -> 1.2263304 | F50: =($T50*F$24+$U50*F$25+$V50*F$26+$W50*F$27+$X50*F$28+$Y50*F$29)/$B$2 -> 1.1934162 | G50: =($T50*G$24+$U50*G$25+$V50*G$26+$W50*G$27+$X50*G$28+$Y50*G$29)/$B$2 -> 1.1576943 | H50: =($T50*H$24+$U50*H$25+$V50*H$26+$W50*H$27+$X50*H$28+$Y50*H$29)/$B$2 -> 1.1219725 | I50: =($T50*I$24+$U50*I$25+$V50*I$26+$W50*I$27+$X50*I$28+$Y50*I$29)/$B$2 -> 1.1962238 | J50: =($T50*J$24+$U50*J$25+$V50*J$26+$W50*J$27+$X50*J$28+$Y50*J$29)/$B$2 -> 1.2235227 | ... N50: =($T50*N$24+$U50*N$25+$V50*N$26+$W50*N$27+$X50*N$28+$Y50*N$29)/$B$2 -> 1.7270487 | O50: =MAX(C50:N50) -> 1.7270487 | P50: ='Parametros Recargas'!$M$104 -> 25.043478 | Q50: =MAX(1,ROUNDUP(O50/(P50*'Parametros Recargas'!B$8*'Parametros Recargas'!$B$19),0)) -> 1 | R50: =IF(AND('Parametros Recargas'!B$8=2,O50/(P50*Q50*'Parametros Recargas'!$B$19)>1),2,1) -> 1 | S50: =O50/(P50*Q50*R50) -> 0.068962013 | T50: ='Parametros Recargas'!D73 -> 1 | U50: ='Parametros Recargas'!E73 -> 1 | V50: ='Parametros Recargas'!F73 -> 1 | W50: ='Parametros Recargas'!G73 -> 1 | X50: ='Parametros Recargas'!H73 -> 0.35 | Y50: ='Parametros Recargas'!I73 -> 0.35 | Z50: ='Parametros Recargas'!$U$104/P50 -> 0.039930556
A51: Presurización con N₂ (común) | B51: u/h | C51: =($T51*C$24+$U51*C$25+$V51*C$26+$W51*C$27+$X51*C$28+$Y51*C$29)/$B$2 -> 1.4008581 | D51: =($T51*D$24+$U51*D$25+$V51*D$26+$W51*D$27+$X51*D$28+$Y51*D$29)/$B$2 -> 1.1537945 | E51: =($T51*E$24+$U51*E$25+$V51*E$26+$W51*E$27+$X51*E$28+$Y51*E$29)/$B$2 -> 1.1872154 | F51: =($T51*F$24+$U51*F$25+$V51*F$26+$W51*F$27+$X51*F$28+$Y51*F$29)/$B$2 -> 1.1566021 | G51: =($T51*G$24+$U51*G$25+$V51*G$26+$W51*G$27+$X51*G$28+$Y51*G$29)/$B$2 -> 1.1231812 | H51: =($T51*H$24+$U51*H$25+$V51*H$26+$W51*H$27+$X51*H$28+$Y51*H$29)/$B$2 -> 1.0897602 | I51: =($T51*I$24+$U51*I$25+$V51*I$26+$W51*I$27+$X51*I$28+$Y51*I$29)/$B$2 -> 1.1594097 | J51: =($T51*J$24+$U51*J$25+$V51*J$26+$W51*J$27+$X51*J$28+$Y51*J$29)/$B$2 -> 1.1844078 | ... N51: =($T51*N$24+$U51*N$25+$V51*N$26+$W51*N$27+$X51*N$28+$Y51*N$29)/$B$2 -> 1.6764294 | O51: =MAX(C51:N51) -> 1.6764294 | P51: ='Parametros Recargas'!$M$105 -> 52.363636 | Q51: =MAX(1,ROUNDUP(O51/(P51*'Parametros Recargas'!B$8*'Parametros Recargas'!$B$19),0)) -> 1 | R51: =IF(AND('Parametros Recargas'!B$8=2,O51/(P51*Q51*'Parametros Recargas'!$B$19)>1),2,1) -> 1 | S51: =O51/(P51*Q51*R51) -> 0.032015144 | T51: ='Parametros Recargas'!D74 -> 1 | U51: ='Parametros Recargas'!E74 -> 1 | V51: ='Parametros Recargas'!F74 -> 1 | W51: ='Parametros Recargas'!G74 -> 1 | X51: ='Parametros Recargas'!H74 -> 0 | Y51: ='Parametros Recargas'!I74 -> 0.35 | Z51: ='Parametros Recargas'!$U$105/P51 -> 0.019097222
A52: Ensayo de peso (control de masa) (común) | B52: u/h | C52: =($T52*C$24+$U52*C$25+$V52*C$26+$W52*C$27+$X52*C$28+$Y52*C$29)/$B$2 -> 0.12202871 | D52: =($T52*D$24+$U52*D$25+$V52*D$26+$W52*D$27+$X52*D$28+$Y52*D$29)/$B$2 -> 0.10846997 | E52: =($T52*E$24+$U52*E$25+$V52*E$26+$W52*E$27+$X52*E$28+$Y52*E$29)/$B$2 -> 0.11524934 | F52: =($T52*F$24+$U52*F$25+$V52*F$26+$W52*F$27+$X52*F$28+$Y52*F$29)/$B$2 -> 0.10846997 | G52: =($T52*G$24+$U52*G$25+$V52*G$26+$W52*G$27+$X52*G$28+$Y52*G$29)/$B$2 -> 0.10169059 | H52: =($T52*H$24+$U52*H$25+$V52*H$26+$W52*H$27+$X52*H$28+$Y52*H$29)/$B$2 -> 0.094911221 | I52: =($T52*I$24+$U52*I$25+$V52*I$26+$W52*I$27+$X52*I$28+$Y52*I$29)/$B$2 -> 0.10846997 | J52: =($T52*J$24+$U52*J$25+$V52*J$26+$W52*J$27+$X52*J$28+$Y52*J$29)/$B$2 -> 0.11524934 | ... N52: =($T52*N$24+$U52*N$25+$V52*N$26+$W52*N$27+$X52*N$28+$Y52*N$29)/$B$2 -> 0.1491462 | O52: =MAX(C52:N52) -> 0.1491462 | P52: ='Parametros Recargas'!$M$106 -> 55.636364 | Q52: =MAX(1,ROUNDUP(O52/(P52*'Parametros Recargas'!B$8*'Parametros Recargas'!$B$19),0)) -> 1 | R52: =IF(AND('Parametros Recargas'!B$8=2,O52/(P52*Q52*'Parametros Recargas'!$B$19)>1),2,1) -> 1 | S52: =O52/(P52*Q52*R52) -> 0.0026807324 | T52: ='Parametros Recargas'!D75 -> 0 | U52: ='Parametros Recargas'!E75 -> 0 | V52: ='Parametros Recargas'!F75 -> 0 | W52: ='Parametros Recargas'!G75 -> 0 | X52: ='Parametros Recargas'!H75 -> 1 | Y52: ='Parametros Recargas'!I75 -> 1 | Z52: ='Parametros Recargas'!$U$106/P52 -> 0.017973856
A53: Ensayo de hermeticidad (inmersión) (común) | B53: u/h | C53: =($T53*C$24+$U53*C$25+$V53*C$26+$W53*C$27+$X53*C$28+$Y53*C$29)/$B$2 -> 1.5215926 | D53: =($T53*D$24+$U53*D$25+$V53*D$26+$W53*D$27+$X53*D$28+$Y53*D$29)/$B$2 -> 1.261114 | E53: =($T53*E$24+$U53*E$25+$V53*E$26+$W53*E$27+$X53*E$28+$Y53*E$29)/$B$2 -> 1.3012424 | F53: =($T53*F$24+$U53*F$25+$V53*F$26+$W53*F$27+$X53*F$28+$Y53*F$29)/$B$2 -> 1.2639216 | G53: =($T53*G$24+$U53*G$25+$V53*G$26+$W53*G$27+$X53*G$28+$Y53*G$29)/$B$2 -> 1.2237932 | H53: =($T53*H$24+$U53*H$25+$V53*H$26+$W53*H$27+$X53*H$28+$Y53*H$29)/$B$2 -> 1.1836648 | I53: =($T53*I$24+$U53*I$25+$V53*I$26+$W53*I$27+$X53*I$28+$Y53*I$29)/$B$2 -> 1.2667293 | J53: =($T53*J$24+$U53*J$25+$V53*J$26+$W53*J$27+$X53*J$28+$Y53*J$29)/$B$2 -> 1.2984348 | ... N53: =($T53*N$24+$U53*N$25+$V53*N$26+$W53*N$27+$X53*N$28+$Y53*N$29)/$B$2 -> 1.8239937 | O53: =MAX(C53:N53) -> 1.8239937 | P53: ='Parametros Recargas'!$M$107 -> 76.5 | Q53: =MAX(1,ROUNDUP(O53/(P53*'Parametros Recargas'!B$8*'Parametros Recargas'!$B$19),0)) -> 1 | R53: =IF(AND('Parametros Recargas'!B$8=2,O53/(P53*Q53*'Parametros Recargas'!$B$19)>1),2,1) -> 1 | S53: =O53/(P53*Q53*R53) -> 0.023843055 | T53: ='Parametros Recargas'!D76 -> 1 | U53: ='Parametros Recargas'!E76 -> 1 | V53: ='Parametros Recargas'!F76 -> 1 | W53: ='Parametros Recargas'!G76 -> 1 | X53: ='Parametros Recargas'!H76 -> 1 | Y53: ='Parametros Recargas'!I76 -> 1 | Z53: ='Parametros Recargas'!$U$107/P53 -> 0.0032679739
A54: Retoque de pintura (común) | B54: u/h | C54: =($T54*C$24+$U54*C$25+$V54*C$26+$W54*C$27+$X54*C$28+$Y54*C$29)/$B$2 -> 0.22823889 | D54: =($T54*D$24+$U54*D$25+$V54*D$26+$W54*D$27+$X54*D$28+$Y54*D$29)/$B$2 -> 0.1891671 | E54: =($T54*E$24+$U54*E$25+$V54*E$26+$W54*E$27+$X54*E$28+$Y54*E$29)/$B$2 -> 0.19518636 | F54: =($T54*F$24+$U54*F$25+$V54*F$26+$W54*F$27+$X54*F$28+$Y54*F$29)/$B$2 -> 0.18958825 | G54: =($T54*G$24+$U54*G$25+$V54*G$26+$W54*G$27+$X54*G$28+$Y54*G$29)/$B$2 -> 0.18356898 | H54: =($T54*H$24+$U54*H$25+$V54*H$26+$W54*H$27+$X54*H$28+$Y54*H$29)/$B$2 -> 0.17754972 | I54: =($T54*I$24+$U54*I$25+$V54*I$26+$W54*I$27+$X54*I$28+$Y54*I$29)/$B$2 -> 0.19000939 | J54: =($T54*J$24+$U54*J$25+$V54*J$26+$W54*J$27+$X54*J$28+$Y54*J$29)/$B$2 -> 0.19476522 | ... N54: =($T54*N$24+$U54*N$25+$V54*N$26+$W54*N$27+$X54*N$28+$Y54*N$29)/$B$2 -> 0.27359906 | O54: =MAX(C54:N54) -> 0.27359906 | P54: ='Parametros Recargas'!$M$108 -> 8 | Q54: =MAX(1,ROUNDUP(O54/(P54*'Parametros Recargas'!B$8*'Parametros Recargas'!$B$19),0)) -> 1 | R54: =IF(AND('Parametros Recargas'!B$8=2,O54/(P54*Q54*'Parametros Recargas'!$B$19)>1),2,1) -> 1 | S54: =O54/(P54*Q54*R54) -> 0.034199882 | T54: ='Parametros Recargas'!D77 -> 0.15 | U54: ='Parametros Recargas'!E77 -> 0.15 | V54: ='Parametros Recargas'!F77 -> 0.15 | W54: ='Parametros Recargas'!G77 -> 0.15 | X54: ='Parametros Recargas'!H77 -> 0.15 | Y54: ='Parametros Recargas'!I77 -> 0.15 | Z54: ='Parametros Recargas'!$U$108/P54 -> 0.125
A55: Etiquetado (oblea IRAM + marbete) (común) | B55: u/h | C55: =($T55*C$24+$U55*C$25+$V55*C$26+$W55*C$27+$X55*C$28+$Y55*C$29)/$B$2 -> 1.5215926 | D55: =($T55*D$24+$U55*D$25+$V55*D$26+$W55*D$27+$X55*D$28+$Y55*D$29)/$B$2 -> 1.261114 | E55: =($T55*E$24+$U55*E$25+$V55*E$26+$W55*E$27+$X55*E$28+$Y55*E$29)/$B$2 -> 1.3012424 | F55: =($T55*F$24+$U55*F$25+$V55*F$26+$W55*F$27+$X55*F$28+$Y55*F$29)/$B$2 -> 1.2639216 | G55: =($T55*G$24+$U55*G$25+$V55*G$26+$W55*G$27+$X55*G$28+$Y55*G$29)/$B$2 -> 1.2237932 | H55: =($T55*H$24+$U55*H$25+$V55*H$26+$W55*H$27+$X55*H$28+$Y55*H$29)/$B$2 -> 1.1836648 | I55: =($T55*I$24+$U55*I$25+$V55*I$26+$W55*I$27+$X55*I$28+$Y55*I$29)/$B$2 -> 1.2667293 | J55: =($T55*J$24+$U55*J$25+$V55*J$26+$W55*J$27+$X55*J$28+$Y55*J$29)/$B$2 -> 1.2984348 | ... N55: =($T55*N$24+$U55*N$25+$V55*N$26+$W55*N$27+$X55*N$28+$Y55*N$29)/$B$2 -> 1.8239937 | O55: =MAX(C55:N55) -> 1.8239937 | P55: ='Parametros Recargas'!$M$109 -> 52.363636 | Q55: =MAX(1,ROUNDUP(O55/(P55*'Parametros Recargas'!B$8*'Parametros Recargas'!$B$19),0)) -> 1 | R55: =IF(AND('Parametros Recargas'!B$8=2,O55/(P55*Q55*'Parametros Recargas'!$B$19)>1),2,1) -> 1 | S55: =O55/(P55*Q55*R55) -> 0.034833213 | T55: ='Parametros Recargas'!D78 -> 1 | U55: ='Parametros Recargas'!E78 -> 1 | V55: ='Parametros Recargas'!F78 -> 1 | W55: ='Parametros Recargas'!G78 -> 1 | X55: ='Parametros Recargas'!H78 -> 1 | Y55: ='Parametros Recargas'!I78 -> 1 | Z55: ='Parametros Recargas'!$U$109/P55 -> 0.019097222
A56: Despacho (común) | B56: u/h | C56: =($T56*C$24+$U56*C$25+$V56*C$26+$W56*C$27+$X56*C$28+$Y56*C$29)/$B$2 -> 1.5215926 | D56: =($T56*D$24+$U56*D$25+$V56*D$26+$W56*D$27+$X56*D$28+$Y56*D$29)/$B$2 -> 1.261114 | E56: =($T56*E$24+$U56*E$25+$V56*E$26+$W56*E$27+$X56*E$28+$Y56*E$29)/$B$2 -> 1.3012424 | F56: =($T56*F$24+$U56*F$25+$V56*F$26+$W56*F$27+$X56*F$28+$Y56*F$29)/$B$2 -> 1.2639216 | G56: =($T56*G$24+$U56*G$25+$V56*G$26+$W56*G$27+$X56*G$28+$Y56*G$29)/$B$2 -> 1.2237932 | H56: =($T56*H$24+$U56*H$25+$V56*H$26+$W56*H$27+$X56*H$28+$Y56*H$29)/$B$2 -> 1.1836648 | I56: =($T56*I$24+$U56*I$25+$V56*I$26+$W56*I$27+$X56*I$28+$Y56*I$29)/$B$2 -> 1.2667293 | J56: =($T56*J$24+$U56*J$25+$V56*J$26+$W56*J$27+$X56*J$28+$Y56*J$29)/$B$2 -> 1.2984348 | ... N56: =($T56*N$24+$U56*N$25+$V56*N$26+$W56*N$27+$X56*N$28+$Y56*N$29)/$B$2 -> 1.8239937 | O56: =MAX(C56:N56) -> 1.8239937 | P56: ='Parametros Recargas'!$M$110 -> 57.6 | Q56: =MAX(1,ROUNDUP(O56/(P56*'Parametros Recargas'!B$8*'Parametros Recargas'!$B$19),0)) -> 1 | R56: =IF(AND('Parametros Recargas'!B$8=2,O56/(P56*Q56*'Parametros Recargas'!$B$19)>1),2,1) -> 1 | S56: =O56/(P56*Q56*R56) -> 0.031666558 | T56: ='Parametros Recargas'!D79 -> 1 | U56: ='Parametros Recargas'!E79 -> 1 | V56: ='Parametros Recargas'!F79 -> 1 | W56: ='Parametros Recargas'!G79 -> 1 | X56: ='Parametros Recargas'!H79 -> 1 | Y56: ='Parametros Recargas'!I79 -> 1 | Z56: ='Parametros Recargas'!$U$110/P56 -> 0.017361111
A57: Horas-hombre de recargas (h/mes) | B57: h | C57: =SUMPRODUCT(C31:C56,$Z31:$Z56)*$B$2 -> 52.198458 | D57: =SUMPRODUCT(D31:D56,$Z31:$Z56)*$B$2 -> 43.247114 | E57: =SUMPRODUCT(E31:E56,$Z31:$Z56)*$B$2 -> 44.620181 | F57: =SUMPRODUCT(F31:F56,$Z31:$Z56)*$B$2 -> 43.348969 | G57: =SUMPRODUCT(G31:G56,$Z31:$Z56)*$B$2 -> 41.975903 | H57: =SUMPRODUCT(H31:H56,$Z31:$Z56)*$B$2 -> 40.602836 | I57: =SUMPRODUCT(I31:I56,$Z31:$Z56)*$B$2 -> 43.450824 | J57: =SUMPRODUCT(J31:J56,$Z31:$Z56)*$B$2 -> 44.518326 | ... N57: =SUMPRODUCT(N31:N56,$Z31:$Z56)*$B$2 -> 62.535506 | O57: =MAX(C57:N57) -> 62.535506
A59: AÑO 2027
A60: Demanda por tipo (u. eq./mes) | B60: Familia | C60: Ene | D60: Feb | E60: Mar | F60: Abr | G60: May | H60: Jun | I60: Jul | J60: Ago | K60: Sep | L60: Oct | M60: Nov | N60: Dic | O60: Total
A61: =datos_base!$A$55 -> ABC 1 kg | B61: Polvo ABC | C61: =datos_base!$C$55*'Parametros Recargas'!D$33*'Parametros Recargas'!$Q$33 -> 581.07443 | D61: =datos_base!$C$55*'Parametros Recargas'!E$33*'Parametros Recargas'!$Q$33 -> 453.23806 | E61: =datos_base!$C$55*'Parametros Recargas'!F$33*'Parametros Recargas'!$Q$33 -> 453.23806 | F61: =datos_base!$C$55*'Parametros Recargas'!G$33*'Parametros Recargas'!$Q$33 -> 453.23806 | G61: =datos_base!$C$55*'Parametros Recargas'!H$33*'Parametros Recargas'!$Q$33 -> 453.23806 | H61: =datos_base!$C$55*'Parametros Recargas'!I$33*'Parametros Recargas'!$Q$33 -> 453.23806 | I61: =datos_base!$C$55*'Parametros Recargas'!J$33*'Parametros Recargas'!$Q$33 -> 453.23806 | J61: =datos_base!$C$55*'Parametros Recargas'!K$33*'Parametros Recargas'!$Q$33 -> 453.23806 | ... N61: =datos_base!$C$55*'Parametros Recargas'!O$33*'Parametros Recargas'!$Q$33 -> 697.28932 | O61: =SUM(C61:N61) -> 5810.7443
A62: =datos_base!$A$56 -> ABC 2,5 kg | B62: Polvo ABC | C62: =datos_base!$C$56*'Parametros Recargas'!D$34*'Parametros Recargas'!$Q$34 -> 39.659332 | D62: =datos_base!$C$56*'Parametros Recargas'!E$34*'Parametros Recargas'!$Q$34 -> 35.252739 | E62: =datos_base!$C$56*'Parametros Recargas'!F$34*'Parametros Recargas'!$Q$34 -> 37.456035 | F62: =datos_base!$C$56*'Parametros Recargas'!G$34*'Parametros Recargas'!$Q$34 -> 35.252739 | G62: =datos_base!$C$56*'Parametros Recargas'!H$34*'Parametros Recargas'!$Q$34 -> 33.049443 | H62: =datos_base!$C$56*'Parametros Recargas'!I$34*'Parametros Recargas'!$Q$34 -> 30.846147 | I62: =datos_base!$C$56*'Parametros Recargas'!J$34*'Parametros Recargas'!$Q$34 -> 35.252739 | J62: =datos_base!$C$56*'Parametros Recargas'!K$34*'Parametros Recargas'!$Q$34 -> 37.456035 | ... N62: =datos_base!$C$56*'Parametros Recargas'!O$34*'Parametros Recargas'!$Q$34 -> 48.472516 | O62: =SUM(C62:N62) -> 440.65924
A63: =datos_base!$A$57 -> ABC 5 kg | B63: Polvo ABC | C63: =datos_base!$C$57*'Parametros Recargas'!D$35*'Parametros Recargas'!$Q$35 -> 241.9928 | D63: =datos_base!$C$57*'Parametros Recargas'!E$35*'Parametros Recargas'!$Q$35 -> 215.10471 | E63: =datos_base!$C$57*'Parametros Recargas'!F$35*'Parametros Recargas'!$Q$35 -> 228.54875 | F63: =datos_base!$C$57*'Parametros Recargas'!G$35*'Parametros Recargas'!$Q$35 -> 215.10471 | G63: =datos_base!$C$57*'Parametros Recargas'!H$35*'Parametros Recargas'!$Q$35 -> 201.66067 | H63: =datos_base!$C$57*'Parametros Recargas'!I$35*'Parametros Recargas'!$Q$35 -> 188.21662 | I63: =datos_base!$C$57*'Parametros Recargas'!J$35*'Parametros Recargas'!$Q$35 -> 215.10471 | J63: =datos_base!$C$57*'Parametros Recargas'!K$35*'Parametros Recargas'!$Q$35 -> 228.54875 | ... N63: =datos_base!$C$57*'Parametros Recargas'!O$35*'Parametros Recargas'!$Q$35 -> 295.76898 | O63: =SUM(C63:N63) -> 2688.8089
A64: =datos_base!$A$58 -> ABC 10 kg | B64: Polvo ABC | C64: =datos_base!$C$58*'Parametros Recargas'!D$36*'Parametros Recargas'!$Q$36 -> 13.4663 | D64: =datos_base!$C$58*'Parametros Recargas'!E$36*'Parametros Recargas'!$Q$36 -> 11.970044 | E64: =datos_base!$C$58*'Parametros Recargas'!F$36*'Parametros Recargas'!$Q$36 -> 12.718172 | F64: =datos_base!$C$58*'Parametros Recargas'!G$36*'Parametros Recargas'!$Q$36 -> 11.970044 | G64: =datos_base!$C$58*'Parametros Recargas'!H$36*'Parametros Recargas'!$Q$36 -> 11.221917 | H64: =datos_base!$C$58*'Parametros Recargas'!I$36*'Parametros Recargas'!$Q$36 -> 10.473789 | I64: =datos_base!$C$58*'Parametros Recargas'!J$36*'Parametros Recargas'!$Q$36 -> 11.970044 | J64: =datos_base!$C$58*'Parametros Recargas'!K$36*'Parametros Recargas'!$Q$36 -> 12.718172 | ... N64: =datos_base!$C$58*'Parametros Recargas'!O$36*'Parametros Recargas'!$Q$36 -> 16.458811 | O64: =SUM(C64:N64) -> 149.62555
A65: =datos_base!$A$69 -> ABC 25 kg s/ruedas | B65: Polvo ABC | C65: =datos_base!$C$69*'Parametros Recargas'!D$37*'Parametros Recargas'!$Q$37 -> 8.8337284 | D65: =datos_base!$C$69*'Parametros Recargas'!E$37*'Parametros Recargas'!$Q$37 -> 7.0669827 | E65: =datos_base!$C$69*'Parametros Recargas'!F$37*'Parametros Recargas'!$Q$37 -> 7.5086691 | F65: =datos_base!$C$69*'Parametros Recargas'!G$37*'Parametros Recargas'!$Q$37 -> 7.5086691 | G65: =datos_base!$C$69*'Parametros Recargas'!H$37*'Parametros Recargas'!$Q$37 -> 7.0669827 | H65: =datos_base!$C$69*'Parametros Recargas'!I$37*'Parametros Recargas'!$Q$37 -> 6.6252963 | I65: =datos_base!$C$69*'Parametros Recargas'!J$37*'Parametros Recargas'!$Q$37 -> 7.9503555 | J65: =datos_base!$C$69*'Parametros Recargas'!K$37*'Parametros Recargas'!$Q$37 -> 7.0669827 | ... N65: =datos_base!$C$69*'Parametros Recargas'!O$37*'Parametros Recargas'!$Q$37 -> 7.9503555 | O65: =SUM(C65:N65) -> 88.337284
A66: =datos_base!$A$70 -> ABC 50 kg s/ruedas | B66: Polvo ABC | C66: =datos_base!$C$70*'Parametros Recargas'!D$38*'Parametros Recargas'!$Q$38 -> 19.413659 | D66: =datos_base!$C$70*'Parametros Recargas'!E$38*'Parametros Recargas'!$Q$38 -> 15.530927 | E66: =datos_base!$C$70*'Parametros Recargas'!F$38*'Parametros Recargas'!$Q$38 -> 16.50161 | F66: =datos_base!$C$70*'Parametros Recargas'!G$38*'Parametros Recargas'!$Q$38 -> 16.50161 | G66: =datos_base!$C$70*'Parametros Recargas'!H$38*'Parametros Recargas'!$Q$38 -> 15.530927 | H66: =datos_base!$C$70*'Parametros Recargas'!I$38*'Parametros Recargas'!$Q$38 -> 14.560244 | I66: =datos_base!$C$70*'Parametros Recargas'!J$38*'Parametros Recargas'!$Q$38 -> 17.472293 | J66: =datos_base!$C$70*'Parametros Recargas'!K$38*'Parametros Recargas'!$Q$38 -> 15.530927 | ... N66: =datos_base!$C$70*'Parametros Recargas'!O$38*'Parametros Recargas'!$Q$38 -> 17.472293 | O66: =SUM(C66:N66) -> 194.13659
A67: =datos_base!$A$71 -> ABC 70 kg s/ruedas | B67: Polvo ABC | C67: =datos_base!$C$71*'Parametros Recargas'!D$39*'Parametros Recargas'!$Q$39 -> 4.2114286 | D67: =datos_base!$C$71*'Parametros Recargas'!E$39*'Parametros Recargas'!$Q$39 -> 3.3691429 | E67: =datos_base!$C$71*'Parametros Recargas'!F$39*'Parametros Recargas'!$Q$39 -> 3.5797143 | F67: =datos_base!$C$71*'Parametros Recargas'!G$39*'Parametros Recargas'!$Q$39 -> 3.5797143 | G67: =datos_base!$C$71*'Parametros Recargas'!H$39*'Parametros Recargas'!$Q$39 -> 3.3691429 | H67: =datos_base!$C$71*'Parametros Recargas'!I$39*'Parametros Recargas'!$Q$39 -> 3.1585715 | I67: =datos_base!$C$71*'Parametros Recargas'!J$39*'Parametros Recargas'!$Q$39 -> 3.7902858 | J67: =datos_base!$C$71*'Parametros Recargas'!K$39*'Parametros Recargas'!$Q$39 -> 3.3691429 | ... N67: =datos_base!$C$71*'Parametros Recargas'!O$39*'Parametros Recargas'!$Q$39 -> 3.7902858 | O67: =SUM(C67:N67) -> 42.114286
A68: =datos_base!$A$72 -> ABC 100 kg s/ruedas | B68: Polvo ABC | C68: =datos_base!$C$72*'Parametros Recargas'!D$40*'Parametros Recargas'!$Q$40 -> 2.8760976 | D68: =datos_base!$C$72*'Parametros Recargas'!E$40*'Parametros Recargas'!$Q$40 -> 2.3008781 | E68: =datos_base!$C$72*'Parametros Recargas'!F$40*'Parametros Recargas'!$Q$40 -> 2.444683 | F68: =datos_base!$C$72*'Parametros Recargas'!G$40*'Parametros Recargas'!$Q$40 -> 2.444683 | G68: =datos_base!$C$72*'Parametros Recargas'!H$40*'Parametros Recargas'!$Q$40 -> 2.3008781 | H68: =datos_base!$C$72*'Parametros Recargas'!I$40*'Parametros Recargas'!$Q$40 -> 2.1570732 | I68: =datos_base!$C$72*'Parametros Recargas'!J$40*'Parametros Recargas'!$Q$40 -> 2.5884878 | J68: =datos_base!$C$72*'Parametros Recargas'!K$40*'Parametros Recargas'!$Q$40 -> 2.3008781 | ... N68: =datos_base!$C$72*'Parametros Recargas'!O$40*'Parametros Recargas'!$Q$40 -> 2.5884878 | O68: =SUM(C68:N68) -> 28.760976
A69: =datos_base!$A$62 -> BC 5 kg | B69: Polvo BC | C69: =datos_base!$C$62*'Parametros Recargas'!D$41*'Parametros Recargas'!$Q$41 -> 1.4483206 | D69: =datos_base!$C$62*'Parametros Recargas'!E$41*'Parametros Recargas'!$Q$41 -> 1.2873961 | E69: =datos_base!$C$62*'Parametros Recargas'!F$41*'Parametros Recargas'!$Q$41 -> 1.3678583 | F69: =datos_base!$C$62*'Parametros Recargas'!G$41*'Parametros Recargas'!$Q$41 -> 1.2873961 | G69: =datos_base!$C$62*'Parametros Recargas'!H$41*'Parametros Recargas'!$Q$41 -> 1.2069338 | H69: =datos_base!$C$62*'Parametros Recargas'!I$41*'Parametros Recargas'!$Q$41 -> 1.1264716 | I69: =datos_base!$C$62*'Parametros Recargas'!J$41*'Parametros Recargas'!$Q$41 -> 1.2873961 | J69: =datos_base!$C$62*'Parametros Recargas'!K$41*'Parametros Recargas'!$Q$41 -> 1.3678583 | ... N69: =datos_base!$C$62*'Parametros Recargas'!O$41*'Parametros Recargas'!$Q$41 -> 1.7701696 | O69: =SUM(C69:N69) -> 16.092451
A70: =datos_base!$A$68 -> Clase D 9 l | B70: Polvo Clase D | C70: =datos_base!$C$68*'Parametros Recargas'!D$42*'Parametros Recargas'!$Q$42 -> 1.4483206 | D70: =datos_base!$C$68*'Parametros Recargas'!E$42*'Parametros Recargas'!$Q$42 -> 1.2873961 | E70: =datos_base!$C$68*'Parametros Recargas'!F$42*'Parametros Recargas'!$Q$42 -> 1.3678583 | F70: =datos_base!$C$68*'Parametros Recargas'!G$42*'Parametros Recargas'!$Q$42 -> 1.2873961 | G70: =datos_base!$C$68*'Parametros Recargas'!H$42*'Parametros Recargas'!$Q$42 -> 1.2069338 | H70: =datos_base!$C$68*'Parametros Recargas'!I$42*'Parametros Recargas'!$Q$42 -> 1.1264716 | I70: =datos_base!$C$68*'Parametros Recargas'!J$42*'Parametros Recargas'!$Q$42 -> 1.2873961 | J70: =datos_base!$C$68*'Parametros Recargas'!K$42*'Parametros Recargas'!$Q$42 -> 1.3678583 | ... N70: =datos_base!$C$68*'Parametros Recargas'!O$42*'Parametros Recargas'!$Q$42 -> 1.7701696 | O70: =SUM(C70:N70) -> 16.092451
A71: =datos_base!$A$59 -> Agua 10 l | B71: Líquidos | C71: =datos_base!$C$59*'Parametros Recargas'!D$43*'Parametros Recargas'!$Q$43 -> 19.814258 | D71: =datos_base!$C$59*'Parametros Recargas'!E$43*'Parametros Recargas'!$Q$43 -> 17.612674 | E71: =datos_base!$C$59*'Parametros Recargas'!F$43*'Parametros Recargas'!$Q$43 -> 18.713466 | F71: =datos_base!$C$59*'Parametros Recargas'!G$43*'Parametros Recargas'!$Q$43 -> 17.612674 | G71: =datos_base!$C$59*'Parametros Recargas'!H$43*'Parametros Recargas'!$Q$43 -> 16.511882 | H71: =datos_base!$C$59*'Parametros Recargas'!I$43*'Parametros Recargas'!$Q$43 -> 15.41109 | I71: =datos_base!$C$59*'Parametros Recargas'!J$43*'Parametros Recargas'!$Q$43 -> 17.612674 | J71: =datos_base!$C$59*'Parametros Recargas'!K$43*'Parametros Recargas'!$Q$43 -> 18.713466 | ... N71: =datos_base!$C$59*'Parametros Recargas'!O$43*'Parametros Recargas'!$Q$43 -> 24.217427 | O71: =SUM(C71:N71) -> 220.15842
A72: =datos_base!$A$60 -> AFFF 10 l | B72: Líquidos | C72: =datos_base!$C$60*'Parametros Recargas'!D$44*'Parametros Recargas'!$Q$44 -> 4.9920837 | D72: =datos_base!$C$60*'Parametros Recargas'!E$44*'Parametros Recargas'!$Q$44 -> 4.4374077 | E72: =datos_base!$C$60*'Parametros Recargas'!F$44*'Parametros Recargas'!$Q$44 -> 4.7147457 | F72: =datos_base!$C$60*'Parametros Recargas'!G$44*'Parametros Recargas'!$Q$44 -> 4.4374077 | G72: =datos_base!$C$60*'Parametros Recargas'!H$44*'Parametros Recargas'!$Q$44 -> 4.1600698 | H72: =datos_base!$C$60*'Parametros Recargas'!I$44*'Parametros Recargas'!$Q$44 -> 3.8827318 | I72: =datos_base!$C$60*'Parametros Recargas'!J$44*'Parametros Recargas'!$Q$44 -> 4.4374077 | J72: =datos_base!$C$60*'Parametros Recargas'!K$44*'Parametros Recargas'!$Q$44 -> 4.7147457 | ... N72: =datos_base!$C$60*'Parametros Recargas'!O$44*'Parametros Recargas'!$Q$44 -> 6.1014356 | O72: =SUM(C72:N72) -> 55.467597
A73: =datos_base!$A$63 -> Sales K 6 l | B73: Líquidos | C73: =datos_base!$C$63*'Parametros Recargas'!D$45*'Parametros Recargas'!$Q$45 -> 10.323136 | D73: =datos_base!$C$63*'Parametros Recargas'!E$45*'Parametros Recargas'!$Q$45 -> 9.1761209 | E73: =datos_base!$C$63*'Parametros Recargas'!F$45*'Parametros Recargas'!$Q$45 -> 9.7496285 | F73: =datos_base!$C$63*'Parametros Recargas'!G$45*'Parametros Recargas'!$Q$45 -> 9.1761209 | G73: =datos_base!$C$63*'Parametros Recargas'!H$45*'Parametros Recargas'!$Q$45 -> 8.6026134 | H73: =datos_base!$C$63*'Parametros Recargas'!I$45*'Parametros Recargas'!$Q$45 -> 8.0291058 | I73: =datos_base!$C$63*'Parametros Recargas'!J$45*'Parametros Recargas'!$Q$45 -> 9.1761209 | J73: =datos_base!$C$63*'Parametros Recargas'!K$45*'Parametros Recargas'!$Q$45 -> 9.7496285 | ... N73: =datos_base!$C$63*'Parametros Recargas'!O$45*'Parametros Recargas'!$Q$45 -> 12.617166 | O73: =SUM(C73:N73) -> 114.70151
A74: =datos_base!$A$61 -> AFFF 50 l s/ruedas | B74: Líquidos | C74: =datos_base!$C$61*'Parametros Recargas'!D$46*'Parametros Recargas'!$Q$46 -> 8.6282928 | D74: =datos_base!$C$61*'Parametros Recargas'!E$46*'Parametros Recargas'!$Q$46 -> 6.9026343 | E74: =datos_base!$C$61*'Parametros Recargas'!F$46*'Parametros Recargas'!$Q$46 -> 7.3340489 | F74: =datos_base!$C$61*'Parametros Recargas'!G$46*'Parametros Recargas'!$Q$46 -> 7.3340489 | G74: =datos_base!$C$61*'Parametros Recargas'!H$46*'Parametros Recargas'!$Q$46 -> 6.9026343 | H74: =datos_base!$C$61*'Parametros Recargas'!I$46*'Parametros Recargas'!$Q$46 -> 6.4712196 | I74: =datos_base!$C$61*'Parametros Recargas'!J$46*'Parametros Recargas'!$Q$46 -> 7.7654635 | J74: =datos_base!$C$61*'Parametros Recargas'!K$46*'Parametros Recargas'!$Q$46 -> 6.9026343 | ... N74: =datos_base!$C$61*'Parametros Recargas'!O$46*'Parametros Recargas'!$Q$46 -> 7.7654635 | O74: =SUM(C74:N74) -> 86.282928
A75: =datos_base!$A$64 -> CO₂ 2 kg | B75: CO₂ | C75: =datos_base!$C$64*'Parametros Recargas'!D$47*'Parametros Recargas'!$Q$47 -> 52.293618 | D75: =datos_base!$C$64*'Parametros Recargas'!E$47*'Parametros Recargas'!$Q$47 -> 46.483216 | E75: =datos_base!$C$64*'Parametros Recargas'!F$47*'Parametros Recargas'!$Q$47 -> 49.388417 | F75: =datos_base!$C$64*'Parametros Recargas'!G$47*'Parametros Recargas'!$Q$47 -> 46.483216 | G75: =datos_base!$C$64*'Parametros Recargas'!H$47*'Parametros Recargas'!$Q$47 -> 43.578015 | H75: =datos_base!$C$64*'Parametros Recargas'!I$47*'Parametros Recargas'!$Q$47 -> 40.672814 | I75: =datos_base!$C$64*'Parametros Recargas'!J$47*'Parametros Recargas'!$Q$47 -> 46.483216 | J75: =datos_base!$C$64*'Parametros Recargas'!K$47*'Parametros Recargas'!$Q$47 -> 49.388417 | ... N75: =datos_base!$C$64*'Parametros Recargas'!O$47*'Parametros Recargas'!$Q$47 -> 63.914422 | O75: =SUM(C75:N75) -> 581.0402
A76: =datos_base!$A$65 -> CO₂ 5 kg | B76: CO₂ | C76: =datos_base!$C$65*'Parametros Recargas'!D$48*'Parametros Recargas'!$Q$48 -> 19.845074 | D76: =datos_base!$C$65*'Parametros Recargas'!E$48*'Parametros Recargas'!$Q$48 -> 17.640065 | E76: =datos_base!$C$65*'Parametros Recargas'!F$48*'Parametros Recargas'!$Q$48 -> 18.742569 | F76: =datos_base!$C$65*'Parametros Recargas'!G$48*'Parametros Recargas'!$Q$48 -> 17.640065 | G76: =datos_base!$C$65*'Parametros Recargas'!H$48*'Parametros Recargas'!$Q$48 -> 16.537561 | H76: =datos_base!$C$65*'Parametros Recargas'!I$48*'Parametros Recargas'!$Q$48 -> 15.435057 | I76: =datos_base!$C$65*'Parametros Recargas'!J$48*'Parametros Recargas'!$Q$48 -> 17.640065 | J76: =datos_base!$C$65*'Parametros Recargas'!K$48*'Parametros Recargas'!$Q$48 -> 18.742569 | ... N76: =datos_base!$C$65*'Parametros Recargas'!O$48*'Parametros Recargas'!$Q$48 -> 24.25509 | O76: =SUM(C76:N76) -> 220.50082
A77: =datos_base!$A$67 -> HCFC/HFC 5 kg | B77: Agente limpio | C77: =datos_base!$C$67*'Parametros Recargas'!D$49*'Parametros Recargas'!$Q$49 -> 3.4513171 | D77: =datos_base!$C$67*'Parametros Recargas'!E$49*'Parametros Recargas'!$Q$49 -> 3.0678374 | E77: =datos_base!$C$67*'Parametros Recargas'!F$49*'Parametros Recargas'!$Q$49 -> 3.2595773 | F77: =datos_base!$C$67*'Parametros Recargas'!G$49*'Parametros Recargas'!$Q$49 -> 3.0678374 | G77: =datos_base!$C$67*'Parametros Recargas'!H$49*'Parametros Recargas'!$Q$49 -> 2.8760976 | H77: =datos_base!$C$67*'Parametros Recargas'!I$49*'Parametros Recargas'!$Q$49 -> 2.6843578 | I77: =datos_base!$C$67*'Parametros Recargas'!J$49*'Parametros Recargas'!$Q$49 -> 3.0678374 | J77: =datos_base!$C$67*'Parametros Recargas'!K$49*'Parametros Recargas'!$Q$49 -> 3.2595773 | ... N77: =datos_base!$C$67*'Parametros Recargas'!O$49*'Parametros Recargas'!$Q$49 -> 4.2182765 | O77: =SUM(C77:N77) -> 38.347968
A78: Demanda por familia (u. eq./mes) | C78: Ene | D78: Feb | E78: Mar | F78: Abr | G78: May | H78: Jun | I78: Jul | J78: Ago | K78: Sep | L78: Oct | M78: Nov | N78: Dic | O78: Total
A79: Polvo ABC | B79: u/mes | C79: =SUM(C61:C68) -> 911.52778 | D79: =SUM(D61:D68) -> 743.83348 | E79: =SUM(E61:E68) -> 761.9957 | F79: =SUM(F61:F68) -> 745.60023 | G79: =SUM(G61:G68) -> 727.43801 | H79: =SUM(H61:H68) -> 709.2758 | I79: =SUM(I61:I68) -> 747.36697 | J79: =SUM(J61:J68) -> 760.22895 | ... N79: =SUM(N61:N68) -> 1089.791 | O79: =SUM(C79:N79) -> 9443.1871
A80: Polvo BC | B80: u/mes | C80: =SUM(C69) -> 1.4483206 | D80: =SUM(D69) -> 1.2873961 | E80: =SUM(E69) -> 1.3678583 | F80: =SUM(F69) -> 1.2873961 | G80: =SUM(G69) -> 1.2069338 | H80: =SUM(H69) -> 1.1264716 | I80: =SUM(I69) -> 1.2873961 | J80: =SUM(J69) -> 1.3678583 | ... N80: =SUM(N69) -> 1.7701696 | O80: =SUM(C80:N80) -> 16.092451
A81: Polvo Clase D | B81: u/mes | C81: =SUM(C70) -> 1.4483206 | D81: =SUM(D70) -> 1.2873961 | E81: =SUM(E70) -> 1.3678583 | F81: =SUM(F70) -> 1.2873961 | G81: =SUM(G70) -> 1.2069338 | H81: =SUM(H70) -> 1.1264716 | I81: =SUM(I70) -> 1.2873961 | J81: =SUM(J70) -> 1.3678583 | ... N81: =SUM(N70) -> 1.7701696 | O81: =SUM(C81:N81) -> 16.092451
A82: Líquidos | B82: u/mes | C82: =SUM(C71:C74) -> 43.757771 | D82: =SUM(D71:D74) -> 38.128837 | E82: =SUM(E71:E74) -> 40.511889 | F82: =SUM(F71:F74) -> 38.560252 | G82: =SUM(G71:G74) -> 36.177199 | H82: =SUM(H71:H74) -> 33.794147 | I82: =SUM(I71:I74) -> 38.991666 | J82: =SUM(J71:J74) -> 40.080475 | ... N82: =SUM(N71:N74) -> 50.701492 | O82: =SUM(C82:N82) -> 476.61046
A83: CO₂ | B83: u/mes | C83: =SUM(C75:C76) -> 72.138691 | D83: =SUM(D75:D76) -> 64.123281 | E83: =SUM(E75:E76) -> 68.130986 | F83: =SUM(F75:F76) -> 64.123281 | G83: =SUM(G75:G76) -> 60.115576 | H83: =SUM(H75:H76) -> 56.107871 | I83: =SUM(I75:I76) -> 64.123281 | J83: =SUM(J75:J76) -> 68.130986 | ... N83: =SUM(N75:N76) -> 88.169511 | O83: =SUM(C83:N83) -> 801.54101
A84: Agente limpio | B84: u/mes | C84: =SUM(C77) -> 3.4513171 | D84: =SUM(D77) -> 3.0678374 | E84: =SUM(E77) -> 3.2595773 | F84: =SUM(F77) -> 3.0678374 | G84: =SUM(G77) -> 2.8760976 | H84: =SUM(H77) -> 2.6843578 | I84: =SUM(I77) -> 3.0678374 | J84: =SUM(J77) -> 3.2595773 | ... N84: =SUM(N77) -> 4.2182765 | O84: =SUM(C84:N84) -> 38.347968
A85: Carga por puesto | B85: unidad | C85: Ene | D85: Feb | E85: Mar | F85: Abr | G85: May | H85: Jun | I85: Jul | J85: Ago | K85: Sep | L85: Oct | M85: Nov | N85: Dic | O85: Pico (u/h) | P85: Cap. real (u/h) | Q85: N° máq. | R85: Turnos | S85: % Aprov. | T85: ABC | U85: BC | V85: D | W85: Líq. | X85: CO₂ | Y85: HC | Z85: h-hombre por u
A86: Recepción y clasificación (común) | B86: u/h | C86: =($T86*C$79+$U86*C$80+$V86*C$81+$W86*C$82+$X86*C$83+$Y86*C$84)/$B$2 -> 6.8918147 | D86: =($T86*D$79+$U86*D$80+$V86*D$81+$W86*D$82+$X86*D$83+$Y86*D$84)/$B$2 -> 5.6781882 | E86: =($T86*E$79+$U86*E$80+$V86*E$81+$W86*E$82+$X86*E$83+$Y86*E$84)/$B$2 -> 5.8442258 | F86: =($T86*F$79+$U86*F$80+$V86*F$81+$W86*F$82+$X86*F$83+$Y86*F$84)/$B$2 -> 5.6928426 | G86: =($T86*G$79+$U86*G$80+$V86*G$81+$W86*G$82+$X86*G$83+$Y86*G$84)/$B$2 -> 5.526805 | H86: =($T86*H$79+$U86*H$80+$V86*H$81+$W86*H$82+$X86*H$83+$Y86*H$84)/$B$2 -> 5.3607675 | I86: =($T86*I$79+$U86*I$80+$V86*I$81+$W86*I$82+$X86*I$83+$Y86*I$84)/$B$2 -> 5.707497 | J86: =($T86*J$79+$U86*J$80+$V86*J$81+$W86*J$82+$X86*J$83+$Y86*J$84)/$B$2 -> 5.8295714 | ... N86: =($T86*N$79+$U86*N$80+$V86*N$81+$W86*N$82+$X86*N$83+$Y86*N$84)/$B$2 -> 8.2428044 | O86: =MAX(C86:N86) -> 8.2428044 | P86: ='Parametros Recargas'!$M$85 -> 72 | Q86: =MAX(Q31,ROUNDUP(O86/(P86*'Parametros Recargas'!C$8*'Parametros Recargas'!$B$19),0)) -> 1 | R86: =IF(AND('Parametros Recargas'!C$8=2,O86/(P86*Q86*'Parametros Recargas'!$B$19)>1),2,1) -> 1 | S86: =O86/(P86*Q86*R86) -> 0.1144834 | T86: ='Parametros Recargas'!D54 -> 1 | U86: ='Parametros Recargas'!E54 -> 1 | V86: ='Parametros Recargas'!F54 -> 1 | W86: ='Parametros Recargas'!G54 -> 1 | X86: ='Parametros Recargas'!H54 -> 1 | Y86: ='Parametros Recargas'!I54 -> 1 | Z86: ='Parametros Recargas'!$U$85/P86 -> 0.013888889
A87: Inspección visual (común) | B87: u/h | C87: =($T87*C$79+$U87*C$80+$V87*C$81+$W87*C$82+$X87*C$83+$Y87*C$84)/$B$2 -> 6.8918147 | D87: =($T87*D$79+$U87*D$80+$V87*D$81+$W87*D$82+$X87*D$83+$Y87*D$84)/$B$2 -> 5.6781882 | E87: =($T87*E$79+$U87*E$80+$V87*E$81+$W87*E$82+$X87*E$83+$Y87*E$84)/$B$2 -> 5.8442258 | F87: =($T87*F$79+$U87*F$80+$V87*F$81+$W87*F$82+$X87*F$83+$Y87*F$84)/$B$2 -> 5.6928426 | G87: =($T87*G$79+$U87*G$80+$V87*G$81+$W87*G$82+$X87*G$83+$Y87*G$84)/$B$2 -> 5.526805 | H87: =($T87*H$79+$U87*H$80+$V87*H$81+$W87*H$82+$X87*H$83+$Y87*H$84)/$B$2 -> 5.3607675 | I87: =($T87*I$79+$U87*I$80+$V87*I$81+$W87*I$82+$X87*I$83+$Y87*I$84)/$B$2 -> 5.707497 | J87: =($T87*J$79+$U87*J$80+$V87*J$81+$W87*J$82+$X87*J$83+$Y87*J$84)/$B$2 -> 5.8295714 | ... N87: =($T87*N$79+$U87*N$80+$V87*N$81+$W87*N$82+$X87*N$83+$Y87*N$84)/$B$2 -> 8.2428044 | O87: =MAX(C87:N87) -> 8.2428044 | P87: ='Parametros Recargas'!$M$86 -> 52.363636 | Q87: =MAX(Q32,ROUNDUP(O87/(P87*'Parametros Recargas'!C$8*'Parametros Recargas'!$B$19),0)) -> 1 | R87: =IF(AND('Parametros Recargas'!C$8=2,O87/(P87*Q87*'Parametros Recargas'!$B$19)>1),2,1) -> 1 | S87: =O87/(P87*Q87*R87) -> 0.15741467 | T87: ='Parametros Recargas'!D55 -> 1 | U87: ='Parametros Recargas'!E55 -> 1 | V87: ='Parametros Recargas'!F55 -> 1 | W87: ='Parametros Recargas'!G55 -> 1 | X87: ='Parametros Recargas'!H55 -> 1 | Y87: ='Parametros Recargas'!I55 -> 1 | Z87: ='Parametros Recargas'!$U$86/P87 -> 0.019097222
A88: Ensayo de funcionamiento — descarga polvo ABC (equipo exclusivo) | B88: u/h | C88: =($T88*C$79+$U88*C$80+$V88*C$81+$W88*C$82+$X88*C$83+$Y88*C$84)/$B$2 -> 6.0768519 | D88: =($T88*D$79+$U88*D$80+$V88*D$81+$W88*D$82+$X88*D$83+$Y88*D$84)/$B$2 -> 4.9588899 | E88: =($T88*E$79+$U88*E$80+$V88*E$81+$W88*E$82+$X88*E$83+$Y88*E$84)/$B$2 -> 5.0799713 | F88: =($T88*F$79+$U88*F$80+$V88*F$81+$W88*F$82+$X88*F$83+$Y88*F$84)/$B$2 -> 4.9706682 | G88: =($T88*G$79+$U88*G$80+$V88*G$81+$W88*G$82+$X88*G$83+$Y88*G$84)/$B$2 -> 4.8495868 | H88: =($T88*H$79+$U88*H$80+$V88*H$81+$W88*H$82+$X88*H$83+$Y88*H$84)/$B$2 -> 4.7285053 | I88: =($T88*I$79+$U88*I$80+$V88*I$81+$W88*I$82+$X88*I$83+$Y88*I$84)/$B$2 -> 4.9824465 | J88: =($T88*J$79+$U88*J$80+$V88*J$81+$W88*J$82+$X88*J$83+$Y88*J$84)/$B$2 -> 5.068193 | ... N88: =($T88*N$79+$U88*N$80+$V88*N$81+$W88*N$82+$X88*N$83+$Y88*N$84)/$B$2 -> 7.2652736 | O88: =MAX(C88:N88) -> 7.2652736 | P88: ='Parametros Recargas'!$M$87 -> 29.142857 | Q88: =MAX(Q33,ROUNDUP(O88/(P88*'Parametros Recargas'!C$8*'Parametros Recargas'!$B$19),0)) -> 1 | R88: =IF(AND('Parametros Recargas'!C$8=2,O88/(P88*Q88*'Parametros Recargas'!$B$19)>1),2,1) -> 1 | S88: =O88/(P88*Q88*R88) -> 0.24929861 | T88: ='Parametros Recargas'!D56 -> 1 | U88: ='Parametros Recargas'!E56 -> 0 | V88: ='Parametros Recargas'!F56 -> 0 | W88: ='Parametros Recargas'!G56 -> 0 | X88: ='Parametros Recargas'!H56 -> 0 | Y88: ='Parametros Recargas'!I56 -> 0 | Z88: ='Parametros Recargas'!$U$87/P88 -> 0.017156863
A89: Ensayo de funcionamiento — descarga polvo BC (equipo exclusivo) | B89: u/h | C89: =($T89*C$79+$U89*C$80+$V89*C$81+$W89*C$82+$X89*C$83+$Y89*C$84)/$B$2 -> 0.0096554705 | D89: =($T89*D$79+$U89*D$80+$V89*D$81+$W89*D$82+$X89*D$83+$Y89*D$84)/$B$2 -> 0.0085826405 | E89: =($T89*E$79+$U89*E$80+$V89*E$81+$W89*E$82+$X89*E$83+$Y89*E$84)/$B$2 -> 0.0091190555 | F89: =($T89*F$79+$U89*F$80+$V89*F$81+$W89*F$82+$X89*F$83+$Y89*F$84)/$B$2 -> 0.0085826405 | G89: =($T89*G$79+$U89*G$80+$V89*G$81+$W89*G$82+$X89*G$83+$Y89*G$84)/$B$2 -> 0.0080462255 | H89: =($T89*H$79+$U89*H$80+$V89*H$81+$W89*H$82+$X89*H$83+$Y89*H$84)/$B$2 -> 0.0075098104 | I89: =($T89*I$79+$U89*I$80+$V89*I$81+$W89*I$82+$X89*I$83+$Y89*I$84)/$B$2 -> 0.0085826405 | J89: =($T89*J$79+$U89*J$80+$V89*J$81+$W89*J$82+$X89*J$83+$Y89*J$84)/$B$2 -> 0.0091190555 | ... N89: =($T89*N$79+$U89*N$80+$V89*N$81+$W89*N$82+$X89*N$83+$Y89*N$84)/$B$2 -> 0.011801131 | O89: =MAX(C89:N89) -> 0.011801131 | P89: ='Parametros Recargas'!$M$88 -> 29.142857 | Q89: =MAX(Q34,ROUNDUP(O89/(P89*'Parametros Recargas'!C$8*'Parametros Recargas'!$B$19),0)) -> 1 | R89: =IF(AND('Parametros Recargas'!C$8=2,O89/(P89*Q89*'Parametros Recargas'!$B$19)>1),2,1) -> 1 | S89: =O89/(P89*Q89*R89) -> 0.00040494076 | T89: ='Parametros Recargas'!D57 -> 0 | U89: ='Parametros Recargas'!E57 -> 1 | V89: ='Parametros Recargas'!F57 -> 0 | W89: ='Parametros Recargas'!G57 -> 0 | X89: ='Parametros Recargas'!H57 -> 0 | Y89: ='Parametros Recargas'!I57 -> 0 | Z89: ='Parametros Recargas'!$U$88/P89 -> 0.034313725
A90: Descarga polvo Clase D (manual, recipiente exclusivo) | B90: u/h | C90: =($T90*C$79+$U90*C$80+$V90*C$81+$W90*C$82+$X90*C$83+$Y90*C$84)/$B$2 -> 0.0096554705 | D90: =($T90*D$79+$U90*D$80+$V90*D$81+$W90*D$82+$X90*D$83+$Y90*D$84)/$B$2 -> 0.0085826405 | E90: =($T90*E$79+$U90*E$80+$V90*E$81+$W90*E$82+$X90*E$83+$Y90*E$84)/$B$2 -> 0.0091190555 | F90: =($T90*F$79+$U90*F$80+$V90*F$81+$W90*F$82+$X90*F$83+$Y90*F$84)/$B$2 -> 0.0085826405 | G90: =($T90*G$79+$U90*G$80+$V90*G$81+$W90*G$82+$X90*G$83+$Y90*G$84)/$B$2 -> 0.0080462255 | H90: =($T90*H$79+$U90*H$80+$V90*H$81+$W90*H$82+$X90*H$83+$Y90*H$84)/$B$2 -> 0.0075098104 | I90: =($T90*I$79+$U90*I$80+$V90*I$81+$W90*I$82+$X90*I$83+$Y90*I$84)/$B$2 -> 0.0085826405 | J90: =($T90*J$79+$U90*J$80+$V90*J$81+$W90*J$82+$X90*J$83+$Y90*J$84)/$B$2 -> 0.0091190555 | ... N90: =($T90*N$79+$U90*N$80+$V90*N$81+$W90*N$82+$X90*N$83+$Y90*N$84)/$B$2 -> 0.011801131 | O90: =MAX(C90:N90) -> 0.011801131 | P90: ='Parametros Recargas'!$M$89 -> 13.5 | Q90: =MAX(Q35,ROUNDUP(O90/(P90*'Parametros Recargas'!C$8*'Parametros Recargas'!$B$19),0)) -> 1 | R90: =IF(AND('Parametros Recargas'!C$8=2,O90/(P90*Q90*'Parametros Recargas'!$B$19)>1),2,1) -> 1 | S90: =O90/(P90*Q90*R90) -> 0.00087415783 | T90: ='Parametros Recargas'!D58 -> 0 | U90: ='Parametros Recargas'!E58 -> 0 | V90: ='Parametros Recargas'!F58 -> 1 | W90: ='Parametros Recargas'!G58 -> 0 | X90: ='Parametros Recargas'!H58 -> 0 | Y90: ='Parametros Recargas'!I58 -> 0 | Z90: ='Parametros Recargas'!$U$89/P90 -> 0.074074074
A91: Ensayo de funcionamiento — descarga líquidos | B91: u/h | C91: =($T91*C$79+$U91*C$80+$V91*C$81+$W91*C$82+$X91*C$83+$Y91*C$84)/$B$2 -> 0.29171847 | D91: =($T91*D$79+$U91*D$80+$V91*D$81+$W91*D$82+$X91*D$83+$Y91*D$84)/$B$2 -> 0.25419225 | E91: =($T91*E$79+$U91*E$80+$V91*E$81+$W91*E$82+$X91*E$83+$Y91*E$84)/$B$2 -> 0.27007926 | F91: =($T91*F$79+$U91*F$80+$V91*F$81+$W91*F$82+$X91*F$83+$Y91*F$84)/$B$2 -> 0.25706834 | G91: =($T91*G$79+$U91*G$80+$V91*G$81+$W91*G$82+$X91*G$83+$Y91*G$84)/$B$2 -> 0.24118133 | H91: =($T91*H$79+$U91*H$80+$V91*H$81+$W91*H$82+$X91*H$83+$Y91*H$84)/$B$2 -> 0.22529431 | I91: =($T91*I$79+$U91*I$80+$V91*I$81+$W91*I$82+$X91*I$83+$Y91*I$84)/$B$2 -> 0.25994444 | J91: =($T91*J$79+$U91*J$80+$V91*J$81+$W91*J$82+$X91*J$83+$Y91*J$84)/$B$2 -> 0.26720316 | ... N91: =($T91*N$79+$U91*N$80+$V91*N$81+$W91*N$82+$X91*N$83+$Y91*N$84)/$B$2 -> 0.33800995 | O91: =MAX(C91:N91) -> 0.33800995 | P91: ='Parametros Recargas'!$M$90 -> 22.666667 | Q91: =MAX(Q36,ROUNDUP(O91/(P91*'Parametros Recargas'!C$8*'Parametros Recargas'!$B$19),0)) -> 1 | R91: =IF(AND('Parametros Recargas'!C$8=2,O91/(P91*Q91*'Parametros Recargas'!$B$19)>1),2,1) -> 1 | S91: =O91/(P91*Q91*R91) -> 0.014912204 | T91: ='Parametros Recargas'!D59 -> 0 | U91: ='Parametros Recargas'!E59 -> 0 | V91: ='Parametros Recargas'!F59 -> 0 | W91: ='Parametros Recargas'!G59 -> 1 | X91: ='Parametros Recargas'!H59 -> 0 | Y91: ='Parametros Recargas'!I59 -> 0 | Z91: ='Parametros Recargas'!$U$90/P91 -> 0.044117647
A92: Ensayo de funcionamiento — descarga CO₂ (muestreo) | B92: u/h | C92: =($T92*C$79+$U92*C$80+$V92*C$81+$W92*C$82+$X92*C$83+$Y92*C$84)/$B$2 -> 0.12023115 | D92: =($T92*D$79+$U92*D$80+$V92*D$81+$W92*D$82+$X92*D$83+$Y92*D$84)/$B$2 -> 0.10687213 | E92: =($T92*E$79+$U92*E$80+$V92*E$81+$W92*E$82+$X92*E$83+$Y92*E$84)/$B$2 -> 0.11355164 | F92: =($T92*F$79+$U92*F$80+$V92*F$81+$W92*F$82+$X92*F$83+$Y92*F$84)/$B$2 -> 0.10687213 | G92: =($T92*G$79+$U92*G$80+$V92*G$81+$W92*G$82+$X92*G$83+$Y92*G$84)/$B$2 -> 0.10019263 | H92: =($T92*H$79+$U92*H$80+$V92*H$81+$W92*H$82+$X92*H$83+$Y92*H$84)/$B$2 -> 0.093513118 | I92: =($T92*I$79+$U92*I$80+$V92*I$81+$W92*I$82+$X92*I$83+$Y92*I$84)/$B$2 -> 0.10687213 | J92: =($T92*J$79+$U92*J$80+$V92*J$81+$W92*J$82+$X92*J$83+$Y92*J$84)/$B$2 -> 0.11355164 | ... N92: =($T92*N$79+$U92*N$80+$V92*N$81+$W92*N$82+$X92*N$83+$Y92*N$84)/$B$2 -> 0.14694919 | O92: =MAX(C92:N92) -> 0.14694919 | P92: ='Parametros Recargas'!$M$91 -> 29.142857 | Q92: =MAX(Q37,ROUNDUP(O92/(P92*'Parametros Recargas'!C$8*'Parametros Recargas'!$B$19),0)) -> 1 | R92: =IF(AND('Parametros Recargas'!C$8=2,O92/(P92*Q92*'Parametros Recargas'!$B$19)>1),2,1) -> 1 | S92: =O92/(P92*Q92*R92) -> 0.005042374 | T92: ='Parametros Recargas'!D60 -> 0 | U92: ='Parametros Recargas'!E60 -> 0 | V92: ='Parametros Recargas'!F60 -> 0 | W92: ='Parametros Recargas'!G60 -> 0 | X92: ='Parametros Recargas'!H60 -> 0.25 | Y92: ='Parametros Recargas'!I60 -> 0 | Z92: ='Parametros Recargas'!$U$91/P92 -> 0.034313725
