Workbook

Sheet Indice
A1: ÍNDICE
A3: Hoja | B3: Contenido
A4: Resumen | B4: Resultados principales 2035, conclusiones y recomendaciones
A5: Volumenes | B5: Producción y recargas 2026–2035 (Drive)
A6: Geometria Acero | B6: Medidas, masas de acero, soldadura y pintura por formato
A7: Coef Fabricacion | B7: Consumo de cada MP por unidad fabricada
A8: Coef Recargas | B8: Consumo de cada MP por recarga
A9: Consumo Anual | B9: Consumo por año de cada MP (2026–2035)
A10: MP Abastecimiento | B10: TABLA PRINCIPAL: cómo viene cada MP, cada cuánto llega, stock, almacenamiento, descarga y zona
A11: Almacen MP | B11: m² por zona vs. layout, ubicación recomendada, recepciones y scrap
A12: Manipulacion | B12: Cómo se descarga y se mueve cada unidad de carga; equipos
A13: Pallets PT | B13: Unidades por pallet de cilindros y matafuegos; stock de PT
A14: Corte Opcion D | B14: Opción elegida: hojas estándar + guillotina CENA + flejes a medida. Acero por SKU, nesting y cortes, guillotina, equipos y manejo en el puesto
... A16: Fuentes | B16: Documentos del Drive y fuentes web
A18: Referencias
A19: Dato | B19: Dato editable (número en azul; en las tablas de parámetros va en negrita)
A20: Fórmula | B20: Cálculo o vínculo a otra hoja (negro): no editar
B21: Total o resultado principal
B22: Sección de la hoja
A23: A | B23: Duda de prioridad A (hoja Dudas): cambia decisiones o superficies
A25: Confianza del dato
A26: DRIVE | B26: Dato tomado de un archivo del Drive del proyecto
A27: COTIZ | B27: Cotización o mail recibido de un proveedor
A28: WEB | B28: Fuente web (ver hoja Fuentes)
A29: EST | B29: Estimación de ingeniería: validar antes de cerrar

Sheet Resumen
A1: FLAMA S.A. — MATERIAS PRIMAS, ABASTECIMIENTO Y ALMACENAMIENTO (año de diseño 2035)
A2: Armado el 27/09/2026 a partir del Drive del proyecto (INVESTIGACION PROVEEDORES + Dimensionamiento (13)) y fuentes web. Todo lo calculado es fórmula: cambiar los datos azules recalcula el libro.
A5: ALCANCE
A6: • Fabricación de matafuegos ABC 1–100 kg (terminados) y de cilindros vendidos vacíos, más las recargas de la PLANTA INDUSTRIAL.
A7: • No incluye las recargas de la planta comercial (otro sitio), ni servicios, EPP ni repuestos de máquinas (están en 'Investigación mercado').
A8: • Año de diseño de stock y superficies: 2035 (el máximo del horizonte). El consumo 2026–2035 está en Consumo Anual.
A10: RESULTADOS PRINCIPALES 2035
A11: Indicador | B11: Valor | C11: Unidad | D11: Dónde se calcula
A12: Acero total (hojas, flejes, caño y casquetes) | B12: ='Corte Opcion D'!F22 -> 506.2327 | C12: t/año | D12: Corte Opcion D A
A13: Polvo ABC (fabricación + recargas) | B13: ='MP Abastecimiento'!$L$36/1000 -> 403.50998 | C13: t/año | D13: Consumo Anual MP-33
A14: Gas Ar/CO₂ para soldadura | B14: ='MP Abastecimiento'!$L$28/12 -> 602.46182 | C14: m³/mes promedio | D14: Consumo Anual MP-25
A15: Nitrógeno | B15: ='MP Abastecimiento'!$L$37/12 -> 394.19828 | C15: m³/mes promedio | D15: Consumo Anual MP-34
A16: Alambre MIG (0,9 + 1,2 mm) | B16: =('MP Abastecimiento'!$L$26+'MP Abastecimiento'!$L$27)/1000 -> 7.2907419 | C16: t/año | D16: Consumo Anual
A17: Stock máximo de MP | B17: ='MP Abastecimiento'!X69 -> 187.64379 | C17: t | D17: MP Abastecimiento
A18: Superficie de almacenamiento de MP requerida (incl. pasillos) | B18: ='Almacen MP'!C28 -> 377.01864 | C18: m² | D18: Almacen MP 2
A19: · AL-1 acero (requerido) | B19: ='Almacen MP'!C21 -> 148.3061 | C19: m² | D19: vs ≈116 m² netos para acero en AL-1 (layout v3)
A20: · Pañol de insumos pesados (requerido) | B20: ='Almacen MP'!C22 -> 35.207333 | C20: m² | D20: No existe junto a P1 en el layout v3
A21: · Polvo químico (requerido) | B21: ='Almacen MP'!C23 -> 23.120917 | C21: m²
A22: · Insumos de terminación y embalaje (requerido) | B22: ='Almacen MP'!C24 -> 97.523375 | C22: m² | D22: No existe en el layout v3
A23: · Jaula de gases (requerido) | B23: ='Almacen MP'!C25 -> 48.78 | C23: m² | D23: vs 16 m² dibujados
A24: Recepciones de MP | B24: ='Almacen MP'!C73 -> 5.039729 | C24: camiones/semana | D24: Almacen MP 5
A25: Pallets de PT despachados | B25: ='Pallets PT'!C67 -> 1201.5258 | C25: pallets/año | D25: Pallets PT D
A26: Posiciones de PT requeridas vs layout (122) | B26: ='Pallets PT'!C75 -> 88 | C26: posiciones | D26: Pallets PT D
A27: Cilindros de 1 kg por pallet (a granel) | B27: ='Pallets PT'!C29 -> 780 | C27: u/pallet | D27: Pallets PT A
A28: Cilindros de 5 kg por pallet (a granel) | B28: ='Pallets PT'!E29 -> 126 | C28: u/pallet | D28: Pallets PT A
A29: Scrap ferroso | B29: ='Almacen MP'!B80 -> 68.847833 | C29: t/año | D29: Almacen MP 6
A30: Inversión en corte y manejo de chapa (opción D, guillotina CENA) | B30: ='Corte Opcion D'!D61 -> 82300 | C30: USD/año | D30: Corte Opcion D D
A32: CONCLUSIONES Y RECOMENDACIONES (para debatir)
A33: Chapa | B33: Opción D: cuerpos desde hojas estándar (1220×2440, 1000×2000, 1500×3000) cortadas en guillotina propia CENA 8×3200 con tope de 1.000 mm; cúpulas y fondos desde flejes a medida (Pacheco / Pradecon). La comparación de alternativas está en Comparacion_corte.xlsx.
A34: Chapa | B34: Especificar en la orden de compra: paquetes de hojas ≤2 t, un formato por paquete, sobre tacos; rollos de fleje de 0,5–1 t parados sobre cama de madera, zunchos radiales.
A35: Manipulación | B35: Sin puente grúa: autoelevador 2,5 t con prolongaciones y espolón. En la guillotina, mesa elevadora de tijera 3 t + mesa de bolas: las hojas de 25–168 kg se deslizan, no se levantan (ver Corte Opcion D).
A36: Autoelevador | B36: Autoelevador eléctrico de 2,0–2,5 t (no 1,5 t) para big bags de polvo, pallets de 1 t en rack y rollos con espolón; transpaletas y carros para la línea (cátedra).
A37: Pañol | B37: Separar un pañol de INSUMOS PESADOS junto a AL-1 y al portón P1 (alambre, granalla, cuplas, asientos, consumibles): hoy el pañol está en la esquina opuesta.
A38: Terminación | B38: Falta un depósito de insumos de terminación y embalaje junto a S3a/AL-3 (válvulas, cajas, etiquetas, film, pallets).
A39: Polvo | B39: Big bag de 1 t con estación de descarga sobre la tolva de carga: en 2035 se consumen ≈2 t/día de polvo.
A40: Cilindros | B40: Cilindros vendidos a granel, parados, con separador de cartón por capa, tapón de rosca y film (ver Pallets PT).
A41: Validar | B41: Antes de cerrar: ver hoja Dudas (prioridad A). En especial, % de polvo nuevo en recargas, medidas de caja y los mails a proveedores con volúmenes equivocados.

Sheet Volumenes
A1: VOLÚMENES DE PRODUCCIÓN Y RECARGAS 2026–2035
A2: Fuente: Dimensionamiento_Tecnico_con_Recargas (13).xlsx › hoja datos_base (Drive, subido 27/09/2026). Recargas = PLANTA INDUSTRIAL sin la fila 'TOTAL CARROS' (es subtotal de 25–100 kg y duplicaba 1.427 u en 2035).
A4: A. MATAFUEGOS TERMINADOS (fabricados + cargados) — unidades/año
A5: Año | B5: 1 kg | C5: 2,5 kg | D5: 5 kg | E5: 10 kg | F5: 25 kg | G5: 50 kg | H5: 70 kg | I5: 100 kg | J5: Total
A6: 2026 | B6: 4179 | C6: 295 | D6: 2256 | E6: 92 | F6: 34 | G6: 75 | H6: 16 | I6: 11 | J6: =SUM(B6:I6) -> 6958
A7: 2027 | B7: 5997 | C7: 709 | D7: 3847 | E7: 177 | F7: 58 | G7: 128 | H7: 29 | I7: 18 | J7: =SUM(B7:I7) -> 10963
A8: 2028 | B8: 6852 | C8: 987 | D8: 5094 | E8: 253 | F8: 76 | G8: 166 | H8: 36 | I8: 24 | J8: =SUM(B8:I8) -> 13488
A9: 2029 | B9: 8467 | C9: 1501 | D9: 6823 | E9: 358 | F9: 100 | G9: 221 | H9: 48 | I9: 33 | J9: =SUM(B9:I9) -> 17551
A10: 2030 | B10: 12681 | C10: 2312 | D10: 10819 | E10: 603 | F10: 156 | G10: 343 | H10: 74 | I10: 50 | J10: =SUM(B10:I10) -> 27038
A11: 2031 | B11: 15620 | C11: 3252 | D11: 14606 | E11: 872 | F11: 212 | G11: 466 | H11: 101 | I11: 67 | J11: =SUM(B11:I11) -> 35196
A12: 2032 | B12: 20333 | C12: 4103 | D12: 18878 | E12: 1127 | F12: 273 | G12: 599 | H12: 131 | I12: 87 | J12: =SUM(B12:I12) -> 45531
A13: 2033 | B13: 25132 | C13: 5105 | D13: 23368 | E13: 1395 | F13: 338 | G13: 743 | H13: 163 | I13: 108 | J13: =SUM(B13:I13) -> 56352
A14: 2034 | B14: 28573 | C14: 6195 | D14: 26968 | E14: 1612 | F14: 393 | G14: 866 | H14: 189 | I14: 126 | J14: =SUM(B14:I14) -> 64922
A15: 2035 | B15: 32073 | C15: 7425 | D15: 30751 | E15: 1841 | F15: 453 | G15: 997 | H15: 218 | I15: 145 | J15: =SUM(B15:I15) -> 73903
A17: B. CILINDROS VENDIDOS VACÍOS (pintados y probados, sin válvula) — unidades/año
A18: Año | B18: 1 kg | C18: 2,5 kg | D18: 5 kg | E18: 10 kg | F18: 25 kg | G18: 50 kg | H18: 70 kg | I18: 100 kg | J18: Total
A19: 2026 | B19: 0 | C19: 0 | D19: 0 | E19: 0 | F19: 0 | G19: 0 | H19: 0 | I19: 0 | J19: =SUM(B19:I19) -> 0
A20: 2027 | B20: 0 | C20: 0 | D20: 0 | E20: 0 | F20: 0 | G20: 0 | H20: 0 | I20: 0 | J20: =SUM(B20:I20) -> 0
A21: 2028 | B21: 7662 | C21: 300 | D21: 1479 | E21: 90 | F21: 14 | G21: 32 | H21: 7 | I21: 5 | J21: =SUM(B21:I21) -> 9589
A22: 2029 | B22: 26695 | C22: 1044 | D22: 5152 | E22: 315 | F22: 50 | G22: 111 | H22: 24 | I22: 16 | J22: =SUM(B22:I22) -> 33407
A23: 2030 | B23: 49435 | C23: 1933 | D23: 9541 | E23: 583 | F23: 93 | G23: 205 | H23: 45 | I23: 30 | J23: =SUM(B23:I23) -> 61865
A24: 2031 | B24: 71680 | C24: 2803 | D24: 13834 | E24: 846 | F24: 135 | G24: 298 | H24: 65 | I24: 43 | J24: =SUM(B24:I24) -> 89704
A25: 2032 | B25: 101341 | C25: 3963 | D25: 19559 | E25: 1195 | F25: 191 | G25: 421 | H25: 92 | I25: 60 | J25: =SUM(B25:I25) -> 126822
A26: 2033 | B26: 131001 | C26: 5123 | D26: 25283 | E26: 1545 | F26: 247 | G26: 544 | H26: 119 | I26: 78 | J26: =SUM(B26:I26) -> 163940
A27: 2034 | B27: 146820 | C27: 5741 | D27: 28336 | E27: 1731 | F27: 277 | G27: 610 | H27: 133 | I27: 88 | J27: =SUM(B27:I27) -> 183736
A28: 2035 | B28: 170548 | C28: 6669 | D28: 32915 | E28: 2011 | F28: 322 | G28: 708 | H28: 155 | I28: 102 | J28: =SUM(B28:I28) -> 213430
A30: C. RECIPIENTES FABRICADOS = TERMINADOS + CILINDROS — unidades/año
A31: Año | B31: 1 kg | C31: 2,5 kg | D31: 5 kg | E31: 10 kg | F31: 25 kg | G31: 50 kg | H31: 70 kg | I31: 100 kg | J31: Total
A32: 2026 | B32: =B6+B19 -> 4179 | C32: =C6+C19 -> 295 | D32: =D6+D19 -> 2256 | E32: =E6+E19 -> 92 | F32: =F6+F19 -> 34 | G32: =G6+G19 -> 75 | H32: =H6+H19 -> 16 | I32: =I6+I19 -> 11 | J32: =SUM(B32:I32) -> 6958
A33: 2027 | B33: =B7+B20 -> 5997 | C33: =C7+C20 -> 709 | D33: =D7+D20 -> 3847 | E33: =E7+E20 -> 177 | F33: =F7+F20 -> 58 | G33: =G7+G20 -> 128 | H33: =H7+H20 -> 29 | I33: =I7+I20 -> 18 | J33: =SUM(B33:I33) -> 10963
A34: 2028 | B34: =B8+B21 -> 14514 | C34: =C8+C21 -> 1287 | D34: =D8+D21 -> 6573 | E34: =E8+E21 -> 343 | F34: =F8+F21 -> 90 | G34: =G8+G21 -> 198 | H34: =H8+H21 -> 43 | I34: =I8+I21 -> 29 | J34: =SUM(B34:I34) -> 23077
A35: 2029 | B35: =B9+B22 -> 35162 | C35: =C9+C22 -> 2545 | D35: =D9+D22 -> 11975 | E35: =E9+E22 -> 673 | F35: =F9+F22 -> 150 | G35: =G9+G22 -> 332 | H35: =H9+H22 -> 72 | I35: =I9+I22 -> 49 | J35: =SUM(B35:I35) -> 50958
A36: 2030 | B36: =B10+B23 -> 62116 | C36: =C10+C23 -> 4245 | D36: =D10+D23 -> 20360 | E36: =E10+E23 -> 1186 | F36: =F10+F23 -> 249 | G36: =G10+G23 -> 548 | H36: =H10+H23 -> 119 | I36: =I10+I23 -> 80 | J36: =SUM(B36:I36) -> 88903
A37: 2031 | B37: =B11+B24 -> 87300 | C37: =C11+C24 -> 6055 | D37: =D11+D24 -> 28440 | E37: =E11+E24 -> 1718 | F37: =F11+F24 -> 347 | G37: =G11+G24 -> 764 | H37: =H11+H24 -> 166 | I37: =I11+I24 -> 110 | J37: =SUM(B37:I37) -> 124900
A38: 2032 | B38: =B12+B25 -> 121674 | C38: =C12+C25 -> 8066 | D38: =D12+D25 -> 38437 | E38: =E12+E25 -> 2322 | F38: =F12+F25 -> 464 | G38: =G12+G25 -> 1020 | H38: =H12+H25 -> 223 | I38: =I12+I25 -> 147 | J38: =SUM(B38:I38) -> 172353
A39: 2033 | B39: =B13+B26 -> 156133 | C39: =C13+C26 -> 10228 | D39: =D13+D26 -> 48651 | E39: =E13+E26 -> 2940 | F39: =F13+F26 -> 585 | G39: =G13+G26 -> 1287 | H39: =H13+H26 -> 282 | I39: =I13+I26 -> 186 | J39: =SUM(B39:I39) -> 220292
A40: 2034 | B40: =B14+B27 -> 175393 | C40: =C14+C27 -> 11936 | D40: =D14+D27 -> 55304 | E40: =E14+E27 -> 3343 | F40: =F14+F27 -> 670 | G40: =G14+G27 -> 1476 | H40: =H14+H27 -> 322 | I40: =I14+I27 -> 214 | J40: =SUM(B40:I40) -> 248658
A41: 2035 | B41: =B15+B28 -> 202621 | C41: =C15+C28 -> 14094 | D41: =D15+D28 -> 63666 | E41: =E15+E28 -> 3852 | F41: =F15+F28 -> 775 | G41: =G15+G28 -> 1705 | H41: =H15+H28 -> 373 | I41: =I15+I28 -> 247 | J41: =SUM(B41:I41) -> 287333
A43: D. RECARGAS PLANTA INDUSTRIAL (se hacen en esta planta) — unidades/año
A44: Año | B44: ABC 1 kg | C44: ABC 2,5 kg | D44: ABC 5 kg | E44: ABC 10 kg | F44: Agua 10 l | G44: AFFF 10 l | H44: AFFF 50 l s/r | I44: BC 5 kg | J44: Sales K 6 l | K44: CO₂ 2 kg | L44: CO₂ 5 kg | M44: HCFC/HFC 5 kg | N44: Clase D 9 l | O44: ABC 25 kg s/r | P44: ABC 50 kg s/r | Q44: ABC 70 kg s/r | R44: ABC 100 kg s/r | S44: Total
A45: 2026 | B45: 1190 | C45: 113 | D45: 668 | E45: 40 | F45: 54 | G45: 8 | H45: 4 | I45: 2 | J45: 28 | K45: 154 | L45: 43 | M45: 6 | N45: 2 | O45: 6 | P45: 13 | Q45: 3 | R45: 2 | S45: =SUM(B45:R45) -> 2336
A46: 2027 | B46: 5811 | C46: 441 | D46: 2689 | E46: 150 | F46: 220 | G46: 55 | H46: 29 | I46: 16 | J46: 115 | K46: 581 | L46: 221 | M46: 38 | N46: 16 | O46: 29 | P46: 65 | Q46: 14 | R46: 10 | S46: =SUM(B46:R46) -> 10500
A47: 2028 | B47: 10459 | C47: 1009 | D47: 6086 | E47: 351 | F47: 505 | G47: 109 | H47: 56 | I47: 30 | J47: 256 | K47: 1354 | L47: 471 | M47: 79 | N47: 30 | O47: 64 | P47: 141 | Q47: 31 | R47: 21 | S47: =SUM(B47:R47) -> 21052
A48: 2029 | B48: 19190 | C48: 1858 | D48: 11506 | E48: 671 | F48: 947 | G48: 181 | H48: 96 | I48: 55 | J48: 465 | K48: 2589 | L48: 842 | M48: 137 | N48: 51 | O48: 115 | P48: 253 | Q48: 55 | R48: 37 | S48: =SUM(B48:R48) -> 39048
A49: 2030 | B49: 28853 | C49: 2688 | D49: 16574 | E49: 974 | F49: 1366 | G49: 255 | H49: 137 | I49: 75 | J49: 671 | K49: 3739 | L49: 1214 | M49: 197 | N49: 70 | O49: 166 | P49: 365 | Q49: 80 | R49: 53 | S49: =SUM(B49:R49) -> 57477
A50: 2031 | B50: 40199 | C50: 3569 | D50: 22024 | E50: 1305 | F50: 1827 | G50: 330 | H50: 176 | I50: 100 | J50: 890 | K50: 4970 | L50: 1617 | M50: 259 | N50: 87 | O50: 220 | P50: 484 | Q50: 105 | R50: 71 | S50: =SUM(B50:R50) -> 78233
A51: 2032 | B51: 50541 | C51: 4386 | D51: 26953 | E51: 1597 | F51: 2239 | G51: 409 | H51: 215 | I51: 126 | J51: 1095 | K51: 6076 | L51: 2004 | M51: 324 | N51: 112 | O51: 271 | P51: 597 | Q51: 130 | R51: 87 | S51: =SUM(B51:R51) -> 97162
A52: 2033 | B52: 58687 | C52: 4884 | D52: 29869 | E52: 1768 | F52: 2489 | G52: 463 | H52: 244 | I52: 140 | J52: 1225 | K52: 6717 | L52: 2263 | M52: 367 | N52: 126 | O52: 305 | P52: 670 | Q52: 146 | R52: 98 | S52: =SUM(B52:R52) -> 110461
A53: 2034 | B53: 62894 | C53: 5284 | D53: 32221 | E53: 1908 | F53: 2690 | G53: 506 | H53: 265 | I53: 153 | J53: 1325 | K53: 7246 | L53: 2460 | M53: 401 | N53: 138 | O53: 330 | P53: 727 | Q53: 159 | R53: 106 | S53: =SUM(B53:R53) -> 118813
A54: 2035 | B54: 67206 | C54: 5691 | D54: 34614 | E54: 2050 | F54: 2893 | G54: 550 | H54: 287 | I54: 165 | J54: 1427 | K54: 7784 | L54: 2660 | M54: 436 | N54: 150 | O54: 357 | P54: 785 | Q54: 171 | R54: 114 | S54: =SUM(B54:R54) -> 127340
A56: E. PARÁMETROS DE CALENDARIO
A57: Factor del mes pico (% del consumo anual) | B57: 0.12 | C57: Supuesto: perfil 1 kg = 12 % (ene/dic). Dimensiona lotes y stock.
A58: Días hábiles por mes | B58: 20 | C58: Dimensionamiento (13): 20 días hábiles/mes
A59: Días hábiles por año | B59: =B58*12 -> 240
A60: Semanas operativas por año | B60: 48 | C60: EST (descontando feriados y vacaciones)

Sheet Geometria Acero
A1: GEOMETRÍA, ACERO Y CONSUMIBLES DE PROCESO POR RECIPIENTE
A2: Medidas: registro FADESA (Dimensiones de chapa), ET's Matafuegos, Materias Primas › Lineamientos, cotizaciones Pacheco N°42021 / Pradecon 173170-173195 y Comparacion_corte.xlsx (opción D elegida: hojas estándar en guillotina propia + fleje a medida). Cuando los archivos se contradicen se anotó en 'Dudas'.
A4: PARÁMETROS GENERALES
A5: Parámetro | B5: Unidad | C5: Valor | D5: Fuente / criterio
A6: Densidad del acero | B6: kg/m³ | C6: 7850 | D6: Valor estándar acero al carbono (Corte_chapa.docx)
A7: Caño cuerpo 1 kg — Ø exterior | B7: mm | C7: 76.2 | D7: Metalprisa: caño c/c LF Ø76,2 (mail 09/09/2026)
A8: Caño cuerpo 1 kg — espesor | B8: mm | C8: 1.25 | D8: Metalprisa Ø76,2 × 1,25 = $37.044 + IVA la barra de 6 m
A9: Largo de barra de caño | B9: mm | C9: 6000 | D9: Metalprisa (caño de 6 m); Ternium: largo estándar 6.000 mm
A10: Merma de corte por cuerpo (ranura + despunte) | B10: mm | C10: 3 | D10: EST
A11: Masa por metro de caño | B11: kg/m | C11: =PI()*($C$7-$C$8)*$C$8*$C$6/1000000 -> 2.3104745 | D11: Fórmula
A12: Masa por barra de caño | B12: kg | C12: =$C$11*$C$9/1000 -> 13.862847 | D12: Fórmula
A13: Puente entre discos en el fleje | B13: mm | C13: 3 | D13: Comparacion_corte (opción D): puente s = 3 mm (≈1,5–3 × e); paso = D₀ + s
A14: Pintura en polvo — peso específico | B14: g/cm³ | C14: 1.5 | D14: EST (poliéster 1,4–1,7). Rendimiento teórico = 1000/(ρ·e) (pinturaenpolvo.org)
A15: Pintura — espesor de película | B15: µm | C15: 70 | D15: Mail a Sinteplast: 60–80 µm en manuales (Drive)
A16: Pintura — pérdidas de aplicación | B16: % | C16: 0.25 | D16: Rendimiento práctico 25–30 % menor que el teórico (pinturaenpolvo.org)
A17: Pintura — consumo práctico | B17: kg/m² | C17: =$C$14*$C$15/1000/(1-$C$16) -> 0.14 | D17: Fórmula
A18: Factor de área de cúpula/fondo embutidos vs. círculo plano | B18: - | C18: 1.15 | D18: EST
A19: Rendimiento de depósito del alambre | B19: % | C19: 0.9 | D19: EST (salpicaduras + despuntes)
A20: Caudal de gas — manuales | B20: L/min | C20: 14 | D20: EST (12–15 L/min según BOM del Drive)
A21: Caudal de gas — rodantes | B21: L/min | C21: 16 | D21: EST
A22: Factor pre/post-flujo y purgas de gas | B22: - | C22: 1.25 | D22: EST
A23: Granalla — consumo por hora de granallado | B23: kg/h | C23: 6 | D23: EST; referencia web ≈9 kg/h en una granalladora comercial (metalmecanica.com)
A24: Granalladora — capacidad real | B24: u/h | C24: 81.2 | D24: Dimensionamiento (13) › Parametros › Granallado = 81,2 u/h
A25: Desengrasante concentrado por m² pintado | B25: L/m² | C25: 0.01 | D25: EST — pedir dato al proveedor del túnel (SP Ingeniería/Electricolor)
A26: Fosfatizante concentrado por m² pintado | B26: L/m² | C26: 0.01 | D26: EST — ídem
A27: Recorrido del tope trasero de la guillotina (CENA 8×3200) | B27: mm | C27: 1000 | D27: Cotización CENA (Drive): versión con tope trasero 20–1.000 mm, USD 36.800 + IVA
A28: Peso máximo por paquete de hojas (orden de compra) | B28: kg | C28: 2000 | D28: Opción D: paquetes ≤2 t (autoelevador 2,5 t y mesa elevadora de 3 t)
A29: DATOS POR FORMATO (una columna por formato)
A30: Concepto | B30: Unidad | C30: 1 kg | D30: 2,5 kg | E30: 5 kg | F30: 10 kg | G30: 25 kg | H30: 50 kg | I30: 70 kg | J30: 100 kg | K30: Fuente / criterio
A31: Tipo de cuerpo | B31: - | C31: Caño | D31: Hoja LAF (guillotina) | E31: Hoja LAF (guillotina) | F31: Hoja LAF (guillotina) | G31: Hoja LAC (guillotina) | H31: Hoja LAC (guillotina) | I31: Hoja LAC (guillotina) | J31: Hoja LAC (guillotina) | K31: Opción D: cuerpos desde hoja estándar cortada en guillotina propia; 1 kg desde caño
A32: Espesor del cuerpo | B32: mm | C32: 1.25 | D32: 1.25 | E32: 1.6 | F32: 2 | G32: 3.2 | H32: 3.2 | I32: 4.75 | J32: 4.75 | K32: FADESA / cotizaciones Pacheco
A33: Ø exterior del recipiente | B33: mm | C33: 76.2 | D33: 124 | E33: 153 | F33: 181.5 | G33: 276.5 | H33: 320 | I33: 390 | J33: 390 | K33: ET's Matafuegos. 70 kg corregido a Ø390: desarrollo 1.212 mm ⇒ Ø≈390 (ET's dice 216,5 → ver Dudas)
A34: Desarrollo de la plancha (= perímetro) | B34: mm | C34: 0 | D34: 385.5 | E34: 474.5 | F34: 563 | G34: 858 | H34: 994 | I34: 1212 | J34: 1212 | K34: FADESA / Lineamientos (Materias Primas)
A35: Alto del cuerpo (1 kg: largo de corte del caño) | B35: mm | C35: 255 | D35: 269.5 | E35: 330 | F35: 495 | G35: 490 | H35: 640 | I35: 680 | J35: 900 | K35: FADESA: caño cortado a 255 mm; planchas L × H
A36: Masa neta del cuerpo | B36: kg | C36: =$C$11*C35/1000 -> 0.589171 | D36: =D34*D35*D32*$C$6/1000000000 -> 1.0194427 | E36: =E34*E35*E32*$C$6/1000000000 -> 1.9667076 | F36: =F34*F35*F32*$C$6/1000000000 -> 4.3753545 | G36: =G34*G35*G32*$C$6/1000000000 -> 10.56095 | H36: =H34*H35*H32*$C$6/1000000000 -> 15.980339 | I36: =I34*I35*I32*$C$6/1000000000 -> 30.730866 | J36: =J34*J35*J32*$C$6/1000000000 -> 40.673205 | K36: Fórmula (1 kg: kg/m de caño × largo)
A37: Espesor de la cúpula | B37: mm | C37: 0.9 | D37: 1.25 | E37: 1.6 | F37: 2 | G37: 0 | H37: 0 | I37: 0 | J37: 0 | K37: FADESA / ET's: 1,6 mm en el 10 kg; la opción D toma 2,0 mm (tabla FLAMA y fleje cotizado por Pacheco) → Dudas
A38: Ø del disco de cúpula (D₀) | B38: mm | C38: 108 | D38: 179 | E38: 221 | F38: 258 | G38: 0 | H38: 0 | I38: 0 | J38: 0 | K38: FADESA 2,5–10 kg; 1 kg = ESTIMADO 108 mm (Comparacion_corte: masa de pieza 0,0461 kg / 0,71) — medir
A39: Ancho del fleje de cúpula | B39: mm | C39: 114 | D39: 200 | E39: 250 | F39: 300 | G39: 0 | H39: 0 | I39: 0 | J39: 0 | K39: Opción D: 1 kg fleje 114 mm (Pradecon, corte a medida sin cargo); 2,5–10 kg Pacheco N°42021
A40: Discos a lo ancho del fleje (cúpula) | B40: u | C40: 1 | D40: 1 | E40: 1 | F40: 1 | G40: 0 | H40: 0 | I40: 0 | J40: 0 | K40: 1 disco por ancho de fleje (troquel simple)
A41: Masa bruta de fleje por cúpula | B41: kg | C41: =IF(C40=0,0,C39/C40*(C38+$C$13)*C37*$C$6/1000000000) -> 0.08940051 | D41: =IF(D40=0,0,D39/D40*(D38+$C$13)*D37*$C$6/1000000000) -> 0.357175 | E41: =IF(E40=0,0,E39/E40*(E38+$C$13)*E37*$C$6/1000000000) -> 0.70336 | F41: =IF(F40=0,0,F39/F40*(F38+$C$13)*F37*$C$6/1000000000) -> 1.22931 | G41: =IF(G40=0,0,G39/G40*(G38+$C$13)*G37*$C$6/1000000000) -> 0 | H41: =IF(H40=0,0,H39/H40*(H38+$C$13)*H37*$C$6/1000000000) -> 0 | I41: =IF(I40=0,0,I39/I40*(I38+$C$13)*I37*$C$6/1000000000) -> 0 | J41: =IF(J40=0,0,J39/J40*(J38+$C$13)*J37*$C$6/1000000000) -> 0 | K41: Fórmula: (ancho/n) × (D₀+puente) × e × ρ
A42: Masa neta del disco de cúpula | B42: kg | C42: =PI()/4*C38^2*C37*$C$6/1000000000 -> 0.064721647 | D42: =PI()/4*D38^2*D37*$C$6/1000000000 -> 0.246931 | E42: =PI()/4*E38^2*E37*$C$6/1000000000 -> 0.48179697 | F42: =PI()/4*F38^2*F37*$C$6/1000000000 -> 0.82078412 | G42: =PI()/4*G38^2*G37*$C$6/1000000000 -> 0 | H42: =PI()/4*H38^2*H37*$C$6/1000000000 -> 0 | I42: =PI()/4*I38^2*I37*$C$6/1000000000 -> 0 | J42: =PI()/4*J38^2*J37*$C$6/1000000000 -> 0 | K42: Fórmula: π/4 × D₀² × e × ρ
A43: Espesor del fondo | B43: mm | C43: 0.9 | D43: 1.25 | E43: 1.6 | F43: 2 | G43: 0 | H43: 0 | I43: 0 | J43: 0 | K43: FADESA
A44: Ø del disco de fondo (D₀) | B44: mm | C44: 100 | D44: 148 | E44: 177 | F44: 205 | G44: 0 | H44: 0 | I44: 0 | J44: 0 | K44: FADESA 2,5–10 kg; 1 kg = ESTIMADO 100 mm (Comparacion_corte: masa de pieza 0,0497 kg / 0,90) — medir
A45: Ancho del fleje de fondo | B45: mm | C45: 106 | D45: 200 | E45: 200 | F45: 249 | G45: 0 | H45: 0 | I45: 0 | J45: 0 | K45: Opción D: 1 kg 106 mm (Pradecon); 2,5–10 kg Pacheco N°42021 (10 kg: 249 mm)
A46: Discos a lo ancho del fleje (fondo) | B46: u | C46: 1 | D46: 1 | E46: 1 | F46: 1 | G46: 0 | H46: 0 | I46: 0 | J46: 0 | K46: 1 disco por ancho de fleje
A47: Masa bruta de fleje por fondo | B47: kg | C47: =IF(C46=0,0,C45/C46*(C44+$C$13)*C43*$C$6/1000000000) -> 0.07713567 | D47: =IF(D46=0,0,D45/D46*(D44+$C$13)*D43*$C$6/1000000000) -> 0.2963375 | E47: =IF(E46=0,0,E45/E46*(E44+$C$13)*E43*$C$6/1000000000) -> 0.45216 | F47: =IF(F46=0,0,F45/F46*(F44+$C$13)*F43*$C$6/1000000000) -> 0.8131344 | G47: =IF(G46=0,0,G45/G46*(G44+$C$13)*G43*$C$6/1000000000) -> 0 | H47: =IF(H46=0,0,H45/H46*(H44+$C$13)*H43*$C$6/1000000000) -> 0 | I47: =IF(I46=0,0,I45/I46*(I44+$C$13)*I43*$C$6/1000000000) -> 0 | J47: =IF(J46=0,0,J45/J46*(J44+$C$13)*J43*$C$6/1000000000) -> 0 | K47: Fórmula
A48: Masa neta del disco de fondo | B48: kg | C48: =PI()/4*C44^2*C43*$C$6/1000000000 -> 0.05548838 | D48: =PI()/4*D44^2*D43*$C$6/1000000000 -> 0.16880798 | E48: =PI()/4*E44^2*E43*$C$6/1000000000 -> 0.30904808 | F48: =PI()/4*F44^2*F43*$C$6/1000000000 -> 0.51819982 | G48: =PI()/4*G44^2*G43*$C$6/1000000000 -> 0 | H48: =PI()/4*H44^2*H43*$C$6/1000000000 -> 0 | I48: =PI()/4*I44^2*I43*$C$6/1000000000 -> 0 | J48: =PI()/4*J44^2*J43*$C$6/1000000000 -> 0 | K48: Fórmula
A49: Casquetes comprados por recipiente | B49: u | C49: 0 | D49: 0 | E49: 0 | F49: 0 | G49: 2 | H49: 2 | I49: 2 | J49: 2 | K49: Carros: fondo y cúpula comprados estampados (Dimensionamiento 13)
A50: Masa por casquete | B50: kg | C50: 0 | D50: 0 | E50: 0 | F50: 0 | G50: 2.44 | H50: 3.36 | I50: 6.64 | J50: 6.64 | K50: FADESA: 10" 2,44 · 12" 3,36 · 15" 6,64 kg (100 kg: se asume igual al 70)
A51: Altura de cúpula / casquete superior | B51: mm | C51: 12.5 | D51: 39.5 | E51: 54.5 | F51: 62.5 | G51: 87 | H51: 105 | I51: 110 | J51: 110 | K51: ET's / Lineamientos; 70–100 kg EST
A52: Altura de fondo / casquete inferior | B52: mm | C52: 22 | D52: 16 | E52: 21.5 | F52: 16.5 | G52: 87 | H52: 105 | I52: 110 | J52: 110 | K52: ET's / Lineamientos; 70–100 kg EST
A53: Altura del recipiente sin válvula | B53: mm | C53: =C35+C51+C52+8 -> 297.5 | D53: =D35+D51+D52+8 -> 333 | E53: =E35+E51+E52+8 -> 414 | F53: =F35+F51+F52+8 -> 582 | G53: =G35+G51+G52+8 -> 672 | H53: =H35+H51+H52+8 -> 858 | I53: =I35+I51+I52+8 -> 908 | J53: =J35+J51+J52+8 -> 1128 | K53: EST = cuerpo + cúpula + fondo + 8 mm de cuello (verificar con plano)
A54: Masa de asiento de válvula / cupla | B54: kg | C54: 0.06 | D54: 0.08 | E54: 0.08 | F54: 0.08 | G54: 0.25 | H54: 0.25 | I54: 0.6 | J54: 0.6 | K54: EST
A55: Masa de varilla de refuerzo | B55: kg | C55: 0 | D55: 0 | E55: 0 | F55: 0 | G55: 0 | H55: 0 | I55: 1.5 | J55: 1.5 | K55: EST (dimensión sin definir en ET's)
A56: Masa del recipiente vacío (cálculo) | B56: kg | C56: =C36+C42+C48+C49*C50+C54+C55+C67 -> 0.78437522 | D56: =D36+D42+D48+D49*D50+D54+D55+D67 -> 1.5455798 | E56: =E36+E42+E48+E49*E50+E54+E55+E67 -> 2.8743018 | F56: =F36+F42+F48+F49*F50+F54+F55+F67 -> 5.8400907 | G56: =G36+G42+G48+G49*G50+G54+G55+G67 -> 15.993548 | H56: =H36+H42+H48+H49*H50+H54+H55+H67 -> 23.300937 | I56: =I36+I42+I48+I49*I50+I54+I55+I67 -> 46.861763 | J56: =J36+J42+J48+J49*J50+J54+J55+J67 -> 56.846317 | K56: Fórmula: cuerpo + discos netos + casquetes + cuello + varilla + cordón
A57: Masa del recipiente según planos (Drive) | B57: kg | C57: 0.76 | D57: 1.48 | E57: 2.78 | F57: 5.48 | G57: 15.92 | H57: 23.3 | I57: 0 | J57: 0 | K57: Materias Primas › Lineamientos: planos G809/G731/G732/G733/G690/G689
A58: Masa del recipiente adoptada | B58: kg | C58: =IF(C57>0,C57,C56) -> 0.76 | D58: =IF(D57>0,D57,D56) -> 1.48 | E58: =IF(E57>0,E57,E56) -> 2.78 | F58: =IF(F57>0,F57,F56) -> 5.48 | G58: =IF(G57>0,G57,G56) -> 15.92 | H58: =IF(H57>0,H57,H56) -> 23.3 | I58: =IF(I57>0,I57,I56) -> 46.861763 | J58: =IF(J57>0,J57,J56) -> 56.846317 | K58: Plano si existe; si no, cálculo
A59: Costura longitudinal | B59: m | C59: 0 | D59: =D35/1000 -> 0.2695 | E59: =E35/1000 -> 0.33 | F59: =F35/1000 -> 0.495 | G59: =G35/1000 -> 0.49 | H59: =H35/1000 -> 0.64 | I59: =I35/1000 -> 0.68 | J59: =J35/1000 -> 0.9 | K59: Fórmula = alto de cuerpo (1 kg: caño, sin costura)
A60: Costuras circunferenciales (cúpula + fondo) | B60: m | C60: =2*PI()*C33/1000 -> 0.47877872 | D60: =2*PI()*D33/1000 -> 0.77911498 | E60: =2*PI()*E33/1000 -> 0.96132735 | F60: =2*PI()*F33/1000 -> 1.1403981 | G60: =2*PI()*G33/1000 -> 1.7373007 | H60: =2*PI()*H33/1000 -> 2.0106193 | I60: =2*PI()*I33/1000 -> 2.4504423 | J60: =2*PI()*J33/1000 -> 2.4504423 | K60: Fórmula = 2 × π × Ø
A61: Ø del cordón de cuello | B61: mm | C61: 30 | D61: 36 | E61: 36 | F61: 36 | G61: 45 | H61: 45 | I61: 90 | J61: 90 | K61: EST (M22 / M30 / 2½")
A62: Cordón de cuello | B62: m | C62: =PI()*C61/1000 -> 0.09424778 | D62: =PI()*D61/1000 -> 0.11309734 | E62: =PI()*E61/1000 -> 0.11309734 | F62: =PI()*F61/1000 -> 0.11309734 | G62: =PI()*G61/1000 -> 0.14137167 | H62: =PI()*H61/1000 -> 0.14137167 | I62: =PI()*I61/1000 -> 0.28274334 | J62: =PI()*J61/1000 -> 0.28274334 | K62: Fórmula = π × Ø
A63: Otras soldaduras (varilla, estructura de carro) | B63: m | C63: 0 | D63: 0 | E63: 0 | F63: 0 | G63: 0.3 | H63: 0.3 | I63: 0.5 | J63: 0.5 | K63: EST
A64: Longitud total de soldadura | B64: m | C64: =C59+C60+C62+C63 -> 0.5730265 | D64: =D59+D60+D62+D63 -> 1.1617123 | E64: =E59+E60+E62+E63 -> 1.4044247 | F64: =F59+F60+F62+F63 -> 1.7484955 | G64: =G59+G60+G62+G63 -> 2.6686724 | H64: =H59+H60+H62+H63 -> 3.091991 | I64: =I59+I60+I62+I63 -> 3.9131856 | J64: =J59+J60+J62+J63 -> 4.1331856 | K64: Fórmula
A65: Sección de cordón depositado | B65: mm² | C65: 3 | D65: 3 | E65: 3 | F65: 3 | G65: 13 | H65: 13 | I65: 22 | J65: 22 | K65: EST (≤2 mm: filete ≈2 mm; 3,2–4,75 mm: bisel + sobreespesor)
A66: Alambre por metro de cordón | B66: g/m | C66: =C65*$C$6/1000/$C$19 -> 26.166667 | D66: =D65*$C$6/1000/$C$19 -> 26.166667 | E66: =E65*$C$6/1000/$C$19 -> 26.166667 | F66: =F65*$C$6/1000/$C$19 -> 26.166667 | G66: =G65*$C$6/1000/$C$19 -> 113.38889 | H66: =H65*$C$6/1000/$C$19 -> 113.38889 | I66: =I65*$C$6/1000/$C$19 -> 191.88889 | J66: =J65*$C$6/1000/$C$19 -> 191.88889 | K66: Fórmula = sección × ρ / rendimiento
A67: Alambre por recipiente | B67: kg | C67: =C64*C66/1000 -> 0.014994193 | D67: =D64*D66/1000 -> 0.030398139 | E67: =E64*E66/1000 -> 0.036749113 | F67: =F64*F66/1000 -> 0.045752298 | G67: =G64*G66/1000 -> 0.3025978 | H67: =H64*H66/1000 -> 0.35059742 | I67: =I64*I66/1000 -> 0.75089684 | J67: =J64*J66/1000 -> 0.79311239 | K67: Fórmula
A68: Ø de alambre | B68: mm | C68: 0.9 | D68: 0.9 | E68: 0.9 | F68: 0.9 | G68: 1.2 | H68: 1.2 | I68: 1.2 | J68: 1.2 | K68: Recomendación cátedra (Drive): 0,9 mm chapa fina; 1,2 mm más de 2 mm
A69: Velocidad de soldadura | B69: m/min | C69: 0.6 | D69: 0.6 | E69: 0.6 | F69: 0.6 | G69: 0.35 | H69: 0.35 | I69: 0.35 | J69: 0.35 | K69: EST (soldadoras automáticas)
A70: Tiempo de arco | B70: min | C70: =C64/C69 -> 0.95504417 | D70: =D64/D69 -> 1.9361872 | E70: =E64/E69 -> 2.3407078 | F70: =F64/F69 -> 2.9141591 | G70: =G64/G69 -> 7.6247783 | H70: =H64/H69 -> 8.8342599 | I70: =I64/I69 -> 11.18053 | J70: =J64/J69 -> 11.809102 | K70: Fórmula
A71: Gas Ar/CO₂ por recipiente | B71: m³ | C71: =C70*IF(C32<3,$C$20,$C$21)*$C$22/1000 -> 0.016713273 | D71: =D70*IF(D32<3,$C$20,$C$21)*$C$22/1000 -> 0.033883276 | E71: =E70*IF(E32<3,$C$20,$C$21)*$C$22/1000 -> 0.040962387 | F71: =F70*IF(F32<3,$C$20,$C$21)*$C$22/1000 -> 0.050997785 | G71: =G70*IF(G32<3,$C$20,$C$21)*$C$22/1000 -> 0.15249557 | H71: =H70*IF(H32<3,$C$20,$C$21)*$C$22/1000 -> 0.1766852 | I71: =I70*IF(I32<3,$C$20,$C$21)*$C$22/1000 -> 0.22361061 | J71: =J70*IF(J32<3,$C$20,$C$21)*$C$22/1000 -> 0.23618203 | K71: Fórmula = tiempo de arco × caudal × factor
A72: Área exterior del recipiente | B72: m² | C72: =PI()*C33*C53/1000000+2*PI()/4*C33^2/1000000*$C$18 -> 0.081707179 | D72: =PI()*D33*D53/1000000+2*PI()/4*D33^2/1000000*$C$18 -> 0.15749809 | E72: =PI()*E33*E53/1000000+2*PI()/4*E33^2/1000000*$C$18 -> 0.24128115 | F72: =PI()*F33*F53/1000000+2*PI()/4*F33^2/1000000*$C$18 -> 0.39136326 | G72: =PI()*G33*G53/1000000+2*PI()/4*G33^2/1000000*$C$18 -> 0.7218376 | H72: =PI()*H33*H53/1000000+2*PI()/4*H33^2/1000000*$C$18 -> 1.0475327 | I72: =PI()*I33*I53/1000000+2*PI()/4*I33^2/1000000*$C$18 -> 1.3872566 | J72: =PI()*J33*J53/1000000+2*PI()/4*J33^2/1000000*$C$18 -> 1.6568053 | K72: Fórmula = π·Ø·H + 2·π/4·Ø²·factor domo
A73: ¿Se pinta en planta? (1 = sí) | B73: - | C73: 1 | D73: 1 | E73: 1 | F73: 1 | G73: 0 | H73: 0 | I73: 0 | J73: 0 | K73: Dimensionamiento (13): pintura de carros tercerizada siempre
A74: Pintura en polvo por recipiente | B74: kg | C74: =C72*C73*$C$17 -> 0.011439005 | D74: =D72*D73*$C$17 -> 0.022049733 | E74: =E72*E73*$C$17 -> 0.033779361 | F74: =F72*F73*$C$17 -> 0.054790856 | G74: =G72*G73*$C$17 -> 0 | H74: =H72*H73*$C$17 -> 0 | I74: =I72*I73*$C$17 -> 0 | J74: =J72*J73*$C$17 -> 0 | K74: Fórmula
A75: ¿Se granalla? (1 = sí) | B75: - | C75: 0 | D75: 1 | E75: 1 | F75: 1 | G75: 0 | H75: 0 | I75: 0 | J75: 0 | K75: Dimensionamiento (13): el 1 kg no se granalla; carros van a pintura tercerizada
A76: Granalla por recipiente | B76: kg | C76: =C75*$C$23/$C$24 -> 0 | D76: =D75*$C$23/$C$24 -> 0.073891626 | E76: =E75*$C$23/$C$24 -> 0.073891626 | F76: =F75*$C$23/$C$24 -> 0.073891626 | G76: =G75*$C$23/$C$24 -> 0 | H76: =H75*$C$23/$C$24 -> 0 | I76: =I75*$C$23/$C$24 -> 0 | J76: =J75*$C$23/$C$24 -> 0 | K76: Fórmula = consumo kg/h ÷ u/h
A77: Desengrasante por recipiente | B77: L | C77: =C72*C73*$C$25 -> 0.00081707179 | D77: =D72*D73*$C$25 -> 0.0015749809 | E77: =E72*E73*$C$25 -> 0.0024128115 | F77: =F72*F73*$C$25 -> 0.0039136326 | G77: =G72*G73*$C$25 -> 0 | H77: =H72*H73*$C$25 -> 0 | I77: =I72*I73*$C$25 -> 0 | J77: =J72*J73*$C$25 -> 0 | K77: Fórmula
A78: Fosfatizante por recipiente | B78: L | C78: =C72*C73*$C$26 -> 0.00081707179 | D78: =D72*D73*$C$26 -> 0.0015749809 | E78: =E72*E73*$C$26 -> 0.0024128115 | F78: =F72*F73*$C$26 -> 0.0039136326 | G78: =G72*G73*$C$26 -> 0 | H78: =H72*H73*$C$26 -> 0 | I78: =I72*I73*$C$26 -> 0 | J78: =J72*J73*$C$26 -> 0 | K78: Fórmula
A79: Hoja estándar — ancho | B79: mm | C79: 0 | D79: 1220 | E79: 1000 | F79: 1500 | G79: 1500 | H79: 1500 | I79: 1500 | J79: 1500 | K79: Opción D (Comparacion_corte › Nesting): formatos comerciales Pradecon 173195 / Parrotta 413329
A80: Hoja estándar — largo | B80: mm | C80: 0 | D80: 2440 | E80: 2000 | F80: 3000 | G80: 3000 | H80: 3000 | I80: 3000 | J80: 3000 | K80: Ídem
A81: Cuerpos de 1 kg por barra de 6 m | B81: u | C81: =FLOOR($C$9/(C35+$C$10),1) -> 23 | D81: 0 | E81: 0 | F81: 0 | G81: 0 | H81: 0 | I81: 0 | J81: 0 | K81: Fórmula = FLOOR(barra / (largo + merma))
A82: Barras de caño por cuerpo de 1 kg | B82: barra | C82: =1/C81 -> 0.043478261 | D82: 0 | E82: 0 | F82: 0 | G82: 0 | H82: 0 | I82: 0 | J82: 0 | K82: Fórmula
A83: Masa bruta de caño por cuerpo de 1 kg | B83: kg | C83: =$C$12/C81 -> 0.60273248 | D83: 0 | E83: 0 | F83: 0 | G83: 0 | H83: 0 | I83: 0 | J83: 0 | K83: Fórmula
A84: Masa de la hoja estándar | B84: kg | C84: 0 | D84: =IF(D79=0,0,D79*D80*D32*$C$6/1000000000) -> 29.20985 | E84: =IF(E79=0,0,E79*E80*E32*$C$6/1000000000) -> 25.12 | F84: =IF(F79=0,0,F79*F80*F32*$C$6/1000000000) -> 70.65 | G84: =IF(G79=0,0,G79*G80*G32*$C$6/1000000000) -> 113.04 | H84: =IF(H79=0,0,H79*H80*H32*$C$6/1000000000) -> 113.04 | I84: =IF(I79=0,0,I79*I80*I32*$C$6/1000000000) -> 167.79375 | J84: =IF(J79=0,0,J79*J80*J32*$C$6/1000000000) -> 167.79375 | K84: Fórmula = ancho × largo × e × ρ
A85: Cuerpos por hoja | B85: u | C85: 0 | D85: 27 | E85: 12 | F85: 15 | G85: 9 | H85: 6 | I85: 3 | J85: 3 | K85: Comparacion_corte › Nesting. 70 kg: hoja mixta (3 de 70 + 1 de 100 en 1212 × 2940 mm); 100 kg: 3 por hoja
A86: Cuerpos de 100 kg por hoja mixta | B86: u | C86: 0 | D86: 0 | E86: 0 | F86: 0 | G86: 0 | H86: 0 | I86: 1 | J86: 0 | K86: Solo en la hoja mixta del 70 kg (mezcla activa en Comparacion_corte)
A87: Hojas por cuerpo | B87: hoja | C87: 0 | D87: =IF(D85=0,0,1/D85) -> 0.037037037 | E87: =IF(E85=0,0,1/E85) -> 0.083333333 | F87: =IF(F85=0,0,1/F85) -> 0.066666667 | G87: =IF(G85=0,0,1/G85) -> 0.11111111 | H87: =IF(H85=0,0,1/H85) -> 0.16666667 | I87: =IF(I85=0,0,1/I85-I86/(I85*J85)) -> 0.22222222 | J87: =IF(J85=0,0,1/J85) -> 0.33333333 | K87: 1 / cuerpos por hoja. 70 kg: 1/3 − 1/9 (el 100 kg que sale de la misma hoja se cuenta en el 100 kg); vale mientras los 100 kg ≥ ⅓ de los 70 kg
A88: Aprovechamiento de la hoja | B88: % | C88: 0 | D88: =IF(D84=0,0,D85*D36/D84) -> 0.94231751 | E88: =IF(E84=0,0,E85*E36/E84) -> 0.93951 | F88: =IF(F84=0,0,F85*F36/F84) -> 0.92895 | G88: =IF(G84=0,0,G85*G36/G84) -> 0.84084 | H88: =IF(H84=0,0,H85*H36/H84) -> 0.84821333 | I88: =IF(I84=0,0,(I85*I36+I86*J36)/I84) -> 0.79184 | J88: =IF(J84=0,0,J85*J36/J84) -> 0.7272 | K88: Fórmula (70 kg: hoja mixta completa)
A89: Masa bruta de hoja por cuerpo | B89: kg | C89: 0 | D89: =D87*D84 -> 1.0818463 | E89: =E87*E84 -> 2.0933333 | F89: =F87*F84 -> 4.71 | G89: =G87*G84 -> 12.56 | H89: =H87*H84 -> 18.84 | I89: =I87*I84 -> 37.2875 | J89: =J87*J84 -> 55.93125 | K89: Hojas por cuerpo × masa de la hoja
A90: Orillas de guillotina (scrap) por cuerpo | B90: kg | C90: 0 | D90: =IF(D89=0,0,D89-D36) -> 0.062403593 | E90: =IF(E89=0,0,E89-E36) -> 0.12662573 | F90: =IF(F89=0,0,F89-F36) -> 0.3346455 | G90: =IF(G89=0,0,G89-G36) -> 1.9990496 | H90: =IF(H89=0,0,H89-H36) -> 2.8596608 | I90: =IF(I89=0,0,I89-I36) -> 6.556634 | J90: =IF(J89=0,0,J89-J36) -> 15.258045 | K90: Masa bruta − masa neta del cuerpo
A91: 1er corte: ancho de franja | B91: mm | C91: 0 | D91: 385.5 | E91: 330 | F91: 495 | G91: 490 | H91: 640 | I91: 1212 | J91: 1212 | K91: Comparacion_corte › Proceso D (70 kg: franja de 1212 de la hoja mixta)
A92: Franjas por hoja | B92: u | C92: 0 | D92: 3 | E92: 3 | F92: 3 | G92: 3 | H92: 2 | I92: 1 | J92: 1 | K92: Ídem
A93: 2º corte: largo de pieza | B93: mm | C93: 0 | D93: 269.5 | E93: 474.5 | F93: 563 | G93: 858 | H93: 994 | I93: 680 | J93: 900 | K93: Ídem
A94: Cortes de guillotina por hoja | B94: u | C94: 0 | D94: 30 | E94: 15 | F94: 18 | G94: 12 | H94: 8 | I94: 5 | J94: 4 | K94: Comparacion_corte › Nesting (hoja mixta: 5 cortes)
A95: Peso de la franja | B95: kg | C95: 0 | D95: =IF(D91=0,0,D91*D80*D32*$C$6/1000000000) -> 9.2298337 | E95: =IF(E91=0,0,E91*E80*E32*$C$6/1000000000) -> 8.2896 | F95: =IF(F91=0,0,F91*F80*F32*$C$6/1000000000) -> 23.3145 | G95: =IF(G91=0,0,G91*G80*G32*$C$6/1000000000) -> 36.9264 | H95: =IF(H91=0,0,H91*H80*H32*$C$6/1000000000) -> 48.2304 | I95: =IF(I91=0,0,I91*I80*I32*$C$6/1000000000) -> 135.57735 | J95: =IF(J91=0,0,J91*J80*J32*$C$6/1000000000) -> 135.57735 | K95: Ancho de franja × largo de hoja × e × ρ
A96: Cota máxima de tope trasero | B96: mm | C96: 0 | D96: =IF(D79=0,0,MAX(IF(D91>$C$27,D79-D91,D91),D93)) -> 385.5 | E96: =IF(E79=0,0,MAX(IF(E91>$C$27,E79-E91,E91),E93)) -> 474.5 | F96: =IF(F79=0,0,MAX(IF(F91>$C$27,F79-F91,F91),F93)) -> 563 | G96: =IF(G79=0,0,MAX(IF(G91>$C$27,G79-G91,G91),G93)) -> 858 | H96: =IF(H79=0,0,MAX(IF(H91>$C$27,H79-H91,H91),H93)) -> 994 | I96: =IF(I79=0,0,MAX(IF(I91>$C$27,I79-I91,I91),I93,J93)) -> 900 | J96: =IF(J79=0,0,MAX(IF(J91>$C$27,J79-J91,J91),J93)) -> 900 | K96: Si la franja supera el recorrido del tope, se corta primero la orilla (hoja − franja) y la franja queda adelante
A97: ¿Todos los cortes con tope? | B97: - | C97: — | D97: =IF(D79=0,"—",IF(D96<=$C$27,"SÍ","NO")) -> SÍ | E97: =IF(E79=0,"—",IF(E96<=$C$27,"SÍ","NO")) -> SÍ | F97: =IF(F79=0,"—",IF(F96<=$C$27,"SÍ","NO")) -> SÍ | G97: =IF(G79=0,"—",IF(G96<=$C$27,"SÍ","NO")) -> SÍ | H97: =IF(H79=0,"—",IF(H96<=$C$27,"SÍ","NO")) -> SÍ | I97: =IF(I79=0,"—",IF(I96<=$C$27,"SÍ","NO")) -> SÍ | J97: =IF(J79=0,"—",IF(J96<=$C$27,"SÍ","NO")) -> SÍ | K97: Compara con el recorrido del tope (C27)

Sheet Coef Fabricacion
A1: COEFICIENTES DE CONSUMO POR UNIDAD — FABRICACIÓN
A2: Cada fila es una MP. Consumo anual = Σ coef × volumen (hoja Consumo Anual). R = por recipiente fabricado (terminado + cilindro) · T = por matafuego terminado · C = por cilindro vendido vacío.
A4: PARÁMETROS
A5: Parámetro | B5: Unidad | C5: Valor | D5: Fuente / criterio
A6: Densidad aparente del polvo ABC | B6: kg/L | C6: 0.95 | D6: EST (0,9–1,1)
A7: Volumen libre para el gas (fracción del volumen interior) | B7: % | C7: 0.25 | D7: EST
A8: Presión de carga absoluta (1,4 MPa + 1 bar) | B8: bar | C8: 15 | D8: IRAM 3523: servicio 1,4 MPa (mails del Drive)
A9: Factor de pérdidas de N₂ en la carga (purga, mangueras) | B9: - | C9: 1.3 | D9: EST
A10: Merma de polvo en el llenado | B10: % | C10: 0.01 | D10: EST
A11: Matafuegos de 1 kg por caja | B11: u | C11: 6 | D11: ET's Matafuegos (caja × 6)
A12: Tapones de enmascarado — ciclos de vida | B12: ciclos | C12: 50 | D12: EST
A13: Alambre por punta de contacto | B13: kg | C13: 4 | D13: EST
A14: Recipientes por disco de amolado | B14: u | C14: 150 | D14: EST
A15: Film stretch por pallet | B15: kg | C15: 0.35 | D15: EST (con pre-estirado, recubridor EDOS PS5)
A16: Esquineros por pallet | B16: u | C16: 4 | D16: EST
A17: Masa válvula 1 kg (M22) | B17: kg | C17: 0.2 | D17: EST
A18: Masa válvula M30 + manómetro | B18: kg | C18: 0.35 | D18: EST
A20: Carga nominal de polvo por formato (kg) | B20: kg | L20: 1 | M20: 2.5 | N20: 5 | O20: 10 | P20: 25 | Q20: 50 | R20: 70 | S20: 100
D22: R — por RECIPIENTE fabricado | L22: T — por matafuego TERMINADO | T22: C — por CILINDRO vendido vacío
A23: Código | B23: Materia prima / insumo | C23: Unidad | D23: 1 kg | E23: 2,5 kg | F23: 5 kg | G23: 10 kg | H23: 25 kg | I23: 50 kg | J23: 70 kg | K23: 100 kg | L23: 1 kg | M23: 2,5 kg | N23: 5 kg | O23: 10 kg | P23: 25 kg | Q23: 50 kg | R23: 70 kg | S23: 100 kg | T23: 1 kg | U23: 2,5 kg | V23: 5 kg | W23: 10 kg | X23: 25 kg | Y23: 50 kg | Z23: 70 kg | AA23: 100 kg | AB23: Criterio / fuente | AC23: Confianza
A24: MP-01 | B24: Caño SAE 1010 c/costura Ø76,2 × 1,25 mm × 6 m (cuerpo 1 kg) | C24: barra | D24: ='Geometria Acero'!$C$82 -> 0.043478261 | E24: 0 | F24: 0 | G24: 0 | H24: 0 | I24: 0 | J24: 0 | K24: 0 | L24: 0 | M24: 0 | N24: 0 | O24: 0 | P24: 0 | Q24: 0 | R24: 0 | S24: 0 | T24: 0 | U24: 0 | V24: 0 | W24: 0 | X24: 0 | Y24: 0 | Z24: 0 | AA24: 0 | AB24: Barras por cuerpo = 1 / cuerpos por barra (Geometria) | AC24: COTIZ + EST
A25: MP-02 | B25: Hoja LAF 1,25 × 1220 × 2440 mm (cuerpos 2,5 kg; 27 por hoja) | C25: hoja | D25: 0 | E25: ='Geometria Acero'!$D$87 -> 0.037037037 | F25: 0 | G25: 0 | H25: 0 | I25: 0 | J25: 0 | K25: 0 | L25: 0 | M25: 0 | N25: 0 | O25: 0 | P25: 0 | Q25: 0 | R25: 0 | S25: 0 | T25: 0 | U25: 0 | V25: 0 | W25: 0 | X25: 0 | Y25: 0 | Z25: 0 | AA25: 0 | AB25: Hojas por cuerpo (Geometria, opción D) | AC25: COTIZ + nesting
A26: MP-03 | B26: Hoja LAF 1,6 × 1000 × 2000 mm (cuerpos 5 kg; 12 por hoja) | C26: hoja | D26: 0 | E26: 0 | F26: ='Geometria Acero'!$E$87 -> 0.083333333 | G26: 0 | H26: 0 | I26: 0 | J26: 0 | K26: 0 | L26: 0 | M26: 0 | N26: 0 | O26: 0 | P26: 0 | Q26: 0 | R26: 0 | S26: 0 | T26: 0 | U26: 0 | V26: 0 | W26: 0 | X26: 0 | Y26: 0 | Z26: 0 | AA26: 0 | AB26: Hojas por cuerpo (Geometria, opción D) | AC26: COTIZ + nesting
A27: MP-04 | B27: Hoja LAF 2,0 × 1500 × 3000 mm (cuerpos 10 kg; 15 por hoja) | C27: hoja | D27: 0 | E27: 0 | F27: 0 | G27: ='Geometria Acero'!$F$87 -> 0.066666667 | H27: 0 | I27: 0 | J27: 0 | K27: 0 | L27: 0 | M27: 0 | N27: 0 | O27: 0 | P27: 0 | Q27: 0 | R27: 0 | S27: 0 | T27: 0 | U27: 0 | V27: 0 | W27: 0 | X27: 0 | Y27: 0 | Z27: 0 | AA27: 0 | AB27: Hojas por cuerpo (Geometria, opción D) | AC27: COTIZ + nesting
A28: MP-05 | B28: Fleje LAF 0,9 × 114 mm (cúpula 1 kg) | C28: kg | D28: ='Geometria Acero'!$C$41 -> 0.08940051 | E28: 0 | F28: 0 | G28: 0 | H28: 0 | I28: 0 | J28: 0 | K28: 0 | L28: 0 | M28: 0 | N28: 0 | O28: 0 | P28: 0 | Q28: 0 | R28: 0 | S28: 0 | T28: 0 | U28: 0 | V28: 0 | W28: 0 | X28: 0 | Y28: 0 | Z28: 0 | AA28: 0 | AB28: Masa bruta de fleje por cúpula (Geometria) | AC28: COTIZ + EST
A29: MP-06 | B29: Fleje LAF 1,25 × 200 mm (cúpula Ø179 + fondo Ø148, 2,5 kg) | C29: kg | D29: 0 | E29: ='Geometria Acero'!$D$41+'Geometria Acero'!$D$47 -> 0.6535125 | F29: 0 | G29: 0 | H29: 0 | I29: 0 | J29: 0 | K29: 0 | L29: 0 | M29: 0 | N29: 0 | O29: 0 | P29: 0 | Q29: 0 | R29: 0 | S29: 0 | T29: 0 | U29: 0 | V29: 0 | W29: 0 | X29: 0 | Y29: 0 | Z29: 0 | AA29: 0 | AB29: Masa bruta de fleje cúpula + fondo | AC29: COTIZ
A30: MP-07 | B30: Fleje LAF 1,6 × 250 mm (cúpula Ø221, 5 kg) | C30: kg | D30: 0 | E30: 0 | F30: ='Geometria Acero'!$E$41 -> 0.70336 | G30: 0 | H30: 0 | I30: 0 | J30: 0 | K30: 0 | L30: 0 | M30: 0 | N30: 0 | O30: 0 | P30: 0 | Q30: 0 | R30: 0 | S30: 0 | T30: 0 | U30: 0 | V30: 0 | W30: 0 | X30: 0 | Y30: 0 | Z30: 0 | AA30: 0 | AB30: Masa bruta de fleje por cúpula | AC30: COTIZ
A31: MP-08 | B31: Fleje LAF 1,6 × 200 mm (fondo Ø177, 5 kg) | C31: kg | D31: 0 | E31: 0 | F31: ='Geometria Acero'!$E$47 -> 0.45216 | G31: 0 | H31: 0 | I31: 0 | J31: 0 | K31: 0 | L31: 0 | M31: 0 | N31: 0 | O31: 0 | P31: 0 | Q31: 0 | R31: 0 | S31: 0 | T31: 0 | U31: 0 | V31: 0 | W31: 0 | X31: 0 | Y31: 0 | Z31: 0 | AA31: 0 | AB31: Masa bruta de fleje por fondo | AC31: COTIZ
A32: MP-09 | B32: Fleje LAF 2,0 × 300 mm (cúpula Ø258, 10 kg) | C32: kg | D32: 0 | E32: 0 | F32: 0 | G32: ='Geometria Acero'!$F$41 -> 1.22931 | H32: 0 | I32: 0 | J32: 0 | K32: 0 | L32: 0 | M32: 0 | N32: 0 | O32: 0 | P32: 0 | Q32: 0 | R32: 0 | S32: 0 | T32: 0 | U32: 0 | V32: 0 | W32: 0 | X32: 0 | Y32: 0 | Z32: 0 | AA32: 0 | AB32: Masa bruta de fleje por cúpula | AC32: COTIZ
A33: MP-10 | B33: Fleje LAF 2,0 × 249 mm (fondo Ø205, 10 kg) | C33: kg | D33: 0 | E33: 0 | F33: 0 | G33: ='Geometria Acero'!$F$47 -> 0.8131344 | H33: 0 | I33: 0 | J33: 0 | K33: 0 | L33: 0 | M33: 0 | N33: 0 | O33: 0 | P33: 0 | Q33: 0 | R33: 0 | S33: 0 | T33: 0 | U33: 0 | V33: 0 | W33: 0 | X33: 0 | Y33: 0 | Z33: 0 | AA33: 0 | AB33: Masa bruta de fleje por fondo | AC33: COTIZ
A34: MP-11 | B34: Hoja LAC 3,2 × 1500 × 3000 mm (cuerpos 25 kg: 9 por hoja; 50 kg: 6 por hoja) | C34: hoja | D34: 0 | E34: 0 | F34: 0 | G34: 0 | H34: ='Geometria Acero'!$G$87 -> 0.11111111 | I34: ='Geometria Acero'!$H$87 -> 0.16666667 | J34: 0 | K34: 0 | L34: 0 | M34: 0 | N34: 0 | O34: 0 | P34: 0 | Q34: 0 | R34: 0 | S34: 0 | T34: 0 | U34: 0 | V34: 0 | W34: 0 | X34: 0 | Y34: 0 | Z34: 0 | AA34: 0 | AB34: Hojas por cuerpo (Geometria, opción D) | AC34: COTIZ + nesting
A35: MP-12 | B35: Hoja LAC 4,75 × 1500 × 3000 mm (cuerpos 70 y 100 kg; hoja mixta 3 × 70 + 1 × 100) | C35: hoja | D35: 0 | E35: 0 | F35: 0 | G35: 0 | H35: 0 | I35: 0 | J35: ='Geometria Acero'!$I$87 -> 0.22222222 | K35: ='Geometria Acero'!$J$87 -> 0.33333333 | L35: 0 | M35: 0 | N35: 0 | O35: 0 | P35: 0 | Q35: 0 | R35: 0 | S35: 0 | T35: 0 | U35: 0 | V35: 0 | W35: 0 | X35: 0 | Y35: 0 | Z35: 0 | AA35: 0 | AB35: Hojas por cuerpo; el 70 kg descuenta el 100 kg que sale de la hoja mixta (Geometria) | AC35: COTIZ + nesting
A36: MP-13 | B36: Fleje LAF 0,9 × 106 mm (fondo 1 kg) | C36: kg | D36: ='Geometria Acero'!$C$47 -> 0.07713567 | E36: 0 | F36: 0 | G36: 0 | H36: 0 | I36: 0 | J36: 0 | K36: 0 | L36: 0 | M36: 0 | N36: 0 | O36: 0 | P36: 0 | Q36: 0 | R36: 0 | S36: 0 | T36: 0 | U36: 0 | V36: 0 | W36: 0 | X36: 0 | Y36: 0 | Z36: 0 | AA36: 0 | AB36: Masa bruta de fleje por fondo (Geometria) | AC36: COTIZ + EST
A37: MP-15 | B37: Casquete embutido 10" × 3,2 mm (carro 25 kg) | C37: u | D37: 0 | E37: 0 | F37: 0 | G37: 0 | H37: 2 | I37: 0 | J37: 0 | K37: 0 | L37: 0 | M37: 0 | N37: 0 | O37: 0 | P37: 0 | Q37: 0 | R37: 0 | S37: 0 | T37: 0 | U37: 0 | V37: 0 | W37: 0 | X37: 0 | Y37: 0 | Z37: 0 | AA37: 0 | AB37: 2 casquetes (fondo = cúpula) por recipiente | AC37: DRIVE + EST
A38: MP-16 | B38: Casquete embutido 12" × 3,2 mm (carro 50 kg) | C38: u | D38: 0 | E38: 0 | F38: 0 | G38: 0 | H38: 0 | I38: 2 | J38: 0 | K38: 0 | L38: 0 | M38: 0 | N38: 0 | O38: 0 | P38: 0 | Q38: 0 | R38: 0 | S38: 0 | T38: 0 | U38: 0 | V38: 0 | W38: 0 | X38: 0 | Y38: 0 | Z38: 0 | AA38: 0 | AB38: 2 por recipiente | AC38: DRIVE + EST
A39: MP-17 | B39: Casquete embutido 15" × 4,75 mm (carros 70 y 100 kg) | C39: u | D39: 0 | E39: 0 | F39: 0 | G39: 0 | H39: 0 | I39: 0 | J39: 2 | K39: 2 | L39: 0 | M39: 0 | N39: 0 | O39: 0 | P39: 0 | Q39: 0 | R39: 0 | S39: 0 | T39: 0 | U39: 0 | V39: 0 | W39: 0 | X39: 0 | Y39: 0 | Z39: 0 | AA39: 0 | AB39: 2 por recipiente | AC39: DRIVE + EST
A40: MP-18 | B40: Asiento de válvula roscado M22 (cúpula 1 kg) | C40: u | D40: 1 | E40: 0 | F40: 0 | G40: 0 | H40: 0 | I40: 0 | J40: 0 | K40: 0 | L40: 0 | M40: 0 | N40: 0 | O40: 0 | P40: 0 | Q40: 0 | R40: 0 | S40: 0 | T40: 0 | U40: 0 | V40: 0 | W40: 0 | X40: 0 | Y40: 0 | Z40: 0 | AA40: 0 | AB40: 1 por recipiente | AC40: EST
A41: MP-19 | B41: Asiento de válvula roscado M30 × 1,5 (cúpula 2,5–10 kg) | C41: u | D41: 0 | E41: 1 | F41: 1 | G41: 1 | H41: 0 | I41: 0 | J41: 0 | K41: 0 | L41: 0 | M41: 0 | N41: 0 | O41: 0 | P41: 0 | Q41: 0 | R41: 0 | S41: 0 | T41: 0 | U41: 0 | V41: 0 | W41: 0 | X41: 0 | Y41: 0 | Z41: 0 | AA41: 0 | AB41: 1 por recipiente | AC41: EST
A42: MP-20 | B42: Cupla soldable M30 × 1,5 (carros 25 y 50 kg) | C42: u | D42: 0 | E42: 0 | F42: 0 | G42: 0 | H42: 1 | I42: 1 | J42: 0 | K42: 0 | L42: 0 | M42: 0 | N42: 0 | O42: 0 | P42: 0 | Q42: 0 | R42: 0 | S42: 0 | T42: 0 | U42: 0 | V42: 0 | W42: 0 | X42: 0 | Y42: 0 | Z42: 0 | AA42: 0 | AB42: 1 por recipiente | AC42: COTIZ
A43: MP-21 | B43: Cupla soldable 2½" BSP (carros 70 y 100 kg) | C43: u | D43: 0 | E43: 0 | F43: 0 | G43: 0 | H43: 0 | I43: 0 | J43: 1 | K43: 1 | L43: 0 | M43: 0 | N43: 0 | O43: 0 | P43: 0 | Q43: 0 | R43: 0 | S43: 0 | T43: 0 | U43: 0 | V43: 0 | W43: 0 | X43: 0 | Y43: 0 | Z43: 0 | AA43: 0 | AB43: 1 por recipiente | AC43: COTIZ
A44: MP-22 | B44: Varilla de refuerzo (carros 70 y 100 kg) | C44: kg | D44: 0 | E44: 0 | F44: 0 | G44: 0 | H44: 0 | I44: 0 | J44: ='Geometria Acero'!$I$55 -> 1.5 | K44: ='Geometria Acero'!$J$55 -> 1.5 | L44: 0 | M44: 0 | N44: 0 | O44: 0 | P44: 0 | Q44: 0 | R44: 0 | S44: 0 | T44: 0 | U44: 0 | V44: 0 | W44: 0 | X44: 0 | Y44: 0 | Z44: 0 | AA44: 0 | AB44: kg por recipiente (Geometria) | AC44: COTIZ + EST
A45: MP-23 | B45: Alambre MIG ER70S-6 Ø0,9 mm (manuales 1–10 kg) | C45: kg | D45: ='Geometria Acero'!$C$67 -> 0.014994193 | E45: ='Geometria Acero'!$D$67 -> 0.030398139 | F45: ='Geometria Acero'!$E$67 -> 0.036749113 | G45: ='Geometria Acero'!$F$67 -> 0.045752298 | H45: 0 | I45: 0 | J45: 0 | K45: 0 | L45: 0 | M45: 0 | N45: 0 | O45: 0 | P45: 0 | Q45: 0 | R45: 0 | S45: 0 | T45: 0 | U45: 0 | V45: 0 | W45: 0 | X45: 0 | Y45: 0 | Z45: 0 | AA45: 0 | AB45: kg por recipiente (Geometria) | AC45: WEB + EST
A46: MP-24 | B46: Alambre MIG ER70S-6 Ø1,2 mm (carros 25–100 kg) | C46: kg | D46: 0 | E46: 0 | F46: 0 | G46: 0 | H46: ='Geometria Acero'!$G$67 -> 0.3025978 | I46: ='Geometria Acero'!$H$67 -> 0.35059742 | J46: ='Geometria Acero'!$I$67 -> 0.75089684 | K46: ='Geometria Acero'!$J$67 -> 0.79311239 | L46: 0 | M46: 0 | N46: 0 | O46: 0 | P46: 0 | Q46: 0 | R46: 0 | S46: 0 | T46: 0 | U46: 0 | V46: 0 | W46: 0 | X46: 0 | Y46: 0 | Z46: 0 | AA46: 0 | AB46: kg por recipiente (Geometria) | AC46: WEB + EST
A47: MP-25 | B47: Gas de protección Ar + 8 % CO₂ (ARCAL 21) | C47: m³ | D47: ='Geometria Acero'!$C$71 -> 0.016713273 | E47: ='Geometria Acero'!$D$71 -> 0.033883276 | F47: ='Geometria Acero'!$E$71 -> 0.040962387 | G47: ='Geometria Acero'!$F$71 -> 0.050997785 | H47: ='Geometria Acero'!$G$71 -> 0.15249557 | I47: ='Geometria Acero'!$H$71 -> 0.1766852 | J47: ='Geometria Acero'!$I$71 -> 0.22361061 | K47: ='Geometria Acero'!$J$71 -> 0.23618203 | L47: 0 | M47: 0 | N47: 0 | O47: 0 | P47: 0 | Q47: 0 | R47: 0 | S47: 0 | T47: 0 | U47: 0 | V47: 0 | W47: 0 | X47: 0 | Y47: 0 | Z47: 0 | AA47: 0 | AB47: m³ por recipiente (Geometria) | AC47: DRIVE + EST
A48: MP-26 | B48: Puntas de contacto y toberas MIG | C48: u | D48: ='Geometria Acero'!$C$67/'Coef Fabricacion'!$C$13 -> 0.0037485484 | E48: ='Geometria Acero'!$D$67/'Coef Fabricacion'!$C$13 -> 0.0075995347 | F48: ='Geometria Acero'!$E$67/'Coef Fabricacion'!$C$13 -> 0.0091872782 | G48: ='Geometria Acero'!$F$67/'Coef Fabricacion'!$C$13 -> 0.011438075 | H48: ='Geometria Acero'!$G$67/'Coef Fabricacion'!$C$13 -> 0.07564945 | I48: ='Geometria Acero'!$H$67/'Coef Fabricacion'!$C$13 -> 0.087649355 | J48: ='Geometria Acero'!$I$67/'Coef Fabricacion'!$C$13 -> 0.18772421 | K48: ='Geometria Acero'!$J$67/'Coef Fabricacion'!$C$13 -> 0.1982781 | L48: 0 | M48: 0 | N48: 0 | O48: 0 | P48: 0 | Q48: 0 | R48: 0 | S48: 0 | T48: 0 | U48: 0 | V48: 0 | W48: 0 | X48: 0 | Y48: 0 | Z48: 0 | AA48: 0 | AB48: 1 punta cada 4 kg de alambre | AC48: EST
A49: MP-27 | B49: Discos de amolado y corte Ø115 mm | C49: u | D49: =1/'Coef Fabricacion'!$C$14 -> 0.0066666667 | E49: =1/'Coef Fabricacion'!$C$14 -> 0.0066666667 | F49: =1/'Coef Fabricacion'!$C$14 -> 0.0066666667 | G49: =1/'Coef Fabricacion'!$C$14 -> 0.0066666667 | H49: =1/'Coef Fabricacion'!$C$14 -> 0.0066666667 | I49: =1/'Coef Fabricacion'!$C$14 -> 0.0066666667 | J49: =1/'Coef Fabricacion'!$C$14 -> 0.0066666667 | K49: =1/'Coef Fabricacion'!$C$14 -> 0.0066666667 | L49: 0 | M49: 0 | N49: 0 | O49: 0 | P49: 0 | Q49: 0 | R49: 0 | S49: 0 | T49: 0 | U49: 0 | V49: 0 | W49: 0 | X49: 0 | Y49: 0 | Z49: 0 | AA49: 0 | AB49: 1 disco cada 150 recipientes | AC49: EST
A50: MP-28 | B50: Granalla de acero S330/S390 (reposición) | C50: kg | D50: ='Geometria Acero'!$C$76 -> 0 | E50: ='Geometria Acero'!$D$76 -> 0.073891626 | F50: ='Geometria Acero'!$E$76 -> 0.073891626 | G50: ='Geometria Acero'!$F$76 -> 0.073891626 | H50: ='Geometria Acero'!$G$76 -> 0 | I50: ='Geometria Acero'!$H$76 -> 0 | J50: ='Geometria Acero'!$I$76 -> 0 | K50: ='Geometria Acero'!$J$76 -> 0 | L50: 0 | M50: 0 | N50: 0 | O50: 0 | P50: 0 | Q50: 0 | R50: 0 | S50: 0 | T50: 0 | U50: 0 | V50: 0 | W50: 0 | X50: 0 | Y50: 0 | Z50: 0 | AA50: 0 | AB50: kg por recipiente granallado (Geometria) | AC50: COTIZ + EST
A51: MP-29 | B51: Desengrasante alcalino (pretratamiento) | C51: L | D51: ='Geometria Acero'!$C$77 -> 0.00081707179 | E51: ='Geometria Acero'!$D$77 -> 0.0015749809 | F51: ='Geometria Acero'!$E$77 -> 0.0024128115 | G51: ='Geometria Acero'!$F$77 -> 0.0039136326 | H51: ='Geometria Acero'!$G$77 -> 0 | I51: ='Geometria Acero'!$H$77 -> 0 | J51: ='Geometria Acero'!$I$77 -> 0 | K51: ='Geometria Acero'!$J$77 -> 0 | L51: 0 | M51: 0 | N51: 0 | O51: 0 | P51: 0 | Q51: 0 | R51: 0 | S51: 0 | T51: 0 | U51: 0 | V51: 0 | W51: 0 | X51: 0 | Y51: 0 | Z51: 0 | AA51: 0 | AB51: L por recipiente pintado (Geometria) | AC51: EST
A52: MP-30 | B52: Fosfatizante (fosfato de hierro) | C52: L | D52: ='Geometria Acero'!$C$78 -> 0.00081707179 | E52: ='Geometria Acero'!$D$78 -> 0.0015749809 | F52: ='Geometria Acero'!$E$78 -> 0.0024128115 | G52: ='Geometria Acero'!$F$78 -> 0.0039136326 | H52: ='Geometria Acero'!$G$78 -> 0 | I52: ='Geometria Acero'!$H$78 -> 0 | J52: ='Geometria Acero'!$I$78 -> 0 | K52: ='Geometria Acero'!$J$78 -> 0 | L52: 0 | M52: 0 | N52: 0 | O52: 0 | P52: 0 | Q52: 0 | R52: 0 | S52: 0 | T52: 0 | U52: 0 | V52: 0 | W52: 0 | X52: 0 | Y52: 0 | Z52: 0 | AA52: 0 | AB52: L por recipiente pintado | AC52: EST
A53: MP-31 | B53: Pintura en polvo poliéster RAL 3000 (rojo) | C53: kg | D53: ='Geometria Acero'!$C$74 -> 0.011439005 | E53: ='Geometria Acero'!$D$74 -> 0.022049733 | F53: ='Geometria Acero'!$E$74 -> 0.033779361 | G53: ='Geometria Acero'!$F$74 -> 0.054790856 | H53: ='Geometria Acero'!$G$74 -> 0 | I53: ='Geometria Acero'!$H$74 -> 0 | J53: ='Geometria Acero'!$I$74 -> 0 | K53: ='Geometria Acero'!$J$74 -> 0 | L53: 0 | M53: 0 | N53: 0 | O53: 0 | P53: 0 | Q53: 0 | R53: 0 | S53: 0 | T53: 0 | U53: 0 | V53: 0 | W53: 0 | X53: 0 | Y53: 0 | Z53: 0 | AA53: 0 | AB53: kg por recipiente (área × consumo práctico) | AC53: WEB + EST
A54: MP-32 | B54: Tapones de enmascarado (silicona) para rosca | C54: u | D54: ='Geometria Acero'!$C$73/'Coef Fabricacion'!$C$12 -> 0.02 | E54: ='Geometria Acero'!$D$73/'Coef Fabricacion'!$C$12 -> 0.02 | F54: ='Geometria Acero'!$E$73/'Coef Fabricacion'!$C$12 -> 0.02 | G54: ='Geometria Acero'!$F$73/'Coef Fabricacion'!$C$12 -> 0.02 | H54: ='Geometria Acero'!$G$73/'Coef Fabricacion'!$C$12 -> 0 | I54: ='Geometria Acero'!$H$73/'Coef Fabricacion'!$C$12 -> 0 | J54: ='Geometria Acero'!$I$73/'Coef Fabricacion'!$C$12 -> 0 | K54: ='Geometria Acero'!$J$73/'Coef Fabricacion'!$C$12 -> 0 | L54: 0 | M54: 0 | N54: 0 | O54: 0 | P54: 0 | Q54: 0 | R54: 0 | S54: 0 | T54: 0 | U54: 0 | V54: 0 | W54: 0 | X54: 0 | Y54: 0 | Z54: 0 | AA54: 0 | AB54: 1 cada 50 ciclos de pintura | AC54: EST
A55: MP-33 | B55: Polvo químico ABC (MAP ≥55 %, IRAM 3569) | C55: kg | D55: 0 | E55: 0 | F55: 0 | G55: 0 | H55: 0 | I55: 0 | J55: 0 | K55: 0 | L55: =L$20*(1+$C$10) -> 1.01 | M55: =M$20*(1+$C$10) -> 2.525 | N55: =N$20*(1+$C$10) -> 5.05 | O55: =O$20*(1+$C$10) -> 10.1 | P55: =P$20*(1+$C$10) -> 25.25 | Q55: =Q$20*(1+$C$10) -> 50.5 | R55: =R$20*(1+$C$10) -> 70.7 | S55: =S$20*(1+$C$10) -> 101 | T55: 0 | U55: 0 | V55: 0 | W55: 0 | X55: 0 | Y55: 0 | Z55: 0 | AA55: 0 | AB55: Carga nominal + 1 % de merma; recargas: % de polvo nuevo | AC55: COTIZ + WEB + EST
A56: MP-34 | B56: Nitrógeno seco (≥99,8 %, rocío ≤ −40 °C) | C56: m³ | D56: 0 | E56: 0 | F56: 0 | G56: 0 | H56: 0 | I56: 0 | J56: 0 | K56: 0 | L56: =L$20/$C$6*$C$7/(1-$C$7)*$C$8*$C$9/1000 -> 0.0068421053 | M56: =M$20/$C$6*$C$7/(1-$C$7)*$C$8*$C$9/1000 -> 0.017105263 | N56: =N$20/$C$6*$C$7/(1-$C$7)*$C$8*$C$9/1000 -> 0.034210526 | O56: =O$20/$C$6*$C$7/(1-$C$7)*$C$8*$C$9/1000 -> 0.068421053 | P56: =P$20/$C$6*$C$7/(1-$C$7)*$C$8*$C$9/1000 -> 0.17105263 | Q56: =Q$20/$C$6*$C$7/(1-$C$7)*$C$8*$C$9/1000 -> 0.34210526 | R56: =R$20/$C$6*$C$7/(1-$C$7)*$C$8*$C$9/1000 -> 0.47894737 | S56: =S$20/$C$6*$C$7/(1-$C$7)*$C$8*$C$9/1000 -> 0.68421053 | T56: 0 | U56: 0 | V56: 0 | W56: 0 | X56: 0 | Y56: 0 | Z56: 0 | AA56: 0 | AB56: Volumen libre × 15 bar × pérdidas | AC56: DRIVE + EST
A57: MP-42 | B57: Válvula M-22 para 1 kg con tubo de pesca | C57: u | D57: 0 | E57: 0 | F57: 0 | G57: 0 | H57: 0 | I57: 0 | J57: 0 | K57: 0 | L57: 1 | M57: 0 | N57: 0 | O57: 0 | P57: 0 | Q57: 0 | R57: 0 | S57: 0 | T57: 0 | U57: 0 | V57: 0 | W57: 0 | X57: 0 | Y57: 0 | Z57: 0 | AA57: 0 | AB57: 1 por terminado; 3 % de reposición en recargas | AC57: COTIZ
A58: MP-43 | B58: Válvula M-30 con resorte para 2,5–10 kg | C58: u | D58: 0 | E58: 0 | F58: 0 | G58: 0 | H58: 0 | I58: 0 | J58: 0 | K58: 0 | L58: 0 | M58: 1 | N58: 1 | O58: 1 | P58: 0 | Q58: 0 | R58: 0 | S58: 0 | T58: 0 | U58: 0 | V58: 0 | W58: 0 | X58: 0 | Y58: 0 | Z58: 0 | AA58: 0 | AB58: 1 por terminado; 3 % de reposición | AC58: COTIZ
A59: MP-44 | B59: Válvula para carro 25–100 kg (con traba, manija y resorte) | C59: u | D59: 0 | E59: 0 | F59: 0 | G59: 0 | H59: 0 | I59: 0 | J59: 0 | K59: 0 | L59: 0 | M59: 0 | N59: 0 | O59: 0 | P59: 1 | Q59: 1 | R59: 1 | S59: 1 | T59: 0 | U59: 0 | V59: 0 | W59: 0 | X59: 0 | Y59: 0 | Z59: 0 | AA59: 0 | AB59: 1 por carro terminado | AC59: COTIZ
A60: MP-45 | B60: Manómetro IRAM 3533 (1,4 MPa) | C60: u | D60: 0 | E60: 0 | F60: 0 | G60: 0 | H60: 0 | I60: 0 | J60: 0 | K60: 0 | L60: 1 | M60: 1 | N60: 1 | O60: 1 | P60: 1 | Q60: 1 | R60: 1 | S60: 1 | T60: 0 | U60: 0 | V60: 0 | W60: 0 | X60: 0 | Y60: 0 | Z60: 0 | AA60: 0 | AB60: 1 por terminado; 8 % de reposición | AC60: EST
A61: MP-46 | B61: Tubo pescante PP/PEAD (2,5–10 kg) | C61: u | D61: 0 | E61: 0 | F61: 0 | G61: 0 | H61: 0 | I61: 0 | J61: 0 | K61: 0 | L61: 0 | M61: 1 | N61: 1 | O61: 1 | P61: 0 | Q61: 0 | R61: 0 | S61: 0 | T61: 0 | U61: 0 | V61: 0 | W61: 0 | X61: 0 | Y61: 0 | Z61: 0 | AA61: 0 | AB61: 1 por terminado (en 1 kg viene con la válvula) | AC61: EST
A62: MP-47 | B62: Tubo pescante de acero (carros) | C62: u | D62: 0 | E62: 0 | F62: 0 | G62: 0 | H62: 0 | I62: 0 | J62: 0 | K62: 0 | L62: 0 | M62: 0 | N62: 0 | O62: 0 | P62: 1 | Q62: 1 | R62: 1 | S62: 1 | T62: 0 | U62: 0 | V62: 0 | W62: 0 | X62: 0 | Y62: 0 | Z62: 0 | AA62: 0 | AB62: 1 por carro | AC62: EST
A63: MP-48 | B63: Manguera + tobera (2,5–10 kg) | C63: u | D63: 0 | E63: 0 | F63: 0 | G63: 0 | H63: 0 | I63: 0 | J63: 0 | K63: 0 | L63: 0 | M63: 1 | N63: 1 | O63: 1 | P63: 0 | Q63: 0 | R63: 0 | S63: 0 | T63: 0 | U63: 0 | V63: 0 | W63: 0 | X63: 0 | Y63: 0 | Z63: 0 | AA63: 0 | AB63: 1 por terminado (el 1 kg no lleva) | AC63: EST
A64: MP-49 | B64: Manguera + lanza/pistola para carro | C64: u | D64: 0 | E64: 0 | F64: 0 | G64: 0 | H64: 0 | I64: 0 | J64: 0 | K64: 0 | L64: 0 | M64: 0 | N64: 0 | O64: 0 | P64: 1 | Q64: 1 | R64: 1 | S64: 1 | T64: 0 | U64: 0 | V64: 0 | W64: 0 | X64: 0 | Y64: 0 | Z64: 0 | AA64: 0 | AB64: 1 por carro | AC64: EST
A65: MP-50 | B65: O-ring NBR 70 | C65: u | D65: 0 | E65: 0 | F65: 0 | G65: 0 | H65: 0 | I65: 0 | J65: 0 | K65: 0 | L65: 2 | M65: 2 | N65: 2 | O65: 2 | P65: 2 | Q65: 2 | R65: 2 | S65: 2 | T65: 0 | U65: 0 | V65: 0 | W65: 0 | X65: 0 | Y65: 0 | Z65: 0 | AA65: 0 | AB65: 2 por válvula; en recargas solo si se desarma | AC65: EST
A66: MP-51 | B66: Pasador + precinto de seguridad numerado | C66: u | D66: 0 | E66: 0 | F66: 0 | G66: 0 | H66: 0 | I66: 0 | J66: 0 | K66: 0 | L66: 1 | M66: 1 | N66: 1 | O66: 1 | P66: 1 | Q66: 1 | R66: 1 | S66: 1 | T66: 0 | U66: 0 | V66: 0 | W66: 0 | X66: 0 | Y66: 0 | Z66: 0 | AA66: 0 | AB66: 1 por terminado y por recarga | AC66: EST
A67: MP-52 | B67: Soporte de pared (1–10 kg) | C67: u | D67: 0 | E67: 0 | F67: 0 | G67: 0 | H67: 0 | I67: 0 | J67: 0 | K67: 0 | L67: 1 | M67: 1 | N67: 1 | O67: 1 | P67: 0 | Q67: 0 | R67: 0 | S67: 0 | T67: 0 | U67: 0 | V67: 0 | W67: 0 | X67: 0 | Y67: 0 | Z67: 0 | AA67: 0 | AB67: 1 por terminado manual | AC67: EST
A68: MP-53 | B68: Estructura de carro (chasis, eje, manija, ganchos) | C68: u | D68: 0 | E68: 0 | F68: 0 | G68: 0 | H68: 0 | I68: 0 | J68: 0 | K68: 0 | L68: 0 | M68: 0 | N68: 0 | O68: 0 | P68: 1 | Q68: 1 | R68: 1 | S68: 1 | T68: 0 | U68: 0 | V68: 0 | W68: 0 | X68: 0 | Y68: 0 | Z68: 0 | AA68: 0 | AB68: 1 por carro terminado | AC68: EST
... A71: MP-58 | B71: Tarjeta de control / mantenimiento | C71: u | D71: 0 | E71: 0 | F71: 0 | G71: 0 | H71: 0 | I71: 0 | J71: 0 | K71: 0 | L71: 1 | M71: 1 | N71: 1 | O71: 1 | P71: 1 | Q71: 1 | R71: 1 | S71: 1 | T71: 0 | U71: 0 | V71: 0 | W71: 0 | X71: 0 | Y71: 0 | Z71: 0 | AA71: 0 | AB71: 1 por terminado y por recarga | AC71: EST
A72: MP-59 | B72: Caja de cartón corrugado (individual 2,5–10 kg; × 6 para 1 kg) | C72: u | D72: 0 | E72: 0 | F72: 0 | G72: 0 | H72: 0 | I72: 0 | J72: 0 | K72: 0 | L72: =1/$C$11 -> 0.16666667 | M72: 1 | N72: 1 | O72: 1 | P72: 0 | Q72: 0 | R72: 0 | S72: 0 | T72: 0 | U72: 0 | V72: 0 | W72: 0 | X72: 0 | Y72: 0 | Z72: 0 | AA72: 0 | AB72: 1 por terminado (1 kg: 1 cada 6) | AC72: EST
A73: MP-60 | B73: Pallet ARLOG 1200 × 1000 (despacho de PT) | C73: u | D73: 0 | E73: 0 | F73: 0 | G73: 0 | H73: 0 | I73: 0 | J73: 0 | K73: 0 | L73: =IF('Pallets PT'!C$49=0,0,1/'Pallets PT'!C$49) -> 0.0027777778 | M73: =IF('Pallets PT'!D$49=0,0,1/'Pallets PT'!D$49) -> 0.005952381 | N73: =IF('Pallets PT'!E$49=0,0,1/'Pallets PT'!E$49) -> 0.011904762 | O73: =IF('Pallets PT'!F$49=0,0,1/'Pallets PT'!F$49) -> 0.016666667 | P73: 0 | Q73: 0 | R73: 0 | S73: 0 | T73: =IF('Pallets PT'!C$29=0,0,1/'Pallets PT'!C$29) -> 0.0012820513 | U73: =IF('Pallets PT'!D$29=0,0,1/'Pallets PT'!D$29) -> 0.0034722222 | V73: =IF('Pallets PT'!E$29=0,0,1/'Pallets PT'!E$29) -> 0.0079365079 | W73: =IF('Pallets PT'!F$29=0,0,1/'Pallets PT'!F$29) -> 0.016666667 | X73: =IF('Pallets PT'!G$29=0,0,1/'Pallets PT'!G$29) -> 0.041666667 | Y73: =IF('Pallets PT'!H$29=0,0,1/'Pallets PT'!H$29) -> 0.11111111 | Z73: =IF('Pallets PT'!I$29=0,0,1/'Pallets PT'!I$29) -> 0.16666667 | AA73: =IF('Pallets PT'!J$29=0,0,1/'Pallets PT'!J$29) -> 0.16666667 | AB73: 1 / unidades por pallet (Pallets PT) | AC73: WEB + EST
A74: MP-61 | B74: Separador de capa (cartón) para pallets de cilindros | C74: u | D74: 0 | E74: 0 | F74: 0 | G74: 0 | H74: 0 | I74: 0 | J74: 0 | K74: 0 | L74: 0 | M74: 0 | N74: 0 | O74: 0 | P74: 0 | Q74: 0 | R74: 0 | S74: 0 | T74: =IF('Pallets PT'!C$29=0,0,'Pallets PT'!C$30/'Pallets PT'!C$29) -> 0.0064102564 | U74: =IF('Pallets PT'!D$29=0,0,'Pallets PT'!D$30/'Pallets PT'!D$29) -> 0.017361111 | V74: =IF('Pallets PT'!E$29=0,0,'Pallets PT'!E$30/'Pallets PT'!E$29) -> 0.031746032 | W74: =IF('Pallets PT'!F$29=0,0,'Pallets PT'!F$30/'Pallets PT'!F$29) -> 0.05 | X74: =IF('Pallets PT'!G$29=0,0,'Pallets PT'!G$30/'Pallets PT'!G$29) -> 0.125 | Y74: =IF('Pallets PT'!H$29=0,0,'Pallets PT'!H$30/'Pallets PT'!H$29) -> 0.22222222 | Z74: =IF('Pallets PT'!I$29=0,0,'Pallets PT'!I$30/'Pallets PT'!I$29) -> 0.33333333 | AA74: =IF('Pallets PT'!J$29=0,0,'Pallets PT'!J$30/'Pallets PT'!J$29) -> 0.33333333 | AB74: (capas + 1) / unidades por pallet | AC74: EST
A75: MP-62 | B75: Tapón protector de rosca (cilindros vendidos) | C75: u | D75: 0 | E75: 0 | F75: 0 | G75: 0 | H75: 0 | I75: 0 | J75: 0 | K75: 0 | L75: 0 | M75: 0 | N75: 0 | O75: 0 | P75: 0 | Q75: 0 | R75: 0 | S75: 0 | T75: 1 | U75: 1 | V75: 1 | W75: 1 | X75: 1 | Y75: 1 | Z75: 1 | AA75: 1 | AB75: 1 por cilindro vendido | AC75: EST
A76: MP-63 | B76: Film stretch 500 mm (bobina ≈16 kg) | C76: kg | D76: 0 | E76: 0 | F76: 0 | G76: 0 | H76: 0 | I76: 0 | J76: 0 | K76: 0 | L76: =IF('Pallets PT'!C$49=0,0,$C$15/'Pallets PT'!C$49) -> 0.00097222222 | M76: =IF('Pallets PT'!D$49=0,0,$C$15/'Pallets PT'!D$49) -> 0.0020833333 | N76: =IF('Pallets PT'!E$49=0,0,$C$15/'Pallets PT'!E$49) -> 0.0041666667 | O76: =IF('Pallets PT'!F$49=0,0,$C$15/'Pallets PT'!F$49) -> 0.0058333333 | P76: 0 | Q76: 0 | R76: 0 | S76: 0 | T76: =IF('Pallets PT'!C$29=0,0,$C$15/'Pallets PT'!C$29) -> 0.00044871795 | U76: =IF('Pallets PT'!D$29=0,0,$C$15/'Pallets PT'!D$29) -> 0.0012152778 | V76: =IF('Pallets PT'!E$29=0,0,$C$15/'Pallets PT'!E$29) -> 0.0027777778 | W76: =IF('Pallets PT'!F$29=0,0,$C$15/'Pallets PT'!F$29) -> 0.0058333333 | X76: =IF('Pallets PT'!G$29=0,0,$C$15/'Pallets PT'!G$29) -> 0.014583333 | Y76: =IF('Pallets PT'!H$29=0,0,$C$15/'Pallets PT'!H$29) -> 0.038888889 | Z76: =IF('Pallets PT'!I$29=0,0,$C$15/'Pallets PT'!I$29) -> 0.058333333 | AA76: =IF('Pallets PT'!J$29=0,0,$C$15/'Pallets PT'!J$29) -> 0.058333333 | AB76: kg por pallet / unidades por pallet | AC76: COTIZ + EST
A77: MP-64 | B77: Esquineros de cartón | C77: u | D77: 0 | E77: 0 | F77: 0 | G77: 0 | H77: 0 | I77: 0 | J77: 0 | K77: 0 | L77: =IF('Pallets PT'!C$49=0,0,$C$16/'Pallets PT'!C$49) -> 0.011111111 | M77: =IF('Pallets PT'!D$49=0,0,$C$16/'Pallets PT'!D$49) -> 0.023809524 | N77: =IF('Pallets PT'!E$49=0,0,$C$16/'Pallets PT'!E$49) -> 0.047619048 | O77: =IF('Pallets PT'!F$49=0,0,$C$16/'Pallets PT'!F$49) -> 0.066666667 | P77: 0 | Q77: 0 | R77: 0 | S77: 0 | T77: =IF('Pallets PT'!C$29=0,0,$C$16/'Pallets PT'!C$29) -> 0.0051282051 | U77: =IF('Pallets PT'!D$29=0,0,$C$16/'Pallets PT'!D$29) -> 0.013888889 | V77: =IF('Pallets PT'!E$29=0,0,$C$16/'Pallets PT'!E$29) -> 0.031746032 | W77: =IF('Pallets PT'!F$29=0,0,$C$16/'Pallets PT'!F$29) -> 0.066666667 | X77: =IF('Pallets PT'!G$29=0,0,$C$16/'Pallets PT'!G$29) -> 0.16666667 | Y77: =IF('Pallets PT'!H$29=0,0,$C$16/'Pallets PT'!H$29) -> 0.44444444 | Z77: =IF('Pallets PT'!I$29=0,0,$C$16/'Pallets PT'!I$29) -> 0.66666667 | AA77: =IF('Pallets PT'!J$29=0,0,$C$16/'Pallets PT'!J$29) -> 0.66666667 | AB77: 4 por pallet | AC77: EST

Sheet Coef Recargas
A1: COEFICIENTES DE CONSUMO POR UNIDAD — RECARGAS (planta industrial)
A2: Por recarga, según tipo de equipo. Se usan los % del Dimensionamiento (13) › Parametros Recargas cuando existen.
A4: PARÁMETROS
A5: Parámetro | B5: Unidad | C5: Valor | D5: Fuente / criterio
A6: Polvo ABC/BC nuevo por recarga (reposición + rechazos) | B6: % | C6: 0.25 | D6: EST: ≈15 % de reposición + 10 % de rechazo en el ensayo Puffer (IRAM 3672, muestreo 10 %)
A7: Polvo clase D nuevo por recarga | B7: % | C7: 0.3 | D7: EST
A8: % CO₂ / agente limpio que se vacían y recargan | B8: % | C8: 0.35 | D8: Dimensionamiento (13) › Parametros Recargas
A9: Pérdidas de trasvase de CO₂ | B9: % | C9: 0.1 | D9: EST
A10: Pérdidas de agente limpio | B10: % | C10: 0.05 | D10: EST
A11: Concentración de AFFF en la premezcla | B11: % | C11: 0.06 | D11: EST conservador (AFFF 3 % o 6 %; lista de precios Drive)
A12: N₂ por recarga agua / AFFF 10 l | B12: m³ | C12: 0.036 | D12: EST: 2,5 L libres × 11 bar × 1,3
A13: N₂ por recarga AFFF 50 l | B13: m³ | C13: 0.18 | D13: EST
A14: N₂ por recarga clase K 6 l | B14: m³ | C14: 0.022 | D14: EST
A15: Argón por recarga de agente limpio vaciado | B15: m³ | C15: 0.02 | D15: EST
A16: Reposición de manómetros | B16: % | C16: 0.08 | D16: EST
A17: Reposición de válvulas | B17: % | C17: 0.03 | D17: EST
... A22: Carga de un equipo clase D 9 l | B22: kg | C22: 10 | D22: EST (BOM Drive: CLD-10)
A24: Carga nominal (kg o litros) | D24: 1 | E24: 2.5 | F24: 5 | G24: 10 | H24: 10 | I24: 10 | J24: 50 | K24: 5 | L24: 6 | M24: 2 | N24: 5 | O24: 5 | P24: =$C$22 -> 10 | Q24: 25 | R24: 50 | S24: 70 | T24: 100
A25: Familia | D25: ABC | E25: ABC | F25: ABC | G25: ABC | H25: LIQ | I25: LIQ | J25: LIQ | K25: BC | L25: LIQ | M25: CO2 | N25: CO2 | O25: LIM | P25: D | Q25: ABC | R25: ABC | S25: ABC | T25: ABC
A26: % de equipos que se desarman (cambio de O-ring) | D26: 1 | E26: 1 | F26: 1 | G26: 1 | H26: 1 | I26: 1 | J26: 1 | K26: 1 | L26: 1 | M26: =$C$8 -> 0.35 | N26: =$C$8 -> 0.35 | O26: =$C$8 -> 0.35 | P26: 1 | Q26: 1 | R26: 1 | S26: 1 | T26: 1
A28: Código | B28: Materia prima / insumo | C28: Unidad | D28: ABC 1 kg | E28: ABC 2,5 kg | F28: ABC 5 kg | G28: ABC 10 kg | H28: Agua 10 l | I28: AFFF 10 l | J28: AFFF 50 l s/r | K28: BC 5 kg | L28: Sales K 6 l | M28: CO₂ 2 kg | N28: CO₂ 5 kg | O28: HCFC/HFC 5 kg | P28: Clase D 9 l | Q28: ABC 25 kg s/r | R28: ABC 50 kg s/r | S28: ABC 70 kg s/r | T28: ABC 100 kg s/r | U28: Criterio / fuente | V28: Confianza
A29: MP-33 | B29: Polvo químico ABC (MAP ≥55 %, IRAM 3569) | C29: kg | D29: =D$24*$C$6 -> 0.25 | E29: =E$24*$C$6 -> 0.625 | F29: =F$24*$C$6 -> 1.25 | G29: =G$24*$C$6 -> 2.5 | H29: 0 | I29: 0 | J29: 0 | K29: 0 | L29: 0 | M29: 0 | N29: 0 | O29: 0 | P29: 0 | Q29: =Q$24*$C$6 -> 6.25 | R29: =R$24*$C$6 -> 12.5 | S29: =S$24*$C$6 -> 17.5 | T29: =T$24*$C$6 -> 25 | U29: Carga nominal + 1 % de merma; recargas: % de polvo nuevo | V29: COTIZ + WEB + EST
A30: MP-34 | B30: Nitrógeno seco (≥99,8 %, rocío ≤ −40 °C) | C30: m³ | D30: =D$24/'Coef Fabricacion'!$C$6*'Coef Fabricacion'!$C$7/(1-'Coef Fabricacion'!$C$7)*'Coef Fabricacion'!$C$8*'Coef Fabricacion'!$C$9/1000 -> 0.0068421053 | E30: =E$24/'Coef Fabricacion'!$C$6*'Coef Fabricacion'!$C$7/(1-'Coef Fabricacion'!$C$7)*'Coef Fabricacion'!$C$8*'Coef Fabricacion'!$C$9/1000 -> 0.017105263 | F30: =F$24/'Coef Fabricacion'!$C$6*'Coef Fabricacion'!$C$7/(1-'Coef Fabricacion'!$C$7)*'Coef Fabricacion'!$C$8*'Coef Fabricacion'!$C$9/1000 -> 0.034210526 | G30: =G$24/'Coef Fabricacion'!$C$6*'Coef Fabricacion'!$C$7/(1-'Coef Fabricacion'!$C$7)*'Coef Fabricacion'!$C$8*'Coef Fabricacion'!$C$9/1000 -> 0.068421053 | H30: =$C$12 -> 0.036 | I30: =$C$12 -> 0.036 | J30: =$C$13 -> 0.18 | K30: =K$24/'Coef Fabricacion'!$C$6*'Coef Fabricacion'!$C$7/(1-'Coef Fabricacion'!$C$7)*'Coef Fabricacion'!$C$8*'Coef Fabricacion'!$C$9/1000 -> 0.034210526 | L30: =$C$14 -> 0.022 | M30: 0 | N30: 0 | O30: 0 | P30: 0 | Q30: =Q$24/'Coef Fabricacion'!$C$6*'Coef Fabricacion'!$C$7/(1-'Coef Fabricacion'!$C$7)*'Coef Fabricacion'!$C$8*'Coef Fabricacion'!$C$9/1000 -> 0.17105263 | R30: =R$24/'Coef Fabricacion'!$C$6*'Coef Fabricacion'!$C$7/(1-'Coef Fabricacion'!$C$7)*'Coef Fabricacion'!$C$8*'Coef Fabricacion'!$C$9/1000 -> 0.34210526 | S30: =S$24/'Coef Fabricacion'!$C$6*'Coef Fabricacion'!$C$7/(1-'Coef Fabricacion'!$C$7)*'Coef Fabricacion'!$C$8*'Coef Fabricacion'!$C$9/1000 -> 0.47894737 | T30: =T$24/'Coef Fabricacion'!$C$6*'Coef Fabricacion'!$C$7/(1-'Coef Fabricacion'!$C$7)*'Coef Fabricacion'!$C$8*'Coef Fabricacion'!$C$9/1000 -> 0.68421053 | U30: Volumen libre × 15 bar × pérdidas | V30: DRIVE + EST
A31: MP-35 | B31: Polvo químico BC (recargas) | C31: kg | D31: 0 | E31: 0 | F31: 0 | G31: 0 | H31: 0 | I31: 0 | J31: 0 | K31: =K$24*$C$6 -> 1.25 | L31: 0 | M31: 0 | N31: 0 | O31: 0 | P31: 0 | Q31: 0 | R31: 0 | S31: 0 | T31: 0 | U31: % de polvo nuevo | V31: COTIZ
A32: MP-36 | B32: Polvo clase D (recargas) | C32: kg | D32: 0 | E32: 0 | F32: 0 | G32: 0 | H32: 0 | I32: 0 | J32: 0 | K32: 0 | L32: 0 | M32: 0 | N32: 0 | O32: 0 | P32: =P$24*$C$7 -> 3 | Q32: 0 | R32: 0 | S32: 0 | T32: 0 | U32: % de polvo nuevo | V32: EST
A33: MP-37 | B33: CO₂ líquido (recargas) | C33: kg | D33: 0 | E33: 0 | F33: 0 | G33: 0 | H33: 0 | I33: 0 | J33: 0 | K33: 0 | L33: 0 | M33: =M$24*$C$8*(1+$C$9) -> 0.77 | N33: =N$24*$C$8*(1+$C$9) -> 1.925 | O33: 0 | P33: 0 | Q33: 0 | R33: 0 | S33: 0 | T33: 0 | U33: Carga × % vaciados × pérdidas de trasvase | V33: DRIVE + EST
A34: MP-38 | B34: Agente limpio HCFC/HFC (recargas) | C34: kg | D34: 0 | E34: 0 | F34: 0 | G34: 0 | H34: 0 | I34: 0 | J34: 0 | K34: 0 | L34: 0 | M34: 0 | N34: 0 | O34: =O$24*$C$8*(1+$C$10) -> 1.8375 | P34: 0 | Q34: 0 | R34: 0 | S34: 0 | T34: 0 | U34: Carga × % vaciados × pérdidas | V34: EST
A35: MP-39 | B35: Argón (presurización de agente limpio) | C35: m³ | D35: 0 | E35: 0 | F35: 0 | G35: 0 | H35: 0 | I35: 0 | J35: 0 | K35: 0 | L35: 0 | M35: 0 | N35: 0 | O35: =$C$8*$C$15 -> 0.007 | P35: 0 | Q35: 0 | R35: 0 | S35: 0 | T35: 0 | U35: % vaciados × m³ por carga | V35: EST
A36: MP-40 | B36: Concentrado AFFF (recargas) | C36: L | D36: 0 | E36: 0 | F36: 0 | G36: 0 | H36: 0 | I36: =I$24*$C$11 -> 0.6 | J36: =J$24*$C$11 -> 3 | K36: 0 | L36: 0 | M36: 0 | N36: 0 | O36: 0 | P36: 0 | Q36: 0 | R36: 0 | S36: 0 | T36: 0 | U36: Volumen × concentración (la premezcla se reemplaza) | V36: COTIZ + WEB
A37: MP-41 | B37: Solución clase K — acetato de potasio (recargas) | C37: L | D37: 0 | E37: 0 | F37: 0 | G37: 0 | H37: 0 | I37: 0 | J37: 0 | K37: 0 | L37: =L$24 -> 6 | M37: 0 | N37: 0 | O37: 0 | P37: 0 | Q37: 0 | R37: 0 | S37: 0 | T37: 0 | U37: Se reemplaza la carga completa | V37: COTIZ + EST
A38: MP-42 | B38: Válvula M-22 para 1 kg con tubo de pesca | C38: u | D38: =$C$17 -> 0.03 | E38: 0 | F38: 0 | G38: 0 | H38: 0 | I38: 0 | J38: 0 | K38: 0 | L38: 0 | M38: 0 | N38: 0 | O38: 0 | P38: 0 | Q38: 0 | R38: 0 | S38: 0 | T38: 0 | U38: 1 por terminado; 3 % de reposición en recargas | V38: COTIZ
A39: MP-43 | B39: Válvula M-30 con resorte para 2,5–10 kg | C39: u | D39: 0 | E39: =$C$17 -> 0.03 | F39: =$C$17 -> 0.03 | G39: =$C$17 -> 0.03 | H39: =$C$17 -> 0.03 | I39: =$C$17 -> 0.03 | J39: 0 | K39: =$C$17 -> 0.03 | L39: =$C$17 -> 0.03 | M39: 0 | N39: 0 | O39: =$C$17 -> 0.03 | P39: 0 | Q39: 0 | R39: 0 | S39: 0 | T39: 0 | U39: 1 por terminado; 3 % de reposición | V39: COTIZ
A40: MP-44 | B40: Válvula para carro 25–100 kg (con traba, manija y resorte) | C40: u | D40: 0 | E40: 0 | F40: 0 | G40: 0 | H40: 0 | I40: 0 | J40: =$C$17 -> 0.03 | K40: 0 | L40: 0 | M40: 0 | N40: 0 | O40: 0 | P40: 0 | Q40: =$C$17 -> 0.03 | R40: =$C$17 -> 0.03 | S40: =$C$17 -> 0.03 | T40: =$C$17 -> 0.03 | U40: 1 por carro terminado | V40: COTIZ
A41: MP-45 | B41: Manómetro IRAM 3533 (1,4 MPa) | C41: u | D41: =$C$16 -> 0.08 | E41: =$C$16 -> 0.08 | F41: =$C$16 -> 0.08 | G41: =$C$16 -> 0.08 | H41: =$C$16 -> 0.08 | I41: =$C$16 -> 0.08 | J41: =$C$16 -> 0.08 | K41: =$C$16 -> 0.08 | L41: =$C$16 -> 0.08 | M41: 0 | N41: 0 | O41: =$C$16 -> 0.08 | P41: 0 | Q41: =$C$16 -> 0.08 | R41: =$C$16 -> 0.08 | S41: =$C$16 -> 0.08 | T41: =$C$16 -> 0.08 | U41: 1 por terminado; 8 % de reposición | V41: EST
A42: MP-46 | B42: Tubo pescante PP/PEAD (2,5–10 kg) | C42: u | D42: 0 | E42: =$C$19 -> 0.03 | F42: =$C$19 -> 0.03 | G42: =$C$19 -> 0.03 | H42: =$C$19 -> 0.03 | I42: =$C$19 -> 0.03 | J42: 0 | K42: =$C$19 -> 0.03 | L42: =$C$19 -> 0.03 | M42: 0 | N42: 0 | O42: =$C$19 -> 0.03 | P42: 0 | Q42: 0 | R42: 0 | S42: 0 | T42: 0 | U42: 1 por terminado (en 1 kg viene con la válvula) | V42: EST
A43: MP-47 | B43: Tubo pescante de acero (carros) | C43: u | D43: 0 | E43: 0 | F43: 0 | G43: 0 | H43: 0 | I43: 0 | J43: =$C$19 -> 0.03 | K43: 0 | L43: 0 | M43: 0 | N43: 0 | O43: 0 | P43: 0 | Q43: =$C$19 -> 0.03 | R43: =$C$19 -> 0.03 | S43: =$C$19 -> 0.03 | T43: =$C$19 -> 0.03 | U43: 1 por carro | V43: EST
A44: MP-48 | B44: Manguera + tobera (2,5–10 kg) | C44: u | D44: 0 | E44: =$C$18 -> 0.05 | F44: =$C$18 -> 0.05 | G44: =$C$18 -> 0.05 | H44: =$C$18 -> 0.05 | I44: =$C$18 -> 0.05 | J44: 0 | K44: =$C$18 -> 0.05 | L44: =$C$18 -> 0.05 | M44: =$C$18 -> 0.05 | N44: =$C$18 -> 0.05 | O44: =$C$18 -> 0.05 | P44: =$C$18 -> 0.05 | Q44: 0 | R44: 0 | S44: 0 | T44: 0 | U44: 1 por terminado (el 1 kg no lleva) | V44: EST
A45: MP-49 | B45: Manguera + lanza/pistola para carro | C45: u | D45: 0 | E45: 0 | F45: 0 | G45: 0 | H45: 0 | I45: 0 | J45: =$C$18 -> 0.05 | K45: 0 | L45: 0 | M45: 0 | N45: 0 | O45: 0 | P45: 0 | Q45: =$C$18 -> 0.05 | R45: =$C$18 -> 0.05 | S45: =$C$18 -> 0.05 | T45: =$C$18 -> 0.05 | U45: 1 por carro | V45: EST
A46: MP-50 | B46: O-ring NBR 70 | C46: u | D46: =2*D$26 -> 2 | E46: =2*E$26 -> 2 | F46: =2*F$26 -> 2 | G46: =2*G$26 -> 2 | H46: =2*H$26 -> 2 | I46: =2*I$26 -> 2 | J46: =2*J$26 -> 2 | K46: =2*K$26 -> 2 | ... T46: =2*T$26 -> 2 | U46: 2 por válvula; en recargas solo si se desarma | V46: EST
A47: MP-51 | B47: Pasador + precinto de seguridad numerado | C47: u | D47: 1 | E47: 1 | F47: 1 | G47: 1 | H47: 1 | I47: 1 | J47: 1 | K47: 1 | L47: 1 | M47: 1 | N47: 1 | O47: 1 | P47: 1 | Q47: 1 | R47: 1 | S47: 1 | T47: 1 | U47: 1 por terminado y por recarga | V47: EST
A48: MP-55 | B48: Conjunto de seguridad CO₂ (IRAM 2736) | C48: u | D48: 0 | E48: 0 | F48: 0 | G48: 0 | H48: 0 | I48: 0 | J48: 0 | K48: 0 | L48: 0 | M48: =$C$8 -> 0.35 | N48: =$C$8 -> 0.35 | O48: 0 | P48: 0 | Q48: 0 | R48: 0 | S48: 0 | T48: 0 | U48: Se reemplaza en cada vaciado total | V48: DRIVE
A49: MP-57 | B49: Marbete/oblea de mantenimiento IRAM 3517-2 (recargas) | C49: u | D49: 1 | E49: 1 | F49: 1 | G49: 1 | H49: 1 | I49: 1 | J49: 1 | K49: 1 | L49: 1 | M49: 1 | N49: 1 | O49: 1 | P49: 1 | Q49: 1 | R49: 1 | S49: 1 | T49: 1 | U49: 1 por recarga | V49: EST
A50: MP-58 | B50: Tarjeta de control / mantenimiento | C50: u | D50: 1 | E50: 1 | F50: 1 | G50: 1 | H50: 1 | I50: 1 | J50: 1 | K50: 1 | L50: 1 | M50: 1 | N50: 1 | O50: 1 | P50: 1 | Q50: 1 | R50: 1 | S50: 1 | T50: 1 | U50: 1 por terminado y por recarga | V50: EST
A51: MP-65 | B51: Pintura de retoque (esmalte rojo) — recargas | C51: L | D51: =$C$20*$C$21 -> 0.0075 | E51: =$C$20*$C$21 -> 0.0075 | F51: =$C$20*$C$21 -> 0.0075 | G51: =$C$20*$C$21 -> 0.0075 | H51: =$C$20*$C$21 -> 0.0075 | I51: =$C$20*$C$21 -> 0.0075 | J51: =$C$20*$C$21 -> 0.0075 | K51: =$C$20*$C$21 -> 0.0075 | ... T51: =$C$20*$C$21 -> 0.0075 | U51: 15 % de los equipos × 0,05 L | V51: DRIVE + EST

Sheet Consumo Anual
A1: CONSUMO ANUAL DE MATERIAS PRIMAS E INSUMOS 2026–2035
A2: Fórmula por celda: Σ(coef R × recipientes) + Σ(coef T × terminados) + Σ(coef C × cilindros) + Σ(coef recarga × recargas).
A5: Código | B5: Materia prima / insumo | C5: Unidad | D5: 2026 | E5: 2027 | F5: 2028 | G5: 2029 | H5: 2030 | I5: 2031 | J5: 2032 | K5: 2033 | L5: 2034 | M5: 2035 | N5: Crecimiento 2035/2028
A6: MP-01 | B6: Caño SAE 1010 c/costura Ø76,2 × 1,25 mm × 6 m (cuerpo 1 kg) | C6: barra | D6: =SUMPRODUCT('Coef Fabricacion'!$D$24:$K$24,Volumenes!$B$32:$I$32)+SUMPRODUCT('Coef Fabricacion'!$L$24:$S$24,Volumenes!$B$6:$I$6)+SUMPRODUCT('Coef Fabricacion'!$T$24:$AA$24,Volumenes!$B$19:$I$19) -> 181.69565 | E6: =SUMPRODUCT('Coef Fabricacion'!$D$24:$K$24,Volumenes!$B$33:$I$33)+SUMPRODUCT('Coef Fabricacion'!$L$24:$S$24,Volumenes!$B$7:$I$7)+SUMPRODUCT('Coef Fabricacion'!$T$24:$AA$24,Volumenes!$B$20:$I$20) -> 260.73913 | F6: =SUMPRODUCT('Coef Fabricacion'!$D$24:$K$24,Volumenes!$B$34:$I$34)+SUMPRODUCT('Coef Fabricacion'!$L$24:$S$24,Volumenes!$B$8:$I$8)+SUMPRODUCT('Coef Fabricacion'!$T$24:$AA$24,Volumenes!$B$21:$I$21) -> 631.04348 | G6: =SUMPRODUCT('Coef Fabricacion'!$D$24:$K$24,Volumenes!$B$35:$I$35)+SUMPRODUCT('Coef Fabricacion'!$L$24:$S$24,Volumenes!$B$9:$I$9)+SUMPRODUCT('Coef Fabricacion'!$T$24:$AA$24,Volumenes!$B$22:$I$22) -> 1528.7826 | H6: =SUMPRODUCT('Coef Fabricacion'!$D$24:$K$24,Volumenes!$B$36:$I$36)+SUMPRODUCT('Coef Fabricacion'!$L$24:$S$24,Volumenes!$B$10:$I$10)+SUMPRODUCT('Coef Fabricacion'!$T$24:$AA$24,Volumenes!$B$23:$I$23) -> 2700.6957 | I6: =SUMPRODUCT('Coef Fabricacion'!$D$24:$K$24,Volumenes!$B$37:$I$37)+SUMPRODUCT('Coef Fabricacion'!$L$24:$S$24,Volumenes!$B$11:$I$11)+SUMPRODUCT('Coef Fabricacion'!$T$24:$AA$24,Volumenes!$B$24:$I$24) -> 3795.6522 | J6: =SUMPRODUCT('Coef Fabricacion'!$D$24:$K$24,Volumenes!$B$38:$I$38)+SUMPRODUCT('Coef Fabricacion'!$L$24:$S$24,Volumenes!$B$12:$I$12)+SUMPRODUCT('Coef Fabricacion'!$T$24:$AA$24,Volumenes!$B$25:$I$25) -> 5290.1739 | K6: =SUMPRODUCT('Coef Fabricacion'!$D$24:$K$24,Volumenes!$B$39:$I$39)+SUMPRODUCT('Coef Fabricacion'!$L$24:$S$24,Volumenes!$B$13:$I$13)+SUMPRODUCT('Coef Fabricacion'!$T$24:$AA$24,Volumenes!$B$26:$I$26) -> 6788.3913 | L6: =SUMPRODUCT('Coef Fabricacion'!$D$24:$K$24,Volumenes!$B$40:$I$40)+SUMPRODUCT('Coef Fabricacion'!$L$24:$S$24,Volumenes!$B$14:$I$14)+SUMPRODUCT('Coef Fabricacion'!$T$24:$AA$24,Volumenes!$B$27:$I$27) -> 7625.7826 | M6: =SUMPRODUCT('Coef Fabricacion'!$D$24:$K$24,Volumenes!$B$41:$I$41)+SUMPRODUCT('Coef Fabricacion'!$L$24:$S$24,Volumenes!$B$15:$I$15)+SUMPRODUCT('Coef Fabricacion'!$T$24:$AA$24,Volumenes!$B$28:$I$28) -> 8809.6087 | N6: =IF(F6=0,"—",M6/F6) -> 13.960383
A7: MP-02 | B7: Hoja LAF 1,25 × 1220 × 2440 mm (cuerpos 2,5 kg; 27 por hoja) | C7: hoja | D7: =SUMPRODUCT('Coef Fabricacion'!$D$25:$K$25,Volumenes!$B$32:$I$32)+SUMPRODUCT('Coef Fabricacion'!$L$25:$S$25,Volumenes!$B$6:$I$6)+SUMPRODUCT('Coef Fabricacion'!$T$25:$AA$25,Volumenes!$B$19:$I$19) -> 10.925926 | E7: =SUMPRODUCT('Coef Fabricacion'!$D$25:$K$25,Volumenes!$B$33:$I$33)+SUMPRODUCT('Coef Fabricacion'!$L$25:$S$25,Volumenes!$B$7:$I$7)+SUMPRODUCT('Coef Fabricacion'!$T$25:$AA$25,Volumenes!$B$20:$I$20) -> 26.259259 | F7: =SUMPRODUCT('Coef Fabricacion'!$D$25:$K$25,Volumenes!$B$34:$I$34)+SUMPRODUCT('Coef Fabricacion'!$L$25:$S$25,Volumenes!$B$8:$I$8)+SUMPRODUCT('Coef Fabricacion'!$T$25:$AA$25,Volumenes!$B$21:$I$21) -> 47.666667 | G7: =SUMPRODUCT('Coef Fabricacion'!$D$25:$K$25,Volumenes!$B$35:$I$35)+SUMPRODUCT('Coef Fabricacion'!$L$25:$S$25,Volumenes!$B$9:$I$9)+SUMPRODUCT('Coef Fabricacion'!$T$25:$AA$25,Volumenes!$B$22:$I$22) -> 94.259259 | H7: =SUMPRODUCT('Coef Fabricacion'!$D$25:$K$25,Volumenes!$B$36:$I$36)+SUMPRODUCT('Coef Fabricacion'!$L$25:$S$25,Volumenes!$B$10:$I$10)+SUMPRODUCT('Coef Fabricacion'!$T$25:$AA$25,Volumenes!$B$23:$I$23) -> 157.22222 | I7: =SUMPRODUCT('Coef Fabricacion'!$D$25:$K$25,Volumenes!$B$37:$I$37)+SUMPRODUCT('Coef Fabricacion'!$L$25:$S$25,Volumenes!$B$11:$I$11)+SUMPRODUCT('Coef Fabricacion'!$T$25:$AA$25,Volumenes!$B$24:$I$24) -> 224.25926 | J7: =SUMPRODUCT('Coef Fabricacion'!$D$25:$K$25,Volumenes!$B$38:$I$38)+SUMPRODUCT('Coef Fabricacion'!$L$25:$S$25,Volumenes!$B$12:$I$12)+SUMPRODUCT('Coef Fabricacion'!$T$25:$AA$25,Volumenes!$B$25:$I$25) -> 298.74074 | K7: =SUMPRODUCT('Coef Fabricacion'!$D$25:$K$25,Volumenes!$B$39:$I$39)+SUMPRODUCT('Coef Fabricacion'!$L$25:$S$25,Volumenes!$B$13:$I$13)+SUMPRODUCT('Coef Fabricacion'!$T$25:$AA$25,Volumenes!$B$26:$I$26) -> 378.81481 | L7: =SUMPRODUCT('Coef Fabricacion'!$D$25:$K$25,Volumenes!$B$40:$I$40)+SUMPRODUCT('Coef Fabricacion'!$L$25:$S$25,Volumenes!$B$14:$I$14)+SUMPRODUCT('Coef Fabricacion'!$T$25:$AA$25,Volumenes!$B$27:$I$27) -> 442.07407 | M7: =SUMPRODUCT('Coef Fabricacion'!$D$25:$K$25,Volumenes!$B$41:$I$41)+SUMPRODUCT('Coef Fabricacion'!$L$25:$S$25,Volumenes!$B$15:$I$15)+SUMPRODUCT('Coef Fabricacion'!$T$25:$AA$25,Volumenes!$B$28:$I$28) -> 522 | N7: =IF(F7=0,"—",M7/F7) -> 10.951049
A8: MP-03 | B8: Hoja LAF 1,6 × 1000 × 2000 mm (cuerpos 5 kg; 12 por hoja) | C8: hoja | D8: =SUMPRODUCT('Coef Fabricacion'!$D$26:$K$26,Volumenes!$B$32:$I$32)+SUMPRODUCT('Coef Fabricacion'!$L$26:$S$26,Volumenes!$B$6:$I$6)+SUMPRODUCT('Coef Fabricacion'!$T$26:$AA$26,Volumenes!$B$19:$I$19) -> 188 | E8: =SUMPRODUCT('Coef Fabricacion'!$D$26:$K$26,Volumenes!$B$33:$I$33)+SUMPRODUCT('Coef Fabricacion'!$L$26:$S$26,Volumenes!$B$7:$I$7)+SUMPRODUCT('Coef Fabricacion'!$T$26:$AA$26,Volumenes!$B$20:$I$20) -> 320.58333 | F8: =SUMPRODUCT('Coef Fabricacion'!$D$26:$K$26,Volumenes!$B$34:$I$34)+SUMPRODUCT('Coef Fabricacion'!$L$26:$S$26,Volumenes!$B$8:$I$8)+SUMPRODUCT('Coef Fabricacion'!$T$26:$AA$26,Volumenes!$B$21:$I$21) -> 547.75 | G8: =SUMPRODUCT('Coef Fabricacion'!$D$26:$K$26,Volumenes!$B$35:$I$35)+SUMPRODUCT('Coef Fabricacion'!$L$26:$S$26,Volumenes!$B$9:$I$9)+SUMPRODUCT('Coef Fabricacion'!$T$26:$AA$26,Volumenes!$B$22:$I$22) -> 997.91667 | H8: =SUMPRODUCT('Coef Fabricacion'!$D$26:$K$26,Volumenes!$B$36:$I$36)+SUMPRODUCT('Coef Fabricacion'!$L$26:$S$26,Volumenes!$B$10:$I$10)+SUMPRODUCT('Coef Fabricacion'!$T$26:$AA$26,Volumenes!$B$23:$I$23) -> 1696.6667 | I8: =SUMPRODUCT('Coef Fabricacion'!$D$26:$K$26,Volumenes!$B$37:$I$37)+SUMPRODUCT('Coef Fabricacion'!$L$26:$S$26,Volumenes!$B$11:$I$11)+SUMPRODUCT('Coef Fabricacion'!$T$26:$AA$26,Volumenes!$B$24:$I$24) -> 2370 | J8: =SUMPRODUCT('Coef Fabricacion'!$D$26:$K$26,Volumenes!$B$38:$I$38)+SUMPRODUCT('Coef Fabricacion'!$L$26:$S$26,Volumenes!$B$12:$I$12)+SUMPRODUCT('Coef Fabricacion'!$T$26:$AA$26,Volumenes!$B$25:$I$25) -> 3203.0833 | K8: =SUMPRODUCT('Coef Fabricacion'!$D$26:$K$26,Volumenes!$B$39:$I$39)+SUMPRODUCT('Coef Fabricacion'!$L$26:$S$26,Volumenes!$B$13:$I$13)+SUMPRODUCT('Coef Fabricacion'!$T$26:$AA$26,Volumenes!$B$26:$I$26) -> 4054.25 | L8: =SUMPRODUCT('Coef Fabricacion'!$D$26:$K$26,Volumenes!$B$40:$I$40)+SUMPRODUCT('Coef Fabricacion'!$L$26:$S$26,Volumenes!$B$14:$I$14)+SUMPRODUCT('Coef Fabricacion'!$T$26:$AA$26,Volumenes!$B$27:$I$27) -> 4608.6667 | M8: =SUMPRODUCT('Coef Fabricacion'!$D$26:$K$26,Volumenes!$B$41:$I$41)+SUMPRODUCT('Coef Fabricacion'!$L$26:$S$26,Volumenes!$B$15:$I$15)+SUMPRODUCT('Coef Fabricacion'!$T$26:$AA$26,Volumenes!$B$28:$I$28) -> 5305.5 | N8: =IF(F8=0,"—",M8/F8) -> 9.6859881
A9: MP-04 | B9: Hoja LAF 2,0 × 1500 × 3000 mm (cuerpos 10 kg; 15 por hoja) | C9: hoja | D9: =SUMPRODUCT('Coef Fabricacion'!$D$27:$K$27,Volumenes!$B$32:$I$32)+SUMPRODUCT('Coef Fabricacion'!$L$27:$S$27,Volumenes!$B$6:$I$6)+SUMPRODUCT('Coef Fabricacion'!$T$27:$AA$27,Volumenes!$B$19:$I$19) -> 6.1333333 | E9: =SUMPRODUCT('Coef Fabricacion'!$D$27:$K$27,Volumenes!$B$33:$I$33)+SUMPRODUCT('Coef Fabricacion'!$L$27:$S$27,Volumenes!$B$7:$I$7)+SUMPRODUCT('Coef Fabricacion'!$T$27:$AA$27,Volumenes!$B$20:$I$20) -> 11.8 | F9: =SUMPRODUCT('Coef Fabricacion'!$D$27:$K$27,Volumenes!$B$34:$I$34)+SUMPRODUCT('Coef Fabricacion'!$L$27:$S$27,Volumenes!$B$8:$I$8)+SUMPRODUCT('Coef Fabricacion'!$T$27:$AA$27,Volumenes!$B$21:$I$21) -> 22.866667 | G9: =SUMPRODUCT('Coef Fabricacion'!$D$27:$K$27,Volumenes!$B$35:$I$35)+SUMPRODUCT('Coef Fabricacion'!$L$27:$S$27,Volumenes!$B$9:$I$9)+SUMPRODUCT('Coef Fabricacion'!$T$27:$AA$27,Volumenes!$B$22:$I$22) -> 44.866667 | H9: =SUMPRODUCT('Coef Fabricacion'!$D$27:$K$27,Volumenes!$B$36:$I$36)+SUMPRODUCT('Coef Fabricacion'!$L$27:$S$27,Volumenes!$B$10:$I$10)+SUMPRODUCT('Coef Fabricacion'!$T$27:$AA$27,Volumenes!$B$23:$I$23) -> 79.066667 | I9: =SUMPRODUCT('Coef Fabricacion'!$D$27:$K$27,Volumenes!$B$37:$I$37)+SUMPRODUCT('Coef Fabricacion'!$L$27:$S$27,Volumenes!$B$11:$I$11)+SUMPRODUCT('Coef Fabricacion'!$T$27:$AA$27,Volumenes!$B$24:$I$24) -> 114.53333 | J9: =SUMPRODUCT('Coef Fabricacion'!$D$27:$K$27,Volumenes!$B$38:$I$38)+SUMPRODUCT('Coef Fabricacion'!$L$27:$S$27,Volumenes!$B$12:$I$12)+SUMPRODUCT('Coef Fabricacion'!$T$27:$AA$27,Volumenes!$B$25:$I$25) -> 154.8 | K9: =SUMPRODUCT('Coef Fabricacion'!$D$27:$K$27,Volumenes!$B$39:$I$39)+SUMPRODUCT('Coef Fabricacion'!$L$27:$S$27,Volumenes!$B$13:$I$13)+SUMPRODUCT('Coef Fabricacion'!$T$27:$AA$27,Volumenes!$B$26:$I$26) -> 196 | L9: =SUMPRODUCT('Coef Fabricacion'!$D$27:$K$27,Volumenes!$B$40:$I$40)+SUMPRODUCT('Coef Fabricacion'!$L$27:$S$27,Volumenes!$B$14:$I$14)+SUMPRODUCT('Coef Fabricacion'!$T$27:$AA$27,Volumenes!$B$27:$I$27) -> 222.86667 | M9: =SUMPRODUCT('Coef Fabricacion'!$D$27:$K$27,Volumenes!$B$41:$I$41)+SUMPRODUCT('Coef Fabricacion'!$L$27:$S$27,Volumenes!$B$15:$I$15)+SUMPRODUCT('Coef Fabricacion'!$T$27:$AA$27,Volumenes!$B$28:$I$28) -> 256.8 | N9: =IF(F9=0,"—",M9/F9) -> 11.230321
A10: MP-05 | B10: Fleje LAF 0,9 × 114 mm (cúpula 1 kg) | C10: kg | D10: =SUMPRODUCT('Coef Fabricacion'!$D$28:$K$28,Volumenes!$B$32:$I$32)+SUMPRODUCT('Coef Fabricacion'!$L$28:$S$28,Volumenes!$B$6:$I$6)+SUMPRODUCT('Coef Fabricacion'!$T$28:$AA$28,Volumenes!$B$19:$I$19) -> 373.60473 | E10: =SUMPRODUCT('Coef Fabricacion'!$D$28:$K$28,Volumenes!$B$33:$I$33)+SUMPRODUCT('Coef Fabricacion'!$L$28:$S$28,Volumenes!$B$7:$I$7)+SUMPRODUCT('Coef Fabricacion'!$T$28:$AA$28,Volumenes!$B$20:$I$20) -> 536.13486 | F10: =SUMPRODUCT('Coef Fabricacion'!$D$28:$K$28,Volumenes!$B$34:$I$34)+SUMPRODUCT('Coef Fabricacion'!$L$28:$S$28,Volumenes!$B$8:$I$8)+SUMPRODUCT('Coef Fabricacion'!$T$28:$AA$28,Volumenes!$B$21:$I$21) -> 1297.559 | G10: =SUMPRODUCT('Coef Fabricacion'!$D$28:$K$28,Volumenes!$B$35:$I$35)+SUMPRODUCT('Coef Fabricacion'!$L$28:$S$28,Volumenes!$B$9:$I$9)+SUMPRODUCT('Coef Fabricacion'!$T$28:$AA$28,Volumenes!$B$22:$I$22) -> 3143.5007 | H10: =SUMPRODUCT('Coef Fabricacion'!$D$28:$K$28,Volumenes!$B$36:$I$36)+SUMPRODUCT('Coef Fabricacion'!$L$28:$S$28,Volumenes!$B$10:$I$10)+SUMPRODUCT('Coef Fabricacion'!$T$28:$AA$28,Volumenes!$B$23:$I$23) -> 5553.2021 | I10: =SUMPRODUCT('Coef Fabricacion'!$D$28:$K$28,Volumenes!$B$37:$I$37)+SUMPRODUCT('Coef Fabricacion'!$L$28:$S$28,Volumenes!$B$11:$I$11)+SUMPRODUCT('Coef Fabricacion'!$T$28:$AA$28,Volumenes!$B$24:$I$24) -> 7804.6645 | J10: =SUMPRODUCT('Coef Fabricacion'!$D$28:$K$28,Volumenes!$B$38:$I$38)+SUMPRODUCT('Coef Fabricacion'!$L$28:$S$28,Volumenes!$B$12:$I$12)+SUMPRODUCT('Coef Fabricacion'!$T$28:$AA$28,Volumenes!$B$25:$I$25) -> 10877.718 | K10: =SUMPRODUCT('Coef Fabricacion'!$D$28:$K$28,Volumenes!$B$39:$I$39)+SUMPRODUCT('Coef Fabricacion'!$L$28:$S$28,Volumenes!$B$13:$I$13)+SUMPRODUCT('Coef Fabricacion'!$T$28:$AA$28,Volumenes!$B$26:$I$26) -> 13958.37 | L10: =SUMPRODUCT('Coef Fabricacion'!$D$28:$K$28,Volumenes!$B$40:$I$40)+SUMPRODUCT('Coef Fabricacion'!$L$28:$S$28,Volumenes!$B$14:$I$14)+SUMPRODUCT('Coef Fabricacion'!$T$28:$AA$28,Volumenes!$B$27:$I$27) -> 15680.224 | M10: =SUMPRODUCT('Coef Fabricacion'!$D$28:$K$28,Volumenes!$B$41:$I$41)+SUMPRODUCT('Coef Fabricacion'!$L$28:$S$28,Volumenes!$B$15:$I$15)+SUMPRODUCT('Coef Fabricacion'!$T$28:$AA$28,Volumenes!$B$28:$I$28) -> 18114.421 | N10: =IF(F10=0,"—",M10/F10) -> 13.960383
A11: MP-06 | B11: Fleje LAF 1,25 × 200 mm (cúpula Ø179 + fondo Ø148, 2,5 kg) | C11: kg | D11: =SUMPRODUCT('Coef Fabricacion'!$D$29:$K$29,Volumenes!$B$32:$I$32)+SUMPRODUCT('Coef Fabricacion'!$L$29:$S$29,Volumenes!$B$6:$I$6)+SUMPRODUCT('Coef Fabricacion'!$T$29:$AA$29,Volumenes!$B$19:$I$19) -> 192.78619 | E11: =SUMPRODUCT('Coef Fabricacion'!$D$29:$K$29,Volumenes!$B$33:$I$33)+SUMPRODUCT('Coef Fabricacion'!$L$29:$S$29,Volumenes!$B$7:$I$7)+SUMPRODUCT('Coef Fabricacion'!$T$29:$AA$29,Volumenes!$B$20:$I$20) -> 463.34036 | F11: =SUMPRODUCT('Coef Fabricacion'!$D$29:$K$29,Volumenes!$B$34:$I$34)+SUMPRODUCT('Coef Fabricacion'!$L$29:$S$29,Volumenes!$B$8:$I$8)+SUMPRODUCT('Coef Fabricacion'!$T$29:$AA$29,Volumenes!$B$21:$I$21) -> 841.07059 | G11: =SUMPRODUCT('Coef Fabricacion'!$D$29:$K$29,Volumenes!$B$35:$I$35)+SUMPRODUCT('Coef Fabricacion'!$L$29:$S$29,Volumenes!$B$9:$I$9)+SUMPRODUCT('Coef Fabricacion'!$T$29:$AA$29,Volumenes!$B$22:$I$22) -> 1663.1893 | H11: =SUMPRODUCT('Coef Fabricacion'!$D$29:$K$29,Volumenes!$B$36:$I$36)+SUMPRODUCT('Coef Fabricacion'!$L$29:$S$29,Volumenes!$B$10:$I$10)+SUMPRODUCT('Coef Fabricacion'!$T$29:$AA$29,Volumenes!$B$23:$I$23) -> 2774.1606 | I11: =SUMPRODUCT('Coef Fabricacion'!$D$29:$K$29,Volumenes!$B$37:$I$37)+SUMPRODUCT('Coef Fabricacion'!$L$29:$S$29,Volumenes!$B$11:$I$11)+SUMPRODUCT('Coef Fabricacion'!$T$29:$AA$29,Volumenes!$B$24:$I$24) -> 3957.0182 | J11: =SUMPRODUCT('Coef Fabricacion'!$D$29:$K$29,Volumenes!$B$38:$I$38)+SUMPRODUCT('Coef Fabricacion'!$L$29:$S$29,Volumenes!$B$12:$I$12)+SUMPRODUCT('Coef Fabricacion'!$T$29:$AA$29,Volumenes!$B$25:$I$25) -> 5271.2318 | K11: =SUMPRODUCT('Coef Fabricacion'!$D$29:$K$29,Volumenes!$B$39:$I$39)+SUMPRODUCT('Coef Fabricacion'!$L$29:$S$29,Volumenes!$B$13:$I$13)+SUMPRODUCT('Coef Fabricacion'!$T$29:$AA$29,Volumenes!$B$26:$I$26) -> 6684.1259 | L11: =SUMPRODUCT('Coef Fabricacion'!$D$29:$K$29,Volumenes!$B$40:$I$40)+SUMPRODUCT('Coef Fabricacion'!$L$29:$S$29,Volumenes!$B$14:$I$14)+SUMPRODUCT('Coef Fabricacion'!$T$29:$AA$29,Volumenes!$B$27:$I$27) -> 7800.3252 | M11: =SUMPRODUCT('Coef Fabricacion'!$D$29:$K$29,Volumenes!$B$41:$I$41)+SUMPRODUCT('Coef Fabricacion'!$L$29:$S$29,Volumenes!$B$15:$I$15)+SUMPRODUCT('Coef Fabricacion'!$T$29:$AA$29,Volumenes!$B$28:$I$28) -> 9210.6052 | N11: =IF(F11=0,"—",M11/F11) -> 10.951049
A12: MP-07 | B12: Fleje LAF 1,6 × 250 mm (cúpula Ø221, 5 kg) | C12: kg | D12: =SUMPRODUCT('Coef Fabricacion'!$D$30:$K$30,Volumenes!$B$32:$I$32)+SUMPRODUCT('Coef Fabricacion'!$L$30:$S$30,Volumenes!$B$6:$I$6)+SUMPRODUCT('Coef Fabricacion'!$T$30:$AA$30,Volumenes!$B$19:$I$19) -> 1586.7802 | E12: =SUMPRODUCT('Coef Fabricacion'!$D$30:$K$30,Volumenes!$B$33:$I$33)+SUMPRODUCT('Coef Fabricacion'!$L$30:$S$30,Volumenes!$B$7:$I$7)+SUMPRODUCT('Coef Fabricacion'!$T$30:$AA$30,Volumenes!$B$20:$I$20) -> 2705.8259 | F12: =SUMPRODUCT('Coef Fabricacion'!$D$30:$K$30,Volumenes!$B$34:$I$34)+SUMPRODUCT('Coef Fabricacion'!$L$30:$S$30,Volumenes!$B$8:$I$8)+SUMPRODUCT('Coef Fabricacion'!$T$30:$AA$30,Volumenes!$B$21:$I$21) -> 4623.1853 | G12: =SUMPRODUCT('Coef Fabricacion'!$D$30:$K$30,Volumenes!$B$35:$I$35)+SUMPRODUCT('Coef Fabricacion'!$L$30:$S$30,Volumenes!$B$9:$I$9)+SUMPRODUCT('Coef Fabricacion'!$T$30:$AA$30,Volumenes!$B$22:$I$22) -> 8422.736 | H12: =SUMPRODUCT('Coef Fabricacion'!$D$30:$K$30,Volumenes!$B$36:$I$36)+SUMPRODUCT('Coef Fabricacion'!$L$30:$S$30,Volumenes!$B$10:$I$10)+SUMPRODUCT('Coef Fabricacion'!$T$30:$AA$30,Volumenes!$B$23:$I$23) -> 14320.41 | I12: =SUMPRODUCT('Coef Fabricacion'!$D$30:$K$30,Volumenes!$B$37:$I$37)+SUMPRODUCT('Coef Fabricacion'!$L$30:$S$30,Volumenes!$B$11:$I$11)+SUMPRODUCT('Coef Fabricacion'!$T$30:$AA$30,Volumenes!$B$24:$I$24) -> 20003.558 | J12: =SUMPRODUCT('Coef Fabricacion'!$D$30:$K$30,Volumenes!$B$38:$I$38)+SUMPRODUCT('Coef Fabricacion'!$L$30:$S$30,Volumenes!$B$12:$I$12)+SUMPRODUCT('Coef Fabricacion'!$T$30:$AA$30,Volumenes!$B$25:$I$25) -> 27035.048 | K12: =SUMPRODUCT('Coef Fabricacion'!$D$30:$K$30,Volumenes!$B$39:$I$39)+SUMPRODUCT('Coef Fabricacion'!$L$30:$S$30,Volumenes!$B$13:$I$13)+SUMPRODUCT('Coef Fabricacion'!$T$30:$AA$30,Volumenes!$B$26:$I$26) -> 34219.167 | L12: =SUMPRODUCT('Coef Fabricacion'!$D$30:$K$30,Volumenes!$B$40:$I$40)+SUMPRODUCT('Coef Fabricacion'!$L$30:$S$30,Volumenes!$B$14:$I$14)+SUMPRODUCT('Coef Fabricacion'!$T$30:$AA$30,Volumenes!$B$27:$I$27) -> 38898.621 | M12: =SUMPRODUCT('Coef Fabricacion'!$D$30:$K$30,Volumenes!$B$41:$I$41)+SUMPRODUCT('Coef Fabricacion'!$L$30:$S$30,Volumenes!$B$15:$I$15)+SUMPRODUCT('Coef Fabricacion'!$T$30:$AA$30,Volumenes!$B$28:$I$28) -> 44780.118 | N12: =IF(F12=0,"—",M12/F12) -> 9.6859881
A13: MP-08 | B13: Fleje LAF 1,6 × 200 mm (fondo Ø177, 5 kg) | C13: kg | D13: =SUMPRODUCT('Coef Fabricacion'!$D$31:$K$31,Volumenes!$B$32:$I$32)+SUMPRODUCT('Coef Fabricacion'!$L$31:$S$31,Volumenes!$B$6:$I$6)+SUMPRODUCT('Coef Fabricacion'!$T$31:$AA$31,Volumenes!$B$19:$I$19) -> 1020.073 | E13: =SUMPRODUCT('Coef Fabricacion'!$D$31:$K$31,Volumenes!$B$33:$I$33)+SUMPRODUCT('Coef Fabricacion'!$L$31:$S$31,Volumenes!$B$7:$I$7)+SUMPRODUCT('Coef Fabricacion'!$T$31:$AA$31,Volumenes!$B$20:$I$20) -> 1739.4595 | F13: =SUMPRODUCT('Coef Fabricacion'!$D$31:$K$31,Volumenes!$B$34:$I$34)+SUMPRODUCT('Coef Fabricacion'!$L$31:$S$31,Volumenes!$B$8:$I$8)+SUMPRODUCT('Coef Fabricacion'!$T$31:$AA$31,Volumenes!$B$21:$I$21) -> 2972.0477 | G13: =SUMPRODUCT('Coef Fabricacion'!$D$31:$K$31,Volumenes!$B$35:$I$35)+SUMPRODUCT('Coef Fabricacion'!$L$31:$S$31,Volumenes!$B$9:$I$9)+SUMPRODUCT('Coef Fabricacion'!$T$31:$AA$31,Volumenes!$B$22:$I$22) -> 5414.616 | H13: =SUMPRODUCT('Coef Fabricacion'!$D$31:$K$31,Volumenes!$B$36:$I$36)+SUMPRODUCT('Coef Fabricacion'!$L$31:$S$31,Volumenes!$B$10:$I$10)+SUMPRODUCT('Coef Fabricacion'!$T$31:$AA$31,Volumenes!$B$23:$I$23) -> 9205.9776 | I13: =SUMPRODUCT('Coef Fabricacion'!$D$31:$K$31,Volumenes!$B$37:$I$37)+SUMPRODUCT('Coef Fabricacion'!$L$31:$S$31,Volumenes!$B$11:$I$11)+SUMPRODUCT('Coef Fabricacion'!$T$31:$AA$31,Volumenes!$B$24:$I$24) -> 12859.43 | J13: =SUMPRODUCT('Coef Fabricacion'!$D$31:$K$31,Volumenes!$B$38:$I$38)+SUMPRODUCT('Coef Fabricacion'!$L$31:$S$31,Volumenes!$B$12:$I$12)+SUMPRODUCT('Coef Fabricacion'!$T$31:$AA$31,Volumenes!$B$25:$I$25) -> 17379.674 | K13: =SUMPRODUCT('Coef Fabricacion'!$D$31:$K$31,Volumenes!$B$39:$I$39)+SUMPRODUCT('Coef Fabricacion'!$L$31:$S$31,Volumenes!$B$13:$I$13)+SUMPRODUCT('Coef Fabricacion'!$T$31:$AA$31,Volumenes!$B$26:$I$26) -> 21998.036 | L13: =SUMPRODUCT('Coef Fabricacion'!$D$31:$K$31,Volumenes!$B$40:$I$40)+SUMPRODUCT('Coef Fabricacion'!$L$31:$S$31,Volumenes!$B$14:$I$14)+SUMPRODUCT('Coef Fabricacion'!$T$31:$AA$31,Volumenes!$B$27:$I$27) -> 25006.257 | M13: =SUMPRODUCT('Coef Fabricacion'!$D$31:$K$31,Volumenes!$B$41:$I$41)+SUMPRODUCT('Coef Fabricacion'!$L$31:$S$31,Volumenes!$B$15:$I$15)+SUMPRODUCT('Coef Fabricacion'!$T$31:$AA$31,Volumenes!$B$28:$I$28) -> 28787.219 | N13: =IF(F13=0,"—",M13/F13) -> 9.6859881
A14: MP-09 | B14: Fleje LAF 2,0 × 300 mm (cúpula Ø258, 10 kg) | C14: kg | D14: =SUMPRODUCT('Coef Fabricacion'!$D$32:$K$32,Volumenes!$B$32:$I$32)+SUMPRODUCT('Coef Fabricacion'!$L$32:$S$32,Volumenes!$B$6:$I$6)+SUMPRODUCT('Coef Fabricacion'!$T$32:$AA$32,Volumenes!$B$19:$I$19) -> 113.09652 | E14: =SUMPRODUCT('Coef Fabricacion'!$D$32:$K$32,Volumenes!$B$33:$I$33)+SUMPRODUCT('Coef Fabricacion'!$L$32:$S$32,Volumenes!$B$7:$I$7)+SUMPRODUCT('Coef Fabricacion'!$T$32:$AA$32,Volumenes!$B$20:$I$20) -> 217.58787 | F14: =SUMPRODUCT('Coef Fabricacion'!$D$32:$K$32,Volumenes!$B$34:$I$34)+SUMPRODUCT('Coef Fabricacion'!$L$32:$S$32,Volumenes!$B$8:$I$8)+SUMPRODUCT('Coef Fabricacion'!$T$32:$AA$32,Volumenes!$B$21:$I$21) -> 421.65333 | G14: =SUMPRODUCT('Coef Fabricacion'!$D$32:$K$32,Volumenes!$B$35:$I$35)+SUMPRODUCT('Coef Fabricacion'!$L$32:$S$32,Volumenes!$B$9:$I$9)+SUMPRODUCT('Coef Fabricacion'!$T$32:$AA$32,Volumenes!$B$22:$I$22) -> 827.32563 | H14: =SUMPRODUCT('Coef Fabricacion'!$D$32:$K$32,Volumenes!$B$36:$I$36)+SUMPRODUCT('Coef Fabricacion'!$L$32:$S$32,Volumenes!$B$10:$I$10)+SUMPRODUCT('Coef Fabricacion'!$T$32:$AA$32,Volumenes!$B$23:$I$23) -> 1457.9617 | I14: =SUMPRODUCT('Coef Fabricacion'!$D$32:$K$32,Volumenes!$B$37:$I$37)+SUMPRODUCT('Coef Fabricacion'!$L$32:$S$32,Volumenes!$B$11:$I$11)+SUMPRODUCT('Coef Fabricacion'!$T$32:$AA$32,Volumenes!$B$24:$I$24) -> 2111.9546 | J14: =SUMPRODUCT('Coef Fabricacion'!$D$32:$K$32,Volumenes!$B$38:$I$38)+SUMPRODUCT('Coef Fabricacion'!$L$32:$S$32,Volumenes!$B$12:$I$12)+SUMPRODUCT('Coef Fabricacion'!$T$32:$AA$32,Volumenes!$B$25:$I$25) -> 2854.4578 | K14: =SUMPRODUCT('Coef Fabricacion'!$D$32:$K$32,Volumenes!$B$39:$I$39)+SUMPRODUCT('Coef Fabricacion'!$L$32:$S$32,Volumenes!$B$13:$I$13)+SUMPRODUCT('Coef Fabricacion'!$T$32:$AA$32,Volumenes!$B$26:$I$26) -> 3614.1714 | L14: =SUMPRODUCT('Coef Fabricacion'!$D$32:$K$32,Volumenes!$B$40:$I$40)+SUMPRODUCT('Coef Fabricacion'!$L$32:$S$32,Volumenes!$B$14:$I$14)+SUMPRODUCT('Coef Fabricacion'!$T$32:$AA$32,Volumenes!$B$27:$I$27) -> 4109.5833 | M14: =SUMPRODUCT('Coef Fabricacion'!$D$32:$K$32,Volumenes!$B$41:$I$41)+SUMPRODUCT('Coef Fabricacion'!$L$32:$S$32,Volumenes!$B$15:$I$15)+SUMPRODUCT('Coef Fabricacion'!$T$32:$AA$32,Volumenes!$B$28:$I$28) -> 4735.3021 | N14: =IF(F14=0,"—",M14/F14) -> 11.230321
A15: MP-10 | B15: Fleje LAF 2,0 × 249 mm (fondo Ø205, 10 kg) | C15: kg | D15: =SUMPRODUCT('Coef Fabricacion'!$D$33:$K$33,Volumenes!$B$32:$I$32)+SUMPRODUCT('Coef Fabricacion'!$L$33:$S$33,Volumenes!$B$6:$I$6)+SUMPRODUCT('Coef Fabricacion'!$T$33:$AA$33,Volumenes!$B$19:$I$19) -> 74.808365 | E15: =SUMPRODUCT('Coef Fabricacion'!$D$33:$K$33,Volumenes!$B$33:$I$33)+SUMPRODUCT('Coef Fabricacion'!$L$33:$S$33,Volumenes!$B$7:$I$7)+SUMPRODUCT('Coef Fabricacion'!$T$33:$AA$33,Volumenes!$B$20:$I$20) -> 143.92479 | F15: =SUMPRODUCT('Coef Fabricacion'!$D$33:$K$33,Volumenes!$B$34:$I$34)+SUMPRODUCT('Coef Fabricacion'!$L$33:$S$33,Volumenes!$B$8:$I$8)+SUMPRODUCT('Coef Fabricacion'!$T$33:$AA$33,Volumenes!$B$21:$I$21) -> 278.9051 | G15: =SUMPRODUCT('Coef Fabricacion'!$D$33:$K$33,Volumenes!$B$35:$I$35)+SUMPRODUCT('Coef Fabricacion'!$L$33:$S$33,Volumenes!$B$9:$I$9)+SUMPRODUCT('Coef Fabricacion'!$T$33:$AA$33,Volumenes!$B$22:$I$22) -> 547.23945 | H15: =SUMPRODUCT('Coef Fabricacion'!$D$33:$K$33,Volumenes!$B$36:$I$36)+SUMPRODUCT('Coef Fabricacion'!$L$33:$S$33,Volumenes!$B$10:$I$10)+SUMPRODUCT('Coef Fabricacion'!$T$33:$AA$33,Volumenes!$B$23:$I$23) -> 964.3774 | I15: =SUMPRODUCT('Coef Fabricacion'!$D$33:$K$33,Volumenes!$B$37:$I$37)+SUMPRODUCT('Coef Fabricacion'!$L$33:$S$33,Volumenes!$B$11:$I$11)+SUMPRODUCT('Coef Fabricacion'!$T$33:$AA$33,Volumenes!$B$24:$I$24) -> 1396.9649 | J15: =SUMPRODUCT('Coef Fabricacion'!$D$33:$K$33,Volumenes!$B$38:$I$38)+SUMPRODUCT('Coef Fabricacion'!$L$33:$S$33,Volumenes!$B$12:$I$12)+SUMPRODUCT('Coef Fabricacion'!$T$33:$AA$33,Volumenes!$B$25:$I$25) -> 1888.0981 | K15: =SUMPRODUCT('Coef Fabricacion'!$D$33:$K$33,Volumenes!$B$39:$I$39)+SUMPRODUCT('Coef Fabricacion'!$L$33:$S$33,Volumenes!$B$13:$I$13)+SUMPRODUCT('Coef Fabricacion'!$T$33:$AA$33,Volumenes!$B$26:$I$26) -> 2390.6151 | L15: =SUMPRODUCT('Coef Fabricacion'!$D$33:$K$33,Volumenes!$B$40:$I$40)+SUMPRODUCT('Coef Fabricacion'!$L$33:$S$33,Volumenes!$B$14:$I$14)+SUMPRODUCT('Coef Fabricacion'!$T$33:$AA$33,Volumenes!$B$27:$I$27) -> 2718.3083 | M15: =SUMPRODUCT('Coef Fabricacion'!$D$33:$K$33,Volumenes!$B$41:$I$41)+SUMPRODUCT('Coef Fabricacion'!$L$33:$S$33,Volumenes!$B$15:$I$15)+SUMPRODUCT('Coef Fabricacion'!$T$33:$AA$33,Volumenes!$B$28:$I$28) -> 3132.1937 | N15: =IF(F15=0,"—",M15/F15) -> 11.230321
A16: MP-11 | B16: Hoja LAC 3,2 × 1500 × 3000 mm (cuerpos 25 kg: 9 por hoja; 50 kg: 6 por hoja) | C16: hoja | D16: =SUMPRODUCT('Coef Fabricacion'!$D$34:$K$34,Volumenes!$B$32:$I$32)+SUMPRODUCT('Coef Fabricacion'!$L$34:$S$34,Volumenes!$B$6:$I$6)+SUMPRODUCT('Coef Fabricacion'!$T$34:$AA$34,Volumenes!$B$19:$I$19) -> 16.277778 | E16: =SUMPRODUCT('Coef Fabricacion'!$D$34:$K$34,Volumenes!$B$33:$I$33)+SUMPRODUCT('Coef Fabricacion'!$L$34:$S$34,Volumenes!$B$7:$I$7)+SUMPRODUCT('Coef Fabricacion'!$T$34:$AA$34,Volumenes!$B$20:$I$20) -> 27.777778 | F16: =SUMPRODUCT('Coef Fabricacion'!$D$34:$K$34,Volumenes!$B$34:$I$34)+SUMPRODUCT('Coef Fabricacion'!$L$34:$S$34,Volumenes!$B$8:$I$8)+SUMPRODUCT('Coef Fabricacion'!$T$34:$AA$34,Volumenes!$B$21:$I$21) -> 43 | G16: =SUMPRODUCT('Coef Fabricacion'!$D$34:$K$34,Volumenes!$B$35:$I$35)+SUMPRODUCT('Coef Fabricacion'!$L$34:$S$34,Volumenes!$B$9:$I$9)+SUMPRODUCT('Coef Fabricacion'!$T$34:$AA$34,Volumenes!$B$22:$I$22) -> 72 | H16: =SUMPRODUCT('Coef Fabricacion'!$D$34:$K$34,Volumenes!$B$36:$I$36)+SUMPRODUCT('Coef Fabricacion'!$L$34:$S$34,Volumenes!$B$10:$I$10)+SUMPRODUCT('Coef Fabricacion'!$T$34:$AA$34,Volumenes!$B$23:$I$23) -> 119 | I16: =SUMPRODUCT('Coef Fabricacion'!$D$34:$K$34,Volumenes!$B$37:$I$37)+SUMPRODUCT('Coef Fabricacion'!$L$34:$S$34,Volumenes!$B$11:$I$11)+SUMPRODUCT('Coef Fabricacion'!$T$34:$AA$34,Volumenes!$B$24:$I$24) -> 165.88889 | J16: =SUMPRODUCT('Coef Fabricacion'!$D$34:$K$34,Volumenes!$B$38:$I$38)+SUMPRODUCT('Coef Fabricacion'!$L$34:$S$34,Volumenes!$B$12:$I$12)+SUMPRODUCT('Coef Fabricacion'!$T$34:$AA$34,Volumenes!$B$25:$I$25) -> 221.55556 | K16: =SUMPRODUCT('Coef Fabricacion'!$D$34:$K$34,Volumenes!$B$39:$I$39)+SUMPRODUCT('Coef Fabricacion'!$L$34:$S$34,Volumenes!$B$13:$I$13)+SUMPRODUCT('Coef Fabricacion'!$T$34:$AA$34,Volumenes!$B$26:$I$26) -> 279.5 | L16: =SUMPRODUCT('Coef Fabricacion'!$D$34:$K$34,Volumenes!$B$40:$I$40)+SUMPRODUCT('Coef Fabricacion'!$L$34:$S$34,Volumenes!$B$14:$I$14)+SUMPRODUCT('Coef Fabricacion'!$T$34:$AA$34,Volumenes!$B$27:$I$27) -> 320.44444 | M16: =SUMPRODUCT('Coef Fabricacion'!$D$34:$K$34,Volumenes!$B$41:$I$41)+SUMPRODUCT('Coef Fabricacion'!$L$34:$S$34,Volumenes!$B$15:$I$15)+SUMPRODUCT('Coef Fabricacion'!$T$34:$AA$34,Volumenes!$B$28:$I$28) -> 370.27778 | N16: =IF(F16=0,"—",M16/F16) -> 8.6111111
A17: MP-12 | B17: Hoja LAC 4,75 × 1500 × 3000 mm (cuerpos 70 y 100 kg; hoja mixta 3 × 70 + 1 × 100) | C17: hoja | D17: =SUMPRODUCT('Coef Fabricacion'!$D$35:$K$35,Volumenes!$B$32:$I$32)+SUMPRODUCT('Coef Fabricacion'!$L$35:$S$35,Volumenes!$B$6:$I$6)+SUMPRODUCT('Coef Fabricacion'!$T$35:$AA$35,Volumenes!$B$19:$I$19) -> 7.2222222 | E17: =SUMPRODUCT('Coef Fabricacion'!$D$35:$K$35,Volumenes!$B$33:$I$33)+SUMPRODUCT('Coef Fabricacion'!$L$35:$S$35,Volumenes!$B$7:$I$7)+SUMPRODUCT('Coef Fabricacion'!$T$35:$AA$35,Volumenes!$B$20:$I$20) -> 12.444444 | F17: =SUMPRODUCT('Coef Fabricacion'!$D$35:$K$35,Volumenes!$B$34:$I$34)+SUMPRODUCT('Coef Fabricacion'!$L$35:$S$35,Volumenes!$B$8:$I$8)+SUMPRODUCT('Coef Fabricacion'!$T$35:$AA$35,Volumenes!$B$21:$I$21) -> 19.222222 | G17: =SUMPRODUCT('Coef Fabricacion'!$D$35:$K$35,Volumenes!$B$35:$I$35)+SUMPRODUCT('Coef Fabricacion'!$L$35:$S$35,Volumenes!$B$9:$I$9)+SUMPRODUCT('Coef Fabricacion'!$T$35:$AA$35,Volumenes!$B$22:$I$22) -> 32.333333 | H17: =SUMPRODUCT('Coef Fabricacion'!$D$35:$K$35,Volumenes!$B$36:$I$36)+SUMPRODUCT('Coef Fabricacion'!$L$35:$S$35,Volumenes!$B$10:$I$10)+SUMPRODUCT('Coef Fabricacion'!$T$35:$AA$35,Volumenes!$B$23:$I$23) -> 53.111111 | I17: =SUMPRODUCT('Coef Fabricacion'!$D$35:$K$35,Volumenes!$B$37:$I$37)+SUMPRODUCT('Coef Fabricacion'!$L$35:$S$35,Volumenes!$B$11:$I$11)+SUMPRODUCT('Coef Fabricacion'!$T$35:$AA$35,Volumenes!$B$24:$I$24) -> 73.555556 | J17: =SUMPRODUCT('Coef Fabricacion'!$D$35:$K$35,Volumenes!$B$38:$I$38)+SUMPRODUCT('Coef Fabricacion'!$L$35:$S$35,Volumenes!$B$12:$I$12)+SUMPRODUCT('Coef Fabricacion'!$T$35:$AA$35,Volumenes!$B$25:$I$25) -> 98.555556 | K17: =SUMPRODUCT('Coef Fabricacion'!$D$35:$K$35,Volumenes!$B$39:$I$39)+SUMPRODUCT('Coef Fabricacion'!$L$35:$S$35,Volumenes!$B$13:$I$13)+SUMPRODUCT('Coef Fabricacion'!$T$35:$AA$35,Volumenes!$B$26:$I$26) -> 124.66667 | L17: =SUMPRODUCT('Coef Fabricacion'!$D$35:$K$35,Volumenes!$B$40:$I$40)+SUMPRODUCT('Coef Fabricacion'!$L$35:$S$35,Volumenes!$B$14:$I$14)+SUMPRODUCT('Coef Fabricacion'!$T$35:$AA$35,Volumenes!$B$27:$I$27) -> 142.88889 | M17: =SUMPRODUCT('Coef Fabricacion'!$D$35:$K$35,Volumenes!$B$41:$I$41)+SUMPRODUCT('Coef Fabricacion'!$L$35:$S$35,Volumenes!$B$15:$I$15)+SUMPRODUCT('Coef Fabricacion'!$T$35:$AA$35,Volumenes!$B$28:$I$28) -> 165.22222 | N17: =IF(F17=0,"—",M17/F17) -> 8.5953757
A18: MP-13 | B18: Fleje LAF 0,9 × 106 mm (fondo 1 kg) | C18: kg | D18: =SUMPRODUCT('Coef Fabricacion'!$D$36:$K$36,Volumenes!$B$32:$I$32)+SUMPRODUCT('Coef Fabricacion'!$L$36:$S$36,Volumenes!$B$6:$I$6)+SUMPRODUCT('Coef Fabricacion'!$T$36:$AA$36,Volumenes!$B$19:$I$19) -> 322.34996 | E18: =SUMPRODUCT('Coef Fabricacion'!$D$36:$K$36,Volumenes!$B$33:$I$33)+SUMPRODUCT('Coef Fabricacion'!$L$36:$S$36,Volumenes!$B$7:$I$7)+SUMPRODUCT('Coef Fabricacion'!$T$36:$AA$36,Volumenes!$B$20:$I$20) -> 462.58261 | F18: =SUMPRODUCT('Coef Fabricacion'!$D$36:$K$36,Volumenes!$B$34:$I$34)+SUMPRODUCT('Coef Fabricacion'!$L$36:$S$36,Volumenes!$B$8:$I$8)+SUMPRODUCT('Coef Fabricacion'!$T$36:$AA$36,Volumenes!$B$21:$I$21) -> 1119.5471 | G18: =SUMPRODUCT('Coef Fabricacion'!$D$36:$K$36,Volumenes!$B$35:$I$35)+SUMPRODUCT('Coef Fabricacion'!$L$36:$S$36,Volumenes!$B$9:$I$9)+SUMPRODUCT('Coef Fabricacion'!$T$36:$AA$36,Volumenes!$B$22:$I$22) -> 2712.2444 | H18: =SUMPRODUCT('Coef Fabricacion'!$D$36:$K$36,Volumenes!$B$36:$I$36)+SUMPRODUCT('Coef Fabricacion'!$L$36:$S$36,Volumenes!$B$10:$I$10)+SUMPRODUCT('Coef Fabricacion'!$T$36:$AA$36,Volumenes!$B$23:$I$23) -> 4791.3593 | I18: =SUMPRODUCT('Coef Fabricacion'!$D$36:$K$36,Volumenes!$B$37:$I$37)+SUMPRODUCT('Coef Fabricacion'!$L$36:$S$36,Volumenes!$B$11:$I$11)+SUMPRODUCT('Coef Fabricacion'!$T$36:$AA$36,Volumenes!$B$24:$I$24) -> 6733.944 | J18: =SUMPRODUCT('Coef Fabricacion'!$D$36:$K$36,Volumenes!$B$38:$I$38)+SUMPRODUCT('Coef Fabricacion'!$L$36:$S$36,Volumenes!$B$12:$I$12)+SUMPRODUCT('Coef Fabricacion'!$T$36:$AA$36,Volumenes!$B$25:$I$25) -> 9385.4055 | K18: =SUMPRODUCT('Coef Fabricacion'!$D$36:$K$36,Volumenes!$B$39:$I$39)+SUMPRODUCT('Coef Fabricacion'!$L$36:$S$36,Volumenes!$B$13:$I$13)+SUMPRODUCT('Coef Fabricacion'!$T$36:$AA$36,Volumenes!$B$26:$I$26) -> 12043.424 | L18: =SUMPRODUCT('Coef Fabricacion'!$D$36:$K$36,Volumenes!$B$40:$I$40)+SUMPRODUCT('Coef Fabricacion'!$L$36:$S$36,Volumenes!$B$14:$I$14)+SUMPRODUCT('Coef Fabricacion'!$T$36:$AA$36,Volumenes!$B$27:$I$27) -> 13529.057 | M18: =SUMPRODUCT('Coef Fabricacion'!$D$36:$K$36,Volumenes!$B$41:$I$41)+SUMPRODUCT('Coef Fabricacion'!$L$36:$S$36,Volumenes!$B$15:$I$15)+SUMPRODUCT('Coef Fabricacion'!$T$36:$AA$36,Volumenes!$B$28:$I$28) -> 15629.307 | N18: =IF(F18=0,"—",M18/F18) -> 13.960383
A19: MP-15 | B19: Casquete embutido 10" × 3,2 mm (carro 25 kg) | C19: u | D19: =SUMPRODUCT('Coef Fabricacion'!$D$37:$K$37,Volumenes!$B$32:$I$32)+SUMPRODUCT('Coef Fabricacion'!$L$37:$S$37,Volumenes!$B$6:$I$6)+SUMPRODUCT('Coef Fabricacion'!$T$37:$AA$37,Volumenes!$B$19:$I$19) -> 68 | E19: =SUMPRODUCT('Coef Fabricacion'!$D$37:$K$37,Volumenes!$B$33:$I$33)+SUMPRODUCT('Coef Fabricacion'!$L$37:$S$37,Volumenes!$B$7:$I$7)+SUMPRODUCT('Coef Fabricacion'!$T$37:$AA$37,Volumenes!$B$20:$I$20) -> 116 | F19: =SUMPRODUCT('Coef Fabricacion'!$D$37:$K$37,Volumenes!$B$34:$I$34)+SUMPRODUCT('Coef Fabricacion'!$L$37:$S$37,Volumenes!$B$8:$I$8)+SUMPRODUCT('Coef Fabricacion'!$T$37:$AA$37,Volumenes!$B$21:$I$21) -> 180 | G19: =SUMPRODUCT('Coef Fabricacion'!$D$37:$K$37,Volumenes!$B$35:$I$35)+SUMPRODUCT('Coef Fabricacion'!$L$37:$S$37,Volumenes!$B$9:$I$9)+SUMPRODUCT('Coef Fabricacion'!$T$37:$AA$37,Volumenes!$B$22:$I$22) -> 300 | H19: =SUMPRODUCT('Coef Fabricacion'!$D$37:$K$37,Volumenes!$B$36:$I$36)+SUMPRODUCT('Coef Fabricacion'!$L$37:$S$37,Volumenes!$B$10:$I$10)+SUMPRODUCT('Coef Fabricacion'!$T$37:$AA$37,Volumenes!$B$23:$I$23) -> 498 | I19: =SUMPRODUCT('Coef Fabricacion'!$D$37:$K$37,Volumenes!$B$37:$I$37)+SUMPRODUCT('Coef Fabricacion'!$L$37:$S$37,Volumenes!$B$11:$I$11)+SUMPRODUCT('Coef Fabricacion'!$T$37:$AA$37,Volumenes!$B$24:$I$24) -> 694 | J19: =SUMPRODUCT('Coef Fabricacion'!$D$37:$K$37,Volumenes!$B$38:$I$38)+SUMPRODUCT('Coef Fabricacion'!$L$37:$S$37,Volumenes!$B$12:$I$12)+SUMPRODUCT('Coef Fabricacion'!$T$37:$AA$37,Volumenes!$B$25:$I$25) -> 928 | K19: =SUMPRODUCT('Coef Fabricacion'!$D$37:$K$37,Volumenes!$B$39:$I$39)+SUMPRODUCT('Coef Fabricacion'!$L$37:$S$37,Volumenes!$B$13:$I$13)+SUMPRODUCT('Coef Fabricacion'!$T$37:$AA$37,Volumenes!$B$26:$I$26) -> 1170 | L19: =SUMPRODUCT('Coef Fabricacion'!$D$37:$K$37,Volumenes!$B$40:$I$40)+SUMPRODUCT('Coef Fabricacion'!$L$37:$S$37,Volumenes!$B$14:$I$14)+SUMPRODUCT('Coef Fabricacion'!$T$37:$AA$37,Volumenes!$B$27:$I$27) -> 1340 | M19: =SUMPRODUCT('Coef Fabricacion'!$D$37:$K$37,Volumenes!$B$41:$I$41)+SUMPRODUCT('Coef Fabricacion'!$L$37:$S$37,Volumenes!$B$15:$I$15)+SUMPRODUCT('Coef Fabricacion'!$T$37:$AA$37,Volumenes!$B$28:$I$28) -> 1550 | N19: =IF(F19=0,"—",M19/F19) -> 8.6111111
A20: MP-16 | B20: Casquete embutido 12" × 3,2 mm (carro 50 kg) | C20: u | D20: =SUMPRODUCT('Coef Fabricacion'!$D$38:$K$38,Volumenes!$B$32:$I$32)+SUMPRODUCT('Coef Fabricacion'!$L$38:$S$38,Volumenes!$B$6:$I$6)+SUMPRODUCT('Coef Fabricacion'!$T$38:$AA$38,Volumenes!$B$19:$I$19) -> 150 | E20: =SUMPRODUCT('Coef Fabricacion'!$D$38:$K$38,Volumenes!$B$33:$I$33)+SUMPRODUCT('Coef Fabricacion'!$L$38:$S$38,Volumenes!$B$7:$I$7)+SUMPRODUCT('Coef Fabricacion'!$T$38:$AA$38,Volumenes!$B$20:$I$20) -> 256 | F20: =SUMPRODUCT('Coef Fabricacion'!$D$38:$K$38,Volumenes!$B$34:$I$34)+SUMPRODUCT('Coef Fabricacion'!$L$38:$S$38,Volumenes!$B$8:$I$8)+SUMPRODUCT('Coef Fabricacion'!$T$38:$AA$38,Volumenes!$B$21:$I$21) -> 396 | G20: =SUMPRODUCT('Coef Fabricacion'!$D$38:$K$38,Volumenes!$B$35:$I$35)+SUMPRODUCT('Coef Fabricacion'!$L$38:$S$38,Volumenes!$B$9:$I$9)+SUMPRODUCT('Coef Fabricacion'!$T$38:$AA$38,Volumenes!$B$22:$I$22) -> 664 | H20: =SUMPRODUCT('Coef Fabricacion'!$D$38:$K$38,Volumenes!$B$36:$I$36)+SUMPRODUCT('Coef Fabricacion'!$L$38:$S$38,Volumenes!$B$10:$I$10)+SUMPRODUCT('Coef Fabricacion'!$T$38:$AA$38,Volumenes!$B$23:$I$23) -> 1096 | I20: =SUMPRODUCT('Coef Fabricacion'!$D$38:$K$38,Volumenes!$B$37:$I$37)+SUMPRODUCT('Coef Fabricacion'!$L$38:$S$38,Volumenes!$B$11:$I$11)+SUMPRODUCT('Coef Fabricacion'!$T$38:$AA$38,Volumenes!$B$24:$I$24) -> 1528 | J20: =SUMPRODUCT('Coef Fabricacion'!$D$38:$K$38,Volumenes!$B$38:$I$38)+SUMPRODUCT('Coef Fabricacion'!$L$38:$S$38,Volumenes!$B$12:$I$12)+SUMPRODUCT('Coef Fabricacion'!$T$38:$AA$38,Volumenes!$B$25:$I$25) -> 2040 | K20: =SUMPRODUCT('Coef Fabricacion'!$D$38:$K$38,Volumenes!$B$39:$I$39)+SUMPRODUCT('Coef Fabricacion'!$L$38:$S$38,Volumenes!$B$13:$I$13)+SUMPRODUCT('Coef Fabricacion'!$T$38:$AA$38,Volumenes!$B$26:$I$26) -> 2574 | L20: =SUMPRODUCT('Coef Fabricacion'!$D$38:$K$38,Volumenes!$B$40:$I$40)+SUMPRODUCT('Coef Fabricacion'!$L$38:$S$38,Volumenes!$B$14:$I$14)+SUMPRODUCT('Coef Fabricacion'!$T$38:$AA$38,Volumenes!$B$27:$I$27) -> 2952 | M20: =SUMPRODUCT('Coef Fabricacion'!$D$38:$K$38,Volumenes!$B$41:$I$41)+SUMPRODUCT('Coef Fabricacion'!$L$38:$S$38,Volumenes!$B$15:$I$15)+SUMPRODUCT('Coef Fabricacion'!$T$38:$AA$38,Volumenes!$B$28:$I$28) -> 3410 | N20: =IF(F20=0,"—",M20/F20) -> 8.6111111
A21: MP-17 | B21: Casquete embutido 15" × 4,75 mm (carros 70 y 100 kg) | C21: u | D21: =SUMPRODUCT('Coef Fabricacion'!$D$39:$K$39,Volumenes!$B$32:$I$32)+SUMPRODUCT('Coef Fabricacion'!$L$39:$S$39,Volumenes!$B$6:$I$6)+SUMPRODUCT('Coef Fabricacion'!$T$39:$AA$39,Volumenes!$B$19:$I$19) -> 54 | E21: =SUMPRODUCT('Coef Fabricacion'!$D$39:$K$39,Volumenes!$B$33:$I$33)+SUMPRODUCT('Coef Fabricacion'!$L$39:$S$39,Volumenes!$B$7:$I$7)+SUMPRODUCT('Coef Fabricacion'!$T$39:$AA$39,Volumenes!$B$20:$I$20) -> 94 | F21: =SUMPRODUCT('Coef Fabricacion'!$D$39:$K$39,Volumenes!$B$34:$I$34)+SUMPRODUCT('Coef Fabricacion'!$L$39:$S$39,Volumenes!$B$8:$I$8)+SUMPRODUCT('Coef Fabricacion'!$T$39:$AA$39,Volumenes!$B$21:$I$21) -> 144 | G21: =SUMPRODUCT('Coef Fabricacion'!$D$39:$K$39,Volumenes!$B$35:$I$35)+SUMPRODUCT('Coef Fabricacion'!$L$39:$S$39,Volumenes!$B$9:$I$9)+SUMPRODUCT('Coef Fabricacion'!$T$39:$AA$39,Volumenes!$B$22:$I$22) -> 242 | H21: =SUMPRODUCT('Coef Fabricacion'!$D$39:$K$39,Volumenes!$B$36:$I$36)+SUMPRODUCT('Coef Fabricacion'!$L$39:$S$39,Volumenes!$B$10:$I$10)+SUMPRODUCT('Coef Fabricacion'!$T$39:$AA$39,Volumenes!$B$23:$I$23) -> 398 | I21: =SUMPRODUCT('Coef Fabricacion'!$D$39:$K$39,Volumenes!$B$37:$I$37)+SUMPRODUCT('Coef Fabricacion'!$L$39:$S$39,Volumenes!$B$11:$I$11)+SUMPRODUCT('Coef Fabricacion'!$T$39:$AA$39,Volumenes!$B$24:$I$24) -> 552 | J21: =SUMPRODUCT('Coef Fabricacion'!$D$39:$K$39,Volumenes!$B$38:$I$38)+SUMPRODUCT('Coef Fabricacion'!$L$39:$S$39,Volumenes!$B$12:$I$12)+SUMPRODUCT('Coef Fabricacion'!$T$39:$AA$39,Volumenes!$B$25:$I$25) -> 740 | K21: =SUMPRODUCT('Coef Fabricacion'!$D$39:$K$39,Volumenes!$B$39:$I$39)+SUMPRODUCT('Coef Fabricacion'!$L$39:$S$39,Volumenes!$B$13:$I$13)+SUMPRODUCT('Coef Fabricacion'!$T$39:$AA$39,Volumenes!$B$26:$I$26) -> 936 | L21: =SUMPRODUCT('Coef Fabricacion'!$D$39:$K$39,Volumenes!$B$40:$I$40)+SUMPRODUCT('Coef Fabricacion'!$L$39:$S$39,Volumenes!$B$14:$I$14)+SUMPRODUCT('Coef Fabricacion'!$T$39:$AA$39,Volumenes!$B$27:$I$27) -> 1072 | M21: =SUMPRODUCT('Coef Fabricacion'!$D$39:$K$39,Volumenes!$B$41:$I$41)+SUMPRODUCT('Coef Fabricacion'!$L$39:$S$39,Volumenes!$B$15:$I$15)+SUMPRODUCT('Coef Fabricacion'!$T$39:$AA$39,Volumenes!$B$28:$I$28) -> 1240 | N21: =IF(F21=0,"—",M21/F21) -> 8.6111111
A22: MP-18 | B22: Asiento de válvula roscado M22 (cúpula 1 kg) | C22: u | D22: =SUMPRODUCT('Coef Fabricacion'!$D$40:$K$40,Volumenes!$B$32:$I$32)+SUMPRODUCT('Coef Fabricacion'!$L$40:$S$40,Volumenes!$B$6:$I$6)+SUMPRODUCT('Coef Fabricacion'!$T$40:$AA$40,Volumenes!$B$19:$I$19) -> 4179 | E22: =SUMPRODUCT('Coef Fabricacion'!$D$40:$K$40,Volumenes!$B$33:$I$33)+SUMPRODUCT('Coef Fabricacion'!$L$40:$S$40,Volumenes!$B$7:$I$7)+SUMPRODUCT('Coef Fabricacion'!$T$40:$AA$40,Volumenes!$B$20:$I$20) -> 5997 | F22: =SUMPRODUCT('Coef Fabricacion'!$D$40:$K$40,Volumenes!$B$34:$I$34)+SUMPRODUCT('Coef Fabricacion'!$L$40:$S$40,Volumenes!$B$8:$I$8)+SUMPRODUCT('Coef Fabricacion'!$T$40:$AA$40,Volumenes!$B$21:$I$21) -> 14514 | G22: =SUMPRODUCT('Coef Fabricacion'!$D$40:$K$40,Volumenes!$B$35:$I$35)+SUMPRODUCT('Coef Fabricacion'!$L$40:$S$40,Volumenes!$B$9:$I$9)+SUMPRODUCT('Coef Fabricacion'!$T$40:$AA$40,Volumenes!$B$22:$I$22) -> 35162 | H22: =SUMPRODUCT('Coef Fabricacion'!$D$40:$K$40,Volumenes!$B$36:$I$36)+SUMPRODUCT('Coef Fabricacion'!$L$40:$S$40,Volumenes!$B$10:$I$10)+SUMPRODUCT('Coef Fabricacion'!$T$40:$AA$40,Volumenes!$B$23:$I$23) -> 62116 | I22: =SUMPRODUCT('Coef Fabricacion'!$D$40:$K$40,Volumenes!$B$37:$I$37)+SUMPRODUCT('Coef Fabricacion'!$L$40:$S$40,Volumenes!$B$11:$I$11)+SUMPRODUCT('Coef Fabricacion'!$T$40:$AA$40,Volumenes!$B$24:$I$24) -> 87300 | J22: =SUMPRODUCT('Coef Fabricacion'!$D$40:$K$40,Volumenes!$B$38:$I$38)+SUMPRODUCT('Coef Fabricacion'!$L$40:$S$40,Volumenes!$B$12:$I$12)+SUMPRODUCT('Coef Fabricacion'!$T$40:$AA$40,Volumenes!$B$25:$I$25) -> 121674 | K22: =SUMPRODUCT('Coef Fabricacion'!$D$40:$K$40,Volumenes!$B$39:$I$39)+SUMPRODUCT('Coef Fabricacion'!$L$40:$S$40,Volumenes!$B$13:$I$13)+SUMPRODUCT('Coef Fabricacion'!$T$40:$AA$40,Volumenes!$B$26:$I$26) -> 156133 | L22: =SUMPRODUCT('Coef Fabricacion'!$D$40:$K$40,Volumenes!$B$40:$I$40)+SUMPRODUCT('Coef Fabricacion'!$L$40:$S$40,Volumenes!$B$14:$I$14)+SUMPRODUCT('Coef Fabricacion'!$T$40:$AA$40,Volumenes!$B$27:$I$27) -> 175393 | M22: =SUMPRODUCT('Coef Fabricacion'!$D$40:$K$40,Volumenes!$B$41:$I$41)+SUMPRODUCT('Coef Fabricacion'!$L$40:$S$40,Volumenes!$B$15:$I$15)+SUMPRODUCT('Coef Fabricacion'!$T$40:$AA$40,Volumenes!$B$28:$I$28) -> 202621 | N22: =IF(F22=0,"—",M22/F22) -> 13.960383
A23: MP-19 | B23: Asiento de válvula roscado M30 × 1,5 (cúpula 2,5–10 kg) | C23: u | D23: =SUMPRODUCT('Coef Fabricacion'!$D$41:$K$41,Volumenes!$B$32:$I$32)+SUMPRODUCT('Coef Fabricacion'!$L$41:$S$41,Volumenes!$B$6:$I$6)+SUMPRODUCT('Coef Fabricacion'!$T$41:$AA$41,Volumenes!$B$19:$I$19) -> 2643 | E23: =SUMPRODUCT('Coef Fabricacion'!$D$41:$K$41,Volumenes!$B$33:$I$33)+SUMPRODUCT('Coef Fabricacion'!$L$41:$S$41,Volumenes!$B$7:$I$7)+SUMPRODUCT('Coef Fabricacion'!$T$41:$AA$41,Volumenes!$B$20:$I$20) -> 4733 | F23: =SUMPRODUCT('Coef Fabricacion'!$D$41:$K$41,Volumenes!$B$34:$I$34)+SUMPRODUCT('Coef Fabricacion'!$L$41:$S$41,Volumenes!$B$8:$I$8)+SUMPRODUCT('Coef Fabricacion'!$T$41:$AA$41,Volumenes!$B$21:$I$21) -> 8203 | G23: =SUMPRODUCT('Coef Fabricacion'!$D$41:$K$41,Volumenes!$B$35:$I$35)+SUMPRODUCT('Coef Fabricacion'!$L$41:$S$41,Volumenes!$B$9:$I$9)+SUMPRODUCT('Coef Fabricacion'!$T$41:$AA$41,Volumenes!$B$22:$I$22) -> 15193 | H23: =SUMPRODUCT('Coef Fabricacion'!$D$41:$K$41,Volumenes!$B$36:$I$36)+SUMPRODUCT('Coef Fabricacion'!$L$41:$S$41,Volumenes!$B$10:$I$10)+SUMPRODUCT('Coef Fabricacion'!$T$41:$AA$41,Volumenes!$B$23:$I$23) -> 25791 | I23: =SUMPRODUCT('Coef Fabricacion'!$D$41:$K$41,Volumenes!$B$37:$I$37)+SUMPRODUCT('Coef Fabricacion'!$L$41:$S$41,Volumenes!$B$11:$I$11)+SUMPRODUCT('Coef Fabricacion'!$T$41:$AA$41,Volumenes!$B$24:$I$24) -> 36213 | J23: =SUMPRODUCT('Coef Fabricacion'!$D$41:$K$41,Volumenes!$B$38:$I$38)+SUMPRODUCT('Coef Fabricacion'!$L$41:$S$41,Volumenes!$B$12:$I$12)+SUMPRODUCT('Coef Fabricacion'!$T$41:$AA$41,Volumenes!$B$25:$I$25) -> 48825 | K23: =SUMPRODUCT('Coef Fabricacion'!$D$41:$K$41,Volumenes!$B$39:$I$39)+SUMPRODUCT('Coef Fabricacion'!$L$41:$S$41,Volumenes!$B$13:$I$13)+SUMPRODUCT('Coef Fabricacion'!$T$41:$AA$41,Volumenes!$B$26:$I$26) -> 61819 | L23: =SUMPRODUCT('Coef Fabricacion'!$D$41:$K$41,Volumenes!$B$40:$I$40)+SUMPRODUCT('Coef Fabricacion'!$L$41:$S$41,Volumenes!$B$14:$I$14)+SUMPRODUCT('Coef Fabricacion'!$T$41:$AA$41,Volumenes!$B$27:$I$27) -> 70583 | M23: =SUMPRODUCT('Coef Fabricacion'!$D$41:$K$41,Volumenes!$B$41:$I$41)+SUMPRODUCT('Coef Fabricacion'!$L$41:$S$41,Volumenes!$B$15:$I$15)+SUMPRODUCT('Coef Fabricacion'!$T$41:$AA$41,Volumenes!$B$28:$I$28) -> 81612 | N23: =IF(F23=0,"—",M23/F23) -> 9.949043
A24: MP-20 | B24: Cupla soldable M30 × 1,5 (carros 25 y 50 kg) | C24: u | D24: =SUMPRODUCT('Coef Fabricacion'!$D$42:$K$42,Volumenes!$B$32:$I$32)+SUMPRODUCT('Coef Fabricacion'!$L$42:$S$42,Volumenes!$B$6:$I$6)+SUMPRODUCT('Coef Fabricacion'!$T$42:$AA$42,Volumenes!$B$19:$I$19) -> 109 | E24: =SUMPRODUCT('Coef Fabricacion'!$D$42:$K$42,Volumenes!$B$33:$I$33)+SUMPRODUCT('Coef Fabricacion'!$L$42:$S$42,Volumenes!$B$7:$I$7)+SUMPRODUCT('Coef Fabricacion'!$T$42:$AA$42,Volumenes!$B$20:$I$20) -> 186 | F24: =SUMPRODUCT('Coef Fabricacion'!$D$42:$K$42,Volumenes!$B$34:$I$34)+SUMPRODUCT('Coef Fabricacion'!$L$42:$S$42,Volumenes!$B$8:$I$8)+SUMPRODUCT('Coef Fabricacion'!$T$42:$AA$42,Volumenes!$B$21:$I$21) -> 288 | G24: =SUMPRODUCT('Coef Fabricacion'!$D$42:$K$42,Volumenes!$B$35:$I$35)+SUMPRODUCT('Coef Fabricacion'!$L$42:$S$42,Volumenes!$B$9:$I$9)+SUMPRODUCT('Coef Fabricacion'!$T$42:$AA$42,Volumenes!$B$22:$I$22) -> 482 | H24: =SUMPRODUCT('Coef Fabricacion'!$D$42:$K$42,Volumenes!$B$36:$I$36)+SUMPRODUCT('Coef Fabricacion'!$L$42:$S$42,Volumenes!$B$10:$I$10)+SUMPRODUCT('Coef Fabricacion'!$T$42:$AA$42,Volumenes!$B$23:$I$23) -> 797 | I24: =SUMPRODUCT('Coef Fabricacion'!$D$42:$K$42,Volumenes!$B$37:$I$37)+SUMPRODUCT('Coef Fabricacion'!$L$42:$S$42,Volumenes!$B$11:$I$11)+SUMPRODUCT('Coef Fabricacion'!$T$42:$AA$42,Volumenes!$B$24:$I$24) -> 1111 | J24: =SUMPRODUCT('Coef Fabricacion'!$D$42:$K$42,Volumenes!$B$38:$I$38)+SUMPRODUCT('Coef Fabricacion'!$L$42:$S$42,Volumenes!$B$12:$I$12)+SUMPRODUCT('Coef Fabricacion'!$T$42:$AA$42,Volumenes!$B$25:$I$25) -> 1484 | K24: =SUMPRODUCT('Coef Fabricacion'!$D$42:$K$42,Volumenes!$B$39:$I$39)+SUMPRODUCT('Coef Fabricacion'!$L$42:$S$42,Volumenes!$B$13:$I$13)+SUMPRODUCT('Coef Fabricacion'!$T$42:$AA$42,Volumenes!$B$26:$I$26) -> 1872 | L24: =SUMPRODUCT('Coef Fabricacion'!$D$42:$K$42,Volumenes!$B$40:$I$40)+SUMPRODUCT('Coef Fabricacion'!$L$42:$S$42,Volumenes!$B$14:$I$14)+SUMPRODUCT('Coef Fabricacion'!$T$42:$AA$42,Volumenes!$B$27:$I$27) -> 2146 | M24: =SUMPRODUCT('Coef Fabricacion'!$D$42:$K$42,Volumenes!$B$41:$I$41)+SUMPRODUCT('Coef Fabricacion'!$L$42:$S$42,Volumenes!$B$15:$I$15)+SUMPRODUCT('Coef Fabricacion'!$T$42:$AA$42,Volumenes!$B$28:$I$28) -> 2480 | N24: =IF(F24=0,"—",M24/F24) -> 8.6111111
A25: MP-21 | B25: Cupla soldable 2½" BSP (carros 70 y 100 kg) | C25: u | D25: =SUMPRODUCT('Coef Fabricacion'!$D$43:$K$43,Volumenes!$B$32:$I$32)+SUMPRODUCT('Coef Fabricacion'!$L$43:$S$43,Volumenes!$B$6:$I$6)+SUMPRODUCT('Coef Fabricacion'!$T$43:$AA$43,Volumenes!$B$19:$I$19) -> 27 | E25: =SUMPRODUCT('Coef Fabricacion'!$D$43:$K$43,Volumenes!$B$33:$I$33)+SUMPRODUCT('Coef Fabricacion'!$L$43:$S$43,Volumenes!$B$7:$I$7)+SUMPRODUCT('Coef Fabricacion'!$T$43:$AA$43,Volumenes!$B$20:$I$20) -> 47 | F25: =SUMPRODUCT('Coef Fabricacion'!$D$43:$K$43,Volumenes!$B$34:$I$34)+SUMPRODUCT('Coef Fabricacion'!$L$43:$S$43,Volumenes!$B$8:$I$8)+SUMPRODUCT('Coef Fabricacion'!$T$43:$AA$43,Volumenes!$B$21:$I$21) -> 72 | G25: =SUMPRODUCT('Coef Fabricacion'!$D$43:$K$43,Volumenes!$B$35:$I$35)+SUMPRODUCT('Coef Fabricacion'!$L$43:$S$43,Volumenes!$B$9:$I$9)+SUMPRODUCT('Coef Fabricacion'!$T$43:$AA$43,Volumenes!$B$22:$I$22) -> 121 | H25: =SUMPRODUCT('Coef Fabricacion'!$D$43:$K$43,Volumenes!$B$36:$I$36)+SUMPRODUCT('Coef Fabricacion'!$L$43:$S$43,Volumenes!$B$10:$I$10)+SUMPRODUCT('Coef Fabricacion'!$T$43:$AA$43,Volumenes!$B$23:$I$23) -> 199 | I25: =SUMPRODUCT('Coef Fabricacion'!$D$43:$K$43,Volumenes!$B$37:$I$37)+SUMPRODUCT('Coef Fabricacion'!$L$43:$S$43,Volumenes!$B$11:$I$11)+SUMPRODUCT('Coef Fabricacion'!$T$43:$AA$43,Volumenes!$B$24:$I$24) -> 276 | J25: =SUMPRODUCT('Coef Fabricacion'!$D$43:$K$43,Volumenes!$B$38:$I$38)+SUMPRODUCT('Coef Fabricacion'!$L$43:$S$43,Volumenes!$B$12:$I$12)+SUMPRODUCT('Coef Fabricacion'!$T$43:$AA$43,Volumenes!$B$25:$I$25) -> 370 | K25: =SUMPRODUCT('Coef Fabricacion'!$D$43:$K$43,Volumenes!$B$39:$I$39)+SUMPRODUCT('Coef Fabricacion'!$L$43:$S$43,Volumenes!$B$13:$I$13)+SUMPRODUCT('Coef Fabricacion'!$T$43:$AA$43,Volumenes!$B$26:$I$26) -> 468 | L25: =SUMPRODUCT('Coef Fabricacion'!$D$43:$K$43,Volumenes!$B$40:$I$40)+SUMPRODUCT('Coef Fabricacion'!$L$43:$S$43,Volumenes!$B$14:$I$14)+SUMPRODUCT('Coef Fabricacion'!$T$43:$AA$43,Volumenes!$B$27:$I$27) -> 536 | M25: =SUMPRODUCT('Coef Fabricacion'!$D$43:$K$43,Volumenes!$B$41:$I$41)+SUMPRODUCT('Coef Fabricacion'!$L$43:$S$43,Volumenes!$B$15:$I$15)+SUMPRODUCT('Coef Fabricacion'!$T$43:$AA$43,Volumenes!$B$28:$I$28) -> 620 | N25: =IF(F25=0,"—",M25/F25) -> 8.6111111
A26: MP-22 | B26: Varilla de refuerzo (carros 70 y 100 kg) | C26: kg | D26: =SUMPRODUCT('Coef Fabricacion'!$D$44:$K$44,Volumenes!$B$32:$I$32)+SUMPRODUCT('Coef Fabricacion'!$L$44:$S$44,Volumenes!$B$6:$I$6)+SUMPRODUCT('Coef Fabricacion'!$T$44:$AA$44,Volumenes!$B$19:$I$19) -> 40.5 | E26: =SUMPRODUCT('Coef Fabricacion'!$D$44:$K$44,Volumenes!$B$33:$I$33)+SUMPRODUCT('Coef Fabricacion'!$L$44:$S$44,Volumenes!$B$7:$I$7)+SUMPRODUCT('Coef Fabricacion'!$T$44:$AA$44,Volumenes!$B$20:$I$20) -> 70.5 | F26: =SUMPRODUCT('Coef Fabricacion'!$D$44:$K$44,Volumenes!$B$34:$I$34)+SUMPRODUCT('Coef Fabricacion'!$L$44:$S$44,Volumenes!$B$8:$I$8)+SUMPRODUCT('Coef Fabricacion'!$T$44:$AA$44,Volumenes!$B$21:$I$21) -> 108 | G26: =SUMPRODUCT('Coef Fabricacion'!$D$44:$K$44,Volumenes!$B$35:$I$35)+SUMPRODUCT('Coef Fabricacion'!$L$44:$S$44,Volumenes!$B$9:$I$9)+SUMPRODUCT('Coef Fabricacion'!$T$44:$AA$44,Volumenes!$B$22:$I$22) -> 181.5 | H26: =SUMPRODUCT('Coef Fabricacion'!$D$44:$K$44,Volumenes!$B$36:$I$36)+SUMPRODUCT('Coef Fabricacion'!$L$44:$S$44,Volumenes!$B$10:$I$10)+SUMPRODUCT('Coef Fabricacion'!$T$44:$AA$44,Volumenes!$B$23:$I$23) -> 298.5 | I26: =SUMPRODUCT('Coef Fabricacion'!$D$44:$K$44,Volumenes!$B$37:$I$37)+SUMPRODUCT('Coef Fabricacion'!$L$44:$S$44,Volumenes!$B$11:$I$11)+SUMPRODUCT('Coef Fabricacion'!$T$44:$AA$44,Volumenes!$B$24:$I$24) -> 414 | J26: =SUMPRODUCT('Coef Fabricacion'!$D$44:$K$44,Volumenes!$B$38:$I$38)+SUMPRODUCT('Coef Fabricacion'!$L$44:$S$44,Volumenes!$B$12:$I$12)+SUMPRODUCT('Coef Fabricacion'!$T$44:$AA$44,Volumenes!$B$25:$I$25) -> 555 | K26: =SUMPRODUCT('Coef Fabricacion'!$D$44:$K$44,Volumenes!$B$39:$I$39)+SUMPRODUCT('Coef Fabricacion'!$L$44:$S$44,Volumenes!$B$13:$I$13)+SUMPRODUCT('Coef Fabricacion'!$T$44:$AA$44,Volumenes!$B$26:$I$26) -> 702 | L26: =SUMPRODUCT('Coef Fabricacion'!$D$44:$K$44,Volumenes!$B$40:$I$40)+SUMPRODUCT('Coef Fabricacion'!$L$44:$S$44,Volumenes!$B$14:$I$14)+SUMPRODUCT('Coef Fabricacion'!$T$44:$AA$44,Volumenes!$B$27:$I$27) -> 804 | M26: =SUMPRODUCT('Coef Fabricacion'!$D$44:$K$44,Volumenes!$B$41:$I$41)+SUMPRODUCT('Coef Fabricacion'!$L$44:$S$44,Volumenes!$B$15:$I$15)+SUMPRODUCT('Coef Fabricacion'!$T$44:$AA$44,Volumenes!$B$28:$I$28) -> 930 | N26: =IF(F26=0,"—",M26/F26) -> 8.6111111
A27: MP-23 | B27: Alambre MIG ER70S-6 Ø0,9 mm (manuales 1–10 kg) | C27: kg | D27: =SUMPRODUCT('Coef Fabricacion'!$D$45:$K$45,Volumenes!$B$32:$I$32)+SUMPRODUCT('Coef Fabricacion'!$L$45:$S$45,Volumenes!$B$6:$I$6)+SUMPRODUCT('Coef Fabricacion'!$T$45:$AA$45,Volumenes!$B$19:$I$19) -> 158.74339 | E27: =SUMPRODUCT('Coef Fabricacion'!$D$45:$K$45,Volumenes!$B$33:$I$33)+SUMPRODUCT('Coef Fabricacion'!$L$45:$S$45,Volumenes!$B$7:$I$7)+SUMPRODUCT('Coef Fabricacion'!$T$45:$AA$45,Volumenes!$B$20:$I$20) -> 260.94445 | F27: =SUMPRODUCT('Coef Fabricacion'!$D$45:$K$45,Volumenes!$B$34:$I$34)+SUMPRODUCT('Coef Fabricacion'!$L$45:$S$45,Volumenes!$B$8:$I$8)+SUMPRODUCT('Coef Fabricacion'!$T$45:$AA$45,Volumenes!$B$21:$I$21) -> 513.99308 | G27: =SUMPRODUCT('Coef Fabricacion'!$D$45:$K$45,Volumenes!$B$35:$I$35)+SUMPRODUCT('Coef Fabricacion'!$L$45:$S$45,Volumenes!$B$9:$I$9)+SUMPRODUCT('Coef Fabricacion'!$T$45:$AA$45,Volumenes!$B$22:$I$22) -> 1075.451 | H27: =SUMPRODUCT('Coef Fabricacion'!$D$45:$K$45,Volumenes!$B$36:$I$36)+SUMPRODUCT('Coef Fabricacion'!$L$45:$S$45,Volumenes!$B$10:$I$10)+SUMPRODUCT('Coef Fabricacion'!$T$45:$AA$45,Volumenes!$B$23:$I$23) -> 1862.8936 | I27: =SUMPRODUCT('Coef Fabricacion'!$D$45:$K$45,Volumenes!$B$37:$I$37)+SUMPRODUCT('Coef Fabricacion'!$L$45:$S$45,Volumenes!$B$11:$I$11)+SUMPRODUCT('Coef Fabricacion'!$T$45:$AA$45,Volumenes!$B$24:$I$24) -> 2616.801 | J27: =SUMPRODUCT('Coef Fabricacion'!$D$45:$K$45,Volumenes!$B$38:$I$38)+SUMPRODUCT('Coef Fabricacion'!$L$45:$S$45,Volumenes!$B$12:$I$12)+SUMPRODUCT('Coef Fabricacion'!$T$45:$AA$45,Volumenes!$B$25:$I$25) -> 3588.3574 | K27: =SUMPRODUCT('Coef Fabricacion'!$D$45:$K$45,Volumenes!$B$39:$I$39)+SUMPRODUCT('Coef Fabricacion'!$L$45:$S$45,Volumenes!$B$13:$I$13)+SUMPRODUCT('Coef Fabricacion'!$T$45:$AA$45,Volumenes!$B$26:$I$26) -> 4574.3934 | L27: =SUMPRODUCT('Coef Fabricacion'!$D$45:$K$45,Volumenes!$B$40:$I$40)+SUMPRODUCT('Coef Fabricacion'!$L$45:$S$45,Volumenes!$B$14:$I$14)+SUMPRODUCT('Coef Fabricacion'!$T$45:$AA$45,Volumenes!$B$27:$I$27) -> 5178.0316 | M27: =SUMPRODUCT('Coef Fabricacion'!$D$45:$K$45,Volumenes!$B$41:$I$41)+SUMPRODUCT('Coef Fabricacion'!$L$45:$S$45,Volumenes!$B$15:$I$15)+SUMPRODUCT('Coef Fabricacion'!$T$45:$AA$45,Volumenes!$B$28:$I$28) -> 5982.4767 | N27: =IF(F27=0,"—",M27/F27) -> 11.639216
A28: MP-24 | B28: Alambre MIG ER70S-6 Ø1,2 mm (carros 25–100 kg) | C28: kg | D28: =SUMPRODUCT('Coef Fabricacion'!$D$46:$K$46,Volumenes!$B$32:$I$32)+SUMPRODUCT('Coef Fabricacion'!$L$46:$S$46,Volumenes!$B$6:$I$6)+SUMPRODUCT('Coef Fabricacion'!$T$46:$AA$46,Volumenes!$B$19:$I$19) -> 57.321717 | E28: =SUMPRODUCT('Coef Fabricacion'!$D$46:$K$46,Volumenes!$B$33:$I$33)+SUMPRODUCT('Coef Fabricacion'!$L$46:$S$46,Volumenes!$B$7:$I$7)+SUMPRODUCT('Coef Fabricacion'!$T$46:$AA$46,Volumenes!$B$20:$I$20) -> 98.479174 | F28: =SUMPRODUCT('Coef Fabricacion'!$D$46:$K$46,Volumenes!$B$34:$I$34)+SUMPRODUCT('Coef Fabricacion'!$L$46:$S$46,Volumenes!$B$8:$I$8)+SUMPRODUCT('Coef Fabricacion'!$T$46:$AA$46,Volumenes!$B$21:$I$21) -> 151.94091 | G28: =SUMPRODUCT('Coef Fabricacion'!$D$46:$K$46,Volumenes!$B$35:$I$35)+SUMPRODUCT('Coef Fabricacion'!$L$46:$S$46,Volumenes!$B$9:$I$9)+SUMPRODUCT('Coef Fabricacion'!$T$46:$AA$46,Volumenes!$B$22:$I$22) -> 254.71509 | H28: =SUMPRODUCT('Coef Fabricacion'!$D$46:$K$46,Volumenes!$B$36:$I$36)+SUMPRODUCT('Coef Fabricacion'!$L$46:$S$46,Volumenes!$B$10:$I$10)+SUMPRODUCT('Coef Fabricacion'!$T$46:$AA$46,Volumenes!$B$23:$I$23) -> 420.27995 | I28: =SUMPRODUCT('Coef Fabricacion'!$D$46:$K$46,Volumenes!$B$37:$I$37)+SUMPRODUCT('Coef Fabricacion'!$L$46:$S$46,Volumenes!$B$11:$I$11)+SUMPRODUCT('Coef Fabricacion'!$T$46:$AA$46,Volumenes!$B$24:$I$24) -> 584.7491 | J28: =SUMPRODUCT('Coef Fabricacion'!$D$46:$K$46,Volumenes!$B$38:$I$38)+SUMPRODUCT('Coef Fabricacion'!$L$46:$S$46,Volumenes!$B$12:$I$12)+SUMPRODUCT('Coef Fabricacion'!$T$46:$AA$46,Volumenes!$B$25:$I$25) -> 782.05226 | K28: =SUMPRODUCT('Coef Fabricacion'!$D$46:$K$46,Volumenes!$B$39:$I$39)+SUMPRODUCT('Coef Fabricacion'!$L$46:$S$46,Volumenes!$B$13:$I$13)+SUMPRODUCT('Coef Fabricacion'!$T$46:$AA$46,Volumenes!$B$26:$I$26) -> 987.51041 | L28: =SUMPRODUCT('Coef Fabricacion'!$D$46:$K$46,Volumenes!$B$40:$I$40)+SUMPRODUCT('Coef Fabricacion'!$L$46:$S$46,Volumenes!$B$14:$I$14)+SUMPRODUCT('Coef Fabricacion'!$T$46:$AA$46,Volumenes!$B$27:$I$27) -> 1131.7372 | M28: =SUMPRODUCT('Coef Fabricacion'!$D$46:$K$46,Volumenes!$B$41:$I$41)+SUMPRODUCT('Coef Fabricacion'!$L$46:$S$46,Volumenes!$B$15:$I$15)+SUMPRODUCT('Coef Fabricacion'!$T$46:$AA$46,Volumenes!$B$28:$I$28) -> 1308.2652 | N28: =IF(F28=0,"—",M28/F28) -> 8.6103548
A29: MP-25 | B29: Gas de protección Ar + 8 % CO₂ (ARCAL 21) | C29: m³ | D29: =SUMPRODUCT('Coef Fabricacion'!$D$47:$K$47,Volumenes!$B$32:$I$32)+SUMPRODUCT('Coef Fabricacion'!$L$47:$S$47,Volumenes!$B$6:$I$6)+SUMPRODUCT('Coef Fabricacion'!$T$47:$AA$47,Volumenes!$B$19:$I$19) -> 201.55529 | E29: =SUMPRODUCT('Coef Fabricacion'!$D$47:$K$47,Volumenes!$B$33:$I$33)+SUMPRODUCT('Coef Fabricacion'!$L$47:$S$47,Volumenes!$B$7:$I$7)+SUMPRODUCT('Coef Fabricacion'!$T$47:$AA$47,Volumenes!$B$20:$I$20) -> 333.05808 | F29: =SUMPRODUCT('Coef Fabricacion'!$D$47:$K$47,Volumenes!$B$34:$I$34)+SUMPRODUCT('Coef Fabricacion'!$L$47:$S$47,Volumenes!$B$8:$I$8)+SUMPRODUCT('Coef Fabricacion'!$T$47:$AA$47,Volumenes!$B$21:$I$21) -> 638.09503 | G29: =SUMPRODUCT('Coef Fabricacion'!$D$47:$K$47,Volumenes!$B$35:$I$35)+SUMPRODUCT('Coef Fabricacion'!$L$47:$S$47,Volumenes!$B$9:$I$9)+SUMPRODUCT('Coef Fabricacion'!$T$47:$AA$47,Volumenes!$B$22:$I$22) -> 1307.9578 | H29: =SUMPRODUCT('Coef Fabricacion'!$D$47:$K$47,Volumenes!$B$36:$I$36)+SUMPRODUCT('Coef Fabricacion'!$L$47:$S$47,Volumenes!$B$10:$I$10)+SUMPRODUCT('Coef Fabricacion'!$T$47:$AA$47,Volumenes!$B$23:$I$23) -> 2256.7728 | I29: =SUMPRODUCT('Coef Fabricacion'!$D$47:$K$47,Volumenes!$B$37:$I$37)+SUMPRODUCT('Coef Fabricacion'!$L$47:$S$47,Volumenes!$B$11:$I$11)+SUMPRODUCT('Coef Fabricacion'!$T$47:$AA$47,Volumenes!$B$24:$I$24) -> 3167.8193 | J29: =SUMPRODUCT('Coef Fabricacion'!$D$47:$K$47,Volumenes!$B$38:$I$38)+SUMPRODUCT('Coef Fabricacion'!$L$47:$S$47,Volumenes!$B$12:$I$12)+SUMPRODUCT('Coef Fabricacion'!$T$47:$AA$47,Volumenes!$B$25:$I$25) -> 4335.3222 | K29: =SUMPRODUCT('Coef Fabricacion'!$D$47:$K$47,Volumenes!$B$39:$I$39)+SUMPRODUCT('Coef Fabricacion'!$L$47:$S$47,Volumenes!$B$13:$I$13)+SUMPRODUCT('Coef Fabricacion'!$T$47:$AA$47,Volumenes!$B$26:$I$26) -> 5522.438 | L29: =SUMPRODUCT('Coef Fabricacion'!$D$47:$K$47,Volumenes!$B$40:$I$40)+SUMPRODUCT('Coef Fabricacion'!$L$47:$S$47,Volumenes!$B$14:$I$14)+SUMPRODUCT('Coef Fabricacion'!$T$47:$AA$47,Volumenes!$B$27:$I$27) -> 6257.1962 | M29: =SUMPRODUCT('Coef Fabricacion'!$D$47:$K$47,Volumenes!$B$41:$I$41)+SUMPRODUCT('Coef Fabricacion'!$L$47:$S$47,Volumenes!$B$15:$I$15)+SUMPRODUCT('Coef Fabricacion'!$T$47:$AA$47,Volumenes!$B$28:$I$28) -> 7229.5418 | N29: =IF(F29=0,"—",M29/F29) -> 11.329883
A30: MP-26 | B30: Puntas de contacto y toberas MIG | C30: u | D30: =SUMPRODUCT('Coef Fabricacion'!$D$48:$K$48,Volumenes!$B$32:$I$32)+SUMPRODUCT('Coef Fabricacion'!$L$48:$S$48,Volumenes!$B$6:$I$6)+SUMPRODUCT('Coef Fabricacion'!$T$48:$AA$48,Volumenes!$B$19:$I$19) -> 54.016278 | E30: =SUMPRODUCT('Coef Fabricacion'!$D$48:$K$48,Volumenes!$B$33:$I$33)+SUMPRODUCT('Coef Fabricacion'!$L$48:$S$48,Volumenes!$B$7:$I$7)+SUMPRODUCT('Coef Fabricacion'!$T$48:$AA$48,Volumenes!$B$20:$I$20) -> 89.855906 | F30: =SUMPRODUCT('Coef Fabricacion'!$D$48:$K$48,Volumenes!$B$34:$I$34)+SUMPRODUCT('Coef Fabricacion'!$L$48:$S$48,Volumenes!$B$8:$I$8)+SUMPRODUCT('Coef Fabricacion'!$T$48:$AA$48,Volumenes!$B$21:$I$21) -> 166.4835 | G30: =SUMPRODUCT('Coef Fabricacion'!$D$48:$K$48,Volumenes!$B$35:$I$35)+SUMPRODUCT('Coef Fabricacion'!$L$48:$S$48,Volumenes!$B$9:$I$9)+SUMPRODUCT('Coef Fabricacion'!$T$48:$AA$48,Volumenes!$B$22:$I$22) -> 332.54153 | H30: =SUMPRODUCT('Coef Fabricacion'!$D$48:$K$48,Volumenes!$B$36:$I$36)+SUMPRODUCT('Coef Fabricacion'!$L$48:$S$48,Volumenes!$B$10:$I$10)+SUMPRODUCT('Coef Fabricacion'!$T$48:$AA$48,Volumenes!$B$23:$I$23) -> 570.79338 | I30: =SUMPRODUCT('Coef Fabricacion'!$D$48:$K$48,Volumenes!$B$37:$I$37)+SUMPRODUCT('Coef Fabricacion'!$L$48:$S$48,Volumenes!$B$11:$I$11)+SUMPRODUCT('Coef Fabricacion'!$T$48:$AA$48,Volumenes!$B$24:$I$24) -> 800.38753 | J30: =SUMPRODUCT('Coef Fabricacion'!$D$48:$K$48,Volumenes!$B$38:$I$38)+SUMPRODUCT('Coef Fabricacion'!$L$48:$S$48,Volumenes!$B$12:$I$12)+SUMPRODUCT('Coef Fabricacion'!$T$48:$AA$48,Volumenes!$B$25:$I$25) -> 1092.6024 | K30: =SUMPRODUCT('Coef Fabricacion'!$D$48:$K$48,Volumenes!$B$39:$I$39)+SUMPRODUCT('Coef Fabricacion'!$L$48:$S$48,Volumenes!$B$13:$I$13)+SUMPRODUCT('Coef Fabricacion'!$T$48:$AA$48,Volumenes!$B$26:$I$26) -> 1390.476 | L30: =SUMPRODUCT('Coef Fabricacion'!$D$48:$K$48,Volumenes!$B$40:$I$40)+SUMPRODUCT('Coef Fabricacion'!$L$48:$S$48,Volumenes!$B$14:$I$14)+SUMPRODUCT('Coef Fabricacion'!$T$48:$AA$48,Volumenes!$B$27:$I$27) -> 1577.4422 | M30: =SUMPRODUCT('Coef Fabricacion'!$D$48:$K$48,Volumenes!$B$41:$I$41)+SUMPRODUCT('Coef Fabricacion'!$L$48:$S$48,Volumenes!$B$15:$I$15)+SUMPRODUCT('Coef Fabricacion'!$T$48:$AA$48,Volumenes!$B$28:$I$28) -> 1822.6855 | N30: =IF(F30=0,"—",M30/F30) -> 10.948145
A31: MP-27 | B31: Discos de amolado y corte Ø115 mm | C31: u | D31: =SUMPRODUCT('Coef Fabricacion'!$D$49:$K$49,Volumenes!$B$32:$I$32)+SUMPRODUCT('Coef Fabricacion'!$L$49:$S$49,Volumenes!$B$6:$I$6)+SUMPRODUCT('Coef Fabricacion'!$T$49:$AA$49,Volumenes!$B$19:$I$19) -> 46.386667 | E31: =SUMPRODUCT('Coef Fabricacion'!$D$49:$K$49,Volumenes!$B$33:$I$33)+SUMPRODUCT('Coef Fabricacion'!$L$49:$S$49,Volumenes!$B$7:$I$7)+SUMPRODUCT('Coef Fabricacion'!$T$49:$AA$49,Volumenes!$B$20:$I$20) -> 73.086667 | F31: =SUMPRODUCT('Coef Fabricacion'!$D$49:$K$49,Volumenes!$B$34:$I$34)+SUMPRODUCT('Coef Fabricacion'!$L$49:$S$49,Volumenes!$B$8:$I$8)+SUMPRODUCT('Coef Fabricacion'!$T$49:$AA$49,Volumenes!$B$21:$I$21) -> 153.84667 | G31: =SUMPRODUCT('Coef Fabricacion'!$D$49:$K$49,Volumenes!$B$35:$I$35)+SUMPRODUCT('Coef Fabricacion'!$L$49:$S$49,Volumenes!$B$9:$I$9)+SUMPRODUCT('Coef Fabricacion'!$T$49:$AA$49,Volumenes!$B$22:$I$22) -> 339.72 | H31: =SUMPRODUCT('Coef Fabricacion'!$D$49:$K$49,Volumenes!$B$36:$I$36)+SUMPRODUCT('Coef Fabricacion'!$L$49:$S$49,Volumenes!$B$10:$I$10)+SUMPRODUCT('Coef Fabricacion'!$T$49:$AA$49,Volumenes!$B$23:$I$23) -> 592.68667 | I31: =SUMPRODUCT('Coef Fabricacion'!$D$49:$K$49,Volumenes!$B$37:$I$37)+SUMPRODUCT('Coef Fabricacion'!$L$49:$S$49,Volumenes!$B$11:$I$11)+SUMPRODUCT('Coef Fabricacion'!$T$49:$AA$49,Volumenes!$B$24:$I$24) -> 832.66667 | J31: =SUMPRODUCT('Coef Fabricacion'!$D$49:$K$49,Volumenes!$B$38:$I$38)+SUMPRODUCT('Coef Fabricacion'!$L$49:$S$49,Volumenes!$B$12:$I$12)+SUMPRODUCT('Coef Fabricacion'!$T$49:$AA$49,Volumenes!$B$25:$I$25) -> 1149.02 | K31: =SUMPRODUCT('Coef Fabricacion'!$D$49:$K$49,Volumenes!$B$39:$I$39)+SUMPRODUCT('Coef Fabricacion'!$L$49:$S$49,Volumenes!$B$13:$I$13)+SUMPRODUCT('Coef Fabricacion'!$T$49:$AA$49,Volumenes!$B$26:$I$26) -> 1468.6133 | L31: =SUMPRODUCT('Coef Fabricacion'!$D$49:$K$49,Volumenes!$B$40:$I$40)+SUMPRODUCT('Coef Fabricacion'!$L$49:$S$49,Volumenes!$B$14:$I$14)+SUMPRODUCT('Coef Fabricacion'!$T$49:$AA$49,Volumenes!$B$27:$I$27) -> 1657.72 | M31: =SUMPRODUCT('Coef Fabricacion'!$D$49:$K$49,Volumenes!$B$41:$I$41)+SUMPRODUCT('Coef Fabricacion'!$L$49:$S$49,Volumenes!$B$15:$I$15)+SUMPRODUCT('Coef Fabricacion'!$T$49:$AA$49,Volumenes!$B$28:$I$28) -> 1915.5533 | N31: =IF(F31=0,"—",M31/F31) -> 12.451055
A32: MP-28 | B32: Granalla de acero S330/S390 (reposición) | C32: kg | D32: =SUMPRODUCT('Coef Fabricacion'!$D$50:$K$50,Volumenes!$B$32:$I$32)+SUMPRODUCT('Coef Fabricacion'!$L$50:$S$50,Volumenes!$B$6:$I$6)+SUMPRODUCT('Coef Fabricacion'!$T$50:$AA$50,Volumenes!$B$19:$I$19) -> 195.29557 | E32: =SUMPRODUCT('Coef Fabricacion'!$D$50:$K$50,Volumenes!$B$33:$I$33)+SUMPRODUCT('Coef Fabricacion'!$L$50:$S$50,Volumenes!$B$7:$I$7)+SUMPRODUCT('Coef Fabricacion'!$T$50:$AA$50,Volumenes!$B$20:$I$20) -> 349.72906 | F32: =SUMPRODUCT('Coef Fabricacion'!$D$50:$K$50,Volumenes!$B$34:$I$34)+SUMPRODUCT('Coef Fabricacion'!$L$50:$S$50,Volumenes!$B$8:$I$8)+SUMPRODUCT('Coef Fabricacion'!$T$50:$AA$50,Volumenes!$B$21:$I$21) -> 606.133 | G32: =SUMPRODUCT('Coef Fabricacion'!$D$50:$K$50,Volumenes!$B$35:$I$35)+SUMPRODUCT('Coef Fabricacion'!$L$50:$S$50,Volumenes!$B$9:$I$9)+SUMPRODUCT('Coef Fabricacion'!$T$50:$AA$50,Volumenes!$B$22:$I$22) -> 1122.6355 | H32: =SUMPRODUCT('Coef Fabricacion'!$D$50:$K$50,Volumenes!$B$36:$I$36)+SUMPRODUCT('Coef Fabricacion'!$L$50:$S$50,Volumenes!$B$10:$I$10)+SUMPRODUCT('Coef Fabricacion'!$T$50:$AA$50,Volumenes!$B$23:$I$23) -> 1905.7389 | I32: =SUMPRODUCT('Coef Fabricacion'!$D$50:$K$50,Volumenes!$B$37:$I$37)+SUMPRODUCT('Coef Fabricacion'!$L$50:$S$50,Volumenes!$B$11:$I$11)+SUMPRODUCT('Coef Fabricacion'!$T$50:$AA$50,Volumenes!$B$24:$I$24) -> 2675.8374 | J32: =SUMPRODUCT('Coef Fabricacion'!$D$50:$K$50,Volumenes!$B$38:$I$38)+SUMPRODUCT('Coef Fabricacion'!$L$50:$S$50,Volumenes!$B$12:$I$12)+SUMPRODUCT('Coef Fabricacion'!$T$50:$AA$50,Volumenes!$B$25:$I$25) -> 3607.7586 | K32: =SUMPRODUCT('Coef Fabricacion'!$D$50:$K$50,Volumenes!$B$39:$I$39)+SUMPRODUCT('Coef Fabricacion'!$L$50:$S$50,Volumenes!$B$13:$I$13)+SUMPRODUCT('Coef Fabricacion'!$T$50:$AA$50,Volumenes!$B$26:$I$26) -> 4567.9064 | L32: =SUMPRODUCT('Coef Fabricacion'!$D$50:$K$50,Volumenes!$B$40:$I$40)+SUMPRODUCT('Coef Fabricacion'!$L$50:$S$50,Volumenes!$B$14:$I$14)+SUMPRODUCT('Coef Fabricacion'!$T$50:$AA$50,Volumenes!$B$27:$I$27) -> 5215.4926 | M32: =SUMPRODUCT('Coef Fabricacion'!$D$50:$K$50,Volumenes!$B$41:$I$41)+SUMPRODUCT('Coef Fabricacion'!$L$50:$S$50,Volumenes!$B$15:$I$15)+SUMPRODUCT('Coef Fabricacion'!$T$50:$AA$50,Volumenes!$B$28:$I$28) -> 6030.4433 | N32: =IF(F32=0,"—",M32/F32) -> 9.949043
A33: MP-29 | B33: Desengrasante alcalino (pretratamiento) | C33: L | D33: =SUMPRODUCT('Coef Fabricacion'!$D$51:$K$51,Volumenes!$B$32:$I$32)+SUMPRODUCT('Coef Fabricacion'!$L$51:$S$51,Volumenes!$B$6:$I$6)+SUMPRODUCT('Coef Fabricacion'!$T$51:$AA$51,Volumenes!$B$19:$I$19) -> 9.6825193 | E33: =SUMPRODUCT('Coef Fabricacion'!$D$51:$K$51,Volumenes!$B$33:$I$33)+SUMPRODUCT('Coef Fabricacion'!$L$51:$S$51,Volumenes!$B$7:$I$7)+SUMPRODUCT('Coef Fabricacion'!$T$51:$AA$51,Volumenes!$B$20:$I$20) -> 15.99144 | F33: =SUMPRODUCT('Coef Fabricacion'!$D$51:$K$51,Volumenes!$B$34:$I$34)+SUMPRODUCT('Coef Fabricacion'!$L$51:$S$51,Volumenes!$B$8:$I$8)+SUMPRODUCT('Coef Fabricacion'!$T$51:$AA$51,Volumenes!$B$21:$I$21) -> 31.087766 | G33: =SUMPRODUCT('Coef Fabricacion'!$D$51:$K$51,Volumenes!$B$35:$I$35)+SUMPRODUCT('Coef Fabricacion'!$L$51:$S$51,Volumenes!$B$9:$I$9)+SUMPRODUCT('Coef Fabricacion'!$T$51:$AA$51,Volumenes!$B$22:$I$22) -> 64.265497 | H33: =SUMPRODUCT('Coef Fabricacion'!$D$51:$K$51,Volumenes!$B$36:$I$36)+SUMPRODUCT('Coef Fabricacion'!$L$51:$S$51,Volumenes!$B$10:$I$10)+SUMPRODUCT('Coef Fabricacion'!$T$51:$AA$51,Volumenes!$B$23:$I$23) -> 111.20544 | I33: =SUMPRODUCT('Coef Fabricacion'!$D$51:$K$51,Volumenes!$B$37:$I$37)+SUMPRODUCT('Coef Fabricacion'!$L$51:$S$51,Volumenes!$B$11:$I$11)+SUMPRODUCT('Coef Fabricacion'!$T$51:$AA$51,Volumenes!$B$24:$I$24) -> 156.21086 | J33: =SUMPRODUCT('Coef Fabricacion'!$D$51:$K$51,Volumenes!$B$38:$I$38)+SUMPRODUCT('Coef Fabricacion'!$L$51:$S$51,Volumenes!$B$12:$I$12)+SUMPRODUCT('Coef Fabricacion'!$T$51:$AA$51,Volumenes!$B$25:$I$25) -> 213.94888 | K33: =SUMPRODUCT('Coef Fabricacion'!$D$51:$K$51,Volumenes!$B$39:$I$39)+SUMPRODUCT('Coef Fabricacion'!$L$51:$S$51,Volumenes!$B$13:$I$13)+SUMPRODUCT('Coef Fabricacion'!$T$51:$AA$51,Volumenes!$B$26:$I$26) -> 272.57255 | L33: =SUMPRODUCT('Coef Fabricacion'!$D$51:$K$51,Volumenes!$B$40:$I$40)+SUMPRODUCT('Coef Fabricacion'!$L$51:$S$51,Volumenes!$B$14:$I$14)+SUMPRODUCT('Coef Fabricacion'!$T$51:$AA$51,Volumenes!$B$27:$I$27) -> 308.62905 | M33: =SUMPRODUCT('Coef Fabricacion'!$D$51:$K$51,Volumenes!$B$41:$I$41)+SUMPRODUCT('Coef Fabricacion'!$L$51:$S$51,Volumenes!$B$15:$I$15)+SUMPRODUCT('Coef Fabricacion'!$T$51:$AA$51,Volumenes!$B$28:$I$28) -> 356.44305 | N33: =IF(F33=0,"—",M33/F33) -> 11.465702
A34: MP-30 | B34: Fosfatizante (fosfato de hierro) | C34: L | D34: =SUMPRODUCT('Coef Fabricacion'!$D$52:$K$52,Volumenes!$B$32:$I$32)+SUMPRODUCT('Coef Fabricacion'!$L$52:$S$52,Volumenes!$B$6:$I$6)+SUMPRODUCT('Coef Fabricacion'!$T$52:$AA$52,Volumenes!$B$19:$I$19) -> 9.6825193 | E34: =SUMPRODUCT('Coef Fabricacion'!$D$52:$K$52,Volumenes!$B$33:$I$33)+SUMPRODUCT('Coef Fabricacion'!$L$52:$S$52,Volumenes!$B$7:$I$7)+SUMPRODUCT('Coef Fabricacion'!$T$52:$AA$52,Volumenes!$B$20:$I$20) -> 15.99144 | F34: =SUMPRODUCT('Coef Fabricacion'!$D$52:$K$52,Volumenes!$B$34:$I$34)+SUMPRODUCT('Coef Fabricacion'!$L$52:$S$52,Volumenes!$B$8:$I$8)+SUMPRODUCT('Coef Fabricacion'!$T$52:$AA$52,Volumenes!$B$21:$I$21) -> 31.087766 | G34: =SUMPRODUCT('Coef Fabricacion'!$D$52:$K$52,Volumenes!$B$35:$I$35)+SUMPRODUCT('Coef Fabricacion'!$L$52:$S$52,Volumenes!$B$9:$I$9)+SUMPRODUCT('Coef Fabricacion'!$T$52:$AA$52,Volumenes!$B$22:$I$22) -> 64.265497 | H34: =SUMPRODUCT('Coef Fabricacion'!$D$52:$K$52,Volumenes!$B$36:$I$36)+SUMPRODUCT('Coef Fabricacion'!$L$52:$S$52,Volumenes!$B$10:$I$10)+SUMPRODUCT('Coef Fabricacion'!$T$52:$AA$52,Volumenes!$B$23:$I$23) -> 111.20544 | I34: =SUMPRODUCT('Coef Fabricacion'!$D$52:$K$52,Volumenes!$B$37:$I$37)+SUMPRODUCT('Coef Fabricacion'!$L$52:$S$52,Volumenes!$B$11:$I$11)+SUMPRODUCT('Coef Fabricacion'!$T$52:$AA$52,Volumenes!$B$24:$I$24) -> 156.21086 | J34: =SUMPRODUCT('Coef Fabricacion'!$D$52:$K$52,Volumenes!$B$38:$I$38)+SUMPRODUCT('Coef Fabricacion'!$L$52:$S$52,Volumenes!$B$12:$I$12)+SUMPRODUCT('Coef Fabricacion'!$T$52:$AA$52,Volumenes!$B$25:$I$25) -> 213.94888 | K34: =SUMPRODUCT('Coef Fabricacion'!$D$52:$K$52,Volumenes!$B$39:$I$39)+SUMPRODUCT('Coef Fabricacion'!$L$52:$S$52,Volumenes!$B$13:$I$13)+SUMPRODUCT('Coef Fabricacion'!$T$52:$AA$52,Volumenes!$B$26:$I$26) -> 272.57255 | L34: =SUMPRODUCT('Coef Fabricacion'!$D$52:$K$52,Volumenes!$B$40:$I$40)+SUMPRODUCT('Coef Fabricacion'!$L$52:$S$52,Volumenes!$B$14:$I$14)+SUMPRODUCT('Coef Fabricacion'!$T$52:$AA$52,Volumenes!$B$27:$I$27) -> 308.62905 | M34: =SUMPRODUCT('Coef Fabricacion'!$D$52:$K$52,Volumenes!$B$41:$I$41)+SUMPRODUCT('Coef Fabricacion'!$L$52:$S$52,Volumenes!$B$15:$I$15)+SUMPRODUCT('Coef Fabricacion'!$T$52:$AA$52,Volumenes!$B$28:$I$28) -> 356.44305 | N34: =IF(F34=0,"—",M34/F34) -> 11.465702
A35: MP-31 | B35: Pintura en polvo poliéster RAL 3000 (rojo) | C35: kg | D35: =SUMPRODUCT('Coef Fabricacion'!$D$53:$K$53,Volumenes!$B$32:$I$32)+SUMPRODUCT('Coef Fabricacion'!$L$53:$S$53,Volumenes!$B$6:$I$6)+SUMPRODUCT('Coef Fabricacion'!$T$53:$AA$53,Volumenes!$B$19:$I$19) -> 135.55527 | E35: =SUMPRODUCT('Coef Fabricacion'!$D$53:$K$53,Volumenes!$B$33:$I$33)+SUMPRODUCT('Coef Fabricacion'!$L$53:$S$53,Volumenes!$B$7:$I$7)+SUMPRODUCT('Coef Fabricacion'!$T$53:$AA$53,Volumenes!$B$20:$I$20) -> 223.88016 | F35: =SUMPRODUCT('Coef Fabricacion'!$D$53:$K$53,Volumenes!$B$34:$I$34)+SUMPRODUCT('Coef Fabricacion'!$L$53:$S$53,Volumenes!$B$8:$I$8)+SUMPRODUCT('Coef Fabricacion'!$T$53:$AA$53,Volumenes!$B$21:$I$21) -> 435.22873 | G35: =SUMPRODUCT('Coef Fabricacion'!$D$53:$K$53,Volumenes!$B$35:$I$35)+SUMPRODUCT('Coef Fabricacion'!$L$53:$S$53,Volumenes!$B$9:$I$9)+SUMPRODUCT('Coef Fabricacion'!$T$53:$AA$53,Volumenes!$B$22:$I$22) -> 899.71696 | H35: =SUMPRODUCT('Coef Fabricacion'!$D$53:$K$53,Volumenes!$B$36:$I$36)+SUMPRODUCT('Coef Fabricacion'!$L$53:$S$53,Volumenes!$B$10:$I$10)+SUMPRODUCT('Coef Fabricacion'!$T$53:$AA$53,Volumenes!$B$23:$I$23) -> 1556.8761 | I35: =SUMPRODUCT('Coef Fabricacion'!$D$53:$K$53,Volumenes!$B$37:$I$37)+SUMPRODUCT('Coef Fabricacion'!$L$53:$S$53,Volumenes!$B$11:$I$11)+SUMPRODUCT('Coef Fabricacion'!$T$53:$AA$53,Volumenes!$B$24:$I$24) -> 2186.952 | J35: =SUMPRODUCT('Coef Fabricacion'!$D$53:$K$53,Volumenes!$B$38:$I$38)+SUMPRODUCT('Coef Fabricacion'!$L$53:$S$53,Volumenes!$B$12:$I$12)+SUMPRODUCT('Coef Fabricacion'!$T$53:$AA$53,Volumenes!$B$25:$I$25) -> 2995.2843 | K35: =SUMPRODUCT('Coef Fabricacion'!$D$53:$K$53,Volumenes!$B$39:$I$39)+SUMPRODUCT('Coef Fabricacion'!$L$53:$S$53,Volumenes!$B$13:$I$13)+SUMPRODUCT('Coef Fabricacion'!$T$53:$AA$53,Volumenes!$B$26:$I$26) -> 3816.0157 | L35: =SUMPRODUCT('Coef Fabricacion'!$D$53:$K$53,Volumenes!$B$40:$I$40)+SUMPRODUCT('Coef Fabricacion'!$L$53:$S$53,Volumenes!$B$14:$I$14)+SUMPRODUCT('Coef Fabricacion'!$T$53:$AA$53,Volumenes!$B$27:$I$27) -> 4320.8066 | M35: =SUMPRODUCT('Coef Fabricacion'!$D$53:$K$53,Volumenes!$B$41:$I$41)+SUMPRODUCT('Coef Fabricacion'!$L$53:$S$53,Volumenes!$B$15:$I$15)+SUMPRODUCT('Coef Fabricacion'!$T$53:$AA$53,Volumenes!$B$28:$I$28) -> 4990.2028 | N35: =IF(F35=0,"—",M35/F35) -> 11.465702
A36: MP-32 | B36: Tapones de enmascarado (silicona) para rosca | C36: u | D36: =SUMPRODUCT('Coef Fabricacion'!$D$54:$K$54,Volumenes!$B$32:$I$32)+SUMPRODUCT('Coef Fabricacion'!$L$54:$S$54,Volumenes!$B$6:$I$6)+SUMPRODUCT('Coef Fabricacion'!$T$54:$AA$54,Volumenes!$B$19:$I$19) -> 136.44 | E36: =SUMPRODUCT('Coef Fabricacion'!$D$54:$K$54,Volumenes!$B$33:$I$33)+SUMPRODUCT('Coef Fabricacion'!$L$54:$S$54,Volumenes!$B$7:$I$7)+SUMPRODUCT('Coef Fabricacion'!$T$54:$AA$54,Volumenes!$B$20:$I$20) -> 214.6 | F36: =SUMPRODUCT('Coef Fabricacion'!$D$54:$K$54,Volumenes!$B$34:$I$34)+SUMPRODUCT('Coef Fabricacion'!$L$54:$S$54,Volumenes!$B$8:$I$8)+SUMPRODUCT('Coef Fabricacion'!$T$54:$AA$54,Volumenes!$B$21:$I$21) -> 454.34 | G36: =SUMPRODUCT('Coef Fabricacion'!$D$54:$K$54,Volumenes!$B$35:$I$35)+SUMPRODUCT('Coef Fabricacion'!$L$54:$S$54,Volumenes!$B$9:$I$9)+SUMPRODUCT('Coef Fabricacion'!$T$54:$AA$54,Volumenes!$B$22:$I$22) -> 1007.1 | H36: =SUMPRODUCT('Coef Fabricacion'!$D$54:$K$54,Volumenes!$B$36:$I$36)+SUMPRODUCT('Coef Fabricacion'!$L$54:$S$54,Volumenes!$B$10:$I$10)+SUMPRODUCT('Coef Fabricacion'!$T$54:$AA$54,Volumenes!$B$23:$I$23) -> 1758.14 | I36: =SUMPRODUCT('Coef Fabricacion'!$D$54:$K$54,Volumenes!$B$37:$I$37)+SUMPRODUCT('Coef Fabricacion'!$L$54:$S$54,Volumenes!$B$11:$I$11)+SUMPRODUCT('Coef Fabricacion'!$T$54:$AA$54,Volumenes!$B$24:$I$24) -> 2470.26 | J36: =SUMPRODUCT('Coef Fabricacion'!$D$54:$K$54,Volumenes!$B$38:$I$38)+SUMPRODUCT('Coef Fabricacion'!$L$54:$S$54,Volumenes!$B$12:$I$12)+SUMPRODUCT('Coef Fabricacion'!$T$54:$AA$54,Volumenes!$B$25:$I$25) -> 3409.98 | K36: =SUMPRODUCT('Coef Fabricacion'!$D$54:$K$54,Volumenes!$B$39:$I$39)+SUMPRODUCT('Coef Fabricacion'!$L$54:$S$54,Volumenes!$B$13:$I$13)+SUMPRODUCT('Coef Fabricacion'!$T$54:$AA$54,Volumenes!$B$26:$I$26) -> 4359.04 | L36: =SUMPRODUCT('Coef Fabricacion'!$D$54:$K$54,Volumenes!$B$40:$I$40)+SUMPRODUCT('Coef Fabricacion'!$L$54:$S$54,Volumenes!$B$14:$I$14)+SUMPRODUCT('Coef Fabricacion'!$T$54:$AA$54,Volumenes!$B$27:$I$27) -> 4919.52 | M36: =SUMPRODUCT('Coef Fabricacion'!$D$54:$K$54,Volumenes!$B$41:$I$41)+SUMPRODUCT('Coef Fabricacion'!$L$54:$S$54,Volumenes!$B$15:$I$15)+SUMPRODUCT('Coef Fabricacion'!$T$54:$AA$54,Volumenes!$B$28:$I$28) -> 5684.66 | N36: =IF(F36=0,"—",M36/F36) -> 12.511907
A37: MP-33 | B37: Polvo químico ABC (MAP ≥55 %, IRAM 3569) | C37: kg | D37: =SUMPRODUCT('Coef Fabricacion'!$D$55:$K$55,Volumenes!$B$32:$I$32)+SUMPRODUCT('Coef Fabricacion'!$L$55:$S$55,Volumenes!$B$6:$I$6)+SUMPRODUCT('Coef Fabricacion'!$T$55:$AA$55,Volumenes!$B$19:$I$19)+SUMPRODUCT('Coef Recargas'!$D$29:$T$29,Volumenes!$B$45:$R$45) -> 25781.49 | E37: =SUMPRODUCT('Coef Fabricacion'!$D$55:$K$55,Volumenes!$B$33:$I$33)+SUMPRODUCT('Coef Fabricacion'!$L$55:$S$55,Volumenes!$B$7:$I$7)+SUMPRODUCT('Coef Fabricacion'!$T$55:$AA$55,Volumenes!$B$20:$I$20)+SUMPRODUCT('Coef Recargas'!$D$29:$T$29,Volumenes!$B$46:$R$46) -> 47812.42 | F37: =SUMPRODUCT('Coef Fabricacion'!$D$55:$K$55,Volumenes!$B$34:$I$34)+SUMPRODUCT('Coef Fabricacion'!$L$55:$S$55,Volumenes!$B$8:$I$8)+SUMPRODUCT('Coef Fabricacion'!$T$55:$AA$55,Volumenes!$B$21:$I$21)+SUMPRODUCT('Coef Recargas'!$D$29:$T$29,Volumenes!$B$47:$R$47) -> 67924.27 | G37: =SUMPRODUCT('Coef Fabricacion'!$D$55:$K$55,Volumenes!$B$35:$I$35)+SUMPRODUCT('Coef Fabricacion'!$L$55:$S$55,Volumenes!$B$9:$I$9)+SUMPRODUCT('Coef Fabricacion'!$T$55:$AA$55,Volumenes!$B$22:$I$22)+SUMPRODUCT('Coef Recargas'!$D$29:$T$29,Volumenes!$B$48:$R$48) -> 98613.245 | H37: =SUMPRODUCT('Coef Fabricacion'!$D$55:$K$55,Volumenes!$B$36:$I$36)+SUMPRODUCT('Coef Fabricacion'!$L$55:$S$55,Volumenes!$B$10:$I$10)+SUMPRODUCT('Coef Fabricacion'!$T$55:$AA$55,Volumenes!$B$23:$I$23)+SUMPRODUCT('Coef Recargas'!$D$29:$T$29,Volumenes!$B$49:$R$49) -> 151284.91 | I37: =SUMPRODUCT('Coef Fabricacion'!$D$55:$K$55,Volumenes!$B$37:$I$37)+SUMPRODUCT('Coef Fabricacion'!$L$55:$S$55,Volumenes!$B$11:$I$11)+SUMPRODUCT('Coef Fabricacion'!$T$55:$AA$55,Volumenes!$B$24:$I$24)+SUMPRODUCT('Coef Recargas'!$D$29:$T$29,Volumenes!$B$50:$R$50) -> 203459.08 | J37: =SUMPRODUCT('Coef Fabricacion'!$D$55:$K$55,Volumenes!$B$38:$I$38)+SUMPRODUCT('Coef Fabricacion'!$L$55:$S$55,Volumenes!$B$12:$I$12)+SUMPRODUCT('Coef Fabricacion'!$T$55:$AA$55,Volumenes!$B$25:$I$25)+SUMPRODUCT('Coef Recargas'!$D$29:$T$29,Volumenes!$B$51:$R$51) -> 259470.95 | K37: =SUMPRODUCT('Coef Fabricacion'!$D$55:$K$55,Volumenes!$B$39:$I$39)+SUMPRODUCT('Coef Fabricacion'!$L$55:$S$55,Volumenes!$B$13:$I$13)+SUMPRODUCT('Coef Fabricacion'!$T$55:$AA$55,Volumenes!$B$26:$I$26)+SUMPRODUCT('Coef Recargas'!$D$29:$T$29,Volumenes!$B$52:$R$52) -> 313626.2 | L37: =SUMPRODUCT('Coef Fabricacion'!$D$55:$K$55,Volumenes!$B$40:$I$40)+SUMPRODUCT('Coef Fabricacion'!$L$55:$S$55,Volumenes!$B$14:$I$14)+SUMPRODUCT('Coef Fabricacion'!$T$55:$AA$55,Volumenes!$B$27:$I$27)+SUMPRODUCT('Coef Recargas'!$D$29:$T$29,Volumenes!$B$53:$R$53) -> 357370.01 | M37: =SUMPRODUCT('Coef Fabricacion'!$D$55:$K$55,Volumenes!$B$41:$I$41)+SUMPRODUCT('Coef Fabricacion'!$L$55:$S$55,Volumenes!$B$15:$I$15)+SUMPRODUCT('Coef Fabricacion'!$T$55:$AA$55,Volumenes!$B$28:$I$28)+SUMPRODUCT('Coef Recargas'!$D$29:$T$29,Volumenes!$B$54:$R$54) -> 403509.98 | N37: =IF(F37=0,"—",M37/F37) -> 5.9405862
A38: MP-34 | B38: Nitrógeno seco (≥99,8 %, rocío ≤ −40 °C) | C38: m³ | D38: =SUMPRODUCT('Coef Fabricacion'!$D$56:$K$56,Volumenes!$B$32:$I$32)+SUMPRODUCT('Coef Fabricacion'!$L$56:$S$56,Volumenes!$B$6:$I$6)+SUMPRODUCT('Coef Fabricacion'!$T$56:$AA$56,Volumenes!$B$19:$I$19)+SUMPRODUCT('Coef Recargas'!$D$30:$T$30,Volumenes!$B$45:$R$45) -> 211.35589 | E38: =SUMPRODUCT('Coef Fabricacion'!$D$56:$K$56,Volumenes!$B$33:$I$33)+SUMPRODUCT('Coef Fabricacion'!$L$56:$S$56,Volumenes!$B$7:$I$7)+SUMPRODUCT('Coef Fabricacion'!$T$56:$AA$56,Volumenes!$B$20:$I$20)+SUMPRODUCT('Coef Recargas'!$D$30:$T$30,Volumenes!$B$46:$R$46) -> 485.29421 | F38: =SUMPRODUCT('Coef Fabricacion'!$D$56:$K$56,Volumenes!$B$34:$I$34)+SUMPRODUCT('Coef Fabricacion'!$L$56:$S$56,Volumenes!$B$8:$I$8)+SUMPRODUCT('Coef Fabricacion'!$T$56:$AA$56,Volumenes!$B$21:$I$21)+SUMPRODUCT('Coef Recargas'!$D$30:$T$30,Volumenes!$B$47:$R$47) -> 807.08074 | G38: =SUMPRODUCT('Coef Fabricacion'!$D$56:$K$56,Volumenes!$B$35:$I$35)+SUMPRODUCT('Coef Fabricacion'!$L$56:$S$56,Volumenes!$B$9:$I$9)+SUMPRODUCT('Coef Fabricacion'!$T$56:$AA$56,Volumenes!$B$22:$I$22)+SUMPRODUCT('Coef Recargas'!$D$30:$T$30,Volumenes!$B$48:$R$48) -> 1310.2988 | H38: =SUMPRODUCT('Coef Fabricacion'!$D$56:$K$56,Volumenes!$B$36:$I$36)+SUMPRODUCT('Coef Fabricacion'!$L$56:$S$56,Volumenes!$B$10:$I$10)+SUMPRODUCT('Coef Fabricacion'!$T$56:$AA$56,Volumenes!$B$23:$I$23)+SUMPRODUCT('Coef Recargas'!$D$30:$T$30,Volumenes!$B$49:$R$49) -> 1956.6001 | I38: =SUMPRODUCT('Coef Fabricacion'!$D$56:$K$56,Volumenes!$B$37:$I$37)+SUMPRODUCT('Coef Fabricacion'!$L$56:$S$56,Volumenes!$B$11:$I$11)+SUMPRODUCT('Coef Fabricacion'!$T$56:$AA$56,Volumenes!$B$24:$I$24)+SUMPRODUCT('Coef Recargas'!$D$30:$T$30,Volumenes!$B$50:$R$50) -> 2624.9907 | J38: =SUMPRODUCT('Coef Fabricacion'!$D$56:$K$56,Volumenes!$B$38:$I$38)+SUMPRODUCT('Coef Fabricacion'!$L$56:$S$56,Volumenes!$B$12:$I$12)+SUMPRODUCT('Coef Fabricacion'!$T$56:$AA$56,Volumenes!$B$25:$I$25)+SUMPRODUCT('Coef Recargas'!$D$30:$T$30,Volumenes!$B$51:$R$51) -> 3293.1125 | K38: =SUMPRODUCT('Coef Fabricacion'!$D$56:$K$56,Volumenes!$B$39:$I$39)+SUMPRODUCT('Coef Fabricacion'!$L$56:$S$56,Volumenes!$B$13:$I$13)+SUMPRODUCT('Coef Fabricacion'!$T$56:$AA$56,Volumenes!$B$26:$I$26)+SUMPRODUCT('Coef Recargas'!$D$30:$T$30,Volumenes!$B$52:$R$52) -> 3846.2996 | L38: =SUMPRODUCT('Coef Fabricacion'!$D$56:$K$56,Volumenes!$B$40:$I$40)+SUMPRODUCT('Coef Fabricacion'!$L$56:$S$56,Volumenes!$B$14:$I$14)+SUMPRODUCT('Coef Fabricacion'!$T$56:$AA$56,Volumenes!$B$27:$I$27)+SUMPRODUCT('Coef Recargas'!$D$30:$T$30,Volumenes!$B$53:$R$53) -> 4279.1026 | M38: =SUMPRODUCT('Coef Fabricacion'!$D$56:$K$56,Volumenes!$B$41:$I$41)+SUMPRODUCT('Coef Fabricacion'!$L$56:$S$56,Volumenes!$B$15:$I$15)+SUMPRODUCT('Coef Fabricacion'!$T$56:$AA$56,Volumenes!$B$28:$I$28)+SUMPRODUCT('Coef Recargas'!$D$30:$T$30,Volumenes!$B$54:$R$54) -> 4730.3794 | N38: =IF(F38=0,"—",M38/F38) -> 5.8610981
A39: MP-35 | B39: Polvo químico BC (recargas) | C39: kg | D39: =SUMPRODUCT('Coef Recargas'!$D$31:$T$31,Volumenes!$B$45:$R$45) -> 2.5 | E39: =SUMPRODUCT('Coef Recargas'!$D$31:$T$31,Volumenes!$B$46:$R$46) -> 20 | F39: =SUMPRODUCT('Coef Recargas'!$D$31:$T$31,Volumenes!$B$47:$R$47) -> 37.5 | G39: =SUMPRODUCT('Coef Recargas'!$D$31:$T$31,Volumenes!$B$48:$R$48) -> 68.75 | H39: =SUMPRODUCT('Coef Recargas'!$D$31:$T$31,Volumenes!$B$49:$R$49) -> 93.75 | I39: =SUMPRODUCT('Coef Recargas'!$D$31:$T$31,Volumenes!$B$50:$R$50) -> 125 | J39: =SUMPRODUCT('Coef Recargas'!$D$31:$T$31,Volumenes!$B$51:$R$51) -> 157.5 | K39: =SUMPRODUCT('Coef Recargas'!$D$31:$T$31,Volumenes!$B$52:$R$52) -> 175 | L39: =SUMPRODUCT('Coef Recargas'!$D$31:$T$31,Volumenes!$B$53:$R$53) -> 191.25 | M39: =SUMPRODUCT('Coef Recargas'!$D$31:$T$31,Volumenes!$B$54:$R$54) -> 206.25 | N39: =IF(F39=0,"—",M39/F39) -> 5.5
A40: MP-36 | B40: Polvo clase D (recargas) | C40: kg | D40: =SUMPRODUCT('Coef Recargas'!$D$32:$T$32,Volumenes!$B$45:$R$45) -> 6 | E40: =SUMPRODUCT('Coef Recargas'!$D$32:$T$32,Volumenes!$B$46:$R$46) -> 48 | F40: =SUMPRODUCT('Coef Recargas'!$D$32:$T$32,Volumenes!$B$47:$R$47) -> 90 | G40: =SUMPRODUCT('Coef Recargas'!$D$32:$T$32,Volumenes!$B$48:$R$48) -> 153 | H40: =SUMPRODUCT('Coef Recargas'!$D$32:$T$32,Volumenes!$B$49:$R$49) -> 210 | I40: =SUMPRODUCT('Coef Recargas'!$D$32:$T$32,Volumenes!$B$50:$R$50) -> 261 | J40: =SUMPRODUCT('Coef Recargas'!$D$32:$T$32,Volumenes!$B$51:$R$51) -> 336 | K40: =SUMPRODUCT('Coef Recargas'!$D$32:$T$32,Volumenes!$B$52:$R$52) -> 378 | L40: =SUMPRODUCT('Coef Recargas'!$D$32:$T$32,Volumenes!$B$53:$R$53) -> 414 | M40: =SUMPRODUCT('Coef Recargas'!$D$32:$T$32,Volumenes!$B$54:$R$54) -> 450 | N40: =IF(F40=0,"—",M40/F40) -> 5
A41: MP-37 | B41: CO₂ líquido (recargas) | C41: kg | D41: =SUMPRODUCT('Coef Recargas'!$D$33:$T$33,Volumenes!$B$45:$R$45) -> 201.355 | E41: =SUMPRODUCT('Coef Recargas'!$D$33:$T$33,Volumenes!$B$46:$R$46) -> 872.795 | F41: =SUMPRODUCT('Coef Recargas'!$D$33:$T$33,Volumenes!$B$47:$R$47) -> 1949.255 | G41: =SUMPRODUCT('Coef Recargas'!$D$33:$T$33,Volumenes!$B$48:$R$48) -> 3614.38 | H41: =SUMPRODUCT('Coef Recargas'!$D$33:$T$33,Volumenes!$B$49:$R$49) -> 5215.98 | I41: =SUMPRODUCT('Coef Recargas'!$D$33:$T$33,Volumenes!$B$50:$R$50) -> 6939.625 | J41: =SUMPRODUCT('Coef Recargas'!$D$33:$T$33,Volumenes!$B$51:$R$51) -> 8536.22 | K41: =SUMPRODUCT('Coef Recargas'!$D$33:$T$33,Volumenes!$B$52:$R$52) -> 9528.365 | L41: =SUMPRODUCT('Coef Recargas'!$D$33:$T$33,Volumenes!$B$53:$R$53) -> 10314.92 | M41: =SUMPRODUCT('Coef Recargas'!$D$33:$T$33,Volumenes!$B$54:$R$54) -> 11114.18 | N41: =IF(F41=0,"—",M41/F41) -> 5.7017579
A42: MP-38 | B42: Agente limpio HCFC/HFC (recargas) | C42: kg | D42: =SUMPRODUCT('Coef Recargas'!$D$34:$T$34,Volumenes!$B$45:$R$45) -> 11.025 | E42: =SUMPRODUCT('Coef Recargas'!$D$34:$T$34,Volumenes!$B$46:$R$46) -> 69.825 | F42: =SUMPRODUCT('Coef Recargas'!$D$34:$T$34,Volumenes!$B$47:$R$47) -> 145.1625 | G42: =SUMPRODUCT('Coef Recargas'!$D$34:$T$34,Volumenes!$B$48:$R$48) -> 251.7375 | H42: =SUMPRODUCT('Coef Recargas'!$D$34:$T$34,Volumenes!$B$49:$R$49) -> 361.9875 | I42: =SUMPRODUCT('Coef Recargas'!$D$34:$T$34,Volumenes!$B$50:$R$50) -> 475.9125 | J42: =SUMPRODUCT('Coef Recargas'!$D$34:$T$34,Volumenes!$B$51:$R$51) -> 595.35 | K42: =SUMPRODUCT('Coef Recargas'!$D$34:$T$34,Volumenes!$B$52:$R$52) -> 674.3625 | L42: =SUMPRODUCT('Coef Recargas'!$D$34:$T$34,Volumenes!$B$53:$R$53) -> 736.8375 | M42: =SUMPRODUCT('Coef Recargas'!$D$34:$T$34,Volumenes!$B$54:$R$54) -> 801.15 | N42: =IF(F42=0,"—",M42/F42) -> 5.5189873
A43: MP-39 | B43: Argón (presurización de agente limpio) | C43: m³ | D43: =SUMPRODUCT('Coef Recargas'!$D$35:$T$35,Volumenes!$B$45:$R$45) -> 0.042 | E43: =SUMPRODUCT('Coef Recargas'!$D$35:$T$35,Volumenes!$B$46:$R$46) -> 0.266 | F43: =SUMPRODUCT('Coef Recargas'!$D$35:$T$35,Volumenes!$B$47:$R$47) -> 0.553 | G43: =SUMPRODUCT('Coef Recargas'!$D$35:$T$35,Volumenes!$B$48:$R$48) -> 0.959 | H43: =SUMPRODUCT('Coef Recargas'!$D$35:$T$35,Volumenes!$B$49:$R$49) -> 1.379 | I43: =SUMPRODUCT('Coef Recargas'!$D$35:$T$35,Volumenes!$B$50:$R$50) -> 1.813 | J43: =SUMPRODUCT('Coef Recargas'!$D$35:$T$35,Volumenes!$B$51:$R$51) -> 2.268 | K43: =SUMPRODUCT('Coef Recargas'!$D$35:$T$35,Volumenes!$B$52:$R$52) -> 2.569 | L43: =SUMPRODUCT('Coef Recargas'!$D$35:$T$35,Volumenes!$B$53:$R$53) -> 2.807 | M43: =SUMPRODUCT('Coef Recargas'!$D$35:$T$35,Volumenes!$B$54:$R$54) -> 3.052 | N43: =IF(F43=0,"—",M43/F43) -> 5.5189873
A44: MP-40 | B44: Concentrado AFFF (recargas) | C44: L | D44: =SUMPRODUCT('Coef Recargas'!$D$36:$T$36,Volumenes!$B$45:$R$45) -> 16.8 | E44: =SUMPRODUCT('Coef Recargas'!$D$36:$T$36,Volumenes!$B$46:$R$46) -> 120 | F44: =SUMPRODUCT('Coef Recargas'!$D$36:$T$36,Volumenes!$B$47:$R$47) -> 233.4 | G44: =SUMPRODUCT('Coef Recargas'!$D$36:$T$36,Volumenes!$B$48:$R$48) -> 396.6 | H44: =SUMPRODUCT('Coef Recargas'!$D$36:$T$36,Volumenes!$B$49:$R$49) -> 564 | I44: =SUMPRODUCT('Coef Recargas'!$D$36:$T$36,Volumenes!$B$50:$R$50) -> 726 | J44: =SUMPRODUCT('Coef Recargas'!$D$36:$T$36,Volumenes!$B$51:$R$51) -> 890.4 | K44: =SUMPRODUCT('Coef Recargas'!$D$36:$T$36,Volumenes!$B$52:$R$52) -> 1009.8 | L44: =SUMPRODUCT('Coef Recargas'!$D$36:$T$36,Volumenes!$B$53:$R$53) -> 1098.6 | M44: =SUMPRODUCT('Coef Recargas'!$D$36:$T$36,Volumenes!$B$54:$R$54) -> 1191 | N44: =IF(F44=0,"—",M44/F44) -> 5.1028278
A45: MP-41 | B45: Solución clase K — acetato de potasio (recargas) | C45: L | D45: =SUMPRODUCT('Coef Recargas'!$D$37:$T$37,Volumenes!$B$45:$R$45) -> 168 | E45: =SUMPRODUCT('Coef Recargas'!$D$37:$T$37,Volumenes!$B$46:$R$46) -> 690 | F45: =SUMPRODUCT('Coef Recargas'!$D$37:$T$37,Volumenes!$B$47:$R$47) -> 1536 | G45: =SUMPRODUCT('Coef Recargas'!$D$37:$T$37,Volumenes!$B$48:$R$48) -> 2790 | H45: =SUMPRODUCT('Coef Recargas'!$D$37:$T$37,Volumenes!$B$49:$R$49) -> 4026 | I45: =SUMPRODUCT('Coef Recargas'!$D$37:$T$37,Volumenes!$B$50:$R$50) -> 5340 | J45: =SUMPRODUCT('Coef Recargas'!$D$37:$T$37,Volumenes!$B$51:$R$51) -> 6570 | K45: =SUMPRODUCT('Coef Recargas'!$D$37:$T$37,Volumenes!$B$52:$R$52) -> 7350 | L45: =SUMPRODUCT('Coef Recargas'!$D$37:$T$37,Volumenes!$B$53:$R$53) -> 7950 | M45: =SUMPRODUCT('Coef Recargas'!$D$37:$T$37,Volumenes!$B$54:$R$54) -> 8562 | N45: =IF(F45=0,"—",M45/F45) -> 5.5742188
A46: MP-42 | B46: Válvula M-22 para 1 kg con tubo de pesca | C46: u | D46: =SUMPRODUCT('Coef Fabricacion'!$D$57:$K$57,Volumenes!$B$32:$I$32)+SUMPRODUCT('Coef Fabricacion'!$L$57:$S$57,Volumenes!$B$6:$I$6)+SUMPRODUCT('Coef Fabricacion'!$T$57:$AA$57,Volumenes!$B$19:$I$19)+SUMPRODUCT('Coef Recargas'!$D$38:$T$38,Volumenes!$B$45:$R$45) -> 4214.7 | E46: =SUMPRODUCT('Coef Fabricacion'!$D$57:$K$57,Volumenes!$B$33:$I$33)+SUMPRODUCT('Coef Fabricacion'!$L$57:$S$57,Volumenes!$B$7:$I$7)+SUMPRODUCT('Coef Fabricacion'!$T$57:$AA$57,Volumenes!$B$20:$I$20)+SUMPRODUCT('Coef Recargas'!$D$38:$T$38,Volumenes!$B$46:$R$46) -> 6171.33 | F46: =SUMPRODUCT('Coef Fabricacion'!$D$57:$K$57,Volumenes!$B$34:$I$34)+SUMPRODUCT('Coef Fabricacion'!$L$57:$S$57,Volumenes!$B$8:$I$8)+SUMPRODUCT('Coef Fabricacion'!$T$57:$AA$57,Volumenes!$B$21:$I$21)+SUMPRODUCT('Coef Recargas'!$D$38:$T$38,Volumenes!$B$47:$R$47) -> 7165.77 | G46: =SUMPRODUCT('Coef Fabricacion'!$D$57:$K$57,Volumenes!$B$35:$I$35)+SUMPRODUCT('Coef Fabricacion'!$L$57:$S$57,Volumenes!$B$9:$I$9)+SUMPRODUCT('Coef Fabricacion'!$T$57:$AA$57,Volumenes!$B$22:$I$22)+SUMPRODUCT('Coef Recargas'!$D$38:$T$38,Volumenes!$B$48:$R$48) -> 9042.7 | H46: =SUMPRODUCT('Coef Fabricacion'!$D$57:$K$57,Volumenes!$B$36:$I$36)+SUMPRODUCT('Coef Fabricacion'!$L$57:$S$57,Volumenes!$B$10:$I$10)+SUMPRODUCT('Coef Fabricacion'!$T$57:$AA$57,Volumenes!$B$23:$I$23)+SUMPRODUCT('Coef Recargas'!$D$38:$T$38,Volumenes!$B$49:$R$49) -> 13546.59 | I46: =SUMPRODUCT('Coef Fabricacion'!$D$57:$K$57,Volumenes!$B$37:$I$37)+SUMPRODUCT('Coef Fabricacion'!$L$57:$S$57,Volumenes!$B$11:$I$11)+SUMPRODUCT('Coef Fabricacion'!$T$57:$AA$57,Volumenes!$B$24:$I$24)+SUMPRODUCT('Coef Recargas'!$D$38:$T$38,Volumenes!$B$50:$R$50) -> 16825.97 | J46: =SUMPRODUCT('Coef Fabricacion'!$D$57:$K$57,Volumenes!$B$38:$I$38)+SUMPRODUCT('Coef Fabricacion'!$L$57:$S$57,Volumenes!$B$12:$I$12)+SUMPRODUCT('Coef Fabricacion'!$T$57:$AA$57,Volumenes!$B$25:$I$25)+SUMPRODUCT('Coef Recargas'!$D$38:$T$38,Volumenes!$B$51:$R$51) -> 21849.23 | K46: =SUMPRODUCT('Coef Fabricacion'!$D$57:$K$57,Volumenes!$B$39:$I$39)+SUMPRODUCT('Coef Fabricacion'!$L$57:$S$57,Volumenes!$B$13:$I$13)+SUMPRODUCT('Coef Fabricacion'!$T$57:$AA$57,Volumenes!$B$26:$I$26)+SUMPRODUCT('Coef Recargas'!$D$38:$T$38,Volumenes!$B$52:$R$52) -> 26892.61 | L46: =SUMPRODUCT('Coef Fabricacion'!$D$57:$K$57,Volumenes!$B$40:$I$40)+SUMPRODUCT('Coef Fabricacion'!$L$57:$S$57,Volumenes!$B$14:$I$14)+SUMPRODUCT('Coef Fabricacion'!$T$57:$AA$57,Volumenes!$B$27:$I$27)+SUMPRODUCT('Coef Recargas'!$D$38:$T$38,Volumenes!$B$53:$R$53) -> 30459.82 | M46: =SUMPRODUCT('Coef Fabricacion'!$D$57:$K$57,Volumenes!$B$41:$I$41)+SUMPRODUCT('Coef Fabricacion'!$L$57:$S$57,Volumenes!$B$15:$I$15)+SUMPRODUCT('Coef Fabricacion'!$T$57:$AA$57,Volumenes!$B$28:$I$28)+SUMPRODUCT('Coef Recargas'!$D$38:$T$38,Volumenes!$B$54:$R$54) -> 34089.18 | N46: =IF(F46=0,"—",M46/F46) -> 4.757225
A47: MP-43 | B47: Válvula M-30 con resorte para 2,5–10 kg | C47: u | D47: =SUMPRODUCT('Coef Fabricacion'!$D$58:$K$58,Volumenes!$B$32:$I$32)+SUMPRODUCT('Coef Fabricacion'!$L$58:$S$58,Volumenes!$B$6:$I$6)+SUMPRODUCT('Coef Fabricacion'!$T$58:$AA$58,Volumenes!$B$19:$I$19)+SUMPRODUCT('Coef Recargas'!$D$39:$T$39,Volumenes!$B$45:$R$45) -> 2670.57 | E47: =SUMPRODUCT('Coef Fabricacion'!$D$58:$K$58,Volumenes!$B$33:$I$33)+SUMPRODUCT('Coef Fabricacion'!$L$58:$S$58,Volumenes!$B$7:$I$7)+SUMPRODUCT('Coef Fabricacion'!$T$58:$AA$58,Volumenes!$B$20:$I$20)+SUMPRODUCT('Coef Recargas'!$D$39:$T$39,Volumenes!$B$46:$R$46) -> 4844.72 | F47: =SUMPRODUCT('Coef Fabricacion'!$D$58:$K$58,Volumenes!$B$34:$I$34)+SUMPRODUCT('Coef Fabricacion'!$L$58:$S$58,Volumenes!$B$8:$I$8)+SUMPRODUCT('Coef Fabricacion'!$T$58:$AA$58,Volumenes!$B$21:$I$21)+SUMPRODUCT('Coef Recargas'!$D$39:$T$39,Volumenes!$B$47:$R$47) -> 6586.75 | G47: =SUMPRODUCT('Coef Fabricacion'!$D$58:$K$58,Volumenes!$B$35:$I$35)+SUMPRODUCT('Coef Fabricacion'!$L$58:$S$58,Volumenes!$B$9:$I$9)+SUMPRODUCT('Coef Fabricacion'!$T$58:$AA$58,Volumenes!$B$22:$I$22)+SUMPRODUCT('Coef Recargas'!$D$39:$T$39,Volumenes!$B$48:$R$48) -> 9156.6 | H47: =SUMPRODUCT('Coef Fabricacion'!$D$58:$K$58,Volumenes!$B$36:$I$36)+SUMPRODUCT('Coef Fabricacion'!$L$58:$S$58,Volumenes!$B$10:$I$10)+SUMPRODUCT('Coef Fabricacion'!$T$58:$AA$58,Volumenes!$B$23:$I$23)+SUMPRODUCT('Coef Recargas'!$D$39:$T$39,Volumenes!$B$49:$R$49) -> 14418 | I47: =SUMPRODUCT('Coef Fabricacion'!$D$58:$K$58,Volumenes!$B$37:$I$37)+SUMPRODUCT('Coef Fabricacion'!$L$58:$S$58,Volumenes!$B$11:$I$11)+SUMPRODUCT('Coef Fabricacion'!$T$58:$AA$58,Volumenes!$B$24:$I$24)+SUMPRODUCT('Coef Recargas'!$D$39:$T$39,Volumenes!$B$50:$R$50) -> 19639.12 | J47: =SUMPRODUCT('Coef Fabricacion'!$D$58:$K$58,Volumenes!$B$38:$I$38)+SUMPRODUCT('Coef Fabricacion'!$L$58:$S$58,Volumenes!$B$12:$I$12)+SUMPRODUCT('Coef Fabricacion'!$T$58:$AA$58,Volumenes!$B$25:$I$25)+SUMPRODUCT('Coef Recargas'!$D$39:$T$39,Volumenes!$B$51:$R$51) -> 25221.87 | K47: =SUMPRODUCT('Coef Fabricacion'!$D$58:$K$58,Volumenes!$B$39:$I$39)+SUMPRODUCT('Coef Fabricacion'!$L$58:$S$58,Volumenes!$B$13:$I$13)+SUMPRODUCT('Coef Fabricacion'!$T$58:$AA$58,Volumenes!$B$26:$I$26)+SUMPRODUCT('Coef Recargas'!$D$39:$T$39,Volumenes!$B$52:$R$52) -> 31104.15 | L47: =SUMPRODUCT('Coef Fabricacion'!$D$58:$K$58,Volumenes!$B$40:$I$40)+SUMPRODUCT('Coef Fabricacion'!$L$58:$S$58,Volumenes!$B$14:$I$14)+SUMPRODUCT('Coef Fabricacion'!$T$58:$AA$58,Volumenes!$B$27:$I$27)+SUMPRODUCT('Coef Recargas'!$D$39:$T$39,Volumenes!$B$53:$R$53) -> 36109.64 | M47: =SUMPRODUCT('Coef Fabricacion'!$D$58:$K$58,Volumenes!$B$41:$I$41)+SUMPRODUCT('Coef Fabricacion'!$L$58:$S$58,Volumenes!$B$15:$I$15)+SUMPRODUCT('Coef Fabricacion'!$T$58:$AA$58,Volumenes!$B$28:$I$28)+SUMPRODUCT('Coef Recargas'!$D$39:$T$39,Volumenes!$B$54:$R$54) -> 41451.78 | N47: =IF(F47=0,"—",M47/F47) -> 6.2932068
A48: MP-44 | B48: Válvula para carro 25–100 kg (con traba, manija y resorte) | C48: u | D48: =SUMPRODUCT('Coef Fabricacion'!$D$59:$K$59,Volumenes!$B$32:$I$32)+SUMPRODUCT('Coef Fabricacion'!$L$59:$S$59,Volumenes!$B$6:$I$6)+SUMPRODUCT('Coef Fabricacion'!$T$59:$AA$59,Volumenes!$B$19:$I$19)+SUMPRODUCT('Coef Recargas'!$D$40:$T$40,Volumenes!$B$45:$R$45) -> 136.84 | E48: =SUMPRODUCT('Coef Fabricacion'!$D$59:$K$59,Volumenes!$B$33:$I$33)+SUMPRODUCT('Coef Fabricacion'!$L$59:$S$59,Volumenes!$B$7:$I$7)+SUMPRODUCT('Coef Fabricacion'!$T$59:$AA$59,Volumenes!$B$20:$I$20)+SUMPRODUCT('Coef Recargas'!$D$40:$T$40,Volumenes!$B$46:$R$46) -> 237.41 | F48: =SUMPRODUCT('Coef Fabricacion'!$D$59:$K$59,Volumenes!$B$34:$I$34)+SUMPRODUCT('Coef Fabricacion'!$L$59:$S$59,Volumenes!$B$8:$I$8)+SUMPRODUCT('Coef Fabricacion'!$T$59:$AA$59,Volumenes!$B$21:$I$21)+SUMPRODUCT('Coef Recargas'!$D$40:$T$40,Volumenes!$B$47:$R$47) -> 311.39 | G48: =SUMPRODUCT('Coef Fabricacion'!$D$59:$K$59,Volumenes!$B$35:$I$35)+SUMPRODUCT('Coef Fabricacion'!$L$59:$S$59,Volumenes!$B$9:$I$9)+SUMPRODUCT('Coef Fabricacion'!$T$59:$AA$59,Volumenes!$B$22:$I$22)+SUMPRODUCT('Coef Recargas'!$D$40:$T$40,Volumenes!$B$48:$R$48) -> 418.68 | H48: =SUMPRODUCT('Coef Fabricacion'!$D$59:$K$59,Volumenes!$B$36:$I$36)+SUMPRODUCT('Coef Fabricacion'!$L$59:$S$59,Volumenes!$B$10:$I$10)+SUMPRODUCT('Coef Fabricacion'!$T$59:$AA$59,Volumenes!$B$23:$I$23)+SUMPRODUCT('Coef Recargas'!$D$40:$T$40,Volumenes!$B$49:$R$49) -> 647.03 | I48: =SUMPRODUCT('Coef Fabricacion'!$D$59:$K$59,Volumenes!$B$37:$I$37)+SUMPRODUCT('Coef Fabricacion'!$L$59:$S$59,Volumenes!$B$11:$I$11)+SUMPRODUCT('Coef Fabricacion'!$T$59:$AA$59,Volumenes!$B$24:$I$24)+SUMPRODUCT('Coef Recargas'!$D$40:$T$40,Volumenes!$B$50:$R$50) -> 877.68 | J48: =SUMPRODUCT('Coef Fabricacion'!$D$59:$K$59,Volumenes!$B$38:$I$38)+SUMPRODUCT('Coef Fabricacion'!$L$59:$S$59,Volumenes!$B$12:$I$12)+SUMPRODUCT('Coef Fabricacion'!$T$59:$AA$59,Volumenes!$B$25:$I$25)+SUMPRODUCT('Coef Recargas'!$D$40:$T$40,Volumenes!$B$51:$R$51) -> 1129 | K48: =SUMPRODUCT('Coef Fabricacion'!$D$59:$K$59,Volumenes!$B$39:$I$39)+SUMPRODUCT('Coef Fabricacion'!$L$59:$S$59,Volumenes!$B$13:$I$13)+SUMPRODUCT('Coef Fabricacion'!$T$59:$AA$59,Volumenes!$B$26:$I$26)+SUMPRODUCT('Coef Recargas'!$D$40:$T$40,Volumenes!$B$52:$R$52) -> 1395.89 | L48: =SUMPRODUCT('Coef Fabricacion'!$D$59:$K$59,Volumenes!$B$40:$I$40)+SUMPRODUCT('Coef Fabricacion'!$L$59:$S$59,Volumenes!$B$14:$I$14)+SUMPRODUCT('Coef Fabricacion'!$T$59:$AA$59,Volumenes!$B$27:$I$27)+SUMPRODUCT('Coef Recargas'!$D$40:$T$40,Volumenes!$B$53:$R$53) -> 1621.61 | M48: =SUMPRODUCT('Coef Fabricacion'!$D$59:$K$59,Volumenes!$B$41:$I$41)+SUMPRODUCT('Coef Fabricacion'!$L$59:$S$59,Volumenes!$B$15:$I$15)+SUMPRODUCT('Coef Fabricacion'!$T$59:$AA$59,Volumenes!$B$28:$I$28)+SUMPRODUCT('Coef Recargas'!$D$40:$T$40,Volumenes!$B$54:$R$54) -> 1864.42 | N48: =IF(F48=0,"—",M48/F48) -> 5.9874113
A49: MP-45 | B49: Manómetro IRAM 3533 (1,4 MPa) | C49: u | D49: =SUMPRODUCT('Coef Fabricacion'!$D$60:$K$60,Volumenes!$B$32:$I$32)+SUMPRODUCT('Coef Fabricacion'!$L$60:$S$60,Volumenes!$B$6:$I$6)+SUMPRODUCT('Coef Fabricacion'!$T$60:$AA$60,Volumenes!$B$19:$I$19)+SUMPRODUCT('Coef Recargas'!$D$41:$T$41,Volumenes!$B$45:$R$45) -> 7128.96 | E49: =SUMPRODUCT('Coef Fabricacion'!$D$60:$K$60,Volumenes!$B$33:$I$33)+SUMPRODUCT('Coef Fabricacion'!$L$60:$S$60,Volumenes!$B$7:$I$7)+SUMPRODUCT('Coef Fabricacion'!$T$60:$AA$60,Volumenes!$B$20:$I$20)+SUMPRODUCT('Coef Recargas'!$D$41:$T$41,Volumenes!$B$46:$R$46) -> 11737.56 | F49: =SUMPRODUCT('Coef Fabricacion'!$D$60:$K$60,Volumenes!$B$34:$I$34)+SUMPRODUCT('Coef Fabricacion'!$L$60:$S$60,Volumenes!$B$8:$I$8)+SUMPRODUCT('Coef Fabricacion'!$T$60:$AA$60,Volumenes!$B$21:$I$21)+SUMPRODUCT('Coef Recargas'!$D$41:$T$41,Volumenes!$B$47:$R$47) -> 15023.76 | G49: =SUMPRODUCT('Coef Fabricacion'!$D$60:$K$60,Volumenes!$B$35:$I$35)+SUMPRODUCT('Coef Fabricacion'!$L$60:$S$60,Volumenes!$B$9:$I$9)+SUMPRODUCT('Coef Fabricacion'!$T$60:$AA$60,Volumenes!$B$22:$I$22)+SUMPRODUCT('Coef Recargas'!$D$41:$T$41,Volumenes!$B$48:$R$48) -> 20396.28 | H49: =SUMPRODUCT('Coef Fabricacion'!$D$60:$K$60,Volumenes!$B$36:$I$36)+SUMPRODUCT('Coef Fabricacion'!$L$60:$S$60,Volumenes!$B$10:$I$10)+SUMPRODUCT('Coef Fabricacion'!$T$60:$AA$60,Volumenes!$B$23:$I$23)+SUMPRODUCT('Coef Recargas'!$D$41:$T$41,Volumenes!$B$49:$R$49) -> 31234.32 | I49: =SUMPRODUCT('Coef Fabricacion'!$D$60:$K$60,Volumenes!$B$37:$I$37)+SUMPRODUCT('Coef Fabricacion'!$L$60:$S$60,Volumenes!$B$11:$I$11)+SUMPRODUCT('Coef Fabricacion'!$T$60:$AA$60,Volumenes!$B$24:$I$24)+SUMPRODUCT('Coef Recargas'!$D$41:$T$41,Volumenes!$B$50:$R$50) -> 40920.72 | J49: =SUMPRODUCT('Coef Fabricacion'!$D$60:$K$60,Volumenes!$B$38:$I$38)+SUMPRODUCT('Coef Fabricacion'!$L$60:$S$60,Volumenes!$B$12:$I$12)+SUMPRODUCT('Coef Fabricacion'!$T$60:$AA$60,Volumenes!$B$25:$I$25)+SUMPRODUCT('Coef Recargas'!$D$41:$T$41,Volumenes!$B$51:$R$51) -> 52648.6 | K49: =SUMPRODUCT('Coef Fabricacion'!$D$60:$K$60,Volumenes!$B$39:$I$39)+SUMPRODUCT('Coef Fabricacion'!$L$60:$S$60,Volumenes!$B$13:$I$13)+SUMPRODUCT('Coef Fabricacion'!$T$60:$AA$60,Volumenes!$B$26:$I$26)+SUMPRODUCT('Coef Recargas'!$D$41:$T$41,Volumenes!$B$52:$R$52) -> 64460.4 | L49: =SUMPRODUCT('Coef Fabricacion'!$D$60:$K$60,Volumenes!$B$40:$I$40)+SUMPRODUCT('Coef Fabricacion'!$L$60:$S$60,Volumenes!$B$14:$I$14)+SUMPRODUCT('Coef Fabricacion'!$T$60:$AA$60,Volumenes!$B$27:$I$27)+SUMPRODUCT('Coef Recargas'!$D$41:$T$41,Volumenes!$B$53:$R$53) -> 73639.52 | M49: =SUMPRODUCT('Coef Fabricacion'!$D$60:$K$60,Volumenes!$B$41:$I$41)+SUMPRODUCT('Coef Fabricacion'!$L$60:$S$60,Volumenes!$B$15:$I$15)+SUMPRODUCT('Coef Fabricacion'!$T$60:$AA$60,Volumenes!$B$28:$I$28)+SUMPRODUCT('Coef Recargas'!$D$41:$T$41,Volumenes!$B$54:$R$54) -> 83242.68 | N49: =IF(F49=0,"—",M49/F49) -> 5.5407355
A50: MP-46 | B50: Tubo pescante PP/PEAD (2,5–10 kg) | C50: u | D50: =SUMPRODUCT('Coef Fabricacion'!$D$61:$K$61,Volumenes!$B$32:$I$32)+SUMPRODUCT('Coef Fabricacion'!$L$61:$S$61,Volumenes!$B$6:$I$6)+SUMPRODUCT('Coef Fabricacion'!$T$61:$AA$61,Volumenes!$B$19:$I$19)+SUMPRODUCT('Coef Recargas'!$D$42:$T$42,Volumenes!$B$45:$R$45) -> 2670.57 | E50: =SUMPRODUCT('Coef Fabricacion'!$D$61:$K$61,Volumenes!$B$33:$I$33)+SUMPRODUCT('Coef Fabricacion'!$L$61:$S$61,Volumenes!$B$7:$I$7)+SUMPRODUCT('Coef Fabricacion'!$T$61:$AA$61,Volumenes!$B$20:$I$20)+SUMPRODUCT('Coef Recargas'!$D$42:$T$42,Volumenes!$B$46:$R$46) -> 4844.72 | F50: =SUMPRODUCT('Coef Fabricacion'!$D$61:$K$61,Volumenes!$B$34:$I$34)+SUMPRODUCT('Coef Fabricacion'!$L$61:$S$61,Volumenes!$B$8:$I$8)+SUMPRODUCT('Coef Fabricacion'!$T$61:$AA$61,Volumenes!$B$21:$I$21)+SUMPRODUCT('Coef Recargas'!$D$42:$T$42,Volumenes!$B$47:$R$47) -> 6586.75 | G50: =SUMPRODUCT('Coef Fabricacion'!$D$61:$K$61,Volumenes!$B$35:$I$35)+SUMPRODUCT('Coef Fabricacion'!$L$61:$S$61,Volumenes!$B$9:$I$9)+SUMPRODUCT('Coef Fabricacion'!$T$61:$AA$61,Volumenes!$B$22:$I$22)+SUMPRODUCT('Coef Recargas'!$D$42:$T$42,Volumenes!$B$48:$R$48) -> 9156.6 | H50: =SUMPRODUCT('Coef Fabricacion'!$D$61:$K$61,Volumenes!$B$36:$I$36)+SUMPRODUCT('Coef Fabricacion'!$L$61:$S$61,Volumenes!$B$10:$I$10)+SUMPRODUCT('Coef Fabricacion'!$T$61:$AA$61,Volumenes!$B$23:$I$23)+SUMPRODUCT('Coef Recargas'!$D$42:$T$42,Volumenes!$B$49:$R$49) -> 14418 | I50: =SUMPRODUCT('Coef Fabricacion'!$D$61:$K$61,Volumenes!$B$37:$I$37)+SUMPRODUCT('Coef Fabricacion'!$L$61:$S$61,Volumenes!$B$11:$I$11)+SUMPRODUCT('Coef Fabricacion'!$T$61:$AA$61,Volumenes!$B$24:$I$24)+SUMPRODUCT('Coef Recargas'!$D$42:$T$42,Volumenes!$B$50:$R$50) -> 19639.12 | J50: =SUMPRODUCT('Coef Fabricacion'!$D$61:$K$61,Volumenes!$B$38:$I$38)+SUMPRODUCT('Coef Fabricacion'!$L$61:$S$61,Volumenes!$B$12:$I$12)+SUMPRODUCT('Coef Fabricacion'!$T$61:$AA$61,Volumenes!$B$25:$I$25)+SUMPRODUCT('Coef Recargas'!$D$42:$T$42,Volumenes!$B$51:$R$51) -> 25221.87 | K50: =SUMPRODUCT('Coef Fabricacion'!$D$61:$K$61,Volumenes!$B$39:$I$39)+SUMPRODUCT('Coef Fabricacion'!$L$61:$S$61,Volumenes!$B$13:$I$13)+SUMPRODUCT('Coef Fabricacion'!$T$61:$AA$61,Volumenes!$B$26:$I$26)+SUMPRODUCT('Coef Recargas'!$D$42:$T$42,Volumenes!$B$52:$R$52) -> 31104.15 | L50: =SUMPRODUCT('Coef Fabricacion'!$D$61:$K$61,Volumenes!$B$40:$I$40)+SUMPRODUCT('Coef Fabricacion'!$L$61:$S$61,Volumenes!$B$14:$I$14)+SUMPRODUCT('Coef Fabricacion'!$T$61:$AA$61,Volumenes!$B$27:$I$27)+SUMPRODUCT('Coef Recargas'!$D$42:$T$42,Volumenes!$B$53:$R$53) -> 36109.64 | M50: =SUMPRODUCT('Coef Fabricacion'!$D$61:$K$61,Volumenes!$B$41:$I$41)+SUMPRODUCT('Coef Fabricacion'!$L$61:$S$61,Volumenes!$B$15:$I$15)+SUMPRODUCT('Coef Fabricacion'!$T$61:$AA$61,Volumenes!$B$28:$I$28)+SUMPRODUCT('Coef Recargas'!$D$42:$T$42,Volumenes!$B$54:$R$54) -> 41451.78 | N50: =IF(F50=0,"—",M50/F50) -> 6.2932068
A51: MP-47 | B51: Tubo pescante de acero (carros) | C51: u | D51: =SUMPRODUCT('Coef Fabricacion'!$D$62:$K$62,Volumenes!$B$32:$I$32)+SUMPRODUCT('Coef Fabricacion'!$L$62:$S$62,Volumenes!$B$6:$I$6)+SUMPRODUCT('Coef Fabricacion'!$T$62:$AA$62,Volumenes!$B$19:$I$19)+SUMPRODUCT('Coef Recargas'!$D$43:$T$43,Volumenes!$B$45:$R$45) -> 136.84 | E51: =SUMPRODUCT('Coef Fabricacion'!$D$62:$K$62,Volumenes!$B$33:$I$33)+SUMPRODUCT('Coef Fabricacion'!$L$62:$S$62,Volumenes!$B$7:$I$7)+SUMPRODUCT('Coef Fabricacion'!$T$62:$AA$62,Volumenes!$B$20:$I$20)+SUMPRODUCT('Coef Recargas'!$D$43:$T$43,Volumenes!$B$46:$R$46) -> 237.41 | F51: =SUMPRODUCT('Coef Fabricacion'!$D$62:$K$62,Volumenes!$B$34:$I$34)+SUMPRODUCT('Coef Fabricacion'!$L$62:$S$62,Volumenes!$B$8:$I$8)+SUMPRODUCT('Coef Fabricacion'!$T$62:$AA$62,Volumenes!$B$21:$I$21)+SUMPRODUCT('Coef Recargas'!$D$43:$T$43,Volumenes!$B$47:$R$47) -> 311.39 | G51: =SUMPRODUCT('Coef Fabricacion'!$D$62:$K$62,Volumenes!$B$35:$I$35)+SUMPRODUCT('Coef Fabricacion'!$L$62:$S$62,Volumenes!$B$9:$I$9)+SUMPRODUCT('Coef Fabricacion'!$T$62:$AA$62,Volumenes!$B$22:$I$22)+SUMPRODUCT('Coef Recargas'!$D$43:$T$43,Volumenes!$B$48:$R$48) -> 418.68 | H51: =SUMPRODUCT('Coef Fabricacion'!$D$62:$K$62,Volumenes!$B$36:$I$36)+SUMPRODUCT('Coef Fabricacion'!$L$62:$S$62,Volumenes!$B$10:$I$10)+SUMPRODUCT('Coef Fabricacion'!$T$62:$AA$62,Volumenes!$B$23:$I$23)+SUMPRODUCT('Coef Recargas'!$D$43:$T$43,Volumenes!$B$49:$R$49) -> 647.03 | I51: =SUMPRODUCT('Coef Fabricacion'!$D$62:$K$62,Volumenes!$B$37:$I$37)+SUMPRODUCT('Coef Fabricacion'!$L$62:$S$62,Volumenes!$B$11:$I$11)+SUMPRODUCT('Coef Fabricacion'!$T$62:$AA$62,Volumenes!$B$24:$I$24)+SUMPRODUCT('Coef Recargas'!$D$43:$T$43,Volumenes!$B$50:$R$50) -> 877.68 | J51: =SUMPRODUCT('Coef Fabricacion'!$D$62:$K$62,Volumenes!$B$38:$I$38)+SUMPRODUCT('Coef Fabricacion'!$L$62:$S$62,Volumenes!$B$12:$I$12)+SUMPRODUCT('Coef Fabricacion'!$T$62:$AA$62,Volumenes!$B$25:$I$25)+SUMPRODUCT('Coef Recargas'!$D$43:$T$43,Volumenes!$B$51:$R$51) -> 1129 | K51: =SUMPRODUCT('Coef Fabricacion'!$D$62:$K$62,Volumenes!$B$39:$I$39)+SUMPRODUCT('Coef Fabricacion'!$L$62:$S$62,Volumenes!$B$13:$I$13)+SUMPRODUCT('Coef Fabricacion'!$T$62:$AA$62,Volumenes!$B$26:$I$26)+SUMPRODUCT('Coef Recargas'!$D$43:$T$43,Volumenes!$B$52:$R$52) -> 1395.89 | L51: =SUMPRODUCT('Coef Fabricacion'!$D$62:$K$62,Volumenes!$B$40:$I$40)+SUMPRODUCT('Coef Fabricacion'!$L$62:$S$62,Volumenes!$B$14:$I$14)+SUMPRODUCT('Coef Fabricacion'!$T$62:$AA$62,Volumenes!$B$27:$I$27)+SUMPRODUCT('Coef Recargas'!$D$43:$T$43,Volumenes!$B$53:$R$53) -> 1621.61 | M51: =SUMPRODUCT('Coef Fabricacion'!$D$62:$K$62,Volumenes!$B$41:$I$41)+SUMPRODUCT('Coef Fabricacion'!$L$62:$S$62,Volumenes!$B$15:$I$15)+SUMPRODUCT('Coef Fabricacion'!$T$62:$AA$62,Volumenes!$B$28:$I$28)+SUMPRODUCT('Coef Recargas'!$D$43:$T$43,Volumenes!$B$54:$R$54) -> 1864.42 | N51: =IF(F51=0,"—",M51/F51) -> 5.9874113
A52: MP-48 | B52: Manguera + tobera (2,5–10 kg) | C52: u | D52: =SUMPRODUCT('Coef Fabricacion'!$D$63:$K$63,Volumenes!$B$32:$I$32)+SUMPRODUCT('Coef Fabricacion'!$L$63:$S$63,Volumenes!$B$6:$I$6)+SUMPRODUCT('Coef Fabricacion'!$T$63:$AA$63,Volumenes!$B$19:$I$19)+SUMPRODUCT('Coef Recargas'!$D$44:$T$44,Volumenes!$B$45:$R$45) -> 2698.9 | E52: =SUMPRODUCT('Coef Fabricacion'!$D$63:$K$63,Volumenes!$B$33:$I$33)+SUMPRODUCT('Coef Fabricacion'!$L$63:$S$63,Volumenes!$B$7:$I$7)+SUMPRODUCT('Coef Fabricacion'!$T$63:$AA$63,Volumenes!$B$20:$I$20)+SUMPRODUCT('Coef Recargas'!$D$44:$T$44,Volumenes!$B$46:$R$46) -> 4960.1 | F52: =SUMPRODUCT('Coef Fabricacion'!$D$63:$K$63,Volumenes!$B$34:$I$34)+SUMPRODUCT('Coef Fabricacion'!$L$63:$S$63,Volumenes!$B$8:$I$8)+SUMPRODUCT('Coef Fabricacion'!$T$63:$AA$63,Volumenes!$B$21:$I$21)+SUMPRODUCT('Coef Recargas'!$D$44:$T$44,Volumenes!$B$47:$R$47) -> 6848 | G52: =SUMPRODUCT('Coef Fabricacion'!$D$63:$K$63,Volumenes!$B$35:$I$35)+SUMPRODUCT('Coef Fabricacion'!$L$63:$S$63,Volumenes!$B$9:$I$9)+SUMPRODUCT('Coef Fabricacion'!$T$63:$AA$63,Volumenes!$B$22:$I$22)+SUMPRODUCT('Coef Recargas'!$D$44:$T$44,Volumenes!$B$48:$R$48) -> 9647.1 | H52: =SUMPRODUCT('Coef Fabricacion'!$D$63:$K$63,Volumenes!$B$36:$I$36)+SUMPRODUCT('Coef Fabricacion'!$L$63:$S$63,Volumenes!$B$10:$I$10)+SUMPRODUCT('Coef Fabricacion'!$T$63:$AA$63,Volumenes!$B$23:$I$23)+SUMPRODUCT('Coef Recargas'!$D$44:$T$44,Volumenes!$B$49:$R$49) -> 15125.15 | I52: =SUMPRODUCT('Coef Fabricacion'!$D$63:$K$63,Volumenes!$B$37:$I$37)+SUMPRODUCT('Coef Fabricacion'!$L$63:$S$63,Volumenes!$B$11:$I$11)+SUMPRODUCT('Coef Fabricacion'!$T$63:$AA$63,Volumenes!$B$24:$I$24)+SUMPRODUCT('Coef Recargas'!$D$44:$T$44,Volumenes!$B$50:$R$50) -> 20578.9 | J52: =SUMPRODUCT('Coef Fabricacion'!$D$63:$K$63,Volumenes!$B$38:$I$38)+SUMPRODUCT('Coef Fabricacion'!$L$63:$S$63,Volumenes!$B$12:$I$12)+SUMPRODUCT('Coef Fabricacion'!$T$63:$AA$63,Volumenes!$B$25:$I$25)+SUMPRODUCT('Coef Recargas'!$D$44:$T$44,Volumenes!$B$51:$R$51) -> 26374.05 | K52: =SUMPRODUCT('Coef Fabricacion'!$D$63:$K$63,Volumenes!$B$39:$I$39)+SUMPRODUCT('Coef Fabricacion'!$L$63:$S$63,Volumenes!$B$13:$I$13)+SUMPRODUCT('Coef Fabricacion'!$T$63:$AA$63,Volumenes!$B$26:$I$26)+SUMPRODUCT('Coef Recargas'!$D$44:$T$44,Volumenes!$B$52:$R$52) -> 32383.55 | L52: =SUMPRODUCT('Coef Fabricacion'!$D$63:$K$63,Volumenes!$B$40:$I$40)+SUMPRODUCT('Coef Fabricacion'!$L$63:$S$63,Volumenes!$B$14:$I$14)+SUMPRODUCT('Coef Fabricacion'!$T$63:$AA$63,Volumenes!$B$27:$I$27)+SUMPRODUCT('Coef Recargas'!$D$44:$T$44,Volumenes!$B$53:$R$53) -> 37491.6 | M52: =SUMPRODUCT('Coef Fabricacion'!$D$63:$K$63,Volumenes!$B$41:$I$41)+SUMPRODUCT('Coef Fabricacion'!$L$63:$S$63,Volumenes!$B$15:$I$15)+SUMPRODUCT('Coef Fabricacion'!$T$63:$AA$63,Volumenes!$B$28:$I$28)+SUMPRODUCT('Coef Recargas'!$D$44:$T$44,Volumenes!$B$54:$R$54) -> 42938 | N52: =IF(F52=0,"—",M52/F52) -> 6.2701519
A53: MP-49 | B53: Manguera + lanza/pistola para carro | C53: u | D53: =SUMPRODUCT('Coef Fabricacion'!$D$64:$K$64,Volumenes!$B$32:$I$32)+SUMPRODUCT('Coef Fabricacion'!$L$64:$S$64,Volumenes!$B$6:$I$6)+SUMPRODUCT('Coef Fabricacion'!$T$64:$AA$64,Volumenes!$B$19:$I$19)+SUMPRODUCT('Coef Recargas'!$D$45:$T$45,Volumenes!$B$45:$R$45) -> 137.4 | E53: =SUMPRODUCT('Coef Fabricacion'!$D$64:$K$64,Volumenes!$B$33:$I$33)+SUMPRODUCT('Coef Fabricacion'!$L$64:$S$64,Volumenes!$B$7:$I$7)+SUMPRODUCT('Coef Fabricacion'!$T$64:$AA$64,Volumenes!$B$20:$I$20)+SUMPRODUCT('Coef Recargas'!$D$45:$T$45,Volumenes!$B$46:$R$46) -> 240.35 | F53: =SUMPRODUCT('Coef Fabricacion'!$D$64:$K$64,Volumenes!$B$34:$I$34)+SUMPRODUCT('Coef Fabricacion'!$L$64:$S$64,Volumenes!$B$8:$I$8)+SUMPRODUCT('Coef Fabricacion'!$T$64:$AA$64,Volumenes!$B$21:$I$21)+SUMPRODUCT('Coef Recargas'!$D$45:$T$45,Volumenes!$B$47:$R$47) -> 317.65 | G53: =SUMPRODUCT('Coef Fabricacion'!$D$64:$K$64,Volumenes!$B$35:$I$35)+SUMPRODUCT('Coef Fabricacion'!$L$64:$S$64,Volumenes!$B$9:$I$9)+SUMPRODUCT('Coef Fabricacion'!$T$64:$AA$64,Volumenes!$B$22:$I$22)+SUMPRODUCT('Coef Recargas'!$D$45:$T$45,Volumenes!$B$48:$R$48) -> 429.8 | H53: =SUMPRODUCT('Coef Fabricacion'!$D$64:$K$64,Volumenes!$B$36:$I$36)+SUMPRODUCT('Coef Fabricacion'!$L$64:$S$64,Volumenes!$B$10:$I$10)+SUMPRODUCT('Coef Fabricacion'!$T$64:$AA$64,Volumenes!$B$23:$I$23)+SUMPRODUCT('Coef Recargas'!$D$45:$T$45,Volumenes!$B$49:$R$49) -> 663.05 | I53: =SUMPRODUCT('Coef Fabricacion'!$D$64:$K$64,Volumenes!$B$37:$I$37)+SUMPRODUCT('Coef Fabricacion'!$L$64:$S$64,Volumenes!$B$11:$I$11)+SUMPRODUCT('Coef Fabricacion'!$T$64:$AA$64,Volumenes!$B$24:$I$24)+SUMPRODUCT('Coef Recargas'!$D$45:$T$45,Volumenes!$B$50:$R$50) -> 898.8 | J53: =SUMPRODUCT('Coef Fabricacion'!$D$64:$K$64,Volumenes!$B$38:$I$38)+SUMPRODUCT('Coef Fabricacion'!$L$64:$S$64,Volumenes!$B$12:$I$12)+SUMPRODUCT('Coef Fabricacion'!$T$64:$AA$64,Volumenes!$B$25:$I$25)+SUMPRODUCT('Coef Recargas'!$D$45:$T$45,Volumenes!$B$51:$R$51) -> 1155 | K53: =SUMPRODUCT('Coef Fabricacion'!$D$64:$K$64,Volumenes!$B$39:$I$39)+SUMPRODUCT('Coef Fabricacion'!$L$64:$S$64,Volumenes!$B$13:$I$13)+SUMPRODUCT('Coef Fabricacion'!$T$64:$AA$64,Volumenes!$B$26:$I$26)+SUMPRODUCT('Coef Recargas'!$D$45:$T$45,Volumenes!$B$52:$R$52) -> 1425.15 | L53: =SUMPRODUCT('Coef Fabricacion'!$D$64:$K$64,Volumenes!$B$40:$I$40)+SUMPRODUCT('Coef Fabricacion'!$L$64:$S$64,Volumenes!$B$14:$I$14)+SUMPRODUCT('Coef Fabricacion'!$T$64:$AA$64,Volumenes!$B$27:$I$27)+SUMPRODUCT('Coef Recargas'!$D$45:$T$45,Volumenes!$B$53:$R$53) -> 1653.35 | M53: =SUMPRODUCT('Coef Fabricacion'!$D$64:$K$64,Volumenes!$B$41:$I$41)+SUMPRODUCT('Coef Fabricacion'!$L$64:$S$64,Volumenes!$B$15:$I$15)+SUMPRODUCT('Coef Fabricacion'!$T$64:$AA$64,Volumenes!$B$28:$I$28)+SUMPRODUCT('Coef Recargas'!$D$45:$T$45,Volumenes!$B$54:$R$54) -> 1898.7 | N53: =IF(F53=0,"—",M53/F53) -> 5.9773335
A54: MP-50 | B54: O-ring NBR 70 | C54: u | D54: =SUMPRODUCT('Coef Fabricacion'!$D$65:$K$65,Volumenes!$B$32:$I$32)+SUMPRODUCT('Coef Fabricacion'!$L$65:$S$65,Volumenes!$B$6:$I$6)+SUMPRODUCT('Coef Fabricacion'!$T$65:$AA$65,Volumenes!$B$19:$I$19)+SUMPRODUCT('Coef Recargas'!$D$46:$T$46,Volumenes!$B$45:$R$45) -> 18324.1 | E54: =SUMPRODUCT('Coef Fabricacion'!$D$65:$K$65,Volumenes!$B$33:$I$33)+SUMPRODUCT('Coef Fabricacion'!$L$65:$S$65,Volumenes!$B$7:$I$7)+SUMPRODUCT('Coef Fabricacion'!$T$65:$AA$65,Volumenes!$B$20:$I$20)+SUMPRODUCT('Coef Recargas'!$D$46:$T$46,Volumenes!$B$46:$R$46) -> 41834 | F54: =SUMPRODUCT('Coef Fabricacion'!$D$65:$K$65,Volumenes!$B$34:$I$34)+SUMPRODUCT('Coef Fabricacion'!$L$65:$S$65,Volumenes!$B$8:$I$8)+SUMPRODUCT('Coef Fabricacion'!$T$65:$AA$65,Volumenes!$B$21:$I$21)+SUMPRODUCT('Coef Recargas'!$D$46:$T$46,Volumenes!$B$47:$R$47) -> 66604.8 | G54: =SUMPRODUCT('Coef Fabricacion'!$D$65:$K$65,Volumenes!$B$35:$I$35)+SUMPRODUCT('Coef Fabricacion'!$L$65:$S$65,Volumenes!$B$9:$I$9)+SUMPRODUCT('Coef Fabricacion'!$T$65:$AA$65,Volumenes!$B$22:$I$22)+SUMPRODUCT('Coef Recargas'!$D$46:$T$46,Volumenes!$B$48:$R$48) -> 108559.6 | H54: =SUMPRODUCT('Coef Fabricacion'!$D$65:$K$65,Volumenes!$B$36:$I$36)+SUMPRODUCT('Coef Fabricacion'!$L$65:$S$65,Volumenes!$B$10:$I$10)+SUMPRODUCT('Coef Fabricacion'!$T$65:$AA$65,Volumenes!$B$23:$I$23)+SUMPRODUCT('Coef Recargas'!$D$46:$T$46,Volumenes!$B$49:$R$49) -> 162335 | I54: =SUMPRODUCT('Coef Fabricacion'!$D$65:$K$65,Volumenes!$B$37:$I$37)+SUMPRODUCT('Coef Fabricacion'!$L$65:$S$65,Volumenes!$B$11:$I$11)+SUMPRODUCT('Coef Fabricacion'!$T$65:$AA$65,Volumenes!$B$24:$I$24)+SUMPRODUCT('Coef Recargas'!$D$46:$T$46,Volumenes!$B$50:$R$50) -> 217958.2 | J54: =SUMPRODUCT('Coef Fabricacion'!$D$65:$K$65,Volumenes!$B$38:$I$38)+SUMPRODUCT('Coef Fabricacion'!$L$65:$S$65,Volumenes!$B$12:$I$12)+SUMPRODUCT('Coef Fabricacion'!$T$65:$AA$65,Volumenes!$B$25:$I$25)+SUMPRODUCT('Coef Recargas'!$D$46:$T$46,Volumenes!$B$51:$R$51) -> 274460.8 | K54: =SUMPRODUCT('Coef Fabricacion'!$D$65:$K$65,Volumenes!$B$39:$I$39)+SUMPRODUCT('Coef Fabricacion'!$L$65:$S$65,Volumenes!$B$13:$I$13)+SUMPRODUCT('Coef Fabricacion'!$T$65:$AA$65,Volumenes!$B$26:$I$26)+SUMPRODUCT('Coef Recargas'!$D$46:$T$46,Volumenes!$B$52:$R$52) -> 321474.9 | L54: =SUMPRODUCT('Coef Fabricacion'!$D$65:$K$65,Volumenes!$B$40:$I$40)+SUMPRODUCT('Coef Fabricacion'!$L$65:$S$65,Volumenes!$B$14:$I$14)+SUMPRODUCT('Coef Fabricacion'!$T$65:$AA$65,Volumenes!$B$27:$I$27)+SUMPRODUCT('Coef Recargas'!$D$46:$T$46,Volumenes!$B$53:$R$53) -> 354330.9 | M54: =SUMPRODUCT('Coef Fabricacion'!$D$65:$K$65,Volumenes!$B$41:$I$41)+SUMPRODUCT('Coef Fabricacion'!$L$65:$S$65,Volumenes!$B$15:$I$15)+SUMPRODUCT('Coef Fabricacion'!$T$65:$AA$65,Volumenes!$B$28:$I$28)+SUMPRODUCT('Coef Recargas'!$D$46:$T$46,Volumenes!$B$54:$R$54) -> 388342 | N54: =IF(F54=0,"—",M54/F54) -> 5.8305407
A55: MP-51 | B55: Pasador + precinto de seguridad numerado | C55: u | D55: =SUMPRODUCT('Coef Fabricacion'!$D$66:$K$66,Volumenes!$B$32:$I$32)+SUMPRODUCT('Coef Fabricacion'!$L$66:$S$66,Volumenes!$B$6:$I$6)+SUMPRODUCT('Coef Fabricacion'!$T$66:$AA$66,Volumenes!$B$19:$I$19)+SUMPRODUCT('Coef Recargas'!$D$47:$T$47,Volumenes!$B$45:$R$45) -> 9294 | E55: =SUMPRODUCT('Coef Fabricacion'!$D$66:$K$66,Volumenes!$B$33:$I$33)+SUMPRODUCT('Coef Fabricacion'!$L$66:$S$66,Volumenes!$B$7:$I$7)+SUMPRODUCT('Coef Fabricacion'!$T$66:$AA$66,Volumenes!$B$20:$I$20)+SUMPRODUCT('Coef Recargas'!$D$47:$T$47,Volumenes!$B$46:$R$46) -> 21463 | F55: =SUMPRODUCT('Coef Fabricacion'!$D$66:$K$66,Volumenes!$B$34:$I$34)+SUMPRODUCT('Coef Fabricacion'!$L$66:$S$66,Volumenes!$B$8:$I$8)+SUMPRODUCT('Coef Fabricacion'!$T$66:$AA$66,Volumenes!$B$21:$I$21)+SUMPRODUCT('Coef Recargas'!$D$47:$T$47,Volumenes!$B$47:$R$47) -> 34540 | G55: =SUMPRODUCT('Coef Fabricacion'!$D$66:$K$66,Volumenes!$B$35:$I$35)+SUMPRODUCT('Coef Fabricacion'!$L$66:$S$66,Volumenes!$B$9:$I$9)+SUMPRODUCT('Coef Fabricacion'!$T$66:$AA$66,Volumenes!$B$22:$I$22)+SUMPRODUCT('Coef Recargas'!$D$47:$T$47,Volumenes!$B$48:$R$48) -> 56599 | H55: =SUMPRODUCT('Coef Fabricacion'!$D$66:$K$66,Volumenes!$B$36:$I$36)+SUMPRODUCT('Coef Fabricacion'!$L$66:$S$66,Volumenes!$B$10:$I$10)+SUMPRODUCT('Coef Fabricacion'!$T$66:$AA$66,Volumenes!$B$23:$I$23)+SUMPRODUCT('Coef Recargas'!$D$47:$T$47,Volumenes!$B$49:$R$49) -> 84515 | I55: =SUMPRODUCT('Coef Fabricacion'!$D$66:$K$66,Volumenes!$B$37:$I$37)+SUMPRODUCT('Coef Fabricacion'!$L$66:$S$66,Volumenes!$B$11:$I$11)+SUMPRODUCT('Coef Fabricacion'!$T$66:$AA$66,Volumenes!$B$24:$I$24)+SUMPRODUCT('Coef Recargas'!$D$47:$T$47,Volumenes!$B$50:$R$50) -> 113429 | J55: =SUMPRODUCT('Coef Fabricacion'!$D$66:$K$66,Volumenes!$B$38:$I$38)+SUMPRODUCT('Coef Fabricacion'!$L$66:$S$66,Volumenes!$B$12:$I$12)+SUMPRODUCT('Coef Fabricacion'!$T$66:$AA$66,Volumenes!$B$25:$I$25)+SUMPRODUCT('Coef Recargas'!$D$47:$T$47,Volumenes!$B$51:$R$51) -> 142693 | K55: =SUMPRODUCT('Coef Fabricacion'!$D$66:$K$66,Volumenes!$B$39:$I$39)+SUMPRODUCT('Coef Fabricacion'!$L$66:$S$66,Volumenes!$B$13:$I$13)+SUMPRODUCT('Coef Fabricacion'!$T$66:$AA$66,Volumenes!$B$26:$I$26)+SUMPRODUCT('Coef Recargas'!$D$47:$T$47,Volumenes!$B$52:$R$52) -> 166813 | L55: =SUMPRODUCT('Coef Fabricacion'!$D$66:$K$66,Volumenes!$B$40:$I$40)+SUMPRODUCT('Coef Fabricacion'!$L$66:$S$66,Volumenes!$B$14:$I$14)+SUMPRODUCT('Coef Fabricacion'!$T$66:$AA$66,Volumenes!$B$27:$I$27)+SUMPRODUCT('Coef Recargas'!$D$47:$T$47,Volumenes!$B$53:$R$53) -> 183735 | M55: =SUMPRODUCT('Coef Fabricacion'!$D$66:$K$66,Volumenes!$B$41:$I$41)+SUMPRODUCT('Coef Fabricacion'!$L$66:$S$66,Volumenes!$B$15:$I$15)+SUMPRODUCT('Coef Fabricacion'!$T$66:$AA$66,Volumenes!$B$28:$I$28)+SUMPRODUCT('Coef Recargas'!$D$47:$T$47,Volumenes!$B$54:$R$54) -> 201243 | N55: =IF(F55=0,"—",M55/F55) -> 5.8263752
A56: MP-52 | B56: Soporte de pared (1–10 kg) | C56: u | D56: =SUMPRODUCT('Coef Fabricacion'!$D$67:$K$67,Volumenes!$B$32:$I$32)+SUMPRODUCT('Coef Fabricacion'!$L$67:$S$67,Volumenes!$B$6:$I$6)+SUMPRODUCT('Coef Fabricacion'!$T$67:$AA$67,Volumenes!$B$19:$I$19) -> 6822 | E56: =SUMPRODUCT('Coef Fabricacion'!$D$67:$K$67,Volumenes!$B$33:$I$33)+SUMPRODUCT('Coef Fabricacion'!$L$67:$S$67,Volumenes!$B$7:$I$7)+SUMPRODUCT('Coef Fabricacion'!$T$67:$AA$67,Volumenes!$B$20:$I$20) -> 10730 | F56: =SUMPRODUCT('Coef Fabricacion'!$D$67:$K$67,Volumenes!$B$34:$I$34)+SUMPRODUCT('Coef Fabricacion'!$L$67:$S$67,Volumenes!$B$8:$I$8)+SUMPRODUCT('Coef Fabricacion'!$T$67:$AA$67,Volumenes!$B$21:$I$21) -> 13186 | G56: =SUMPRODUCT('Coef Fabricacion'!$D$67:$K$67,Volumenes!$B$35:$I$35)+SUMPRODUCT('Coef Fabricacion'!$L$67:$S$67,Volumenes!$B$9:$I$9)+SUMPRODUCT('Coef Fabricacion'!$T$67:$AA$67,Volumenes!$B$22:$I$22) -> 17149 | H56: =SUMPRODUCT('Coef Fabricacion'!$D$67:$K$67,Volumenes!$B$36:$I$36)+SUMPRODUCT('Coef Fabricacion'!$L$67:$S$67,Volumenes!$B$10:$I$10)+SUMPRODUCT('Coef Fabricacion'!$T$67:$AA$67,Volumenes!$B$23:$I$23) -> 26415 | I56: =SUMPRODUCT('Coef Fabricacion'!$D$67:$K$67,Volumenes!$B$37:$I$37)+SUMPRODUCT('Coef Fabricacion'!$L$67:$S$67,Volumenes!$B$11:$I$11)+SUMPRODUCT('Coef Fabricacion'!$T$67:$AA$67,Volumenes!$B$24:$I$24) -> 34350 | J56: =SUMPRODUCT('Coef Fabricacion'!$D$67:$K$67,Volumenes!$B$38:$I$38)+SUMPRODUCT('Coef Fabricacion'!$L$67:$S$67,Volumenes!$B$12:$I$12)+SUMPRODUCT('Coef Fabricacion'!$T$67:$AA$67,Volumenes!$B$25:$I$25) -> 44441 | K56: =SUMPRODUCT('Coef Fabricacion'!$D$67:$K$67,Volumenes!$B$39:$I$39)+SUMPRODUCT('Coef Fabricacion'!$L$67:$S$67,Volumenes!$B$13:$I$13)+SUMPRODUCT('Coef Fabricacion'!$T$67:$AA$67,Volumenes!$B$26:$I$26) -> 55000 | L56: =SUMPRODUCT('Coef Fabricacion'!$D$67:$K$67,Volumenes!$B$40:$I$40)+SUMPRODUCT('Coef Fabricacion'!$L$67:$S$67,Volumenes!$B$14:$I$14)+SUMPRODUCT('Coef Fabricacion'!$T$67:$AA$67,Volumenes!$B$27:$I$27) -> 63348 | M56: =SUMPRODUCT('Coef Fabricacion'!$D$67:$K$67,Volumenes!$B$41:$I$41)+SUMPRODUCT('Coef Fabricacion'!$L$67:$S$67,Volumenes!$B$15:$I$15)+SUMPRODUCT('Coef Fabricacion'!$T$67:$AA$67,Volumenes!$B$28:$I$28) -> 72090 | N56: =IF(F56=0,"—",M56/F56) -> 5.4671621
A57: MP-53 | B57: Estructura de carro (chasis, eje, manija, ganchos) | C57: u | D57: =SUMPRODUCT('Coef Fabricacion'!$D$68:$K$68,Volumenes!$B$32:$I$32)+SUMPRODUCT('Coef Fabricacion'!$L$68:$S$68,Volumenes!$B$6:$I$6)+SUMPRODUCT('Coef Fabricacion'!$T$68:$AA$68,Volumenes!$B$19:$I$19) -> 136 | E57: =SUMPRODUCT('Coef Fabricacion'!$D$68:$K$68,Volumenes!$B$33:$I$33)+SUMPRODUCT('Coef Fabricacion'!$L$68:$S$68,Volumenes!$B$7:$I$7)+SUMPRODUCT('Coef Fabricacion'!$T$68:$AA$68,Volumenes!$B$20:$I$20) -> 233 | F57: =SUMPRODUCT('Coef Fabricacion'!$D$68:$K$68,Volumenes!$B$34:$I$34)+SUMPRODUCT('Coef Fabricacion'!$L$68:$S$68,Volumenes!$B$8:$I$8)+SUMPRODUCT('Coef Fabricacion'!$T$68:$AA$68,Volumenes!$B$21:$I$21) -> 302 | G57: =SUMPRODUCT('Coef Fabricacion'!$D$68:$K$68,Volumenes!$B$35:$I$35)+SUMPRODUCT('Coef Fabricacion'!$L$68:$S$68,Volumenes!$B$9:$I$9)+SUMPRODUCT('Coef Fabricacion'!$T$68:$AA$68,Volumenes!$B$22:$I$22) -> 402 | H57: =SUMPRODUCT('Coef Fabricacion'!$D$68:$K$68,Volumenes!$B$36:$I$36)+SUMPRODUCT('Coef Fabricacion'!$L$68:$S$68,Volumenes!$B$10:$I$10)+SUMPRODUCT('Coef Fabricacion'!$T$68:$AA$68,Volumenes!$B$23:$I$23) -> 623 | I57: =SUMPRODUCT('Coef Fabricacion'!$D$68:$K$68,Volumenes!$B$37:$I$37)+SUMPRODUCT('Coef Fabricacion'!$L$68:$S$68,Volumenes!$B$11:$I$11)+SUMPRODUCT('Coef Fabricacion'!$T$68:$AA$68,Volumenes!$B$24:$I$24) -> 846 | J57: =SUMPRODUCT('Coef Fabricacion'!$D$68:$K$68,Volumenes!$B$38:$I$38)+SUMPRODUCT('Coef Fabricacion'!$L$68:$S$68,Volumenes!$B$12:$I$12)+SUMPRODUCT('Coef Fabricacion'!$T$68:$AA$68,Volumenes!$B$25:$I$25) -> 1090 | K57: =SUMPRODUCT('Coef Fabricacion'!$D$68:$K$68,Volumenes!$B$39:$I$39)+SUMPRODUCT('Coef Fabricacion'!$L$68:$S$68,Volumenes!$B$13:$I$13)+SUMPRODUCT('Coef Fabricacion'!$T$68:$AA$68,Volumenes!$B$26:$I$26) -> 1352 | L57: =SUMPRODUCT('Coef Fabricacion'!$D$68:$K$68,Volumenes!$B$40:$I$40)+SUMPRODUCT('Coef Fabricacion'!$L$68:$S$68,Volumenes!$B$14:$I$14)+SUMPRODUCT('Coef Fabricacion'!$T$68:$AA$68,Volumenes!$B$27:$I$27) -> 1574 | M57: =SUMPRODUCT('Coef Fabricacion'!$D$68:$K$68,Volumenes!$B$41:$I$41)+SUMPRODUCT('Coef Fabricacion'!$L$68:$S$68,Volumenes!$B$15:$I$15)+SUMPRODUCT('Coef Fabricacion'!$T$68:$AA$68,Volumenes!$B$28:$I$28) -> 1813 | N57: =IF(F57=0,"—",M57/F57) -> 6.0033113
A58: MP-54 | B58: Ruedas de carro (par) Ø300–500 mm | C58: par | D58: =SUMPRODUCT('Coef Fabricacion'!$D$69:$K$69,Volumenes!$B$32:$I$32)+SUMPRODUCT('Coef Fabricacion'!$L$69:$S$69,Volumenes!$B$6:$I$6)+SUMPRODUCT('Coef Fabricacion'!$T$69:$AA$69,Volumenes!$B$19:$I$19) -> 136 | E58: =SUMPRODUCT('Coef Fabricacion'!$D$69:$K$69,Volumenes!$B$33:$I$33)+SUMPRODUCT('Coef Fabricacion'!$L$69:$S$69,Volumenes!$B$7:$I$7)+SUMPRODUCT('Coef Fabricacion'!$T$69:$AA$69,Volumenes!$B$20:$I$20) -> 233 | F58: =SUMPRODUCT('Coef Fabricacion'!$D$69:$K$69,Volumenes!$B$34:$I$34)+SUMPRODUCT('Coef Fabricacion'!$L$69:$S$69,Volumenes!$B$8:$I$8)+SUMPRODUCT('Coef Fabricacion'!$T$69:$AA$69,Volumenes!$B$21:$I$21) -> 302 | G58: =SUMPRODUCT('Coef Fabricacion'!$D$69:$K$69,Volumenes!$B$35:$I$35)+SUMPRODUCT('Coef Fabricacion'!$L$69:$S$69,Volumenes!$B$9:$I$9)+SUMPRODUCT('Coef Fabricacion'!$T$69:$AA$69,Volumenes!$B$22:$I$22) -> 402 | H58: =SUMPRODUCT('Coef Fabricacion'!$D$69:$K$69,Volumenes!$B$36:$I$36)+SUMPRODUCT('Coef Fabricacion'!$L$69:$S$69,Volumenes!$B$10:$I$10)+SUMPRODUCT('Coef Fabricacion'!$T$69:$AA$69,Volumenes!$B$23:$I$23) -> 623 | I58: =SUMPRODUCT('Coef Fabricacion'!$D$69:$K$69,Volumenes!$B$37:$I$37)+SUMPRODUCT('Coef Fabricacion'!$L$69:$S$69,Volumenes!$B$11:$I$11)+SUMPRODUCT('Coef Fabricacion'!$T$69:$AA$69,Volumenes!$B$24:$I$24) -> 846 | J58: =SUMPRODUCT('Coef Fabricacion'!$D$69:$K$69,Volumenes!$B$38:$I$38)+SUMPRODUCT('Coef Fabricacion'!$L$69:$S$69,Volumenes!$B$12:$I$12)+SUMPRODUCT('Coef Fabricacion'!$T$69:$AA$69,Volumenes!$B$25:$I$25) -> 1090 | K58: =SUMPRODUCT('Coef Fabricacion'!$D$69:$K$69,Volumenes!$B$39:$I$39)+SUMPRODUCT('Coef Fabricacion'!$L$69:$S$69,Volumenes!$B$13:$I$13)+SUMPRODUCT('Coef Fabricacion'!$T$69:$AA$69,Volumenes!$B$26:$I$26) -> 1352 | L58: =SUMPRODUCT('Coef Fabricacion'!$D$69:$K$69,Volumenes!$B$40:$I$40)+SUMPRODUCT('Coef Fabricacion'!$L$69:$S$69,Volumenes!$B$14:$I$14)+SUMPRODUCT('Coef Fabricacion'!$T$69:$AA$69,Volumenes!$B$27:$I$27) -> 1574 | M58: =SUMPRODUCT('Coef Fabricacion'!$D$69:$K$69,Volumenes!$B$41:$I$41)+SUMPRODUCT('Coef Fabricacion'!$L$69:$S$69,Volumenes!$B$15:$I$15)+SUMPRODUCT('Coef Fabricacion'!$T$69:$AA$69,Volumenes!$B$28:$I$28) -> 1813 | N58: =IF(F58=0,"—",M58/F58) -> 6.0033113
A59: MP-55 | B59: Conjunto de seguridad CO₂ (IRAM 2736) | C59: u | D59: =SUMPRODUCT('Coef Recargas'!$D$48:$T$48,Volumenes!$B$45:$R$45) -> 68.95 | E59: =SUMPRODUCT('Coef Recargas'!$D$48:$T$48,Volumenes!$B$46:$R$46) -> 280.7 | F59: =SUMPRODUCT('Coef Recargas'!$D$48:$T$48,Volumenes!$B$47:$R$47) -> 638.75 | G59: =SUMPRODUCT('Coef Recargas'!$D$48:$T$48,Volumenes!$B$48:$R$48) -> 1200.85 | H59: =SUMPRODUCT('Coef Recargas'!$D$48:$T$48,Volumenes!$B$49:$R$49) -> 1733.55 | I59: =SUMPRODUCT('Coef Recargas'!$D$48:$T$48,Volumenes!$B$50:$R$50) -> 2305.45 | J59: =SUMPRODUCT('Coef Recargas'!$D$48:$T$48,Volumenes!$B$51:$R$51) -> 2828 | K59: =SUMPRODUCT('Coef Recargas'!$D$48:$T$48,Volumenes!$B$52:$R$52) -> 3143 | L59: =SUMPRODUCT('Coef Recargas'!$D$48:$T$48,Volumenes!$B$53:$R$53) -> 3397.1 | M59: =SUMPRODUCT('Coef Recargas'!$D$48:$T$48,Volumenes!$B$54:$R$54) -> 3655.4 | N59: =IF(F59=0,"—",M59/F59) -> 5.7227397
A60: MP-56 | B60: Oblea/etiqueta IRAM 3534 + calcos + QR (fabricación) | C60: u | D60: =SUMPRODUCT('Coef Fabricacion'!$D$70:$K$70,Volumenes!$B$32:$I$32)+SUMPRODUCT('Coef Fabricacion'!$L$70:$S$70,Volumenes!$B$6:$I$6)+SUMPRODUCT('Coef Fabricacion'!$T$70:$AA$70,Volumenes!$B$19:$I$19) -> 6958 | E60: =SUMPRODUCT('Coef Fabricacion'!$D$70:$K$70,Volumenes!$B$33:$I$33)+SUMPRODUCT('Coef Fabricacion'!$L$70:$S$70,Volumenes!$B$7:$I$7)+SUMPRODUCT('Coef Fabricacion'!$T$70:$AA$70,Volumenes!$B$20:$I$20) -> 10963 | F60: =SUMPRODUCT('Coef Fabricacion'!$D$70:$K$70,Volumenes!$B$34:$I$34)+SUMPRODUCT('Coef Fabricacion'!$L$70:$S$70,Volumenes!$B$8:$I$8)+SUMPRODUCT('Coef Fabricacion'!$T$70:$AA$70,Volumenes!$B$21:$I$21) -> 13488 | G60: =SUMPRODUCT('Coef Fabricacion'!$D$70:$K$70,Volumenes!$B$35:$I$35)+SUMPRODUCT('Coef Fabricacion'!$L$70:$S$70,Volumenes!$B$9:$I$9)+SUMPRODUCT('Coef Fabricacion'!$T$70:$AA$70,Volumenes!$B$22:$I$22) -> 17551 | H60: =SUMPRODUCT('Coef Fabricacion'!$D$70:$K$70,Volumenes!$B$36:$I$36)+SUMPRODUCT('Coef Fabricacion'!$L$70:$S$70,Volumenes!$B$10:$I$10)+SUMPRODUCT('Coef Fabricacion'!$T$70:$AA$70,Volumenes!$B$23:$I$23) -> 27038 | I60: =SUMPRODUCT('Coef Fabricacion'!$D$70:$K$70,Volumenes!$B$37:$I$37)+SUMPRODUCT('Coef Fabricacion'!$L$70:$S$70,Volumenes!$B$11:$I$11)+SUMPRODUCT('Coef Fabricacion'!$T$70:$AA$70,Volumenes!$B$24:$I$24) -> 35196 | J60: =SUMPRODUCT('Coef Fabricacion'!$D$70:$K$70,Volumenes!$B$38:$I$38)+SUMPRODUCT('Coef Fabricacion'!$L$70:$S$70,Volumenes!$B$12:$I$12)+SUMPRODUCT('Coef Fabricacion'!$T$70:$AA$70,Volumenes!$B$25:$I$25) -> 45531 | K60: =SUMPRODUCT('Coef Fabricacion'!$D$70:$K$70,Volumenes!$B$39:$I$39)+SUMPRODUCT('Coef Fabricacion'!$L$70:$S$70,Volumenes!$B$13:$I$13)+SUMPRODUCT('Coef Fabricacion'!$T$70:$AA$70,Volumenes!$B$26:$I$26) -> 56352 | L60: =SUMPRODUCT('Coef Fabricacion'!$D$70:$K$70,Volumenes!$B$40:$I$40)+SUMPRODUCT('Coef Fabricacion'!$L$70:$S$70,Volumenes!$B$14:$I$14)+SUMPRODUCT('Coef Fabricacion'!$T$70:$AA$70,Volumenes!$B$27:$I$27) -> 64922 | M60: =SUMPRODUCT('Coef Fabricacion'!$D$70:$K$70,Volumenes!$B$41:$I$41)+SUMPRODUCT('Coef Fabricacion'!$L$70:$S$70,Volumenes!$B$15:$I$15)+SUMPRODUCT('Coef Fabricacion'!$T$70:$AA$70,Volumenes!$B$28:$I$28) -> 73903 | N60: =IF(F60=0,"—",M60/F60) -> 5.4791667
A61: MP-57 | B61: Marbete/oblea de mantenimiento IRAM 3517-2 (recargas) | C61: u | D61: =SUMPRODUCT('Coef Recargas'!$D$49:$T$49,Volumenes!$B$45:$R$45) -> 2336 | E61: =SUMPRODUCT('Coef Recargas'!$D$49:$T$49,Volumenes!$B$46:$R$46) -> 10500 | F61: =SUMPRODUCT('Coef Recargas'!$D$49:$T$49,Volumenes!$B$47:$R$47) -> 21052 | G61: =SUMPRODUCT('Coef Recargas'!$D$49:$T$49,Volumenes!$B$48:$R$48) -> 39048 | H61: =SUMPRODUCT('Coef Recargas'!$D$49:$T$49,Volumenes!$B$49:$R$49) -> 57477 | I61: =SUMPRODUCT('Coef Recargas'!$D$49:$T$49,Volumenes!$B$50:$R$50) -> 78233 | J61: =SUMPRODUCT('Coef Recargas'!$D$49:$T$49,Volumenes!$B$51:$R$51) -> 97162 | K61: =SUMPRODUCT('Coef Recargas'!$D$49:$T$49,Volumenes!$B$52:$R$52) -> 110461 | L61: =SUMPRODUCT('Coef Recargas'!$D$49:$T$49,Volumenes!$B$53:$R$53) -> 118813 | M61: =SUMPRODUCT('Coef Recargas'!$D$49:$T$49,Volumenes!$B$54:$R$54) -> 127340 | N61: =IF(F61=0,"—",M61/F61) -> 6.0488315
