Workbook

Sheet Resumen
A1: Recargas 2035 — pulmón, vehículos y transitorios
A2: FLAMA S.A. · Proyecto Final UTN-FRBA. Todo se calcula con los datos de Supuestos (celdas amarillas).
A4: 1. ¿Cuántos llegan?
A5: Recargas 2035 (u/año) | B5: ='Demanda y mix'!D23 -> 127340 | C5: Dimensionamiento_Recargas, datos_base
A6: Llegan por día — mes promedio (u/día) | B6: ='Demanda y mix'!O57 -> 530.58333 | C6: año ÷ 12 meses ÷ 20 días hábiles
A7: Llegan por día — mes pico (u/día) | B7: ='Demanda y mix'!P57 -> 594.89565
A8: Mes pico | B8: ='Demanda y mix'!B59 -> Dic
A9: Llegan en el día pico (u/día) | B9: ='Demanda y mix'!Q57 -> 684.13 | C9: mes pico × factor del día pico
A10: Llegan por turno en el día pico (u/turno) | B10: =B9/Supuestos!$B$8 -> 342.065
A12: 2. Mix entrante
A13: Familia | B13: % del total | C13: u/día promedio | D13: u/día mes pico
A14: ='Demanda y mix'!A64 -> ABC 1 kg | B14: ='Demanda y mix'!C64 -> 0.52776818 | C14: ='Demanda y mix'!D64 -> 280.025 | D14: ='Demanda y mix'!E64 -> 336.02267
A15: ='Demanda y mix'!A65 -> Manual 2,5 a 6 kg/l | B15: ='Demanda y mix'!C65 -> 0.3935684 | C15: ='Demanda y mix'!D65 -> 208.82083 | D15: ='Demanda y mix'!E65 -> 216.7124
A16: ='Demanda y mix'!A66 -> Manual 9 a 10 kg/l | B16: ='Demanda y mix'!C66 -> 0.065203392 | C16: ='Demanda y mix'!D66 -> 34.595833 | D16: ='Demanda y mix'!E66 -> 35.001636
A17: ='Demanda y mix'!A67 -> Rodante | B17: ='Demanda y mix'!C67 -> 0.013460028 | C17: ='Demanda y mix'!D67 -> 7.1416667 | D17: ='Demanda y mix'!E67 -> 7.1589454
A19: Rubro | B19: % del total | C19: u/día promedio | D19: u/día mes pico | E19: Vehículo
A20: ='Demanda y mix'!A50 -> Automotriz | B20: ='Demanda y mix'!B50/'Demanda y mix'!B57 -> 0.54949806 | C20: ='Demanda y mix'!O50 -> 291.55451 | D20: ='Demanda y mix'!P50 -> 349.86542 | E20: ='Vehículos y viajes'!B14 -> Kangoo
A21: ='Demanda y mix'!A51 -> Edificios | B21: ='Demanda y mix'!B51/'Demanda y mix'!B57 -> 0.24891499 | C21: ='Demanda y mix'!O51 -> 132.07015 | D21: ='Demanda y mix'!P51 -> 142.63576 | E21: ='Vehículos y viajes'!B15 -> Master
A22: ='Demanda y mix'!A52 -> Salud | B22: ='Demanda y mix'!B52/'Demanda y mix'!B57 -> 0.038744495 | C22: ='Demanda y mix'!O52 -> 20.557183 | D22: ='Demanda y mix'!P52 -> 19.734896 | E22: ='Vehículos y viajes'!B16 -> Master
A23: ='Demanda y mix'!A53 -> Educación | B23: ='Demanda y mix'!B53/'Demanda y mix'!B57 -> 0.073301449 | C23: ='Demanda y mix'!O53 -> 38.892527 | D23: ='Demanda y mix'!P53 -> 32.669723 | E23: ='Vehículos y viajes'!B17 -> Master
A24: ='Demanda y mix'!A54 -> Hoteles | B24: ='Demanda y mix'!B54/'Demanda y mix'!B57 -> 0.032356722 | C24: ='Demanda y mix'!O54 -> 17.167937 | D24: ='Demanda y mix'!P54 -> 20.601525 | E24: ='Vehículos y viajes'!B18 -> Master
A25: ='Demanda y mix'!A55 -> Industrias | B25: ='Demanda y mix'!B55/'Demanda y mix'!B57 -> 0.053085814 | C25: ='Demanda y mix'!O55 -> 28.166448 | D25: ='Demanda y mix'!P55 -> 27.03979 | E25: ='Vehículos y viajes'!B19 -> Master
A26: ='Demanda y mix'!A56 -> Supermercados | B26: ='Demanda y mix'!B56/'Demanda y mix'!B57 -> 0.004098464 | C26: ='Demanda y mix'!O56 -> 2.1745767 | D26: ='Demanda y mix'!P56 -> 2.3485428 | E26: ='Vehículos y viajes'!B20 -> Kangoo
A28: 3. Vehículos y viajes (dimensionado para el día pico)
A29: Kangoo Express furgón (cantidad) | B29: ='Vehículos y viajes'!E65 -> 3 | C29: autos (puntos de acopio) y supermercados
A30: Master que conviene | B30: ='Vehículos y viajes'!B50 -> Master L1H1 | C30: menos vehículos y, si empatan, la más barata
A31: Master (cantidad) | B31: ='Vehículos y viajes'!E66 -> 4 | C31: edificios, salud, educación, hoteles e industrias
A32: Viajes por día en el día pico | B32: ='Vehículos y viajes'!G67 -> 11.667618 | C32: cada viaje entrega, retira y cambia transitorios
A33: Paradas por día en el día pico | B33: ='Vehículos y viajes'!I61 -> 65.180777
A34: Inversión en vehículos (ARS, oct-2026) | B34: ='Vehículos y viajes'!H67 -> 371999455
A36: 4. Transitorios
A37: Stock recomendado (u) | B37: ='Transitorios y pulmón'!H23 -> 2646 | C37: mes pico, ciclo base, con margen
A38: Punto mínimo (u) | B38: ='Transitorios y pulmón'!I23 -> 1066 | C38: día promedio con el ciclo más corto
A39: Días que tarda en volver (base) | B39: ='Transitorios y pulmón'!B30 -> 4.0173952 | C39: proceso + espera + revisión del transitorio
A40: Revisiones y recargas extra por año (u) | B40: ='Transitorios y pulmón'!B36 -> 3436.3333
A41: … como % de las recargas 2035 | B41: ='Transitorios y pulmón'!C36 -> 0.026985498
A43: 5. Pulmón de recargas (día pico)
A44: Zona | B44: Posiciones necesarias | C44: En el plano | D44: Faltan (−) / sobran (+)
A45: ='Transitorios y pulmón'!A40 -> Recepción (R0) | B45: ='Transitorios y pulmón'!E40 -> 14 | C45: ='Transitorios y pulmón'!F40 -> 16 | D45: ='Transitorios y pulmón'!G40 -> 2
A46: ='Transitorios y pulmón'!A41 -> Despacho | B46: ='Transitorios y pulmón'!E41 -> 14 | C46: ='Transitorios y pulmón'!F41 -> 7 | D46: ='Transitorios y pulmón'!G41 -> -7
A47: ='Transitorios y pulmón'!A42 -> Transitorios en la planta | B47: ='Transitorios y pulmón'!E42 -> 14 | C47: ='Transitorios y pulmón'!F42 -> 0 | D47: ='Transitorios y pulmón'!G42 -> -14
A48: ='Transitorios y pulmón'!A43 -> Jaulas vacías | B48: ='Transitorios y pulmón'!E43 -> 4 | C48: ='Transitorios y pulmón'!F43 -> 5 | D48: ='Transitorios y pulmón'!G43 -> 1
A49: ='Transitorios y pulmón'!A44 -> Total | B49: ='Transitorios y pulmón'!E44 -> 46 | C49: ='Transitorios y pulmón'!F44 -> 28 | D49: ='Transitorios y pulmón'!G44 -> -18
A50: Superficie del pulmón con su pasillo (m²) | B50: ='Transitorios y pulmón'!B45 -> 110.4
A52: 6. Supuestos para validar con el grupo
A53: • Estacionalidad: el archivo la tiene pareja (8,33 %); se usó un perfil supuesto por rubro (Supuestos, punto 8).
A54: • Cantidad de matafuegos por cliente y minutos por matafuego en el cliente (Supuestos, punto 7): el consolidado no trae clientes.
A55: • Zona de clientes en AMBA, a ~1,5 h ida y vuelta; 2 turnos de logística de 7,5 h.
A56: • Precios de Master L2H2 y L3H2 estimados con la relación de precios de lanzamiento; Kangoo = Express furgón.
A57: • Los autos (1 kg) se retiran en puntos de acopio (flotas, concesionarias, lubricentros), no casa por casa.
A58: • Peso lleno de cada tipo: valores típicos de catálogo (Supuestos, punto 6).
A60: Fuentes
A61: Dimensionamiento_Recargas_Planta_Industrial.xlsx (datos_base y parametros_recargas) — demanda 2035, % con PH, horas.
A62: CONSOLIDADO_24.xlsx — recargas del mercado por rubro y tipo (hojas MERCADO TOTAL de cada rubro).
A63: Renault Master MY2026: 16 Válvulas, jul-2025 (precios de lanzamiento, volumen y capacidad de carga) y configurador Renault (L1H1).
A64: Kangoo Express: Autotest (3,3 m³, hasta 750 kg) y elcerokm (precio furgón 1.6 SCe).
A65: Proceso de recargas (documento del grupo): jaulas A y B de 1,2 × 1,0 m y sustitutos (9.4.5).

Sheet Supuestos
A1: Supuestos — pulmón de recargas, vehículos y transitorios (FLAMA S.A., año 2035)
A2: Celdas con fondo amarillo y texto azul: datos o supuestos que se pueden cambiar. Todo lo demás del libro se calcula solo con fórmulas.
A4: 1. Generales
A5: Dato | B5: Valor | C5: Unidad | D5: Fuente / criterio
A6: Días hábiles por mes | B6: 20 | C6: días | D6: Dimensionamiento_Recargas (parametros_recargas). Pedido: dividir por 12 y por 20.
A7: Meses por año | B7: 12 | C7: meses
A8: Turnos de logística por día | B8: 2 | C8: turnos | D8: Dos turnos: los vehículos salen a la mañana y a la tarde.
A9: Horas productivas por turno | B9: 7.5 | C9: h | D9: Dimensionamiento_Recargas: 8 h − 30 min de refrigerio.
A10: Factor del día pico dentro del mes pico | B10: 1.15 | C10: × | D10: Supuesto: variación de un día a otro (+15 %).
A12: 2. Recorrido de los vehículos
A13: Dato | B13: Valor | C13: Unidad | D13: Fuente / criterio
A14: Ida y vuelta planta ↔ zona de clientes | B14: 1.5 | C14: h por viaje | D14: Supuesto: clientes en AMBA, ~25 km promedio por tramo.
A15: Tiempo fijo por parada | B15: 20 | C15: min | D15: Supuesto: estacionar, presentarse, remito y firma.
A16: Tiempo de manejo entre paradas | B16: 15 | C16: min | D16: Supuesto.
A17: Personas en el vehículo (chofer + ayudante) | B17: 2 | C17: personas | D17: Se descuentan de la carga útil.
A18: Peso por persona | B18: 80 | C18: kg
A19: Tara de estantería, cinchas y cajones | B19: 0.1 | C19: de la carga útil | D19: Supuesto.
A20: Aprovechamiento del piso de carga | B20: 0.75 | C20: del piso | D20: Descuenta pasarruedas, pasillo de carga y ataduras.
A21: Niveles de carga (estantería con celdas) | B21: 2 | C21: niveles | D21: Manuales en 2 niveles; los rodantes ocupan toda la altura.
A23: 3. Ciclo del transitorio (días hábiles)
A24: Dato | B24: Base | C24: Mínimo | D24: Fuente / criterio
A25: Proceso en planta sin prueba hidráulica | B25: 2 | C25: 1 | D25: Supuesto: entra un día y sale al siguiente.
A26: Proceso en planta con prueba hidráulica (PH + secado) | B26: 4 | C26: 3 | D26: Supuesto.
A27: Espera en despacho hasta el recorrido | B27: 0.5 | C27: 0 | D27: Con 2 turnos sale en el turno siguiente.
A28: Revisión del transitorio cuando vuelve | B28: 1 | C28: 0.5 | D28: Control de peso, presión y precinto antes de volver a salir.
A29: Dato | B29: Valor | C29: Unidad | D29: Fuente / criterio
A30: Margen de seguridad del stock de transitorios | B30: 0.1 | C30: del stock | D30: Supuesto.
A31: Revisión o recarga anual de cada transitorio | B31: 1 | C31: veces por año | D31: Pedido: todos los años se les hace recarga o revisión.
A32: Días fuera de servicio por revisión o recarga | B32: 3 | C32: días | D32: Supuesto: pasa por el proceso como cualquier recarga.
A33: Salidas en que el cliente usa el transitorio | B33: 0.005 | C33: de las salidas | D33: Supuesto: si lo usa, vuelve para recarga.
A35: 4. Pulmón de recargas
A36: Dato | B36: Valor | C36: Unidad | D36: Fuente / criterio
A37: Días de llegada que se guardan en recepción | B37: 0.5 | C37: días | D37: Con 2 turnos en la planta, lo que trae un turno entra al proceso en el turno siguiente.
A38: Días de recargados esperando el recorrido | B38: 0.5 | C38: días | D38: Con 2 turnos salen en el turno siguiente.
A39: Factor de jaulas a medio llenar | B39: 1.15 | C39: × | D39: Las jaulas se separan por cliente y familia de agente.
A40: Jaulas vacías de reserva | B40: 0.15 | C40: de las ocupadas | D40: Supuesto.
A41: Niveles de la estantería de transitorios | B41: 3 | C41: niveles | D41: Los transitorios son stock: van en estantería (los rodantes, en el piso).
A42: Jaulas vacías apiladas por posición | B42: 2 | C42: jaulas | D42: Vacías se apilan con transpaleta manual de a 2 (o con el apilador).
A43: Posiciones de recepción en el plano actual (R0) | B43: 16 | C43: posic. 1,2 × 1,0 | D43: Plano rev 50: 9 contra el muro norte + 7 contra el muro viejo.
A44: Posiciones de despacho en el plano actual | B44: 7 | C44: posic. 1,2 × 1,0 | D44: Plano rev 50.
A45: Posiciones de jaulas vacías en el plano actual | B45: 5 | C45: posic. 1,2 × 1,0 | D45: Plano rev 50.
A46: Posiciones de transitorios en el plano actual | B46: 0 | C46: posic. 1,2 × 1,0 | D46: Plano rev 50: todavía no hay lugar para transitorios.
A48: 5. Vehículos (Renault Argentina)
A49: Dato | B49: Kangoo Express | C49: Master L1H1 | D49: Master L2H2 | E49: Master L3H2 | F49: Fuente
A50: Largo útil de carga (m) | B50: 1.48 | C50: 2.583 | D50: 3.083 | E50: 3.733 | F50: Master: ficha Master III (L1H1 2.583 mm confirmado en el configurador de Renault). Kangoo: ficha Kangoo II Express.
A51: Ancho útil máximo (m) | B51: 1.46 | C51: 1.765 | D51: 1.765 | E51: 1.765 | F51: Ídem.
A52: Alto útil (m) | B52: 1.13 | C52: 1.7 | D52: 1.894 | E52: 1.894 | F52: H1 = techo bajo, H2 = techo alto.
A53: Volumen de carga (m³) | B53: 3.3 | C53: 8 | D53: 10.8 | E53: 13 | F53: Autotest (Kangoo) y 16 Válvulas, jul-2025 (Master).
A54: Carga útil (kg) | B54: 750 | C54: 1522 | D54: 1451 | E54: 1375 | F54: Autotest (Kangoo) y 16 Válvulas, jul-2025 (Master).
A55: Puede llevar rodantes (1 = sí) | B55: 0 | C55: 1 | D55: 1 | E55: 1 | F55: Kangoo: los rodantes no entran por altura (1,13 m) ni por peso.
A56: Precio de lanzamiento jul-2025 (ARS) | B56: — | C56: 48750000 | D56: 53140000 | E56: 56332600 | F56: 16 Válvulas, lanzamiento Master MY2026.
A57: Precio actual (ARS, oct-2026) | B57: 33626485 | C57: 67780000 | D57: =C57*D56/C56 -> 73883676 | E57: =C57*E56/C56 -> 78322536 | F57: Kangoo Express furgón 1.6 SCe (elcerokm). L1H1: configurador Renault (captura). L2H2 y L3H2: estimados con la relación de precios del lanzamiento; reemplazar por el precio del configurador.
A58: La Kangoo de la captura (Stepway) es de pasajeros: para recargas va la Kangoo Express furgón, con compartimiento de carga.
A60: 6. Tipos de matafuego
A61: Tipo | B61: Código en el consolidado | C61: Agente | D61: Familia | E61: Peso lleno (kg) | F61: u. por jaula 1,2 × 1,0 | G61: Rodante (1 = sí) | H61: % con PH | I61: m² de piso en el vehículo por u.
A62: ABC 1 kg | B62: ABC-1 | C62: ABC | D62: ABC 1 kg | E62: 2 | F62: 72 | G62: 0 | H62: 0.25 | I62: =1.2/F62/IF(G62=1,1,Supuestos!$B$21) -> 0.0083333333
A63: ABC 2,5 kg | B63: ABC-2.5 | C63: ABC | D63: Manual 2,5 a 6 kg/l | E63: 4.5 | F63: 30 | G63: 0 | H63: 0.25 | I63: =1.2/F63/IF(G63=1,1,Supuestos!$B$21) -> 0.02
A64: ABC 5 kg | B64: ABC-5 | C64: ABC | D64: Manual 2,5 a 6 kg/l | E64: 8.5 | F64: 24 | G64: 0 | H64: 0.25 | I64: =1.2/F64/IF(G64=1,1,Supuestos!$B$21) -> 0.025
A65: ABC 10 kg | B65: ABC-10P | C65: ABC | D65: Manual 9 a 10 kg/l | E65: 16 | F65: 16 | G65: 0 | H65: 0.25 | I65: =1.2/F65/IF(G65=1,1,Supuestos!$B$21) -> 0.0375
A66: Agua 10 l | B66: AGUA-10 | C66: Agua | D66: Manual 9 a 10 kg/l | E66: 14 | F66: 16 | G66: 0 | H66: 0.5 | I66: =1.2/F66/IF(G66=1,1,Supuestos!$B$21) -> 0.0375
A67: AFFF 10 l | B67: AFFF-9 | C67: AFFF | D67: Manual 9 a 10 kg/l | E67: 14.5 | F67: 16 | G67: 0 | H67: 0.5 | I67: =1.2/F67/IF(G67=1,1,Supuestos!$B$21) -> 0.0375
A68: AFFF 50 l s/ruedas | B68: AFFF-50R | C68: AFFF | D68: Rodante | E68: 90 | F68: 2 | G68: 1 | H68: 0.5 | I68: =1.2/F68/IF(G68=1,1,Supuestos!$B$21) -> 0.6
A69: BC 5 kg | B69: BC-5 | C69: BC | D69: Manual 2,5 a 6 kg/l | E69: 8.5 | F69: 24 | G69: 0 | H69: 0.25 | I69: =1.2/F69/IF(G69=1,1,Supuestos!$B$21) -> 0.025
A70: Sales K 6 l | B70: SALK-6 | C70: Sales K | D70: Manual 2,5 a 6 kg/l | E70: 10.5 | F70: 20 | G70: 0 | H70: 0.5 | I70: =1.2/F70/IF(G70=1,1,Supuestos!$B$21) -> 0.03
A71: CO₂ 2 kg | B71: CO2-2 | C71: CO₂ | D71: Manual 2,5 a 6 kg/l | E71: 7 | F71: 30 | G71: 0 | H71: 0.25 | I71: =1.2/F71/IF(G71=1,1,Supuestos!$B$21) -> 0.02
A72: CO₂ 5 kg | B72: CO2-5 | C72: CO₂ | D72: Manual 9 a 10 kg/l | E72: 15 | F72: 20 | G72: 0 | H72: 0.25 | I72: =1.2/F72/IF(G72=1,1,Supuestos!$B$21) -> 0.03
A73: HCFC/HFC 5 kg | B73: HCFC | C73: Halogenado | D73: Manual 2,5 a 6 kg/l | E73: 10 | F73: 24 | G73: 0 | H73: 0.25 | I73: =1.2/F73/IF(G73=1,1,Supuestos!$B$21) -> 0.025
... A78: ABC 100 kg s/ruedas | B78: ABC-50R | C78: ABC | D78: Rodante | E78: 160 | F78: 1 | G78: 1 | H78: 0.25 | I78: =1.2/F78/IF(G78=1,1,Supuestos!$B$21) -> 1.2
A79: Peso lleno: valores típicos de catálogo, a confirmar. u. por jaula: archivo de recargas (A: 72 de 1 kg; B: 30 de 2,5 kg, 24 de 5 kg o 16 de 10 kg); el resto, por tamaño parecido.
A80: % con PH: Dimensionamiento_Recargas (polvos 25 %, agua/AFFF/sales K 50 %, CO₂ 25 %, halogenados 25 %).
A82: 7. Segmentos de clientes (los 7 rubros del consolidado comercial)
A83: Segmento | B83: Vehículo | C83: u. por cliente (por parada) | D83: % de u. con transitorio | E83: min por u. en el cliente | F83: Cliente típico (criterio del supuesto)
A84: Automotriz | B84: Kangoo | C84: 25 | D84: 1 | E84: 0.5 | F84: Punto de acopio: flota, concesionaria o lubricentro. 97 % son de 1 kg.
A85: Edificios | B85: Master | C85: 14 | D85: 1 | E85: 1.5 | F85: Consorcio de ~10 pisos: uno por piso + cocheras, medidores y sala de máquinas.
A86: Salud | B86: Master | C86: 35 | D86: 0.9 | E86: 1.5 | F86: Clínica mediana; algunas tienen dotación de reserva propia.
A87: Educación | B87: Master | C87: 18 | D87: 1 | E87: 1.5 | F87: Escuela: aulas, pasillos, tableros y cocina.
A88: Hoteles | B88: Master | C88: 20 | D88: 1 | E88: 1.5 | F88: Hotel mediano; los alquileres temporarios se juntan por administradora.
A89: Industrias | B89: Master | C89: 45 | D89: 0.8 | E89: 1.5 | F89: Planta o depósito; el 20 % tiene reserva propia y no pide transitorio.
A90: Supermercados | B90: Kangoo | C90: 16 | D90: 1 | E90: 1 | F90: Sucursal: salón, cajas, depósito y tableros.
A91: u. por cliente y min por u.: supuestos (el consolidado no trae cantidad de clientes). Criterio: Kangoo para clientes chicos y puntos de acopio; Master para empresas, industrias y edificios completos.
A92: % con transitorio: se deja sustituto si el cliente no tiene dotación de reserva (proceso de recargas, 9.4.5).
A94: 8. Estacionalidad (% de la demanda anual de cada mes)
A95: Segmento | B95: Ene | C95: Feb | D95: Mar | E95: Abr | F95: May | G95: Jun | H95: Jul | I95: Ago | J95: Sep | K95: Oct | L95: Nov | M95: Dic | N95: Total (debe dar 100 %)
A96: Automotriz | B96: 0.09 | C96: 0.08 | D96: 0.08 | E96: 0.08 | F96: 0.08 | G96: 0.08 | H96: 0.08 | I96: 0.08 | J96: 0.08 | K96: 0.08 | L96: 0.09 | M96: 0.1 | N96: =SUM(B96:M96) -> 1
A97: Edificios | B97: 0.06 | C97: 0.07 | D97: 0.09 | E97: 0.09 | F97: 0.09 | G97: 0.08 | H97: 0.07 | I97: 0.09 | J97: 0.09 | K97: 0.09 | L97: 0.09 | M97: 0.09 | N97: =SUM(B97:M97) -> 1
A98: Salud | B98: 0.08 | C98: 0.08 | D98: 0.09 | E98: 0.08 | F98: 0.08 | G98: 0.08 | H98: 0.08 | I98: 0.09 | J98: 0.09 | K98: 0.08 | L98: 0.09 | M98: 0.08 | N98: =SUM(B98:M98) -> 1
A99: Educación | B99: 0.04 | C99: 0.18 | D99: 0.1 | E99: 0.07 | F99: 0.07 | G99: 0.07 | H99: 0.14 | I99: 0.07 | J99: 0.07 | K99: 0.06 | L99: 0.06 | M99: 0.07 | N99: =SUM(B99:M99) -> 1
A100: Hoteles | B100: 0.05 | C100: 0.05 | D100: 0.07 | E100: 0.08 | F100: 0.09 | G100: 0.1 | H100: 0.06 | I100: 0.07 | J100: 0.09 | K100: 0.11 | L100: 0.13 | M100: 0.1 | N100: =SUM(B100:M100) -> 1
A101: Industrias | B101: 0.05 | C101: 0.08 | D101: 0.09 | E101: 0.09 | F101: 0.09 | G101: 0.08 | H101: 0.08 | I101: 0.09 | J101: 0.09 | K101: 0.09 | L101: 0.09 | M101: 0.08 | N101: =SUM(B101:M101) -> 1
A102: Supermercados | B102: 0.08 | C102: 0.08 | D102: 0.08 | E102: 0.08 | F102: 0.08 | G102: 0.08 | H102: 0.08 | I102: 0.08 | J102: 0.09 | K102: 0.09 | L102: 0.09 | M102: 0.09 | N102: =SUM(B102:M102) -> 1
A103: En Dimensionamiento_Recargas la estacionalidad es pareja (8,33 % todos los meses). Este perfil es un supuesto para tener mes pico: autos con pico en diciembre (viajes), escuelas antes de clases (feb) y en el receso (jul),
A104: hoteles antes de temporada (oct-dic), consorcios e industrias más bajos en enero. Si tienen el perfil real, se pega acá y se recalcula todo.

Sheet Demanda y mix
A1: Demanda 2035 y mix entrante
A2: Cuántos matafuegos llegan por año, mes y día, de qué tipo y de qué rubro.
A4: 1. Recargas 2035 por tipo y por rubro (u/año)
A5: Tipo | B5: Código | C5: Familia | D5: Recargas 2035 (u/año) | E5: % del total | F5: Automotriz | G5: Edificios | H5: Salud | I5: Educación | J5: Hoteles | K5: Industrias | L5: Supermercados | M5: Control | N5: u/día promedio | O5: u/día mes pico | P5: u/día día pico
A6: =Supuestos!A62 -> ABC 1 kg | B6: =Supuestos!B62 -> ABC-1 | C6: =Supuestos!D62 -> ABC 1 kg | D6: 67206 | E6: =D6/$D$23 -> 0.52776818 | F6: =IFERROR($D6*INDEX($B$31:$B$44,MATCH($B6,$A$31:$A$44,0))/INDEX($I$31:$I$44,MATCH($B6,$A$31:$A$44,0)),0) -> 67173.077 | G6: =IFERROR($D6*INDEX($C$31:$C$44,MATCH($B6,$A$31:$A$44,0))/INDEX($I$31:$I$44,MATCH($B6,$A$31:$A$44,0)),0) -> 0 | H6: =IFERROR($D6*INDEX($D$31:$D$44,MATCH($B6,$A$31:$A$44,0))/INDEX($I$31:$I$44,MATCH($B6,$A$31:$A$44,0)),0) -> 0 | I6: =IFERROR($D6*INDEX($E$31:$E$44,MATCH($B6,$A$31:$A$44,0))/INDEX($I$31:$I$44,MATCH($B6,$A$31:$A$44,0)),0) -> 0 | J6: =IFERROR($D6*INDEX($F$31:$F$44,MATCH($B6,$A$31:$A$44,0))/INDEX($I$31:$I$44,MATCH($B6,$A$31:$A$44,0)),0) -> 18.260158 | K6: =IFERROR($D6*INDEX($G$31:$G$44,MATCH($B6,$A$31:$A$44,0))/INDEX($I$31:$I$44,MATCH($B6,$A$31:$A$44,0)),0) -> 0 | L6: =IFERROR($D6*INDEX($H$31:$H$44,MATCH($B6,$A$31:$A$44,0))/INDEX($I$31:$I$44,MATCH($B6,$A$31:$A$44,0)),0) -> 14.662722 | M6: =SUM(F6:L6)-D6 -> 0 | N6: =D6/(Supuestos!$B$7*Supuestos!$B$6) -> 280.025 | O6: =SUMPRODUCT(F6:L6,$F$24:$L$24)/Supuestos!$B$6 -> 336.02267 | P6: =O6*Supuestos!$B$10 -> 386.42607 | Q6: ← Recargas 2035: Dimensionamiento_Recargas, hoja datos_base (127.340 u).
A7: =Supuestos!A63 -> ABC 2,5 kg | B7: =Supuestos!B63 -> ABC-2.5 | C7: =Supuestos!D63 -> Manual 2,5 a 6 kg/l | D7: 5691 | E7: =D7/$D$23 -> 0.044691377 | F7: =IFERROR($D7*INDEX($B$31:$B$44,MATCH($B7,$A$31:$A$44,0))/INDEX($I$31:$I$44,MATCH($B7,$A$31:$A$44,0)),0) -> 0 | G7: =IFERROR($D7*INDEX($C$31:$C$44,MATCH($B7,$A$31:$A$44,0))/INDEX($I$31:$I$44,MATCH($B7,$A$31:$A$44,0)),0) -> 2409.8333 | H7: =IFERROR($D7*INDEX($D$31:$D$44,MATCH($B7,$A$31:$A$44,0))/INDEX($I$31:$I$44,MATCH($B7,$A$31:$A$44,0)),0) -> 313.40556 | I7: =IFERROR($D7*INDEX($E$31:$E$44,MATCH($B7,$A$31:$A$44,0))/INDEX($I$31:$I$44,MATCH($B7,$A$31:$A$44,0)),0) -> 1171.1417 | J7: =IFERROR($D7*INDEX($F$31:$F$44,MATCH($B7,$A$31:$A$44,0))/INDEX($I$31:$I$44,MATCH($B7,$A$31:$A$44,0)),0) -> 1597.5787 | K7: =IFERROR($D7*INDEX($G$31:$G$44,MATCH($B7,$A$31:$A$44,0))/INDEX($I$31:$I$44,MATCH($B7,$A$31:$A$44,0)),0) -> 0 | L7: =IFERROR($D7*INDEX($H$31:$H$44,MATCH($B7,$A$31:$A$44,0))/INDEX($I$31:$I$44,MATCH($B7,$A$31:$A$44,0)),0) -> 199.04075 | M7: =SUM(F7:L7)-D7 -> 0 | N7: =D7/(Supuestos!$B$7*Supuestos!$B$6) -> 23.7125 | O7: =SUMPRODUCT(F7:L7,$F$24:$L$24)/Supuestos!$B$6 -> 25.080445 | P7: =O7*Supuestos!$B$10 -> 28.842512 | Q7: La tabla de la captura suma además "TOTAL CARROS" (1.427) y da 128.766: cuenta los rodantes dos veces.
A8: =Supuestos!A64 -> ABC 5 kg | B8: =Supuestos!B64 -> ABC-5 | C8: =Supuestos!D64 -> Manual 2,5 a 6 kg/l | D8: 34614 | E8: =D8/$D$23 -> 0.27182346 | F8: =IFERROR($D8*INDEX($B$31:$B$44,MATCH($B8,$A$31:$A$44,0))/INDEX($I$31:$I$44,MATCH($B8,$A$31:$A$44,0)),0) -> 2800.0062 | G8: =IFERROR($D8*INDEX($C$31:$C$44,MATCH($B8,$A$31:$A$44,0))/INDEX($I$31:$I$44,MATCH($B8,$A$31:$A$44,0)),0) -> 20119.458 | H8: =IFERROR($D8*INDEX($D$31:$D$44,MATCH($B8,$A$31:$A$44,0))/INDEX($I$31:$I$44,MATCH($B8,$A$31:$A$44,0)),0) -> 2293.2739 | I8: =IFERROR($D8*INDEX($E$31:$E$44,MATCH($B8,$A$31:$A$44,0))/INDEX($I$31:$I$44,MATCH($B8,$A$31:$A$44,0)),0) -> 4992.3336 | J8: =IFERROR($D8*INDEX($F$31:$F$44,MATCH($B8,$A$31:$A$44,0))/INDEX($I$31:$I$44,MATCH($B8,$A$31:$A$44,0)),0) -> 1057.1033 | K8: =IFERROR($D8*INDEX($G$31:$G$44,MATCH($B8,$A$31:$A$44,0))/INDEX($I$31:$I$44,MATCH($B8,$A$31:$A$44,0)),0) -> 3154.3123 | L8: =IFERROR($D8*INDEX($H$31:$H$44,MATCH($B8,$A$31:$A$44,0))/INDEX($I$31:$I$44,MATCH($B8,$A$31:$A$44,0)),0) -> 197.51207 | M8: =SUM(F8:L8)-D8 -> 0 | N8: =D8/(Supuestos!$B$7*Supuestos!$B$6) -> 144.225 | O8: =SUMPRODUCT(F8:L8,$F$24:$L$24)/Supuestos!$B$6 -> 149.97543 | P8: =O8*Supuestos!$B$10 -> 172.47174 | Q8: Reparto por rubro: cada tipo se reparte como se reparten las recargas de ese tipo en el mercado (tabla 2).
A9: =Supuestos!A65 -> ABC 10 kg | B9: =Supuestos!B65 -> ABC-10P | C9: =Supuestos!D65 -> Manual 9 a 10 kg/l | D9: 2050 | E9: =D9/$D$23 -> 0.016098634 | F9: =IFERROR($D9*INDEX($B$31:$B$44,MATCH($B9,$A$31:$A$44,0))/INDEX($I$31:$I$44,MATCH($B9,$A$31:$A$44,0)),0) -> 0 | G9: =IFERROR($D9*INDEX($C$31:$C$44,MATCH($B9,$A$31:$A$44,0))/INDEX($I$31:$I$44,MATCH($B9,$A$31:$A$44,0)),0) -> 1084.9537 | H9: =IFERROR($D9*INDEX($D$31:$D$44,MATCH($B9,$A$31:$A$44,0))/INDEX($I$31:$I$44,MATCH($B9,$A$31:$A$44,0)),0) -> 269.74811 | I9: =IFERROR($D9*INDEX($E$31:$E$44,MATCH($B9,$A$31:$A$44,0))/INDEX($I$31:$I$44,MATCH($B9,$A$31:$A$44,0)),0) -> 472.08235 | J9: =IFERROR($D9*INDEX($F$31:$F$44,MATCH($B9,$A$31:$A$44,0))/INDEX($I$31:$I$44,MATCH($B9,$A$31:$A$44,0)),0) -> 223.21587 | K9: =IFERROR($D9*INDEX($G$31:$G$44,MATCH($B9,$A$31:$A$44,0))/INDEX($I$31:$I$44,MATCH($B9,$A$31:$A$44,0)),0) -> 0 | L9: =IFERROR($D9*INDEX($H$31:$H$44,MATCH($B9,$A$31:$A$44,0))/INDEX($I$31:$I$44,MATCH($B9,$A$31:$A$44,0)),0) -> 0 | M9: =SUM(F9:L9)-D9 -> 0 | N9: =D9/(Supuestos!$B$7*Supuestos!$B$6) -> 8.5416667 | O9: =SUMPRODUCT(F9:L9,$F$24:$L$24)/Supuestos!$B$6 -> 8.7296515 | P9: =O9*Supuestos!$B$10 -> 10.039099
A10: =Supuestos!A66 -> Agua 10 l | B10: =Supuestos!B66 -> AGUA-10 | C10: =Supuestos!D66 -> Manual 9 a 10 kg/l | D10: 2893 | E10: =D10/$D$23 -> 0.022718706 | F10: =IFERROR($D10*INDEX($B$31:$B$44,MATCH($B10,$A$31:$A$44,0))/INDEX($I$31:$I$44,MATCH($B10,$A$31:$A$44,0)),0) -> 0 | G10: =IFERROR($D10*INDEX($C$31:$C$44,MATCH($B10,$A$31:$A$44,0))/INDEX($I$31:$I$44,MATCH($B10,$A$31:$A$44,0)),0) -> 1516.9691 | H10: =IFERROR($D10*INDEX($D$31:$D$44,MATCH($B10,$A$31:$A$44,0))/INDEX($I$31:$I$44,MATCH($B10,$A$31:$A$44,0)),0) -> 426.59431 | I10: =IFERROR($D10*INDEX($E$31:$E$44,MATCH($B10,$A$31:$A$44,0))/INDEX($I$31:$I$44,MATCH($B10,$A$31:$A$44,0)),0) -> 449.14442 | J10: =IFERROR($D10*INDEX($F$31:$F$44,MATCH($B10,$A$31:$A$44,0))/INDEX($I$31:$I$44,MATCH($B10,$A$31:$A$44,0)),0) -> 164.71832 | K10: =IFERROR($D10*INDEX($G$31:$G$44,MATCH($B10,$A$31:$A$44,0))/INDEX($I$31:$I$44,MATCH($B10,$A$31:$A$44,0)),0) -> 315.36844 | L10: =IFERROR($D10*INDEX($H$31:$H$44,MATCH($B10,$A$31:$A$44,0))/INDEX($I$31:$I$44,MATCH($B10,$A$31:$A$44,0)),0) -> 20.205413 | M10: =SUM(F10:L10)-D10 -> 0 | N10: =D10/(Supuestos!$B$7*Supuestos!$B$6) -> 12.054167 | O10: =SUMPRODUCT(F10:L10,$F$24:$L$24)/Supuestos!$B$6 -> 12.280733 | P10: =O10*Supuestos!$B$10 -> 14.122843
A11: =Supuestos!A67 -> AFFF 10 l | B11: =Supuestos!B67 -> AFFF-9 | C11: =Supuestos!D67 -> Manual 9 a 10 kg/l | D11: 550 | E11: =D11/$D$23 -> 0.0043191456 | F11: =IFERROR($D11*INDEX($B$31:$B$44,MATCH($B11,$A$31:$A$44,0))/INDEX($I$31:$I$44,MATCH($B11,$A$31:$A$44,0)),0) -> 0 | G11: =IFERROR($D11*INDEX($C$31:$C$44,MATCH($B11,$A$31:$A$44,0))/INDEX($I$31:$I$44,MATCH($B11,$A$31:$A$44,0)),0) -> 0 | H11: =IFERROR($D11*INDEX($D$31:$D$44,MATCH($B11,$A$31:$A$44,0))/INDEX($I$31:$I$44,MATCH($B11,$A$31:$A$44,0)),0) -> 0 | I11: =IFERROR($D11*INDEX($E$31:$E$44,MATCH($B11,$A$31:$A$44,0))/INDEX($I$31:$I$44,MATCH($B11,$A$31:$A$44,0)),0) -> 0 | J11: =IFERROR($D11*INDEX($F$31:$F$44,MATCH($B11,$A$31:$A$44,0))/INDEX($I$31:$I$44,MATCH($B11,$A$31:$A$44,0)),0) -> 0 | K11: =IFERROR($D11*INDEX($G$31:$G$44,MATCH($B11,$A$31:$A$44,0))/INDEX($I$31:$I$44,MATCH($B11,$A$31:$A$44,0)),0) -> 550 | L11: =IFERROR($D11*INDEX($H$31:$H$44,MATCH($B11,$A$31:$A$44,0))/INDEX($I$31:$I$44,MATCH($B11,$A$31:$A$44,0)),0) -> 0 | M11: =SUM(F11:L11)-D11 -> 0 | N11: =D11/(Supuestos!$B$7*Supuestos!$B$6) -> 2.2916667 | O11: =SUMPRODUCT(F11:L11,$F$24:$L$24)/Supuestos!$B$6 -> 2.2 | P11: =O11*Supuestos!$B$10 -> 2.53
A12: =Supuestos!A68 -> AFFF 50 l s/ruedas | B12: =Supuestos!B68 -> AFFF-50R | C12: =Supuestos!D68 -> Rodante | D12: 287 | E12: =D12/$D$23 -> 0.0022538087 | F12: =IFERROR($D12*INDEX($B$31:$B$44,MATCH($B12,$A$31:$A$44,0))/INDEX($I$31:$I$44,MATCH($B12,$A$31:$A$44,0)),0) -> 0 | G12: =IFERROR($D12*INDEX($C$31:$C$44,MATCH($B12,$A$31:$A$44,0))/INDEX($I$31:$I$44,MATCH($B12,$A$31:$A$44,0)),0) -> 0 | H12: =IFERROR($D12*INDEX($D$31:$D$44,MATCH($B12,$A$31:$A$44,0))/INDEX($I$31:$I$44,MATCH($B12,$A$31:$A$44,0)),0) -> 0 | I12: =IFERROR($D12*INDEX($E$31:$E$44,MATCH($B12,$A$31:$A$44,0))/INDEX($I$31:$I$44,MATCH($B12,$A$31:$A$44,0)),0) -> 0 | J12: =IFERROR($D12*INDEX($F$31:$F$44,MATCH($B12,$A$31:$A$44,0))/INDEX($I$31:$I$44,MATCH($B12,$A$31:$A$44,0)),0) -> 0 | K12: =IFERROR($D12*INDEX($G$31:$G$44,MATCH($B12,$A$31:$A$44,0))/INDEX($I$31:$I$44,MATCH($B12,$A$31:$A$44,0)),0) -> 287 | L12: =IFERROR($D12*INDEX($H$31:$H$44,MATCH($B12,$A$31:$A$44,0))/INDEX($I$31:$I$44,MATCH($B12,$A$31:$A$44,0)),0) -> 0 | M12: =SUM(F12:L12)-D12 -> 0 | N12: =D12/(Supuestos!$B$7*Supuestos!$B$6) -> 1.1958333 | O12: =SUMPRODUCT(F12:L12,$F$24:$L$24)/Supuestos!$B$6 -> 1.148 | P12: =O12*Supuestos!$B$10 -> 1.3202
A13: =Supuestos!A69 -> BC 5 kg | B13: =Supuestos!B69 -> BC-5 | C13: =Supuestos!D69 -> Manual 2,5 a 6 kg/l | D13: 165 | E13: =D13/$D$23 -> 0.0012957437 | F13: =IFERROR($D13*INDEX($B$31:$B$44,MATCH($B13,$A$31:$A$44,0))/INDEX($I$31:$I$44,MATCH($B13,$A$31:$A$44,0)),0) -> 0 | G13: =IFERROR($D13*INDEX($C$31:$C$44,MATCH($B13,$A$31:$A$44,0))/INDEX($I$31:$I$44,MATCH($B13,$A$31:$A$44,0)),0) -> 0 | H13: =IFERROR($D13*INDEX($D$31:$D$44,MATCH($B13,$A$31:$A$44,0))/INDEX($I$31:$I$44,MATCH($B13,$A$31:$A$44,0)),0) -> 0 | I13: =IFERROR($D13*INDEX($E$31:$E$44,MATCH($B13,$A$31:$A$44,0))/INDEX($I$31:$I$44,MATCH($B13,$A$31:$A$44,0)),0) -> 0 | J13: =IFERROR($D13*INDEX($F$31:$F$44,MATCH($B13,$A$31:$A$44,0))/INDEX($I$31:$I$44,MATCH($B13,$A$31:$A$44,0)),0) -> 0 | K13: =IFERROR($D13*INDEX($G$31:$G$44,MATCH($B13,$A$31:$A$44,0))/INDEX($I$31:$I$44,MATCH($B13,$A$31:$A$44,0)),0) -> 165 | L13: =IFERROR($D13*INDEX($H$31:$H$44,MATCH($B13,$A$31:$A$44,0))/INDEX($I$31:$I$44,MATCH($B13,$A$31:$A$44,0)),0) -> 0 | M13: =SUM(F13:L13)-D13 -> 0 | N13: =D13/(Supuestos!$B$7*Supuestos!$B$6) -> 0.6875 | O13: =SUMPRODUCT(F13:L13,$F$24:$L$24)/Supuestos!$B$6 -> 0.66 | P13: =O13*Supuestos!$B$10 -> 0.759
A14: =Supuestos!A70 -> Sales K 6 l | B14: =Supuestos!B70 -> SALK-6 | C14: =Supuestos!D70 -> Manual 2,5 a 6 kg/l | D14: 1427 | E14: =D14/$D$23 -> 0.01120622 | F14: =IFERROR($D14*INDEX($B$31:$B$44,MATCH($B14,$A$31:$A$44,0))/INDEX($I$31:$I$44,MATCH($B14,$A$31:$A$44,0)),0) -> 0 | G14: =IFERROR($D14*INDEX($C$31:$C$44,MATCH($B14,$A$31:$A$44,0))/INDEX($I$31:$I$44,MATCH($B14,$A$31:$A$44,0)),0) -> 444.48792 | H14: =IFERROR($D14*INDEX($D$31:$D$44,MATCH($B14,$A$31:$A$44,0))/INDEX($I$31:$I$44,MATCH($B14,$A$31:$A$44,0)),0) -> 110.47537 | I14: =IFERROR($D14*INDEX($E$31:$E$44,MATCH($B14,$A$31:$A$44,0))/INDEX($I$31:$I$44,MATCH($B14,$A$31:$A$44,0)),0) -> 339.77907 | J14: =IFERROR($D14*INDEX($F$31:$F$44,MATCH($B14,$A$31:$A$44,0))/INDEX($I$31:$I$44,MATCH($B14,$A$31:$A$44,0)),0) -> 340.69068 | K14: =IFERROR($D14*INDEX($G$31:$G$44,MATCH($B14,$A$31:$A$44,0))/INDEX($I$31:$I$44,MATCH($B14,$A$31:$A$44,0)),0) -> 191.56696 | L14: =IFERROR($D14*INDEX($H$31:$H$44,MATCH($B14,$A$31:$A$44,0))/INDEX($I$31:$I$44,MATCH($B14,$A$31:$A$44,0)),0) -> 0 | M14: =SUM(F14:L14)-D14 -> 0 | N14: =D14/(Supuestos!$B$7*Supuestos!$B$6) -> 5.9458333 | O14: =SUMPRODUCT(F14:L14,$F$24:$L$24)/Supuestos!$B$6 -> 6.1010451 | P14: =O14*Supuestos!$B$10 -> 7.0162019
A15: =Supuestos!A71 -> CO₂ 2 kg | B15: =Supuestos!B71 -> CO2-2 | C15: =Supuestos!D71 -> Manual 2,5 a 6 kg/l | D15: 7784 | E15: =D15/$D$23 -> 0.06112769 | F15: =IFERROR($D15*INDEX($B$31:$B$44,MATCH($B15,$A$31:$A$44,0))/INDEX($I$31:$I$44,MATCH($B15,$A$31:$A$44,0)),0) -> 0 | G15: =IFERROR($D15*INDEX($C$31:$C$44,MATCH($B15,$A$31:$A$44,0))/INDEX($I$31:$I$44,MATCH($B15,$A$31:$A$44,0)),0) -> 4865.2052 | H15: =IFERROR($D15*INDEX($D$31:$D$44,MATCH($B15,$A$31:$A$44,0))/INDEX($I$31:$I$44,MATCH($B15,$A$31:$A$44,0)),0) -> 498.93667 | I15: =IFERROR($D15*INDEX($E$31:$E$44,MATCH($B15,$A$31:$A$44,0))/INDEX($I$31:$I$44,MATCH($B15,$A$31:$A$44,0)),0) -> 1742.7025 | J15: =IFERROR($D15*INDEX($F$31:$F$44,MATCH($B15,$A$31:$A$44,0))/INDEX($I$31:$I$44,MATCH($B15,$A$31:$A$44,0)),0) -> 408.99369 | K15: =IFERROR($D15*INDEX($G$31:$G$44,MATCH($B15,$A$31:$A$44,0))/INDEX($I$31:$I$44,MATCH($B15,$A$31:$A$44,0)),0) -> 177.68447 | L15: =IFERROR($D15*INDEX($H$31:$H$44,MATCH($B15,$A$31:$A$44,0))/INDEX($I$31:$I$44,MATCH($B15,$A$31:$A$44,0)),0) -> 90.477447 | M15: =SUM(F15:L15)-D15 -> 0 | N15: =D15/(Supuestos!$B$7*Supuestos!$B$6) -> 32.433333 | O15: =SUMPRODUCT(F15:L15,$F$24:$L$24)/Supuestos!$B$6 -> 33.151484 | P15: =O15*Supuestos!$B$10 -> 38.124206
A16: =Supuestos!A72 -> CO₂ 5 kg | B16: =Supuestos!B72 -> CO2-5 | C16: =Supuestos!D72 -> Manual 9 a 10 kg/l | D16: 2660 | E16: =D16/$D$23 -> 0.020888959 | F16: =IFERROR($D16*INDEX($B$31:$B$44,MATCH($B16,$A$31:$A$44,0))/INDEX($I$31:$I$44,MATCH($B16,$A$31:$A$44,0)),0) -> 0 | G16: =IFERROR($D16*INDEX($C$31:$C$44,MATCH($B16,$A$31:$A$44,0))/INDEX($I$31:$I$44,MATCH($B16,$A$31:$A$44,0)),0) -> 747.89716 | H16: =IFERROR($D16*INDEX($D$31:$D$44,MATCH($B16,$A$31:$A$44,0))/INDEX($I$31:$I$44,MATCH($B16,$A$31:$A$44,0)),0) -> 605.96691 | I16: =IFERROR($D16*INDEX($E$31:$E$44,MATCH($B16,$A$31:$A$44,0))/INDEX($I$31:$I$44,MATCH($B16,$A$31:$A$44,0)),0) -> 88.358402 | J16: =IFERROR($D16*INDEX($F$31:$F$44,MATCH($B16,$A$31:$A$44,0))/INDEX($I$31:$I$44,MATCH($B16,$A$31:$A$44,0)),0) -> 221.48175 | K16: =IFERROR($D16*INDEX($G$31:$G$44,MATCH($B16,$A$31:$A$44,0))/INDEX($I$31:$I$44,MATCH($B16,$A$31:$A$44,0)),0) -> 996.29577 | L16: =IFERROR($D16*INDEX($H$31:$H$44,MATCH($B16,$A$31:$A$44,0))/INDEX($I$31:$I$44,MATCH($B16,$A$31:$A$44,0)),0) -> 0 | M16: =SUM(F16:L16)-D16 -> 0 | N16: =D16/(Supuestos!$B$7*Supuestos!$B$6) -> 11.083333 | O16: =SUMPRODUCT(F16:L16,$F$24:$L$24)/Supuestos!$B$6 -> 11.191251 | P16: =O16*Supuestos!$B$10 -> 12.869939
A17: =Supuestos!A73 -> HCFC/HFC 5 kg | B17: =Supuestos!B73 -> HCFC | C17: =Supuestos!D73 -> Manual 2,5 a 6 kg/l | D17: 436 | E17: =D17/$D$23 -> 0.0034239045 | F17: =IFERROR($D17*INDEX($B$31:$B$44,MATCH($B17,$A$31:$A$44,0))/INDEX($I$31:$I$44,MATCH($B17,$A$31:$A$44,0)),0) -> 0 | G17: =IFERROR($D17*INDEX($C$31:$C$44,MATCH($B17,$A$31:$A$44,0))/INDEX($I$31:$I$44,MATCH($B17,$A$31:$A$44,0)),0) -> 0 | H17: =IFERROR($D17*INDEX($D$31:$D$44,MATCH($B17,$A$31:$A$44,0))/INDEX($I$31:$I$44,MATCH($B17,$A$31:$A$44,0)),0) -> 136.83253 | I17: =IFERROR($D17*INDEX($E$31:$E$44,MATCH($B17,$A$31:$A$44,0))/INDEX($I$31:$I$44,MATCH($B17,$A$31:$A$44,0)),0) -> 0 | J17: =IFERROR($D17*INDEX($F$31:$F$44,MATCH($B17,$A$31:$A$44,0))/INDEX($I$31:$I$44,MATCH($B17,$A$31:$A$44,0)),0) -> 0 | K17: =IFERROR($D17*INDEX($G$31:$G$44,MATCH($B17,$A$31:$A$44,0))/INDEX($I$31:$I$44,MATCH($B17,$A$31:$A$44,0)),0) -> 299.16747 | L17: =IFERROR($D17*INDEX($H$31:$H$44,MATCH($B17,$A$31:$A$44,0))/INDEX($I$31:$I$44,MATCH($B17,$A$31:$A$44,0)),0) -> 0 | M17: =SUM(F17:L17)-D17 -> 0 | N17: =D17/(Supuestos!$B$7*Supuestos!$B$6) -> 1.8166667 | O17: =SUMPRODUCT(F17:L17,$F$24:$L$24)/Supuestos!$B$6 -> 1.744 | P17: =O17*Supuestos!$B$10 -> 2.0056
A18: =Supuestos!A74 -> Clase D 9 l | B18: =Supuestos!B74 -> CLD-10 | C18: =Supuestos!D74 -> Manual 9 a 10 kg/l | D18: 150 | E18: =D18/$D$23 -> 0.0011779488 | F18: =IFERROR($D18*INDEX($B$31:$B$44,MATCH($B18,$A$31:$A$44,0))/INDEX($I$31:$I$44,MATCH($B18,$A$31:$A$44,0)),0) -> 0 | G18: =IFERROR($D18*INDEX($C$31:$C$44,MATCH($B18,$A$31:$A$44,0))/INDEX($I$31:$I$44,MATCH($B18,$A$31:$A$44,0)),0) -> 0 | H18: =IFERROR($D18*INDEX($D$31:$D$44,MATCH($B18,$A$31:$A$44,0))/INDEX($I$31:$I$44,MATCH($B18,$A$31:$A$44,0)),0) -> 0 | I18: =IFERROR($D18*INDEX($E$31:$E$44,MATCH($B18,$A$31:$A$44,0))/INDEX($I$31:$I$44,MATCH($B18,$A$31:$A$44,0)),0) -> 0 | J18: =IFERROR($D18*INDEX($F$31:$F$44,MATCH($B18,$A$31:$A$44,0))/INDEX($I$31:$I$44,MATCH($B18,$A$31:$A$44,0)),0) -> 0 | K18: =IFERROR($D18*INDEX($G$31:$G$44,MATCH($B18,$A$31:$A$44,0))/INDEX($I$31:$I$44,MATCH($B18,$A$31:$A$44,0)),0) -> 150 | L18: =IFERROR($D18*INDEX($H$31:$H$44,MATCH($B18,$A$31:$A$44,0))/INDEX($I$31:$I$44,MATCH($B18,$A$31:$A$44,0)),0) -> 0 | M18: =SUM(F18:L18)-D18 -> 0 | N18: =D18/(Supuestos!$B$7*Supuestos!$B$6) -> 0.625 | O18: =SUMPRODUCT(F18:L18,$F$24:$L$24)/Supuestos!$B$6 -> 0.6 | P18: =O18*Supuestos!$B$10 -> 0.69
A19: =Supuestos!A75 -> ABC 25 kg s/ruedas | B19: =Supuestos!B75 -> ABC-50R | C19: =Supuestos!D75 -> Rodante | D19: 357 | E19: =D19/$D$23 -> 0.0028035181 | F19: =IFERROR($D19*INDEX($B$31:$B$44,MATCH($B19,$A$31:$A$44,0))/INDEX($I$31:$I$44,MATCH($B19,$A$31:$A$44,0)),0) -> 0 | G19: =IFERROR($D19*INDEX($C$31:$C$44,MATCH($B19,$A$31:$A$44,0))/INDEX($I$31:$I$44,MATCH($B19,$A$31:$A$44,0)),0) -> 127.09662 | H19: =IFERROR($D19*INDEX($D$31:$D$44,MATCH($B19,$A$31:$A$44,0))/INDEX($I$31:$I$44,MATCH($B19,$A$31:$A$44,0)),0) -> 69.671439 | I19: =IFERROR($D19*INDEX($E$31:$E$44,MATCH($B19,$A$31:$A$44,0))/INDEX($I$31:$I$44,MATCH($B19,$A$31:$A$44,0)),0) -> 19.679897 | J19: =IFERROR($D19*INDEX($F$31:$F$44,MATCH($B19,$A$31:$A$44,0))/INDEX($I$31:$I$44,MATCH($B19,$A$31:$A$44,0)),0) -> 22.081058 | K19: =IFERROR($D19*INDEX($G$31:$G$44,MATCH($B19,$A$31:$A$44,0))/INDEX($I$31:$I$44,MATCH($B19,$A$31:$A$44,0)),0) -> 118.47099 | L19: =IFERROR($D19*INDEX($H$31:$H$44,MATCH($B19,$A$31:$A$44,0))/INDEX($I$31:$I$44,MATCH($B19,$A$31:$A$44,0)),0) -> 0 | M19: =SUM(F19:L19)-D19 -> 0 | N19: =D19/(Supuestos!$B$7*Supuestos!$B$6) -> 1.4875 | O19: =SUMPRODUCT(F19:L19,$F$24:$L$24)/Supuestos!$B$6 -> 1.5037894 | P19: =O19*Supuestos!$B$10 -> 1.7293578
A20: =Supuestos!A76 -> ABC 50 kg s/ruedas | B20: =Supuestos!B76 -> ABC-50R | C20: =Supuestos!D76 -> Rodante | D20: 785 | E20: =D20/$D$23 -> 0.0061645987 | F20: =IFERROR($D20*INDEX($B$31:$B$44,MATCH($B20,$A$31:$A$44,0))/INDEX($I$31:$I$44,MATCH($B20,$A$31:$A$44,0)),0) -> 0 | G20: =IFERROR($D20*INDEX($C$31:$C$44,MATCH($B20,$A$31:$A$44,0))/INDEX($I$31:$I$44,MATCH($B20,$A$31:$A$44,0)),0) -> 279.47015 | H20: =IFERROR($D20*INDEX($D$31:$D$44,MATCH($B20,$A$31:$A$44,0))/INDEX($I$31:$I$44,MATCH($B20,$A$31:$A$44,0)),0) -> 153.1991 | I20: =IFERROR($D20*INDEX($E$31:$E$44,MATCH($B20,$A$31:$A$44,0))/INDEX($I$31:$I$44,MATCH($B20,$A$31:$A$44,0)),0) -> 43.273724 | J20: =IFERROR($D20*INDEX($F$31:$F$44,MATCH($B20,$A$31:$A$44,0))/INDEX($I$31:$I$44,MATCH($B20,$A$31:$A$44,0)),0) -> 48.553586 | K20: =IFERROR($D20*INDEX($G$31:$G$44,MATCH($B20,$A$31:$A$44,0))/INDEX($I$31:$I$44,MATCH($B20,$A$31:$A$44,0)),0) -> 260.50344 | L20: =IFERROR($D20*INDEX($H$31:$H$44,MATCH($B20,$A$31:$A$44,0))/INDEX($I$31:$I$44,MATCH($B20,$A$31:$A$44,0)),0) -> 0 | M20: =SUM(F20:L20)-D20 -> 0 | N20: =D20/(Supuestos!$B$7*Supuestos!$B$6) -> 3.2708333 | O20: =SUMPRODUCT(F20:L20,$F$24:$L$24)/Supuestos!$B$6 -> 3.3066518 | P20: =O20*Supuestos!$B$10 -> 3.8026496
... A22: =Supuestos!A78 -> ABC 100 kg s/ruedas | B22: =Supuestos!B78 -> ABC-50R | C22: =Supuestos!D78 -> Rodante | D22: 114 | E22: =D22/$D$23 -> 0.00089524109 | F22: =IFERROR($D22*INDEX($B$31:$B$44,MATCH($B22,$A$31:$A$44,0))/INDEX($I$31:$I$44,MATCH($B22,$A$31:$A$44,0)),0) -> 0 | G22: =IFERROR($D22*INDEX($C$31:$C$44,MATCH($B22,$A$31:$A$44,0))/INDEX($I$31:$I$44,MATCH($B22,$A$31:$A$44,0)),0) -> 40.585474 | H22: =IFERROR($D22*INDEX($D$31:$D$44,MATCH($B22,$A$31:$A$44,0))/INDEX($I$31:$I$44,MATCH($B22,$A$31:$A$44,0)),0) -> 22.248023 | I22: =IFERROR($D22*INDEX($E$31:$E$44,MATCH($B22,$A$31:$A$44,0))/INDEX($I$31:$I$44,MATCH($B22,$A$31:$A$44,0)),0) -> 6.2843369 | J22: =IFERROR($D22*INDEX($F$31:$F$44,MATCH($B22,$A$31:$A$44,0))/INDEX($I$31:$I$44,MATCH($B22,$A$31:$A$44,0)),0) -> 7.051094 | K22: =IFERROR($D22*INDEX($G$31:$G$44,MATCH($B22,$A$31:$A$44,0))/INDEX($I$31:$I$44,MATCH($B22,$A$31:$A$44,0)),0) -> 37.831072 | L22: =IFERROR($D22*INDEX($H$31:$H$44,MATCH($B22,$A$31:$A$44,0))/INDEX($I$31:$I$44,MATCH($B22,$A$31:$A$44,0)),0) -> 0 | M22: =SUM(F22:L22)-D22 -> 0 | N22: =D22/(Supuestos!$B$7*Supuestos!$B$6) -> 0.475 | O22: =SUMPRODUCT(F22:L22,$F$24:$L$24)/Supuestos!$B$6 -> 0.48020166 | P22: =O22*Supuestos!$B$10 -> 0.55223191
A23: Total | D23: =SUM(D6:D22) -> 127340 | E23: =SUM(E6:E22) -> 1 | F23: =SUM(F6:F22) -> 69973.083 | G23: =SUM(G6:G22) -> 31696.835 | H23: =SUM(H6:H22) -> 4933.724 | I23: =SUM(I6:I22) -> 9334.2065 | J23: =SUM(J6:J22) -> 4120.3049 | K23: =SUM(K6:K22) -> 6759.9476 | ... P23: =SUM(P6:P22) -> 684.13
A24: Estacionalidad del mes pico | F24: =INDEX(Supuestos!$B$96:$M$102,MATCH(F$5,Supuestos!$A$96:$A$102,0),$C$59) -> 0.1 | G24: =INDEX(Supuestos!$B$96:$M$102,MATCH(G$5,Supuestos!$A$96:$A$102,0),$C$59) -> 0.09 | H24: =INDEX(Supuestos!$B$96:$M$102,MATCH(H$5,Supuestos!$A$96:$A$102,0),$C$59) -> 0.08 | I24: =INDEX(Supuestos!$B$96:$M$102,MATCH(I$5,Supuestos!$A$96:$A$102,0),$C$59) -> 0.07 | J24: =INDEX(Supuestos!$B$96:$M$102,MATCH(J$5,Supuestos!$A$96:$A$102,0),$C$59) -> 0.1 | K24: =INDEX(Supuestos!$B$96:$M$102,MATCH(K$5,Supuestos!$A$96:$A$102,0),$C$59) -> 0.08 | L24: =INDEX(Supuestos!$B$96:$M$102,MATCH(L$5,Supuestos!$A$96:$A$102,0),$C$59) -> 0.09
A25: % con transitorio | F25: =INDEX(Supuestos!$D$84:$D$90,MATCH(F$5,Supuestos!$A$84:$A$90,0)) -> 1 | G25: =INDEX(Supuestos!$D$84:$D$90,MATCH(G$5,Supuestos!$A$84:$A$90,0)) -> 1 | H25: =INDEX(Supuestos!$D$84:$D$90,MATCH(H$5,Supuestos!$A$84:$A$90,0)) -> 0.9 | I25: =INDEX(Supuestos!$D$84:$D$90,MATCH(I$5,Supuestos!$A$84:$A$90,0)) -> 1 | J25: =INDEX(Supuestos!$D$84:$D$90,MATCH(J$5,Supuestos!$A$84:$A$90,0)) -> 1 | K25: =INDEX(Supuestos!$D$84:$D$90,MATCH(K$5,Supuestos!$A$84:$A$90,0)) -> 0.8 | L25: =INDEX(Supuestos!$D$84:$D$90,MATCH(L$5,Supuestos!$A$84:$A$90,0)) -> 1
A29: 2. Mercado argentino de recargas por rubro y tipo (u/año) — CONSOLIDADO_24
A30: Código | B30: Automotriz | C30: Edificios | D30: Salud | E30: Educación | F30: Hoteles | G30: Industrias | H30: Supermercados | I30: Total
A31: ABC-1 | B31: 6890147 | C31: 0 | D31: 0 | E31: 0 | F31: 1873 | G31: 0 | H31: 1504 | I31: =SUM(B31:H31) -> 6893524 | J31: ← Suma de la columna RECARGAS de cada hoja de rubro de CONSOLIDADO_24 (industrias incluye almacenes;
A32: ABC-2.5 | B32: 0 | C32: 209661 | D32: 27267 | E32: 101892 | F32: 138993 | G32: 0 | H32: 17317 | I32: =SUM(B32:H32) -> 495130 | J32: supermercados incluye góndola; hoteles incluye alquiler temporario). Los rodantes del mercado vienen
A33: ABC-5 | B33: 212830 | C33: 1529291 | D33: 174313 | E33: 379470 | F33: 80351 | G33: 239761 | H33: 15013 | I33: =SUM(B33:H33) -> 2631029 | J33: todos como ABC 50 kg: los de 25, 70 y 100 kg se reparten igual.
A34: ABC-10P | B34: 0 | C34: 93731 | D34: 23304 | E34: 40784 | F34: 19284 | G34: 0 | H34: 0 | I34: =SUM(B34:H34) -> 177103
A35: AGUA-10 | B35: 0 | C35: 118397 | D35: 33295 | E35: 35055 | F35: 12856 | G35: 24614 | H35: 1577 | I35: =SUM(B35:H35) -> 225794
A36: AFFF-9 | B36: 0 | C36: 0 | D36: 0 | E36: 0 | F36: 0 | G36: 33670 | H36: 0 | I36: =SUM(B36:H36) -> 33670
A37: AFFF-50R | B37: 0 | C37: 0 | D37: 0 | E37: 0 | F37: 0 | G37: 18051 | H37: 0 | I37: =SUM(B37:H37) -> 18051
A38: BC-5 | B38: 0 | C38: 0 | D38: 0 | E38: 0 | F38: 0 | G38: 9854 | H38: 0 | I38: =SUM(B38:H38) -> 9854
A39: SALK-6 | B39: 0 | C39: 41932 | D39: 10422 | E39: 32054 | F39: 32140 | G39: 18072 | H39: 0 | I39: =SUM(B39:H39) -> 134620
A40: CO2-2 | B40: 0 | C40: 382323 | D40: 39208 | E40: 136947 | F40: 32140 | G40: 13963 | H40: 7110 | I40: =SUM(B40:H40) -> 611691
A41: CO2-5 | B41: 0 | C41: 54265 | D41: 43967 | E41: 6411 | F41: 16070 | G41: 72288 | H41: 0 | I41: =SUM(B41:H41) -> 193001
A42: HCFC | B42: 0 | C42: 0 | D42: 9014 | E42: 0 | F42: 0 | G42: 19708 | H42: 0 | I42: =SUM(B42:H42) -> 28722
A43: CLD-10 | B43: 0 | C43: 0 | D43: 0 | E43: 0 | F43: 0 | G43: 8218 | H43: 0 | I43: =SUM(B43:H43) -> 8218
A44: ABC-50R | B44: 0 | C44: 36999 | D44: 20282 | E44: 5729 | F44: 6428 | G44: 34488 | H44: 0 | I44: =SUM(B44:H44) -> 103926
A45: Total | B45: =SUM(B31:B44) -> 7102977 | C45: =SUM(C31:C44) -> 2466599 | D45: =SUM(D31:D44) -> 381072 | E45: =SUM(E31:E44) -> 738342 | F45: =SUM(F31:F44) -> 340135 | G45: =SUM(G31:G44) -> 492687 | H45: =SUM(H31:H44) -> 42521 | I45: =SUM(I31:I44) -> 11564333
A46: % del mercado | B46: =B45/$I$45 -> 0.61421415 | C46: =C45/$I$45 -> 0.21329367 | D46: =D45/$I$45 -> 0.032952354 | E46: =E45/$I$45 -> 0.063846484 | F46: =F45/$I$45 -> 0.029412418 | G46: =G45/$I$45 -> 0.042604014 | H46: =H45/$I$45 -> 0.003676909 | I46: =I45/$I$45 -> 1
A48: 3. Llegadas por mes y por día (u)
A49: Rubro | B49: Total año | C49: Ene | D49: Feb | E49: Mar | F49: Abr | G49: May | H49: Jun | I49: Jul | J49: Ago | K49: Sep | L49: Oct | M49: Nov | N49: Dic | O49: u/día promedio | P49: u/día mes pico | Q49: u/día día pico | R49: Peso medio (kg/u) | S49: m² de piso por u. | T49: % rodantes
A50: Automotriz | B50: =F23 -> 69973.083 | C50: =$B50*INDEX(Supuestos!$B$96:$M$102,MATCH($A50,Supuestos!$A$96:$A$102,0),1) -> 6297.5775 | D50: =$B50*INDEX(Supuestos!$B$96:$M$102,MATCH($A50,Supuestos!$A$96:$A$102,0),2) -> 5597.8467 | E50: =$B50*INDEX(Supuestos!$B$96:$M$102,MATCH($A50,Supuestos!$A$96:$A$102,0),3) -> 5597.8467 | F50: =$B50*INDEX(Supuestos!$B$96:$M$102,MATCH($A50,Supuestos!$A$96:$A$102,0),4) -> 5597.8467 | G50: =$B50*INDEX(Supuestos!$B$96:$M$102,MATCH($A50,Supuestos!$A$96:$A$102,0),5) -> 5597.8467 | H50: =$B50*INDEX(Supuestos!$B$96:$M$102,MATCH($A50,Supuestos!$A$96:$A$102,0),6) -> 5597.8467 | I50: =$B50*INDEX(Supuestos!$B$96:$M$102,MATCH($A50,Supuestos!$A$96:$A$102,0),7) -> 5597.8467 | J50: =$B50*INDEX(Supuestos!$B$96:$M$102,MATCH($A50,Supuestos!$A$96:$A$102,0),8) -> 5597.8467 | K50: =$B50*INDEX(Supuestos!$B$96:$M$102,MATCH($A50,Supuestos!$A$96:$A$102,0),9) -> 5597.8467 | L50: =$B50*INDEX(Supuestos!$B$96:$M$102,MATCH($A50,Supuestos!$A$96:$A$102,0),10) -> 5597.8467 | M50: =$B50*INDEX(Supuestos!$B$96:$M$102,MATCH($A50,Supuestos!$A$96:$A$102,0),11) -> 6297.5775 | N50: =$B50*INDEX(Supuestos!$B$96:$M$102,MATCH($A50,Supuestos!$A$96:$A$102,0),12) -> 6997.3083 | O50: =B50/(Supuestos!$B$7*Supuestos!$B$6) -> 291.55451 | P50: =INDEX(C50:N50,$C$59)/Supuestos!$B$6 -> 349.86542 | Q50: =P50*Supuestos!$B$10 -> 402.34523 | R50: =SUMPRODUCT(F$6:F$22,Supuestos!$E$62:$E$78)/B50 -> 2.2601006 | S50: =SUMPRODUCT(F$6:F$22,Supuestos!$I$62:$I$78)/B50 -> 0.0090002579 | T50: =SUMPRODUCT(F$6:F$22,Supuestos!$G$62:$G$78)/B50 -> 0
A51: Edificios | B51: =G23 -> 31696.835 | C51: =$B51*INDEX(Supuestos!$B$96:$M$102,MATCH($A51,Supuestos!$A$96:$A$102,0),1) -> 1901.8101 | D51: =$B51*INDEX(Supuestos!$B$96:$M$102,MATCH($A51,Supuestos!$A$96:$A$102,0),2) -> 2218.7785 | E51: =$B51*INDEX(Supuestos!$B$96:$M$102,MATCH($A51,Supuestos!$A$96:$A$102,0),3) -> 2852.7152 | F51: =$B51*INDEX(Supuestos!$B$96:$M$102,MATCH($A51,Supuestos!$A$96:$A$102,0),4) -> 2852.7152 | G51: =$B51*INDEX(Supuestos!$B$96:$M$102,MATCH($A51,Supuestos!$A$96:$A$102,0),5) -> 2852.7152 | H51: =$B51*INDEX(Supuestos!$B$96:$M$102,MATCH($A51,Supuestos!$A$96:$A$102,0),6) -> 2535.7468 | I51: =$B51*INDEX(Supuestos!$B$96:$M$102,MATCH($A51,Supuestos!$A$96:$A$102,0),7) -> 2218.7785 | J51: =$B51*INDEX(Supuestos!$B$96:$M$102,MATCH($A51,Supuestos!$A$96:$A$102,0),8) -> 2852.7152 | K51: =$B51*INDEX(Supuestos!$B$96:$M$102,MATCH($A51,Supuestos!$A$96:$A$102,0),9) -> 2852.7152 | L51: =$B51*INDEX(Supuestos!$B$96:$M$102,MATCH($A51,Supuestos!$A$96:$A$102,0),10) -> 2852.7152 | M51: =$B51*INDEX(Supuestos!$B$96:$M$102,MATCH($A51,Supuestos!$A$96:$A$102,0),11) -> 2852.7152 | N51: =$B51*INDEX(Supuestos!$B$96:$M$102,MATCH($A51,Supuestos!$A$96:$A$102,0),12) -> 2852.7152 | O51: =B51/(Supuestos!$B$7*Supuestos!$B$6) -> 132.07015 | P51: =INDEX(C51:N51,$C$59)/Supuestos!$B$6 -> 142.63576 | Q51: =P51*Supuestos!$B$10 -> 164.03112 | R51: =SUMPRODUCT(G$6:G$22,Supuestos!$E$62:$E$78)/B51 -> 9.9521135 | S51: =SUMPRODUCT(G$6:G$22,Supuestos!$I$62:$I$78)/B51 -> 0.03424888 | T51: =SUMPRODUCT(G$6:G$22,Supuestos!$G$62:$G$78)/B51 -> 0.016027797
A52: Salud | B52: =H23 -> 4933.724 | C52: =$B52*INDEX(Supuestos!$B$96:$M$102,MATCH($A52,Supuestos!$A$96:$A$102,0),1) -> 394.69792 | D52: =$B52*INDEX(Supuestos!$B$96:$M$102,MATCH($A52,Supuestos!$A$96:$A$102,0),2) -> 394.69792 | E52: =$B52*INDEX(Supuestos!$B$96:$M$102,MATCH($A52,Supuestos!$A$96:$A$102,0),3) -> 444.03516 | F52: =$B52*INDEX(Supuestos!$B$96:$M$102,MATCH($A52,Supuestos!$A$96:$A$102,0),4) -> 394.69792 | G52: =$B52*INDEX(Supuestos!$B$96:$M$102,MATCH($A52,Supuestos!$A$96:$A$102,0),5) -> 394.69792 | H52: =$B52*INDEX(Supuestos!$B$96:$M$102,MATCH($A52,Supuestos!$A$96:$A$102,0),6) -> 394.69792 | I52: =$B52*INDEX(Supuestos!$B$96:$M$102,MATCH($A52,Supuestos!$A$96:$A$102,0),7) -> 394.69792 | J52: =$B52*INDEX(Supuestos!$B$96:$M$102,MATCH($A52,Supuestos!$A$96:$A$102,0),8) -> 444.03516 | K52: =$B52*INDEX(Supuestos!$B$96:$M$102,MATCH($A52,Supuestos!$A$96:$A$102,0),9) -> 444.03516 | L52: =$B52*INDEX(Supuestos!$B$96:$M$102,MATCH($A52,Supuestos!$A$96:$A$102,0),10) -> 394.69792 | M52: =$B52*INDEX(Supuestos!$B$96:$M$102,MATCH($A52,Supuestos!$A$96:$A$102,0),11) -> 444.03516 | N52: =$B52*INDEX(Supuestos!$B$96:$M$102,MATCH($A52,Supuestos!$A$96:$A$102,0),12) -> 394.69792 | O52: =B52/(Supuestos!$B$7*Supuestos!$B$6) -> 20.557183 | P52: =INDEX(C52:N52,$C$59)/Supuestos!$B$6 -> 19.734896 | Q52: =P52*Supuestos!$B$10 -> 22.69513 | R52: =SUMPRODUCT(H$6:H$22,Supuestos!$E$62:$E$78)/B52 -> 14.390407 | S52: =SUMPRODUCT(H$6:H$22,Supuestos!$I$62:$I$78)/B52 -> 0.059005024 | T52: =SUMPRODUCT(H$6:H$22,Supuestos!$G$62:$G$78)/B52 -> 0.056446327
A53: Educación | B53: =I23 -> 9334.2065 | C53: =$B53*INDEX(Supuestos!$B$96:$M$102,MATCH($A53,Supuestos!$A$96:$A$102,0),1) -> 373.36826 | D53: =$B53*INDEX(Supuestos!$B$96:$M$102,MATCH($A53,Supuestos!$A$96:$A$102,0),2) -> 1680.1572 | E53: =$B53*INDEX(Supuestos!$B$96:$M$102,MATCH($A53,Supuestos!$A$96:$A$102,0),3) -> 933.42065 | F53: =$B53*INDEX(Supuestos!$B$96:$M$102,MATCH($A53,Supuestos!$A$96:$A$102,0),4) -> 653.39446 | G53: =$B53*INDEX(Supuestos!$B$96:$M$102,MATCH($A53,Supuestos!$A$96:$A$102,0),5) -> 653.39446 | H53: =$B53*INDEX(Supuestos!$B$96:$M$102,MATCH($A53,Supuestos!$A$96:$A$102,0),6) -> 653.39446 | I53: =$B53*INDEX(Supuestos!$B$96:$M$102,MATCH($A53,Supuestos!$A$96:$A$102,0),7) -> 1306.7889 | J53: =$B53*INDEX(Supuestos!$B$96:$M$102,MATCH($A53,Supuestos!$A$96:$A$102,0),8) -> 653.39446 | K53: =$B53*INDEX(Supuestos!$B$96:$M$102,MATCH($A53,Supuestos!$A$96:$A$102,0),9) -> 653.39446 | L53: =$B53*INDEX(Supuestos!$B$96:$M$102,MATCH($A53,Supuestos!$A$96:$A$102,0),10) -> 560.05239 | M53: =$B53*INDEX(Supuestos!$B$96:$M$102,MATCH($A53,Supuestos!$A$96:$A$102,0),11) -> 560.05239 | N53: =$B53*INDEX(Supuestos!$B$96:$M$102,MATCH($A53,Supuestos!$A$96:$A$102,0),12) -> 653.39446 | O53: =B53/(Supuestos!$B$7*Supuestos!$B$6) -> 38.892527 | P53: =INDEX(C53:N53,$C$59)/Supuestos!$B$6 -> 32.669723 | Q53: =P53*Supuestos!$B$10 -> 37.570181 | R53: =SUMPRODUCT(I$6:I$22,Supuestos!$E$62:$E$78)/B53 -> 9.1720953 | S53: =SUMPRODUCT(I$6:I$22,Supuestos!$I$62:$I$78)/B53 -> 0.029730289 | T53: =SUMPRODUCT(I$6:I$22,Supuestos!$G$62:$G$78)/B53 -> 0.0084275469
A54: Hoteles | B54: =J23 -> 4120.3049 | C54: =$B54*INDEX(Supuestos!$B$96:$M$102,MATCH($A54,Supuestos!$A$96:$A$102,0),1) -> 206.01525 | D54: =$B54*INDEX(Supuestos!$B$96:$M$102,MATCH($A54,Supuestos!$A$96:$A$102,0),2) -> 206.01525 | E54: =$B54*INDEX(Supuestos!$B$96:$M$102,MATCH($A54,Supuestos!$A$96:$A$102,0),3) -> 288.42134 | F54: =$B54*INDEX(Supuestos!$B$96:$M$102,MATCH($A54,Supuestos!$A$96:$A$102,0),4) -> 329.62439 | G54: =$B54*INDEX(Supuestos!$B$96:$M$102,MATCH($A54,Supuestos!$A$96:$A$102,0),5) -> 370.82744 | H54: =$B54*INDEX(Supuestos!$B$96:$M$102,MATCH($A54,Supuestos!$A$96:$A$102,0),6) -> 412.03049 | I54: =$B54*INDEX(Supuestos!$B$96:$M$102,MATCH($A54,Supuestos!$A$96:$A$102,0),7) -> 247.2183 | J54: =$B54*INDEX(Supuestos!$B$96:$M$102,MATCH($A54,Supuestos!$A$96:$A$102,0),8) -> 288.42134 | K54: =$B54*INDEX(Supuestos!$B$96:$M$102,MATCH($A54,Supuestos!$A$96:$A$102,0),9) -> 370.82744 | L54: =$B54*INDEX(Supuestos!$B$96:$M$102,MATCH($A54,Supuestos!$A$96:$A$102,0),10) -> 453.23354 | M54: =$B54*INDEX(Supuestos!$B$96:$M$102,MATCH($A54,Supuestos!$A$96:$A$102,0),11) -> 535.63964 | N54: =$B54*INDEX(Supuestos!$B$96:$M$102,MATCH($A54,Supuestos!$A$96:$A$102,0),12) -> 412.03049 | O54: =B54/(Supuestos!$B$7*Supuestos!$B$6) -> 17.167937 | P54: =INDEX(C54:N54,$C$59)/Supuestos!$B$6 -> 20.601525 | Q54: =P54*Supuestos!$B$10 -> 23.691753 | R54: =SUMPRODUCT(J$6:J$22,Supuestos!$E$62:$E$78)/B54 -> 9.6298779 | S54: =SUMPRODUCT(J$6:J$22,Supuestos!$I$62:$I$78)/B54 -> 0.036622478 | T54: =SUMPRODUCT(J$6:J$22,Supuestos!$G$62:$G$78)/B54 -> 0.021421322
A55: Industrias | B55: =K23 -> 6759.9476 | C55: =$B55*INDEX(Supuestos!$B$96:$M$102,MATCH($A55,Supuestos!$A$96:$A$102,0),1) -> 337.99738 | D55: =$B55*INDEX(Supuestos!$B$96:$M$102,MATCH($A55,Supuestos!$A$96:$A$102,0),2) -> 540.7958 | E55: =$B55*INDEX(Supuestos!$B$96:$M$102,MATCH($A55,Supuestos!$A$96:$A$102,0),3) -> 608.39528 | F55: =$B55*INDEX(Supuestos!$B$96:$M$102,MATCH($A55,Supuestos!$A$96:$A$102,0),4) -> 608.39528 | G55: =$B55*INDEX(Supuestos!$B$96:$M$102,MATCH($A55,Supuestos!$A$96:$A$102,0),5) -> 608.39528 | H55: =$B55*INDEX(Supuestos!$B$96:$M$102,MATCH($A55,Supuestos!$A$96:$A$102,0),6) -> 540.7958 | I55: =$B55*INDEX(Supuestos!$B$96:$M$102,MATCH($A55,Supuestos!$A$96:$A$102,0),7) -> 540.7958 | J55: =$B55*INDEX(Supuestos!$B$96:$M$102,MATCH($A55,Supuestos!$A$96:$A$102,0),8) -> 608.39528 | K55: =$B55*INDEX(Supuestos!$B$96:$M$102,MATCH($A55,Supuestos!$A$96:$A$102,0),9) -> 608.39528 | L55: =$B55*INDEX(Supuestos!$B$96:$M$102,MATCH($A55,Supuestos!$A$96:$A$102,0),10) -> 608.39528 | M55: =$B55*INDEX(Supuestos!$B$96:$M$102,MATCH($A55,Supuestos!$A$96:$A$102,0),11) -> 608.39528 | N55: =$B55*INDEX(Supuestos!$B$96:$M$102,MATCH($A55,Supuestos!$A$96:$A$102,0),12) -> 540.7958 | O55: =B55/(Supuestos!$B$7*Supuestos!$B$6) -> 28.166448 | P55: =INDEX(C55:N55,$C$59)/Supuestos!$B$6 -> 27.03979 | Q55: =P55*Supuestos!$B$10 -> 31.095759 | R55: =SUMPRODUCT(K$6:K$22,Supuestos!$E$62:$E$78)/B55 -> 19.50757 | S55: =SUMPRODUCT(K$6:K$22,Supuestos!$I$62:$I$78)/B55 -> 0.092169885 | T55: =SUMPRODUCT(K$6:K$22,Supuestos!$G$62:$G$78)/B55 -> 0.11250858
A56: Supermercados | B56: =L23 -> 521.8984 | C56: =$B56*INDEX(Supuestos!$B$96:$M$102,MATCH($A56,Supuestos!$A$96:$A$102,0),1) -> 41.751872 | D56: =$B56*INDEX(Supuestos!$B$96:$M$102,MATCH($A56,Supuestos!$A$96:$A$102,0),2) -> 41.751872 | E56: =$B56*INDEX(Supuestos!$B$96:$M$102,MATCH($A56,Supuestos!$A$96:$A$102,0),3) -> 41.751872 | F56: =$B56*INDEX(Supuestos!$B$96:$M$102,MATCH($A56,Supuestos!$A$96:$A$102,0),4) -> 41.751872 | G56: =$B56*INDEX(Supuestos!$B$96:$M$102,MATCH($A56,Supuestos!$A$96:$A$102,0),5) -> 41.751872 | H56: =$B56*INDEX(Supuestos!$B$96:$M$102,MATCH($A56,Supuestos!$A$96:$A$102,0),6) -> 41.751872 | I56: =$B56*INDEX(Supuestos!$B$96:$M$102,MATCH($A56,Supuestos!$A$96:$A$102,0),7) -> 41.751872 | J56: =$B56*INDEX(Supuestos!$B$96:$M$102,MATCH($A56,Supuestos!$A$96:$A$102,0),8) -> 41.751872 | K56: =$B56*INDEX(Supuestos!$B$96:$M$102,MATCH($A56,Supuestos!$A$96:$A$102,0),9) -> 46.970856 | L56: =$B56*INDEX(Supuestos!$B$96:$M$102,MATCH($A56,Supuestos!$A$96:$A$102,0),10) -> 46.970856 | M56: =$B56*INDEX(Supuestos!$B$96:$M$102,MATCH($A56,Supuestos!$A$96:$A$102,0),11) -> 46.970856 | N56: =$B56*INDEX(Supuestos!$B$96:$M$102,MATCH($A56,Supuestos!$A$96:$A$102,0),12) -> 46.970856 | O56: =B56/(Supuestos!$B$7*Supuestos!$B$6) -> 2.1745767 | P56: =INDEX(C56:N56,$C$59)/Supuestos!$B$6 -> 2.3485428 | Q56: =P56*Supuestos!$B$10 -> 2.7008242 | R56: =SUMPRODUCT(L$6:L$22,Supuestos!$E$62:$E$78)/B56 -> 6.7447597 | S56: =SUMPRODUCT(L$6:L$22,Supuestos!$I$62:$I$78)/B56 -> 0.022241988 | T56: =SUMPRODUCT(L$6:L$22,Supuestos!$G$62:$G$78)/B56 -> 0
A57: Total | B57: =SUM(B50:B56) -> 127340 | C57: =SUM(C50:C56) -> 9553.2183 | D57: =SUM(D50:D56) -> 10680.043 | E57: =SUM(E50:E56) -> 10766.586 | F57: =SUM(F50:F56) -> 10478.426 | G57: =SUM(G50:G56) -> 10519.629 | H57: =SUM(H50:H56) -> 10176.264 | I57: =SUM(I50:I56) -> 10347.878 | ... Q57: =SUM(Q50:Q56) -> 684.13
A58: u/día de cada mes | C58: =C57/Supuestos!$B$6 -> 477.66091 | D58: =D57/Supuestos!$B$6 -> 534.00216 | E58: =E57/Supuestos!$B$6 -> 538.32931 | F58: =F57/Supuestos!$B$6 -> 523.92129 | G58: =G57/Supuestos!$B$6 -> 525.98144 | H58: =H57/Supuestos!$B$6 -> 508.8132 | I58: =I57/Supuestos!$B$6 -> 517.3939 | J58: =J57/Supuestos!$B$6 -> 524.328 | ... N58: =N57/Supuestos!$B$6 -> 594.89565
A59: Mes pico | B59: =INDEX($C$49:$N$49,C59) -> Dic | C59: =MATCH(MAX(C58:N58),C58:N58,0) -> 12 | D59: ← n.º de mes (lo usan las demás hojas)
A60: Factor mes pico / promedio | B60: =MAX(C58:N58)/O57 -> 1.1212106
A62: 4. Mix entrante por familia
A63: Familia | B63: u/año | C63: % del total | D63: u/día promedio | E63: u/día mes pico | F63: u/día día pico | G63: Cómo llega
A64: ABC 1 kg | B64: =SUMIF($C$6:$C$22,$A64,D$6:D$22) -> 67206 | C64: =B64/$D$23 -> 0.52776818 | D64: =SUMIF($C$6:$C$22,$A64,N$6:N$22) -> 280.025 | E64: =SUMIF($C$6:$C$22,$A64,O$6:O$22) -> 336.02267 | F64: =SUMIF($C$6:$C$22,$A64,P$6:P$22) -> 386.42607 | G64: Casi todos de autos (puntos de acopio): Kangoo. Jaula A de 72.
A65: Manual 2,5 a 6 kg/l | B65: =SUMIF($C$6:$C$22,$A65,D$6:D$22) -> 50117 | C65: =B65/$D$23 -> 0.3935684 | D65: =SUMIF($C$6:$C$22,$A65,N$6:N$22) -> 208.82083 | E65: =SUMIF($C$6:$C$22,$A65,O$6:O$22) -> 216.7124 | F65: =SUMIF($C$6:$C$22,$A65,P$6:P$22) -> 249.21926 | G65: ABC 2,5 y 5, BC, sales K, CO₂ 2 y HCFC: jaula B (24 a 30 por jaula).
A66: Manual 9 a 10 kg/l | B66: =SUMIF($C$6:$C$22,$A66,D$6:D$22) -> 8303 | C66: =B66/$D$23 -> 0.065203392 | D66: =SUMIF($C$6:$C$22,$A66,N$6:N$22) -> 34.595833 | E66: =SUMIF($C$6:$C$22,$A66,O$6:O$22) -> 35.001636 | F66: =SUMIF($C$6:$C$22,$A66,P$6:P$22) -> 40.251881 | G66: ABC 10, agua, AFFF, CO₂ 5 y clase D: jaula B en cuadrícula de 16.
A67: Rodante | B67: =SUMIF($C$6:$C$22,$A67,D$6:D$22) -> 1714 | C67: =B67/$D$23 -> 0.013460028 | D67: =SUMIF($C$6:$C$22,$A67,N$6:N$22) -> 7.1416667 | E67: =SUMIF($C$6:$C$22,$A67,O$6:O$22) -> 7.1589454 | F67: =SUMIF($C$6:$C$22,$A67,P$6:P$22) -> 8.2327872 | G67: Rodantes: solo en Master, en el piso y con cinchas; jaula de rodantes (1 a 3).
A68: Total | B68: =SUM(B64:B67) -> 127340 | C68: =SUM(C64:C67) -> 1 | D68: =SUM(D64:D67) -> 530.58333 | E68: =SUM(E64:E67) -> 594.89565 | F68: =SUM(F64:F67) -> 684.13
A70: 5. Qué tiene un cliente típico de cada rubro (u. por cliente × mix del rubro)
A71: Tipo | B71: Automotriz | C71: Edificios | D71: Salud | E71: Educación | F71: Hoteles | G71: Industrias | H71: Supermercados
A72: =A6 -> ABC 1 kg | B72: =IFERROR(F6/F$23*INDEX(Supuestos!$C$84:$C$90,MATCH(B$71,Supuestos!$A$84:$A$90,0)),0) -> 23.999613 | C72: =IFERROR(G6/G$23*INDEX(Supuestos!$C$84:$C$90,MATCH(C$71,Supuestos!$A$84:$A$90,0)),0) -> 0 | D72: =IFERROR(H6/H$23*INDEX(Supuestos!$C$84:$C$90,MATCH(D$71,Supuestos!$A$84:$A$90,0)),0) -> 0 | E72: =IFERROR(I6/I$23*INDEX(Supuestos!$C$84:$C$90,MATCH(E$71,Supuestos!$A$84:$A$90,0)),0) -> 0 | F72: =IFERROR(J6/J$23*INDEX(Supuestos!$C$84:$C$90,MATCH(F$71,Supuestos!$A$84:$A$90,0)),0) -> 0.088634984 | G72: =IFERROR(K6/K$23*INDEX(Supuestos!$C$84:$C$90,MATCH(G$71,Supuestos!$A$84:$A$90,0)),0) -> 0 | H72: =IFERROR(L6/L$23*INDEX(Supuestos!$C$84:$C$90,MATCH(H$71,Supuestos!$A$84:$A$90,0)),0) -> 0.44951957 | I72: ← por ejemplo, un edificio típico de 14 matafuegos: ~9 ABC 5 kg, ~2 CO₂ 2 kg, ~1 ABC 2,5 kg, ~1 agua y el resto
A73: =A7 -> ABC 2,5 kg | B73: =IFERROR(F7/F$23*INDEX(Supuestos!$C$84:$C$90,MATCH(B$71,Supuestos!$A$84:$A$90,0)),0) -> 0 | C73: =IFERROR(G7/G$23*INDEX(Supuestos!$C$84:$C$90,MATCH(C$71,Supuestos!$A$84:$A$90,0)),0) -> 1.0643859 | D73: =IFERROR(H7/H$23*INDEX(Supuestos!$C$84:$C$90,MATCH(D$71,Supuestos!$A$84:$A$90,0)),0) -> 2.2233094 | E73: =IFERROR(I7/I$23*INDEX(Supuestos!$C$84:$C$90,MATCH(E$71,Supuestos!$A$84:$A$90,0)),0) -> 2.2584191 | F73: =IFERROR(J7/J$23*INDEX(Supuestos!$C$84:$C$90,MATCH(F$71,Supuestos!$A$84:$A$90,0)),0) -> 7.7546627 | G73: =IFERROR(K7/K$23*INDEX(Supuestos!$C$84:$C$90,MATCH(G$71,Supuestos!$A$84:$A$90,0)),0) -> 0 | H73: =IFERROR(L7/L$23*INDEX(Supuestos!$C$84:$C$90,MATCH(H$71,Supuestos!$A$84:$A$90,0)),0) -> 6.1020536 | I73: (cocheras, cocina). El mix sale del consolidado comercial; la cantidad por cliente es un supuesto.
A74: =A8 -> ABC 5 kg | B74: =IFERROR(F8/F$23*INDEX(Supuestos!$C$84:$C$90,MATCH(B$71,Supuestos!$A$84:$A$90,0)),0) -> 1.0003869 | C74: =IFERROR(G8/G$23*INDEX(Supuestos!$C$84:$C$90,MATCH(C$71,Supuestos!$A$84:$A$90,0)),0) -> 8.8864524 | D74: =IFERROR(H8/H$23*INDEX(Supuestos!$C$84:$C$90,MATCH(D$71,Supuestos!$A$84:$A$90,0)),0) -> 16.26856 | E74: =IFERROR(I8/I$23*INDEX(Supuestos!$C$84:$C$90,MATCH(E$71,Supuestos!$A$84:$A$90,0)),0) -> 9.6271713 | F74: =IFERROR(J8/J$23*INDEX(Supuestos!$C$84:$C$90,MATCH(F$71,Supuestos!$A$84:$A$90,0)),0) -> 5.1311898 | G74: =IFERROR(K8/K$23*INDEX(Supuestos!$C$84:$C$90,MATCH(G$71,Supuestos!$A$84:$A$90,0)),0) -> 20.997804 | H74: =IFERROR(L8/L$23*INDEX(Supuestos!$C$84:$C$90,MATCH(H$71,Supuestos!$A$84:$A$90,0)),0) -> 6.0551883
A75: =A9 -> ABC 10 kg | B75: =IFERROR(F9/F$23*INDEX(Supuestos!$C$84:$C$90,MATCH(B$71,Supuestos!$A$84:$A$90,0)),0) -> 0 | C75: =IFERROR(G9/G$23*INDEX(Supuestos!$C$84:$C$90,MATCH(C$71,Supuestos!$A$84:$A$90,0)),0) -> 0.47920719 | D75: =IFERROR(H9/H$23*INDEX(Supuestos!$C$84:$C$90,MATCH(D$71,Supuestos!$A$84:$A$90,0)),0) -> 1.913602 | E75: =IFERROR(I9/I$23*INDEX(Supuestos!$C$84:$C$90,MATCH(E$71,Supuestos!$A$84:$A$90,0)),0) -> 0.91035936 | F75: =IFERROR(J9/J$23*INDEX(Supuestos!$C$84:$C$90,MATCH(F$71,Supuestos!$A$84:$A$90,0)),0) -> 1.083492 | G75: =IFERROR(K9/K$23*INDEX(Supuestos!$C$84:$C$90,MATCH(G$71,Supuestos!$A$84:$A$90,0)),0) -> 0 | H75: =IFERROR(L9/L$23*INDEX(Supuestos!$C$84:$C$90,MATCH(H$71,Supuestos!$A$84:$A$90,0)),0) -> 0
A76: =A10 -> Agua 10 l | B76: =IFERROR(F10/F$23*INDEX(Supuestos!$C$84:$C$90,MATCH(B$71,Supuestos!$A$84:$A$90,0)),0) -> 0 | C76: =IFERROR(G10/G$23*INDEX(Supuestos!$C$84:$C$90,MATCH(C$71,Supuestos!$A$84:$A$90,0)),0) -> 0.6700217 | D76: =IFERROR(H10/H$23*INDEX(Supuestos!$C$84:$C$90,MATCH(D$71,Supuestos!$A$84:$A$90,0)),0) -> 3.026274 | E76: =IFERROR(I10/I$23*INDEX(Supuestos!$C$84:$C$90,MATCH(E$71,Supuestos!$A$84:$A$90,0)),0) -> 0.86612606 | F76: =IFERROR(J10/J$23*INDEX(Supuestos!$C$84:$C$90,MATCH(F$71,Supuestos!$A$84:$A$90,0)),0) -> 0.79954431 | G76: =IFERROR(K10/K$23*INDEX(Supuestos!$C$84:$C$90,MATCH(G$71,Supuestos!$A$84:$A$90,0)),0) -> 2.0993624 | H76: =IFERROR(L10/L$23*INDEX(Supuestos!$C$84:$C$90,MATCH(H$71,Supuestos!$A$84:$A$90,0)),0) -> 0.61944356
A77: =A11 -> AFFF 10 l | B77: =IFERROR(F11/F$23*INDEX(Supuestos!$C$84:$C$90,MATCH(B$71,Supuestos!$A$84:$A$90,0)),0) -> 0 | C77: =IFERROR(G11/G$23*INDEX(Supuestos!$C$84:$C$90,MATCH(C$71,Supuestos!$A$84:$A$90,0)),0) -> 0 | D77: =IFERROR(H11/H$23*INDEX(Supuestos!$C$84:$C$90,MATCH(D$71,Supuestos!$A$84:$A$90,0)),0) -> 0 | E77: =IFERROR(I11/I$23*INDEX(Supuestos!$C$84:$C$90,MATCH(E$71,Supuestos!$A$84:$A$90,0)),0) -> 0 | F77: =IFERROR(J11/J$23*INDEX(Supuestos!$C$84:$C$90,MATCH(F$71,Supuestos!$A$84:$A$90,0)),0) -> 0 | G77: =IFERROR(K11/K$23*INDEX(Supuestos!$C$84:$C$90,MATCH(G$71,Supuestos!$A$84:$A$90,0)),0) -> 3.661271 | H77: =IFERROR(L11/L$23*INDEX(Supuestos!$C$84:$C$90,MATCH(H$71,Supuestos!$A$84:$A$90,0)),0) -> 0
A78: =A12 -> AFFF 50 l s/ruedas | B78: =IFERROR(F12/F$23*INDEX(Supuestos!$C$84:$C$90,MATCH(B$71,Supuestos!$A$84:$A$90,0)),0) -> 0 | C78: =IFERROR(G12/G$23*INDEX(Supuestos!$C$84:$C$90,MATCH(C$71,Supuestos!$A$84:$A$90,0)),0) -> 0 | D78: =IFERROR(H12/H$23*INDEX(Supuestos!$C$84:$C$90,MATCH(D$71,Supuestos!$A$84:$A$90,0)),0) -> 0 | E78: =IFERROR(I12/I$23*INDEX(Supuestos!$C$84:$C$90,MATCH(E$71,Supuestos!$A$84:$A$90,0)),0) -> 0 | F78: =IFERROR(J12/J$23*INDEX(Supuestos!$C$84:$C$90,MATCH(F$71,Supuestos!$A$84:$A$90,0)),0) -> 0 | G78: =IFERROR(K12/K$23*INDEX(Supuestos!$C$84:$C$90,MATCH(G$71,Supuestos!$A$84:$A$90,0)),0) -> 1.9105178 | H78: =IFERROR(L12/L$23*INDEX(Supuestos!$C$84:$C$90,MATCH(H$71,Supuestos!$A$84:$A$90,0)),0) -> 0
A79: =A13 -> BC 5 kg | B79: =IFERROR(F13/F$23*INDEX(Supuestos!$C$84:$C$90,MATCH(B$71,Supuestos!$A$84:$A$90,0)),0) -> 0 | C79: =IFERROR(G13/G$23*INDEX(Supuestos!$C$84:$C$90,MATCH(C$71,Supuestos!$A$84:$A$90,0)),0) -> 0 | D79: =IFERROR(H13/H$23*INDEX(Supuestos!$C$84:$C$90,MATCH(D$71,Supuestos!$A$84:$A$90,0)),0) -> 0 | E79: =IFERROR(I13/I$23*INDEX(Supuestos!$C$84:$C$90,MATCH(E$71,Supuestos!$A$84:$A$90,0)),0) -> 0 | F79: =IFERROR(J13/J$23*INDEX(Supuestos!$C$84:$C$90,MATCH(F$71,Supuestos!$A$84:$A$90,0)),0) -> 0 | G79: =IFERROR(K13/K$23*INDEX(Supuestos!$C$84:$C$90,MATCH(G$71,Supuestos!$A$84:$A$90,0)),0) -> 1.0983813 | H79: =IFERROR(L13/L$23*INDEX(Supuestos!$C$84:$C$90,MATCH(H$71,Supuestos!$A$84:$A$90,0)),0) -> 0
A80: =A14 -> Sales K 6 l | B80: =IFERROR(F14/F$23*INDEX(Supuestos!$C$84:$C$90,MATCH(B$71,Supuestos!$A$84:$A$90,0)),0) -> 0 | C80: =IFERROR(G14/G$23*INDEX(Supuestos!$C$84:$C$90,MATCH(C$71,Supuestos!$A$84:$A$90,0)),0) -> 0.19632341 | D80: =IFERROR(H14/H$23*INDEX(Supuestos!$C$84:$C$90,MATCH(D$71,Supuestos!$A$84:$A$90,0)),0) -> 0.78371589 | E80: =IFERROR(I14/I$23*INDEX(Supuestos!$C$84:$C$90,MATCH(E$71,Supuestos!$A$84:$A$90,0)),0) -> 0.6552269 | F80: =IFERROR(J14/J$23*INDEX(Supuestos!$C$84:$C$90,MATCH(F$71,Supuestos!$A$84:$A$90,0)),0) -> 1.6537159 | G80: =IFERROR(K14/K$23*INDEX(Supuestos!$C$84:$C$90,MATCH(G$71,Supuestos!$A$84:$A$90,0)),0) -> 1.2752337 | H80: =IFERROR(L14/L$23*INDEX(Supuestos!$C$84:$C$90,MATCH(H$71,Supuestos!$A$84:$A$90,0)),0) -> 0
A81: =A15 -> CO₂ 2 kg | B81: =IFERROR(F15/F$23*INDEX(Supuestos!$C$84:$C$90,MATCH(B$71,Supuestos!$A$84:$A$90,0)),0) -> 0 | C81: =IFERROR(G15/G$23*INDEX(Supuestos!$C$84:$C$90,MATCH(C$71,Supuestos!$A$84:$A$90,0)),0) -> 2.1488856 | D81: =IFERROR(H15/H$23*INDEX(Supuestos!$C$84:$C$90,MATCH(D$71,Supuestos!$A$84:$A$90,0)),0) -> 3.5394731 | E81: =IFERROR(I15/I$23*INDEX(Supuestos!$C$84:$C$90,MATCH(E$71,Supuestos!$A$84:$A$90,0)),0) -> 3.3606119 | F81: =IFERROR(J15/J$23*INDEX(Supuestos!$C$84:$C$90,MATCH(F$71,Supuestos!$A$84:$A$90,0)),0) -> 1.9852593 | G81: =IFERROR(K15/K$23*INDEX(Supuestos!$C$84:$C$90,MATCH(G$71,Supuestos!$A$84:$A$90,0)),0) -> 1.18282 | H81: =IFERROR(L15/L$23*INDEX(Supuestos!$C$84:$C$90,MATCH(H$71,Supuestos!$A$84:$A$90,0)),0) -> 2.773795
A82: =A16 -> CO₂ 5 kg | B82: =IFERROR(F16/F$23*INDEX(Supuestos!$C$84:$C$90,MATCH(B$71,Supuestos!$A$84:$A$90,0)),0) -> 0 | C82: =IFERROR(G16/G$23*INDEX(Supuestos!$C$84:$C$90,MATCH(C$71,Supuestos!$A$84:$A$90,0)),0) -> 0.33033456 | D82: =IFERROR(H16/H$23*INDEX(Supuestos!$C$84:$C$90,MATCH(D$71,Supuestos!$A$84:$A$90,0)),0) -> 4.2987492 | E82: =IFERROR(I16/I$23*INDEX(Supuestos!$C$84:$C$90,MATCH(E$71,Supuestos!$A$84:$A$90,0)),0) -> 0.17038955 | F82: =IFERROR(J16/J$23*INDEX(Supuestos!$C$84:$C$90,MATCH(F$71,Supuestos!$A$84:$A$90,0)),0) -> 1.0750746 | G82: =IFERROR(K16/K$23*INDEX(Supuestos!$C$84:$C$90,MATCH(G$71,Supuestos!$A$84:$A$90,0)),0) -> 6.6321979 | H82: =IFERROR(L16/L$23*INDEX(Supuestos!$C$84:$C$90,MATCH(H$71,Supuestos!$A$84:$A$90,0)),0) -> 0
A83: =A17 -> HCFC/HFC 5 kg | B83: =IFERROR(F17/F$23*INDEX(Supuestos!$C$84:$C$90,MATCH(B$71,Supuestos!$A$84:$A$90,0)),0) -> 0 | C83: =IFERROR(G17/G$23*INDEX(Supuestos!$C$84:$C$90,MATCH(C$71,Supuestos!$A$84:$A$90,0)),0) -> 0 | D83: =IFERROR(H17/H$23*INDEX(Supuestos!$C$84:$C$90,MATCH(D$71,Supuestos!$A$84:$A$90,0)),0) -> 0.97069448 | E83: =IFERROR(I17/I$23*INDEX(Supuestos!$C$84:$C$90,MATCH(E$71,Supuestos!$A$84:$A$90,0)),0) -> 0 | F83: =IFERROR(J17/J$23*INDEX(Supuestos!$C$84:$C$90,MATCH(F$71,Supuestos!$A$84:$A$90,0)),0) -> 0 | G83: =IFERROR(K17/K$23*INDEX(Supuestos!$C$84:$C$90,MATCH(G$71,Supuestos!$A$84:$A$90,0)),0) -> 1.9915149 | H83: =IFERROR(L17/L$23*INDEX(Supuestos!$C$84:$C$90,MATCH(H$71,Supuestos!$A$84:$A$90,0)),0) -> 0
A84: =A18 -> Clase D 9 l | B84: =IFERROR(F18/F$23*INDEX(Supuestos!$C$84:$C$90,MATCH(B$71,Supuestos!$A$84:$A$90,0)),0) -> 0 | C84: =IFERROR(G18/G$23*INDEX(Supuestos!$C$84:$C$90,MATCH(C$71,Supuestos!$A$84:$A$90,0)),0) -> 0 | D84: =IFERROR(H18/H$23*INDEX(Supuestos!$C$84:$C$90,MATCH(D$71,Supuestos!$A$84:$A$90,0)),0) -> 0 | E84: =IFERROR(I18/I$23*INDEX(Supuestos!$C$84:$C$90,MATCH(E$71,Supuestos!$A$84:$A$90,0)),0) -> 0 | F84: =IFERROR(J18/J$23*INDEX(Supuestos!$C$84:$C$90,MATCH(F$71,Supuestos!$A$84:$A$90,0)),0) -> 0 | G84: =IFERROR(K18/K$23*INDEX(Supuestos!$C$84:$C$90,MATCH(G$71,Supuestos!$A$84:$A$90,0)),0) -> 0.99852846 | H84: =IFERROR(L18/L$23*INDEX(Supuestos!$C$84:$C$90,MATCH(H$71,Supuestos!$A$84:$A$90,0)),0) -> 0
A85: =A19 -> ABC 25 kg s/ruedas | B85: =IFERROR(F19/F$23*INDEX(Supuestos!$C$84:$C$90,MATCH(B$71,Supuestos!$A$84:$A$90,0)),0) -> 0 | C85: =IFERROR(G19/G$23*INDEX(Supuestos!$C$84:$C$90,MATCH(C$71,Supuestos!$A$84:$A$90,0)),0) -> 0.056136602 | D85: =IFERROR(H19/H$23*INDEX(Supuestos!$C$84:$C$90,MATCH(D$71,Supuestos!$A$84:$A$90,0)),0) -> 0.49425148 | E85: =IFERROR(I19/I$23*INDEX(Supuestos!$C$84:$C$90,MATCH(E$71,Supuestos!$A$84:$A$90,0)),0) -> 0.037950537 | F85: =IFERROR(J19/J$23*INDEX(Supuestos!$C$84:$C$90,MATCH(F$71,Supuestos!$A$84:$A$90,0)),0) -> 0.10718167 | G85: =IFERROR(K19/K$23*INDEX(Supuestos!$C$84:$C$90,MATCH(G$71,Supuestos!$A$84:$A$90,0)),0) -> 0.78864436 | H85: =IFERROR(L19/L$23*INDEX(Supuestos!$C$84:$C$90,MATCH(H$71,Supuestos!$A$84:$A$90,0)),0) -> 0
... A88: =A22 -> ABC 100 kg s/ruedas | B88: =IFERROR(F22/F$23*INDEX(Supuestos!$C$84:$C$90,MATCH(B$71,Supuestos!$A$84:$A$90,0)),0) -> 0 | C88: =IFERROR(G22/G$23*INDEX(Supuestos!$C$84:$C$90,MATCH(C$71,Supuestos!$A$84:$A$90,0)),0) -> 0.017925974 | D88: =IFERROR(H22/H$23*INDEX(Supuestos!$C$84:$C$90,MATCH(D$71,Supuestos!$A$84:$A$90,0)),0) -> 0.1578282 | E88: =IFERROR(I22/I$23*INDEX(Supuestos!$C$84:$C$90,MATCH(E$71,Supuestos!$A$84:$A$90,0)),0) -> 0.012118659 | F88: =IFERROR(J22/J$23*INDEX(Supuestos!$C$84:$C$90,MATCH(F$71,Supuestos!$A$84:$A$90,0)),0) -> 0.034226079 | G88: =IFERROR(K22/K$23*INDEX(Supuestos!$C$84:$C$90,MATCH(G$71,Supuestos!$A$84:$A$90,0)),0) -> 0.25183601 | H88: =IFERROR(L22/L$23*INDEX(Supuestos!$C$84:$C$90,MATCH(H$71,Supuestos!$A$84:$A$90,0)),0) -> 0
A89: u. por cliente | B89: =SUM(B72:B88) -> 25 | C89: =SUM(C72:C88) -> 14 | D89: =SUM(D72:D88) -> 35 | E89: =SUM(E72:E88) -> 18 | F89: =SUM(F72:F88) -> 20 | G89: =SUM(G72:G88) -> 45 | H89: =SUM(H72:H88) -> 16

Sheet Vehículos y viajes
A1: Vehículos y viajes
A2: Cada viaje sale con recargados + transitorios para dejar y vuelve con los del cliente + los transitorios que retira. En cada turno el vehículo hace su recorrido y vuelve cargado.
A4: 1. Capacidad de cada vehículo
A5: Dato | B5: Kangoo Express | C5: Master L1H1 | D5: Master L2H2 | E5: Master L3H2 | F5: Cómo se calcula
A6: Piso útil (m²) | B6: =Supuestos!$B$50*Supuestos!$B$51*Supuestos!$B$20 -> 1.6206 | C6: =Supuestos!$C$50*Supuestos!$C$51*Supuestos!$B$20 -> 3.4192463 | D6: =Supuestos!$D$50*Supuestos!$D$51*Supuestos!$B$20 -> 4.0811212 | E6: =Supuestos!$E$50*Supuestos!$E$51*Supuestos!$B$20 -> 4.9415588 | F6: largo × ancho × aprovechamiento
A7: Carga neta disponible (kg) | B7: =(Supuestos!$B$54-Supuestos!$B$17*Supuestos!$B$18)*(1-Supuestos!$B$19) -> 531 | C7: =(Supuestos!$C$54-Supuestos!$B$17*Supuestos!$B$18)*(1-Supuestos!$B$19) -> 1225.8 | D7: =(Supuestos!$D$54-Supuestos!$B$17*Supuestos!$B$18)*(1-Supuestos!$B$19) -> 1161.9 | E7: =(Supuestos!$E$54-Supuestos!$B$17*Supuestos!$B$18)*(1-Supuestos!$B$19) -> 1093.5 | F7: (carga útil − personas) × (1 − tara)
A8: Volumen nominal (m³) | B8: =Supuestos!$B$53 -> 3.3 | C8: =Supuestos!$C$53 -> 8 | D8: =Supuestos!$D$53 -> 10.8 | E8: =Supuestos!$E$53 -> 13 | F8: dato de Renault
A9: Precio actual (ARS) | B9: =Supuestos!$B$57 -> 33626485 | C9: =Supuestos!$C$57 -> 67780000 | D9: =Supuestos!$D$57 -> 73883676 | E9: =Supuestos!$E$57 -> 78322536 | F9: ver Supuestos
A10: Lleva rodantes | B10: =IF(Supuestos!$B$55=1,"Sí","No") -> No | C10: =IF(Supuestos!$C$55=1,"Sí","No") -> Sí | D10: =IF(Supuestos!$D$55=1,"Sí","No") -> Sí | E10: =IF(Supuestos!$E$55=1,"Sí","No") -> Sí
A12: 2. Datos de cada rubro para el recorrido
A13: Rubro | B13: Vehículo | C13: u/día promedio | D13: u/día pico | E13: % con transitorio | F13: u. por cliente | G13: min por u. | H13: Peso medio (kg/u) | I13: m² de piso por u. | J13: h por u. del cliente | K13: u. del cliente por turno (límite de tiempo)
A14: Automotriz | B14: =INDEX(Supuestos!$B$84:$B$90,MATCH($A14,Supuestos!$A$84:$A$90,0)) -> Kangoo | C14: ='Demanda y mix'!O50 -> 291.55451 | D14: ='Demanda y mix'!Q50 -> 402.34523 | E14: =INDEX(Supuestos!$D$84:$D$90,MATCH($A14,Supuestos!$A$84:$A$90,0)) -> 1 | F14: =INDEX(Supuestos!$C$84:$C$90,MATCH($A14,Supuestos!$A$84:$A$90,0)) -> 25 | G14: =INDEX(Supuestos!$E$84:$E$90,MATCH($A14,Supuestos!$A$84:$A$90,0)) -> 0.5 | H14: ='Demanda y mix'!R50 -> 2.2601006 | I14: ='Demanda y mix'!S50 -> 0.0090002579 | J14: =2/F14*(Supuestos!$B$15+Supuestos!$B$16)/60+2*G14/60 -> 0.063333333 | K14: =(Supuestos!$B$9-Supuestos!$B$14)/J14 -> 94.736842
A15: Edificios | B15: =INDEX(Supuestos!$B$84:$B$90,MATCH($A15,Supuestos!$A$84:$A$90,0)) -> Master | C15: ='Demanda y mix'!O51 -> 132.07015 | D15: ='Demanda y mix'!Q51 -> 164.03112 | E15: =INDEX(Supuestos!$D$84:$D$90,MATCH($A15,Supuestos!$A$84:$A$90,0)) -> 1 | F15: =INDEX(Supuestos!$C$84:$C$90,MATCH($A15,Supuestos!$A$84:$A$90,0)) -> 14 | G15: =INDEX(Supuestos!$E$84:$E$90,MATCH($A15,Supuestos!$A$84:$A$90,0)) -> 1.5 | H15: ='Demanda y mix'!R51 -> 9.9521135 | I15: ='Demanda y mix'!S51 -> 0.03424888 | J15: =2/F15*(Supuestos!$B$15+Supuestos!$B$16)/60+2*G15/60 -> 0.13333333 | K15: =(Supuestos!$B$9-Supuestos!$B$14)/J15 -> 45
A16: Salud | B16: =INDEX(Supuestos!$B$84:$B$90,MATCH($A16,Supuestos!$A$84:$A$90,0)) -> Master | C16: ='Demanda y mix'!O52 -> 20.557183 | D16: ='Demanda y mix'!Q52 -> 22.69513 | E16: =INDEX(Supuestos!$D$84:$D$90,MATCH($A16,Supuestos!$A$84:$A$90,0)) -> 0.9 | F16: =INDEX(Supuestos!$C$84:$C$90,MATCH($A16,Supuestos!$A$84:$A$90,0)) -> 35 | G16: =INDEX(Supuestos!$E$84:$E$90,MATCH($A16,Supuestos!$A$84:$A$90,0)) -> 1.5 | H16: ='Demanda y mix'!R52 -> 14.390407 | I16: ='Demanda y mix'!S52 -> 0.059005024 | J16: =2/F16*(Supuestos!$B$15+Supuestos!$B$16)/60+2*G16/60 -> 0.083333333 | K16: =(Supuestos!$B$9-Supuestos!$B$14)/J16 -> 72
A17: Educación | B17: =INDEX(Supuestos!$B$84:$B$90,MATCH($A17,Supuestos!$A$84:$A$90,0)) -> Master | C17: ='Demanda y mix'!O53 -> 38.892527 | D17: ='Demanda y mix'!Q53 -> 37.570181 | E17: =INDEX(Supuestos!$D$84:$D$90,MATCH($A17,Supuestos!$A$84:$A$90,0)) -> 1 | F17: =INDEX(Supuestos!$C$84:$C$90,MATCH($A17,Supuestos!$A$84:$A$90,0)) -> 18 | G17: =INDEX(Supuestos!$E$84:$E$90,MATCH($A17,Supuestos!$A$84:$A$90,0)) -> 1.5 | H17: ='Demanda y mix'!R53 -> 9.1720953 | I17: ='Demanda y mix'!S53 -> 0.029730289 | J17: =2/F17*(Supuestos!$B$15+Supuestos!$B$16)/60+2*G17/60 -> 0.11481481 | K17: =(Supuestos!$B$9-Supuestos!$B$14)/J17 -> 52.258065
A18: Hoteles | B18: =INDEX(Supuestos!$B$84:$B$90,MATCH($A18,Supuestos!$A$84:$A$90,0)) -> Master | C18: ='Demanda y mix'!O54 -> 17.167937 | D18: ='Demanda y mix'!Q54 -> 23.691753 | E18: =INDEX(Supuestos!$D$84:$D$90,MATCH($A18,Supuestos!$A$84:$A$90,0)) -> 1 | F18: =INDEX(Supuestos!$C$84:$C$90,MATCH($A18,Supuestos!$A$84:$A$90,0)) -> 20 | G18: =INDEX(Supuestos!$E$84:$E$90,MATCH($A18,Supuestos!$A$84:$A$90,0)) -> 1.5 | H18: ='Demanda y mix'!R54 -> 9.6298779 | I18: ='Demanda y mix'!S54 -> 0.036622478 | J18: =2/F18*(Supuestos!$B$15+Supuestos!$B$16)/60+2*G18/60 -> 0.10833333 | K18: =(Supuestos!$B$9-Supuestos!$B$14)/J18 -> 55.384615
A19: Industrias | B19: =INDEX(Supuestos!$B$84:$B$90,MATCH($A19,Supuestos!$A$84:$A$90,0)) -> Master | C19: ='Demanda y mix'!O55 -> 28.166448 | D19: ='Demanda y mix'!Q55 -> 31.095759 | E19: =INDEX(Supuestos!$D$84:$D$90,MATCH($A19,Supuestos!$A$84:$A$90,0)) -> 0.8 | F19: =INDEX(Supuestos!$C$84:$C$90,MATCH($A19,Supuestos!$A$84:$A$90,0)) -> 45 | G19: =INDEX(Supuestos!$E$84:$E$90,MATCH($A19,Supuestos!$A$84:$A$90,0)) -> 1.5 | H19: ='Demanda y mix'!R55 -> 19.50757 | I19: ='Demanda y mix'!S55 -> 0.092169885 | J19: =2/F19*(Supuestos!$B$15+Supuestos!$B$16)/60+2*G19/60 -> 0.075925926 | K19: =(Supuestos!$B$9-Supuestos!$B$14)/J19 -> 79.02439
A20: Supermercados | B20: =INDEX(Supuestos!$B$84:$B$90,MATCH($A20,Supuestos!$A$84:$A$90,0)) -> Kangoo | C20: ='Demanda y mix'!O56 -> 2.1745767 | D20: ='Demanda y mix'!Q56 -> 2.7008242 | E20: =INDEX(Supuestos!$D$84:$D$90,MATCH($A20,Supuestos!$A$84:$A$90,0)) -> 1 | F20: =INDEX(Supuestos!$C$84:$C$90,MATCH($A20,Supuestos!$A$84:$A$90,0)) -> 16 | G20: =INDEX(Supuestos!$E$84:$E$90,MATCH($A20,Supuestos!$A$84:$A$90,0)) -> 1 | H20: ='Demanda y mix'!R56 -> 6.7447597 | I20: ='Demanda y mix'!S56 -> 0.022241988 | J20: =2/F20*(Supuestos!$B$15+Supuestos!$B$16)/60+2*G20/60 -> 0.10625 | K20: =(Supuestos!$B$9-Supuestos!$B$14)/J20 -> 56.470588
A21: h por u. del cliente = 2 paradas cada "u. por cliente" (una para retirar y otra para entregar) × (parada + manejo) + 2 manipulaciones por u. (retiro con transitorio y entrega).
A23: 3. Carga por viaje (u. en cada sentido, recargados o del cliente + transitorios) — el menor entre espacio y peso
A24: Rubro | B24: Kangoo Express | C24: Master L1H1 | D24: Master L2H2 | E24: Master L3H2
A25: Automotriz | B25: =MIN(B$6/$I14,B$7/$H14) -> 180.06151 | C25: =MIN(C$6/$I14,C$7/$H14) -> 379.90536 | D25: =MIN(D$6/$I14,D$7/$H14) -> 453.44492 | E25: =MIN(E$6/$I14,E$7/$H14) -> 483.82802 | F25: ← espacio: piso útil / m² por u. (2 niveles; los rodantes ocupan toda la altura)
A26: Edificios | B26: =MIN(B$6/$I15,B$7/$H15) -> 47.318335 | C26: =MIN(C$6/$I15,C$7/$H15) -> 99.835271 | D26: =MIN(D$6/$I15,D$7/$H15) -> 116.74907 | E26: =MIN(E$6/$I15,E$7/$H15) -> 109.87616 | F26: peso: carga neta / peso medio del mix del rubro
A27: Salud | B27: =MIN(B$6/$I16,B$7/$H16) -> 27.465458 | C27: =MIN(C$6/$I16,C$7/$H16) -> 57.948392 | D27: =MIN(D$6/$I16,D$7/$H16) -> 69.165657 | E27: =MIN(E$6/$I16,E$7/$H16) -> 75.988121
A28: Educación | B28: =MIN(B$6/$I17,B$7/$H17) -> 54.510066 | C28: =MIN(C$6/$I17,C$7/$H17) -> 115.00885 | D28: =MIN(D$6/$I17,D$7/$H17) -> 126.67771 | E28: =MIN(E$6/$I17,E$7/$H17) -> 119.22031
A29: Hoteles | B29: =MIN(B$6/$I18,B$7/$H18) -> 44.251511 | C29: =MIN(C$6/$I18,C$7/$H18) -> 93.364688 | D29: =MIN(D$6/$I18,D$7/$H18) -> 111.4376 | E29: =MIN(E$6/$I18,E$7/$H18) -> 113.55284
A30: Industrias | B30: =MIN(B$6/$I19,B$7/$H19) -> 17.582749 | C30: =MIN(C$6/$I19,C$7/$H19) -> 37.097217 | D30: =MIN(D$6/$I19,D$7/$H19) -> 44.27825 | E30: =MIN(E$6/$I19,E$7/$H19) -> 53.613593
A31: Supermercados | B31: =MIN(B$6/$I20,B$7/$H20) -> 72.862192 | C31: =MIN(C$6/$I20,C$7/$H20) -> 153.72934 | D31: =MIN(D$6/$I20,D$7/$H20) -> 172.26707 | E31: =MIN(E$6/$I20,E$7/$H20) -> 162.12586
A33: 4. Matafuegos del cliente que mueve un vehículo en un turno
A34: Rubro | B34: Kangoo Express | C34: Master L1H1 | D34: Master L2H2 | E34: Master L3H2 | F34: Viajes por turno (Kangoo) | G34: Viajes por turno (L1H1) | H34: Viajes por turno (L2H2) | I34: Viajes por turno (L3H2)
A35: Automotriz | B35: =IF(B25/(1+$E14)>=$K14,$K14,B25/(1+$E14)*F35) -> 90.030753 | C35: =IF(C25/(1+$E14)>=$K14,$K14,C25/(1+$E14)*G35) -> 94.736842 | D35: =IF(D25/(1+$E14)>=$K14,$K14,D25/(1+$E14)*H35) -> 94.736842 | E35: =IF(E25/(1+$E14)>=$K14,$K14,E25/(1+$E14)*I35) -> 94.736842 | F35: =IF(B25/(1+$E14)>=$K14,1,MAX(1,INT(Supuestos!$B$9/(Supuestos!$B$14+B25/(1+$E14)*$J14)))) -> 1 | G35: =IF(C25/(1+$E14)>=$K14,1,MAX(1,INT(Supuestos!$B$9/(Supuestos!$B$14+C25/(1+$E14)*$J14)))) -> 1 | H35: =IF(D25/(1+$E14)>=$K14,1,MAX(1,INT(Supuestos!$B$9/(Supuestos!$B$14+D25/(1+$E14)*$J14)))) -> 1 | I35: =IF(E25/(1+$E14)>=$K14,1,MAX(1,INT(Supuestos!$B$9/(Supuestos!$B$14+E25/(1+$E14)*$J14)))) -> 1
A36: Edificios | B36: =IF(B26/(1+$E15)>=$K15,$K15,B26/(1+$E15)*F36) -> 23.659168 | C36: =IF(C26/(1+$E15)>=$K15,$K15,C26/(1+$E15)*G36) -> 45 | D36: =IF(D26/(1+$E15)>=$K15,$K15,D26/(1+$E15)*H36) -> 45 | E36: =IF(E26/(1+$E15)>=$K15,$K15,E26/(1+$E15)*I36) -> 45 | F36: =IF(B26/(1+$E15)>=$K15,1,MAX(1,INT(Supuestos!$B$9/(Supuestos!$B$14+B26/(1+$E15)*$J15)))) -> 1 | G36: =IF(C26/(1+$E15)>=$K15,1,MAX(1,INT(Supuestos!$B$9/(Supuestos!$B$14+C26/(1+$E15)*$J15)))) -> 1 | H36: =IF(D26/(1+$E15)>=$K15,1,MAX(1,INT(Supuestos!$B$9/(Supuestos!$B$14+D26/(1+$E15)*$J15)))) -> 1 | I36: =IF(E26/(1+$E15)>=$K15,1,MAX(1,INT(Supuestos!$B$9/(Supuestos!$B$14+E26/(1+$E15)*$J15)))) -> 1
A37: Salud | B37: =IF(B27/(1+$E16)>=$K16,$K16,B27/(1+$E16)*F37) -> 28.911008 | C37: =IF(C27/(1+$E16)>=$K16,$K16,C27/(1+$E16)*G37) -> 30.499154 | D37: =IF(D27/(1+$E16)>=$K16,$K16,D27/(1+$E16)*H37) -> 36.402978 | E37: =IF(E27/(1+$E16)>=$K16,$K16,E27/(1+$E16)*I37) -> 39.993748 | F37: =IF(B27/(1+$E16)>=$K16,1,MAX(1,INT(Supuestos!$B$9/(Supuestos!$B$14+B27/(1+$E16)*$J16)))) -> 2 | G37: =IF(C27/(1+$E16)>=$K16,1,MAX(1,INT(Supuestos!$B$9/(Supuestos!$B$14+C27/(1+$E16)*$J16)))) -> 1 | H37: =IF(D27/(1+$E16)>=$K16,1,MAX(1,INT(Supuestos!$B$9/(Supuestos!$B$14+D27/(1+$E16)*$J16)))) -> 1 | I37: =IF(E27/(1+$E16)>=$K16,1,MAX(1,INT(Supuestos!$B$9/(Supuestos!$B$14+E27/(1+$E16)*$J16)))) -> 1
A38: Educación | B38: =IF(B28/(1+$E17)>=$K17,$K17,B28/(1+$E17)*F38) -> 27.255033 | C38: =IF(C28/(1+$E17)>=$K17,$K17,C28/(1+$E17)*G38) -> 52.258065 | D38: =IF(D28/(1+$E17)>=$K17,$K17,D28/(1+$E17)*H38) -> 52.258065 | E38: =IF(E28/(1+$E17)>=$K17,$K17,E28/(1+$E17)*I38) -> 52.258065 | F38: =IF(B28/(1+$E17)>=$K17,1,MAX(1,INT(Supuestos!$B$9/(Supuestos!$B$14+B28/(1+$E17)*$J17)))) -> 1 | G38: =IF(C28/(1+$E17)>=$K17,1,MAX(1,INT(Supuestos!$B$9/(Supuestos!$B$14+C28/(1+$E17)*$J17)))) -> 1 | H38: =IF(D28/(1+$E17)>=$K17,1,MAX(1,INT(Supuestos!$B$9/(Supuestos!$B$14+D28/(1+$E17)*$J17)))) -> 1 | I38: =IF(E28/(1+$E17)>=$K17,1,MAX(1,INT(Supuestos!$B$9/(Supuestos!$B$14+E28/(1+$E17)*$J17)))) -> 1
A39: Hoteles | B39: =IF(B29/(1+$E18)>=$K18,$K18,B29/(1+$E18)*F39) -> 22.125756 | C39: =IF(C29/(1+$E18)>=$K18,$K18,C29/(1+$E18)*G39) -> 46.682344 | D39: =IF(D29/(1+$E18)>=$K18,$K18,D29/(1+$E18)*H39) -> 55.384615 | E39: =IF(E29/(1+$E18)>=$K18,$K18,E29/(1+$E18)*I39) -> 55.384615 | F39: =IF(B29/(1+$E18)>=$K18,1,MAX(1,INT(Supuestos!$B$9/(Supuestos!$B$14+B29/(1+$E18)*$J18)))) -> 1 | G39: =IF(C29/(1+$E18)>=$K18,1,MAX(1,INT(Supuestos!$B$9/(Supuestos!$B$14+C29/(1+$E18)*$J18)))) -> 1 | H39: =IF(D29/(1+$E18)>=$K18,1,MAX(1,INT(Supuestos!$B$9/(Supuestos!$B$14+D29/(1+$E18)*$J18)))) -> 1 | I39: =IF(E29/(1+$E18)>=$K18,1,MAX(1,INT(Supuestos!$B$9/(Supuestos!$B$14+E29/(1+$E18)*$J18)))) -> 1
A40: Industrias | B40: =IF(B30/(1+$E19)>=$K19,$K19,B30/(1+$E19)*F40) -> 29.304582 | C40: =IF(C30/(1+$E19)>=$K19,$K19,C30/(1+$E19)*G40) -> 41.21913 | D40: =IF(D30/(1+$E19)>=$K19,$K19,D30/(1+$E19)*H40) -> 49.198056 | E40: =IF(E30/(1+$E19)>=$K19,$K19,E30/(1+$E19)*I40) -> 29.78533 | F40: =IF(B30/(1+$E19)>=$K19,1,MAX(1,INT(Supuestos!$B$9/(Supuestos!$B$14+B30/(1+$E19)*$J19)))) -> 3 | G40: =IF(C30/(1+$E19)>=$K19,1,MAX(1,INT(Supuestos!$B$9/(Supuestos!$B$14+C30/(1+$E19)*$J19)))) -> 2 | H40: =IF(D30/(1+$E19)>=$K19,1,MAX(1,INT(Supuestos!$B$9/(Supuestos!$B$14+D30/(1+$E19)*$J19)))) -> 2 | I40: =IF(E30/(1+$E19)>=$K19,1,MAX(1,INT(Supuestos!$B$9/(Supuestos!$B$14+E30/(1+$E19)*$J19)))) -> 1
A41: Supermercados | B41: =IF(B31/(1+$E20)>=$K20,$K20,B31/(1+$E20)*F41) -> 36.431096 | C41: =IF(C31/(1+$E20)>=$K20,$K20,C31/(1+$E20)*G41) -> 56.470588 | D41: =IF(D31/(1+$E20)>=$K20,$K20,D31/(1+$E20)*H41) -> 56.470588 | E41: =IF(E31/(1+$E20)>=$K20,$K20,E31/(1+$E20)*I41) -> 56.470588 | F41: =IF(B31/(1+$E20)>=$K20,1,MAX(1,INT(Supuestos!$B$9/(Supuestos!$B$14+B31/(1+$E20)*$J20)))) -> 1 | G41: =IF(C31/(1+$E20)>=$K20,1,MAX(1,INT(Supuestos!$B$9/(Supuestos!$B$14+C31/(1+$E20)*$J20)))) -> 1 | H41: =IF(D31/(1+$E20)>=$K20,1,MAX(1,INT(Supuestos!$B$9/(Supuestos!$B$14+D31/(1+$E20)*$J20)))) -> 1 | I41: =IF(E31/(1+$E20)>=$K20,1,MAX(1,INT(Supuestos!$B$9/(Supuestos!$B$14+E31/(1+$E20)*$J20)))) -> 1
A42: Si el vehículo se llena antes de que se termine el turno, puede hacer más de un viaje; si no, el límite es el tiempo (un solo recorrido por turno).
A44: 5. ¿Qué Master conviene? (rubros asignados a Master, en el mes pico)
A45: Dato | B45: Kangoo Express | C45: Master L1H1 | D45: Master L2H2 | E45: Master L3H2
A46: Vehículo-turnos por día (pico) | B46: =SUMPRODUCT(($B$14:$B$20="Kangoo")*$D$14:$D$20/B$35:B$41) -> 4.5431106 | C46: =SUMPRODUCT(($B$14:$B$20="Master")*$D$14:$D$20/C$35:C$41) -> 6.370106 | D46: =SUMPRODUCT(($B$14:$B$20="Master")*$D$14:$D$20/D$35:D$41) -> 6.0473336 | E46: =SUMPRODUCT(($B$14:$B$20="Master")*$D$14:$D$20/E$35:E$41) -> 6.4033021
A47: Vehículos necesarios | B47: =ROUNDUP(B46/Supuestos!$B$8,0) -> 3 | C47: =ROUNDUP(C46/Supuestos!$B$8,0) -> 4 | D47: =ROUNDUP(D46/Supuestos!$B$8,0) -> 4 | E47: =ROUNDUP(E46/Supuestos!$B$8,0) -> 4
A48: Inversión (ARS) | B48: =B47*B$9 -> 100879455 | C48: =C47*C$9 -> 271120000 | D48: =D47*D$9 -> 2.955347e+08 | E48: =E47*E$9 -> 3.1329014e+08
A49: Puntaje (menos vehículos, después menor precio) | B49: — | C49: =C47*1000000000000+C$9 -> 4000067780000 | D49: =D47*1000000000000+D$9 -> 4.0000739e+12 | E49: =E47*1000000000000+E$9 -> 4.0000783e+12
A50: Master que conviene | B50: =INDEX($C$45:$E$45,MATCH(MIN(C49:E49),C49:E49,0)) -> Master L1H1 | C50: =MATCH(B50,$C$45:$E$45,0)+1 -> 2 | D50: ← columna del modelo elegido (1 = Kangoo, 2 a 4 = Master)
A52: 6. Plan de recorridos con los vehículos elegidos
A53: Rubro | B53: Vehículo | C53: Modelo | D53: u. del cliente por vehículo-turno | E53: Viajes por turno | F53: Vehículo-turnos (prom.) | G53: Vehículo-turnos (pico) | H53: Viajes por día (pico) | I53: Paradas por día (pico) | J53: Carga por viaje (u., cada sentido)
A54: Automotriz | B54: =B14 -> Kangoo | C54: =IF(B54="Kangoo",$B$5,$B$50) -> Kangoo Express | D54: =INDEX($B35:$E35,IF(B54="Kangoo",1,$C$50)) -> 90.030753 | E54: =INDEX($F35:$I35,IF(B54="Kangoo",1,$C$50)) -> 1 | F54: =C14/D54 -> 3.238388 | G54: =D14/D54 -> 4.4689755 | H54: =G54*E54 -> 4.4689755 | I54: =D14/F14*2 -> 32.187618 | J54: =MIN(INDEX($B25:$E25,IF(B54="Kangoo",1,$C$50)),D54/E54*(1+E14)) -> 180.06151
A55: Edificios | B55: =B15 -> Master | C55: =IF(B55="Kangoo",$B$5,$B$50) -> Master L1H1 | D55: =INDEX($B36:$E36,IF(B55="Kangoo",1,$C$50)) -> 45 | E55: =INDEX($F36:$I36,IF(B55="Kangoo",1,$C$50)) -> 1 | F55: =C15/D55 -> 2.9348922 | G55: =D15/D55 -> 3.6451361 | H55: =G55*E55 -> 3.6451361 | I55: =D15/F15*2 -> 23.433017 | J55: =MIN(INDEX($B26:$E26,IF(B55="Kangoo",1,$C$50)),D55/E55*(1+E15)) -> 90
A56: Salud | B56: =B16 -> Master | C56: =IF(B56="Kangoo",$B$5,$B$50) -> Master L1H1 | D56: =INDEX($B37:$E37,IF(B56="Kangoo",1,$C$50)) -> 30.499154 | E56: =INDEX($F37:$I37,IF(B56="Kangoo",1,$C$50)) -> 1 | F56: =C16/D56 -> 0.67402471 | G56: =D16/D56 -> 0.74412328 | H56: =G56*E56 -> 0.74412328 | I56: =D16/F16*2 -> 1.2968646 | J56: =MIN(INDEX($B27:$E27,IF(B56="Kangoo",1,$C$50)),D56/E56*(1+E16)) -> 57.948392
A57: Educación | B57: =B17 -> Master | C57: =IF(B57="Kangoo",$B$5,$B$50) -> Master L1H1 | D57: =INDEX($B38:$E38,IF(B57="Kangoo",1,$C$50)) -> 52.258065 | E57: =INDEX($F38:$I38,IF(B57="Kangoo",1,$C$50)) -> 1 | F57: =C17/D57 -> 0.74423972 | G57: =D17/D57 -> 0.71893557 | H57: =G57*E57 -> 0.71893557 | I57: =D17/F17*2 -> 4.1744646 | J57: =MIN(INDEX($B28:$E28,IF(B57="Kangoo",1,$C$50)),D57/E57*(1+E17)) -> 104.51613
A58: Hoteles | B58: =B18 -> Master | C58: =IF(B58="Kangoo",$B$5,$B$50) -> Master L1H1 | D58: =INDEX($B39:$E39,IF(B58="Kangoo",1,$C$50)) -> 46.682344 | E58: =INDEX($F39:$I39,IF(B58="Kangoo",1,$C$50)) -> 1 | F58: =C18/D58 -> 0.36776082 | G58: =D18/D58 -> 0.50750993 | H58: =G58*E58 -> 0.50750993 | I58: =D18/F18*2 -> 2.3691753 | J58: =MIN(INDEX($B29:$E29,IF(B58="Kangoo",1,$C$50)),D58/E58*(1+E18)) -> 93.364688
A59: Industrias | B59: =B19 -> Master | C59: =IF(B59="Kangoo",$B$5,$B$50) -> Master L1H1 | D59: =INDEX($B40:$E40,IF(B59="Kangoo",1,$C$50)) -> 41.21913 | E59: =INDEX($F40:$I40,IF(B59="Kangoo",1,$C$50)) -> 2 | F59: =C19/D59 -> 0.68333437 | G59: =D19/D59 -> 0.75440114 | H59: =G59*E59 -> 1.5088023 | I59: =D19/F19*2 -> 1.3820337 | J59: =MIN(INDEX($B30:$E30,IF(B59="Kangoo",1,$C$50)),D59/E59*(1+E19)) -> 37.097217
A60: Supermercados | B60: =B20 -> Kangoo | C60: =IF(B60="Kangoo",$B$5,$B$50) -> Kangoo Express | D60: =INDEX($B41:$E41,IF(B60="Kangoo",1,$C$50)) -> 36.431096 | E60: =INDEX($F41:$I41,IF(B60="Kangoo",1,$C$50)) -> 1 | F60: =C20/D60 -> 0.059690125 | G60: =D20/D60 -> 0.074135135 | H60: =G60*E60 -> 0.074135135 | I60: =D20/F20*2 -> 0.33760303 | J60: =MIN(INDEX($B31:$E31,IF(B60="Kangoo",1,$C$50)),D60/E60*(1+E20)) -> 72.862192
A61: Total | F61: =SUM(F54:F60) -> 8.7023299 | G61: =SUM(G54:G60) -> 10.913217 | H61: =SUM(H54:H60) -> 11.667618 | I61: =SUM(I54:I60) -> 65.180777
A63: 7. Flota
A64: Vehículo | B64: Modelo | C64: Vehículo-turnos (prom.) | D64: Vehículo-turnos (pico) | E64: Vehículos necesarios | F64: Ocupación en el mes promedio | G64: Viajes por día (pico) | H64: Inversión (ARS)
A65: Kangoo | B65: =$B$5 -> Kangoo Express | C65: =SUMIF($B$54:$B$60,A65,$F$54:$F$60) -> 3.2980782 | D65: =SUMIF($B$54:$B$60,A65,$G$54:$G$60) -> 4.5431106 | E65: =ROUNDUP(D65/Supuestos!$B$8,0) -> 3 | F65: =IFERROR(C65/(E65*Supuestos!$B$8),0) -> 0.54967969 | G65: =SUMIF($B$54:$B$60,A65,$H$54:$H$60) -> 4.5431106 | H65: =E65*$B$9 -> 100879455
A66: Master | B66: =$B$50 -> Master L1H1 | C66: =SUMIF($B$54:$B$60,A66,$F$54:$F$60) -> 5.4042518 | D66: =SUMIF($B$54:$B$60,A66,$G$54:$G$60) -> 6.370106 | E66: =ROUNDUP(D66/Supuestos!$B$8,0) -> 4 | F66: =IFERROR(C66/(E66*Supuestos!$B$8),0) -> 0.67553147 | G66: =SUMIF($B$54:$B$60,A66,$H$54:$H$60) -> 7.1245071 | H66: =E66*INDEX($B$9:$E$9,$C$50) -> 271120000
A67: Total | C67: =SUM(C65:C66) -> 8.7023299 | D67: =SUM(D65:D66) -> 10.913217 | E67: =SUM(E65:E66) -> 7 | G67: =SUM(G65:G66) -> 11.667618 | H67: =SUM(H65:H66) -> 371999455
A68: Vehículos necesarios = vehículo-turnos del día pico / turnos. Viajes por día = vehículo-turnos × viajes por turno.
A69: Master: se cargan a mano en el cliente, en estantería con celdas; en la planta se descargan a las jaulas A/B con transpaleta (no hace falta autoelevador en recargas).

Sheet Transitorios y pulmón
A1: Transitorios y pulmón de recargas
A2: Transitorio = matafuego de FLAMA que se le deja al cliente mientras el suyo está en la planta. Pulmón = lugar en la planta para lo que llega, lo que sale y los transitorios.
A4: 1. Transitorios por tipo
A5: Tipo | B5: Salen por día (prom.) | C5: Salen por día (mes pico) | D5: % con PH | E5: Días afuera + revisión (base) | F5: Días (mínimo) | G5: Fuera de servicio por su revisión | H5: Stock recomendado (u) | I5: Punto mínimo (u) | J5: En la planta (u) | K5: Jaulas en la planta | L5: Rodante
A6: =Supuestos!A62 -> ABC 1 kg | B6: =SUMPRODUCT('Demanda y mix'!F6:L6,'Demanda y mix'!$F$25:$L$25)/(Supuestos!$B$7*Supuestos!$B$6) -> 280.025 | C6: =SUMPRODUCT('Demanda y mix'!F6:L6,'Demanda y mix'!$F$24:$L$24,'Demanda y mix'!$F$25:$L$25)/Supuestos!$B$6 -> 336.02267 | D6: =Supuestos!H62 -> 0.25 | E6: =Supuestos!$B$25*(1-D6)+Supuestos!$B$26*D6+Supuestos!$B$27+Supuestos!$B$28 -> 4 | F6: =Supuestos!$C$25*(1-D6)+Supuestos!$C$26*D6+Supuestos!$C$27+Supuestos!$C$28 -> 2 | G6: =(Supuestos!$B$31*Supuestos!$B$32+(Supuestos!$B$7*Supuestos!$B$6/E6)*Supuestos!$B$33*Supuestos!$B$32)/(Supuestos!$B$7*Supuestos!$B$6) -> 0.01625 | H6: =ROUNDUP(C6*E6*(1+Supuestos!$B$30)/(1-G6),0) -> 1503 | I6: =ROUNDUP(B6*F6,0) -> 561 | J6: =MAX(0,H6-C6*(E6-Supuestos!$B$28)) -> 494.93199 | K6: =J6/Supuestos!F62 -> 6.8740555 | L6: =Supuestos!G62 -> 0
A7: =Supuestos!A63 -> ABC 2,5 kg | B7: =SUMPRODUCT('Demanda y mix'!F7:L7,'Demanda y mix'!$F$25:$L$25)/(Supuestos!$B$7*Supuestos!$B$6) -> 23.581914 | C7: =SUMPRODUCT('Demanda y mix'!F7:L7,'Demanda y mix'!$F$24:$L$24,'Demanda y mix'!$F$25:$L$25)/Supuestos!$B$6 -> 24.955083 | D7: =Supuestos!H63 -> 0.25 | E7: =Supuestos!$B$25*(1-D7)+Supuestos!$B$26*D7+Supuestos!$B$27+Supuestos!$B$28 -> 4 | F7: =Supuestos!$C$25*(1-D7)+Supuestos!$C$26*D7+Supuestos!$C$27+Supuestos!$C$28 -> 2 | G7: =(Supuestos!$B$31*Supuestos!$B$32+(Supuestos!$B$7*Supuestos!$B$6/E7)*Supuestos!$B$33*Supuestos!$B$32)/(Supuestos!$B$7*Supuestos!$B$6) -> 0.01625 | H7: =ROUNDUP(C7*E7*(1+Supuestos!$B$30)/(1-G7),0) -> 112 | I7: =ROUNDUP(B7*F7,0) -> 48 | J7: =MAX(0,H7-C7*(E7-Supuestos!$B$28)) -> 37.134752 | K7: =J7/Supuestos!F63 -> 1.2378251 | L7: =Supuestos!G63 -> 0
A8: =Supuestos!A64 -> ABC 5 kg | B8: =SUMPRODUCT('Demanda y mix'!F8:L8,'Demanda y mix'!$F$25:$L$25)/(Supuestos!$B$7*Supuestos!$B$6) -> 140.64088 | C8: =SUMPRODUCT('Demanda y mix'!F8:L8,'Demanda y mix'!$F$24:$L$24,'Demanda y mix'!$F$25:$L$25)/Supuestos!$B$6 -> 146.53467 | D8: =Supuestos!H64 -> 0.25 | E8: =Supuestos!$B$25*(1-D8)+Supuestos!$B$26*D8+Supuestos!$B$27+Supuestos!$B$28 -> 4 | F8: =Supuestos!$C$25*(1-D8)+Supuestos!$C$26*D8+Supuestos!$C$27+Supuestos!$C$28 -> 2 | G8: =(Supuestos!$B$31*Supuestos!$B$32+(Supuestos!$B$7*Supuestos!$B$6/E8)*Supuestos!$B$33*Supuestos!$B$32)/(Supuestos!$B$7*Supuestos!$B$6) -> 0.01625 | H8: =ROUNDUP(C8*E8*(1+Supuestos!$B$30)/(1-G8),0) -> 656 | I8: =ROUNDUP(B8*F8,0) -> 282 | J8: =MAX(0,H8-C8*(E8-Supuestos!$B$28)) -> 216.39599 | K8: =J8/Supuestos!F64 -> 9.0164998 | L8: =Supuestos!G64 -> 0
A9: =Supuestos!A65 -> ABC 10 kg | B9: =SUMPRODUCT('Demanda y mix'!F9:L9,'Demanda y mix'!$F$25:$L$25)/(Supuestos!$B$7*Supuestos!$B$6) -> 8.4292716 | C9: =SUMPRODUCT('Demanda y mix'!F9:L9,'Demanda y mix'!$F$24:$L$24,'Demanda y mix'!$F$25:$L$25)/Supuestos!$B$6 -> 8.6217523 | D9: =Supuestos!H65 -> 0.25 | E9: =Supuestos!$B$25*(1-D9)+Supuestos!$B$26*D9+Supuestos!$B$27+Supuestos!$B$28 -> 4 | F9: =Supuestos!$C$25*(1-D9)+Supuestos!$C$26*D9+Supuestos!$C$27+Supuestos!$C$28 -> 2 | G9: =(Supuestos!$B$31*Supuestos!$B$32+(Supuestos!$B$7*Supuestos!$B$6/E9)*Supuestos!$B$33*Supuestos!$B$32)/(Supuestos!$B$7*Supuestos!$B$6) -> 0.01625 | H9: =ROUNDUP(C9*E9*(1+Supuestos!$B$30)/(1-G9),0) -> 39 | I9: =ROUNDUP(B9*F9,0) -> 17 | J9: =MAX(0,H9-C9*(E9-Supuestos!$B$28)) -> 13.134743 | K9: =J9/Supuestos!F65 -> 0.82092145 | L9: =Supuestos!G65 -> 0
A10: =Supuestos!A66 -> Agua 10 l | B10: =SUMPRODUCT('Demanda y mix'!F10:L10,'Demanda y mix'!$F$25:$L$25)/(Supuestos!$B$7*Supuestos!$B$6) -> 11.613612 | C10: =SUMPRODUCT('Demanda y mix'!F10:L10,'Demanda y mix'!$F$24:$L$24,'Demanda y mix'!$F$25:$L$25)/Supuestos!$B$6 -> 11.857801 | D10: =Supuestos!H66 -> 0.5 | E10: =Supuestos!$B$25*(1-D10)+Supuestos!$B$26*D10+Supuestos!$B$27+Supuestos!$B$28 -> 4.5 | F10: =Supuestos!$C$25*(1-D10)+Supuestos!$C$26*D10+Supuestos!$C$27+Supuestos!$C$28 -> 2.5 | G10: =(Supuestos!$B$31*Supuestos!$B$32+(Supuestos!$B$7*Supuestos!$B$6/E10)*Supuestos!$B$33*Supuestos!$B$32)/(Supuestos!$B$7*Supuestos!$B$6) -> 0.015833333 | H10: =ROUNDUP(C10*E10*(1+Supuestos!$B$30)/(1-G10),0) -> 60 | I10: =ROUNDUP(B10*F10,0) -> 30 | J10: =MAX(0,H10-C10*(E10-Supuestos!$B$28)) -> 18.497697 | K10: =J10/Supuestos!F66 -> 1.1561061 | L10: =Supuestos!G66 -> 0
A11: =Supuestos!A67 -> AFFF 10 l | B11: =SUMPRODUCT('Demanda y mix'!F11:L11,'Demanda y mix'!$F$25:$L$25)/(Supuestos!$B$7*Supuestos!$B$6) -> 1.8333333 | C11: =SUMPRODUCT('Demanda y mix'!F11:L11,'Demanda y mix'!$F$24:$L$24,'Demanda y mix'!$F$25:$L$25)/Supuestos!$B$6 -> 1.76 | D11: =Supuestos!H67 -> 0.5 | E11: =Supuestos!$B$25*(1-D11)+Supuestos!$B$26*D11+Supuestos!$B$27+Supuestos!$B$28 -> 4.5 | F11: =Supuestos!$C$25*(1-D11)+Supuestos!$C$26*D11+Supuestos!$C$27+Supuestos!$C$28 -> 2.5 | G11: =(Supuestos!$B$31*Supuestos!$B$32+(Supuestos!$B$7*Supuestos!$B$6/E11)*Supuestos!$B$33*Supuestos!$B$32)/(Supuestos!$B$7*Supuestos!$B$6) -> 0.015833333 | H11: =ROUNDUP(C11*E11*(1+Supuestos!$B$30)/(1-G11),0) -> 9 | I11: =ROUNDUP(B11*F11,0) -> 5 | J11: =MAX(0,H11-C11*(E11-Supuestos!$B$28)) -> 2.84 | K11: =J11/Supuestos!F67 -> 0.1775 | L11: =Supuestos!G67 -> 0
A12: =Supuestos!A68 -> AFFF 50 l s/ruedas | B12: =SUMPRODUCT('Demanda y mix'!F12:L12,'Demanda y mix'!$F$25:$L$25)/(Supuestos!$B$7*Supuestos!$B$6) -> 0.95666667 | C12: =SUMPRODUCT('Demanda y mix'!F12:L12,'Demanda y mix'!$F$24:$L$24,'Demanda y mix'!$F$25:$L$25)/Supuestos!$B$6 -> 0.9184 | D12: =Supuestos!H68 -> 0.5 | E12: =Supuestos!$B$25*(1-D12)+Supuestos!$B$26*D12+Supuestos!$B$27+Supuestos!$B$28 -> 4.5 | F12: =Supuestos!$C$25*(1-D12)+Supuestos!$C$26*D12+Supuestos!$C$27+Supuestos!$C$28 -> 2.5 | G12: =(Supuestos!$B$31*Supuestos!$B$32+(Supuestos!$B$7*Supuestos!$B$6/E12)*Supuestos!$B$33*Supuestos!$B$32)/(Supuestos!$B$7*Supuestos!$B$6) -> 0.015833333 | H12: =ROUNDUP(C12*E12*(1+Supuestos!$B$30)/(1-G12),0) -> 5 | I12: =ROUNDUP(B12*F12,0) -> 3 | J12: =MAX(0,H12-C12*(E12-Supuestos!$B$28)) -> 1.7856 | K12: =J12/Supuestos!F68 -> 0.8928 | L12: =Supuestos!G68 -> 1
A13: =Supuestos!A69 -> BC 5 kg | B13: =SUMPRODUCT('Demanda y mix'!F13:L13,'Demanda y mix'!$F$25:$L$25)/(Supuestos!$B$7*Supuestos!$B$6) -> 0.55 | C13: =SUMPRODUCT('Demanda y mix'!F13:L13,'Demanda y mix'!$F$24:$L$24,'Demanda y mix'!$F$25:$L$25)/Supuestos!$B$6 -> 0.528 | D13: =Supuestos!H69 -> 0.25 | E13: =Supuestos!$B$25*(1-D13)+Supuestos!$B$26*D13+Supuestos!$B$27+Supuestos!$B$28 -> 4 | F13: =Supuestos!$C$25*(1-D13)+Supuestos!$C$26*D13+Supuestos!$C$27+Supuestos!$C$28 -> 2 | G13: =(Supuestos!$B$31*Supuestos!$B$32+(Supuestos!$B$7*Supuestos!$B$6/E13)*Supuestos!$B$33*Supuestos!$B$32)/(Supuestos!$B$7*Supuestos!$B$6) -> 0.01625 | H13: =ROUNDUP(C13*E13*(1+Supuestos!$B$30)/(1-G13),0) -> 3 | I13: =ROUNDUP(B13*F13,0) -> 2 | J13: =MAX(0,H13-C13*(E13-Supuestos!$B$28)) -> 1.416 | K13: =J13/Supuestos!F69 -> 0.059 | L13: =Supuestos!G69 -> 0
A14: =Supuestos!A70 -> Sales K 6 l | B14: =SUMPRODUCT('Demanda y mix'!F14:L14,'Demanda y mix'!$F$25:$L$25)/(Supuestos!$B$7*Supuestos!$B$6) -> 5.7401628 | C14: =SUMPRODUCT('Demanda y mix'!F14:L14,'Demanda y mix'!$F$24:$L$24,'Demanda y mix'!$F$25:$L$25)/Supuestos!$B$6 -> 5.9036014 | D14: =Supuestos!H70 -> 0.5 | E14: =Supuestos!$B$25*(1-D14)+Supuestos!$B$26*D14+Supuestos!$B$27+Supuestos!$B$28 -> 4.5 | F14: =Supuestos!$C$25*(1-D14)+Supuestos!$C$26*D14+Supuestos!$C$27+Supuestos!$C$28 -> 2.5 | G14: =(Supuestos!$B$31*Supuestos!$B$32+(Supuestos!$B$7*Supuestos!$B$6/E14)*Supuestos!$B$33*Supuestos!$B$32)/(Supuestos!$B$7*Supuestos!$B$6) -> 0.015833333 | H14: =ROUNDUP(C14*E14*(1+Supuestos!$B$30)/(1-G14),0) -> 30 | I14: =ROUNDUP(B14*F14,0) -> 15 | J14: =MAX(0,H14-C14*(E14-Supuestos!$B$28)) -> 9.3373951 | K14: =J14/Supuestos!F70 -> 0.46686976 | L14: =Supuestos!G70 -> 0
A15: =Supuestos!A71 -> CO₂ 2 kg | B15: =SUMPRODUCT('Demanda y mix'!F15:L15,'Demanda y mix'!$F$25:$L$25)/(Supuestos!$B$7*Supuestos!$B$6) -> 32.077373 | C15: =SUMPRODUCT('Demanda y mix'!F15:L15,'Demanda y mix'!$F$24:$L$24,'Demanda y mix'!$F$25:$L$25)/Supuestos!$B$6 -> 32.809762 | D15: =Supuestos!H71 -> 0.25 | E15: =Supuestos!$B$25*(1-D15)+Supuestos!$B$26*D15+Supuestos!$B$27+Supuestos!$B$28 -> 4 | F15: =Supuestos!$C$25*(1-D15)+Supuestos!$C$26*D15+Supuestos!$C$27+Supuestos!$C$28 -> 2 | G15: =(Supuestos!$B$31*Supuestos!$B$32+(Supuestos!$B$7*Supuestos!$B$6/E15)*Supuestos!$B$33*Supuestos!$B$32)/(Supuestos!$B$7*Supuestos!$B$6) -> 0.01625 | H15: =ROUNDUP(C15*E15*(1+Supuestos!$B$30)/(1-G15),0) -> 147 | I15: =ROUNDUP(B15*F15,0) -> 65 | J15: =MAX(0,H15-C15*(E15-Supuestos!$B$28)) -> 48.570715 | K15: =J15/Supuestos!F71 -> 1.6190238 | L15: =Supuestos!G71 -> 0
A16: =Supuestos!A72 -> CO₂ 5 kg | B16: =SUMPRODUCT('Demanda y mix'!F16:L16,'Demanda y mix'!$F$25:$L$25)/(Supuestos!$B$7*Supuestos!$B$6) -> 10.000601 | C16: =SUMPRODUCT('Demanda y mix'!F16:L16,'Demanda y mix'!$F$24:$L$24,'Demanda y mix'!$F$25:$L$25)/Supuestos!$B$6 -> 10.151828 | D16: =Supuestos!H72 -> 0.25 | E16: =Supuestos!$B$25*(1-D16)+Supuestos!$B$26*D16+Supuestos!$B$27+Supuestos!$B$28 -> 4 | F16: =Supuestos!$C$25*(1-D16)+Supuestos!$C$26*D16+Supuestos!$C$27+Supuestos!$C$28 -> 2 | G16: =(Supuestos!$B$31*Supuestos!$B$32+(Supuestos!$B$7*Supuestos!$B$6/E16)*Supuestos!$B$33*Supuestos!$B$32)/(Supuestos!$B$7*Supuestos!$B$6) -> 0.01625 | H16: =ROUNDUP(C16*E16*(1+Supuestos!$B$30)/(1-G16),0) -> 46 | I16: =ROUNDUP(B16*F16,0) -> 21 | J16: =MAX(0,H16-C16*(E16-Supuestos!$B$28)) -> 15.544517 | K16: =J16/Supuestos!F72 -> 0.77722584 | L16: =Supuestos!G72 -> 0
A17: =Supuestos!A73 -> HCFC/HFC 5 kg | B17: =SUMPRODUCT('Demanda y mix'!F17:L17,'Demanda y mix'!$F$25:$L$25)/(Supuestos!$B$7*Supuestos!$B$6) -> 1.5103469 | C17: =SUMPRODUCT('Demanda y mix'!F17:L17,'Demanda y mix'!$F$24:$L$24,'Demanda y mix'!$F$25:$L$25)/Supuestos!$B$6 -> 1.449933 | D17: =Supuestos!H73 -> 0.25 | E17: =Supuestos!$B$25*(1-D17)+Supuestos!$B$26*D17+Supuestos!$B$27+Supuestos!$B$28 -> 4 | F17: =Supuestos!$C$25*(1-D17)+Supuestos!$C$26*D17+Supuestos!$C$27+Supuestos!$C$28 -> 2 | G17: =(Supuestos!$B$31*Supuestos!$B$32+(Supuestos!$B$7*Supuestos!$B$6/E17)*Supuestos!$B$33*Supuestos!$B$32)/(Supuestos!$B$7*Supuestos!$B$6) -> 0.01625 | H17: =ROUNDUP(C17*E17*(1+Supuestos!$B$30)/(1-G17),0) -> 7 | I17: =ROUNDUP(B17*F17,0) -> 4 | J17: =MAX(0,H17-C17*(E17-Supuestos!$B$28)) -> 2.650201 | K17: =J17/Supuestos!F73 -> 0.11042504 | L17: =Supuestos!G73 -> 0
... A22: =Supuestos!A78 -> ABC 100 kg s/ruedas | B22: =SUMPRODUCT('Demanda y mix'!F22:L22,'Demanda y mix'!$F$25:$L$25)/(Supuestos!$B$7*Supuestos!$B$6) -> 0.4342041 | C22: =SUMPRODUCT('Demanda y mix'!F22:L22,'Demanda y mix'!$F$24:$L$24,'Demanda y mix'!$F$25:$L$25)/Supuestos!$B$6 -> 0.4410376 | D22: =Supuestos!H78 -> 0.25 | E22: =Supuestos!$B$25*(1-D22)+Supuestos!$B$26*D22+Supuestos!$B$27+Supuestos!$B$28 -> 4 | F22: =Supuestos!$C$25*(1-D22)+Supuestos!$C$26*D22+Supuestos!$C$27+Supuestos!$C$28 -> 2 | G22: =(Supuestos!$B$31*Supuestos!$B$32+(Supuestos!$B$7*Supuestos!$B$6/E22)*Supuestos!$B$33*Supuestos!$B$32)/(Supuestos!$B$7*Supuestos!$B$6) -> 0.01625 | H22: =ROUNDUP(C22*E22*(1+Supuestos!$B$30)/(1-G22),0) -> 2 | I22: =ROUNDUP(B22*F22,0) -> 1 | J22: =MAX(0,H22-C22*(E22-Supuestos!$B$28)) -> 0.67688721 | K22: =J22/Supuestos!F78 -> 0.67688721 | L22: =Supuestos!G78 -> 1
A23: Total | B23: =SUM(B6:B22) -> 522.89433 | C23: =SUM(C6:C22) -> 587.5142 | H23: =SUM(H6:H22) -> 2646 | I23: =SUM(I6:I22) -> 1066 | J23: =SUM(J6:J22) -> 873.23749 | K23: =SUM(K6:K22) -> 27.88704
A24: Stock recomendado = salen por día en el mes pico × días afuera (+ revisión) × (1 + margen) / (1 − fuera de servicio). Es la ley de Little: lo que hay afuera = lo que sale por día × los días que tarda en volver.
A25: Punto mínimo = salidas de un día promedio × el ciclo más corto posible (proceso en 1 día, PH en 3, sin espera). Por debajo de eso falta transitorio aunque todo salga perfecto. Salen de la propia línea de manuales y carros.
A27: 2. ¿Cuántos transitorios hacen falta según los días que tarda en volver el matafuego del cliente?
A28: Días afuera + revisión | B28: 1 | C28: 2 | D28: 3 | E28: 4 | F28: 5 | G28: 6 | H28: 7
A29: Transitorios (u) | B29: =ROUNDUP(SUM($C$6:$C$22)*1*(1+Supuestos!$B$30),0) -> 647 | C29: =ROUNDUP(SUM($C$6:$C$22)*2*(1+Supuestos!$B$30),0) -> 1293 | D29: =ROUNDUP(SUM($C$6:$C$22)*3*(1+Supuestos!$B$30),0) -> 1939 | E29: =ROUNDUP(SUM($C$6:$C$22)*4*(1+Supuestos!$B$30),0) -> 2586 | F29: =ROUNDUP(SUM($C$6:$C$22)*5*(1+Supuestos!$B$30),0) -> 3232 | G29: =ROUNDUP(SUM($C$6:$C$22)*6*(1+Supuestos!$B$30),0) -> 3878 | H29: =ROUNDUP(SUM($C$6:$C$22)*7*(1+Supuestos!$B$30),0) -> 4524
A30: Días del caso base (promedio) | B30: =SUMPRODUCT(C6:C22,E6:E22)/C23 -> 4.0173952 | C30: ← cada día que se acorta el ciclo ahorra una fila de transitorios: es la palanca más fuerte.
A32: 3. Trabajo extra en la planta por los transitorios (por año)
A33: Concepto | B33: u/año | C33: % de las recargas 2035
A34: Revisión o recarga anual | B34: =H23*Supuestos!$B$31 -> 2646 | C34: =B34/'Demanda y mix'!$D$23 -> 0.020779017
A35: Recarga porque el cliente lo usó | B35: =SUMPRODUCT(H6:H22,1/E6:E22)*Supuestos!$B$7*Supuestos!$B$6*Supuestos!$B$33 -> 790.33333 | C35: =B35/'Demanda y mix'!$D$23 -> 0.0062064813
A36: Total | B36: =SUM(B34:B35) -> 3436.3333 | C36: =B36/'Demanda y mix'!$D$23 -> 0.026985498
A38: 4. Pulmón de recargas en el día pico (posiciones de 1,2 × 1,0 m en el piso, 1 nivel: en recargas se mueve con transpaleta)
A39: Zona | B39: Matafuegos (u) | C39: Jaulas de manuales | D39: Jaulas de rodantes | E39: Posiciones necesarias | F39: Posiciones en el plano | G39: Faltan (−) / sobran (+) | H39: Dónde y cómo van
A40: Recepción (R0) | B40: =SUM('Demanda y mix'!$P$6:$P$22)*Supuestos!$B$37 -> 342.065 | C40: =SUMPRODUCT((Supuestos!$G$62:$G$78=0)*'Demanda y mix'!$P$6:$P$22/Supuestos!$F$62:$F$78)*Supuestos!$B$37*Supuestos!$B$39 -> 10.123706 | D40: =SUMPRODUCT((Supuestos!$G$62:$G$78=1)*'Demanda y mix'!$P$6:$P$22/Supuestos!$F$62:$F$78)*Supuestos!$B$37*Supuestos!$B$39 -> 2.3599629 | E40: =ROUNDUP(C40,0)+ROUNDUP(D40,0) -> 14 | F40: =Supuestos!$B$43 -> 16 | G40: =F40-E40 -> 2 | H40: Jaulas A (1 kg) y B por cliente, en orden de llegada, contra el muro norte. Rodantes en jaula de rodantes junto a la abertura a R1, para entrar con rampa.
A41: Despacho | B41: =SUM('Demanda y mix'!$P$6:$P$22)*Supuestos!$B$38 -> 342.065 | C41: =SUMPRODUCT((Supuestos!$G$62:$G$78=0)*'Demanda y mix'!$P$6:$P$22/Supuestos!$F$62:$F$78)*Supuestos!$B$38*Supuestos!$B$39 -> 10.123706 | D41: =SUMPRODUCT((Supuestos!$G$62:$G$78=1)*'Demanda y mix'!$P$6:$P$22/Supuestos!$F$62:$F$78)*Supuestos!$B$38*Supuestos!$B$39 -> 2.3599629 | E41: =ROUNDUP(C41,0)+ROUNDUP(D41,0) -> 14 | F41: =Supuestos!$B$44 -> 7 | G41: =F41-E41 -> -7 | H41: Jaulas armadas por recorrido y en el orden de entrega, al lado del portón R.
A42: Transitorios en la planta | B42: =J23 -> 873.23749 | C42: =SUMPRODUCT((L6:L22=0)*K6:K22) -> 22.412952 | D42: =SUMPRODUCT((L6:L22=1)*K6:K22) -> 5.4740878 | E42: =ROUNDUP(C42/Supuestos!$B$41,0)+ROUNDUP(D42,0) -> 14 | F42: =Supuestos!$B$46 -> 0 | G42: =F42-E42 -> -14 | H42: Estantería de 3 niveles con faja amarilla, separados por tipo, entre despacho y el portón R (salen en el mismo viaje). Rodantes en el piso.
A43: Jaulas vacías | B43: — | C43: — | D43: — | E43: =ROUNDUP(SUM(E40:E42)*Supuestos!$B$40/Supuestos!$B$42,0) -> 4 | F43: =Supuestos!$B$45 -> 5 | G43: =F43-E43 -> 1 | H43: Apiladas de a 2, junto a despacho.
A44: Total | E44: =SUM(E40:E43) -> 46 | F44: =SUM(F40:F43) -> 28 | G44: =SUM(G40:G43) -> -18
A45: Superficie necesaria (m²) | B45: =E44*1.2*1*2 -> 110.4 | C45: ← posiciones × 1,2 m² × 2 (pasillo de transpaleta de 2,5 m compartido por las dos filas)
